Workbook
Name _DLX1.INC: HAVERD!$B$2:$BD$7
Name cdids: [2]Data!$A$2:$A$10
Name data: [2]Data!$B$2:$EZ$10
Name Data: [1]sheet0!$C$2
Name dates: [2]Data!$B$1:$EZ$1

Sheet Chart Data
A1: Existing - 2019=100 | R1: New - 2019=100 | AA1: New - 2019=100 | AQ1: Annual - 2019=100 | BA1: Annual - levels | BK1: Sectors - retail (2019=100) | BP1: Sectors - health (2019=100) | BU1: Sectors - manufacturing (2019=100) | BZ1: Equity prices - last week | CL1: Equity prices - since August 1
B2: UK | C2: US | D2: Japan | E2: Germany | F2: France | G2: Italy | H2: Canada | J2: UK | K2: US | L2: Japan | M2: Germany | N2: France | O2: Italy | P2: Canada | S2: UK | T2: US | U2: Japan | V2: Germany | W2: France | X2: Italy | Y2: Canada | AB2: UK (current) | AC2: UK (new) | AD2: G7 median | AE2: Bottom of range | AF2: G7 range | AG2: 100 LINE | AI2: UK | AJ2: US | AK2: Japan | AL2: Germany | AM2: France | AN2: Italy | AO2: Canada | AR2: UK (current) | AS2: UK (new) | AT2: US | AU2: Japan | AV2: Germany | AW2: France | AX2: Italy | AY2: Canada | BB2: UK (current) | BC2: UK (new) | BD2: US | BE2: Japan | BF2: Germany | BG2: France | BH2: Italy | BI2: Canada | BL2: Current | BM2: New | BN2: 100 LINE | BQ2: Current | BR2: New | BS2: 100 LINE | BV2: Current | BW2: New | BX2: 100 LINE | CA2: =HAVERD!C1 -> US | CB2: =HAVERD!D1 -> Japan | CC2: =HAVERD!E1 -> Eurozone | CD2: =HAVERD!F1 -> UK | CE2: =HAVERD!M1 -> Canada | CF2: =HAVERD!T1 -> France | CG2: =HAVERD!U1 -> Germany | CH2: =HAVERD!Y1 -> India | CI2: =HAVERD!AB1 -> Italy | CJ2: =HAVERD!AZ1 -> Global | CM2: UK | CN2: Global | CO2: US | CP2: Eurozone | CQ2: Japan | CR2: Canada | CS2: 100 LINE
A3: 2019 | B3: =100*(Data!C191/AVERAGE(Data!C$191:C$194)) -> 99.402083 | C3: =100*(Data!D191/AVERAGE(Data!D$191:D$194)) -> 98.661808 | D3: =100*(Data!E191/AVERAGE(Data!E$191:E$194)) -> 100.30738 | E3: =100*(Data!F191/AVERAGE(Data!F$191:F$194)) -> 99.80617 | F3: =100*(Data!G191/AVERAGE(Data!G$191:G$194)) -> 99.672108 | G3: =100*(Data!H191/AVERAGE(Data!H$191:H$194)) -> 99.88523 | H3: =100*(Data!I191/AVERAGE(Data!I$191:I$194)) -> 98.975819 | J3: =RANK(B3,$B3:$H3) -> 5 | K3: =RANK(C3,$B3:$H3) -> 7 | L3: =RANK(D3,$B3:$H3) -> 1 | M3: =RANK(E3,$B3:$H3) -> 3 | N3: =RANK(F3,$B3:$H3) -> 4 | O3: =RANK(G3,$B3:$H3) -> 2 | P3: =RANK(H3,$B3:$H3) -> 6 | R3: 2019 | S3: =100*('ONS - Annex F'!C94/AVERAGE('ONS - Annex F'!$C$94:$C$97)) -> 99.413922 | T3: =C3 -> 98.661808 | U3: =D3 -> 100.30738 | V3: =E3 -> 99.80617 | W3: =F3 -> 99.672108 | X3: =G3 -> 99.88523 | Y3: =H3 -> 98.975819 | AA3: 2019 | AB3: =B3 -> 99.402083 | AC3: =S3 -> 99.413922 | AD3: =MEDIAN($S3:$Y3) -> 99.672108 | AE3: =MIN($S3:$Y3) -> 98.661808 | AF3: =MAX($S3:$Y3)-AE3 -> 1.6455682 | AG3: 100 | AI3: =RANK(S3,$S3:$Y3) -> 5 | AJ3: =RANK(T3,$S3:$Y3) -> 7 | AK3: =RANK(U3,$S3:$Y3) -> 1 | AL3: =RANK(V3,$S3:$Y3) -> 3 | AM3: =RANK(W3,$S3:$Y3) -> 4 | AN3: =RANK(X3,$S3:$Y3) -> 2 | AO3: =RANK(Y3,$S3:$Y3) -> 6 | AQ3: 2019 | AR3: =100*(BB3/BB$3) -> 100 | AS3: =100*(BC3/BC$3) -> 100 | AT3: =100*(BD3/BD$3) -> 100 | AU3: =100*(BE3/BE$3) -> 100 | AV3: =100*(BF3/BF$3) -> 100 | AW3: =100*(BG3/BG$3) -> 100 | AX3: =100*(BH3/BH$3) -> 100 | AY3: =100*(BI3/BI$3) -> 100 | BA3: 2019 | BB3: =SUMIF(Data!$A:$A,'Chart Data'!$BA3,Data!C:C) -> 2233921 | BC3: =SUM('ONS - Annex F'!C94:C97) -> 2474245 | BD3: =SUMIF(Data!$A:$A,'Chart Data'!$BA3,Data!D:D) -> 20692.1 | BE3: =SUMIF(Data!$A:$A,'Chart Data'!$BA3,Data!E:E) -> 552514.9 | BF3: =SUMIF(Data!$A:$A,'Chart Data'!$BA3,Data!F:F) -> 3309.2443 | BG3: =SUMIF(Data!$A:$A,'Chart Data'!$BA3,Data!G:G) -> 2507.53 | BH3: =SUMIF(Data!$A:$A,'Chart Data'!$BA3,Data!H:H) -> 1728.668 | BI3: =SUMIF(Data!$A:$A,'Chart Data'!$BA3,Data!I:I) -> 2241331.3 | BK3: 43466 | BL3: =100*('ONS - Table 1'!CK270/AVERAGE('ONS - Table 1'!$CK$270:$CK$281)) -> 100.90841 | BM3: =100*('ONS - Table 2'!CK270/AVERAGE('ONS - Table 2'!$CK$270:$CK$281)) -> 101.11317 | BN3: 100 | BP3: 43466 | BQ3: =100*('ONS - Table 1'!ET270/AVERAGE('ONS - Table 1'!$ET$270:$ET$281)) -> 97.5 | BR3: =100*('ONS - Table 2'!ET270/AVERAGE('ONS - Table 2'!$ET$270:$ET$281)) -> 98.038311 | BS3: 100 | BU3: 43466 | BV3: =100*('ONS - Table 1'!J270/AVERAGE('ONS - Table 1'!$J$270:$J$281)) -> 98.183636 | BW3: =100*('ONS - Table 2'!J270/AVERAGE('ONS - Table 2'!$J$270:$J$281)) -> 98.640904 | BX3: 100 | BZ3: Past week | CA3: =100*((HAVERD!C166/HAVERD!C161)-1) -> -2.3384888 | CB3: =100*((HAVERD!D166/HAVERD!D161)-1) -> -8.9503604 | CC3: =100*((HAVERD!E166/HAVERD!E161)-1) -> -2.0349496 | CD3: =100*((HAVERD!F166/HAVERD!F161)-1) -> -2.0785707 | CE3: =100*((HAVERD!M166/HAVERD!M161)-1) -> -2.1898315 | CF3: =100*((HAVERD!T166/HAVERD!T161)-1) -> -1.6688262 | CG3: =100*((HAVERD!U166/HAVERD!U161)-1) -> -2.2267102 | CH3: =100*((HAVERD!Y166/HAVERD!Y161)-1) -> -3.6416504 | CI3: =100*((HAVERD!AB166/HAVERD!AB161)-1) -> -3.3950312 | CJ3: =100*((HAVERD!AZ166/HAVERD!AZ161)-1) -> -2.8154827 | CL3: 45505 | CM3: =100*(HAVERD!F161/HAVERD!F$161) -> 100 | CN3: =100*(HAVERD!AZ161/HAVERD!AZ$161) -> 100 | CO3: =100*(HAVERD!C161/HAVERD!C$161) -> 100 | CP3: =100*(HAVERD!E161/HAVERD!E$161) -> 100 | CQ3: =100*(HAVERD!D161/HAVERD!D$161) -> 100 | CR3: =100*(HAVERD!M161/HAVERD!M$161) -> 100 | CS3: 100
B4: =100*(Data!C192/AVERAGE(Data!C$191:C$194)) -> 99.722774 | C4: =100*(Data!D192/AVERAGE(Data!D$191:D$194)) -> 99.479995 | D4: =100*(Data!E192/AVERAGE(Data!E$191:E$194)) -> 100.73046 | E4: =100*(Data!F192/AVERAGE(Data!F$191:F$194)) -> 99.91185 | F4: =100*(Data!G192/AVERAGE(Data!G$191:G$194)) -> 100.25276 | G4: =100*(Data!H192/AVERAGE(Data!H$191:H$194)) -> 100.21543 | H4: =100*(Data!I192/AVERAGE(Data!I$191:I$194)) -> 100.05937 | J4: =RANK(B4,$B4:$H4) -> 6 | K4: =RANK(C4,$B4:$H4) -> 7 | L4: =RANK(D4,$B4:$H4) -> 1 | M4: =RANK(E4,$B4:$H4) -> 5 | N4: =RANK(F4,$B4:$H4) -> 2 | O4: =RANK(G4,$B4:$H4) -> 3 | P4: =RANK(H4,$B4:$H4) -> 4 | S4: =100*('ONS - Annex F'!C95/AVERAGE('ONS - Annex F'!$C$94:$C$97)) -> 99.723835 | T4: =C4 -> 99.479995 | U4: =D4 -> 100.73046 | V4: =E4 -> 99.91185 | W4: =F4 -> 100.25276 | X4: =G4 -> 100.21543 | Y4: =H4 -> 100.05937 | AB4: =B4 -> 99.722774 | AC4: =S4 -> 99.723835 | AD4: =MEDIAN($S4:$Y4) -> 100.05937 | AE4: =MIN($S4:$Y4) -> 99.479995 | AF4: =MAX($S4:$Y4)-AE4 -> 1.2504652 | AG4: 100 | AI4: =RANK(S4,$S4:$Y4) -> 6 | AJ4: =RANK(T4,$S4:$Y4) -> 7 | AK4: =RANK(U4,$S4:$Y4) -> 1 | AL4: =RANK(V4,$S4:$Y4) -> 5 | AM4: =RANK(W4,$S4:$Y4) -> 2 | AN4: =RANK(X4,$S4:$Y4) -> 3 | AO4: =RANK(Y4,$S4:$Y4) -> 4 | AQ4: 2020 | AR4: =100*(BB4/BB$3) -> 89.640099 | AS4: =100*(BC4/BC$3) -> 89.703081 | AT4: =100*(BD4/BD$3) -> 97.786474 | AU4: =100*(BE4/BE$3) -> 95.779716 | AV4: =100*(BF4/BF$3) -> 95.543578 | AW4: =100*(BG4/BG$3) -> 92.408187 | AX4: =100*(BH4/BH$3) -> 90.950373 | AY4: =100*(BI4/BI$3) -> 94.961767 | BA4: 2020 | BB4: =SUMIF(Data!$A:$A,'Chart Data'!$BA4,Data!C:C) -> 2002489 | BC4: =SUM('ONS - Annex F'!C98:C101) -> 2219474 | BD4: =SUMIF(Data!$A:$A,'Chart Data'!$BA4,Data!D:D) -> 20234.075 | BE4: =SUMIF(Data!$A:$A,'Chart Data'!$BA4,Data!E:E) -> 529197.2 | BF4: =SUMIF(Data!$A:$A,'Chart Data'!$BA4,Data!F:F) -> 3161.7704 | BG4: =SUMIF(Data!$A:$A,'Chart Data'!$BA4,Data!G:G) -> 2317.163 | BH4: =SUMIF(Data!$A:$A,'Chart Data'!$BA4,Data!H:H) -> 1572.23 | BI4: =SUMIF(Data!$A:$A,'Chart Data'!$BA4,Data!I:I) -> 2128407.8 | BK4: 43497 | BL4: =100*('ONS - Table 1'!CK271/AVERAGE('ONS - Table 1'!$CK$270:$CK$281)) -> 101.10843 | BM4: =100*('ONS - Table 2'!CK271/AVERAGE('ONS - Table 2'!$CK$270:$CK$281)) -> 101.48423 | BN4: 100 | BP4: 43497 | BQ4: =100*('ONS - Table 1'!ET271/AVERAGE('ONS - Table 1'!$ET$270:$ET$281)) -> 99.1 | BR4: =100*('ONS - Table 2'!ET271/AVERAGE('ONS - Table 2'!$ET$270:$ET$281)) -> 99.607662 | BS4: 100 | BU4: 43497 | BV4: =100*('ONS - Table 1'!J271/AVERAGE('ONS - Table 1'!$J$270:$J$281)) -> 99.383436 | BW4: =100*('ONS - Table 2'!J271/AVERAGE('ONS - Table 2'!$J$270:$J$281)) -> 99.328639 | BX4: 100 | CL4: =+CL3+1 -> 45506 | CM4: =100*(HAVERD!F162/HAVERD!F$161) -> 98.447728 | CN4: =100*(HAVERD!AZ162/HAVERD!AZ$161) -> 97.935863 | CO4: =100*(HAVERD!C162/HAVERD!C$161) -> 98.161816 | CP4: =100*(HAVERD!E162/HAVERD!E$161) -> 97.334715 | CQ4: =100*(HAVERD!D162/HAVERD!D$161) -> 93.856914 | CR4: =100*(HAVERD!M162/HAVERD!M$161) -> 97.819058 | CS4: 100
B5: =100*(Data!C193/AVERAGE(Data!C$191:C$194)) -> 100.44885 | C5: =100*(Data!D193/AVERAGE(Data!D$191:D$194)) -> 100.60651 | D5: =100*(Data!E193/AVERAGE(Data!E$191:E$194)) -> 100.9129 | E5: =100*(Data!F193/AVERAGE(Data!F$191:F$194)) -> 100.14099 | F5: =100*(Data!G193/AVERAGE(Data!G$191:G$194)) -> 100.2936 | G5: =100*(Data!H193/AVERAGE(Data!H$191:H$194)) -> 100.27744 | H5: =100*(Data!I193/AVERAGE(Data!I$191:I$194)) -> 100.33917 | J5: =RANK(B5,$B5:$H5) -> 3 | K5: =RANK(C5,$B5:$H5) -> 2 | L5: =RANK(D5,$B5:$H5) -> 1 | M5: =RANK(E5,$B5:$H5) -> 7 | N5: =RANK(F5,$B5:$H5) -> 5 | O5: =RANK(G5,$B5:$H5) -> 6 | P5: =RANK(H5,$B5:$H5) -> 4 | S5: =100*('ONS - Annex F'!C96/AVERAGE('ONS - Annex F'!$C$94:$C$97)) -> 100.43096 | T5: =C5 -> 100.60651 | U5: =D5 -> 100.9129 | V5: =E5 -> 100.14099 | W5: =F5 -> 100.2936 | X5: =G5 -> 100.27744 | Y5: =H5 -> 100.33917 | AB5: =B5 -> 100.44885 | AC5: =S5 -> 100.43096 | AD5: =MEDIAN($S5:$Y5) -> 100.33917 | AE5: =MIN($S5:$Y5) -> 100.14099 | AF5: =MAX($S5:$Y5)-AE5 -> 0.77190856 | AG5: 100 | AI5: =RANK(S5,$S5:$Y5) -> 3 | AJ5: =RANK(T5,$S5:$Y5) -> 2 | AK5: =RANK(U5,$S5:$Y5) -> 1 | AL5: =RANK(V5,$S5:$Y5) -> 7 | AM5: =RANK(W5,$S5:$Y5) -> 5 | AN5: =RANK(X5,$S5:$Y5) -> 6 | AO5: =RANK(Y5,$S5:$Y5) -> 4 | AQ5: 2021 | AR5: =100*(BB5/BB$3) -> 97.416292 | AS5: =100*(BC5/BC$3) -> 97.395973 | AT5: =100*(BD5/BD$3) -> 103.4582 | AU5: =100*(BE5/BE$3) -> 98.435083 | AV5: =100*(BF5/BF$3) -> 98.927408 | AW5: =100*(BG5/BG$3) -> 98.718659 | AX5: =100*(BH5/BH$3) -> 98.479523 | AY5: =100*(BI5/BI$3) -> 99.982359 | BA5: 2021 | BB5: =SUMIF(Data!$A:$A,'Chart Data'!$BA5,Data!C:C) -> 2176203 | BC5: =SUM('ONS - Annex F'!C102:C105) -> 2409815 | BD5: =SUMIF(Data!$A:$A,'Chart Data'!$BA5,Data!D:D) -> 21407.675 | BE5: =SUMIF(Data!$A:$A,'Chart Data'!$BA5,Data!E:E) -> 543868.5 | BF5: =SUMIF(Data!$A:$A,'Chart Data'!$BA5,Data!F:F) -> 3273.7496 | BG5: =SUMIF(Data!$A:$A,'Chart Data'!$BA5,Data!G:G) -> 2475.4 | BH5: =SUMIF(Data!$A:$A,'Chart Data'!$BA5,Data!H:H) -> 1702.384 | BI5: =SUMIF(Data!$A:$A,'Chart Data'!$BA5,Data!I:I) -> 2240935.9 | BK5: 43525 | BL5: =100*('ONS - Table 1'!CK272/AVERAGE('ONS - Table 1'!$CK$270:$CK$281)) -> 101.00842 | BM5: =100*('ONS - Table 2'!CK272/AVERAGE('ONS - Table 2'!$CK$270:$CK$281)) -> 101.11317 | BN5: 100 | BP5: 43525 | BQ5: =100*('ONS - Table 1'!ET272/AVERAGE('ONS - Table 1'!$ET$270:$ET$281)) -> 100.5 | BR5: =100*('ONS - Table 2'!ET272/AVERAGE('ONS - Table 2'!$ET$270:$ET$281)) -> 101.45396 | BS5: 100 | BU5: 43525 | BV5: =100*('ONS - Table 1'!J272/AVERAGE('ONS - Table 1'!$J$270:$J$281)) -> 100.58324 | BW5: =100*('ONS - Table 2'!J272/AVERAGE('ONS - Table 2'!$J$270:$J$281)) -> 100.21287 | BX5: 100 | CL5: =+CL4+3 -> 45509 | CM5: =100*(HAVERD!F163/HAVERD!F$161) -> 96.320972 | CN5: =100*(HAVERD!AZ163/HAVERD!AZ$161) -> 94.712507 | CO5: =100*(HAVERD!C163/HAVERD!C$161) -> 95.220024 | CP5: =100*(HAVERD!E163/HAVERD!E$161) -> 95.926743 | CQ5: =100*(HAVERD!D163/HAVERD!D$161) -> 82.374459 | CR5: =100*(HAVERD!M163/HAVERD!M$161) -> #N/A | CS5: 100
B6: =100*(Data!C194/AVERAGE(Data!C$191:C$194)) -> 100.42629 | C6: =100*(Data!D194/AVERAGE(Data!D$191:D$194)) -> 101.25169 | D6: =100*(Data!E194/AVERAGE(Data!E$191:E$194)) -> 98.049265 | E6: =100*(Data!F194/AVERAGE(Data!F$191:F$194)) -> 100.14099 | F6: =100*(Data!G194/AVERAGE(Data!G$191:G$194)) -> 99.781538 | G6: =100*(Data!H194/AVERAGE(Data!H$191:H$194)) -> 99.621905 | H6: =100*(Data!I194/AVERAGE(Data!I$191:I$194)) -> 100.62564 | J6: =RANK(B6,$B6:$H6) -> 3 | K6: =RANK(C6,$B6:$H6) -> 1 | L6: =RANK(D6,$B6:$H6) -> 7 | M6: =RANK(E6,$B6:$H6) -> 4 | N6: =RANK(F6,$B6:$H6) -> 5 | O6: =RANK(G6,$B6:$H6) -> 6 | P6: =RANK(H6,$B6:$H6) -> 2 | S6: =100*('ONS - Annex F'!C97/AVERAGE('ONS - Annex F'!$C$94:$C$97)) -> 100.43128 | T6: =C6 -> 101.25169 | U6: =D6 -> 98.049265 | V6: =E6 -> 100.14099 | W6: =F6 -> 99.781538 | X6: =G6 -> 99.621905 | Y6: =H6 -> 100.62564 | AB6: =B6 -> 100.42629 | AC6: =S6 -> 100.43128 | AD6: =MEDIAN($S6:$Y6) -> 100.14099 | AE6: =MIN($S6:$Y6) -> 98.049265 | AF6: =MAX($S6:$Y6)-AE6 -> 3.2024201 | AG6: 100 | AI6: =RANK(S6,$S6:$Y6) -> 3 | AJ6: =RANK(T6,$S6:$Y6) -> 1 | AK6: =RANK(U6,$S6:$Y6) -> 7 | AL6: =RANK(V6,$S6:$Y6) -> 4 | AM6: =RANK(W6,$S6:$Y6) -> 5 | AN6: =RANK(X6,$S6:$Y6) -> 6 | AO6: =RANK(Y6,$S6:$Y6) -> 2 | AQ6: 2022 | AR6: =100*(BB6/BB$3) -> 101.64925 | AS6: =100*(BC6/BC$3) -> 102.10905 | AT6: =100*(BD6/BD$3) -> 105.46078 | AU6: =100*(BE6/BE$3) -> 99.603775 | AV6: =100*(BF6/BF$3) -> 100.64629 | AW6: =100*(BG6/BG$3) -> 101.30379 | AX6: =100*(BH6/BH$3) -> 102.56174 | AY6: =100*(BI6/BI$3) -> 103.80155 | BA6: 2022 | BB6: =SUMIF(Data!$A:$A,'Chart Data'!$BA6,Data!C:C) -> 2270764 | BC6: =SUM('ONS - Annex F'!C106:C109) -> 2526428 | BD6: =SUMIF(Data!$A:$A,'Chart Data'!$BA6,Data!D:D) -> 21822.05 | BE6: =SUMIF(Data!$A:$A,'Chart Data'!$BA6,Data!E:E) -> 550325.7 | BF6: =SUMIF(Data!$A:$A,'Chart Data'!$BA6,Data!F:F) -> 3330.6316 | BG6: =SUMIF(Data!$A:$A,'Chart Data'!$BA6,Data!G:G) -> 2540.223 | BH6: =SUMIF(Data!$A:$A,'Chart Data'!$BA6,Data!H:H) -> 1772.952 | BI6: =SUMIF(Data!$A:$A,'Chart Data'!$BA6,Data!I:I) -> 2326536.7 | BK6: 43556 | BL6: =100*('ONS - Table 1'!CK273/AVERAGE('ONS - Table 1'!$CK$270:$CK$281)) -> 100.90841 | BM6: =100*('ONS - Table 2'!CK273/AVERAGE('ONS - Table 2'!$CK$270:$CK$281)) -> 101.02041 | BN6: 100 | BP6: 43556 | BQ6: =100*('ONS - Table 1'!ET273/AVERAGE('ONS - Table 1'!$ET$270:$ET$281)) -> 99.5 | BR6: =100*('ONS - Table 2'!ET273/AVERAGE('ONS - Table 2'!$ET$270:$ET$281)) -> 100.06924 | BS6: 100 | BU6: 43556 | BV6: =100*('ONS - Table 1'!J273/AVERAGE('ONS - Table 1'!$J$270:$J$281)) -> 97.583736 | BW6: =100*('ONS - Table 2'!J273/AVERAGE('ONS - Table 2'!$J$270:$J$281)) -> 97.854921 | BX6: 100 | CL6: =+CL5+1 -> 45510 | CM6: =100*(HAVERD!F164/HAVERD!F$161) -> 96.607663 | CN6: =100*(HAVERD!AZ164/HAVERD!AZ$161) -> 95.865121 | CO6: =100*(HAVERD!C164/HAVERD!C$161) -> 96.205946 | CP6: =100*(HAVERD!E164/HAVERD!E$161) -> 96.002703 | CQ6: =100*(HAVERD!D164/HAVERD!D$161) -> 90.032881 | CR6: =100*(HAVERD!M164/HAVERD!M$161) -> 96.726475 | CS6: 100
A7: 2020 | B7: =100*(Data!C195/AVERAGE(Data!C$191:C$194)) -> 97.693159 | C7: =100*(Data!D195/AVERAGE(Data!D$191:D$194)) -> 99.871932 | D7: =100*(Data!E195/AVERAGE(Data!E$191:E$194)) -> 98.536202 | E7: =100*(Data!F195/AVERAGE(Data!F$191:F$194)) -> 97.900684 | F7: =100*(Data!G195/AVERAGE(Data!G$191:G$194)) -> 94.654261 | G7: =100*(Data!H195/AVERAGE(Data!H$191:H$194)) -> 93.608027 | H7: =100*(Data!I195/AVERAGE(Data!I$191:I$194)) -> 98.663504 | J7: =RANK(B7,$B7:$H7) -> 5 | K7: =RANK(C7,$B7:$H7) -> 1 | L7: =RANK(D7,$B7:$H7) -> 3 | M7: =RANK(E7,$B7:$H7) -> 4 | N7: =RANK(F7,$B7:$H7) -> 6 | O7: =RANK(G7,$B7:$H7) -> 7 | P7: =RANK(H7,$B7:$H7) -> 2 | R7: 2020 | S7: =100*('ONS - Annex F'!C98/AVERAGE('ONS - Annex F'!$C$94:$C$97)) -> 97.762186 | T7: =C7 -> 99.871932 | U7: =D7 -> 98.536202 | V7: =E7 -> 97.900684 | W7: =F7 -> 94.654261 | X7: =G7 -> 93.608027 | Y7: =H7 -> 98.663504 | AA7: 2020 | AB7: =B7 -> 97.693159 | AC7: =S7 -> 97.762186 | AD7: =MEDIAN($S7:$Y7) -> 97.900684 | AE7: =MIN($S7:$Y7) -> 93.608027 | AF7: =MAX($S7:$Y7)-AE7 -> 6.2639053 | AG7: 100 | AI7: =RANK(S7,$S7:$Y7) -> 5 | AJ7: =RANK(T7,$S7:$Y7) -> 1 | AK7: =RANK(U7,$S7:$Y7) -> 3 | AL7: =RANK(V7,$S7:$Y7) -> 4 | AM7: =RANK(W7,$S7:$Y7) -> 6 | AN7: =RANK(X7,$S7:$Y7) -> 7 | AO7: =RANK(Y7,$S7:$Y7) -> 2 | AQ7: 2023 | AR7: =100*(BB7/BB$3) -> 101.75499 | AS7: =100*(BC7/BC$3) -> 0 | AT7: =100*(BD7/BD$3) -> 108.14236 | AU7: =100*(BE7/BE$3) -> 101.40516 | AV7: =100*(BF7/BF$3) -> 100.5865 | AW7: =100*(BG7/BG$3) -> 102.43846 | AX7: =100*(BH7/BH$3) -> 103.60503 | AY7: =100*(BI7/BI$3) -> 105.09795 | BA7: 2023 | BB7: =SUMIF(Data!$A:$A,'Chart Data'!$BA7,Data!C:C) -> 2273126 | BD7: =SUMIF(Data!$A:$A,'Chart Data'!$BA7,Data!D:D) -> 22376.925 | BE7: =SUMIF(Data!$A:$A,'Chart Data'!$BA7,Data!E:E) -> 560278.6 | BF7: =SUMIF(Data!$A:$A,'Chart Data'!$BA7,Data!F:F) -> 3328.6531 | BG7: =SUMIF(Data!$A:$A,'Chart Data'!$BA7,Data!G:G) -> 2568.675 | BH7: =SUMIF(Data!$A:$A,'Chart Data'!$BA7,Data!H:H) -> 1790.987 | BI7: =SUMIF(Data!$A:$A,'Chart Data'!$BA7,Data!I:I) -> 2355593.3 | BK7: 43586 | BL7: =100*('ONS - Table 1'!CK274/AVERAGE('ONS - Table 1'!$CK$270:$CK$281)) -> 100.00833 | BM7: =100*('ONS - Table 2'!CK274/AVERAGE('ONS - Table 2'!$CK$270:$CK$281)) -> 100 | BN7: 100 | BP7: 43586 | BQ7: =100*('ONS - Table 1'!ET274/AVERAGE('ONS - Table 1'!$ET$270:$ET$281)) -> 99.4 | BR7: =100*('ONS - Table 2'!ET274/AVERAGE('ONS - Table 2'!$ET$270:$ET$281)) -> 99.884607 | BS7: 100 | BU7: 43586 | BV7: =100*('ONS - Table 1'!J274/AVERAGE('ONS - Table 1'!$J$270:$J$281)) -> 98.583569 | BW7: =100*('ONS - Table 2'!J274/AVERAGE('ONS - Table 2'!$J$270:$J$281)) -> 98.542656 | BX7: 100 | CL7: =+CL6+1 -> 45511 | CM7: =100*(HAVERD!F165/HAVERD!F$161) -> 98.187659 | CN7: =100*(HAVERD!AZ165/HAVERD!AZ$161) -> 95.871726 | CO7: =100*(HAVERD!C165/HAVERD!C$161) -> 95.461823 | CP7: =100*(HAVERD!E165/HAVERD!E$161) -> 97.950782 | CQ7: =100*(HAVERD!D165/HAVERD!D$161) -> 92.067138 | CR7: =100*(HAVERD!M165/HAVERD!M$161) -> 96.293393 | CS7: 100
B8: =100*(Data!C196/AVERAGE(Data!C$191:C$194)) -> 77.839458 | C8: =100*(Data!D196/AVERAGE(Data!D$191:D$194)) -> 91.990663 | D8: =100*(Data!E196/AVERAGE(Data!E$191:E$194)) -> 90.985564 | E8: =100*(Data!F196/AVERAGE(Data!F$191:F$194)) -> 89.22755 | F8: =100*(Data!G196/AVERAGE(Data!G$191:G$194)) -> 82.956056 | G8: =100*(Data!H196/AVERAGE(Data!H$191:H$194)) -> 82.56114 | H8: =100*(Data!I196/AVERAGE(Data!I$191:I$194)) -> 87.810579 | J8: =RANK(B8,$B8:$H8) -> 7 | K8: =RANK(C8,$B8:$H8) -> 1 | L8: =RANK(D8,$B8:$H8) -> 2 | M8: =RANK(E8,$B8:$H8) -> 3 | N8: =RANK(F8,$B8:$H8) -> 5 | O8: =RANK(G8,$B8:$H8) -> 6 | P8: =RANK(H8,$B8:$H8) -> 4 | S8: =100*('ONS - Annex F'!C99/AVERAGE('ONS - Annex F'!$C$94:$C$97)) -> 77.885416 | T8: =C8 -> 91.990663 | U8: =D8 -> 90.985564 | V8: =E8 -> 89.22755 | W8: =F8 -> 82.956056 | X8: =G8 -> 82.56114 | Y8: =H8 -> 87.810579 | AB8: =B8 -> 77.839458 | AC8: =S8 -> 77.885416 | AD8: =MEDIAN($S8:$Y8) -> 87.810579 | AE8: =MIN($S8:$Y8) -> 77.885416 | AF8: =MAX($S8:$Y8)-AE8 -> 14.105248 | AG8: 100 | AI8: =RANK(S8,$S8:$Y8) -> 7 | AJ8: =RANK(T8,$S8:$Y8) -> 1 | AK8: =RANK(U8,$S8:$Y8) -> 2 | AL8: =RANK(V8,$S8:$Y8) -> 3 | AM8: =RANK(W8,$S8:$Y8) -> 5 | AN8: =RANK(X8,$S8:$Y8) -> 6 | AO8: =RANK(Y8,$S8:$Y8) -> 4 | BK8: 43617 | BL8: =100*('ONS - Table 1'!CK275/AVERAGE('ONS - Table 1'!$CK$270:$CK$281)) -> 100.30836 | BM8: =100*('ONS - Table 2'!CK275/AVERAGE('ONS - Table 2'!$CK$270:$CK$281)) -> 100.37106 | BN8: 100 | BP8: 43617 | BQ8: =100*('ONS - Table 1'!ET275/AVERAGE('ONS - Table 1'!$ET$270:$ET$281)) -> 100 | BR8: =100*('ONS - Table 2'!ET275/AVERAGE('ONS - Table 2'!$ET$270:$ET$281)) -> 100.71544 | BS8: 100 | BU8: 43617 | BV8: =100*('ONS - Table 1'!J275/AVERAGE('ONS - Table 1'!$J$270:$J$281)) -> 99.483419 | BW8: =100*('ONS - Table 2'!J275/AVERAGE('ONS - Table 2'!$J$270:$J$281)) -> 99.328639 | BX8: 100 | CL8: =+CL7+1 -> 45512 | CM8: =100*(HAVERD!F166/HAVERD!F$161) -> 97.921429 | CN8: =100*(HAVERD!AZ166/HAVERD!AZ$161) -> 97.184517 | CO8: =100*(HAVERD!C166/HAVERD!C$161) -> 97.661511 | CP8: =100*(HAVERD!E166/HAVERD!E$161) -> 97.96505 | CQ8: =100*(HAVERD!D166/HAVERD!D$161) -> 91.04964 | CR8: =100*(HAVERD!M166/HAVERD!M$161) -> 97.810169 | CS8: 100
B9: =100*(Data!C197/AVERAGE(Data!C$191:C$194)) -> 90.897216 | C9: =100*(Data!D197/AVERAGE(Data!D$191:D$194)) -> 99.128653 | D9: =100*(Data!E197/AVERAGE(Data!E$191:E$194)) -> 95.957014 | E9: =100*(Data!F197/AVERAGE(Data!F$191:F$194)) -> 96.944055 | F9: =100*(Data!G197/AVERAGE(Data!G$191:G$194)) -> 96.080525 | G9: =100*(Data!H197/AVERAGE(Data!H$191:H$194)) -> 94.048134 | H9: =100*(Data!I197/AVERAGE(Data!I$191:I$194)) -> 95.786875 | J9: =RANK(B9,$B9:$H9) -> 7 | K9: =RANK(C9,$B9:$H9) -> 1 | L9: =RANK(D9,$B9:$H9) -> 4 | M9: =RANK(E9,$B9:$H9) -> 2 | N9: =RANK(F9,$B9:$H9) -> 3 | O9: =RANK(G9,$B9:$H9) -> 6 | P9: =RANK(H9,$B9:$H9) -> 5 | S9: =100*('ONS - Annex F'!C100/AVERAGE('ONS - Annex F'!$C$94:$C$97)) -> 90.960758 | T9: =C9 -> 99.128653 | U9: =D9 -> 95.957014 | V9: =E9 -> 96.944055 | W9: =F9 -> 96.080525 | X9: =G9 -> 94.048134 | Y9: =H9 -> 95.786875 | AB9: =B9 -> 90.897216 | AC9: =S9 -> 90.960758 | AD9: =MEDIAN($S9:$Y9) -> 95.957014 | AE9: =MIN($S9:$Y9) -> 90.960758 | AF9: =MAX($S9:$Y9)-AE9 -> 8.1678952 | AG9: 100 | AI9: =RANK(S9,$S9:$Y9) -> 7 | AJ9: =RANK(T9,$S9:$Y9) -> 1 | AK9: =RANK(U9,$S9:$Y9) -> 4 | AL9: =RANK(V9,$S9:$Y9) -> 2 | AM9: =RANK(W9,$S9:$Y9) -> 3 | AN9: =RANK(X9,$S9:$Y9) -> 6 | AO9: =RANK(Y9,$S9:$Y9) -> 5 | AQ9: 2020 | AR9: =100*((AR4/AR3)-1) -> -10.359901 | AS9: =100*((AS4/AS3)-1) -> -10.296919 | AT9: =100*((AT4/AT3)-1) -> -2.2135259 | AU9: =100*((AU4/AU3)-1) -> -4.2202844 | AV9: =100*((AV4/AV3)-1) -> -4.4564223 | AW9: =100*((AW4/AW3)-1) -> -7.5918135 | AX9: =100*((AX4/AX3)-1) -> -9.0496266 | AY9: =100*((AY4/AY3)-1) -> -5.0382333 | BA9: 2020 | BB9: =100*((BB4/BB3)-1) -> -10.359901 | BC9: =100*((BC4/BC3)-1) -> -10.296919 | BD9: =100*((BD4/BD3)-1) -> -2.2135259 | BE9: =100*((BE4/BE3)-1) -> -4.2202844 | BF9: =100*((BF4/BF3)-1) -> -4.4564223 | BG9: =100*((BG4/BG3)-1) -> -7.5918135 | BH9: =100*((BH4/BH3)-1) -> -9.0496266 | BI9: =100*((BI4/BI3)-1) -> -5.0382333 | BK9: 43647 | BL9: =100*('ONS - Table 1'!CK276/AVERAGE('ONS - Table 1'!$CK$270:$CK$281)) -> 100.60838 | BM9: =100*('ONS - Table 2'!CK276/AVERAGE('ONS - Table 2'!$CK$270:$CK$281)) -> 100.46382 | BN9: 100 | BP9: 43647 | BQ9: =100*('ONS - Table 1'!ET276/AVERAGE('ONS - Table 1'!$ET$270:$ET$281)) -> 102.1 | BR9: =100*('ONS - Table 2'!ET276/AVERAGE('ONS - Table 2'!$ET$270:$ET$281)) -> 102.65405 | BS9: 100 | BU9: 43647 | BV9: =100*('ONS - Table 1'!J276/AVERAGE('ONS - Table 1'!$J$270:$J$281)) -> 100.1833 | BW9: =100*('ONS - Table 2'!J276/AVERAGE('ONS - Table 2'!$J$270:$J$281)) -> 100.21287 | BX9: 100
B10: =100*(Data!C198/AVERAGE(Data!C$191:C$194)) -> 92.130563 | C10: =100*(Data!D198/AVERAGE(Data!D$191:D$194)) -> 100.15465 | D10: =100*(Data!E198/AVERAGE(Data!E$191:E$194)) -> 97.640082 | E10: =100*(Data!F198/AVERAGE(Data!F$191:F$194)) -> 98.102023 | F10: =100*(Data!G198/AVERAGE(Data!G$191:G$194)) -> 95.941903 | G10: =100*(Data!H198/AVERAGE(Data!H$191:H$194)) -> 93.584193 | H10: =100*(Data!I198/AVERAGE(Data!I$191:I$194)) -> 97.586109 | J10: =RANK(B10,$B10:$H10) -> 7 | K10: =RANK(C10,$B10:$H10) -> 1 | L10: =RANK(D10,$B10:$H10) -> 3 | M10: =RANK(E10,$B10:$H10) -> 2 | N10: =RANK(F10,$B10:$H10) -> 5 | O10: =RANK(G10,$B10:$H10) -> 6 | P10: =RANK(H10,$B10:$H10) -> 4 | S10: =100*('ONS - Annex F'!C101/AVERAGE('ONS - Annex F'!$C$94:$C$97)) -> 92.203965 | T10: =C10 -> 100.15465 | U10: =D10 -> 97.640082 | V10: =E10 -> 98.102023 | W10: =F10 -> 95.941903 | X10: =G10 -> 93.584193 | Y10: =H10 -> 97.586109 | AB10: =B10 -> 92.130563 | AC10: =S10 -> 92.203965 | AD10: =MEDIAN($S10:$Y10) -> 97.586109 | AE10: =MIN($S10:$Y10) -> 92.203965 | AF10: =MAX($S10:$Y10)-AE10 -> 7.9506831 | AG10: 100 | AI10: =RANK(S10,$S10:$Y10) -> 7 | AJ10: =RANK(T10,$S10:$Y10) -> 1 | AK10: =RANK(U10,$S10:$Y10) -> 3 | AL10: =RANK(V10,$S10:$Y10) -> 2 | AM10: =RANK(W10,$S10:$Y10) -> 5 | AN10: =RANK(X10,$S10:$Y10) -> 6 | AO10: =RANK(Y10,$S10:$Y10) -> 4 | AQ10: 2021 | AR10: =100*((AR5/AR4)-1) -> 8.6749041 | AS10: =100*((AS5/AS4)-1) -> 8.5759509 | AT10: =100*((AT5/AT4)-1) -> 5.8001169 | AU10: =100*((AU5/AU4)-1) -> 2.7723692 | AV10: =100*((AV5/AV4)-1) -> 3.5416613 | AW10: =100*((AW5/AW4)-1) -> 6.828911 | AX10: =100*((AX5/AX4)-1) -> 8.2783053 | AY10: =100*((AY5/AY4)-1) -> 5.2869615 | BA10: 2021 | BB10: =100*((BB5/BB4)-1) -> 8.6749041 | BC10: =100*((BC5/BC4)-1) -> 8.5759509 | BD10: =100*((BD5/BD4)-1) -> 5.8001169 | BE10: =100*((BE5/BE4)-1) -> 2.7723692 | BF10: =100*((BF5/BF4)-1) -> 3.5416613 | BG10: =100*((BG5/BG4)-1) -> 6.828911 | BH10: =100*((BH5/BH4)-1) -> 8.2783053 | BI10: =100*((BI5/BI4)-1) -> 5.2869615 | BK10: 43678 | BL10: =100*('ONS - Table 1'!CK277/AVERAGE('ONS - Table 1'!$CK$270:$CK$281)) -> 100.00833 | BM10: =100*('ONS - Table 2'!CK277/AVERAGE('ONS - Table 2'!$CK$270:$CK$281)) -> 99.907236 | BN10: 100 | BP10: 43678 | BQ10: =100*('ONS - Table 1'!ET277/AVERAGE('ONS - Table 1'!$ET$270:$ET$281)) -> 100.1 | BR10: =100*('ONS - Table 2'!ET277/AVERAGE('ONS - Table 2'!$ET$270:$ET$281)) -> 100.34618 | BS10: 100 | BU10: 43678 | BV10: =100*('ONS - Table 1'!J277/AVERAGE('ONS - Table 1'!$J$270:$J$281)) -> 99.283453 | BW10: =100*('ONS - Table 2'!J277/AVERAGE('ONS - Table 2'!$J$270:$J$281)) -> 99.525135 | BX10: 100 | CM10: =100*((CM8/CM3)-1) -> -2.0785707 | CN10: =100*((CN8/CN3)-1) -> -2.8154827 | CO10: =100*((CO8/CO3)-1) -> -2.3384888 | CP10: =100*((CP8/CP3)-1) -> -2.0349496 | CQ10: =100*((CQ8/CQ3)-1) -> -8.9503604 | CR10: =100*((CR8/CR3)-1) -> -2.1898315
A11: 2021 | B11: =100*(Data!C199/AVERAGE(Data!C$191:C$194)) -> 91.186931 | C11: =100*(Data!D199/AVERAGE(Data!D$191:D$194)) -> 101.4421 | D11: =100*(Data!E199/AVERAGE(Data!E$191:E$194)) -> 97.930608 | E11: =100*(Data!F199/AVERAGE(Data!F$191:F$194)) -> 96.895113 | F11: =100*(Data!G199/AVERAGE(Data!G$191:G$194)) -> 96.229517 | G11: =100*(Data!H199/AVERAGE(Data!H$191:H$194)) -> 95.007023 | H11: =100*(Data!I199/AVERAGE(Data!I$191:I$194)) -> 98.99122 | J11: =RANK(B11,$B11:$H11) -> 7 | K11: =RANK(C11,$B11:$H11) -> 1 | L11: =RANK(D11,$B11:$H11) -> 3 | M11: =RANK(E11,$B11:$H11) -> 4 | N11: =RANK(F11,$B11:$H11) -> 5 | O11: =RANK(G11,$B11:$H11) -> 6 | P11: =RANK(H11,$B11:$H11) -> 2 | R11: 2021 | S11: =100*('ONS - Annex F'!C102/AVERAGE('ONS - Annex F'!$C$94:$C$97)) -> 91.245774 | T11: =C11 -> 101.4421 | U11: =D11 -> 97.930608 | V11: =E11 -> 96.895113 | W11: =F11 -> 96.229517 | X11: =G11 -> 95.007023 | Y11: =H11 -> 98.99122 | AA11: 2021 | AB11: =B11 -> 91.186931 | AC11: =S11 -> 91.245774 | AD11: =MEDIAN($S11:$Y11) -> 96.895113 | AE11: =MIN($S11:$Y11) -> 91.245774 | AF11: =MAX($S11:$Y11)-AE11 -> 10.196322 | AG11: 100 | AI11: =RANK(S11,$S11:$Y11) -> 7 | AJ11: =RANK(T11,$S11:$Y11) -> 1 | AK11: =RANK(U11,$S11:$Y11) -> 3 | AL11: =RANK(V11,$S11:$Y11) -> 4 | AM11: =RANK(W11,$S11:$Y11) -> 5 | AN11: =RANK(X11,$S11:$Y11) -> 6 | AO11: =RANK(Y11,$S11:$Y11) -> 2 | AQ11: 2022 | AR11: =100*((AR6/AR5)-1) -> 4.3452288 | AS11: =100*((AS6/AS5)-1) -> 4.8390852 | AT11: =100*((AT6/AT5)-1) -> 1.9356376 | AU11: =100*((AU6/AU5)-1) -> 1.1872723 | AV11: =100*((AV6/AV5)-1) -> 1.7375183 | AW11: =100*((AW6/AW5)-1) -> 2.6186879 | AX11: =100*((AX6/AX5)-1) -> 4.1452457 | AY11: =100*((AY6/AY5)-1) -> 3.8198683 | BA11: 2022 | BB11: =100*((BB6/BB5)-1) -> 4.3452288 | BC11: =100*((BC6/BC5)-1) -> 4.8390852 | BD11: =100*((BD6/BD5)-1) -> 1.9356376 | BE11: =100*((BE6/BE5)-1) -> 1.1872723 | BF11: =100*((BF6/BF5)-1) -> 1.7375183 | BG11: =100*((BG6/BG5)-1) -> 2.6186879 | BH11: =100*((BH6/BH5)-1) -> 4.1452457 | BI11: =100*((BI6/BI5)-1) -> 3.8198683 | BK11: 43709 | BL11: =100*('ONS - Table 1'!CK278/AVERAGE('ONS - Table 1'!$CK$270:$CK$281)) -> 98.708226 | BM11: =100*('ONS - Table 2'!CK278/AVERAGE('ONS - Table 2'!$CK$270:$CK$281)) -> 99.443414 | BN11: 100 | BP11: 43709 | BQ11: =100*('ONS - Table 1'!ET278/AVERAGE('ONS - Table 1'!$ET$270:$ET$281)) -> 100.9 | BR11: =100*('ONS - Table 2'!ET278/AVERAGE('ONS - Table 2'!$ET$270:$ET$281)) -> 101.17701 | BS11: 100 | BU11: 43709 | BV11: =100*('ONS - Table 1'!J278/AVERAGE('ONS - Table 1'!$J$270:$J$281)) -> 100.7832 | BW11: =100*('ONS - Table 2'!J278/AVERAGE('ONS - Table 2'!$J$270:$J$281)) -> 100.90061 | BX11: 100
B12: =100*(Data!C200/AVERAGE(Data!C$191:C$194)) -> 97.868994 | C12: =100*(Data!D200/AVERAGE(Data!D$191:D$194)) -> 102.98375 | D12: =100*(Data!E200/AVERAGE(Data!E$191:E$194)) -> 98.415228 | E12: =100*(Data!F200/AVERAGE(Data!F$191:F$194)) -> 99.317841 | F12: =100*(Data!G200/AVERAGE(Data!G$191:G$194)) -> 97.491954 | G12: =100*(Data!H200/AVERAGE(Data!H$191:H$194)) -> 97.51832 | H12: =100*(Data!I200/AVERAGE(Data!I$191:I$194)) -> 98.682511 | J12: =RANK(B12,$B12:$H12) -> 5 | K12: =RANK(C12,$B12:$H12) -> 1 | L12: =RANK(D12,$B12:$H12) -> 4 | M12: =RANK(E12,$B12:$H12) -> 2 | N12: =RANK(F12,$B12:$H12) -> 7 | O12: =RANK(G12,$B12:$H12) -> 6 | P12: =RANK(H12,$B12:$H12) -> 3 | S12: =100*('ONS - Annex F'!C103/AVERAGE('ONS - Annex F'!$C$94:$C$97)) -> 97.864682 | T12: =C12 -> 102.98375 | U12: =D12 -> 98.415228 | V12: =E12 -> 99.317841 | W12: =F12 -> 97.491954 | X12: =G12 -> 97.51832 | Y12: =H12 -> 98.682511 | AB12: =B12 -> 97.868994 | AC12: =S12 -> 97.864682 | AD12: =MEDIAN($S12:$Y12) -> 98.415228 | AE12: =MIN($S12:$Y12) -> 97.491954 | AF12: =MAX($S12:$Y12)-AE12 -> 5.4917932 | AG12: 100 | AI12: =RANK(S12,$S12:$Y12) -> 5 | AJ12: =RANK(T12,$S12:$Y12) -> 1 | AK12: =RANK(U12,$S12:$Y12) -> 4 | AL12: =RANK(V12,$S12:$Y12) -> 2 | AM12: =RANK(W12,$S12:$Y12) -> 7 | AN12: =RANK(X12,$S12:$Y12) -> 6 | AO12: =RANK(Y12,$S12:$Y12) -> 3 | AQ12: 2023 | AR12: =100*((AR7/AR6)-1) -> 0.10401785 | AT12: =100*((AT7/AT6)-1) -> 2.5427263 | AU12: =100*((AU7/AU6)-1) -> 1.8085472 | AV12: =100*((AV7/AV6)-1) -> -0.059403147 | AW12: =100*((AW7/AW6)-1) -> 1.1200591 | AX12: =100*((AX7/AX6)-1) -> 1.01723 | AY12: =100*((AY7/AY6)-1) -> 1.2489208 | BA12: 2023 | BB12: =100*((BB7/BB6)-1) -> 0.10401785 | BD12: =100*((BD7/BD6)-1) -> 2.5427263 | BE12: =100*((BE7/BE6)-1) -> 1.8085472 | BF12: =100*((BF7/BF6)-1) -> -0.059403147 | BG12: =100*((BG7/BG6)-1) -> 1.1200591 | BH12: =100*((BH7/BH6)-1) -> 1.01723 | BI12: =100*((BI7/BI6)-1) -> 1.2489208 | BK12: 43739 | BL12: =100*('ONS - Table 1'!CK279/AVERAGE('ONS - Table 1'!$CK$270:$CK$281)) -> 99.508292 | BM12: =100*('ONS - Table 2'!CK279/AVERAGE('ONS - Table 2'!$CK$270:$CK$281)) -> 98.701299 | BN12: 100 | BP12: 43739 | BQ12: =100*('ONS - Table 1'!ET279/AVERAGE('ONS - Table 1'!$ET$270:$ET$281)) -> 99.7 | BR12: =100*('ONS - Table 2'!ET279/AVERAGE('ONS - Table 2'!$ET$270:$ET$281)) -> 100.16155 | BS12: 100 | BU12: 43739 | BV12: =100*('ONS - Table 1'!J279/AVERAGE('ONS - Table 1'!$J$270:$J$281)) -> 101.78304 | BW12: =100*('ONS - Table 2'!J279/AVERAGE('ONS - Table 2'!$J$270:$J$281)) -> 101.49009 | BX12: 100
B13: =100*(Data!C201/AVERAGE(Data!C$191:C$194)) -> 99.548014 | C13: =100*(Data!D201/AVERAGE(Data!D$191:D$194)) -> 103.82271 | D13: =100*(Data!E201/AVERAGE(Data!E$191:E$194)) -> 98.099581 | E13: =100*(Data!F201/AVERAGE(Data!F$191:F$194)) -> 99.451334 | F13: =100*(Data!G201/AVERAGE(Data!G$191:G$194)) -> 100.27637 | G13: =100*(Data!H201/AVERAGE(Data!H$191:H$194)) -> 100.28392 | H13: =100*(Data!I201/AVERAGE(Data!I$191:I$194)) -> 100.34051 | J13: =RANK(B13,$B13:$H13) -> 5 | K13: =RANK(C13,$B13:$H13) -> 1 | L13: =RANK(D13,$B13:$H13) -> 7 | M13: =RANK(E13,$B13:$H13) -> 6 | N13: =RANK(F13,$B13:$H13) -> 4 | O13: =RANK(G13,$B13:$H13) -> 3 | P13: =RANK(H13,$B13:$H13) -> 2 | S13: =100*('ONS - Annex F'!C104/AVERAGE('ONS - Annex F'!$C$94:$C$97)) -> 99.498473 | T13: =C13 -> 103.82271 | U13: =D13 -> 98.099581 | V13: =E13 -> 99.451334 | W13: =F13 -> 100.27637 | X13: =G13 -> 100.28392 | Y13: =H13 -> 100.34051 | AB13: =B13 -> 99.548014 | AC13: =S13 -> 99.498473 | AD13: =MEDIAN($S13:$Y13) -> 100.27637 | AE13: =MIN($S13:$Y13) -> 98.099581 | AF13: =MAX($S13:$Y13)-AE13 -> 5.7231343 | AG13: 100 | AI13: =RANK(S13,$S13:$Y13) -> 5 | AJ13: =RANK(T13,$S13:$Y13) -> 1 | AK13: =RANK(U13,$S13:$Y13) -> 7 | AL13: =RANK(V13,$S13:$Y13) -> 6 | AM13: =RANK(W13,$S13:$Y13) -> 4 | AN13: =RANK(X13,$S13:$Y13) -> 3 | AO13: =RANK(Y13,$S13:$Y13) -> 2 | BK13: 43770 | BL13: =100*('ONS - Table 1'!CK280/AVERAGE('ONS - Table 1'!$CK$270:$CK$281)) -> 98.908242 | BM13: =100*('ONS - Table 2'!CK280/AVERAGE('ONS - Table 2'!$CK$270:$CK$281)) -> 98.51577 | BN13: 100 | BP13: 43770 | BQ13: =100*('ONS - Table 1'!ET280/AVERAGE('ONS - Table 1'!$ET$270:$ET$281)) -> 100.1 | BR13: =100*('ONS - Table 2'!ET280/AVERAGE('ONS - Table 2'!$ET$270:$ET$281)) -> 98.499885 | BS13: 100 | BU13: 43770 | BV13: =100*('ONS - Table 1'!J280/AVERAGE('ONS - Table 1'!$J$270:$J$281)) -> 100.98317 | BW13: =100*('ONS - Table 2'!J280/AVERAGE('ONS - Table 2'!$J$270:$J$281)) -> 100.90061 | BX13: 100
B14: =100*(Data!C202/AVERAGE(Data!C$191:C$194)) -> 101.06123 | C14: =100*(Data!D202/AVERAGE(Data!D$191:D$194)) -> 105.58426 | D14: =100*(Data!E202/AVERAGE(Data!E$191:E$194)) -> 99.294915 | E14: =100*(Data!F202/AVERAGE(Data!F$191:F$194)) -> 100.04534 | F14: =100*(Data!G202/AVERAGE(Data!G$191:G$194)) -> 100.8768 | G14: =100*(Data!H202/AVERAGE(Data!H$191:H$194)) -> 101.10883 | H14: =100*(Data!I202/AVERAGE(Data!I$191:I$194)) -> 101.9152 | J14: =RANK(B14,$B14:$H14) -> 4 | K14: =RANK(C14,$B14:$H14) -> 1 | L14: =RANK(D14,$B14:$H14) -> 7 | M14: =RANK(E14,$B14:$H14) -> 6 | N14: =RANK(F14,$B14:$H14) -> 5 | O14: =RANK(G14,$B14:$H14) -> 3 | P14: =RANK(H14,$B14:$H14) -> 2 | S14: =100*('ONS - Annex F'!C105/AVERAGE('ONS - Annex F'!$C$94:$C$97)) -> 100.97496 | T14: =C14 -> 105.58426 | U14: =D14 -> 99.294915 | V14: =E14 -> 100.04534 | W14: =F14 -> 100.8768 | X14: =G14 -> 101.10883 | Y14: =H14 -> 101.9152 | AB14: =B14 -> 101.06123 | AC14: =S14 -> 100.97496 | AD14: =MEDIAN($S14:$Y14) -> 100.97496 | AE14: =MIN($S14:$Y14) -> 99.294915 | AF14: =MAX($S14:$Y14)-AE14 -> 6.2893419 | AG14: 100 | AI14: =RANK(S14,$S14:$Y14) -> 4 | AJ14: =RANK(T14,$S14:$Y14) -> 1 | AK14: =RANK(U14,$S14:$Y14) -> 7 | AL14: =RANK(V14,$S14:$Y14) -> 6 | AM14: =RANK(W14,$S14:$Y14) -> 5 | AN14: =RANK(X14,$S14:$Y14) -> 3 | AO14: =RANK(Y14,$S14:$Y14) -> 2 | BK14: 43800 | BL14: =100*('ONS - Table 1'!CK281/AVERAGE('ONS - Table 1'!$CK$270:$CK$281)) -> 98.008167 | BM14: =100*('ONS - Table 2'!CK281/AVERAGE('ONS - Table 2'!$CK$270:$CK$281)) -> 97.866419 | BN14: 100 | BP14: 43800 | BQ14: =100*('ONS - Table 1'!ET281/AVERAGE('ONS - Table 1'!$ET$270:$ET$281)) -> 101.1 | BR14: =100*('ONS - Table 2'!ET281/AVERAGE('ONS - Table 2'!$ET$270:$ET$281)) -> 97.392107 | BS14: 100 | BU14: 43800 | BV14: =100*('ONS - Table 1'!J281/AVERAGE('ONS - Table 1'!$J$270:$J$281)) -> 103.1828 | BW14: =100*('ONS - Table 2'!J281/AVERAGE('ONS - Table 2'!$J$270:$J$281)) -> 103.06206 | BX14: 100
A15: 2022 | B15: =100*(Data!C203/AVERAGE(Data!C$191:C$194)) -> 101.59643 | C15: =100*(Data!D203/AVERAGE(Data!D$191:D$194)) -> 105.05894 | D15: =100*(Data!E203/AVERAGE(Data!E$191:E$194)) -> 98.740939 | E15: =100*(Data!F203/AVERAGE(Data!F$191:F$194)) -> 100.46693 | F15: =100*(Data!G203/AVERAGE(Data!G$191:G$194)) -> 100.73323 | G15: =100*(Data!H203/AVERAGE(Data!H$191:H$194)) -> 101.30991 | H15: =100*(Data!I203/AVERAGE(Data!I$191:I$194)) -> 102.89488 | J15: =RANK(B15,$B15:$H15) -> 3 | K15: =RANK(C15,$B15:$H15) -> 1 | L15: =RANK(D15,$B15:$H15) -> 7 | M15: =RANK(E15,$B15:$H15) -> 6 | N15: =RANK(F15,$B15:$H15) -> 5 | O15: =RANK(G15,$B15:$H15) -> 4 | P15: =RANK(H15,$B15:$H15) -> 2 | R15: 2022 | S15: =100*('ONS - Annex F'!C106/AVERAGE('ONS - Annex F'!$C$94:$C$97)) -> 101.71167 | T15: =C15 -> 105.05894 | U15: =D15 -> 98.740939 | V15: =E15 -> 100.46693 | W15: =F15 -> 100.73323 | X15: =G15 -> 101.30991 | Y15: =H15 -> 102.89488 | AA15: 2022 | AB15: =B15 -> 101.59643 | AC15: =S15 -> 101.71167 | AD15: =MEDIAN($S15:$Y15) -> 101.30991 | AE15: =MIN($S15:$Y15) -> 98.740939 | AF15: =MAX($S15:$Y15)-AE15 -> 6.3179966 | AG15: 100 | AI15: =RANK(S15,$S15:$Y15) -> 3 | AJ15: =RANK(T15,$S15:$Y15) -> 1 | AK15: =RANK(U15,$S15:$Y15) -> 7 | AL15: =RANK(V15,$S15:$Y15) -> 6 | AM15: =RANK(W15,$S15:$Y15) -> 5 | AN15: =RANK(X15,$S15:$Y15) -> 4 | AO15: =RANK(Y15,$S15:$Y15) -> 2 | BK15: 43831 | BL15: =100*('ONS - Table 1'!CK282/AVERAGE('ONS - Table 1'!$CK$270:$CK$281)) -> 97.508126 | BM15: =100*('ONS - Table 2'!CK282/AVERAGE('ONS - Table 2'!$CK$270:$CK$281)) -> 97.03154 | BN15: 100 | BP15: 43831 | BQ15: =100*('ONS - Table 1'!ET282/AVERAGE('ONS - Table 1'!$ET$270:$ET$281)) -> 101.8 | BR15: =100*('ONS - Table 2'!ET282/AVERAGE('ONS - Table 2'!$ET$270:$ET$281)) -> 98.22294 | BS15: 100 | BU15: 43831 | BV15: =100*('ONS - Table 1'!J282/AVERAGE('ONS - Table 1'!$J$270:$J$281)) -> 105.88235 | BW15: =100*('ONS - Table 2'!J282/AVERAGE('ONS - Table 2'!$J$270:$J$281)) -> 105.71475 | BX15: 100
B16: =100*(Data!C204/AVERAGE(Data!C$191:C$194)) -> 101.68471 | C16: =100*(Data!D204/AVERAGE(Data!D$191:D$194)) -> 104.91057 | D16: =100*(Data!E204/AVERAGE(Data!E$191:E$194)) -> 99.897396 | E16: =100*(Data!F204/AVERAGE(Data!F$191:F$194)) -> 100.4569 | F16: =100*(Data!G204/AVERAGE(Data!G$191:G$194)) -> 101.11337 | G16: =100*(Data!H204/AVERAGE(Data!H$191:H$194)) -> 102.72696 | H16: =100*(Data!I204/AVERAGE(Data!I$191:I$194)) -> 103.86154 | J16: =RANK(B16,$B16:$H16) -> 4 | K16: =RANK(C16,$B16:$H16) -> 1 | L16: =RANK(D16,$B16:$H16) -> 7 | M16: =RANK(E16,$B16:$H16) -> 6 | N16: =RANK(F16,$B16:$H16) -> 5 | O16: =RANK(G16,$B16:$H16) -> 3 | P16: =RANK(H16,$B16:$H16) -> 2 | S16: =100*('ONS - Annex F'!C107/AVERAGE('ONS - Annex F'!$C$94:$C$97)) -> 102.05263 | T16: =C16 -> 104.91057 | U16: =D16 -> 99.897396 | V16: =E16 -> 100.4569 | W16: =F16 -> 101.11337 | X16: =G16 -> 102.72696 | Y16: =H16 -> 103.86154 | AB16: =B16 -> 101.68471 | AC16: =S16 -> 102.05263 | AD16: =MEDIAN($S16:$Y16) -> 102.05263 | AE16: =MIN($S16:$Y16) -> 99.897396 | AF16: =MAX($S16:$Y16)-AE16 -> 5.0131733 | AG16: 100 | AI16: =RANK(S16,$S16:$Y16) -> 4 | AJ16: =RANK(T16,$S16:$Y16) -> 1 | AK16: =RANK(U16,$S16:$Y16) -> 7 | AL16: =RANK(V16,$S16:$Y16) -> 6 | AM16: =RANK(W16,$S16:$Y16) -> 5 | AN16: =RANK(X16,$S16:$Y16) -> 3 | AO16: =RANK(Y16,$S16:$Y16) -> 2 | BK16: 43862 | BL16: =100*('ONS - Table 1'!CK283/AVERAGE('ONS - Table 1'!$CK$270:$CK$281)) -> 96.608051 | BM16: =100*('ONS - Table 2'!CK283/AVERAGE('ONS - Table 2'!$CK$270:$CK$281)) -> 96.103896 | BN16: 100 | BP16: 43862 | BQ16: =100*('ONS - Table 1'!ET283/AVERAGE('ONS - Table 1'!$ET$270:$ET$281)) -> 102 | BR16: =100*('ONS - Table 2'!ET283/AVERAGE('ONS - Table 2'!$ET$270:$ET$281)) -> 97.022848 | BS16: 100 | BU16: 43862 | BV16: =100*('ONS - Table 1'!J283/AVERAGE('ONS - Table 1'!$J$270:$J$281)) -> 107.68205 | BW16: =100*('ONS - Table 2'!J283/AVERAGE('ONS - Table 2'!$J$270:$J$281)) -> 107.87621 | BX16: 100
B17: =100*(Data!C205/AVERAGE(Data!C$191:C$194)) -> 101.6052 | C17: =100*(Data!D205/AVERAGE(Data!D$191:D$194)) -> 105.60117 | D17: =100*(Data!E205/AVERAGE(Data!E$191:E$194)) -> 99.706488 | E17: =100*(Data!F205/AVERAGE(Data!F$191:F$194)) -> 101.09874 | F17: =100*(Data!G205/AVERAGE(Data!G$191:G$194)) -> 101.65621 | G17: =100*(Data!H205/AVERAGE(Data!H$191:H$194)) -> 103.13328 | H17: =100*(Data!I205/AVERAGE(Data!I$191:I$194)) -> 104.33724 | J17: =RANK(B17,$B17:$H17) -> 5 | K17: =RANK(C17,$B17:$H17) -> 1 | L17: =RANK(D17,$B17:$H17) -> 7 | M17: =RANK(E17,$B17:$H17) -> 6 | N17: =RANK(F17,$B17:$H17) -> 4 | O17: =RANK(G17,$B17:$H17) -> 3 | P17: =RANK(H17,$B17:$H17) -> 2 | S17: =100*('ONS - Annex F'!C108/AVERAGE('ONS - Annex F'!$C$94:$C$97)) -> 102.16886 | T17: =C17 -> 105.60117 | U17: =D17 -> 99.706488 | V17: =E17 -> 101.09874 | W17: =F17 -> 101.65621 | X17: =G17 -> 103.13328 | Y17: =H17 -> 104.33724 | AB17: =B17 -> 101.6052 | AC17: =S17 -> 102.16886 | AD17: =MEDIAN($S17:$Y17) -> 102.16886 | AE17: =MIN($S17:$Y17) -> 99.706488 | AF17: =MAX($S17:$Y17)-AE17 -> 5.8946839 | AG17: 100 | AI17: =RANK(S17,$S17:$Y17) -> 4 | AJ17: =RANK(T17,$S17:$Y17) -> 1 | AK17: =RANK(U17,$S17:$Y17) -> 7 | AL17: =RANK(V17,$S17:$Y17) -> 6 | AM17: =RANK(W17,$S17:$Y17) -> 5 | AN17: =RANK(X17,$S17:$Y17) -> 3 | AO17: =RANK(Y17,$S17:$Y17) -> 2 | BK17: 43891 | BL17: =100*('ONS - Table 1'!CK284/AVERAGE('ONS - Table 1'!$CK$270:$CK$281)) -> 82.806901 | BM17: =100*('ONS - Table 2'!CK284/AVERAGE('ONS - Table 2'!$CK$270:$CK$281)) -> 83.116883 | BN17: 100 | BP17: 43891 | BQ17: =100*('ONS - Table 1'!ET284/AVERAGE('ONS - Table 1'!$ET$270:$ET$281)) -> 86.9 | BR17: =100*('ONS - Table 2'!ET284/AVERAGE('ONS - Table 2'!$ET$270:$ET$281)) -> 83.175629 | BS17: 100 | BU17: 43891 | BV17: =100*('ONS - Table 1'!J284/AVERAGE('ONS - Table 1'!$J$270:$J$281)) -> 97.383769 | BW17: =100*('ONS - Table 2'!J284/AVERAGE('ONS - Table 2'!$J$270:$J$281)) -> 97.756673 | BX17: 100
B18: =100*(Data!C206/AVERAGE(Data!C$191:C$194)) -> 101.71067 | C18: =100*(Data!D206/AVERAGE(Data!D$191:D$194)) -> 106.27244 | D18: =100*(Data!E206/AVERAGE(Data!E$191:E$194)) -> 100.07028 | E18: =100*(Data!F206/AVERAGE(Data!F$191:F$194)) -> 100.56258 | F18: =100*(Data!G206/AVERAGE(Data!G$191:G$194)) -> 101.71236 | G18: =100*(Data!H206/AVERAGE(Data!H$191:H$194)) -> 103.07682 | H18: =100*(Data!I206/AVERAGE(Data!I$191:I$194)) -> 104.11255 | J18: =RANK(B18,$B18:$H18) -> 5 | K18: =RANK(C18,$B18:$H18) -> 1 | L18: =RANK(D18,$B18:$H18) -> 7 | M18: =RANK(E18,$B18:$H18) -> 6 | N18: =RANK(F18,$B18:$H18) -> 4 | O18: =RANK(G18,$B18:$H18) -> 3 | P18: =RANK(H18,$B18:$H18) -> 2 | S18: =100*('ONS - Annex F'!C109/AVERAGE('ONS - Annex F'!$C$94:$C$97)) -> 102.50303 | T18: =C18 -> 106.27244 | U18: =D18 -> 100.07028 | V18: =E18 -> 100.56258 | W18: =F18 -> 101.71236 | X18: =G18 -> 103.07682 | Y18: =H18 -> 104.11255 | AB18: =B18 -> 101.71067 | AC18: =S18 -> 102.50303 | AD18: =MEDIAN($S18:$Y18) -> 102.50303 | AE18: =MIN($S18:$Y18) -> 100.07028 | AF18: =MAX($S18:$Y18)-AE18 -> 6.2021635 | AG18: 100 | AI18: =RANK(S18,$S18:$Y18) -> 4 | AJ18: =RANK(T18,$S18:$Y18) -> 1 | AK18: =RANK(U18,$S18:$Y18) -> 7 | AL18: =RANK(V18,$S18:$Y18) -> 6 | AM18: =RANK(W18,$S18:$Y18) -> 5 | AN18: =RANK(X18,$S18:$Y18) -> 3 | AO18: =RANK(Y18,$S18:$Y18) -> 2 | BK18: 43922 | BL18: =100*('ONS - Table 1'!CK285/AVERAGE('ONS - Table 1'!$CK$270:$CK$281)) -> 64.505375 | BM18: =100*('ONS - Table 2'!CK285/AVERAGE('ONS - Table 2'!$CK$270:$CK$281)) -> 64.471243 | BN18: 100 | BP18: 43922 | BQ18: =100*('ONS - Table 1'!ET285/AVERAGE('ONS - Table 1'!$ET$270:$ET$281)) -> 50.9 | BR18: =100*('ONS - Table 2'!ET285/AVERAGE('ONS - Table 2'!$ET$270:$ET$281)) -> 55.481191 | BS18: 100 | BU18: 43922 | BV18: =100*('ONS - Table 1'!J285/AVERAGE('ONS - Table 1'!$J$270:$J$281)) -> 77.587069 | BW18: =100*('ONS - Table 2'!J285/AVERAGE('ONS - Table 2'!$J$270:$J$281)) -> 77.026363 | BX18: 100
BK19: 43952 | BL19: =100*('ONS - Table 1'!CK286/AVERAGE('ONS - Table 1'!$CK$270:$CK$281)) -> 76.406367 | BM19: =100*('ONS - Table 2'!CK286/AVERAGE('ONS - Table 2'!$CK$270:$CK$281)) -> 76.159555 | BN19: 100 | BP19: 43952 | BQ19: =100*('ONS - Table 1'!ET286/AVERAGE('ONS - Table 1'!$ET$270:$ET$281)) -> 52.3 | BR19: =100*('ONS - Table 2'!ET286/AVERAGE('ONS - Table 2'!$ET$270:$ET$281)) -> 55.204246 | BS19: 100 | BU19: 43952 | BV19: =100*('ONS - Table 1'!J286/AVERAGE('ONS - Table 1'!$J$270:$J$281)) -> 86.385602 | BW19: =100*('ONS - Table 2'!J286/AVERAGE('ONS - Table 2'!$J$270:$J$281)) -> 84.493205 | BX19: 100
BK20: 43983 | BL20: =100*('ONS - Table 1'!CK287/AVERAGE('ONS - Table 1'!$CK$270:$CK$281)) -> 88.507376 | BM20: =100*('ONS - Table 2'!CK287/AVERAGE('ONS - Table 2'!$CK$270:$CK$281)) -> 87.755102 | BN20: 100 | BP20: 43983 | BQ20: =100*('ONS - Table 1'!ET287/AVERAGE('ONS - Table 1'!$ET$270:$ET$281)) -> 57 | BR20: =100*('ONS - Table 2'!ET287/AVERAGE('ONS - Table 2'!$ET$270:$ET$281)) -> 58.250635 | BS20: 100 | BU20: 43983 | BV20: =100*('ONS - Table 1'!J287/AVERAGE('ONS - Table 1'!$J$270:$J$281)) -> 97.883686 | BW20: =100*('ONS - Table 2'!J287/AVERAGE('ONS - Table 2'!$J$270:$J$281)) -> 96.675946 | BX20: 100
BK21: 44013 | BL21: =100*('ONS - Table 1'!CK288/AVERAGE('ONS - Table 1'!$CK$270:$CK$281)) -> 90.707559 | BM21: =100*('ONS - Table 2'!CK288/AVERAGE('ONS - Table 2'!$CK$270:$CK$281)) -> 89.61039 | BN21: 100 | BP21: 44013 | BQ21: =100*('ONS - Table 1'!ET288/AVERAGE('ONS - Table 1'!$ET$270:$ET$281)) -> 60.8 | BR21: =100*('ONS - Table 2'!ET288/AVERAGE('ONS - Table 2'!$ET$270:$ET$281)) -> 62.497115 | BS21: 100 | BU21: 44013 | BV21: =100*('ONS - Table 1'!J288/AVERAGE('ONS - Table 1'!$J$270:$J$281)) -> 104.58257 | BW21: =100*('ONS - Table 2'!J288/AVERAGE('ONS - Table 2'!$J$270:$J$281)) -> 103.65155 | BX21: 100
BK22: 44044 | BL22: =100*('ONS - Table 1'!CK289/AVERAGE('ONS - Table 1'!$CK$270:$CK$281)) -> 91.807651 | BM22: =100*('ONS - Table 2'!CK289/AVERAGE('ONS - Table 2'!$CK$270:$CK$281)) -> 90.630798 | BN22: 100 | BP22: 44044 | BQ22: =100*('ONS - Table 1'!ET289/AVERAGE('ONS - Table 1'!$ET$270:$ET$281)) -> 63 | BR22: =100*('ONS - Table 2'!ET289/AVERAGE('ONS - Table 2'!$ET$270:$ET$281)) -> 65.543503 | BS22: 100 | BU22: 44044 | BV22: =100*('ONS - Table 1'!J289/AVERAGE('ONS - Table 1'!$J$270:$J$281)) -> 108.5819 | BW22: =100*('ONS - Table 2'!J289/AVERAGE('ONS - Table 2'!$J$270:$J$281)) -> 108.36745 | BX22: 100
BK23: 44075 | BL23: =100*('ONS - Table 1'!CK290/AVERAGE('ONS - Table 1'!$CK$270:$CK$281)) -> 93.007751 | BM23: =100*('ONS - Table 2'!CK290/AVERAGE('ONS - Table 2'!$CK$270:$CK$281)) -> 92.022263 | BN23: 100 | BP23: 44075 | BQ23: =100*('ONS - Table 1'!ET290/AVERAGE('ONS - Table 1'!$ET$270:$ET$281)) -> 65.2 | BR23: =100*('ONS - Table 2'!ET290/AVERAGE('ONS - Table 2'!$ET$270:$ET$281)) -> 67.666744 | BS23: 100 | BU23: 44075 | BV23: =100*('ONS - Table 1'!J290/AVERAGE('ONS - Table 1'!$J$270:$J$281)) -> 110.28162 | BW23: =100*('ONS - Table 2'!J290/AVERAGE('ONS - Table 2'!$J$270:$J$281)) -> 111.11839 | BX23: 100
BK24: 44105 | BL24: =100*('ONS - Table 1'!CK291/AVERAGE('ONS - Table 1'!$CK$270:$CK$281)) -> 93.807817 | BM24: =100*('ONS - Table 2'!CK291/AVERAGE('ONS - Table 2'!$CK$270:$CK$281)) -> 92.207792 | BN24: 100 | BP24: 44105 | BQ24: =100*('ONS - Table 1'!ET291/AVERAGE('ONS - Table 1'!$ET$270:$ET$281)) -> 66.5 | BR24: =100*('ONS - Table 2'!ET291/AVERAGE('ONS - Table 2'!$ET$270:$ET$281)) -> 69.32841 | BS24: 100 | BU24: 44105 | BV24: =100*('ONS - Table 1'!J291/AVERAGE('ONS - Table 1'!$J$270:$J$281)) -> 110.28162 | BW24: =100*('ONS - Table 2'!J291/AVERAGE('ONS - Table 2'!$J$270:$J$281)) -> 110.23416 | BX24: 100
BK25: 44136 | BL25: =100*('ONS - Table 1'!CK292/AVERAGE('ONS - Table 1'!$CK$270:$CK$281)) -> 90.207517 | BM25: =100*('ONS - Table 2'!CK292/AVERAGE('ONS - Table 2'!$CK$270:$CK$281)) -> 88.589981 | BN25: 100 | BP25: 44136 | BQ25: =100*('ONS - Table 1'!ET292/AVERAGE('ONS - Table 1'!$ET$270:$ET$281)) -> 66.4 | BR25: =100*('ONS - Table 2'!ET292/AVERAGE('ONS - Table 2'!$ET$270:$ET$281)) -> 69.420725 | BS25: 100 | BU25: 44136 | BV25: =100*('ONS - Table 1'!J292/AVERAGE('ONS - Table 1'!$J$270:$J$281)) -> 111.48142 | BW25: =100*('ONS - Table 2'!J292/AVERAGE('ONS - Table 2'!$J$270:$J$281)) -> 112.59211 | BX25: 100
BK26: 44166 | BL26: =100*('ONS - Table 1'!CK293/AVERAGE('ONS - Table 1'!$CK$270:$CK$281)) -> 91.707642 | BM26: =100*('ONS - Table 2'!CK293/AVERAGE('ONS - Table 2'!$CK$270:$CK$281)) -> 90.352505 | BN26: 100 | BP26: 44166 | BQ26: =100*('ONS - Table 1'!ET293/AVERAGE('ONS - Table 1'!$ET$270:$ET$281)) -> 66.8 | BR26: =100*('ONS - Table 2'!ET293/AVERAGE('ONS - Table 2'!$ET$270:$ET$281)) -> 70.066928 | BS26: 100 | BU26: 44166 | BV26: =100*('ONS - Table 1'!J293/AVERAGE('ONS - Table 1'!$J$270:$J$281)) -> 108.68189 | BW26: =100*('ONS - Table 2'!J293/AVERAGE('ONS - Table 2'!$J$270:$J$281)) -> 111.11839 | BX26: 100
BK27: 44197 | BL27: =100*('ONS - Table 1'!CK294/AVERAGE('ONS - Table 1'!$CK$270:$CK$281)) -> 85.607134 | BM27: =100*('ONS - Table 2'!CK294/AVERAGE('ONS - Table 2'!$CK$270:$CK$281)) -> 83.209647 | BN27: 100 | BP27: 44197 | BQ27: =100*('ONS - Table 1'!ET294/AVERAGE('ONS - Table 1'!$ET$270:$ET$281)) -> 68.4 | BR27: =100*('ONS - Table 2'!ET294/AVERAGE('ONS - Table 2'!$ET$270:$ET$281)) -> 71.267021 | BS27: 100 | BU27: 44197 | BV27: =100*('ONS - Table 1'!J294/AVERAGE('ONS - Table 1'!$J$270:$J$281)) -> 105.38244 | BW27: =100*('ONS - Table 2'!J294/AVERAGE('ONS - Table 2'!$J$270:$J$281)) -> 107.38497 | BX27: 100
BK28: 44228 | BL28: =100*('ONS - Table 1'!CK295/AVERAGE('ONS - Table 1'!$CK$270:$CK$281)) -> 87.707309 | BM28: =100*('ONS - Table 2'!CK295/AVERAGE('ONS - Table 2'!$CK$270:$CK$281)) -> 85.250464 | BN28: 100 | BP28: 44228 | BQ28: =100*('ONS - Table 1'!ET295/AVERAGE('ONS - Table 1'!$ET$270:$ET$281)) -> 70.8 | BR28: =100*('ONS - Table 2'!ET295/AVERAGE('ONS - Table 2'!$ET$270:$ET$281)) -> 74.498038 | BS28: 100 | BU28: 44228 | BV28: =100*('ONS - Table 1'!J295/AVERAGE('ONS - Table 1'!$J$270:$J$281)) -> 105.48242 | BW28: =100*('ONS - Table 2'!J295/AVERAGE('ONS - Table 2'!$J$270:$J$281)) -> 108.17095 | BX28: 100
BK29: 44256 | BL29: =100*('ONS - Table 1'!CK296/AVERAGE('ONS - Table 1'!$CK$270:$CK$281)) -> 92.407701 | BM29: =100*('ONS - Table 2'!CK296/AVERAGE('ONS - Table 2'!$CK$270:$CK$281)) -> 89.703154 | BN29: 100 | BP29: 44256 | BQ29: =100*('ONS - Table 1'!ET296/AVERAGE('ONS - Table 1'!$ET$270:$ET$281)) -> 77.8 | BR29: =100*('ONS - Table 2'!ET296/AVERAGE('ONS - Table 2'!$ET$270:$ET$281)) -> 81.790907 | BS29: 100 | BU29: 44256 | BV29: =100*('ONS - Table 1'!J296/AVERAGE('ONS - Table 1'!$J$270:$J$281)) -> 105.48242 | BW29: =100*('ONS - Table 2'!J296/AVERAGE('ONS - Table 2'!$J$270:$J$281)) -> 108.85869 | BX29: 100
BK30: 44287 | BL30: =100*('ONS - Table 1'!CK297/AVERAGE('ONS - Table 1'!$CK$270:$CK$281)) -> 101.20843 | BM30: =100*('ONS - Table 2'!CK297/AVERAGE('ONS - Table 2'!$CK$270:$CK$281)) -> 97.680891 | BN30: 100 | BP30: 44287 | BQ30: =100*('ONS - Table 1'!ET297/AVERAGE('ONS - Table 1'!$ET$270:$ET$281)) -> 85.1 | BR30: =100*('ONS - Table 2'!ET297/AVERAGE('ONS - Table 2'!$ET$270:$ET$281)) -> 86.683591 | BS30: 100 | BU30: 44287 | BV30: =100*('ONS - Table 1'!J297/AVERAGE('ONS - Table 1'!$J$270:$J$281)) -> 105.08249 | BW30: =100*('ONS - Table 2'!J297/AVERAGE('ONS - Table 2'!$J$270:$J$281)) -> 108.95693 | BX30: 100
... BK50: 44896 | BL50: =100*('ONS - Table 1'!CK317/AVERAGE('ONS - Table 1'!$CK$270:$CK$281)) -> 93.207767 | BM50: =100*('ONS - Table 2'!CK317/AVERAGE('ONS - Table 2'!$CK$270:$CK$281)) -> 90.352505 | BN50: 100 | BP50: 44896 | BQ50: =100*('ONS - Table 1'!ET317/AVERAGE('ONS - Table 1'!$ET$270:$ET$281)) -> 101.3 | BR50: =100*('ONS - Table 2'!ET317/AVERAGE('ONS - Table 2'!$ET$270:$ET$281)) -> 90.468498 | BS50: 100 | BU50: 44896 | BV50: =100*('ONS - Table 1'!J317/AVERAGE('ONS - Table 1'!$J$270:$J$281)) -> 99.983336 | BW50: =100*('ONS - Table 2'!J317/AVERAGE('ONS - Table 2'!$J$270:$J$281)) -> 97.560177 | BX50: 100
BU52: 2019 | BV52: =AVERAGE(BV3:BV14) -> 100 | BW52: =AVERAGE(BW3:BW14) -> 100
BU53: 2020 | BV53: =AVERAGE(BV15:BV26) -> 102.22463 | BW53: =AVERAGE(BW15:BW26) -> 102.21877
BU54: 2021 | BV54: =AVERAGE(BV27:BV38) -> 103.84103 | BW54: =AVERAGE(BW27:BW38) -> 106.09137
BU55: 2022 | BV55: =AVERAGE(BV39:BV50) -> 100.4166 | BW55: =AVERAGE(BW39:BW50) -> 98.2561
BU57: 2020 | BV57: =100*((BV53/BV52)-1) -> 2.2246292 | BW57: =100*((BW53/BW52)-1) -> 2.2187654
BU58: 2021 | BV58: =100*((BV54/BV53)-1) -> 1.581221 | BW58: =100*((BW54/BW53)-1) -> 3.7885463
BU59: 2022 | BV59: =100*((BV55/BV54)-1) -> -3.2977614 | BW59: =100*((BW55/BW54)-1) -> -7.385399

Sheet HAVERD
C1: US | D1: Japan | E1: Eurozone | F1: UK | G1: Argentina | H1: Australia | I1: Austria | J1: Belgium | K1: Brazil | L1: Bulgaria | M1: Canada | N1: Chile | O1: China | P1: Croatia | Q1: Czechia | R1: Denmark | S1: Finland | T1: France | U1: Germany | V1: Greece | W1: Hong Kong | X1: Hungary | Y1: India | Z1: Indonesia | AA1: Ireland | AB1: Italy | AC1: Kenya | AD1: Malaysia | AE1: Mexico | AF1: Netherlands | AG1: New Zealand | AH1: Nigeria | AI1: Norway | AJ1: Philippines | AK1: Poland | AL1: Portugal | AM1: Romania | AN1: Russia | AO1: Singapore | AP1: Slovakia | AQ1: South Africa | AR1: Korea | AS1: Spain | AT1: Sweden | AU1: Taiwan | AV1: Tanzania | AW1: Thailand | AX1: Turkey | AY1: Venezuela | AZ1: Global
B2: 20240101 !D | C2: S111SP5@INTDAILY | D2: S158TPX@INTDAILY | E2: S0235Z@INTDAILY | F2: S112FTA@INTDAILY | G2: SPGENN@DAILY | H2: S193SNP@INTDAILY | I2: S122TRI@INTDAILY | J2: S124B20@INTDAILY | K2: S223BOV@INTDAILY | L2: S918SOF@INTDAILY | M2: S156TOI@INTDAILY | N2: SPIGP@DAILY | O2: S924S@INTDAILY | P2: S960ZCX@INTDAILY | Q2: S935P50@INTDAILY | R2: S128KFX@INTDAILY | S2: S172HEX@INTDAILY | T2: S132CAC@INTDAILY | U2: S134DAP@INTDAILY | V2: S174ASE@INTDAILY | W2: S532HNG@INTDAILY | X2: SPBUX@DAILY | Y2: S534SX@INTDAILY | Z2: S536JKC@INTDAILY | AA2: SPISE@DAILY | AB2: S136MBI@INTDAILY | AC2: S664NS@INTDAILY | AD2: S548KLS@INTDAILY | AE2: S273IPC@INTDAILY | AF2: S138CBS@INTDAILY | AG2: S196K5P@INTDAILY | AH2: S694SEA@INTDAILY | AI2: S142OSE@INTDAILY | AJ2: S566MNC@INTDAILY | AK2: S964WIG@INTDAILY | AL2: S182PSI@INTDAILY | AM2: S968BET@INTDAILY | AN2: S922MXC@INTDAILY | AO2: S576STT@INTDAILY | AP2: S936SAX@INTDAILY | AQ2: S199FJA@INTDAILY | AR2: S542CEX@INTDAILY | AS2: S184MGI@INTDAILY | AT2: S144AFF@INTDAILY | AU2: S528TWN@INTDAILY | AV2: S738DSI@INTDAILY | AW2: S578BST@INTDAILY | AX2: S186IMK@INTDAILY | AY2: SPVEN@DAILY | AZ2: S001DJW@INTDAILY
B3: .DESC | C3: Standard & Poor's 500 Stock Price Index (1941-43=10) | D3: Japan: Tokyo Stock Price Index: Topix Cash Index (Jan-04-68=100) | E3: Euro area: EURO STOXX 50 Price Index: Based in Euro (EOP, Dec-31-91=1000) | F3: UK: Stock Price Index: London Financial Times All Share (Apr-10-62=100) | G3: Stock Price Index: Argentina: Buenos Aires General (Jun-30-00=19570.98) | H3: Australia: Share Price Index: S&P/ASX 200(Dec-31-79=500) | I3: Austria: Stock Price Index: Traded Index (Jan-2-91=1000) | J3: Belgium: Stock Price Index: Bel-20 Index (Jan-1-91=1000) | K3: Brazil: Equity Index: IBovespa [Total Return] (Jan-2-68=0.0000000001) | L3: Bulgaria: Stock Price Index: SOFIX (Oct-20-00=100) | M3: S&P/TSX Composite Index, Close Price (Index) | N3: Stock Price Index: Chile: IGPA General (Dec-31-80=100) | O3: China: Shanghai Stock Price SSE Index (Dec-19-90=100) | P3: Croatia: Stock Price Index: CROBEX (Jul-1-97=1000) | Q3: Czechia: Stock Price Index: PX50 (Apr-4-94=1000) | R3: Denmark: Stock Price Index: OMX Copenhagen C20 (Jul-3-89=100) | S3: Finland: Stock Price Index: OMX Helsinki General (Dec-28-90=100) | T3: France: Stock Price Index: Paris CAC 40 (Dec-31-87=1000) | U3: Germany: Stock Market Indexes: DAX Price Index (Dec-30-87=1000) | V3: Greece: Stock Price Index: Athens, SE (Dec-31-80=100) | W3: Hong Kong: Stock Price Index: Hang Seng (Jul-31-64=100) | X3: Stock Price Index: Hungary: BUX (Jan-2-91=1000) | Y3: India: Stock Price Index: BSE: Sensitive [Sensex] (1978-79=100) | Z3: Indonesia: Stock Price Index: Jakarta Composite (Aug-10-82=100) | AA3: Stock Price Index: Ireland: ISEQ Overall (Jan-4-88=1000) | AB3: Italy: Stock Price Index: FTSE MIB (Dec-31-97=24401.54) | AC3: Kenya: NSE 20-Share Index (1966=100) | AD3: Malaysia: Stock Price Index: FTSE Bursa Malaysia KLCI (Jan-1-77=100) | AE3: Mexico: Stock Price Index: IPC (Nov-78=0.78) | AF3: Netherlands: Stock Price Index: Amsterdam ANP-CBS General (Dec-31-52=13.20) | AG3: New Zealand: Stock Price Index: NZX 50 Price Index (Mar-03-03=1880.85) | AH3: Nigeria: Stock Price Index: All Share Index (Jan-3-84=100) | AI3: Norway: Stock Price Index: Oslo OSE All Share Index (Dec-29-95=100) | AJ3: Philippines: Stock Price Index: Manila Composite (Jan-2-85=100) | AK3: Poland: Stock Price Index: WIG (Apr-16-91=1000) | AL3: Portugal: Stock Price Index: PSI-20 (Dec-31-92=3000) | AM3: Romania: Stock Price Index: BET (Sep-19-97=1000) | AN3: Russia: MOEX Russia Index: Closing Value (Sep-22-97=100) | AO3: Singapore: Stock Price Index: Straits Times (Jan-09-08=3344.53) | AP3: Slovakia: Stock Price Index: SAX (Sep-14-93=100) | AQ3: South Africa: Stock Price Index: FTSE/JSE All Share Index (Jun-21-02=10815.08) | AR3: Korea: Stock Price Index: KOSPI (Jan-4-80=100) | AS3: Spain: Stock Price Index: Madrid General Index (Dec-30-85=100) | AT3: Sweden: Stock Price Index: Stockholm Affarsvarlden (Dec-29-95=100) | AU3: Taiwan Stock Exchange Capitalization Weighted Index (1966=100) | AV3: Tanzania: All Shares Index (Dec-15-06=1000) | AW3: Thailand: Stock Price Index: Bangkok SET (Apr-30-75=100) | AX3: Turkey: BIST 100 Stock Price Index (Jan-01-86=.01) | AY3: Venezuela: Stock Price Index: Bursatil Index (Dec-31-93=0.000000001) | AZ3: Dow Jones Global Index: World (Avg, Dec-31-91=100)
B4: .T1 | C4: 02-Jan-1953 | D4: 04-Jan-1989 | E4: 31-Dec-1986 | F4: 01-Jan-1990 | G4: 02-Jan-1991 | H4: 17-Oct-2001 | I4: 07-Jan-1986 | J4: 08-Apr-1991 | K4: 03-Jan-1994 | L4: 23-Oct-2000 | M4: 03-Jan-1977 | N4: 02-Jan-1990 | O4: 20-Dec-1990 | P4: 02-Sep-1997 | Q4: 07-Sep-1993 | R4: 04-Dec-1989 | S4: 02-Jan-1995 | T4: 31-Dec-1987 | U4: 04-Jan-1999 | V4: 02-Jan-1995 | W4: 24-Nov-1969 | X4: 02-Jan-1991 | Y4: 03-Apr-1979 | Z4: 02-Jan-1995 | AA4: 03-Jan-1995 | AB4: 31-Dec-1997 | AC4: 13-Feb-2008 | AD4: 03-Jan-1995 | AE4: 30-Oct-1978 | AF4: 03-Oct-1988 | AG4: 03-Jan-2003 | AH4: 04-Sep-1997 | AI4: 29-Dec-1995 | AJ4: 02-Jan-1996 | AK4: 16-Apr-1991 | AL4: 31-Dec-1992 | AM4: 19-Sep-1997 | AN4: 22-Sep-1997 | AO4: 02-Jan-1975 | AP4: 04-Sep-1997 | AQ4: 21-Jun-2002 | AR4: 06-Jan-1975 | AS4: 02-Jan-1985 | AT4: 02-Jan-1987 | AU4: 05-Jan-1994 | AV4: 16-May-2013 | AW4: 03-Jan-1995 | AX4: 07-Feb-1986 | AY4: 12-Jun-2017 | AZ4: 31-Dec-1991
B5: .TN | C5: 08-Aug-2024 | D5: 08-Aug-2024 | E5: 08-Aug-2024 | F5: 08-Aug-2024 | G5: 08-Aug-2024 | H5: 08-Aug-2024 | I5: 08-Aug-2024 | J5: 08-Aug-2024 | K5: 08-Aug-2024 | L5: 08-Aug-2024 | M5: 08-Aug-2024 | N5: 08-Aug-2024 | O5: 08-Aug-2024 | P5: 08-Aug-2024 | Q5: 08-Aug-2024 | R5: 08-Aug-2024 | S5: 08-Aug-2024 | T5: 08-Aug-2024 | U5: 08-Aug-2024 | V5: 08-Aug-2024 | W5: 08-Aug-2024 | X5: 08-Aug-2024 | Y5: 08-Aug-2024 | Z5: 08-Aug-2024 | AA5: 08-Aug-2024 | AB5: 08-Aug-2024 | AC5: 08-Aug-2024 | AD5: 08-Aug-2024 | AE5: 08-Aug-2024 | AF5: 08-Aug-2024 | AG5: 08-Aug-2024 | AH5: 08-Aug-2024 | AI5: 08-Aug-2024 | AJ5: 08-Aug-2024 | AK5: 08-Aug-2024 | AL5: 08-Aug-2024 | AM5: 08-Aug-2024 | AN5: 08-Aug-2024 | AO5: 08-Aug-2024 | AP5: 08-Aug-2024 | AQ5: 08-Aug-2024 | AR5: 08-Aug-2024 | AS5: 08-Aug-2024 | AT5: 08-Aug-2024 | AU5: 08-Aug-2024 | AV5: 07-Aug-2024 | AW5: 08-Aug-2024 | AX5: 08-Aug-2024 | AY5: 08-Aug-2024 | AZ5: 08-Aug-2024
B6: .LSOURCE | C6: Standard & Poor's | D6: Financial Times | E6: STOXX Limited | F6: Financial Times | G6: Financial Times | H6: Standard & Poor's | I6: Wall Street Journal | J6: Financial Times | K6: Financial Times | L6: Bulgarian Stock Exchange | M6: Toronto Stock Exchange | N6: Financial Times | O6: Shanghai Stock Exchange | P6: Zagreb Stock Exchange | Q6: Financial Times | R6: OMX Nordic Exchange | S6: OMX Nordic Exchange | T6: Financial Times | U6: Deutsche Bourse | V6: Financial Times | W6: Hang Seng Indexes Company | X6: Financial Times | Y6: Bombay Stock Exchange | Z6: Financial Times | AA6: Wall Street Journal | AB6: Borsa Italiana | AC6: Nairobi Stock Exchange | AD6: Financial Times | AE6: Wall Street Journal | AF6: Financial Times | AG6: Standard & Poor's | AH6: Financial Times | AI6: Oslo Bors ASA | AJ6: Financial Times | AK6: Warsaw Stock Exchange | AL6: Financial Times | AM6: Bucharest Stock Exchange | AN6: Moscow Exchange | AO6: Financial Times | AP6: Financial Times | AQ6: Financial Times | AR6: Korea Stock Exchange | AS6: Bolsa de Madrid | AT6: OMX Nordic Exchange | AU6: Taiwan Stock Exchange | AV6: Dar Es Salaam Stock Exchange | AW6: Financial Times | AX6: Central Bank of the Republic of Turkey | AY6: Wall Street Journal | AZ6: Dow Jones
B7: .DTLM | C7: Aug-08-2024 21:40 | D7: Aug-08-2024 09:04 | E7: Aug-08-2024 18:52 | F7: Aug-08-2024 17:06 | G7: Aug-08-2024 23:08 | H7: Aug-08-2024 09:46 | I7: Aug-08-2024 17:10 | J7: Aug-08-2024 17:10 | K7: Aug-08-2024 22:46 | L7: Aug-08-2024 15:23 | M7: Aug-09-2024 02:22 | N7: Aug-08-2024 23:08 | O7: Aug-08-2024 11:21 | P7: Aug-08-2024 16:01 | Q7: Aug-08-2024 16:17 | R7: Aug-08-2024 16:54 | S7: Aug-08-2024 16:54 | T7: Aug-08-2024 17:10 | U7: Aug-08-2024 17:17 | V7: Aug-08-2024 15:35 | W7: Aug-08-2024 11:15 | X7: Aug-08-2024 17:22 | Y7: Aug-08-2024 11:56 | Z7: Aug-08-2024 13:00 | AA7: Aug-08-2024 23:08 | AB7: Aug-08-2024 17:04 | AC7: Aug-08-2024 16:30 | AD7: Aug-08-2024 11:05 | AE7: Aug-08-2024 22:01 | AF7: Aug-08-2024 17:10 | AG7: Aug-08-2024 09:46 | AH7: Aug-08-2024 18:30 | AI7: Aug-08-2024 17:04 | AJ7: Aug-08-2024 11:05 | AK7: Aug-08-2024 17:53 | AL7: Aug-08-2024 17:10 | AM7: Aug-08-2024 16:43 | AN7: Aug-08-2024 17:30 | AO7: Aug-08-2024 11:05 | AP7: Aug-08-2024 16:45 | AQ7: Aug-08-2024 17:30 | AR7: Aug-08-2024 10:11 | AS7: Aug-08-2024 17:04 | AT7: Aug-08-2024 16:54 | AU7: Aug-08-2024 10:05 | AV7: Aug-07-2024 16:01 | AW7: Aug-08-2024 11:05 | AX7: Aug-08-2024 16:31 | AY7: Aug-08-2024 23:08 | AZ7: Aug-09-2024 05:09
A8: 45292 | B8: 20240101 | C8: #N/A | D8: #N/A | E8: #N/A | F8: #N/A | G8: #N/A | H8: #N/A | I8: #N/A | J8: #N/A | K8: #N/A | L8: #N/A | M8: #N/A | N8: #N/A | O8: #N/A | P8: #N/A | Q8: #N/A | R8: #N/A | S8: #N/A | T8: #N/A | U8: #N/A | V8: #N/A | W8: #N/A | X8: #N/A | Y8: 72271.94 | Z8: #N/A | AA8: #N/A | AB8: #N/A | AC8: #N/A | AD8: #N/A | AE8: #N/A | AF8: #N/A | AG8: #N/A | AH8: #N/A | AI8: #N/A | AJ8: #N/A | AK8: #N/A | AL8: #N/A | AM8: #N/A | AN8: #N/A | AO8: #N/A | AP8: #N/A | AQ8: #N/A | AR8: #N/A | AS8: #N/A | AT8: #N/A | AU8: #N/A | AV8: #N/A | AW8: #N/A | AX8: #N/A | AY8: #N/A | AZ8: 550.64
A9: =+A8+1 -> 45293 | B9: 20240102 | C9: 4742.83 | D9: #N/A | E9: 4512.81 | F9: 4220.9 | G9: 40172120 | H9: 7627.79 | I9: 3412.02 | J9: 3718.22 | K9: 132696.63 | L9: 768.87 | M9: 20872.14 | N9: 31520.9 | O9: 2962.28 | P9: 2518.65 | Q9: 1422.34 | R9: 2283.27 | S9: 10167.09 | T9: 7530.86 | U9: 6635.86 | V9: 1307.63 | W9: 16788.55 | X9: 60744.59 | Y9: 71892.48 | Z9: 7323.59 | AA9: 8739.47 | AB9: 30524.63 | AC9: 1508.83 | AD9: 1453.1 | AE9: 56980.44 | AF9: 1065.91 | AG9: #N/A | AH9: 75990.88 | AI9: 1522.15 | AJ9: 6554.04 | AK9: 77451.31 | AL9: 6454.32 | AM9: #N/A | AN9: #N/A | AO9: 3229.95 | AP9: 313.3 | AQ9: 75709.14 | AR9: 2669.81 | AS9: 1005.63 | AT9: 900.25 | AU9: 17853.76 | AV9: 1764.12 | AW9: 1433.38 | AX9: 7624.29 | AY9: 58288.82 | AZ9: 546.53
A10: =+A9+1 -> 45294 | B10: 20240103 | C10: 4704.81 | D10: #N/A | E10: 4448.13 | F10: 4196.69 | G10: 41931359 | H10: 7523.2 | I10: 3377.58 | J10: 3685.15 | K10: 132833.95 | L10: 757.78 | M10: 20818.58 | N10: 31166.36 | O10: 2967.25 | P10: 2520.22 | Q10: 1419.08 | R10: 2286.98 | S10: 10051.55 | T10: 7411.86 | U10: 6544.46 | V10: 1301.34 | W10: 16646.41 | X10: 60685.11 | Y10: 71356.6 | Z10: 7279.09 | AA10: 8646.28 | AB10: 30100.84 | AC10: 1509.36 | AD10: 1462.37 | AE10: 55726.64 | AF10: 1057.38 | AG10: 4509.08 | AH10: 77537.57 | AI10: 1524.2 | AJ10: 6498.88 | AK10: 77053.98 | AL10: 6410.86 | AM10: 15231.29 | AN10: 3130.23 | AO10: 3199.44 | AP10: 313.3 | AQ10: 74510.72 | AR10: 2607.31 | AS10: 993.71 | AT10: 884.03 | AU10: 17559.31 | AV10: 1763.21 | AW10: 1429.62 | AX10: 7412.04 | AY10: 58059.49 | AZ10: 540.84
A11: =+A10+1 -> 45295 | B11: 20240104 | C11: 4688.68 | D11: 2378.79 | E11: 4474.01 | F11: 4217.03 | G11: 43270494 | H11: 7494.1 | I11: 3420.17 | J11: 3721.89 | K11: 131225.91 | L11: 764.52 | M11: 20871.35 | N11: 30851.54 | O11: 2954.35 | P11: 2529.84 | Q11: 1438.01 | R11: 2352.29 | S11: 10212.55 | T11: 7450.63 | U11: 6575.68 | V11: 1310.87 | W11: 16645.98 | X11: 60838.3 | Y11: 71847.57 | Z11: 7359.76 | AA11: 8666.29 | AB11: 30403.96 | AC11: 1512.22 | AD11: 1477.26 | AE11: 55406.96 | AF11: 1059.06 | AG11: 4520.23 | AH11: 78020.54 | AI11: 1543.44 | AJ11: 6602.52 | AK11: 76827.85 | AL11: 6486.34 | AM11: 15355.08 | AN11: 3136.07 | AO11: 3174.01 | AP11: 313.3 | AQ11: 74522.49 | AR11: 2587.02 | AS11: 1007.01 | AT11: 886.93 | AU11: 17549.65 | AV11: 1766.98 | AW11: 1434.59 | AX11: 7547.84 | AY11: 57525.8 | AZ11: 540.72
A12: =+A11+1 -> 45296 | B12: 20240105 | C12: 4697.24 | D12: 2393.54 | E12: 4463.51 | F12: 4196.35 | G12: 45258658 | H12: 7489.07 | I12: 3430.08 | J12: 3717.81 | K12: 132022.92 | L12: 766.84 | M12: 20937.55 | N12: 30715.23 | O12: 2929.18 | P12: 2554.52 | Q12: 1438.49 | R12: 2348.56 | S12: 10271.21 | T12: 7420.69 | U12: 6566.55 | V12: 1311.67 | W12: 16535.33 | X12: 61454.62 | Y12: 72026.15 | Z12: 7350.62 | AA12: 8661.46 | AB12: 30440.95 | AC12: 1518.4 | AD12: 1487.61 | AE12: 56192.78 | AF12: 1055.49 | AG12: 4515.94 | AH12: 79664.66 | AI12: 1538.67 | AJ12: 6629.64 | AK12: 76593.76 | AL12: 6533.68 | AM12: 15338.36 | AN12: 3136.37 | AO12: 3184.3 | AP12: 313.3 | AQ12: 74488.2 | AR12: 2578.08 | AS12: 1006.03 | AT12: 877.02 | AU12: 17519.14 | AV12: 1770.55 | AW12: 1427.96 | AX12: 7628.73 | AY12: 57164.41 | AZ12: 541.68
A13: =+A8+7 -> 45299 | B13: 20240108 | C13: 4763.54 | D13: #N/A | E13: 4485.48 | F13: 4204.14 | G13: 47476179 | H13: 7451.55 | I13: 3425.55 | J13: 3736.42 | K13: 132426.54 | L13: 758.55 | M13: 21074.91 | N13: 30775.14 | O13: 2887.54 | P13: 2579.35 | Q13: 1446.96 | R13: 2337.17 | S13: 10267.61 | T13: 7450.24 | U13: 6614.93 | V13: 1330.61 | W13: 16224.45 | X13: 61374.1 | Y13: 71355.22 | Z13: 7283.58 | AA13: 8723.22 | AB13: 30569.92 | AC13: 1520.82 | AD13: 1495.7 | AE13: 56175.67 | AF13: 1057.16 | AG13: 4510.77 | AH13: 80328.58 | AI13: 1515.99 | AJ13: 6609.22 | AK13: 76876.5 | AL13: 6478.25 | AM13: 15468.65 | AN13: 3158.58 | AO13: 3187.02 | AP13: 313.3 | AQ13: 74103.23 | AR13: 2567.82 | AS13: 1010.1 | AT13: 885.9 | AU13: 17572.66 | AV13: 1767.52 | AW13: 1418.45 | AX13: 7818.89 | AY13: 56755.28 | AZ13: 546.32
A14: =+A9+7 -> 45300 | B14: 20240109 | C14: 4756.5 | D14: 2413.09 | E14: 4467.17 | F14: 4196.15 | G14: 45906597 | H14: 7520.52 | I14: 3426.39 | J14: 3721.87 | K14: 131446.59 | L14: 767.21 | M14: 20970.98 | N14: 30992.77 | O14: 2893.25 | P14: 2611.82 | Q14: 1448.28 | R14: 2348.89 | S14: 10227.43 | T14: 7426.62 | U14: 6603.81 | V14: 1341.1 | W14: 16190.02 | X14: 61921.62 | Y14: 71386.21 | Z14: 7200.2 | AA14: 8633.17 | AB14: 30408.78 | AC14: 1504.36 | AD14: 1498.83 | AE14: 55105.58 | AF14: 1055.52 | AG14: 4552.65 | AH14: 83191.84 | AI14: 1516.21 | AJ14: 6618.52 | AK14: 77268.35 | AL14: 6461.02 | AM14: 15610.27 | AN14: 3155.55 | AO14: 3197.96 | AP14: 315.64 | AQ14: 73826.15 | AR14: 2561.24 | AS14: 994.81 | AT14: 881.95 | AU14: 17535.49 | AV14: 1761.51 | AW14: 1414.93 | AX14: 7736.26 | AY14: 56041.38 | AZ14: 545.08
A15: =+A10+7 -> 45301 | B15: 20240110 | C15: 4783.45 | D15: 2444.48 | E15: 4468.98 | F15: 4180.83 | G15: 46412763 | H15: 7468.46 | I15: 3421.4 | J15: 3705.22 | K15: 130841.09 | L15: 763.63 | M15: 20989.42 | N15: 30748.01 | O15: 2877.7 | P15: 2591.42 | Q15: 1451.34 | R15: 2375.21 | S15: 10202.43 | T15: 7426.08 | U15: 6604.38 | V15: 1344.51 | W15: 16097.28 | X15: 62804.52 | Y15: 71657.71 | Z15: 7227.3 | AA15: 8470.87 | AB15: 30450.78 | AC15: #N/A | AD15: 1486.86 | AE15: 55318.67 | AF15: 1051.82 | AG15: 4523.83 | AH15: 82024.38 | AI15: 1508.14 | AJ15: 6546.11 | AK15: 76840.58 | AL15: 6602.22 | AM15: 15682.37 | AN15: 3164.7 | AO15: 3179.96 | AP15: 315.64 | AQ15: 73586.98 | AR15: 2541.98 | AS15: 994.57 | AT15: 880.86 | AU15: 17465.63 | AV15: 1761.37 | AW15: 1413.52 | AX15: 7874.16 | AY15: 56142.25 | AZ15: 546.95
A16: =+A11+7 -> 45302 | B16: 20240111 | C16: 4780.24 | D16: 2482.87 | E16: 4442.28 | F16: 4140.73 | G16: 45604542 | H16: 7506.03 | I16: 3398.23 | J16: 3659.44 | K16: 130648.75 | L16: 769.78 | M16: 20918.4 | N16: 30607.91 | O16: 2886.65 | P16: 2599.86 | Q16: 1456.26 | R16: 2358.31 | S16: 10132.04 | T16: 7387.62 | U16: 6547.88 | V16: 1347.9 | W16: 16302.04 | X16: 63066.57 | Y16: 71721.18 | Z16: 7219.96 | AA16: 8410.45 | AB16: 30249.16 | AC16: 1506.21 | AD16: 1483 | AE16: 55438.75 | AF16: 1051.74 | AG16: 4536.75 | AH16: 82597.08 | AI16: 1499.46 | AJ16: 6613.73 | AK16: 76042.95 | AL16: 6589.57 | AM16: 15732.52 | AN16: 3181.25 | AO16: 3201.41 | AP16: 315.64 | AQ16: 73834.28 | AR16: 2540.27 | AS16: 987.66 | AT16: 876.3 | AU16: 17545.32 | AV16: 1757.26 | AW16: 1408.24 | AX16: 7895.96 | AY16: 55762.9 | AZ16: 546.66
A17: =+A12+7 -> 45303 | B17: 20240112 | C17: 4783.83 | D17: 2494.23 | E17: 4480.02 | F17: 4165.62 | G17: 45248761 | H17: 7498.28 | I17: 3398.61 | J17: 3684.03 | K17: 130987.67 | L17: 777.54 | M17: 20990.22 | N17: 30295.94 | O17: 2881.98 | P17: 2604.99 | Q17: 1457.47 | R17: 2362.85 | S17: 10212.54 | T17: 7465.14 | U17: 6610.22 | V17: 1352.65 | W17: 16244.58 | X17: 63628.13 | Y17: 72568.45 | Z17: 7241.14 | AA17: 8417.55 | AB17: 30470.55 | AC17: 1514.07 | AD17: 1487.34 | AE17: 55607.07 | AF17: 1060.7 | AG17: 4558 | AH17: 83042.96 | AI17: 1513.32 | AJ17: 6643.18 | AK17: 76106.23 | AL17: 6537.66 | AM17: 15776.45 | AN17: 3185.22 | AO17: 3191.72 | AP17: 315.64 | AQ17: 74240.76 | AR17: 2525.05 | AS17: 995.53 | AT17: 886.52 | AU17: 17512.83 | AV17: #N/A | AW17: 1413.53 | AX17: 7986.47 | AY17: 55899.57 | AZ17: 548.37
A18: =+A13+7 -> 45306 | B18: 20240115 | C18: #N/A | D18: 2524.6 | E18: 4454.68 | F18: 4152.21 | G18: 45737816 | H18: 7496.27 | I18: 3410.35 | J18: 3667.32 | K18: 131520.91 | L18: 772.96 | M18: 21061.88 | N18: 30439.98 | O18: 2886.29 | P18: 2615.12 | Q18: 1457.28 | R18: 2355.23 | S18: 10180.52 | T18: 7411.68 | U18: 6577.63 | V18: 1353.46 | W18: 16216.33 | X18: 63787.07 | Y18: 73327.94 | Z18: 7224 | AA18: 8492.4 | AB18: 30327.72 | AC18: 1515.21 | AD18: 1501.11 | AE18: 55501.11 | AF18: 1057.83 | AG18: 4525.17 | AH18: 84640.89 | AI18: 1496.92 | AJ18: 6680.45 | AK18: 75127.54 | AL18: 6503.1 | AM18: 15803.32 | AN18: 3184.88 | AO18: 3199.42 | AP18: 315.64 | AQ18: 73675.74 | AR18: 2525.99 | AS18: 993.62 | AT18: 876.9 | AU18: 17546.82 | AV18: #N/A | AW18: 1407.02 | AX18: 8044.02 | AY18: 56602.8 | AZ18: 547.85
A19: =+A14+7 -> 45307 | B19: 20240116 | C19: 4765.98 | D19: 2503.98 | E19: 4446.51 | F19: 4134.31 | G19: 46306380 | H19: 7414.79 | I19: 3383.83 | J19: 3630.3 | K19: 129294.04 | L19: 774.57 | M19: 20948.09 | N19: 30335.98 | O19: 2893.99 | P19: 2627.23 | Q19: 1445.83 | R19: 2360.47 | S19: 10134.43 | T19: 7398 | U19: 6557.64 | V19: 1332.47 | W19: 15865.92 | X19: 63292.9 | Y19: 73128.77 | Z19: 7242.79 | AA19: 8491.37 | AB19: 30337.62 | AC19: 1512.64 | AD19: 1493.87 | AE19: 55124.58 | AF19: 1055.88 | AG19: 4524.35 | AH19: 87971.1 | AI19: 1496.69 | AJ19: 6637 | AK19: 74950.09 | AL19: 6415.15 | AM19: 15780.71 | AN19: 3179.45 | AO19: 3184.99 | AP19: 315.64 | AQ19: 73007.62 | AR19: 2497.59 | AS19: 985.44 | AT19: 871.91 | AU19: 17346.87 | AV19: 1749.09 | AW19: 1401.72 | AX19: 8032.17 | AY19: 56758.28 | AZ19: 543.78
A20: =+A15+7 -> 45308 | B20: 20240117 | C20: 4739.21 | D20: 2496.38 | E20: 4403.08 | F20: 4072.19 | G20: 48820459 | H20: 7393.08 | I20: 3327.04 | J20: 3568.52 | K20: 128523.83 | L20: 773.78 | M20: 20695.02 | N20: 30011.49 | O20: 2833.62 | P20: 2632.25 | Q20: 1434.89 | R20: 2349.17 | S20: 9969.73 | T20: 7318.69 | U20: 6502.24 | V20: 1331.34 | W20: 15276.9 | X20: 63019.94 | Y20: 71500.76 | Z20: 7200.64 | AA20: 8469.85 | AB20: 30098.86 | AC20: 1503.34 | AD20: 1491.21 | AE20: 54711.69 | AF20: 1045.41 | AG20: 4522.92 | AH20: 90063.25 | AI20: 1481.14 | AJ20: 6572.51 | AK20: 73582.3 | AL20: 6322.8 | AM20: 15563.64 | AN20: 3185.23 | AO20: 3142.22 | AP20: 315.64 | AQ20: 71693.09 | AR20: 2435.9 | AS20: 973.77 | AT20: 861.13 | AU20: 17161.79 | AV20: 1741.21 | AW20: 1380.65 | AX20: 8024.37 | AY20: 56790.57 | AZ20: 538.34
A21: =+A16+7 -> 45309 | B21: 20240118 | C21: 4780.94 | D21: 2492.09 | E21: 4453.05 | F21: 4080.28 | G21: 49339682 | H21: 7346.48 | I21: 3343.28 | J21: 3552.84 | K21: 127315.74 | L21: 777.23 | M21: 20756.73 | N21: 29846.54 | O21: 2845.78 | P21: 2606.23 | Q21: 1432.36 | R21: 2347.21 | S21: 9952.82 | T21: 7401.35 | U21: 6555.92 | V21: 1341.1 | W21: 15391.79 | X21: 63571.82 | Y21: 71186.86 | Z21: 7252.97 | AA21: 8796.6 | AB21: 30350.53 | AC21: 1512.56 | AD21: 1479.18 | AE21: 54707.89 | AF21: 1056.15 | AG21: 4492.22 | AH21: 91896.97 | AI21: 1483.3 | AJ21: 6510.87 | AK21: 74367.89 | AL21: 6322.62 | AM21: 15555.4 | AN21: 3178.85 | AO21: 3139.78 | AP21: 315.64 | AQ21: 72344.4 | AR21: 2440.04 | AS21: 974.71 | AT21: 865.47 | AU21: 17227.79 | AV21: 1746.27 | AW21: 1377.93 | AX21: 8016.09 | AY21: 56618.17 | AZ21: 541.84
A22: =+A17+7 -> 45310 | B22: 20240119 | C22: 4839.81 | D22: 2510.03 | E22: 4448.83 | F22: 4079.87 | G22: 50946298 | H22: 7421.24 | I22: 3344.38 | J22: 3556.71 | K22: 127635.65 | L22: 782.93 | M22: 20906.52 | N22: 29729.7 | O22: 2832.28 | P22: 2624.33 | Q22: 1442.17 | R22: 2340.8 | S22: 9843.33 | T22: 7371.64 | U22: 6551.09 | V22: 1340.03 | W22: 15308.69 | X22: 64580.87 | Y22: 71683.23 | Z22: 7227.4 | AA22: 8845.06 | AB22: 30283.61 | AC22: 1516.75 | AD22: 1486.37 | AE22: 55452.1 | AF22: 1057.78 | AG22: 4484.11 | AH22: 94538.12 | AI22: 1484.89 | AJ22: 6503.54 | AK22: 74774.93 | AL22: 6313.51 | AM22: 15617.64 | AN22: 3166.37 | AO22: 3152.29 | AP22: 313.46 | AQ22: 72660.91 | AR22: 2472.74 | AS22: 972.17 | AT22: 859.65 | AU22: 17681.52 | AV22: 1742.92 | AW22: 1382.51 | AX22: 7996.7 | AY22: 57584.23 | AZ22: 547.13
A23: =+A18+7 -> 45313 | B23: 20240122 | C23: 4850.43 | D23: 2544.92 | E23: 4480.32 | F23: 4098.31 | G23: 52818019 | H23: 7476.57 | I23: 3371.06 | J23: 3592.87 | K23: 126601.55 | L23: 781.82 | M23: 20924.3 | N23: 30076.07 | O23: 2756.34 | P23: 2617.34 | Q23: 1441.59 | R23: 2338.62 | S23: 9910.48 | T23: 7413.25 | U23: 6601.83 | V23: 1351.56 | W23: 14961.18 | X23: 64709.34 | Y23: #N/A | Z23: 7247.93 | AA23: 8896.63 | AB23: 30182.32 | AC23: 1510.6 | AD23: 1491.19 | AE23: 54667.61 | AF23: 1068.3 | AG23: 4491.37 | AH23: 95768.12 | AI23: 1483.17 | AJ23: 6583.47 | AK23: 74954.24 | AL23: 6335.69 | AM23: 15492.47 | AN23: 3172.15 | AO23: 3149.12 | AP23: 308.15 | AQ23: 72351.5 | AR23: 2464.35 | AS23: 982.6 | AT23: 869.8 | AU23: 17815.1 | AV23: 1738.51 | AW23: 1369.92 | AX23: 8010.14 | AY23: 57953.2 | AZ23: 549.09
A24: =+A19+7 -> 45314 | B24: 20240123 | C24: 4864.6 | D24: 2542.07 | E24: 4465.91 | F24: 4095.09 | G24: 52168914 | H24: 7514.94 | I24: 3384.41 | J24: 3598.54 | K24: 128262.52 | L24: 778.21 | M24: 21034.59 | N24: 30294.92 | O24: 2770.98 | P24: 2615.69 | Q24: 1437.6 | R24: 2324.45 | S24: 9951.81 | T24: 7388.04 | U24: 6579.56 | V24: 1353.14 | W24: 15353.98 | X24: 63825.73 | Y24: 70370.55 | Z24: 7256.23 | AA24: 8910.56 | AB24: 30077.46 | AC24: 1502.01 | AD24: 1496.11 | AE24: 55520.39 | AF24: 1070.43 | AG24: 4536.7 | AH24: 98616.97 | AI24: 1489.6 | AJ24: 6621.88 | AK24: 74601.92 | AL24: 6268.8 | AM24: 15234.98 | AN24: 3175.74 | AO24: 3135.25 | AP24: 307.62 | AQ24: 73337.19 | AR24: 2478.61 | AS24: 972.57 | AT24: 872.89 | AU24: 17874.59 | AV24: 1734.67 | AW24: 1356.54 | AX24: 7950.06 | AY24: 57979.93 | AZ24: 549.47
A25: =+A20+7 -> 45315 | B25: 20240124 | C25: 4868.55 | D25: 2529.22 | E25: 4564.11 | F25: 4120.13 | G25: 54080945 | H25: 7519.19 | I25: 3431.27 | J25: 3631.05 | K25: 127815.7 | L25: 783.72 | M25: 21025.78 | N25: 30733.38 | O25: 2820.77 | P25: 2626 | Q25: 1446.44 | R25: 2330.94 | S25: 10051.65 | T25: 7455.64 | U25: 6683.57 | V25: 1362.05 | W25: 15899.87 | X25: 64128.4 | Y25: 71060.31 | Z25: 7227.82 | AA25: 8972.71 | AB25: 30338.35 | AC25: 1503.75 | AD25: 1504.1 | AE25: 55396.55 | AF25: 1100.24 | AG25: 4557.35 | AH25: 101571.11 | AI25: 1490.82 | AJ25: 6679.96 | AK25: 75351.32 | AL25: 6327.36 | AM25: #N/A | AN25: 3162.41 | AO25: 3153.33 | AP25: 309.21 | AQ25: 74320.11 | AR25: 2469.69 | AS25: 983.45 | AT25: 879.26 | AU25: 17875.83 | AV25: 1739.08 | AW25: 1381.19 | AX25: 8090.9 | AY25: 57539.41 | AZ25: 552.06
A26: =+A21+7 -> 45316 | B26: 20240125 | C26: 4894.16 | D26: 2531.92 | E26: 4582.26 | F26: 4122.73 | G26: 55614626 | H26: 7555.36 | I26: 3437.99 | J26: 3632.33 | K26: 128168.73 | L26: 782.07 | M26: 21101.54 | N26: 30390.55 | O26: 2906.11 | P26: 2623.58 | Q26: 1450.2 | R26: 2336.23 | S26: 10157.38 | T26: 7464.2 | U26: 6690.29 | V26: 1352.86 | W26: 16211.96 | X26: 64543.96 | Y26: 70700.67 | Z26: 7178.04 | AA26: 9033.04 | AB26: 30157.8 | AC26: 1506.65 | AD26: #N/A | AE26: 56160.07 | AF26: 1112.98 | AG26: 4570.04 | AH26: 102149.93 | AI26: 1491.53 | AJ26: 6673.5 | AK26: 75219.71 | AL26: 6294.55 | AM26: 15138.28 | AN26: 3157.74 | AO26: 3147.64 | AP26: 307.09 | AQ26: 74040.54 | AR26: 2470.34 | AS26: 976.85 | AT26: 883.98 | AU26: 18002.62 | AV26: 1731.38 | AW26: 1376.09 | AX26: 8169.89 | AY26: 56841.48 | AZ26: 553.78
A27: =+A22+7 -> 45317 | B27: 20240126 | C27: 4890.97 | D27: 2497.65 | E27: 4635.47 | F27: 4174.89 | G27: 54270953 | H27: #N/A | I27: 3455.57 | J27: 3672.03 | K27: 128967.32 | L27: 787.72 | M27: 21125.28 | N27: 30734.27 | O27: 2910.22 | P27: 2632.34 | Q27: 1447.36 | R27: 2351.75 | S27: 10241.9 | T27: 7634.14 | U27: 6711.85 | V27: 1360.89 | W27: 15952.23 | X27: 64092.56 | Y27: #N/A | Z27: 7137.09 | AA27: 9066.84 | AB27: 30379.33 | AC27: 1497.97 | AD27: 1506.28 | AE27: 56855.88 | AF27: 1115.25 | AG27: 4564.43 | AH27: 102401.88 | AI27: 1501.4 | AJ27: 6686.09 | AK27: 75683.59 | AL27: 6275.73 | AM27: 15126.22 | AN27: 3163.21 | AO27: 3159.53 | AP27: 308.84 | AQ27: 75084.38 | AR27: 2478.56 | AS27: 978.76 | AT27: 888.02 | AU27: 17995.03 | AV27: 1703.16 | AW27: 1368.15 | AX27: 8346.28 | AY27: 55030.26 | AZ27: 554.16
A28: =+A23+7 -> 45320 | B28: 20240129 | C28: 4927.93 | D28: 2529.48 | E28: 4639.36 | F28: 4172.58 | G28: 54119480 | H28: 7578.44 | I28: 3446.96 | J28: 3655.73 | K28: 128502.66 | L28: 789.8 | M28: 21200.06 | N28: 30739.4 | O28: 2883.36 | P28: 2642.61 | Q28: 1445.44 | R28: 2378.93 | S28: 10239.36 | T28: 7640.81 | U28: 6704.06 | V28: 1350.95 | W28: 16077.24 | X28: 63192.77 | Y28: 71941.57 | Z28: 7157.18 | AA28: 9171.19 | AB28: 30233.61 | AC28: 1487.89 | AD28: 1515.39 | AE28: 57175.73 | AF28: 1118.74 | AG28: 4578.59 | AH28: 104674.67 | AI28: 1496.97 | AJ28: 6630.68 | AK28: 75347.11 | AL28: 6252.96 | AM28: 15141.09 | AN28: 3176.61 | AO28: 3140.31 | AP28: 308.84 | AQ28: 74370.53 | AR28: 2500.65 | AS28: 974.42 | AT28: 888.27 | AU28: 18119.63 | AV28: 1711.64 | AW28: 1376.28 | AX28: 8471.7 | AY28: 54140.02 | AZ28: 557.59
A29: =+A24+7 -> 45321 | B29: 20240130 | C29: 4924.97 | D29: 2526.93 | E29: 4662.7 | F29: 4189.31 | G29: 54713800 | H29: 7600.19 | I29: 3455 | J29: 3643.93 | K29: 127401.81 | L29: 787.71 | M29: 21227.87 | N29: 30289.76 | O29: 2830.53 | P29: 2649.04 | Q29: 1450.49 | R29: 2381.57 | S29: 10204.49 | T29: 7677.47 | U29: 6716.18 | V29: 1355.12 | W29: 15703.45 | X29: 63213.55 | Y29: 71139.9 | Z29: 7192.22 | AA29: 9214.55 | AB29: 30623.27 | AC29: 1499.31 | AD29: 1512.75 | AE29: 57537.14 | AF29: 1119.81 | AG29: 4579.56 | AH29: 103110.15 | AI29: 1491.05 | AJ29: 6622.01 | AK29: 76072.25 | AL29: 6292.61 | AM29: 15376.62 | AN29: 3196.08 | AO29: 3150.04 | AP29: 308.84 | AQ29: 74611.45 | AR29: 2498.81 | AS29: 989.1 | AT29: 888.94 | AU29: 18034.63 | AV29: 1712.23 | AW29: 1373.14 | AX29: 8474.3 | AY29: 54237.16 | AZ29: 556.99
A30: =+A25+7 -> 45322 | B30: 20240131 | C30: 4845.65 | D30: 2551.1 | E30: 4648.4 | F30: 4173.06 | G30: 54505402 | H30: 7680.72 | I30: 3456.48 | J30: 3662.96 | K30: 127752.28 | L30: 786.68 | M30: 21021.88 | N30: 30339.78 | O30: 2788.55 | P30: 2665.94 | Q30: 1452.92 | R30: 2436.89 | S30: 10167.38 | T30: 7656.75 | U30: 6689.05 | V30: 1367.41 | W30: 15485.07 | X30: 64044.46 | Y30: 71752.11 | Z30: 7207.94 | AA30: 9178.12 | AB30: 30744.24 | AC30: 1508.86 | AD30: 1512.98 | AE30: 57372.76 | AF30: 1116.31 | AG30: 4563.3 | AH30: 101154.46 | AI30: 1486.47 | AJ30: 6646.44 | AK30: 77416.31 | AL30: 6322.76 | AM30: 15512.12 | AN30: 3214.19 | AO30: 3153.01 | AP30: 308.31 | AQ30: 74555.87 | AR30: 2497.09 | AS30: 993.64 | AT30: 888.52 | AU30: 17889.56 | AV30: 1723.85 | AW30: 1364.52 | AX30: 8496.66 | AY30: 53529.95 | AZ30: 552.14
A31: =+A26+7 -> 45323 | B31: 20240201 | C31: 4906.19 | D31: 2534.04 | E31: 4638.6 | F31: 4161.89 | G31: 56313535 | H31: 7588.19 | I31: 3450.57 | J31: 3623.3 | K31: 128481.02 | L31: 783.52 | M31: 21119.21 | N31: 30616.2 | O31: 2770.74 | P31: 2670.35 | Q31: 1458.36 | R31: 2461.43 | S31: 10054.82 | T31: 7588.75 | U31: 6671.35 | V31: 1376.62 | W31: 15566.21 | X31: 65320.88 | Y31: 71645.3 | Z31: 7201.7 | AA31: 9121.74 | AB31: 30689.11 | AC31: 1511.89 | AD31: #N/A | AE31: 57828.08 | AF31: 1121.56 | AG31: 4580.48 | AH31: 102802.25 | AI31: 1490.36 | AJ31: 6623.01 | AK31: 78417.88 | AL31: 6285.35 | AM31: 15621.43 | AN31: 3229.89 | AO31: 3143.06 | AP31: 308.31 | AQ31: 74469.95 | AR31: 2542.46 | AS31: 987.97 | AT31: 892.01 | AU31: 17968.11 | AV31: 1727.7 | AW31: 1367.96 | AX31: 8646.12 | AY31: 53253.29 | AZ31: 555.58
A32: =+A27+7 -> 45324 | B32: 20240202 | C32: 4958.61 | D32: 2539.68 | E32: 4654.55 | F32: 4160.19 | G32: 56966933 | H32: 7699.4 | I32: 3440.78 | J32: 3615.28 | K32: 127182.25 | L32: 779.96 | M32: 21085.09 | N32: 30316.96 | O32: 2730.15 | P32: 2671.65 | Q32: 1457.31 | R32: 2450.37 | S32: 10042.83 | T32: 7592.26 | U32: 6694.76 | V32: 1385.01 | W32: 15533.56 | X32: 65290.31 | Y32: 72085.63 | Z32: 7238.79 | AA32: 9111.48 | AB32: 30717.95 | AC32: 1512.56 | AD32: 1516.58 | AE32: 58226.77 | AF32: 1123.31 | AG32: 4586.03 | AH32: 104421.23 | AI32: 1480.71 | AJ32: 6707.25 | AK32: 79575.14 | AL32: 6257.38 | AM32: 15640.73 | AN32: 3226.35 | AO32: 3179.77 | AP32: 308.8 | AQ32: 74381.96 | AR32: 2615.31 | AS32: 994.28 | AT32: 891.37 | AU32: 18059.93 | AV32: 1739.63 | AW32: 1384.08 | AX32: 8665.68 | AY32: 54103.19 | AZ32: 558.76
A33: =+A28+7 -> 45327 | B33: 20240205 | C33: 4942.81 | D33: 2556.71 | E33: 4655.27 | F33: 4154.01 | G33: 54591081 | H33: 7625.85 | I33: 3420.01 | J33: 3625.62 | K33: 127593.49 | L33: 778.98 | M33: 20871.89 | N33: 30367.69 | O33: 2702.19 | P33: 2669.03 | Q33: 1460.46 | R33: 2502.02 | S33: 9909.64 | T33: 7589.96 | U33: 6689.16 | V33: 1395.99 | W33: 15510.01 | X33: 64830.41 | Y33: 71731.42 | Z33: 7198.62 | AA33: 9038.49 | AB33: 30952.79 | AC33: 1522.92 | AD33: 1511.34 | AE33: #N/A | AF33: 1126.01 | AG33: 4585.06 | AH33: 103659.81 | AI33: 1473.25 | AJ33: 6728.22 | AK33: 79002.75 | AL33: 6223.45 | AM33: 15697.3 | AN33: 3226.79 | AO33: 3134.29 | AP33: 307.66 | AQ33: 74033.92 | AR33: 2591.31 | AS33: 982.04 | AT33: 882.38 | AU33: 18096.07 | AV33: 1740.4 | AW33: 1383.93 | AX33: 8776.7 | AY33: 53702.64 | AZ33: 555.94
A34: =+A29+7 -> 45328 | B34: 20240206 | C34: 4954.23 | D34: 2539.25 | E34: 4690.87 | F34: 4190.18 | G34: 52726811 | H34: 7581.58 | I34: 3425.43 | J34: 3620.51 | K34: 130416.31 | L34: 777.84 | M34: 20957.74 | N34: 30374.78 | O34: 2789.49 | P34: 2668.93 | Q34: 1459.37 | R34: 2513.56 | S34: 9956.86 | T34: 7638.97 | U34: 6740.28 | V34: 1403.76 | W34: 16136.87 | X34: 64991.89 | Y34: 72186.09 | Z34: 7247.41 | AA34: 9060.97 | AB34: 31116.75 | AC34: 1522.45 | AD34: 1512.98 | AE34: 58645.42 | AF34: 1136.2 | AG34: #N/A | AH34: 102108.05 | AI34: 1488.66 | AJ34: 6755.26 | AK34: 79150.11 | AL34: 6236.62 | AM34: 15694.24 | AN34: 3238.4 | AO34: 3125.68 | AP34: 312.13 | AQ34: 74558.52 | AR34: 2576.2 | AS34: 987.97 | AT34: 888.97 | AU34: #N/A | AV34: 1746.84 | AW34: 1396.96 | AX34: 8869.14 | AY34: 53543.86 | AZ34: 558.81
A35: =+A30+7 -> 45329 | B35: 20240207 | C35: 4995.06 | D35: 2549.95 | E35: 4678.85 | F35: 4163.67 | G35: 49999015 | H35: 7615.84 | I35: 3378.98 | J35: 3625.95 | K35: 129949.9 | L35: 781.87 | M35: 20969.18 | N35: 30409.79 | O35: 2829.7 | P35: 2680.27 | Q35: 1444.47 | R35: 2539.69 | S35: 9903.55 | T35: 7611.26 | U35: 6696.25 | V35: 1397.14 | W35: 16081.89 | X35: 64345.88 | Y35: 72152 | Z35: 7235.15 | AA35: 9144.64 | AB35: 30976.02 | AC35: 1523.02 | AD35: 1513.11 | AE35: 58711.87 | AF35: 1137.24 | AG35: 4594.08 | AH35: 102106.31 | AI35: 1451.77 | AJ35: 6830.04 | AK35: 79473.35 | AL35: 6182.29 | AM35: 15726.44 | AN35: 3256.58 | AO35: 3156.15 | AP35: 312.13 | AQ35: 74313.44 | AR35: 2609.58 | AS35: 976.56 | AT35: 890.46 | AU35: #N/A | AV35: 1750.36 | AW35: 1400.02 | AX35: 8843.01 | AY35: 52077.81 | AZ35: 562.07
A36: =+A31+7 -> 45330 | B36: 20240208 | C36: 4997.91 | D36: 2562.63 | E36: 4710.78 | F36: 4148.28 | G36: 48487022 | H36: 7639.25 | I36: 3369.02 | J36: 3665.65 | K36: 128216.92 | L36: 781.32 | M36: 20919.64 | N36: 30364.83 | O36: 2865.9 | P36: 2680.12 | Q36: 1462.95 | R36: 2514.03 | S36: 9834.78 | T36: 7665.63 | U36: 6712.82 | V36: 1404.88 | W36: 15878.07 | X36: 64442.63 | Y36: #N/A | Z36: #N/A | AA36: 9290.35 | AB36: 31064.15 | AC36: 1526.48 | AD36: 1512.36 | AE36: 57762.44 | AF36: 1152.04 | AG36: 4563.39 | AH36: 101227.67 | AI36: 1440.55 | AJ36: 6850.16 | AK36: 78711.66 | AL36: 6112.79 | AM36: 15721.62 | AN36: 3241.81 | AO36: 3142.91 | AP36: 312.13 | AQ36: 73725.38 | AR36: 2620.32 | AS36: 977.75 | AT36: 894.02 | AU36: #N/A | AV36: 1758.14 | AW36: 1388.6 | AX36: 8949.79 | AY36: 52839.06 | AZ36: 562.19
A37: =+A32+7 -> 45331 | B37: 20240209 | C37: 5026.61 | D37: 2557.88 | E37: 4715.87 | F37: 4136.74 | G37: 49327579 | H37: 7644.84 | I37: 3358.95 | J37: 3676.59 | K37: 128025.7 | L37: 781.02 | M37: 21009.6 | N37: 30512.17 | O37: #N/A | P37: 2686.88 | Q37: 1452.8 | R37: 2556.1 | S37: 9756.86 | T37: 7647.52 | U37: 6678.94 | V37: 1401.01 | W37: 15746.58 | X37: 64982.98 | Y37: 71595.49 | Z37: #N/A | AA37: 9251 | AB37: 31156.06 | AC37: 1516.5 | AD37: 1512.28 | AE37: 57327.5 | AF37: 1161.12 | AG37: 4559.79 | AH37: 101858.37 | AI37: 1444.23 | AJ37: #N/A | AK37: 78450.66 | AL37: 6126.4 | AM37: 15695.88 | AN37: 3242.38 | AO37: 3138.3 | AP37: 315.41 | AQ37: 73423.3 | AR37: #N/A | AS37: 977.21 | AT37: 890.75 | AU37: #N/A | AV37: 1764.65 | AW37: 1388.37 | AX37: 9045.97 | AY37: 53320.11 | AZ37: 564.38
A38: =+A33+7 -> 45334 | B38: 20240212 | C38: 5021.84 | D38: #N/A | E38: 4746.35 | F38: 4141.81 | G38: #N/A | H38: 7614.92 | I38: 3387.22 | J38: 3715.85 | K38: #N/A | L38: 781.76 | M38: 21067.3 | N38: 30859.22 | O38: #N/A | P38: 2688.74 | Q38: 1464.71 | R38: 2553.29 | S38: 9776.29 | T38: 7689.8 | U38: 6722.85 | V38: 1394.08 | W38: #N/A | X38: 64763.57 | Y38: 71072.49 | Z38: 7297.67 | AA38: 9311.83 | AB38: 31456.73 | AC38: 1511.62 | AD38: #N/A | AE38: 57418.55 | AF38: 1166.48 | AG38: 4519.43 | AH38: 102042.32 | AI38: 1455.66 | AJ38: 6807.82 | AK38: 79424.63 | AL38: 6194.21 | AM38: 15741.87 | AN38: 3248.5 | AO38: #N/A | AP38: 314.08 | AQ38: 73722.1 | AR38: #N/A | AS38: 985.85 | AT38: 897.93 | AU38: #N/A | AV38: 1764.65 | AW38: 1389.3 | AX38: 9174.58 | AY38: #N/A | AZ38: 564.57
A39: =+A34+7 -> 45335 | B39: 20240213 | C39: 4953.17 | D39: 2612.03 | E39: 4689.28 | F39: 4104.81 | G39: #N/A | H39: 7603.58 | I39: 3368.35 | J39: 3675.52 | K39: #N/A | L39: 780.02 | M39: 20584.97 | N39: 30493.85 | O39: #N/A | P39: 2699.63 | Q39: 1470.99 | R39: 2546.86 | S39: 9683.07 | T39: 7625.31 | U39: 6661.08 | V39: 1385.47 | W39: #N/A | X39: 64756.5 | Y39: 71555.19 | Z39: 7209.74 | AA39: 9284.7 | AB39: 31134.17 | AC39: 1518.22 | AD39: 1531.37 | AE39: 56906.99 | AF39: 1148.18 | AG39: 4512.4 | AH39: 101707.7 | AI39: 1441.7 | AJ39: 6827.92 | AK39: 78038.67 | AL39: 6134.12 | AM39: 15675.54 | AN39: 3254.6 | AO39: 3141.87 | AP39: 313.08 | AQ39: 73062.59 | AR39: 2649.64 | AS39: 980.42 | AT39: 890.56 | AU39: #N/A | AV39: 1764.23 | AW39: 1391.73 | AX39: 8994 | AY39: #N/A | AZ39: 558.23
A40: =+A35+7 -> 45336 | B40: 20240214 | C40: 5000.62 | D40: 2584.59 | E40: 4709.22 | F40: 4132.87 | G40: 48346709 | H40: 7547.74 | I40: 3366.27 | J40: 3665.3 | K40: 127018.29 | L40: 785.2 | M40: 20889.4 | N40: 30759.43 | O40: #N/A | P40: 2698.16 | Q40: 1479.23 | R40: 2581.08 | S40: 9688.81 | T40: 7677.35 | U40: 6686.51 | V40: 1405.38 | W40: 15879.38 | X40: 64999.45 | Y40: 71822.83 | Z40: #N/A | AA40: 9371.6 | AB40: 31329.38 | AC40: 1511.79 | AD40: 1529.33 | AE40: 57248.47 | AF40: 1147.28 | AG40: 4482.28 | AH40: 103498.28 | AI40: 1453.91 | AJ40: 6854.53 | AK40: 79421.21 | AL40: 6100.1 | AM40: 15693.33 | AN40: 3258.14 | AO40: 3139.07 | AP40: 313.08 | AQ40: 73009.74 | AR40: 2620.42 | AS40: 979.23 | AT40: 894.18 | AU40: #N/A | AV40: 1764.36 | AW40: 1385.11 | AX40: 9072.08 | AY40: 53005.23 | AZ40: 562.27
A41: =+A36+7 -> 45337 | B41: 20240215 | C41: 5029.73 | D41: 2591.85 | E41: 4743.17 | F41: 4149.98 | G41: 47753935 | H41: 7605.72 | I41: 3372.09 | J41: 3694.38 | K41: 127804.13 | L41: 780.69 | M41: 21222.69 | N41: 31273.98 | O41: #N/A | P41: 2692.79 | Q41: 1482.34 | R41: 2593.81 | S41: 9755.3 | T41: 7743.42 | U41: 6726.33 | V41: 1403.5 | W41: 15944.63 | X41: 65660.8 | Y41: 72050.38 | Z41: 7303.28 | AA41: 9313.84 | AB41: 31694.44 | AC41: 1517.92 | AD41: 1528.38 | AE41: 57251.89 | AF41: 1153.06 | AG41: 4474.11 | AH41: 104100 | AI41: 1451.28 | AJ41: 6882.15 | AK41: 79333.22 | AL41: 6127.1 | AM41: 15657.02 | AN41: 3265.63 | AO41: 3176.69 | AP41: 313.08 | AQ41: 73218.44 | AR41: 2613.8 | AS41: 979.19 | AT41: 903.15 | AU41: 18644.57 | AV41: 1764.2 | AW41: 1387.27 | AX41: 9242.15 | AY41: 53114.01 | AZ41: 566.69
A42: =+A37+7 -> 45338 | B42: 20240216 | C42: 5005.57 | D42: 2624.73 | E42: 4765.65 | F42: 4205.25 | G42: 46488661 | H42: 7658.32 | I42: 3406.72 | J42: 3690.07 | K42: 128725.88 | L42: 785.36 | M42: 21255.61 | N42: 31995.79 | O42: #N/A | P42: 2702.8 | Q42: 1489.38 | R42: 2599.95 | S42: 9924.47 | T42: 7768.18 | U42: 6754.07 | V42: 1405.32 | W42: 16339.96 | X42: 65769.75 | Y42: 72426.64 | Z42: 7335.55 | AA42: 9329.34 | AB42: 31732.39 | AC42: 1521.44 | AD42: 1533.55 | AE42: 57132.11 | AF42: 1164.46 | AG42: 4506.56 | AH42: 105722.78 | AI42: 1463.57 | AJ42: 6873.23 | AK42: 80147.01 | AL42: 6199.81 | AM42: 15718.39 | AN42: 3242.48 | AO42: 3221.94 | AP42: 313.08 | AQ42: 73616.06 | AR42: 2648.76 | AS42: 975.25 | AT42: 911.05 | AU42: 18607.25 | AV42: 1767.18 | AW42: 1386.27 | AX42: 9250.36 | AY42: 51607.08 | AZ42: 566.63
A43: =+A38+7 -> 45341 | B43: 20240219 | C43: #N/A | D43: 2639.69 | E43: 4763.07 | F43: 4213.95 | G43: 46676574 | H43: 7665.1 | I43: 3393.62 | J43: 3685.02 | K43: 129035.74 | L43: 781.73 | M43: #N/A | N43: 32214.33 | O43: 2910.54 | P43: 2709.57 | Q43: 1480.92 | R43: 2614.09 | S43: 9890.3 | T43: 7768.55 | U43: 6744.06 | V43: 1422.41 | W43: 16155.61 | X43: 66000.08 | Y43: 72708.16 | Z43: 7296.7 | AA43: 9428.14 | AB43: 31676.05 | AC43: 1527.84 | AD43: 1538.61 | AE43: 57490.05 | AF43: 1159.98 | AG43: 4479.19 | AH43: 102393.23 | AI43: 1468.19 | AJ43: 6798.61 | AK43: 80827.33 | AL43: 6245.96 | AM43: 15790.52 | AN43: 3244.56 | AO43: 3225.91 | AP43: 314.08 | AQ43: 73580.88 | AR43: 2680.26 | AS43: 981.09 | AT43: 911.27 | AU43: 18635.8 | AV43: 1771.43 | AW43: 1387.33 | AX43: 9196.41 | AY43: 51535.57 | AZ43: 567.01
A44: =+A39+7 -> 45342 | B44: 20240220 | C44: 4975.51 | D44: 2632.3 | E44: 4760.28 | F44: 4206.04 | G44: 46009682 | H44: 7659.05 | I44: 3395.14 | J44: 3668.88 | K44: 129916.11 | L44: 781.07 | M44: 21217.53 | N44: 32040.14 | O44: 2922.73 | P44: 2712.69 | Q44: 1479.21 | R44: 2580.78 | S44: 9888.8 | T44: 7795.22 | U44: 6734.73 | V44: 1424.35 | W44: 16247.51 | X44: 65940.94 | Y44: 73057.4 | Z44: 7352.6 | AA44: 9437.5 | AB44: 31701.48 | AC44: 1533.05 | AD44: 1555.59 | AE44: 57227.67 | AF44: 1147.89 | AG44: 4447.65 | AH44: 101060.67 | AI44: 1461.91 | AJ44: 6854.66 | AK44: 81780.51 | AL44: 6226.09 | AM44: 15715.6 | AN44: 3207.49 | AO44: 3244.06 | AP44: 313.58 | AQ44: 72946.01 | AR44: 2657.79 | AS44: 989.95 | AT44: 909.34 | AU44: 18753.16 | AV44: 1771.43 | AW44: 1381.07 | AX44: 9344.97 | AY44: 51268.63 | AZ44: 565.24
A45: =+A40+7 -> 45343 | B45: 20240221 | C45: 4981.8 | D45: 2627.3 | E45: 4775.31 | F45: 4180.19 | G45: 45062376 | H45: 7608.36 | I45: 3404.68 | J45: 3677.35 | K45: 130031.58 | L45: 780.01 | M45: 21172.38 | N45: 31602.74 | O45: 2950.96 | P45: 2730.05 | Q45: 1487.11 | R45: 2556.34 | S45: 9904.32 | T45: 7812.09 | U45: 6754.32 | V45: 1420.28 | W45: 16503.1 | X45: 66344.17 | Y45: 72623.09 | Z45: 7349.02 | AA45: 9513.58 | AB45: 32018.4 | AC45: 1535.94 | AD45: 1552.4 | AE45: 57021.03 | AF45: 1146.53 | AG45: 4455.05 | AH45: 101362.38 | AI45: 1459.35 | AJ45: 6897.36 | AK45: 81412.34 | AL45: 6250.49 | AM45: 15888.48 | AN45: 3139.5 | AO45: 3217.11 | AP45: 313.58 | AQ45: 73029.61 | AR45: 2653.31 | AS45: 996.8 | AT45: 908.13 | AU45: 18676.31 | AV45: 1768.58 | AW45: 1393.61 | AX45: 9312.12 | AY45: 49772.51 | AZ45: 564.91
A46: =+A41+7 -> 45344 | B46: 20240222 | C46: 5087.03 | D46: 2660.71 | E46: 4855.36 | F46: 4195.17 | G46: 46834227 | H46: 7611.24 | I46: 3413.31 | J46: 3696.15 | K46: 130240.55 | L46: 784.84 | M46: 21318.08 | N46: 31562.17 | O46: 2988.36 | P46: 2755.56 | Q46: 1497.1 | R46: 2600.02 | S46: 9894.63 | T46: 7911.6 | U46: 6853.86 | V46: 1419.25 | W46: 16742.95 | X46: 66185.37 | Y46: 73158.24 | Z46: 7339.64 | AA46: 9562.77 | AB46: 32356.26 | AC46: 1531.68 | AD46: 1545.49 | AE46: 57130.84 | AF46: 1165.37 | AG46: 4493.4 | AH46: 101239.1 | AI46: 1463.65 | AJ46: 6903.15 | AK46: 82464.52 | AL46: 6199.61 | AM46: 16013.66 | AN46: 3142.3 | AO46: 3222.94 | AP46: 314.08 | AQ46: 74112.74 | AR46: 2664.27 | AS46: 1000.01 | AT46: 914.1 | AU46: 18852.78 | AV46: 1768.58 | AW46: 1402.47 | AX46: 9347.17 | AY46: 50620.56 | AZ46: 573.94
A47: =+A42+7 -> 45345 | B47: 20240223 | C47: 5088.8 | D47: #N/A | E47: 4872.57 | F47: 4202.76 | G47: 47923411 | H47: 7643.59 | I47: 3384.84 | J47: 3707.48 | K47: 129418.73 | L47: 785.45 | M47: 21413.15 | N47: 31376.07 | O47: 3004.88 | P47: 2801.96 | Q47: 1492.45 | R47: 2588.79 | S47: 9881.26 | T47: 7966.68 | U47: 6872.83 | V47: 1413.26 | W47: 16725.86 | X47: 66263.18 | Y47: 73142.8 | Z47: 7295.1 | AA47: 9660.86 | AB47: 32700.92 | AC47: 1536.69 | AD47: 1549.11 | AE47: 56659.8 | AF47: 1160.88 | AG47: 4504.35 | AH47: 102088.3 | AI47: 1460.03 | AJ47: 6913.21 | AK47: 83265.56 | AL47: 6242.11 | AM47: 15926.46 | AN47: #N/A | AO47: 3184.91 | AP47: 314.08 | AQ47: 74213.39 | AR47: 2667.7 | AS47: 999.25 | AT47: 916.99 | AU47: 18889.19 | AV47: 1765.96 | AW47: 1398.14 | AX47: 9374.2 | AY47: 50807.87 | AZ47: 574.63
A48: =+A43+7 -> 45348 | B48: 20240226 | C48: 5069.53 | D48: 2673.62 | E48: 4864.29 | F48: 4190.8 | G48: 46807649 | H48: 7652.84 | I48: 3375.95 | J48: 3685.19 | K48: 129609.05 | L48: 785.07 | M48: 21324.31 | N48: 31451.94 | O48: 2977.02 | P48: 2803.49 | Q48: 1489.56 | R48: 2578.09 | S48: 9827.35 | T48: 7929.82 | U48: 6871.87 | V48: 1414.51 | W48: 16634.74 | X48: 66038.2 | Y48: 72790.13 | Z48: 7283.82 | AA48: 9454.75 | AB48: 32557.81 | AC48: 1544.68 | AD48: 1547.6 | AE48: 56194.72 | AF48: 1157.46 | AG48: 4496.28 | AH48: 101995.53 | AI48: 1460.46 | AJ48: 6891.49 | AK48: 83116.29 | AL48: 6179.67 | AM48: 16011.7 | AN48: 3213.17 | AO48: 3171.12 | AP48: 314.08 | AQ48: 73621.24 | AR48: 2647.08 | AS48: 999.83 | AT48: 917.29 | AU48: 18948.05 | AV48: 1772.1 | AW48: #N/A | AX48: 9334.13 | AY48: 49461.59 | AZ48: 573.25
A49: =+A44+7 -> 45349 | B49: 20240227 | C49: 5078.18 | D49: 2678.46 | E49: 4885.74 | F49: 4191.43 | G49: 44733692 | H49: 7663.01 | I49: 3396.57 | J49: 3696.65 | K49: 131689.37 | L49: 783.41 | M49: 21318.9 | N49: 31990.55 | O49: 3015.48 | P49: 2790.48 | Q49: 1480 | R49: 2557.47 | S49: 9894.42 | T49: 7948.4 | U49: 6924.31 | V49: 1411.98 | W49: 16790.8 | X49: 65541.56 | Y49: 73095.22 | Z49: 7285.32 | AA49: 9495.06 | AB49: 32706.44 | AC49: 1540.23 | AD49: 1558.8 | AE49: 56241.03 | AF49: 1159.49 | AG49: 4490.41 | AH49: 100582.89 | AI49: 1456.91 | AJ49: 6860.67 | AK49: 83007.32 | AL49: 6220.07 | AM49: 15818.35 | AN49: 3208.99 | AO49: 3157.32 | AP49: 311.59 | AQ49: 73142.11 | AR49: 2625.05 | AS49: 997.91 | AT49: 919.39 | AU49: 18854.41 | AV49: 1770.94 | AW49: 1393.7 | AX49: 9179.48 | AY49: 49769.94 | AZ49: 574.53
A50: =+A45+7 -> 45350 | B50: 20240228 | C50: 5069.76 | D50: 2674.95 | E50: 4883.77 | F50: 4159.57 | G50: 43080054 | H50: 7660.42 | I50: 3388.73 | J50: 3700.02 | K50: 130155.43 | L50: 784.03 | M50: 21243.77 | N50: 32123.63 | O50: 2957.85 | P50: 2768.98 | Q50: 1479.13 | R50: 2552.36 | S50: 9894.1 | T50: 7954.39 | U50: 6941.74 | V50: 1407.74 | W50: 16536.85 | X50: 66080.19 | Y50: 72304.88 | Z50: 7328.64 | AA50: 9530.01 | AB50: 32617.96 | AC50: 1544.56 | AD50: 1545.59 | AE50: 55350.61 | AF50: 1151.07 | AG50: 4516.61 | AH50: 99266.02 | AI50: 1463.01 | AJ50: 6876.52 | AK50: 81661.42 | AL50: 6192.9 | AM50: 15874.35 | AN50: 3227.05 | AO50: 3138.93 | AP50: 311.59 | AQ50: 72204.53 | AR50: 2652.29 | AS50: 994.17 | AT50: 919.32 | AU50: #N/A | AV50: 1770.94 | AW50: 1382.05 | AX50: 9062.36 | AY50: 49247.9 | AZ50: 572.54
A51: =+A46+7 -> 45351 | B51: 20240229 | C51: 5096.27 | D51: 2675.73 | E51: 4877.77 | F51: 4163.21 | G51: 43738360 | H51: 7698.7 | I51: 3348.13 | J51: 3661.42 | K51: 129020.02 | L51: 788.42 | M51: 21363.61 | N51: 32664.63 | O51: 3015.17 | P51: 2727.54 | Q51: 1457.17 | R51: 2534.15 | S51: 9839.53 | T51: 7927.43 | U51: 6971.85 | V51: 1424.77 | W51: 16511.44 | X51: 65938.65 | Y51: 72500.3 | Z51: 7316.11 | AA51: 9489.67 | AB51: 32580.94 | AC51: 1535.89 | AD51: 1551.44 | AE51: 55414 | AF51: 1152.47 | AG51: 4503.83 | AH51: 99980.3 | AI51: 1463.93 | AJ51: 6944.71 | AK51: 81944.56 | AL51: 6157.96 | AM51: 15891.07 | AN51: 3256.8 | AO51: 3141.85 | AP51: 310.1 | AQ51: 72729.73 | AR51: 2642.36 | AS51: 986.69 | AT51: 922.24 | AU51: 18966.77 | AV51: 1770.94 | AW51: 1370.67 | AX51: 9193.69 | AY51: 49444.03 | AZ51: 575.01
A52: =+A47+7 -> 45352 | B52: 20240301 | C52: 5137.08 | D52: 2709.42 | E52: 4894.86 | F52: 4197.12 | G52: 45535674 | H52: 7745.61 | I52: 3378.58 | J52: 3698.82 | K52: 129180.37 | L52: 793.16 | M52: 21552.35 | N52: 32844.99 | O52: 3027.02 | P52: 2760.46 | Q52: 1460.6 | R52: 2605.63 | S52: 9849.62 | T52: 7934.17 | U52: 6994.48 | V52: 1422.75 | W52: 16589.44 | X52: 66169.03 | Y52: 73745.35 | Z52: 7311.91 | AA52: 9521.49 | AB52: 32934.29 | AC52: 1539.22 | AD52: 1538.02 | AE52: 55536.32 | AF52: 1160.53 | AG52: 4504.48 | AH52: 98751.98 | AI52: 1474.5 | AJ52: 6919.59 | AK52: 82172.36 | AL52: 6199.59 | AM52: 16009.52 | AN52: 3266.66 | AO52: 3135.76 | AP52: 310.1 | AQ52: 72775.49 | AR52: #N/A | AS52: 993.52 | AT52: 929.79 | AU52: 18935.93 | AV52: 1770.2 | AW52: 1367.42 | AX52: 9097.15 | AY52: 49196.7 | AZ52: 579.32
A53: =+A48+7 -> 45355 | B53: 20240304 | C53: 5130.95 | D53: 2706.28 | E53: 4912.92 | F53: 4174.28 | G53: 45478962 | H53: 7735.79 | I53: 3371.78 | J53: 3672.25 | K53: 128340.54 | L53: #N/A | M53: 21531.07 | N53: 32147.2 | O53: 3039.31 | P53: 2771.7 | Q53: 1447.5 | R53: 2653.22 | S53: 9779.74 | T53: 7956.41 | U53: 6987.05 | V53: 1434.87 | W53: 16595.97 | X53: 66319.5 | Y53: 73872.29 | Z53: 7276.75 | AA53: 9535.5 | AB53: 32912.34 | AC53: 1548.28 | AD53: 1539.27 | AE53: 55462.49 | AF53: 1164.15 | AG53: 4496.11 | AH53: 98847.89 | AI53: 1468.63 | AJ53: 6951.67 | AK53: 81264.27 | AL53: 6175.64 | AM53: 16129.36 | AN53: 3296.75 | AO53: 3122.21 | AP53: 310.6 | AQ53: 72633.15 | AR53: 2674.27 | AS53: 993.52 | AT53: 925.2 | AU53: 19305.31 | AV53: 1773.33 | AW53: 1362.57 | AX53: 8907.65 | AY53: 48873.58 | AZ53: 579.35
A54: =+A49+7 -> 45356 | B54: 20240305 | C54: 5078.65 | D54: 2719.93 | E54: 4893.07 | F54: 4177.42 | G54: 43160889 | H54: 7724.2 | I54: 3370.51 | J54: 3663.6 | K54: 128098.11 | L54: 794.35 | M54: 21525.93 | N54: 31750.74 | O54: 3047.79 | P54: 2775.42 | Q54: 1457.93 | R54: 2600.26 | S54: 9731.37 | T54: 7932.82 | U54: 6980.34 | V54: 1430.94 | W54: 16162.64 | X54: 65840.02 | Y54: 73677.13 | Z54: 7247.46 | AA54: 9509.95 | AB54: 33146.16 | AC54: 1545.08 | AD54: 1536.98 | AE54: 55476.25 | AF54: 1155.4 | AG54: 4506.15 | AH54: 99190.46 | AI54: 1477.08 | AJ54: 6905.46 | AK54: 80537.55 | AL54: 6187.35 | AM54: 16204.68 | AN54: 3300.89 | AO54: 3107.1 | AP54: 309.11 | AQ54: 72241.72 | AR54: 2649.4 | AS54: 998.39 | AT54: 918.8 | AU54: 19386.92 | AV54: 1767.74 | AW54: 1359.26 | AX54: 8860.52 | AY54: 47998.11 | AZ54: 575.23
A55: =+A50+7 -> 45357 | B55: 20240306 | C55: 5104.76 | D55: 2730.67 | E55: 4915.49 | F55: 4199.15 | G55: 43267087 | H55: 7733.54 | I55: 3390.45 | J55: 3695.03 | K55: 128890.23 | L55: 800.72 | M55: 21593.96 | N55: 32175.42 | O55: 3039.93 | P55: 2766.21 | Q55: 1461.51 | R55: 2591.15 | S55: 9739.96 | T55: 7954.74 | U55: 6987.37 | V55: 1433.04 | W55: 16438.09 | X55: 65986.52 | Y55: 74085.99 | Z55: 7329.8 | AA55: 9633.35 | AB55: 33363.84 | AC55: 1551.08 | AD55: 1531.51 | AE55: 55284.51 | AF55: 1163.6 | AG55: 4520.6 | AH55: 99591.64 | AI55: 1477.02 | AJ55: 6878.54 | AK55: 80742.03 | AL55: 6203.64 | AM55: 16239.24 | AN55: 3310.58 | AO55: 3136.14 | AP55: 309.11 | AQ55: 73578.18 | AR55: 2641.49 | AS55: 1006.13 | AT55: 925.98 | AU55: 19499.45 | AV55: 1767.05 | AW55: 1370.55 | AX55: 8744.58 | AY55: 50095.08 | AZ55: 578.7
A56: =+A51+7 -> 45358 | B56: 20240307 | C56: 5157.36 | D56: 2718.54 | E56: 4974.22 | F56: 4208.82 | G56: 42887214 | H56: 7763.71 | I56: 3386 | J56: 3718.28 | K56: 128339.76 | L56: 797.24 | M56: 21794.56 | N56: 32233.5 | O56: 3027.4 | P56: 2762.87 | Q56: 1468.4 | R56: 2738.69 | S56: 9816.43 | T56: 8016.22 | U56: 7037.03 | V56: 1425.44 | W56: 16229.78 | X56: 66201.33 | Y56: 74119.39 | Z56: 7373.96 | AA56: 9661.5 | AB56: 33418.68 | AC56: 1545.83 | AD56: 1535.83 | AE56: 55049.49 | AF56: 1181.44 | AG56: 4519.1 | AH56: 100335.3 | AI56: 1474.58 | AJ56: 6837.34 | AK56: 79879.2 | AL56: 6192.75 | AM56: 16228.56 | AN56: 3315.68 | AO56: 3133.78 | AP56: 311.72 | AQ56: 73604.11 | AR56: 2647.62 | AS56: 1018.55 | AT56: 930.04 | AU56: 19693.52 | AV56: 1767.05 | AW56: 1372.16 | AX56: 9054.18 | AY56: 50100 | AZ56: 583.93
A57: =+A52+7 -> 45359 | B57: 20240308 | C57: 5123.69 | D57: 2726.8 | E57: 4961.11 | F57: 4194.47 | G57: 43133792 | H57: 7846.97 | I57: 3378.54 | J57: 3733.99 | K57: 127070.79 | L57: 803 | M57: 21737.53 | N57: 32130.16 | O57: 3046.02 | P57: 2760.77 | Q57: 1463.23 | R57: 2718.42 | S57: 9835.99 | T57: 8028.01 | U57: 7025.81 | V57: 1427.02 | W57: 16353.39 | X57: 66093.62 | Y57: #N/A | Z57: 7381.91 | AA57: 9678.32 | AB57: 33403.8 | AC57: 1556.1 | AD57: 1539.86 | AE57: 54935.99 | AF57: 1171.31 | AG57: 4560.84 | AH57: 101330.85 | AI57: 1482.1 | AJ57: 6942.21 | AK57: 80199.54 | AL57: 6155.48 | AM57: 16298.59 | AN57: #N/A | AO57: 3147.09 | AP57: 311.72 | AQ57: 73717.78 | AR57: 2680.35 | AS57: 1017.39 | AT57: 938.67 | AU57: 19785.32 | AV57: 1767.05 | AW57: 1386.42 | AX57: 9155.32 | AY57: 50438.99 | AZ57: 582.86
A58: =+A53+7 -> 45362 | B58: 20240311 | C58: 5117.94 | D58: 2666.83 | E58: 4930.42 | F58: 4196.01 | G58: 41254538 | H58: 7704.22 | I58: 3353.14 | J58: 3741.71 | K58: 126123.56 | L58: 813.81 | M58: 21769.22 | N58: 32538.51 | O58: 3068.46 | P58: 2775.97 | Q58: 1465.79 | R58: 2696.84 | S58: 9772.42 | T58: 8019.73 | U58: 6999 | V58: 1391.26 | W58: 16587.57 | X58: 65599.49 | Y58: 73502.64 | Z58: #N/A | AA58: 9656.88 | AB58: 33315.07 | AC58: 1566.28 | AD58: 1544.71 | AE58: 55076.12 | AF58: 1157.55 | AG58: 4541.55 | AH58: 102044.84 | AI58: 1469.11 | AJ58: 6872.24 | AK58: 80359.43 | AL58: 6158.39 | AM58: 16241.58 | AN58: 3320.31 | AO58: 3138.42 | AP58: 311.72 | AQ58: 73481.74 | AR58: 2659.84 | AS58: 1019.22 | AT58: 936.52 | AU58: 19726.08 | AV58: 1763.98 | AW58: 1380.23 | AX58: 9131.82 | AY58: 51503.7 | AZ58: 580.84
A59: =+A54+7 -> 45363 | B59: 20240312 | C59: 5175.27 | D59: 2657.24 | E59: 4983.2 | F59: 4233.33 | G59: 44316874 | H59: 7712.53 | I59: 3364.01 | J59: 3749.94 | K59: 127667.84 | L59: 810.13 | M59: 21831.02 | N59: 32923.77 | O59: 3055.94 | P59: 2784.78 | Q59: 1466.88 | R59: 2739.6 | S59: 9870.59 | T59: 8087.48 | U59: 7085.27 | V59: 1395.86 | W59: 17093.5 | X59: 66455.07 | Y59: 73667.96 | Z59: #N/A | AA59: 9706.32 | AB59: 33753.12 | AC59: 1562.41 | AD59: 1554.56 | AE59: 54898.95 | AF59: 1168.15 | AG59: 4523.98 | AH59: 103524.44 | AI59: 1480.8 | AJ59: 6879.59 | AK59: 81916.43 | AL59: 6142.97 | AM59: 16232.1 | AN59: 3332.6 | AO59: 3141.47 | AP59: 309.23 | AQ59: 73484.56 | AR59: 2681.81 | AS59: 1025.79 | AT59: 950.32 | AU59: 19914.55 | AV59: 1763.99 | AW59: 1379.63 | AX59: 9069.03 | AY59: 52193.78 | AZ59: 585.64
A60: =+A55+7 -> 45364 | B60: 20240313 | C60: 5165.31 | D60: 2648.51 | E60: 5000.55 | F60: 4243.71 | G60: 45375169 | H60: 7729.44 | I60: 3401.67 | J60: 3728.49 | K60: 128006.05 | L60: 809.41 | M60: 21970.11 | N60: 32855.93 | O60: 3043.83 | P60: 2804.03 | Q60: 1483.58 | R60: 2718.18 | S60: 9845.68 | T60: 8137.58 | U60: 7083.66 | V60: 1399.87 | W60: 17082.11 | X60: 65600.63 | Y60: 72761.89 | Z60: 7421.21 | AA60: 9658.95 | AB60: 33885.43 | AC60: 1573.37 | AD60: 1538.13 | AE60: 55848.72 | AF60: 1166.57 | AG60: 4513.29 | AH60: 104007.31 | AI60: 1495.1 | AJ60: 6965.51 | AK60: 81647.32 | AL60: 6110.35 | AM60: 16230.92 | AN60: 3320.68 | AO60: 3160.72 | AP60: 309.23 | AQ60: 74258.63 | AR60: 2693.57 | AS60: 1040.63 | AT60: 952.95 | AU60: 19928.51 | AV60: 1767.18 | AW60: 1384.51 | AX60: 8910.23 | AY60: 53488.57 | AZ60: 585.28
A61: =+A56+7 -> 45365 | B61: 20240314 | C61: 5150.48 | D61: 2661.59 | E61: 4993.12 | F61: 4228.42 | G61: 44822624 | H61: 7713.62 | I61: 3394.38 | J61: 3691.85 | K61: 127689.97 | L61: 813.62 | M61: 21829.85 | N61: 32721.51 | O61: 3038.23 | P61: 2810.04 | Q61: 1486.64 | R61: 2751.08 | S61: 9771.13 | T61: 8161.42 | U61: 7076.06 | V61: 1417.64 | W61: 16961.66 | X61: 64988.33 | Y61: 73097.28 | Z61: 7433.32 | AA61: 9673.64 | AB61: 33786.18 | AC61: 1611.07 | AD61: 1543.75 | AE61: 56059.26 | AF61: 1164.61 | AG61: 4511.77 | AH61: 104056.21 | AI61: 1495.17 | AJ61: 6967.96 | AK61: 81787.89 | AL61: 6055.53 | AM61: 16295.44 | AN61: 3297 | AO61: 3186.4 | AP61: 309.81 | AQ61: 73866.79 | AR61: 2718.76 | AS61: 1033.71 | AT61: 951.96 | AU61: 19937.92 | AV61: 1767.51 | AW61: 1394.93 | AX61: 8883.52 | AY61: 53589.25 | AZ61: 583.19
A62: =+A57+7 -> 45366 | B62: 20240315 | C62: 5117.09 | D62: 2670.8 | E62: 4986.02 | F62: 4222.09 | G62: 46050614 | H62: 7670.28 | I62: 3410.12 | J62: 3684.2 | K62: 126741.81 | L62: 813.82 | M62: 21849.15 | N62: 32753.57 | O62: 3054.64 | P62: 2796.6 | Q62: 1480.68 | R62: 2698.09 | S62: 9757.96 | T62: 8164.35 | U62: 7073.98 | V62: 1422.03 | W62: 16720.89 | X62: #N/A | Y62: 72643.43 | Z62: 7328.05 | AA62: 9834.65 | AB62: 33940.03 | AC62: 1637.74 | AD62: 1552.83 | AE62: 56228.4 | AF62: 1155.31 | AG62: 4495.97 | AH62: 105085.25 | AI62: 1499.82 | AJ62: 6822.32 | AK62: 80199.35 | AL62: 6130.85 | AM62: 16246.54 | AN62: 3300.07 | AO62: 3172.96 | AP62: 309.81 | AQ62: 72990.7 | AR62: 2666.84 | AS62: 1044.9 | AT62: 954.79 | AU62: 19682.5 | AV62: 1770.77 | AW62: 1386.04 | AX62: 8828.7 | AY62: 52081.14 | AZ62: 579.7
A63: =+A58+7 -> 45369 | B63: 20240318 | C63: 5149.42 | D63: 2721.99 | E63: 4982.76 | F63: 4218.89 | G63: 48370338 | H63: 7675.84 | I63: 3429.3 | J63: 3673.19 | K63: 126954.18 | L63: 814.4 | M63: 21837.18 | N63: 32715.82 | O63: 3084.93 | P63: 2773.56 | Q63: 1492.38 | R63: 2717.7 | S63: 9705.34 | T63: 8148.14 | U63: 7074.99 | V63: #N/A | W63: 16737.12 | X63: 65450.33 | Y63: 72748.42 | Z63: 7302.45 | AA63: 9841.2 | AB63: 33940.96 | AC63: 1630.81 | AD63: 1553.64 | AE63: #N/A | AF63: 1159.07 | AG63: 4477.91 | AH63: 104663.34 | AI63: 1509.16 | AJ63: 6853.29 | AK63: 79997.2 | AL63: 6170.73 | AM63: 16347.25 | AN63: 3296.3 | AO63: 3171.93 | AP63: 309.81 | AQ63: 72430.46 | AR63: 2685.84 | AS63: 1044.8 | AT63: 945.7 | AU63: 19879.85 | AV63: 1770.58 | AW63: 1385.94 | AX63: 8718.11 | AY63: 52064.66 | AZ63: 582.46
A64: =+A59+7 -> 45370 | B64: 20240319 | C64: 5178.51 | D64: 2750.97 | E64: 5007.92 | F64: 4224.36 | G64: 48451343 | H64: 7703.23 | I64: 3453.88 | J64: 3681.14 | K64: 127528.85 | L64: 809.24 | M64: 21860.58 | N64: 32518.05 | O64: 3062.76 | P64: 2797.35 | Q64: 1495.44 | R64: 2687.69 | S64: 9795.46 | T64: 8201.05 | U64: 7094.28 | V64: 1403.47 | W64: 16529.48 | X64: 65933.87 | Y64: 72012.05 | Z64: 7336.75 | AA64: 9910.51 | AB64: 34262.36 | AC64: 1633.87 | AD64: 1544.96 | AE64: 55548.07 | AF64: 1165.69 | AG64: 4508.83 | AH64: 104553.31 | AI64: 1512.55 | AJ64: 6848.43 | AK64: 79698.76 | AL64: 6122.82 | AM64: 16369.18 | AN64: 3264.97 | AO64: 3173.55 | AP64: 310.8 | AQ64: 71868.07 | AR64: 2656.17 | AS64: 1054.44 | AT64: 951.6 | AU64: 19857.2 | AV64: 1770.51 | AW64: 1382.46 | AX64: 8929.88 | AY64: #N/A | AZ64: 583.73
A65: =+A60+7 -> 45371 | B65: 20240320 | C65: 5224.62 | D65: #N/A | E65: 5000.31 | F65: 4225.49 | G65: 50642436 | H65: 7695.76 | I65: 3453.91 | J65: 3685.41 | K65: 129124.83 | L65: 811.35 | M65: 22045.71 | N65: 32916.67 | O65: 3079.69 | P65: 2820.36 | Q65: 1495.31 | R65: 2703.66 | S65: 9778.73 | T65: 8161.41 | U65: 7104.06 | V65: 1417.72 | W65: 16543.07 | X65: 65982.86 | Y65: 72101.69 | Z65: 7331.13 | AA65: 9867.88 | AB65: 34293.29 | AC65: 1667.01 | AD65: 1535.79 | AE65: 56618.01 | AF65: 1167.78 | AG65: 4513 | AH65: 104256.81 | AI65: 1512.46 | AJ65: 6856.77 | AK65: 79709.28 | AL65: 6152.21 | AM65: 16481.29 | AN65: 3267.1 | AO65: 3177.48 | AP65: 310.8 | AQ65: 72419.7 | AR65: 2690.14 | AS65: 1058.59 | AT65: 951.42 | AU65: 19784.45 | AV65: 1770.53 | AW65: 1373.18 | AX65: 8955.12 | AY65: 51513.75 | AZ65: 587.3
A66: =+A61+7 -> 45372 | B66: 20240321 | C66: 5241.53 | D66: 2796.21 | E66: 5052.31 | F66: 4300.46 | G66: 52280300 | H66: 7781.97 | I66: 3483.75 | J66: 3787.97 | K66: 128158.57 | L66: 811.02 | M66: 22087.26 | N66: 32853.08 | O66: 3077.11 | P66: 2834.73 | Q66: 1483.08 | R66: 2690.17 | S66: 9856.48 | T66: 8179.72 | U66: 7167.5 | V66: 1430.35 | W66: 16863.1 | X66: 65841.44 | Y66: 72641.19 | Z66: 7338.35 | AA66: 9902.68 | AB66: 34327.95 | AC66: 1658.96 | AD66: 1541.41 | AE66: 56657.44 | AF66: 1191.2 | AG66: 4534.91 | AH66: 104387.47 | AI66: 1521.01 | AJ66: 6963.22 | AK66: 81814.93 | AL66: 6178.82 | AM66: 16601.85 | AN66: 3286.69 | AO66: 3220.37 | AP66: 310.8 | AQ66: #N/A | AR66: 2754.86 | AS66: 1070.5 | AT66: 968.32 | AU66: 20199.09 | AV66: 1773.81 | AW66: 1387.62 | AX66: 9140.7 | AY66: 51002.88 | AZ66: 591.53
A67: =+A62+7 -> 45373 | B67: 20240322 | C67: 5234.18 | D67: 2813.22 | E67: 5031.15 | F67: 4322.51 | G67: 52332328 | H67: 7770.55 | I67: 3499.4 | J67: 3803.73 | K67: 127027.1 | L67: 806.02 | M67: 21984.08 | N67: 32991.36 | O67: 3048.03 | P67: 2846.94 | Q67: 1490.66 | R67: 2683.39 | S67: 9752.49 | T67: 8151.92 | U67: 7180.18 | V67: 1425.16 | W67: 16499.47 | X67: 65236.93 | Y67: 72831.94 | Z67: 7350.15 | AA67: 9866.9 | AB67: 34343.61 | AC67: 1687.17 | AD67: 1542.39 | AE67: 56610.54 | AF67: 1190.35 | AG67: 4558.85 | AH67: 104647.37 | AI67: 1530.56 | AJ67: 6881.97 | AK67: 80992.64 | AL67: 6227.92 | AM67: 16754.73 | AN67: 3273.49 | AO67: 3217.97 | AP67: 307.32 | AQ67: 73254.19 | AR67: 2748.56 | AS67: 1078.73 | AT67: 966.9 | AU67: 20228.43 | AV67: 1776.94 | AW67: 1381.04 | AX67: 9111.5 | AY67: 50902.39 | AZ67: 589.85
A68: =+A63+7 -> 45376 | B68: 20240325 | C68: 5218.19 | D68: 2777.64 | E68: 5044.19 | F68: 4312.78 | G68: 51665995 | H68: 7811.94 | I68: 3496.32 | J68: 3811.5 | K68: 126931.47 | L68: 805.51 | M68: 21942.28 | N68: 32881.55 | O68: 3026.31 | P68: 2840.62 | Q68: 1488.83 | R68: 2697.51 | S68: 9765.16 | T68: 8151.6 | U68: 7202.02 | V68: #N/A | W68: 16473.64 | X68: 65095.72 | Y68: #N/A | Z68: 7377.76 | AA68: 9808.6 | AB68: 34639.41 | AC68: 1712.76 | AD68: 1537.54 | AE68: 56552.54 | AF68: 1192.48 | AG68: 4592.5 | AH68: 104136.35 | AI68: 1538.37 | AJ68: 6853.1 | AK68: 80081.15 | AL68: 6199.21 | AM68: 16702.44 | AN68: 3281.63 | AO68: 3198.1 | AP68: 307.32 | AQ68: 73282.9 | AR68: 2737.57 | AS68: 1080.44 | AT68: 965.74 | AU68: 20192.25 | AV68: 1776.94 | AW68: 1372.49 | AX68: 9029.38 | AY68: 51433.26 | AZ68: 588.49
A69: =+A64+7 -> 45377 | B69: 20240326 | C69: 5203.58 | D69: 2780.8 | E69: 5064.18 | F69: 4324.29 | G69: 51609073 | H69: 7780.23 | I69: 3499.12 | J69: 3807.47 | K69: 126863.02 | L69: 804.48 | M69: 21912.52 | N69: 33006.28 | O69: 3031.48 | P69: 2848.76 | Q69: 1489.88 | R69: 2687.53 | S69: 9787.15 | T69: 8184.75 | U69: 7250.55 | V69: 1422.51 | W69: 16618.32 | X69: 65005.38 | Y69: 72470.3 | Z69: 7365.66 | AA69: 9895.7 | AB69: 34688.17 | AC69: 1748.15 | AD69: 1538.42 | AE69: 57209.7 | AF69: 1192.44 | AG69: 4579.1 | AH69: 103952.47 | AI69: 1535.74 | AJ69: 6898.17 | AK69: 81286.31 | AL69: 6222.03 | AM69: 16781.47 | AN69: 3285.54 | AO69: 3233.33 | AP69: 307.32 | AQ69: 73608.07 | AR69: 2757.09 | AS69: 1084.8 | AT69: 971.52 | AU69: 20126.49 | AV69: 1787.63 | AW69: 1377.23 | AX69: 8807.38 | AY69: 54853.01 | AZ69: 587.86
A70: =+A65+7 -> 45378 | B70: 20240327 | C70: 5248.49 | D70: 2799.28 | E70: 5081.74 | F70: 4325.93 | G70: 51706700 | H70: 7819.61 | I70: 3523.44 | J70: 3832.99 | K70: 127690.62 | L70: 803.52 | M70: 22107.08 | N70: 33372.58 | O70: 2993.14 | P70: 2842.41 | Q70: 1513.01 | R70: 2669.49 | S70: 9797.77 | T70: 8204.81 | U70: 7287.12 | V70: 1417.59 | W70: 16392.84 | X70: 64830.3 | Y70: 72996.31 | Z70: 7310.09 | AA70: 9867.82 | AB70: 34759.69 | AC70: 1753.02 | AD70: 1530.6 | AE70: 57369.01 | AF70: 1193.41 | AG70: 4569.54 | AH70: 104283.64 | AI70: 1541.53 | AJ70: 6903.53 | AK70: 81560.33 | AL70: 6276.69 | AM70: 16830.02 | AN70: 3304.09 | AO70: 3251.71 | AP70: 307.32 | AQ70: 73909.47 | AR70: 2755.11 | AS70: 1096.16 | AT70: 971.19 | AU70: 20200.12 | AV70: 1790.2 | AW70: 1380.83 | AX70: 8806.72 | AY70: 55619.96 | AZ70: 591.3
A71: =+A66+7 -> 45379 | B71: 20240328 | C71: 5254.35 | D71: 2750.81 | E71: 5083.42 | F71: 4338.05 | G71: #N/A | H71: 7896.86 | I71: 3535.79 | J71: 3845.63 | K71: 128106.1 | L71: 807.47 | M71: 22167.03 | N71: 33600.36 | O71: 3010.66 | P71: 2834.52 | Q71: 1515.16 | R71: #N/A | S71: 9746.89 | T71: 8205.81 | U71: 7293.2 | V71: 1422.35 | W71: 16541.42 | X71: 65384.6 | Y71: 73651.35 | Z71: 7288.81 | AA71: 9957.27 | AB71: 34750.35 | AC71: 1752.43 | AD71: #N/A | AE71: #N/A | AF71: 1195.85 | AG71: 4605.54 | AH71: 104562.06 | AI71: 1541.53 | AJ71: #N/A | AK71: 82745.58 | AL71: 6280.5 | AM71: 16928.98 | AN71: 3312.77 | AO71: 3224.01 | AP71: 307.32 | AQ71: 74535.99 | AR71: 2745.82 | AS71: 1094.2 | AT71: 963.34 | AU71: 20146.55 | AV71: 1790.24 | AW71: 1370.34 | AX71: 9079.97 | AY71: #N/A | AZ71: 591.43
A72: =+A67+7 -> 45380 | B72: 20240329 | C72: #N/A | D72: 2768.62 | E72: #N/A | F72: #N/A | G72: #N/A | H72: #N/A | I72: #N/A | J72: #N/A | K72: #N/A | L72: #N/A | M72: #N/A | N72: #N/A | O72: 3041.17 | P72: #N/A | Q72: #N/A | R72: #N/A | S72: #N/A | T72: #N/A | U72: #N/A | V72: #N/A | W72: #N/A | X72: #N/A | Y72: #N/A | Z72: #N/A | AA72: #N/A | AB72: #N/A | AC72: #N/A | AD72: 1536.07 | AE72: #N/A | AF72: #N/A | AG72: #N/A | AH72: #N/A | AI72: #N/A | AJ72: #N/A | AK72: #N/A | AL72: #N/A | AM72: 17025.61 | AN72: 3332.53 | AO72: #N/A | AP72: #N/A | AQ72: #N/A | AR72: 2746.63 | AS72: #N/A | AT72: #N/A | AU72: 20294.45 | AV72: #N/A | AW72: 1377.94 | AX72: 9142.4 | AY72: #N/A | AZ72: 591.8
A73: =+A68+7 -> 45383 | B73: 20240401 | C73: 5243.77 | D73: 2721.22 | E73: #N/A | F73: #N/A | G73: #N/A | H73: #N/A | I73: #N/A | J73: #N/A | K73: 126990.45 | L73: #N/A | M73: 22185.25 | N73: 33593.81 | O73: 3077.38 | P73: #N/A | Q73: #N/A | R73: #N/A | S73: #N/A | T73: #N/A | U73: #N/A | V73: #N/A | W73: #N/A | X73: #N/A | Y73: 74014.55 | Z73: 7205.06 | AA73: #N/A | AB73: #N/A | AC73: #N/A | AD73: 1544.02 | AE73: 57653.23 | AF73: #N/A | AG73: #N/A | AH73: #N/A | AI73: #N/A | AJ73: 6979.81 | AK73: #N/A | AL73: #N/A | AM73: 17027.05 | AN73: 3363.29 | AO73: 3234.89 | AP73: #N/A | AQ73: #N/A | AR73: 2747.86 | AS73: #N/A | AT73: #N/A | AU73: 20222.33 | AV73: #N/A | AW73: 1379.48 | AX73: 9157.54 | AY73: 57672.99 | AZ73: 589.57
A74: =+A69+7 -> 45384 | B74: 20240402 | C74: 5205.81 | D74: 2714.45 | E74: 5042 | F74: 4324.53 | G74: #N/A | H74: 7887.87 | I74: 3537.13 | J74: 3829.98 | K74: 127548.52 | L74: 807.7 | M74: 22075.1 | N74: 33564.28 | O74: 3074.96 | P74: 2835.44 | Q74: 1525.39 | R74: 2632.86 | S74: 9727.71 | T74: 8130.05 | U74: 7210.53 | V74: 1393.84 | W74: 16931.52 | X74: 65811.24 | Y74: 73903.91 | Z74: 7236.98 | AA74: 9894.42 | AB74: 34325.23 | AC74: 1758.59 | AD74: 1547.99 | AE74: 57581.81 | AF74: 1194.75 | AG74: 4601.95 | AH74: 104518.14 | AI74: 1563.16 | AJ74: 6960.43 | AK74: 82895.6 | AL74: 6307.21 | AM74: 17022.84 | AN74: 3371.29 | AO74: 3247.72 | AP74: 307.32 | AQ74: 74429.48 | AR74: 2753.16 | AS74: 1085.78 | AT74: 958.26 | AU74: 20466.57 | AV74: 1784.06 | AW74: 1379.46 | AX74: 9040.87 | AY74: 58116.66 | AZ74: 586.7
A75: =+A70+7 -> 45385 | B75: 20240403 | C75: 5211.49 | D75: 2706.51 | E75: 5069.25 | F75: 4326.83 | G75: 51773396 | H75: 7782.53 | I75: 3551.06 | J75: 3856.1 | K75: 127318.39 | L75: 808.4 | M75: 22112.46 | N75: 33476.07 | O75: 3069.3 | P75: 2830.81 | Q75: 1520.43 | R75: 2659.92 | S75: 9785.12 | T75: 8153.23 | U75: 7243.89 | V75: 1383.69 | W75: 16725.1 | X75: 66839.15 | Y75: 73876.82 | Z75: 7166.84 | AA75: 10063.55 | AB75: 34480.87 | AC75: 1751.5 | AD75: 1537.01 | AE75: 57503.39 | AF75: 1202.79 | AG75: 4580.89 | AH75: 104181.32 | AI75: 1572.67 | AJ75: 6863.82 | AK75: 82863.21 | AL75: 6304.03 | AM75: 17044.36 | AN75: 3395.59 | AO75: 3222.66 | AP75: 308.97 | AQ75: 74097.93 | AR75: 2706.97 | AS75: 1091.57 | AT75: 959.91 | AU75: 20337.6 | AV75: 1787.54 | AW75: 1375.69 | AX75: 8945.8 | AY75: 57595.93 | AZ75: 587.35
A76: =+A71+7 -> 45386 | B76: 20240404 | C76: 5147.21 | D76: 2732 | E76: 5070.76 | F76: 4348.49 | G76: 50618241 | H76: 7817.34 | I76: 3571.94 | J76: 3872.45 | K76: 127427.53 | L76: 798.58 | M76: 22051.79 | N76: 33343.87 | O76: #N/A | P76: 2831.47 | Q76: 1528.88 | R76: 2626.72 | S76: 9893.12 | T76: 8151.55 | U76: 7257.86 | V76: 1386.38 | W76: #N/A | X76: 66625.06 | Y76: 74227.63 | Z76: 7254.4 | AA76: 10020.34 | AB76: 34454.58 | AC76: 1747.85 | AD76: 1553.24 | AE76: 57882.76 | AF76: 1202.83 | AG76: 4578.9 | AH76: 103736.08 | AI76: 1571.8 | AJ76: 6827.06 | AK76: 83866.96 | AL76: 6309.65 | AM76: 17072.07 | AN76: 3407.57 | AO76: 3235.01 | AP76: 308.97 | AQ76: 75372.98 | AR76: 2742 | AS76: 1098.95 | AT76: 962.77 | AU76: #N/A | AV76: 1787.37 | AW76: 1373.89 | AX76: 9129.02 | AY76: 57754.91 | AZ76: 584.39
A77: =+A72+7 -> 45387 | B77: 20240405 | C77: 5204.34 | D77: 2702.62 | E77: 5014.75 | F77: 4313.94 | G77: 51934477 | H77: 7773.27 | I77: 3566.61 | J77: 3834.33 | K77: 126795.41 | L77: 799.05 | M77: 22264.38 | N77: 33003.3 | O77: 3047.05 | P77: 2825.21 | Q77: 1525.51 | R77: 2633.19 | S77: 9896 | T77: 8061.31 | U77: 7167.9 | V77: 1383.45 | W77: 16723.92 | X77: 66527.41 | Y77: 74248.22 | Z77: 7286.88 | AA77: 10050.54 | AB77: 34010.88 | AC77: 1748.1 | AD77: 1555.25 | AE77: 58092.44 | AF77: 1198.82 | AG77: 4569.93 | AH77: 103437.67 | AI77: 1574.32 | AJ77: 6745.46 | AK77: 83642.11 | AL77: 6219.01 | AM77: 17152.91 | AN77: 3395.37 | AO77: 3218.26 | AP77: 309.62 | AQ77: 74774.72 | AR77: 2714.21 | AS77: 1081.89 | AT77: 955.12 | AU77: #N/A | AV77: #N/A | AW77: 1375.58 | AX77: 9618.83 | AY77: 58983.84 | AZ77: 586.47
A78: =+A73+7 -> 45390 | B78: 20240408 | C78: 5202.39 | D78: 2728.32 | E78: 5046.05 | F78: 4333.28 | G78: 52670391 | H78: 7789.08 | I78: 3592.33 | J78: 3849.87 | K78: 128857.16 | L78: 798.26 | M78: 22260.3 | N78: 33439.44 | O78: 3047.05 | P78: 2831.7 | Q78: 1533.54 | R78: 2642.31 | S78: 9935.87 | T78: 8119.3 | U78: 7224.66 | V78: 1401.35 | W78: 16732.85 | X78: 66544.12 | Y78: 74742.5 | Z78: #N/A | AA78: 10147.02 | AB78: 34315.96 | AC78: 1742.41 | AD78: 1559.98 | AE78: 57989.94 | AF78: 1206.13 | AG78: 4555.22 | AH78: 103046.99 | AI78: 1571.37 | AJ78: 6741.07 | AK78: 84664.91 | AL78: 6265.47 | AM78: 17251.45 | AN78: 3417.38 | AO78: 3215.99 | AP78: 309.62 | AQ78: 75334.92 | AR78: 2717.65 | AS78: 1080.71 | AT78: 962.73 | AU78: 20417.7 | AV78: 1784.66 | AW78: #N/A | AX78: 9756.69 | AY78: 58662.53 | AZ78: 587.81
A79: =+A74+7 -> 45391 | B79: 20240409 | C79: 5209.91 | D79: 2754.69 | E79: 4990.9 | F79: 4326.48 | G79: 53532802 | H79: 7824.24 | I79: 3585.94 | J79: 3845.42 | K79: 129890.37 | L79: 801.37 | M79: 22361.78 | N79: 33759.57 | O79: 3048.54 | P79: 2817.97 | Q79: 1536.49 | R79: 2610.94 | S79: 9957.61 | T79: 8049.17 | U79: 7129.11 | V79: 1417.75 | W79: 16828.07 | X79: 66343.66 | Y79: 74683.7 | Z79: #N/A | AA79: 10068.16 | AB79: 33946.29 | AC79: 1738.99 | AD79: 1553.51 | AE79: 57571.15 | AF79: 1199.07 | AG79: 4533.61 | AH79: #N/A | AI79: 1572.64 | AJ79: #N/A | AK79: 83705.16 | AL79: 6275.83 | AM79: 17209.48 | AN79: 3414.26 | AO79: 3237.52 | AP79: 309.62 | AQ79: 75486.92 | AR79: 2705.16 | AS79: 1070.69 | AT79: 956.36 | AU79: 20796.2 | AV79: 1784.97 | AW79: 1401.11 | AX79: 9814.19 | AY79: 58959.94 | AZ79: 588.8
A80: =+A75+7 -> 45392 | B80: 20240410 | C80: 5160.64 | D80: 2742.79 | E80: 5000.83 | F80: 4339.84 | G80: 52799815 | H80: 7848.45 | I80: 3565.22 | J80: 3831.77 | K80: 128053.74 | L80: 805.67 | M80: 22199.13 | N80: 33868.27 | O80: 3027.33 | P80: 2817.56 | Q80: 1548.83 | R80: 2622.45 | S80: 9948.45 | T80: 8045.38 | U80: 7137.24 | V80: 1420.3 | W80: 17139.17 | X80: 67271.28 | Y80: 75038.15 | Z80: #N/A | AA80: 10146.21 | AB80: 34039.63 | AC80: #N/A | AD80: #N/A | AE80: 56636.54 | AF80: 1207.73 | AG80: 4554.15 | AH80: #N/A | AI80: 1577.6 | AJ80: #N/A | AK80: 84406.4 | AL80: 6279.78 | AM80: 17199.85 | AN80: 3439.11 | AO80: #N/A | AP80: 309.62 | AQ80: 75520.37 | AR80: #N/A | AS80: 1067.17 | AT80: 955.15 | AU80: 20763.53 | AV80: #N/A | AW80: 1408.17 | AX80: #N/A | AY80: 60564.84 | AZ80: 583.74
A81: =+A76+7 -> 45393 | B81: 20240411 | C81: 5199.06 | D81: 2746.96 | E81: 4966.68 | F81: 4322.37 | G81: 53848949 | H81: 7813.58 | I81: 3544.84 | J81: 3836.85 | K81: 127396.35 | L81: 811.83 | M81: 22110.11 | N81: 34048.07 | O81: 3034.25 | P81: 2811.12 | Q81: 1546.89 | R81: 2631.02 | S81: 9924.63 | T81: 8023.74 | U81: 7066.87 | V81: 1416.53 | W81: 17095.03 | X81: 67205.07 | Y81: #N/A | Z81: #N/A | AA81: 9983.67 | AB81: 33713.94 | AC81: 1741.12 | AD81: #N/A | AE81: 56830.32 | AF81: 1203.31 | AG81: 4539.84 | AH81: #N/A | AI81: 1580.18 | AJ81: 6677.65 | AK81: 83492.28 | AL81: 6296.44 | AM81: 17013.16 | AN81: 3439.53 | AO81: 3227.61 | AP81: 316.19 | AQ81: 75303.25 | AR81: 2706.96 | AS81: 1054.76 | AT81: 947.71 | AU81: 20753.22 | AV81: #N/A | AW81: 1396.38 | AX81: #N/A | AY81: 60547.92 | AZ81: 585.03
A82: =+A77+7 -> 45394 | B82: 20240412 | C82: 5123.41 | D82: 2759.64 | E82: 4955.01 | F82: 4353.66 | G82: 53195703 | H82: 7788.08 | I82: 3554.82 | J82: 3850.04 | K82: 125946.09 | L82: 809.86 | M82: 21899.99 | N82: 33261.4 | O82: 3019.47 | P82: 2829.89 | Q82: 1558.96 | R82: 2646.56 | S82: 9903.21 | T82: 8010.83 | U82: 7057.36 | V82: 1400.61 | W82: 16721.69 | X82: 67289.07 | Y82: 74244.9 | Z82: #N/A | AA82: 9891.51 | AB82: 33764.15 | AC82: 1724.86 | AD82: 1551.04 | AE82: 56565.92 | AF82: 1203.57 | AG82: 4538.7 | AH82: 102314.56 | AI82: 1606.79 | AJ82: 6659.39 | AK82: 82864.67 | AL82: 6337.43 | AM82: 16882.42 | AN82: 3456.24 | AO82: 3216.91 | AP82: 316.19 | AQ82: 75311.76 | AR82: 2681.82 | AS82: 1057.78 | AT82: 947.32 | AU82: 20736.57 | AV82: 1783.4 | AW82: #N/A | AX82: #N/A | AY82: 61239.2 | AZ82: 578.23
A83: =+A78+7 -> 45397 | B83: 20240415 | C83: 5061.82 | D83: 2753.2 | E83: 4984.48 | F83: 4338.9 | G83: 51191324 | H83: 7752.53 | I83: 3539.24 | J83: 3853.74 | K83: 125333.89 | L83: 810.58 | M83: 21740.2 | N83: 32864.56 | O83: 3057.38 | P83: 2831.55 | Q83: 1557.56 | R83: 2648.05 | S83: 9839.12 | T83: 8045.11 | U83: 7095.25 | V83: 1390.69 | W83: 16600.46 | X83: 67407.86 | Y83: 73399.78 | Z83: #N/A | AA83: 9898.35 | AB83: 33954.28 | AC83: 1709.9 | AD83: 1542.53 | AE83: 55984 | AF83: 1203.14 | AG83: 4533.17 | AH83: 101777.12 | AI83: 1586.94 | AJ83: 6562.43 | AK83: 83173.12 | AL83: 6268.88 | AM83: 16908.2 | AN83: 3472.19 | AO83: 3183.61 | AP83: 316.19 | AQ83: 74518.63 | AR83: 2670.43 | AS83: 1058.28 | AT83: 951.58 | AU83: 20449.77 | AV83: 1782.37 | AW83: #N/A | AX83: 9679.8 | AY83: 64994.51 | AZ83: 572.46
A84: =+A79+7 -> 45398 | B84: 20240416 | C84: 5051.41 | D84: 2697.11 | E84: 4916.99 | F84: 4260.41 | G84: 51374486 | H84: 7612.49 | I84: 3497.4 | J84: 3796.92 | K84: 124388.62 | L84: 805.73 | M84: 21642.87 | N84: 32624.79 | O84: 3007.07 | P84: 2813.06 | Q84: 1546.99 | R84: 2613.41 | S84: 9742.59 | T84: 7932.61 | U84: 6986.45 | V84: 1357.3 | W84: 16248.97 | X84: 65428.99 | Y84: 72943.68 | Z84: 7164.81 | AA84: 9778.52 | AB84: 33393.85 | AC84: 1698.46 | AD84: 1535 | AE84: 55797.25 | AF84: 1192.59 | AG84: 4490.59 | AH84: 99808.34 | AI84: 1567.74 | AJ84: 6404.97 | AK84: 81281.34 | AL84: 6224.16 | AM84: 16811.2 | AN84: 3462.94 | AO84: 3144.76 | AP84: 316.76 | AQ84: 72999.6 | AR84: 2609.63 | AS84: 1042.25 | AT84: 937.55 | AU84: 19901.96 | AV84: 1779.39 | AW84: #N/A | AX84: 9548.09 | AY84: 65445.7 | AZ84: 567.75
A85: =+A80+7 -> 45399 | B85: 20240417 | C85: 5022.21 | D85: 2663.15 | E85: 4914.13 | F85: 4273.02 | G85: 50151237 | H85: 7605.59 | I85: 3507.97 | J85: 3794.57 | K85: 124171.15 | L85: 805.34 | M85: 21656.05 | N85: 32727.97 | O85: 3071.38 | P85: #N/A | Q85: 1547.54 | R85: 2615.93 | S85: 9735.18 | T85: 7981.51 | U85: 6987.94 | V85: 1365.48 | W85: 16251.84 | X85: 66115.42 | Y85: #N/A | Z85: 7130.84 | AA85: 9828.81 | AB85: 33632.71 | AC85: 1703.13 | AD85: 1540.42 | AE85: 55415.69 | AF85: 1172.51 | AG85: 4517.42 | AH85: 99908.89 | AI85: 1571.07 | AJ85: 6450.04 | AK85: 82393.93 | AL85: 6234.41 | AM85: 16919.27 | AN85: 3454.07 | AO85: 3154.69 | AP85: 316.76 | AQ85: 72995.18 | AR85: 2584.18 | AS85: 1053.46 | AT85: 940.62 | AU85: 20213.33 | AV85: 1776.26 | AW85: 1366.94 | AX85: 9530.47 | AY85: 66016.25 | AZ85: 565.6
A86: =+A81+7 -> 45400 | B86: 20240418 | C86: 5011.12 | D86: 2677.45 | E86: 4936.57 | F86: 4290.02 | G86: 50123441 | H86: 7642.11 | I86: 3538.38 | J86: 3826.58 | K86: 124196.18 | L86: 807.23 | M86: 21708.44 | N86: 32693.15 | O86: 3074.22 | P86: 2803.31 | Q86: 1550.34 | R86: 2595.73 | S86: 9768.28 | T86: 8023.26 | U86: 7014.43 | V86: 1381.07 | W86: 16385.87 | X86: 65674.41 | Y86: 72488.99 | Z86: 7166.81 | AA86: 9941.69 | AB86: 33881.5 | AC86: 1698.26 | AD86: 1544.76 | AE86: 55739.43 | AF86: 1171 | AG86: 4502.46 | AH86: 99845.91 | AI86: 1565.28 | AJ86: 6523.19 | AK86: 83189.46 | AL86: 6327.7 | AM86: 16883.08 | AN86: 3455.82 | AO86: 3187.66 | AP86: 317.01 | AQ86: 73271.43 | AR86: 2634.7 | AS86: 1067.15 | AT86: 942.13 | AU86: 20301.2 | AV86: 1776.19 | AW86: 1361.02 | AX86: 9524.59 | AY86: 64513.2 | AZ86: 565.99
A87: =+A82+7 -> 45401 | B87: 20240419 | C87: 4967.23 | D87: 2626.32 | E87: 4918.09 | F87: 4296.41 | G87: 50683210 | H87: 7567.28 | I87: 3537 | J87: 3827.75 | K87: 125124.3 | L87: 805.96 | M87: 21807.37 | N87: 32290.1 | O87: 3065.26 | P87: 2799.37 | Q87: 1550.61 | R87: 2607.91 | S87: 9837.57 | T87: 8022.41 | U87: 6973.19 | V87: 1392.62 | W87: 16224.14 | X87: 65045.06 | Y87: 73088.33 | Z87: 7087.32 | AA87: 9931 | AB87: 33922.16 | AC87: 1689.31 | AD87: 1547.57 | AE87: 55862.85 | AF87: 1162.27 | AG87: 4487.31 | AH87: 99539.75 | AI87: 1563.68 | AJ87: 6443 | AK87: 83206.02 | AL87: 6295.12 | AM87: 16838.36 | AN87: 3470.88 | AO87: 3176.51 | AP87: 317.01 | AQ87: 73363.56 | AR87: 2591.86 | AS87: 1063.01 | AT87: 936.75 | AU87: 19527.12 | AV87: 1776.25 | AW87: 1332.08 | AX87: 9693.46 | AY87: #N/A | AZ87: 561.5
A88: =+A83+7 -> 45404 | B88: 20240422 | C88: 5010.6 | D88: 2662.46 | E88: 4936.85 | F88: 4362.6 | G88: 53941162 | H88: 7649.16 | I88: 3554.19 | J88: 3863.26 | K88: 125573.16 | L88: 806.46 | M88: 21871.96 | N88: 32328.81 | O88: 3044.6 | P88: 2803.42 | Q88: 1557.17 | R88: 2635.67 | S88: 9942.26 | T88: 8040.36 | U88: 7021.71 | V88: 1420.4 | W88: 16511.69 | X88: 65125.52 | Y88: 73648.62 | Z88: 7073.82 | AA88: 9962.42 | AB88: 33724.82 | AC88: 1666.8 | AD88: 1559.59 | AE88: 56551.9 | AF88: 1170.06 | AG88: 4508.84 | AH88: 99665.05 | AI88: 1561.41 | AJ88: 6444.08 | AK88: 84463.9 | AL88: 6515.47 | AM88: 16879.46 | AN88: 3479.17 | AO88: 3225.17 | AP88: 317.01 | AQ88: 73551.12 | AR88: 2629.44 | AS88: 1079.45 | AT88: 939.37 | AU88: 19411.22 | AV88: 1775.3 | AW88: 1349.52 | AX88: 9645.02 | AY88: 63631.22 | AZ88: 565.99
A89: =+A84+7 -> 45405 | B89: 20240423 | C89: 5070.55 | D89: 2666.23 | E89: 5008.17 | F89: 4378.75 | G89: 53016339 | H89: 7683.51 | I89: 3580.87 | J89: 3890.71 | K89: 125148.07 | L89: 805.04 | M89: 22011.72 | N89: 32758.39 | O89: 3021.98 | P89: 2787.06 | Q89: 1564.82 | R89: 2674.13 | S89: 9978.25 | T89: 8105.78 | U89: 7128.93 | V89: 1447.82 | W89: 16828.93 | X89: 65939.26 | Y89: 73738.45 | Z89: 7110.81 | AA89: 10066.68 | AB89: 34363.75 | AC89: 1676.65 | AD89: 1561.64 | AE89: 56633.75 | AF89: 1182.4 | AG89: 4490 | AH89: 99311.54 | AI89: 1561.8 | AJ89: 6506.8 | AK89: 84839.47 | AL89: 6592.89 | AM89: 16864.29 | AN89: 3439.42 | AO89: 3272.72 | AP89: 314.14 | AQ89: 74010.83 | AR89: 2623.02 | AS89: 1097.35 | AT89: 953.69 | AU89: 19599.28 | AV89: 1778.46 | AW89: 1357.46 | AX89: #N/A | AY89: 62278.9 | AZ89: 572.54
A90: =+A85+7 -> 45406 | B90: 20240424 | C90: 5071.63 | D90: 2710.73 | E90: 4989.88 | F90: 4374.06 | G90: 51244309 | H90: 7683 | I90: 3580.28 | J90: 3883.83 | K90: 124740.69 | L90: 816.99 | M90: 21873.72 | N90: 32280.14 | O90: 3044.82 | P90: 2785.53 | Q90: 1563.57 | R90: 2636.87 | S90: 9925.43 | T90: 8091.86 | U90: 7109.69 | V90: 1448.7 | W90: 17201.27 | X90: 66376.55 | Y90: 73852.94 | Z90: 7174.53 | AA90: 9963.97 | AB90: 34271.12 | AC90: 1680.83 | AD90: 1571.48 | AE90: 56463.99 | AF90: 1182.44 | AG90: 4544.45 | AH90: 98121.3 | AI90: 1575.3 | AJ90: 6572.75 | AK90: 84201.22 | AL90: 6529.93 | AM90: 16947.98 | AN90: 3428.93 | AO90: 3293.13 | AP90: 314.14 | AQ90: 74513.93 | AR90: 2675.75 | AS90: 1093.47 | AT90: 949.57 | AU90: 20131.74 | AV90: 1781.81 | AW90: 1361.1 | AX90: 9722.09 | AY90: 62348.7 | AZ90: 573.56
A91: =+A86+7 -> 45407 | B91: 20240425 | C91: 5048.42 | D91: 2663.53 | E91: 4939.01 | F91: 4387.94 | G91: 52827207 | H91: #N/A | I91: 3562.39 | J91: 3857.94 | K91: 124645.58 | L91: 815.26 | M91: 21885.38 | N91: 32033.74 | O91: 3052.9 | P91: 2805.17 | Q91: 1558.62 | R91: 2594.12 | S91: 9726.3 | T91: 8016.65 | U91: 7042.32 | V91: 1435.19 | W91: 17284.54 | X91: 66129.26 | Y91: 74339.44 | Z91: 7155.29 | AA91: 9915.57 | AB91: 33939.75 | AC91: 1681.37 | AD91: 1569.25 | AE91: 57071.78 | AF91: 1176.94 | AG91: #N/A | AH91: 98169.3 | AI91: 1582.95 | AJ91: 6574.88 | AK91: 83535.02 | AL91: 6542.23 | AM91: 16971.24 | AN91: 3439.76 | AO91: 3287.75 | AP91: 319.56 | AQ91: 74329.37 | AR91: 2628.62 | AS91: 1089.15 | AT91: 937.06 | AU91: 19857.42 | AV91: 1784.71 | AW91: 1364.27 | AX91: 9716.77 | AY91: 62905.39 | AZ91: 570.54
A92: =+A87+7 -> 45408 | B92: 20240426 | C92: 5099.96 | D92: 2686.48 | E92: 5006.85 | F92: 4423.59 | G92: 54321526 | H92: 7575.91 | I92: 3548.29 | J92: 3874.87 | K92: 126526.27 | L92: 818.59 | M92: 21969.24 | N92: 32397.72 | O92: 3088.64 | P92: 2814.85 | Q92: 1543.38 | R92: 2652.99 | S92: 9834.91 | T92: 8088.24 | U92: 7110.8 | V92: 1454.98 | W92: 17651.15 | X92: 67039.3 | Y92: 73730.16 | Z92: 7036.08 | AA92: 9967.45 | AB92: 34249.77 | AC92: 1688.32 | AD92: 1575.16 | AE92: 57833.85 | AF92: 1195.07 | AG92: 4490.69 | AH92: 98152.91 | AI92: 1591.22 | AJ92: 6628.75 | AK92: 84443.72 | AL92: 6612.51 | AM92: 16992.22 | AN92: 3449.77 | AO92: 3280.1 | AP92: 316.11 | AQ92: 75370.99 | AR92: 2656.33 | AS92: 1106.91 | AT92: 951.83 | AU92: 20120.51 | AV92: #N/A | AW92: 1359.94 | AX92: 9915.62 | AY92: 62436.86 | AZ92: 575.4
A93: =+A88+7 -> 45411 | B93: 20240429 | C93: 5116.17 | D93: #N/A | E93: 4981.09 | F93: 4435.18 | G93: 55444476 | H93: 7637.38 | I93: 3564.38 | J93: 3886.76 | K93: 127351.79 | L93: 814.25 | M93: 22011.62 | N93: 33140.19 | O93: 3113.04 | P93: 2800.93 | Q93: 1550.68 | R93: 2651.64 | S93: 9892.24 | T93: 8065.15 | U93: 7090.75 | V93: 1455.48 | W93: 17746.91 | X93: 67885.92 | Y93: 74671.28 | Z93: 7155.78 | AA93: 9954 | AB93: 34296.31 | AC93: 1685.32 | AD93: 1582.66 | AE93: 57827.86 | AF93: 1194.13 | AG93: 4532.97 | AH93: 97879.94 | AI93: 1591.26 | AJ93: 6769.64 | AK93: 85375.3 | AL93: 6680.62 | AM93: 17120.96 | AN93: 3478.08 | AO93: 3282.05 | AP93: 316.11 | AQ93: 76456.15 | AR93: 2687.44 | AS93: 1102.16 | AT93: 959.18 | AU93: 20495.52 | AV93: 1784.7 | AW93: 1361.97 | AX93: 10082.77 | AY93: 62033.81 | AZ93: 578
A94: =+A89+7 -> 45412 | B94: 20240430 | C94: 5035.69 | D94: 2743.17 | E94: 4921.22 | F94: 4430.25 | G94: 56303862 | H94: 7664.07 | I94: 3560.42 | J94: 3883.26 | K94: 125924.19 | L94: 813.54 | M94: 21714.54 | N94: 32969.77 | O94: 3104.82 | P94: 2806.29 | Q94: 1548.85 | R94: 2681.79 | S94: 9855.51 | T94: 7984.93 | U94: 7017.9 | V94: 1448.48 | W94: 17763.03 | X94: 68142.02 | Y94: 74482.78 | Z94: 7234.2 | AA94: 9917.34 | AB94: 33746.66 | AC94: 1690.98 | AD94: 1575.97 | AE94: 56727.98 | AF94: 1187.21 | AG94: 4548.66 | AH94: 98225.63 | AI94: 1594.44 | AJ94: 6700.49 | AK94: 84569.65 | AL94: 6615.56 | AM94: 17060.94 | AN94: 3469.83 | AO94: 3292.69 | AP94: 309.29 | AQ94: 76076.17 | AR94: 2692.06 | AS94: 1076.93 | AT94: 957.95 | AU94: 20396.6 | AV94: 1784.92 | AW94: 1367.95 | AX94: 10045.74 | AY94: 62713.43 | AZ94: 571.42
A95: =+A90+7 -> 45413 | B95: 20240501 | C95: 5018.39 | D95: 2729.4 | E95: 4921.22 | F95: 4418.6 | G95: #N/A | H95: 7569.95 | I95: #N/A | J95: #N/A | K95: #N/A | L95: #N/A | M95: 21728.55 | N95: #N/A | O95: #N/A | P95: #N/A | Q95: #N/A | R95: 2666.39 | S95: #N/A | T95: #N/A | U95: #N/A | V95: #N/A | W95: #N/A | X95: #N/A | Y95: #N/A | Z95: #N/A | AA95: #N/A | AB95: #N/A | AC95: #N/A | AD95: #N/A | AE95: #N/A | AF95: #N/A | AG95: 4514.46 | AH95: #N/A | AI95: #N/A | AJ95: #N/A | AK95: #N/A | AL95: #N/A | AM95: #N/A | AN95: #N/A | AO95: #N/A | AP95: #N/A | AQ95: #N/A | AR95: #N/A | AS95: #N/A | AT95: #N/A | AU95: #N/A | AV95: #N/A | AW95: #N/A | AX95: #N/A | AY95: #N/A | AZ95: 569.75
A96: =+A91+7 -> 45414 | B96: 20240502 | C96: 5064.2 | D96: 2728.53 | E96: 4890.61 | F96: 4446.15 | G96: 58164282 | H96: 7586.97 | I96: 3590.35 | J96: 3893.2 | K96: 127122.25 | L96: 813.65 | M96: 21823.22 | N96: 32924.59 | O96: #N/A | P96: 2812.76 | Q96: 1555.44 | R96: 2616.36 | S96: 9907.12 | T96: 7914.65 | U96: 7002 | V96: 1452.24 | W96: 18207.13 | X96: 68123.99 | Y96: 74611.11 | Z96: 7117.43 | AA96: 10069.34 | AB96: 33736.4 | AC96: 1659.45 | AD96: 1580.3 | AE96: 56677.05 | AF96: 1185.31 | AG96: 4516.92 | AH96: 98762.78 | AI96: 1589.31 | AJ96: 6646.55 | AK96: 84393.73 | AL96: 6665.17 | AM96: 17220.62 | AN96: 3442.83 | AO96: 3296.89 | AP96: 309.79 | AQ96: 76046.85 | AR96: 2683.65 | AS96: 1076.95 | AT96: 947.3 | AU96: 20222.44 | AV96: 1784.8 | AW96: 1363.25 | AX96: 10208.65 | AY96: 64350.48 | AZ96: 574.63
A97: =+A92+7 -> 45415 | B97: 20240503 | C97: 5127.79 | D97: #N/A | E97: 4921.48 | F97: 4469.09 | G97: 61477181 | H97: 7628.97 | I97: 3590.96 | J97: 3913.37 | K97: 128508.67 | L97: #N/A | M97: 21947.41 | N97: 33229.93 | O97: #N/A | P97: 2814.05 | Q97: 1520.22 | R97: 2581.24 | S97: 9966.99 | T97: 7957.57 | U97: 7043.12 | V97: #N/A | W97: 18475.92 | X97: 68002.24 | Y97: 73878.15 | Z97: 7134.72 | AA97: 10082.22 | AB97: 33629.21 | AC97: 1647.8 | AD97: 1589.59 | AE97: 57135.26 | AF97: 1198.83 | AG97: 4541.28 | AH97: 99587.25 | AI97: 1594.34 | AJ97: 6615.55 | AK97: #N/A | AL97: 6648.67 | AM97: #N/A | AN97: 3441.77 | AO97: 3292.93 | AP97: 309.79 | AQ97: 76428.33 | AR97: 2676.63 | AS97: 1075.99 | AT97: 954.5 | AU97: 20330.32 | AV97: 1784.5 | AW97: 1369.92 | AX97: 10276.88 | AY97: 64629.6 | AZ97: 581.09
A98: =+A93+7 -> 45418 | B98: 20240506 | C98: 5180.74 | D98: #N/A | E98: 4956.96 | F98: #N/A | G98: 63502378 | H98: 7682.37 | I98: 3614.61 | J98: 3929 | K98: 128465.69 | L98: #N/A | M98: 22259.47 | N98: 32972.16 | O98: 3140.72 | P98: 2815.98 | Q98: 1529.77 | R98: 2587.28 | S98: 10079.68 | T98: 7996.64 | U98: 7097.89 | V98: #N/A | W98: 18578.3 | X98: 68568.49 | Y98: 73895.54 | Z98: 7135.89 | AA98: #N/A | AB98: 33986.9 | AC98: 1656.77 | AD98: 1597.39 | AE98: 57282.95 | AF98: 1205.49 | AG98: 4496.66 | AH98: 98703.68 | AI98: 1617.07 | AJ98: 6652.49 | AK98: 86575.3 | AL98: 6652.71 | AM98: #N/A | AN98: 3436.05 | AO98: 3303.19 | AP98: 309.79 | AQ98: 76776.45 | AR98: #N/A | AS98: 1081.96 | AT98: 962.29 | AU98: 20523.31 | AV98: 1784.22 | AW98: #N/A | AX98: 10267.09 | AY98: 63369.31 | AZ98: 585.89
A99: =+A94+7 -> 45419 | B99: 20240507 | C99: 5187.7 | D99: 2746.22 | E99: 5016.1 | F99: 4522.99 | G99: 62318174 | H99: 7793.32 | I99: 3645.84 | J99: 3996.52 | K99: 129210.48 | L99: 823.08 | M99: 22290.62 | N99: 33442.11 | O99: 3147.74 | P99: 2810.54 | Q99: 1548.65 | R99: 2657.04 | S99: 10110.9 | T99: 8075.68 | U99: 7195.37 | V99: #N/A | W99: 18479.37 | X99: 68882.55 | Y99: 73511.85 | Z99: 7123.61 | AA99: 10109.05 | AB99: 34242.49 | AC99: 1645.36 | AD99: 1605.68 | AE99: 57108.32 | AF99: 1215.48 | AG99: 4489.05 | AH99: 98228.5 | AI99: 1619.44 | AJ99: 6618.58 | AK99: 86483.54 | AL99: 6716.1 | AM99: 17244.57 | AN99: 3427.61 | AO99: 3300.04 | AP99: 309.79 | AQ99: 76929.48 | AR99: 2734.36 | AS99: 1099.39 | AT99: 974.31 | AU99: 20653.53 | AV99: #N/A | AW99: 1376.37 | AX99: 10336.5 | AY99: 63838.69 | AZ99: 587.5
A100: =+A95+7 -> 45420 | B100: 20240508 | C100: 5187.67 | D100: 2706.43 | E100: 5038.17 | F100: 4544.24 | G100: 61844957 | H100: 7804.49 | I100: 3634.69 | J100: 4015.67 | K100: 129480.89 | L100: 829.14 | M100: 22259.16 | N100: 33624.23 | O100: 3128.48 | P100: 2799.32 | Q100: #N/A | R100: 2662.96 | S100: 10109.49 | T100: 8131.41 | U100: 7222.05 | V100: 1473.53 | W100: 18313.86 | X100: 68900.51 | Y100: 73466.39 | Z100: 7088.8 | AA100: 10163.24 | AB100: 34151.41 | AC100: 1659.01 | AD100: 1604.75 | AE100: 57081 | AF100: 1214.55 | AG100: 4482.24 | AH100: 98223.97 | AI100: 1624.6 | AJ100: 6659.18 | AK100: 86888.67 | AL100: 6726.2 | AM100: 17161.64 | AN100: 3432.54 | AO100: 3264.53 | AP100: #N/A | AQ100: 77177.43 | AR100: 2745.05 | AS100: 1106.61 | AT100: 974.44 | AU100: 20700.51 | AV100: 1784.62 | AW100: 1373.33 | AX100: 10247.75 | AY100: 64127.9 | AZ100: 586.27
...

Sheet GMW
A1: Location | B1: Indicator | C1: Scenario | D1: Units | E1: Scale | F1: Measurement | G1: 1973 Q1 | H1: 1973 Q2 | I1: 1973 Q3 | J1: 1973 Q4 | K1: 1974 Q1 | L1: 1974 Q2 | M1: 1974 Q3 | N1: 1974 Q4 | O1: 1975 Q1 | P1: 1975 Q2 | Q1: 1975 Q3 | R1: 1975 Q4 | S1: 1976 Q1 | T1: 1976 Q2 | U1: 1976 Q3 | V1: 1976 Q4 | W1: 1977 Q1 | X1: 1977 Q2 | Y1: 1977 Q3 | Z1: 1977 Q4 | AA1: 1978 Q1 | AB1: 1978 Q2 | AC1: 1978 Q3 | AD1: 1978 Q4 | AE1: 1979 Q1 | AF1: 1979 Q2 | AG1: 1979 Q3 | AH1: 1979 Q4 | AI1: 1980 Q1 | AJ1: 1980 Q2 | AK1: 1980 Q3 | AL1: 1980 Q4 | AM1: 1981 Q1 | AN1: 1981 Q2 | AO1: 1981 Q3 | AP1: 1981 Q4 | AQ1: 1982 Q1 | AR1: 1982 Q2 | AS1: 1982 Q3 | AT1: 1982 Q4 | AU1: 1983 Q1 | AV1: 1983 Q2 | AW1: 1983 Q3 | AX1: 1983 Q4 | AY1: 1984 Q1 | AZ1: 1984 Q2 | BA1: 1984 Q3 | BB1: 1984 Q4 | BC1: 1985 Q1 | BD1: 1985 Q2 | BE1: 1985 Q3 | BF1: 1985 Q4 | BG1: 1986 Q1 | BH1: 1986 Q2 | BI1: 1986 Q3 | BJ1: 1986 Q4 | BK1: 1987 Q1 | BL1: 1987 Q2 | BM1: 1987 Q3 | BN1: 1987 Q4 | BO1: 1988 Q1 | BP1: 1988 Q2 | BQ1: 1988 Q3 | BR1: 1988 Q4 | BS1: 1989 Q1 | BT1: 1989 Q2 | BU1: 1989 Q3 | BV1: 1989 Q4 | BW1: 1990 Q1 | BX1: 1990 Q2 | BY1: 1990 Q3 | BZ1: 1990 Q4 | CA1: 1991 Q1 | CB1: 1991 Q2 | CC1: 1991 Q3 | CD1: 1991 Q4 | CE1: 1992 Q1 | CF1: 1992 Q2 | CG1: 1992 Q3 | CH1: 1992 Q4 | CI1: 1993 Q1 | CJ1: 1993 Q2 | CK1: 1993 Q3 | CL1: 1993 Q4 | CM1: 1994 Q1 | CN1: 1994 Q2 | CO1: 1994 Q3 | CP1: 1994 Q4 | CQ1: 1995 Q1 | CR1: 1995 Q2 | CS1: 1995 Q3 | CT1: 1995 Q4 | CU1: 1996 Q1 | CV1: 1996 Q2 | CW1: 1996 Q3 | CX1: 1996 Q4 | CY1: 1997 Q1 | CZ1: 1997 Q2 | DA1: 1997 Q3 | DB1: 1997 Q4 | DC1: 1998 Q1 | DD1: 1998 Q2 | DE1: 1998 Q3 | DF1: 1998 Q4 | DG1: 1999 Q1 | DH1: 1999 Q2 | DI1: 1999 Q3 | DJ1: 1999 Q4 | DK1: 2000 Q1 | DL1: 2000 Q2 | DM1: 2000 Q3 | DN1: 2000 Q4 | DO1: 2001 Q1 | DP1: 2001 Q2 | DQ1: 2001 Q3 | DR1: 2001 Q4 | DS1: 2002 Q1 | DT1: 2002 Q2 | DU1: 2002 Q3 | DV1: 2002 Q4 | DW1: 2003 Q1 | DX1: 2003 Q2 | DY1: 2003 Q3 | DZ1: 2003 Q4 | EA1: 2004 Q1 | EB1: 2004 Q2 | EC1: 2004 Q3 | ED1: 2004 Q4 | EE1: 2005 Q1 | EF1: 2005 Q2 | EG1: 2005 Q3 | EH1: 2005 Q4 | EI1: 2006 Q1 | EJ1: 2006 Q2 | EK1: 2006 Q3 | EL1: 2006 Q4 | EM1: 2007 Q1 | EN1: 2007 Q2 | EO1: 2007 Q3 | EP1: 2007 Q4 | EQ1: 2008 Q1 | ER1: 2008 Q2 | ES1: 2008 Q3 | ET1: 2008 Q4 | EU1: 2009 Q1 | EV1: 2009 Q2 | EW1: 2009 Q3 | EX1: 2009 Q4 | EY1: 2010 Q1 | EZ1: 2010 Q2 | FA1: 2010 Q3 | FB1: 2010 Q4 | FC1: 2011 Q1 | FD1: 2011 Q2 | FE1: 2011 Q3 | FF1: 2011 Q4 | FG1: 2012 Q1 | FH1: 2012 Q2 | FI1: 2012 Q3 | FJ1: 2012 Q4 | FK1: 2013 Q1 | FL1: 2013 Q2 | FM1: 2013 Q3 | FN1: 2013 Q4 | FO1: 2014 Q1 | FP1: 2014 Q2 | FQ1: 2014 Q3 | FR1: 2014 Q4 | FS1: 2015 Q1 | FT1: 2015 Q2 | FU1: 2015 Q3 | FV1: 2015 Q4 | FW1: 2016 Q1 | FX1: 2016 Q2 | FY1: 2016 Q3 | FZ1: 2016 Q4 | GA1: 2017 Q1 | GB1: 2017 Q2 | GC1: 2017 Q3 | GD1: 2017 Q4 | GE1: 2018 Q1 | GF1: 2018 Q2 | GG1: 2018 Q3 | GH1: 2018 Q4 | GI1: 2019 Q1 | GJ1: 2019 Q2 | GK1: 2019 Q3 | GL1: 2019 Q4 | GM1: 2020 Q1 | GN1: 2020 Q2 | GO1: 2020 Q3 | GP1: 2020 Q4 | GQ1: 2021 Q1 | GR1: 2021 Q2 | GS1: 2021 Q3 | GT1: 2021 Q4 | GU1: 2022 Q1 | GV1: 2022 Q2 | GW1: 2022 Q3 | GX1: 2022 Q4 | GY1: 2023 Q1 | GZ1: 2023 Q2 | HA1: 2023 Q3 | HB1: 2023 Q4 | HC1: 2024 Q1 | HD1: 2024 Q2 | HE1: 2024 Q3 | HF1: 2024 Q4 | HG1: 2025 Q1 | HH1: 2025 Q2 | HI1: 2025 Q3 | HJ1: 2025 Q4 | HK1: 2026 Q1 | HL1: 2026 Q2 | HM1: 2026 Q3 | HN1: 2026 Q4 | HO1: 2027 Q1 | HP1: 2027 Q2 | HQ1: 2027 Q3 | HR1: 2027 Q4 | HS1: 2028 Q1 | HT1: 2028 Q2 | HU1: 2028 Q3 | HV1: 2028 Q4 | HW1: 2029 Q1 | HX1: 2029 Q2 | HY1: 2029 Q3 | HZ1: 2029 Q4 | IA1: 2030 Q1 | IB1: 2030 Q2 | IC1: 2030 Q3 | ID1: 2030 Q4 | IE1: 2031 Q1 | IF1: 2031 Q2 | IG1: 2031 Q3 | IH1: 2031 Q4 | II1: 2032 Q1 | IJ1: 2032 Q2 | IK1: 2032 Q3 | IL1: 2032 Q4 | IM1: 2033 Q1 | IN1: 2033 Q2 | IO1: 2033 Q3 | IP1: 2033 Q4 | IQ1: 2034 Q1 | IR1: 2034 Q2 | IS1: 2034 Q3 | IT1: 2034 Q4 | IU1: 2035 Q1 | IV1: 2035 Q2 | IW1: 2035 Q3 | IX1: 2035 Q4 | IY1: 2036 Q1 | IZ1: 2036 Q2 | JA1: 2036 Q3 | JB1: 2036 Q4 | JC1: 2037 Q1 | JD1: 2037 Q2 | JE1: 2037 Q3 | JF1: 2037 Q4 | JG1: 2038 Q1 | JH1: 2038 Q2 | JI1: 2038 Q3 | JJ1: 2038 Q4 | JK1: 2039 Q1 | JL1: 2039 Q2 | JM1: 2039 Q3 | JN1: 2039 Q4 | JO1: 2040 Q1 | JP1: 2040 Q2 | JQ1: 2040 Q3 | JR1: 2040 Q4 | JS1: 2041 Q1 | JT1: 2041 Q2 | JU1: 2041 Q3 | JV1: 2041 Q4 | JW1: 2042 Q1 | JX1: 2042 Q2 | JY1: 2042 Q3 | JZ1: 2042 Q4 | KA1: 2043 Q1 | KB1: 2043 Q2 | KC1: 2043 Q3 | KD1: 2043 Q4 | KE1: 2044 Q1 | KF1: 2044 Q2 | KG1: 2044 Q3 | KH1: 2044 Q4 | KI1: 2045 Q1 | KJ1: 2045 Q2 | KK1: 2045 Q3 | KL1: 2045 Q4 | KM1: 2046 Q1 | KN1: 2046 Q2 | KO1: 2046 Q3 | KP1: 2046 Q4 | KQ1: 2047 Q1 | KR1: 2047 Q2 | KS1: 2047 Q3 | KT1: 2047 Q4 | KU1: 2048 Q1 | KV1: 2048 Q2 | KW1: 2048 Q3 | KX1: 2048 Q4 | KY1: 2049 Q1 | KZ1: 2049 Q2 | LA1: 2049 Q3 | LB1: 2049 Q4 | LC1: 2050 Q1 | LD1: 2050 Q2 | LE1: 2050 Q3 | LF1: 2050 Q4 | LG1: Source | LH1: Seasonally adjusted | LI1: Base year price | LJ1: Base year index | LK1: Historical end year | LL1: Historical end quarter | LM1: Date of last update | LN1: Source details | LO1: Additional source details | LP1: Location code | LQ1: Indicator code | LR1: Databank code
A2: United Kingdom | B2: GDP, real, LCU | C2: AUG006N | D2: Pound | E2: Millions | F2: Level | G2: 223780 | H2: 224213 | I2: 222122 | J2: 221266 | K2: 215122 | L2: 218215 | M2: 219517 | N2: 216301 | O2: 216390 | P2: 212882 | Q2: 212192 | R2: 214585 | S2: 218180 | T2: 217883 | U2: 220587 | V2: 225228 | W2: 225362 | X2: 223815 | Y2: 225295 | Z2: 229115 | AA2: 231258 | AB2: 233910 | AC2: 237107 | AD2: 239186 | AE2: 238472 | AF2: 248867 | AG2: 243369 | AH2: 245858 | AI2: 243513 | AJ2: 238722 | AK2: 238432 | AL2: 235866 | AM2: 235712 | AN2: 236272 | AO2: 238846 | AP2: 239131 | AQ2: 239578 | AR2: 242095 | AS2: 242639 | AT2: 244317 | AU2: 249032 | AV2: 250761 | AW2: 253655 | AX2: 255533 | AY2: 257683 | AZ2: 255100 | BA2: 256975 | BB2: 261627 | BC2: 264127 | BD2: 269787 | BE2: 269737 | BF2: 269896 | BG2: 272720 | BH2: 275136 | BI2: 276863 | BJ2: 282193 | BK2: 284172 | BL2: 288385 | BM2: 295493 | BN2: 298855 | BO2: 303698 | BP2: 305281 | BQ2: 309097 | BR2: 311574 | BS2: 313083 | BT2: 315039 | BU2: 315554 | BV2: 315515 | BW2: 317117 | BX2: 319239 | BY2: 315744 | BZ2: 314148 | CA2: 312596 | CB2: 312235 | CC2: 311624 | CD2: 312006 | CE2: 311904 | CF2: 311418 | CG2: 312896 | CH2: 315307 | CI2: 316882 | CJ2: 318302 | CK2: 321218 | CL2: 323400 | CM2: 326585 | CN2: 329584 | CO2: 332911 | CP2: 334363 | CQ2: 336090 | CR2: 336789 | CS2: 340542 | CT2: 341602 | CU2: 343859 | CV2: 344979 | CW2: 348214 | CX2: 352958 | CY2: 358611 | CZ2: 362573 | DA2: 365942 | DB2: 371341 | DC2: 374037 | DD2: 376421 | DE2: 377650 | DF2: 380155 | DG2: 382789 | DH2: 384605 | DI2: 390758 | DJ2: 396357 | DK2: 401242 | DL2: 404196 | DM2: 406795 | DN2: 409411 | DO2: 413054 | DP2: 414878 | DQ2: 417085 | DR2: 418445 | DS2: 419534 | DT2: 421587 | DU2: 424425 | DV2: 427725 | DW2: 430832 | DX2: 434837 | DY2: 438710 | DZ2: 442172 | EA2: 443853 | EB2: 446443 | EC2: 448171 | ED2: 450464 | EE2: 453784 | EF2: 457557 | EG2: 461135 | EH2: 465451 | EI2: 467840 | EJ2: 469655 | EK2: 470918 | EL2: 473372 | EM2: 477823 | EN2: 481314 | EO2: 484544 | EP2: 487413 | EQ2: 489783 | ER2: 487386 | ES2: 479872 | ET2: 469694 | EU2: 460105 | EV2: 458599 | EW2: 458875 | EX2: 460238 | EY2: 464543 | EZ2: 469606 | FA2: 472199 | FB2: 472612 | FC2: 473819 | FD2: 474365 | FE2: 475813 | FF2: 476479 | FG2: 480632 | FH2: 479979 | FI2: 484579 | FJ2: 484039 | FK2: 485409 | FL2: 488930 | FM2: 493002 | FN2: 496466 | FO2: 500552 | FP2: 504939 | FQ2: 508741 | FR2: 512334 | FS2: 513850 | FT2: 516876 | FU2: 518915 | FV2: 521920 | FW2: 523813 | FX2: 526750 | FY2: 528712 | FZ2: 532082 | GA2: 536566 | GB2: 540020 | GC2: 543452 | GD2: 547377 | GE2: 547688 | GF2: 548600 | GG2: 550425 | GH2: 551128 | GI2: 555141 | GJ2: 556932 | GK2: 560987 | GL2: 560861 | GM2: 545597 | GN2: 434718 | GO2: 507643 | GP2: 514531 | GQ2: 509261 | GR2: 546579 | GS2: 555956 | GT2: 564407 | GU2: 567396 | GV2: 567889 | GW2: 567445 | GX2: 568034 | GY2: 569027 | GZ2: 569076 | HA2: 568397 | HB2: 566626 | HC2: 570694 | HD2: 573830.8 | HE2: 575345.5 | HF2: 577872.9 | HG2: 580628.8 | HH2: 583503.5 | HI2: 586275.3 | HJ2: 589088.9 | HK2: 591916.7 | HL2: 594522.1 | HM2: 596959.8 | HN2: 599377.1 | HO2: 601834.6 | HP2: 604302.1 | HQ2: 606749.8 | HR2: 609297.9 | HS2: 611857 | HT2: 614426.8 | HU2: 616915.3 | HV2: 619413.8 | HW2: 621860.4 | HX2: 624285.7 | HY2: 626689.2 | HZ2: 629070.6 | IA2: 631461.1 | IB2: 633829.1 | IC2: 636205.9 | ID2: 638591.7 | IE2: 640986.4 | IF2: 643422.2 | IG2: 645867.2 | IH2: 648289.2 | II2: 650687.8 | IJ2: 653127.9 | IK2: 655511.8 | IL2: 657904.4 | IM2: 660363.3 | IN2: 662726.2 | IO2: 665095.1 | IP2: 667467.1 | IQ2: 669898.4 | IR2: 672340.5 | IS2: 674779.1 | IT2: 677201.1 | IU2: 679755.9 | IV2: 682320.4 | IW2: 684894.4 | IX2: 687477.6 | IY2: 690132.4 | IZ2: 692799.7 | JA2: 695479.6 | JB2: 698171.9 | JC2: 700876.9 | JD2: 703594.3 | JE2: 706324.3 | JF2: 709067.1 | JG2: 711884.1 | JH2: 714714.9 | JI2: 717559.9 | JJ2: 720419.2 | JK2: 723292.7 | JL2: 726180.6 | JM2: 729083 | JN2: 731999.9 | JO2: 734931.4 | JP2: 737871.6 | JQ2: 740820.8 | JR2: 743778.7 | JS2: 746675.4 | JT2: 749579.9 | JU2: 752492.2 | JV2: 755412.4 | JW2: 758340.4 | JX2: 761276.3 | JY2: 764219.9 | JZ2: 767171.6 | KA2: 770130.9 | KB2: 773097.9 | KC2: 776072 | KD2: 779053.4 | KE2: 782041.8 | KF2: 785037.5 | KG2: 788040.4 | KH2: 791050.6 | KI2: 794067.9 | KJ2: 797092.6 | KK2: 800124.4 | KL2: 803163.7 | KM2: 806210.3 | KN2: 809264.3 | KO2: 812325.7 | KP2: 815394.7 | KQ2: 818471.3 | KR2: 821555.3 | KS2: 824647 | KT2: 827746.8 | KU2: 830854.1 | KV2: 833969.3 | KW2: 837092.1 | KX2: 840222.9 | KY2: 843361.3 | KZ2: 846507.7 | LA2: 849661.6 | LB2: 852823.4 | LC2: 855992.7 | LD2: 859169.9 | LE2: 862354.7 | LF2: 865547.4 | LG2: Office for National Statistics\Haver Analytics | LH2: TRUE | LI2: chained 2019 | LJ2: NA | LK2: 2024 | LL2: 1 | LM2: NA | LN2: ABMIQ@UK | LO2: U.K.: Real Gross Domestic Product (SA, Mil.Chn.2019.GBP) | LP2: GBR | LQ2: GDP | LR2: AUG006N.db
A3: United States | B3: GDP, real, LCU | C3: AUG006N | D3: US$ | E3: Billions | F3: Level | G3: 1514.625 | H3: 1531.125 | I3: 1523.075 | J3: 1537.525 | K3: 1524.325 | L3: 1527.95 | M3: 1513.5 | N3: 1507.625 | O3: 1489.25 | P3: 1499.9 | Q3: 1525.575 | R3: 1546.125 | S3: 1580.9 | T3: 1592.5 | U3: 1601.225 | V3: 1612.8 | W3: 1631.925 | X3: 1663.625 | Y3: 1693.625 | Z3: 1693.65 | AA3: 1699.075 | AB3: 1764.725 | AC3: 1782.475 | AD3: 1806.45 | AE3: 1809.675 | AF3: 1811.625 | AG3: 1825.075 | AH3: 1829.625 | AI3: 1835.4 | AJ3: 1797.575 | AK3: 1795.425 | AL3: 1828.925 | AM3: 1864.75 | AN3: 1850.925 | AO3: 1873.1 | AP3: 1852.7 | AQ3: 1823.9 | AR3: 1832.225 | AS3: 1825.225 | AT3: 1825.95 | AU3: 1850.025 | AV3: 1892.125 | AW3: 1929.925 | AX3: 1970.2 | AY3: 2008.7 | AZ3: 2043.425 | BA3: 2063.125 | BB3: 2080.05 | BC3: 2100.2 | BD3: 2118.7 | BE3: 2151.05 | BF3: 2167.05 | BG3: 2187.275 | BH3: 2197.125 | BI3: 2218.15 | BJ3: 2230.05 | BK3: 2246.6 | BL3: 2270.825 | BM3: 2290.5 | BN3: 2329.825 | BO3: 2341.875 | BP3: 2372.65 | BQ3: 2386.55 | BR3: 2418.35 | BS3: 2442.925 | BT3: 2461.575 | BU3: 2479.8 | BV3: 2484.7 | BW3: 2511.85 | BX3: 2520.975 | BY3: 2522.65 | BZ3: 2499.675 | CA3: 2487.975 | CB3: 2507.375 | CC3: 2520.05 | CD3: 2528.825 | CE3: 2559.1 | CF3: 2586.85 | CG3: 2612.425 | CH3: 2639.65 | CI3: 2644.075 | CJ3: 2659.45 | CK3: 2672.15 | CL3: 2708.5 | CM3: 2734.775 | CN3: 2771.85 | CO3: 2788.05 | CP3: 2819.975 | CQ3: 2830 | CR3: 2838.425 | CS3: 2862.575 | CT3: 2882.025 | CU3: 2903.6 | CV3: 2952.025 | CW3: 2978.525 | CX3: 3009.45 | CY3: 3028.875 | CZ3: 3079.3 | DA3: 3117.75 | DB3: 3144.375 | DC3: 3175.925 | DD3: 3205.325 | DE3: 3245.7 | DF3: 3297.925 | DG3: 3328.9 | DH3: 3356.675 | DI3: 3401.2 | DJ3: 3457 | DK3: 3469.525 | DL3: 3532.725 | DM3: 3536.325 | DN3: 3557.45 | DO3: 3545.775 | DP3: 3567.925 | DQ3: 3553.625 | DR3: 3563.4 | DS3: 3593.2 | DT3: 3615.2 | DU3: 3629.9 | DV3: 3634.4 | DW3: 3653.525 | DX3: 3685.9 | DY3: 3747.2 | DZ3: 3790.7 | EA3: 3812.175 | EB3: 3841.725 | EC3: 3878.15 | ED3: 3917.725 | EE3: 3961.175 | EF3: 3980.7 | EG3: 4011.9 | EH3: 4034.175 | EI3: 4088.45 | EJ3: 4099.05 | EK3: 4105.175 | EL3: 4140.475 | EM3: 4152.925 | EN3: 4178.325 | EO3: 4202.4 | EP3: 4228.8 | EQ3: 4210.75 | ER3: 4235.825 | ES3: 4213.575 | ET3: 4121.35 | EU3: 4074.575 | EV3: 4067.275 | EW3: 4081.575 | EX3: 4125.7 | EY3: 4145.675 | EZ3: 4185.8 | FA3: 4218.075 | FB3: 4240.225 | FC3: 4230.15 | FD3: 4258.775 | FE3: 4257.825 | FF3: 4305.65 | FG3: 4341.75 | FH3: 4361.125 | FI3: 4367.425 | FJ3: 4372.475 | FK3: 4415.6 | FL3: 4427.425 | FM3: 4465.125 | FN3: 4504.025 | FO3: 4488.5 | FP3: 4546.475 | FQ3: 4601.725 | FR3: 4625 | FS3: 4666.65 | FT3: 4695.55 | FU3: 4714.35 | FV3: 4723.05 | FW3: 4750.425 | FX3: 4765.675 | FY3: 4799.475 | FZ3: 4826.1 | GA3: 4849.575 | GB3: 4876.725 | GC3: 4915.2 | GD3: 4970.6 | GE3: 5011.025 | GF3: 5037.625 | GG3: 5069.05 | GH3: 5076.225 | GI3: 5103.8 | GJ3: 5146.125 | GK3: 5204.4 | GL3: 5237.775 | GM3: 5166.4 | GN3: 4758.7 | GO3: 5127.95 | GP3: 5181.025 | GQ3: 5247.625 | GR3: 5327.375 | GS3: 5370.775 | GT3: 5461.9 | GU3: 5434.725 | GV3: 5427.05 | GW3: 5462.775 | GX3: 5497.5 | GY3: 5528.075 | GZ3: 5556.35 | HA3: 5622.675 | HB3: 5669.825 | HC3: 5689.7 | HD3: 5729.675 | HE3: 5756.699 | HF3: 5781.011 | HG3: 5806.852 | HH3: 5834.955 | HI3: 5863.914 | HJ3: 5893.738 | HK3: 5923.786 | HL3: 5955.082 | HM3: 5986.981 | HN3: 6019.642 | HO3: 6051.814 | HP3: 6084.098 | HQ3: 6116.315 | HR3: 6148.19 | HS3: 6179.991 | HT3: 6211.651 | HU3: 6243.167 | HV3: 6274.459 | HW3: 6305.599 | HX3: 6337.058 | HY3: 6368.481 | HZ3: 6399.986 | IA3: 6431.443 | IB3: 6462.742 | IC3: 6493.677 | ID3: 6524.474 | IE3: 6555.241 | IF3: 6585.921 | IG3: 6616.62 | IH3: 6647.298 | II3: 6677.923 | IJ3: 6708.655 | IK3: 6739.465 | IL3: 6770.25 | IM3: 6801.008 | IN3: 6831.888 | IO3: 6862.892 | IP3: 6894.011 | IQ3: 6925.246 | IR3: 6956.587 | IS3: 6988.037 | IT3: 7019.594 | IU3: 7051.259 | IV3: 7083.05 | IW3: 7114.966 | IX3: 7147.009 | IY3: 7179.114 | IZ3: 7211.344 | JA3: 7243.624 | JB3: 7275.974 | JC3: 7308.403 | JD3: 7340.875 | JE3: 7373.523 | JF3: 7406.187 | JG3: 7438.97 | JH3: 7471.777 | JI3: 7504.715 | JJ3: 7537.859 | JK3: 7570.986 | JL3: 7604.126 | JM3: 7637.359 | JN3: 7670.741 | JO3: 7704.025 | JP3: 7737.5 | JQ3: 7771.08 | JR3: 7804.621 | JS3: 7838.287 | JT3: 7872.039 | JU3: 7905.766 | JV3: 7939.522 | JW3: 7973.378 | JX3: 8007.321 | JY3: 8041.283 | JZ3: 8075.307 | KA3: 8109.416 | KB3: 8143.565 | KC3: 8177.827 | KD3: 8212.151 | KE3: 8246.524 | KF3: 8281.025 | KG3: 8315.555 | KH3: 8350.189 | KI3: 8384.9 | KJ3: 8419.718 | KK3: 8454.584 | KL3: 8489.51 | KM3: 8524.608 | KN3: 8559.746 | KO3: 8594.936 | KP3: 8630.222 | KQ3: 8665.596 | KR3: 8701.066 | KS3: 8736.631 | KT3: 8772.313 | KU3: 8808.062 | KV3: 8843.923 | KW3: 8879.884 | KX3: 8915.907 | KY3: 8952.128 | KZ3: 8988.344 | LA3: 9024.702 | LB3: 9061.114 | LC3: 9097.691 | LD3: 9134.354 | LE3: 9171.124 | LF3: 9207.993 | LG3: Bureau of Economic Analysis\Haver Analytics | LH3: TRUE | LI3: chained 2017 | LJ3: NA | LK3: 2024 | LL3: 2 | LM3: NA | LN3: GDPH@USNA / 4 | LO3: Real Gross Domestic Product (SAAR, Bil.Chn.2017$) / 4 | LP3: USA | LQ3: GDP | LR3: AUG006N.db
A4: Japan | B4: GDP, real, LCU | C4: AUG006N | D4: Yen | E4: Billions | F4: Level | G4: 52242.65 | H4: 52722.43 | I4: 52875.77 | J4: 53539.66 | K4: 51759.14 | L4: 52134.51 | M4: 52810.48 | N4: 52526.84 | O4: 52595.21 | P4: 53789.34 | Q4: 54409.61 | R4: 54986.97 | S4: 55458.37 | T4: 55787.51 | U4: 56585.37 | V4: 56653.35 | W4: 57921.84 | X4: 58330.15 | Y4: 58729.51 | Z4: 59539.25 | AA4: 60686.21 | AB4: 61280.64 | AC4: 62081.49 | AD4: 62988.52 | AE4: 64175.77 | AF4: 65372.08 | AG4: 65872.72 | AH4: 66157.2 | AI4: 67431.65 | AJ4: 67125.25 | AK4: 68540.48 | AL4: 69895.05 | AM4: 70493.48 | AN4: 71146.73 | AO4: 71480.1 | AP4: 71827.58 | AQ4: 72823.85 | AR4: 73296.85 | AS4: 73595.08 | AT4: 74635.23 | AU4: 75168.8 | AV4: 75743.88 | AW4: 76764.23 | AX4: 77307.77 | AY4: 78032.58 | AZ4: 79658.95 | BA4: 80246.33 | BB4: 80542.25 | BC4: 81627.42 | BD4: 83146.85 | BE4: 84384.77 | BF4: 85720.3 | BG4: 85758.42 | BH4: 86018.4 | BI4: 86623.83 | BJ4: 87631.63 | BK4: 87931.4 | BL4: 89458.15 | BM4: 91089.55 | BN4: 93422.8 | BO4: 94866.7 | BP4: 95559.08 | BQ4: 97321.1 | BR4: 98386.73 | BS4: 100718.5 | BT4: 99521.33 | BU4: 101067.9 | BV4: 103823.8 | BW4: 103264 | BX4: 105791 | BY4: 107937.8 | BZ4: 107869 | CA4: 109030.2 | CB4: 109977.8 | CC4: 109973 | CD4: 110813.9 | CE4: 110645.6 | CF4: 110982.4 | CG4: 111402.7 | CH4: 110721.5 | CI4: 111282 | CJ4: 110343.9 | CK4: 109839 | CL4: 110263.7 | CM4: 111562.7 | CN4: 110952 | CO4: 112227 | CP4: 111792.8 | CQ4: 113013.4 | CR4: 114083.8 | CS4: 115422.8 | CT4: 115713.4 | CU4: 116649 | CV4: 118135.9 | CW4: 118290.6 | CX4: 119611.5 | CY4: 119901 | CZ4: 119018.6 | DA4: 119251.9 | DB4: 119295.2 | DC4: 117832.7 | DD4: 117325.8 | DE4: 117536.6 | DF4: 118476.4 | DG4: 116845.4 | DH4: 117293.8 | DI4: 117919.3 | DJ4: 117955.1 | DK4: 119981.1 | DL4: 120528.3 | DM4: 120564.4 | DN4: 121728.4 | DO4: 122638.9 | DP4: 121712.8 | DQ4: 120398.2 | DR4: 119971 | DS4: 120187.2 | DT4: 121146.3 | DU4: 121543.4 | DV4: 121872.3 | DW4: 121952.1 | DX4: 122779.1 | DY4: 123155.6 | DZ4: 124494.3 | EA4: 125421.2 | EB4: 125417.4 | EC4: 126193.6 | ED4: 125958.1 | EE4: 126596.9 | EF4: 127578.2 | EG4: 128875.4 | EH4: 129110.5 | EI4: 129304.9 | EJ4: 129495.4 | EK4: 129253.3 | EL4: 131000.5 | EM4: 131852.7 | EN4: 131893 | EO4: 131210.9 | EP4: 131764.2 | EQ4: 132236.8 | ER4: 131448.2 | ES4: 129864.3 | ET4: 126612.5 | EU4: 120512.2 | EV4: 122891.9 | EW4: 122876.2 | EX4: 124344.3 | EY4: 125647.1 | EZ4: 127185.6 | FA4: 129508.2 | FB4: 128405.4 | FC4: 127065.6 | FD4: 125987.3 | FE4: 129043.4 | FF4: 128830.6 | FG4: 130669.4 | FH4: 129461.4 | FI4: 128960.7 | FJ4: 128849.6 | FK4: 130670.5 | FL4: 131834.4 | FM4: 133095.5 | FN4: 132914.7 | FO4: 134034.5 | FP4: 131599.5 | FQ4: 131723 | FR4: 132295.4 | FS4: 134381.1 | FT4: 134559.9 | FU4: 134713.5 | FV4: 134449.3 | FW4: 135473 | FX4: 135259.1 | FY4: 135551.7 | FZ4: 135722.2 | GA4: 136791.4 | GB4: 137332 | GC4: 138497.7 | GD4: 138612.5 | GE4: 138708.8 | GF4: 139243.2 | GG4: 138515.5 | GH4: 138240.8 | GI4: 138553.3 | GJ4: 139137.7 | GK4: 139389.7 | GL4: 135434.2 | GM4: 136106.8 | GN4: 125677.2 | GO4: 132544.2 | GP4: 134869 | GQ4: 135270.3 | GR4: 135939.7 | GS4: 135503.7 | GT4: 137154.8 | GU4: 136389.6 | GV4: 137987 | GW4: 137723.3 | GX4: 138225.8 | GY4: 139817.7 | GZ4: 141101.6 | HA4: 139669.1 | HB4: 139690.2 | HC4: 138682 | HD4: 139695 | HE4: 141092.7 | HF4: 141664 | HG4: 141793.2 | HH4: 141889.3 | HI4: 142022.8 | HJ4: 142171.9 | HK4: 142375.8 | HL4: 142563.6 | HM4: 142731.5 | HN4: 142888.7 | HO4: 143050.3 | HP4: 143199 | HQ4: 143338.1 | HR4: 143498.6 | HS4: 143611.1 | HT4: 143732.6 | HU4: 143838.1 | HV4: 143927.9 | HW4: 143996.7 | HX4: 144070.1 | HY4: 144136.9 | HZ4: 144192 | IA4: 144240 | IB4: 144293.2 | IC4: 144328 | ID4: 144347.6 | IE4: 144351 | IF4: 144361.5 | IG4: 144375.5 | IH4: 144393.8 | II4: 144401.4 | IJ4: 144395.3 | IK4: 144390.7 | IL4: 144387.5 | IM4: 144383.3 | IN4: 144370.1 | IO4: 144341.4 | IP4: 144298.9 | IQ4: 144261.9 | IR4: 144227.8 | IS4: 144176.9 | IT4: 144109.5 | IU4: 144046.1 | IV4: 143987.4 | IW4: 143916 | IX4: 143831.1 | IY4: 143746 | IZ4: 143664.6 | JA4: 143580 | JB4: 143492.9 | JC4: 143405.6 | JD4: 143317.5 | JE4: 143227 | JF4: 143133.5 | JG4: 143040.4 | JH4: 142946.2 | JI4: 142848.4 | JJ4: 142746.5 | JK4: 142642.2 | JL4: 142537.4 | JM4: 142436.5 | JN4: 142340 | JO4: 142244.8 | JP4: 142148.8 | JQ4: 142057.4 | JR4: 141970.5 | JS4: 141885.4 | JT4: 141800.1 | JU4: 141718.7 | JV4: 141641 | JW4: 141565.8 | JX4: 141491.4 | JY4: 141421.7 | JZ4: 141356 | KA4: 141293 | KB4: 141231.3 | KC4: 141172.8 | KD4: 141117.5 | KE4: 141066.3 | KF4: 141019.9 | KG4: 140980.8 | KH4: 140948.7 | KI4: 140922.1 | KJ4: 140899.6 | KK4: 140883 | KL4: 140872.2 | KM4: 140866.2 | KN4: 140864.2 | KO4: 140867.2 | KP4: 140874.4 | KQ4: 140882.6 | KR4: 140891.6 | KS4: 140905.7 | KT4: 140924.3 | KU4: 140942 | KV4: 140958.5 | KW4: 140977.9 | KX4: 141000.7 | KY4: 141020.2 | KZ4: 141039.2 | LA4: 141066.7 | LB4: 141103.8 | LC4: 141141.3 | LD4: 141177.9 | LE4: 141224.1 | LF4: 141280 | LG4: Cabinet Office of Japan/Haver Analytics | LH4: TRUE | LI4: 2015 | LJ4: NA | LK4: 2024 | LL4: 1 | LM4: NA | LN4: REDPC2@JAPAN/4 | LO4: Japan: Gross Domestic Product (SAAR, Bil.Chn.2015.Yen) | LP4: JPN | LQ4: GDP | LR4: AUG006N.db
A5: Germany | B5: GDP, real, LCU | C5: AUG006N | D5: Euro | E5: Billions | F5: Level | G5: 354.5728 | H5: 357.0943 | I5: 358.3091 | J5: 359.2109 | K5: 362.1098 | L5: 361.7969 | M5: 361.9442 | N5: 357.3152 | O5: 355.263 | P5: 353.5144 | Q5: 357.3152 | R5: 364.4565 | S5: 367.5762 | T5: 373.1255 | U5: 373.282 | V5: 380.1196 | W5: 383.4694 | X5: 385.586 | Y5: 385.4388 | Z5: 392.0555 | AA5: 393.7213 | AB5: 395.3225 | AC5: 400.4117 | AD5: 405.1235 | AE5: 405.6572 | AF5: 418.2006 | AG5: 418.2742 | AH5: 420.7773 | AI5: 424.1271 | AJ5: 421.3847 | AK5: 419.719 | AL5: 419.1116 | AM5: 424.2008 | AN5: 423.0596 | AO5: 424.2008 | AP5: 423.8142 | AQ5: 425.4984 | AR5: 422.8296 | AS5: 418.7343 | AT5: 419.719 | AU5: 423.5934 | AV5: 428.0015 | AW5: 427.0168 | AX5: 432.9342 | AY5: 438.6399 | AZ5: 431.8022 | BA5: 443.5081 | BB5: 447.226 | BC5: 444.8701 | BD5: 449.2046 | BE5: 455.1404 | BF5: 457.8 | BG5: 455.2877 | BH5: 460.5332 | BI5: 463.9474 | BJ5: 468.512 | BK5: 456.7325 | BL5: 466.9936 | BM5: 470.2605 | BN5: 477.7148 | BO5: 473.5367 | BP5: 482.1229 | BQ5: 487.442 | BR5: 493.295 | BS5: 498.3105 | BT5: 500.3627 | BU5: 504.9273 | BV5: 510.7802 | BW5: 521.3358 | BX5: 524.0046 | BY5: 535.0203 | BZ5: 544.4439 | CA5: 560.6131 | CB5: 558.156 | CC5: 557.1253 | CD5: 564.966 | CE5: 572.9632 | CF5: 569.4846 | CG5: 567.9753 | CH5: 566.3096 | CI5: 561.8739 | CJ5: 562.1132 | CK5: 565.2789 | CL5: 564.8832 | CM5: 572.7239 | CN5: 576.0554 | CO5: 579.3775 | CP5: 585.8747 | CQ5: 583.5004 | CR5: 588.249 | CS5: 589.2797 | CT5: 589.519 | CU5: 585.3961 | CV5: 593.559 | CW5: 595.6204 | CX5: 601.004 | CY5: 598.1511 | CZ5: 604.8876 | DA5: 607.0226 | DB5: 611.5411 | DC5: 617.5598 | DD5: 614.7069 | DE5: 617.5598 | DF5: 617.4033 | DG5: 624.6827 | DH5: 623.8912 | DI5: 632.2933 | DJ5: 635.3027 | DK5: 645.3613 | DL5: 650.3491 | DM5: 650.7449 | DN5: 647.9749 | DO5: 661.9078 | DP5: 660.012 | DQ5: 659.9292 | DR5: 657.9506 | DS5: 655.1806 | DT5: 657.472 | DU5: 661.9906 | DV5: 660.2513 | DW5: 651.3798 | DX5: 652.1713 | DY5: 658.1071 | DZ5: 658.8985 | EA5: 658.1071 | EB5: 661.8342 | EC5: 659.6899 | ED5: 659.377 | EE5: 660.5642 | EF5: 664.2085 | EG5: 669.6749 | EH5: 672.2057 | EI5: 679.7335 | EJ5: 691.2922 | EK5: 696.685 | EL5: 706.8172 | EM5: 707.7743 | EN5: 712.4401 | EO5: 716.0107 | EP5: 721.3115 | EQ5: 725.6736 | ER5: 723.0601 | ES5: 719.0937 | ET5: 708.0044 | EU5: 674.7456 | EV5: 676.5677 | EW5: 680.6078 | EX5: 685.9086 | EY5: 690.8228 | EZ5: 705.8693 | FA5: 712.6794 | FB5: 717.3544 | FC5: 730.3486 | FD5: 732.3272 | FE5: 736.3672 | FF5: 736.2844 | FG5: 737.8673 | FH5: 738.5851 | FI5: 740.168 | FJ5: 737.7108 | FK5: 733.5144 | FL5: 742.5423 | FM5: 746.1866 | FN5: 747.0609 | FO5: 754.9016 | FP5: 755.1317 | FQ5: 759.0152 | FR5: 764.6381 | FS5: 762.8987 | FT5: 767.5738 | FU5: 771.1353 | FV5: 774.7795 | FW5: 782.2245 | FX5: 784.8381 | FY5: 786.9731 | FZ5: 790.3046 | GA5: 799.6453 | GB5: 806.7775 | GC5: 812.2439 | GD5: 820.2411 | GE5: 816.0447 | GF5: 822.1461 | GG5: 815.9619 | GH5: 821.3546 | GI5: 825.7075 | GJ5: 826.5818 | GK5: 828.4775 | GL5: 828.4775 | GM5: 809.9432 | GN5: 738.1894 | GO5: 802.0289 | GP5: 811.6089 | GQ5: 801.624 | GR5: 821.6675 | GS5: 822.7719 | GT5: 827.6862 | GU5: 831.174 | GV5: 831.0911 | GW5: 836.4011 | GX5: 831.9654 | GY5: 832.9961 | GZ5: 831.809 | HA5: 833.5483 | HB5: 830.2997 | HC5: 831.9654 | HD5: 831.3304 | HE5: 832.0853 | HF5: 833.7725 | HG5: 835.83 | HH5: 838.4352 | HI5: 841.3331 | HJ5: 844.4431 | HK5: 847.8085 | HL5: 851.2791 | HM5: 854.8037 | HN5: 858.4617 | HO5: 862.1141 | HP5: 865.8005 | HQ5: 869.4185 | HR5: 873.0561 | HS5: 876.5159 | HT5: 879.9359 | HU5: 883.3175 | HV5: 886.4839 | HW5: 889.3903 | HX5: 892.1225 | HY5: 894.55 | HZ5: 896.7458 | IA5: 898.894 | IB5: 900.955 | IC5: 902.9482 | ID5: 904.8655 | IE5: 906.7487 | IF5: 908.6138 | IG5: 910.4602 | IH5: 912.2879 | II5: 914.2051 | IJ5: 916.1036 | IK5: 917.9162 | IL5: 919.7092 | IM5: 921.4946 | IN5: 923.2595 | IO5: 925.0037 | IP5: 926.7271 | IQ5: 928.4962 | IR5: 930.2447 | IS5: 931.9724 | IT5: 933.679 | IU5: 935.4529 | IV5: 937.2068 | IW5: 938.9406 | IX5: 940.585 | IY5: 942.4559 | IZ5: 944.3277 | JA5: 946.2003 | JB5: 948.0736 | JC5: 949.967 | JD5: 951.8623 | JE5: 953.7596 | JF5: 955.6589 | JG5: 957.5446 | JH5: 959.4328 | JI5: 961.3238 | JJ5: 963.2175 | JK5: 965.3837 | JL5: 967.5558 | JM5: 969.7333 | JN5: 971.9167 | JO5: 974.3641 | JP5: 976.8205 | JQ5: 979.2858 | JR5: 981.7602 | JS5: 984.2961 | JT5: 986.8417 | JU5: 989.3965 | JV5: 991.9606 | JW5: 994.5839 | JX5: 997.217 | JY5: 999.86 | JZ5: 1002.513 | KA5: 1005.116 | KB5: 1007.728 | KC5: 1010.349 | KD5: 1012.98 | KE5: 1015.561 | KF5: 1018.13 | KG5: 1020.688 | KH5: 1023.233 | KI5: 1025.717 | KJ5: 1028.187 | KK5: 1030.665 | KL5: 1033.149 | KM5: 1035.578 | KN5: 1038.013 | KO5: 1040.455 | KP5: 1042.905 | KQ5: 1045.178 | KR5: 1047.456 | KS5: 1049.741 | KT5: 1052.031 | KU5: 1054.317 | KV5: 1056.609 | KW5: 1058.908 | KX5: 1061.214 | KY5: 1063.472 | KZ5: 1065.736 | LA5: 1067.995 | LB5: 1070.249 | LC5: 1072.535 | LD5: 1074.817 | LE5: 1077.094 | LF5: 1079.367 | LG5: Federal Statistics Office\Haver Analytics | LH5: TRUE | LI5: chained 2015 | LJ5: NA | LK5: 2024 | LL5: 2 | LM5: NA | LN5: DESNGDPC@GERMANY | LO5: Germany: Gross Domestic Product (SWDA, Bil.Chained.2015.Euros) | LP5: DEU | LQ5: GDP | LR5: AUG006N.db
A6: France | B6: GDP, real, LCU | C6: AUG006N | D6: Euro | E6: Billions | F6: Level | G6: 244.379 | H6: 247.949 | I6: 251.887 | J6: 254.935 | K6: 259.118 | L6: 260.946 | M6: 263.841 | N6: 259.134 | O6: 257.134 | P6: 257.051 | Q6: 256.883 | R6: 262.376 | S6: 264.851 | T6: 268.472 | U6: 271.536 | V6: 273.453 | W6: 276.547 | X6: 277.655 | Y6: 279.927 | Z6: 282.16 | AA6: 286.062 | AB6: 289.179 | AC6: 290.979 | AD6: 294.294 | AE6: 297.552 | AF6: 299.071 | AG6: 302.92 | AH6: 303.971 | AI6: 307.574 | AJ6: 305.096 | AK6: 305.557 | AL6: 305.08 | AM6: 306.214 | AN6: 308.53 | AO6: 310.602 | AP6: 312.474 | AQ6: 314.838 | AR6: 317.069 | AS6: 316.885 | AT6: 318.782 | AU6: 320.007 | AV6: 320.182 | AW6: 320.696 | AX6: 322.692 | AY6: 324.129 | AZ6: 325.672 | BA6: 327.777 | BB6: 327.475 | BC6: 328.296 | BD6: 331.027 | BE6: 332.921 | BF6: 334.602 | BG6: 335.636 | BH6: 339.318 | BI6: 341.16 | BJ6: 341.586 | BK6: 341.867 | BL6: 346.957 | BM6: 349.29 | BN6: 354.442 | BO6: 358.993 | BP6: 362.135 | BQ6: 366.718 | BR6: 369.743 | BS6: 374.552 | BT6: 378.731 | BU6: 382.998 | BV6: 388.135 | BW6: 388.956 | BX6: 391.046 | BY6: 393.587 | BZ6: 393.398 | CA6: 394.433 | CB6: 395.89 | CC6: 397.495 | CD6: 399.413 | CE6: 402.27 | CF6: 402.721 | CG6: 402.258 | CH6: 402.334 | CI6: 400.161 | CJ6: 400.18 | CK6: 400.67 | CL6: 401.724 | CM6: 404.451 | CN6: 408.509 | CO6: 412.199 | CP6: 416.085 | CQ6: 418.051 | CR6: 420.792 | CS6: 421.449 | CT6: 421.283 | CU6: 424.211 | CV6: 425.029 | CW6: 426.67 | CX6: 428.311 | CY6: 430.14 | CZ6: 434.654 | DA6: 438.976 | DB6: 443.314 | DC6: 447.564 | DD6: 450.769 | DE6: 453.1 | DF6: 456.206 | DG6: 459.345 | DH6: 462.324 | DI6: 469.134 | DJ6: 475.778 | DK6: 480.525 | DL6: 485.704 | DM6: 489.527 | DN6: 492.291 | DO6: 495.104 | DP6: 495.335 | DQ6: 497.844 | DR6: 495.723 | DS6: 498.599 | DT6: 501.099 | DU6: 502.966 | DV6: 503.549 | DW6: 505.06 | DX6: 502.934 | DY6: 508.149 | DZ6: 510.007 | EA6: 515.449 | EB6: 517.72 | EC6: 519.686 | ED6: 524.353 | EE6: 525.706 | EF6: 527.027 | EG6: 531.02 | EH6: 534.731 | EI6: 539.169 | EJ6: 545.766 | EK6: 546.329 | EL6: 549.288 | EM6: 555.148 | EN6: 558.738 | EO6: 560.299 | EP6: 560.575 | EQ6: 565.422 | ER6: 561.567 | ES6: 560.23 | ET6: 553.439 | EU6: 542.642 | EV6: 543.543 | EW6: 544.404 | EX6: 548.836 | EY6: 550.163 | EZ6: 552.906 | FA6: 556.548 | FB6: 559.985 | FC6: 567.315 | FD6: 567.238 | FE6: 569.233 | FF6: 570.964 | FG6: 571.198 | FH6: 568.665 | FI6: 569.954 | FJ6: 569.98 | FK6: 570.471 | FL6: 575.404 | FM6: 575.298 | FN6: 579.508 | FO6: 578.981 | FP6: 579.817 | FQ6: 583.284 | FR6: 582.059 | FS6: 585.519 | FT6: 585.711 | FU6: 587.226 | FV6: 588.586 | FW6: 590.881 | FX6: 589.492 | FY6: 590.262 | FZ6: 593.365 | GA6: 597.342 | GB6: 602.713 | GC6: 607.186 | GD6: 610.981 | GE6: 610.453 | GF6: 611.708 | GG6: 614.753 | GH6: 619.645 | GI6: 624.827 | GJ6: 628.467 | GK6: 628.723 | GL6: 625.513 | GM6: 593.371 | GN6: 520.037 | GO6: 602.312 | GP6: 601.443 | GQ6: 603.246 | GR6: 611.16 | GS6: 628.615 | GT6: 632.379 | GU6: 631.479 | GV6: 633.862 | GW6: 637.265 | GX6: 637.617 | GY6: 638.045 | GZ6: 642.143 | HA6: 642.855 | HB6: 645.632 | HC6: 647.369 | HD6: 649.184 | HE6: 652.54 | HF6: 651.6 | HG6: 653.69 | HH6: 656.15 | HI6: 658.82 | HJ6: 661.17 | HK6: 663.58 | HL6: 666.13 | HM6: 668.64 | HN6: 671.12 | HO6: 673.8 | HP6: 676.49 | HQ6: 679.16 | HR6: 681.94 | HS6: 684.54 | HT6: 687.22 | HU6: 689.91 | HV6: 692.57 | HW6: 695.17 | HX6: 697.84 | HY6: 700.49 | HZ6: 703.08 | IA6: 705.49 | IB6: 707.78 | IC6: 709.97 | ID6: 712.15 | IE6: 714.33 | IF6: 716.51 | IG6: 718.7 | IH6: 720.84 | II6: 722.99 | IJ6: 725.13 | IK6: 727.28 | IL6: 729.3 | IM6: 731.33 | IN6: 733.4 | IO6: 735.48 | IP6: 737.48 | IQ6: 739.48 | IR6: 741.5 | IS6: 743.52 | IT6: 745.41 | IU6: 747.3 | IV6: 749.18 | IW6: 751.07 | IX6: 752.95 | IY6: 754.82 | IZ6: 756.7 | JA6: 758.58 | JB6: 760.29 | JC6: 762.01 | JD6: 763.72 | JE6: 765.44 | JF6: 767.15 | JG6: 768.87 | JH6: 770.58 | JI6: 772.17 | JJ6: 773.76 | JK6: 775.34 | JL6: 776.93 | JM6: 778.51 | JN6: 780.1 | JO6: 781.68 | JP6: 783.2 | JQ6: 784.72 | JR6: 786.23 | JS6: 787.78 | JT6: 789.32 | JU6: 790.87 | JV6: 792.47 | JW6: 794.08 | JX6: 795.68 | JY6: 797.31 | JZ6: 798.94 | KA6: 800.57 | KB6: 802.2 | KC6: 803.83 | KD6: 805.46 | KE6: 807.09 | KF6: 808.61 | KG6: 810.13 | KH6: 811.65 | KI6: 813.17 | KJ6: 814.69 | KK6: 816.13 | KL6: 817.58 | KM6: 819.03 | KN6: 820.47 | KO6: 821.85 | KP6: 823.15 | KQ6: 824.45 | KR6: 825.68 | KS6: 826.88 | KT6: 828.06 | KU6: 829.25 | KV6: 830.49 | KW6: 831.7 | KX6: 832.88 | KY6: 834.07 | KZ6: 835.31 | LA6: 836.52 | LB6: 837.71 | LC6: 839.03 | LD6: 840.39 | LE6: 841.72 | LF6: 843.04 | LG6: Institut National de la Statistique et des Etudes Economiques\Haver Analytics | LH6: TRUE | LI6: chained 2020 | LJ6: NA | LK6: 2024 | LL6: 2 | LM6: NA | LN6: FRSNGDPC@FRANCE/1000 | LO6: France: Gross Domestic Product (SA/WDA, Mil.Chn.2020.Euros)/1000 | LP6: FRA | LQ6: GDP | LR6: AUG006N.db
A7: Italy | B7: GDP, real, LCU | C7: AUG006N | D7: Euro | E7: Billions | F7: Level | G7: 209.6728 | H7: 215.9544 | I7: 222.827 | J7: 228.2695 | K7: 230.1201 | L7: 232.3188 | M7: 232.7052 | N7: 227.8411 | O7: 223.8772 | P7: 223.7629 | Q7: 226.9424 | R7: 229.4855 | S7: 233.5283 | T7: 237.7498 | U7: 243.7914 | V7: 248.021 | W7: 248.1192 | X7: 246.7374 | Y7: 244.4292 | Z7: 246.5231 | AA7: 250.5531 | AB7: 254.8873 | AC7: 256.2274 | AD7: 260.1316 | AE7: 264.2419 | AF7: 266.1635 | AG7: 270.7701 | AH7: 277.1434 | AI7: 276.6473 | AJ7: 278.7943 | AK7: 279.028 | AL7: 281.4052 | AM7: 280.492 | AN7: 281.039 | AO7: 281.17 | AP7: 283.452 | AQ7: 283.339 | AR7: 282.534 | AS7: 282.383 | AT7: 281.56 | AU7: 282.349 | AV7: 282.011 | AW7: 287.261 | AX7: 293.63 | AY7: 293.052 | AZ7: 293.998 | BA7: 297.459 | BB7: 297.507 | BC7: 299.206 | BD7: 303.16 | BE7: 305.587 | BF7: 307.625 | BG7: 309.543 | BH7: 311.544 | BI7: 314.655 | BJ7: 315.946 | BK7: 317.241 | BL7: 322.044 | BM7: 322.974 | BN7: 326.449 | BO7: 331.254 | BP7: 333.358 | BQ7: 337.739 | BR7: 341.771 | BS7: 343.893 | BT7: 345.382 | BU7: 348.982 | BV7: 352.574 | BW7: 353.978 | BX7: 355.057 | BY7: 355.628 | BZ7: 353.316 | CA7: 356.85 | CB7: 354.897 | CC7: 355.024 | CD7: 359.191 | CE7: 360.158 | CF7: 359.951 | CG7: 359.151 | CH7: 356.676 | CI7: 356.177 | CJ7: 355.319 | CK7: 354.758 | CL7: 357.359 | CM7: 360.081 | CN7: 362.687 | CO7: 364.95 | CP7: 368.376 | CQ7: 373 | CR7: 373.262 | CS7: 374.922 | CT7: 378.027 | CU7: 379.565 | CV7: 379.583 | CW7: 380.006 | CX7: 378.838 | CY7: 379.993 | CZ7: 385.205 | DA7: 387.935 | DB7: 394.652 | DC7: 391.689 | DD7: 394.016 | DE7: 394.497 | DF7: 392.565 | DG7: 395.043 | DH7: 396.553 | DI7: 400.093 | DJ7: 405.648 | DK7: 410.635 | DL7: 413.417 | DM7: 416.296 | DN7: 422.773 | DO7: 424.978 | DP7: 423.795 | DQ7: 422.05 | DR7: 421.287 | DS7: 422.232 | DT7: 423.723 | DU7: 424.484 | DV7: 425.887 | DW7: 424.613 | DX7: 424.162 | DY7: 423.874 | DZ7: 427.812 | EA7: 428.823 | EB7: 430.24 | EC7: 430.022 | ED7: 431.433 | EE7: 430.282 | EF7: 433.909 | EG7: 437.002 | EH7: 437.171 | EI7: 437.855 | EJ7: 441.119 | EK7: 443.304 | EL7: 449.12 | EM7: 447.871 | EN7: 448.931 | EO7: 449.677 | EP7: 448.228 | EQ7: 453.499 | ER7: 448.97 | ES7: 443.405 | ET7: 431.569 | EU7: 421.027 | EV7: 418.491 | EW7: 420.837 | EX7: 422.293 | EY7: 423.696 | EZ7: 426.835 | FA7: 428.956 | FB7: 431.16 | FC7: 433.31 | FD7: 433.67 | FE7: 431.458 | FF7: 427.181 | FG7: 422.347 | FH7: 419.511 | FI7: 417.381 | FJ7: 414.304 | FK7: 410.076 | FL7: 410.391 | FM7: 411.306 | FN7: 410.569 | FO7: 410.962 | FP7: 410.949 | FQ7: 411.624 | FR7: 410.249 | FS7: 411.434 | FT7: 413.001 | FU7: 413.867 | FV7: 415.877 | FW7: 417.331 | FX7: 418.146 | FY7: 420.375 | FZ7: 421.947 | GA7: 423.956 | GB7: 425.841 | GC7: 427.477 | GD7: 429.835 | GE7: 429.42 | GF7: 429.678 | GG7: 430.012 | GH7: 431.297 | GI7: 431.671 | GJ7: 433.098 | GK7: 433.366 | GL7: 430.533 | GM7: 404.543 | GN7: 356.802 | GO7: 406.445 | GP7: 404.44 | GQ7: 410.589 | GR7: 421.442 | GS7: 433.394 | GT7: 436.959 | GU7: 437.828 | GV7: 443.952 | GW7: 445.708 | GX7: 445.464 | GY7: 447.403 | GZ7: 446.714 | HA7: 448.207 | HB7: 448.663 | HC7: 450.165 | HD7: 450.907 | HE7: 451.7186 | HF7: 453.0738 | HG7: 454.5735 | HH7: 455.8799 | HI7: 457.0016 | HJ7: 458.1234 | HK7: 459.1321 | HL7: 459.8973 | HM7: 460.4535 | HN7: 461.0976 | HO7: 461.7416 | HP7: 462.3857 | HQ7: 463.1095 | HR7: 463.8333 | HS7: 464.5572 | HT7: 465.1833 | HU7: 465.8094 | HV7: 466.4355 | HW7: 467.0617 | HX7: 467.6878 | HY7: 468.3139 | HZ7: 468.9401 | IA7: 469.5662 | IB7: 470.1007 | IC7: 470.6353 | ID7: 471.1698 | IE7: 471.7043 | IF7: 472.2388 | IG7: 472.7347 | IH7: 473.2307 | II7: 473.7265 | IJ7: 474.2224 | IK7: 474.7183 | IL7: 475.2142 | IM7: 475.7101 | IN7: 476.1461 | IO7: 476.5821 | IP7: 476.9378 | IQ7: 477.2935 | IR7: 477.6493 | IS7: 477.9648 | IT7: 478.2805 | IU7: 478.5961 | IV7: 478.9117 | IW7: 479.2273 | IX7: 479.5429 | IY7: 479.8585 | IZ7: 480.0743 | JA7: 480.3206 | JB7: 480.5646 | JC7: 480.7866 | JD7: 481.006 | JE7: 481.2226 | JF7: 481.4366 | JG7: 481.5996 | JH7: 481.7596 | JI7: 481.9162 | JJ7: 482.0693 | JK7: 482.2061 | JL7: 482.3388 | JM7: 482.4673 | JN7: 482.5919 | JO7: 482.7388 | JP7: 482.8815 | JQ7: 483.0204 | JR7: 483.1549 | JS7: 483.28 | JT7: 483.4008 | JU7: 483.5173 | JV7: 483.6297 | JW7: 483.7469 | JX7: 483.8602 | JY7: 483.9696 | JZ7: 484.0752 | KA7: 484.1887 | KB7: 484.2984 | KC7: 484.4047 | KD7: 484.5067 | KE7: 484.5834 | KF7: 484.6564 | KG7: 484.7261 | KH7: 484.792 | KI7: 484.9159 | KJ7: 485.0365 | KK7: 485.1542 | KL7: 485.2687 | KM7: 485.4268 | KN7: 485.5823 | KO7: 485.7351 | KP7: 485.8851 | KQ7: 486.0916 | KR7: 486.2952 | KS7: 486.4971 | KT7: 486.6966 | KU7: 486.9105 | KV7: 487.1229 | KW7: 487.3337 | KX7: 487.5426 | KY7: 487.8271 | KZ7: 488.1104 | LA7: 488.3922 | LB7: 488.6729 | LC7: 488.9919 | LD7: 489.3101 | LE7: 489.6274 | LF7: 489.9439 | LG7: Statistical Office of the European Communities\Haver Analytics | LH7: TRUE | LI7: chained 2015 | LJ7: NA | LK7: 2024 | LL7: 2 | LM7: NA | LN7: ITSNGDPC@ITALY/1000 | LO7: Italy: Gross Domestic Product (SWDA, Mil.Ch.15.EUR) /1000 | LP7: ITA | LQ7: GDP | LR7: AUG006N.db
A8: Canada | B8: GDP, real, LCU | C8: AUG006N | D8: C$ | E8: Millions | F8: Level | G8: 174319.5 | H8: 175982.5 | I8: 176800.8 | J8: 180061.8 | K8: 181552 | L8: 183414.3 | M8: 183449.5 | N8: 182493.8 | O8: 181499.5 | P8: 183828 | Q8: 187354.8 | R8: 189522.8 | S8: 192825.5 | T8: 196983.8 | U8: 197893.3 | V8: 198213 | W8: 201253.3 | X8: 202280.3 | Y8: 203469.3 | Z8: 206693.5 | AA8: 208478.5 | AB8: 209897.5 | AC8: 211855.5 | AD8: 213864.3 | AE8: 215570.5 | AF8: 218430.3 | AG8: 220031.5 | AH8: 221507.8 | AI8: 223045.8 | AJ8: 222948.3 | AK8: 222763 | AL8: 225845.3 | AM8: 230710.8 | AN8: 233233.3 | AO8: 231136.3 | AP8: 230073.3 | AQ8: 227440.3 | AR8: 224821.8 | AS8: 222828 | AT8: 220771.8 | AU8: 224379.8 | AV8: 228806.3 | AW8: 231376.8 | AX8: 234253.3 | AY8: 238310.5 | AZ8: 242935.3 | BA8: 243979.8 | BB8: 247787.5 | BC8: 251594.5 | BD8: 252403.8 | BE8: 255608 | BF8: 259505 | BG8: 259373.5 | BH8: 260864.3 | BI8: 261192.3 | BJ8: 259301.5 | BK8: 265295 | BL8: 268693.5 | BM8: 272798.8 | BN8: 276323 | BO8: 280349 | BP8: 282836.8 | BQ8: 282878.8 | BR8: 284820 | BS8: 288111 | BT8: 289231.8 | BU8: 290276 | BV8: 289698.3 | BW8: 292484.3 | BX8: 291310.8 | BY8: 289223 | BZ8: 286647.8 | CA8: 282524 | CB8: 283880 | CC8: 284256.5 | CD8: 284756 | CE8: 284957 | CF8: 285281.8 | CG8: 286827 | CH8: 288461.3 | CI8: 290292.8 | CJ8: 292937 | CK8: 295738.5 | CL8: 297003.5 | CM8: 301382.8 | CN8: 305782.5 | CO8: 309702.8 | CP8: 311952.5 | CQ8: 314818.8 | CR8: 314952.5 | CS8: 315368.8 | CT8: 316641.5 | CU8: 317101 | CV8: 319358.5 | CW8: 322040.8 | CX8: 324592.3 | CY8: 328941.5 | CZ8: 332643.3 | DA8: 336586.8 | DB8: 339839.5 | DC8: 344638 | DD8: 344820.5 | DE8: 347962.5 | DF8: 352677.3 | DG8: 359045 | DH8: 362006.3 | DI8: 367680.5 | DJ8: 372831.5 | DK8: 378669 | DL8: 383125.8 | DM8: 387053 | DN8: 387818.5 | DO8: 390001.5 | DP8: 391228 | DQ8: 390953 | DR8: 393297.8 | DS8: 399048.5 | DT8: 401406.3 | DU8: 404877.3 | DV8: 407101 | DW8: 409366 | DX8: 408772.3 | DY8: 410300.5 | DZ8: 413121 | EA8: 416125 | EB8: 421055.5 | EC8: 426033.8 | ED8: 429108.5 | EE8: 430611.3 | EF8: 433723.5 | EG8: 438979.8 | EH8: 443339.5 | EI8: 446939 | EJ8: 447162.5 | EK8: 448421.3 | EL8: 450207 | EM8: 453080.3 | EN8: 457455.8 | EO8: 459169.8 | EP8: 459773.3 | EQ8: 460118.3 | ER8: 461794.8 | ES8: 465589.5 | ET8: 460187.3 | EU8: 449802.8 | EV8: 444950.8 | EW8: 446940.8 | EX8: 452133.8 | EY8: 457611.5 | EZ8: 460007.8 | FA8: 463228 | FB8: 468424.5 | FC8: 471992 | FD8: 472848.8 | FE8: 479318.5 | FF8: 483127.8 | FG8: 483432.8 | FH8: 485004.3 | FI8: 485668 | FJ8: 486667.5 | FK8: 491023.8 | FL8: 493851.5 | FM8: 497912.5 | FN8: 503123.5 | FO8: 503973.8 | FP8: 508567.8 | FQ8: 513442.8 | FR8: 516991.5 | FS8: 514113 | FT8: 512709.5 | FU8: 514545.5 | FV8: 514886.5 | FW8: 517933 | FX8: 515353 | FY8: 520701.3 | FZ8: 523622.5 | GA8: 530210.8 | GB8: 535791.5 | GC8: 535959.8 | GD8: 538679 | GE8: 544941.3 | GF8: 549192 | GG8: 551962.3 | GH8: 553262.5 | GI8: 554594 | GJ8: 560665.5 | GK8: 562233.3 | GL8: 563838.5 | GM8: 552844 | GN8: 492031.5 | GO8: 536725.3 | GP8: 546807 | GQ8: 554680.3 | GR8: 552950.5 | GS8: 562240.8 | GT8: 571064.3 | GU8: 576553.8 | GV8: 581970.3 | GW8: 584635.8 | GX8: 583376.8 | GY8: 588322.8 | GZ8: 589342.5 | HA8: 588909.5 | HB8: 589018.5 | HC8: 591452.8 | HD8: 592644.2 | HE8: 591280.3 | HF8: 593129.9 | HG8: 595408.1 | HH8: 598563.7 | HI8: 602239.9 | HJ8: 606228.5 | HK8: 610277.7 | HL8: 614310.6 | HM8: 618442.6 | HN8: 622555.4 | HO8: 626551.9 | HP8: 630445.4 | HQ8: 634258.6 | HR8: 637970.4 | HS8: 641573.3 | HT8: 645102.3 | HU8: 648618.1 | HV8: 652245.4 | HW8: 655801.9 | HX8: 659308.3 | HY8: 662796.5 | HZ8: 666378.8 | IA8: 669948.9 | IB8: 673489.7 | IC8: 676993.9 | ID8: 680477.8 | IE8: 683897.3 | IF8: 687295.5 | IG8: 690724.6 | IH8: 694136.5 | II8: 697511.7 | IJ8: 700892.5 | IK8: 704272.1 | IL8: 707746.7 | IM8: 711280.5 | IN8: 714812.4 | IO8: 718354 | IP8: 721914.7 | IQ8: 725485.4 | IR8: 729081.6 | IS8: 732699.8 | IT8: 736331.8 | IU8: 739908.7 | IV8: 743565.9 | IW8: 747248.6 | IX8: 750953.3 | IY8: 754659.1 | IZ8: 758373.3 | JA8: 762110.4 | JB8: 765879.7 | JC8: 769671.4 | JD8: 773473.9 | JE8: 777276.9 | JF8: 781080.5 | JG8: 784873.7 | JH8: 788689.1 | JI8: 792547.1 | JJ8: 796445.4 | JK8: 800350.3 | JL8: 804273.2 | JM8: 808232.1 | JN8: 812222.9 | JO8: 816194.1 | JP8: 820185.7 | JQ8: 824229.3 | JR8: 828325.7 | JS8: 832426.3 | JT8: 836538.9 | JU8: 840677.9 | JV8: 844843.6 | JW8: 849044.6 | JX8: 853239.1 | JY8: 857449.9 | JZ8: 861682.4 | KA8: 865942.3 | KB8: 870196 | KC8: 874450.2 | KD8: 878690.8 | KE8: 882977.9 | KF8: 887242.2 | KG8: 891505.5 | KH8: 895765.6 | KI8: 899979.7 | KJ8: 904237.6 | KK8: 908518.3 | KL8: 912818.9 | KM8: 917120.3 | KN8: 921445.6 | KO8: 925785.3 | KP8: 930132.1 | KQ8: 934514.4 | KR8: 938886.4 | KS8: 943264.4 | KT8: 947639.4 | KU8: 952022.7 | KV8: 956418.9 | KW8: 960811.7 | KX8: 965205.6 | KY8: 969667.8 | KZ8: 974113.9 | LA8: 978551.4 | LB8: 982972.5 | LC8: 987347 | LD8: 991782.1 | LE8: 996218.6 | LF8: 1000668 | LG8: Statistics Canada\Haver Analytics | LH8: TRUE | LI8: chained 2017 | LJ8: NA | LK8: 2024 | LL8: 1 | LM8: NA | LN8: V6E05752@CANADA/4 | LO8: Canada: Gross Domestic Product at Market Prices (SAAR, Mil.Chn.2017.C$)/4 | LP8: CAN | LQ8: GDP | LR8: AUG006N.db

Sheet Data
C1: AUG006N.db | D1: =$C$1 -> AUG006N.db | E1: =$C$1 -> AUG006N.db | F1: =$C$1 -> AUG006N.db | G1: =$C$1 -> AUG006N.db | H1: =$C$1 -> AUG006N.db | I1: =$C$1 -> AUG006N.db
C2: UK | D2: US | E2: Japan | F2: Germany | G2: France | H2: Italy | I2: Canada
C3: GDP | D3: GDP | E3: GDP | F3: GDP | G3: GDP | H3: GDP | I3: GDP
C4: GBR | D4: USA | E4: JPN | F4: DEU | G4: FRA | H4: ITA | I4: CAN
C5: L | D5: L | E5: L | F5: L | G5: L | H5: L | I5: L
B6: =B318+5 -> 2289 | C6: {=_xlfn.CONCAT(INDEX(GMW!$A$2:$LR$60,MATCH(1,(GMW!$LQ$2:$LQ$60=C$3)*(GMW!$LP$2:$LP$60=C$4)*(GMW!$LR$2:$LR$60=C$1),0),$B6-1966),"0",(INDEX(GMW!$A$2:$LR$60,MATCH(1,(GMW!$LQ$2:$LQ$60=C$3)*(GMW!$LP$2:$LP$60=C$4)*(GMW!$LR$2:$LR$60=C$1),0),$B6-1965)))} -> 202401 | D6: {=_xlfn.CONCAT(INDEX(GMW!$A$2:$LR$60,MATCH(1,(GMW!$LQ$2:$LQ$60=D$3)*(GMW!$LP$2:$LP$60=D$4)*(GMW!$LR$2:$LR$60=D$1),0),$B6-1966),"0",(INDEX(GMW!$A$2:$LR$60,MATCH(1,(GMW!$LQ$2:$LQ$60=D$3)*(GMW!$LP$2:$LP$60=D$4)*(GMW!$LR$2:$LR$60=D$1),0),$B6-1965)))} -> 202402 | E6: {=_xlfn.CONCAT(INDEX(GMW!$A$2:$LR$60,MATCH(1,(GMW!$LQ$2:$LQ$60=E$3)*(GMW!$LP$2:$LP$60=E$4)*(GMW!$LR$2:$LR$60=E$1),0),$B6-1966),"0",(INDEX(GMW!$A$2:$LR$60,MATCH(1,(GMW!$LQ$2:$LQ$60=E$3)*(GMW!$LP$2:$LP$60=E$4)*(GMW!$LR$2:$LR$60=E$1),0),$B6-1965)))} -> 202401 | F6: {=_xlfn.CONCAT(INDEX(GMW!$A$2:$LR$60,MATCH(1,(GMW!$LQ$2:$LQ$60=F$3)*(GMW!$LP$2:$LP$60=F$4)*(GMW!$LR$2:$LR$60=F$1),0),$B6-1966),"0",(INDEX(GMW!$A$2:$LR$60,MATCH(1,(GMW!$LQ$2:$LQ$60=F$3)*(GMW!$LP$2:$LP$60=F$4)*(GMW!$LR$2:$LR$60=F$1),0),$B6-1965)))} -> 202402 | G6: {=_xlfn.CONCAT(INDEX(GMW!$A$2:$LR$60,MATCH(1,(GMW!$LQ$2:$LQ$60=G$3)*(GMW!$LP$2:$LP$60=G$4)*(GMW!$LR$2:$LR$60=G$1),0),$B6-1966),"0",(INDEX(GMW!$A$2:$LR$60,MATCH(1,(GMW!$LQ$2:$LQ$60=G$3)*(GMW!$LP$2:$LP$60=G$4)*(GMW!$LR$2:$LR$60=G$1),0),$B6-1965)))} -> 202402 | H6: {=_xlfn.CONCAT(INDEX(GMW!$A$2:$LR$60,MATCH(1,(GMW!$LQ$2:$LQ$60=H$3)*(GMW!$LP$2:$LP$60=H$4)*(GMW!$LR$2:$LR$60=H$1),0),$B6-1966),"0",(INDEX(GMW!$A$2:$LR$60,MATCH(1,(GMW!$LQ$2:$LQ$60=H$3)*(GMW!$LP$2:$LP$60=H$4)*(GMW!$LR$2:$LR$60=H$1),0),$B6-1965)))} -> 202402 | I6: {=_xlfn.CONCAT(INDEX(GMW!$A$2:$LR$60,MATCH(1,(GMW!$LQ$2:$LQ$60=I$3)*(GMW!$LP$2:$LP$60=I$4)*(GMW!$LR$2:$LR$60=I$1),0),$B6-1966),"0",(INDEX(GMW!$A$2:$LR$60,MATCH(1,(GMW!$LQ$2:$LQ$60=I$3)*(GMW!$LP$2:$LP$60=I$4)*(GMW!$LR$2:$LR$60=I$1),0),$B6-1965)))} -> 202401
A7: 1973 | B7: 1973 | C7: {=INDEX(GMW!$A$2:$LR$60,MATCH(1,(GMW!$LQ$2:$LQ$60=C$3)*(GMW!$LP$2:$LP$60=C$4)*(GMW!$LR$2:$LR$60=C$1),0),$B7-1966)} -> 223780 | D7: {=INDEX(GMW!$A$2:$LR$60,MATCH(1,(GMW!$LQ$2:$LQ$60=D$3)*(GMW!$LP$2:$LP$60=D$4)*(GMW!$LR$2:$LR$60=D$1),0),$B7-1966)} -> 1514.625 | E7: {=INDEX(GMW!$A$2:$LR$60,MATCH(1,(GMW!$LQ$2:$LQ$60=E$3)*(GMW!$LP$2:$LP$60=E$4)*(GMW!$LR$2:$LR$60=E$1),0),$B7-1966)} -> 52242.65 | F7: {=INDEX(GMW!$A$2:$LR$60,MATCH(1,(GMW!$LQ$2:$LQ$60=F$3)*(GMW!$LP$2:$LP$60=F$4)*(GMW!$LR$2:$LR$60=F$1),0),$B7-1966)} -> 354.5728 | G7: {=INDEX(GMW!$A$2:$LR$60,MATCH(1,(GMW!$LQ$2:$LQ$60=G$3)*(GMW!$LP$2:$LP$60=G$4)*(GMW!$LR$2:$LR$60=G$1),0),$B7-1966)} -> 244.379 | H7: {=INDEX(GMW!$A$2:$LR$60,MATCH(1,(GMW!$LQ$2:$LQ$60=H$3)*(GMW!$LP$2:$LP$60=H$4)*(GMW!$LR$2:$LR$60=H$1),0),$B7-1966)} -> 209.6728 | I7: {=INDEX(GMW!$A$2:$LR$60,MATCH(1,(GMW!$LQ$2:$LQ$60=I$3)*(GMW!$LP$2:$LP$60=I$4)*(GMW!$LR$2:$LR$60=I$1),0),$B7-1966)} -> 174319.5
A8: =A7 -> 1973 | B8: =+B7+1 -> 1974 | C8: {=INDEX(GMW!$A$2:$LR$60,MATCH(1,(GMW!$LQ$2:$LQ$60=C$3)*(GMW!$LP$2:$LP$60=C$4)*(GMW!$LR$2:$LR$60=C$1),0),$B8-1966)} -> 224213 | D8: {=INDEX(GMW!$A$2:$LR$60,MATCH(1,(GMW!$LQ$2:$LQ$60=D$3)*(GMW!$LP$2:$LP$60=D$4)*(GMW!$LR$2:$LR$60=D$1),0),$B8-1966)} -> 1531.125 | E8: {=INDEX(GMW!$A$2:$LR$60,MATCH(1,(GMW!$LQ$2:$LQ$60=E$3)*(GMW!$LP$2:$LP$60=E$4)*(GMW!$LR$2:$LR$60=E$1),0),$B8-1966)} -> 52722.43 | F8: {=INDEX(GMW!$A$2:$LR$60,MATCH(1,(GMW!$LQ$2:$LQ$60=F$3)*(GMW!$LP$2:$LP$60=F$4)*(GMW!$LR$2:$LR$60=F$1),0),$B8-1966)} -> 357.0943 | G8: {=INDEX(GMW!$A$2:$LR$60,MATCH(1,(GMW!$LQ$2:$LQ$60=G$3)*(GMW!$LP$2:$LP$60=G$4)*(GMW!$LR$2:$LR$60=G$1),0),$B8-1966)} -> 247.949 | H8: {=INDEX(GMW!$A$2:$LR$60,MATCH(1,(GMW!$LQ$2:$LQ$60=H$3)*(GMW!$LP$2:$LP$60=H$4)*(GMW!$LR$2:$LR$60=H$1),0),$B8-1966)} -> 215.9544 | I8: {=INDEX(GMW!$A$2:$LR$60,MATCH(1,(GMW!$LQ$2:$LQ$60=I$3)*(GMW!$LP$2:$LP$60=I$4)*(GMW!$LR$2:$LR$60=I$1),0),$B8-1966)} -> 175982.5
A9: =A8 -> 1973 | B9: =+B8+1 -> 1975 | C9: {=INDEX(GMW!$A$2:$LR$60,MATCH(1,(GMW!$LQ$2:$LQ$60=C$3)*(GMW!$LP$2:$LP$60=C$4)*(GMW!$LR$2:$LR$60=C$1),0),$B9-1966)} -> 222122 | D9: {=INDEX(GMW!$A$2:$LR$60,MATCH(1,(GMW!$LQ$2:$LQ$60=D$3)*(GMW!$LP$2:$LP$60=D$4)*(GMW!$LR$2:$LR$60=D$1),0),$B9-1966)} -> 1523.075 | E9: {=INDEX(GMW!$A$2:$LR$60,MATCH(1,(GMW!$LQ$2:$LQ$60=E$3)*(GMW!$LP$2:$LP$60=E$4)*(GMW!$LR$2:$LR$60=E$1),0),$B9-1966)} -> 52875.77 | F9: {=INDEX(GMW!$A$2:$LR$60,MATCH(1,(GMW!$LQ$2:$LQ$60=F$3)*(GMW!$LP$2:$LP$60=F$4)*(GMW!$LR$2:$LR$60=F$1),0),$B9-1966)} -> 358.3091 | G9: {=INDEX(GMW!$A$2:$LR$60,MATCH(1,(GMW!$LQ$2:$LQ$60=G$3)*(GMW!$LP$2:$LP$60=G$4)*(GMW!$LR$2:$LR$60=G$1),0),$B9-1966)} -> 251.887 | H9: {=INDEX(GMW!$A$2:$LR$60,MATCH(1,(GMW!$LQ$2:$LQ$60=H$3)*(GMW!$LP$2:$LP$60=H$4)*(GMW!$LR$2:$LR$60=H$1),0),$B9-1966)} -> 222.827 | I9: {=INDEX(GMW!$A$2:$LR$60,MATCH(1,(GMW!$LQ$2:$LQ$60=I$3)*(GMW!$LP$2:$LP$60=I$4)*(GMW!$LR$2:$LR$60=I$1),0),$B9-1966)} -> 176800.8
A10: =A9 -> 1973 | B10: =+B9+1 -> 1976 | C10: {=INDEX(GMW!$A$2:$LR$60,MATCH(1,(GMW!$LQ$2:$LQ$60=C$3)*(GMW!$LP$2:$LP$60=C$4)*(GMW!$LR$2:$LR$60=C$1),0),$B10-1966)} -> 221266 | D10: {=INDEX(GMW!$A$2:$LR$60,MATCH(1,(GMW!$LQ$2:$LQ$60=D$3)*(GMW!$LP$2:$LP$60=D$4)*(GMW!$LR$2:$LR$60=D$1),0),$B10-1966)} -> 1537.525 | E10: {=INDEX(GMW!$A$2:$LR$60,MATCH(1,(GMW!$LQ$2:$LQ$60=E$3)*(GMW!$LP$2:$LP$60=E$4)*(GMW!$LR$2:$LR$60=E$1),0),$B10-1966)} -> 53539.66 | F10: {=INDEX(GMW!$A$2:$LR$60,MATCH(1,(GMW!$LQ$2:$LQ$60=F$3)*(GMW!$LP$2:$LP$60=F$4)*(GMW!$LR$2:$LR$60=F$1),0),$B10-1966)} -> 359.2109 | G10: {=INDEX(GMW!$A$2:$LR$60,MATCH(1,(GMW!$LQ$2:$LQ$60=G$3)*(GMW!$LP$2:$LP$60=G$4)*(GMW!$LR$2:$LR$60=G$1),0),$B10-1966)} -> 254.935 | H10: {=INDEX(GMW!$A$2:$LR$60,MATCH(1,(GMW!$LQ$2:$LQ$60=H$3)*(GMW!$LP$2:$LP$60=H$4)*(GMW!$LR$2:$LR$60=H$1),0),$B10-1966)} -> 228.2695 | I10: {=INDEX(GMW!$A$2:$LR$60,MATCH(1,(GMW!$LQ$2:$LQ$60=I$3)*(GMW!$LP$2:$LP$60=I$4)*(GMW!$LR$2:$LR$60=I$1),0),$B10-1966)} -> 180061.8
A11: =+A7+1 -> 1974 | B11: =+B10+1 -> 1977 | C11: {=INDEX(GMW!$A$2:$LR$60,MATCH(1,(GMW!$LQ$2:$LQ$60=C$3)*(GMW!$LP$2:$LP$60=C$4)*(GMW!$LR$2:$LR$60=C$1),0),$B11-1966)} -> 215122 | D11: {=INDEX(GMW!$A$2:$LR$60,MATCH(1,(GMW!$LQ$2:$LQ$60=D$3)*(GMW!$LP$2:$LP$60=D$4)*(GMW!$LR$2:$LR$60=D$1),0),$B11-1966)} -> 1524.325 | E11: {=INDEX(GMW!$A$2:$LR$60,MATCH(1,(GMW!$LQ$2:$LQ$60=E$3)*(GMW!$LP$2:$LP$60=E$4)*(GMW!$LR$2:$LR$60=E$1),0),$B11-1966)} -> 51759.14 | F11: {=INDEX(GMW!$A$2:$LR$60,MATCH(1,(GMW!$LQ$2:$LQ$60=F$3)*(GMW!$LP$2:$LP$60=F$4)*(GMW!$LR$2:$LR$60=F$1),0),$B11-1966)} -> 362.1098 | G11: {=INDEX(GMW!$A$2:$LR$60,MATCH(1,(GMW!$LQ$2:$LQ$60=G$3)*(GMW!$LP$2:$LP$60=G$4)*(GMW!$LR$2:$LR$60=G$1),0),$B11-1966)} -> 259.118 | H11: {=INDEX(GMW!$A$2:$LR$60,MATCH(1,(GMW!$LQ$2:$LQ$60=H$3)*(GMW!$LP$2:$LP$60=H$4)*(GMW!$LR$2:$LR$60=H$1),0),$B11-1966)} -> 230.1201 | I11: {=INDEX(GMW!$A$2:$LR$60,MATCH(1,(GMW!$LQ$2:$LQ$60=I$3)*(GMW!$LP$2:$LP$60=I$4)*(GMW!$LR$2:$LR$60=I$1),0),$B11-1966)} -> 181552
A12: =+A8+1 -> 1974 | B12: =+B11+1 -> 1978 | C12: {=INDEX(GMW!$A$2:$LR$60,MATCH(1,(GMW!$LQ$2:$LQ$60=C$3)*(GMW!$LP$2:$LP$60=C$4)*(GMW!$LR$2:$LR$60=C$1),0),$B12-1966)} -> 218215 | D12: {=INDEX(GMW!$A$2:$LR$60,MATCH(1,(GMW!$LQ$2:$LQ$60=D$3)*(GMW!$LP$2:$LP$60=D$4)*(GMW!$LR$2:$LR$60=D$1),0),$B12-1966)} -> 1527.95 | E12: {=INDEX(GMW!$A$2:$LR$60,MATCH(1,(GMW!$LQ$2:$LQ$60=E$3)*(GMW!$LP$2:$LP$60=E$4)*(GMW!$LR$2:$LR$60=E$1),0),$B12-1966)} -> 52134.51 | F12: {=INDEX(GMW!$A$2:$LR$60,MATCH(1,(GMW!$LQ$2:$LQ$60=F$3)*(GMW!$LP$2:$LP$60=F$4)*(GMW!$LR$2:$LR$60=F$1),0),$B12-1966)} -> 361.7969 | G12: {=INDEX(GMW!$A$2:$LR$60,MATCH(1,(GMW!$LQ$2:$LQ$60=G$3)*(GMW!$LP$2:$LP$60=G$4)*(GMW!$LR$2:$LR$60=G$1),0),$B12-1966)} -> 260.946 | H12: {=INDEX(GMW!$A$2:$LR$60,MATCH(1,(GMW!$LQ$2:$LQ$60=H$3)*(GMW!$LP$2:$LP$60=H$4)*(GMW!$LR$2:$LR$60=H$1),0),$B12-1966)} -> 232.3188 | I12: {=INDEX(GMW!$A$2:$LR$60,MATCH(1,(GMW!$LQ$2:$LQ$60=I$3)*(GMW!$LP$2:$LP$60=I$4)*(GMW!$LR$2:$LR$60=I$1),0),$B12-1966)} -> 183414.3
A13: =+A9+1 -> 1974 | B13: =+B12+1 -> 1979 | C13: {=INDEX(GMW!$A$2:$LR$60,MATCH(1,(GMW!$LQ$2:$LQ$60=C$3)*(GMW!$LP$2:$LP$60=C$4)*(GMW!$LR$2:$LR$60=C$1),0),$B13-1966)} -> 219517 | D13: {=INDEX(GMW!$A$2:$LR$60,MATCH(1,(GMW!$LQ$2:$LQ$60=D$3)*(GMW!$LP$2:$LP$60=D$4)*(GMW!$LR$2:$LR$60=D$1),0),$B13-1966)} -> 1513.5 | E13: {=INDEX(GMW!$A$2:$LR$60,MATCH(1,(GMW!$LQ$2:$LQ$60=E$3)*(GMW!$LP$2:$LP$60=E$4)*(GMW!$LR$2:$LR$60=E$1),0),$B13-1966)} -> 52810.48 | F13: {=INDEX(GMW!$A$2:$LR$60,MATCH(1,(GMW!$LQ$2:$LQ$60=F$3)*(GMW!$LP$2:$LP$60=F$4)*(GMW!$LR$2:$LR$60=F$1),0),$B13-1966)} -> 361.9442 | G13: {=INDEX(GMW!$A$2:$LR$60,MATCH(1,(GMW!$LQ$2:$LQ$60=G$3)*(GMW!$LP$2:$LP$60=G$4)*(GMW!$LR$2:$LR$60=G$1),0),$B13-1966)} -> 263.841 | H13: {=INDEX(GMW!$A$2:$LR$60,MATCH(1,(GMW!$LQ$2:$LQ$60=H$3)*(GMW!$LP$2:$LP$60=H$4)*(GMW!$LR$2:$LR$60=H$1),0),$B13-1966)} -> 232.7052 | I13: {=INDEX(GMW!$A$2:$LR$60,MATCH(1,(GMW!$LQ$2:$LQ$60=I$3)*(GMW!$LP$2:$LP$60=I$4)*(GMW!$LR$2:$LR$60=I$1),0),$B13-1966)} -> 183449.5
A14: =+A10+1 -> 1974 | B14: =+B13+1 -> 1980 | C14: {=INDEX(GMW!$A$2:$LR$60,MATCH(1,(GMW!$LQ$2:$LQ$60=C$3)*(GMW!$LP$2:$LP$60=C$4)*(GMW!$LR$2:$LR$60=C$1),0),$B14-1966)} -> 216301 | D14: {=INDEX(GMW!$A$2:$LR$60,MATCH(1,(GMW!$LQ$2:$LQ$60=D$3)*(GMW!$LP$2:$LP$60=D$4)*(GMW!$LR$2:$LR$60=D$1),0),$B14-1966)} -> 1507.625 | E14: {=INDEX(GMW!$A$2:$LR$60,MATCH(1,(GMW!$LQ$2:$LQ$60=E$3)*(GMW!$LP$2:$LP$60=E$4)*(GMW!$LR$2:$LR$60=E$1),0),$B14-1966)} -> 52526.84 | F14: {=INDEX(GMW!$A$2:$LR$60,MATCH(1,(GMW!$LQ$2:$LQ$60=F$3)*(GMW!$LP$2:$LP$60=F$4)*(GMW!$LR$2:$LR$60=F$1),0),$B14-1966)} -> 357.3152 | G14: {=INDEX(GMW!$A$2:$LR$60,MATCH(1,(GMW!$LQ$2:$LQ$60=G$3)*(GMW!$LP$2:$LP$60=G$4)*(GMW!$LR$2:$LR$60=G$1),0),$B14-1966)} -> 259.134 | H14: {=INDEX(GMW!$A$2:$LR$60,MATCH(1,(GMW!$LQ$2:$LQ$60=H$3)*(GMW!$LP$2:$LP$60=H$4)*(GMW!$LR$2:$LR$60=H$1),0),$B14-1966)} -> 227.8411 | I14: {=INDEX(GMW!$A$2:$LR$60,MATCH(1,(GMW!$LQ$2:$LQ$60=I$3)*(GMW!$LP$2:$LP$60=I$4)*(GMW!$LR$2:$LR$60=I$1),0),$B14-1966)} -> 182493.8
A15: =+A11+1 -> 1975 | B15: =+B14+1 -> 1981 | C15: {=INDEX(GMW!$A$2:$LR$60,MATCH(1,(GMW!$LQ$2:$LQ$60=C$3)*(GMW!$LP$2:$LP$60=C$4)*(GMW!$LR$2:$LR$60=C$1),0),$B15-1966)} -> 216390 | D15: {=INDEX(GMW!$A$2:$LR$60,MATCH(1,(GMW!$LQ$2:$LQ$60=D$3)*(GMW!$LP$2:$LP$60=D$4)*(GMW!$LR$2:$LR$60=D$1),0),$B15-1966)} -> 1489.25 | E15: {=INDEX(GMW!$A$2:$LR$60,MATCH(1,(GMW!$LQ$2:$LQ$60=E$3)*(GMW!$LP$2:$LP$60=E$4)*(GMW!$LR$2:$LR$60=E$1),0),$B15-1966)} -> 52595.21 | F15: {=INDEX(GMW!$A$2:$LR$60,MATCH(1,(GMW!$LQ$2:$LQ$60=F$3)*(GMW!$LP$2:$LP$60=F$4)*(GMW!$LR$2:$LR$60=F$1),0),$B15-1966)} -> 355.263 | G15: {=INDEX(GMW!$A$2:$LR$60,MATCH(1,(GMW!$LQ$2:$LQ$60=G$3)*(GMW!$LP$2:$LP$60=G$4)*(GMW!$LR$2:$LR$60=G$1),0),$B15-1966)} -> 257.134 | H15: {=INDEX(GMW!$A$2:$LR$60,MATCH(1,(GMW!$LQ$2:$LQ$60=H$3)*(GMW!$LP$2:$LP$60=H$4)*(GMW!$LR$2:$LR$60=H$1),0),$B15-1966)} -> 223.8772 | I15: {=INDEX(GMW!$A$2:$LR$60,MATCH(1,(GMW!$LQ$2:$LQ$60=I$3)*(GMW!$LP$2:$LP$60=I$4)*(GMW!$LR$2:$LR$60=I$1),0),$B15-1966)} -> 181499.5
A16: =+A12+1 -> 1975 | B16: =+B15+1 -> 1982 | C16: {=INDEX(GMW!$A$2:$LR$60,MATCH(1,(GMW!$LQ$2:$LQ$60=C$3)*(GMW!$LP$2:$LP$60=C$4)*(GMW!$LR$2:$LR$60=C$1),0),$B16-1966)} -> 212882 | D16: {=INDEX(GMW!$A$2:$LR$60,MATCH(1,(GMW!$LQ$2:$LQ$60=D$3)*(GMW!$LP$2:$LP$60=D$4)*(GMW!$LR$2:$LR$60=D$1),0),$B16-1966)} -> 1499.9 | E16: {=INDEX(GMW!$A$2:$LR$60,MATCH(1,(GMW!$LQ$2:$LQ$60=E$3)*(GMW!$LP$2:$LP$60=E$4)*(GMW!$LR$2:$LR$60=E$1),0),$B16-1966)} -> 53789.34 | F16: {=INDEX(GMW!$A$2:$LR$60,MATCH(1,(GMW!$LQ$2:$LQ$60=F$3)*(GMW!$LP$2:$LP$60=F$4)*(GMW!$LR$2:$LR$60=F$1),0),$B16-1966)} -> 353.5144 | G16: {=INDEX(GMW!$A$2:$LR$60,MATCH(1,(GMW!$LQ$2:$LQ$60=G$3)*(GMW!$LP$2:$LP$60=G$4)*(GMW!$LR$2:$LR$60=G$1),0),$B16-1966)} -> 257.051 | H16: {=INDEX(GMW!$A$2:$LR$60,MATCH(1,(GMW!$LQ$2:$LQ$60=H$3)*(GMW!$LP$2:$LP$60=H$4)*(GMW!$LR$2:$LR$60=H$1),0),$B16-1966)} -> 223.7629 | I16: {=INDEX(GMW!$A$2:$LR$60,MATCH(1,(GMW!$LQ$2:$LQ$60=I$3)*(GMW!$LP$2:$LP$60=I$4)*(GMW!$LR$2:$LR$60=I$1),0),$B16-1966)} -> 183828
A17: =+A13+1 -> 1975 | B17: =+B16+1 -> 1983 | C17: {=INDEX(GMW!$A$2:$LR$60,MATCH(1,(GMW!$LQ$2:$LQ$60=C$3)*(GMW!$LP$2:$LP$60=C$4)*(GMW!$LR$2:$LR$60=C$1),0),$B17-1966)} -> 212192 | D17: {=INDEX(GMW!$A$2:$LR$60,MATCH(1,(GMW!$LQ$2:$LQ$60=D$3)*(GMW!$LP$2:$LP$60=D$4)*(GMW!$LR$2:$LR$60=D$1),0),$B17-1966)} -> 1525.575 | E17: {=INDEX(GMW!$A$2:$LR$60,MATCH(1,(GMW!$LQ$2:$LQ$60=E$3)*(GMW!$LP$2:$LP$60=E$4)*(GMW!$LR$2:$LR$60=E$1),0),$B17-1966)} -> 54409.61 | F17: {=INDEX(GMW!$A$2:$LR$60,MATCH(1,(GMW!$LQ$2:$LQ$60=F$3)*(GMW!$LP$2:$LP$60=F$4)*(GMW!$LR$2:$LR$60=F$1),0),$B17-1966)} -> 357.3152 | G17: {=INDEX(GMW!$A$2:$LR$60,MATCH(1,(GMW!$LQ$2:$LQ$60=G$3)*(GMW!$LP$2:$LP$60=G$4)*(GMW!$LR$2:$LR$60=G$1),0),$B17-1966)} -> 256.883 | H17: {=INDEX(GMW!$A$2:$LR$60,MATCH(1,(GMW!$LQ$2:$LQ$60=H$3)*(GMW!$LP$2:$LP$60=H$4)*(GMW!$LR$2:$LR$60=H$1),0),$B17-1966)} -> 226.9424 | I17: {=INDEX(GMW!$A$2:$LR$60,MATCH(1,(GMW!$LQ$2:$LQ$60=I$3)*(GMW!$LP$2:$LP$60=I$4)*(GMW!$LR$2:$LR$60=I$1),0),$B17-1966)} -> 187354.8
A18: =+A14+1 -> 1975 | B18: =+B17+1 -> 1984 | C18: {=INDEX(GMW!$A$2:$LR$60,MATCH(1,(GMW!$LQ$2:$LQ$60=C$3)*(GMW!$LP$2:$LP$60=C$4)*(GMW!$LR$2:$LR$60=C$1),0),$B18-1966)} -> 214585 | D18: {=INDEX(GMW!$A$2:$LR$60,MATCH(1,(GMW!$LQ$2:$LQ$60=D$3)*(GMW!$LP$2:$LP$60=D$4)*(GMW!$LR$2:$LR$60=D$1),0),$B18-1966)} -> 1546.125 | E18: {=INDEX(GMW!$A$2:$LR$60,MATCH(1,(GMW!$LQ$2:$LQ$60=E$3)*(GMW!$LP$2:$LP$60=E$4)*(GMW!$LR$2:$LR$60=E$1),0),$B18-1966)} -> 54986.97 | F18: {=INDEX(GMW!$A$2:$LR$60,MATCH(1,(GMW!$LQ$2:$LQ$60=F$3)*(GMW!$LP$2:$LP$60=F$4)*(GMW!$LR$2:$LR$60=F$1),0),$B18-1966)} -> 364.4565 | G18: {=INDEX(GMW!$A$2:$LR$60,MATCH(1,(GMW!$LQ$2:$LQ$60=G$3)*(GMW!$LP$2:$LP$60=G$4)*(GMW!$LR$2:$LR$60=G$1),0),$B18-1966)} -> 262.376 | H18: {=INDEX(GMW!$A$2:$LR$60,MATCH(1,(GMW!$LQ$2:$LQ$60=H$3)*(GMW!$LP$2:$LP$60=H$4)*(GMW!$LR$2:$LR$60=H$1),0),$B18-1966)} -> 229.4855 | I18: {=INDEX(GMW!$A$2:$LR$60,MATCH(1,(GMW!$LQ$2:$LQ$60=I$3)*(GMW!$LP$2:$LP$60=I$4)*(GMW!$LR$2:$LR$60=I$1),0),$B18-1966)} -> 189522.8
A19: =+A15+1 -> 1976 | B19: =+B18+1 -> 1985 | C19: {=INDEX(GMW!$A$2:$LR$60,MATCH(1,(GMW!$LQ$2:$LQ$60=C$3)*(GMW!$LP$2:$LP$60=C$4)*(GMW!$LR$2:$LR$60=C$1),0),$B19-1966)} -> 218180 | D19: {=INDEX(GMW!$A$2:$LR$60,MATCH(1,(GMW!$LQ$2:$LQ$60=D$3)*(GMW!$LP$2:$LP$60=D$4)*(GMW!$LR$2:$LR$60=D$1),0),$B19-1966)} -> 1580.9 | E19: {=INDEX(GMW!$A$2:$LR$60,MATCH(1,(GMW!$LQ$2:$LQ$60=E$3)*(GMW!$LP$2:$LP$60=E$4)*(GMW!$LR$2:$LR$60=E$1),0),$B19-1966)} -> 55458.37 | F19: {=INDEX(GMW!$A$2:$LR$60,MATCH(1,(GMW!$LQ$2:$LQ$60=F$3)*(GMW!$LP$2:$LP$60=F$4)*(GMW!$LR$2:$LR$60=F$1),0),$B19-1966)} -> 367.5762 | G19: {=INDEX(GMW!$A$2:$LR$60,MATCH(1,(GMW!$LQ$2:$LQ$60=G$3)*(GMW!$LP$2:$LP$60=G$4)*(GMW!$LR$2:$LR$60=G$1),0),$B19-1966)} -> 264.851 | H19: {=INDEX(GMW!$A$2:$LR$60,MATCH(1,(GMW!$LQ$2:$LQ$60=H$3)*(GMW!$LP$2:$LP$60=H$4)*(GMW!$LR$2:$LR$60=H$1),0),$B19-1966)} -> 233.5283 | I19: {=INDEX(GMW!$A$2:$LR$60,MATCH(1,(GMW!$LQ$2:$LQ$60=I$3)*(GMW!$LP$2:$LP$60=I$4)*(GMW!$LR$2:$LR$60=I$1),0),$B19-1966)} -> 192825.5
A20: =+A16+1 -> 1976 | B20: =+B19+1 -> 1986 | C20: {=INDEX(GMW!$A$2:$LR$60,MATCH(1,(GMW!$LQ$2:$LQ$60=C$3)*(GMW!$LP$2:$LP$60=C$4)*(GMW!$LR$2:$LR$60=C$1),0),$B20-1966)} -> 217883 | D20: {=INDEX(GMW!$A$2:$LR$60,MATCH(1,(GMW!$LQ$2:$LQ$60=D$3)*(GMW!$LP$2:$LP$60=D$4)*(GMW!$LR$2:$LR$60=D$1),0),$B20-1966)} -> 1592.5 | E20: {=INDEX(GMW!$A$2:$LR$60,MATCH(1,(GMW!$LQ$2:$LQ$60=E$3)*(GMW!$LP$2:$LP$60=E$4)*(GMW!$LR$2:$LR$60=E$1),0),$B20-1966)} -> 55787.51 | F20: {=INDEX(GMW!$A$2:$LR$60,MATCH(1,(GMW!$LQ$2:$LQ$60=F$3)*(GMW!$LP$2:$LP$60=F$4)*(GMW!$LR$2:$LR$60=F$1),0),$B20-1966)} -> 373.1255 | G20: {=INDEX(GMW!$A$2:$LR$60,MATCH(1,(GMW!$LQ$2:$LQ$60=G$3)*(GMW!$LP$2:$LP$60=G$4)*(GMW!$LR$2:$LR$60=G$1),0),$B20-1966)} -> 268.472 | H20: {=INDEX(GMW!$A$2:$LR$60,MATCH(1,(GMW!$LQ$2:$LQ$60=H$3)*(GMW!$LP$2:$LP$60=H$4)*(GMW!$LR$2:$LR$60=H$1),0),$B20-1966)} -> 237.7498 | I20: {=INDEX(GMW!$A$2:$LR$60,MATCH(1,(GMW!$LQ$2:$LQ$60=I$3)*(GMW!$LP$2:$LP$60=I$4)*(GMW!$LR$2:$LR$60=I$1),0),$B20-1966)} -> 196983.8
A21: =+A17+1 -> 1976 | B21: =+B20+1 -> 1987 | C21: {=INDEX(GMW!$A$2:$LR$60,MATCH(1,(GMW!$LQ$2:$LQ$60=C$3)*(GMW!$LP$2:$LP$60=C$4)*(GMW!$LR$2:$LR$60=C$1),0),$B21-1966)} -> 220587 | D21: {=INDEX(GMW!$A$2:$LR$60,MATCH(1,(GMW!$LQ$2:$LQ$60=D$3)*(GMW!$LP$2:$LP$60=D$4)*(GMW!$LR$2:$LR$60=D$1),0),$B21-1966)} -> 1601.225 | E21: {=INDEX(GMW!$A$2:$LR$60,MATCH(1,(GMW!$LQ$2:$LQ$60=E$3)*(GMW!$LP$2:$LP$60=E$4)*(GMW!$LR$2:$LR$60=E$1),0),$B21-1966)} -> 56585.37 | F21: {=INDEX(GMW!$A$2:$LR$60,MATCH(1,(GMW!$LQ$2:$LQ$60=F$3)*(GMW!$LP$2:$LP$60=F$4)*(GMW!$LR$2:$LR$60=F$1),0),$B21-1966)} -> 373.282 | G21: {=INDEX(GMW!$A$2:$LR$60,MATCH(1,(GMW!$LQ$2:$LQ$60=G$3)*(GMW!$LP$2:$LP$60=G$4)*(GMW!$LR$2:$LR$60=G$1),0),$B21-1966)} -> 271.536 | H21: {=INDEX(GMW!$A$2:$LR$60,MATCH(1,(GMW!$LQ$2:$LQ$60=H$3)*(GMW!$LP$2:$LP$60=H$4)*(GMW!$LR$2:$LR$60=H$1),0),$B21-1966)} -> 243.7914 | I21: {=INDEX(GMW!$A$2:$LR$60,MATCH(1,(GMW!$LQ$2:$LQ$60=I$3)*(GMW!$LP$2:$LP$60=I$4)*(GMW!$LR$2:$LR$60=I$1),0),$B21-1966)} -> 197893.3
A22: =+A18+1 -> 1976 | B22: =+B21+1 -> 1988 | C22: {=INDEX(GMW!$A$2:$LR$60,MATCH(1,(GMW!$LQ$2:$LQ$60=C$3)*(GMW!$LP$2:$LP$60=C$4)*(GMW!$LR$2:$LR$60=C$1),0),$B22-1966)} -> 225228 | D22: {=INDEX(GMW!$A$2:$LR$60,MATCH(1,(GMW!$LQ$2:$LQ$60=D$3)*(GMW!$LP$2:$LP$60=D$4)*(GMW!$LR$2:$LR$60=D$1),0),$B22-1966)} -> 1612.8 | E22: {=INDEX(GMW!$A$2:$LR$60,MATCH(1,(GMW!$LQ$2:$LQ$60=E$3)*(GMW!$LP$2:$LP$60=E$4)*(GMW!$LR$2:$LR$60=E$1),0),$B22-1966)} -> 56653.35 | F22: {=INDEX(GMW!$A$2:$LR$60,MATCH(1,(GMW!$LQ$2:$LQ$60=F$3)*(GMW!$LP$2:$LP$60=F$4)*(GMW!$LR$2:$LR$60=F$1),0),$B22-1966)} -> 380.1196 | G22: {=INDEX(GMW!$A$2:$LR$60,MATCH(1,(GMW!$LQ$2:$LQ$60=G$3)*(GMW!$LP$2:$LP$60=G$4)*(GMW!$LR$2:$LR$60=G$1),0),$B22-1966)} -> 273.453 | H22: {=INDEX(GMW!$A$2:$LR$60,MATCH(1,(GMW!$LQ$2:$LQ$60=H$3)*(GMW!$LP$2:$LP$60=H$4)*(GMW!$LR$2:$LR$60=H$1),0),$B22-1966)} -> 248.021 | I22: {=INDEX(GMW!$A$2:$LR$60,MATCH(1,(GMW!$LQ$2:$LQ$60=I$3)*(GMW!$LP$2:$LP$60=I$4)*(GMW!$LR$2:$LR$60=I$1),0),$B22-1966)} -> 198213
... A318: =+A314+1 -> 2050 | B318: =+B317+1 -> 2284 | C318: {=INDEX(GMW!$A$2:$LR$60,MATCH(1,(GMW!$LQ$2:$LQ$60=C$3)*(GMW!$LP$2:$LP$60=C$4)*(GMW!$LR$2:$LR$60=C$1),0),$B318-1966)} -> 865547.4 | D318: {=INDEX(GMW!$A$2:$LR$60,MATCH(1,(GMW!$LQ$2:$LQ$60=D$3)*(GMW!$LP$2:$LP$60=D$4)*(GMW!$LR$2:$LR$60=D$1),0),$B318-1966)} -> 9207.993 | E318: {=INDEX(GMW!$A$2:$LR$60,MATCH(1,(GMW!$LQ$2:$LQ$60=E$3)*(GMW!$LP$2:$LP$60=E$4)*(GMW!$LR$2:$LR$60=E$1),0),$B318-1966)} -> 141280 | F318: {=INDEX(GMW!$A$2:$LR$60,MATCH(1,(GMW!$LQ$2:$LQ$60=F$3)*(GMW!$LP$2:$LP$60=F$4)*(GMW!$LR$2:$LR$60=F$1),0),$B318-1966)} -> 1079.367 | G318: {=INDEX(GMW!$A$2:$LR$60,MATCH(1,(GMW!$LQ$2:$LQ$60=G$3)*(GMW!$LP$2:$LP$60=G$4)*(GMW!$LR$2:$LR$60=G$1),0),$B318-1966)} -> 843.04 | H318: {=INDEX(GMW!$A$2:$LR$60,MATCH(1,(GMW!$LQ$2:$LQ$60=H$3)*(GMW!$LP$2:$LP$60=H$4)*(GMW!$LR$2:$LR$60=H$1),0),$B318-1966)} -> 489.9439 | I318: {=INDEX(GMW!$A$2:$LR$60,MATCH(1,(GMW!$LQ$2:$LQ$60=I$3)*(GMW!$LP$2:$LP$60=I$4)*(GMW!$LR$2:$LR$60=I$1),0),$B318-1966)} -> 1000668

Sheet ONS - Annex F
A1: Annex F: Impact of Blue Book 2024 changes on quarterly growth rates of real gross domestic product (chained volume measure) (Per cent growth: Q2 1997 to Q4 2022)
A2: Figures are in chained volume measures, seasonally adjusted.
A3: Reference year = 2024 for Blue Book 2022, Reference year = 2019 for Blue Book 2023 | I3: https://www.ons.gov.uk/economy/grossdomesticproductgdp/datasets/impactofbluebook2024changesongrossdomesticproductgdp
A4: Source: Office for National Statistics, UK National Accounts
A5: Time period | B5: GDP at market prices, £ million: Blue Book 2023/QNA | C5: GDP at market prices, £ million: Blue Book 2024 | D5: GDP at market prices, % growth on previous period: Blue Book 2023/QNA | E5: GDP at market prices, % growth on previous period: Blue Book 2024 | F5: GDP at market prices, revision (percentage points)
A6: 1997 Q1 | B6: 358611 | C6: 397303
A7: 1997 Q2 | B7: 362573 | C7: 401790 | D7: 1.1 | E7: 1.1 | F7: 0
A8: 1997 Q3 | B8: 365942 | C8: 405233 | D8: 0.9 | E8: 0.9 | F8: 0
A9: 1997 Q4 | B9: 371341 | C9: 411352 | D9: 1.5 | E9: 1.5 | F9: 0
A10: 1998 Q1 | B10: 374037 | C10: 414377 | D10: 0.7 | E10: 0.7 | F10: 0
A11: 1998 Q2 | B11: 376421 | C11: 416909 | D11: 0.6 | E11: 0.6 | F11: 0
A12: 1998 Q3 | B12: 377650 | C12: 418294 | D12: 0.3 | E12: 0.3 | F12: 0
A13: 1998 Q4 | B13: 380155 | C13: 421074 | D13: 0.7 | E13: 0.7 | F13: 0
A14: 1999 Q1 | B14: 382789 | C14: 423875 | D14: 0.7 | E14: 0.7 | F14: 0
A15: 1999 Q2 | B15: 384605 | C15: 425920 | D15: 0.5 | E15: 0.5 | F15: 0
A16: 1999 Q3 | B16: 390758 | C16: 432860 | D16: 1.6 | E16: 1.6 | F16: 0
A17: 1999 Q4 | B17: 396357 | C17: 439093 | D17: 1.4 | E17: 1.4 | F17: 0
A18: 2000 Q1 | B18: 401242 | C18: 444540 | D18: 1.2 | E18: 1.2 | F18: 0
... A109: 2022 Q4 | B109: 568034 | C109: 634044 | D109: 0.1 | E109: 0.3 | F109: 0.2

Sheet ONS - Table 1
A1: Table 1: Blue Book 2023: Gross value added (GVA) index 2019 = 100, chained volume measures, UK, seasonally adjusted
A2: This worksheet contains one table. Some cells refer to notes which can be found on the notes worksheet.
A3: Some cells in this table are empty because data is not collected for these variables.
A4: Source: GDP Blue Book 2023 estimates
