Workbook
Name _DLX1.INC: 'HAVER Q'!$A$3:$L$8
Name _DLX2.INC: 'HAVER M'!$A$4:$I$9

Sheet HAVER M
A4: 202101 !M | B4: KAI9@UK | C4: KAJ4@UK | D4: UKNVYM@UK | E4: yryr%(UKSEPPP3@UK)
A5: .DESC | B5: Great Britain: AWE, Regular Pay: Whole Economy [3Mo Mvg Avg vs Yr Ago] (SA, %) | C5: Great Britain: AWE, Regular Pay: Private Sector [3Mo Mvg Avg vs Yr Ago] (SA, %) | D5: UK: Indeed Wage Tracker: Posted Wage Growth: 3 Month MA (NSA, Y/Y% Chg) | E5: UK: Monthly Pay Dist: 50th Percentile: PAYE Real Time Information [RTI](SA, GBP) % Change - Year to Year | G5: XpertHR | H5: BoE projections
A6: .T1 | B6: Mar-2001 | C6: Mar-2001 | D6: Mar-2019 | E6: Sep-2014
A7: .TN | B7: Nov-2023 | C7: Nov-2023 | D7: Dec-2023 | E7: Nov-2023
A8: .LSOURCE | B8: Office for National Statistics | C8: Office for National Statistics | D8: Indeed Hiring Lab | E8: Office for National Statistics
A9: .DTLM | B9: Jan-16-2024 07:07 | C9: Jan-16-2024 07:07 | D9: Jan-16-2024 07:59 | E9: Jan-16-2024 07:07
A10: 202101 | B10: 4.3 | C10: 4.1 | D10: 3.2334876 | E10: 0.045108696 | G10: 1
A11: 202102 | B11: 4.4 | C11: 4.2 | D11: 3.2139832 | E11: 0.044348296 | G11: 1
A12: 202103 | B12: 4.6 | C12: 4.3 | D12: 3.0759643 | E12: 0.047001621 | G12: 1.2
A13: 202104 | B13: 5.7 | C13: 5.7 | D13: 2.2602196 | E13: 0.065609623 | G13: 2
A14: 202105 | B14: 6.6 | C14: 7.2 | D14: 1.905701 | E14: 0.08130531 | G14: 2
A15: 202106 | B15: 7.3 | C15: 8.4 | D15: 1.9802468 | E15: 0.089295618 | G15: 2
A16: 202107 | B16: 6.8 | C16: 7.8 | D16: 2.8207625 | E16: 0.078774617 | G16: 2
A17: 202108 | B17: 6 | C17: 6.7 | D17: 3.3846021 | E17: 0.066738428 | G17: 2
A18: 202109 | B18: 5 | C18: 5.5 | D18: 3.7359039 | E18: 0.058979809 | G18: 2
A19: 202110 | B19: 4.3 | C19: 4.6 | D19: 3.974137 | E19: 0.055292259 | G19: 2
A20: 202111 | B20: 3.8 | C20: 4.1 | D20: 4.1001032 | E20: 0.053926702 | G20: 2.5
A21: 202112 | B21: 3.7 | C21: 3.9 | D21: 4.3717699 | E21: 0.054744526 | G21: 2.3
... A44: 202311 | B44: 6.6 | C44: 6.5 | D44: 6.7176433 | E44: 0.061893764 | G44: 6
A45: 202312 | D45: 6.5935256 | H45: 7.2
H46: =NA() -> #N/A
H47: =NA() -> #N/A
H48: 6.5

Sheet HAVER Q
A3: 20161 !Q | B3: UNPD@UK | C3: yryr%(D7BT@UK)
A4: .DESC | B4: UK: BoE CPI Projections Based on Expected Interest Rate: Mode (Y/Y % Chg) | C4: UK: Consumer Price Index: All Items (NSA, 2015=100) % Change - Year to Year | E4: OE inflation profile
A5: .T1 | B5: Q4-2023 | C5: Q1-1988 <- Jan-1988
A6: .TN | B6: Q4-2026 | C6: Q4-2023 <- Dec-2023
A7: .LSOURCE | B7: Bank of England | C7: Office for National Statistics
A8: .DTLM | B8: Nov-02-2023 12:05 | C8: Jan-17-2024 07:04
A9: 20161 | B9: #N/A | C9: 0.0033500838 | E9: 0.33501508
A10: 20162 | B10: #N/A | C10: 0.0033311126 | E10: 0.33307784
A11: 20163 | B11: #N/A | C11: 0.0069883527 | E11: 0.69883504
A12: 20164 | B12: #N/A | C12: 0.011964108 | E12: 1.1964108
A13: 20171 | B13: #N/A | C13: 0.021702838 | E13: 2.170277
A14: 20172 | B14: #N/A | C14: 0.027556441 | E14: 2.7556773
A15: 20173 | B15: #N/A | C15: 0.028089888 | E15: 2.8089548
A16: 20174 | B16: #N/A | C16: 0.030213465 | E16: 3.0213793
A17: 20181 | B17: #N/A | C17: 0.027124183 | E17: 2.712451
A18: 20182 | B18: #N/A | C18: 0.024232633 | E18: 2.4232625
A19: 20183 | B19: #N/A | C19: 0.025072324 | E19: 2.5072324
A20: 20184 | B20: #N/A | C20: 0.022633089 | E20: 2.2632444
... A39: 20233 | B39: #N/A | C39: 0.067135896 | E39: 6.7136185
A40: 20234 | B40: 4.6 | C40: 0.041568008 | E40: 4.1568272
A41: 20241 | B41: 4.4 | E41: 3.7175114
A42: 20242 | B42: 3.6 | E42: 1.5669884
A43: 20243 | B43: 3.3 | E43: 1.6362253
A44: 20244 | B44: 3.1 | E44: 1.4807523
A45: 20251 | B45: 2.5 | E45: 1.3036508
A46: 20252 | B46: 2.1 | E46: 1.5199011
A47: 20253 | B47: 2.1 | E47: 1.6171471
A48: 20254 | B48: 1.9 | E48: 1.7548432
A49: 20261 | B49: 1.9 | E49: 1.8445871
A50: 20262 | B50: 1.7 | E50: 1.8469956
A51: 20263 | B51: 1.6 | E51: 1.8286828
A52: 20264 | B52: 1.5 | E52: 1.8011916

Sheet Chart Data
B1: ONS AWE regular pay | C1: ONS AWE private sector regular pay | D1: ONS RTI median employee pay | E1: Indeed Wage Tracker | F1: XpertHR | G1: BoE November forecast | H1: OE-Penta regular pay indicator | L1: Oxford Economics (Jan-24) | M1: Bank of England modal forecast (Latest - Nov-23) | N1: 2% target
A2: 44197 | B2: ='HAVER M'!B10 -> 4.3 | C2: ='HAVER M'!C10 -> 4.1 | D2: ='HAVER M'!E10*100 -> 4.5108696 | E2: ='HAVER M'!D10 -> 3.2334876 | F2: ='HAVER M'!G10 -> 1 | G2: =NA() -> #N/A | H2: ='[1]Wages data'!$L79 -> 4.4523075 | K2: =LEFT('HAVER Q'!A9,4) -> 2016 | L2: ='HAVER Q'!E9 -> 0.33501508 | M2: =NA() -> #N/A | N2: 2
A3: 44228 | B3: ='HAVER M'!B11 -> 4.4 | C3: ='HAVER M'!C11 -> 4.2 | D3: ='HAVER M'!E11*100 -> 4.4348296 | E3: ='HAVER M'!D11 -> 3.2139832 | F3: ='HAVER M'!G11 -> 1 | G3: =NA() -> #N/A | H3: ='[1]Wages data'!$L80 -> 4.2700779 | K3: =LEFT('HAVER Q'!A10,4) -> 2016 | L3: ='HAVER Q'!E10 -> 0.33307784 | M3: =NA() -> #N/A | N3: 2
A4: 44256 | B4: ='HAVER M'!B12 -> 4.6 | C4: ='HAVER M'!C12 -> 4.3 | D4: ='HAVER M'!E12*100 -> 4.7001621 | E4: ='HAVER M'!D12 -> 3.0759643 | F4: ='HAVER M'!G12 -> 1.2 | G4: =NA() -> #N/A | H4: ='[1]Wages data'!$L81 -> 5.0103525 | K4: =LEFT('HAVER Q'!A11,4) -> 2016 | L4: ='HAVER Q'!E11 -> 0.69883504 | M4: =NA() -> #N/A | N4: 2
A5: 44287 | B5: ='HAVER M'!B13 -> 5.7 | C5: ='HAVER M'!C13 -> 5.7 | D5: ='HAVER M'!E13*100 -> 6.5609623 | E5: ='HAVER M'!D13 -> 2.2602196 | F5: ='HAVER M'!G13 -> 2 | G5: =NA() -> #N/A | H5: ='[1]Wages data'!$L82 -> 8.6422759 | K5: =LEFT('HAVER Q'!A12,4) -> 2016 | L5: ='HAVER Q'!E12 -> 1.1964108 | M5: =NA() -> #N/A | N5: 2
A6: 44317 | B6: ='HAVER M'!B14 -> 6.6 | C6: ='HAVER M'!C14 -> 7.2 | D6: ='HAVER M'!E14*100 -> 8.130531 | E6: ='HAVER M'!D14 -> 1.905701 | F6: ='HAVER M'!G14 -> 2 | G6: =NA() -> #N/A | H6: ='[1]Wages data'!$L83 -> 8.4870707 | K6: =LEFT('HAVER Q'!A13,4) -> 2017 | L6: ='HAVER Q'!E13 -> 2.170277 | M6: =NA() -> #N/A | N6: 2
A7: 44348 | B7: ='HAVER M'!B15 -> 7.3 | C7: ='HAVER M'!C15 -> 8.4 | D7: ='HAVER M'!E15*100 -> 8.9295618 | E7: ='HAVER M'!D15 -> 1.9802468 | F7: ='HAVER M'!G15 -> 2 | G7: =NA() -> #N/A | H7: ='[1]Wages data'!$L84 -> 7.9822522 | K7: =LEFT('HAVER Q'!A14,4) -> 2017 | L7: ='HAVER Q'!E14 -> 2.7556773 | M7: =NA() -> #N/A | N7: 2
A8: 44378 | B8: ='HAVER M'!B16 -> 6.8 | C8: ='HAVER M'!C16 -> 7.8 | D8: ='HAVER M'!E16*100 -> 7.8774617 | E8: ='HAVER M'!D16 -> 2.8207625 | F8: ='HAVER M'!G16 -> 2 | G8: =NA() -> #N/A | H8: ='[1]Wages data'!$L85 -> 7.8057916 | K8: =LEFT('HAVER Q'!A15,4) -> 2017 | L8: ='HAVER Q'!E15 -> 2.8089548 | M8: =NA() -> #N/A | N8: 2
A9: 44409 | B9: ='HAVER M'!B17 -> 6 | C9: ='HAVER M'!C17 -> 6.7 | D9: ='HAVER M'!E17*100 -> 6.6738428 | E9: ='HAVER M'!D17 -> 3.3846021 | F9: ='HAVER M'!G17 -> 2 | G9: =NA() -> #N/A | H9: ='[1]Wages data'!$L86 -> 7.1153515 | K9: =LEFT('HAVER Q'!A16,4) -> 2017 | L9: ='HAVER Q'!E16 -> 3.0213793 | M9: =NA() -> #N/A | N9: 2
A10: 44440 | B10: ='HAVER M'!B18 -> 5 | C10: ='HAVER M'!C18 -> 5.5 | D10: ='HAVER M'!E18*100 -> 5.8979809 | E10: ='HAVER M'!D18 -> 3.7359039 | F10: ='HAVER M'!G18 -> 2 | G10: =NA() -> #N/A | H10: ='[1]Wages data'!$L87 -> 3.8074536 | K10: =LEFT('HAVER Q'!A17,4) -> 2018 | L10: ='HAVER Q'!E17 -> 2.712451 | M10: =NA() -> #N/A | N10: 2
A11: 44470 | B11: ='HAVER M'!B19 -> 4.3 | C11: ='HAVER M'!C19 -> 4.6 | D11: ='HAVER M'!E19*100 -> 5.5292259 | E11: ='HAVER M'!D19 -> 3.974137 | F11: ='HAVER M'!G19 -> 2 | G11: =NA() -> #N/A | H11: ='[1]Wages data'!$L88 -> 4.6500968 | K11: =LEFT('HAVER Q'!A18,4) -> 2018 | L11: ='HAVER Q'!E18 -> 2.4232625 | M11: =NA() -> #N/A | N11: 2
A12: 44501 | B12: ='HAVER M'!B20 -> 3.8 | C12: ='HAVER M'!C20 -> 4.1 | D12: ='HAVER M'!E20*100 -> 5.3926702 | E12: ='HAVER M'!D20 -> 4.1001032 | F12: ='HAVER M'!G20 -> 2.5 | G12: =NA() -> #N/A | H12: ='[1]Wages data'!$L89 -> 4.3678804 | K12: =LEFT('HAVER Q'!A19,4) -> 2018 | L12: ='HAVER Q'!E19 -> 2.5072324 | M12: =NA() -> #N/A | N12: 2
A13: 44531 | B13: ='HAVER M'!B21 -> 3.7 | C13: ='HAVER M'!C21 -> 3.9 | D13: ='HAVER M'!E21*100 -> 5.4744526 | E13: ='HAVER M'!D21 -> 4.3717699 | F13: ='HAVER M'!G21 -> 2.3 | G13: =NA() -> #N/A | H13: ='[1]Wages data'!$L90 -> 5.3609097 | K13: =LEFT('HAVER Q'!A20,4) -> 2018 | L13: ='HAVER Q'!E20 -> 2.2632444 | M13: =NA() -> #N/A | N13: 2
... A31: 45078 | B31: ='HAVER M'!B39 -> 7.8 | C31: ='HAVER M'!C39 -> 8.2 | D31: ='HAVER M'!E39*100 -> 8.3413231 | E31: ='HAVER M'!D39 -> 7.3998335 | F31: ='HAVER M'!G39 -> 6 | G31: =NA() -> #N/A | H31: ='[1]Wages data'!$L108 -> 8.1580844 | K31: =LEFT('HAVER Q'!A38,4) -> 2023 | L31: ='HAVER Q'!E38 -> 8.439049 | M31: =NA() -> #N/A | N31: 2
A32: 45108 | B32: ='HAVER M'!B40 -> 7.9 | C32: ='HAVER M'!C40 -> 8.1 | D32: ='HAVER M'!E40*100 -> 8.4802287 | E32: ='HAVER M'!D40 -> 7.3036252 | F32: ='HAVER M'!G40 -> 5.7 | G32: =NA() -> #N/A | H32: ='[1]Wages data'!$L109 -> 8.1815169 | K32: =LEFT('HAVER Q'!A39,4) -> 2023 | L32: ='HAVER Q'!E39 -> 6.7136185 | M32: =L32 -> 6.7136185 | N32: 2
A33: 45139 | B33: ='HAVER M'!B41 -> 7.9 | C33: ='HAVER M'!C41 -> 8.1 | D33: ='HAVER M'!E41*100 -> 8.2386364 | E33: ='HAVER M'!D41 -> 7.2768894 | F33: ='HAVER M'!G41 -> 5 | G33: =NA() -> #N/A | H33: ='[1]Wages data'!$L110 -> 7.6941703 | K33: =LEFT('HAVER Q'!A40,4) -> 2023 | L33: ='HAVER Q'!E40 -> 4.1568272 | M33: ='HAVER Q'!B40 -> 4.6 | N33: 2
A34: 45170 | B34: ='HAVER M'!B42 -> 7.8 | C34: ='HAVER M'!C42 -> 7.9 | D34: ='HAVER M'!E42*100 -> 7.0051716 | E34: ='HAVER M'!D42 -> 7.1159491 | F34: ='HAVER M'!G42 -> 5.4 | G34: =NA() -> #N/A | H34: ='[1]Wages data'!$L111 -> 7.1815804 | K34: =LEFT('HAVER Q'!A41,4) -> 2024 | L34: ='HAVER Q'!E41 -> 3.7175114 | M34: ='HAVER Q'!B41 -> 4.4 | N34: 2
A35: 45200 | B35: ='HAVER M'!B43 -> 7.2 | C35: ='HAVER M'!C43 -> 7.2 | D35: ='HAVER M'!E43*100 -> 6.588785 | E35: ='HAVER M'!D43 -> 6.9654404 | F35: ='HAVER M'!G43 -> 6 | G35: =NA() -> #N/A | H35: ='[1]Wages data'!$L112 -> 6.8482767 | K35: =LEFT('HAVER Q'!A42,4) -> 2024 | L35: ='HAVER Q'!E42 -> 1.5669884 | M35: ='HAVER Q'!B42 -> 3.6 | N35: 2
A36: 45231 | B36: ='HAVER M'!B44 -> 6.6 | C36: ='HAVER M'!C44 -> 6.5 | D36: ='HAVER M'!E44*100 -> 6.1893764 | E36: ='HAVER M'!D44 -> 6.7176433 | F36: ='HAVER M'!G44 -> 6 | G36: =NA() -> #N/A | H36: ='[1]Wages data'!$L113 -> 6.1591485 | K36: =LEFT('HAVER Q'!A43,4) -> 2024 | L36: ='HAVER Q'!E43 -> 1.6362253 | M36: ='HAVER Q'!B43 -> 3.3 | N36: 2
A37: 45261 | B37: =NA() -> #N/A | C37: =NA() -> #N/A | D37: =NA() -> #N/A | E37: ='HAVER M'!D45 -> 6.5935256 | F37: =NA() -> #N/A | G37: 7.2 | H37: ='[1]Wages data'!$L114 -> 6.2948701 | K37: =LEFT('HAVER Q'!A44,4) -> 2024 | L37: ='HAVER Q'!E44 -> 1.4807523 | M37: ='HAVER Q'!B44 -> 3.1 | N37: 2
A38: 45292 | B38: =NA() -> #N/A | C38: =NA() -> #N/A | D38: =NA() -> #N/A | E38: =NA() -> #N/A | F38: =NA() -> #N/A | G38: =NA() -> #N/A | H38: ='[1]Wages data'!$L115 -> 6.7198473 | K38: =LEFT('HAVER Q'!A45,4) -> 2025 | L38: ='HAVER Q'!E45 -> 1.3036508 | M38: ='HAVER Q'!B45 -> 2.5 | N38: 2
A39: 45323 | B39: =NA() -> #N/A | C39: =NA() -> #N/A | D39: =NA() -> #N/A | E39: =NA() -> #N/A | F39: =NA() -> #N/A | G39: =NA() -> #N/A | K39: =LEFT('HAVER Q'!A46,4) -> 2025 | L39: ='HAVER Q'!E46 -> 1.5199011 | M39: ='HAVER Q'!B46 -> 2.1 | N39: 2
A40: 45352 | B40: =NA() -> #N/A | C40: =NA() -> #N/A | D40: =NA() -> #N/A | E40: =NA() -> #N/A | F40: =NA() -> #N/A | G40: 6.5 | K40: =LEFT('HAVER Q'!A47,4) -> 2025 | L40: ='HAVER Q'!E47 -> 1.6171471 | M40: ='HAVER Q'!B47 -> 2.1 | N40: 2
K41: =LEFT('HAVER Q'!A48,4) -> 2025 | L41: ='HAVER Q'!E48 -> 1.7548432 | M41: ='HAVER Q'!B48 -> 1.9 | N41: 2
K42: =LEFT('HAVER Q'!A49,4) -> 2026 | L42: ='HAVER Q'!E49 -> 1.8445871 | M42: ='HAVER Q'!B49 -> 1.9 | N42: 2
K43: =LEFT('HAVER Q'!A50,4) -> 2026 | L43: ='HAVER Q'!E50 -> 1.8469956 | M43: ='HAVER Q'!B50 -> 1.7 | N43: 2
K44: =LEFT('HAVER Q'!A51,4) -> 2026 | L44: ='HAVER Q'!E51 -> 1.8286828 | M44: ='HAVER Q'!B51 -> 1.6 | N44: 2
K45: =LEFT('HAVER Q'!A52,4) -> 2026 | L45: ='HAVER Q'!E52 -> 1.8011916 | M45: ='HAVER Q'!B52 -> 1.5 | N45: 2
