Workbook
Name _DLX1.INC: HAVERD!$G$3:$BV$8
Name _DLX2.INC: HAVERM!$B$1:$F$6
Name _DLX3.INC: 'Haver Q'!$A$4:$G$9

Sheet Chart Data
B1: November MPR | D1: 15 working days to 28 Oct 2024
B2: Column # | C2: =HAVERD!I1 -> 9 | D2: =HAVERD!J1 -> 10 | E2: =HAVERD!K1 -> 11 | F2: =HAVERD!L1 -> 12 | G2: =HAVERD!M1 -> 13 | H2: =HAVERD!N1 -> 14 | I2: =HAVERD!O1 -> 15 | J2: =HAVERD!P1 -> 16 | ... AY2: =HAVERD!BE1 -> 57
B3: Months | C3: =HAVERD!I2 -> Overnight | D3: =HAVERD!J2 -> 1 | E3: =HAVERD!K2 -> 2 | F3: =HAVERD!L2 -> 3 | G3: =HAVERD!M2 -> 4 | H3: =HAVERD!N2 -> 5 | I3: =HAVERD!O2 -> 6 | J3: =HAVERD!P2 -> 7 | ... AY3: =HAVERD!BE2 -> 48
B4: Days | D4: 30.416667 | E4: =+D4+30.4166667 -> 60.833333 | F4: =+E4+30.4166667 -> 91.25 | G4: =+F4+30.4166667 -> 121.66667 | H4: =+G4+30.4166667 -> 152.08333 | I4: =+H4+30.4166667 -> 182.5 | J4: =+I4+30.4166667 -> 212.91667 | K4: =+J4+30.4166667 -> 243.33333 | L4: =+K4+30.4166667 -> 273.75 | ... AY4: =+AX4+30.4166667 -> 1460
B5: Dates
B6: =B11-7 -> 45574 | C6: =B6 -> 45574 | D6: =$C6+D$4 -> 45604.417 | E6: =$C6+E$4 -> 45634.833 | F6: =$C6+F$4 -> 45665.25 | G6: =$C6+G$4 -> 45695.667 | H6: =$C6+H$4 -> 45726.083 | I6: =$C6+I$4 -> 45756.5 | J6: =$C6+J$4 -> 45786.917 | K6: =$C6+K$4 -> 45817.333 | ... AY6: =$C6+AY$4 -> 47034
B7: =B12-7 -> 45575 | C7: =B7 -> 45575 | D7: =$C7+D$4 -> 45605.417 | E7: =$C7+E$4 -> 45635.833 | F7: =$C7+F$4 -> 45666.25 | G7: =$C7+G$4 -> 45696.667 | H7: =$C7+H$4 -> 45727.083 | I7: =$C7+I$4 -> 45757.5 | J7: =$C7+J$4 -> 45787.917 | K7: =$C7+K$4 -> 45818.333 | ... AY7: =$C7+AY$4 -> 47035
B8: =B13-7 -> 45576 | C8: =B8 -> 45576 | D8: =$C8+D$4 -> 45606.417 | E8: =$C8+E$4 -> 45636.833 | F8: =$C8+F$4 -> 45667.25 | G8: =$C8+G$4 -> 45697.667 | H8: =$C8+H$4 -> 45728.083 | I8: =$C8+I$4 -> 45758.5 | J8: =$C8+J$4 -> 45788.917 | K8: =$C8+K$4 -> 45819.333 | ... AY8: =$C8+AY$4 -> 47036
B9: =B14-7 -> 45579 | C9: =B9 -> 45579 | D9: =$C9+D$4 -> 45609.417 | E9: =$C9+E$4 -> 45639.833 | F9: =$C9+F$4 -> 45670.25 | G9: =$C9+G$4 -> 45700.667 | H9: =$C9+H$4 -> 45731.083 | I9: =$C9+I$4 -> 45761.5 | J9: =$C9+J$4 -> 45791.917 | K9: =$C9+K$4 -> 45822.333 | ... AY9: =$C9+AY$4 -> 47039
B10: =B15-7 -> 45580 | C10: =B10 -> 45580 | D10: =$C10+D$4 -> 45610.417 | E10: =$C10+E$4 -> 45640.833 | F10: =$C10+F$4 -> 45671.25 | G10: =$C10+G$4 -> 45701.667 | H10: =$C10+H$4 -> 45732.083 | I10: =$C10+I$4 -> 45762.5 | J10: =$C10+J$4 -> 45792.917 | K10: =$C10+K$4 -> 45823.333 | ... AY10: =$C10+AY$4 -> 47040
B11: =B16-7 -> 45581 | C11: =B11 -> 45581 | D11: =$C11+D$4 -> 45611.417 | E11: =$C11+E$4 -> 45641.833 | F11: =$C11+F$4 -> 45672.25 | G11: =$C11+G$4 -> 45702.667 | H11: =$C11+H$4 -> 45733.083 | I11: =$C11+I$4 -> 45763.5 | J11: =$C11+J$4 -> 45793.917 | K11: =$C11+K$4 -> 45824.333 | ... AY11: =$C11+AY$4 -> 47041
B12: =B17-7 -> 45582 | C12: =B12 -> 45582 | D12: =$C12+D$4 -> 45612.417 | E12: =$C12+E$4 -> 45642.833 | F12: =$C12+F$4 -> 45673.25 | G12: =$C12+G$4 -> 45703.667 | H12: =$C12+H$4 -> 45734.083 | I12: =$C12+I$4 -> 45764.5 | J12: =$C12+J$4 -> 45794.917 | K12: =$C12+K$4 -> 45825.333 | ... AY12: =$C12+AY$4 -> 47042
B13: =B18-7 -> 45583 | C13: =B13 -> 45583 | D13: =$C13+D$4 -> 45613.417 | E13: =$C13+E$4 -> 45643.833 | F13: =$C13+F$4 -> 45674.25 | G13: =$C13+G$4 -> 45704.667 | H13: =$C13+H$4 -> 45735.083 | I13: =$C13+I$4 -> 45765.5 | J13: =$C13+J$4 -> 45795.917 | K13: =$C13+K$4 -> 45826.333 | ... AY13: =$C13+AY$4 -> 47043
B14: =B19-7 -> 45586 | C14: =B14 -> 45586 | D14: =$C14+D$4 -> 45616.417 | E14: =$C14+E$4 -> 45646.833 | F14: =$C14+F$4 -> 45677.25 | G14: =$C14+G$4 -> 45707.667 | H14: =$C14+H$4 -> 45738.083 | I14: =$C14+I$4 -> 45768.5 | J14: =$C14+J$4 -> 45798.917 | K14: =$C14+K$4 -> 45829.333 | ... AY14: =$C14+AY$4 -> 47046
B15: =B20-7 -> 45587 | C15: =B15 -> 45587 | D15: =$C15+D$4 -> 45617.417 | E15: =$C15+E$4 -> 45647.833 | F15: =$C15+F$4 -> 45678.25 | G15: =$C15+G$4 -> 45708.667 | H15: =$C15+H$4 -> 45739.083 | I15: =$C15+I$4 -> 45769.5 | J15: =$C15+J$4 -> 45799.917 | K15: =$C15+K$4 -> 45830.333 | ... AY15: =$C15+AY$4 -> 47047
A16: =TEXT(B16,"dddd") -> Wednesday | B16: =IF(A17="Monday",B17-3,B17-1) -> 45588 | C16: =B16 -> 45588 | D16: =$C16+D$4 -> 45618.417 | E16: =$C16+E$4 -> 45648.833 | F16: =$C16+F$4 -> 45679.25 | G16: =$C16+G$4 -> 45709.667 | H16: =$C16+H$4 -> 45740.083 | I16: =$C16+I$4 -> 45770.5 | J16: =$C16+J$4 -> 45800.917 | K16: =$C16+K$4 -> 45831.333 | ... AY16: =$C16+AY$4 -> 47048
A17: =TEXT(B17,"dddd") -> Thursday | B17: =IF(A18="Monday",B18-3,B18-1) -> 45589 | C17: =B17 -> 45589 | D17: =$C17+D$4 -> 45619.417 | E17: =$C17+E$4 -> 45649.833 | F17: =$C17+F$4 -> 45680.25 | G17: =$C17+G$4 -> 45710.667 | H17: =$C17+H$4 -> 45741.083 | I17: =$C17+I$4 -> 45771.5 | J17: =$C17+J$4 -> 45801.917 | K17: =$C17+K$4 -> 45832.333 | ... AY17: =$C17+AY$4 -> 47049
A18: =TEXT(B18,"dddd") -> Friday | B18: =IF(A19="Monday",B19-3,B19-1) -> 45590 | C18: =B18 -> 45590 | D18: =$C18+D$4 -> 45620.417 | E18: =$C18+E$4 -> 45650.833 | F18: =$C18+F$4 -> 45681.25 | G18: =$C18+G$4 -> 45711.667 | H18: =$C18+H$4 -> 45742.083 | I18: =$C18+I$4 -> 45772.5 | J18: =$C18+J$4 -> 45802.917 | K18: =$C18+K$4 -> 45833.333 | ... AY18: =$C18+AY$4 -> 47050
A19: =TEXT(B19,"dddd") -> Monday | B19: =IF(A20="Monday",B20-3,B20-1) -> 45593 | C19: =B19 -> 45593 | D19: =$C19+D$4 -> 45623.417 | E19: =$C19+E$4 -> 45653.833 | F19: =$C19+F$4 -> 45684.25 | G19: =$C19+G$4 -> 45714.667 | H19: =$C19+H$4 -> 45745.083 | I19: =$C19+I$4 -> 45775.5 | J19: =$C19+J$4 -> 45805.917 | K19: =$C19+K$4 -> 45836.333 | ... AY19: =$C19+AY$4 -> 47053
A20: =TEXT(B20,"dddd") -> Tuesday | B20: 45594 | C20: =B20 -> 45594 | D20: =$C20+D$4 -> 45624.417 | E20: =$C20+E$4 -> 45654.833 | F20: =$C20+F$4 -> 45685.25 | G20: =$C20+G$4 -> 45715.667 | H20: =$C20+H$4 -> 45746.083 | I20: =$C20+I$4 -> 45776.5 | J20: =$C20+J$4 -> 45806.917 | K20: =$C20+K$4 -> 45837.333 | ... AY20: =$C20+AY$4 -> 47054
B22: Market expectations
B23: =B6 -> 45574 | C23: =VLOOKUP($B23,HAVERD!$A:$BS,C$2,FALSE) -> 4.95 | D23: =VLOOKUP($B23,HAVERD!$A:$BS,D$2,FALSE) -> 4.8392344 | E23: =VLOOKUP($B23,HAVERD!$A:$BS,E$2,FALSE) -> 4.6898294 | F23: =VLOOKUP($B23,HAVERD!$A:$BS,F$2,FALSE) -> 4.5714834 | G23: =VLOOKUP($B23,HAVERD!$A:$BS,G$2,FALSE) -> 4.4638079 | H23: =VLOOKUP($B23,HAVERD!$A:$BS,H$2,FALSE) -> 4.3570305 | I23: =VLOOKUP($B23,HAVERD!$A:$BS,I$2,FALSE) -> 4.253062 | J23: =VLOOKUP($B23,HAVERD!$A:$BS,J$2,FALSE) -> 4.1565231 | ... AY23: =VLOOKUP($B23,HAVERD!$A:$BS,AY$2,FALSE) -> 3.5754092
B24: =B7 -> 45575 | C24: =VLOOKUP($B24,HAVERD!$A:$BS,C$2,FALSE) -> 4.95 | D24: =VLOOKUP($B24,HAVERD!$A:$BS,D$2,FALSE) -> 4.8360175 | E24: =VLOOKUP($B24,HAVERD!$A:$BS,E$2,FALSE) -> 4.6861475 | F24: =VLOOKUP($B24,HAVERD!$A:$BS,F$2,FALSE) -> 4.5642992 | G24: =VLOOKUP($B24,HAVERD!$A:$BS,G$2,FALSE) -> 4.4507986 | H24: =VLOOKUP($B24,HAVERD!$A:$BS,H$2,FALSE) -> 4.3378835 | I24: =VLOOKUP($B24,HAVERD!$A:$BS,I$2,FALSE) -> 4.2286761 | J24: =VLOOKUP($B24,HAVERD!$A:$BS,J$2,FALSE) -> 4.1278571 | ... AY24: =VLOOKUP($B24,HAVERD!$A:$BS,AY$2,FALSE) -> 3.6084418
B25: =B8 -> 45576 | C25: =VLOOKUP($B25,HAVERD!$A:$BS,C$2,FALSE) -> 4.95 | D25: =VLOOKUP($B25,HAVERD!$A:$BS,D$2,FALSE) -> 4.830099 | E25: =VLOOKUP($B25,HAVERD!$A:$BS,E$2,FALSE) -> 4.6749844 | F25: =VLOOKUP($B25,HAVERD!$A:$BS,F$2,FALSE) -> 4.5457742 | G25: =VLOOKUP($B25,HAVERD!$A:$BS,G$2,FALSE) -> 4.423792 | H25: =VLOOKUP($B25,HAVERD!$A:$BS,H$2,FALSE) -> 4.3019174 | I25: =VLOOKUP($B25,HAVERD!$A:$BS,I$2,FALSE) -> 4.1846934 | J25: =VLOOKUP($B25,HAVERD!$A:$BS,J$2,FALSE) -> 4.0786496 | ... AY25: =VLOOKUP($B25,HAVERD!$A:$BS,AY$2,FALSE) -> 3.6001446
B26: =B9 -> 45579 | C26: =VLOOKUP($B26,HAVERD!$A:$BS,C$2,FALSE) -> 4.95 | D26: =VLOOKUP($B26,HAVERD!$A:$BS,D$2,FALSE) -> 4.8075783 | E26: =VLOOKUP($B26,HAVERD!$A:$BS,E$2,FALSE) -> 4.6717311 | F26: =VLOOKUP($B26,HAVERD!$A:$BS,F$2,FALSE) -> 4.5557245 | G26: =VLOOKUP($B26,HAVERD!$A:$BS,G$2,FALSE) -> 4.4414894 | H26: =VLOOKUP($B26,HAVERD!$A:$BS,H$2,FALSE) -> 4.3232448 | I26: =VLOOKUP($B26,HAVERD!$A:$BS,I$2,FALSE) -> 4.2068587 | J26: =VLOOKUP($B26,HAVERD!$A:$BS,J$2,FALSE) -> 4.0999515 | ... AY26: =VLOOKUP($B26,HAVERD!$A:$BS,AY$2,FALSE) -> 3.6176902
B27: =B10 -> 45580 | C27: =VLOOKUP($B27,HAVERD!$A:$BS,C$2,FALSE) -> 4.95 | D27: =VLOOKUP($B27,HAVERD!$A:$BS,D$2,FALSE) -> 4.8042216 | E27: =VLOOKUP($B27,HAVERD!$A:$BS,E$2,FALSE) -> 4.6688134 | F27: =VLOOKUP($B27,HAVERD!$A:$BS,F$2,FALSE) -> 4.5480962 | G27: =VLOOKUP($B27,HAVERD!$A:$BS,G$2,FALSE) -> 4.4272003 | H27: =VLOOKUP($B27,HAVERD!$A:$BS,H$2,FALSE) -> 4.3027498 | I27: =VLOOKUP($B27,HAVERD!$A:$BS,I$2,FALSE) -> 4.181326 | J27: =VLOOKUP($B27,HAVERD!$A:$BS,J$2,FALSE) -> 4.0705947 | ... AY27: =VLOOKUP($B27,HAVERD!$A:$BS,AY$2,FALSE) -> 3.549409
B28: =B11 -> 45581 | C28: =VLOOKUP($B28,HAVERD!$A:$BS,C$2,FALSE) -> 4.95 | D28: =VLOOKUP($B28,HAVERD!$A:$BS,D$2,FALSE) -> 4.7700832 | E28: =VLOOKUP($B28,HAVERD!$A:$BS,E$2,FALSE) -> 4.618622 | F28: =VLOOKUP($B28,HAVERD!$A:$BS,F$2,FALSE) -> 4.4825589 | G28: =VLOOKUP($B28,HAVERD!$A:$BS,G$2,FALSE) -> 4.3493559 | H28: =VLOOKUP($B28,HAVERD!$A:$BS,H$2,FALSE) -> 4.2159912 | I28: =VLOOKUP($B28,HAVERD!$A:$BS,I$2,FALSE) -> 4.0880923 | J28: =VLOOKUP($B28,HAVERD!$A:$BS,J$2,FALSE) -> 3.9724897 | ... AY28: =VLOOKUP($B28,HAVERD!$A:$BS,AY$2,FALSE) -> 3.4714759
B29: =B12 -> 45582 | C29: =VLOOKUP($B29,HAVERD!$A:$BS,C$2,FALSE) -> 4.95 | D29: =VLOOKUP($B29,HAVERD!$A:$BS,D$2,FALSE) -> 4.7696391 | E29: =VLOOKUP($B29,HAVERD!$A:$BS,E$2,FALSE) -> 4.6221703 | F29: =VLOOKUP($B29,HAVERD!$A:$BS,F$2,FALSE) -> 4.4867502 | G29: =VLOOKUP($B29,HAVERD!$A:$BS,G$2,FALSE) -> 4.3528363 | H29: =VLOOKUP($B29,HAVERD!$A:$BS,H$2,FALSE) -> 4.2186078 | I29: =VLOOKUP($B29,HAVERD!$A:$BS,I$2,FALSE) -> 4.0901854 | J29: =VLOOKUP($B29,HAVERD!$A:$BS,J$2,FALSE) -> 3.9742385 | ... AY29: =VLOOKUP($B29,HAVERD!$A:$BS,AY$2,FALSE) -> 3.4871615
B30: =B13 -> 45583 | C30: =VLOOKUP($B30,HAVERD!$A:$BS,C$2,FALSE) -> 4.95 | D30: =VLOOKUP($B30,HAVERD!$A:$BS,D$2,FALSE) -> 4.7565408 | E30: =VLOOKUP($B30,HAVERD!$A:$BS,E$2,FALSE) -> 4.6112876 | F30: =VLOOKUP($B30,HAVERD!$A:$BS,F$2,FALSE) -> 4.4736636 | G30: =VLOOKUP($B30,HAVERD!$A:$BS,G$2,FALSE) -> 4.3371063 | H30: =VLOOKUP($B30,HAVERD!$A:$BS,H$2,FALSE) -> 4.2003865 | I30: =VLOOKUP($B30,HAVERD!$A:$BS,I$2,FALSE) -> 4.0688589 | J30: =VLOOKUP($B30,HAVERD!$A:$BS,J$2,FALSE) -> 3.9476923 | ... AY30: =VLOOKUP($B30,HAVERD!$A:$BS,AY$2,FALSE) -> 3.4528242
B31: =B14 -> 45586 | C31: =VLOOKUP($B31,HAVERD!$A:$BS,C$2,FALSE) -> 4.95 | D31: =VLOOKUP($B31,HAVERD!$A:$BS,D$2,FALSE) -> 4.7245473 | E31: =VLOOKUP($B31,HAVERD!$A:$BS,E$2,FALSE) -> 4.6069933 | F31: =VLOOKUP($B31,HAVERD!$A:$BS,F$2,FALSE) -> 4.4780541 | G31: =VLOOKUP($B31,HAVERD!$A:$BS,G$2,FALSE) -> 4.3408241 | H31: =VLOOKUP($B31,HAVERD!$A:$BS,H$2,FALSE) -> 4.202394 | I31: =VLOOKUP($B31,HAVERD!$A:$BS,I$2,FALSE) -> 4.0715595 | J31: =VLOOKUP($B31,HAVERD!$A:$BS,J$2,FALSE) -> 3.9552244 | ... AY31: =VLOOKUP($B31,HAVERD!$A:$BS,AY$2,FALSE) -> 3.5231036
B32: =B15 -> 45587 | C32: =VLOOKUP($B32,HAVERD!$A:$BS,C$2,FALSE) -> 4.95 | D32: =VLOOKUP($B32,HAVERD!$A:$BS,D$2,FALSE) -> 4.7159403 | E32: =VLOOKUP($B32,HAVERD!$A:$BS,E$2,FALSE) -> 4.605852 | F32: =VLOOKUP($B32,HAVERD!$A:$BS,F$2,FALSE) -> 4.4784973 | G32: =VLOOKUP($B32,HAVERD!$A:$BS,G$2,FALSE) -> 4.3411959 | H32: =VLOOKUP($B32,HAVERD!$A:$BS,H$2,FALSE) -> 4.2037503 | I32: =VLOOKUP($B32,HAVERD!$A:$BS,I$2,FALSE) -> 4.0749352 | J32: =VLOOKUP($B32,HAVERD!$A:$BS,J$2,FALSE) -> 3.9618383 | ... AY32: =VLOOKUP($B32,HAVERD!$A:$BS,AY$2,FALSE) -> 3.5491538
B33: =B16 -> 45588 | C33: =VLOOKUP($B33,HAVERD!$A:$BS,C$2,FALSE) -> 4.95 | D33: =VLOOKUP($B33,HAVERD!$A:$BS,D$2,FALSE) -> 4.7066383 | E33: =VLOOKUP($B33,HAVERD!$A:$BS,E$2,FALSE) -> 4.6034616 | F33: =VLOOKUP($B33,HAVERD!$A:$BS,F$2,FALSE) -> 4.476719 | G33: =VLOOKUP($B33,HAVERD!$A:$BS,G$2,FALSE) -> 4.3384223 | H33: =VLOOKUP($B33,HAVERD!$A:$BS,H$2,FALSE) -> 4.2008419 | I33: =VLOOKUP($B33,HAVERD!$A:$BS,I$2,FALSE) -> 4.0734887 | J33: =VLOOKUP($B33,HAVERD!$A:$BS,J$2,FALSE) -> 3.9631634 | ... AY33: =VLOOKUP($B33,HAVERD!$A:$BS,AY$2,FALSE) -> 3.6087754
B34: =B17 -> 45589 | C34: =VLOOKUP($B34,HAVERD!$A:$BS,C$2,FALSE) -> 4.95 | D34: =VLOOKUP($B34,HAVERD!$A:$BS,D$2,FALSE) -> 4.7055673 | E34: =VLOOKUP($B34,HAVERD!$A:$BS,E$2,FALSE) -> 4.6146926 | F34: =VLOOKUP($B34,HAVERD!$A:$BS,F$2,FALSE) -> 4.4929688 | G34: =VLOOKUP($B34,HAVERD!$A:$BS,G$2,FALSE) -> 4.3555884 | H34: =VLOOKUP($B34,HAVERD!$A:$BS,H$2,FALSE) -> 4.2185595 | I34: =VLOOKUP($B34,HAVERD!$A:$BS,I$2,FALSE) -> 4.093252 | J34: =VLOOKUP($B34,HAVERD!$A:$BS,J$2,FALSE) -> 3.9865325 | ... AY34: =VLOOKUP($B34,HAVERD!$A:$BS,AY$2,FALSE) -> 3.6223193
... B37: =B20 -> 45594 | C37: =VLOOKUP($B37,HAVERD!$A:$BS,C$2,FALSE) -> 4.95 | D37: =VLOOKUP($B37,HAVERD!$A:$BS,D$2,FALSE) -> 4.7010619 | E37: =VLOOKUP($B37,HAVERD!$A:$BS,E$2,FALSE) -> 4.6042869 | F37: =VLOOKUP($B37,HAVERD!$A:$BS,F$2,FALSE) -> 4.484879 | G37: =VLOOKUP($B37,HAVERD!$A:$BS,G$2,FALSE) -> 4.3523008 | H37: =VLOOKUP($B37,HAVERD!$A:$BS,H$2,FALSE) -> 4.2233455 | I37: =VLOOKUP($B37,HAVERD!$A:$BS,I$2,FALSE) -> 4.1088538 | J37: =VLOOKUP($B37,HAVERD!$A:$BS,J$2,FALSE) -> 4.014894 | ... AY37: =VLOOKUP($B37,HAVERD!$A:$BS,AY$2,FALSE) -> 3.7143726
C39: 45566 | D39: 45597 | E39: 45627 | F39: 45658 | G39: 45689 | H39: 45717 | I39: 45748 | J39: 45778 | K39: 45809 | L39: 45839 | M39: 45870 | N39: 45901 | O39: 45931 | P39: 45962 | Q39: 45992 | R39: 46023 | S39: 46054 | T39: 46082 | U39: 46113 | V39: 46143 | W39: 46174 | X39: 46204 | Y39: 46235 | Z39: 46266 | AA39: 46296 | AB39: 46327 | AC39: 46357 | AD39: 46388 | AE39: 46419 | AF39: 46447 | AG39: 46478 | AH39: 46508 | AI39: 46539 | AJ39: 46569 | AK39: 46600 | AL39: 46631 | AM39: 46661 | AN39: 46692 | AO39: 46722 | AP39: 46753 | AQ39: 46784 | AR39: 46813 | AS39: 46844 | AT39: 46874 | AU39: 46905 | AV39: 46935 | AW39: 46966 | AX39: 46997 | AY39: 47027 | AZ39: 47058 | BA39: 47088
B40: November MPR | C40: =AVERAGE(C23:C37) -> 4.95 | D40: =AVERAGE(D23:D37) -> 4.7578202 | E40: =AVERAGE(E23:E37) -> 4.6327906 | F40: =AVERAGE(F23:F37) -> 4.5073895 | G40: =AVERAGE(G23:G37) -> 4.3782999 | H40: =AVERAGE(H23:H37) -> 4.2492232 | I40: =AVERAGE(I23:I37) -> 4.1275689 | J40: =AVERAGE(J23:J37) -> 4.0197837 | ... BA40: =AVERAGE(BA23:BA37) -> #DIV/0!
A41: 45601 | B41: 6th November | C41: =VLOOKUP($A41,HAVERD!$A:$BS,C$2,FALSE) -> 4.95 | D41: =VLOOKUP($A41,HAVERD!$A:$BS,D$2,FALSE) -> 4.705506 | E41: =VLOOKUP($A41,HAVERD!$A:$BS,E$2,FALSE) -> 4.635297 | F41: =VLOOKUP($A41,HAVERD!$A:$BS,F$2,FALSE) -> 4.5488242 | G41: =VLOOKUP($A41,HAVERD!$A:$BS,G$2,FALSE) -> 4.4563583 | H41: =VLOOKUP($A41,HAVERD!$A:$BS,H$2,FALSE) -> 4.3713069 | I41: =VLOOKUP($A41,HAVERD!$A:$BS,I$2,FALSE) -> 4.2991426 | J41: =VLOOKUP($A41,HAVERD!$A:$BS,J$2,FALSE) -> 4.242551 | ... BA41: =VLOOKUP($A41,HAVERD!$A:$BS,BA$2,FALSE) -> #VALUE!
B42: Difference | C42: =C41-C40 -> 0 | D42: =D41-D40 -> -0.052314153 | E42: =E41-E40 -> 0.00250642 | F42: =F41-F40 -> 0.0414347 | G42: =G41-G40 -> 0.07805844 | H42: =H41-H40 -> 0.12208371 | I42: =I41-I40 -> 0.17157372 | J42: =J41-J40 -> 0.22276731 | ... BA42: =BA41-BA40 -> #VALUE!
B44: Chart data
C45: 44562 | D45: 44593 | E45: 44621 | F45: 44652 | G45: 44682 | H45: 44713 | I45: 44743 | J45: 44774 | K45: 44805 | L45: 44835 | M45: 44866 | N45: 44896 | O45: 44927 | P45: 44958 | Q45: 44986 | R45: 45017 | S45: 45047 | T45: 45078 | U45: 45108 | V45: 45139 | W45: 45170 | X45: 45200 | Y45: 45231 | Z45: 45261 | AA45: 45292 | AB45: 45323 | AC45: 45352 | AD45: 45383 | AE45: 45413 | AF45: 45444 | AG45: 45474 | AH45: 45505 | AI45: 45536 | AJ45: 45566 | AK45: 45597 | AL45: 45627 | AM45: 45658 | AN45: 45689 | AO45: 45717 | AP45: 45748 | AQ45: 45778 | AR45: 45809 | AS45: 45839 | AT45: 45870 | AU45: 45901 | AV45: 45931 | AW45: 45962 | AX45: 45992 | AY45: 46023 | AZ45: 46054 | BA45: 46082 | BB45: 46113 | BC45: 46143 | BD45: 46174 | BE45: 46204 | BF45: 46235 | BG45: 46266 | BH45: 46296 | BI45: 46327 | BJ45: 46357
B46: Bank Rate | C46: =VLOOKUP(C$45,HAVERM!$A:$C,3,FALSE) -> 0.25 | D46: =VLOOKUP(D$45,HAVERM!$A:$C,3,FALSE) -> 0.475 | E46: =VLOOKUP(E$45,HAVERM!$A:$C,3,FALSE) -> 0.61956522 | F46: =VLOOKUP(F$45,HAVERM!$A:$C,3,FALSE) -> 0.75 | G46: =VLOOKUP(G$45,HAVERM!$A:$C,3,FALSE) -> 0.96590909 | H46: =VLOOKUP(H$45,HAVERM!$A:$C,3,FALSE) -> 1.125 | I46: =VLOOKUP(I$45,HAVERM!$A:$C,3,FALSE) -> 1.25 | J46: =VLOOKUP(J$45,HAVERM!$A:$C,3,FALSE) -> 1.6847826 | ... BJ46: =VLOOKUP(BJ$45,HAVERM!$A:$C,3,FALSE) -> #N/A
B47: =B40 -> November MPR | C47: =HLOOKUP(C$45,$C$39:$AY$41,2,FALSE) -> #N/A | D47: =HLOOKUP(D$45,$C$39:$AY$41,2,FALSE) -> #N/A | E47: =HLOOKUP(E$45,$C$39:$AY$41,2,FALSE) -> #N/A | F47: =HLOOKUP(F$45,$C$39:$AY$41,2,FALSE) -> #N/A | G47: =HLOOKUP(G$45,$C$39:$AY$41,2,FALSE) -> #N/A | H47: =HLOOKUP(H$45,$C$39:$AY$41,2,FALSE) -> #N/A | I47: =HLOOKUP(I$45,$C$39:$AY$41,2,FALSE) -> #N/A | J47: =HLOOKUP(J$45,$C$39:$AY$41,2,FALSE) -> #N/A | ... BJ47: =HLOOKUP(BJ$45,$C$39:$AY$41,2,FALSE) -> 3.6510664
B48: =B41 -> 6th November | C48: =HLOOKUP(C$45,$C$39:$AY$41,3,FALSE) -> #N/A | D48: =HLOOKUP(D$45,$C$39:$AY$41,3,FALSE) -> #N/A | E48: =HLOOKUP(E$45,$C$39:$AY$41,3,FALSE) -> #N/A | F48: =HLOOKUP(F$45,$C$39:$AY$41,3,FALSE) -> #N/A | G48: =HLOOKUP(G$45,$C$39:$AY$41,3,FALSE) -> #N/A | H48: =HLOOKUP(H$45,$C$39:$AY$41,3,FALSE) -> #N/A | I48: =HLOOKUP(I$45,$C$39:$AY$41,3,FALSE) -> #N/A | J48: =HLOOKUP(J$45,$C$39:$AY$41,3,FALSE) -> #N/A | ... BJ48: =HLOOKUP(BJ$45,$C$39:$AY$41,3,FALSE) -> 4.1011052
B50: Average
B51: Month | C51: =MONTH(C20) -> 10 | D51: =MONTH(D20) -> 11 | E51: =MONTH(E20) -> 12 | F51: =MONTH(F20) -> 1 | G51: =MONTH(G20) -> 2 | H51: =MONTH(H20) -> 3 | I51: =MONTH(I20) -> 4 | J51: =MONTH(J20) -> 5 | ... AY51: =MONTH(AY20) -> 10
B52: Year | C52: =YEAR(C20) -> 2024 | D52: =YEAR(D20) -> 2024 | E52: =YEAR(E20) -> 2024 | F52: =YEAR(F20) -> 2025 | G52: =YEAR(G20) -> 2025 | H52: =YEAR(H20) -> 2025 | I52: =YEAR(I20) -> 2025 | J52: =YEAR(J20) -> 2025 | ... AY52: =YEAR(AY20) -> 2028
B53: YYYYMM | C53: =C52*100+C51 -> 202410 | D53: =D52*100+D51 -> 202411 | E53: =E52*100+E51 -> 202412 | F53: =F52*100+F51 -> 202501 | G53: =G52*100+G51 -> 202502 | H53: =H52*100+H51 -> 202503 | I53: =I52*100+I51 -> 202504 | J53: =J52*100+J51 -> 202505 | ... AY53: =AY52*100+AY51 -> 202810
B54: Quarter | C54: =IF(C51<4,1,IF(C51<7,2,IF(C51<10,3,4))) -> 4 | D54: =IF(D51<4,1,IF(D51<7,2,IF(D51<10,3,4))) -> 4 | E54: =IF(E51<4,1,IF(E51<7,2,IF(E51<10,3,4))) -> 4 | F54: =IF(F51<4,1,IF(F51<7,2,IF(F51<10,3,4))) -> 1 | G54: =IF(G51<4,1,IF(G51<7,2,IF(G51<10,3,4))) -> 1 | H54: =IF(H51<4,1,IF(H51<7,2,IF(H51<10,3,4))) -> 1 | I54: =IF(I51<4,1,IF(I51<7,2,IF(I51<10,3,4))) -> 2 | J54: =IF(J51<4,1,IF(J51<7,2,IF(J51<10,3,4))) -> 2 | ... AY54: =IF(AY51<4,1,IF(AY51<7,2,IF(AY51<10,3,4))) -> 4
B55: YYYYQQ | C55: =C52*100+C54 -> 202404 | D55: =D52*100+D54 -> 202404 | E55: =E52*100+E54 -> 202404 | F55: =F52*100+F54 -> 202501 | G55: =G52*100+G54 -> 202501 | H55: =H52*100+H54 -> 202501 | I55: =I52*100+I54 -> 202502 | J55: =J52*100+J54 -> 202502 | ... AY55: =AY52*100+AY54 -> 202804
B56: Average | C56: =AVERAGE(C23:C37) -> 4.95 | D56: =AVERAGE(D23:D37) -> 4.7578202 | E56: =AVERAGE(E23:E37) -> 4.6327906 | F56: =AVERAGE(F23:F37) -> 4.5073895 | G56: =AVERAGE(G23:G37) -> 4.3782999 | H56: =AVERAGE(H23:H37) -> 4.2492232 | I56: =AVERAGE(I23:I37) -> 4.1275689 | J56: =AVERAGE(J23:J37) -> 4.0197837 | ... AY56: =AVERAGE(AY23:AY37) -> 3.581085
B58: Quarterly series
C59: =C55 -> 202404 | D59: =IF(RIGHT(C59)="4",C59+97,C59+1) -> 202501 | E59: =IF(RIGHT(D59)="4",D59+97,D59+1) -> 202502 | F59: =IF(RIGHT(E59)="4",E59+97,E59+1) -> 202503 | G59: =IF(RIGHT(F59)="4",F59+97,F59+1) -> 202504 | H59: =IF(RIGHT(G59)="4",G59+97,G59+1) -> 202601 | I59: =IF(RIGHT(H59)="4",H59+97,H59+1) -> 202602 | J59: =IF(RIGHT(I59)="4",I59+97,I59+1) -> 202603 | K59: =IF(RIGHT(J59)="4",J59+97,J59+1) -> 202604 | ... S59: =IF(RIGHT(R59)="4",R59+97,R59+1) -> 202804
B60: =B1 -> November MPR | C60: =AVERAGEIF($C$55:$AY$55,C59,$C$56:$AY$56) -> 4.7802036 | D60: =AVERAGEIF($C$55:$AY$55,D59,$C$56:$AY$56) -> 4.3783042 | E60: =AVERAGEIF($C$55:$AY$55,E59,$C$56:$AY$56) -> 4.0256298 | F60: =AVERAGEIF($C$55:$AY$55,F59,$C$56:$AY$56) -> 3.8084322 | G60: =AVERAGEIF($C$55:$AY$55,G59,$C$56:$AY$56) -> 3.7187209 | H60: =AVERAGEIF($C$55:$AY$55,H59,$C$56:$AY$56) -> 3.6879262 | I60: =AVERAGEIF($C$55:$AY$55,I59,$C$56:$AY$56) -> 3.6772047 | J60: =AVERAGEIF($C$55:$AY$55,J59,$C$56:$AY$56) -> 3.6670578 | ... S60: =AVERAGEIF($C$55:$AY$55,S59,$C$56:$AY$56) -> 3.581085

Sheet HAVERD
A1: 1 | B1: =+A1+1 -> 2 | C1: =+B1+1 -> 3 | D1: =+C1+1 -> 4 | E1: =+D1+1 -> 5 | F1: =+E1+1 -> 6 | G1: =+F1+1 -> 7 | H1: =+G1+1 -> 8 | I1: =+H1+1 -> 9 | ... BS1: =+BR1+1 -> 71
A2: Date | B2: Month | C2: Year | D2: YYYYMM | E2: Quarter | F2: YYYYQQ | G2: 20240101 !D | H2: Bank Rate | I2: Overnight | J2: 1 | K2: 2 | L2: 3 | M2: 4 | N2: 5 | O2: 6 | P2: 7 | Q2: 8 | R2: 9 | S2: 10 | T2: 11 | U2: 12 | V2: 13 | W2: 14 | X2: 15 | Y2: 16 | Z2: 17 | AA2: 18 | AB2: 19 | AC2: 20 | AD2: 21 | AE2: 22 | AF2: 23 | AG2: 24 | AH2: 25 | AI2: 26 | AJ2: 27 | AK2: 28 | AL2: 29 | AM2: 30 | AN2: 31 | AO2: 32 | AP2: 33 | AQ2: 34 | AR2: 35 | AS2: 36 | AT2: 37 | AU2: 38 | AV2: 39 | AW2: 40 | AX2: 41 | AY2: 42 | AZ2: 43 | BA2: 44 | BB2: 45 | BC2: 46 | BD2: 47 | BE2: 48 | BF2: 49 | BG2: 50 | BH2: 51 | BI2: 52 | BJ2: 53 | BK2: 54 | BL2: 55 | BM2: 56 | BN2: 57 | BO2: 58 | BP2: 59 | BQ2: 60 | BR2: 5.5yrs | BS2: 6yrs
H3: R112RD@INTDAILY | I3: R112LOS@INTDAILY | J3: R11201F@INTDAILY | K3: R11202F@INTDAILY | L3: R11203F@INTDAILY | M3: R11204F@INTDAILY | N3: R11205F@INTDAILY | O3: R11206F@INTDAILY | P3: R11207F@INTDAILY | Q3: R11208F@INTDAILY | R3: R11209F@INTDAILY | S3: R11210F@INTDAILY | T3: R11211F@INTDAILY | U3: R11212F@INTDAILY | V3: R11213F@INTDAILY | W3: R11214F@INTDAILY | X3: R11215F@INTDAILY | Y3: R11216F@INTDAILY | Z3: R11217F@INTDAILY | AA3: R11218F@INTDAILY | AB3: R11219F@INTDAILY | AC3: R11220F@INTDAILY | AD3: R11221F@INTDAILY | AE3: R11222F@INTDAILY | AF3: R11223F@INTDAILY | AG3: R11224F@INTDAILY | AH3: R11225F@INTDAILY | AI3: R11226F@INTDAILY | AJ3: R11227F@INTDAILY | AK3: R11228F@INTDAILY | AL3: R11229F@INTDAILY | AM3: R11230F@INTDAILY | AN3: R11231F@INTDAILY | AO3: R11232F@INTDAILY | AP3: R11233F@INTDAILY | AQ3: R11234F@INTDAILY | AR3: R11235F@INTDAILY | AS3: R11236F@INTDAILY | AT3: R11237F@INTDAILY | AU3: R11238F@INTDAILY | AV3: R11239F@INTDAILY | AW3: R11240F@INTDAILY | AX3: R11241F@INTDAILY | AY3: R11242F@INTDAILY | AZ3: R11243F@INTDAILY | BA3: R11244F@INTDAILY | BB3: R11245F@INTDAILY | BC3: R11246F@INTDAILY | BD3: R11247F@INTDAILY | BE3: R11248F@INTDAILY | BF3: R11249F@INTDAILY | BG3: R11250F@INTDAILY | BH3: R11251F@INTDAILY | BI3: R11252F@INTDAILY | BJ3: R11253F@INTDAILY | BK3: R11254F@INTDAILY | BL3: R11255F@INTDAILY | BM3: R11256F@INTDAILY | BN3: R11257F@INTDAILY | BO3: R11258F@INTDAILY | BP3: R11259F@INTDAILY | BQ3: R11260F@INTDAILY | BR3: R112I5B@INTDAILY | BS3: R112I6A@INTDAILY
G4: .DESC | H4: United Kingdom: Official Bank Rate (%) | I4: UK:Lending Rate: Sterling Overnight Interbank Average [SONIA] (% pa) | J4: UK: Overnight Index Swap: Forward Yields, 1-Month (% p.a.) | K4: UK: Overnight Index Swap: Forward Yields, 2-Month (% p.a.) | L4: UK: Overnight Index Swap: Forward Yields, 3-Month (% p.a.) | M4: UK: Overnight Index Swap: Forward Yields, 4-Month (% p.a.) | N4: UK: Overnight Index Swap: Forward Yields, 5-Month (% p.a.) | O4: UK: Overnight Index Swap: Forward Yields, 6-Month (% p.a.) | P4: UK: Overnight Index Swap: Forward Yields, 7-Month (% p.a.) | Q4: UK: Overnight Index Swap: Forward Yields, 8-Month (% p.a.) | R4: UK: Overnight Index Swap: Forward Yields, 9-Month (% p.a.) | S4: UK: Overnight Index Swap: Forward Yields, 10-Month (% p.a.) | T4: UK: Overnight Index Swap: Forward Yields, 11-Month (% p.a.) | U4: UK: Overnight Index Swap: Forward Yields, 12-Month (% p.a.) | V4: UK: Overnight Index Swap: Forward Yields, 13-Month (% p.a.) | W4: UK: Overnight Index Swap: Forward Yields, 14-Month (% p.a.) | X4: UK: Overnight Index Swap: Forward Yields, 15-Month (% p.a.) | Y4: UK: Overnight Index Swap: Forward Yields, 16-Month (% p.a.) | Z4: UK: Overnight Index Swap: Forward Yields, 17-Month (% p.a.) | AA4: UK: Overnight Index Swap: Forward Yields, 18-Month (% p.a.) | AB4: UK: Overnight Index Swap: Forward Yields, 19-Month (% p.a.) | AC4: UK: Overnight Index Swap: Forward Yields, 20-Month (% p.a.) | AD4: UK: Overnight Index Swap: Forward Yields, 21-Month (% p.a.) | AE4: UK: Overnight Index Swap: Forward Yields, 22-Month (% p.a.) | AF4: UK: Overnight Index Swap: Forward Yields, 23-Month (% p.a.) | AG4: UK: Overnight Index Swap: Forward Yields, 24-Month (% p.a.) | AH4: UK: Overnight Index Swap: Forward Yields, 25-Month (% p.a.) | AI4: UK: Overnight Index Swap: Forward Yields, 26-Month (% p.a.) | AJ4: UK: Overnight Index Swap: Forward Yields, 27-Month (% p.a.) | AK4: UK: Overnight Index Swap: Forward Yields, 28-Month (% p.a.) | AL4: UK: Overnight Index Swap: Forward Yields, 29-Month (% p.a.) | AM4: UK: Overnight Index Swap: Forward Yields, 30-Month (% p.a.) | AN4: UK: Overnight Index Swap: Forward Yields, 31-Month (% p.a.) | AO4: UK: Overnight Index Swap: Forward Yields, 32-Month (% p.a.) | AP4: UK: Overnight Index Swap: Forward Yields, 33-Month (% p.a.) | AQ4: UK: Overnight Index Swap: Forward Yields, 34-Month (% p.a.) | AR4: UK: Overnight Index Swap: Forward Yields, 35-Month (% p.a.) | AS4: UK: Overnight Index Swap: Forward Yields, 36-Month (% p.a.) | AT4: UK: Overnight Index Swap: Forward Yields, 37-Month (% p.a.) | AU4: UK: Overnight Index Swap: Forward Yields, 38-Month (% p.a.) | AV4: UK: Overnight Index Swap: Forward Yields, 39-Month (% p.a.) | AW4: UK: Overnight Index Swap: Forward Yields, 40-Month (% p.a.) | AX4: UK: Overnight Index Swap: Forward Yields, 41-Month (% p.a.) | AY4: UK: Overnight Index Swap: Forward Yields, 42-Month (% p.a.) | AZ4: UK: Overnight Index Swap: Forward Yields, 43-Month (% p.a.) | BA4: UK: Overnight Index Swap: Forward Yields, 44-Month (% p.a.) | BB4: UK: Overnight Index Swap: Forward Yields, 45-Month (% p.a.) | BC4: UK: Overnight Index Swap: Forward Yields, 46-Month (% p.a.) | BD4: UK: Overnight Index Swap: Forward Yields, 47-Month (% p.a.) | BE4: UK: Overnight Index Swap: Forward Yields, 48-Month (% p.a.) | BF4: UK: Overnight Index Swap: Forward Yields, 49-Month (% p.a.) | BG4: UK: Overnight Index Swap: Forward Yields, 50-Month (% p.a.) | BH4: UK: Overnight Index Swap: Forward Yields, 51-Month (% p.a.) | BI4: UK: Overnight Index Swap: Forward Yields, 52-Month (% p.a.) | BJ4: UK: Overnight Index Swap: Forward Yields, 53-Month (% p.a.) | BK4: UK: Overnight Index Swap: Forward Yields, 54-Month (% p.a.) | BL4: UK: Overnight Index Swap: Forward Yields, 55-Month (% p.a.) | BM4: UK: Overnight Index Swap: Forward Yields, 56-Month (% p.a.) | BN4: UK: Overnight Index Swap: Forward Yields, 57-Month (% p.a.) | BO4: UK: Overnight Index Swap: Forward Yields, 58-Month (% p.a.) | BP4: UK: Overnight Index Swap: Forward Yields, 59-Month (% p.a.) | BQ4: UK: Overnight Index Swap: Forward Yields, 60-Month (% p.a.) | BR4: UK: Overnight Index Swap: Forward Yields, 5.5-Year (% p.a.) | BS4: UK: Overnight Index Swap: Forward Yields, 6-Year (% p.a.)
G5: .T1 | H5: 01-Jan-1953 | I5: 02-Jan-1997 | J5: 02-Jan-2009 | K5: 02-Jan-2009 | L5: 02-Jan-2009 | M5: 02-Jan-2009 | N5: 02-Jan-2009 | O5: 02-Jan-2009 | P5: 02-Jan-2009 | Q5: 02-Jan-2009 | R5: 02-Jan-2009 | S5: 02-Jan-2009 | T5: 02-Jan-2009 | U5: 02-Jan-2009 | V5: 02-Jan-2009 | W5: 02-Jan-2009 | X5: 02-Jan-2009 | Y5: 02-Jan-2009 | Z5: 02-Jan-2009 | AA5: 02-Jan-2009 | AB5: 02-Jan-2009 | AC5: 02-Jan-2009 | AD5: 02-Jan-2009 | AE5: 02-Jan-2009 | AF5: 02-Jan-2009 | AG5: 02-Jan-2009 | AH5: 02-Jan-2009 | AI5: 02-Jan-2009 | AJ5: 02-Jan-2009 | AK5: 02-Jan-2009 | AL5: 02-Jan-2009 | AM5: 02-Jan-2009 | AN5: 02-Jan-2009 | AO5: 02-Jan-2009 | AP5: 02-Jan-2009 | AQ5: 02-Jan-2009 | AR5: 02-Jan-2009 | AS5: 02-Jan-2009 | AT5: 02-Jan-2009 | AU5: 02-Jan-2009 | AV5: 02-Jan-2009 | AW5: 02-Jan-2009 | AX5: 02-Jan-2009 | AY5: 02-Jan-2009 | AZ5: 02-Jan-2009 | BA5: 02-Jan-2009 | BB5: 02-Jan-2009 | BC5: 02-Jan-2009 | BD5: 02-Jan-2009 | BE5: 02-Jan-2009 | BF5: 02-Jan-2009 | BG5: 02-Jan-2009 | BH5: 02-Jan-2009 | BI5: 02-Jan-2009 | BJ5: 02-Jan-2009 | BK5: 02-Jan-2009 | BL5: 02-Jan-2009 | BM5: 02-Jan-2009 | BN5: 02-Jan-2009 | BO5: 02-Jan-2009 | BP5: 02-Jan-2009 | BQ5: 02-Jan-2009 | BR5: 01-Dec-2021 | BS5: 01-Dec-2021
G6: .TN | H6: 07-Nov-2024 | I6: 05-Nov-2024 | J6: 06-Nov-2024 | K6: 06-Nov-2024 | L6: 06-Nov-2024 | M6: 06-Nov-2024 | N6: 06-Nov-2024 | O6: 06-Nov-2024 | P6: 06-Nov-2024 | Q6: 06-Nov-2024 | R6: 06-Nov-2024 | S6: 06-Nov-2024 | T6: 06-Nov-2024 | U6: 06-Nov-2024 | V6: 06-Nov-2024 | W6: 06-Nov-2024 | X6: 06-Nov-2024 | Y6: 06-Nov-2024 | Z6: 06-Nov-2024 | AA6: 06-Nov-2024 | AB6: 06-Nov-2024 | AC6: 06-Nov-2024 | AD6: 06-Nov-2024 | AE6: 06-Nov-2024 | AF6: 06-Nov-2024 | AG6: 06-Nov-2024 | AH6: 06-Nov-2024 | AI6: 06-Nov-2024 | AJ6: 06-Nov-2024 | AK6: 06-Nov-2024 | AL6: 06-Nov-2024 | AM6: 06-Nov-2024 | AN6: 06-Nov-2024 | AO6: 06-Nov-2024 | AP6: 06-Nov-2024 | AQ6: 06-Nov-2024 | AR6: 06-Nov-2024 | AS6: 06-Nov-2024 | AT6: 06-Nov-2024 | AU6: 06-Nov-2024 | AV6: 06-Nov-2024 | AW6: 06-Nov-2024 | AX6: 06-Nov-2024 | AY6: 06-Nov-2024 | AZ6: 06-Nov-2024 | BA6: 06-Nov-2024 | BB6: 06-Nov-2024 | BC6: 06-Nov-2024 | BD6: 06-Nov-2024 | BE6: 06-Nov-2024 | BF6: 06-Nov-2024 | BG6: 06-Nov-2024 | BH6: 06-Nov-2024 | BI6: 06-Nov-2024 | BJ6: 06-Nov-2024 | BK6: 06-Nov-2024 | BL6: 06-Nov-2024 | BM6: 06-Nov-2024 | BN6: 06-Nov-2024 | BO6: 06-Nov-2024 | BP6: 06-Nov-2024 | BQ6: 06-Nov-2024 | BR6: 06-Nov-2024 | BS6: 06-Nov-2024
G7: .LSOURCE | H7: Bank of England | I7: Bank of England | J7: Bank of England | K7: Bank of England | L7: Bank of England | M7: Bank of England | N7: Bank of England | O7: Bank of England | P7: Bank of England | Q7: Bank of England | R7: Bank of England | S7: Bank of England | T7: Bank of England | U7: Bank of England | V7: Bank of England | W7: Bank of England | X7: Bank of England | Y7: Bank of England | Z7: Bank of England | AA7: Bank of England | AB7: Bank of England | AC7: Bank of England | AD7: Bank of England | AE7: Bank of England | AF7: Bank of England | AG7: Bank of England | AH7: Bank of England | AI7: Bank of England | AJ7: Bank of England | AK7: Bank of England | AL7: Bank of England | AM7: Bank of England | AN7: Bank of England | AO7: Bank of England | AP7: Bank of England | AQ7: Bank of England | AR7: Bank of England | AS7: Bank of England | AT7: Bank of England | AU7: Bank of England | AV7: Bank of England | AW7: Bank of England | AX7: Bank of England | AY7: Bank of England | AZ7: Bank of England | BA7: Bank of England | BB7: Bank of England | BC7: Bank of England | BD7: Bank of England | BE7: Bank of England | BF7: Bank of England | BG7: Bank of England | BH7: Bank of England | BI7: Bank of England | BJ7: Bank of England | BK7: Bank of England | BL7: Bank of England | BM7: Bank of England | BN7: Bank of England | BO7: Bank of England | BP7: Bank of England | BQ7: Bank of England | BR7: Bank of England | BS7: Bank of England
G8: .DTLM | H8: Nov-07-2024 12:05 | I8: Nov-07-2024 09:31 | J8: Nov-07-2024 12:47 | K8: Nov-07-2024 12:47 | L8: Nov-07-2024 12:47 | M8: Nov-07-2024 12:47 | N8: Nov-07-2024 12:47 | O8: Nov-07-2024 12:47 | P8: Nov-07-2024 12:47 | Q8: Nov-07-2024 12:47 | R8: Nov-07-2024 12:47 | S8: Nov-07-2024 12:47 | T8: Nov-07-2024 12:47 | U8: Nov-07-2024 12:47 | V8: Nov-07-2024 12:47 | W8: Nov-07-2024 12:47 | X8: Nov-07-2024 12:47 | Y8: Nov-07-2024 12:47 | Z8: Nov-07-2024 12:47 | AA8: Nov-07-2024 12:47 | AB8: Nov-07-2024 12:47 | AC8: Nov-07-2024 12:47 | AD8: Nov-07-2024 12:47 | AE8: Nov-07-2024 12:47 | AF8: Nov-07-2024 12:47 | AG8: Nov-07-2024 12:47 | AH8: Nov-07-2024 12:47 | AI8: Nov-07-2024 12:47 | AJ8: Nov-07-2024 12:47 | AK8: Nov-07-2024 12:47 | AL8: Nov-07-2024 12:47 | AM8: Nov-07-2024 12:47 | AN8: Nov-07-2024 12:47 | AO8: Nov-07-2024 12:47 | AP8: Nov-07-2024 12:47 | AQ8: Nov-07-2024 12:47 | AR8: Nov-07-2024 12:47 | AS8: Nov-07-2024 12:47 | AT8: Nov-07-2024 12:47 | AU8: Nov-07-2024 12:47 | AV8: Nov-07-2024 12:47 | AW8: Nov-07-2024 12:47 | AX8: Nov-07-2024 12:47 | AY8: Nov-07-2024 12:47 | AZ8: Nov-07-2024 12:47 | BA8: Nov-07-2024 12:47 | BB8: Nov-07-2024 12:47 | BC8: Nov-07-2024 12:47 | BD8: Nov-07-2024 12:47 | BE8: Nov-07-2024 12:47 | BF8: Nov-07-2024 12:47 | BG8: Nov-07-2024 12:47 | BH8: Nov-07-2024 12:47 | BI8: Nov-07-2024 12:47 | BJ8: Nov-07-2024 12:47 | BK8: Nov-07-2024 12:47 | BL8: Nov-07-2024 12:47 | BM8: Nov-07-2024 12:47 | BN8: Nov-07-2024 12:47 | BO8: Nov-07-2024 12:47 | BP8: Nov-07-2024 12:47 | BQ8: Nov-07-2024 12:47 | BR8: Nov-07-2024 12:47 | BS8: Nov-07-2024 12:47
A9: 45292 | B9: =MONTH(A9) -> 1 | C9: =YEAR(A9) -> 2024 | D9: =C9*100+B9 -> 202401 | E9: =IF(B9<4,1,IF(B9<7,2,IF(B9<10,3,4))) -> 1 | F9: =C9*100+E9 -> 202401 | G9: 20240101 | H9: 5.25 | I9: #N/A | J9: #N/A | K9: #N/A | L9: #N/A | M9: #N/A | N9: #N/A | O9: #N/A | P9: #N/A | Q9: #N/A | R9: #N/A | S9: #N/A | T9: #N/A | U9: #N/A | V9: #N/A | W9: #N/A | X9: #N/A | Y9: #N/A | Z9: #N/A | AA9: #N/A | AB9: #N/A | AC9: #N/A | AD9: #N/A | AE9: #N/A | AF9: #N/A | AG9: #N/A | AH9: #N/A | AI9: #N/A | AJ9: #N/A | AK9: #N/A | AL9: #N/A | AM9: #N/A | AN9: #N/A | AO9: #N/A | AP9: #N/A | AQ9: #N/A | AR9: #N/A | AS9: #N/A | AT9: #N/A | AU9: #N/A | AV9: #N/A | AW9: #N/A | AX9: #N/A | AY9: #N/A | AZ9: #N/A | BA9: #N/A | BB9: #N/A | BC9: #N/A | BD9: #N/A | BE9: #N/A | BF9: #N/A | BG9: #N/A | BH9: #N/A | BI9: #N/A | BJ9: #N/A | BK9: #N/A | BL9: #N/A | BM9: #N/A | BN9: #N/A | BO9: #N/A | BP9: #N/A | BQ9: #N/A | BR9: #N/A | BS9: #N/A
A10: 45293 | B10: =MONTH(A10) -> 1 | C10: =YEAR(A10) -> 2024 | D10: =C10*100+B10 -> 202401 | E10: =IF(B10<4,1,IF(B10<7,2,IF(B10<10,3,4))) -> 1 | F10: =C10*100+E10 -> 202401 | G10: 20240102 | H10: 5.25 | I10: 5.1863 | J10: 5.1869458 | K10: 5.1737152 | L10: 5.1274641 | M10: 5.0330693 | N10: 4.8948084 | O10: 4.7267552 | P10: 4.5455904 | Q10: 4.3673209 | R10: 4.2024467 | S10: 4.0550731 | T10: 3.9257072 | U10: 3.8133507 | V10: 3.7135649 | W10: 3.6243989 | X10: 3.5449015 | Y10: 3.4741183 | Z10: 3.4110951 | AA10: 3.3548802 | AB10: 3.3045933 | AC10: 3.2596362 | AD10: 3.2194791 | AE10: 3.1835906 | AF10: 3.1514396 | AG10: 3.122496 | AH10: 3.0962854 | AI10: 3.0725845 | AJ10: 3.0512401 | AK10: 3.0320982 | AL10: 3.0150048 | AM10: 2.9998064 | AN10: 2.9863491 | AO10: 2.974479 | AP10: 2.9640426 | AQ10: 2.9548859 | AR10: 2.9468551 | AS10: 2.9397965 | AT10: 2.9335733 | AU10: 2.9281397 | AV10: 2.9234809 | AW10: 2.9195818 | AX10: 2.9164273 | AY10: 2.9140026 | AZ10: 2.9122925 | BA10: 2.9112821 | BB10: 2.9109564 | BC10: 2.9113003 | BD10: 2.912299 | BE10: 2.9139373 | BF10: 2.9161996 | BG10: 2.919067 | BH10: 2.9225195 | BI10: 2.9265371 | BJ10: 2.9310997 | BK10: 2.9361872 | BL10: 2.9417797 | BM10: 2.9478571 | BN10: 2.9543994 | BO10: 2.9613864 | BP10: 2.9687984 | BQ10: 2.976615 | BR10: 3.030969 | BS10: 3.0953136
A11: 45294 | B11: =MONTH(A11) -> 1 | C11: =YEAR(A11) -> 2024 | D11: =C11*100+B11 -> 202401 | E11: =IF(B11<4,1,IF(B11<7,2,IF(B11<10,3,4))) -> 1 | F11: =C11*100+E11 -> 202401 | G11: 20240103 | H11: 5.25 | I11: 5.1863 | J11: 5.1879346 | K11: 5.1698623 | L11: 5.1217679 | M11: 5.0292524 | N11: 4.8955915 | O11: 4.7327474 | P11: 4.5561573 | Q11: 4.3801251 | R11: 4.2145866 | S11: 4.0638514 | T11: 3.9292761 | U11: 3.8103909 | V11: 3.7037411 | W11: 3.6077142 | X11: 3.521457 | Y11: 3.4441131 | Z11: 3.3748263 | AA11: 3.3127429 | AB11: 3.2570771 | AC11: 3.2073119 | AD11: 3.1629961 | AE11: 3.1236764 | AF11: 3.0889 | AG11: 3.0582151 | AH11: 3.0311935 | AI11: 3.0075393 | AJ11: 2.9870022 | AK11: 2.969331 | AL11: 2.9542745 | AM11: 2.9415821 | AN11: 2.9310026 | AO11: 2.9222851 | AP11: 2.9151788 | AQ11: 2.9094326 | AR11: 2.9047955 | AS11: 2.9010166 | AT11: 2.8978771 | AU11: 2.895314 | AV11: 2.8933122 | AW11: 2.8918564 | AX11: 2.8909314 | AY11: 2.8905219 | AZ11: 2.8906127 | BA11: 2.8911885 | BB11: 2.8922341 | BC11: 2.8937342 | BD11: 2.8956737 | BE11: 2.8980372 | BF11: 2.9008111 | BG11: 2.9039899 | BH11: 2.9075703 | BI11: 2.9115491 | BJ11: 2.9159234 | BK11: 2.9206896 | BL11: 2.9258448 | BM11: 2.9313858 | BN11: 2.9373093 | BO11: 2.9436122 | BP11: 2.9502914 | BQ11: 2.9573435 | BR11: 3.0068421 | BS11: 3.066086
A12: 45295 | B12: =MONTH(A12) -> 1 | C12: =YEAR(A12) -> 2024 | D12: =C12*100+B12 -> 202401 | E12: =IF(B12<4,1,IF(B12<7,2,IF(B12<10,3,4))) -> 1 | F12: =C12*100+E12 -> 202401 | G12: 20240104 | H12: 5.25 | I12: 5.187 | J12: 5.1847631 | K12: 5.1706678 | L12: 5.1289199 | M12: 5.0490298 | N12: 4.9325416 | O12: 4.7903404 | P12: 4.6344699 | Q12: 4.4767792 | R12: 4.325913 | S12: 4.1861158 | T12: 4.0594066 | U12: 3.9458216 | V12: 3.8430555 | W12: 3.7499596 | X12: 3.6659829 | Y12: 3.5905712 | Z12: 3.5231711 | AA12: 3.4632312 | AB12: 3.4101861 | AC12: 3.3634253 | AD12: 3.3223291 | AE12: 3.2862764 | AF12: 3.2546461 | AG12: 3.2268182 | AH12: 3.202227 | AI12: 3.1805764 | AJ12: 3.1616533 | AK12: 3.1452434 | AL12: 3.1311331 | AM12: 3.1191088 | AN12: 3.1089566 | AO12: 3.1004627 | AP12: 3.0934135 | AQ12: 3.0875952 | AR12: 3.082794 | AS12: 3.0787962 | AT12: 3.0754178 | AU12: 3.0726057 | AV12: 3.0703431 | AW12: 3.0686133 | AX12: 3.0673993 | AY12: 3.0666845 | AZ12: 3.066452 | BA12: 3.0666849 | BB12: 3.0673665 | BC12: 3.0684799 | BD12: 3.0700083 | BE12: 3.071935 | BF12: 3.0742445 | BG12: 3.0769279 | BH12: 3.0799781 | BI12: 3.083388 | BJ12: 3.0871505 | BK12: 3.0912583 | BL12: 3.0957043 | BM12: 3.1004814 | BN12: 3.1055825 | BO12: 3.1110004 | BP12: 3.1167281 | BQ12: 3.1227582 | BR12: 3.164827 | BS12: 3.2155848
A13: 45296 | B13: =MONTH(A13) -> 1 | C13: =YEAR(A13) -> 2024 | D13: =C13*100+B13 -> 202401 | E13: =IF(B13<4,1,IF(B13<7,2,IF(B13<10,3,4))) -> 1 | F13: =C13*100+E13 -> 202401 | G13: 20240105 | H13: 5.25 | I13: 5.1869 | J13: 5.1873271 | K13: 5.1720792 | L13: 5.1334347 | M13: 5.0598045 | N13: 4.9517376 | O13: 4.818767 | P13: 4.6723585 | Q13: 4.5243145 | R13: 4.3831627 | S13: 4.2534108 | T13: 4.1364167 | U13: 4.0318583 | V13: 3.9368302 | W13: 3.85008 | X13: 3.7711019 | Y13: 3.6993871 | Z13: 3.6344272 | AA13: 3.5757159 | AB13: 3.5227608 | AC13: 3.4751452 | AD13: 3.4324758 | AE13: 3.3943576 | AF13: 3.3603956 | AG13: 3.3301963 | AH13: 3.3033905 | AI13: 3.2797228 | AJ13: 3.2589696 | AK13: 3.2409068 | AL13: 3.2253104 | AM13: 3.2119566 | AN13: 3.2006214 | AO13: 3.1910808 | AP13: 3.1831111 | AQ13: 3.1764881 | AR13: 3.1709879 | AS13: 3.1663868 | AT13: 3.1624898 | AU13: 3.1592315 | AV13: 3.156582 | AW13: 3.1545114 | AX13: 3.1529896 | AY13: 3.1519869 | AZ13: 3.1514732 | BA13: 3.1514186 | BB13: 3.1517933 | BC13: 3.1525672 | BD13: 3.1537105 | BE13: 3.1551932 | BF13: 3.1569896 | BG13: 3.1590924 | BH13: 3.1614995 | BI13: 3.1642087 | BJ13: 3.1672179 | BK13: 3.170525 | BL13: 3.1741276 | BM13: 3.1780239 | BN13: 3.1822114 | BO13: 3.1866882 | BP13: 3.191452 | BQ13: 3.1965007 | BR13: 3.2325006 | BS13: 3.2772656
A14: =A9+7 -> 45299 | B14: =MONTH(A14) -> 1 | C14: =YEAR(A14) -> 2024 | D14: =C14*100+B14 -> 202401 | E14: =IF(B14<4,1,IF(B14<7,2,IF(B14<10,3,4))) -> 1 | F14: =C14*100+E14 -> 202401 | G14: 20240108 | H14: 5.25 | I14: 5.1869 | J14: 5.1875371 | K14: 5.1723518 | L14: 5.1318123 | M14: 5.0538828 | N14: 4.940707 | O14: 4.8022983 | P14: 4.6506226 | Q14: 4.4975445 | R14: 4.3519114 | S14: 4.2180825 | T14: 4.0980801 | U14: 3.9915985 | V14: 3.8957127 | W14: 3.8090536 | X14: 3.7309025 | Y14: 3.6605376 | Z14: 3.5972375 | AA14: 3.5402832 | AB14: 3.489008 | AC14: 3.4429542 | AD14: 3.4017156 | AE14: 3.3648842 | AF14: 3.3320521 | AG14: 3.3028128 | AH14: 3.2767879 | AI14: 3.2537295 | AJ14: 3.2334264 | AK14: 3.2156666 | AL14: 3.2002382 | AM14: 3.1869299 | AN14: 3.1755298 | AO14: 3.1658259 | AP14: 3.1576069 | AQ14: 3.1506609 | AR14: 3.1447761 | AS14: 3.1397409 | AT14: 3.135372 | AU14: 3.1316118 | AV14: 3.1284378 | AW14: 3.1258269 | AX14: 3.1237565 | AY14: 3.1222038 | AZ14: 3.1211458 | BA14: 3.12056 | BB14: 3.1204234 | BC14: 3.1207133 | BD14: 3.1214068 | BE14: 3.1224812 | BF14: 3.1239165 | BG14: 3.1257072 | BH14: 3.1278529 | BI14: 3.1303531 | BJ14: 3.1332076 | BK14: 3.1364157 | BL14: 3.139977 | BM14: 3.1438913 | BN14: 3.1481579 | BO14: 3.1527765 | BP14: 3.1577466 | BQ14: 3.1630678 | BR14: 3.2019754 | BS14: 3.2511539
A15: =A10+7 -> 45300 | B15: =MONTH(A15) -> 1 | C15: =YEAR(A15) -> 2024 | D15: =C15*100+B15 -> 202401 | E15: =IF(B15<4,1,IF(B15<7,2,IF(B15<10,3,4))) -> 1 | F15: =C15*100+E15 -> 202401 | G15: 20240109 | H15: 5.25 | I15: 5.1867 | J15: 5.1852612 | K15: 5.1702463 | L15: 5.1298316 | M15: 5.0519415 | N15: 4.9396491 | O15: 4.8037639 | P15: 4.656196 | Q15: 4.5079649 | R15: 4.3668257 | S15: 4.2366576 | T15: 4.1187677 | U15: 4.0132622 | V15: 3.9177742 | W15: 3.8311198 | X15: 3.7526542 | Y15: 3.6817291 | Z15: 3.6176969 | AA15: 3.5599118 | AB15: 3.5077647 | AC15: 3.4607923 | AD15: 3.4185682 | AE15: 3.3806642 | AF15: 3.3466522 | AG15: 3.3161053 | AH15: 3.2886325 | AI15: 3.2640061 | AJ15: 3.2420446 | AK15: 3.2225655 | AL15: 3.2053862 | AM15: 3.190325 | AN15: 3.1771994 | AO15: 3.1658272 | AP15: 3.1560262 | AQ15: 3.1476142 | AR15: 3.1404089 | AS15: 3.1342282 | AT15: 3.1289081 | AU15: 3.1243834 | AV15: 3.1206224 | AW15: 3.1175928 | AX15: 3.1152628 | AY15: 3.1136004 | AZ15: 3.1125735 | BA15: 3.1121503 | BB15: 3.1122987 | BC15: 3.1129868 | BD15: 3.1141825 | BE15: 3.1158539 | BF15: 3.117972 | BG15: 3.1205215 | BH15: 3.1234918 | BI15: 3.1268719 | BJ15: 3.1306511 | BK15: 3.1348186 | BL15: 3.1393635 | BM15: 3.1442751 | BN15: 3.1495424 | BO15: 3.1551547 | BP15: 3.1611013 | BQ15: 3.1673712 | BR15: 3.2111431 | BS15: 3.2636287
A16: =A11+7 -> 45301 | B16: =MONTH(A16) -> 1 | C16: =YEAR(A16) -> 2024 | D16: =C16*100+B16 -> 202401 | E16: =IF(B16<4,1,IF(B16<7,2,IF(B16<10,3,4))) -> 1 | F16: =C16*100+E16 -> 202401 | G16: 20240110 | H16: 5.25 | I16: 5.1872 | J16: 5.1850912 | K16: 5.1708219 | L16: 5.1309503 | M16: 5.0544508 | N16: 4.9451799 | O16: 4.8134886 | P16: 4.6711024 | Q16: 4.5282674 | R16: 4.3923388 | S16: 4.2669033 | T16: 4.1533587 | U16: 4.0516976 | V16: 3.9600377 | W16: 3.8771955 | X16: 3.8023256 | Y16: 3.7345796 | Z16: 3.6731095 | AA16: 3.6170693 | AB16: 3.5657097 | AC16: 3.5186568 | AD16: 3.4756281 | AE16: 3.4363392 | AF16: 3.4005058 | AG16: 3.367845 | AH16: 3.3380884 | AI16: 3.311053 | AJ16: 3.2865854 | AK16: 3.2645311 | AL16: 3.2447358 | AM16: 3.2270459 | AN16: 3.2113071 | AO16: 3.1973651 | AP16: 3.1850661 | AQ16: 3.1742559 | AR16: 3.1647803 | AS16: 3.1564854 | AT16: 3.1492323 | AU16: 3.1429566 | AV16: 3.1376166 | AW16: 3.1331706 | AX16: 3.1295768 | AY16: 3.1267935 | AZ16: 3.124779 | BA16: 3.1234916 | BB16: 3.1228895 | BC16: 3.122931 | BD16: 3.1235745 | BE16: 3.1247781 | BF16: 3.126504 | BG16: 3.1287318 | BH16: 3.1314456 | BI16: 3.1346296 | BJ16: 3.1382682 | BK16: 3.1423454 | BL16: 3.1468455 | BM16: 3.1517528 | BN16: 3.1570515 | BO16: 3.1627257 | BP16: 3.1687597 | BQ16: 3.1751377 | BR16: 3.2197924 | BS16: 3.2731349
A17: =A12+7 -> 45302 | B17: =MONTH(A17) -> 1 | C17: =YEAR(A17) -> 2024 | D17: =C17*100+B17 -> 202401 | E17: =IF(B17<4,1,IF(B17<7,2,IF(B17<10,3,4))) -> 1 | F17: =C17*100+E17 -> 202401 | G17: 20240111 | H17: 5.25 | I17: 5.1876 | J17: 5.1883039 | K17: 5.1673171 | L17: 5.1189594 | M17: 5.0346508 | N17: 4.9187015 | O17: 4.782997 | P17: 4.639412 | Q17: 4.4977175 | R17: 4.3643034 | S17: 4.2417532 | T17: 4.1308656 | U17: 4.0309256 | V17: 3.9389315 | W17: 3.8538379 | X17: 3.7754857 | Y17: 3.7037131 | Z17: 3.6383589 | AA17: 3.579264 | AB17: 3.5262153 | AC17: 3.478802 | AD17: 3.4365684 | AE17: 3.3990568 | AF17: 3.3658098 | AG17: 3.3363711 | AH17: 3.3103155 | AI17: 3.287374 | AJ17: 3.267326 | AK17: 3.2499503 | AL17: 3.2350255 | AM17: 3.222331 | AN17: 3.2116455 | AO17: 3.2027477 | AP17: 3.195417 | AQ17: 3.189432 | AR17: 3.1845717 | AS17: 3.180615 | AT17: 3.1773707 | AU17: 3.1747784 | AV17: 3.1728145 | AW17: 3.1714548 | AX17: 3.1706755 | AY17: 3.1704526 | AZ17: 3.1707622 | BA17: 3.1715805 | BB17: 3.1728834 | BC17: 3.174647 | BD17: 3.1768474 | BE17: 3.1794607 | BF17: 3.1824649 | BG17: 3.1858464 | BH17: 3.1895941 | BI17: 3.1936968 | BJ17: 3.1981434 | BK17: 3.2029227 | BL17: 3.2080234 | BM17: 3.2134345 | BN17: 3.2191448 | BO17: 3.225143 | BP17: 3.2314182 | BQ17: 3.2379589 | BR17: 3.2822065 | BS17: 3.3335096
A18: =A13+7 -> 45303 | B18: =MONTH(A18) -> 1 | C18: =YEAR(A18) -> 2024 | D18: =C18*100+B18 -> 202401 | E18: =IF(B18<4,1,IF(B18<7,2,IF(B18<10,3,4))) -> 1 | F18: =C18*100+E18 -> 202401 | G18: 20240112 | H18: 5.25 | I18: 5.1884 | J18: 5.188735 | K18: 5.1604989 | L18: 5.0990229 | M18: 4.995414 | N18: 4.8574653 | O18: 4.7009555 | P18: 4.5407209 | Q18: 4.3873025 | R18: 4.2463179 | S18: 4.1196492 | T18: 4.0067672 | U18: 3.906338 | V18: 3.8150971 | W18: 3.7317978 | X18: 3.656016 | Y18: 3.5873251 | Z18: 3.5252985 | AA18: 3.4695121 | AB18: 3.4195369 | AC18: 3.374933 | AD18: 3.3352586 | AE18: 3.3000704 | AF18: 3.2689254 | AG18: 3.2413816 | AH18: 3.2170317 | AI18: 3.1956271 | AJ18: 3.1769635 | AK18: 3.1608361 | AL18: 3.14704 | AM18: 3.1353707 | AN18: 3.1256236 | AO18: 3.1175937 | AP18: 3.1110766 | AQ18: 3.1058674 | AR18: 3.1017615 | AS18: 3.0985542 | AT18: 3.0960678 | AU18: 3.0942432 | AV18: 3.0930544 | AW18: 3.0924751 | AX18: 3.0924793 | AY18: 3.0930407 | AZ18: 3.0941333 | BA18: 3.0957309 | BB18: 3.0978072 | BC18: 3.1003363 | BD18: 3.1032919 | BE18: 3.1066479 | BF18: 3.1103807 | BG18: 3.1144784 | BH18: 3.1189321 | BI18: 3.123733 | BJ18: 3.1288724 | BK18: 3.1343415 | BL18: 3.1401313 | BM18: 3.1462333 | BN18: 3.1526384 | BO18: 3.1593379 | BP18: 3.1663232 | BQ18: 3.1735852 | BR18: 3.2224388 | BS18: 3.2788019
A19: =A14+7 -> 45306 | B19: =MONTH(A19) -> 1 | C19: =YEAR(A19) -> 2024 | D19: =C19*100+B19 -> 202401 | E19: =IF(B19<4,1,IF(B19<7,2,IF(B19<10,3,4))) -> 1 | F19: =C19*100+E19 -> 202401 | G19: 20240115 | H19: 5.25 | I19: 5.1874 | J19: 5.1864987 | K19: 5.1613939 | L19: 5.1015345 | M19: 4.9956199 | N19: 4.8521908 | O19: 4.688973 | P19: 4.5229898 | Q19: 4.3655985 | R19: 4.2226677 | S19: 4.0950554 | T19: 3.9821699 | U19: 3.882187 | V19: 3.7914806 | W19: 3.7087614 | X19: 3.6335691 | Y19: 3.5654407 | Z19: 3.5039133 | AA19: 3.4485262 | AB19: 3.3988263 | AC19: 3.3543966 | AD19: 3.3148308 | AE19: 3.2797206 | AF19: 3.2486582 | AG19: 3.2212368 | AH19: 3.1970775 | AI19: 3.1759309 | AJ19: 3.1575841 | AK19: 3.1418233 | AL19: 3.1284346 | AM19: 3.117205 | AN19: 3.1079206 | AO19: 3.1003678 | AP19: 3.0943333 | AQ19: 3.0896034 | AR19: 3.0859646 | AS19: 3.0832033 | AT19: 3.0811348 | AU19: 3.0797022 | AV19: 3.0788836 | AW19: 3.078657 | AX19: 3.0790008 | AY19: 3.0798929 | AZ19: 3.0813115 | BA19: 3.0832348 | BB19: 3.0856409 | BC19: 3.088508 | BD19: 3.0918143 | BE19: 3.0955378 | BF19: 3.0996584 | BG19: 3.1041662 | BH19: 3.109054 | BI19: 3.1143149 | BJ19: 3.1199422 | BK19: 3.1259288 | BL19: 3.1322677 | BM19: 3.1389522 | BN19: 3.1459753 | BO19: 3.15333 | BP19: 3.1610095 | BQ19: 3.1690068 | BR19: 3.2230363 | BS19: 3.2852854
A20: =A15+7 -> 45307 | B20: =MONTH(A20) -> 1 | C20: =YEAR(A20) -> 2024 | D20: =C20*100+B20 -> 202401 | E20: =IF(B20<4,1,IF(B20<7,2,IF(B20<10,3,4))) -> 1 | F20: =C20*100+E20 -> 202401 | G20: 20240116 | H20: 5.25 | I20: 5.1876 | J20: 5.1912832 | K20: 5.1664072 | L20: 5.1080097 | M20: 5.0063493 | N20: 4.867976 | O20: 4.7086042 | P20: 4.5445595 | Q20: 4.38725 | R20: 4.2424888 | S20: 4.1116753 | T20: 3.9942376 | U20: 3.8892679 | V20: 3.7938851 | W20: 3.707063 | X20: 3.6284902 | Y20: 3.557852 | Z20: 3.4948342 | AA20: 3.4391248 | AB20: 3.3903464 | AC20: 3.3478821 | AD20: 3.3110591 | AE20: 3.2792031 | AF20: 3.2516403 | AG20: 3.2276975 | AH20: 3.2067727 | AI20: 3.188581 | AJ20: 3.1729261 | AK20: 3.1596107 | AL20: 3.1484378 | AM20: 3.1392107 | AN20: 3.1317324 | AO20: 3.1258057 | AP20: 3.121234 | AQ20: 3.1178202 | AR20: 3.1153674 | AS20: 3.1136786 | AT20: 3.1125798 | AU20: 3.1120197 | AV20: 3.1119887 | AW20: 3.1124767 | AX20: 3.1134739 | AY20: 3.1149705 | AZ20: 3.1169565 | BA20: 3.1194223 | BB20: 3.1223578 | BC20: 3.1257533 | BD20: 3.1295988 | BE20: 3.1338846 | BF20: 3.1386005 | BG20: 3.1437357 | BH20: 3.1492789 | BI20: 3.155219 | BJ20: 3.1615448 | BK20: 3.168245 | BL20: 3.1753084 | BM20: 3.182724 | BN20: 3.1904803 | BO20: 3.1985663 | BP20: 3.2069709 | BQ20: 3.2156826 | BR20: 3.2737519 | BS20: 3.3398985
A21: =A16+7 -> 45308 | B21: =MONTH(A21) -> 1 | C21: =YEAR(A21) -> 2024 | D21: =C21*100+B21 -> 202401 | E21: =IF(B21<4,1,IF(B21<7,2,IF(B21<10,3,4))) -> 1 | F21: =C21*100+E21 -> 202401 | G21: 20240117 | H21: 5.25 | I21: 5.188 | J21: 5.1870648 | K21: 5.1803458 | L21: 5.1485105 | M21: 5.0809502 | N21: 4.98113 | O21: 4.8598482 | P21: 4.7298052 | Q21: 4.6007117 | R21: 4.4787319 | S21: 4.3664604 | T21: 4.2645357 | U21: 4.1724997 | V21: 4.0877527 | W21: 4.0093645 | X21: 3.9370579 | Y21: 3.8705529 | Z21: 3.8095699 | AA21: 3.7538311 | AB21: 3.7030483 | AC21: 3.6569008 | AD21: 3.6150618 | AE21: 3.5772029 | AF21: 3.5429957 | AG21: 3.5121132 | AH21: 3.4842457 | AI21: 3.4591839 | AJ21: 3.4367527 | AK21: 3.4167765 | AL21: 3.3990794 | AM21: 3.3834865 | AN21: 3.3698221 | AO21: 3.3579105 | AP21: 3.3475765 | AQ21: 3.3386445 | AR21: 3.3309389 | AS21: 3.3242844 | AT21: 3.3185256 | AU21: 3.3136055 | AV21: 3.3094973 | AW21: 3.3061737 | AX21: 3.3036079 | AY21: 3.3017729 | AZ21: 3.3006415 | BA21: 3.3001869 | BB21: 3.3003819 | BC21: 3.3011997 | BD21: 3.3026131 | BE21: 3.3045953 | BF21: 3.3071205 | BG21: 3.3101696 | BH21: 3.3137253 | BI21: 3.31777 | BJ21: 3.3222865 | BK21: 3.3272571 | BL21: 3.3326646 | BM21: 3.3384916 | BN21: 3.3447204 | BO21: 3.3513339 | BP21: 3.3583145 | BQ21: 3.3656448 | BR21: 3.4160227 | BS21: 3.4747675
A22: =A17+7 -> 45309 | B22: =MONTH(A22) -> 1 | C22: =YEAR(A22) -> 2024 | D22: =C22*100+B22 -> 202401 | E22: =IF(B22<4,1,IF(B22<7,2,IF(B22<10,3,4))) -> 1 | F22: =C22*100+E22 -> 202401 | G22: 20240118 | H22: 5.25 | I22: 5.1883 | J22: 5.1869164 | K22: 5.1776901 | L22: 5.1408352 | M22: 5.0663889 | N22: 4.9579612 | O22: 4.8290191 | P22: 4.6930677 | Q22: 4.5596575 | R22: 4.4343029 | S22: 4.3189017 | T22: 4.2137297 | U22: 4.1179306 | V22: 4.0287191 | W22: 3.9452892 | X22: 3.8677035 | Y22: 3.7960222 | Z22: 3.7303058 | AA22: 3.670617 | AB22: 3.6169267 | AC22: 3.5688652 | AD22: 3.5259831 | AE22: 3.4878294 | AF22: 3.4539534 | AG22: 3.4239054 | AH22: 3.3972655 | AI22: 3.3737641 | AJ22: 3.3531784 | AK22: 3.3352845 | AL22: 3.3198589 | AM22: 3.3066783 | AN22: 3.2955192 | AO22: 3.2861579 | AP22: 3.2783713 | AQ22: 3.2719357 | AR22: 3.2666275 | AS22: 3.2622235 | AT22: 3.2585313 | AU22: 3.2554963 | AV22: 3.2531022 | AW22: 3.2513323 | AX22: 3.2501701 | AY22: 3.2495992 | AZ22: 3.249603 | BA22: 3.250165 | BB22: 3.2512688 | BC22: 3.2528977 | BD22: 3.2550354 | BE22: 3.2576652 | BF22: 3.2607713 | BG22: 3.2643408 | BH22: 3.2683613 | BI22: 3.2728207 | BJ22: 3.2777068 | BK22: 3.2830074 | BL22: 3.2887101 | BM22: 3.294803 | BN22: 3.3012737 | BO22: 3.3081099 | BP22: 3.3152996 | BQ22: 3.3228304 | BR22: 3.374397 | BS22: 3.4345602
A23: =A18+7 -> 45310 | B23: =MONTH(A23) -> 1 | C23: =YEAR(A23) -> 2024 | D23: =C23*100+B23 -> 202401 | E23: =IF(B23<4,1,IF(B23<7,2,IF(B23<10,3,4))) -> 1 | F23: =C23*100+E23 -> 202401 | G23: 20240119 | H23: 5.25 | I23: 5.1876 | J23: 5.1887528 | K23: 5.1780003 | L23: 5.1399208 | M23: 5.0660792 | N23: 4.9607851 | O23: 4.8358842 | P23: 4.7040655 | Q23: 4.5747957 | R23: 4.4535067 | S23: 4.342442 | T23: 4.2414709 | U23: 4.1495841 | V23: 4.0640079 | W23: 3.9839484 | X23: 3.9094062 | Y23: 3.8403786 | Z23: 3.7768635 | AA23: 3.718861 | AB23: 3.6663115 | AC23: 3.6188895 | AD23: 3.5761943 | AE23: 3.5378231 | AF23: 3.5033735 | AG23: 3.4724444 | AH23: 3.4446637 | AI23: 3.4197932 | AJ23: 3.3976326 | AK23: 3.3779807 | AL23: 3.3606364 | AM23: 3.3453992 | AN23: 3.332068 | AO23: 3.3204417 | AP23: 3.3103197 | AQ23: 3.3015011 | AR23: 3.2937847 | AS23: 3.2869698 | AT23: 3.2808836 | AU23: 3.2754765 | AV23: 3.2707334 | AW23: 3.2666391 | AX23: 3.2631784 | AY23: 3.260336 | AZ23: 3.2580967 | BA23: 3.2564452 | BB23: 3.2553664 | BC23: 3.2548451 | BD23: 3.2548659 | BE23: 3.2554136 | BF23: 3.2564736 | BG23: 3.258033 | BH23: 3.2600796 | BI23: 3.2626013 | BJ23: 3.2655858 | BK23: 3.269021 | BL23: 3.2728947 | BM23: 3.2771947 | BN23: 3.2819087 | BO23: 3.2870246 | BP23: 3.2925303 | BQ23: 3.2984134 | BR23: 3.3409003 | BS23: 3.3935567
A24: =A19+7 -> 45313 | B24: =MONTH(A24) -> 1 | C24: =YEAR(A24) -> 2024 | D24: =C24*100+B24 -> 202401 | E24: =IF(B24<4,1,IF(B24<7,2,IF(B24<10,3,4))) -> 1 | F24: =C24*100+E24 -> 202401 | G24: 20240122 | H24: 5.25 | I24: 5.1879 | J24: 5.1876758 | K24: 5.1735163 | L24: 5.1304359 | M24: 5.0506997 | N24: 4.9406132 | O24: 4.8124133 | P24: 4.6785996 | Q24: 4.548289 | R24: 4.4266204 | S24: 4.3151828 | T24: 4.2142326 | U24: 4.1228926 | V24: 4.0394159 | W24: 3.9630131 | X24: 3.8932351 | Y24: 3.8296297 | Z24: 3.7717453 | AA24: 3.7191321 | AB24: 3.6713504 | AC24: 3.6280058 | AD24: 3.5887163 | AE24: 3.5530986 | AF24: 3.5207691 | AG24: 3.4913458 | AH24: 3.4644814 | AI24: 3.4399885 | AJ24: 3.4177248 | AK24: 3.3975468 | AL24: 3.3793113 | AM24: 3.3628758 | AN24: 3.3480969 | AO24: 3.3348316 | AP24: 3.322937 | AQ24: 3.31227 | AR24: 3.3026875 | AS24: 3.2940466 | AT24: 3.2862231 | AU24: 3.2791755 | AV24: 3.2728859 | AW24: 3.2673357 | AX24: 3.2625067 | AY24: 3.2583806 | AZ24: 3.2549391 | BA24: 3.2521639 | BB24: 3.2500366 | BC24: 3.2485391 | BD24: 3.2476529 | BE24: 3.2473597 | BF24: 3.247642 | BG24: 3.2484853 | BH24: 3.2498763 | BI24: 3.251802 | BJ24: 3.2542491 | BK24: 3.2572043 | BL24: 3.2606544 | BM24: 3.2645863 | BN24: 3.2689867 | BO24: 3.2738422 | BP24: 3.2791399 | BQ24: 3.2848664 | BR24: 3.3273444 | BS24: 3.3810345
A25: =A20+7 -> 45314 | B25: =MONTH(A25) -> 1 | C25: =YEAR(A25) -> 2024 | D25: =C25*100+B25 -> 202401 | E25: =IF(B25<4,1,IF(B25<7,2,IF(B25<10,3,4))) -> 1 | F25: =C25*100+E25 -> 202401 | G25: 20240123 | H25: 5.25 | I25: 5.1873 | J25: 5.1859941 | K25: 5.174959 | L25: 5.1400496 | M25: 5.0725396 | N25: 4.9760912 | O25: 4.8604414 | P25: 4.7365585 | Q25: 4.6134216 | R25: 4.496681 | S25: 4.3890212 | T25: 4.2910856 | U25: 4.2025817 | V25: 4.1210901 | W25: 4.0457403 | X25: 3.9762845 | Y25: 3.912472 | Z25: 3.8540524 | AA25: 3.8007774 | AB25: 3.752374 | AC25: 3.7084834 | AD25: 3.668728 | AE25: 3.6327287 | AF25: 3.6001064 | AG25: 3.5704832 | AH25: 3.5435145 | AI25: 3.519007 | AJ25: 3.4968103 | AK25: 3.4767731 | AL25: 3.4587441 | AM25: 3.4425727 | AN25: 3.4281076 | AO25: 3.4151976 | AP25: 3.403692 | AQ25: 3.3934397 | AR25: 3.3842894 | AS25: 3.3760902 | AT25: 3.3687072 | AU25: 3.3620912 | AV25: 3.3562225 | AW25: 3.3510809 | AX25: 3.3466465 | AY25: 3.3428994 | AZ25: 3.3398195 | BA25: 3.3373869 | BB25: 3.3355815 | BC25: 3.3343835 | BD25: 3.3337727 | BE25: 3.3337293 | BF25: 3.334234 | BG25: 3.3352711 | BH25: 3.3368259 | BI25: 3.3388839 | BJ25: 3.3414304 | BK25: 3.3444509 | BL25: 3.3479307 | BM25: 3.3518553 | BN25: 3.3562099 | BO25: 3.36098 | BP25: 3.3661511 | BQ25: 3.3717084 | BR25: 3.4123271 | BS25: 3.4630552
... A72: =A67+7 -> 45379 | B72: =MONTH(A72) -> 3 | C72: =YEAR(A72) -> 2024 | D72: =C72*100+B72 -> 202403 | E72: =IF(B72<4,1,IF(B72<7,2,IF(B72<10,3,4))) -> 1 | F72: =C72*100+E72 -> 202401 | G72: 20240328 | H72: 5.25 | I72: 5.1911 | J72: 5.1827949 | K72: 5.1285197 | L72: 5.0548387 | M72: 4.9650427 | N72: 4.8685886 | O72: 4.7708037 | P72: 4.6732194 | Q72: 4.5769532 | R72: 4.4834965 | S72: 4.3944428 | T72: 4.3108747 | U72: 4.2335021 | V72: 4.162811 | W72: 4.0982378 | X72: 4.0389508 | Y72: 3.9841158 | Z72: 3.9328986 | AA72: 3.8844672 | AB72: 3.8381017 | AC72: 3.7936677 | AD72: 3.7512193 | AE72: 3.7108091 | AF72: 3.6724898 | AG72: 3.6363153 | AH72: 3.6023211 | AI72: 3.5704587 | AJ72: 3.5406553 | AK72: 3.5128369 | AL72: 3.4869296 | AM72: 3.4628602 | AN72: 3.440555 | AO72: 3.4199399 | AP72: 3.400942 | AQ72: 3.3834872 | AR72: 3.3675018 | AS72: 3.3529125 | AT72: 3.3396465 | AU72: 3.3276361 | AV72: 3.3168154 | AW72: 3.307118 | AX72: 3.2984779 | AY72: 3.2908291 | AZ72: 3.2841052 | BA72: 3.2782402 | BB72: 3.273168 | BC72: 3.2688225 | BD72: 3.2651374 | BE72: 3.2620468 | BF72: 3.2594922 | BG72: 3.2574503 | BH72: 3.2559073 | BI72: 3.2548493 | BJ72: 3.2542624 | BK72: 3.2541328 | BL72: 3.2544467 | BM72: 3.2551903 | BN72: 3.2563496 | BO72: 3.2579108 | BP72: 3.2598602 | BQ72: 3.2621838 | BR72: 3.2833438 | BS72: 3.3153029
A73: =A68+7 -> 45380 | B73: =MONTH(A73) -> 3 | C73: =YEAR(A73) -> 2024 | D73: =C73*100+B73 -> 202403 | E73: =IF(B73<4,1,IF(B73<7,2,IF(B73<10,3,4))) -> 1 | F73: =C73*100+E73 -> 202401 | G73: 20240329 | H73: 5.25 | I73: #N/A | J73: #N/A | K73: #N/A | L73: #N/A | M73: #N/A | N73: #N/A | O73: #N/A | P73: #N/A | Q73: #N/A | R73: #N/A | S73: #N/A | T73: #N/A | U73: #N/A | V73: #N/A | W73: #N/A | X73: #N/A | Y73: #N/A | Z73: #N/A | AA73: #N/A | AB73: #N/A | AC73: #N/A | AD73: #N/A | AE73: #N/A | AF73: #N/A | AG73: #N/A | AH73: #N/A | AI73: #N/A | AJ73: #N/A | AK73: #N/A | AL73: #N/A | AM73: #N/A | AN73: #N/A | AO73: #N/A | AP73: #N/A | AQ73: #N/A | AR73: #N/A | AS73: #N/A | AT73: #N/A | AU73: #N/A | AV73: #N/A | AW73: #N/A | AX73: #N/A | AY73: #N/A | AZ73: #N/A | BA73: #N/A | BB73: #N/A | BC73: #N/A | BD73: #N/A | BE73: #N/A | BF73: #N/A | BG73: #N/A | BH73: #N/A | BI73: #N/A | BJ73: #N/A | BK73: #N/A | BL73: #N/A | BM73: #N/A | BN73: #N/A | BO73: #N/A | BP73: #N/A | BQ73: #N/A | BR73: #N/A | BS73: #N/A
A74: =A69+7 -> 45383 | B74: =MONTH(A74) -> 4 | C74: =YEAR(A74) -> 2024 | D74: =C74*100+B74 -> 202404 | E74: =IF(B74<4,1,IF(B74<7,2,IF(B74<10,3,4))) -> 2 | F74: =C74*100+E74 -> 202402 | G74: 20240401 | H74: 5.25 | I74: #N/A | J74: #N/A | K74: #N/A | L74: #N/A | M74: #N/A | N74: #N/A | O74: #N/A | P74: #N/A | Q74: #N/A | R74: #N/A | S74: #N/A | T74: #N/A | U74: #N/A | V74: #N/A | W74: #N/A | X74: #N/A | Y74: #N/A | Z74: #N/A | AA74: #N/A | AB74: #N/A | AC74: #N/A | AD74: #N/A | AE74: #N/A | AF74: #N/A | AG74: #N/A | AH74: #N/A | AI74: #N/A | AJ74: #N/A | AK74: #N/A | AL74: #N/A | AM74: #N/A | AN74: #N/A | AO74: #N/A | AP74: #N/A | AQ74: #N/A | AR74: #N/A | AS74: #N/A | AT74: #N/A | AU74: #N/A | AV74: #N/A | AW74: #N/A | AX74: #N/A | AY74: #N/A | AZ74: #N/A | BA74: #N/A | BB74: #N/A | BC74: #N/A | BD74: #N/A | BE74: #N/A | BF74: #N/A | BG74: #N/A | BH74: #N/A | BI74: #N/A | BJ74: #N/A | BK74: #N/A | BL74: #N/A | BM74: #N/A | BN74: #N/A | BO74: #N/A | BP74: #N/A | BQ74: #N/A | BR74: #N/A | BS74: #N/A
A75: =A70+7 -> 45384 | B75: =MONTH(A75) -> 4 | C75: =YEAR(A75) -> 2024 | D75: =C75*100+B75 -> 202404 | E75: =IF(B75<4,1,IF(B75<7,2,IF(B75<10,3,4))) -> 2 | F75: =C75*100+E75 -> 202402 | G75: 20240402 | H75: 5.25 | I75: 5.1956 | J75: 5.1807489 | K75: 5.1199562 | L75: 5.0432068 | M75: 4.9538124 | N75: 4.8601742 | O75: 4.7672807 | P75: 4.6768675 | Q75: 4.5904147 | R75: 4.5095263 | S75: 4.4349691 | T75: 4.3666138 | U75: 4.3040203 | V75: 4.245397 | W75: 4.1899963 | X75: 4.1374546 | Y75: 4.0874062 | Z75: 4.0394856 | AA75: 3.993329 | AB75: 3.9486534 | AC75: 3.9055228 | AD75: 3.8640941 | AE75: 3.8245225 | AF75: 3.7869632 | AG75: 3.751573 | AH75: 3.7184638 | AI75: 3.6875746 | AJ75: 3.6588023 | AK75: 3.6320425 | AL75: 3.6071911 | AM75: 3.5841446 | AN75: 3.5627989 | AO75: 3.5430499 | AP75: 3.5247939 | AQ75: 3.507927 | AR75: 3.4923449 | AS75: 3.4779442 | AT75: 3.4646324 | AU75: 3.4523639 | AV75: 3.4411054 | AW75: 3.430823 | AX75: 3.4214829 | AY75: 3.4130515 | AZ75: 3.4054951 | BA75: 3.3987798 | BB75: 3.3928722 | BC75: 3.3877384 | BD75: 3.3833446 | BE75: 3.3796573 | BF75: 3.3766452 | BG75: 3.3742886 | BH75: 3.3725717 | BI75: 3.3714786 | BJ75: 3.3709933 | BK75: 3.3710999 | BL75: 3.3717825 | BM75: 3.3730252 | BN75: 3.3748121 | BO75: 3.3771271 | BP75: 3.3799545 | BQ75: 3.3832782 | BR75: 3.4124666 | BS75: 3.4537561
A76: =A71+7 -> 45385 | B76: =MONTH(A76) -> 4 | C76: =YEAR(A76) -> 2024 | D76: =C76*100+B76 -> 202404 | E76: =IF(B76<4,1,IF(B76<7,2,IF(B76<10,3,4))) -> 2 | F76: =C76*100+E76 -> 202402 | G76: 20240403 | H76: 5.25 | I76: 5.1952 | J76: 5.1797674 | K76: 5.1131197 | L76: 5.0320872 | M76: 4.9409016 | N76: 4.8471024 | O76: 4.7546427 | P76: 4.6646348 | Q76: 4.5782068 | R76: 4.4967782 | S76: 4.4211358 | T76: 4.3513992 | U76: 4.2873411 | V76: 4.2279176 | W76: 4.1723537 | X76: 4.1200009 | Y76: 4.0702083 | Z76: 4.0223254 | AA76: 3.9757031 | AB76: 3.9298374 | AC76: 3.8848387 | AD76: 3.8409809 | AE76: 3.7985361 | AF76: 3.7577764 | AG76: 3.7189756 | AH76: 3.6823697 | AI76: 3.6479792 | AJ76: 3.6157465 | AK76: 3.5856125 | AL76: 3.5575183 | AM76: 3.531406 | AN76: 3.5072165 | AO76: 3.4848911 | AP76: 3.4643715 | AQ76: 3.445599 | AR76: 3.4285146 | AS76: 3.4130603 | AT76: 3.399174 | AU76: 3.3867787 | AV76: 3.375793 | AW76: 3.3661353 | AX76: 3.3577239 | AY76: 3.3504775 | AZ76: 3.3443143 | BA76: 3.3391528 | BB76: 3.3349114 | BC76: 3.3315087 | BD76: 3.3288628 | BE76: 3.3268925 | BF76: 3.3255251 | BG76: 3.324728 | BH76: 3.3244799 | BI76: 3.3247592 | BJ76: 3.3255443 | BK76: 3.3268139 | BL76: 3.3285463 | BM76: 3.3307202 | BN76: 3.3333139 | BO76: 3.3363061 | BP76: 3.3396751 | BQ76: 3.3433996 | BR76: 3.3723498 | BS76: 3.4107635
A77: =A72+7 -> 45386 | B77: =MONTH(A77) -> 4 | C77: =YEAR(A77) -> 2024 | D77: =C77*100+B77 -> 202404 | E77: =IF(B77<4,1,IF(B77<7,2,IF(B77<10,3,4))) -> 2 | F77: =C77*100+E77 -> 202402 | G77: 20240404 | H77: 5.25 | I77: 5.1949 | J77: 5.1769496 | K77: 5.1016997 | L77: 5.0170889 | M77: 4.9251208 | N77: 4.8317243 | O77: 4.740301 | P77: 4.6518337 | Q77: 4.5674583 | R77: 4.488418 | S77: 4.415362 | T77: 4.3478637 | U77: 4.285214 | V77: 4.2255322 | W77: 4.1681248 | X77: 4.1126996 | Y77: 4.0589627 | Z77: 4.0066199 | AA77: 3.9553792 | AB77: 3.9050367 | AC77: 3.8558508 | AD77: 3.8082292 | AE77: 3.762578 | AF77: 3.7193033 | AG77: 3.6788126 | AH77: 3.6414432 | AI77: 3.6071603 | AJ77: 3.5758061 | AK77: 3.5472212 | AL77: 3.5212464 | AM77: 3.4977234 | AN77: 3.4764931 | AO77: 3.4573963 | AP77: 3.4402745 | AQ77: 3.4249688 | AR77: 3.4113199 | AS77: 3.3991694 | AT77: 3.3883705 | AU77: 3.3788308 | AV77: 3.3704734 | AW77: 3.3632209 | AX77: 3.356996 | AY77: 3.3517216 | AZ77: 3.3473204 | BA77: 3.3437151 | BB77: 3.3408285 | BC77: 3.3385835 | BD77: 3.3369027 | BE77: 3.3357089 | BF77: 3.3349356 | BG77: 3.3345643 | BH77: 3.3345893 | BI77: 3.3350051 | BJ77: 3.3358062 | BK77: 3.3369869 | BL77: 3.3385418 | BM77: 3.3404654 | BN77: 3.3427521 | BO77: 3.3453962 | BP77: 3.3483924 | BQ77: 3.3517351 | BR77: 3.3785759 | BS77: 3.4153988
A78: =A73+7 -> 45387 | B78: =MONTH(A78) -> 4 | C78: =YEAR(A78) -> 2024 | D78: =C78*100+B78 -> 202404 | E78: =IF(B78<4,1,IF(B78<7,2,IF(B78<10,3,4))) -> 2 | F78: =C78*100+E78 -> 202402 | G78: 20240405 | H78: 5.25 | I78: 5.1949 | J78: 5.1743507 | K78: 5.0990626 | L78: 5.0156411 | M78: 4.9256211 | N78: 4.8342136 | O78: 4.7444207 | P78: 4.6568399 | Q78: 4.5722358 | R78: 4.4916264 | S78: 4.4156849 | T78: 4.3445416 | U78: 4.2781786 | V78: 4.2157358 | W78: 4.1567632 | X78: 4.1010152 | Y78: 4.0482438 | Z78: 3.9982015 | AA78: 3.9506425 | AB78: 3.9053601 | AC78: 3.862339 | AD78: 3.8216207 | AE78: 3.783245 | AF78: 3.747252 | AG78: 3.7136829 | AH78: 3.682556 | AI78: 3.6537839 | AJ78: 3.6272481 | AK78: 3.6028289 | AL78: 3.5804068 | AM78: 3.5598631 | AN78: 3.5410783 | AO78: 3.5239328 | AP78: 3.5083079 | AQ78: 3.494084 | AR78: 3.4811418 | AS78: 3.4693622 | AT78: 3.4586379 | AU78: 3.4489092 | AV78: 3.440129 | AW78: 3.4322496 | AX78: 3.4252234 | AY78: 3.4190032 | AZ78: 3.4135414 | BA78: 3.4087904 | BB78: 3.4047029 | BC78: 3.4012313 | BD78: 3.3983281 | BE78: 3.3959459 | BF78: 3.394043 | BG78: 3.3926035 | BH78: 3.3916186 | BI78: 3.3910794 | BJ78: 3.390977 | BK78: 3.3913028 | BL78: 3.3920477 | BM78: 3.3932031 | BN78: 3.39476 | BO78: 3.3967096 | BP78: 3.3990431 | BQ78: 3.4017517 | BR78: 3.4253239 | BS78: 3.4598017
A79: =A74+7 -> 45390 | B79: =MONTH(A79) -> 4 | C79: =YEAR(A79) -> 2024 | D79: =C79*100+B79 -> 202404 | E79: =IF(B79<4,1,IF(B79<7,2,IF(B79<10,3,4))) -> 2 | F79: =C79*100+E79 -> 202402 | G79: 20240408 | H79: 5.25 | I79: 5.1949 | J79: 5.1730522 | K79: 5.0963888 | L79: 5.0139903 | M79: 4.927098 | N79: 4.8391915 | O79: 4.7523231 | P79: 4.6673225 | Q79: 4.5856252 | R79: 4.5090046 | S79: 4.438254 | T79: 4.3734106 | U79: 4.3140391 | V79: 4.2587921 | W79: 4.2069901 | X79: 4.1582037 | Y79: 4.1120019 | Z79: 4.0679533 | AA79: 4.0256285 | AB79: 3.9846795 | AC79: 3.945108 | AD79: 3.9070088 | AE79: 3.8704753 | AF79: 3.8356012 | AG79: 3.802481 | AH79: 3.7711816 | AI79: 3.7416622 | AJ79: 3.7138564 | AK79: 3.6876969 | AL79: 3.6631161 | AM79: 3.6400476 | AN79: 3.6184239 | AO79: 3.5981777 | AP79: 3.5792423 | AQ79: 3.5615504 | AR79: 3.5450348 | AS79: 3.5296285 | AT79: 3.5152706 | AU79: 3.5019243 | AV79: 3.4895598 | AW79: 3.4781464 | AX79: 3.4676539 | AY79: 3.458052 | AZ79: 3.4493105 | BA79: 3.4413988 | BB79: 3.4342869 | BC79: 3.4279443 | BD79: 3.4223407 | BE79: 3.417446 | BF79: 3.4132316 | BG79: 3.4096799 | BH79: 3.4067769 | BI79: 3.4045083 | BJ79: 3.4028602 | BK79: 3.4018183 | BL79: 3.4013687 | BM79: 3.4014971 | BN79: 3.4021895 | BO79: 3.4034318 | BP79: 3.4052099 | BQ79: 3.4075096 | BR79: 3.431248 | BS79: 3.4688325
A80: =A75+7 -> 45391 | B80: =MONTH(A80) -> 4 | C80: =YEAR(A80) -> 2024 | D80: =C80*100+B80 -> 202404 | E80: =IF(B80<4,1,IF(B80<7,2,IF(B80<10,3,4))) -> 2 | F80: =C80*100+E80 -> 202402 | G80: 20240409 | H80: 5.25 | I80: 5.1976 | J80: 5.1735725 | K80: 5.0952865 | L80: 5.0105427 | M80: 4.9211557 | N80: 4.8305117 | O80: 4.7405381 | P80: 4.6521592 | Q80: 4.5669255 | R80: 4.4867711 | S80: 4.4127683 | T80: 4.3449946 | U80: 4.2831506 | V80: 4.225535 | W80: 4.1713594 | X80: 4.1201866 | Y80: 4.0715771 | Z80: 4.025092 | AA80: 3.9802938 | AB80: 3.936831 | AC80: 3.8947212 | AD80: 3.8540801 | AE80: 3.815022 | AF80: 3.7776613 | AG80: 3.7421137 | AH80: 3.7084644 | AI80: 3.676683 | AJ80: 3.6467111 | AK80: 3.6184892 | AL80: 3.5919577 | AM80: 3.5670583 | AN80: 3.5437313 | AO80: 3.5219175 | AP80: 3.5015582 | AQ80: 3.482594 | AR80: 3.4649655 | AS80: 3.448614 | AT80: 3.4334831 | AU80: 3.4195288 | AV80: 3.4067104 | AW80: 3.3949868 | AX80: 3.3843168 | AY80: 3.3746598 | AZ80: 3.3659747 | BA80: 3.3582204 | BB80: 3.3513561 | BC80: 3.3453409 | BD80: 3.3401336 | BE80: 3.3356935 | BF80: 3.331982 | BG80: 3.3289729 | BH80: 3.3266437 | BI80: 3.324972 | BJ80: 3.3239351 | BK80: 3.3235107 | BL80: 3.3236762 | BM80: 3.3244091 | BN80: 3.325687 | BO80: 3.3274873 | BP80: 3.3297875 | BQ80: 3.3325652 | BR80: 3.3580989 | BS80: 3.395766
A81: =A76+7 -> 45392 | B81: =MONTH(A81) -> 4 | C81: =YEAR(A81) -> 2024 | D81: =C81*100+B81 -> 202404 | E81: =IF(B81<4,1,IF(B81<7,2,IF(B81<10,3,4))) -> 2 | F81: =C81*100+E81 -> 202402 | G81: 20240410 | H81: 5.25 | I81: 5.1978 | J81: 5.1829638 | K81: 5.1267104 | L81: 5.0605244 | M81: 4.9882833 | N81: 4.9138514 | O81: 4.8392415 | P81: 4.765667 | Q81: 4.6950966 | R81: 4.629687 | S81: 4.570391 | T81: 4.5169311 | U81: 4.4683502 | V81: 4.4221688 | W81: 4.3774853 | X81: 4.3339173 | Y81: 4.2910808 | Z81: 4.248592 | AA81: 4.2060685 | AB81: 4.163245 | AC81: 4.1203548 | AD81: 4.0777634 | AE81: 4.035835 | AF81: 3.9949337 | AG81: 3.9554252 | AH81: 3.9176095 | AI81: 3.8815302 | AJ81: 3.8471681 | AK81: 3.8145029 | AL81: 3.7835141 | AM81: 3.7541825 | AN81: 3.7264876 | AO81: 3.7004092 | AP81: 3.6759277 | AQ81: 3.653023 | AR81: 3.6316746 | AS81: 3.6118631 | AT81: 3.5935624 | AU81: 3.5767178 | AV81: 3.5612664 | AW81: 3.547145 | AX81: 3.5342902 | AY81: 3.5226391 | AZ81: 3.5121283 | BA81: 3.5026947 | BB81: 3.4942752 | BC81: 3.4868066 | BD81: 3.4802256 | BE81: 3.4744691 | BF81: 3.4694794 | BG81: 3.4652226 | BH81: 3.4616714 | BI81: 3.4587988 | BJ81: 3.4565772 | BK81: 3.4549797 | BL81: 3.453979 | BM81: 3.4535477 | BN81: 3.4536587 | BO81: 3.4542847 | BP81: 3.4553985 | BQ81: 3.4569729 | BR81: 3.4749519 | BS81: 3.5049891
A82: =A77+7 -> 45393 | B82: =MONTH(A82) -> 4 | C82: =YEAR(A82) -> 2024 | D82: =C82*100+B82 -> 202404 | E82: =IF(B82<4,1,IF(B82<7,2,IF(B82<10,3,4))) -> 2 | F82: =C82*100+E82 -> 202402 | G82: 20240411 | H82: 5.25 | I82: 5.198 | J82: 5.1842682 | K82: 5.1430865 | L82: 5.0913354 | M82: 5.0313446 | N82: 4.9668834 | O82: 4.9006882 | P82: 4.8343025 | Q82: 4.7698293 | R82: 4.70966 | S82: 4.6552127 | T82: 4.6062733 | U82: 4.5618678 | V82: 4.5187788 | W82: 4.4759072 | X82: 4.4328707 | Y82: 4.3892856 | Z82: 4.3447682 | AA82: 4.2989362 | AB82: 4.2515468 | AC82: 4.2030786 | AD82: 4.1542425 | AE82: 4.1057479 | AF82: 4.058304 | AG82: 4.0126218 | AH82: 3.9693057 | AI82: 3.9284478 | AJ82: 3.8899863 | AK82: 3.8538578 | AL82: 3.8199987 | AM82: 3.788347 | AN82: 3.7588392 | AO82: 3.7314121 | AP82: 3.7060033 | AQ82: 3.6825495 | AR82: 3.6609875 | AS82: 3.6412548 | AT82: 3.6232832 | AU82: 3.6069827 | AV82: 3.5922578 | AW82: 3.5790124 | AX82: 3.5671505 | AY82: 3.5565765 | AZ82: 3.5471944 | BA82: 3.5389083 | BB82: 3.5316223 | BC82: 3.5252406 | BD82: 3.5196672 | BE82: 3.5148063 | BF82: 3.5105735 | BG82: 3.5069347 | BH82: 3.5038699 | BI82: 3.501359 | BJ82: 3.4993819 | BK82: 3.4979186 | BL82: 3.4969489 | BM82: 3.4964528 | BN82: 3.4964103 | BO82: 3.4968011 | BP82: 3.4976054 | BQ82: 3.4988029 | BR82: 3.5134585 | BS82: 3.5392484
A83: =A78+7 -> 45394 | B83: =MONTH(A83) -> 4 | C83: =YEAR(A83) -> 2024 | D83: =C83*100+B83 -> 202404 | E83: =IF(B83<4,1,IF(B83<7,2,IF(B83<10,3,4))) -> 2 | F83: =C83*100+E83 -> 202402 | G83: 20240412 | H83: 5.25 | I83: 5.198 | J83: 5.1777519 | K83: 5.1243654 | L83: 5.0619834 | M83: 4.99353 | N83: 4.922471 | O83: 4.8506936 | P83: 4.7792744 | Q83: 4.7097298 | R83: 4.6435819 | S83: 4.5815523 | T83: 4.5234462 | U83: 4.4687694 | V83: 4.4162013 | W83: 4.3652519 | X83: 4.3157671 | Y83: 4.2675908 | Z83: 4.2205672 | AA83: 4.174542 | AB83: 4.1294101 | AC83: 4.0853022 | AD83: 4.0424186 | AE83: 4.0009584 | AF83: 3.9611205 | AG83: 3.9231054 | AH83: 3.8870719 | AI83: 3.8530021 | AJ83: 3.8208309 | AK83: 3.7904914 | AL83: 3.7619172 | AM83: 3.7350428 | AN83: 3.7098016 | AO83: 3.6861272 | AP83: 3.6639539 | AQ83: 3.6432152 | AR83: 3.6238448 | AS83: 3.6057768 | AT83: 3.588948 | AU83: 3.5733078 | AV83: 3.5588093 | AW83: 3.5454051 | AX83: 3.5330478 | AY83: 3.5216904 | AZ83: 3.5112855 | BA83: 3.5017858 | BB83: 3.4931442 | BC83: 3.4853134 | BD83: 3.4782459 | BE83: 3.4718949 | BF83: 3.4662174 | BG83: 3.4611909 | BH83: 3.4567989 | BI83: 3.4530242 | BJ83: 3.4498502 | BK83: 3.4472599 | BL83: 3.4452364 | BM83: 3.443763 | BN83: 3.4428228 | BO83: 3.4423989 | BP83: 3.4424745 | BQ83: 3.4430327 | BR83: 3.4556619 | BS83: 3.4819572
A84: =A79+7 -> 45397 | B84: =MONTH(A84) -> 4 | C84: =YEAR(A84) -> 2024 | D84: =C84*100+B84 -> 202404 | E84: =IF(B84<4,1,IF(B84<7,2,IF(B84<10,3,4))) -> 2 | F84: =C84*100+E84 -> 202402 | G84: 20240415 | H84: 5.25 | I84: 5.1984 | J84: 5.1768825 | K84: 5.1245399 | L84: 5.0626385 | M84: 4.9957348 | N84: 4.9274829 | O84: 4.8597546 | P84: 4.794103 | Q84: 4.7324453 | R84: 4.6765649 | S84: 4.6268466 | T84: 4.5824389 | U84: 4.5418212 | V84: 4.5020418 | W84: 4.4622795 | X84: 4.4224011 | Y84: 4.3822716 | Z84: 4.3417564 | AA84: 4.300722 | AB84: 4.2591184 | AC84: 4.2172519 | AD84: 4.1755238 | AE84: 4.1343338 | AF84: 4.0940818 | AG84: 4.0551691 | AH84: 4.0179235 | AI84: 3.9823854 | AJ84: 3.9485244 | AK84: 3.9163092 | AL84: 3.885708 | AM84: 3.8566906 | AN84: 3.8292254 | AO84: 3.803281 | AP84: 3.7788268 | AQ84: 3.7558314 | AR84: 3.7342635 | AS84: 3.7140923 | AT84: 3.6952842 | AU84: 3.6777964 | AV84: 3.6615844 | AW84: 3.646603 | AX84: 3.6328071 | AY84: 3.6201523 | AZ84: 3.6085933 | BA84: 3.5980852 | BB84: 3.5885833 | BC84: 3.5800426 | BD84: 3.572418 | BE84: 3.5656648 | BF84: 3.5597402 | BG84: 3.5546147 | BH84: 3.550264 | BI84: 3.5466632 | BJ84: 3.5437879 | BK84: 3.5416135 | BL84: 3.5401155 | BM84: 3.5392693 | BN84: 3.5390503 | BO84: 3.539434 | BP84: 3.5403957 | BQ84: 3.541911 | BR84: 3.5613048 | BS84: 3.5947629
A85: =A80+7 -> 45398 | B85: =MONTH(A85) -> 4 | C85: =YEAR(A85) -> 2024 | D85: =C85*100+B85 -> 202404 | E85: =IF(B85<4,1,IF(B85<7,2,IF(B85<10,3,4))) -> 2 | F85: =C85*100+E85 -> 202402 | G85: 20240416 | H85: 5.25 | I85: 5.1984 | J85: 5.1825747 | K85: 5.1409117 | L85: 5.0900899 | M85: 5.034852 | N85: 4.9785409 | O85: 4.9223758 | P85: 4.8672673 | Q85: 4.8146038 | R85: 4.7658647 | S85: 4.7216218 | T85: 4.6813829 | U85: 4.6441791 | V85: 4.6078024 | W85: 4.5714875 | X85: 4.5349473 | Y85: 4.4978936 | Z85: 4.4600379 | AA85: 4.4210934 | AB85: 4.3808913 | AC85: 4.3397655 | AD85: 4.2981834 | AE85: 4.2566108 | AF85: 4.2155137 | AG85: 4.1753595 | AH85: 4.1365375 | AI85: 4.0991307 | AJ85: 4.0631469 | AK85: 4.0285926 | AL85: 3.9954743 | AM85: 3.9637998 | AN85: 3.9335754 | AO85: 3.9048077 | AP85: 3.8775045 | AQ85: 3.8516721 | AR85: 3.8273173 | AS85: 3.8044475 | AT85: 3.78306 | AU85: 3.7631148 | AV85: 3.7445632 | AW85: 3.7273558 | AX85: 3.7114432 | AY85: 3.6967768 | AZ85: 3.6833072 | BA85: 3.6709851 | BB85: 3.6597616 | BC85: 3.6495875 | BD85: 3.6404135 | BE85: 3.6321907 | BF85: 3.6248722 | BG85: 3.6184239 | BH85: 3.6128164 | BI85: 3.6080198 | BJ85: 3.6040043 | BK85: 3.6007404 | BL85: 3.5981984 | BM85: 3.5963484 | BN85: 3.5951608 | BO85: 3.594606 | BP85: 3.5946542 | BQ85: 3.5952757 | BR85: 3.6095937 | BS85: 3.6383558
A86: =A81+7 -> 45399 | B86: =MONTH(A86) -> 4 | C86: =YEAR(A86) -> 2024 | D86: =C86*100+B86 -> 202404 | E86: =IF(B86<4,1,IF(B86<7,2,IF(B86<10,3,4))) -> 2 | F86: =C86*100+E86 -> 202402 | G86: 20240417 | H86: 5.25 | I86: 5.1984 | J86: 5.1864649 | K86: 5.1406635 | L86: 5.082378 | M86: 5.0182776 | N86: 4.9533389 | O86: 4.8893764 | P86: 4.8279117 | Q86: 4.7707196 | R86: 4.7193814 | S86: 4.674208 | T86: 4.634165 | U86: 4.5975445 | V86: 4.5610471 | W86: 4.5238099 | X86: 4.4857238 | Y86: 4.4466787 | Z86: 4.4065642 | AA86: 4.3652716 | AB86: 4.3227819 | AC86: 4.2794604 | AD86: 4.235775 | AE86: 4.1921919 | AF86: 4.1491773 | AG86: 4.1071989 | AH86: 4.0666479 | AI86: 4.0276152 | AJ86: 3.9901181 | AK86: 3.9541724 | AL86: 3.9197939 | AM86: 3.8869999 | AN86: 3.8558062 | AO86: 3.8262287 | AP86: 3.7982845 | AQ86: 3.7719895 | AR86: 3.7473598 | AS86: 3.7244121 | AT86: 3.7031517 | AU86: 3.6835306 | AV86: 3.6654853 | AW86: 3.6489518 | AX86: 3.6338659 | AY86: 3.6201642 | AZ86: 3.6077825 | BA86: 3.596657 | BB86: 3.5867238 | BC86: 3.5779191 | BD86: 3.5701788 | BE86: 3.5634393 | BF86: 3.5576398 | BG86: 3.5527354 | BH86: 3.5486865 | BI86: 3.5454529 | BJ86: 3.5429948 | BK86: 3.5412723 | BL86: 3.5402453 | BM86: 3.539874 | BN86: 3.5401185 | BO86: 3.5409387 | BP86: 3.5422949 | BQ86: 3.544147 | BR86: 3.5641156 | BS86: 3.5959834
... A98: =A93+7 -> 45415 | B98: =MONTH(A98) -> 5 | C98: =YEAR(A98) -> 2024 | D98: =C98*100+B98 -> 202405 | E98: =IF(B98<4,1,IF(B98<7,2,IF(B98<10,3,4))) -> 2 | F98: =C98*100+E98 -> 202402 | G98: 20240503 | H98: 5.25 | I98: 5.2001 | J98: 5.1712702 | K98: 5.1003635 | L98: 5.0239676 | M98: 4.9492633 | N98: 4.8792355 | O98: 4.8124831 | P98: 4.7483961 | Q98: 4.6876538 | R98: 4.6308991 | S98: 4.578289 | T98: 4.5293833 | U98: 4.4832177 | V98: 4.4378251 | W98: 4.392694 | X98: 4.3479186 | Y98: 4.3035917 | Z98: 4.2598065 | AA98: 4.2166574 | AB98: 4.1742532 | AC98: 4.1327758 | AD98: 4.0924297 | AE98: 4.0534181 | AF98: 4.015944 | AG98: 3.9802119 | AH98: 3.9463882 | AI98: 3.9144595 | AJ98: 3.8843591 | AK98: 3.856019 | AL98: 3.8293713 | AM98: 3.804349 | AN98: 3.7808843 | AO98: 3.7589094 | AP98: 3.7383572 | AQ98: 3.7191599 | AR98: 3.7012497 | AS98: 3.6845594 | AT98: 3.669025 | AU98: 3.6545989 | AV98: 3.6412384 | AW98: 3.6289004 | AX98: 3.6175419 | AY98: 3.6071201 | AZ98: 3.597592 | BA98: 3.5889146 | BB98: 3.5810451 | BC98: 3.5739404 | BD98: 3.5675576 | BE98: 3.5618538 | BF98: 3.5567901 | BG98: 3.5523454 | BH98: 3.5485037 | BI98: 3.5452489 | BJ98: 3.5425648 | BK98: 3.5404353 | BL98: 3.5388445 | BM98: 3.5377761 | BN98: 3.5372141 | BO98: 3.5371425 | BP98: 3.537545 | BQ98: 3.5384056 | BR98: 3.5524607 | BS98: 3.5799985
A99: =A94+7 -> 45418 | B99: =MONTH(A99) -> 5 | C99: =YEAR(A99) -> 2024 | D99: =C99*100+B99 -> 202405 | E99: =IF(B99<4,1,IF(B99<7,2,IF(B99<10,3,4))) -> 2 | F99: =C99*100+E99 -> 202402 | G99: 20240506 | H99: 5.25 | I99: #N/A | J99: #N/A | K99: #N/A | L99: #N/A | M99: #N/A | N99: #N/A | O99: #N/A | P99: #N/A | Q99: #N/A | R99: #N/A | S99: #N/A | T99: #N/A | U99: #N/A | V99: #N/A | W99: #N/A | X99: #N/A | Y99: #N/A | Z99: #N/A | AA99: #N/A | AB99: #N/A | AC99: #N/A | AD99: #N/A | AE99: #N/A | AF99: #N/A | AG99: #N/A | AH99: #N/A | AI99: #N/A | AJ99: #N/A | AK99: #N/A | AL99: #N/A | AM99: #N/A | AN99: #N/A | AO99: #N/A | AP99: #N/A | AQ99: #N/A | AR99: #N/A | AS99: #N/A | AT99: #N/A | AU99: #N/A | AV99: #N/A | AW99: #N/A | AX99: #N/A | AY99: #N/A | AZ99: #N/A | BA99: #N/A | BB99: #N/A | BC99: #N/A | BD99: #N/A | BE99: #N/A | BF99: #N/A | BG99: #N/A | BH99: #N/A | BI99: #N/A | BJ99: #N/A | BK99: #N/A | BL99: #N/A | BM99: #N/A | BN99: #N/A | BO99: #N/A | BP99: #N/A | BQ99: #N/A | BR99: #N/A | BS99: #N/A
A100: =A95+7 -> 45419 | B100: =MONTH(A100) -> 5 | C100: =YEAR(A100) -> 2024 | D100: =C100*100+B100 -> 202405 | E100: =IF(B100<4,1,IF(B100<7,2,IF(B100<10,3,4))) -> 2 | F100: =C100*100+E100 -> 202402 | G100: 20240507 | H100: 5.25 | I100: 5.2 | J100: 5.1658608 | K100: 5.0926656 | L100: 5.0167812 | M100: 4.9418598 | N100: 4.868704 | O100: 4.7956925 | P100: 4.7232078 | Q100: 4.6533796 | R100: 4.5881558 | S100: 4.5286464 | T100: 4.4751233 | U100: 4.4268952 | V100: 4.3825152 | W100: 4.3410095 | X100: 4.3015751 | Y100: 4.2634071 | Z100: 4.2257011 | AA100: 4.1876536 | AB100: 4.1486331 | AC100: 4.1088111 | AD100: 4.068593 | AE100: 4.0283828 | AF100: 3.9885846 | AG100: 3.9496039 | AH100: 3.9117837 | AI100: 3.8752231 | AJ100: 3.8399614 | AK100: 3.8060366 | AL100: 3.773487 | AM100: 3.7423516 | AN100: 3.7126687 | AO100: 3.6844763 | AP100: 3.6578136 | AQ100: 3.6327188 | AR100: 3.60923 | AS100: 3.5873863 | AT100: 3.5672085 | AU100: 3.5486485 | AV100: 3.5316413 | AW100: 3.5161215 | AX100: 3.5020234 | AY100: 3.4892821 | AZ100: 3.4778321 | BA100: 3.4676079 | BB100: 3.4585445 | BC100: 3.4505764 | BD100: 3.4436383 | BE100: 3.4376648 | BF100: 3.432595 | BG100: 3.4283889 | BH100: 3.4250133 | BI100: 3.4224346 | BJ100: 3.4206194 | BK100: 3.4195344 | BL100: 3.4191461 | BM100: 3.419421 | BN100: 3.4203258 | BO100: 3.421827 | BP100: 3.4238912 | BQ100: 3.426485 | BR100: 3.4516748 | BS100: 3.489822
A101: =A96+7 -> 45420 | B101: =MONTH(A101) -> 5 | C101: =YEAR(A101) -> 2024 | D101: =C101*100+B101 -> 202405 | E101: =IF(B101<4,1,IF(B101<7,2,IF(B101<10,3,4))) -> 2 | F101: =C101*100+E101 -> 202402 | G101: 20240508 | H101: 5.25 | I101: 5.2 | J101: 5.1566669 | K101: 5.0761636 | L101: 4.997842 | M101: 4.9231594 | N101: 4.8509448 | O101: 4.7793498 | P101: 4.7094935 | Q101: 4.6441852 | R101: 4.5851155 | S101: 4.5327786 | T101: 4.4861275 | U101: 4.4436754 | V101: 4.4026643 | W101: 4.3621283 | X101: 4.3216844 | Y101: 4.280948 | Z101: 4.2395345 | AA101: 4.1970609 | AB101: 4.1532546 | AC101: 4.1084779 | AD101: 4.063318 | AE101: 4.0183606 | AF101: 3.9741917 | AG101: 3.9313985 | AH101: 3.8904668 | AI101: 3.851482 | AJ101: 3.8144311 | AK101: 3.7792993 | AL101: 3.7460722 | AM101: 3.7147364 | AN101: 3.6852775 | AO101: 3.6576808 | AP101: 3.631933 | AQ101: 3.6080197 | AR101: 3.5859263 | AS101: 3.5656394 | AT101: 3.5471347 | AU101: 3.5303398 | AV101: 3.5151687 | AW101: 3.5015344 | AX101: 3.4893501 | AY101: 3.4785295 | AZ101: 3.4689857 | BA101: 3.460632 | BB101: 3.4533819 | BC101: 3.4471488 | BD101: 3.4418457 | BE101: 3.4373864 | BF101: 3.4336924 | BG101: 3.4307235 | BH101: 3.4284496 | BI101: 3.4268407 | BJ101: 3.4258667 | BK101: 3.4254977 | BL101: 3.4257035 | BM101: 3.4264543 | BN101: 3.42772 | BO101: 3.4294705 | BP101: 3.4316758 | BQ101: 3.4343059 | BR101: 3.4578475 | BS101: 3.492279
A102: =A97+7 -> 45421 | B102: =MONTH(A102) -> 5 | C102: =YEAR(A102) -> 2024 | D102: =C102*100+B102 -> 202405 | E102: =IF(B102<4,1,IF(B102<7,2,IF(B102<10,3,4))) -> 2 | F102: =C102*100+E102 -> 202402 | G102: 20240509 | H102: 5.25 | I102: 5.2 | J102: 5.1626161 | K102: 5.0646919 | L102: 4.9759418 | M102: 4.8958561 | N102: 4.8203431 | O102: 4.7453182 | P102: 4.6697515 | Q102: 4.5951484 | R102: 4.5236859 | S102: 4.4571984 | T102: 4.396587 | U102: 4.3419605 | V102: 4.2924698 | W102: 4.2470985 | X102: 4.2048483 | Y102: 4.1647193 | Z102: 4.1257118 | AA102: 4.0868272 | AB102: 4.0472549 | AC102: 4.0071517 | AD102: 3.9669854 | AE102: 3.9272224 | AF102: 3.888329 | AG102: 3.850773 | AH102: 3.8149553 | AI102: 3.7809581 | AJ102: 3.7487675 | AK102: 3.7183684 | AL102: 3.689746 | AM102: 3.6628863 | AN102: 3.6377742 | AO102: 3.614395 | AP102: 3.5927346 | AQ102: 3.572778 | AR102: 3.5545104 | AS102: 3.5379177 | AT102: 3.522974 | AU102: 3.5096053 | AV102: 3.497725 | AW102: 3.4872455 | AX102: 3.4780798 | AY102: 3.4701408 | AZ102: 3.4633413 | BA102: 3.4575941 | BB102: 3.4528121 | BC102: 3.4489083 | BD102: 3.4457953 | BE102: 3.4433861 | BF102: 3.4416034 | BG102: 3.4404131 | BH102: 3.4397932 | BI102: 3.4397215 | BJ102: 3.4401759 | BK102: 3.4411345 | BL102: 3.4425751 | BM102: 3.4444757 | BN102: 3.4468141 | BO102: 3.4495683 | BP102: 3.4527163 | BQ102: 3.4562358 | BR102: 3.4842411 | BS102: 3.5220022
A103: =A98+7 -> 45422 | B103: =MONTH(A103) -> 5 | C103: =YEAR(A103) -> 2024 | D103: =C103*100+B103 -> 202405 | E103: =IF(B103<4,1,IF(B103<7,2,IF(B103<10,3,4))) -> 2 | F103: =C103*100+E103 -> 202402 | G103: 20240510 | H103: 5.25 | I103: 5.2 | J103: 5.1592683 | K103: 5.0635548 | L103: 4.979909 | M103: 4.9063664 | N103: 4.8371351 | O103: 4.7684671 | P103: 4.7001132 | Q103: 4.6339371 | R103: 4.5717753 | S103: 4.5145216 | T103: 4.4621251 | U103: 4.4136821 | V103: 4.3673676 | W103: 4.3224751 | X103: 4.278729 | Y103: 4.2358525 | Z103: 4.1935683 | AA103: 4.151601 | AB103: 4.1097573 | AC103: 4.0682314 | AD103: 4.0273316 | AE103: 3.9873646 | AF103: 3.9486372 | AG103: 3.9114576 | AH103: 3.8760802 | AI103: 3.8425284 | AJ103: 3.8107628 | AK103: 3.780743 | AL103: 3.7524285 | AM103: 3.7257801 | AN103: 3.7007573 | AO103: 3.6773198 | AP103: 3.6554281 | AQ103: 3.6350417 | AR103: 3.6161206 | AS103: 3.5986249 | AT103: 3.5825116 | AU103: 3.5677257 | AV103: 3.55421 | AW103: 3.5419067 | AX103: 3.530758 | AY103: 3.5207067 | AZ103: 3.5116948 | BA103: 3.5036649 | BB103: 3.4965593 | BC103: 3.4903205 | BD103: 3.4848906 | BE103: 3.4802124 | BF103: 3.4762334 | BG103: 3.472926 | BH103: 3.470269 | BI103: 3.4682413 | BJ103: 3.4668218 | BK103: 3.4659893 | BL103: 3.4657227 | BM103: 3.4660009 | BN103: 3.4668028 | BO103: 3.4681073 | BP103: 3.4698931 | BQ103: 3.4721393 | BR103: 3.4943368 | BS103: 3.5292218
A104: =A99+7 -> 45425 | B104: =MONTH(A104) -> 5 | C104: =YEAR(A104) -> 2024 | D104: =C104*100+B104 -> 202405 | E104: =IF(B104<4,1,IF(B104<7,2,IF(B104<10,3,4))) -> 2 | F104: =C104*100+E104 -> 202402 | G104: 20240513 | H104: 5.25 | I104: 5.2 | J104: 5.1597455 | K104: 5.063519 | L104: 4.9821352 | M104: 4.9109913 | N104: 4.8429709 | O104: 4.7749746 | P104: 4.70779 | Q104: 4.6442508 | R104: 4.5867096 | S104: 4.5358374 | T104: 4.4909189 | U104: 4.4502711 | V104: 4.4110852 | W104: 4.372419 | X104: 4.3339156 | Y104: 4.2952165 | Z104: 4.2559635 | AA104: 4.2157994 | AB104: 4.1744892 | AC104: 4.1323685 | AD104: 4.0899399 | AE104: 4.0477047 | AF104: 4.006164 | AG104: 3.9658206 | AH104: 3.92709 | AI104: 3.8900458 | AJ104: 3.854677 | AK104: 3.8209717 | AL104: 3.7889177 | AM104: 3.7585041 | AN104: 3.7297189 | AO104: 3.70255 | AP104: 3.6769865 | AQ104: 3.6530163 | AR104: 3.6306275 | AS104: 3.609809 | AT104: 3.5905412 | AU104: 3.5727746 | AV104: 3.5564526 | AW104: 3.5415182 | AX104: 3.5279141 | AY104: 3.5155838 | AZ104: 3.5044702 | BA104: 3.4945162 | BB104: 3.4856652 | BC104: 3.47786 | BD104: 3.4710438 | BE104: 3.4651596 | BF104: 3.4601538 | BG104: 3.4559911 | BH104: 3.4526422 | BI104: 3.4500778 | BJ104: 3.4482686 | BK104: 3.4471855 | BL104: 3.446799 | BM104: 3.4470799 | BN104: 3.4479989 | BO104: 3.4495267 | BP104: 3.4516342 | BQ104: 3.4542919 | BR104: 3.4803464 | BS104: 3.5200075
A105: =A100+7 -> 45426 | B105: =MONTH(A105) -> 5 | C105: =YEAR(A105) -> 2024 | D105: =C105*100+B105 -> 202405 | E105: =IF(B105<4,1,IF(B105<7,2,IF(B105<10,3,4))) -> 2 | F105: =C105*100+E105 -> 202402 | G105: 20240514 | H105: 5.25 | I105: 5.2 | J105: 5.1570657 | K105: 5.0577854 | L105: 4.9745817 | M105: 4.9018868 | N105: 4.8328847 | O105: 4.7645375 | P105: 4.6973956 | Q105: 4.633822 | R105: 4.5758667 | S105: 4.5241403 | T105: 4.4780785 | U105: 4.4361707 | V105: 4.3956175 | W105: 4.3555107 | X105: 4.315535 | Y105: 4.2753733 | Z105: 4.2347087 | AA105: 4.1932258 | AB105: 4.1507255 | AC105: 4.107555 | AD105: 4.0642215 | AE105: 4.0212307 | AF105: 3.9790883 | AG105: 3.9383014 | AH105: 3.8992883 | AI105: 3.8621181 | AJ105: 3.8267738 | AK105: 3.793237 | AL105: 3.7614896 | AM105: 3.7315144 | AN105: 3.7032931 | AO105: 3.6768076 | AP105: 3.6520406 | AQ105: 3.628974 | AR105: 3.6075896 | AS105: 3.58787 | AT105: 3.5697882 | AU105: 3.5532813 | AV105: 3.5382779 | AW105: 3.5247062 | AX105: 3.5124944 | AY105: 3.501571 | AZ105: 3.4918643 | BA105: 3.4833025 | BB105: 3.4758141 | BC105: 3.4693273 | BD105: 3.4637703 | BE105: 3.4590717 | BF105: 3.4551654 | BG105: 3.4520137 | BH105: 3.4495874 | BI105: 3.4478572 | BJ105: 3.446794 | BK105: 3.4463685 | BL105: 3.4465515 | BM105: 3.4473139 | BN105: 3.4486263 | BO105: 3.4504596 | BP105: 3.4527846 | BQ105: 3.4555721 | BR105: 3.4807717 | BS105: 3.5176793
A106: =A101+7 -> 45427 | B106: =MONTH(A106) -> 5 | C106: =YEAR(A106) -> 2024 | D106: =C106*100+B106 -> 202405 | E106: =IF(B106<4,1,IF(B106<7,2,IF(B106<10,3,4))) -> 2 | F106: =C106*100+E106 -> 202402 | G106: 20240515 | H106: 5.25 | I106: 5.2 | J106: 5.1536761 | K106: 5.0425642 | L106: 4.9530835 | M106: 4.8765879 | N106: 4.8037872 | O106: 4.7307557 | P106: 4.6574133 | Q106: 4.5859727 | R106: 4.5187779 | S106: 4.4572718 | T106: 4.4013475 | U106: 4.3502609 | V106: 4.3016155 | W106: 4.2544778 | X106: 4.2084324 | Y106: 4.1630623 | Z106: 4.1179505 | AA106: 4.0726816 | AB106: 4.0269436 | AC106: 3.9810199 | AD106: 3.9354043 | AE106: 3.8905896 | AF106: 3.8470685 | AG106: 3.8053352 | AH106: 3.765792 | AI106: 3.7284797 | AJ106: 3.69335 | AK106: 3.6603531 | AL106: 3.6294394 | AM106: 3.6005607 | AN106: 3.5736671 | AO106: 3.5487093 | AP106: 3.5256386 | AQ106: 3.5044055 | AR106: 3.4849605 | AS106: 3.467255 | AT106: 3.4512341 | AU106: 3.4368176 | AV106: 3.4239176 | AW106: 3.4124459 | AX106: 3.4023144 | AY106: 3.3934352 | AZ106: 3.3857201 | BA106: 3.3790811 | BB106: 3.3734302 | BC106: 3.3686792 | BD106: 3.3647402 | BE106: 3.361525 | BF106: 3.3589552 | BG106: 3.356995 | BH106: 3.3556204 | BI106: 3.3548072 | BJ106: 3.3545314 | BK106: 3.3547688 | BL106: 3.3554954 | BM106: 3.3566871 | BN106: 3.3583198 | BO106: 3.3603695 | BP106: 3.362812 | BQ106: 3.3656233 | BR106: 3.389331 | BS106: 3.4229422
A107: =A102+7 -> 45428 | B107: =MONTH(A107) -> 5 | C107: =YEAR(A107) -> 2024 | D107: =C107*100+B107 -> 202405 | E107: =IF(B107<4,1,IF(B107<7,2,IF(B107<10,3,4))) -> 2 | F107: =C107*100+E107 -> 202402 | G107: 20240516 | H107: 5.25 | I107: 5.2 | J107: 5.1477799 | K107: 5.036401 | L107: 4.9501748 | M107: 4.8789412 | N107: 4.811774 | O107: 4.7436211 | P107: 4.673774 | Q107: 4.6038292 | R107: 4.5358026 | S107: 4.4711083 | T107: 4.4103961 | U107: 4.3538116 | V107: 4.3012296 | W107: 4.2520515 | X107: 4.2055673 | Y107: 4.1610654 | Z107: 4.1178342 | AA107: 4.0751638 | AB107: 4.0324795 | AC107: 3.9899091 | AD107: 3.9478061 | AE107: 3.9065225 | AF107: 3.8664105 | AG107: 3.8278236 | AH107: 3.7910624 | AI107: 3.7561766 | AJ107: 3.7231409 | AK107: 3.6919285 | AL107: 3.6625128 | AM107: 3.6348683 | AN107: 3.6089683 | AO107: 3.5847863 | AP107: 3.5622965 | AQ107: 3.5414725 | AR107: 3.5222877 | AS107: 3.5047163 | AT107: 3.4887239 | AU107: 3.4742411 | AV107: 3.4611891 | AW107: 3.4494889 | AX107: 3.4390614 | AY107: 3.4298279 | AZ107: 3.4217093 | BA107: 3.4146265 | BB107: 3.4085007 | BC107: 3.403253 | BD107: 3.3988043 | BE107: 3.3950757 | BF107: 3.3919969 | BG107: 3.3895366 | BH107: 3.387674 | BI107: 3.3863882 | BJ107: 3.3856584 | BK107: 3.3854639 | BL107: 3.3857839 | BM107: 3.3865977 | BN107: 3.3878843 | BO107: 3.389623 | BP107: 3.3917931 | BQ107: 3.3943738 | BR107: 3.417582 | BS107: 3.4519508
A108: =A103+7 -> 45429 | B108: =MONTH(A108) -> 5 | C108: =YEAR(A108) -> 2024 | D108: =C108*100+B108 -> 202405 | E108: =IF(B108<4,1,IF(B108<7,2,IF(B108<10,3,4))) -> 2 | F108: =C108*100+E108 -> 202402 | G108: 20240517 | H108: 5.25 | I108: 5.2 | J108: 5.1480381 | K108: 5.0431696 | L108: 4.9609866 | M108: 4.8918344 | N108: 4.8259089 | O108: 4.7593501 | P108: 4.6921448 | Q108: 4.62633 | R108: 4.563981 | S108: 4.5060875 | T108: 4.4526572 | U108: 4.4029029 | V108: 4.3549837 | W108: 4.3082671 | X108: 4.2625933 | Y108: 4.2178012 | Z108: 4.1737297 | AA108: 4.130219 | AB108: 4.0871701 | AC108: 4.0447718 | AD108: 4.003298 | AE108: 3.9630207 | AF108: 3.9242125 | AG108: 3.887147 | AH108: 3.8520461 | AI108: 3.8189101 | AJ108: 3.7876787 | AK108: 3.7582909 | AL108: 3.7306855 | AM108: 3.7048023 | AN108: 3.6805802 | AO108: 3.6579582 | AP108: 3.6368759 | AQ108: 3.6172722 | AR108: 3.5990862 | AS108: 3.5822574 | AT108: 3.5667258 | AU108: 3.5524355 | AV108: 3.5393318 | AW108: 3.5273598 | AX108: 3.5164645 | AY108: 3.5065913 | AZ108: 3.4976852 | BA108: 3.4896912 | BB108: 3.4825548 | BC108: 3.4762209 | BD108: 3.4706347 | BE108: 3.4657414 | BF108: 3.4614917 | BG108: 3.4578614 | BH108: 3.4548332 | BI108: 3.4523898 | BJ108: 3.4505137 | BK108: 3.4491877 | BL108: 3.4483945 | BM108: 3.4481165 | BN108: 3.4483366 | BO108: 3.4490374 | BP108: 3.4502015 | BQ108: 3.4518116 | BR108: 3.4700334 | BS108: 3.5009502
A109: =A104+7 -> 45432 | B109: =MONTH(A109) -> 5 | C109: =YEAR(A109) -> 2024 | D109: =C109*100+B109 -> 202405 | E109: =IF(B109<4,1,IF(B109<7,2,IF(B109<10,3,4))) -> 2 | F109: =C109*100+E109 -> 202402 | G109: 20240520 | H109: 5.25 | I109: 5.2 | J109: 5.1458317 | K109: 5.0407189 | L109: 4.9615556 | M109: 4.8962773 | N109: 4.8333933 | O109: 4.7694833 | P109: 4.7053932 | Q109: 4.6437869 | R109: 4.58688 | S109: 4.5354488 | T109: 4.4891519 | U109: 4.4466964 | V109: 4.4056142 | W109: 4.3650799 | X109: 4.3248078 | Y109: 4.2845108 | Z109: 4.2439017 | AA109: 4.2026948 | AB109: 4.1607125 | AC109: 4.1182859 | AD109: 4.0758948 | AE109: 4.0340175 | AF109: 3.9931324 | AG109: 3.9537193 | AH109: 3.9161698 | AI109: 3.8805293 | AJ109: 3.8467573 | AK109: 3.8148124 | AL109: 3.7846532 | AM109: 3.7562393 | AN109: 3.7295293 | AO109: 3.7044817 | AP109: 3.681056 | AQ109: 3.659211 | AR109: 3.6389052 | AS109: 3.6200981 | AT109: 3.6027457 | AU109: 3.5867932 | AV109: 3.5721838 | AW109: 3.5588601 | AX109: 3.5467648 | AY109: 3.5358409 | AZ109: 3.5260312 | BA109: 3.5172782 | BB109: 3.509525 | BC109: 3.5027143 | BD109: 3.4967887 | BE109: 3.4916913 | BF109: 3.487369 | BG109: 3.4837912 | BH109: 3.4809352 | BI109: 3.4787781 | BJ109: 3.4772971 | BK109: 3.4764692 | BL109: 3.4762718 | BM109: 3.4766818 | BN109: 3.4776764 | BO109: 3.4792329 | BP109: 3.4813283 | BQ109: 3.4839397 | BR109: 3.5091961 | BS109: 3.5474531
A110: =A105+7 -> 45433 | B110: =MONTH(A110) -> 5 | C110: =YEAR(A110) -> 2024 | D110: =C110*100+B110 -> 202405 | E110: =IF(B110<4,1,IF(B110<7,2,IF(B110<10,3,4))) -> 2 | F110: =C110*100+E110 -> 202402 | G110: 20240521 | H110: 5.25 | I110: 5.2 | J110: 5.1435703 | K110: 5.0432979 | L110: 4.9648542 | M110: 4.8972071 | N110: 4.830589 | O110: 4.7622113 | P110: 4.6931747 | Q110: 4.6262303 | R110: 4.5639472 | S110: 4.5075423 | T110: 4.4570337 | U110: 4.4113217 | V110: 4.3676578 | W110: 4.3250259 | X110: 4.2829982 | Y110: 4.2411453 | Z110: 4.1990379 | AA110: 4.156248 | AB110: 4.1124902 | AC110: 4.0681461 | AD110: 4.0237921 | AE110: 3.9800031 | AF110: 3.9373541 | AG110: 3.8964215 | AH110: 3.8576737 | AI110: 3.8211525 | AJ110: 3.7867943 | AK110: 3.7545346 | AL110: 3.7243084 | AM110: 3.6960524 | AN110: 3.6697016 | AO110: 3.6451915 | AP110: 3.6224584 | AQ110: 3.6014376 | AR110: 3.5820646 | AS110: 3.5642754 | AT110: 3.5480043 | AU110: 3.5331808 | AV110: 3.5197336 | AW110: 3.5075909 | AX110: 3.4966811 | AY110: 3.4869329 | AZ110: 3.4782744 | BA110: 3.4706342 | BB110: 3.4639407 | BC110: 3.4581222 | BD110: 3.4531073 | BE110: 3.4488243 | BF110: 3.445209 | BG110: 3.4422325 | BH110: 3.439877 | BI110: 3.4381244 | BJ110: 3.4369569 | BK110: 3.4363564 | BL110: 3.4363051 | BM110: 3.4367849 | BN110: 3.4377779 | BO110: 3.4392662 | BP110: 3.4412319 | BQ110: 3.4436568 | BR110: 3.4668715 | BS110: 3.5022427
A111: =A106+7 -> 45434 | B111: =MONTH(A111) -> 5 | C111: =YEAR(A111) -> 2024 | D111: =C111*100+B111 -> 202405 | E111: =IF(B111<4,1,IF(B111<7,2,IF(B111<10,3,4))) -> 2 | F111: =C111*100+E111 -> 202402 | G111: 20240522 | H111: 5.25 | I111: 5.2 | J111: 5.1884426 | K111: 5.1484831 | L111: 5.0960044 | M111: 5.0258805 | N111: 4.940567 | O111: 4.8514404 | P111: 4.7719343 | Q111: 4.7101938 | R111: 4.6608673 | S111: 4.6198459 | T111: 4.590465 | U111: 4.5755412 | V111: 4.5617168 | W111: 4.5445679 | X111: 4.5232344 | Y111: 4.4968556 | Z111: 4.4645703 | AA111: 4.4255188 | AB111: 4.3791576 | AC111: 4.3267421 | AD111: 4.2701621 | AE111: 4.2113063 | AF111: 4.1520633 | AG111: 4.0943236 | AH111: 4.0396473 | AI111: 3.9882797 | AJ111: 3.9401392 | AK111: 3.8951427 | AL111: 3.8532067 | AM111: 3.8142498 | AN111: 3.7781885 | AO111: 3.7449398 | AP111: 3.7144219 | AQ111: 3.6865515 | AR111: 3.6612457 | AS111: 3.6384224 | AT111: 3.6179905 | AU111: 3.5998204 | AV111: 3.5837712 | AW111: 3.5697013 | AX111: 3.5574693 | AY111: 3.5469342 | AZ111: 3.5379545 | BA111: 3.5303887 | BB111: 3.5240958 | BC111: 3.5189344 | BD111: 3.514763 | BE111: 3.5114404 | BF111: 3.5088419 | BG111: 3.5069151 | BH111: 3.5056282 | BI111: 3.504949 | BJ111: 3.5048456 | BK111: 3.5052858 | BL111: 3.5062377 | BM111: 3.5076692 | BN111: 3.5095482 | BO111: 3.5118427 | BP111: 3.5145207 | BQ111: 3.51755 | BR111: 3.5420274 | BS111: 3.5754235
... A113: =A108+7 -> 45436 | B113: =MONTH(A113) -> 5 | C113: =YEAR(A113) -> 2024 | D113: =C113*100+B113 -> 202405 | E113: =IF(B113<4,1,IF(B113<7,2,IF(B113<10,3,4))) -> 2 | F113: =C113*100+E113 -> 202402 | G113: 20240524 | H113: 5.25 | I113: 5.2 | J113: 5.1918997 | K113: 5.1544352 | L113: 5.110974 | M113: 5.0623055 | N113: 5.0089365 | O113: 4.9529316 | P113: 4.8968827 | Q113: 4.8430324 | R113: 4.7925632 | S113: 4.7454649 | T113: 4.7008909 | U113: 4.6575197 | V113: 4.6130578 | W113: 4.5670033 | X113: 4.5195777 | Y113: 4.4710013 | Z113: 4.4214946 | AA113: 4.3712795 | AB113: 4.3206152 | AC113: 4.2699407 | AD113: 4.2197491 | AE113: 4.1705314 | AF113: 4.1227788 | AG113: 4.0769844 | AH113: 4.0335622 | AI113: 3.992551 | AJ113: 3.9538769 | AK113: 3.9174641 | AL113: 3.8832375 | AM113: 3.8511226 | AN113: 3.8210442 | AO113: 3.7929269 | AP113: 3.7666962 | AQ113: 3.7422769 | AR113: 3.7195936 | AS113: 3.6985719 | AT113: 3.6791373 | AU113: 3.6612188 | AV113: 3.6447472 | AW113: 3.6296521 | AX113: 3.6158637 | AY113: 3.6033123 | AZ113: 3.5919279 | BA113: 3.5816406 | BB113: 3.5723807 | BC113: 3.5640781 | BD113: 3.556663 | BE113: 3.5500656 | BF113: 3.544223 | BG113: 3.539104 | BH113: 3.5346858 | BI113: 3.5309457 | BJ113: 3.5278611 | BK113: 3.5254092 | BL113: 3.5235673 | BM113: 3.5223128 | BN113: 3.521623 | BO113: 3.5214751 | BP113: 3.5218465 | BQ113: 3.5227144 | BR113: 3.5373486 | BS113: 3.5657763
A114: =A109+7 -> 45439 | B114: =MONTH(A114) -> 5 | C114: =YEAR(A114) -> 2024 | D114: =C114*100+B114 -> 202405 | E114: =IF(B114<4,1,IF(B114<7,2,IF(B114<10,3,4))) -> 2 | F114: =C114*100+E114 -> 202402 | G114: 20240527 | H114: 5.25 | I114: #N/A | J114: #N/A | K114: #N/A | L114: #N/A | M114: #N/A | N114: #N/A | O114: #N/A | P114: #N/A | Q114: #N/A | R114: #N/A | S114: #N/A | T114: #N/A | U114: #N/A | V114: #N/A | W114: #N/A | X114: #N/A | Y114: #N/A | Z114: #N/A | AA114: #N/A | AB114: #N/A | AC114: #N/A | AD114: #N/A | AE114: #N/A | AF114: #N/A | AG114: #N/A | AH114: #N/A | AI114: #N/A | AJ114: #N/A | AK114: #N/A | AL114: #N/A | AM114: #N/A | AN114: #N/A | AO114: #N/A | AP114: #N/A | AQ114: #N/A | AR114: #N/A | AS114: #N/A | AT114: #N/A | AU114: #N/A | AV114: #N/A | AW114: #N/A | AX114: #N/A | AY114: #N/A | AZ114: #N/A | BA114: #N/A | BB114: #N/A | BC114: #N/A | BD114: #N/A | BE114: #N/A | BF114: #N/A | BG114: #N/A | BH114: #N/A | BI114: #N/A | BJ114: #N/A | BK114: #N/A | BL114: #N/A | BM114: #N/A | BN114: #N/A | BO114: #N/A | BP114: #N/A | BQ114: #N/A | BR114: #N/A | BS114: #N/A
A115: =A110+7 -> 45440 | B115: =MONTH(A115) -> 5 | C115: =YEAR(A115) -> 2024 | D115: =C115*100+B115 -> 202405 | E115: =IF(B115<4,1,IF(B115<7,2,IF(B115<10,3,4))) -> 2 | F115: =C115*100+E115 -> 202402 | G115: 20240528 | H115: 5.25 | I115: 5.2 | J115: 5.1907866 | K115: 5.1537904 | L115: 5.1111076 | M115: 5.0630185 | N115: 5.0089531 | O115: 4.9513151 | P115: 4.8936897 | Q115: 4.8390533 | R115: 4.7892072 | S115: 4.7444465 | T115: 4.703955 | U115: 4.6661869 | V115: 4.6285819 | W115: 4.590306 | X115: 4.5510569 | Y115: 4.510531 | Z115: 4.4684244 | AA115: 4.4244351 | AB115: 4.3783986 | AC115: 4.3307957 | AD115: 4.2822962 | AE115: 4.2335681 | AF115: 4.1852795 | AG115: 4.1380999 | AH115: 4.0925884 | AI115: 4.0488672 | AJ115: 4.0069508 | AK115: 3.9668524 | AL115: 3.9285851 | AM115: 3.8921634 | AN115: 3.8576005 | AO115: 3.8249095 | AP115: 3.7941048 | AQ115: 3.7651997 | AR115: 3.7382074 | AS115: 3.7131421 | AT115: 3.6900014 | AU115: 3.6687199 | AV115: 3.6492174 | AW115: 3.6314127 | AX115: 3.6152249 | AY115: 3.6005735 | AZ115: 3.5873774 | BA115: 3.5755558 | BB115: 3.5650281 | BC115: 3.5557132 | BD115: 3.5475304 | BE115: 3.5403989 | BF115: 3.5342434 | BG115: 3.5290174 | BH115: 3.5246847 | BI115: 3.5212087 | BJ115: 3.5185531 | BK115: 3.5166815 | BL115: 3.5155573 | BM115: 3.5151442 | BN115: 3.5154058 | BO115: 3.5163055 | BP115: 3.5178071 | BQ115: 3.5198739 | BR115: 3.5425562 | BS115: 3.5791635
A116: =A111+7 -> 45441 | B116: =MONTH(A116) -> 5 | C116: =YEAR(A116) -> 2024 | D116: =C116*100+B116 -> 202405 | E116: =IF(B116<4,1,IF(B116<7,2,IF(B116<10,3,4))) -> 2 | F116: =C116*100+E116 -> 202402 | G116: 20240529 | H116: 5.25 | I116: 5.2 | J116: 5.1930598 | K116: 5.1596666 | L116: 5.1192513 | M116: 5.073743 | N116: 5.0236947 | O116: 4.9718467 | P116: 4.9214158 | Q116: 4.8746751 | R116: 4.8326907 | S116: 4.7954835 | T116: 4.7617536 | U116: 4.7297872 | V116: 4.6964982 | W116: 4.6611643 | X116: 4.6238048 | Y116: 4.5844381 | Z116: 4.5430824 | AA116: 4.4997573 | AB116: 4.4545562 | AC116: 4.4079963 | AD116: 4.3607464 | AE116: 4.3134733 | AF116: 4.2668441 | AG116: 4.2215273 | AH116: 4.178077 | AI116: 4.1365947 | AJ116: 4.0970707 | AK116: 4.0594935 | AL116: 4.0238518 | AM116: 3.9901357 | AN116: 3.9583338 | AO116: 3.9284348 | AP116: 3.9004287 | AQ116: 3.8743041 | AR116: 3.85005 | AS116: 3.827656 | AT116: 3.8071021 | AU116: 3.7883202 | AV116: 3.7712271 | AW116: 3.7557386 | AX116: 3.7417708 | AY116: 3.7292402 | AZ116: 3.7180627 | BA116: 3.7081545 | BB116: 3.6994319 | BC116: 3.691811 | BD116: 3.6852079 | BE116: 3.6795389 | BF116: 3.6747269 | BG116: 3.6707279 | BH116: 3.6675082 | BI116: 3.6650338 | BJ116: 3.663271 | BK116: 3.6621859 | BL116: 3.6617447 | BM116: 3.6619134 | BN116: 3.6626584 | BO116: 3.6639456 | BP116: 3.6657414 | BQ116: 3.6680118 | BR116: 3.6902643 | BS116: 3.724459
A117: =A112+7 -> 45442 | B117: =MONTH(A117) -> 5 | C117: =YEAR(A117) -> 2024 | D117: =C117*100+B117 -> 202405 | E117: =IF(B117<4,1,IF(B117<7,2,IF(B117<10,3,4))) -> 2 | F117: =C117*100+E117 -> 202402 | G117: 20240530 | H117: 5.25 | I117: 5.2 | J117: 5.1906704 | K117: 5.1519018 | L117: 5.1072776 | M117: 5.0587532 | N117: 5.0059869 | O117: 4.9506031 | P117: 4.8952542 | Q117: 4.8420042 | R117: 4.7917629 | S117: 4.7446814 | T117: 4.7001742 | U117: 4.6573225 | V117: 4.6144859 | W117: 4.5712955 | X117: 4.5277779 | Y117: 4.4839581 | Z117: 4.4398613 | AA117: 4.395514 | AB117: 4.3509874 | AC117: 4.3065884 | AD117: 4.2627013 | AE117: 4.2197084 | AF117: 4.1779924 | AG117: 4.1379372 | AH117: 4.099866 | AI117: 4.0638124 | AJ117: 4.0297232 | AK117: 3.9975438 | AL117: 3.9672197 | AM117: 3.9386976 | AN117: 3.9119231 | AO117: 3.8868416 | AP117: 3.8633997 | AQ117: 3.8415431 | AR117: 3.8212173 | AS117: 3.8023687 | AT117: 3.7849412 | AU117: 3.7688698 | AV117: 3.7540873 | AW117: 3.7405262 | AX117: 3.7281186 | AY117: 3.7167975 | AZ117: 3.7064952 | BA117: 3.697144 | BB117: 3.6886768 | BC117: 3.6810258 | BD117: 3.6741236 | BE117: 3.6679027 | BF117: 3.6623037 | BG117: 3.6573026 | BH117: 3.6528854 | BI117: 3.649038 | BJ117: 3.6457461 | BK117: 3.6429959 | BL117: 3.6407731 | BM117: 3.6390637 | BN117: 3.6378536 | BO117: 3.6371286 | BP117: 3.6368747 | BQ117: 3.6370778 | BR117: 3.6472413 | BS117: 3.6711414
A118: =A113+7 -> 45443 | B118: =MONTH(A118) -> 5 | C118: =YEAR(A118) -> 2024 | D118: =C118*100+B118 -> 202405 | E118: =IF(B118<4,1,IF(B118<7,2,IF(B118<10,3,4))) -> 2 | F118: =C118*100+E118 -> 202402 | G118: 20240531 | H118: 5.25 | I118: 5.2 | J118: 5.1914862 | K118: 5.1532652 | L118: 5.1085288 | M118: 5.0601905 | N118: 5.0075459 | O118: 4.9512707 | P118: 4.8933999 | Q118: 4.8355564 | R118: 4.7787506 | S118: 4.723548 | T118: 4.6702708 | U118: 4.6189747 | V118: 4.5698104 | W118: 4.522524 | X118: 4.476721 | Y118: 4.4320052 | Z118: 4.3879804 | AA118: 4.3442521 | AB118: 4.3005318 | AC118: 4.2570309 | AD118: 4.214107 | AE118: 4.1721163 | AF118: 4.1314151 | AG118: 4.0923609 | AH118: 4.055249 | AI118: 4.0201054 | AJ118: 3.9868831 | AK118: 3.9555339 | AL118: 3.9260095 | AM118: 3.898263 | AN118: 3.872246 | AO118: 3.8479105 | AP118: 3.8252092 | AQ118: 3.804094 | AR118: 3.7845168 | AS118: 3.7664304 | AT118: 3.7497829 | AU118: 3.7345068 | AV118: 3.7205307 | AW118: 3.7077824 | AX118: 3.6961902 | AY118: 3.6856824 | AZ118: 3.676187 | BA118: 3.6676321 | BB118: 3.6599461 | BC118: 3.6530571 | BD118: 3.6468931 | BE118: 3.6413826 | BF118: 3.6364624 | BG118: 3.632109 | BH118: 3.6283096 | BI118: 3.6250515 | BJ118: 3.6223218 | BK118: 3.6201079 | BL118: 3.618397 | BM118: 3.6171762 | BN118: 3.6164329 | BO118: 3.6161542 | BP118: 3.6163275 | BQ118: 3.6169398 | BR118: 3.6291925 | BS118: 3.6544702
A119: =A114+7 -> 45446 | B119: =MONTH(A119) -> 6 | C119: =YEAR(A119) -> 2024 | D119: =C119*100+B119 -> 202406 | E119: =IF(B119<4,1,IF(B119<7,2,IF(B119<10,3,4))) -> 2 | F119: =C119*100+E119 -> 202402 | G119: 20240603 | H119: 5.25 | I119: 5.2 | J119: 5.1837953 | K119: 5.1408526 | L119: 5.0905588 | M119: 5.0343781 | N119: 4.9724934 | O119: 4.907684 | P119: 4.8437055 | Q119: 4.7831394 | R119: 4.7273848 | S119: 4.6764946 | T119: 4.6297622 | U119: 4.5858413 | V119: 4.5426647 | W119: 4.4996039 | X119: 4.4564777 | Y119: 4.4131032 | Z119: 4.3692976 | AA119: 4.3248795 | AB119: 4.2797657 | AC119: 4.2342904 | AD119: 4.1888995 | AE119: 4.144037 | AF119: 4.1001472 | AG119: 4.0576759 | AH119: 4.0169887 | AI119: 3.9781387 | AJ119: 3.9411018 | AK119: 3.9058526 | AL119: 3.8723656 | AM119: 3.8406168 | AN119: 3.8105808 | AO119: 3.7822323 | AP119: 3.7555469 | AQ119: 3.7304995 | AR119: 3.7070647 | AS119: 3.6852182 | AT119: 3.6649289 | AU119: 3.6461432 | AV119: 3.6288022 | AW119: 3.6128464 | AX119: 3.5982165 | AY119: 3.5848533 | AZ119: 3.5726976 | BA119: 3.56169 | BB119: 3.5517713 | BC119: 3.5428823 | BD119: 3.5349636 | BE119: 3.5279561 | BF119: 3.5218044 | BG119: 3.5164752 | BH119: 3.5119423 | BI119: 3.5081796 | BJ119: 3.5051609 | BK119: 3.5028601 | BL119: 3.5012511 | BM119: 3.5003077 | BN119: 3.5000038 | BO119: 3.5003132 | BP119: 3.5012099 | BQ119: 3.5026677 | BR119: 3.521895 | BS119: 3.5557243
A120: =A115+7 -> 45447 | B120: =MONTH(A120) -> 6 | C120: =YEAR(A120) -> 2024 | D120: =C120*100+B120 -> 202406 | E120: =IF(B120<4,1,IF(B120<7,2,IF(B120<10,3,4))) -> 2 | F120: =C120*100+E120 -> 202402 | G120: 20240604 | H120: 5.25 | I120: 5.2 | J120: 5.1849217 | K120: 5.1420211 | L120: 5.0904666 | M120: 5.0323024 | N120: 4.9680967 | O120: 4.9008148 | P120: 4.834459 | Q120: 4.7717549 | R120: 4.7142725 | S120: 4.6620265 | T120: 4.6141403 | U120: 4.5690585 | V120: 4.5241912 | W120: 4.4788812 | X120: 4.43307 | Y120: 4.386697 | Z120: 4.3397021 | AA120: 4.2920264 | AB120: 4.243697 | AC120: 4.1951077 | AD120: 4.1467503 | AE120: 4.0991149 | AF120: 4.0526918 | AG120: 4.0079726 | AH120: 3.9653577 | AI120: 3.9248872 | AJ120: 3.886513 | AK120: 3.8501852 | AL120: 3.8158542 | AM120: 3.7834717 | AN120: 3.7529879 | AO120: 3.7243533 | AP120: 3.6975193 | AQ120: 3.6724364 | AR120: 3.6490549 | AS120: 3.6273264 | AT120: 3.6071987 | AU120: 3.5886107 | AV120: 3.5714992 | AW120: 3.5558004 | AX120: 3.5414508 | AY120: 3.528387 | AZ120: 3.5165455 | BA120: 3.5058626 | BB120: 3.496275 | BC120: 3.4877191 | BD120: 3.4801313 | BE120: 3.4734482 | BF120: 3.4676111 | BG120: 3.4625854 | BH120: 3.4583438 | BI120: 3.4548589 | BJ120: 3.4521033 | BK120: 3.4500497 | BL120: 3.4486708 | BM120: 3.4479391 | BN120: 3.4478273 | BO120: 3.4483081 | BP120: 3.4493542 | BQ120: 3.450938 | BR120: 3.4704155 | BS120: 3.5036427
A121: =A116+7 -> 45448 | B121: =MONTH(A121) -> 6 | C121: =YEAR(A121) -> 2024 | D121: =C121*100+B121 -> 202406 | E121: =IF(B121<4,1,IF(B121<7,2,IF(B121<10,3,4))) -> 2 | F121: =C121*100+E121 -> 202402 | G121: 20240605 | H121: 5.25 | I121: 5.2 | J121: 5.1868982 | K121: 5.1455249 | L121: 5.0955964 | M121: 5.038482 | N121: 4.9747153 | O121: 4.9076476 | P121: 4.8412077 | Q121: 4.7779631 | R121: 4.7194609 | S121: 4.6660153 | T121: 4.6169117 | U121: 4.5709155 | V121: 4.525484 | W121: 4.4798959 | X121: 4.4340134 | Y121: 4.387697 | Z121: 4.340807 | AA121: 4.2932055 | AB121: 4.2448501 | AC121: 4.1961061 | AD121: 4.1474478 | AE121: 4.0993478 | AF121: 4.0522786 | AG121: 4.0067145 | AH121: 3.9630473 | AI121: 3.9213461 | AJ121: 3.8816008 | AK121: 3.8437997 | AL121: 3.8079312 | AM121: 3.7739851 | AN121: 3.7419499 | AO121: 3.711814 | AP121: 3.6835669 | AQ121: 3.6571973 | AR121: 3.6326937 | AS121: 3.6100455 | AT121: 3.5892318 | AU121: 3.5701857 | AV121: 3.5528265 | AW121: 3.5370733 | AX121: 3.522845 | AY121: 3.5100611 | AZ121: 3.4986404 | BA121: 3.4885021 | BB121: 3.4795654 | BC121: 3.4717494 | BD121: 3.464973 | BE121: 3.4591557 | BF121: 3.4542229 | BG121: 3.4501292 | BH121: 3.4468374 | BI121: 3.4443101 | BJ121: 3.4425098 | BK121: 3.4413992 | BL121: 3.4409409 | BM121: 3.4410976 | BN121: 3.4418317 | BO121: 3.4431061 | BP121: 3.4448832 | BQ121: 3.4471257 | BR121: 3.4689866 | BS121: 3.5025835
A122: =A117+7 -> 45449 | B122: =MONTH(A122) -> 6 | C122: =YEAR(A122) -> 2024 | D122: =C122*100+B122 -> 202406 | E122: =IF(B122<4,1,IF(B122<7,2,IF(B122<10,3,4))) -> 2 | F122: =C122*100+E122 -> 202402 | G122: 20240606 | H122: 5.25 | I122: 5.2 | J122: 5.1779003 | K122: 5.135123 | L122: 5.0821582 | M122: 5.0203309 | N122: 4.9509381 | O122: 4.8782304 | P122: 4.8069992 | Q122: 4.7402836 | R122: 4.6796515 | S122: 4.6251147 | T122: 4.5756481 | U122: 4.5295635 | V122: 4.4839205 | W122: 4.437919 | X122: 4.3914083 | Y122: 4.3442362 | Z122: 4.2962503 | AA122: 4.2472998 | AB122: 4.1973344 | AC122: 4.1468254 | AD122: 4.0964127 | AE122: 4.0467343 | AF122: 3.9984284 | AG122: 3.952135 | AH122: 3.9083945 | AI122: 3.8672721 | AJ122: 3.8286896 | AK122: 3.7925674 | AL122: 3.7588258 | AM122: 3.7273865 | AN122: 3.6981699 | AO122: 3.6710965 | AP122: 3.6460878 | AQ122: 3.6230642 | AR122: 3.6019464 | AS122: 3.5826557 | AT122: 3.5651108 | AU122: 3.5492216 | AV122: 3.5348967 | AW122: 3.5220439 | AX122: 3.5105709 | AY122: 3.5003861 | AZ122: 3.4913972 | BA122: 3.4835122 | BB122: 3.4766393 | BC122: 3.4706863 | BD122: 3.4655612 | BE122: 3.461172 | BF122: 3.4574375 | BG122: 3.4543239 | BH122: 3.4518104 | BI122: 3.4498765 | BJ122: 3.4485014 | BK122: 3.4476644 | BL122: 3.4473449 | BM122: 3.4475221 | BN122: 3.4481755 | BO122: 3.4492842 | BP122: 3.4508276 | BQ122: 3.4527851 | BR122: 3.4723554 | BS122: 3.5033721
A123: =A118+7 -> 45450 | B123: =MONTH(A123) -> 6 | C123: =YEAR(A123) -> 2024 | D123: =C123*100+B123 -> 202406 | E123: =IF(B123<4,1,IF(B123<7,2,IF(B123<10,3,4))) -> 2 | F123: =C123*100+E123 -> 202402 | G123: 20240607 | H123: 5.25 | I123: 5.2 | J123: 5.1782711 | K123: 5.1375844 | L123: 5.0895905 | M123: 5.0355631 | N123: 4.9763842 | O123: 4.9147388 | P123: 4.8536952 | Q123: 4.7950121 | R123: 4.7394472 | S123: 4.6869343 | T123: 4.6369173 | U123: 4.588547 | V123: 4.5405592 | W123: 4.492661 | X123: 4.4449026 | Y123: 4.3973327 | Z123: 4.35 | AA123: 4.3029548 | AB123: 4.2562841 | AC123: 4.2102536 | AD123: 4.1651818 | AE123: 4.121386 | AF123: 4.0791834 | AG123: 4.0388925 | AH123: 4.0007716 | AI123: 3.9648187 | AJ123: 3.9309613 | AK123: 3.8991256 | AL123: 3.8692379 | AM123: 3.8412255 | AN123: 3.8150146 | AO123: 3.7905315 | AP123: 3.7677036 | AQ123: 3.7464571 | AR123: 3.7267184 | AS123: 3.7084146 | AT123: 3.6914743 | AU123: 3.6758349 | AV123: 3.6614365 | AW123: 3.6482187 | AX123: 3.6361213 | AY123: 3.6250842 | AZ123: 3.6150471 | BA123: 3.6059497 | BB123: 3.597732 | BC123: 3.5903337 | BD123: 3.5836944 | BE123: 3.5777542 | BF123: 3.5724593 | BG123: 3.5677853 | BH123: 3.563716 | BI123: 3.5602351 | BJ123: 3.5573261 | BK123: 3.5549729 | BL123: 3.5531591 | BM123: 3.5518683 | BN123: 3.5510844 | BO123: 3.5507908 | BP123: 3.5509714 | BQ123: 3.5516098 | BR123: 3.5642626 | BS123: 3.5900259
A124: =A119+7 -> 45453 | B124: =MONTH(A124) -> 6 | C124: =YEAR(A124) -> 2024 | D124: =C124*100+B124 -> 202406 | E124: =IF(B124<4,1,IF(B124<7,2,IF(B124<10,3,4))) -> 2 | F124: =C124*100+E124 -> 202402 | G124: 20240610 | H124: 5.25 | I124: 5.2 | J124: 5.1819706 | K124: 5.1425089 | L124: 5.098925 | M124: 5.0496074 | N124: 4.9938682 | O124: 4.9343501 | P124: 4.8752344 | Q124: 4.8198587 | R124: 4.7701855 | S124: 4.7263871 | T124: 4.6874822 | U124: 4.6515531 | V124: 4.6153975 | W124: 4.5782235 | X124: 4.5399823 | Y124: 4.500624 | Z124: 4.4600982 | AA124: 4.4183565 | AB124: 4.3754419 | AC124: 4.3317893 | AD124: 4.2879379 | AE124: 4.2444255 | AF124: 4.2017898 | AG124: 4.1605701 | AH124: 4.1212075 | AI124: 4.0837575 | AJ124: 4.0481802 | AK124: 4.0144344 | AL124: 3.9824792 | AM124: 3.9522745 | AN124: 3.9237793 | AO124: 3.8969526 | AP124: 3.8717543 | AQ124: 3.8481433 | AR124: 3.8260787 | AS124: 3.8055203 | AT124: 3.7864245 | AU124: 3.7687363 | AV124: 3.7523989 | AW124: 3.7373547 | AX124: 3.7235461 | AY124: 3.7109162 | AZ124: 3.6994074 | BA124: 3.6889622 | BB124: 3.6795235 | BC124: 3.6710338 | BD124: 3.6634358 | BE124: 3.6566721 | BF124: 3.6506898 | BG124: 3.6454594 | BH124: 3.6409597 | BI124: 3.6371691 | BJ124: 3.6340662 | BK124: 3.6316296 | BL124: 3.629838 | BM124: 3.6286698 | BN124: 3.6281036 | BO124: 3.6281181 | BP124: 3.6286918 | BQ124: 3.6298033 | BR124: 3.6466187 | BS124: 3.6777185
A125: =A120+7 -> 45454 | B125: =MONTH(A125) -> 6 | C125: =YEAR(A125) -> 2024 | D125: =C125*100+B125 -> 202406 | E125: =IF(B125<4,1,IF(B125<7,2,IF(B125<10,3,4))) -> 2 | F125: =C125*100+E125 -> 202402 | G125: 20240611 | H125: 5.25 | I125: 5.2 | J125: 5.1757966 | K125: 5.1287645 | L125: 5.0786992 | M125: 5.025058 | N125: 4.9668391 | O125: 4.9057687 | P125: 4.8450249 | Q125: 4.787136 | R125: 4.7338184 | S125: 4.6854377 | T125: 4.6414598 | U125: 4.6005562 | V125: 4.5601926 | W125: 4.5196576 | X125: 4.4788081 | Y125: 4.4374999 | Z125: 4.3955884 | AA125: 4.352931 | AB125: 4.3094788 | AC125: 4.2655849 | AD125: 4.2217095 | AE125: 4.1783113 | AF125: 4.135849 | AG125: 4.0947827 | AH125: 4.05549 | AI125: 4.0180244 | AJ125: 3.9823594 | AK125: 3.9484674 | AL125: 3.9163209 | AM125: 3.8858932 | AN125: 3.857157 | AO125: 3.8300845 | AP125: 3.8046492 | AQ125: 3.7808236 | AR125: 3.7585801 | AS125: 3.7378922 | AT125: 3.7187271 | AU125: 3.7010322 | AV125: 3.6847502 | AW125: 3.6698233 | AX125: 3.6561936 | AY125: 3.6438039 | AZ125: 3.6325964 | BA125: 3.6225133 | BB125: 3.6134972 | BC125: 3.6054904 | BD125: 3.5984352 | BE125: 3.592274 | BF125: 3.5869531 | BG125: 3.5824379 | BH125: 3.5787 | BI125: 3.5757105 | BJ125: 3.5734408 | BK125: 3.5718624 | BL125: 3.5709465 | BM125: 3.5706644 | BN125: 3.5709876 | BO125: 3.5718874 | BP125: 3.5733351 | BQ125: 3.575302 | BR125: 3.5966746 | BS125: 3.6311633
A126: =A121+7 -> 45455 | B126: =MONTH(A126) -> 6 | C126: =YEAR(A126) -> 2024 | D126: =C126*100+B126 -> 202406 | E126: =IF(B126<4,1,IF(B126<7,2,IF(B126<10,3,4))) -> 2 | F126: =C126*100+E126 -> 202402 | G126: 20240612 | H126: 5.25 | I126: 5.2 | J126: 5.1684716 | K126: 5.111535 | L126: 5.0509285 | M126: 4.9863636 | N126: 4.9167901 | O126: 4.8438631 | P126: 4.7707456 | Q126: 4.70028 | R126: 4.6345547 | S126: 4.57428 | T126: 4.5189559 | U126: 4.4675252 | V126: 4.4178369 | W126: 4.3691873 | X126: 4.3213299 | Y126: 4.2740163 | Z126: 4.2269981 | AA126: 4.1800286 | AB126: 4.1329582 | AC126: 4.0860516 | AD126: 4.0396844 | AE126: 3.9942302 | AF126: 3.9500629 | AG126: 3.9075578 | AH126: 3.8670222 | AI126: 3.8284973 | AJ126: 3.7919592 | AK126: 3.7573826 | AL126: 3.7247423 | AM126: 3.6940143 | AN126: 3.6651734 | AO126: 3.6381943 | AP126: 3.6130529 | AQ126: 3.5897241 | AR126: 3.5681828 | AS126: 3.5484046 | AT126: 3.5303569 | AU126: 3.5139704 | AV126: 3.4991649 | AW126: 3.4858599 | AX126: 3.4739749 | AY126: 3.4634297 | AZ126: 3.4541437 | BA126: 3.4460364 | BB126: 3.4390277 | BC126: 3.433037 | BD126: 3.4279838 | BE126: 3.4237879 | BF126: 3.4203758 | BG126: 3.4177051 | BH126: 3.4157421 | BI126: 3.414453 | BJ126: 3.413804 | BK126: 3.4137614 | BL126: 3.4142914 | BM126: 3.4153601 | BN126: 3.4169338 | BO126: 3.4189788 | BP126: 3.4214612 | BQ126: 3.4243472 | BR126: 3.4489612 | BS126: 3.4839155
... A178: =A173+7 -> 45527 | B178: =MONTH(A178) -> 8 | C178: =YEAR(A178) -> 2024 | D178: =C178*100+B178 -> 202408 | E178: =IF(B178<4,1,IF(B178<7,2,IF(B178<10,3,4))) -> 3 | F178: =C178*100+E178 -> 202403 | G178: 20240823 | H178: 5 | I178: 4.95 | J178: 4.9202451 | K178: 4.8231984 | L178: 4.7112609 | M178: 4.5902003 | N178: 4.4674263 | O178: 4.3482197 | P178: 4.2364686 | Q178: 4.1355253 | R178: 4.0470246 | S178: 3.9711465 | T178: 3.9071501 | U178: 3.8533241 | V178: 3.8066292 | W178: 3.7656688 | X178: 3.7297257 | Y178: 3.6980818 | Z178: 3.6700193 | AA178: 3.6448211 | AB178: 3.6218332 | AC178: 3.600698 | AD178: 3.5811445 | AE178: 3.5629011 | AF178: 3.545696 | AG178: 3.5292582 | AH178: 3.5133592 | AI178: 3.4979608 | AJ178: 3.4830779 | AK178: 3.468725 | AL178: 3.4549165 | AM178: 3.4416672 | AN178: 3.4289916 | AO178: 3.4169041 | AP178: 3.4054196 | AQ178: 3.3945525 | AR178: 3.3843172 | AS178: 3.3747286 | AT178: 3.3657976 | AU178: 3.3575209 | AV178: 3.349892 | AW178: 3.3429042 | AX178: 3.3365505 | AY178: 3.3308246 | AZ178: 3.3257195 | BA178: 3.3212286 | BB178: 3.3173452 | BC178: 3.3140626 | BD178: 3.3113741 | BE178: 3.309273 | BF178: 3.3077502 | BG178: 3.3067865 | BH178: 3.30636 | BI178: 3.3064486 | BJ178: 3.3070302 | BK178: 3.3080829 | BL178: 3.3095846 | BM178: 3.3115134 | BN178: 3.313847 | BO178: 3.3165637 | BP178: 3.3196413 | BQ178: 3.3230577 | BR178: 3.3497909 | BS178: 3.3853037
A179: =A174+7 -> 45530 | B179: =MONTH(A179) -> 8 | C179: =YEAR(A179) -> 2024 | D179: =C179*100+B179 -> 202408 | E179: =IF(B179<4,1,IF(B179<7,2,IF(B179<10,3,4))) -> 3 | F179: =C179*100+E179 -> 202403 | G179: 20240826 | H179: 5 | I179: #N/A | J179: #N/A | K179: #N/A | L179: #N/A | M179: #N/A | N179: #N/A | O179: #N/A | P179: #N/A | Q179: #N/A | R179: #N/A | S179: #N/A | T179: #N/A | U179: #N/A | V179: #N/A | W179: #N/A | X179: #N/A | Y179: #N/A | Z179: #N/A | AA179: #N/A | AB179: #N/A | AC179: #N/A | AD179: #N/A | AE179: #N/A | AF179: #N/A | AG179: #N/A | AH179: #N/A | AI179: #N/A | AJ179: #N/A | AK179: #N/A | AL179: #N/A | AM179: #N/A | AN179: #N/A | AO179: #N/A | AP179: #N/A | AQ179: #N/A | AR179: #N/A | AS179: #N/A | AT179: #N/A | AU179: #N/A | AV179: #N/A | AW179: #N/A | AX179: #N/A | AY179: #N/A | AZ179: #N/A | BA179: #N/A | BB179: #N/A | BC179: #N/A | BD179: #N/A | BE179: #N/A | BF179: #N/A | BG179: #N/A | BH179: #N/A | BI179: #N/A | BJ179: #N/A | BK179: #N/A | BL179: #N/A | BM179: #N/A | BN179: #N/A | BO179: #N/A | BP179: #N/A | BQ179: #N/A | BR179: #N/A | BS179: #N/A
A180: =A175+7 -> 45531 | B180: =MONTH(A180) -> 8 | C180: =YEAR(A180) -> 2024 | D180: =C180*100+B180 -> 202408 | E180: =IF(B180<4,1,IF(B180<7,2,IF(B180<10,3,4))) -> 3 | F180: =C180*100+E180 -> 202403 | G180: 20240827 | H180: 5 | I180: 4.95 | J180: 4.9155234 | K180: 4.8196772 | L180: 4.7080794 | M180: 4.5892358 | N180: 4.4695406 | O180: 4.3533755 | P180: 4.2449205 | Q180: 4.1477281 | R180: 4.0640678 | S180: 3.9941422 | T180: 3.9371556 | U180: 3.8910961 | V180: 3.8526007 | W180: 3.8200022 | X180: 3.7921702 | Y180: 3.7679732 | Z180: 3.7462797 | AA180: 3.725959 | AB180: 3.7060487 | AC180: 3.6863693 | AD180: 3.6669692 | AE180: 3.6478961 | AF180: 3.6291976 | AG180: 3.6109221 | AH180: 3.5931132 | AI180: 3.5757987 | AJ180: 3.5590028 | AK180: 3.5427494 | AL180: 3.5270621 | AM180: 3.5119653 | AN180: 3.4974828 | AO180: 3.4836382 | AP180: 3.4704558 | AQ180: 3.4579595 | AR180: 3.4461729 | AS180: 3.4351204 | AT180: 3.4248191 | AU180: 3.4152602 | AV180: 3.4064287 | AW180: 3.3983093 | AX180: 3.3908864 | AY180: 3.3841452 | AZ180: 3.3780702 | BA180: 3.372646 | BB180: 3.3678577 | BC180: 3.3636897 | BD180: 3.3601269 | BE180: 3.357154 | BF180: 3.3547557 | BG180: 3.3529164 | BH180: 3.3516202 | BI180: 3.3508516 | BJ180: 3.3505947 | BK180: 3.3508338 | BL180: 3.3515532 | BM180: 3.3527372 | BN180: 3.3543699 | BO180: 3.3564358 | BP180: 3.358919 | BQ180: 3.3618037 | BR180: 3.3866825 | BS180: 3.422161
A181: =A176+7 -> 45532 | B181: =MONTH(A181) -> 8 | C181: =YEAR(A181) -> 2024 | D181: =C181*100+B181 -> 202408 | E181: =IF(B181<4,1,IF(B181<7,2,IF(B181<10,3,4))) -> 3 | F181: =C181*100+E181 -> 202403 | G181: 20240828 | H181: 5 | I181: 4.95 | J181: 4.9147241 | K181: 4.8208686 | L181: 4.7098016 | M181: 4.5906903 | N181: 4.4705404 | O181: 4.3544316 | P181: 4.2471195 | Q181: 4.1522049 | R181: 4.0712523 | S181: 4.0039765 | T181: 3.9483948 | U181: 3.9020871 | V181: 3.8606716 | W181: 3.8228102 | X181: 3.7881129 | Y181: 3.7561881 | Z181: 3.7266443 | AA181: 3.6990913 | AB181: 3.6731815 | AC181: 3.6488164 | AD181: 3.6259857 | AE181: 3.6046784 | AF181: 3.5848834 | AG181: 3.5665907 | AH181: 3.5497761 | AI181: 3.5343635 | AJ181: 3.5202643 | AK181: 3.507389 | AL181: 3.4956487 | AM181: 3.4849545 | AN181: 3.4752172 | AO181: 3.4663477 | AP181: 3.4582571 | AQ181: 3.4508563 | AR181: 3.4440562 | AS181: 3.4377678 | AT181: 3.4319121 | AU181: 3.426464 | AV181: 3.4214166 | AW181: 3.4167632 | AX181: 3.4124966 | AY181: 3.4086101 | AZ181: 3.4050968 | BA181: 3.4019496 | BB181: 3.3991619 | BC181: 3.3967267 | BD181: 3.3946369 | BE181: 3.3928859 | BF181: 3.3914675 | BG181: 3.3903804 | BH181: 3.3896243 | BI181: 3.3891993 | BJ181: 3.3891052 | BK181: 3.3893418 | BL181: 3.3899091 | BM181: 3.390807 | BN181: 3.3920353 | BO181: 3.393594 | BP181: 3.395483 | BQ181: 3.397702 | BR181: 3.4176884 | BS181: 3.4479857
A182: =A177+7 -> 45533 | B182: =MONTH(A182) -> 8 | C182: =YEAR(A182) -> 2024 | D182: =C182*100+B182 -> 202408 | E182: =IF(B182<4,1,IF(B182<7,2,IF(B182<10,3,4))) -> 3 | F182: =C182*100+E182 -> 202403 | G182: 20240829 | H182: 5 | I182: 4.95 | J182: 4.9128535 | K182: 4.8158218 | L182: 4.7036191 | M182: 4.585279 | N182: 4.4657977 | O182: 4.3488956 | P182: 4.2389323 | Q182: 4.1399069 | R182: 4.0532131 | S182: 3.9789079 | T182: 3.9161136 | U182: 3.8634857 | V182: 3.8187566 | W182: 3.7806357 | X182: 3.7481527 | Y182: 3.7203361 | Z182: 3.6962144 | AA182: 3.6748169 | AB182: 3.6552768 | AC182: 3.6372627 | AD182: 3.6206151 | AE182: 3.6051738 | AF182: 3.5907787 | AG182: 3.5772703 | AH182: 3.5645041 | AI182: 3.5524213 | AJ182: 3.5409918 | AK182: 3.5301853 | AL182: 3.5199714 | AM182: 3.5103201 | AN182: 3.501201 | AO182: 3.4925839 | AP182: 3.4844385 | AQ182: 3.4767347 | AR182: 3.469442 | AS182: 3.4625304 | AT182: 3.4559738 | AU182: 3.4497661 | AV182: 3.4439079 | AW182: 3.4383995 | AX182: 3.433241 | AY182: 3.428433 | AZ182: 3.4239757 | BA182: 3.4198694 | BB182: 3.4161145 | BC182: 3.4127112 | BD182: 3.40966 | BE182: 3.4069611 | BF182: 3.4046151 | BG182: 3.4026238 | BH182: 3.4009893 | BI182: 3.3997138 | BJ182: 3.3987992 | BK182: 3.3982477 | BL182: 3.3980614 | BM182: 3.3982424 | BN182: 3.3987928 | BO182: 3.3997147 | BP182: 3.4010102 | BQ182: 3.4026814 | BR182: 3.4203305 | BS182: 3.4496974
A183: =A178+7 -> 45534 | B183: =MONTH(A183) -> 8 | C183: =YEAR(A183) -> 2024 | D183: =C183*100+B183 -> 202408 | E183: =IF(B183<4,1,IF(B183<7,2,IF(B183<10,3,4))) -> 3 | F183: =C183*100+E183 -> 202403 | G183: 20240830 | H183: 5 | I183: 4.95 | J183: 4.9142292 | K183: 4.8179299 | L183: 4.7029606 | M183: 4.5820289 | N183: 4.461815 | O183: 4.3455396 | P183: 4.2374484 | Q183: 4.1415479 | R183: 4.0592538 | S183: 3.9901739 | T183: 3.932853 | U183: 3.8850393 | V183: 3.8436478 | W183: 3.8073614 | X183: 3.775487 | Y183: 3.7473301 | Z183: 3.7221966 | AA183: 3.6993931 | AB183: 3.6783046 | AC183: 3.6586827 | AD183: 3.6403859 | AE183: 3.6232722 | AF183: 3.6071995 | AG183: 3.5920264 | AH183: 3.577626 | AI183: 3.5639452 | AJ183: 3.550954 | AK183: 3.5386219 | AL183: 3.5269185 | AM183: 3.5158136 | AN183: 3.5052767 | AO183: 3.4952774 | AP183: 3.4857855 | AQ183: 3.4767706 | AR183: 3.4682021 | AS183: 3.4600501 | AT183: 3.4522897 | AU183: 3.4449216 | AV183: 3.4379537 | AW183: 3.4313938 | AX183: 3.4252496 | AY183: 3.4195289 | AZ183: 3.4142394 | BA183: 3.4093889 | BB183: 3.4049852 | BC183: 3.4010361 | BD183: 3.3975492 | BE183: 3.3945325 | BF183: 3.3919916 | BG183: 3.389923 | BH183: 3.388321 | BI183: 3.3871797 | BJ183: 3.3864932 | BK183: 3.3862556 | BL183: 3.386461 | BM183: 3.3871036 | BN183: 3.3881775 | BO183: 3.3896768 | BP183: 3.3915956 | BQ183: 3.3939281 | BR183: 3.4160202 | BS183: 3.4499439
A184: =A179+7 -> 45537 | B184: =MONTH(A184) -> 9 | C184: =YEAR(A184) -> 2024 | D184: =C184*100+B184 -> 202409 | E184: =IF(B184<4,1,IF(B184<7,2,IF(B184<10,3,4))) -> 3 | F184: =C184*100+E184 -> 202403 | G184: 20240902 | H184: 5 | I184: 4.95 | J184: 4.906436 | K184: 4.8077444 | L184: 4.690097 | M184: 4.5692522 | N184: 4.4502733 | O184: 4.3360239 | P184: 4.2304493 | Q184: 4.136261 | R184: 4.0546779 | S184: 3.9857809 | T184: 3.9286367 | U184: 3.8812505 | V184: 3.8407002 | W184: 3.8056632 | X184: 3.7753099 | Y184: 3.7488095 | Z184: 3.7253315 | AA184: 3.7040461 | AB184: 3.6842597 | AC184: 3.6657514 | AD184: 3.6484031 | AE184: 3.6320959 | AF184: 3.6167108 | AG184: 3.6021297 | AH184: 3.5882496 | AI184: 3.5750309 | AJ184: 3.5624507 | AK184: 3.5504853 | AL184: 3.5391113 | AM184: 3.5283056 | AN184: 3.5180445 | AO184: 3.5083046 | AP184: 3.4990626 | AQ184: 3.4902952 | AR184: 3.4819788 | AS184: 3.4740902 | AT184: 3.4666107 | AU184: 3.459541 | AV184: 3.4528868 | AW184: 3.4466535 | AX184: 3.4408466 | AY184: 3.4354718 | AZ184: 3.4305345 | BA184: 3.4260404 | BB184: 3.4219949 | BC184: 3.4184037 | BD184: 3.4152721 | BE184: 3.4126059 | BF184: 3.4104092 | BG184: 3.4086789 | BH184: 3.4074099 | BI184: 3.4065965 | BJ184: 3.4062335 | BK184: 3.4063154 | BL184: 3.4068369 | BM184: 3.4077926 | BN184: 3.409177 | BO184: 3.4109848 | BP184: 3.4132106 | BQ184: 3.4158489 | BR184: 3.439767 | BS184: 3.4754962
A185: =A180+7 -> 45538 | B185: =MONTH(A185) -> 9 | C185: =YEAR(A185) -> 2024 | D185: =C185*100+B185 -> 202409 | E185: =IF(B185<4,1,IF(B185<7,2,IF(B185<10,3,4))) -> 3 | F185: =C185*100+E185 -> 202403 | G185: 20240903 | H185: 5 | I185: 4.95 | J185: 4.9003963 | K185: 4.8015128 | L185: 4.6812848 | M185: 4.5565761 | N185: 4.4334875 | O185: 4.3155879 | P185: 4.2071772 | Q185: 4.1107718 | R185: 4.0281445 | S185: 3.9589297 | T185: 3.9020065 | U185: 3.8549786 | V185: 3.8141116 | W185: 3.7780208 | X185: 3.7460315 | Y185: 3.7174677 | Z185: 3.6916534 | AA185: 3.6679137 | AB185: 3.6456859 | AC185: 3.6247991 | AD185: 3.6051672 | AE185: 3.5867036 | AF185: 3.5693216 | AG185: 3.5529352 | AH185: 3.5374654 | AI185: 3.522864 | AJ185: 3.5090912 | AK185: 3.4961064 | AL185: 3.4838693 | AM185: 3.4723399 | AN185: 3.4614777 | AO185: 3.4512422 | AP185: 3.4415936 | AQ185: 3.4324914 | AR185: 3.4238951 | AS185: 3.4157647 | AT185: 3.4080674 | AU185: 3.4008003 | AV185: 3.3939684 | AW185: 3.3875764 | AX185: 3.381629 | AY185: 3.3761311 | AZ185: 3.3710874 | BA185: 3.3665027 | BB185: 3.3623819 | BC185: 3.3587296 | BD185: 3.3555507 | BE185: 3.35285 | BF185: 3.3506308 | BG185: 3.3488892 | BH185: 3.3476192 | BI185: 3.3468148 | BJ185: 3.3464698 | BK185: 3.3465784 | BL185: 3.3471344 | BM185: 3.3481318 | BN185: 3.3495646 | BO185: 3.3514268 | BP185: 3.3537123 | BQ185: 3.3564151 | BR185: 3.3807659 | BS185: 3.4168547
A186: =A181+7 -> 45539 | B186: =MONTH(A186) -> 9 | C186: =YEAR(A186) -> 2024 | D186: =C186*100+B186 -> 202409 | E186: =IF(B186<4,1,IF(B186<7,2,IF(B186<10,3,4))) -> 3 | F186: =C186*100+E186 -> 202403 | G186: 20240904 | H186: 5 | I186: 4.95 | J186: 4.8856779 | K186: 4.7833925 | L186: 4.6567402 | M186: 4.5241174 | N186: 4.3927461 | O186: 4.26702 | P186: 4.1519874 | Q186: 4.0504343 | R186: 3.9639362 | S186: 3.8919522 | T186: 3.8331027 | U186: 3.7847822 | V186: 3.7430858 | W186: 3.7065486 | X186: 3.6744265 | Y186: 3.6459746 | Z186: 3.6204479 | AA186: 3.5971023 | AB186: 3.5753141 | AC186: 3.5548788 | AD186: 3.5356825 | AE186: 3.517611 | AF186: 3.5005499 | AG186: 3.4843853 | AH186: 3.4690182 | AI186: 3.4544108 | AJ186: 3.4405411 | AK186: 3.4273864 | AL186: 3.4149242 | AM186: 3.4031324 | AN186: 3.3919885 | AO186: 3.3814701 | AP186: 3.3715548 | AQ186: 3.3622203 | AR186: 3.353444 | AS186: 3.3452037 | AT186: 3.3374802 | AU186: 3.3302696 | AV186: 3.3235733 | AW186: 3.3173921 | AX186: 3.311727 | AY186: 3.3065793 | AZ186: 3.3019499 | BA186: 3.2978398 | BB186: 3.2942501 | BC186: 3.291182 | BD186: 3.2886363 | BE186: 3.2866142 | BF186: 3.2851146 | BG186: 3.2841273 | BH186: 3.2836397 | BI186: 3.2836388 | BJ186: 3.2841121 | BK186: 3.2850467 | BL186: 3.28643 | BM186: 3.2882491 | BN186: 3.2904913 | BO186: 3.293144 | BP186: 3.2961943 | BQ186: 3.2996294 | BR186: 3.327553 | BS186: 3.3657764
A187: =A182+7 -> 45540 | B187: =MONTH(A187) -> 9 | C187: =YEAR(A187) -> 2024 | D187: =C187*100+B187 -> 202409 | E187: =IF(B187<4,1,IF(B187<7,2,IF(B187<10,3,4))) -> 3 | F187: =C187*100+E187 -> 202403 | G187: 20240905 | H187: 5 | I187: 4.95 | J187: 4.8860558 | K187: 4.7832631 | L187: 4.6536579 | M187: 4.5163281 | N187: 4.3788518 | O187: 4.2465353 | P187: 4.125351 | Q187: 4.0188145 | R187: 3.928436 | S187: 3.8538697 | T187: 3.7931911 | U187: 3.7437769 | V187: 3.7013532 | W187: 3.6643015 | X187: 3.6318186 | Y187: 3.6031002 | Z187: 3.5773421 | AA187: 3.5537409 | AB187: 3.5316387 | AC187: 3.510882 | AD187: 3.4914267 | AE187: 3.4732281 | AF187: 3.4562415 | AG187: 3.4404229 | AH187: 3.4257253 | AI187: 3.4120923 | AJ187: 3.3994643 | AK187: 3.3877817 | AL187: 3.3769848 | AM187: 3.3670141 | AN187: 3.35781 | AO187: 3.3493127 | AP187: 3.3414629 | AQ187: 3.3342008 | AR187: 3.3274667 | AS187: 3.3212012 | AT187: 3.3153534 | AU187: 3.3099117 | AV187: 3.3048751 | AW187: 3.3002429 | AX187: 3.296014 | AY187: 3.2921876 | AZ187: 3.2887629 | BA187: 3.2857388 | BB187: 3.2831145 | BC187: 3.2808892 | BD187: 3.2790618 | BE187: 3.2776317 | BF187: 3.2765973 | BG187: 3.2759555 | BH187: 3.2757027 | BI187: 3.2758352 | BJ187: 3.2763492 | BK187: 3.2772411 | BL187: 3.2785072 | BM187: 3.2801438 | BN187: 3.2821472 | BO187: 3.2845137 | BP187: 3.2872397 | BQ187: 3.2903214 | BR187: 3.3157778 | BS187: 3.3513045
A188: =A183+7 -> 45541 | B188: =MONTH(A188) -> 9 | C188: =YEAR(A188) -> 2024 | D188: =C188*100+B188 -> 202409 | E188: =IF(B188<4,1,IF(B188<7,2,IF(B188<10,3,4))) -> 3 | F188: =C188*100+E188 -> 202403 | G188: 20240906 | H188: 5 | I188: 4.95 | J188: 4.9041651 | K188: 4.7948696 | L188: 4.6584504 | M188: 4.5148264 | N188: 4.3714608 | O188: 4.2337155 | P188: 4.1077646 | Q188: 3.9972356 | R188: 3.903413 | S188: 3.8261304 | T188: 3.7635688 | U188: 3.712911 | V188: 3.6696164 | W188: 3.6319597 | X188: 3.5992474 | Y188: 3.5707847 | Z188: 3.5458773 | AA188: 3.5238314 | AB188: 3.5040405 | AC188: 3.4862016 | AD188: 3.4700776 | AE188: 3.4554309 | AF188: 3.4420238 | AG188: 3.4296193 | AH188: 3.4180098 | AI188: 3.4071204 | AJ188: 3.396913 | AK188: 3.3873493 | AL188: 3.378391 | AM188: 3.3700001 | AN188: 3.3621382 | AO188: 3.354767 | AP188: 3.3478485 | AQ188: 3.3413443 | AR188: 3.3352162 | AS188: 3.329426 | AT188: 3.3239436 | AU188: 3.3187711 | AV188: 3.313919 | AW188: 3.3093975 | AX188: 3.3052169 | AY188: 3.3013876 | AZ188: 3.29792 | BA188: 3.2948242 | BB188: 3.2921107 | BC188: 3.2897897 | BD188: 3.2878716 | BE188: 3.2863668 | BF188: 3.2852827 | BG188: 3.2846149 | BH188: 3.2843555 | BI188: 3.2844966 | BJ188: 3.2850303 | BK188: 3.2859488 | BL188: 3.2872442 | BM188: 3.2889085 | BN188: 3.290934 | BO188: 3.2933128 | BP188: 3.2960369 | BQ188: 3.2990986 | BR188: 3.3240548 | BS188: 3.3588111
A189: =A184+7 -> 45544 | B189: =MONTH(A189) -> 9 | C189: =YEAR(A189) -> 2024 | D189: =C189*100+B189 -> 202409 | E189: =IF(B189<4,1,IF(B189<7,2,IF(B189<10,3,4))) -> 3 | F189: =C189*100+E189 -> 202403 | G189: 20240909 | H189: 5 | I189: 4.95 | J189: 4.8853628 | K189: 4.7642633 | L189: 4.6189551 | M189: 4.4668059 | N189: 4.3139844 | O189: 4.1648674 | P189: 4.0257366 | Q189: 3.9013888 | R189: 3.7942975 | S189: 3.7050396 | T189: 3.6325393 | U189: 3.5741923 | V189: 3.5263291 | W189: 3.4871014 | X189: 3.4552184 | Y189: 3.4293879 | Z189: 3.4083183 | AA189: 3.3907183 | AB189: 3.375492 | AC189: 3.3622198 | AD189: 3.3506283 | AE189: 3.3404435 | AF189: 3.3313916 | AG189: 3.323199 | AH189: 3.3156314 | AI189: 3.3086127 | AJ189: 3.3021065 | AK189: 3.2960762 | AL189: 3.2904851 | AM189: 3.2852969 | AN189: 3.2804749 | AO189: 3.2759826 | AP189: 3.2717835 | AQ189: 3.267841 | AR189: 3.2641186 | AS189: 3.2605798 | AT189: 3.2571966 | AU189: 3.2539757 | AV189: 3.2509324 | AW189: 3.2480821 | AX189: 3.24544 | AY189: 3.2430215 | AZ189: 3.2408419 | BA189: 3.2389164 | BB189: 3.2372604 | BC189: 3.2358892 | BD189: 3.2348181 | BE189: 3.2340624 | BF189: 3.2336358 | BG189: 3.2335433 | BH189: 3.2337871 | BI189: 3.2343693 | BJ189: 3.2352921 | BK189: 3.2365575 | BL189: 3.2381676 | BM189: 3.2401247 | BN189: 3.2424308 | BO189: 3.2450881 | BP189: 3.2480987 | BQ189: 3.2514646 | BR189: 3.2788154 | BS189: 3.3168726
A190: =A185+7 -> 45545 | B190: =MONTH(A190) -> 9 | C190: =YEAR(A190) -> 2024 | D190: =C190*100+B190 -> 202409 | E190: =IF(B190<4,1,IF(B190<7,2,IF(B190<10,3,4))) -> 3 | F190: =C190*100+E190 -> 202403 | G190: 20240910 | H190: 5 | I190: 4.95 | J190: 4.8949669 | K190: 4.7715874 | L190: 4.6249608 | M190: 4.4705417 | N190: 4.3132438 | O190: 4.1583668 | P190: 4.0138801 | Q190: 3.885435 | R190: 3.7762738 | S190: 3.6862882 | T190: 3.6140426 | U190: 3.5564259 | V190: 3.508887 | W190: 3.4694552 | X190: 3.4369345 | Y190: 3.410127 | Z190: 3.3878356 | AA190: 3.3688634 | AB190: 3.3521979 | AC190: 3.3374634 | AD190: 3.3244224 | AE190: 3.3128367 | AF190: 3.3024683 | AG190: 3.2930794 | AH190: 3.2844639 | AI190: 3.276543 | AJ190: 3.2692701 | AK190: 3.2625983 | AL190: 3.2564808 | AM190: 3.2508709 | AN190: 3.2457218 | AO190: 3.2409866 | AP190: 3.2366187 | AQ190: 3.2325712 | AR190: 3.2287972 | AS190: 3.2252501 | AT190: 3.221893 | AU190: 3.2187285 | AV190: 3.2157692 | AW190: 3.2130276 | AX190: 3.2105163 | AY190: 3.2082479 | AZ190: 3.2062349 | BA190: 3.2044899 | BB190: 3.2030255 | BC190: 3.2018543 | BD190: 3.2009887 | BE190: 3.2004414 | BF190: 3.2002234 | BG190: 3.2003393 | BH190: 3.2007912 | BI190: 3.2015815 | BJ190: 3.2027123 | BK190: 3.2041861 | BL190: 3.2060049 | BM190: 3.2081713 | BN190: 3.2106873 | BO190: 3.2135553 | BP190: 3.2167776 | BQ190: 3.2203563 | BR190: 3.248987 | BS190: 3.2882552
A191: =A186+7 -> 45546 | B191: =MONTH(A191) -> 9 | C191: =YEAR(A191) -> 2024 | D191: =C191*100+B191 -> 202409 | E191: =IF(B191<4,1,IF(B191<7,2,IF(B191<10,3,4))) -> 3 | F191: =C191*100+E191 -> 202403 | G191: 20240911 | H191: 5 | I191: 4.95 | J191: 4.8989112 | K191: 4.7599605 | L191: 4.5995921 | M191: 4.4331474 | N191: 4.2651541 | O191: 4.1007895 | P191: 3.9481891 | Q191: 3.8133996 | R191: 3.6994655 | S191: 3.6061975 | T191: 3.5317677 | U191: 3.4727622 | V191: 3.4244171 | W191: 3.3846456 | X191: 3.3521458 | Y191: 3.3256141 | Z191: 3.3037474 | AA191: 3.2852435 | AB191: 3.2690008 | AC191: 3.2546138 | AD191: 3.2418278 | AE191: 3.2303872 | AF191: 3.2200367 | AG191: 3.2105214 | AH191: 3.2016253 | AI191: 3.1932906 | AJ191: 3.1854991 | AK191: 3.1782323 | AL191: 3.1714718 | AM191: 3.1651994 | AN191: 3.1593968 | AO191: 3.1540454 | AP191: 3.1491271 | AQ191: 3.1446235 | AR191: 3.1405162 | AS191: 3.1367868 | AT191: 3.1334203 | AU191: 3.1304172 | AV191: 3.127783 | AW191: 3.125523 | AX191: 3.1236426 | AY191: 3.1221473 | AZ191: 3.1210423 | BA191: 3.1203331 | BB191: 3.120025 | BC191: 3.1201235 | BD191: 3.120634 | BE191: 3.1215617 | BF191: 3.1229099 | BG191: 3.1246716 | BH191: 3.126837 | BI191: 3.1293964 | BJ191: 3.13234 | BK191: 3.135658 | BL191: 3.1393408 | BM191: 3.1433786 | BN191: 3.1477616 | BO191: 3.1524801 | BP191: 3.1575243 | BQ191: 3.1628846 | BR191: 3.2010687 | BS191: 3.2477642
... A230: =A225+7 -> 45601 | B230: =MONTH(A230) -> 11 | C230: =YEAR(A230) -> 2024 | D230: =C230*100+B230 -> 202411 | E230: =IF(B230<4,1,IF(B230<7,2,IF(B230<10,3,4))) -> 4 | F230: =C230*100+E230 -> 202404 | G230: 20241105 | H230: 5 | I230: 4.95 | J230: 4.705506 | K230: 4.635297 | L230: 4.5488242 | M230: 4.4563583 | N230: 4.3713069 | O230: 4.2991426 | P230: 4.242551 | Q230: 4.2017392 | R230: 4.1752247 | S230: 4.1602589 | T230: 4.1541492 | U230: 4.1539544 | V230: 4.1559362 | W230: 4.1587442 | X230: 4.1617227 | Y230: 4.1642158 | Z230: 4.1655678 | AA230: 4.165123 | AB230: 4.1624098 | AC230: 4.1575927 | AD230: 4.1509734 | AE230: 4.1428534 | AF230: 4.1335344 | AG230: 4.1233179 | AH230: 4.1124688 | AI230: 4.1011052 | AJ230: 4.0893085 | AK230: 4.0771602 | AL230: 4.0647415 | AM230: 4.052134 | AN230: 4.0394189 | AO230: 4.0266777 | AP230: 4.0139918 | AQ230: 4.0014426 | AR230: 3.9891114 | AS230: 3.9770798 | AT230: 3.9654169 | AU230: 3.9541436 | AV230: 3.9432688 | AW230: 3.9328013 | AX230: 3.9227499 | AY230: 3.9131233 | AZ230: 3.9039304 | BA230: 3.89518 | BB230: 3.8868808 | BC230: 3.8790417 | BD230: 3.8716714 | BE230: 3.8647788 | BF230: 3.8583711 | BG230: 3.8524473 | BH230: 3.8470044 | BI230: 3.8420391 | BJ230: 3.8375482 | BK230: 3.8335284 | BL230: 3.8299766 | BM230: 3.8268895 | BN230: 3.8242639 | BO230: 3.8220966 | BP230: 3.8203843 | BQ230: 3.8191239 | BR230: 3.8205608 | BS230: 3.8355769
A231: =A226+7 -> 45602 | B231: =MONTH(A231) -> 11 | C231: =YEAR(A231) -> 2024 | D231: =C231*100+B231 -> 202411 | E231: =IF(B231<4,1,IF(B231<7,2,IF(B231<10,3,4))) -> 4 | F231: =C231*100+E231 -> 202404 | G231: 20241106 | H231: 5

Sheet HAVERM
B1: 202001 !M | C1: R112RD@INTDAILY
B2: .DESC | C2: United Kingdom: Official Bank Rate (%)
B3: .T1 | C3: Jan-1953 <- 01-Jan-1953
B4: .TN | C4: Oct-2024 <- 07-Nov-2024
B5: .LSOURCE | C5: Bank of England
B6: .DTLM | C6: Nov-07-2024 12:05
A7: 43831 | B7: 202001 | C7: 0.75
A8: 43862 | B8: 202002 | C8: 0.75
A9: 43891 | B9: 202003 | C9: 0.34772727
A10: 43922 | B10: 202004 | C10: 0.1
A11: 43952 | B11: 202005 | C11: 0.1
A12: 43983 | B12: 202006 | C12: 0.1
A13: 44013 | B13: 202007 | C13: 0.1
A14: 44044 | B14: 202008 | C14: 0.1
A15: 44075 | B15: 202009 | C15: 0.1
A16: 44105 | B16: 202010 | C16: 0.1
A17: 44136 | B17: 202011 | C17: 0.1
A18: 44166 | B18: 202012 | C18: 0.1
... A64: 45566 | B64: 202410 | C64: 5

Sheet Haver Q
B3: November meeting | F3: August meeting
A4: 20191 !Q | B4: UNPD@UK | C4: UNPM@UK | D4: yryr%(D7BT@UK) | F4: UNPD243@UK | G4: UNPM243@UK
A5: .DESC | B5: UK: BoE CPI Projections Based on Expected Interest Rate: Mode (Y/Y % Chg) | C5: UK: BoE CPI Projections Based on Expected Interest Rate: Median (Y/Y % Chg) | D5: UK: Consumer Price Index: All Items (NSA, 2015=100) % Change - Year to Year | F5: UK: BoE CPI Projections Based on Exp Interest Rate: Mode [Q3-24] (Y/Y % Chg) | G5: UK: BoE CPI Proj Based on Expected Interest Rate: Median [Q3-24] (Y/Y % Chg)
A6: .T1 | B6: Q4-2024 | C6: Q4-2024 | D6: Q1-1988 <- Jan-1988 | F6: Q3-2024 | G6: Q3-2024
A7: .TN | B7: Q4-2027 | C7: Q4-2027 | D7: Q3-2024 <- Sep-2024 | F7: Q3-2027 | G7: Q3-2027
A8: .LSOURCE | B8: Bank of England | C8: Bank of England | D8: Office for National Statistics | F8: Discontinued | G8: Discontinued
A9: .DTLM | B9: Nov-07-2024 12:04 | C9: Nov-07-2024 12:04 | D9: Oct-16-2024 07:06 | F9: Aug-01-2024 13:36 | G9: Aug-01-2024 13:36 | J9: Date | K9: 45597 | L9: 45505 | M9: 2% line
A10: 20191 | B10: #N/A | C10: #N/A | D10: 0.018453707 | F10: #N/A | G10: #N/A | J10: =LEFT(A10,4) -> 2019 | K10: =NA() -> #N/A | L10: =D10*100 -> 1.8453707 | M10: 2
A11: 20192 | B11: #N/A | C11: #N/A | D11: 0.020189274 | F11: #N/A | G11: #N/A | J11: =LEFT(A11,4) -> 2019 | K11: =NA() -> #N/A | L11: =D11*100 -> 2.0189274 | M11: 2
A12: 20193 | B12: #N/A | C12: #N/A | D12: 0.018501098 | F12: #N/A | G12: #N/A | J12: =LEFT(A12,4) -> 2019 | K12: =NA() -> #N/A | L12: =D12*100 -> 1.8501098 | M12: 2
A13: 20194 | B13: #N/A | C13: #N/A | D13: 0.014027431 | F13: #N/A | G13: #N/A | J13: =LEFT(A13,4) -> 2019 | K13: =NA() -> #N/A | L13: =D13*100 -> 1.4027431 | M13: 2
A14: 20201 | B14: #N/A | C14: #N/A | D14: 0.016557326 | F14: #N/A | G14: #N/A | J14: =LEFT(A14,4) -> 2020 | K14: =NA() -> #N/A | L14: =D14*100 -> 1.6557326 | M14: 2
A15: 20202 | B15: #N/A | C15: #N/A | D15: 0.0068027211 | F15: #N/A | G15: #N/A | J15: =LEFT(A15,4) -> 2020 | K15: =NA() -> #N/A | L15: =D15*100 -> 0.68027211 | M15: 2
A16: 20203 | B16: #N/A | C16: #N/A | D16: 0.0061576355 | F16: #N/A | G16: #N/A | J16: =LEFT(A16,4) -> 2020 | K16: =NA() -> #N/A | L16: =D16*100 -> 0.61576355 | M16: 2
A17: 20204 | B17: #N/A | C17: #N/A | D17: 0.0058407624 | F17: #N/A | G17: #N/A | J17: =LEFT(A17,4) -> 2020 | K17: =NA() -> #N/A | L17: =D17*100 -> 0.58407624 | M17: 2
A18: 20211 | B18: #N/A | C18: #N/A | D18: 0.0064535956 | F18: #N/A | G18: #N/A | J18: =LEFT(A18,4) -> 2021 | K18: =NA() -> #N/A | L18: =D18*100 -> 0.64535956 | M18: 2
A19: 20212 | B19: #N/A | C19: #N/A | D19: 0.02027027 | F19: #N/A | G19: #N/A | J19: =LEFT(A19,4) -> 2021 | K19: =NA() -> #N/A | L19: =D19*100 -> 2.027027 | M19: 2
A20: 20213 | B20: #N/A | C20: #N/A | D20: 0.02753978 | F20: #N/A | G20: #N/A | J20: =LEFT(A20,4) -> 2021 | K20: =NA() -> #N/A | L20: =D20*100 -> 2.753978 | M20: 2
A21: 20214 | B21: #N/A | C21: #N/A | D21: 0.048899756 | F21: #N/A | G21: #N/A | J21: =LEFT(A21,4) -> 2021 | K21: =NA() -> #N/A | L21: =D21*100 -> 4.8899756 | M21: 2
... A30: 20241 | B30: #N/A | C30: #N/A | D30: 0.035490605 | F30: #N/A | G30: #N/A | J30: =LEFT(A30,4) -> 2024 | K30: =NA() -> #N/A | L30: =D30*100 -> 3.5490605 | M30: 2
A31: 20242 | B31: #N/A | C31: #N/A | D31: 0.02110885 | F31: #N/A | G31: #N/A | J31: =LEFT(A31,4) -> 2024 | K31: =D31*100 -> 2.110885 | L31: =D31*100 -> 2.110885 | M31: 2
A32: 20243 | B32: #N/A | C32: #N/A | D32: 0.020547945 | F32: 2.3 | G32: 2.3 | J32: =LEFT(A32,4) -> 2024 | K32: =D32*100 -> 2.0547945 | L32: =F32 -> 2.3 | M32: 2
A33: 20244 | B33: 2.4 | C33: 2.4 | F33: 2.7 | G33: 2.7 | J33: =LEFT(A33,4) -> 2024 | K33: =B33 -> 2.4 | L33: =F33 -> 2.7 | M33: 2
A34: 20251 | B34: 2.4 | C34: 2.4 | F34: 2.7 | G34: 2.7 | J34: =LEFT(A34,4) -> 2025 | K34: =B34 -> 2.4 | L34: =F34 -> 2.7 | M34: 2
A35: 20252 | B35: 2.6 | C35: 2.6 | F35: 2.6 | G35: 2.7 | J35: =LEFT(A35,4) -> 2025 | K35: =B35 -> 2.6 | L35: =F35 -> 2.6 | M35: 2
A36: 20253 | B36: 2.8 | C36: 2.8 | F36: 2.4 | G36: 2.5 | J36: =LEFT(A36,4) -> 2025 | K36: =B36 -> 2.8 | L36: =F36 -> 2.4 | M36: 2
A37: 20254 | B37: 2.7 | C37: 2.7 | F37: 2.2 | G37: 2.3 | J37: =LEFT(A37,4) -> 2025 | K37: =B37 -> 2.7 | L37: =F37 -> 2.2 | M37: 2
A38: 20261 | B38: 2.6 | C38: 2.6 | F38: 2 | G38: 2.1 | J38: =LEFT(A38,4) -> 2026 | K38: =B38 -> 2.6 | L38: =F38 -> 2 | M38: 2
A39: 20262 | B39: 2.4 | C39: 2.4 | F39: 1.7 | G39: 1.9 | J39: =LEFT(A39,4) -> 2026 | K39: =B39 -> 2.4 | L39: =F39 -> 1.7 | M39: 2
A40: 20263 | B40: 2.3 | C40: 2.3 | F40: 1.7 | G40: 1.9 | J40: =LEFT(A40,4) -> 2026 | K40: =B40 -> 2.3 | L40: =F40 -> 1.7 | M40: 2
A41: 20264 | B41: 2.2 | C41: 2.2 | F41: 1.6 | G41: 1.8 | J41: =LEFT(A41,4) -> 2026 | K41: =B41 -> 2.2 | L41: =F41 -> 1.6 | M41: 2
A42: 20271 | B42: 2.1 | C42: 2.1 | F42: 1.5 | G42: 1.7 | J42: =LEFT(A42,4) -> 2027 | K42: =B42 -> 2.1 | L42: =F42 -> 1.5 | M42: 2
A43: 20272 | B43: 1.9 | C43: 1.9 | F43: 1.5 | G43: 1.7 | J43: =LEFT(A43,4) -> 2027 | K43: =B43 -> 1.9 | L43: =F43 -> 1.5 | M43: 2
A44: 20273 | B44: 1.9 | C44: 1.9 | F44: 1.5 | G44: 1.8 | J44: =LEFT(A44,4) -> 2027 | K44: =B44 -> 1.9 | L44: =F44 -> 1.5 | M44: 2
A45: 20274 | B45: 1.8 | C45: 1.8
