Workbook

Sheet Chart Data
C1: Levels | H1: Diff
C2: Public sector net debt | D2: Public sector net debt (ex BoE) | E2: Public sector net financial liabilities | F2: Public sector net worth (inverted) | H2: Public sector net debt | I2: Public sector net debt (ex BoE) | J2: Public sector net financial liabilities | K2: Public sector net worth (inverted)
A3: ='Aggregates (per cent of GDP)'!B57 -> 2000-01 | B3: =LEFT(A3,4) -> 2000 | C3: ='Aggregates (per cent of GDP)'!X57 -> 28.279102 | D3: ='Aggregates (per cent of GDP)'!R57 -> 28.38449 | E3: ='Aggregates (per cent of GDP)'!Y57 -> 26.9 | F3: ='Aggregates (per cent of GDP)'!Z57 -> 32.412418
A4: ='Aggregates (per cent of GDP)'!B58 -> 2001-02 | B4: =LEFT(A4,4) -> 2001 | C4: ='Aggregates (per cent of GDP)'!X58 -> 28.112245 | D4: ='Aggregates (per cent of GDP)'!R58 -> 28.214286 | E4: ='Aggregates (per cent of GDP)'!Y58 -> 28.4 | F4: ='Aggregates (per cent of GDP)'!Z58 -> 34.163435 | H4: =C4-C3 -> -0.16685755 | I4: =D4-D3 -> -0.17020469 | J4: =E4-E3 -> 1.5 | K4: =F4-F3 -> 1.7510172
A5: ='Aggregates (per cent of GDP)'!B59 -> 2002-03 | B5: =LEFT(A5,4) -> 2002 | C5: ='Aggregates (per cent of GDP)'!X59 -> 29.796493 | D5: ='Aggregates (per cent of GDP)'!R59 -> 29.885269 | E5: ='Aggregates (per cent of GDP)'!Y59 -> 31.3 | F5: ='Aggregates (per cent of GDP)'!Z59 -> 36.648476 | H5: =C5-C4 -> 1.684248 | I5: =D5-D4 -> 1.6709833 | J5: =E5-E4 -> 2.9 | K5: =F5-F4 -> 2.4850403
A6: ='Aggregates (per cent of GDP)'!B60 -> 2003-04 | B6: =LEFT(A6,4) -> 2003 | C6: ='Aggregates (per cent of GDP)'!X60 -> 30.93456 | D6: ='Aggregates (per cent of GDP)'!R60 -> 31.041627 | E6: ='Aggregates (per cent of GDP)'!Y60 -> 31.3 | F6: ='Aggregates (per cent of GDP)'!Z60 -> 37.496587 | H6: =C6-C5 -> 1.1380674 | I6: =D6-D5 -> 1.1563577 | J6: =E6-E5 -> 0 | K6: =F6-F5 -> 0.84811162
A7: ='Aggregates (per cent of GDP)'!B61 -> 2004-05 | B7: =LEFT(A7,4) -> 2004 | C7: ='Aggregates (per cent of GDP)'!X61 -> 33.463198 | D7: ='Aggregates (per cent of GDP)'!R61 -> 33.572104 | E7: ='Aggregates (per cent of GDP)'!Y61 -> 33.4 | F7: ='Aggregates (per cent of GDP)'!Z61 -> 37.345263 | H7: =C7-C6 -> 2.5286375 | I7: =D7-D6 -> 2.5304771 | J7: =E7-E6 -> 2.1 | K7: =F7-F6 -> -0.1513246
A8: ='Aggregates (per cent of GDP)'!B62 -> 2005-06 | B8: =LEFT(A8,4) -> 2005 | C8: ='Aggregates (per cent of GDP)'!X62 -> 34.311233 | D8: ='Aggregates (per cent of GDP)'!R62 -> 34.462384 | E8: ='Aggregates (per cent of GDP)'!Y62 -> 32.4 | F8: ='Aggregates (per cent of GDP)'!Z62 -> 34.945861 | H8: =C8-C7 -> 0.84803551 | I8: =D8-D7 -> 0.89028027 | J8: =E8-E7 -> -1 | K8: =F8-F7 -> -2.3994021
A9: ='Aggregates (per cent of GDP)'!B63 -> 2006-07 | B9: =LEFT(A9,4) -> 2006 | C9: ='Aggregates (per cent of GDP)'!X63 -> 35.122259 | D9: ='Aggregates (per cent of GDP)'!R63 -> 35.253508 | E9: ='Aggregates (per cent of GDP)'!Y63 -> 32.4 | F9: ='Aggregates (per cent of GDP)'!Z63 -> 35.138599 | H9: =C9-C8 -> 0.81102528 | I9: =D9-D8 -> 0.79112357 | J9: =E9-E8 -> 0 | K9: =F9-F8 -> 0.19273852
A10: ='Aggregates (per cent of GDP)'!B64 -> 2007-08 | B10: =LEFT(A10,4) -> 2007 | C10: ='Aggregates (per cent of GDP)'!X64 -> 35.619527 | D10: ='Aggregates (per cent of GDP)'!R64 -> 35.751404 | E10: ='Aggregates (per cent of GDP)'!Y64 -> 34.2 | F10: ='Aggregates (per cent of GDP)'!Z64 -> 37.433221 | H10: =C10-C9 -> 0.49726815 | I10: =D10-D9 -> 0.49789671 | J10: =E10-E9 -> 1.8 | K10: =F10-F9 -> 2.2946222
A11: ='Aggregates (per cent of GDP)'!B65 -> 2008-09 | B11: =LEFT(A11,4) -> 2008 | C11: ='Aggregates (per cent of GDP)'!X65 -> 50.601601 | D11: ='Aggregates (per cent of GDP)'!R65 -> 50.633741 | E11: ='Aggregates (per cent of GDP)'!Y65 -> 47.5 | F11: ='Aggregates (per cent of GDP)'!Z65 -> 46.925464 | H11: =C11-C10 -> 14.982074 | I11: =D11-D10 -> 14.882337 | J11: =E11-E10 -> 13.3 | K11: =F11-F10 -> 9.492243
A12: ='Aggregates (per cent of GDP)'!B66 -> 2009-10 | B12: =LEFT(A12,4) -> 2009 | C12: ='Aggregates (per cent of GDP)'!X66 -> 64.719805 | D12: ='Aggregates (per cent of GDP)'!R66 -> 63.932765 | E12: ='Aggregates (per cent of GDP)'!Y66 -> 54.6 | F12: ='Aggregates (per cent of GDP)'!Z66 -> 54.074313 | H12: =C12-C11 -> 14.118204 | I12: =D12-D11 -> 13.299024 | J12: =E12-E11 -> 7.1 | K12: =F12-F11 -> 7.1488487
A13: ='Aggregates (per cent of GDP)'!B67 -> 2010-11 | B13: =LEFT(A13,4) -> 2010 | C13: ='Aggregates (per cent of GDP)'!X67 -> 70.872526 | D13: ='Aggregates (per cent of GDP)'!R67 -> 70.593572 | E13: ='Aggregates (per cent of GDP)'!Y67 -> 58.9 | F13: ='Aggregates (per cent of GDP)'!Z67 -> 49.525323 | H13: =C13-C12 -> 6.1527213 | I13: =D13-D12 -> 6.6608064 | J13: =E13-E12 -> 4.3 | K13: =F13-F12 -> -4.5489896
A14: ='Aggregates (per cent of GDP)'!B68 -> 2011-12 | B14: =LEFT(A14,4) -> 2011 | C14: ='Aggregates (per cent of GDP)'!X68 -> 74.265559 | D14: ='Aggregates (per cent of GDP)'!R68 -> 74.583537 | E14: ='Aggregates (per cent of GDP)'!Y68 -> 65 | F14: ='Aggregates (per cent of GDP)'!Z68 -> 54.641597 | H14: =C14-C13 -> 3.393033 | I14: =D14-D13 -> 3.9899652 | J14: =E14-E13 -> 6.1 | K14: =F14-F13 -> 5.1162742
A15: ='Aggregates (per cent of GDP)'!B69 -> 2012-13 | B15: =LEFT(A15,4) -> 2012 | C15: ='Aggregates (per cent of GDP)'!X69 -> 77.471554 | D15: ='Aggregates (per cent of GDP)'!R69 -> 76.201342 | E15: ='Aggregates (per cent of GDP)'!Y69 -> 69.7 | F15: ='Aggregates (per cent of GDP)'!Z69 -> 58.717052 | H15: =C15-C14 -> 3.2059947 | I15: =D15-D14 -> 1.6178051 | J15: =E15-E14 -> 4.7 | K15: =F15-F14 -> 4.075455
... A31: ='Aggregates (per cent of GDP)'!B85 -> 2028-29 | B31: =LEFT(A31,4) -> 2028 | C31: ='Aggregates (per cent of GDP)'!X85 -> 94.29872 | D31: ='Aggregates (per cent of GDP)'!R85 -> 92.918595 | E31: ='Aggregates (per cent of GDP)'!Y85 -> 78.712157 | F31: ='Aggregates (per cent of GDP)'!Z85 -> 63.915277 | H31: =C31-C30 -> -0.76290538 | I31: =D31-D30 -> -0.27406689 | J31: =E31-E30 -> -1.8983327 | K31: =F31-F30 -> -2.0462828
A35: 23-24 | C35: 97.6 | D35: 88.8 | E35: 82.9 | F35: 69.5
A36: 24-25 | C36: 98.8 | D36: 91.7 | E36: 83.6 | F36: 70.2
A37: 25-26 | C37: 96.4 | D37: 92.8 | E37: 83.2 | F37: 69.5
A38: 26-27 | C38: 95.5 | D38: 93.2 | E38: 82.1 | F38: 67.9
A39: 27-28 | C39: 95.1 | D39: 93.2 | E39: 80.6 | F39: 66
A40: 28-29 | C40: 94.3 | D40: 92.9 | E40: 78.7 | F40: 63.9

Sheet Aggregates (per cent of GDP)
C1: Per cent of GDP1
C3: Receipts and expenditure | K3: Deficit | Q3: Fiscal targets | T3: Financing | X3: Other Debt and Deficit measures | AE3: Economic indicators
C4: Public sector current receipts | D4: Total managed expenditure | E4: Public sector current expenditure | F4: Public sector net investment | G4: Depreciation | H4: Public sector gross investment | I4: National account taxes | K4: Cyclically-adjusted current budget deficit | L4: Current budget deficit | M4: Primary balance | N4: Cyclically-adjusted primary balance | O4: Cyclically-adjusted net borrowing | Q4: Public sector net borrowing | R4: Public sector net debt (ex BOE)2 | T4: Central government net cash requirement | U4: Public sector net cash requirement | V4: Central government debt interest, net of APF | X4: Public sector net debt2 | Y4: Public sector net financial liabilities | Z4: Public sector net worth (inverted) | AA4: General government net borrowing | AB4: Cyclically-adjusted general government net borrowing | AC4: General Government Gross Debt | AE4: Nominal GDP (£ billion) | AF4: Nominal GDP, centred end-March (£ billion) | AG4: Output gap (per cent of GDP) | BS4: Forecast
B5: 1948 | C5: 42.940919 | D5: 38.599562 | E5: 33.234136 | F5: 2.6345733 | G5: 2.7308534 | H5: 5.3654267 | I5: 37.207877 | K5: - | L5: -6.97593 | M5: 7.6936543 | N5: - | O5: - | Q5: -4.3413567 | R5: - | T5: -5.9256018 | U5: -4.3413567 | V5: 4.5514223 | X5: - | AA5: -3.7986871 | AB5: - | AC5: - | AE5: 11.425 | AF5: - | AG5: -
B6: 1949 | C6: 43.298545 | D6: 38.474813 | E6: 32.780015 | F6: 2.9912072 | G6: 2.7035911 | H6: 5.6947983 | I6: 36.929904 | K6: - | L6: -7.8149396 | M6: 7.8724628 | N6: - | O6: - | Q6: -4.8237324 | R6: - | T6: -6.5247761 | U6: -4.8237324 | V6: 4.2649355 | X6: - | AA6: -4.2320651 | AB6: - | AC6: - | AE6: 12.169 | AF6: - | AG6: -
B7: 1950 | C7: 42.841444 | D7: 39.183673 | E7: 32.629513 | F7: 3.7598116 | G7: 2.7943485 | H7: 6.5541601 | I7: 36.075353 | K7: - | L7: -7.4175824 | M7: 6.4678179 | N7: - | O7: - | Q7: -3.6577708 | R7: - | T7: -5.8477237 | U7: -3.6577708 | V7: 4.1679749 | X7: - | AA7: -3.2731554 | AB7: - | AC7: - | AE7: 12.74 | AF7: - | AG7: -
B8: 1951 | C8: 41.131231 | D8: 40.648815 | E8: 32.300916 | F8: 5.4394183 | G8: 2.9084807 | H8: 8.347899 | I8: 34.782913 | K8: - | L8: -5.9218346 | M8: 3.4118716 | N8: - | O8: - | Q8: -0.48241628 | R8: - | T8: -2.6847515 | U8: -0.48241628 | V8: 4.0481018 | X8: - | AA8: -0.0069915402 | AB8: - | AC8: - | AE8: 14.303 | AF8: - | AG8: -
B9: 1952 | C9: 39.926622 | D9: 41.271885 | E9: 32.537333 | F9: 5.7736869 | G9: 2.9608651 | H9: 8.734552 | I9: 33.953399 | K9: - | L9: -4.4284243 | M9: 1.911689 | N9: - | O9: - | Q9: 1.3452626 | R9: - | T9: -1.930999 | U9: 1.3452626 | V9: 4.0808445 | X9: - | AA9: 0.99124614 | AB9: - | AC9: - | AE9: 15.536 | AF9: - | AG9: -
B10: 1953 | C10: 37.998202 | D10: 40.503446 | E10: 31.603236 | F10: 6.0593347 | G10: 2.840875 | H10: 8.9002098 | I10: 31.705124 | K10: - | L10: -3.5540905 | M10: 0.45549895 | N10: - | O10: - | Q10: 2.5052442 | R10: - | T10: -0.94695835 | U10: 2.5052442 | V10: 3.9376686 | X10: - | AA10: 1.7620617 | AB10: - | AC10: - | AE10: 16.685 | AF10: - | AG10: -
B11: 1954 | C11: 37.46378 | D11: 38.923925 | E11: 31.123232 | F11: 4.965627 | G11: 2.8350662 | H11: 7.8006931 | I11: 30.913016 | K11: - | L11: -3.5054826 | M11: 1.0794841 | N11: - | O11: - | Q11: 1.4601443 | R11: - | T11: -1.7442191 | U11: 1.4601443 | V11: 3.727061 | X11: - | AA11: 0.64200898 | AB11: - | AC11: - | AE11: 17.601 | AF11: - | AG11: -
B12: 1955-56 | C12: 35.966077 | D12: 35.771942 | E12: 28.665577 | F12: 4.3118422 | G12: 2.7945233 | H12: 7.1063656 | I12: 29.64647 | K12: - | L12: -4.5059773 | M12: 2.7536528 | N12: - | O12: - | Q12: -0.19413508 | R12: - | T12: -2.8405027 | U12: -0.19413508 | V12: 3.7907428 | X12: - | AA12: -0.55175232 | AB12: - | AC12: - | AE12: 19.574 | AF12: - | AG12: -
B13: 1956-57 | C13: 35.573197 | D13: 35.960684 | E13: 28.886684 | F13: 4.2481807 | G13: 2.8258199 | H13: 7.0740006 | I13: 29.250543 | K13: - | L13: -3.8606937 | M13: 1.8476515 | N13: - | O13: - | Q13: 0.38748701 | R13: - | T13: -1.7956715 | U13: 0.38748701 | V13: 3.4543049 | X13: - | AA13: 0.15121444 | AB13: - | AC13: - | AE13: 21.162 | AF13: 21.81 | AG13: -
B14: 1957-58 | C14: 35.168155 | D14: 35.194811 | E14: 28.379759 | F14: 3.9628593 | G14: 2.8521925 | H14: 6.8150518 | I14: 28.917322 | K14: - | L14: -3.9362033 | M14: 2.2257764 | N14: - | O14: - | Q14: 0.026656004 | R14: - | T14: -2.0791683 | U14: 0.026656004 | V14: 3.4164112 | X14: - | AA14: -0.4353814 | AB14: - | AC14: - | AE14: 22.509 | AF14: 23.004 | AG14: -
B15: 1958-59 | C15: 35.650311 | D15: 35.954575 | E15: 28.995072 | F15: 4.0754232 | G15: 2.8840797 | H15: 6.9595029 | I15: 29.535033 | K15: - | L15: -3.7711592 | M15: 2.3398329 | N15: - | O15: - | Q15: 0.30426398 | R15: - | T15: -2.2284123 | U15: 0.30426398 | V15: 3.3983287 | X15: - | AA15: -0.72851939 | AB15: - | AC15: - | AE15: 23.335 | AF15: 23.957 | AG15: -
B16: 1959-60 | C16: 33.658988 | D16: 35.946609 | E16: 29.075705 | F16: 4.1169139 | G16: 2.7539903 | H16: 6.8709042 | I16: 28.432437 | K16: - | L16: -1.8292928 | M16: 1.4594138 | N16: - | O16: - | Q16: 2.2876211 | R16: - | T16: -1.1337595 | U16: 2.2876211 | V16: 3.2927271 | X16: - | AA16: 0.22916415 | AB16: - | AC16: - | AE16: 24.873 | AF16: 25.789 | AG16: -
B17: 1960-61 | C17: 33.458463 | D17: 35.943541 | E17: 29.1565 | F17: 4.0016517 | G17: 2.7853898 | H17: 6.7870416 | I17: 27.887683 | K17: - | L17: -1.5165734 | M17: 1.3776793 | N17: - | O17: - | Q17: 2.4850783 | R17: - | T17: -0.79207177 | U17: 2.4850783 | V17: 3.3297046 | X17: - | AA17: 0.6306543 | AB17: - | AC17: - | AE17: 26.639 | AF17: 27.583 | AG17: -
B18: 1961-62 | C18: 35.464269 | D18: 37.631925 | E18: 30.155289 | F18: 4.4028286 | G18: 3.0738069 | H18: 7.4766355 | I18: 29.849686 | K18: - | L18: -2.2351729 | M18: 1.8051953 | N18: - | O18: - | Q18: 2.1676557 | R18: - | T18: -1.670161 | U18: 2.1676557 | V18: 3.3723038 | X18: - | AA18: 0.1670161 | AB18: - | AC18: - | AE18: 28.141 | AF18: 28.843 | AG18: -
B19: 1962-63 | C19: 35.480475 | D19: 37.307301 | E19: 29.908319 | F19: 4.2716469 | G19: 3.1273345 | H19: 7.3989813 | I19: 29.646859 | K19: - | L19: -2.4448217 | M19: 1.8675722 | N19: - | O19: - | Q19: 1.8268251 | R19: - | T19: -1.3039049 | U19: 2.1935484 | V19: 3.1748727 | X19: - | AA19: 0.22750424 | AB19: - | AC19: - | AE19: 29.45 | AF19: 30.383 | AG19: -
B20: 1963-64 | C20: 34.635506 | D20: 37.339056 | E20: 28.664516 | F20: 5.5355409 | G20: 3.1389994 | H20: 8.6745403 | I20: 28.695843 | K20: - | L20: -2.8319915 | M20: 0.90536011 | N20: - | O20: - | Q20: 2.7035494 | R20: - | T20: 0.94921838 | U20: 3.0982739 | V20: 3.0826102 | X20: - | AA20: 2.4216033 | AB20: - | AC20: - | AE20: 31.921 | AF20: 33.341 | AG20: -
B21: 1964-65 | C21: 35.165686 | D21: 37.033424 | E21: 27.898436 | F21: 6.0134844 | G21: 3.1215034 | H21: 9.1349878 | I21: 29.083345 | K21: - | L21: -4.1457467 | M21: 1.5464065 | N21: - | O21: - | Q21: 1.8677378 | R21: - | T21: 0.9353034 | U21: 2.6222924 | V21: 2.8288624 | X21: - | AA21: 0.088939894 | AB21: - | AC21: - | AE21: 34.855 | AF21: 36.162 | AG21: -
B22: 1965-66 | C22: 36.961106 | D22: 38.485358 | E22: 29.273111 | F22: 6.0089159 | G22: 3.2033315 | H22: 9.2122474 | I22: 30.693254 | K22: - | L22: -4.4846641 | M22: 1.7671712 | N22: - | O22: - | Q22: 1.5242519 | R22: - | T22: 1.2519687 | U22: 2.4612263 | V22: 2.7068151 | X22: - | AA22: 1.2199354 | AB22: - | AC22: - | AE22: 37.461 | AF22: 38.754 | AG22: -
B23: 1966-67 | C23: 37.640492 | D23: 40.036046 | E23: 29.933165 | F23: 6.7511077 | G23: 3.3517735 | H23: 10.102881 | I23: 31.392525 | K23: - | L23: -4.3555533 | M23: 0.9512128 | N23: - | O23: - | Q23: 2.3955543 | R23: - | T23: 1.8598713 | U23: 2.9187214 | V23: 2.7910586 | X23: - | AA23: 0.08010213 | AB23: - | AC23: - | AE23: 39.949 | AF23: 41.146 | AG23: -
B24: 1967-68 | C24: 39.090439 | D24: 42.941841 | E24: 31.571146 | F24: 7.9663091 | G24: 3.4043855 | H24: 11.370695 | I24: 32.611048 | K24: - | L24: -4.1149068 | M24: -0.18351214 | N24: - | O24: - | Q24: 3.8514022 | R24: - | T24: 3.2326369 | U24: 4.7548466 | V24: 2.879729 | X24: - | AA24: 1.4845662 | AB24: - | AC24: - | AE24: 42.504 | AF24: 44.387 | AG24: -
... B28: 1971-72 | C28: 38.373984 | D28: 39.355788 | E28: 30.189702 | F28: 5.3735966 | G28: 3.7924894 | H28: 9.1660859 | I28: 32.068138 | K28: - | L28: -4.3917925 | M28: 1.9759969 | N28: - | O28: - | Q28: 0.9818041 | R28: - | T28: 0.75571041 | U28: 1.3162989 | V28: 2.3910182 | X28: - | AA28: -0.63027487 | AB28: - | AC28: - | AE28: 64.575 | AF28: 68.129 | AG28: -
B29: 1972-73 | C29: 35.879608 | D29: 38.467366 | E29: 29.80859 | F29: 4.915793 | G29: 3.7429828 | H29: 8.6587758 | I29: 29.831586 | K29: - | L29: -2.3280352 | M29: 0.14879946 | N29: - | O29: - | Q29: 2.5877579 | R29: - | T29: 2.5809943 | U29: 3.312817 | V29: 2.3347988 | X29: - | AA29: 1.9655056 | AB29: - | AC29: - | AE29: 73.925 | AF29: 79.218 | AG29: 2.558748
B30: 1973-74 | C30: 36.176453 | D30: 40.259489 | E30: 30.998733 | F30: 5.2441011 | G30: 4.0166556 | H30: 9.2607567 | I30: 29.796633 | K30: - | L30: -1.1610645 | M30: -1.0512341 | N30: - | O30: - | Q30: 4.0830366 | R30: - | T30: 2.5767908 | U30: 5.2754813 | V30: 2.4343733 | X30: - | AA30: 3.6618188 | AB30: - | AC30: - | AE30: 82.855 | AF30: 88.827 | AG30: 6.5398237
B31: 1974-75 | C31: 39.012243 | D31: 44.707788 | E31: 34.771139 | F31: 5.5264712 | G31: 4.410177 | H31: 9.9366483 | I31: 32.492718 | K31: - | L31: 0.16907376 | M31: -2.296755 | N31: - | O31: - | Q31: 5.695545 | R31: - | T31: 5.1883237 | U31: 8.1348923 | V31: 2.4159215 | X31: 47.749102 | AA31: 3.4334196 | AB31: - | AC31: 54.663788 | AE31: 98.182 | AF31: 109.112 | AG31: 3.0701742
B32: 1975-76 | C32: 40.119493 | D32: 46.450796 | E32: 36.344378 | F32: 5.5608884 | G32: 4.5455298 | H32: 10.106418 | I32: 33.353745 | K32: 0.51324429 | L32: 0.77041475 | M32: -2.9972527 | N32: -2.7400822 | O32: 6.0741327 | Q32: 6.3313032 | R32: - | T32: 7.2432227 | U32: 8.5076628 | V32: 2.5727384 | X32: 49.329064 | AA32: 4.212042 | AB32: 3.9548715 | AC32: 54.316309 | AE32: 120.844 | AF32: 131.16 | AG32: -1.7424106
B33: 1976-77 | C33: 40.209182 | D33: 45.138904 | E33: 36.083251 | F33: 4.5038958 | G33: 4.5517571 | H33: 9.0556529 | I33: 32.758997 | K33: -0.23458395 | L33: 0.42582543 | M33: -1.3070377 | N33: -0.64662835 | O33: 4.2693118 | Q33: 4.9297212 | R33: - | T33: 4.1097433 | U33: 5.8038951 | V33: 2.8709784 | X33: 47.790346 | AA33: 3.6177566 | AB33: 2.9573472 | AC33: 53.485786 | AE33: 142.077 | AF33: 154.006 | AG33: -0.62385452
B34: 1977-78 | C34: 38.385912 | D34: 42.253462 | E34: 34.650813 | F34: 3.1505117 | G34: 4.4521373 | H34: 7.602649 | I34: 31.617098 | K34: 0.35804888 | L34: 0.71703793 | M34: -0.32269717 | N34: 0.036291883 | O34: 3.5085606 | Q34: 3.8675497 | R34: - | T34: 2.8163757 | U34: 3.3521975 | V34: 2.9542444 | X34: 44.320805 | AA34: 3.2203492 | AB34: 2.8613601 | AC34: 51.990969 | AE34: 166.1 | AF34: 179.374 | AG34: -0.4684363
B35: 1978-79 | C35: 36.902026 | D35: 41.417045 | E35: 34.347935 | F35: 2.725647 | G35: 4.3434637 | H35: 7.0691107 | I35: 30.376693 | K35: 2.4762578 | L35: 1.7893719 | M35: -1.0537643 | N35: -1.7406502 | O35: 5.2019048 | Q35: 4.5150189 | R35: - | T35: 4.0315453 | U35: 4.6938521 | V35: 3.0443236 | X35: 42.17963 | AA35: 3.7638154 | AB35: 4.4507013 | AC35: 50.286965 | AE35: 192.358 | AF35: 210.054 | AG35: 1.5611463
B36: 1979-80 | C36: 37.265684 | D36: 40.939929 | E36: 34.176154 | F36: 2.5263122 | G36: 4.237463 | H36: 6.7637752 | I36: 31.188949 | K36: 1.4084716 | L36: 1.1479329 | M36: -0.069649859 | N36: -0.33018859 | O36: 3.9347838 | Q36: 3.674245 | R36: - | T36: 3.4670152 | U36: 4.1802814 | V36: 3.2619351 | X36: 39.075401 | AA36: 2.6105799 | AB36: 2.8711186 | AC36: 46.217841 | AE36: 232.592 | AF36: 251.309 | AG36: -0.10338107
B37: 1980-81 | C37: 38.496101 | D37: 42.808708 | E37: 36.123177 | F37: 2.2495683 | G37: 4.4359632 | H37: 6.6855314 | I37: 32.112979 | K37: 0.63512272 | L37: 2.0630387 | M37: -0.55659806 | N37: 0.87131797 | O37: 2.884691 | Q37: 4.312607 | R37: - | T37: 4.6714614 | U37: 4.5854858 | V37: 3.4251901 | X37: 40.331584 | AA37: 3.3466907 | AB37: 1.9187747 | AC37: 47.182619 | AE37: 267.518 | AF37: 282.161 | AG37: -2.8144796
B38: 1981-82 | C38: 40.877621 | D38: 42.888946 | E38: 37.077258 | F38: 1.4644892 | G38: 4.3471993 | H38: 5.8116884 | I38: 34.023892 | K38: -1.5976101 | L38: 0.5468365 | M38: 1.9265006 | N38: 4.0709472 | O38: -0.13312094 | Q38: 2.0113257 | R38: - | T38: 2.5598385 | U38: 2.9075206 | V38: 3.7658293 | X38: 40.020458 | AA38: 2.7888326 | AB38: 0.64438601 | AC38: 44.809077 | AE38: 298.261 | AF38: 312.84 | AG38: -3.1631013
B39: 1982-83 | C39: 40.58006 | D39: 43.18871 | E39: 37.08547 | F39: 1.9352632 | G39: 4.1679773 | H39: 6.1032405 | I39: 33.721587 | K39: -1.3145188 | L39: 0.67338731 | M39: 1.0279463 | N39: 3.0158525 | O39: 0.62074437 | Q39: 2.6086505 | R39: - | T39: 3.9148081 | U39: 2.7479088 | V39: 3.6912618 | X39: 38.661072 | AA39: 2.6584293 | AB39: 0.67052311 | AC39: 43.637024 | AE39: 327.449 | AF39: 342.722 | AG39: -2.7105717
B40: 1983-84 | C40: 39.479476 | D40: 42.775553 | E40: 36.593383 | F40: 2.1867721 | G40: 3.9953974 | H40: 6.1821696 | I40: 33.041764 | K40: -0.175941 | L40: 1.1093051 | M40: 0.1622624 | N40: 1.4475085 | O40: 2.0108311 | Q40: 3.2960772 | R40: - | T40: 3.4318079 | U40: 2.7355598 | V40: 3.6934944 | X40: 38.822563 | AA40: 3.2843474 | AB40: 1.9991013 | AC40: 43.329926 | AE40: 358.062 | AF40: 369.888 | AG40: -1.4862635
B41: 1984-85 | C41: 39.215864 | D41: 42.46345 | E41: 36.742673 | F41: 1.9348203 | G41: 3.7859573 | H41: 5.7207776 | I41: 33.615041 | K41: 0.83044238 | L41: 1.3127657 | M41: 0.36789566 | N41: 0.85021901 | O41: 2.7652627 | Q41: 3.247586 | R41: - | T41: 2.6618028 | U41: 2.6579166 | V41: 3.813679 | X41: 38.690153 | AA41: 2.8646636 | AB41: 2.3823403 | AC41: 43.132398 | AE41: 385.979 | AF41: 405.788 | AG41: -0.37014129
B42: 1985-86 | C42: 38.290255 | D42: 40.422303 | E42: 35.5328 | F42: 1.494133 | G42: 3.3953706 | H42: 4.8895035 | I42: 32.704544 | K42: 0.62133587 | L42: 0.63791525 | M42: 1.3100509 | N42: 1.3266303 | O42: 2.1154688 | Q42: 2.1320482 | R42: - | T42: 2.6229338 | U42: 1.3544194 | V42: 3.9178805 | X42: 37.082085 | AA42: 2.2771899 | AB42: 2.2606105 | AC42: 42.311269 | AE42: 423.724 | AF42: 438.217 | AG42: 0.11489776
B43: 1986-87 | C43: 37.404077 | D43: 39.324184 | E43: 34.90684 | F43: 0.93303133 | G43: 3.4843129 | H43: 4.4173442 | I43: 32.509782 | K43: 1.1405711 | L43: 0.98707553 | M43: 1.357476 | N43: 1.2039805 | O43: 2.0736024 | Q43: 1.9201069 | R43: - | T43: 2.2920452 | U43: 0.81000389 | V43: 3.8138507 | X43: 34.863765 | AA43: 2.1340867 | AB43: 2.2875823 | AC43: 41.891723 | AE43: 455.183 | AF43: 481.302 | AG43: 0.26103195
... B53: 1996-97 | C53: 32.449835 | D53: 35.583539 | E53: 32.878438 | F53: 0.35742261 | G53: 2.3476783 | H53: 2.7051009 | I53: 29.674311 | K53: 2.3180661 | L53: 2.776282 | M53: -0.51116092 | N53: -0.052944941 | O53: 2.6754887 | Q53: 3.1337047 | R53: - | T53: 2.7199438 | U53: 2.4508205 | V53: 3.0326209 | X53: 36.570046 | AA53: 3.3407476 | AB53: 2.8825316 | AC53: 44.269808 | AE53: 922.997 | AF53: 948.864 | AG53: 0.0020808682
B54: 1997-98 | C54: 34.624184 | D54: 35.713034 | E54: 32.898443 | F54: 0.49808902 | G54: 2.3165027 | H54: 2.8145917 | I54: 31.205873 | K54: 1.6803614 | L54: 0.59076156 | M54: 1.5748113 | N54: 0.4852115 | O54: 2.1784504 | Q54: 1.0888506 | R54: 36.728443 | T54: 0.36726938 | U54: 0.09339817 | V54: 3.1026644 | X54: 36.647096 | AA54: 1.2231947 | AB54: 2.3127945 | AC54: 42.736971 | AE54: 964.687 | AF54: 983.434 | AG54: 2.1783673
B55: 1998-99 | C55: 35.147548 | D55: 35.174379 | E55: 32.384 | F55: 0.51215692 | G55: 2.2782221 | H55: 2.790379 | I55: 31.797292 | K55: 0.70331393 | L55: -0.48532635 | M55: 2.482273 | N55: 1.2936327 | O55: 1.2154708 | Q55: 0.026830567 | R55: 35.223023 | T55: -0.44998129 | U55: -0.76115647 | V55: 2.9318583 | X55: 35.135933 | AA55: 0.07583843 | AB55: 1.2644787 | AC55: 41.09938 | AE55: 1010.042 | AF55: 1033.415 | AG55: 1.5059337
B56: 1999-00 | C56: 35.812882 | D56: 34.769377 | E56: 32.0188 | F56: 0.46424194 | G56: 2.2863348 | H56: 2.7505768 | I56: 32.542585 | K56: -0.33756958 | L56: -1.5077467 | M56: 3.1602854 | N56: 1.9901083 | O56: 0.12667235 | Q56: -1.0435047 | R56: 32.588386 | T56: -0.86355427 | U56: -0.82792332 | V56: 2.463828 | X56: 32.487237 | Y56: 27.6 | Z56: 32.338916 | AA56: -0.96496542 | AB56: 0.20521166 | AC56: 38.591718 | AE56: 1058.069 | AF56: 1087.504 | AG56: 1.7379807
B57: 2000-01 | C57: 36.513436 | D57: 35.073508 | E57: 32.409237 | F57: 0.40470502 | G57: 2.2595657 | H57: 2.6642707 | I57: 33.058596 | K57: -0.92840919 | L57: -1.8446331 | M57: 3.3631517 | N57: 2.4469277 | O57: -0.52370417 | Q57: -1.4399281 | R57: 28.38449 | T57: -3.191078 | U57: -3.4116876 | V57: 2.4293067 | X57: 28.279102 | Y57: 26.9 | Z57: 32.412418 | AA57: -1.3575696 | AB57: -0.44134567 | AC57: 35.739374 | AE57: 1114.639 | AF57: 1138.65 | AG57: 1.1372556
B58: 2001-02 | C58: 35.829075 | D58: 36.346099 | E58: 32.964266 | F58: 1.0969634 | G58: 2.2848703 | H58: 3.3818337 | I58: 32.500783 | K58: -0.1262734 | L58: -0.57993879 | M58: 1.1975393 | N58: 0.74387393 | O58: 0.97068997 | Q58: 0.51702458 | R58: 28.214286 | T58: 0.24046242 | U58: 0.34667895 | V58: 2.0145562 | X58: 28.112245 | Y58: 28.4 | Z58: 34.163435 | AA58: 0.44968469 | AB58: 0.90335008 | AC58: 34.507703 | AE58: 1152.363 | AF58: 1176 | AG58: 0.45242855
B59: 2002-03 | C59: 34.611338 | D59: 37.554928 | E59: 33.777993 | F59: 1.4448275 | G59: 2.3321068 | H59: 3.7769344 | I59: 31.448037 | K59: 1.3760055 | L59: 1.4987625 | M59: -1.2678018 | N59: -1.1450448 | O59: 2.820833 | Q59: 2.94359 | R59: 29.885269 | T59: 1.7992926 | U59: 1.9342126 | V59: 1.8177396 | X59: 29.796493 | Y59: 31.3 | Z59: 36.648476 | AA59: 2.547433 | AB59: 2.4246759 | AC59: 34.909221 | AE59: 1208.864 | AF59: 1239.072 | AG59: -0.42648546
B60: 2003-04 | C60: 35.455339 | D60: 38.931841 | E60: 35.009952 | F60: 1.6922036 | G60: 2.2296855 | H60: 3.9218891 | I60: 32.351224 | K60: 1.9350617 | L60: 1.7842985 | M60: -1.693068 | N60: -1.8438312 | O60: 3.6272653 | Q60: 3.4765021 | R60: 31.041627 | T60: 3.0953142 | U60: 3.1420689 | V60: 1.8440972 | X60: 30.93456 | Y60: 31.3 | Z60: 37.496587 | AA60: 2.9824745 | AB60: 3.1332377 | AC60: 36.749539 | AE60: 1272.601 | AF60: 1307.599 | AG60: 0.47212062
B61: 2004-05 | C61: 36.029052 | D61: 39.938368 | E61: 35.66881 | F61: 2.0459664 | G61: 2.2235915 | H61: 4.2695579 | I61: 32.944456 | K61: 2.369677 | L61: 1.8633494 | M61: -2.0843376 | N61: -2.5906652 | O61: 4.4156434 | Q61: 3.9093159 | R61: 33.572104 | T61: 3.0630636 | U61: 3.1564956 | V61: 1.9482876 | X61: 33.463198 | Y61: 33.4 | Z61: 37.345263 | AA61: 3.3529709 | AB61: 3.8592985 | AC61: 39.162301 | AE61: 1342.153 | AF61: 1377.334 | AG61: 0.82380687
B62: 2005-06 | C62: 36.667637 | D62: 39.941075 | E62: 35.818592 | F62: 1.8521352 | G62: 2.2703479 | H62: 4.122483 | I62: 33.359019 | K62: 1.7745129 | L62: 1.4213028 | M62: -1.4494327 | N62: -1.8026429 | O62: 3.6266481 | Q62: 3.2734379 | R62: 34.462384 | T62: 3.0343686 | U62: 3.0343686 | V62: 1.9795307 | X62: 34.311233 | Y62: 32.4 | Z62: 34.945861 | AA62: 3.0016561 | AB62: 3.3548663 | AC62: 40.520101 | AE62: 1418.417 | AF62: 1455.5 | AG62: 0.37689762
B63: 2006-07 | C63: 37.102852 | D63: 39.926661 | E63: 35.808593 | F63: 1.8163774 | G63: 2.3016912 | H63: 4.1180686 | I63: 33.798036 | K63: 1.2786672 | L63: 1.0074314 | M63: -0.91855032 | N63: -1.1897861 | O63: 3.0950446 | Q63: 2.8238088 | R63: 35.253508 | T63: 2.5192178 | U63: 2.405711 | V63: 2.0484372 | X63: 35.122259 | Y63: 32.4 | Z63: 35.138599 | AA63: 2.6274092 | AB63: 2.8986449 | AC63: 41.582434 | AE63: 1486.255 | AF63: 1523.82 | AG63: 0.39171248
B64: 2007-08 | C64: 37.317971 | D64: 40.256172 | E64: 36.132076 | F64: 1.7924771 | G64: 2.3316188 | H64: 4.1240958 | I64: 33.774209 | K64: 1.9739223 | L64: 1.1457241 | M64: -1.1383158 | N64: -1.966514 | O64: 3.7663993 | Q64: 2.9382011 | R64: 35.751404 | T64: 2.1243155 | U64: 1.8599177 | V64: 2.1204837 | X64: 35.619527 | Y64: 34.2 | Z64: 37.433221 | AA64: 2.935455 | AB64: 3.7636531 | AC64: 42.273387 | AE64: 1565.822 | AF64: 1592.385 | AG64: 1.4997113
B65: 2008-09 | C65: 36.01665 | D65: 43.456862 | E65: 37.928993 | F65: 3.0053462 | G65: 2.5225224 | H65: 5.5278687 | I65: 32.230181 | K65: 4.1026083 | L65: 4.4348662 | M65: -5.455284 | N65: -5.1230261 | O65: 7.1079545 | Q65: 7.4402124 | R65: 50.633741 | T65: 10.349411 | U65: 10.986248 | V65: 2.1218222 | X65: 50.601601 | Y65: 47.5 | Z65: 46.925464 | AA65: 6.8355297 | AB65: 6.5032718 | AC65: 53.532422 | AE65: 1582.979 | AF65: 1555.682 | AG65: -1.2644003
B66: 2009-10 | C66: 36.120417 | D66: 46.454463 | E66: 40.769787 | F66: 3.0029004 | G66: 2.6817758 | H66: 5.6846762 | I66: 32.36024 | K66: 5.2415189 | L66: 7.3311463 | M66: -8.2908593 | N66: -6.2012319 | O66: 8.2444193 | Q66: 10.334047 | R66: 63.932765 | T66: 12.754555 | U66: 12.894887 | V66: 1.8135833 | X66: 64.719805 | Y66: 54.6 | Z66: 54.074313 | AA66: 10.083698 | AB66: 7.9940705 | AC66: 70.796415 | AE66: 1557.028 | AF66: 1588.231 | AG66: -3.6734947
B67: 2010-11 | C67: 37.010473 | D67: 45.738204 | E67: 40.703258 | F67: 2.4446147 | G67: 2.5903308 | H67: 5.0349454 | I67: 33.220319 | K67: 4.3554613 | L67: 6.2831155 | M67: -6.1156526 | N67: -4.1879984 | O67: 6.800076 | Q67: 8.7277302 | R67: 70.593572 | T67: 8.2326518 | U67: 7.7430409 | V67: 2.528039 | X67: 70.872526 | Y67: 58.9 | Z67: 49.525323 | AA67: 8.7782885 | AB67: 6.8506343 | AC67: 76.214552 | AE67: 1627.823 | AF67: 1649.017 | AG67: -2.3859106
... B76: 2019-20 | C76: 36.883523 | D76: 39.582421 | E76: 35.3443 | F76: 1.8960049 | G76: 2.3421158 | H76: 4.2381207 | I76: 33.146982 | K76: 1.1560289 | L76: 0.80289275 | M76: -1.3216699 | N76: -1.6748061 | O76: 3.0520338 | Q76: 2.6988976 | R76: 77.133323 | T76: 2.4983638 | U76: 0.7656463 | V76: 1.721401 | X76: 85.192589 | Y76: 74.5 | Z76: 67.135562 | AA76: 2.9442519 | AB76: 3.2973881 | AC76: 84.601398 | AE76: 2244.509 | AF76: 2130.467 | AG76: 0.55448633
B77: 2020-21 | C77: 38.006382 | D77: 53.103232 | E77: 47.078487 | F77: 3.4519952 | G77: 2.5727501 | H77: 6.0247453 | I77: 34.084286 | K77: 11.60453 | L77: 11.644855 | M77: -14.080392 | N77: -14.040067 | O77: 15.056525 | Q77: 15.09685 | R77: 86.537211 | T77: 16.209563 | U77: 16.235077 | V77: 1.2105507 | X77: 96.486233 | Y77: 83 | Z77: 73.502872 | AA77: 15.310894 | AB77: 15.270569 | AC77: 107.6384 | AE77: 2085.084 | AF77: 2230.37 | AG77: -0.30244458 | BS77: 60
B78: 2021-22 | C78: 38.990779 | D78: 44.338377 | E78: 39.696095 | F78: 2.3021101 | G78: 2.3401724 | H78: 4.6422825 | I78: 35.237095 | K78: 3.8891334 | L78: 3.0454884 | M78: -3.182919 | N78: -4.0265639 | O78: 6.1912435 | Q78: 5.3475986 | R78: 83.186433 | T78: 5.453614 | U78: 7.3307733 | V78: 2.4384399 | X78: 96.603207 | Y78: 80.5 | Z78: 67.397726 | AA78: 5.9205223 | AB78: 6.7641672 | AC78: 100.99677 | AE78: 2361.92 | AF78: 2464.825 | AG78: 1.7841179 | BS78: 60
B79: 2022-23 | C79: 40.296242 | D79: 45.327784 | E79: 41.163567 | F79: 1.7982158 | G79: 2.3660013 | H79: 4.1642172 | I79: 36.240514 | K79: 4.1082821 | L79: 3.2333263 | M79: -1.1957295 | N79: -2.0706854 | O79: 5.9064979 | Q79: 5.0315421 | R79: 84.868663 | T79: 4.3614166 | U79: 1.2828341 | V79: 4.3687797 | X79: 95.7 | Y79: 81.4 | Z79: 69.626448 | AA79: 5.3784329 | AB79: 6.2533888 | AC79: 99.42493 | AE79: 2553.253 | AF79: 2653.394 | AG79: 1.0266046 | BS79: 60
B80: 2023-24 | C80: 40.306668 | D80: 44.729828 | E80: 39.729924 | F80: 2.6051807 | G80: 2.3947238 | H80: 4.9999044 | I80: 36.057313 | K80: 1.9153047 | L80: 1.81798 | M80: -1.4250413 | N80: -1.522366 | O80: 4.5204853 | Q80: 4.4231606 | R80: 89.3 | T80: 5.8406292 | U80: 1.1233435 | V80: 3.7556538 | X80: 98.1 | Y80: 83.2 | Z80: 71.448627 | AA80: 5.3853071 | AB80: 5.4826317 | AC80: 100.58571 | AE80: 2720.272 | AF80: 2757.1297 | AG80: -0.21599244 | BS80: 60
B81: 2024-25 | C81: 40.893017 | D81: 44.024341 | E81: 39.143595 | F81: 2.3896524 | G81: 2.4910931 | H81: 4.8807455 | I81: 36.477369 | K81: 0.31926811 | L81: 0.74167091 | M81: -0.80321854 | N81: -0.38081574 | O81: 2.7089205 | Q81: 3.1313233 | R81: 91.690627 | T81: 5.121383 | U81: 4.0636212 | V81: 3.1933992 | X81: 98.777579 | Y81: 83.564071 | Z81: 70.249244 | AA81: 3.9383121 | AB81: 3.5159093 | AC81: 102.50772 | AE81: 2785.614 | AF81: 2827.4832 | AG81: -0.75840862 | BS81: 60
B82: 2025-26 | C82: 40.83999 | D82: 43.534969 | E82: 38.941681 | F82: 2.1199635 | G82: 2.4733249 | H82: 4.5932884 | I82: 36.679998 | K82: 0.15728435 | L82: 0.5750158 | M82: -0.22541386 | N82: 0.19231759 | O82: 2.2772479 | Q82: 2.6949793 | R82: 92.763531 | T82: 3.929668 | U82: 0.89539796 | V82: 3.0917099 | X82: 96.357307 | Y82: 83.171162 | Z82: 69.481722 | AA82: 3.1211129 | AB82: 2.7033814 | AC82: 103.63285 | AE82: 2875.0616 | AF82: 2926.6497 | AG82: -0.53209946 | BS82: 60
B83: 2026-27 | C83: 40.926671 | D83: 43.226989 | E83: 38.796497 | F83: 1.9804928 | G83: 2.4499995 | H83: 4.4304923 | I83: 36.861183 | K83: 0.12373945 | L83: 0.31982559 | M83: 0.37482925 | N83: 0.57091539 | O83: 2.1042322 | Q83: 2.3003184 | R83: 93.161002 | T83: 3.2799007 | U83: 2.4729648 | V83: 3.2231029 | X83: 95.479822 | Y83: 82.127309 | Z83: 67.879921 | AA83: 2.9145201 | AB83: 2.7184339 | AC83: 103.80085 | AE83: 2984.8321 | AF83: 3040.2162 | AG83: -0.1793325
B84: 2027-28 | C84: 41.121457 | D84: 42.755398 | E84: 38.497964 | F84: 1.8204393 | G84: 2.4369946 | H84: 4.2574339 | I84: 37.029354 | K84: -0.24673504 | L84: -0.18649814 | M84: 1.1142813 | N84: 1.1745182 | O84: 1.5737042 | Q84: 1.6339411 | R84: 93.192662 | T84: 3.1352606 | U84: 3.1540234 | V84: 3.3299183 | X84: 95.061625 | Y84: 80.61049 | Z84: 65.961559 | AA84: 2.283619 | AB84: 2.2233821 | AC84: 103.52665 | AE84: 3094.4904 | AF84: 3150.5577 | AG84: -0.048740788
B85: 2028-29 | C85: 41.223728 | D85: 42.453192 | E85: 38.382664 | F85: 1.6542068 | G85: 2.4163215 | H85: 4.0705283 | I85: 37.137296 | K85: -0.4365458 | L85: -0.42474275 | M85: 1.5949869 | N85: 1.6067899 | O85: 1.217661 | Q85: 1.2294641 | R85: 92.918595 | T85: 3.0299654 | U85: 3.0235767 | V85: 3.4181321 | X85: 94.29872 | Y85: 78.712157 | Z85: 63.915277 | AA85: 1.946879 | AB85: 1.935076 | AC85: 102.9825 | AE85: 3207.4756 | AF85: 3264.2524 | AG85: -0.0041097795
B86: Notes: | C86: 1 Outturn data presented as a per cent of GDP is consistent with the latest available ONS GDP data (GDP first quarterly estimate published 15th August 2024). Calendar year GDP used for 1948-1954.
C87: 2 Debt at end March; GDP centred on end-March.
C88: Outturn fiscal data consistent with the ONS/HM Treasury Public Sector Finances Statistical Bulletin released on 21 August 2024.
C89: Forecast years from 2024-25 are consistent with the OBR Economic and fiscal outlook forecast published March 2024.
C90: A full list of sources is available in the glossary.
C91: Cyclically adjusted aggregates are OBR estimates based on internal calculations of the size of the output gap. For more information see Working paper No. 3: Cyclically-adjusting the public finances (https://obr.uk/download/working-paper-no-3-cyclically-adjusting-the-public-finances/)

Sheet T5.3
A1: Back to contents
B2: Table 5.3: Dashboard of balance sheet and fiscal affordability indicators
