Workbook
Name _DLX1.INC: HAVERA!$A$3:$BO$8
Name _DLX2.INC: HAVERD!$B$2:$L$7
Name Data: [1]sheet0!$C$2

Sheet >> CHARTS

Sheet >> DATA

Sheet Chart Data
A1: Budget policy decisions | I1: Fiscal rules | U1: Fiscal rules | AA1: Public sector net investment | AH1: OBR estimates of fiscal tightening | AM1: NICs impact | BH1: Opinion polls | BO1: Conservative RDEL plans | BU1: Government investment | CC1: Conservative DEL plans | CI1: AE debt dynamics (2024-2028) | DE1: Taxes as share of total | DH1: How could headroom be eroded | DK1: OBR GC forecasts
K2: Levels | P2: Diff | V2: Public sector net debt | W2: Public sector net debt (ex BoE) | X2: Public sector net financial liabilities | Y2: Public sector net worth | AN2: GDP | AR2: ER | AV2: ETILO | AZ2: UPILO | BD2: TP | BH2: YouGov | BI2: https://yougov.co.uk/politics/articles/50820-britons-say-public-services-are-bad-but-they-arent-willing-to-pay-more-to-fix-them | DL2: 2022=100 | DT2: Level £bn
B3: 2024-2025 | C3: 2025-2026 | D3: 2026-2027 | E3: 2027-2028 | F3: 2028-2029 | G3: 2029-2030 | K3: Public sector net debt | L3: Public sector net debt (ex BoE) | M3: Public sector net financial liabilities | N3: Public sector net worth (inverted) | P3: Public sector net debt | Q3: Public sector net debt (ex BoE) | R3: Public sector net financial liabilities | S3: Public sector net worth (inverted) | V3: Public sector net debt | W3: Public sector net debt (ex BoE) | X3: Public sector net financial liabilities | Y3: Public sector net worth (inverted) | AC3: Budget (Oct24) | AD3: Budget (Mar24) | AE3: UK average (2004-2023) | AF3: OECD average | AJ3: Budget (Oct24) | AK3: Budget (Mar24) | AN3: Baseline | AO3: Scenario | AP3: Diff | AR3: Baseline | AS3: Scenario | AT3: Diff | AV3: Baseline | AW3: Scenario | AX3: Diff | AZ3: Baseline | BA3: Scenario | BB3: Diff | BD3: Baseline | BE3: Scenario | BF3: Diff | BI3: Higher taxes and more funding for public services | BJ3: Current tax levels and public services funding remaining as it is | BK3: Lower taxes and less funding for public services | BL3: Don't know | BP3: Real PSCE in RDEL per capita | BQ3: 100 LINE | BS3: Real PSCE in RDEL per capita | BW3: 2003-2022 | CA3: 2003-2022 | CD3: Real PSGI in RDEL per capita | CE3: 100 LINE | CG3: Real PSGI in RDEL per capita | CJ3: =DataA!BK2 -> UK | CK3: =DataA!BL2 -> US | CL3: =DataA!BM2 -> Japan | CM3: =DataA!BN2 -> Canada | CN3: =DataA!BO2 -> Australia | CO3: =DataA!BP2 -> Denmark | CP3: =DataA!BQ2 -> Sweden | CQ3: =DataA!BR2 -> Switzerland | ... DC3: =DataA!CD2 -> Portugal | DF3: 2024-2025 | DI3: £bn | DL3: =DT3 -> 44621 | DM3: =DU3 -> 44866 | DN3: =DV3 -> 44986 | DO3: =DW3 -> 45231 | DP3: =DX3 -> 45352 | DQ3: =DY3 -> 45566 | DT3: 44621 | DU3: 44866 | DV3: 44986 | DW3: 45231 | DX3: 45352 | DY3: 45566
A4: Tax | B4: ='HMT - Table 5.1'!F88 -> 1160 | C4: ='HMT - Table 5.1'!G88 -> 24005 | D4: ='HMT - Table 5.1'!H88 -> 34785 | E4: ='HMT - Table 5.1'!I88 -> 39065 | F4: ='HMT - Table 5.1'!J88 -> 39725 | G4: ='HMT - Table 5.1'!K88 -> 41170 | I4: 2000-01 | J4: =LEFT(I4,4) -> 2000 | K4: {=TRANSPOSE('C6.11'!D26:AG29)} -> 28.3 | L4: 28.4 | M4: 26.955398 | N4: 32.43637 | U4: 2029-2030 | V4: =-(P33/100)*$V$7 -> 6.6405827 | W4: =-(Q33/100)*$V$7 -> -5.7796597 | X4: =-(R33/100)*$V$7 -> 15.747235 | Y4: =-(S33/100)*$V$7 -> 16.945561 | AA4: ='Aggregates (% GDP) Oct24'!B57 -> 2000-01 | AB4: =LEFT(AA4,4) -> 2000 | AC4: ='Aggregates (% GDP) Oct24'!F57 -> 0.40470502 | AD4: ='Aggregates (% GDP) Mar24'!F57 -> 0.40470502 | AE4: =AVERAGE($AD$8:$AD$27) -> 2.145275 | AH4: ='Aggregates (% GDP) Oct24'!B57 -> 2000-01 | AI4: =LEFT(AH4,4) -> 2000 | AJ4: =-('Aggregates (% GDP) Oct24'!M57-'Aggregates (% GDP) Oct24'!M56) -> -0.014492648 | AM4: 2024 | AN4: =100*((DataCY!B51/DataCY!B50)-1) -> 0.98266797 | AO4: =100*((DataCY!H51/DataCY!H50)-1) -> 0.98266797 | AP4: =AO4-AN4 -> 0 | AR4: =100*((DataCY!D51/DataCY!D50)-1) -> 4.2451725 | AS4: =100*((DataCY!J51/DataCY!J50)-1) -> 4.2451725 | AT4: =AS4-AR4 -> 0 | AV4: =DataCY!C51 -> 33138.705 | AW4: =DataCY!I51 -> 33138.705 | AX4: =AW4-AV4 -> 0 | AZ4: =DataCY!E51 -> 4.2879467 | BA4: =DataCY!K51 -> 4.2879467 | BB4: =BA4-AZ4 -> 0 | BD4: =DataFY!G51 -> 152663.25 | BE4: =DataFY!M51 -> 152663.25 | BF4: =BE4-BD4 -> 0 | BH4: All Britons | BI4: 31 | BJ4: 30 | BK4: 20 | BL4: 19 | BM4: =SUM(BI4:BL4) -> 100 | BO4: {=TRANSPOSE(OBR_MAR24_ST4.3!E4:Z4)} -> 2007-08 | BP4: =100*(BS4/$BS$20) -> 100.43541 | BQ4: 100 | BS4: {=TRANSPOSE(OBR_MAR24_ST4.3!E11:Z11)} -> 6193.1143 | BU4: 1 | BV4: =VLOOKUP($BU4,$BY$4:$CA$34,2,FALSE) -> Estonia | BW4: =VLOOKUP($BU4,$BY$4:$CA$34,3,FALSE) -> 5.3362375 | BY4: =RANK(CA4,$CA$4:$CA$34) -> 27 | BZ4: {=TRANSPOSE(HAVERA!BN1:CR2)} -> UK | CA4: 2.814318 | CC4: {=TRANSPOSE(OBR_MAR24_ST4.3!E4:Z4)} -> 2007-08 | CD4: =100*(CG4/$CG$20) -> 83.985641 | CE4: 100 | CG4: {=TRANSPOSE(OBR_MAR24_ST4.3!E17:Z17)} -> 1170.3834 | CI4: Expected effective interest rates on government debt (r) | CJ4: =AVERAGE(DataA!BK58:BK62) -> 3.9112168 | CK4: =AVERAGE(DataA!BL58:BL62) -> 3.4758633 | CL4: =AVERAGE(DataA!BM58:BM62) -> 0.78474053 | CM4: =AVERAGE(DataA!BN58:BN62) -> 3.286119 | CN4: =AVERAGE(DataA!BO58:BO62) -> 2.8132632 | CO4: =AVERAGE(DataA!BP58:BP62) -> 1.951017 | CP4: =AVERAGE(DataA!BQ58:BQ62) -> 1.4633902 | CQ4: =AVERAGE(DataA!BR58:BR62) -> 1.2019786 | ... DC4: =AVERAGE(DataA!CD58:CD62) -> 2.4149445 | DE4: Income tax | DF4: =OBR_MAR24_ST3.9!F7 -> 302.63177 | DH4: Headroom | DI4: 9.9 | DK4: 2020 | DS4: 2020 | DT4: ='[2]1.1'!D53 -> 105.648 | DU4: ='[3]1.1'!D53 -> 104.088 | DV4: ='[4]1.1'!D53 -> 104.088 | DW4: ='[5]1.1'!D53 -> 103.574 | DX4: ='[6]1.1'!D53 -> 103.574 | DY4: ='[7]1.1'!D53 -> 103.574
A5: Current spending | B5: ='HMT - Table 5.1'!F87-'Chart Data'!B6 -> -27630 | C5: ='HMT - Table 5.1'!G87-'Chart Data'!C6 -> -48190 | D5: ='HMT - Table 5.1'!H87-'Chart Data'!D6 -> -50675 | E5: ='HMT - Table 5.1'!I87-'Chart Data'!E6 -> -51825 | F5: ='HMT - Table 5.1'!J87-'Chart Data'!F6 -> -52805 | G5: ='HMT - Table 5.1'!K87-'Chart Data'!G6 -> -51035 | I5: 2001-02 | J5: =LEFT(I5,4) -> 2001 | K5: 28.1 | L5: 28.2 | M5: 28.366806 | N5: 34.14847 | P5: =K5-K4 -> -0.2 | Q5: =L5-L4 -> -0.2 | R5: =M5-M4 -> 1.4114071 | S5: =N5-N4 -> 1.7120996 | AA5: ='Aggregates (% GDP) Oct24'!B58 -> 2001-02 | AB5: =LEFT(AA5,4) -> 2001 | AC5: ='Aggregates (% GDP) Oct24'!F58 -> 1.0969634 | AD5: ='Aggregates (% GDP) Mar24'!F58 -> 1.0969634 | AE5: =AVERAGE($AD$8:$AD$27) -> 2.145275 | AH5: ='Aggregates (% GDP) Oct24'!B58 -> 2001-02 | AI5: =LEFT(AH5,4) -> 2001 | AJ5: =-('Aggregates (% GDP) Oct24'!M58-'Aggregates (% GDP) Oct24'!M57) -> 1.9591308 | AM5: 2025 | AN5: =100*((DataCY!B52/DataCY!B51)-1) -> 1.5341097 | AO5: =100*((DataCY!H52/DataCY!H51)-1) -> 1.39618 | AP5: =AO5-AN5 -> -0.13792967 | AR5: =100*((DataCY!D52/DataCY!D51)-1) -> 3.5514545 | AS5: =100*((DataCY!J52/DataCY!J51)-1) -> 3.478492 | AT5: =AS5-AR5 -> -0.072962485 | AV5: =DataCY!C52 -> 33430.338 | AW5: =DataCY!I52 -> 33403.51 | AX5: =AW5-AV5 -> -26.8275 | AZ5: =DataCY!E52 -> 4.3347963 | BA5: =DataCY!K52 -> 4.4113922 | BB5: =BA5-AZ5 -> 0.076596 | BD5: =DataFY!G52 -> 159368.98 | BE5: =DataFY!M52 -> 182720.43 | BF5: =BE5-BD5 -> 23351.45 | BH5: Labour voters | BI5: 51 | BJ5: 25 | BK5: 10 | BL5: 14 | BM5: =SUM(BI5:BL5) -> 100 | BO5: 2008-09 | BP5: =100*(BS5/$BS$20) -> 100.66341 | BQ5: 100 | BS5: 6207.1735 | BU5: =+BU4+1 -> 2 | BV5: =VLOOKUP($BU5,$BY$4:$CA$34,2,FALSE) -> Korea | BW5: =VLOOKUP($BU5,$BY$4:$CA$34,3,FALSE) -> 4.956172 | BY5: =RANK(CA5,$CA$4:$CA$34) -> 19 | BZ5: US | CA5: 3.5916962 | CC5: 2008-09 | CD5: =100*(CG5/$CG$20) -> 86.761543 | CE5: 100 | CG5: 1209.067 | CI5: Expected annual average nominal GDP growth (g) | CJ5: =100*((DataA!AP62/DataA!AP57)^(1/5)-1) -> 3.8491937 | CK5: =100*((DataA!AQ62/DataA!AQ57)^(1/5)-1) -> 4.5938897 | CL5: =100*((DataA!AR62/DataA!AR57)^(1/5)-1) -> 1.8311871 | CM5: =100*((DataA!AS62/DataA!AS57)^(1/5)-1) -> 4.0511319 | CN5: =100*((DataA!AT62/DataA!AT57)^(1/5)-1) -> 4.2423302 | CO5: =100*((DataA!AU62/DataA!AU57)^(1/5)-1) -> 4.1839752 | CP5: =100*((DataA!AV62/DataA!AV57)^(1/5)-1) -> 4.0221267 | CQ5: =100*((DataA!AW62/DataA!AW57)^(1/5)-1) -> 2.5650576 | ... DC5: =100*((DataA!BI62/DataA!BI57)^(1/5)-1) -> 3.882884 | DE5: Employees' NICs | DF5: =OBR_MAR24_ST3.9!F12*(OBR_MAR24_ST3.4!E15/OBR_MAR24_ST3.4!$E$14) -> 55.860867 | DT5: ='[2]1.1'!D54 -> 86.758 | DU5: ='[3]1.1'!D54 -> 85.179 | DV5: ='[4]1.1'!D54 -> 85.179 | DW5: ='[5]1.1'!D54 -> 84.624 | DX5: ='[6]1.1'!D54 -> 84.624 | DY5: ='[7]1.1'!D54 -> 84.624
A6: Capital spending | B6: ='HMT - Table 5.1'!F5 -> 1765 | C6: ='HMT - Table 5.1'!G5 -> -15360 | D6: ='HMT - Table 5.1'!H5 -> -19440 | E6: ='HMT - Table 5.1'!I5 -> -23820 | F6: ='HMT - Table 5.1'!J5 -> -25695 | G6: ='HMT - Table 5.1'!K5 -> -23125 | I6: 2002-03 | J6: =LEFT(I6,4) -> 2002 | K6: 29.8 | L6: 29.9 | M6: 31.350052 | N6: 36.652789 | P6: =K6-K5 -> 1.7 | Q6: =L6-L5 -> 1.7 | R6: =M6-M5 -> 2.9832465 | S6: =N6-N5 -> 2.5043195 | U6: Change % of GDP | AA6: ='Aggregates (% GDP) Oct24'!B59 -> 2002-03 | AB6: =LEFT(AA6,4) -> 2002 | AC6: ='Aggregates (% GDP) Oct24'!F59 -> 1.4448275 | AD6: ='Aggregates (% GDP) Mar24'!F59 -> 1.4448275 | AE6: =AVERAGE($AD$8:$AD$27) -> 2.145275 | AH6: ='Aggregates (% GDP) Oct24'!B59 -> 2002-03 | AI6: =LEFT(AH6,4) -> 2002 | AJ6: =-('Aggregates (% GDP) Oct24'!M59-'Aggregates (% GDP) Oct24'!M58) -> 2.0383229 | AM6: 2026 | AN6: =100*((DataCY!B53/DataCY!B52)-1) -> 1.631252 | AO6: =100*((DataCY!H53/DataCY!H52)-1) -> 1.5073108 | AP6: =AO6-AN6 -> -0.12394115 | AR6: =100*((DataCY!D53/DataCY!D52)-1) -> 2.6851513 | AS6: =100*((DataCY!J53/DataCY!J52)-1) -> 2.5624237 | AT6: =AS6-AR6 -> -0.12272757 | AV6: =DataCY!C53 -> 33874.042 | AW6: =DataCY!I53 -> 33820.61 | AX6: =AW6-AV6 -> -53.4325 | AZ6: =DataCY!E53 -> 4.127162 | BA6: =DataCY!K53 -> 4.2783833 | BB6: =BA6-AZ6 -> 0.15122125 | BD6: =DataFY!G53 -> 166351.45 | BE6: =DataFY!M53 -> 189385.05 | BF6: =BE6-BD6 -> 23033.6 | BH6: Lib Dem voters | BI6: 52 | BJ6: 26 | BK6: 10 | BL6: 13 | BM6: =SUM(BI6:BL6) -> 101 | BO6: 2009-10 | BP6: =100*(BS6/$BS$20) -> 104.95422 | BQ6: 100 | BS6: 6471.7565 | BU6: =+BU5+1 -> 3 | BV6: =VLOOKUP($BU6,$BY$4:$CA$34,2,FALSE) -> Latvia | BW6: =VLOOKUP($BU6,$BY$4:$CA$34,3,FALSE) -> 4.7532364 | BY6: =RANK(CA6,$CA$4:$CA$34) -> 13 | BZ6: Japan | CA6: 3.9530871 | CC6: 2009-10 | CD6: =100*(CG6/$CG$20) -> 96.7349 | CE6: 100 | CG6: 1348.0509 | DE6: VAT | DF6: =OBR_MAR24_ST3.9!F13 -> 173.8803 | DH6: Continue to freeze fuel duty | DI6: 4.7 | DT6: ='[2]1.1'!D55 -> 102.475 | DU6: ='[3]1.1'!D55 -> 100.663 | DV6: ='[4]1.1'!D55 -> 100.663 | DW6: ='[5]1.1'!D55 -> 99.934 | DX6: ='[6]1.1'!D55 -> 99.934 | DY6: ='[7]1.1'!D55 -> 99.934
A7: Total | B7: =SUM(B4:B6) -> -24705 | C7: =SUM(C4:C6) -> -39545 | D7: =SUM(D4:D6) -> -35330 | E7: =SUM(E4:E6) -> -36580 | F7: =SUM(F4:F6) -> -38775 | G7: =SUM(G4:G6) -> -32990 | I7: 2003-04 | J7: =LEFT(I7,4) -> 2003 | K7: 30.9 | L7: 31 | M7: 31.244827 | N7: 37.45462 | P7: =K7-K6 -> 1.1 | Q7: =L7-L6 -> 1.1 | R7: =M7-M6 -> -0.10522481 | S7: =N7-N6 -> 0.80183026 | U7: GDP! | V7: 3459.596 | AA7: ='Aggregates (% GDP) Oct24'!B60 -> 2003-04 | AB7: =LEFT(AA7,4) -> 2003 | AC7: ='Aggregates (% GDP) Oct24'!F60 -> 1.6922036 | AD7: ='Aggregates (% GDP) Mar24'!F60 -> 1.6922036 | AE7: =AVERAGE($AD$8:$AD$27) -> 2.145275 | AH7: ='Aggregates (% GDP) Oct24'!B60 -> 2003-04 | AI7: =LEFT(AH7,4) -> 2003 | AJ7: =-('Aggregates (% GDP) Oct24'!M60-'Aggregates (% GDP) Oct24'!M59) -> 0.4553037 | AM7: 2027 | AN7: =100*((DataCY!B54/DataCY!B53)-1) -> 1.6566706 | AO7: =100*((DataCY!H54/DataCY!H53)-1) -> 1.6837409 | AP7: =AO7-AN7 -> 0.027070292 | AR7: =100*((DataCY!D54/DataCY!D53)-1) -> 2.5895984 | AS7: =100*((DataCY!J54/DataCY!J53)-1) -> 2.6013744 | AT7: =AS7-AR7 -> 0.011775959 | AV7: =DataCY!C54 -> 34275.132 | AW7: =DataCY!I54 -> 34229.768 | AX7: =AW7-AV7 -> -45.365 | AZ7: =DataCY!E54 -> 3.940423 | BA7: =DataCY!K54 -> 4.0675903 | BB7: =BA7-AZ7 -> 0.12716725 | BD7: =DataFY!G54 -> 173561.32 | BE7: =DataFY!M54 -> 197158.96 | BF7: =BE7-BD7 -> 23597.64 | BH7: Conservative voters | BI7: 15 | BJ7: 43 | BK7: 27 | BL7: 15 | BM7: =SUM(BI7:BL7) -> 100 | BO7: 2010-11 | BP7: =100*(BS7/$BS$20) -> 104.32871 | BQ7: 100 | BS7: 6433.1857 | BU7: =+BU6+1 -> 4 | BV7: =VLOOKUP($BU7,$BY$4:$CA$34,2,FALSE) -> Czechia | BW7: =VLOOKUP($BU7,$BY$4:$CA$34,3,FALSE) -> 4.7454643 | BY7: =RANK(CA7,$CA$4:$CA$34) -> 31 | BZ7: Germany | CA7: 2.2421639 | CC7: 2010-11 | CD7: =100*(CG7/$CG$20) -> 80.784526 | CE7: 100 | CG7: 1125.7742 | CI7: AE debt dynamics (2025-2029) | DE7: Corporation tax | DF7: =OBR_MAR24_ST3.9!F14 -> 96.966938 | DH7: Increase defence spending to 2.5% of GDP | DI7: 10 | DT7: ='[2]1.1'!D56 -> 106.312 | DU7: ='[3]1.1'!D56 -> 104.53 | DV7: ='[4]1.1'!D56 -> 104.53 | DW7: ='[5]1.1'!D56 -> 104.835 | DX7: ='[6]1.1'!D56 -> 104.835 | DY7: ='[7]1.1'!D56 -> 104.835
I8: 2004-05 | J8: =LEFT(I8,4) -> 2004 | K8: 33.5 | L8: 33.6 | M8: 33.412416 | N8: 37.390259 | P8: =K8-K7 -> 2.6 | Q8: =L8-L7 -> 2.6 | R8: =M8-M7 -> 2.1675887 | S8: =N8-N7 -> -0.064360255 | AA8: ='Aggregates (% GDP) Oct24'!B61 -> 2004-05 | AB8: =LEFT(AA8,4) -> 2004 | AC8: ='Aggregates (% GDP) Oct24'!F61 -> 2.0459664 | AD8: ='Aggregates (% GDP) Mar24'!F61 -> 2.0459664 | AE8: =AVERAGE($AD$8:$AD$27) -> 2.145275 | AH8: ='Aggregates (% GDP) Oct24'!B61 -> 2004-05 | AI8: =LEFT(AH8,4) -> 2004 | AJ8: =-('Aggregates (% GDP) Oct24'!M61-'Aggregates (% GDP) Oct24'!M60) -> 0.50237965 | AM8: 2028 | AN8: =100*((DataCY!B55/DataCY!B54)-1) -> 1.6473682 | AO8: =100*((DataCY!H55/DataCY!H54)-1) -> 1.6778525 | AP8: =AO8-AN8 -> 0.030484248 | AR8: =100*((DataCY!D55/DataCY!D54)-1) -> 2.591253 | AS8: =100*((DataCY!J55/DataCY!J54)-1) -> 2.6296951 | AT8: =AS8-AR8 -> 0.038442166 | AV8: =DataCY!C55 -> 34669.898 | AW8: =DataCY!I55 -> 34633.96 | AX8: =AW8-AV8 -> -35.9375 | AZ8: =DataCY!E55 -> 3.7972135 | BA8: =DataCY!K55 -> 3.8969493 | BB8: =BA8-AZ8 -> 0.09973575 | BD8: =DataFY!G55 -> 180390.25 | BE8: =DataFY!M55 -> 204855.91 | BF8: =BE8-BD8 -> 24465.66 | BH8: Reform UK voters | BI8: 13 | BJ8: 33 | BK8: 37 | BL8: 17 | BM8: =SUM(BI8:BL8) -> 100 | BO8: 2011-12 | BP8: =100*(BS8/$BS$20) -> 100.33174 | BQ8: 100 | BS8: 6186.7218 | BU8: =+BU7+1 -> 5 | BV8: =VLOOKUP($BU8,$BY$4:$CA$34,2,FALSE) -> Hungary | BW8: =VLOOKUP($BU8,$BY$4:$CA$34,3,FALSE) -> 4.6181676 | BY8: =RANK(CA8,$CA$4:$CA$34) -> 15 | BZ8: France | CA8: 3.7980744 | CC8: 2011-12 | CD8: =100*(CG8/$CG$20) -> 68.060388 | CE8: 100 | CG8: 948.45675 | CJ8: =DataA!BK2 -> UK | CK8: =DataA!BL2 -> US | CL8: =DataA!BM2 -> Japan | CM8: =DataA!BN2 -> Canada | CN8: =DataA!BO2 -> Australia | CO8: =DataA!BP2 -> Denmark | CP8: =DataA!BQ2 -> Sweden | CQ8: =DataA!BR2 -> Switzerland | ... DC8: =DataA!CD2 -> Portugal | DE8: Employers' NICs | DF8: =OBR_MAR24_ST3.9!F12*(OBR_MAR24_ST3.4!E16/OBR_MAR24_ST3.4!$E$14) -> 113.47014 | DH8: 100bps increase in gilt yields | DI8: =OBR_OCT24_RR5.1!H6 -> 11.95889 | DK8: 2021 | DS8: 2021 | DT8: ='[2]1.1'!D57 -> 108.097 | DU8: ='[3]1.1'!D57 -> 104.634 | DV8: ='[4]1.1'!D57 -> 104.377 | DW8: ='[5]1.1'!D57 -> 105.864 | DX8: ='[6]1.1'!D57 -> 105.864 | DY8: ='[7]1.1'!D57 -> 105.864
A9: check | B9: ='HMT - Table 5.1'!F86 -> -24705 | C9: ='HMT - Table 5.1'!G86 -> -39550 | D9: ='HMT - Table 5.1'!H86 -> -35330 | E9: ='HMT - Table 5.1'!I86 -> -36585 | F9: ='HMT - Table 5.1'!J86 -> -38775 | G9: ='HMT - Table 5.1'!K86 -> -32990 | I9: 2005-06 | J9: =LEFT(I9,4) -> 2005 | K9: 34.3 | L9: 34.5 | M9: 32.378335 | N9: 34.942387 | P9: =K9-K8 -> 0.8 | Q9: =L9-L8 -> 0.9 | R9: =M9-M8 -> -1.0340813 | S9: =N9-N8 -> -2.4478726 | W9: Diff | X9: £bn | Y9: =X4-W4 -> 21.526895 | AA9: ='Aggregates (% GDP) Oct24'!B62 -> 2005-06 | AB9: =LEFT(AA9,4) -> 2005 | AC9: ='Aggregates (% GDP) Oct24'!F62 -> 1.8521352 | AD9: ='Aggregates (% GDP) Mar24'!F62 -> 1.8521352 | AE9: =AVERAGE($AD$8:$AD$27) -> 2.145275 | AH9: ='Aggregates (% GDP) Oct24'!B62 -> 2005-06 | AI9: =LEFT(AH9,4) -> 2005 | AJ9: =-('Aggregates (% GDP) Oct24'!M62-'Aggregates (% GDP) Oct24'!M61) -> -0.69717717 | AM9: 2029 | AN9: =100*((DataCY!B56/DataCY!B55)-1) -> 1.6121887 | AO9: =100*((DataCY!H56/DataCY!H55)-1) -> 1.6514389 | AP9: =AO9-AN9 -> 0.039250219 | AR9: =100*((DataCY!D56/DataCY!D55)-1) -> 2.649545 | AS9: =100*((DataCY!J56/DataCY!J55)-1) -> 2.6857202 | AT9: =AS9-AR9 -> 0.036175242 | AV9: =DataCY!C56 -> 35019.358 | AW9: =DataCY!I56 -> 34992.588 | AX9: =AW9-AV9 -> -26.77 | AZ9: =DataCY!E56 -> 3.749889 | BA9: =DataCY!K56 -> 3.8234867 | BB9: =BA9-AZ9 -> 0.07359775 | BD9: =DataFY!G56 -> 187169.91 | BE9: =DataFY!M56 -> 212530.68 | BF9: =BE9-BD9 -> 25360.77 | BO9: 2012-13 | BP9: =100*(BS9/$BS$20) -> 96.544117 | BQ9: 100 | BS9: 5953.1669 | BU9: =+BU8+1 -> 6 | BV9: =VLOOKUP($BU9,$BY$4:$CA$34,2,FALSE) -> Sweden | BW9: =VLOOKUP($BU9,$BY$4:$CA$34,3,FALSE) -> 4.5506017 | BY9: =RANK(CA9,$CA$4:$CA$34) -> 28 | BZ9: Italy | CA9: 2.7823445 | CC9: 2012-13 | CD9: =100*(CG9/$CG$20) -> 64.3172 | CE9: 100 | CG9: 896.29347 | CI9: Expected effective interest rates on government debt (r) | CJ9: =AVERAGE(DataA!BK59:BK63) -> 3.7872637 | CK9: =AVERAGE(DataA!BL59:BL63) -> 3.4794354 | CL9: =AVERAGE(DataA!BM59:BM63) -> 0.93904773 | CM9: =AVERAGE(DataA!BN59:BN63) -> 3.284709 | CN9: =AVERAGE(DataA!BO59:BO63) -> 3.099439 | CO9: =AVERAGE(DataA!BP59:BP63) -> 1.8489287 | CP9: =AVERAGE(DataA!BQ59:BQ63) -> 1.4549596 | CQ9: =AVERAGE(DataA!BR59:BR63) -> 1.2277362 | ... DC9: =AVERAGE(DataA!CD59:CD63) -> 2.4551536 | DE9: Fuel duties | DF9: =OBR_MAR24_ST3.9!F21 -> 24.740818 | DH9: 100bps increase in expectations for Bank Rate | DI9: =OBR_OCT24_RR5.1!H7 -> 4.6651018 | DT9: ='[2]1.1'!D58 -> 116.428 | DU9: ='[3]1.1'!D58 -> 112.51 | DV9: ='[4]1.1'!D58 -> 112.392 | DW9: ='[5]1.1'!D58 -> 114.096 | DX9: ='[6]1.1'!D58 -> 114.096 | DY9: ='[7]1.1'!D58 -> 114.096
I10: 2006-07 | J10: =LEFT(I10,4) -> 2006 | K10: 35.1 | L10: 35.3 | M10: 32.440742 | N10: 35.127873 | P10: =K10-K9 -> 0.8 | Q10: =L10-L9 -> 0.8 | R10: =M10-M9 -> 0.062407551 | S10: =N10-N9 -> 0.18548609 | X10: % of GDP | Y10: =R33-Q33 -> -0.62223726 | AA10: ='Aggregates (% GDP) Oct24'!B63 -> 2006-07 | AB10: =LEFT(AA10,4) -> 2006 | AC10: ='Aggregates (% GDP) Oct24'!F63 -> 1.8163774 | AD10: ='Aggregates (% GDP) Mar24'!F63 -> 1.8163774 | AE10: =AVERAGE($AD$8:$AD$27) -> 2.145275 | AH10: ='Aggregates (% GDP) Oct24'!B63 -> 2006-07 | AI10: =LEFT(AH10,4) -> 2006 | AJ10: =-('Aggregates (% GDP) Oct24'!M63-'Aggregates (% GDP) Oct24'!M62) -> -0.71890443 | AM10: 2030 | AN10: =100*((DataCY!B57/DataCY!B56)-1) -> 1.6097059 | AO10: =100*((DataCY!H57/DataCY!H56)-1) -> 1.6548179 | AP10: =AO10-AN10 -> 0.045112052 | AR10: =100*((DataCY!D57/DataCY!D56)-1) -> 2.7035181 | AS10: =100*((DataCY!J57/DataCY!J56)-1) -> 2.7420534 | AT10: =AS10-AR10 -> 0.038535354 | AV10: =DataCY!C57 -> 35334.71 | AW10: =DataCY!I57 -> 35317.572 | AX10: =AW10-AV10 -> -17.1375 | AZ10: =DataCY!E57 -> 3.7498765 | BA10: =DataCY!K57 -> 3.7965653 | BB10: =BA10-AZ10 -> 0.04668875 | BH10: Exclude DKs | BO10: 2013-14 | BP10: =100*(BS10/$BS$20) -> 95.557909 | BQ10: 100 | BS10: 5892.3547 | BU10: =+BU9+1 -> 7 | BV10: =VLOOKUP($BU10,$BY$4:$CA$34,2,FALSE) -> Norway | BW10: =VLOOKUP($BU10,$BY$4:$CA$34,3,FALSE) -> 4.5081333 | BY10: =RANK(CA10,$CA$4:$CA$34) -> 22 | BZ10: Australia | CA10: 3.1343494 | CC10: 2013-14 | CD10: =100*(CG10/$CG$20) -> 67.741493 | CE10: 100 | CG10: 944.01278 | CI10: Expected annual average nominal GDP growth (g) | CJ10: =100*((DataA!AP63/DataA!AP58)^(1/5)-1) -> 3.8045697 | CK10: =100*((DataA!AQ63/DataA!AQ58)^(1/5)-1) -> 4.3724944 | CL10: =100*((DataA!AR63/DataA!AR58)^(1/5)-1) -> 1.7705182 | CM10: =100*((DataA!AS63/DataA!AS58)^(1/5)-1) -> 4.155786 | CN10: =100*((DataA!AT63/DataA!AT58)^(1/5)-1) -> 4.5718689 | CO10: =100*((DataA!AU63/DataA!AU58)^(1/5)-1) -> 4.2828992 | CP10: =100*((DataA!AV63/DataA!AV58)^(1/5)-1) -> 3.9706052 | CQ10: =100*((DataA!AW63/DataA!AW58)^(1/5)-1) -> 2.5674863 | ... DC10: =100*((DataA!BI63/DataA!BI58)^(1/5)-1) -> 3.2856373 | DE10: Business rates | DF10: =OBR_MAR24_ST3.9!F52 -> 32.462397 | DT10: ='[2]1.1'!D59 -> 116.409 | DU10: ='[3]1.1'!D59 -> 112.792 | DV10: ='[4]1.1'!D59 -> 112.854 | DW10: ='[5]1.1'!D59 -> 115.146 | DX10: ='[6]1.1'!D59 -> 115.146 | DY10: ='[7]1.1'!D59 -> 115.146
A11: GDP! | B11: 2814.6771 | C11: 2950.0172 | D11: 3059.3962 | E11: 3167.3346 | F11: 3279.0494 | G11: 3397.2814 | I11: 2007-08 | J11: =LEFT(I11,4) -> 2007 | K11: 35.6 | L11: 35.8 | M11: 34.196775 | N11: 37.427136 | P11: =K11-K10 -> 0.5 | Q11: =L11-L10 -> 0.5 | R11: =M11-M10 -> 1.7560329 | S11: =N11-N10 -> 2.2992633 | AA11: ='Aggregates (% GDP) Oct24'!B64 -> 2007-08 | AB11: =LEFT(AA11,4) -> 2007 | AC11: ='Aggregates (% GDP) Oct24'!F64 -> 1.7924771 | AD11: ='Aggregates (% GDP) Mar24'!F64 -> 1.7924771 | AE11: =AVERAGE($AD$8:$AD$27) -> 2.145275 | AH11: ='Aggregates (% GDP) Oct24'!B64 -> 2007-08 | AI11: =LEFT(AH11,4) -> 2007 | AJ11: =-('Aggregates (% GDP) Oct24'!M64-'Aggregates (% GDP) Oct24'!M63) -> 0.49578275 | BI11: Higher taxes and more funding for public services | BJ11: Current tax levels and public services funding remaining as it is | BK11: Lower taxes and less funding for public services | BO11: 2014-15 | BP11: =100*(BS11/$BS$20) -> 94.289963 | BQ11: 100 | BS11: 5814.1698 | BU11: =+BU10+1 -> 8 | BV11: =VLOOKUP($BU11,$BY$4:$CA$34,2,FALSE) -> Poland | BW11: =VLOOKUP($BU11,$BY$4:$CA$34,3,FALSE) -> 4.29505 | BY11: =RANK(CA11,$CA$4:$CA$34) -> 23 | BZ11: Austria | CA11: 3.0502152 | CC11: 2014-15 | CD11: =100*(CG11/$CG$20) -> 72.034572 | CE11: 100 | CG11: 1003.839 | DE11: Council tax | DF11: =OBR_MAR24_ST3.9!F53 -> 46.298781 | DL11: =100*(DT11/AVERAGE(DT$12:DT$15)) -> 100.60698 | DT11: ='[2]1.1'!D60 -> 118.62 | DU11: ='[3]1.1'!D60 -> 114.347 | DV11: ='[4]1.1'!D60 -> 114.284 | DW11: ='[5]1.1'!D60 -> 116.404 | DX11: ='[6]1.1'!D60 -> 116.404 | DY11: ='[7]1.1'!D60 -> 116.404
I12: 2008-09 | J12: =LEFT(I12,4) -> 2008 | K12: 50.6 | L12: 50.6 | M12: 47.544202 | N12: 46.938699 | P12: =K12-K11 -> 15 | Q12: =L12-L11 -> 14.8 | R12: =M12-M11 -> 13.347427 | S12: =N12-N11 -> 9.5115631 | AA12: ='Aggregates (% GDP) Oct24'!B65 -> 2008-09 | AB12: =LEFT(AA12,4) -> 2008 | AC12: ='Aggregates (% GDP) Oct24'!F65 -> 3.0053462 | AD12: ='Aggregates (% GDP) Mar24'!F65 -> 3.0053462 | AE12: =AVERAGE($AD$8:$AD$27) -> 2.145275 | AH12: ='Aggregates (% GDP) Oct24'!B65 -> 2008-09 | AI12: =LEFT(AH12,4) -> 2008 | AJ12: =-('Aggregates (% GDP) Oct24'!M65-'Aggregates (% GDP) Oct24'!M64) -> 3.6279951 | BH12: All Britons | BI12: =100*(BI4/($BI4+$BJ4+$BK4)) -> 38.271605 | BJ12: =100*(BJ4/($BI4+$BJ4+$BK4)) -> 37.037037 | BK12: =100*(BK4/($BI4+$BJ4+$BK4)) -> 24.691358 | BM12: =SUM(BI12:BL12) -> 100 | BO12: 2015-16 | BP12: =100*(BS12/$BS$20) -> 92.40396 | BQ12: 100 | BS12: 5697.8739 | BU12: =+BU11+1 -> 9 | BV12: =VLOOKUP($BU12,$BY$4:$CA$34,2,FALSE) -> Slovenia | BW12: =VLOOKUP($BU12,$BY$4:$CA$34,3,FALSE) -> 4.2756384 | BY12: =RANK(CA12,$CA$4:$CA$34) -> 30 | BZ12: Belgium | CA12: 2.3573553 | CC12: 2015-16 | CD12: =100*(CG12/$CG$20) -> 68.29393 | CE12: 100 | CG12: 951.71127 | DE12: Capital gains tax | DF12: =OBR_MAR24_ST3.9!F22 -> 15.242148 | DK12: 2022 | DL12: =100*(DT12/AVERAGE(DT$12:DT$15)) -> 99.963094 | DS12: 2022 | DT12: ='[2]1.1'!D61 -> 117.86083 | DU12: ='[3]1.1'!D61 -> 113.062 | DV12: ='[4]1.1'!D61 -> 113.813 | DW12: ='[5]1.1'!D61 -> 117.297 | DX12: ='[6]1.1'!D61 -> 117.6 | DY12: ='[7]1.1'!D61 -> 117.6
A13: % of GDP | I13: 2009-10 | J13: =LEFT(I13,4) -> 2009 | K13: 64.7 | L13: 63.9 | M13: 54.597887 | N13: 54.07218 | P13: =K13-K12 -> 14.1 | Q13: =L13-L12 -> 13.3 | R13: =M13-M12 -> 7.0536849 | S13: =N13-N12 -> 7.1334808 | AA13: ='Aggregates (% GDP) Oct24'!B66 -> 2009-10 | AB13: =LEFT(AA13,4) -> 2009 | AC13: ='Aggregates (% GDP) Oct24'!F66 -> 3.0029004 | AD13: ='Aggregates (% GDP) Mar24'!F66 -> 3.0029004 | AE13: =AVERAGE($AD$8:$AD$27) -> 2.145275 | AH13: ='Aggregates (% GDP) Oct24'!B66 -> 2009-10 | AI13: =LEFT(AH13,4) -> 2009 | AJ13: =-('Aggregates (% GDP) Oct24'!M66-'Aggregates (% GDP) Oct24'!M65) -> 1.4319908 | BH13: Labour voters | BI13: =100*(BI5/($BI5+$BJ5+$BK5)) -> 59.302326 | BJ13: =100*(BJ5/($BI5+$BJ5+$BK5)) -> 29.069767 | BK13: =100*(BK5/($BI5+$BJ5+$BK5)) -> 11.627907 | BM13: =SUM(BI13:BL13) -> 100 | BO13: 2016-17 | BP13: =100*(BS13/$BS$20) -> 90.751464 | BQ13: 100 | BS13: 5595.9765 | BU13: =+BU12+1 -> 10 | BV13: =VLOOKUP($BU13,$BY$4:$CA$34,2,FALSE) -> Luxembourg | BW13: =VLOOKUP($BU13,$BY$4:$CA$34,3,FALSE) -> 4.1890307 | BY13: =RANK(CA13,$CA$4:$CA$34) -> 4 | BZ13: Czechia | CA13: 4.7454643 | CC13: 2016-17 | CD13: =100*(CG13/$CG$20) -> 67.698326 | CE13: 100 | CG13: 943.41122 | DE13: Inheritance tax | DF13: =OBR_MAR24_ST3.9!F23 -> 7.5239694 | DL13: =100*(DT13/AVERAGE(DT$12:DT$15)) -> 99.633216 | DT13: ='[2]1.1'!D62 -> 117.47189 | DU13: ='[3]1.1'!D62 -> 111.34 | DV13: ='[4]1.1'!D62 -> 112.16 | DW13: ='[5]1.1'!D62 -> 114.908 | DX13: ='[6]1.1'!D62 -> 114.55 | DY13: ='[7]1.1'!D62 -> 114.55
A14: Tax | B14: =100*((B4/1000)/B$11) -> 0.041212542 | C14: =100*((C4/1000)/C$11) -> 0.81372406 | D14: =100*((D4/1000)/D$11) -> 1.1369891 | E14: =100*((E4/1000)/E$11) -> 1.2333714 | F14: =100*((F4/1000)/F$11) -> 1.2114791 | G14: =100*((G4/1000)/G$11) -> 1.2118513 | I14: 2010-11 | J14: =LEFT(I14,4) -> 2010 | K14: 70.9 | L14: 70.6 | M14: 58.946492 | N14: 49.558414 | P14: =K14-K13 -> 6.2 | Q14: =L14-L13 -> 6.7 | R14: =M14-M13 -> 4.3486046 | S14: =N14-N13 -> -4.5137655 | AA14: ='Aggregates (% GDP) Oct24'!B67 -> 2010-11 | AB14: =LEFT(AA14,4) -> 2010 | AC14: ='Aggregates (% GDP) Oct24'!F67 -> 2.4446147 | AD14: ='Aggregates (% GDP) Mar24'!F67 -> 2.4446147 | AE14: =AVERAGE($AD$8:$AD$27) -> 2.145275 | AH14: ='Aggregates (% GDP) Oct24'!B67 -> 2010-11 | AI14: =LEFT(AH14,4) -> 2010 | AJ14: =-('Aggregates (% GDP) Oct24'!M67-'Aggregates (% GDP) Oct24'!M66) -> -2.2415985 | BH14: Lib Dem voters | BI14: =100*(BI6/($BI6+$BJ6+$BK6)) -> 59.090909 | BJ14: =100*(BJ6/($BI6+$BJ6+$BK6)) -> 29.545455 | BK14: =100*(BK6/($BI6+$BJ6+$BK6)) -> 11.363636 | BM14: =SUM(BI14:BL14) -> 100 | BO14: 2017-18 | BP14: =100*(BS14/$BS$20) -> 89.829709 | BQ14: 100 | BS14: 5539.1387 | BU14: =+BU13+1 -> 11 | BV14: =VLOOKUP($BU14,$BY$4:$CA$34,2,FALSE) -> Greece | BW14: =VLOOKUP($BU14,$BY$4:$CA$34,3,FALSE) -> 4.0946323 | BY14: =RANK(CA14,$CA$4:$CA$34) -> 21 | BZ14: Denmark | CA14: 3.2815288 | CC14: 2017-18 | CD14: =100*(CG14/$CG$20) -> 70.926661 | CE14: 100 | CG14: 988.39974 | DE14: Stamp duty (land) | DF14: =OBR_MAR24_ST3.9!F24 -> 12.76865 | DL14: =100*(DT14/AVERAGE(DT$12:DT$15)) -> 100.01182 | DM14: =100*(DU14/AVERAGE(DU$12:DU$15)) -> 100.12648 | DT14: ='[2]1.1'!D63 -> 117.91828 | DU14: ='[3]1.1'!D63 -> 113.5668 | DV14: ='[4]1.1'!D63 -> 112.747 | DW14: ='[5]1.1'!D63 -> 115.748 | DX14: ='[6]1.1'!D63 -> 115.094 | DY14: ='[7]1.1'!D63 -> 115.094
A15: Current spending | B15: =100*((B5/1000)/B$11) -> -0.98164012 | C15: =100*((C5/1000)/C$11) -> -1.6335498 | D15: =100*((D5/1000)/D$11) -> -1.6563726 | E15: =100*((E5/1000)/E$11) -> -1.6362338 | F15: =100*((F5/1000)/F$11) -> -1.6103752 | G15: =100*((G5/1000)/G$11) -> -1.5022306 | I15: 2011-12 | J15: =LEFT(I15,4) -> 2011 | K15: 74.3 | L15: 74.6 | M15: 65.016918 | N15: 54.680429 | P15: =K15-K14 -> 3.4 | Q15: =L15-L14 -> 4 | R15: =M15-M14 -> 6.0704267 | S15: =N15-N14 -> 5.1220142 | AA15: ='Aggregates (% GDP) Oct24'!B68 -> 2011-12 | AB15: =LEFT(AA15,4) -> 2011 | AC15: ='Aggregates (% GDP) Oct24'!F68 -> 1.8421103 | AD15: ='Aggregates (% GDP) Mar24'!F68 -> 1.8421103 | AE15: =AVERAGE($AD$8:$AD$27) -> 2.145275 | AH15: ='Aggregates (% GDP) Oct24'!B68 -> 2011-12 | AI15: =LEFT(AH15,4) -> 2011 | AJ15: =-('Aggregates (% GDP) Oct24'!M68-'Aggregates (% GDP) Oct24'!M67) -> -1.4113887 | BH15: Conservative voters | BI15: =100*(BI7/($BI7+$BJ7+$BK7)) -> 17.647059 | BJ15: =100*(BJ7/($BI7+$BJ7+$BK7)) -> 50.588235 | BK15: =100*(BK7/($BI7+$BJ7+$BK7)) -> 31.764706 | BM15: =SUM(BI15:BL15) -> 100 | BO15: 2018-19 | BP15: =100*(BS15/$BS$20) -> 89.519645 | BQ15: 100 | BS15: 5520.0193 | BU15: =+BU14+1 -> 12 | BV15: =VLOOKUP($BU15,$BY$4:$CA$34,2,FALSE) -> Finland | BW15: =VLOOKUP($BU15,$BY$4:$CA$34,3,FALSE) -> 3.9606967 | BY15: =RANK(CA15,$CA$4:$CA$34) -> 1 | BZ15: Estonia | CA15: 5.3362375 | CC15: 2018-19 | CD15: =100*(CG15/$CG$20) -> 73.803986 | CE15: 100 | CG15: 1028.4968 | DE15: Tobacco & alcohol duties | DF15: =OBR_MAR24_ST3.9!F27+OBR_MAR24_ST3.9!F28+OBR_MAR24_ST3.9!F29+OBR_MAR24_ST3.9!F30 -> 21.513849 | DL15: =100*(DT15/AVERAGE(DT$12:DT$15)) -> 100.39187 | DM15: =100*(DU15/AVERAGE(DU$12:DU$15)) -> 102.02888 | DN15: =100*(DV15/AVERAGE(DV$12:DV$15)) -> 100.48634 | DT15: ='[2]1.1'!D64 -> 118.36637 | DU15: ='[3]1.1'!D64 -> 115.72457 | DV15: ='[4]1.1'!D64 -> 113.64 | DW15: ='[5]1.1'!D64 -> 114.896 | DX15: ='[6]1.1'!D64 -> 114.44 | DY15: ='[7]1.1'!D64 -> 114.44
A16: Capital spending | B16: =100*((B6/1000)/B$11) -> 0.062707015 | C16: =100*((C6/1000)/C$11) -> -0.52067492 | D16: =100*((D6/1000)/D$11) -> -0.6354195 | E16: =100*((E6/1000)/E$11) -> -0.7520519 | F16: =100*((F6/1000)/F$11) -> -0.78361125 | G16: =100*((G6/1000)/G$11) -> -0.68069133 | I16: 2012-13 | J16: =LEFT(I16,4) -> 2012 | K16: 77.5 | L16: 76.2 | M16: 69.72436 | N16: 58.751603 | P16: =K16-K15 -> 3.2 | Q16: =L16-L15 -> 1.6 | R16: =M16-M15 -> 4.7074411 | S16: =N16-N15 -> 4.0711743 | AA16: ='Aggregates (% GDP) Oct24'!B69 -> 2012-13 | AB16: =LEFT(AA16,4) -> 2012 | AC16: ='Aggregates (% GDP) Oct24'!F69 -> 1.8798625 | AD16: ='Aggregates (% GDP) Mar24'!F69 -> 1.8798625 | AE16: =AVERAGE($AD$8:$AD$27) -> 2.145275 | AH16: ='Aggregates (% GDP) Oct24'!B69 -> 2012-13 | AI16: =LEFT(AH16,4) -> 2012 | AJ16: =-('Aggregates (% GDP) Oct24'!M69-'Aggregates (% GDP) Oct24'!M68) -> 0.44780765 | BH16: Reform UK voters | BI16: =100*(BI8/($BI8+$BJ8+$BK8)) -> 15.662651 | BJ16: =100*(BJ8/($BI8+$BJ8+$BK8)) -> 39.759036 | BK16: =100*(BK8/($BI8+$BJ8+$BK8)) -> 44.578313 | BM16: =SUM(BI16:BL16) -> 100 | BO16: 2019-20 | BP16: =100*(BS16/$BS$20) -> 93.503228 | BQ16: 100 | BS16: 5765.6577 | BU16: =+BU15+1 -> 13 | BV16: =VLOOKUP($BU16,$BY$4:$CA$34,2,FALSE) -> Japan | BW16: =VLOOKUP($BU16,$BY$4:$CA$34,3,FALSE) -> 3.9530871 | BY16: =RANK(CA16,$CA$4:$CA$34) -> 12 | BZ16: Finland | CA16: 3.9606967 | CC16: 2019-20 | CD16: =100*(CG16/$CG$20) -> 75.285142 | CE16: 100 | CG16: 1049.1374 | DE16: Other | DF16: =DF17-SUM(DF4:DF15) -> 235.761 | DK16: 2023 | DL16: =100*(DT16/AVERAGE(DT$12:DT$15)) -> 100.74324 | DM16: =100*(DU16/AVERAGE(DU$12:DU$15)) -> 103.40627 | DN16: =100*(DV16/AVERAGE(DV$12:DV$15)) -> 102.12992 | DS16: 2023 | DT16: ='[2]1.1'!D65 -> 118.78066 | DU16: ='[3]1.1'!D65 -> 117.28685 | DV16: ='[4]1.1'!D65 -> 115.49872 | DW16: ='[5]1.1'!D65 -> 113.546 | DX16: ='[6]1.1'!D65 -> 113.218 | DY16: ='[7]1.1'!D65 -> 113.488
A17: Total | B17: =100*((B7/1000)/B$11) -> -0.87772057 | C17: =100*((C7/1000)/C$11) -> -1.3405006 | D17: =100*((D7/1000)/D$11) -> -1.154803 | E17: =100*((E7/1000)/E$11) -> -1.1549143 | F17: =100*((F7/1000)/F$11) -> -1.1825073 | G17: =100*((G7/1000)/G$11) -> -0.97107057 | I17: 2013-14 | J17: =LEFT(I17,4) -> 2013 | K17: 79.2 | L17: 77 | M17: 70.718374 | N17: 56.326968 | P17: =K17-K16 -> 1.7 | Q17: =L17-L16 -> 0.8 | R17: =M17-M16 -> 0.99401484 | S17: =N17-N16 -> -2.4246345 | AA17: ='Aggregates (% GDP) Oct24'!B70 -> 2013-14 | AB17: =LEFT(AA17,4) -> 2013 | AC17: ='Aggregates (% GDP) Oct24'!F70 -> 1.4526683 | AD17: ='Aggregates (% GDP) Mar24'!F70 -> 1.4526683 | AE17: =AVERAGE($AD$8:$AD$27) -> 2.145275 | AH17: ='Aggregates (% GDP) Oct24'!B70 -> 2013-14 | AI17: =LEFT(AH17,4) -> 2013 | AJ17: =-('Aggregates (% GDP) Oct24'!M70-'Aggregates (% GDP) Oct24'!M69) -> -0.91274837 | BO17: 2020-21 | BP17: =100*(BS17/$BS$20) -> 112.15508 | BQ17: 100 | BS17: 6915.7804 | BU17: =+BU16+1 -> 14 | BV17: =VLOOKUP($BU17,$BY$4:$CA$34,2,FALSE) -> Lithuania | BW17: =VLOOKUP($BU17,$BY$4:$CA$34,3,FALSE) -> 3.8993341 | BY17: =RANK(CA17,$CA$4:$CA$34) -> 11 | BZ17: Greece | CA17: 4.0946323 | CC17: 2020-21 | CD17: =100*(CG17/$CG$20) -> 91.228347 | CE17: 100 | CG17: 1271.3142 | DE17: Total | DF17: =OBR_MAR24_ST3.9!F63 -> 1139.1216 | DL17: =100*(DT17/AVERAGE(DT$12:DT$15)) -> 101.07569 | DM17: =100*(DU17/AVERAGE(DU$12:DU$15)) -> 104.59545 | DN17: =100*(DV17/AVERAGE(DV$12:DV$15)) -> 103.3951 | DO17: =100*(DW17/AVERAGE(DW$12:DW$15)) -> 100.60646 | DT17: ='[2]1.1'!D66 -> 119.17263 | DU17: ='[3]1.1'!D66 -> 118.63565 | DV17: ='[4]1.1'!D66 -> 116.92951 | DW17: ='[5]1.1'!D66 -> 116.414 | DX17: ='[6]1.1'!D66 -> 116.107 | DY17: ='[7]1.1'!D66 -> 116.016
I18: 2014-15 | J18: =LEFT(I18,4) -> 2014 | K18: 81.6 | L18: 79.2 | M18: 72.913428 | N18: 53.4578 | P18: =K18-K17 -> 2.4 | Q18: =L18-L17 -> 2.2 | R18: =M18-M17 -> 2.1950537 | S18: =N18-N17 -> -2.8691685 | AA18: ='Aggregates (% GDP) Oct24'!B71 -> 2014-15 | AB18: =LEFT(AA18,4) -> 2014 | AC18: ='Aggregates (% GDP) Oct24'!F71 -> 1.929131 | AD18: ='Aggregates (% GDP) Mar24'!F71 -> 1.929131 | AE18: =AVERAGE($AD$8:$AD$27) -> 2.145275 | AH18: ='Aggregates (% GDP) Oct24'!B71 -> 2014-15 | AI18: =LEFT(AH18,4) -> 2014 | AJ18: =-('Aggregates (% GDP) Oct24'!M71-'Aggregates (% GDP) Oct24'!M70) -> 0.36659488 | BO18: 2021-22 | BP18: =100*(BS18/$BS$20) -> 110.01328 | BQ18: 100 | BS18: 6783.7111 | BU18: =+BU17+1 -> 15 | BV18: =VLOOKUP($BU18,$BY$4:$CA$34,2,FALSE) -> France | BW18: =VLOOKUP($BU18,$BY$4:$CA$34,3,FALSE) -> 3.7980744 | BY18: =RANK(CA18,$CA$4:$CA$34) -> 5 | BZ18: Hungary | CA18: 4.6181676 | CC18: 2021-22 | CD18: =100*(CG18/$CG$20) -> 93.606097 | CE18: 100 | CG18: 1304.4494 | DL18: =100*(DT18/AVERAGE(DT$12:DT$15)) -> 101.39913 | DM18: =100*(DU18/AVERAGE(DU$12:DU$15)) -> 105.43221 | DN18: =100*(DV18/AVERAGE(DV$12:DV$15)) -> 104.34503 | DO18: =100*(DW18/AVERAGE(DW$12:DW$15)) -> 101.41131 | DT18: ='[2]1.1'!D67 -> 119.55398 | DU18: ='[3]1.1'!D67 -> 119.58473 | DV18: ='[4]1.1'!D67 -> 118.00379 | DW18: ='[5]1.1'!D67 -> 117.34531 | DX18: ='[6]1.1'!D67 -> 116.994 | DY18: ='[7]1.1'!D67 -> 117.255
I19: 2015-16 | J19: =LEFT(I19,4) -> 2015 | K19: 81.3 | L19: 78.9 | M19: 73.981933 | N19: 51.950634 | P19: =K19-K18 -> -0.3 | Q19: =L19-L18 -> -0.3 | R19: =M19-M18 -> 1.0685047 | S19: =N19-N18 -> -1.5071661 | AA19: ='Aggregates (% GDP) Oct24'!B72 -> 2015-16 | AB19: =LEFT(AA19,4) -> 2015 | AC19: ='Aggregates (% GDP) Oct24'!F72 -> 1.6691683 | AD19: ='Aggregates (% GDP) Mar24'!F72 -> 1.6691683 | AE19: =AVERAGE($AD$8:$AD$27) -> 2.145275 | AH19: ='Aggregates (% GDP) Oct24'!B72 -> 2015-16 | AI19: =LEFT(AH19,4) -> 2015 | AJ19: =-('Aggregates (% GDP) Oct24'!M72-'Aggregates (% GDP) Oct24'!M71) -> -0.50198668 | BO19: 2022-23 | BP19: =100*(BS19/$BS$20) -> 103.59736 | BQ19: 100 | BS19: 6388.0887 | BU19: =+BU18+1 -> 16 | BV19: =VLOOKUP($BU19,$BY$4:$CA$34,2,FALSE) -> Netherlands | BW19: =VLOOKUP($BU19,$BY$4:$CA$34,3,FALSE) -> 3.7365702 | BY19: =RANK(CA19,$CA$4:$CA$34) -> 17 | BZ19: Iceland | CA19: 3.7317937 | CC19: 2022-23 | CD19: =100*(CG19/$CG$20) -> 101.01867 | CE19: 100 | CG19: 1407.7475 | DL19: =100*(DT19/AVERAGE(DT$12:DT$15)) -> 101.73375 | DM19: =100*(DU19/AVERAGE(DU$12:DU$15)) -> 105.90665 | DN19: =100*(DV19/AVERAGE(DV$12:DV$15)) -> 104.74908 | DO19: =100*(DW19/AVERAGE(DW$12:DW$15)) -> 102.52684 | DP19: =100*(DX19/AVERAGE(DX$12:DX$15)) -> 102.80916 | DT19: ='[2]1.1'!D68 -> 119.94851 | DU19: ='[3]1.1'!D68 -> 120.12287 | DV19: ='[4]1.1'!D68 -> 118.46074 | DW19: ='[5]1.1'!D68 -> 118.63611 | DX19: ='[6]1.1'!D68 -> 118.66336 | DY19: ='[7]1.1'!D68 -> 117.343
I20: 2016-17 | J20: =LEFT(I20,4) -> 2016 | K20: 83.5 | L20: 77.4 | M20: 74.221682 | N20: 61.429268 | P20: =K20-K19 -> 2.2 | Q20: =L20-L19 -> -1.5 | R20: =M20-M19 -> 0.23974945 | S20: =N20-N19 -> 9.4786344 | AA20: ='Aggregates (% GDP) Oct24'!B73 -> 2016-17 | AB20: =LEFT(AA20,4) -> 2016 | AC20: ='Aggregates (% GDP) Oct24'!F73 -> 1.8101862 | AD20: ='Aggregates (% GDP) Mar24'!F73 -> 1.8101862 | AE20: =AVERAGE($AD$8:$AD$27) -> 2.145275 | AH20: ='Aggregates (% GDP) Oct24'!B73 -> 2016-17 | AI20: =LEFT(AH20,4) -> 2016 | AJ20: =-('Aggregates (% GDP) Oct24'!M73-'Aggregates (% GDP) Oct24'!M72) -> -1.4760005 | BH20: Alternative survey from Ipsos: | BO20: 2023-24 | BP20: =100*(BS20/$BS$20) -> 100 | BQ20: 100 | BS20: 6166.2659 | BU20: =+BU19+1 -> 17 | BV20: =VLOOKUP($BU20,$BY$4:$CA$34,2,FALSE) -> Iceland | BW20: =VLOOKUP($BU20,$BY$4:$CA$34,3,FALSE) -> 3.7317937 | BY20: =RANK(CA20,$CA$4:$CA$34) -> 26 | BZ20: Ireland | CA20: 2.8311903 | CC20: 2023-24 | CD20: =100*(CG20/$CG$20) -> 100 | CE20: 100 | CG20: 1393.5518 | DK20: 2024 | DL20: =100*(DT20/AVERAGE(DT$12:DT$15)) -> 102.08982 | DM20: =100*(DU20/AVERAGE(DU$12:DU$15)) -> 106.22437 | DN20: =100*(DV20/AVERAGE(DV$12:DV$15)) -> 104.89539 | DO20: =100*(DW20/AVERAGE(DW$12:DW$15)) -> 103.55211 | DP20: =100*(DX20/AVERAGE(DX$12:DX$15)) -> 103.91807 | DS20: 2024 | DT20: ='[2]1.1'!D69 -> 120.36833 | DU20: ='[3]1.1'!D69 -> 120.48324 | DV20: ='[4]1.1'!D69 -> 118.6262 | DW20: ='[5]1.1'!D69 -> 119.82247 | DX20: ='[6]1.1'!D69 -> 119.94327 | DY20: ='[7]1.1'!D69 -> 117.324
I21: 2017-18 | J21: =LEFT(I21,4) -> 2017 | K21: 82.3 | L21: 73.7 | M21: 70.188464 | N21: 63.049303 | P21: =K21-K20 -> -1.2 | Q21: =L21-L20 -> -3.7 | R21: =M21-M20 -> -4.0332186 | S21: =N21-N20 -> 1.6200343 | AA21: ='Aggregates (% GDP) Oct24'!B74 -> 2017-18 | AB21: =LEFT(AA21,4) -> 2017 | AC21: ='Aggregates (% GDP) Oct24'!F74 -> 2.2089205 | AD21: ='Aggregates (% GDP) Mar24'!F74 -> 2.2089205 | AE21: =AVERAGE($AD$8:$AD$27) -> 2.145275 | AH21: ='Aggregates (% GDP) Oct24'!B74 -> 2017-18 | AI21: =LEFT(AH21,4) -> 2017 | AJ21: =-('Aggregates (% GDP) Oct24'!M74-'Aggregates (% GDP) Oct24'!M73) -> 0.080590287 | BH21: https://www.ipsos.com/sites/default/files/ct/news/documents/2024-10/Ipsos_Oct%2024_Pre-Budget_Polling.pdf | BO21: 2024-25 | BP21: =100*(BS21/$BS$20) -> 100.10405 | BQ21: 100 | BS21: 6172.6818 | BU21: =+BU20+1 -> 18 | BV21: =VLOOKUP($BU21,$BY$4:$CA$34,2,FALSE) -> Slovakia | BW21: =VLOOKUP($BU21,$BY$4:$CA$34,3,FALSE) -> 3.5965286 | BY21: =RANK(CA21,$CA$4:$CA$34) -> 29 | BZ21: Israel | CA21: 2.4090049 | CC21: 2024-25 | CD21: =100*(CG21/$CG$20) -> 102.14023 | CE21: 100 | CG21: 1423.377 | DL21: =100*(DT21/AVERAGE(DT$12:DT$15)) -> 102.45734 | DM21: =100*(DU21/AVERAGE(DU$12:DU$15)) -> 106.38371 | DN21: =100*(DV21/AVERAGE(DV$12:DV$15)) -> 105.17799 | DO21: =100*(DW21/AVERAGE(DW$12:DW$15)) -> 104.44265 | DP21: =100*(DX21/AVERAGE(DX$12:DX$15)) -> 104.66146 | DQ21: =100*(DY21/AVERAGE(DY$12:DY$15)) -> 103.11815 | DT21: ='[2]1.1'!D70 -> 120.80166 | DU21: ='[3]1.1'!D70 -> 120.66396 | DV21: ='[4]1.1'!D70 -> 118.94579 | DW21: ='[5]1.1'!D70 -> 120.85295 | DX21: ='[6]1.1'!D70 -> 120.8013 | DY21: ='[7]1.1'!D70 -> 119.02
I22: 2018-19 | J22: =LEFT(I22,4) -> 2018 | K22: 80.3 | L22: 72.3 | M22: 66.982374 | N22: 58.905421 | P22: =K22-K21 -> -2 | Q22: =L22-L21 -> -1.4 | R22: =M22-M21 -> -3.2060891 | S22: =N22-N21 -> -4.1438817 | AA22: ='Aggregates (% GDP) Oct24'!B75 -> 2018-19 | AB22: =LEFT(AA22,4) -> 2018 | AC22: ='Aggregates (% GDP) Oct24'!F75 -> 2.100128 | AD22: ='Aggregates (% GDP) Mar24'!F75 -> 2.100128 | AE22: =AVERAGE($AD$8:$AD$27) -> 2.145275 | AH22: ='Aggregates (% GDP) Oct24'!B75 -> 2018-19 | AI22: =LEFT(AH22,4) -> 2018 | AJ22: =-('Aggregates (% GDP) Oct24'!M75-'Aggregates (% GDP) Oct24'!M74) -> -0.22729184 | BO22: 2025-26 | BP22: =100*(BS22/$BS$20) -> 100.4689 | BQ22: 100 | BS22: 6195.1797 | BU22: =+BU21+1 -> 19 | BV22: =VLOOKUP($BU22,$BY$4:$CA$34,2,FALSE) -> US | BW22: =VLOOKUP($BU22,$BY$4:$CA$34,3,FALSE) -> 3.5916962 | BY22: =RANK(CA22,$CA$4:$CA$34) -> 2 | BZ22: Korea | CA22: 4.956172 | CC22: 2025-26 | CD22: =100*(CG22/$CG$20) -> 99.07125 | CE22: 100 | CG22: 1380.6092 | DL22: =100*(DT22/AVERAGE(DT$12:DT$15)) -> 102.84668 | DM22: =100*(DU22/AVERAGE(DU$12:DU$15)) -> 106.54329 | DN22: =100*(DV22/AVERAGE(DV$12:DV$15)) -> 105.41809 | DO22: =100*(DW22/AVERAGE(DW$12:DW$15)) -> 105.06931 | DP22: =100*(DX22/AVERAGE(DX$12:DX$15)) -> 105.36942 | DQ22: =100*(DY22/AVERAGE(DY$12:DY$15)) -> 103.78939 | DT22: ='[2]1.1'!D71 -> 121.26071 | DU22: ='[3]1.1'!D71 -> 120.84496 | DV22: ='[4]1.1'!D71 -> 119.21731 | DW22: ='[5]1.1'!D71 -> 121.57806 | DX22: ='[6]1.1'!D71 -> 121.61844 | DY22: ='[7]1.1'!D71 -> 119.79476
I23: 2019-20 | J23: =LEFT(I23,4) -> 2019 | K23: 85.2 | L23: 77.1 | M23: 74.576335 | N23: 67.191349 | P23: =K23-K22 -> 4.9 | Q23: =L23-L22 -> 4.8 | R23: =M23-M22 -> 7.5939601 | S23: =N23-N22 -> 8.2859278 | AA23: ='Aggregates (% GDP) Oct24'!B76 -> 2019-20 | AB23: =LEFT(AA23,4) -> 2019 | AC23: ='Aggregates (% GDP) Oct24'!F76 -> 1.8937327 | AD23: ='Aggregates (% GDP) Mar24'!F76 -> 1.8960049 | AE23: =AVERAGE($AD$8:$AD$27) -> 2.145275 | AH23: ='Aggregates (% GDP) Oct24'!B76 -> 2019-20 | AI23: =LEFT(AH23,4) -> 2019 | AJ23: =-('Aggregates (% GDP) Oct24'!M76-'Aggregates (% GDP) Oct24'!M75) -> 1.0124527 | BO23: 2026-27 | BP23: =100*(BS23/$BS$20) -> 100.98314 | BQ23: 100 | BS23: 6226.8892 | BU23: =+BU22+1 -> 20 | BV23: =VLOOKUP($BU23,$BY$4:$CA$34,2,FALSE) -> Spain | BW23: =VLOOKUP($BU23,$BY$4:$CA$34,3,FALSE) -> 3.3271083 | BY23: =RANK(CA23,$CA$4:$CA$34) -> 3 | BZ23: Latvia | CA23: 4.7532364 | CC23: 2026-27 | CD23: =100*(CG23/$CG$20) -> 97.164108 | CE23: 100 | CG23: 1354.0321 | DL23: =100*(DT23/AVERAGE(DT$12:DT$15)) -> 103.24778 | DM23: =100*(DU23/AVERAGE(DU$12:DU$15)) -> 106.7031 | DN23: =100*(DV23/AVERAGE(DV$12:DV$15)) -> 105.77381 | DO23: =100*(DW23/AVERAGE(DW$12:DW$15)) -> 105.6577 | DP23: =100*(DX23/AVERAGE(DX$12:DX$15)) -> 105.92792 | DQ23: =100*(DY23/AVERAGE(DY$12:DY$15)) -> 105.62769 | DT23: ='[2]1.1'!D72 -> 121.73362 | DU23: ='[3]1.1'!D72 -> 121.02622 | DV23: ='[4]1.1'!D72 -> 119.6196 | DW23: ='[5]1.1'!D72 -> 122.2589 | DX23: ='[6]1.1'!D72 -> 122.26306 | DY23: ='[7]1.1'!D72 -> 121.91654
I24: 2020-21 | J24: =LEFT(I24,4) -> 2020 | K24: 96.5 | L24: 86.5 | M24: 83.079863 | N24: 73.560623 | P24: =K24-K23 -> 11.3 | Q24: =L24-L23 -> 9.4 | R24: =M24-M23 -> 8.5035288 | S24: =N24-N23 -> 6.3692739 | AA24: ='Aggregates (% GDP) Oct24'!B77 -> 2020-21 | AB24: =LEFT(AA24,4) -> 2020 | AC24: ='Aggregates (% GDP) Oct24'!F77 -> 3.4413002 | AD24: ='Aggregates (% GDP) Mar24'!F77 -> 3.4519952 | AE24: =AVERAGE($AD$8:$AD$27) -> 2.145275 | AH24: ='Aggregates (% GDP) Oct24'!B77 -> 2020-21 | AI24: =LEFT(AH24,4) -> 2020 | AJ24: =-('Aggregates (% GDP) Oct24'!M77-'Aggregates (% GDP) Oct24'!M76) -> 12.342741 | BO24: 2027-28 | BP24: =100*(BS24/$BS$20) -> 101.50633 | BQ24: 100 | BS24: 6259.1505 | BU24: =+BU23+1 -> 21 | BV24: =VLOOKUP($BU24,$BY$4:$CA$34,2,FALSE) -> Denmark | BW24: =VLOOKUP($BU24,$BY$4:$CA$34,3,FALSE) -> 3.2815288 | BY24: =RANK(CA24,$CA$4:$CA$34) -> 14 | BZ24: Lithuania | CA24: 3.8993341 | CC24: 2027-28 | CD24: =100*(CG24/$CG$20) -> 94.874097 | CE24: 100 | CG24: 1322.1197 | DK24: 2025 | DL24: =100*(DT24/AVERAGE(DT$12:DT$15)) -> 103.66077 | DM24: =100*(DU24/AVERAGE(DU$12:DU$15)) -> 106.89517 | DN24: =100*(DV24/AVERAGE(DV$12:DV$15)) -> 106.14076 | DO24: =100*(DW24/AVERAGE(DW$12:DW$15)) -> 106.17542 | DP24: =100*(DX24/AVERAGE(DX$12:DX$15)) -> 106.38239 | DQ24: =100*(DY24/AVERAGE(DY$12:DY$15)) -> 106.92982 | DS24: 2025 | DT24: ='[2]1.1'!D73 -> 122.22056 | DU24: ='[3]1.1'!D73 -> 121.24407 | DV24: ='[4]1.1'!D73 -> 120.03458 | DW24: ='[5]1.1'!D73 -> 122.85797 | DX24: ='[6]1.1'!D73 -> 122.78761 | DY24: ='[7]1.1'!D73 -> 123.41947
I25: 2021-22 | J25: =LEFT(I25,4) -> 2021 | K25: 96.6 | L25: 83.2 | M25: 80.629863 | N25: 67.135032 | P25: =K25-K24 -> 0.1 | Q25: =L25-L24 -> -3.3 | R25: =M25-M24 -> -2.4500005 | S25: =N25-N24 -> -6.4255903 | AA25: ='Aggregates (% GDP) Oct24'!B78 -> 2021-22 | AB25: =LEFT(AA25,4) -> 2021 | AC25: ='Aggregates (% GDP) Oct24'!F78 -> 2.2556225 | AD25: ='Aggregates (% GDP) Mar24'!F78 -> 2.3021101 | AE25: =AVERAGE($AD$8:$AD$27) -> 2.145275 | AH25: ='Aggregates (% GDP) Oct24'!B78 -> 2021-22 | AI25: =LEFT(AH25,4) -> 2021 | AJ25: =-('Aggregates (% GDP) Oct24'!M78-'Aggregates (% GDP) Oct24'!M77) -> -10.050778 | BO25: 2028-29 | BP25: =100*(BS25/$BS$20) -> 101.96151 | BQ25: 100 | BS25: 6287.2179 | BU25: =+BU24+1 -> 22 | BV25: =VLOOKUP($BU25,$BY$4:$CA$34,2,FALSE) -> Australia | BW25: =VLOOKUP($BU25,$BY$4:$CA$34,3,FALSE) -> 3.1343494 | BY25: =RANK(CA25,$CA$4:$CA$34) -> 10 | BZ25: Luxembourg | CA25: 4.1890307 | CC25: 2028-29 | CD25: =100*(CG25/$CG$20) -> 91.6701 | CE25: 100 | CG25: 1277.4703 | DL25: =100*(DT25/AVERAGE(DT$12:DT$15)) -> 104.08578 | DM25: =100*(DU25/AVERAGE(DU$12:DU$15)) -> 107.1624 | DN25: =100*(DV25/AVERAGE(DV$12:DV$15)) -> 106.36054 | DO25: =100*(DW25/AVERAGE(DW$12:DW$15)) -> 106.68032 | DP25: =100*(DX25/AVERAGE(DX$12:DX$15)) -> 106.75948 | DQ25: =100*(DY25/AVERAGE(DY$12:DY$15)) -> 107.48393 | DT25: ='[2]1.1'!D74 -> 122.72166 | DU25: ='[3]1.1'!D74 -> 121.54718 | DV25: ='[4]1.1'!D74 -> 120.28313 | DW25: ='[5]1.1'!D74 -> 123.4422 | DX25: ='[6]1.1'!D74 -> 123.22286 | DY25: ='[7]1.1'!D74 -> 124.05903
I26: 2022-23 | J26: =LEFT(I26,4) -> 2022 | K26: 95.7 | L26: 84.8 | M26: 81.31136 | N26: 69.332774 | P26: =K26-K25 -> -0.9 | Q26: =L26-L25 -> 1.6 | R26: =M26-M25 -> 0.68149667 | S26: =N26-N25 -> 2.1977416 | AA26: ='Aggregates (% GDP) Oct24'!B79 -> 2022-23 | AB26: =LEFT(AA26,4) -> 2022 | AC26: ='Aggregates (% GDP) Oct24'!F79 -> 1.79943 | AD26: ='Aggregates (% GDP) Mar24'!F79 -> 1.7982158 | AE26: =AVERAGE($AD$8:$AD$27) -> 2.145275 | AH26: ='Aggregates (% GDP) Oct24'!B79 -> 2022-23 | AI26: =LEFT(AH26,4) -> 2022 | AJ26: =-('Aggregates (% GDP) Oct24'!M79-'Aggregates (% GDP) Oct24'!M78) -> -2.0594822 | BU26: =+BU25+1 -> 23 | BV26: =VLOOKUP($BU26,$BY$4:$CA$34,2,FALSE) -> Austria | BW26: =VLOOKUP($BU26,$BY$4:$CA$34,3,FALSE) -> 3.0502152 | BY26: =RANK(CA26,$CA$4:$CA$34) -> 16 | BZ26: Netherlands | CA26: 3.7365702 | DL26: =100*(DT26/AVERAGE(DT$12:DT$15)) -> 104.53335 | DM26: =100*(DU26/AVERAGE(DU$12:DU$15)) -> 107.48389 | DN26: =100*(DV26/AVERAGE(DV$12:DV$15)) -> 106.64407 | DO26: =100*(DW26/AVERAGE(DW$12:DW$15)) -> 107.08886 | DP26: =100*(DX26/AVERAGE(DX$12:DX$15)) -> 107.02354 | DQ26: =100*(DY26/AVERAGE(DY$12:DY$15)) -> 108.01804 | DT26: ='[2]1.1'!D75 -> 123.24936 | DU26: ='[3]1.1'!D75 -> 121.91182 | DV26: ='[4]1.1'!D75 -> 120.60378 | DW26: ='[5]1.1'!D75 -> 123.91492 | DX26: ='[6]1.1'!D75 -> 123.52764 | DY26: ='[7]1.1'!D75 -> 124.6755
I27: 2023-24 | J27: =LEFT(I27,4) -> 2023 | K27: 97.810368 | L27: 88.853958 | M27: 82.794795 | N27: 69.878037 | P27: =K27-K26 -> 2.1103679 | Q27: =L27-L26 -> 4.0539585 | R27: =M27-M26 -> 1.4834357 | S27: =N27-N26 -> 0.54526299 | AA27: ='Aggregates (% GDP) Oct24'!B80 -> 2023-24 | AB27: =LEFT(AA27,4) -> 2023 | AC27: ='Aggregates (% GDP) Oct24'!F80 -> 2.5565458 | AD27: ='Aggregates (% GDP) Mar24'!F80 -> 2.6051807 | AE27: =AVERAGE($AD$8:$AD$27) -> 2.145275 | AH27: ='Aggregates (% GDP) Oct24'!B80 -> 2023-24 | AI27: =LEFT(AH27,4) -> 2023 | AJ27: =-('Aggregates (% GDP) Oct24'!M80-'Aggregates (% GDP) Oct24'!M79) -> -0.20463319 | BU27: =+BU26+1 -> 24 | BV27: =VLOOKUP($BU27,$BY$4:$CA$34,2,FALSE) -> Portugal | BW27: =VLOOKUP($BU27,$BY$4:$CA$34,3,FALSE) -> 2.9605304 | BY27: =RANK(CA27,$CA$4:$CA$34) -> 7 | BZ27: Norway | CA27: 4.5081333 | DL27: =100*(DT27/AVERAGE(DT$12:DT$15)) -> 105.01421 | DM27: =100*(DU27/AVERAGE(DU$12:DU$15)) -> 107.86008 | DN27: =100*(DV27/AVERAGE(DV$12:DV$15)) -> 106.99168 | DO27: =100*(DW27/AVERAGE(DW$12:DW$15)) -> 107.50196 | DP27: =100*(DX27/AVERAGE(DX$12:DX$15)) -> 107.38918 | DQ27: =100*(DY27/AVERAGE(DY$12:DY$15)) -> 108.42934 | DT27: ='[2]1.1'!D76 -> 123.81631 | DU27: ='[3]1.1'!D76 -> 122.33851 | DV27: ='[4]1.1'!D76 -> 120.99689 | DW27: ='[5]1.1'!D76 -> 124.39293 | DX27: ='[6]1.1'!D76 -> 123.94967 | DY27: ='[7]1.1'!D76 -> 125.15023
I28: 2024-25 | J28: =LEFT(I28,4) -> 2024 | K28: 98.395587 | L28: 91.752913 | M28: 83.54479 | N28: 69.572316 | P28: =K28-K27 -> 0.58521875 | Q28: =L28-L27 -> 2.8989543 | R28: =M28-M27 -> 0.74999443 | S28: =N28-N27 -> -0.30572066 | AA28: ='Aggregates (% GDP) Oct24'!B81 -> 2024-25 | AB28: =LEFT(AA28,4) -> 2024 | AC28: ='Aggregates (% GDP) Oct24'!F81 -> 2.5585174 | AD28: ='Aggregates (% GDP) Mar24'!F81 -> 2.3896524 | AE28: =AVERAGE($AD$8:$AD$27) -> 2.145275 | AH28: ='Aggregates (% GDP) Oct24'!B81 -> 2024-25 | AI28: =LEFT(AH28,4) -> 2024 | AJ28: =-('Aggregates (% GDP) Oct24'!M81-'Aggregates (% GDP) Oct24'!M80) -> -0.18733025 | AK28: =-('Aggregates (% GDP) Mar24'!N81-'Aggregates (% GDP) Mar24'!N80) -> -1.1415503 | BU28: =+BU27+1 -> 25 | BV28: =VLOOKUP($BU28,$BY$4:$CA$34,2,FALSE) -> Switzerland | BW28: =VLOOKUP($BU28,$BY$4:$CA$34,3,FALSE) -> 2.9605102 | BY28: =RANK(CA28,$CA$4:$CA$34) -> 8 | BZ28: Poland | CA28: 4.29505 | DK28: 2026 | DL28: =100*(DT28/AVERAGE(DT$12:DT$15)) -> 105.56028 | DM28: =100*(DU28/AVERAGE(DU$12:DU$15)) -> 108.29152 | DN28: =100*(DV28/AVERAGE(DV$12:DV$15)) -> 107.45728 | DO28: =100*(DW28/AVERAGE(DW$12:DW$15)) -> 107.91957 | DP28: =100*(DX28/AVERAGE(DX$12:DX$15)) -> 107.80133 | DQ28: =100*(DY28/AVERAGE(DY$12:DY$15)) -> 108.88743 | DS28: 2026 | DT28: ='[2]1.1'!D77 -> 124.46016 | DU28: ='[3]1.1'!D77 -> 122.82787 | DV28: ='[4]1.1'!D77 -> 121.52344 | DW28: ='[5]1.1'!D77 -> 124.87617 | DX28: ='[6]1.1'!D77 -> 124.42537 | DY28: ='[7]1.1'!D77 -> 125.67896
I29: 2025-26 | J29: =LEFT(I29,4) -> 2025 | K29: 96.921744 | L29: 93.140493 | M29: 83.791436 | N29: 69.261948 | P29: =K29-K28 -> -1.4738427 | Q29: =L29-L28 -> 1.3875805 | R29: =M29-M28 -> 0.24664648 | S29: =N29-N28 -> -0.31036835 | AA29: ='Aggregates (% GDP) Oct24'!B82 -> 2025-26 | AB29: =LEFT(AA29,4) -> 2025 | AC29: ='Aggregates (% GDP) Oct24'!F82 -> 2.6919811 | AD29: ='Aggregates (% GDP) Mar24'!F82 -> 2.1199635 | AE29: =AVERAGE($AD$8:$AD$27) -> 2.145275 | AH29: ='Aggregates (% GDP) Oct24'!B82 -> 2025-26 | AI29: =LEFT(AH29,4) -> 2025 | AJ29: =-('Aggregates (% GDP) Oct24'!M82-'Aggregates (% GDP) Oct24'!M81) -> -0.76306604 | AK29: =-('Aggregates (% GDP) Mar24'!N82-'Aggregates (% GDP) Mar24'!N81) -> -0.57313333 | BU29: =+BU28+1 -> 26 | BV29: =VLOOKUP($BU29,$BY$4:$CA$34,2,FALSE) -> Ireland | BW29: =VLOOKUP($BU29,$BY$4:$CA$34,3,FALSE) -> 2.8311903 | BY29: =RANK(CA29,$CA$4:$CA$34) -> 24 | BZ29: Portugal | CA29: 2.9605304 | DL29: =100*(DT29/AVERAGE(DT$12:DT$15)) -> 106.1303 | DM29: =100*(DU29/AVERAGE(DU$12:DU$15)) -> 108.83298 | DN29: =100*(DV29/AVERAGE(DV$12:DV$15)) -> 107.93466 | DO29: =100*(DW29/AVERAGE(DW$12:DW$15)) -> 108.33983 | DP29: =100*(DX29/AVERAGE(DX$12:DX$15)) -> 108.25083 | DQ29: =100*(DY29/AVERAGE(DY$12:DY$15)) -> 109.14042 | DT29: ='[2]1.1'!D78 -> 125.13224 | DU29: ='[3]1.1'!D78 -> 123.44201 | DV29: ='[4]1.1'!D78 -> 122.06331 | DW29: ='[5]1.1'!D78 -> 125.36246 | DX29: ='[6]1.1'!D78 -> 124.94419 | DY29: ='[7]1.1'!D78 -> 125.97096
I30: 2026-27 | J30: =LEFT(I30,4) -> 2026 | K30: 96.966301 | L30: 94.384386 | M30: 84.227751 | N30: 69.189137 | P30: =K30-K29 -> 0.044556571 | Q30: =L30-L29 -> 1.2438926 | R30: =M30-M29 -> 0.43631488 | S30: =N30-N29 -> -0.072811329 | AA30: ='Aggregates (% GDP) Oct24'!B83 -> 2026-27 | AB30: =LEFT(AA30,4) -> 2026 | AC30: ='Aggregates (% GDP) Oct24'!F83 -> 2.7207402 | AD30: ='Aggregates (% GDP) Mar24'!F83 -> 1.9804928 | AE30: =AVERAGE($AD$8:$AD$27) -> 2.145275 | AH30: ='Aggregates (% GDP) Oct24'!B83 -> 2026-27 | AI30: =LEFT(AH30,4) -> 2026 | AJ30: =-('Aggregates (% GDP) Oct24'!M83-'Aggregates (% GDP) Oct24'!M82) -> -0.52998375 | AK30: =-('Aggregates (% GDP) Mar24'!N83-'Aggregates (% GDP) Mar24'!N82) -> -0.3785978 | BU30: =+BU29+1 -> 27 | BV30: =VLOOKUP($BU30,$BY$4:$CA$34,2,FALSE) -> UK | BW30: =VLOOKUP($BU30,$BY$4:$CA$34,3,FALSE) -> 2.814318 | BY30: =RANK(CA30,$CA$4:$CA$34) -> 18 | BZ30: Slovakia | CA30: 3.5965286 | DL30: =100*(DT30/AVERAGE(DT$12:DT$15)) -> 106.71402 | DM30: =100*(DU30/AVERAGE(DU$12:DU$15)) -> 109.37715 | DN30: =100*(DV30/AVERAGE(DV$12:DV$15)) -> 108.36016 | DO30: =100*(DW30/AVERAGE(DW$12:DW$15)) -> 108.75423 | DP30: =100*(DX30/AVERAGE(DX$12:DX$15)) -> 108.65971 | DQ30: =100*(DY30/AVERAGE(DY$12:DY$15)) -> 109.54207 | DT30: ='[2]1.1'!D79 -> 125.82047 | DU30: ='[3]1.1'!D79 -> 124.05922 | DV30: ='[4]1.1'!D79 -> 122.5445 | DW30: ='[5]1.1'!D79 -> 125.84197 | DX30: ='[6]1.1'!D79 -> 125.41612 | DY30: ='[7]1.1'!D79 -> 126.43455
I31: 2027-28 | J31: =LEFT(I31,4) -> 2027 | K31: 97.245969 | L31: 95.054134 | M31: 84.100989 | N31: 68.709184 | P31: =K31-K30 -> 0.27966853 | Q31: =L31-L30 -> 0.66974783 | R31: =M31-M30 -> -0.12676194 | S31: =N31-N30 -> -0.47995311 | AA31: ='Aggregates (% GDP) Oct24'!B84 -> 2027-28 | AB31: =LEFT(AA31,4) -> 2027 | AC31: ='Aggregates (% GDP) Oct24'!F84 -> 2.6234059 | AD31: ='Aggregates (% GDP) Mar24'!F84 -> 1.8204393 | AE31: =AVERAGE($AD$8:$AD$27) -> 2.145275 | AH31: ='Aggregates (% GDP) Oct24'!B84 -> 2027-28 | AI31: =LEFT(AH31,4) -> 2027 | AJ31: =-('Aggregates (% GDP) Oct24'!M84-'Aggregates (% GDP) Oct24'!M83) -> -0.69853767 | AK31: =-('Aggregates (% GDP) Mar24'!N84-'Aggregates (% GDP) Mar24'!N83) -> -0.60360284 | BU31: =+BU30+1 -> 28 | BV31: =VLOOKUP($BU31,$BY$4:$CA$34,2,FALSE) -> Italy | BW31: =VLOOKUP($BU31,$BY$4:$CA$34,3,FALSE) -> 2.7823445 | BY31: =RANK(CA31,$CA$4:$CA$34) -> 9 | BZ31: Slovenia | CA31: 4.2756384 | DL31: =100*(DT31/AVERAGE(DT$12:DT$15)) -> 107.31162 | DM31: =100*(DU31/AVERAGE(DU$12:DU$15)) -> 109.81466 | DN31: =100*(DV31/AVERAGE(DV$12:DV$15)) -> 108.94983 | DO31: =100*(DW31/AVERAGE(DW$12:DW$15)) -> 109.16886 | DP31: =100*(DX31/AVERAGE(DX$12:DX$15)) -> 109.07563 | DQ31: =100*(DY31/AVERAGE(DY$12:DY$15)) -> 109.97123 | DT31: ='[2]1.1'!D80 -> 126.52506 | DU31: ='[3]1.1'!D80 -> 124.55545 | DV31: ='[4]1.1'!D80 -> 123.21137 | DW31: ='[5]1.1'!D80 -> 126.32174 | DX31: ='[6]1.1'!D80 -> 125.89618 | DY31: ='[7]1.1'!D80 -> 126.9299
I32: 2028-29 | J32: =LEFT(I32,4) -> 2028 | K32: 97.339932 | L32: 95.607594 | M32: 83.872927 | N32: 68.377937 | P32: =K32-K31 -> 0.093962633 | Q32: =L32-L31 -> 0.55346059 | R32: =M32-M31 -> -0.22806211 | S32: =N32-N31 -> -0.33124701 | AA32: ='Aggregates (% GDP) Oct24'!B85 -> 2028-29 | AB32: =LEFT(AA32,4) -> 2028 | AC32: ='Aggregates (% GDP) Oct24'!F85 -> 2.4777518 | AD32: ='Aggregates (% GDP) Mar24'!F85 -> 1.6542068 | AE32: =AVERAGE($AD$8:$AD$27) -> 2.145275 | AH32: ='Aggregates (% GDP) Oct24'!B85 -> 2028-29 | AI32: =LEFT(AH32,4) -> 2028 | AJ32: =-('Aggregates (% GDP) Oct24'!M85-'Aggregates (% GDP) Oct24'!M84) -> -0.21076074 | AK32: =-('Aggregates (% GDP) Mar24'!N85-'Aggregates (% GDP) Mar24'!N84) -> -0.43227169 | BU32: =+BU31+1 -> 29 | BV32: =VLOOKUP($BU32,$BY$4:$CA$34,2,FALSE) -> Israel | BW32: =VLOOKUP($BU32,$BY$4:$CA$34,3,FALSE) -> 2.4090049 | BY32: =RANK(CA32,$CA$4:$CA$34) -> 20 | BZ32: Spain | CA32: 3.3271083 | DK32: 2027 | DL32: =100*(DT32/AVERAGE(DT$12:DT$15)) -> 107.91256 | DM32: =100*(DU32/AVERAGE(DU$12:DU$15)) -> 110.19901 | DN32: =100*(DV32/AVERAGE(DV$12:DV$15)) -> 109.48824 | DO32: =100*(DW32/AVERAGE(DW$12:DW$15)) -> 109.58372 | DP32: =100*(DX32/AVERAGE(DX$12:DX$15)) -> 109.4985 | DQ32: =100*(DY32/AVERAGE(DY$12:DY$15)) -> 110.42759 | DS32: 2027 | DT32: ='[2]1.1'!D81 -> 127.2336 | DU32: ='[3]1.1'!D81 -> 124.9914 | DV32: ='[4]1.1'!D81 -> 123.82025 | DW32: ='[5]1.1'!D81 -> 126.80178 | DX32: ='[6]1.1'!D81 -> 126.38427 | DY32: ='[7]1.1'!D81 -> 127.45663
I33: 2029-30 | J33: =LEFT(I33,4) -> 2029 | K33: 97.147985 | L33: 95.774656 | M33: 83.417751 | N33: 67.888123 | P33: =K33-K32 -> -0.19194677 | Q33: =L33-L32 -> 0.1670617 | R33: =M33-M32 -> -0.45517556 | S33: =N33-N32 -> -0.48981329 | AA33: ='Aggregates (% GDP) Oct24'!B86 -> 2029-30 | AB33: =LEFT(AA33,4) -> 2029 | AC33: ='Aggregates (% GDP) Oct24'!F86 -> 2.3699287 | AE33: =AVERAGE($AD$8:$AD$27) -> 2.145275 | AH33: ='Aggregates (% GDP) Oct24'!B86 -> 2029-30 | AI33: =LEFT(AH33,4) -> 2029 | AJ33: =-('Aggregates (% GDP) Oct24'!M86-'Aggregates (% GDP) Oct24'!M85) -> -0.18679438 | BU33: =+BU32+1 -> 30 | BV33: =VLOOKUP($BU33,$BY$4:$CA$34,2,FALSE) -> Belgium | BW33: =VLOOKUP($BU33,$BY$4:$CA$34,3,FALSE) -> 2.3573553 | BY33: =RANK(CA33,$CA$4:$CA$34) -> 6 | BZ33: Sweden | CA33: 4.5506017 | DM33: =100*(DU33/AVERAGE(DU$12:DU$15)) -> 110.5847 | DN33: =100*(DV33/AVERAGE(DV$12:DV$15)) -> 110.02931 | DO33: =100*(DW33/AVERAGE(DW$12:DW$15)) -> 109.97769 | DP33: =100*(DX33/AVERAGE(DX$12:DX$15)) -> 109.90615 | DQ33: =100*(DY33/AVERAGE(DY$12:DY$15)) -> 110.88451 | DU33: ='[3]1.1'!D82 -> 125.42887 | DV33: ='[4]1.1'!D82 -> 124.43215 | DW33: ='[5]1.1'!D82 -> 127.25766 | DX33: ='[6]1.1'!D82 -> 126.85478 | DY33: ='[7]1.1'!D82 -> 127.98401
BU34: =+BU33+1 -> 31 | BV34: =VLOOKUP($BU34,$BY$4:$CA$34,2,FALSE) -> Germany | BW34: =VLOOKUP($BU34,$BY$4:$CA$34,3,FALSE) -> 2.2421639 | BY34: =RANK(CA34,$CA$4:$CA$34) -> 25 | BZ34: Switzerland | CA34: 2.9605102 | DM34: =100*(DU34/AVERAGE(DU$12:DU$15)) -> 110.97175 | DN34: =100*(DV34/AVERAGE(DV$12:DV$15)) -> 110.46472 | DO34: =100*(DW34/AVERAGE(DW$12:DW$15)) -> 110.38951 | DP34: =100*(DX34/AVERAGE(DX$12:DX$15)) -> 110.32585 | DQ34: =100*(DY34/AVERAGE(DY$12:DY$15)) -> 111.33713 | DU34: ='[3]1.1'!D83 -> 125.86787 | DV34: ='[4]1.1'!D83 -> 124.92455 | DW34: ='[5]1.1'!D83 -> 127.73418 | DX34: ='[6]1.1'!D83 -> 127.3392 | DY34: ='[7]1.1'!D83 -> 128.50642
DM35: =100*(DU35/AVERAGE(DU$12:DU$15)) -> 111.41564 | DN35: =100*(DV35/AVERAGE(DV$12:DV$15)) -> 110.95869 | DO35: =100*(DW35/AVERAGE(DW$12:DW$15)) -> 110.82074 | DP35: =100*(DX35/AVERAGE(DX$12:DX$15)) -> 110.7659 | DQ35: =100*(DY35/AVERAGE(DY$12:DY$15)) -> 111.81399 | DU35: ='[3]1.1'!D84 -> 126.37134 | DV35: ='[4]1.1'!D84 -> 125.48319 | DW35: ='[5]1.1'!D84 -> 128.23318 | DX35: ='[6]1.1'!D84 -> 127.84711 | DY35: ='[7]1.1'!D84 -> 129.05683
I36: 23-24 | K36: 97.6 | L36: 88.8 | M36: 82.9 | N36: 69.5 | DK36: 2028 | DM36: =100*(DU36/AVERAGE(DU$12:DU$15)) -> 111.8613 | DN36: =100*(DV36/AVERAGE(DV$12:DV$15)) -> 111.45645 | DO36: =100*(DW36/AVERAGE(DW$12:DW$15)) -> 111.27118 | DP36: =100*(DX36/AVERAGE(DX$12:DX$15)) -> 111.22606 | DQ36: =100*(DY36/AVERAGE(DY$12:DY$15)) -> 112.31481 | DS36: 2028 | DU36: ='[3]1.1'!D85 -> 126.87682 | DV36: ='[4]1.1'!D85 -> 126.0461 | DW36: ='[5]1.1'!D85 -> 128.75439 | DX36: ='[6]1.1'!D85 -> 128.37823 | DY36: ='[7]1.1'!D85 -> 129.63488
I37: 24-25 | K37: 98.8 | L37: 91.7 | M37: 83.6 | N37: 70.2 | DO37: =100*(DW37/AVERAGE(DW$12:DW$15)) -> 111.72668 | DP37: =100*(DX37/AVERAGE(DX$12:DX$15)) -> 111.72816 | DQ37: =100*(DY37/AVERAGE(DY$12:DY$15)) -> 112.82674 | DW37: ='[5]1.1'!D86 -> 129.28145 | DX37: ='[6]1.1'!D86 -> 128.95775 | DY37: ='[7]1.1'!D86 -> 130.22575
I38: 25-26 | K38: 96.4 | L38: 92.8 | M38: 83.2 | N38: 69.5 | DO38: =100*(DW38/AVERAGE(DW$12:DW$15)) -> 112.18004 | DP38: =100*(DX38/AVERAGE(DX$12:DX$15)) -> 112.15481 | DQ38: =100*(DY38/AVERAGE(DY$12:DY$15)) -> 113.32308 | DW38: ='[5]1.1'!D87 -> 129.80605 | DX38: ='[6]1.1'!D87 -> 129.4502 | DY38: ='[7]1.1'!D87 -> 130.79864
I39: 26-27 | K39: 95.5 | L39: 93.2 | M39: 82.1 | N39: 67.9 | DO39: =100*(DW39/AVERAGE(DW$12:DW$15)) -> 112.63557 | DP39: =100*(DX39/AVERAGE(DX$12:DX$15)) -> 112.60215 | DQ39: =100*(DY39/AVERAGE(DY$12:DY$15)) -> 113.82968 | DW39: ='[5]1.1'!D88 -> 130.33315 | DX39: ='[6]1.1'!D88 -> 129.96653 | DY39: ='[7]1.1'!D88 -> 131.38336
I40: 27-28 | K40: 95.1 | L40: 93.2 | M40: 80.6 | N40: 66 | DK40: 2029 | DO40: =100*(DW40/AVERAGE(DW$12:DW$15)) -> 113.09324 | DP40: =100*(DX40/AVERAGE(DX$12:DX$15)) -> 113.06995 | DQ40: =100*(DY40/AVERAGE(DY$12:DY$15)) -> 114.3464 | DS40: 2029 | DW40: ='[5]1.1'!D89 -> 130.86273 | DX40: ='[6]1.1'!D89 -> 130.50646 | DY40: ='[7]1.1'!D89 -> 131.97976
I41: 28-29 | K41: 94.3 | L41: 92.9 | M41: 78.7 | N41: 63.9 | DQ41: =100*(DY41/AVERAGE(DY$12:DY$15)) -> 114.87047 | DY41: ='[7]1.1'!D90 -> 132.58464
DQ42: =100*(DY42/AVERAGE(DY$12:DY$15)) -> 115.3758 | DY42: ='[7]1.1'!D91 -> 133.1679
DQ43: =100*(DY43/AVERAGE(DY$12:DY$15)) -> 115.89158 | DY43: ='[7]1.1'!D92 -> 133.76322
DK44: 2030 | DQ44: =100*(DY44/AVERAGE(DY$12:DY$15)) -> 116.41765 | DS44: 2030 | DY44: ='[7]1.1'!D93 -> 134.37042

Sheet GMWA
A1: Location | B1: Indicator | C1: Scenario | D1: Units | E1: Scale | F1: Measurement | G1: 1973 | H1: 1974 | I1: 1975 | J1: 1976 | K1: 1977 | L1: 1978 | M1: 1979 | N1: 1980 | O1: 1981 | P1: 1982 | Q1: 1983 | R1: 1984 | S1: 1985 | T1: 1986 | U1: 1987 | V1: 1988 | W1: 1989 | X1: 1990 | Y1: 1991 | Z1: 1992 | AA1: 1993 | AB1: 1994 | AC1: 1995 | AD1: 1996 | AE1: 1997 | AF1: 1998 | AG1: 1999 | AH1: 2000 | AI1: 2001 | AJ1: 2002 | AK1: 2003 | AL1: 2004 | AM1: 2005 | AN1: 2006 | AO1: 2007 | AP1: 2008 | AQ1: 2009 | AR1: 2010 | AS1: 2011 | AT1: 2012 | AU1: 2013 | AV1: 2014 | AW1: 2015 | AX1: 2016 | AY1: 2017 | AZ1: 2018 | BA1: 2019 | BB1: 2020 | BC1: 2021 | BD1: 2022 | BE1: 2023 | BF1: 2024 | BG1: 2025 | BH1: 2026 | BI1: 2027 | BJ1: 2028 | BK1: 2029 | BL1: 2030 | BM1: 2031 | BN1: 2032 | BO1: 2033 | BP1: 2034 | BQ1: 2035 | BR1: 2036 | BS1: 2037 | BT1: 2038 | BU1: 2039 | BV1: 2040 | BW1: 2041 | BX1: 2042 | BY1: 2043 | BZ1: 2044 | CA1: 2045 | CB1: 2046 | CC1: 2047 | CD1: 2048 | CE1: 2049 | CF1: 2050 | CG1: Source | CH1: Seasonally adjusted | CI1: Base year price | CJ1: Base year index | CK1: Historical end year | CL1: Historical end quarter | CM1: Date of last update | CN1: Source details | CO1: Additional source details | CP1: Location code | CQ1: Indicator code | CR1: Databank code
A2: United Kingdom | B2: GDP, nominal, LCU | C2: OCT031G | D2: Pound | E2: Millions | F2: Level | G2: 81793 | H2: 92673 | I2: 115093 | J2: 136999 | K2: 159786 | L2: 186158 | M2: 220981 | N2: 259970 | O2: 290180 | P2: 319558 | Q2: 351347 | R2: 377920 | S2: 414630 | T2: 446600 | U2: 496809 | V2: 555683 | W2: 614631 | X2: 670797 | Y2: 705884 | Z2: 730874 | AA2: 769855 | AB2: 810794 | AC2: 851845 | AD2: 909993 | AE2: 953405 | AF2: 998501 | AG2: 1043248 | AH2: 1100752 | AI2: 1146135 | AJ2: 1191439 | AK2: 1258334 | AL2: 1322637 | AM2: 1398749 | AN2: 1472038 | AO2: 1544637 | AP2: 1593600 | AQ2: 1548802 | AR2: 1608553 | AS2: 1662590 | AT2: 1713715 | AU2: 1781361 | AV2: 1862514 | AW2: 1916451 | AX2: 1991645 | AY2: 2082482 | AZ2: 2152304 | BA2: 2233921 | BB2: 2103486 | BC2: 2285400 | BD2: 2526428 | BE2: 2720029 | BF2: 2825798 | BG2: 2942997 | BH2: 3054124 | BI2: 3168058 | BJ2: 3285407 | BK2: 3405834 | BL2: 3533583 | BM2: 3666656 | BN2: 3803129 | BO2: 3945091 | BP2: 4091992 | BQ2: 4243622 | BR2: 4402689 | BS2: 4568676 | BT2: 4742214 | BU2: 4923252 | BV2: 5111438 | BW2: 5305361 | BX2: 5505381 | BY2: 5712474 | BZ2: 5926900 | CA2: 6148733 | CB2: 6378278 | CC2: 6615900 | CD2: 6861886 | CE2: 7116701 | CF2: 7380563 | CG2: Office for National Statistics\Haver Analytics | CH2: TRUE | CI2: NA | CJ2: NA | CK2: 2024 | CL2: 2 | CM2: NA | CN2: YBHAQ@UK | CO2: U.K.: Gross Domestic Product (SA, Mil.Pounds) | CP2: GBR | CQ2: GDP! | CR2: OCT031G.db
A3: Canada | B3: GDP, nominal, LCU | C3: OCT031G | D3: C$ | E3: Millions | F3: Level | G3: 132966 | H3: 158176 | I3: 177928 | J3: 205986 | K3: 227601 | L3: 252075 | M3: 287608 | N3: 322782 | O3: 368358 | P3: 388181 | Q3: 421316 | R3: 461986 | S3: 500027 | T3: 526630 | U3: 574336 | V3: 626894 | W3: 671579 | X3: 695501 | Y3: 701773 | Z3: 718436 | AA3: 747037 | AB3: 791972 | AC3: 831621 | AD3: 859834 | AE3: 906926 | AF3: 940548 | AG3: 1007927 | AH3: 1106071 | AI3: 1144543 | AJ3: 1193694 | AK3: 1254747 | AL3: 1335731 | AM3: 1421590 | AN3: 1496604 | AO3: 1577661 | AP3: 1657041 | AQ3: 1571334 | AR3: 1666048 | AS3: 1774063 | AT3: 1827201 | AU3: 1902247 | AV3: 1994898 | AW3: 1990441 | AX3: 2025535 | AY3: 2140641 | AZ3: 2235675 | BA3: 2313563 | BB3: 2220527 | BC3: 2517123 | BD3: 2813289 | BE3: 2892140 | BF3: 2997733 | BG3: 3092623 | BH3: 3233068 | BI3: 3382360 | BJ3: 3527389 | BK3: 3674599 | BL3: 3825356 | BM3: 3976218 | BN3: 4129556 | BO3: 4289789 | BP3: 4457389 | BQ3: 4632151 | BR3: 4814400 | BS3: 5003948 | BT3: 5200267 | BU3: 5404938 | BV3: 5618031 | BW3: 5840686 | BX3: 6072584 | BY3: 6313593 | BZ3: 6562048 | CA3: 6817535 | CB3: 7082134 | CC3: 7356859 | CD3: 7640364 | CE3: 7933939 | CF3: 8236279 | CG3: Statistics Canada\Haver Analytics | CH3: TRUE | CI3: NA | CJ3: NA | CK3: 2024 | CL3: 2 | CM3: NA | CN3: V6E05783@CANADA/4 | CO3: Canada: Gross Domestic Product at Market Prices (SAAR, Mil.C$) | CP3: CAN | CQ3: GDP! | CR3: OCT031G.db
A4: United States | B4: GDP, nominal, LCU | C4: OCT031G | D4: US$ | E4: Billions | F4: Level | G4: 1425.375 | H4: 1545.25 | I4: 1684.9 | J4: 1873.425 | K4: 2081.825 | L4: 2351.6 | M4: 2627.325 | N4: 2857.325 | O4: 3207.025 | P4: 3343.8 | Q4: 3634.025 | R4: 4037.65 | S4: 4339 | T4: 4579.625 | U4: 4855.25 | V4: 5236.425 | W4: 5641.6 | X4: 5963.125 | Y4: 6158.125 | Z4: 6520.325 | AA4: 6858.55 | AB4: 7287.25 | AC4: 7639.75 | AD4: 8073.125 | AE4: 8577.551 | AF4: 9062.824 | AG4: 9631.175 | AH4: 10250.95 | AI4: 10581.92 | AJ4: 10929.1 | AK4: 11456.45 | AL4: 12217.17 | AM4: 13039.2 | AN4: 13815.6 | AO4: 14474.25 | AP4: 14769.85 | AQ4: 14478.05 | AR4: 15048.97 | AS4: 15599.73 | AT4: 16253.95 | AU4: 16880.68 | AV4: 17608.13 | AW4: 18295 | AX4: 18804.9 | AY4: 19612.1 | AZ4: 20656.53 | BA4: 21539.97 | BB4: 21354.13 | BC4: 23681.18 | BD4: 26006.9 | BE4: 27720.73 | BF4: 29160.45 | BG4: 30545.01 | BH4: 31903.08 | BI4: 33294.59 | BJ4: 34700.54 | BK4: 36118.07 | BL4: 37562.01 | BM4: 39041.32 | BN4: 40557.74 | BO4: 42127.67 | BP4: 43756.91 | BQ4: 45445.82 | BR4: 47195.18 | BS4: 49005.28 | BT4: 50877.04 | BU4: 52813.96 | BV4: 54817.35 | BW4: 56891.71 | BX4: 59041.82 | BY4: 61272.18 | BZ4: 63585.02 | CA4: 65979.88 | CB4: 68459.07 | CC4: 71026.23 | CD4: 73684.77 | CE4: 76436.81 | CF4: 79285.75 | CG4: Bureau of Economic Analysis\Haver Analytics | CH4: TRUE | CI4: NA | CJ4: NA | CK4: 2024 | CL4: 2 | CM4: NA | CN4: GDP@USNA / 4 | CO4: Gross Domestic Product (SAAR, Bil.$) / 4 | CP4: USA | CQ4: GDP! | CR4: OCT031G.db
A5: Australia | B5: GDP, nominal, LCU | C5: OCT031G | D5: AUS$ | E5: Millions | F5: Level | G5: 54994 | H5: 65665 | I5: 76567 | J5: 90305 | K5: 100551 | L5: 111269 | M5: 126789 | N5: 143160 | O5: 164055 | P5: 184094 | Q5: 199309 | R5: 224325 | S5: 249630 | T5: 271713 | U5: 304684 | V5: 345759 | W5: 389245 | X5: 414932 | Y5: 416413 | Z5: 432493 | AA5: 454555 | AB5: 482973 | AC5: 511360 | AD5: 542501 | AE5: 572994 | AF5: 606108 | AG5: 638396 | AH5: 687471 | AI5: 730418 | AJ5: 782300 | AK5: 830241 | AL5: 894372 | AM5: 964118 | AN5: 1039956 | AO5: 1133003 | AP5: 1235376 | AQ5: 1264795 | AR5: 1364535 | AS5: 1468292 | AT5: 1516049 | AU5: 1569690 | AV5: 1614450 | AW5: 1640230 | AX5: 1698731 | AY5: 1803229 | AZ5: 1897077 | BA5: 1996036 | BB5: 1976801 | BC5: 2206018 | BD5: 2480784 | BE5: 2618157 | BF5: 2708267 | BG5: 2777868 | BH5: 2910437 | BI5: 3062504 | BJ5: 3222673 | BK5: 3386615 | BL5: 3554997 | BM5: 3729276 | BN5: 3909253 | BO5: 4095485 | BP5: 4288564 | BQ5: 4486411 | BR5: 4690920 | BS5: 4903779 | BT5: 5121229 | BU5: 5346279 | BV5: 5579601 | BW5: 5822677 | BX5: 6075903 | BY5: 6339297 | BZ5: 6612139 | CA5: 6894348 | CB5: 7186216 | CC5: 7488065 | CD5: 7800258 | CE5: 8123203 | CF5: 8457310 | CG5: Australian Bureau of Statistics\Haver | CH5: TRUE | CI5: NA | CJ5: NA | CK5: 2024 | CL5: 2 | CM5: NA | CN5: AUSNGDP@ANZ | CO5: Australia: Gross Domestic Product (SA, Mil.A$) | CP5: AUS | CQ5: GDP! | CR5: OCT031G.db
A6: Japan | B6: GDP, nominal, LCU | C6: OCT031G | D6: Yen | E6: Billions | F6: Level | G6: 115345.4 | H6: 137675.5 | I6: 152524.1 | J6: 171384.2 | K6: 191055.8 | L6: 210468.7 | M6: 227860.6 | N6: 255596.3 | O6: 274362.5 | P6: 288540 | Q6: 301733.2 | R6: 319635.5 | S6: 340281.7 | T6: 357296.9 | U6: 373021.4 | V6: 400505.1 | W6: 428693.4 | X6: 460995.4 | Y6: 491194.5 | Z6: 504109.2 | AA6: 504425.6 | AB6: 510924.7 | AC6: 521521.9 | AD6: 535578.2 | AE6: 543807.8 | AF6: 536499.4 | AG6: 528637.3 | AH6: 535693.4 | AI6: 531940.2 | AJ6: 524579.2 | AK6: 524167.9 | AL6: 529352.7 | AM6: 532645.4 | AN6: 535173.9 | AO6: 539325.2 | AP6: 527838.9 | AQ6: 495051.7 | AR6: 505678.8 | AS6: 497674.6 | AT6: 500611.9 | AU6: 508966.7 | AV6: 518723.5 | AW6: 538031.8 | AX6: 544193.7 | AY6: 553045.9 | AZ6: 556551.3 | BA6: 557831.3 | BB6: 539403.9 | BC6: 553341.8 | BD6: 561868 | BE6: 592862.9 | BF6: 607079.6 | BG6: 613654.9 | BH6: 622395 | BI6: 634858.1 | BJ6: 649169.8 | BK6: 662758.9 | BL6: 674374.8 | BM6: 684923.9 | BN6: 695272.4 | BO6: 705750.4 | BP6: 715560.5 | BQ6: 724904.1 | BR6: 733917.1 | BS6: 742821.5 | BT6: 751675.5 | BU6: 760492 | BV6: 769578.1 | BW6: 779023.1 | BX6: 788890.1 | BY6: 799083.9 | BZ6: 809793.1 | CA6: 821266.6 | CB6: 833479.4 | CC6: 846304.3 | CD6: 859607.6 | CE6: 873293.1 | CF6: 887648.6 | CG6: Cabinet Office of Japan\Haver Analytics | CH6: TRUE | CI6: NA | CJ6: NA | CK6: 2024 | CL6: 2 | CM6: NA | CN6: N9DP2@JAPAN/4 | CO6: Japan: Gross Domestic Product (SAAR, Bil.Yen)/4 | CP6: JPN | CQ6: GDP! | CR6: OCT031G.db
A7: Korea, Rep. | B7: GDP, nominal, LCU | C7: OCT031G | D7: Won | E7: Billions | F7: Level | G7: 5728.101 | H7: 8192 | I7: 10926.4 | J7: 14998.2 | K7: 19283.6 | L7: 26067.8 | M7: 33578.7 | N7: 41167.3 | O7: 51472.8 | P7: 59366.3 | Q7: 70551.7 | R7: 81444.5 | S7: 91329 | T7: 106724.5 | U7: 126116.1 | V7: 151294.8 | W7: 171821.2 | X7: 207837.2 | Y7: 251284 | Z7: 287616.6 | AA7: 326623.7 | AB7: 386016.3 | AC7: 452853.3 | AD7: 508670.8 | AE7: 561678.8 | AF7: 556718.4 | AG7: 612925 | AH7: 675732.5 | AI7: 732723.1 | AJ7: 813225.4 | AK7: 868110.6 | AL7: 942885.3 | AM7: 995175.4 | AN7: 1045663 | AO7: 1134541 | AP7: 1202973 | AQ7: 1255306 | AR7: 1379460 | AS7: 1448576 | AT7: 1504674 | AU7: 1570938 | AV7: 1638485 | AW7: 1740776 | AX7: 1833027 | AY7: 1934234 | AZ7: 2006974 | BA7: 2040594 | BB7: 2058467 | BC7: 2221913 | BD7: 2323782 | BE7: 2401190 | BF7: 2569004 | BG7: 2719921 | BH7: 2833516 | BI7: 2946285 | BJ7: 3061796 | BK7: 3182173 | BL7: 3305945 | BM7: 3430523 | BN7: 3556612 | BO7: 3683923 | BP7: 3811969 | BQ7: 3940734 | BR7: 4071887 | BS7: 4202764 | BT7: 4334650 | BU7: 4467086 | BV7: 4601700 | BW7: 4738859 | BX7: 4877046 | BY7: 5015308 | BZ7: 5151545 | CA7: 5284319 | CB7: 5415161 | CC7: 5545111 | CD7: 5675783 | CE7: 5808975 | CF7: 5944039 | CG7: Bank of Korea \ Haver Analytics | CH7: TRUE | CI7: NA | CJ7: NA | CK7: 2024 | CL7: 2 | CM7: NA | CN7: S542NGDP@EMERGEPR | CO7: Gross Domestic Product (SA, Bil.Won) | CP7: KOR | CQ7: GDP! | CR7: OCT031G.db
A8: Taiwan | B8: GDP, nominal, LCU | C8: OCT031G | D8: NT$ | E8: Millions | F8: Level | G8: 418460 | H8: 560085 | I8: 601778 | J8: 721529 | K8: 845592 | L8: 1011422 | M8: 1219496 | N8: 1522495 | O8: 1804431 | P8: 1938023 | Q8: 2169446 | R8: 2418240 | S8: 2535056 | T8: 2965448 | U8: 3344935 | V8: 3615662 | W8: 4032464 | X8: 4474288 | Y8: 5018019 | Z8: 5609357 | AA8: 6200154 | AB8: 6779396 | AC8: 7391062 | AD8: 8031305 | AE8: 8705149 | AF8: 9366337 | AG8: 9804503 | AH8: 10328550 | AI8: 10119430 | AJ8: 10630910 | AK8: 10924030 | AL8: 11596240 | AM8: 12036680 | AN8: 12572590 | AO8: 13363920 | AP8: 13115100 | AQ8: 12919450 | AR8: 14060350 | AS8: 14262200 | AT8: 14677770 | AU8: 15270730 | AV8: 16258050 | AW8: 17055080 | AX8: 17555270 | AY8: 17983350 | AZ8: 18375020 | BA8: 18908630 | BB8: 19914810 | BC8: 21663230 | BD8: 22679840 | BE8: 23544960 | BF8: 25144530 | BG8: 26217250 | BH8: 27262640 | BI8: 28181160 | BJ8: 28987200 | BK8: 29729190 | BL8: 30450850 | BM8: 31170990 | BN8: 31919500 | BO8: 32685190 | BP8: 33460000 | BQ8: 34216630 | BR8: 34958910 | BS8: 35649240 | BT8: 36329940 | BU8: 36984100 | BV8: 37623810 | BW8: 38255550 | BX8: 38869220 | BY8: 39459360 | BZ8: 40048040 | CA8: 40634800 | CB8: 41218550 | CC8: 41798000 | CD8: 42374230 | CE8: 42946380 | CF8: 43513830 | CG8: Directorate-General of Budget, Accounting and Statistics\Haver Analytics | CH8: FALSE | CI8: NA | CJ8: NA | CK8: 2024 | CL8: 2 | CM8: NA | CN8: N528NGDP@EMERGEPR | CO8: Gross Domestic Product (GDP) | CP8: TAI | CQ8: GDP! | CR8: OCT031G.db
A9: Austria | B9: GDP, nominal, LCU | C9: OCT031G | D9: Euro | E9: Billions | F9: Level | G9: 34.91362 | H9: 38.8578 | I9: 41.2161 | J9: 45.4468 | K9: 50.31245 | L9: 53.13455 | M9: 57.99162 | N9: 62.14004 | O9: 67.06662 | P9: 76.30952 | Q9: 85.02529 | R9: 90.64369 | S9: 96.10147 | T9: 105.6946 | U9: 112.6491 | V9: 118.5614 | W9: 127.1467 | X9: 136.5323 | Y9: 146.1061 | Z9: 154.0962 | AA9: 159.713 | AB9: 167.6799 | AC9: 176.6078 | AD9: 182.3722 | AE9: 188.741 | AF9: 196.2383 | AG9: 203.5719 | AH9: 213.6987 | AI9: 220.462 | AJ9: 226.8721 | AK9: 231.9567 | AL9: 241.9611 | AM9: 253.9304 | AN9: 267.8909 | AO9: 283.747 | AP9: 293.6742 | AQ9: 287.9106 | AR9: 295.5378 | AS9: 310.0912 | AT9: 318.6825 | AU9: 323.7637 | AV9: 333.3371 | AW9: 344.2841 | AX9: 357.5813 | AY9: 369.5461 | AZ9: 385.255 | BA9: 397.0386 | BB9: 380.3262 | BC9: 405.0767 | BD9: 447.2757 | BE9: 478.6163 | BF9: 490.7336 | BG9: 502.5448 | BH9: 519.4548 | BI9: 541.6214 | BJ9: 564.9509 | BK9: 589.4691 | BL9: 614.9407 | BM9: 641.5595 | BN9: 669.2448 | BO9: 697.2087 | BP9: 723.2709 | BQ9: 747.5597 | BR9: 771.0039 | BS9: 794.6572 | BT9: 819.1644 | BU9: 844.5794 | BV9: 870.6538 | BW9: 897.5593 | BX9: 925.3297 | BY9: 953.872 | BZ9: 983.1064 | CA9: 1012.817 | CB9: 1042.839 | CC9: 1073.262 | CD9: 1104.447 | CE9: 1136.51 | CF9: 1169.399 | CG9: Statistical Office of the European Communities\Haver Analytics | CH9: TRUE | CI9: NA | CJ9: NA | CK9: 2024 | CL9: 2 | CM9: NA | CN9: J122GDPN@EUDATA/1000 | CO9: Austria: Gross Domestic Product (SWDA, Mil.EUR) | CP9: AUT | CQ9: GDP! | CR9: OCT031G.db
A10: Belgium | B10: GDP, nominal, LCU | C10: OCT031G | D10: Euro | E10: Billions | F10: Level | G10: 45.52564 | H10: 53.37438 | I10: 59.00858 | J10: 67.02715 | K10: 72.41644 | L10: 77.72559 | M10: 83.00247 | N10: 89.064 | O10: 93.778 | P10: 101.472 | Q10: 107.58 | R10: 115.858 | S10: 123.41 | T10: 129.209 | U10: 134.524 | V10: 143.735 | W10: 156.089 | X10: 165.4 | Y10: 173.207 | Z10: 181.521 | AA10: 187.468 | AB10: 197.686 | AC10: 210.494 | AD10: 214.284 | AE10: 224.098 | AF10: 232.623 | AG10: 242.304 | AH10: 256.391 | AI10: 264.334 | AJ10: 273.253 | AK10: 281.196 | AL10: 296.813 | AM10: 310.045 | AN10: 325.163 | AO10: 343.615 | AP10: 351.733 | AQ10: 346.473 | AR10: 363.14 | AS10: 375.968 | AT10: 386.174 | AU10: 392.88 | AV10: 403.003 | AW10: 416.701 | AX10: 430.084 | AY10: 445.05 | AZ10: 460.05 | BA10: 478.676 | BB10: 460.535 | BC10: 508.061 | BD10: 554.213 | BE10: 584.698 | BF10: 610.0013 | BG10: 639.1642 | BH10: 662.2948 | BI10: 685.0191 | BJ10: 708.4242 | BK10: 736.2504 | BL10: 765.3491 | BM10: 792.2235 | BN10: 817.9332 | BO10: 843.6461 | BP10: 870.1347 | BQ10: 897.6048 | BR10: 925.649 | BS10: 953.869 | BT10: 982.2334 | BU10: 1011.01 | BV10: 1040.083 | BW10: 1069.777 | BX10: 1100.232 | BY10: 1131.331 | BZ10: 1162.896 | CA10: 1194.942 | CB10: 1227.317 | CC10: 1260.163 | CD10: 1293.452 | CE10: 1327.516 | CF10: 1362.478 | CG10: Banque Nationale de Belgique\Haver Analytics | CH10: TRUE | CI10: NA | CJ10: NA | CK10: 2024 | CL10: 2 | CM10: NA | CN10: BESNGDP@BENELUX/1000 | CO10: Belgium: Gross Domestic Product (SA/WDA, Mil.Euros) | CP10: BEL | CQ10: GDP! | CR10: OCT031G.db
A11: Denmark | B11: GDP, nominal, LCU | C11: OCT031G | D11: Kroner | E11: Billions | F11: Level | G11: 0.004 | H11: 0.004 | I11: 0.004 | J11: 0.004 | K11: 285.7351 | L11: 318.5398 | M11: 354.8728 | N11: 382.3844 | O11: 417.1718 | P11: 475.1505 | Q11: 524.3302 | R11: 578.2886 | S11: 629.22 | T11: 681.8278 | U11: 716.0104 | V11: 765.487 | W11: 806.7407 | X11: 855.375 | Y11: 890.267 | Z11: 923.32 | AA11: 927.92 | AB11: 992.368 | AC11: 1035.595 | AD11: 1087.146 | AE11: 1144.173 | AF11: 1185.218 | AG11: 1240.98 | AH11: 1325.983 | AI11: 1372.277 | AJ11: 1411.48 | AK11: 1438.894 | AL11: 1509.675 | AM11: 1590.078 | AN11: 1685.241 | AO11: 1743.143 | AP11: 1809.721 | AQ11: 1729.529 | AR11: 1812.896 | AS11: 1848.531 | AT11: 1892.938 | AU11: 1935.555 | AV11: 1980.262 | AW11: 2030.206 | AX11: 2101.52 | AY11: 2189.589 | AZ11: 2243.542 | BA11: 2303.637 | BB11: 2326.591 | BC11: 2567.519 | BD11: 2844.228 | BE11: 2804.742 | BF11: 2906.673 | BG11: 3024.761 | BH11: 3156.506 | BI11: 3302.318 | BJ11: 3442.687 | BK11: 3584.773 | BL11: 3726.613 | BM11: 3866.708 | BN11: 4005.82 | BO11: 4149.054 | BP11: 4296.239 | BQ11: 4444.589 | BR11: 4601.767 | BS11: 4768.809 | BT11: 4940.035 | BU11: 5115.487 | BV11: 5300.867 | BW11: 5491.17 | BX11: 5685.282 | BY11: 5888.177 | BZ11: 6098.751 | CA11: 6314.643 | CB11: 6532.995 | CC11: 6758.938 | CD11: 6994.32 | CE11: 7236.397 | CF11: 7485.534 | CG11: Danmarks Statistik\Haver Analytics | CH11: TRUE | CI11: NA | CJ11: NA | CK11: 2024 | CL11: 2 | CM11: NA | CN11: DKSNGDP@NORDIC/1000 | CO11: Denmark: Gross Domestic Product (SA, Mil.Krone) | CP11: DNK | CQ11: GDP! | CR11: OCT031G.db
A12: Finland | B12: GDP, nominal, LCU | C12: OCT031G | D12: Euro | E12: Billions | F12: Level | G12: 13.89584 | H12: 17.53783 | I12: 18.378 | J12: 20.789 | K12: 22.945 | L12: 25.397 | M12: 29.405 | N12: 33.936 | O12: 38.364 | P12: 43.12 | Q12: 48.133 | R12: 53.775 | S12: 58.516 | T12: 63.007 | U12: 68.466 | V12: 77.677 | W12: 86.802 | X12: 90.964 | Y12: 86.91299 | Z12: 84.786 | AA12: 85.61 | AB12: 90.646 | AC12: 98.454 | AD12: 101.977 | AE12: 110.764 | AF12: 120.431 | AG12: 126.888 | AH12: 136.386 | AI12: 144.613 | AJ12: 148.44 | AK12: 151.714 | AL12: 158.741 | AM12: 164.666 | AN12: 172.861 | AO12: 187.059 | AP12: 194.253 | AQ12: 181.735 | AR12: 188.147 | AS12: 197.655 | AT12: 200.378 | AU12: 203.497 | AV12: 205.855 | AW12: 210.192 | AX12: 215.717 | AY12: 224.706 | AZ12: 231.905 | BA12: 238.518 | BB12: 236.387 | BC12: 248.764 | BD12: 266.124 | BE12: 273.32 | BF12: 276.9979 | BG12: 285.566 | BH12: 296.0818 | BI12: 305.7861 | BJ12: 315.0244 | BK12: 324.0866 | BL12: 333.0002 | BM12: 341.3686 | BN12: 349.4287 | BO12: 357.5457 | BP12: 365.8568 | BQ12: 374.412 | BR12: 383.4621 | BS12: 392.4762 | BT12: 401.7072 | BU12: 411.2924 | BV12: 421.156 | BW12: 431.106 | BX12: 441.1664 | BY12: 451.4399 | BZ12: 461.966 | CA12: 472.7588 | CB12: 483.8026 | CC12: 495.1138 | CD12: 506.5658 | CE12: 518.1923 | CF12: 529.9004 | CG12: Tilastokeskus\Haver Analytics | CH12: TRUE | CI12: NA | CJ12: NA | CK12: 2024 | CL12: 2 | CM12: NA | CN12: FISNGDP@NORDIC /1000 | CO12: Finland: Gross Domestic Product (SWDA, Mil.EUR) /1000 | CP12: FIN | CQ12: GDP! | CR12: OCT031G.db
A13: France | B13: GDP, nominal, LCU | C13: OCT031G | D13: Euro | E13: Billions | F13: Level | G13: 177.825 | H13: 207.305 | I13: 233.583 | J13: 269.714 | K13: 303.907 | L13: 345.187 | M13: 394.491 | N13: 447.345 | O13: 504.566 | P13: 578.925 | Q13: 642.54 | R13: 699.5 | S13: 750.141 | T13: 807.92 | U13: 849.119 | V13: 917.11 | W13: 989.6 | X13: 1044.504 | Y13: 1083.784 | Z13: 1121.331 | AA13: 1134.273 | AB13: 1172.316 | AC13: 1214.909 | AD13: 1247.433 | AE13: 1290.111 | AF13: 1346.951 | AG13: 1394.054 | AH13: 1475.4 | AI13: 1531.277 | AJ13: 1580.375 | AK13: 1624.769 | AL13: 1692.953 | AM13: 1760.508 | AN13: 1848.094 | AO13: 1939.32 | AP13: 1989.256 | AQ13: 1936.898 | AR13: 1993.999 | AS13: 2061.122 | AT13: 2087.895 | AU13: 2122.946 | AV13: 2156.724 | AW13: 2202.681 | AX13: 2230.282 | AY13: 2294.591 | AZ13: 2356.953 | BA13: 2434.982 | BB13: 2317.093 | BC13: 2505.618 | BD13: 2654.006 | BE13: 2826.362 | BF13: 2922.719 | BG13: 2994.343 | BH13: 3087.488 | BI13: 3202.928 | BJ13: 3321.171 | BK13: 3440.682 | BL13: 3557.781 | BM13: 3673.863 | BN13: 3792.323 | BO13: 3911.701 | BP13: 4033.421 | BQ13: 4156.289 | BR13: 4281.051 | BS13: 4407.928 | BT13: 4537.039 | BU13: 4666.756 | BV13: 4798.898 | BW13: 4934.082 | BX13: 5074.696 | BY13: 5220.069 | BZ13: 5368.103 | CA13: 5517.558 | CB13: 5669.309 | CC13: 5819.724 | CD13: 5971.096 | CE13: 6125.781 | CF13: 6286.888 | CG13: Institut National de la Statistique et des Etudes Economiques\Haver Analytics | CH13: TRUE | CI13: NA | CJ13: NA | CK13: 2024 | CL13: 2 | CM13: NA | CN13: FRSNGDP@FRANCE/1000 | CO13: France: Gross Domestic Product (SA/WDA, Mil.Euros) | CP13: FRA | CQ13: GDP! | CR13: OCT031G.db
... A67: Switzerland | B67: Government debt, gross, LCU | C67: OCT031G | D67: CHF | E67: Billions | F67: Level | G67: 101.2708 | H67: 103.1809 | I67: 106.9809 | J67: 109.443 | K67: 111.0199 | L67: 112.7911 | M67: 117.2068 | N67: 119.8709 | O67: 119.4041 | P67: 117.3239 | Q67: 117.2889 | R67: 116.809 | S67: 114.5501 | T67: 110.1491 | U67: 106.4216 | V67: 102.8234 | W67: 100.2261 | X67: 99.06347 | Y67: 110.9729 | Z67: 133.7104 | AA67: 155.5503 | AB67: 165.0656 | AC67: 175.2516 | AD67: 183.1891 | AE67: 197.0585 | AF67: 211.854 | AG67: 199.5193 | AH67: 208.5233 | AI67: 205.2234 | AJ67: 226.6455 | AK67: 228.4095 | AL67: 231.1282 | AM67: 226.347 | AN67: 209.5417 | AO67: 200.1528 | AP67: 195.5485 | AQ67: 182.2513 | AR67: 182.2625 | AS67: 180.9895 | AT67: 190.1952 | AU67: 191.8382 | AV67: 196.5937 | AW67: 191.9227 | AX67: 186.6305 | AY67: 193.9496 | AZ67: 183.9719 | BA67: 182.8395 | BB67: 202.5084 | BC67: 206.4594 | BD67: 199.5809 | BE67: 199.1208 | BF67: 198.765 | BG67: 198.5644 | BH67: 198.1911 | BI67: 198.9263 | BJ67: 200.4855 | BK67: 202.8645 | BL67: 205.8969 | BM67: 209.7572 | BN67: 214.912 | BO67: 221.2681 | BP67: 228.9281 | BQ67: 237.72 | BR67: 247.6592 | BS67: 258.4451 | BT67: 270.0634 | BU67: 282.3909 | BV67: 295.5433 | BW67: 309.5484 | BX67: 324.4413 | BY67: 340.2505 | BZ67: 357.0341 | CA67: 374.8718 | CB67: 393.7931 | CC67: 413.854 | CD67: 435.0677 | CE67: 457.5033 | CF67: 481.194 | CG67: Federal Finance Administration (FFA) | CH67: TRUE | CI67: NA | CJ67: NA | CK67: 2020 | CL67: 4 | CM67: NA | CN67: Government debt: gross | CO67: Maastricht criteria | CP67: CHE | CQ67: GGDBT | CR67: OCT031G.db

Sheet GMWQ
A1: Location | B1: Indicator | C1: Scenario | D1: Units | E1: Scale | F1: Measurement | G1: 1980 Q1 | H1: 1980 Q2 | I1: 1980 Q3 | J1: 1980 Q4 | K1: 1981 Q1 | L1: 1981 Q2 | M1: 1981 Q3 | N1: 1981 Q4 | O1: 1982 Q1 | P1: 1982 Q2 | Q1: 1982 Q3 | R1: 1982 Q4 | S1: 1983 Q1 | T1: 1983 Q2 | U1: 1983 Q3 | V1: 1983 Q4 | W1: 1984 Q1 | X1: 1984 Q2 | Y1: 1984 Q3 | Z1: 1984 Q4 | AA1: 1985 Q1 | AB1: 1985 Q2 | AC1: 1985 Q3 | AD1: 1985 Q4 | AE1: 1986 Q1 | AF1: 1986 Q2 | AG1: 1986 Q3 | AH1: 1986 Q4 | AI1: 1987 Q1 | AJ1: 1987 Q2 | AK1: 1987 Q3 | AL1: 1987 Q4 | AM1: 1988 Q1 | AN1: 1988 Q2 | AO1: 1988 Q3 | AP1: 1988 Q4 | AQ1: 1989 Q1 | AR1: 1989 Q2 | AS1: 1989 Q3 | AT1: 1989 Q4 | AU1: 1990 Q1 | AV1: 1990 Q2 | AW1: 1990 Q3 | AX1: 1990 Q4 | AY1: 1991 Q1 | AZ1: 1991 Q2 | BA1: 1991 Q3 | BB1: 1991 Q4 | BC1: 1992 Q1 | BD1: 1992 Q2 | BE1: 1992 Q3 | BF1: 1992 Q4 | BG1: 1993 Q1 | BH1: 1993 Q2 | BI1: 1993 Q3 | BJ1: 1993 Q4 | BK1: 1994 Q1 | BL1: 1994 Q2 | BM1: 1994 Q3 | BN1: 1994 Q4 | BO1: 1995 Q1 | BP1: 1995 Q2 | BQ1: 1995 Q3 | BR1: 1995 Q4 | BS1: 1996 Q1 | BT1: 1996 Q2 | BU1: 1996 Q3 | BV1: 1996 Q4 | BW1: 1997 Q1 | BX1: 1997 Q2 | BY1: 1997 Q3 | BZ1: 1997 Q4 | CA1: 1998 Q1 | CB1: 1998 Q2 | CC1: 1998 Q3 | CD1: 1998 Q4 | CE1: 1999 Q1 | CF1: 1999 Q2 | CG1: 1999 Q3 | CH1: 1999 Q4 | CI1: 2000 Q1 | CJ1: 2000 Q2 | CK1: 2000 Q3 | CL1: 2000 Q4 | CM1: 2001 Q1 | CN1: 2001 Q2 | CO1: 2001 Q3 | CP1: 2001 Q4 | CQ1: 2002 Q1 | CR1: 2002 Q2 | CS1: 2002 Q3 | CT1: 2002 Q4 | CU1: 2003 Q1 | CV1: 2003 Q2 | CW1: 2003 Q3 | CX1: 2003 Q4 | CY1: 2004 Q1 | CZ1: 2004 Q2 | DA1: 2004 Q3 | DB1: 2004 Q4 | DC1: 2005 Q1 | DD1: 2005 Q2 | DE1: 2005 Q3 | DF1: 2005 Q4 | DG1: 2006 Q1 | DH1: 2006 Q2 | DI1: 2006 Q3 | DJ1: 2006 Q4 | DK1: 2007 Q1 | DL1: 2007 Q2 | DM1: 2007 Q3 | DN1: 2007 Q4 | DO1: 2008 Q1 | DP1: 2008 Q2 | DQ1: 2008 Q3 | DR1: 2008 Q4 | DS1: 2009 Q1 | DT1: 2009 Q2 | DU1: 2009 Q3 | DV1: 2009 Q4 | DW1: 2010 Q1 | DX1: 2010 Q2 | DY1: 2010 Q3 | DZ1: 2010 Q4 | EA1: 2011 Q1 | EB1: 2011 Q2 | EC1: 2011 Q3 | ED1: 2011 Q4 | EE1: 2012 Q1 | EF1: 2012 Q2 | EG1: 2012 Q3 | EH1: 2012 Q4 | EI1: 2013 Q1 | EJ1: 2013 Q2 | EK1: 2013 Q3 | EL1: 2013 Q4 | EM1: 2014 Q1 | EN1: 2014 Q2 | EO1: 2014 Q3 | EP1: 2014 Q4 | EQ1: 2015 Q1 | ER1: 2015 Q2 | ES1: 2015 Q3 | ET1: 2015 Q4 | EU1: 2016 Q1 | EV1: 2016 Q2 | EW1: 2016 Q3 | EX1: 2016 Q4 | EY1: 2017 Q1 | EZ1: 2017 Q2 | FA1: 2017 Q3 | FB1: 2017 Q4 | FC1: 2018 Q1 | FD1: 2018 Q2 | FE1: 2018 Q3 | FF1: 2018 Q4 | FG1: 2019 Q1 | FH1: 2019 Q2 | FI1: 2019 Q3 | FJ1: 2019 Q4 | FK1: 2020 Q1 | FL1: 2020 Q2 | FM1: 2020 Q3 | FN1: 2020 Q4 | FO1: 2021 Q1 | FP1: 2021 Q2 | FQ1: 2021 Q3 | FR1: 2021 Q4 | FS1: 2022 Q1 | FT1: 2022 Q2 | FU1: 2022 Q3 | FV1: 2022 Q4 | FW1: 2023 Q1 | FX1: 2023 Q2 | FY1: 2023 Q3 | FZ1: 2023 Q4 | GA1: 2024 Q1 | GB1: 2024 Q2 | GC1: 2024 Q3 | GD1: 2024 Q4 | GE1: 2025 Q1 | GF1: 2025 Q2 | GG1: 2025 Q3 | GH1: 2025 Q4 | GI1: 2026 Q1 | GJ1: 2026 Q2 | GK1: 2026 Q3 | GL1: 2026 Q4 | GM1: 2027 Q1 | GN1: 2027 Q2 | GO1: 2027 Q3 | GP1: 2027 Q4 | GQ1: 2028 Q1 | GR1: 2028 Q2 | GS1: 2028 Q3 | GT1: 2028 Q4 | GU1: 2029 Q1 | GV1: 2029 Q2 | GW1: 2029 Q3 | GX1: 2029 Q4 | GY1: 2030 Q1 | GZ1: 2030 Q2 | HA1: 2030 Q3 | HB1: 2030 Q4 | HC1: Source | HD1: Seasonally adjusted | HE1: Base year price | HF1: Base year index | HG1: Historical end year | HH1: Historical end quarter | HI1: Date of last update | HJ1: Source details | HK1: Additional source details | HL1: Location code | HM1: Indicator code | HN1: Databank code
A2: United Kingdom | B2: Tax revenue, employer social security contributions, LCU | C2: Oct24_2 | D2: Pound | E2: Millions | F2: Level | G2: 2203.656 | H2: 2273.364 | I2: 2332.952 | J2: 2420.649 | K2: 2498.227 | L2: 2399.287 | M2: 2452.13 | N2: 2560.064 | O2: 2665.75 | P2: 2569.059 | Q2: 2582.55 | R2: 2688.236 | S2: 2872.623 | T2: 2925.466 | U2: 2987.303 | V2: 3060.384 | W2: 3088.492 | X2: 3128.967 | Y2: 3185.183 | Z2: 3267.258 | AA2: 3359.452 | AB2: 3403.3 | AC2: 3447.148 | AD2: 3557.331 | AE2: 3637.157 | AF2: 3792.313 | AG2: 3863.145 | AH2: 3930.603 | AI2: 4305 | AJ2: 4334 | AK2: 4487 | AL2: 4632 | AM2: 4640 | AN2: 4879 | AO2: 5040 | AP2: 5234 | AQ2: 5239 | AR2: 5247 | AS2: 5405 | AT2: 5609 | AU2: 5594 | AV2: 5782 | AW2: 5930 | AX2: 6012 | AY2: 5974 | AZ2: 6126 | BA2: 6125 | BB2: 6492 | BC2: 6453 | BD2: 6234 | BE2: 6198 | BF2: 6517 | BG2: 6477 | BH2: 6646 | BI2: 6727 | BJ2: 6997 | BK2: 6841 | BL2: 6602 | BM2: 6704 | BN2: 6891 | BO2: 6872 | BP2: 6901 | BQ2: 6999 | BR2: 7120 | BS2: 7100 | BT2: 7308 | BU2: 7377 | BV2: 7428 | BW2: 7219 | BX2: 7704 | BY2: 8050 | BZ2: 8065 | CA2: 7887 | CB2: 8048 | CC2: 8448 | CD2: 8468 | CE2: 8757 | CF2: 8818 | CG2: 9094 | CH2: 9184 | CI2: 9313 | CJ2: 9861 | CK2: 9826 | CL2: 10195 | CM2: 10811 | CN2: 9870 | CO2: 10189 | CP2: 10298 | CQ2: 10629 | CR2: 10379 | CS2: 10146 | CT2: 10703 | CU2: 10366 | CV2: 11989 | CW2: 12409 | CX2: 12408 | CY2: 12662 | CZ2: 12920 | DA2: 13279 | DB2: 13669 | DC2: 13668 | DD2: 14205 | DE2: 14681 | DF2: 14643 | DG2: 14713 | DH2: 14863 | DI2: 15292 | DJ2: 15652 | DK2: 15661 | DL2: 16295 | DM2: 16680 | DN2: 17084 | DO2: 17891 | DP2: 17172 | DQ2: 17328 | DR2: 17305 | DS2: 16825 | DT2: 17195 | DU2: 17157 | DV2: 17618 | DW2: 18831 | DX2: 17422 | DY2: 17548 | DZ2: 17762 | EA2: 18475 | EB2: 18242 | EC2: 18350 | ED2: 18382 | EE2: 18603 | EF2: 19029 | EG2: 19095 | EH2: 18982 | EI2: 18597 | EJ2: 19598 | EK2: 19195 | EL2: 19482 | EM2: 19571 | EN2: 19575 | EO2: 19825 | EP2: 19993 | EQ2: 20426 | ER2: 20839 | ES2: 20846 | ET2: 21129 | EU2: 20549 | EV2: 22462 | EW2: 22802 | EX2: 23011 | EY2: 23425 | EZ2: 23645 | FA2: 23594 | FB2: 23997 | FC2: 24296 | FD2: 24403 | FE2: 24535 | FF2: 24830 | FG2: 25806 | FH2: 26406 | FI2: 27085 | FJ2: 27639 | FK2: 27453 | FL2: 27064 | FM2: 27978 | FN2: 28812 | FO2: 28828 | FP2: 29940 | FQ2: 30764 | FR2: 31560 | FS2: 32437 | FT2: 35271 | FU2: 35446 | FV2: 34778 | FW2: 34923 | FX2: 35305 | FY2: 35835 | FZ2: 37193 | GA2: 38998 | GB2: 37308 | GC2: 38127.7 | GD2: 38385.24 | GE2: 38842.31 | GF2: 39239.57 | GG2: 39638.7 | GH2: 40042.66 | GI2: 40448.05 | GJ2: 40902.63 | GK2: 41359.82 | GL2: 41814.05 | GM2: 42274.95 | GN2: 42725.16 | GO2: 43178.24 | GP2: 43638.85 | GQ2: 44019.07 | GR2: 44443.03 | GS2: 44874.24 | GT2: 45316.12 | GU2: 45756.86 | GV2: 46168.63 | GW2: 46582.28 | GX2: 47000.28 | GY2: 47418.72 | GZ2: 47843.01 | HA2: 48273.44 | HB2: 48708.08 | HC2: Office for National Statistics\Haver Analytics | HD2: TRUE | HE2: NA | HF2: NA | HG2: 2024 | HH2: 2 | HI2: NA | HJ2: RNFSQ@UK | HK2: UK: IA: CG: Resources: Employers' Social Contributions (SA, Mil.GBP) | HL2: GBR | HM2: TP | HN2: Oct24_2.db
A3: United Kingdom | B3: GDP, real, LCU | C3: Oct24_2 | D3: Pound | E3: Millions | F3: Level | G3: 269776 | H3: 264448 | I3: 264139 | J3: 261297 | K3: 261131 | L3: 261739 | M3: 264602 | N3: 264902 | O3: 265408 | P3: 268196 | Q3: 268798 | R3: 270653 | S3: 275877 | T3: 277790 | U3: 280996 | V3: 283096 | W3: 285469 | X3: 282605 | Y3: 284676 | Z3: 289829 | AA3: 292612 | AB3: 298873 | AC3: 298814 | AD3: 298979 | AE3: 302117 | AF3: 304797 | AG3: 306708 | AH3: 312615 | AI3: 314804 | AJ3: 319478 | AK3: 327346 | AL3: 331075 | AM3: 336442 | AN3: 338186 | AO3: 342414 | AP3: 345162 | AQ3: 346836 | AR3: 348997 | AS3: 349572 | AT3: 349523 | AU3: 351299 | AV3: 353663 | AW3: 349780 | AX3: 348006 | AY3: 346292 | AZ3: 345892 | BA3: 345216 | BB3: 345643 | BC3: 345523 | BD3: 344987 | BE3: 346628 | BF3: 349299 | BG3: 351046 | BH3: 352612 | BI3: 355841 | BJ3: 358264 | BK3: 361793 | BL3: 365109 | BM3: 368798 | BN3: 370401 | BO3: 372307 | BP3: 373090 | BQ3: 377249 | BR3: 378442 | BS3: 380976 | BT3: 382146 | BU3: 385671 | BV3: 391053 | BW3: 397303 | BX3: 401790 | BY3: 405233 | BZ3: 411352 | CA3: 414377 | CB3: 416909 | CC3: 418294 | CD3: 421074 | CE3: 423875 | CF3: 425920 | CG3: 432860 | CH3: 439093 | CI3: 444540 | CJ3: 447825 | CK3: 450688 | CL3: 453447 | CM3: 457680 | CN3: 459620 | CO3: 462016 | CP3: 463404 | CQ3: 464698 | CR3: 466935 | CS3: 470277 | CT3: 473899 | CU3: 477357 | CV3: 481552 | CW3: 485973 | CX3: 490059 | CY3: 492014 | CZ3: 494824 | DA3: 496642 | DB3: 499020 | DC3: 502702 | DD3: 506906 | DE3: 511132 | DF3: 515935 | DG3: 518495 | DH3: 520318 | DI3: 521780 | DJ3: 524569 | DK3: 529398 | DL3: 533187 | DM3: 537052 | DN3: 540258 | DO3: 542804 | DP3: 539918 | DQ3: 531619 | DR3: 520230 | DS3: 509646 | DT3: 508009 | DU3: 508398 | DV3: 509889 | DW3: 514595 | DX3: 520128 | DY3: 523173 | DZ3: 523515 | EA3: 524955 | EB3: 525418 | EC3: 527034 | ED3: 527698 | EE3: 532300 | EF3: 531663 | EG3: 536720 | EH3: 536188 | EI3: 537974 | EJ3: 541586 | EK3: 546064 | EL3: 549709 | EM3: 554183 | EN3: 559331 | EO3: 563694 | EP3: 567619 | EQ3: 569150 | ER3: 572673 | ES3: 574836 | ET3: 578068 | EU3: 580110 | EV3: 583383 | EW3: 585856 | EX3: 589476 | EY3: 594423 | EZ3: 598176 | FA3: 601961 | FB3: 606396 | FC3: 606785 | FD3: 607775 | FE3: 609653 | FF3: 610481 | FG3: 614936 | FH3: 616853 | FI3: 621227 | FJ3: 621229 | FK3: 604719 | FL3: 481769 | FM3: 562648 | FN3: 570338 | FO3: 564411 | FP3: 605353 | FQ3: 615459 | FR3: 624592 | FS3: 629149 | FT3: 631258 | FU3: 631977 | FV3: 634044 | FW3: 634612 | FX3: 634624 | FY3: 633956 | FZ3: 631825 | GA3: 636222 | GB3: 639095 | GC3: 640741.9 | GD3: 643868.9 | GE3: 646136.9 | GF3: 648529.7 | GG3: 650983.9 | GH3: 653549.4 | GI3: 656294.3 | GJ3: 659051.3 | GK3: 661754 | GL3: 664499.8 | GM3: 667225.6 | GN3: 669961.6 | GO3: 672674.9 | GP3: 675499.9 | GQ3: 678268.4 | GR3: 681049.5 | GS3: 683773.6 | GT3: 686508.3 | GU3: 689254.8 | GV3: 692011.6 | GW3: 694780.4 | GX3: 697559.3 | GY3: 700349.6 | GZ3: 703151.1 | HA3: 705964.2 | HB3: 708788.1 | HC3: Office for National Statistics\Haver Analytics | HD3: TRUE | HE3: chained 2022 | HF3: NA | HG3: 2024 | HH3: 2 | HI3: NA | HJ3: ABMIQ@UK | HK3: U.K.: Real Gross Domestic Product (SA, Mil.Chn.2022.GBP) | HL3: GBR | HM3: GDP | HN3: Oct24_2.db
A4: United Kingdom | B4: Employment, aged 16 and over, ILO definition | C4: Oct24_2 | D4: Person | E4: Thousands | F4: Level | G4: 25250 | H4: 25190 | I4: 25050 | J4: 24855 | K4: 24661 | L4: 24495 | M4: 24355 | N4: 24209 | O4: 24120 | P4: 24027 | Q4: 23901 | R4: 23755 | S4: 23651 | T4: 23647 | U4: 23809 | V4: 23994 | W4: 24125 | X4: 24245 | Y4: 24335 | Z4: 24435 | AA4: 24515 | AB4: 24570 | AC4: 24625 | AD4: 24660 | AE4: 24670 | AF4: 24695 | AG4: 24770 | AH4: 24850 | AI4: 24925 | AJ4: 25110 | AK4: 25345 | AL4: 25575 | AM4: 25795 | AN4: 25970 | AO4: 26160 | AP4: 26355 | AQ4: 26590 | AR4: 26730 | AS4: 26795 | AT4: 26880 | AU4: 26900 | AV4: 26935 | AW4: 26900 | AX4: 26750 | AY4: 26530 | AZ4: 26275 | BA4: 26025 | BB4: 25820 | BC4: 25710 | BD4: 25605 | BE4: 25509 | BF4: 25336 | BG4: 25282 | BH4: 25293 | BI4: 25316 | BJ4: 25320 | BK4: 25408 | BL4: 25451 | BM4: 25559 | BN4: 25600 | BO4: 25670 | BP4: 25770 | BQ4: 25852 | BR4: 25982 | BS4: 25970 | BT4: 26009 | BU4: 26062 | BV4: 26198 | BW4: 26381 | BX4: 26514 | BY4: 26572 | BZ4: 26636 | CA4: 26677 | CB4: 26714 | CC4: 26834 | CD4: 26955 | CE4: 27036 | CF4: 27095 | CG4: 27218 | CH4: 27322 | CI4: 27362 | CJ4: 27468 | CK4: 27555 | CL4: 27549 | CM4: 27623 | CN4: 27707 | CO4: 27715 | CP4: 27803 | CQ4: 27797 | CR4: 27933 | CS4: 27935 | CT4: 28110 | CU4: 28099 | CV4: 28226 | CW4: 28256 | CX4: 28304 | CY4: 28459 | CZ4: 28470 | DA4: 28518 | DB4: 28673 | DC4: 28789 | DD4: 28802 | DE4: 28928 | DF4: 28880 | DG4: 29048 | DH4: 29106 | DI4: 29183 | DJ4: 29214 | DK4: 29194 | DL4: 29322 | DM4: 29420 | DN4: 29576 | DO4: 29684 | DP4: 29722 | DQ4: 29580 | DR4: 29528 | DS4: 29366 | DT4: 29087 | DU4: 29069 | DV4: 29102 | DW4: 29013 | DX4: 29192 | DY4: 29385 | DZ4: 29324 | EA4: 29441 | EB4: 29447 | EC4: 29283 | ED4: 29349 | EE4: 29464 | EF4: 29681 | EG4: 29778 | EH4: 29932 | EI4: 29869 | EJ4: 29974 | EK4: 30144 | EL4: 30330 | EM4: 30573 | EN4: 30747 | EO4: 30873 | EP4: 30981 | EQ4: 31188 | ER4: 31140 | ES4: 31361 | ET4: 31569 | EU4: 31603 | EV4: 31778 | EW4: 31843 | EX4: 31877 | EY4: 31978 | EZ4: 32098 | FA4: 32093 | FB4: 32179 | FC4: 32364 | FD4: 32403 | FE4: 32448 | FF4: 32618 | FG4: 32721 | FH4: 32839 | FI4: 32779 | FJ4: 32954 | FK4: 33000 | FL4: 32571 | FM4: 32354 | FN4: 32198 | FO4: 32221 | FP4: 32377 | FQ4: 32687 | FR4: 32686 | FS4: 32775 | FT4: 32958 | FU4: 32916 | FV4: 33067 | FW4: 33201 | FX4: 33163 | FY4: 33102 | FZ4: 33174 | GA4: 32997 | GB4: 33094 | GC4: 33306.91 | GD4: 33156.91 | GE4: 33260.84 | GF4: 33375.05 | GG4: 33484.89 | GH4: 33600.57 | GI4: 33714.82 | GJ4: 33826.11 | GK4: 33927.58 | GL4: 34027.66 | GM4: 34126.33 | GN4: 34225.34 | GO4: 34322.92 | GP4: 34425.94 | GQ4: 34525.75 | GR4: 34625.88 | GS4: 34718.88 | GT4: 34809.08 | GU4: 34896.14 | GV4: 34979.91 | GW4: 35060.37 | GX4: 35141.01 | GY4: 35218.32 | GZ4: 35295.8 | HA4: 35373.45 | HB4: 35451.27 | HC4: Office for National Statistics\Haver Analytics | HD4: TRUE | HE4: NA | HF4: NA | HG4: 2024 | HH4: 2 | HI4: NA | HJ4: MGRZQ@UK | HK4: UK: LFS: Employment: Aged 16 and Over (SA, Thous) | HL4: GBR | HM4: ETILO | HN4: Oct24_2.db
A5: United Kingdom | B5: Unemployment rate, ILO definition | C5: Oct24_2 | D5: % | E5: NA | F5: Level | G5: 5.8 | H5: 6.3 | I5: 7.1 | J5: 8 | K5: 8.9 | L5: 9.6 | M5: 9.9 | N5: 10.2 | O5: 10.4 | P5: 10.6 | Q5: 10.8 | R5: 11.1 | S5: 11.3 | T5: 11.4 | U5: 11.5 | V5: 11.7 | W5: 11.8 | X5: 11.9 | Y5: 11.7 | Z5: 11.6 | AA5: 11.5 | AB5: 11.4 | AC5: 11.3 | AD5: 11.3 | AE5: 11.3 | AF5: 11.3 | AG5: 11.4 | AH5: 11.3 | AI5: 11.1 | AJ5: 10.7 | AK5: 10.2 | AL5: 9.7 | AM5: 9.2 | AN5: 8.7 | AO5: 8.4 | AP5: 8 | AQ5: 7.6 | AR5: 7.2 | AS5: 7.1 | AT5: 7 | AU5: 6.9 | AV5: 6.9 | AW5: 7.1 | AX5: 7.5 | AY5: 8 | AZ5: 8.7 | BA5: 9.2 | BB5: 9.5 | BC5: 9.7 | BD5: 9.8 | BE5: 9.9 | BF5: 10.4 | BG5: 10.6 | BH5: 10.4 | BI5: 10.2 | BJ5: 10.3 | BK5: 9.9 | BL5: 9.7 | BM5: 9.4 | BN5: 9 | BO5: 8.9 | BP5: 8.7 | BQ5: 8.6 | BR5: 8.3 | BS5: 8.2 | BT5: 8.3 | BU5: 8.1 | BV5: 7.8 | BW5: 7.3 | BX5: 7.2 | BY5: 6.8 | BZ5: 6.5 | CA5: 6.4 | CB5: 6.3 | CC5: 6.2 | CD5: 6.1 | CE5: 6.2 | CF5: 6 | CG5: 5.9 | CH5: 5.8 | CI5: 5.8 | CJ5: 5.5 | CK5: 5.3 | CL5: 5.2 | CM5: 5.1 | CN5: 5 | CO5: 5.1 | CP5: 5.2 | CQ5: 5.2 | CR5: 5.2 | CS5: 5.3 | CT5: 5.1 | CU5: 5.2 | CV5: 4.9 | CW5: 5 | CX5: 4.9 | CY5: 4.8 | CZ5: 4.8 | DA5: 4.7 | DB5: 4.7 | DC5: 4.7 | DD5: 4.8 | DE5: 4.7 | DF5: 5.1 | DG5: 5.2 | DH5: 5.5 | DI5: 5.5 | DJ5: 5.5 | DK5: 5.5 | DL5: 5.4 | DM5: 5.3 | DN5: 5.2 | DO5: 5.2 | DP5: 5.4 | DQ5: 5.9 | DR5: 6.4 | DS5: 7.1 | DT5: 7.8 | DU5: 7.8 | DV5: 7.8 | DW5: 8 | DX5: 7.9 | DY5: 7.8 | DZ5: 7.9 | EA5: 7.8 | EB5: 7.9 | EC5: 8.3 | ED5: 8.4 | EE5: 8.2 | EF5: 8 | EG5: 7.9 | EH5: 7.8 | EI5: 7.9 | EJ5: 7.8 | EK5: 7.6 | EL5: 7.2 | EM5: 6.8 | EN5: 6.3 | EO5: 6 | EP5: 5.7 | EQ5: 5.6 | ER5: 5.6 | ES5: 5.4 | ET5: 5.1 | EU5: 5.1 | EV5: 5 | EW5: 4.9 | EX5: 4.8 | EY5: 4.6 | EZ5: 4.5 | FA5: 4.3 | FB5: 4.4 | FC5: 4.3 | FD5: 4.1 | FE5: 4.2 | FF5: 4.1 | FG5: 3.9 | FH5: 4 | FI5: 3.9 | FJ5: 3.9 | FK5: 4.1 | FL5: 4.2 | FM5: 5 | FN5: 5.3 | FO5: 5.1 | FP5: 4.8 | FQ5: 4.4 | FR5: 4.2 | FS5: 3.9 | FT5: 3.9 | FU5: 3.8 | FV5: 3.9 | FW5: 4 | FX5: 4.2 | FY5: 4.1 | FZ5: 3.8 | GA5: 4.3 | GB5: 4.2 | GC5: 4.243108 | GD5: 4.408679 | GE5: 4.380091 | GF5: 4.351475 | GG5: 4.322893 | GH5: 4.284726 | GI5: 4.2179 | GJ5: 4.151092 | GK5: 4.093759 | GL5: 4.045897 | GM5: 3.998046 | GN5: 3.959662 | GO5: 3.921238 | GP5: 3.882746 | GQ5: 3.844463 | GR5: 3.806106 | GS5: 3.778645 | GT5: 3.75964 | GU5: 3.749948 | GV5: 3.74987 | GW5: 3.749865 | GX5: 3.749873 | GY5: 3.749872 | GZ5: 3.749875 | HA5: 3.74988 | HB5: 3.749879 | HC5: Office for National Statistics\Haver Analytics | HD5: TRUE | HE5: NA | HF5: NA | HG5: 2024 | HH5: 2 | HI5: NA | HJ5: MGSXQ@UK | HK5: UK: LFS: Unemployment Rate: Aged 16 and Over (SA, %) | HL5: GBR | HM5: UPILO | HN5: Oct24_2.db
A6: United Kingdom | B6: Income, personal disposable, real, LCU | C6: Oct24_2 | D6: Pound | E6: Millions | F6: Level | G6: 157780 | H6: 158083 | I6: 160445 | J6: 158931 | K6: 160486 | L6: 158130 | M6: 157598 | N6: 158580 | O6: 157715 | P6: 160483 | Q6: 159367 | R6: 159886 | S6: 158854 | T6: 165111 | U6: 163522 | V6: 164202 | W6: 167088 | X6: 165111 | Y6: 169770 | Z6: 173527 | AA6: 175208 | AB6: 175613 | AC6: 175957 | AD6: 177164 | AE6: 179729 | AF6: 186661 | AG6: 183119 | AH6: 183388 | AI6: 180901 | AJ6: 185020 | AK6: 187551 | AL6: 188860 | AM6: 191709 | AN6: 194935 | AO6: 197179 | AP6: 198740 | AQ6: 201265 | AR6: 204179 | AS6: 209872 | AT6: 207949 | AU6: 213872 | AV6: 211391 | AW6: 213462 | AX6: 216821 | AY6: 218128 | AZ6: 214176 | BA6: 220568 | BB6: 220151 | BC6: 221591 | BD6: 223785 | BE6: 225633 | BF6: 225562 | BG6: 224008 | BH6: 230278 | BI6: 232470 | BJ6: 233411 | BK6: 232541 | BL6: 232173 | BM6: 236870 | BN6: 235558 | BO6: 239669 | BP6: 239943 | BQ6: 242123 | BR6: 243427 | BS6: 247598 | BT6: 247441 | BU6: 250067 | BV6: 245800 | BW6: 249558 | BX6: 251781 | BY6: 254358 | BZ6: 253468 | CA6: 253069 | CB6: 254576 | CC6: 253636 | CD6: 257028 | CE6: 254037 | CF6: 266557 | CG6: 267871 | CH6: 274118 | CI6: 274370 | CJ6: 277466 | CK6: 283106 | CL6: 287523 | CM6: 289476 | CN6: 288052 | CO6: 289545 | CP6: 295002 | CQ6: 295976 | CR6: 298538 | CS6: 297567 | CT6: 298904 | CU6: 301081 | CV6: 302934 | CW6: 304444 | CX6: 308695 | CY6: 309585 | CZ6: 312396 | DA6: 314574 | DB6: 315137 | DC6: 317057 | DD6: 320657 | DE6: 322465 | DF6: 322562 | DG6: 325138 | DH6: 323889 | DI6: 327580 | DJ6: 328682 | DK6: 339067 | DL6: 336009 | DM6: 340647 | DN6: 340314 | DO6: 335815 | DP6: 339732 | DQ6: 333684 | DR6: 340023 | DS6: 335761 | DT6: 344826 | DU6: 343613 | DV6: 346368 | DW6: 346769 | DX6: 347421 | DY6: 346091 | DZ6: 343460 | EA6: 334416 | EB6: 339976 | EC6: 339972 | ED6: 337625 | EE6: 344680 | EF6: 348062 | EG6: 346678 | EH6: 345765 | EI6: 342890 | EJ6: 350923 | EK6: 357263 | EL6: 360126 | EM6: 359009 | EN6: 359599 | EO6: 359708 | EP6: 364730 | EQ6: 372232 | ER6: 381179 | ES6: 388638 | ET6: 388470 | EU6: 386874 | EV6: 387633 | EW6: 384657 | EX6: 381981 | EY6: 382290 | EZ6: 390332 | FA6: 390954 | FB6: 391273 | FC6: 395975 | FD6: 394175 | FE6: 395431 | FF6: 400106 | FG6: 399632 | FH6: 405211 | FI6: 405428 | FJ6: 407970 | FK6: 402584 | FL6: 394596 | FM6: 406593 | FN6: 408367 | FO6: 411074 | FP6: 413832 | FQ6: 410138 | FR6: 402842 | FS6: 401738 | FT6: 398386 | FU6: 400405 | FV6: 408689 | FW6: 407362 | FX6: 412328 | FY6: 413001 | FZ6: 415159 | GA6: 420689 | GB6: 426221 | GC6: 427151.4 | GD6: 427205.6 | GE6: 429422.1 | GF6: 431072.3 | GG6: 432818.3 | GH6: 434694.7 | GI6: 436515.1 | GJ6: 437864.4 | GK6: 439188.4 | GL6: 440408.8 | GM6: 441787.5 | GN6: 443258.1 | GO6: 444859.4 | GP6: 446391.8 | GQ6: 448363 | GR6: 450539.2 | GS6: 452477.2 | GT6: 454341.6 | GU6: 456201.8 | GV6: 458220.1 | GW6: 459983.9 | GX6: 461695.3 | GY6: 463445.7 | GZ6: 465447 | HA6: 467184.9 | HB6: 468872.6 | HC6: Office for National Statistics\Haver Analytics | HD6: TRUE | HE6: chained 2022 | HF6: NA | HG6: 2024 | HH6: 2 | HI6: NA | HJ6: NRJRQ@UK | HK6: UK: HH & NPISH: Real Household Disposable Income (SA, Mil.Chn.2022.Pounds) | HL6: GBR | HM6: PEDY | HN6: Oct24_2.db
A7: United Kingdom | B7: Earnings, quarterly total, whole economy, Gross, LCU | C7: Oct24_2 | D7: Pound per Employee | E7: NA | F7: Level | G7: 1256.656 | H7: 1320.788 | I7: 1377.792 | J7: 1419.042 | K7: 1445.746 | L7: 1481.073 | M7: 1519.57 | N7: 1560.495 | O7: 1588.719 | P7: 1621.852 | Q7: 1645.302 | R7: 1677.714 | S7: 1735.998 | T7: 1757.346 | U7: 1777.221 | V7: 1805.329 | W7: 1833.021 | X7: 1859.965 | Y7: 1876.902 | Z7: 1935.882 | AA7: 1996.246 | AB7: 2015.939 | AC7: 2043.298 | AD7: 2093.281 | AE7: 2142.593 | AF7: 2185.823 | AG7: 2220.435 | AH7: 2251.233 | AI7: 2282.895 | AJ7: 2321.792 | AK7: 2369.95 | AL7: 2418.279 | AM7: 2470.636 | AN7: 2512.313 | AO7: 2569.618 | AP7: 2641.639 | AQ7: 2684.494 | AR7: 2756.293 | AS7: 2816.473 | AT7: 2895.669 | AU7: 2978.668 | AV7: 3042.386 | AW7: 3096.331 | AX7: 3142.508 | AY7: 3224.996 | AZ7: 3293.292 | BA7: 3373.081 | BB7: 3431.946 | BC7: 3467.976 | BD7: 3483.129 | BE7: 3486.288 | BF7: 3519.483 | BG7: 3533.243 | BH7: 3585.394 | BI7: 3630.535 | BJ7: 3662.197 | BK7: 3681.295 | BL7: 3682.575 | BM7: 3730.634 | BN7: 3764.534 | BO7: 3784.689 | BP7: 3813.237 | BQ7: 3825.77 | BR7: 3869.823 | BS7: 3882.18 | BT7: 3914.624 | BU7: 3968.22 | BV7: 3978.247 | BW7: 4081.993 | BX7: 4143.857 | BY7: 4207.873 | BZ7: 4225.691 | CA7: 4229.584 | CB7: 4273.278 | CC7: 4319.682 | CD7: 4319.271 | CE7: 4422.741 | CF7: 4529.62 | CG7: 4579.019 | CH7: 4624.274 | CI7: 4637.771 | CJ7: 4701.495 | CK7: 4802.455 | CL7: 4890.775 | CM7: 5001.369 | CN7: 5002.77 | CO7: 5029.651 | CP7: 5057.922 | CQ7: 5089.49 | CR7: 5073.909 | CS7: 5126.548 | CT7: 5142.66 | CU7: 5215.105 | CV7: 5274.743 | CW7: 5382.108 | CX7: 5458.233 | CY7: 5521.079 | CZ7: 5546.886 | DA7: 5624.504 | DB7: 5694.482 | DC7: 5778.829 | DD7: 5743.093 | DE7: 5808.466 | DF7: 5809.272 | DG7: 5993.517 | DH7: 6001.19 | DI7: 6067.312 | DJ7: 6166.277 | DK7: 6414.875 | DL7: 6339.471 | DM7: 6466.942 | DN7: 6476.04 | DO7: 6580.838 | DP7: 6498.069 | DQ7: 6496.127 | DR7: 6443.408 | DS7: 6371.857 | DT7: 6556.603 | DU7: 6566.035 | DV7: 6577.117 | DW7: 6601.875 | DX7: 6547.224 | DY7: 6603.561 | DZ7: 6617.42 | EA7: 6764.375 | EB7: 6692.795 | EC7: 6733.261 | ED7: 6724.496 | EE7: 6797.859 | EF7: 6797.991 | EG7: 6779.331 | EH7: 6805.55 | EI7: 6831.207 | EJ7: 7064.567 | EK7: 7073.654 | EL7: 7154.167 | EM7: 7221.816 | EN7: 7176 | EO7: 7114.859 | EP7: 7151.244 | EQ7: 7196.032 | ER7: 7235.93 | ES7: 7286.774 | ET7: 7292.882 | EU7: 7378.136 | EV7: 7418.134 | EW7: 7455.118 | EX7: 7453.085 | EY7: 7552.214 | EZ7: 7621.865 | FA7: 7682.057 | FB7: 7709.649 | FC7: 7783.628 | FD7: 7753.096 | FE7: 7876.518 | FF7: 7956.615 | FG7: 7998.079 | FH7: 8102.425 | FI7: 8093.845 | FJ7: 8076.643 | FK7: 8056.795 | FL7: 7842.464 | FM7: 8014.82 | FN7: 8241.492 | FO7: 8267.329 | FP7: 8500.161 | FQ7: 8499.45 | FR7: 8570.438 | FS7: 8762.161 | FT7: 8858.754 | FU7: 8972.382 | FV7: 9187.092 | FW7: 9460.302 | FX7: 9660.59 | FY7: 9771.033 | FZ7: 9774.984 | GA7: 9898.726 | GB7: 10025.21 | GC7: 10139.5 | GD7: 10244.95 | GE7: 10327.93 | GF7: 10399.2 | GG7: 10470.95 | GH7: 10541.84 | GI7: 10611.65 | GJ7: 10680.9 | GK7: 10750.04 | GL7: 10818.11 | GM7: 10887.61 | GN7: 10957.44 | GO7: 11027.81 | GP7: 11097.76 | GQ7: 11168.61 | GR7: 11240.3 | GS7: 11313.43 | GT7: 11387.67 | GU7: 11462.16 | GV7: 11537.54 | GW7: 11614.13 | GX7: 11691.39 | GY7: 11769.48 | GZ7: 11848.68 | HA7: 11928.99 | HB7: 12009.94 | HC7: Oxford Economics calculation using Office for National Statistics data | HD7: TRUE | HE7: NA | HF7: NA | HG7: 2024 | HH7: 2 | HI7: NA | HJ7: Oxford Economics calculation using Office for National Statistics data | HK7: NA | HL7: GBR | HM7: ER | HN7: Oct24_2.db
A8: United Kingdom | B8: Tax revenue, employer social security contributions, LCU | C8: NICS_Scen | D8: Pound | E8: Millions | F8: Level | G8: 2203.656 | H8: 2273.364 | I8: 2332.952 | J8: 2420.649 | K8: 2498.227 | L8: 2399.287 | M8: 2452.13 | N8: 2560.064 | O8: 2665.75 | P8: 2569.059 | Q8: 2582.55 | R8: 2688.236 | S8: 2872.623 | T8: 2925.466 | U8: 2987.303 | V8: 3060.384 | W8: 3088.492 | X8: 3128.967 | Y8: 3185.183 | Z8: 3267.258 | AA8: 3359.452 | AB8: 3403.3 | AC8: 3447.148 | AD8: 3557.331 | AE8: 3637.157 | AF8: 3792.313 | AG8: 3863.145 | AH8: 3930.603 | AI8: 4305 | AJ8: 4334 | AK8: 4487 | AL8: 4632 | AM8: 4640 | AN8: 4879 | AO8: 5040 | AP8: 5234 | AQ8: 5239 | AR8: 5247 | AS8: 5405 | AT8: 5609 | AU8: 5594 | AV8: 5782 | AW8: 5930 | AX8: 6012 | AY8: 5974 | AZ8: 6126 | BA8: 6125 | BB8: 6492 | BC8: 6453 | BD8: 6234 | BE8: 6198 | BF8: 6517 | BG8: 6477 | BH8: 6646 | BI8: 6727 | BJ8: 6997 | BK8: 6841 | BL8: 6602 | BM8: 6704 | BN8: 6891 | BO8: 6872 | BP8: 6901 | BQ8: 6999 | BR8: 7120 | BS8: 7100 | BT8: 7308 | BU8: 7377 | BV8: 7428 | BW8: 7219 | BX8: 7704 | BY8: 8050 | BZ8: 8065 | CA8: 7887 | CB8: 8048 | CC8: 8448 | CD8: 8468 | CE8: 8757 | CF8: 8818 | CG8: 9094 | CH8: 9184 | CI8: 9313 | CJ8: 9861 | CK8: 9826 | CL8: 10195 | CM8: 10811 | CN8: 9870 | CO8: 10189 | CP8: 10298 | CQ8: 10629 | CR8: 10379 | CS8: 10146 | CT8: 10703 | CU8: 10366 | CV8: 11989 | CW8: 12409 | CX8: 12408 | CY8: 12662 | CZ8: 12920 | DA8: 13279 | DB8: 13669 | DC8: 13668 | DD8: 14205 | DE8: 14681 | DF8: 14643 | DG8: 14713 | DH8: 14863 | DI8: 15292 | DJ8: 15652 | DK8: 15661 | DL8: 16295 | DM8: 16680 | DN8: 17084 | DO8: 17891 | DP8: 17172 | DQ8: 17328 | DR8: 17305 | DS8: 16825 | DT8: 17195 | DU8: 17157 | DV8: 17618 | DW8: 18831 | DX8: 17422 | DY8: 17548 | DZ8: 17762 | EA8: 18475 | EB8: 18242 | EC8: 18350 | ED8: 18382 | EE8: 18603 | EF8: 19029 | EG8: 19095 | EH8: 18982 | EI8: 18597 | EJ8: 19598 | EK8: 19195 | EL8: 19482 | EM8: 19571 | EN8: 19575 | EO8: 19825 | EP8: 19993 | EQ8: 20426 | ER8: 20839 | ES8: 20846 | ET8: 21129 | EU8: 20549 | EV8: 22462 | EW8: 22802 | EX8: 23011 | EY8: 23425 | EZ8: 23645 | FA8: 23594 | FB8: 23997 | FC8: 24296 | FD8: 24403 | FE8: 24535 | FF8: 24830 | FG8: 25806 | FH8: 26406 | FI8: 27085 | FJ8: 27639 | FK8: 27453 | FL8: 27064 | FM8: 27978 | FN8: 28812 | FO8: 28828 | FP8: 29940 | FQ8: 30764 | FR8: 31560 | FS8: 32437 | FT8: 35271 | FU8: 35446 | FV8: 34778 | FW8: 34923 | FX8: 35305 | FY8: 35835 | FZ8: 37193 | GA8: 38998 | GB8: 37308 | GC8: 38127.7 | GD8: 38385.24 | GE8: 38842.31 | GF8: 45125.97 | GG8: 45491.81 | GH8: 45860.71 | GI8: 46241.94 | GJ8: 46661.97 | GK8: 47114.59 | GL8: 47570.96 | GM8: 48037.53 | GN8: 48613.55 | GO8: 49073.86 | GP8: 49541.79 | GQ8: 49929.76 | GR8: 50549.02 | GS8: 50986.99 | GT8: 51435.8 | GU8: 51884.1 | GV8: 52496.83 | GW8: 52918.27 | GX8: 53344.36 | GY8: 53771.22 | GZ8: 54261.23 | HA8: 54758.03 | HB8: 55259.36 | HC8: Office for National Statistics\Haver Analytics | HD8: TRUE | HE8: NA | HF8: NA | HG8: 2024 | HH8: 2 | HI8: NA | HJ8: RNFSQ@UK | HK8: UK: IA: CG: Resources: Employers' Social Contributions (SA, Mil.GBP) | HL8: GBR | HM8: TP | HN8: NICS_Scen.db
A9: United Kingdom | B9: GDP, real, LCU | C9: NICS_Scen | D9: Pound | E9: Millions | F9: Level | G9: 269776 | H9: 264448 | I9: 264139 | J9: 261297 | K9: 261131 | L9: 261739 | M9: 264602 | N9: 264902 | O9: 265408 | P9: 268196 | Q9: 268798 | R9: 270653 | S9: 275877 | T9: 277790 | U9: 280996 | V9: 283096 | W9: 285469 | X9: 282605 | Y9: 284676 | Z9: 289829 | AA9: 292612 | AB9: 298873 | AC9: 298814 | AD9: 298979 | AE9: 302117 | AF9: 304797 | AG9: 306708 | AH9: 312615 | AI9: 314804 | AJ9: 319478 | AK9: 327346 | AL9: 331075 | AM9: 336442 | AN9: 338186 | AO9: 342414 | AP9: 345162 | AQ9: 346836 | AR9: 348997 | AS9: 349572 | AT9: 349523 | AU9: 351299 | AV9: 353663 | AW9: 349780 | AX9: 348006 | AY9: 346292 | AZ9: 345892 | BA9: 345216 | BB9: 345643 | BC9: 345523 | BD9: 344987 | BE9: 346628 | BF9: 349299 | BG9: 351046 | BH9: 352612 | BI9: 355841 | BJ9: 358264 | BK9: 361793 | BL9: 365109 | BM9: 368798 | BN9: 370401 | BO9: 372307 | BP9: 373090 | BQ9: 377249 | BR9: 378442 | BS9: 380976 | BT9: 382146 | BU9: 385671 | BV9: 391053 | BW9: 397303 | BX9: 401790 | BY9: 405233 | BZ9: 411352 | CA9: 414377 | CB9: 416909 | CC9: 418294 | CD9: 421074 | CE9: 423875 | CF9: 425920 | CG9: 432860 | CH9: 439093 | CI9: 444540 | CJ9: 447825 | CK9: 450688 | CL9: 453447 | CM9: 457680 | CN9: 459620 | CO9: 462016 | CP9: 463404 | CQ9: 464698 | CR9: 466935 | CS9: 470277 | CT9: 473899 | CU9: 477357 | CV9: 481552 | CW9: 485973 | CX9: 490059 | CY9: 492014 | CZ9: 494824 | DA9: 496642 | DB9: 499020 | DC9: 502702 | DD9: 506906 | DE9: 511132 | DF9: 515935 | DG9: 518495 | DH9: 520318 | DI9: 521780 | DJ9: 524569 | DK9: 529398 | DL9: 533187 | DM9: 537052 | DN9: 540258 | DO9: 542804 | DP9: 539918 | DQ9: 531619 | DR9: 520230 | DS9: 509646 | DT9: 508009 | DU9: 508398 | DV9: 509889 | DW9: 514595 | DX9: 520128 | DY9: 523173 | DZ9: 523515 | EA9: 524955 | EB9: 525418 | EC9: 527034 | ED9: 527698 | EE9: 532300 | EF9: 531663 | EG9: 536720 | EH9: 536188 | EI9: 537974 | EJ9: 541586 | EK9: 546064 | EL9: 549709 | EM9: 554183 | EN9: 559331 | EO9: 563694 | EP9: 567619 | EQ9: 569150 | ER9: 572673 | ES9: 574836 | ET9: 578068 | EU9: 580110 | EV9: 583383 | EW9: 585856 | EX9: 589476 | EY9: 594423 | EZ9: 598176 | FA9: 601961 | FB9: 606396 | FC9: 606785 | FD9: 607775 | FE9: 609653 | FF9: 610481 | FG9: 614936 | FH9: 616853 | FI9: 621227 | FJ9: 621229 | FK9: 604719 | FL9: 481769 | FM9: 562648 | FN9: 570338 | FO9: 564411 | FP9: 605353 | FQ9: 615459 | FR9: 624592 | FS9: 629149 | FT9: 631258 | FU9: 631977 | FV9: 634044 | FW9: 634612 | FX9: 634624 | FY9: 633956 | FZ9: 631825 | GA9: 636222 | GB9: 639095 | GC9: 640741.9 | GD9: 643868.9 | GE9: 646136.9 | GF9: 647772.1 | GG9: 649743.7 | GH9: 652016.3 | GI9: 654585 | GJ9: 657323.1 | GK9: 660047.9 | GL9: 662837.8 | GM9: 665613.3 | GN9: 668386.4 | GO9: 671143.1 | GP9: 674014.1 | GQ9: 676832.3 | GR9: 679646 | GS9: 682417.5 | GT9: 685213.4 | GU9: 688029.5 | GV9: 690845 | GW9: 693682.9 | GX9: 696538.8 | GY9: 699408.1 | GZ9: 702286.3 | HA9: 705169.4 | HB9: 708055.9 | HC9: Office for National Statistics\Haver Analytics | HD9: TRUE | HE9: chained 2022 | HF9: NA | HG9: 2024 | HH9: 2 | HI9: NA | HJ9: ABMIQ@UK | HK9: U.K.: Real Gross Domestic Product (SA, Mil.Chn.2022.GBP) | HL9: GBR | HM9: GDP | HN9: NICS_Scen.db
A10: United Kingdom | B10: Employment, aged 16 and over, ILO definition | C10: NICS_Scen | D10: Person | E10: Thousands | F10: Level | G10: 25250 | H10: 25190 | I10: 25050 | J10: 24855 | K10: 24661 | L10: 24495 | M10: 24355 | N10: 24209 | O10: 24120 | P10: 24027 | Q10: 23901 | R10: 23755 | S10: 23651 | T10: 23647 | U10: 23809 | V10: 23994 | W10: 24125 | X10: 24245 | Y10: 24335 | Z10: 24435 | AA10: 24515 | AB10: 24570 | AC10: 24625 | AD10: 24660 | AE10: 24670 | AF10: 24695 | AG10: 24770 | AH10: 24850 | AI10: 24925 | AJ10: 25110 | AK10: 25345 | AL10: 25575 | AM10: 25795 | AN10: 25970 | AO10: 26160 | AP10: 26355 | AQ10: 26590 | AR10: 26730 | AS10: 26795 | AT10: 26880 | AU10: 26900 | AV10: 26935 | AW10: 26900 | AX10: 26750 | AY10: 26530 | AZ10: 26275 | BA10: 26025 | BB10: 25820 | BC10: 25710 | BD10: 25605 | BE10: 25509 | BF10: 25336 | BG10: 25282 | BH10: 25293 | BI10: 25316 | BJ10: 25320 | BK10: 25408 | BL10: 25451 | BM10: 25559 | BN10: 25600 | BO10: 25670 | BP10: 25770 | BQ10: 25852 | BR10: 25982 | BS10: 25970 | BT10: 26009 | BU10: 26062 | BV10: 26198 | BW10: 26381 | BX10: 26514 | BY10: 26572 | BZ10: 26636 | CA10: 26677 | CB10: 26714 | CC10: 26834 | CD10: 26955 | CE10: 27036 | CF10: 27095 | CG10: 27218 | CH10: 27322 | CI10: 27362 | CJ10: 27468 | CK10: 27555 | CL10: 27549 | CM10: 27623 | CN10: 27707 | CO10: 27715 | CP10: 27803 | CQ10: 27797 | CR10: 27933 | CS10: 27935 | CT10: 28110 | CU10: 28099 | CV10: 28226 | CW10: 28256 | CX10: 28304 | CY10: 28459 | CZ10: 28470 | DA10: 28518 | DB10: 28673 | DC10: 28789 | DD10: 28802 | DE10: 28928 | DF10: 28880 | DG10: 29048 | DH10: 29106 | DI10: 29183 | DJ10: 29214 | DK10: 29194 | DL10: 29322 | DM10: 29420 | DN10: 29576 | DO10: 29684 | DP10: 29722 | DQ10: 29580 | DR10: 29528 | DS10: 29366 | DT10: 29087 | DU10: 29069 | DV10: 29102 | DW10: 29013 | DX10: 29192 | DY10: 29385 | DZ10: 29324 | EA10: 29441 | EB10: 29447 | EC10: 29283 | ED10: 29349 | EE10: 29464 | EF10: 29681 | EG10: 29778 | EH10: 29932 | EI10: 29869 | EJ10: 29974 | EK10: 30144 | EL10: 30330 | EM10: 30573 | EN10: 30747 | EO10: 30873 | EP10: 30981 | EQ10: 31188 | ER10: 31140 | ES10: 31361 | ET10: 31569 | EU10: 31603 | EV10: 31778 | EW10: 31843 | EX10: 31877 | EY10: 31978 | EZ10: 32098 | FA10: 32093 | FB10: 32179 | FC10: 32364 | FD10: 32403 | FE10: 32448 | FF10: 32618 | FG10: 32721 | FH10: 32839 | FI10: 32779 | FJ10: 32954 | FK10: 33000 | FL10: 32571 | FM10: 32354 | FN10: 32198 | FO10: 32221 | FP10: 32377 | FQ10: 32687 | FR10: 32686 | FS10: 32775 | FT10: 32958 | FU10: 32916 | FV10: 33067 | FW10: 33201 | FX10: 33163 | FY10: 33102 | FZ10: 33174 | GA10: 32997 | GB10: 33094 | GC10: 33306.91 | GD10: 33156.91 | GE10: 33260.84 | GF10: 33349.68 | GG10: 33449.47 | GH10: 33554.05 | GI10: 33662.36 | GJ10: 33771.11 | GK10: 33873.27 | GL10: 33975.7 | GM10: 34077.21 | GN10: 34178.63 | GO10: 34278.84 | GP10: 34384.39 | GQ10: 34486.76 | GR10: 34588.66 | GS10: 34683.95 | GT10: 34776.47 | GU10: 34866.05 | GV10: 34951.74 | GW10: 35034.71 | GX10: 35117.85 | GY10: 35197.73 | GZ10: 35277.58 | HA10: 35357.53 | HB10: 35437.45 | HC10: Office for National Statistics\Haver Analytics | HD10: TRUE | HE10: NA | HF10: NA | HG10: 2024 | HH10: 2 | HI10: NA | HJ10: MGRZQ@UK | HK10: UK: LFS: Employment: Aged 16 and Over (SA, Thous) | HL10: GBR | HM10: ETILO | HN10: NICS_Scen.db
A11: United Kingdom | B11: Unemployment rate, ILO definition | C11: NICS_Scen | D11: % | E11: NA | F11: Level | G11: 5.8 | H11: 6.3 | I11: 7.1 | J11: 8 | K11: 8.9 | L11: 9.6 | M11: 9.9 | N11: 10.2 | O11: 10.4 | P11: 10.6 | Q11: 10.8 | R11: 11.1 | S11: 11.3 | T11: 11.4 | U11: 11.5 | V11: 11.7 | W11: 11.8 | X11: 11.9 | Y11: 11.7 | Z11: 11.6 | AA11: 11.5 | AB11: 11.4 | AC11: 11.3 | AD11: 11.3 | AE11: 11.3 | AF11: 11.3 | AG11: 11.4 | AH11: 11.3 | AI11: 11.1 | AJ11: 10.7 | AK11: 10.2 | AL11: 9.7 | AM11: 9.2 | AN11: 8.7 | AO11: 8.4 | AP11: 8 | AQ11: 7.6 | AR11: 7.2 | AS11: 7.1 | AT11: 7 | AU11: 6.9 | AV11: 6.9 | AW11: 7.1 | AX11: 7.5 | AY11: 8 | AZ11: 8.7 | BA11: 9.2 | BB11: 9.5 | BC11: 9.7 | BD11: 9.8 | BE11: 9.9 | BF11: 10.4 | BG11: 10.6 | BH11: 10.4 | BI11: 10.2 | BJ11: 10.3 | BK11: 9.9 | BL11: 9.7 | BM11: 9.4 | BN11: 9 | BO11: 8.9 | BP11: 8.7 | BQ11: 8.6 | BR11: 8.3 | BS11: 8.2 | BT11: 8.3 | BU11: 8.1 | BV11: 7.8 | BW11: 7.3 | BX11: 7.2 | BY11: 6.8 | BZ11: 6.5 | CA11: 6.4 | CB11: 6.3 | CC11: 6.2 | CD11: 6.1 | CE11: 6.2 | CF11: 6 | CG11: 5.9 | CH11: 5.8 | CI11: 5.8 | CJ11: 5.5 | CK11: 5.3 | CL11: 5.2 | CM11: 5.1 | CN11: 5 | CO11: 5.1 | CP11: 5.2 | CQ11: 5.2 | CR11: 5.2 | CS11: 5.3 | CT11: 5.1 | CU11: 5.2 | CV11: 4.9 | CW11: 5 | CX11: 4.9 | CY11: 4.8 | CZ11: 4.8 | DA11: 4.7 | DB11: 4.7 | DC11: 4.7 | DD11: 4.8 | DE11: 4.7 | DF11: 5.1 | DG11: 5.2 | DH11: 5.5 | DI11: 5.5 | DJ11: 5.5 | DK11: 5.5 | DL11: 5.4 | DM11: 5.3 | DN11: 5.2 | DO11: 5.2 | DP11: 5.4 | DQ11: 5.9 | DR11: 6.4 | DS11: 7.1 | DT11: 7.8 | DU11: 7.8 | DV11: 7.8 | DW11: 8 | DX11: 7.9 | DY11: 7.8 | DZ11: 7.9 | EA11: 7.8 | EB11: 7.9 | EC11: 8.3 | ED11: 8.4 | EE11: 8.2 | EF11: 8 | EG11: 7.9 | EH11: 7.8 | EI11: 7.9 | EJ11: 7.8 | EK11: 7.6 | EL11: 7.2 | EM11: 6.8 | EN11: 6.3 | EO11: 6 | EP11: 5.7 | EQ11: 5.6 | ER11: 5.6 | ES11: 5.4 | ET11: 5.1 | EU11: 5.1 | EV11: 5 | EW11: 4.9 | EX11: 4.8 | EY11: 4.6 | EZ11: 4.5 | FA11: 4.3 | FB11: 4.4 | FC11: 4.3 | FD11: 4.1 | FE11: 4.2 | FF11: 4.1 | FG11: 3.9 | FH11: 4 | FI11: 3.9 | FJ11: 3.9 | FK11: 4.1 | FL11: 4.2 | FM11: 5 | FN11: 5.3 | FO11: 5.1 | FP11: 4.8 | FQ11: 4.4 | FR11: 4.2 | FS11: 3.9 | FT11: 3.9 | FU11: 3.8 | FV11: 3.9 | FW11: 4 | FX11: 4.2 | FY11: 4.1 | FZ11: 3.8 | GA11: 4.3 | GB11: 4.2 | GC11: 4.243108 | GD11: 4.408679 | GE11: 4.380091 | GF11: 4.424242 | GG11: 4.424083 | GH11: 4.417153 | GI11: 4.366939 | GJ11: 4.306917 | GK11: 4.247278 | GL11: 4.192399 | GM11: 4.13622 | GN11: 4.09075 | GO11: 4.044635 | GP11: 3.998756 | GQ11: 3.953046 | GR11: 3.909514 | GS11: 3.875439 | GT11: 3.849798 | GU11: 3.832931 | GV11: 3.827398 | GW11: 3.82032 | GX11: 3.813298 | GY11: 3.806122 | GZ11: 3.799546 | HA11: 3.793203 | HB11: 3.78739 | HC11: Office for National Statistics\Haver Analytics | HD11: TRUE | HE11: NA | HF11: NA | HG11: 2024 | HH11: 2 | HI11: NA | HJ11: MGSXQ@UK | HK11: UK: LFS: Unemployment Rate: Aged 16 and Over (SA, %) | HL11: GBR | HM11: UPILO | HN11: NICS_Scen.db
A12: United Kingdom | B12: Income, personal disposable, real, LCU | C12: NICS_Scen | D12: Pound | E12: Millions | F12: Level | G12: 157780 | H12: 158083 | I12: 160445 | J12: 158931 | K12: 160486 | L12: 158130 | M12: 157598 | N12: 158580 | O12: 157715 | P12: 160483 | Q12: 159367 | R12: 159886 | S12: 158854 | T12: 165111 | U12: 163522 | V12: 164202 | W12: 167088 | X12: 165111 | Y12: 169770 | Z12: 173527 | AA12: 175208 | AB12: 175613 | AC12: 175957 | AD12: 177164 | AE12: 179729 | AF12: 186661 | AG12: 183119 | AH12: 183388 | AI12: 180901 | AJ12: 185020 | AK12: 187551 | AL12: 188860 | AM12: 191709 | AN12: 194935 | AO12: 197179 | AP12: 198740 | AQ12: 201265 | AR12: 204179 | AS12: 209872 | AT12: 207949 | AU12: 213872 | AV12: 211391 | AW12: 213462 | AX12: 216821 | AY12: 218128 | AZ12: 214176 | BA12: 220568 | BB12: 220151 | BC12: 221591 | BD12: 223785 | BE12: 225633 | BF12: 225562 | BG12: 224008 | BH12: 230278 | BI12: 232470 | BJ12: 233411 | BK12: 232541 | BL12: 232173 | BM12: 236870 | BN12: 235558 | BO12: 239669 | BP12: 239943 | BQ12: 242123 | BR12: 243427 | BS12: 247598 | BT12: 247441 | BU12: 250067 | BV12: 245800 | BW12: 249558 | BX12: 251781 | BY12: 254358 | BZ12: 253468 | CA12: 253069 | CB12: 254576 | CC12: 253636 | CD12: 257028 | CE12: 254037 | CF12: 266557 | CG12: 267871 | CH12: 274118 | CI12: 274370 | CJ12: 277466 | CK12: 283106 | CL12: 287523 | CM12: 289476 | CN12: 288052 | CO12: 289545 | CP12: 295002 | CQ12: 295976 | CR12: 298538 | CS12: 297567 | CT12: 298904 | CU12: 301081 | CV12: 302934 | CW12: 304444 | CX12: 308695 | CY12: 309585 | CZ12: 312396 | DA12: 314574 | DB12: 315137 | DC12: 317057 | DD12: 320657 | DE12: 322465 | DF12: 322562 | DG12: 325138 | DH12: 323889 | DI12: 327580 | DJ12: 328682 | DK12: 339067 | DL12: 336009 | DM12: 340647 | DN12: 340314 | DO12: 335815 | DP12: 339732 | DQ12: 333684 | DR12: 340023 | DS12: 335761 | DT12: 344826 | DU12: 343613 | DV12: 346368 | DW12: 346769 | DX12: 347421 | DY12: 346091 | DZ12: 343460 | EA12: 334416 | EB12: 339976 | EC12: 339972 | ED12: 337625 | EE12: 344680 | EF12: 348062 | EG12: 346678 | EH12: 345765 | EI12: 342890 | EJ12: 350923 | EK12: 357263 | EL12: 360126 | EM12: 359009 | EN12: 359599 | EO12: 359708 | EP12: 364730 | EQ12: 372232 | ER12: 381179 | ES12: 388638 | ET12: 388470 | EU12: 386874 | EV12: 387633 | EW12: 384657 | EX12: 381981 | EY12: 382290 | EZ12: 390332 | FA12: 390954 | FB12: 391273 | FC12: 395975 | FD12: 394175 | FE12: 395431 | FF12: 400106 | FG12: 399632 | FH12: 405211 | FI12: 405428 | FJ12: 407970 | FK12: 402584 | FL12: 394596 | FM12: 406593 | FN12: 408367 | FO12: 411074 | FP12: 413832 | FQ12: 410138 | FR12: 402842 | FS12: 401738 | FT12: 398386 | FU12: 400405 | FV12: 408689 | FW12: 407362 | FX12: 412328 | FY12: 413001 | FZ12: 415159 | GA12: 420689 | GB12: 426221 | GC12: 427151.4 | GD12: 427205.6 | GE12: 429422 | GF12: 430118.1 | GG12: 431622 | GH12: 433221.2 | GI12: 434859.7 | GJ12: 436100.1 | GK12: 437349.4 | GL12: 438521.8 | GM12: 439874.5 | GN12: 441318.4 | GO12: 442919.5 | GP12: 444458.7 | GQ12: 446442 | GR12: 448606.1 | GS12: 450558.9 | GT12: 452442.6 | GU12: 454329.8 | GV12: 456356.1 | GW12: 458151.5 | GX12: 459896 | GY12: 461682.5 | GZ12: 463721.9 | HA12: 465491.3 | HB12: 467207.5 | HC12: Office for National Statistics\Haver Analytics | HD12: TRUE | HE12: chained 2022 | HF12: NA | HG12: 2024 | HH12: 2 | HI12: NA | HJ12: NRJRQ@UK | HK12: UK: HH & NPISH: Real Household Disposable Income (SA, Mil.Chn.2022.Pounds) | HL12: GBR | HM12: PEDY | HN12: NICS_Scen.db
A13: United Kingdom | B13: Earnings, quarterly total, whole economy, Gross, LCU | C13: NICS_Scen | D13: Pound per Employee | E13: NA | F13: Level | G13: 1256.656 | H13: 1320.788 | I13: 1377.792 | J13: 1419.042 | K13: 1445.746 | L13: 1481.073 | M13: 1519.57 | N13: 1560.495 | O13: 1588.719 | P13: 1621.852 | Q13: 1645.302 | R13: 1677.714 | S13: 1735.998 | T13: 1757.346 | U13: 1777.221 | V13: 1805.329 | W13: 1833.021 | X13: 1859.965 | Y13: 1876.902 | Z13: 1935.882 | AA13: 1996.246 | AB13: 2015.939 | AC13: 2043.298 | AD13: 2093.281 | AE13: 2142.593 | AF13: 2185.823 | AG13: 2220.435 | AH13: 2251.233 | AI13: 2282.895 | AJ13: 2321.792 | AK13: 2369.95 | AL13: 2418.279 | AM13: 2470.636 | AN13: 2512.313 | AO13: 2569.618 | AP13: 2641.639 | AQ13: 2684.494 | AR13: 2756.293 | AS13: 2816.473 | AT13: 2895.669 | AU13: 2978.668 | AV13: 3042.386 | AW13: 3096.331 | AX13: 3142.508 | AY13: 3224.996 | AZ13: 3293.292 | BA13: 3373.081 | BB13: 3431.946 | BC13: 3467.976 | BD13: 3483.129 | BE13: 3486.288 | BF13: 3519.483 | BG13: 3533.243 | BH13: 3585.394 | BI13: 3630.535 | BJ13: 3662.197 | BK13: 3681.295 | BL13: 3682.575 | BM13: 3730.634 | BN13: 3764.534 | BO13: 3784.689 | BP13: 3813.237 | BQ13: 3825.77 | BR13: 3869.823 | BS13: 3882.18 | BT13: 3914.624 | BU13: 3968.22 | BV13: 3978.247 | BW13: 4081.993 | BX13: 4143.857 | BY13: 4207.873 | BZ13: 4225.691 | CA13: 4229.584 | CB13: 4273.278 | CC13: 4319.682 | CD13: 4319.271 | CE13: 4422.741 | CF13: 4529.62 | CG13: 4579.019 | CH13: 4624.274 | CI13: 4637.771 | CJ13: 4701.495 | CK13: 4802.455 | CL13: 4890.775 | CM13: 5001.369 | CN13: 5002.77 | CO13: 5029.651 | CP13: 5057.922 | CQ13: 5089.49 | CR13: 5073.909 | CS13: 5126.548 | CT13: 5142.66 | CU13: 5215.105 | CV13: 5274.743 | CW13: 5382.108 | CX13: 5458.233 | CY13: 5521.079 | CZ13: 5546.886 | DA13: 5624.504 | DB13: 5694.482 | DC13: 5778.829 | DD13: 5743.093 | DE13: 5808.466 | DF13: 5809.272 | DG13: 5993.517 | DH13: 6001.19 | DI13: 6067.312 | DJ13: 6166.277 | DK13: 6414.875 | DL13: 6339.471 | DM13: 6466.942 | DN13: 6476.04 | DO13: 6580.838 | DP13: 6498.069 | DQ13: 6496.127 | DR13: 6443.408 | DS13: 6371.857 | DT13: 6556.603 | DU13: 6566.035 | DV13: 6577.117 | DW13: 6601.875 | DX13: 6547.224 | DY13: 6603.561 | DZ13: 6617.42 | EA13: 6764.375 | EB13: 6692.795 | EC13: 6733.261 | ED13: 6724.496 | EE13: 6797.859 | EF13: 6797.991 | EG13: 6779.331 | EH13: 6805.55 | EI13: 6831.207 | EJ13: 7064.567 | EK13: 7073.654 | EL13: 7154.167 | EM13: 7221.816 | EN13: 7176 | EO13: 7114.859 | EP13: 7151.244 | EQ13: 7196.032 | ER13: 7235.93 | ES13: 7286.774 | ET13: 7292.882 | EU13: 7378.136 | EV13: 7418.134 | EW13: 7455.118 | EX13: 7453.085 | EY13: 7552.214 | EZ13: 7621.865 | FA13: 7682.057 | FB13: 7709.649 | FC13: 7783.628 | FD13: 7753.096 | FE13: 7876.518 | FF13: 7956.615 | FG13: 7998.079 | FH13: 8102.425 | FI13: 8093.845 | FJ13: 8076.643 | FK13: 8056.795 | FL13: 7842.464 | FM13: 8014.82 | FN13: 8241.492 | FO13: 8267.329 | FP13: 8500.161 | FQ13: 8499.45 | FR13: 8570.438 | FS13: 8762.161 | FT13: 8858.754 | FU13: 8972.382 | FV13: 9187.092 | FW13: 9460.302 | FX13: 9660.59 | FY13: 9771.033 | FZ13: 9774.984 | GA13: 9898.726 | GB13: 10025.21 | GC13: 10139.5 | GD13: 10244.95 | GE13: 10327.93 | GF13: 10393.98 | GG13: 10461.16 | GH13: 10527.44 | GI13: 10593.65 | GJ13: 10660.51 | GK13: 10728.56 | GL13: 10796.59 | GM13: 10866.67 | GN13: 10937.3 | GO13: 11008.62 | GP13: 11079.57 | GQ13: 11151.42 | GR13: 11223.94 | GS13: 11297.95 | GT13: 11373.08 | GU13: 11448.53 | GV13: 11524.76 | GW13: 11602.32 | GX13: 11680.6 | GY13: 11759.76 | GZ13: 11840.03 | HA13: 11921.41 | HB13: 12003.38 | HC13: Oxford Economics calculation using Office for National Statistics data | HD13: TRUE | HE13: NA | HF13: NA | HG13: 2024 | HH13: 2 | HI13: NA | HJ13: Oxford Economics calculation using Office for National Statistics data | HK13: NA | HL13: GBR | HM13: ER | HN13: NICS_Scen.db

Sheet DataA
B1: =GMWA!$CR$2 -> OCT031G.db | C1: =$B$1 -> OCT031G.db | D1: =$B$1 -> OCT031G.db | E1: =$B$1 -> OCT031G.db | F1: =$B$1 -> OCT031G.db | G1: =$B$1 -> OCT031G.db | H1: =$B$1 -> OCT031G.db | I1: =$B$1 -> OCT031G.db | J1: =$B$1 -> OCT031G.db | ... BI1: =$B$1 -> OCT031G.db
B2: UK | C2: US | D2: Japan | E2: Canada | F2: Australia | G2: Denmark | H2: Sweden | I2: Switzerland | J2: S Korea | K2: Germany | L2: France | M2: Italy | N2: Spain | O2: Netherlands | P2: Belgium | Q2: Austria | R2: Finland | S2: Ireland | T2: Greece | U2: Portugal | V2: UK | W2: US | X2: Japan | Y2: Canada | Z2: Australia | AA2: Denmark | AB2: Sweden | AC2: Switzerland | AD2: S Korea | AE2: Germany | AF2: France | AG2: Italy | AH2: Spain | AI2: Netherlands | AJ2: Belgium | AK2: Austria | AL2: Finland | AM2: Ireland | AN2: Greece | AO2: Portugal | AP2: UK | AQ2: US | AR2: Japan | AS2: Canada | AT2: Australia | AU2: Denmark | AV2: Sweden | AW2: Switzerland | AX2: S Korea | AY2: Germany | AZ2: France | BA2: Italy | BB2: Spain | BC2: Netherlands | BD2: Belgium | BE2: Austria | BF2: Finland | BG2: Ireland | BH2: Greece | BI2: Portugal | BK2: =B2 -> UK | BL2: =C2 -> US | BM2: =D2 -> Japan | BN2: =E2 -> Canada | BO2: =F2 -> Australia | BP2: =G2 -> Denmark | BQ2: =H2 -> Sweden | BR2: =I2 -> Switzerland | ... CD2: =U2 -> Portugal
B3: GDIP | C3: GDIP | D3: GDIP | E3: GDIP | F3: GDIP | G3: GDIP | H3: GDIP | I3: GDIP | J3: GDIP | K3: GDIP | L3: GDIP | M3: GDIP | N3: GDIP | O3: GDIP | P3: GDIP | Q3: GDIP | R3: GDIP | S3: GDIP | T3: GDIP | U3: GDIP | V3: GGDBT | W3: GGDBT | X3: GGDBT | Y3: GGDBT | Z3: GGDBT | AA3: GGDBT | AB3: GGDBT | AC3: GGDBT | AD3: GGDBT | AE3: GGDBT | AF3: GGDBT | AG3: GGDBT | AH3: GGDBT | AI3: GGDBT | AJ3: GGDBT | AK3: GGDBT | AL3: GGDBT | AM3: GGDBT | AN3: GGDBT | AO3: GGDBT | AP3: GDP! | AQ3: GDP! | AR3: GDP! | AS3: GDP! | AT3: GDP! | AU3: GDP! | AV3: GDP! | AW3: GDP! | AX3: GDP! | AY3: GDP! | AZ3: GDP! | BA3: GDP! | BB3: GDP! | BC3: GDP! | BD3: GDP! | BE3: GDP! | BF3: GDP! | BG3: GDP! | BH3: GDP! | BI3: GDP! | BK3: GDIP/GGDBT | BL3: GDIP/GGDBT | BM3: GDIP/GGDBT | BN3: GDIP/GGDBT | BO3: GDIP/GGDBT | BP3: GDIP/GGDBT | BQ3: GDIP/GGDBT | BR3: GDIP/GGDBT | BS3: GDIP/GGDBT | BT3: GDIP/GGDBT | BU3: GDIP/GGDBT | BV3: GDIP/GGDBT | BW3: GDIP/GGDBT | BX3: GDIP/GGDBT | BY3: GDIP/GGDBT | BZ3: GDIP/GGDBT | CA3: GDIP/GGDBT | CB3: GDIP/GGDBT | CC3: GDIP/GGDBT | CD3: GDIP/GGDBT
B4: GBR | C4: USA | D4: JPN | E4: CAN | F4: AUS | G4: DNK | H4: SWE | I4: CHE | J4: KOR | K4: DEU | L4: FRA | M4: ITA | N4: ESP | O4: NLD | P4: BEL | Q4: AUT | R4: FIN | S4: IRL | T4: GRC | U4: PRT | V4: GBR | W4: USA | X4: JPN | Y4: CAN | Z4: AUS | AA4: DNK | AB4: SWE | AC4: CHE | AD4: KOR | AE4: DEU | AF4: FRA | AG4: ITA | AH4: ESP | AI4: NLD | AJ4: BEL | AK4: AUT | AL4: FIN | AM4: IRL | AN4: GRC | AO4: PRT | AP4: GBR | AQ4: USA | AR4: JPN | AS4: CAN | AT4: AUS | AU4: DNK | AV4: SWE | AW4: CHE | AX4: KOR | AY4: DEU | AZ4: FRA | BA4: ITA | BB4: ESP | BC4: NLD | BD4: BEL | BE4: AUT | BF4: FIN | BG4: IRL | BH4: GRC | BI4: PRT | BK4: =B4 -> GBR | BL4: =C4 -> USA | BM4: =D4 -> JPN | BN4: =E4 -> CAN | BO4: =F4 -> AUS | BP4: =G4 -> DNK | BQ4: =H4 -> SWE | BR4: =I4 -> CHE | ... CD4: =U4 -> PRT
B5: L | C5: L | D5: L | E5: L | F5: L | G5: L | H5: L | I5: L | J5: L | K5: L | L5: L | M5: L | N5: L | O5: L | P5: L | Q5: L | R5: L | S5: L | T5: L | U5: L | V5: L | W5: L | X5: L | Y5: L | Z5: L | AA5: L | AB5: L | AC5: L | AD5: L | AE5: L | AF5: L | AG5: L | AH5: L | AI5: L | AJ5: L | AK5: L | AL5: L | AM5: L | AN5: L | AO5: L | AP5: L | AQ5: L | AR5: L | AS5: L | AT5: L | AU5: L | AV5: L | AW5: L | AX5: L | AY5: L | AZ5: L | BA5: L | BB5: L | BC5: L | BD5: L | BE5: L | BF5: L | BG5: L | BH5: L | BI5: L
A6: =A84+5 -> 2055 | B6: {=_xlfn.CONCAT(INDEX(GMWA!$A$2:$CR$600,MATCH(1,(GMWA!$CQ$2:$CQ$600=B$3)*(GMWA!$CP$2:$CP$600=B$4)*(GMWA!$CR$2:$CR$600=B$1),0),$A6-1966),"0",(INDEX(GMWA!$A$2:$LR$600,MATCH(1,(GMWA!$CQ$2:$CQ$600=B$3)*(GMWA!$CP$2:$CP$600=B$4)*(GMWA!$CR$2:$CR$600=B$1),0),$A6-1965)))} -> 202402 | C6: {=_xlfn.CONCAT(INDEX(GMWA!$A$2:$CR$600,MATCH(1,(GMWA!$CQ$2:$CQ$600=C$3)*(GMWA!$CP$2:$CP$600=C$4)*(GMWA!$CR$2:$CR$600=C$1),0),$A6-1966),"0",(INDEX(GMWA!$A$2:$LR$600,MATCH(1,(GMWA!$CQ$2:$CQ$600=C$3)*(GMWA!$CP$2:$CP$600=C$4)*(GMWA!$CR$2:$CR$600=C$1),0),$A6-1965)))} -> 202402 | D6: {=_xlfn.CONCAT(INDEX(GMWA!$A$2:$CR$600,MATCH(1,(GMWA!$CQ$2:$CQ$600=D$3)*(GMWA!$CP$2:$CP$600=D$4)*(GMWA!$CR$2:$CR$600=D$1),0),$A6-1966),"0",(INDEX(GMWA!$A$2:$LR$600,MATCH(1,(GMWA!$CQ$2:$CQ$600=D$3)*(GMWA!$CP$2:$CP$600=D$4)*(GMWA!$CR$2:$CR$600=D$1),0),$A6-1965)))} -> 202302 | E6: {=_xlfn.CONCAT(INDEX(GMWA!$A$2:$CR$600,MATCH(1,(GMWA!$CQ$2:$CQ$600=E$3)*(GMWA!$CP$2:$CP$600=E$4)*(GMWA!$CR$2:$CR$600=E$1),0),$A6-1966),"0",(INDEX(GMWA!$A$2:$LR$600,MATCH(1,(GMWA!$CQ$2:$CQ$600=E$3)*(GMWA!$CP$2:$CP$600=E$4)*(GMWA!$CR$2:$CR$600=E$1),0),$A6-1965)))} -> 202402 | F6: {=_xlfn.CONCAT(INDEX(GMWA!$A$2:$CR$600,MATCH(1,(GMWA!$CQ$2:$CQ$600=F$3)*(GMWA!$CP$2:$CP$600=F$4)*(GMWA!$CR$2:$CR$600=F$1),0),$A6-1966),"0",(INDEX(GMWA!$A$2:$LR$600,MATCH(1,(GMWA!$CQ$2:$CQ$600=F$3)*(GMWA!$CP$2:$CP$600=F$4)*(GMWA!$CR$2:$CR$600=F$1),0),$A6-1965)))} -> 202402 | G6: {=_xlfn.CONCAT(INDEX(GMWA!$A$2:$CR$600,MATCH(1,(GMWA!$CQ$2:$CQ$600=G$3)*(GMWA!$CP$2:$CP$600=G$4)*(GMWA!$CR$2:$CR$600=G$1),0),$A6-1966),"0",(INDEX(GMWA!$A$2:$LR$600,MATCH(1,(GMWA!$CQ$2:$CQ$600=G$3)*(GMWA!$CP$2:$CP$600=G$4)*(GMWA!$CR$2:$CR$600=G$1),0),$A6-1965)))} -> 202402 | H6: {=_xlfn.CONCAT(INDEX(GMWA!$A$2:$CR$600,MATCH(1,(GMWA!$CQ$2:$CQ$600=H$3)*(GMWA!$CP$2:$CP$600=H$4)*(GMWA!$CR$2:$CR$600=H$1),0),$A6-1966),"0",(INDEX(GMWA!$A$2:$LR$600,MATCH(1,(GMWA!$CQ$2:$CQ$600=H$3)*(GMWA!$CP$2:$CP$600=H$4)*(GMWA!$CR$2:$CR$600=H$1),0),$A6-1965)))} -> 202401 | I6: {=_xlfn.CONCAT(INDEX(GMWA!$A$2:$CR$600,MATCH(1,(GMWA!$CQ$2:$CQ$600=I$3)*(GMWA!$CP$2:$CP$600=I$4)*(GMWA!$CR$2:$CR$600=I$1),0),$A6-1966),"0",(INDEX(GMWA!$A$2:$LR$600,MATCH(1,(GMWA!$CQ$2:$CQ$600=I$3)*(GMWA!$CP$2:$CP$600=I$4)*(GMWA!$CR$2:$CR$600=I$1),0),$A6-1965)))} -> 202004 | ... BI6: {=_xlfn.CONCAT(INDEX(GMWA!$A$2:$CR$600,MATCH(1,(GMWA!$CQ$2:$CQ$600=BI$3)*(GMWA!$CP$2:$CP$600=BI$4)*(GMWA!$CR$2:$CR$600=BI$1),0),$A6-1966),"0",(INDEX(GMWA!$A$2:$LR$600,MATCH(1,(GMWA!$CQ$2:$CQ$600=BI$3)*(GMWA!$CP$2:$CP$600=BI$4)*(GMWA!$CR$2:$CR$600=BI$1),0),$A6-1965)))} -> 202402
A7: 1973 | B7: {=INDEX(GMWA!$A$2:$CR$600,MATCH(1,(GMWA!$CQ$2:$CQ$600=B$3)*(GMWA!$CP$2:$CP$600=B$4)*(GMWA!$CR$2:$CR$600=B$1),0),$A7-1966)} -> 3087 | C7: {=INDEX(GMWA!$A$2:$CR$600,MATCH(1,(GMWA!$CQ$2:$CQ$600=C$3)*(GMWA!$CP$2:$CP$600=C$4)*(GMWA!$CR$2:$CR$600=C$1),0),$A7-1966)} -> 61.95 | D7: {=INDEX(GMWA!$A$2:$CR$600,MATCH(1,(GMWA!$CQ$2:$CQ$600=D$3)*(GMWA!$CP$2:$CP$600=D$4)*(GMWA!$CR$2:$CR$600=D$1),0),$A7-1966)} -> 922.9716 | E7: {=INDEX(GMWA!$A$2:$CR$600,MATCH(1,(GMWA!$CQ$2:$CQ$600=E$3)*(GMWA!$CP$2:$CP$600=E$4)*(GMWA!$CR$2:$CR$600=E$1),0),$A7-1966)} -> 4910 | F7: {=INDEX(GMWA!$A$2:$CR$600,MATCH(1,(GMWA!$CQ$2:$CQ$600=F$3)*(GMWA!$CP$2:$CP$600=F$4)*(GMWA!$CR$2:$CR$600=F$1),0),$A7-1966)} -> 738.1701 | G7: {=INDEX(GMWA!$A$2:$CR$600,MATCH(1,(GMWA!$CQ$2:$CQ$600=G$3)*(GMWA!$CP$2:$CP$600=G$4)*(GMWA!$CR$2:$CR$600=G$1),0),$A7-1966)} -> 1.986917 | H7: {=INDEX(GMWA!$A$2:$CR$600,MATCH(1,(GMWA!$CQ$2:$CQ$600=H$3)*(GMWA!$CP$2:$CP$600=H$4)*(GMWA!$CR$2:$CR$600=H$1),0),$A7-1966)} -> 3553.037 | I7: {=INDEX(GMWA!$A$2:$CR$600,MATCH(1,(GMWA!$CQ$2:$CQ$600=I$3)*(GMWA!$CP$2:$CP$600=I$4)*(GMWA!$CR$2:$CR$600=I$1),0),$A7-1966)} -> 1.915308 | ... BI7: {=INDEX(GMWA!$A$2:$CR$600,MATCH(1,(GMWA!$CQ$2:$CQ$600=BI$3)*(GMWA!$CP$2:$CP$600=BI$4)*(GMWA!$CR$2:$CR$600=BI$1),0),$A7-1966)} -> 23.33603 | BK7: =100*(B7/V7) -> 8.5822878 | BL7: =100*(C7/W7) -> 5.4078119 | BM7: =100*(D7/X7) -> 5.1939876 | BN7: =100*(E7/Y7) -> 7.5628052 | BO7: =100*(F7/Z7) -> 73817010 | BP7: =100*(G7/AA7) -> 1.1897707 | BQ7: =100*(H7/AB7) -> 5.1925969 | BR7: =100*(I7/AC7) -> 1.8912737 | ... CD7: =100*(U7/AO7) -> 1.3545299
A8: =+A7+1 -> 1974 | B8: {=INDEX(GMWA!$A$2:$CR$600,MATCH(1,(GMWA!$CQ$2:$CQ$600=B$3)*(GMWA!$CP$2:$CP$600=B$4)*(GMWA!$CR$2:$CR$600=B$1),0),$A8-1966)} -> 4131 | C8: {=INDEX(GMWA!$A$2:$CR$600,MATCH(1,(GMWA!$CQ$2:$CQ$600=C$3)*(GMWA!$CP$2:$CP$600=C$4)*(GMWA!$CR$2:$CR$600=C$1),0),$A8-1966)} -> 69.55 | D8: {=INDEX(GMWA!$A$2:$CR$600,MATCH(1,(GMWA!$CQ$2:$CQ$600=D$3)*(GMWA!$CP$2:$CP$600=D$4)*(GMWA!$CR$2:$CR$600=D$1),0),$A8-1966)} -> 1196.62 | E8: {=INDEX(GMWA!$A$2:$CR$600,MATCH(1,(GMWA!$CQ$2:$CQ$600=E$3)*(GMWA!$CP$2:$CP$600=E$4)*(GMWA!$CR$2:$CR$600=E$1),0),$A8-1966)} -> 5488 | F8: {=INDEX(GMWA!$A$2:$CR$600,MATCH(1,(GMWA!$CQ$2:$CQ$600=F$3)*(GMWA!$CP$2:$CP$600=F$4)*(GMWA!$CR$2:$CR$600=F$1),0),$A8-1966)} -> 807 | G8: {=INDEX(GMWA!$A$2:$CR$600,MATCH(1,(GMWA!$CQ$2:$CQ$600=G$3)*(GMWA!$CP$2:$CP$600=G$4)*(GMWA!$CR$2:$CR$600=G$1),0),$A8-1966)} -> 2.163271 | H8: {=INDEX(GMWA!$A$2:$CR$600,MATCH(1,(GMWA!$CQ$2:$CQ$600=H$3)*(GMWA!$CP$2:$CP$600=H$4)*(GMWA!$CR$2:$CR$600=H$1),0),$A8-1966)} -> 4397.595 | I8: {=INDEX(GMWA!$A$2:$CR$600,MATCH(1,(GMWA!$CQ$2:$CQ$600=I$3)*(GMWA!$CP$2:$CP$600=I$4)*(GMWA!$CR$2:$CR$600=I$1),0),$A8-1966)} -> 2.263996 | ... BI8: {=INDEX(GMWA!$A$2:$CR$600,MATCH(1,(GMWA!$CQ$2:$CQ$600=BI$3)*(GMWA!$CP$2:$CP$600=BI$4)*(GMWA!$CR$2:$CR$600=BI$1),0),$A8-1966)} -> 23.33603 | BK8: =100*(B8/V8) -> 8.4599839 | BL8: =100*(C8/W8) -> 5.617306 | BM8: =100*(D8/X8) -> 7.2509241 | BN8: =100*(E8/Y8) -> 7.4126101 | BO8: =100*(F8/Z8) -> 80700000 | BP8: =100*(G8/AA8) -> 1.2953719 | BQ8: =100*(H8/AB8) -> 5.6173231 | BR8: =100*(I8/AC8) -> 2.1942007 | ... CD8: =100*(U8/AO8) -> 1.1515709
A9: =+A8+1 -> 1975 | B9: {=INDEX(GMWA!$A$2:$CR$600,MATCH(1,(GMWA!$CQ$2:$CQ$600=B$3)*(GMWA!$CP$2:$CP$600=B$4)*(GMWA!$CR$2:$CR$600=B$1),0),$A9-1966)} -> 4939 | C9: {=INDEX(GMWA!$A$2:$CR$600,MATCH(1,(GMWA!$CQ$2:$CQ$600=C$3)*(GMWA!$CP$2:$CP$600=C$4)*(GMWA!$CR$2:$CR$600=C$1),0),$A9-1966)} -> 77.425 | D9: {=INDEX(GMWA!$A$2:$CR$600,MATCH(1,(GMWA!$CQ$2:$CQ$600=D$3)*(GMWA!$CP$2:$CP$600=D$4)*(GMWA!$CR$2:$CR$600=D$1),0),$A9-1966)} -> 1681.87 | E9: {=INDEX(GMWA!$A$2:$CR$600,MATCH(1,(GMWA!$CQ$2:$CQ$600=E$3)*(GMWA!$CP$2:$CP$600=E$4)*(GMWA!$CR$2:$CR$600=E$1),0),$A9-1966)} -> 6639 | F9: {=INDEX(GMWA!$A$2:$CR$600,MATCH(1,(GMWA!$CQ$2:$CQ$600=F$3)*(GMWA!$CP$2:$CP$600=F$4)*(GMWA!$CR$2:$CR$600=F$1),0),$A9-1966)} -> 916 | G9: {=INDEX(GMWA!$A$2:$CR$600,MATCH(1,(GMWA!$CQ$2:$CQ$600=G$3)*(GMWA!$CP$2:$CP$600=G$4)*(GMWA!$CR$2:$CR$600=G$1),0),$A9-1966)} -> 2.374895 | H9: {=INDEX(GMWA!$A$2:$CR$600,MATCH(1,(GMWA!$CQ$2:$CQ$600=H$3)*(GMWA!$CP$2:$CP$600=H$4)*(GMWA!$CR$2:$CR$600=H$1),0),$A9-1966)} -> 5346.4 | I9: {=INDEX(GMWA!$A$2:$CR$600,MATCH(1,(GMWA!$CQ$2:$CQ$600=I$3)*(GMWA!$CP$2:$CP$600=I$4)*(GMWA!$CR$2:$CR$600=I$1),0),$A9-1966)} -> 2.686347 | ... BI9: {=INDEX(GMWA!$A$2:$CR$600,MATCH(1,(GMWA!$CQ$2:$CQ$600=BI$3)*(GMWA!$CP$2:$CP$600=BI$4)*(GMWA!$CR$2:$CR$600=BI$1),0),$A9-1966)} -> 23.33603 | BK9: =100*(B9/V9) -> 7.883983 | BL9: =100*(C9/W9) -> 5.53676 | BM9: =100*(D9/X9) -> 5.7659502 | BN9: =100*(E9/Y9) -> 8.0669267 | BO9: =100*(F9/Z9) -> 91600000 | BP9: =100*(G9/AA9) -> 1.4220928 | BQ9: =100*(H9/AB9) -> 5.9833203 | BR9: =100*(I9/AC9) -> 2.5110529 | ... CD9: =100*(U9/AO9) -> 0.71420664
A10: =+A9+1 -> 1976 | B10: {=INDEX(GMWA!$A$2:$CR$600,MATCH(1,(GMWA!$CQ$2:$CQ$600=B$3)*(GMWA!$CP$2:$CP$600=B$4)*(GMWA!$CR$2:$CR$600=B$1),0),$A10-1966)} -> 6380 | C10: {=INDEX(GMWA!$A$2:$CR$600,MATCH(1,(GMWA!$CQ$2:$CQ$600=C$3)*(GMWA!$CP$2:$CP$600=C$4)*(GMWA!$CR$2:$CR$600=C$1),0),$A10-1966)} -> 86.725 | D10: {=INDEX(GMWA!$A$2:$CR$600,MATCH(1,(GMWA!$CQ$2:$CQ$600=D$3)*(GMWA!$CP$2:$CP$600=D$4)*(GMWA!$CR$2:$CR$600=D$1),0),$A10-1966)} -> 2416.859 | E10: {=INDEX(GMWA!$A$2:$CR$600,MATCH(1,(GMWA!$CQ$2:$CQ$600=E$3)*(GMWA!$CP$2:$CP$600=E$4)*(GMWA!$CR$2:$CR$600=E$1),0),$A10-1966)} -> 8242 | F10: {=INDEX(GMWA!$A$2:$CR$600,MATCH(1,(GMWA!$CQ$2:$CQ$600=F$3)*(GMWA!$CP$2:$CP$600=F$4)*(GMWA!$CR$2:$CR$600=F$1),0),$A10-1966)} -> 1191 | G10: {=INDEX(GMWA!$A$2:$CR$600,MATCH(1,(GMWA!$CQ$2:$CQ$600=G$3)*(GMWA!$CP$2:$CP$600=G$4)*(GMWA!$CR$2:$CR$600=G$1),0),$A10-1966)} -> 3.083249 | H10: {=INDEX(GMWA!$A$2:$CR$600,MATCH(1,(GMWA!$CQ$2:$CQ$600=H$3)*(GMWA!$CP$2:$CP$600=H$4)*(GMWA!$CR$2:$CR$600=H$1),0),$A10-1966)} -> 5906.224 | I10: {=INDEX(GMWA!$A$2:$CR$600,MATCH(1,(GMWA!$CQ$2:$CQ$600=I$3)*(GMWA!$CP$2:$CP$600=I$4)*(GMWA!$CR$2:$CR$600=I$1),0),$A10-1966)} -> 2.877871 | ... BI10: {=INDEX(GMWA!$A$2:$CR$600,MATCH(1,(GMWA!$CQ$2:$CQ$600=BI$3)*(GMWA!$CP$2:$CP$600=BI$4)*(GMWA!$CR$2:$CR$600=BI$1),0),$A10-1966)} -> 23.33603 | BK10: =100*(B10/V10) -> 8.6917724 | BL10: =100*(C10/W10) -> 5.7520703 | BM10: =100*(D10/X10) -> 5.4923621 | BN10: =100*(E10/Y10) -> 9.0138565 | BO10: =100*(F10/Z10) -> 119100000 | BP10: =100*(G10/AA10) -> 1.8462569 | BQ10: =100*(H10/AB10) -> 6.2641779 | BR10: =100*(I10/AC10) -> 2.6295615 | ... CD10: =100*(U10/AO10) -> 0.47137638
A11: =+A10+1 -> 1977 | B11: {=INDEX(GMWA!$A$2:$CR$600,MATCH(1,(GMWA!$CQ$2:$CQ$600=B$3)*(GMWA!$CP$2:$CP$600=B$4)*(GMWA!$CR$2:$CR$600=B$1),0),$A11-1966)} -> 7333 | C11: {=INDEX(GMWA!$A$2:$CR$600,MATCH(1,(GMWA!$CQ$2:$CQ$600=C$3)*(GMWA!$CP$2:$CP$600=C$4)*(GMWA!$CR$2:$CR$600=C$1),0),$A11-1966)} -> 95.75 | D11: {=INDEX(GMWA!$A$2:$CR$600,MATCH(1,(GMWA!$CQ$2:$CQ$600=D$3)*(GMWA!$CP$2:$CP$600=D$4)*(GMWA!$CR$2:$CR$600=D$1),0),$A11-1966)} -> 3374.968 | E11: {=INDEX(GMWA!$A$2:$CR$600,MATCH(1,(GMWA!$CQ$2:$CQ$600=E$3)*(GMWA!$CP$2:$CP$600=E$4)*(GMWA!$CR$2:$CR$600=E$1),0),$A11-1966)} -> 9432 | F11: {=INDEX(GMWA!$A$2:$CR$600,MATCH(1,(GMWA!$CQ$2:$CQ$600=F$3)*(GMWA!$CP$2:$CP$600=F$4)*(GMWA!$CR$2:$CR$600=F$1),0),$A11-1966)} -> 1532 | G11: {=INDEX(GMWA!$A$2:$CR$600,MATCH(1,(GMWA!$CQ$2:$CQ$600=G$3)*(GMWA!$CP$2:$CP$600=G$4)*(GMWA!$CR$2:$CR$600=G$1),0),$A11-1966)} -> 4.659654 | H11: {=INDEX(GMWA!$A$2:$CR$600,MATCH(1,(GMWA!$CQ$2:$CQ$600=H$3)*(GMWA!$CP$2:$CP$600=H$4)*(GMWA!$CR$2:$CR$600=H$1),0),$A11-1966)} -> 7658.689 | I11: {=INDEX(GMWA!$A$2:$CR$600,MATCH(1,(GMWA!$CQ$2:$CQ$600=I$3)*(GMWA!$CP$2:$CP$600=I$4)*(GMWA!$CR$2:$CR$600=I$1),0),$A11-1966)} -> 3.113591 | ... BI11: {=INDEX(GMWA!$A$2:$CR$600,MATCH(1,(GMWA!$CQ$2:$CQ$600=BI$3)*(GMWA!$CP$2:$CP$600=BI$4)*(GMWA!$CR$2:$CR$600=BI$1),0),$A11-1966)} -> 23.33603 | BK11: =100*(B11/V11) -> 8.7542007 | BL11: =100*(C11/W11) -> 5.8924092 | BM11: =100*(D11/X11) -> 5.7381801 | BN11: =100*(E11/Y11) -> 9.0254918 | BO11: =100*(F11/Z11) -> 153200000 | BP11: =100*(G11/AA11) -> 2.790212 | BQ11: =100*(H11/AB11) -> 6.8816601 | BR11: =100*(I11/AC11) -> 2.8045341 | ... CD11: =100*(U11/AO11) -> 0.33766216
A12: =+A11+1 -> 1978 | B12: {=INDEX(GMWA!$A$2:$CR$600,MATCH(1,(GMWA!$CQ$2:$CQ$600=B$3)*(GMWA!$CP$2:$CP$600=B$4)*(GMWA!$CR$2:$CR$600=B$1),0),$A12-1966)} -> 8160 | C12: {=INDEX(GMWA!$A$2:$CR$600,MATCH(1,(GMWA!$CQ$2:$CQ$600=C$3)*(GMWA!$CP$2:$CP$600=C$4)*(GMWA!$CR$2:$CR$600=C$1),0),$A12-1966)} -> 112.45 | D12: {=INDEX(GMWA!$A$2:$CR$600,MATCH(1,(GMWA!$CQ$2:$CQ$600=D$3)*(GMWA!$CP$2:$CP$600=D$4)*(GMWA!$CR$2:$CR$600=D$1),0),$A12-1966)} -> 4369.668 | E12: {=INDEX(GMWA!$A$2:$CR$600,MATCH(1,(GMWA!$CQ$2:$CQ$600=E$3)*(GMWA!$CP$2:$CP$600=E$4)*(GMWA!$CR$2:$CR$600=E$1),0),$A12-1966)} -> 11741 | F12: {=INDEX(GMWA!$A$2:$CR$600,MATCH(1,(GMWA!$CQ$2:$CQ$600=F$3)*(GMWA!$CP$2:$CP$600=F$4)*(GMWA!$CR$2:$CR$600=F$1),0),$A12-1966)} -> 1796 | G12: {=INDEX(GMWA!$A$2:$CR$600,MATCH(1,(GMWA!$CQ$2:$CQ$600=G$3)*(GMWA!$CP$2:$CP$600=G$4)*(GMWA!$CR$2:$CR$600=G$1),0),$A12-1966)} -> 6.209607 | H12: {=INDEX(GMWA!$A$2:$CR$600,MATCH(1,(GMWA!$CQ$2:$CQ$600=H$3)*(GMWA!$CP$2:$CP$600=H$4)*(GMWA!$CR$2:$CR$600=H$1),0),$A12-1966)} -> 9006.922 | I12: {=INDEX(GMWA!$A$2:$CR$600,MATCH(1,(GMWA!$CQ$2:$CQ$600=I$3)*(GMWA!$CP$2:$CP$600=I$4)*(GMWA!$CR$2:$CR$600=I$1),0),$A12-1966)} -> 3.064492 | ... BI12: {=INDEX(GMWA!$A$2:$CR$600,MATCH(1,(GMWA!$CQ$2:$CQ$600=BI$3)*(GMWA!$CP$2:$CP$600=BI$4)*(GMWA!$CR$2:$CR$600=BI$1),0),$A12-1966)} -> 23.33603 | BK12: =100*(B12/V12) -> 8.6681716 | BL12: =100*(C12/W12) -> 6.3736507 | BM12: =100*(D12/X12) -> 5.3282786 | BN12: =100*(E12/Y12) -> 9.5232302 | BO12: =100*(F12/Z12) -> 179600000 | BP12: =100*(G12/AA12) -> 3.7183275 | BQ12: =100*(H12/AB12) -> 6.285795 | BR12: =100*(I12/AC12) -> 2.7169626 | ... CD12: =100*(U12/AO12) -> 0.2391964
A13: =+A12+1 -> 1979 | B13: {=INDEX(GMWA!$A$2:$CR$600,MATCH(1,(GMWA!$CQ$2:$CQ$600=B$3)*(GMWA!$CP$2:$CP$600=B$4)*(GMWA!$CR$2:$CR$600=B$1),0),$A13-1966)} -> 9791 | C13: {=INDEX(GMWA!$A$2:$CR$600,MATCH(1,(GMWA!$CQ$2:$CQ$600=C$3)*(GMWA!$CP$2:$CP$600=C$4)*(GMWA!$CR$2:$CR$600=C$1),0),$A13-1966)} -> 128.475 | D13: {=INDEX(GMWA!$A$2:$CR$600,MATCH(1,(GMWA!$CQ$2:$CQ$600=D$3)*(GMWA!$CP$2:$CP$600=D$4)*(GMWA!$CR$2:$CR$600=D$1),0),$A13-1966)} -> 5571.224 | E13: {=INDEX(GMWA!$A$2:$CR$600,MATCH(1,(GMWA!$CQ$2:$CQ$600=E$3)*(GMWA!$CP$2:$CP$600=E$4)*(GMWA!$CR$2:$CR$600=E$1),0),$A13-1966)} -> 14057 | F13: {=INDEX(GMWA!$A$2:$CR$600,MATCH(1,(GMWA!$CQ$2:$CQ$600=F$3)*(GMWA!$CP$2:$CP$600=F$4)*(GMWA!$CR$2:$CR$600=F$1),0),$A13-1966)} -> 2136 | G13: {=INDEX(GMWA!$A$2:$CR$600,MATCH(1,(GMWA!$CQ$2:$CQ$600=G$3)*(GMWA!$CP$2:$CP$600=G$4)*(GMWA!$CR$2:$CR$600=G$1),0),$A13-1966)} -> 11.05835 | H13: {=INDEX(GMWA!$A$2:$CR$600,MATCH(1,(GMWA!$CQ$2:$CQ$600=H$3)*(GMWA!$CP$2:$CP$600=H$4)*(GMWA!$CR$2:$CR$600=H$1),0),$A13-1966)} -> 11487.63 | I13: {=INDEX(GMWA!$A$2:$CR$600,MATCH(1,(GMWA!$CQ$2:$CQ$600=I$3)*(GMWA!$CP$2:$CP$600=I$4)*(GMWA!$CR$2:$CR$600=I$1),0),$A13-1966)} -> 2.971176 | ... BI13: {=INDEX(GMWA!$A$2:$CR$600,MATCH(1,(GMWA!$CQ$2:$CQ$600=BI$3)*(GMWA!$CP$2:$CP$600=BI$4)*(GMWA!$CR$2:$CR$600=BI$1),0),$A13-1966)} -> 23.33603 | BK13: =100*(B13/V13) -> 9.3419333 | BL13: =100*(C13/W13) -> 6.7311974 | BM13: =100*(D13/X13) -> 5.6404892 | BN13: =100*(E13/Y13) -> 10.594664 | BO13: =100*(F13/Z13) -> 213600000 | BP13: =100*(G13/AA13) -> 6.6217665 | BQ13: =100*(H13/AB13) -> 6.2418083 | BR13: =100*(I13/AC13) -> 2.534986 | ... CD13: =100*(U13/AO13) -> 0.27793412
A14: =+A13+1 -> 1980 | B14: {=INDEX(GMWA!$A$2:$CR$600,MATCH(1,(GMWA!$CQ$2:$CQ$600=B$3)*(GMWA!$CP$2:$CP$600=B$4)*(GMWA!$CR$2:$CR$600=B$1),0),$A14-1966)} -> 11972 | C14: {=INDEX(GMWA!$A$2:$CR$600,MATCH(1,(GMWA!$CQ$2:$CQ$600=C$3)*(GMWA!$CP$2:$CP$600=C$4)*(GMWA!$CR$2:$CR$600=C$1),0),$A14-1966)} -> 148.775 | D14: {=INDEX(GMWA!$A$2:$CR$600,MATCH(1,(GMWA!$CQ$2:$CQ$600=D$3)*(GMWA!$CP$2:$CP$600=D$4)*(GMWA!$CR$2:$CR$600=D$1),0),$A14-1966)} -> 7259.869 | E14: {=INDEX(GMWA!$A$2:$CR$600,MATCH(1,(GMWA!$CQ$2:$CQ$600=E$3)*(GMWA!$CP$2:$CP$600=E$4)*(GMWA!$CR$2:$CR$600=E$1),0),$A14-1966)} -> 17033 | F14: {=INDEX(GMWA!$A$2:$CR$600,MATCH(1,(GMWA!$CQ$2:$CQ$600=F$3)*(GMWA!$CP$2:$CP$600=F$4)*(GMWA!$CR$2:$CR$600=F$1),0),$A14-1966)} -> 2396 | G14: {=INDEX(GMWA!$A$2:$CR$600,MATCH(1,(GMWA!$CQ$2:$CQ$600=G$3)*(GMWA!$CP$2:$CP$600=G$4)*(GMWA!$CR$2:$CR$600=G$1),0),$A14-1966)} -> 13.37152 | H14: {=INDEX(GMWA!$A$2:$CR$600,MATCH(1,(GMWA!$CQ$2:$CQ$600=H$3)*(GMWA!$CP$2:$CP$600=H$4)*(GMWA!$CR$2:$CR$600=H$1),0),$A14-1966)} -> 16780.39 | I14: {=INDEX(GMWA!$A$2:$CR$600,MATCH(1,(GMWA!$CQ$2:$CQ$600=I$3)*(GMWA!$CP$2:$CP$600=I$4)*(GMWA!$CR$2:$CR$600=I$1),0),$A14-1966)} -> 3.154236 | ... BI14: {=INDEX(GMWA!$A$2:$CR$600,MATCH(1,(GMWA!$CQ$2:$CQ$600=BI$3)*(GMWA!$CP$2:$CP$600=BI$4)*(GMWA!$CR$2:$CR$600=BI$1),0),$A14-1966)} -> 23.33603 | BK14: =100*(B14/V14) -> 9.8501497 | BL14: =100*(C14/W14) -> 7.2611566 | BM14: =100*(D14/X14) -> 6.1974945 | BN14: =100*(E14/Y14) -> 11.32566 | BO14: =100*(F14/Z14) -> 239600000 | BP14: =100*(G14/AA14) -> 7.5300266 | BQ14: =100*(H14/AB14) -> 6.4221104 | BR14: =100*(I14/AC14) -> 2.6313609 | ... CD14: =100*(U14/AO14) -> 0.15037526
A15: =+A14+1 -> 1981 | B15: {=INDEX(GMWA!$A$2:$CR$600,MATCH(1,(GMWA!$CQ$2:$CQ$600=B$3)*(GMWA!$CP$2:$CP$600=B$4)*(GMWA!$CR$2:$CR$600=B$1),0),$A15-1966)} -> 14207 | C15: {=INDEX(GMWA!$A$2:$CR$600,MATCH(1,(GMWA!$CQ$2:$CQ$600=C$3)*(GMWA!$CP$2:$CP$600=C$4)*(GMWA!$CR$2:$CR$600=C$1),0),$A15-1966)} -> 180.075 | D15: {=INDEX(GMWA!$A$2:$CR$600,MATCH(1,(GMWA!$CQ$2:$CQ$600=D$3)*(GMWA!$CP$2:$CP$600=D$4)*(GMWA!$CR$2:$CR$600=D$1),0),$A15-1966)} -> 8747.427 | E15: {=INDEX(GMWA!$A$2:$CR$600,MATCH(1,(GMWA!$CQ$2:$CQ$600=E$3)*(GMWA!$CP$2:$CP$600=E$4)*(GMWA!$CR$2:$CR$600=E$1),0),$A15-1966)} -> 22530 | F15: {=INDEX(GMWA!$A$2:$CR$600,MATCH(1,(GMWA!$CQ$2:$CQ$600=F$3)*(GMWA!$CP$2:$CP$600=F$4)*(GMWA!$CR$2:$CR$600=F$1),0),$A15-1966)} -> 2661 | G15: {=INDEX(GMWA!$A$2:$CR$600,MATCH(1,(GMWA!$CQ$2:$CQ$600=G$3)*(GMWA!$CP$2:$CP$600=G$4)*(GMWA!$CR$2:$CR$600=G$1),0),$A15-1966)} -> 19.54586 | H15: {=INDEX(GMWA!$A$2:$CR$600,MATCH(1,(GMWA!$CQ$2:$CQ$600=H$3)*(GMWA!$CP$2:$CP$600=H$4)*(GMWA!$CR$2:$CR$600=H$1),0),$A15-1966)} -> 24984.48 | I15: {=INDEX(GMWA!$A$2:$CR$600,MATCH(1,(GMWA!$CQ$2:$CQ$600=I$3)*(GMWA!$CP$2:$CP$600=I$4)*(GMWA!$CR$2:$CR$600=I$1),0),$A15-1966)} -> 3.402169 | ... BI15: {=INDEX(GMWA!$A$2:$CR$600,MATCH(1,(GMWA!$CQ$2:$CQ$600=BI$3)*(GMWA!$CP$2:$CP$600=BI$4)*(GMWA!$CR$2:$CR$600=BI$1),0),$A15-1966)} -> 23.33603 | BK15: =100*(B15/V15) -> 10.779906 | BL15: =100*(C15/W15) -> 8.0297351 | BM15: =100*(D15/X15) -> 6.1947545 | BN15: =100*(E15/Y15) -> 12.703478 | BO15: =100*(F15/Z15) -> 266100000 | BP15: =100*(G15/AA15) -> 8.206133 | BQ15: =100*(H15/AB15) -> 7.4161822 | BR15: =100*(I15/AC15) -> 2.8492899 | ... CD15: =100*(U15/AO15) -> 0.099924332
A16: =+A15+1 -> 1982 | B16: {=INDEX(GMWA!$A$2:$CR$600,MATCH(1,(GMWA!$CQ$2:$CQ$600=B$3)*(GMWA!$CP$2:$CP$600=B$4)*(GMWA!$CR$2:$CR$600=B$1),0),$A16-1966)} -> 15540 | C16: {=INDEX(GMWA!$A$2:$CR$600,MATCH(1,(GMWA!$CQ$2:$CQ$600=C$3)*(GMWA!$CP$2:$CP$600=C$4)*(GMWA!$CR$2:$CR$600=C$1),0),$A16-1966)} -> 206.175 | D16: {=INDEX(GMWA!$A$2:$CR$600,MATCH(1,(GMWA!$CQ$2:$CQ$600=D$3)*(GMWA!$CP$2:$CP$600=D$4)*(GMWA!$CR$2:$CR$600=D$1),0),$A16-1966)} -> 10090.23 | E16: {=INDEX(GMWA!$A$2:$CR$600,MATCH(1,(GMWA!$CQ$2:$CQ$600=E$3)*(GMWA!$CP$2:$CP$600=E$4)*(GMWA!$CR$2:$CR$600=E$1),0),$A16-1966)} -> 27419 | F16: {=INDEX(GMWA!$A$2:$CR$600,MATCH(1,(GMWA!$CQ$2:$CQ$600=F$3)*(GMWA!$CP$2:$CP$600=F$4)*(GMWA!$CR$2:$CR$600=F$1),0),$A16-1966)} -> 3141 | G16: {=INDEX(GMWA!$A$2:$CR$600,MATCH(1,(GMWA!$CQ$2:$CQ$600=G$3)*(GMWA!$CP$2:$CP$600=G$4)*(GMWA!$CR$2:$CR$600=G$1),0),$A16-1966)} -> 25.32144 | H16: {=INDEX(GMWA!$A$2:$CR$600,MATCH(1,(GMWA!$CQ$2:$CQ$600=H$3)*(GMWA!$CP$2:$CP$600=H$4)*(GMWA!$CR$2:$CR$600=H$1),0),$A16-1966)} -> 36744.3 | I16: {=INDEX(GMWA!$A$2:$CR$600,MATCH(1,(GMWA!$CQ$2:$CQ$600=I$3)*(GMWA!$CP$2:$CP$600=I$4)*(GMWA!$CR$2:$CR$600=I$1),0),$A16-1966)} -> 3.559402 | ... BI16: {=INDEX(GMWA!$A$2:$CR$600,MATCH(1,(GMWA!$CQ$2:$CQ$600=BI$3)*(GMWA!$CP$2:$CP$600=BI$4)*(GMWA!$CR$2:$CR$600=BI$1),0),$A16-1966)} -> 23.33603 | BK16: =100*(B16/V16) -> 11.054298 | BL16: =100*(C16/W16) -> 8.1881566 | BM16: =100*(D16/X16) -> 6.1194076 | BN16: =100*(E16/Y16) -> 13.073351 | BO16: =100*(F16/Z16) -> 314100000 | BP16: =100*(G16/AA16) -> 7.6570143 | BQ16: =100*(H16/AB16) -> 8.4203707 | BR16: =100*(I16/AC16) -> 3.0338252 | ... CD16: =100*(U16/AO16) -> 0.075589546
A17: =+A16+1 -> 1983 | B17: {=INDEX(GMWA!$A$2:$CR$600,MATCH(1,(GMWA!$CQ$2:$CQ$600=B$3)*(GMWA!$CP$2:$CP$600=B$4)*(GMWA!$CR$2:$CR$600=B$1),0),$A17-1966)} -> 15996 | C17: {=INDEX(GMWA!$A$2:$CR$600,MATCH(1,(GMWA!$CQ$2:$CQ$600=C$3)*(GMWA!$CP$2:$CP$600=C$4)*(GMWA!$CR$2:$CR$600=C$1),0),$A17-1966)} -> 227.975 | D17: {=INDEX(GMWA!$A$2:$CR$600,MATCH(1,(GMWA!$CQ$2:$CQ$600=D$3)*(GMWA!$CP$2:$CP$600=D$4)*(GMWA!$CR$2:$CR$600=D$1),0),$A17-1966)} -> 11534.9 | E17: {=INDEX(GMWA!$A$2:$CR$600,MATCH(1,(GMWA!$CQ$2:$CQ$600=E$3)*(GMWA!$CP$2:$CP$600=E$4)*(GMWA!$CR$2:$CR$600=E$1),0),$A17-1966)} -> 29858 | F17: {=INDEX(GMWA!$A$2:$CR$600,MATCH(1,(GMWA!$CQ$2:$CQ$600=F$3)*(GMWA!$CP$2:$CP$600=F$4)*(GMWA!$CR$2:$CR$600=F$1),0),$A17-1966)} -> 3764 | G17: {=INDEX(GMWA!$A$2:$CR$600,MATCH(1,(GMWA!$CQ$2:$CQ$600=G$3)*(GMWA!$CP$2:$CP$600=G$4)*(GMWA!$CR$2:$CR$600=G$1),0),$A17-1966)} -> 37.50747 | H17: {=INDEX(GMWA!$A$2:$CR$600,MATCH(1,(GMWA!$CQ$2:$CQ$600=H$3)*(GMWA!$CP$2:$CP$600=H$4)*(GMWA!$CR$2:$CR$600=H$1),0),$A17-1966)} -> 43218.67 | I17: {=INDEX(GMWA!$A$2:$CR$600,MATCH(1,(GMWA!$CQ$2:$CQ$600=I$3)*(GMWA!$CP$2:$CP$600=I$4)*(GMWA!$CR$2:$CR$600=I$1),0),$A17-1966)} -> 3.657443 | ... BI17: {=INDEX(GMWA!$A$2:$CR$600,MATCH(1,(GMWA!$CQ$2:$CQ$600=BI$3)*(GMWA!$CP$2:$CP$600=BI$4)*(GMWA!$CR$2:$CR$600=BI$1),0),$A17-1966)} -> 23.33603 | BK17: =100*(B17/V17) -> 10.51792 | BL17: =100*(C17/W17) -> 8.1487452 | BM17: =100*(D17/X17) -> 6.0859908 | BN17: =100*(E17/Y17) -> 11.854622 | BO17: =100*(F17/Z17) -> 376400000 | BP17: =100*(G17/AA17) -> 8.8404927 | BQ17: =100*(H17/AB17) -> 8.3170278 | BR17: =100*(I17/AC17) -> 3.1183198 | ... CD17: =100*(U17/AO17) -> 0.054465
A18: =+A17+1 -> 1984 | B18: {=INDEX(GMWA!$A$2:$CR$600,MATCH(1,(GMWA!$CQ$2:$CQ$600=B$3)*(GMWA!$CP$2:$CP$600=B$4)*(GMWA!$CR$2:$CR$600=B$1),0),$A18-1966)} -> 17461 | C18: {=INDEX(GMWA!$A$2:$CR$600,MATCH(1,(GMWA!$CQ$2:$CQ$600=C$3)*(GMWA!$CP$2:$CP$600=C$4)*(GMWA!$CR$2:$CR$600=C$1),0),$A18-1966)} -> 260.05 | D18: {=INDEX(GMWA!$A$2:$CR$600,MATCH(1,(GMWA!$CQ$2:$CQ$600=D$3)*(GMWA!$CP$2:$CP$600=D$4)*(GMWA!$CR$2:$CR$600=D$1),0),$A18-1966)} -> 12792.81 | E18: {=INDEX(GMWA!$A$2:$CR$600,MATCH(1,(GMWA!$CQ$2:$CQ$600=E$3)*(GMWA!$CP$2:$CP$600=E$4)*(GMWA!$CR$2:$CR$600=E$1),0),$A18-1966)} -> 35147 | F18: {=INDEX(GMWA!$A$2:$CR$600,MATCH(1,(GMWA!$CQ$2:$CQ$600=F$3)*(GMWA!$CP$2:$CP$600=F$4)*(GMWA!$CR$2:$CR$600=F$1),0),$A18-1966)} -> 4951 | G18: {=INDEX(GMWA!$A$2:$CR$600,MATCH(1,(GMWA!$CQ$2:$CQ$600=G$3)*(GMWA!$CP$2:$CP$600=G$4)*(GMWA!$CR$2:$CR$600=G$1),0),$A18-1966)} -> 49.15562 | H18: {=INDEX(GMWA!$A$2:$CR$600,MATCH(1,(GMWA!$CQ$2:$CQ$600=H$3)*(GMWA!$CP$2:$CP$600=H$4)*(GMWA!$CR$2:$CR$600=H$1),0),$A18-1966)} -> 51442.58 | I18: {=INDEX(GMWA!$A$2:$CR$600,MATCH(1,(GMWA!$CQ$2:$CQ$600=I$3)*(GMWA!$CP$2:$CP$600=I$4)*(GMWA!$CR$2:$CR$600=I$1),0),$A18-1966)} -> 3.631457 | ... BI18: {=INDEX(GMWA!$A$2:$CR$600,MATCH(1,(GMWA!$CQ$2:$CQ$600=BI$3)*(GMWA!$CP$2:$CP$600=BI$4)*(GMWA!$CR$2:$CR$600=BI$1),0),$A18-1966)} -> 23.33603 | BK18: =100*(B18/V18) -> 10.66982 | BL18: =100*(C18/W18) -> 8.3536325 | BM18: =100*(D18/X18) -> 6.1521937 | BN18: =100*(E18/Y18) -> 12.091678 | BO18: =100*(F18/Z18) -> 495100000 | BP18: =100*(G18/AA18) -> 10.318747 | BQ18: =100*(H18/AB18) -> 8.6642995 | BR18: =100*(I18/AC18) -> 3.1088846 | ... CD18: =100*(U18/AO18) -> 0.039992361
A19: =+A18+1 -> 1985 | B19: {=INDEX(GMWA!$A$2:$CR$600,MATCH(1,(GMWA!$CQ$2:$CQ$600=B$3)*(GMWA!$CP$2:$CP$600=B$4)*(GMWA!$CR$2:$CR$600=B$1),0),$A19-1966)} -> 19036 | C19: {=INDEX(GMWA!$A$2:$CR$600,MATCH(1,(GMWA!$CQ$2:$CQ$600=C$3)*(GMWA!$CP$2:$CP$600=C$4)*(GMWA!$CR$2:$CR$600=C$1),0),$A19-1966)} -> 285.75 | D19: {=INDEX(GMWA!$A$2:$CR$600,MATCH(1,(GMWA!$CQ$2:$CQ$600=D$3)*(GMWA!$CP$2:$CP$600=D$4)*(GMWA!$CR$2:$CR$600=D$1),0),$A19-1966)} -> 13766.58 | E19: {=INDEX(GMWA!$A$2:$CR$600,MATCH(1,(GMWA!$CQ$2:$CQ$600=E$3)*(GMWA!$CP$2:$CP$600=E$4)*(GMWA!$CR$2:$CR$600=E$1),0),$A19-1966)} -> 40585 | F19: {=INDEX(GMWA!$A$2:$CR$600,MATCH(1,(GMWA!$CQ$2:$CQ$600=F$3)*(GMWA!$CP$2:$CP$600=F$4)*(GMWA!$CR$2:$CR$600=F$1),0),$A19-1966)} -> 6665 | G19: {=INDEX(GMWA!$A$2:$CR$600,MATCH(1,(GMWA!$CQ$2:$CQ$600=G$3)*(GMWA!$CP$2:$CP$600=G$4)*(GMWA!$CR$2:$CR$600=G$1),0),$A19-1966)} -> 55.07229 | H19: {=INDEX(GMWA!$A$2:$CR$600,MATCH(1,(GMWA!$CQ$2:$CQ$600=H$3)*(GMWA!$CP$2:$CP$600=H$4)*(GMWA!$CR$2:$CR$600=H$1),0),$A19-1966)} -> 62413.66 | I19: {=INDEX(GMWA!$A$2:$CR$600,MATCH(1,(GMWA!$CQ$2:$CQ$600=I$3)*(GMWA!$CP$2:$CP$600=I$4)*(GMWA!$CR$2:$CR$600=I$1),0),$A19-1966)} -> 3.735457 | ... BI19: {=INDEX(GMWA!$A$2:$CR$600,MATCH(1,(GMWA!$CQ$2:$CQ$600=BI$3)*(GMWA!$CP$2:$CP$600=BI$4)*(GMWA!$CR$2:$CR$600=BI$1),0),$A19-1966)} -> 23.33603 | BK19: =100*(B19/V19) -> 10.810823 | BL19: =100*(C19/W19) -> 8.1672936 | BM19: =100*(D19/X19) -> 5.9562838 | BN19: =100*(E19/Y19) -> 11.919692 | BO19: =100*(F19/Z19) -> 666500000 | BP19: =100*(G19/AA19) -> 10.996226 | BQ19: =100*(H19/AB19) -> 9.7183358 | BR19: =100*(I19/AC19) -> 3.260981 | ... CD19: =100*(U19/AO19) -> 0.030260414
... A84: =+A83+1 -> 2050 | B84: {=INDEX(GMWA!$A$2:$CR$600,MATCH(1,(GMWA!$CQ$2:$CQ$600=B$3)*(GMWA!$CP$2:$CP$600=B$4)*(GMWA!$CR$2:$CR$600=B$1),0),$A84-1966)} -> 213772.7 | C84: {=INDEX(GMWA!$A$2:$CR$600,MATCH(1,(GMWA!$CQ$2:$CQ$600=C$3)*(GMWA!$CP$2:$CP$600=C$4)*(GMWA!$CR$2:$CR$600=C$1),0),$A84-1966)} -> 4429.109 | D84: {=INDEX(GMWA!$A$2:$CR$600,MATCH(1,(GMWA!$CQ$2:$CQ$600=D$3)*(GMWA!$CP$2:$CP$600=D$4)*(GMWA!$CR$2:$CR$600=D$1),0),$A84-1966)} -> 23218.85 | E84: {=INDEX(GMWA!$A$2:$CR$600,MATCH(1,(GMWA!$CQ$2:$CQ$600=E$3)*(GMWA!$CP$2:$CP$600=E$4)*(GMWA!$CR$2:$CR$600=E$1),0),$A84-1966)} -> 124854.6 | F84: {=INDEX(GMWA!$A$2:$CR$600,MATCH(1,(GMWA!$CQ$2:$CQ$600=F$3)*(GMWA!$CP$2:$CP$600=F$4)*(GMWA!$CR$2:$CR$600=F$1),0),$A84-1966)} -> 134049.1 | G84: {=INDEX(GMWA!$A$2:$CR$600,MATCH(1,(GMWA!$CQ$2:$CQ$600=G$3)*(GMWA!$CP$2:$CP$600=G$4)*(GMWA!$CR$2:$CR$600=G$1),0),$A84-1966)} -> -6.506839 | H84: {=INDEX(GMWA!$A$2:$CR$600,MATCH(1,(GMWA!$CQ$2:$CQ$600=H$3)*(GMWA!$CP$2:$CP$600=H$4)*(GMWA!$CR$2:$CR$600=H$1),0),$A84-1966)} -> 55505.98 | I84: {=INDEX(GMWA!$A$2:$CR$600,MATCH(1,(GMWA!$CQ$2:$CQ$600=I$3)*(GMWA!$CP$2:$CP$600=I$4)*(GMWA!$CR$2:$CR$600=I$1),0),$A84-1966)} -> 4.501213 | ... BI84: {=INDEX(GMWA!$A$2:$CR$600,MATCH(1,(GMWA!$CQ$2:$CQ$600=BI$3)*(GMWA!$CP$2:$CP$600=BI$4)*(GMWA!$CR$2:$CR$600=BI$1),0),$A84-1966)} -> 590.908 | BK84: =100*(B84/V84) -> 3.2215405 | BL84: =100*(C84/W84) -> 3.2699483 | BM84: =100*(D84/X84) -> 1.4568014 | BN84: =100*(E84/Y84) -> 3.6557165 | BO84: =100*(F84/Z84) -> 3.5357242 | BP84: =100*(G84/AA84) -> -2.1011113 | BQ84: =100*(H84/AB84) -> 1.5997587 | BR84: =100*(I84/AC84) -> 0.93542584 | ... CD84: =100*(U84/AO84) -> 2.6990685

Sheet DataQ
E1: Oct24_2.db | F1: =$E$1 -> Oct24_2.db | G1: =$E$1 -> Oct24_2.db | H1: =$E$1 -> Oct24_2.db | I1: =$E$1 -> Oct24_2.db | J1: =$E$1 -> Oct24_2.db | K1: NICs_scen.db | L1: =$K$1 -> NICs_scen.db | M1: =$K$1 -> NICs_scen.db | N1: =$K$1 -> NICs_scen.db | O1: =$K$1 -> NICs_scen.db | P1: =$K$1 -> NICs_scen.db
E2: UK | F2: UK | G2: UK | H2: UK | I2: UK | J2: UK | K2: UK | L2: UK | M2: UK | N2: UK | O2: UK | P2: UK
E3: GDP | F3: ETILO | G3: ER | H3: UPILO | I3: PEDY | J3: TP | K3: GDP | L3: ETILO | M3: ER | N3: UPILO | O3: PEDY | P3: TP
E4: GBR | F4: GBR | G4: GBR | H4: GBR | I4: GBR | J4: GBR | K4: GBR | L4: GBR | M4: GBR | N4: GBR | O4: GBR | P4: GBR
E5: L | F5: L | G5: L | H5: L | I5: L | J5: L | K5: L | L5: L | M5: L | N5: L | O5: L | P5: L
B6: =B210+5 -> 2188 | C6: CY | D6: FY | E6: {=_xlfn.CONCAT(INDEX(GMWQ!$A$2:$HM$50,MATCH(1,(GMWQ!$HM$2:$HM$50=E$3)*(GMWQ!$HL$2:$HL$50=E$4),0),$B6-1973),"0",(INDEX(GMWQ!$A$2:$HM$50,MATCH(1,(GMWQ!$HM$2:$HM$50=E$3)*(GMWQ!$HL$2:$HL$50=E$4),0),$B6-1972)))} -> 202402 | F6: {=_xlfn.CONCAT(INDEX(GMWQ!$A$2:$HM$50,MATCH(1,(GMWQ!$HM$2:$HM$50=F$3)*(GMWQ!$HL$2:$HL$50=F$4),0),$B6-1973),"0",(INDEX(GMWQ!$A$2:$HM$50,MATCH(1,(GMWQ!$HM$2:$HM$50=F$3)*(GMWQ!$HL$2:$HL$50=F$4),0),$B6-1972)))} -> 202402 | G6: {=_xlfn.CONCAT(INDEX(GMWQ!$A$2:$HM$50,MATCH(1,(GMWQ!$HM$2:$HM$50=G$3)*(GMWQ!$HL$2:$HL$50=G$4),0),$B6-1973),"0",(INDEX(GMWQ!$A$2:$HM$50,MATCH(1,(GMWQ!$HM$2:$HM$50=G$3)*(GMWQ!$HL$2:$HL$50=G$4),0),$B6-1972)))} -> 202402 | H6: {=_xlfn.CONCAT(INDEX(GMWQ!$A$2:$HM$50,MATCH(1,(GMWQ!$HM$2:$HM$50=H$3)*(GMWQ!$HL$2:$HL$50=H$4),0),$B6-1973),"0",(INDEX(GMWQ!$A$2:$HM$50,MATCH(1,(GMWQ!$HM$2:$HM$50=H$3)*(GMWQ!$HL$2:$HL$50=H$4),0),$B6-1972)))} -> 202402 | I6: {=_xlfn.CONCAT(INDEX(GMWQ!$A$2:$HM$50,MATCH(1,(GMWQ!$HM$2:$HM$50=I$3)*(GMWQ!$HL$2:$HL$50=I$4),0),$B6-1973),"0",(INDEX(GMWQ!$A$2:$HM$50,MATCH(1,(GMWQ!$HM$2:$HM$50=I$3)*(GMWQ!$HL$2:$HL$50=I$4),0),$B6-1972)))} -> 202402 | J6: {=_xlfn.CONCAT(INDEX(GMWQ!$A$2:$HM$50,MATCH(1,(GMWQ!$HM$2:$HM$50=J$3)*(GMWQ!$HL$2:$HL$50=J$4),0),$B6-1973),"0",(INDEX(GMWQ!$A$2:$HM$50,MATCH(1,(GMWQ!$HM$2:$HM$50=J$3)*(GMWQ!$HL$2:$HL$50=J$4),0),$B6-1972)))} -> 202402 | K6: {=_xlfn.CONCAT(INDEX(GMWQ!$A$2:$HM$50,MATCH(1,(GMWQ!$HM$2:$HM$50=K$3)*(GMWQ!$HL$2:$HL$50=K$4),0),$B6-1973),"0",(INDEX(GMWQ!$A$2:$HM$50,MATCH(1,(GMWQ!$HM$2:$HM$50=K$3)*(GMWQ!$HL$2:$HL$50=K$4),0),$B6-1972)))} -> 202402 | L6: {=_xlfn.CONCAT(INDEX(GMWQ!$A$2:$HM$50,MATCH(1,(GMWQ!$HM$2:$HM$50=L$3)*(GMWQ!$HL$2:$HL$50=L$4),0),$B6-1973),"0",(INDEX(GMWQ!$A$2:$HM$50,MATCH(1,(GMWQ!$HM$2:$HM$50=L$3)*(GMWQ!$HL$2:$HL$50=L$4),0),$B6-1972)))} -> 202402 | ... P6: {=_xlfn.CONCAT(INDEX(GMWQ!$A$2:$HM$50,MATCH(1,(GMWQ!$HM$2:$HM$50=P$3)*(GMWQ!$HL$2:$HL$50=P$4),0),$B6-1973),"0",(INDEX(GMWQ!$A$2:$HM$50,MATCH(1,(GMWQ!$HM$2:$HM$50=P$3)*(GMWQ!$HL$2:$HL$50=P$4),0),$B6-1972)))} -> 202402
A7: 1980 | B7: 1980 | C7: 1980 | E7: {=INDEX(GMWQ!$A$2:$HN$50,MATCH(1,(GMWQ!$HM$2:$HM$50=E$3)*(GMWQ!$HN$2:$HN$50=E$1),0),$B7-1973)} -> 269776 | F7: {=INDEX(GMWQ!$A$2:$HN$50,MATCH(1,(GMWQ!$HM$2:$HM$50=F$3)*(GMWQ!$HN$2:$HN$50=F$1),0),$B7-1973)} -> 25250 | G7: {=INDEX(GMWQ!$A$2:$HN$50,MATCH(1,(GMWQ!$HM$2:$HM$50=G$3)*(GMWQ!$HN$2:$HN$50=G$1),0),$B7-1973)} -> 1256.656 | H7: {=INDEX(GMWQ!$A$2:$HN$50,MATCH(1,(GMWQ!$HM$2:$HM$50=H$3)*(GMWQ!$HN$2:$HN$50=H$1),0),$B7-1973)} -> 5.8 | I7: {=INDEX(GMWQ!$A$2:$HN$50,MATCH(1,(GMWQ!$HM$2:$HM$50=I$3)*(GMWQ!$HN$2:$HN$50=I$1),0),$B7-1973)} -> 157780 | J7: {=INDEX(GMWQ!$A$2:$HN$50,MATCH(1,(GMWQ!$HM$2:$HM$50=J$3)*(GMWQ!$HN$2:$HN$50=J$1),0),$B7-1973)} -> 2203.656 | K7: {=INDEX(GMWQ!$A$2:$HN$50,MATCH(1,(GMWQ!$HM$2:$HM$50=K$3)*(GMWQ!$HN$2:$HN$50=K$1),0),$B7-1973)} -> 269776 | L7: {=INDEX(GMWQ!$A$2:$HN$50,MATCH(1,(GMWQ!$HM$2:$HM$50=L$3)*(GMWQ!$HN$2:$HN$50=L$1),0),$B7-1973)} -> 25250 | ... P7: {=INDEX(GMWQ!$A$2:$HN$50,MATCH(1,(GMWQ!$HM$2:$HM$50=P$3)*(GMWQ!$HN$2:$HN$50=P$1),0),$B7-1973)} -> 2203.656
B8: =+B7+1 -> 1981 | C8: 1980 | D8: 1980 | E8: {=INDEX(GMWQ!$A$2:$HN$50,MATCH(1,(GMWQ!$HM$2:$HM$50=E$3)*(GMWQ!$HN$2:$HN$50=E$1),0),$B8-1973)} -> 264448 | F8: {=INDEX(GMWQ!$A$2:$HN$50,MATCH(1,(GMWQ!$HM$2:$HM$50=F$3)*(GMWQ!$HN$2:$HN$50=F$1),0),$B8-1973)} -> 25190 | G8: {=INDEX(GMWQ!$A$2:$HN$50,MATCH(1,(GMWQ!$HM$2:$HM$50=G$3)*(GMWQ!$HN$2:$HN$50=G$1),0),$B8-1973)} -> 1320.788 | H8: {=INDEX(GMWQ!$A$2:$HN$50,MATCH(1,(GMWQ!$HM$2:$HM$50=H$3)*(GMWQ!$HN$2:$HN$50=H$1),0),$B8-1973)} -> 6.3 | I8: {=INDEX(GMWQ!$A$2:$HN$50,MATCH(1,(GMWQ!$HM$2:$HM$50=I$3)*(GMWQ!$HN$2:$HN$50=I$1),0),$B8-1973)} -> 158083 | J8: {=INDEX(GMWQ!$A$2:$HN$50,MATCH(1,(GMWQ!$HM$2:$HM$50=J$3)*(GMWQ!$HN$2:$HN$50=J$1),0),$B8-1973)} -> 2273.364 | K8: {=INDEX(GMWQ!$A$2:$HN$50,MATCH(1,(GMWQ!$HM$2:$HM$50=K$3)*(GMWQ!$HN$2:$HN$50=K$1),0),$B8-1973)} -> 264448 | L8: {=INDEX(GMWQ!$A$2:$HN$50,MATCH(1,(GMWQ!$HM$2:$HM$50=L$3)*(GMWQ!$HN$2:$HN$50=L$1),0),$B8-1973)} -> 25190 | ... P8: {=INDEX(GMWQ!$A$2:$HN$50,MATCH(1,(GMWQ!$HM$2:$HM$50=P$3)*(GMWQ!$HN$2:$HN$50=P$1),0),$B8-1973)} -> 2273.364
B9: =+B8+1 -> 1982 | C9: 1980 | D9: 1980 | E9: {=INDEX(GMWQ!$A$2:$HN$50,MATCH(1,(GMWQ!$HM$2:$HM$50=E$3)*(GMWQ!$HN$2:$HN$50=E$1),0),$B9-1973)} -> 264139 | F9: {=INDEX(GMWQ!$A$2:$HN$50,MATCH(1,(GMWQ!$HM$2:$HM$50=F$3)*(GMWQ!$HN$2:$HN$50=F$1),0),$B9-1973)} -> 25050 | G9: {=INDEX(GMWQ!$A$2:$HN$50,MATCH(1,(GMWQ!$HM$2:$HM$50=G$3)*(GMWQ!$HN$2:$HN$50=G$1),0),$B9-1973)} -> 1377.792 | H9: {=INDEX(GMWQ!$A$2:$HN$50,MATCH(1,(GMWQ!$HM$2:$HM$50=H$3)*(GMWQ!$HN$2:$HN$50=H$1),0),$B9-1973)} -> 7.1 | I9: {=INDEX(GMWQ!$A$2:$HN$50,MATCH(1,(GMWQ!$HM$2:$HM$50=I$3)*(GMWQ!$HN$2:$HN$50=I$1),0),$B9-1973)} -> 160445 | J9: {=INDEX(GMWQ!$A$2:$HN$50,MATCH(1,(GMWQ!$HM$2:$HM$50=J$3)*(GMWQ!$HN$2:$HN$50=J$1),0),$B9-1973)} -> 2332.952 | K9: {=INDEX(GMWQ!$A$2:$HN$50,MATCH(1,(GMWQ!$HM$2:$HM$50=K$3)*(GMWQ!$HN$2:$HN$50=K$1),0),$B9-1973)} -> 264139 | L9: {=INDEX(GMWQ!$A$2:$HN$50,MATCH(1,(GMWQ!$HM$2:$HM$50=L$3)*(GMWQ!$HN$2:$HN$50=L$1),0),$B9-1973)} -> 25050 | ... P9: {=INDEX(GMWQ!$A$2:$HN$50,MATCH(1,(GMWQ!$HM$2:$HM$50=P$3)*(GMWQ!$HN$2:$HN$50=P$1),0),$B9-1973)} -> 2332.952
B10: =+B9+1 -> 1983 | C10: 1980 | D10: 1980 | E10: {=INDEX(GMWQ!$A$2:$HN$50,MATCH(1,(GMWQ!$HM$2:$HM$50=E$3)*(GMWQ!$HN$2:$HN$50=E$1),0),$B10-1973)} -> 261297 | F10: {=INDEX(GMWQ!$A$2:$HN$50,MATCH(1,(GMWQ!$HM$2:$HM$50=F$3)*(GMWQ!$HN$2:$HN$50=F$1),0),$B10-1973)} -> 24855 | G10: {=INDEX(GMWQ!$A$2:$HN$50,MATCH(1,(GMWQ!$HM$2:$HM$50=G$3)*(GMWQ!$HN$2:$HN$50=G$1),0),$B10-1973)} -> 1419.042 | H10: {=INDEX(GMWQ!$A$2:$HN$50,MATCH(1,(GMWQ!$HM$2:$HM$50=H$3)*(GMWQ!$HN$2:$HN$50=H$1),0),$B10-1973)} -> 8 | I10: {=INDEX(GMWQ!$A$2:$HN$50,MATCH(1,(GMWQ!$HM$2:$HM$50=I$3)*(GMWQ!$HN$2:$HN$50=I$1),0),$B10-1973)} -> 158931 | J10: {=INDEX(GMWQ!$A$2:$HN$50,MATCH(1,(GMWQ!$HM$2:$HM$50=J$3)*(GMWQ!$HN$2:$HN$50=J$1),0),$B10-1973)} -> 2420.649 | K10: {=INDEX(GMWQ!$A$2:$HN$50,MATCH(1,(GMWQ!$HM$2:$HM$50=K$3)*(GMWQ!$HN$2:$HN$50=K$1),0),$B10-1973)} -> 261297 | L10: {=INDEX(GMWQ!$A$2:$HN$50,MATCH(1,(GMWQ!$HM$2:$HM$50=L$3)*(GMWQ!$HN$2:$HN$50=L$1),0),$B10-1973)} -> 24855 | ... P10: {=INDEX(GMWQ!$A$2:$HN$50,MATCH(1,(GMWQ!$HM$2:$HM$50=P$3)*(GMWQ!$HN$2:$HN$50=P$1),0),$B10-1973)} -> 2420.649
A11: 1981 | B11: =+B10+1 -> 1984 | C11: =+C7+1 -> 1981 | D11: 1980 | E11: {=INDEX(GMWQ!$A$2:$HN$50,MATCH(1,(GMWQ!$HM$2:$HM$50=E$3)*(GMWQ!$HN$2:$HN$50=E$1),0),$B11-1973)} -> 261131 | F11: {=INDEX(GMWQ!$A$2:$HN$50,MATCH(1,(GMWQ!$HM$2:$HM$50=F$3)*(GMWQ!$HN$2:$HN$50=F$1),0),$B11-1973)} -> 24661 | G11: {=INDEX(GMWQ!$A$2:$HN$50,MATCH(1,(GMWQ!$HM$2:$HM$50=G$3)*(GMWQ!$HN$2:$HN$50=G$1),0),$B11-1973)} -> 1445.746 | H11: {=INDEX(GMWQ!$A$2:$HN$50,MATCH(1,(GMWQ!$HM$2:$HM$50=H$3)*(GMWQ!$HN$2:$HN$50=H$1),0),$B11-1973)} -> 8.9 | I11: {=INDEX(GMWQ!$A$2:$HN$50,MATCH(1,(GMWQ!$HM$2:$HM$50=I$3)*(GMWQ!$HN$2:$HN$50=I$1),0),$B11-1973)} -> 160486 | J11: {=INDEX(GMWQ!$A$2:$HN$50,MATCH(1,(GMWQ!$HM$2:$HM$50=J$3)*(GMWQ!$HN$2:$HN$50=J$1),0),$B11-1973)} -> 2498.227 | K11: {=INDEX(GMWQ!$A$2:$HN$50,MATCH(1,(GMWQ!$HM$2:$HM$50=K$3)*(GMWQ!$HN$2:$HN$50=K$1),0),$B11-1973)} -> 261131 | L11: {=INDEX(GMWQ!$A$2:$HN$50,MATCH(1,(GMWQ!$HM$2:$HM$50=L$3)*(GMWQ!$HN$2:$HN$50=L$1),0),$B11-1973)} -> 24661 | ... P11: {=INDEX(GMWQ!$A$2:$HN$50,MATCH(1,(GMWQ!$HM$2:$HM$50=P$3)*(GMWQ!$HN$2:$HN$50=P$1),0),$B11-1973)} -> 2498.227
B12: =+B11+1 -> 1985 | C12: =+C8+1 -> 1981 | D12: =+D8+1 -> 1981 | E12: {=INDEX(GMWQ!$A$2:$HN$50,MATCH(1,(GMWQ!$HM$2:$HM$50=E$3)*(GMWQ!$HN$2:$HN$50=E$1),0),$B12-1973)} -> 261739 | F12: {=INDEX(GMWQ!$A$2:$HN$50,MATCH(1,(GMWQ!$HM$2:$HM$50=F$3)*(GMWQ!$HN$2:$HN$50=F$1),0),$B12-1973)} -> 24495 | G12: {=INDEX(GMWQ!$A$2:$HN$50,MATCH(1,(GMWQ!$HM$2:$HM$50=G$3)*(GMWQ!$HN$2:$HN$50=G$1),0),$B12-1973)} -> 1481.073 | H12: {=INDEX(GMWQ!$A$2:$HN$50,MATCH(1,(GMWQ!$HM$2:$HM$50=H$3)*(GMWQ!$HN$2:$HN$50=H$1),0),$B12-1973)} -> 9.6 | I12: {=INDEX(GMWQ!$A$2:$HN$50,MATCH(1,(GMWQ!$HM$2:$HM$50=I$3)*(GMWQ!$HN$2:$HN$50=I$1),0),$B12-1973)} -> 158130 | J12: {=INDEX(GMWQ!$A$2:$HN$50,MATCH(1,(GMWQ!$HM$2:$HM$50=J$3)*(GMWQ!$HN$2:$HN$50=J$1),0),$B12-1973)} -> 2399.287 | K12: {=INDEX(GMWQ!$A$2:$HN$50,MATCH(1,(GMWQ!$HM$2:$HM$50=K$3)*(GMWQ!$HN$2:$HN$50=K$1),0),$B12-1973)} -> 261739 | L12: {=INDEX(GMWQ!$A$2:$HN$50,MATCH(1,(GMWQ!$HM$2:$HM$50=L$3)*(GMWQ!$HN$2:$HN$50=L$1),0),$B12-1973)} -> 24495 | ... P12: {=INDEX(GMWQ!$A$2:$HN$50,MATCH(1,(GMWQ!$HM$2:$HM$50=P$3)*(GMWQ!$HN$2:$HN$50=P$1),0),$B12-1973)} -> 2399.287
B13: =+B12+1 -> 1986 | C13: =+C9+1 -> 1981 | D13: =+D9+1 -> 1981 | E13: {=INDEX(GMWQ!$A$2:$HN$50,MATCH(1,(GMWQ!$HM$2:$HM$50=E$3)*(GMWQ!$HN$2:$HN$50=E$1),0),$B13-1973)} -> 264602 | F13: {=INDEX(GMWQ!$A$2:$HN$50,MATCH(1,(GMWQ!$HM$2:$HM$50=F$3)*(GMWQ!$HN$2:$HN$50=F$1),0),$B13-1973)} -> 24355 | G13: {=INDEX(GMWQ!$A$2:$HN$50,MATCH(1,(GMWQ!$HM$2:$HM$50=G$3)*(GMWQ!$HN$2:$HN$50=G$1),0),$B13-1973)} -> 1519.57 | H13: {=INDEX(GMWQ!$A$2:$HN$50,MATCH(1,(GMWQ!$HM$2:$HM$50=H$3)*(GMWQ!$HN$2:$HN$50=H$1),0),$B13-1973)} -> 9.9 | I13: {=INDEX(GMWQ!$A$2:$HN$50,MATCH(1,(GMWQ!$HM$2:$HM$50=I$3)*(GMWQ!$HN$2:$HN$50=I$1),0),$B13-1973)} -> 157598 | J13: {=INDEX(GMWQ!$A$2:$HN$50,MATCH(1,(GMWQ!$HM$2:$HM$50=J$3)*(GMWQ!$HN$2:$HN$50=J$1),0),$B13-1973)} -> 2452.13 | K13: {=INDEX(GMWQ!$A$2:$HN$50,MATCH(1,(GMWQ!$HM$2:$HM$50=K$3)*(GMWQ!$HN$2:$HN$50=K$1),0),$B13-1973)} -> 264602 | L13: {=INDEX(GMWQ!$A$2:$HN$50,MATCH(1,(GMWQ!$HM$2:$HM$50=L$3)*(GMWQ!$HN$2:$HN$50=L$1),0),$B13-1973)} -> 24355 | ... P13: {=INDEX(GMWQ!$A$2:$HN$50,MATCH(1,(GMWQ!$HM$2:$HM$50=P$3)*(GMWQ!$HN$2:$HN$50=P$1),0),$B13-1973)} -> 2452.13
B14: =+B13+1 -> 1987 | C14: =+C10+1 -> 1981 | D14: =+D10+1 -> 1981 | E14: {=INDEX(GMWQ!$A$2:$HN$50,MATCH(1,(GMWQ!$HM$2:$HM$50=E$3)*(GMWQ!$HN$2:$HN$50=E$1),0),$B14-1973)} -> 264902 | F14: {=INDEX(GMWQ!$A$2:$HN$50,MATCH(1,(GMWQ!$HM$2:$HM$50=F$3)*(GMWQ!$HN$2:$HN$50=F$1),0),$B14-1973)} -> 24209 | G14: {=INDEX(GMWQ!$A$2:$HN$50,MATCH(1,(GMWQ!$HM$2:$HM$50=G$3)*(GMWQ!$HN$2:$HN$50=G$1),0),$B14-1973)} -> 1560.495 | H14: {=INDEX(GMWQ!$A$2:$HN$50,MATCH(1,(GMWQ!$HM$2:$HM$50=H$3)*(GMWQ!$HN$2:$HN$50=H$1),0),$B14-1973)} -> 10.2 | I14: {=INDEX(GMWQ!$A$2:$HN$50,MATCH(1,(GMWQ!$HM$2:$HM$50=I$3)*(GMWQ!$HN$2:$HN$50=I$1),0),$B14-1973)} -> 158580 | J14: {=INDEX(GMWQ!$A$2:$HN$50,MATCH(1,(GMWQ!$HM$2:$HM$50=J$3)*(GMWQ!$HN$2:$HN$50=J$1),0),$B14-1973)} -> 2560.064 | K14: {=INDEX(GMWQ!$A$2:$HN$50,MATCH(1,(GMWQ!$HM$2:$HM$50=K$3)*(GMWQ!$HN$2:$HN$50=K$1),0),$B14-1973)} -> 264902 | L14: {=INDEX(GMWQ!$A$2:$HN$50,MATCH(1,(GMWQ!$HM$2:$HM$50=L$3)*(GMWQ!$HN$2:$HN$50=L$1),0),$B14-1973)} -> 24209 | ... P14: {=INDEX(GMWQ!$A$2:$HN$50,MATCH(1,(GMWQ!$HM$2:$HM$50=P$3)*(GMWQ!$HN$2:$HN$50=P$1),0),$B14-1973)} -> 2560.064
A15: 1982 | B15: =+B14+1 -> 1988 | C15: =+C11+1 -> 1982 | D15: =+D11+1 -> 1981 | E15: {=INDEX(GMWQ!$A$2:$HN$50,MATCH(1,(GMWQ!$HM$2:$HM$50=E$3)*(GMWQ!$HN$2:$HN$50=E$1),0),$B15-1973)} -> 265408 | F15: {=INDEX(GMWQ!$A$2:$HN$50,MATCH(1,(GMWQ!$HM$2:$HM$50=F$3)*(GMWQ!$HN$2:$HN$50=F$1),0),$B15-1973)} -> 24120 | G15: {=INDEX(GMWQ!$A$2:$HN$50,MATCH(1,(GMWQ!$HM$2:$HM$50=G$3)*(GMWQ!$HN$2:$HN$50=G$1),0),$B15-1973)} -> 1588.719 | H15: {=INDEX(GMWQ!$A$2:$HN$50,MATCH(1,(GMWQ!$HM$2:$HM$50=H$3)*(GMWQ!$HN$2:$HN$50=H$1),0),$B15-1973)} -> 10.4 | I15: {=INDEX(GMWQ!$A$2:$HN$50,MATCH(1,(GMWQ!$HM$2:$HM$50=I$3)*(GMWQ!$HN$2:$HN$50=I$1),0),$B15-1973)} -> 157715 | J15: {=INDEX(GMWQ!$A$2:$HN$50,MATCH(1,(GMWQ!$HM$2:$HM$50=J$3)*(GMWQ!$HN$2:$HN$50=J$1),0),$B15-1973)} -> 2665.75 | K15: {=INDEX(GMWQ!$A$2:$HN$50,MATCH(1,(GMWQ!$HM$2:$HM$50=K$3)*(GMWQ!$HN$2:$HN$50=K$1),0),$B15-1973)} -> 265408 | L15: {=INDEX(GMWQ!$A$2:$HN$50,MATCH(1,(GMWQ!$HM$2:$HM$50=L$3)*(GMWQ!$HN$2:$HN$50=L$1),0),$B15-1973)} -> 24120 | ... P15: {=INDEX(GMWQ!$A$2:$HN$50,MATCH(1,(GMWQ!$HM$2:$HM$50=P$3)*(GMWQ!$HN$2:$HN$50=P$1),0),$B15-1973)} -> 2665.75
B16: =+B15+1 -> 1989 | C16: =+C12+1 -> 1982 | D16: =+D12+1 -> 1982 | E16: {=INDEX(GMWQ!$A$2:$HN$50,MATCH(1,(GMWQ!$HM$2:$HM$50=E$3)*(GMWQ!$HN$2:$HN$50=E$1),0),$B16-1973)} -> 268196 | F16: {=INDEX(GMWQ!$A$2:$HN$50,MATCH(1,(GMWQ!$HM$2:$HM$50=F$3)*(GMWQ!$HN$2:$HN$50=F$1),0),$B16-1973)} -> 24027 | G16: {=INDEX(GMWQ!$A$2:$HN$50,MATCH(1,(GMWQ!$HM$2:$HM$50=G$3)*(GMWQ!$HN$2:$HN$50=G$1),0),$B16-1973)} -> 1621.852 | H16: {=INDEX(GMWQ!$A$2:$HN$50,MATCH(1,(GMWQ!$HM$2:$HM$50=H$3)*(GMWQ!$HN$2:$HN$50=H$1),0),$B16-1973)} -> 10.6 | I16: {=INDEX(GMWQ!$A$2:$HN$50,MATCH(1,(GMWQ!$HM$2:$HM$50=I$3)*(GMWQ!$HN$2:$HN$50=I$1),0),$B16-1973)} -> 160483 | J16: {=INDEX(GMWQ!$A$2:$HN$50,MATCH(1,(GMWQ!$HM$2:$HM$50=J$3)*(GMWQ!$HN$2:$HN$50=J$1),0),$B16-1973)} -> 2569.059 | K16: {=INDEX(GMWQ!$A$2:$HN$50,MATCH(1,(GMWQ!$HM$2:$HM$50=K$3)*(GMWQ!$HN$2:$HN$50=K$1),0),$B16-1973)} -> 268196 | L16: {=INDEX(GMWQ!$A$2:$HN$50,MATCH(1,(GMWQ!$HM$2:$HM$50=L$3)*(GMWQ!$HN$2:$HN$50=L$1),0),$B16-1973)} -> 24027 | ... P16: {=INDEX(GMWQ!$A$2:$HN$50,MATCH(1,(GMWQ!$HM$2:$HM$50=P$3)*(GMWQ!$HN$2:$HN$50=P$1),0),$B16-1973)} -> 2569.059
B17: =+B16+1 -> 1990 | C17: =+C13+1 -> 1982 | D17: =+D13+1 -> 1982 | E17: {=INDEX(GMWQ!$A$2:$HN$50,MATCH(1,(GMWQ!$HM$2:$HM$50=E$3)*(GMWQ!$HN$2:$HN$50=E$1),0),$B17-1973)} -> 268798 | F17: {=INDEX(GMWQ!$A$2:$HN$50,MATCH(1,(GMWQ!$HM$2:$HM$50=F$3)*(GMWQ!$HN$2:$HN$50=F$1),0),$B17-1973)} -> 23901 | G17: {=INDEX(GMWQ!$A$2:$HN$50,MATCH(1,(GMWQ!$HM$2:$HM$50=G$3)*(GMWQ!$HN$2:$HN$50=G$1),0),$B17-1973)} -> 1645.302 | H17: {=INDEX(GMWQ!$A$2:$HN$50,MATCH(1,(GMWQ!$HM$2:$HM$50=H$3)*(GMWQ!$HN$2:$HN$50=H$1),0),$B17-1973)} -> 10.8 | I17: {=INDEX(GMWQ!$A$2:$HN$50,MATCH(1,(GMWQ!$HM$2:$HM$50=I$3)*(GMWQ!$HN$2:$HN$50=I$1),0),$B17-1973)} -> 159367 | J17: {=INDEX(GMWQ!$A$2:$HN$50,MATCH(1,(GMWQ!$HM$2:$HM$50=J$3)*(GMWQ!$HN$2:$HN$50=J$1),0),$B17-1973)} -> 2582.55 | K17: {=INDEX(GMWQ!$A$2:$HN$50,MATCH(1,(GMWQ!$HM$2:$HM$50=K$3)*(GMWQ!$HN$2:$HN$50=K$1),0),$B17-1973)} -> 268798 | L17: {=INDEX(GMWQ!$A$2:$HN$50,MATCH(1,(GMWQ!$HM$2:$HM$50=L$3)*(GMWQ!$HN$2:$HN$50=L$1),0),$B17-1973)} -> 23901 | ... P17: {=INDEX(GMWQ!$A$2:$HN$50,MATCH(1,(GMWQ!$HM$2:$HM$50=P$3)*(GMWQ!$HN$2:$HN$50=P$1),0),$B17-1973)} -> 2582.55
B18: =+B17+1 -> 1991 | C18: =+C14+1 -> 1982 | D18: =+D14+1 -> 1982 | E18: {=INDEX(GMWQ!$A$2:$HN$50,MATCH(1,(GMWQ!$HM$2:$HM$50=E$3)*(GMWQ!$HN$2:$HN$50=E$1),0),$B18-1973)} -> 270653 | F18: {=INDEX(GMWQ!$A$2:$HN$50,MATCH(1,(GMWQ!$HM$2:$HM$50=F$3)*(GMWQ!$HN$2:$HN$50=F$1),0),$B18-1973)} -> 23755 | G18: {=INDEX(GMWQ!$A$2:$HN$50,MATCH(1,(GMWQ!$HM$2:$HM$50=G$3)*(GMWQ!$HN$2:$HN$50=G$1),0),$B18-1973)} -> 1677.714 | H18: {=INDEX(GMWQ!$A$2:$HN$50,MATCH(1,(GMWQ!$HM$2:$HM$50=H$3)*(GMWQ!$HN$2:$HN$50=H$1),0),$B18-1973)} -> 11.1 | I18: {=INDEX(GMWQ!$A$2:$HN$50,MATCH(1,(GMWQ!$HM$2:$HM$50=I$3)*(GMWQ!$HN$2:$HN$50=I$1),0),$B18-1973)} -> 159886 | J18: {=INDEX(GMWQ!$A$2:$HN$50,MATCH(1,(GMWQ!$HM$2:$HM$50=J$3)*(GMWQ!$HN$2:$HN$50=J$1),0),$B18-1973)} -> 2688.236 | K18: {=INDEX(GMWQ!$A$2:$HN$50,MATCH(1,(GMWQ!$HM$2:$HM$50=K$3)*(GMWQ!$HN$2:$HN$50=K$1),0),$B18-1973)} -> 270653 | L18: {=INDEX(GMWQ!$A$2:$HN$50,MATCH(1,(GMWQ!$HM$2:$HM$50=L$3)*(GMWQ!$HN$2:$HN$50=L$1),0),$B18-1973)} -> 23755 | ... P18: {=INDEX(GMWQ!$A$2:$HN$50,MATCH(1,(GMWQ!$HM$2:$HM$50=P$3)*(GMWQ!$HN$2:$HN$50=P$1),0),$B18-1973)} -> 2688.236
A19: 1983 | B19: =+B18+1 -> 1992 | C19: =+C15+1 -> 1983 | D19: =+D15+1 -> 1982 | E19: {=INDEX(GMWQ!$A$2:$HN$50,MATCH(1,(GMWQ!$HM$2:$HM$50=E$3)*(GMWQ!$HN$2:$HN$50=E$1),0),$B19-1973)} -> 275877 | F19: {=INDEX(GMWQ!$A$2:$HN$50,MATCH(1,(GMWQ!$HM$2:$HM$50=F$3)*(GMWQ!$HN$2:$HN$50=F$1),0),$B19-1973)} -> 23651 | G19: {=INDEX(GMWQ!$A$2:$HN$50,MATCH(1,(GMWQ!$HM$2:$HM$50=G$3)*(GMWQ!$HN$2:$HN$50=G$1),0),$B19-1973)} -> 1735.998 | H19: {=INDEX(GMWQ!$A$2:$HN$50,MATCH(1,(GMWQ!$HM$2:$HM$50=H$3)*(GMWQ!$HN$2:$HN$50=H$1),0),$B19-1973)} -> 11.3 | I19: {=INDEX(GMWQ!$A$2:$HN$50,MATCH(1,(GMWQ!$HM$2:$HM$50=I$3)*(GMWQ!$HN$2:$HN$50=I$1),0),$B19-1973)} -> 158854 | J19: {=INDEX(GMWQ!$A$2:$HN$50,MATCH(1,(GMWQ!$HM$2:$HM$50=J$3)*(GMWQ!$HN$2:$HN$50=J$1),0),$B19-1973)} -> 2872.623 | K19: {=INDEX(GMWQ!$A$2:$HN$50,MATCH(1,(GMWQ!$HM$2:$HM$50=K$3)*(GMWQ!$HN$2:$HN$50=K$1),0),$B19-1973)} -> 275877 | L19: {=INDEX(GMWQ!$A$2:$HN$50,MATCH(1,(GMWQ!$HM$2:$HM$50=L$3)*(GMWQ!$HN$2:$HN$50=L$1),0),$B19-1973)} -> 23651 | ... P19: {=INDEX(GMWQ!$A$2:$HN$50,MATCH(1,(GMWQ!$HM$2:$HM$50=P$3)*(GMWQ!$HN$2:$HN$50=P$1),0),$B19-1973)} -> 2872.623
B20: =+B19+1 -> 1993 | C20: =+C16+1 -> 1983 | D20: =+D16+1 -> 1983 | E20: {=INDEX(GMWQ!$A$2:$HN$50,MATCH(1,(GMWQ!$HM$2:$HM$50=E$3)*(GMWQ!$HN$2:$HN$50=E$1),0),$B20-1973)} -> 277790 | F20: {=INDEX(GMWQ!$A$2:$HN$50,MATCH(1,(GMWQ!$HM$2:$HM$50=F$3)*(GMWQ!$HN$2:$HN$50=F$1),0),$B20-1973)} -> 23647 | G20: {=INDEX(GMWQ!$A$2:$HN$50,MATCH(1,(GMWQ!$HM$2:$HM$50=G$3)*(GMWQ!$HN$2:$HN$50=G$1),0),$B20-1973)} -> 1757.346 | H20: {=INDEX(GMWQ!$A$2:$HN$50,MATCH(1,(GMWQ!$HM$2:$HM$50=H$3)*(GMWQ!$HN$2:$HN$50=H$1),0),$B20-1973)} -> 11.4 | I20: {=INDEX(GMWQ!$A$2:$HN$50,MATCH(1,(GMWQ!$HM$2:$HM$50=I$3)*(GMWQ!$HN$2:$HN$50=I$1),0),$B20-1973)} -> 165111 | J20: {=INDEX(GMWQ!$A$2:$HN$50,MATCH(1,(GMWQ!$HM$2:$HM$50=J$3)*(GMWQ!$HN$2:$HN$50=J$1),0),$B20-1973)} -> 2925.466 | K20: {=INDEX(GMWQ!$A$2:$HN$50,MATCH(1,(GMWQ!$HM$2:$HM$50=K$3)*(GMWQ!$HN$2:$HN$50=K$1),0),$B20-1973)} -> 277790 | L20: {=INDEX(GMWQ!$A$2:$HN$50,MATCH(1,(GMWQ!$HM$2:$HM$50=L$3)*(GMWQ!$HN$2:$HN$50=L$1),0),$B20-1973)} -> 23647 | ... P20: {=INDEX(GMWQ!$A$2:$HN$50,MATCH(1,(GMWQ!$HM$2:$HM$50=P$3)*(GMWQ!$HN$2:$HN$50=P$1),0),$B20-1973)} -> 2925.466
B21: =+B20+1 -> 1994 | C21: =+C17+1 -> 1983 | D21: =+D17+1 -> 1983 | E21: {=INDEX(GMWQ!$A$2:$HN$50,MATCH(1,(GMWQ!$HM$2:$HM$50=E$3)*(GMWQ!$HN$2:$HN$50=E$1),0),$B21-1973)} -> 280996 | F21: {=INDEX(GMWQ!$A$2:$HN$50,MATCH(1,(GMWQ!$HM$2:$HM$50=F$3)*(GMWQ!$HN$2:$HN$50=F$1),0),$B21-1973)} -> 23809 | G21: {=INDEX(GMWQ!$A$2:$HN$50,MATCH(1,(GMWQ!$HM$2:$HM$50=G$3)*(GMWQ!$HN$2:$HN$50=G$1),0),$B21-1973)} -> 1777.221 | H21: {=INDEX(GMWQ!$A$2:$HN$50,MATCH(1,(GMWQ!$HM$2:$HM$50=H$3)*(GMWQ!$HN$2:$HN$50=H$1),0),$B21-1973)} -> 11.5 | I21: {=INDEX(GMWQ!$A$2:$HN$50,MATCH(1,(GMWQ!$HM$2:$HM$50=I$3)*(GMWQ!$HN$2:$HN$50=I$1),0),$B21-1973)} -> 163522 | J21: {=INDEX(GMWQ!$A$2:$HN$50,MATCH(1,(GMWQ!$HM$2:$HM$50=J$3)*(GMWQ!$HN$2:$HN$50=J$1),0),$B21-1973)} -> 2987.303 | K21: {=INDEX(GMWQ!$A$2:$HN$50,MATCH(1,(GMWQ!$HM$2:$HM$50=K$3)*(GMWQ!$HN$2:$HN$50=K$1),0),$B21-1973)} -> 280996 | L21: {=INDEX(GMWQ!$A$2:$HN$50,MATCH(1,(GMWQ!$HM$2:$HM$50=L$3)*(GMWQ!$HN$2:$HN$50=L$1),0),$B21-1973)} -> 23809 | ... P21: {=INDEX(GMWQ!$A$2:$HN$50,MATCH(1,(GMWQ!$HM$2:$HM$50=P$3)*(GMWQ!$HN$2:$HN$50=P$1),0),$B21-1973)} -> 2987.303
B22: =+B21+1 -> 1995 | C22: =+C18+1 -> 1983 | D22: =+D18+1 -> 1983 | E22: {=INDEX(GMWQ!$A$2:$HN$50,MATCH(1,(GMWQ!$HM$2:$HM$50=E$3)*(GMWQ!$HN$2:$HN$50=E$1),0),$B22-1973)} -> 283096 | F22: {=INDEX(GMWQ!$A$2:$HN$50,MATCH(1,(GMWQ!$HM$2:$HM$50=F$3)*(GMWQ!$HN$2:$HN$50=F$1),0),$B22-1973)} -> 23994 | G22: {=INDEX(GMWQ!$A$2:$HN$50,MATCH(1,(GMWQ!$HM$2:$HM$50=G$3)*(GMWQ!$HN$2:$HN$50=G$1),0),$B22-1973)} -> 1805.329 | H22: {=INDEX(GMWQ!$A$2:$HN$50,MATCH(1,(GMWQ!$HM$2:$HM$50=H$3)*(GMWQ!$HN$2:$HN$50=H$1),0),$B22-1973)} -> 11.7 | I22: {=INDEX(GMWQ!$A$2:$HN$50,MATCH(1,(GMWQ!$HM$2:$HM$50=I$3)*(GMWQ!$HN$2:$HN$50=I$1),0),$B22-1973)} -> 164202 | J22: {=INDEX(GMWQ!$A$2:$HN$50,MATCH(1,(GMWQ!$HM$2:$HM$50=J$3)*(GMWQ!$HN$2:$HN$50=J$1),0),$B22-1973)} -> 3060.384 | K22: {=INDEX(GMWQ!$A$2:$HN$50,MATCH(1,(GMWQ!$HM$2:$HM$50=K$3)*(GMWQ!$HN$2:$HN$50=K$1),0),$B22-1973)} -> 283096 | L22: {=INDEX(GMWQ!$A$2:$HN$50,MATCH(1,(GMWQ!$HM$2:$HM$50=L$3)*(GMWQ!$HN$2:$HN$50=L$1),0),$B22-1973)} -> 23994 | ... P22: {=INDEX(GMWQ!$A$2:$HN$50,MATCH(1,(GMWQ!$HM$2:$HM$50=P$3)*(GMWQ!$HN$2:$HN$50=P$1),0),$B22-1973)} -> 3060.384
A23: 1984 | B23: =+B22+1 -> 1996 | C23: =+C19+1 -> 1984 | D23: =+D19+1 -> 1983 | E23: {=INDEX(GMWQ!$A$2:$HN$50,MATCH(1,(GMWQ!$HM$2:$HM$50=E$3)*(GMWQ!$HN$2:$HN$50=E$1),0),$B23-1973)} -> 285469 | F23: {=INDEX(GMWQ!$A$2:$HN$50,MATCH(1,(GMWQ!$HM$2:$HM$50=F$3)*(GMWQ!$HN$2:$HN$50=F$1),0),$B23-1973)} -> 24125 | G23: {=INDEX(GMWQ!$A$2:$HN$50,MATCH(1,(GMWQ!$HM$2:$HM$50=G$3)*(GMWQ!$HN$2:$HN$50=G$1),0),$B23-1973)} -> 1833.021 | H23: {=INDEX(GMWQ!$A$2:$HN$50,MATCH(1,(GMWQ!$HM$2:$HM$50=H$3)*(GMWQ!$HN$2:$HN$50=H$1),0),$B23-1973)} -> 11.8 | I23: {=INDEX(GMWQ!$A$2:$HN$50,MATCH(1,(GMWQ!$HM$2:$HM$50=I$3)*(GMWQ!$HN$2:$HN$50=I$1),0),$B23-1973)} -> 167088 | J23: {=INDEX(GMWQ!$A$2:$HN$50,MATCH(1,(GMWQ!$HM$2:$HM$50=J$3)*(GMWQ!$HN$2:$HN$50=J$1),0),$B23-1973)} -> 3088.492 | K23: {=INDEX(GMWQ!$A$2:$HN$50,MATCH(1,(GMWQ!$HM$2:$HM$50=K$3)*(GMWQ!$HN$2:$HN$50=K$1),0),$B23-1973)} -> 285469 | L23: {=INDEX(GMWQ!$A$2:$HN$50,MATCH(1,(GMWQ!$HM$2:$HM$50=L$3)*(GMWQ!$HN$2:$HN$50=L$1),0),$B23-1973)} -> 24125 | ... P23: {=INDEX(GMWQ!$A$2:$HN$50,MATCH(1,(GMWQ!$HM$2:$HM$50=P$3)*(GMWQ!$HN$2:$HN$50=P$1),0),$B23-1973)} -> 3088.492
B24: =+B23+1 -> 1997 | C24: =+C20+1 -> 1984 | D24: =+D20+1 -> 1984 | E24: {=INDEX(GMWQ!$A$2:$HN$50,MATCH(1,(GMWQ!$HM$2:$HM$50=E$3)*(GMWQ!$HN$2:$HN$50=E$1),0),$B24-1973)} -> 282605 | F24: {=INDEX(GMWQ!$A$2:$HN$50,MATCH(1,(GMWQ!$HM$2:$HM$50=F$3)*(GMWQ!$HN$2:$HN$50=F$1),0),$B24-1973)} -> 24245 | G24: {=INDEX(GMWQ!$A$2:$HN$50,MATCH(1,(GMWQ!$HM$2:$HM$50=G$3)*(GMWQ!$HN$2:$HN$50=G$1),0),$B24-1973)} -> 1859.965 | H24: {=INDEX(GMWQ!$A$2:$HN$50,MATCH(1,(GMWQ!$HM$2:$HM$50=H$3)*(GMWQ!$HN$2:$HN$50=H$1),0),$B24-1973)} -> 11.9 | I24: {=INDEX(GMWQ!$A$2:$HN$50,MATCH(1,(GMWQ!$HM$2:$HM$50=I$3)*(GMWQ!$HN$2:$HN$50=I$1),0),$B24-1973)} -> 165111 | J24: {=INDEX(GMWQ!$A$2:$HN$50,MATCH(1,(GMWQ!$HM$2:$HM$50=J$3)*(GMWQ!$HN$2:$HN$50=J$1),0),$B24-1973)} -> 3128.967 | K24: {=INDEX(GMWQ!$A$2:$HN$50,MATCH(1,(GMWQ!$HM$2:$HM$50=K$3)*(GMWQ!$HN$2:$HN$50=K$1),0),$B24-1973)} -> 282605 | L24: {=INDEX(GMWQ!$A$2:$HN$50,MATCH(1,(GMWQ!$HM$2:$HM$50=L$3)*(GMWQ!$HN$2:$HN$50=L$1),0),$B24-1973)} -> 24245 | ... P24: {=INDEX(GMWQ!$A$2:$HN$50,MATCH(1,(GMWQ!$HM$2:$HM$50=P$3)*(GMWQ!$HN$2:$HN$50=P$1),0),$B24-1973)} -> 3128.967
B25: =+B24+1 -> 1998 | C25: =+C21+1 -> 1984 | D25: =+D21+1 -> 1984 | E25: {=INDEX(GMWQ!$A$2:$HN$50,MATCH(1,(GMWQ!$HM$2:$HM$50=E$3)*(GMWQ!$HN$2:$HN$50=E$1),0),$B25-1973)} -> 284676 | F25: {=INDEX(GMWQ!$A$2:$HN$50,MATCH(1,(GMWQ!$HM$2:$HM$50=F$3)*(GMWQ!$HN$2:$HN$50=F$1),0),$B25-1973)} -> 24335 | G25: {=INDEX(GMWQ!$A$2:$HN$50,MATCH(1,(GMWQ!$HM$2:$HM$50=G$3)*(GMWQ!$HN$2:$HN$50=G$1),0),$B25-1973)} -> 1876.902 | H25: {=INDEX(GMWQ!$A$2:$HN$50,MATCH(1,(GMWQ!$HM$2:$HM$50=H$3)*(GMWQ!$HN$2:$HN$50=H$1),0),$B25-1973)} -> 11.7 | I25: {=INDEX(GMWQ!$A$2:$HN$50,MATCH(1,(GMWQ!$HM$2:$HM$50=I$3)*(GMWQ!$HN$2:$HN$50=I$1),0),$B25-1973)} -> 169770 | J25: {=INDEX(GMWQ!$A$2:$HN$50,MATCH(1,(GMWQ!$HM$2:$HM$50=J$3)*(GMWQ!$HN$2:$HN$50=J$1),0),$B25-1973)} -> 3185.183 | K25: {=INDEX(GMWQ!$A$2:$HN$50,MATCH(1,(GMWQ!$HM$2:$HM$50=K$3)*(GMWQ!$HN$2:$HN$50=K$1),0),$B25-1973)} -> 284676 | L25: {=INDEX(GMWQ!$A$2:$HN$50,MATCH(1,(GMWQ!$HM$2:$HM$50=L$3)*(GMWQ!$HN$2:$HN$50=L$1),0),$B25-1973)} -> 24335 | ... P25: {=INDEX(GMWQ!$A$2:$HN$50,MATCH(1,(GMWQ!$HM$2:$HM$50=P$3)*(GMWQ!$HN$2:$HN$50=P$1),0),$B25-1973)} -> 3185.183
B26: =+B25+1 -> 1999 | C26: =+C22+1 -> 1984 | D26: =+D22+1 -> 1984 | E26: {=INDEX(GMWQ!$A$2:$HN$50,MATCH(1,(GMWQ!$HM$2:$HM$50=E$3)*(GMWQ!$HN$2:$HN$50=E$1),0),$B26-1973)} -> 289829 | F26: {=INDEX(GMWQ!$A$2:$HN$50,MATCH(1,(GMWQ!$HM$2:$HM$50=F$3)*(GMWQ!$HN$2:$HN$50=F$1),0),$B26-1973)} -> 24435 | G26: {=INDEX(GMWQ!$A$2:$HN$50,MATCH(1,(GMWQ!$HM$2:$HM$50=G$3)*(GMWQ!$HN$2:$HN$50=G$1),0),$B26-1973)} -> 1935.882 | H26: {=INDEX(GMWQ!$A$2:$HN$50,MATCH(1,(GMWQ!$HM$2:$HM$50=H$3)*(GMWQ!$HN$2:$HN$50=H$1),0),$B26-1973)} -> 11.6 | I26: {=INDEX(GMWQ!$A$2:$HN$50,MATCH(1,(GMWQ!$HM$2:$HM$50=I$3)*(GMWQ!$HN$2:$HN$50=I$1),0),$B26-1973)} -> 173527 | J26: {=INDEX(GMWQ!$A$2:$HN$50,MATCH(1,(GMWQ!$HM$2:$HM$50=J$3)*(GMWQ!$HN$2:$HN$50=J$1),0),$B26-1973)} -> 3267.258 | K26: {=INDEX(GMWQ!$A$2:$HN$50,MATCH(1,(GMWQ!$HM$2:$HM$50=K$3)*(GMWQ!$HN$2:$HN$50=K$1),0),$B26-1973)} -> 289829 | L26: {=INDEX(GMWQ!$A$2:$HN$50,MATCH(1,(GMWQ!$HM$2:$HM$50=L$3)*(GMWQ!$HN$2:$HN$50=L$1),0),$B26-1973)} -> 24435 | ... P26: {=INDEX(GMWQ!$A$2:$HN$50,MATCH(1,(GMWQ!$HM$2:$HM$50=P$3)*(GMWQ!$HN$2:$HN$50=P$1),0),$B26-1973)} -> 3267.258
A27: 1985 | B27: =+B26+1 -> 2000 | C27: =+C23+1 -> 1985 | D27: =+D23+1 -> 1984 | E27: {=INDEX(GMWQ!$A$2:$HN$50,MATCH(1,(GMWQ!$HM$2:$HM$50=E$3)*(GMWQ!$HN$2:$HN$50=E$1),0),$B27-1973)} -> 292612 | F27: {=INDEX(GMWQ!$A$2:$HN$50,MATCH(1,(GMWQ!$HM$2:$HM$50=F$3)*(GMWQ!$HN$2:$HN$50=F$1),0),$B27-1973)} -> 24515 | G27: {=INDEX(GMWQ!$A$2:$HN$50,MATCH(1,(GMWQ!$HM$2:$HM$50=G$3)*(GMWQ!$HN$2:$HN$50=G$1),0),$B27-1973)} -> 1996.246 | H27: {=INDEX(GMWQ!$A$2:$HN$50,MATCH(1,(GMWQ!$HM$2:$HM$50=H$3)*(GMWQ!$HN$2:$HN$50=H$1),0),$B27-1973)} -> 11.5 | I27: {=INDEX(GMWQ!$A$2:$HN$50,MATCH(1,(GMWQ!$HM$2:$HM$50=I$3)*(GMWQ!$HN$2:$HN$50=I$1),0),$B27-1973)} -> 175208 | J27: {=INDEX(GMWQ!$A$2:$HN$50,MATCH(1,(GMWQ!$HM$2:$HM$50=J$3)*(GMWQ!$HN$2:$HN$50=J$1),0),$B27-1973)} -> 3359.452 | K27: {=INDEX(GMWQ!$A$2:$HN$50,MATCH(1,(GMWQ!$HM$2:$HM$50=K$3)*(GMWQ!$HN$2:$HN$50=K$1),0),$B27-1973)} -> 292612 | L27: {=INDEX(GMWQ!$A$2:$HN$50,MATCH(1,(GMWQ!$HM$2:$HM$50=L$3)*(GMWQ!$HN$2:$HN$50=L$1),0),$B27-1973)} -> 24515 | ... P27: {=INDEX(GMWQ!$A$2:$HN$50,MATCH(1,(GMWQ!$HM$2:$HM$50=P$3)*(GMWQ!$HN$2:$HN$50=P$1),0),$B27-1973)} -> 3359.452
B28: =+B27+1 -> 2001 | C28: =+C24+1 -> 1985 | D28: =+D24+1 -> 1985 | E28: {=INDEX(GMWQ!$A$2:$HN$50,MATCH(1,(GMWQ!$HM$2:$HM$50=E$3)*(GMWQ!$HN$2:$HN$50=E$1),0),$B28-1973)} -> 298873 | F28: {=INDEX(GMWQ!$A$2:$HN$50,MATCH(1,(GMWQ!$HM$2:$HM$50=F$3)*(GMWQ!$HN$2:$HN$50=F$1),0),$B28-1973)} -> 24570 | G28: {=INDEX(GMWQ!$A$2:$HN$50,MATCH(1,(GMWQ!$HM$2:$HM$50=G$3)*(GMWQ!$HN$2:$HN$50=G$1),0),$B28-1973)} -> 2015.939 | H28: {=INDEX(GMWQ!$A$2:$HN$50,MATCH(1,(GMWQ!$HM$2:$HM$50=H$3)*(GMWQ!$HN$2:$HN$50=H$1),0),$B28-1973)} -> 11.4 | I28: {=INDEX(GMWQ!$A$2:$HN$50,MATCH(1,(GMWQ!$HM$2:$HM$50=I$3)*(GMWQ!$HN$2:$HN$50=I$1),0),$B28-1973)} -> 175613 | J28: {=INDEX(GMWQ!$A$2:$HN$50,MATCH(1,(GMWQ!$HM$2:$HM$50=J$3)*(GMWQ!$HN$2:$HN$50=J$1),0),$B28-1973)} -> 3403.3 | K28: {=INDEX(GMWQ!$A$2:$HN$50,MATCH(1,(GMWQ!$HM$2:$HM$50=K$3)*(GMWQ!$HN$2:$HN$50=K$1),0),$B28-1973)} -> 298873 | L28: {=INDEX(GMWQ!$A$2:$HN$50,MATCH(1,(GMWQ!$HM$2:$HM$50=L$3)*(GMWQ!$HN$2:$HN$50=L$1),0),$B28-1973)} -> 24570 | ... P28: {=INDEX(GMWQ!$A$2:$HN$50,MATCH(1,(GMWQ!$HM$2:$HM$50=P$3)*(GMWQ!$HN$2:$HN$50=P$1),0),$B28-1973)} -> 3403.3
B29: =+B28+1 -> 2002 | C29: =+C25+1 -> 1985 | D29: =+D25+1 -> 1985 | E29: {=INDEX(GMWQ!$A$2:$HN$50,MATCH(1,(GMWQ!$HM$2:$HM$50=E$3)*(GMWQ!$HN$2:$HN$50=E$1),0),$B29-1973)} -> 298814 | F29: {=INDEX(GMWQ!$A$2:$HN$50,MATCH(1,(GMWQ!$HM$2:$HM$50=F$3)*(GMWQ!$HN$2:$HN$50=F$1),0),$B29-1973)} -> 24625 | G29: {=INDEX(GMWQ!$A$2:$HN$50,MATCH(1,(GMWQ!$HM$2:$HM$50=G$3)*(GMWQ!$HN$2:$HN$50=G$1),0),$B29-1973)} -> 2043.298 | H29: {=INDEX(GMWQ!$A$2:$HN$50,MATCH(1,(GMWQ!$HM$2:$HM$50=H$3)*(GMWQ!$HN$2:$HN$50=H$1),0),$B29-1973)} -> 11.3 | I29: {=INDEX(GMWQ!$A$2:$HN$50,MATCH(1,(GMWQ!$HM$2:$HM$50=I$3)*(GMWQ!$HN$2:$HN$50=I$1),0),$B29-1973)} -> 175957 | J29: {=INDEX(GMWQ!$A$2:$HN$50,MATCH(1,(GMWQ!$HM$2:$HM$50=J$3)*(GMWQ!$HN$2:$HN$50=J$1),0),$B29-1973)} -> 3447.148 | K29: {=INDEX(GMWQ!$A$2:$HN$50,MATCH(1,(GMWQ!$HM$2:$HM$50=K$3)*(GMWQ!$HN$2:$HN$50=K$1),0),$B29-1973)} -> 298814 | L29: {=INDEX(GMWQ!$A$2:$HN$50,MATCH(1,(GMWQ!$HM$2:$HM$50=L$3)*(GMWQ!$HN$2:$HN$50=L$1),0),$B29-1973)} -> 24625 | ... P29: {=INDEX(GMWQ!$A$2:$HN$50,MATCH(1,(GMWQ!$HM$2:$HM$50=P$3)*(GMWQ!$HN$2:$HN$50=P$1),0),$B29-1973)} -> 3447.148
B30: =+B29+1 -> 2003 | C30: =+C26+1 -> 1985 | D30: =+D26+1 -> 1985 | E30: {=INDEX(GMWQ!$A$2:$HN$50,MATCH(1,(GMWQ!$HM$2:$HM$50=E$3)*(GMWQ!$HN$2:$HN$50=E$1),0),$B30-1973)} -> 298979 | F30: {=INDEX(GMWQ!$A$2:$HN$50,MATCH(1,(GMWQ!$HM$2:$HM$50=F$3)*(GMWQ!$HN$2:$HN$50=F$1),0),$B30-1973)} -> 24660 | G30: {=INDEX(GMWQ!$A$2:$HN$50,MATCH(1,(GMWQ!$HM$2:$HM$50=G$3)*(GMWQ!$HN$2:$HN$50=G$1),0),$B30-1973)} -> 2093.281 | H30: {=INDEX(GMWQ!$A$2:$HN$50,MATCH(1,(GMWQ!$HM$2:$HM$50=H$3)*(GMWQ!$HN$2:$HN$50=H$1),0),$B30-1973)} -> 11.3 | I30: {=INDEX(GMWQ!$A$2:$HN$50,MATCH(1,(GMWQ!$HM$2:$HM$50=I$3)*(GMWQ!$HN$2:$HN$50=I$1),0),$B30-1973)} -> 177164 | J30: {=INDEX(GMWQ!$A$2:$HN$50,MATCH(1,(GMWQ!$HM$2:$HM$50=J$3)*(GMWQ!$HN$2:$HN$50=J$1),0),$B30-1973)} -> 3557.331 | K30: {=INDEX(GMWQ!$A$2:$HN$50,MATCH(1,(GMWQ!$HM$2:$HM$50=K$3)*(GMWQ!$HN$2:$HN$50=K$1),0),$B30-1973)} -> 298979 | L30: {=INDEX(GMWQ!$A$2:$HN$50,MATCH(1,(GMWQ!$HM$2:$HM$50=L$3)*(GMWQ!$HN$2:$HN$50=L$1),0),$B30-1973)} -> 24660 | ... P30: {=INDEX(GMWQ!$A$2:$HN$50,MATCH(1,(GMWQ!$HM$2:$HM$50=P$3)*(GMWQ!$HN$2:$HN$50=P$1),0),$B30-1973)} -> 3557.331
A31: 1986 | B31: =+B30+1 -> 2004 | C31: =+C27+1 -> 1986 | D31: =+D27+1 -> 1985 | E31: {=INDEX(GMWQ!$A$2:$HN$50,MATCH(1,(GMWQ!$HM$2:$HM$50=E$3)*(GMWQ!$HN$2:$HN$50=E$1),0),$B31-1973)} -> 302117 | F31: {=INDEX(GMWQ!$A$2:$HN$50,MATCH(1,(GMWQ!$HM$2:$HM$50=F$3)*(GMWQ!$HN$2:$HN$50=F$1),0),$B31-1973)} -> 24670 | G31: {=INDEX(GMWQ!$A$2:$HN$50,MATCH(1,(GMWQ!$HM$2:$HM$50=G$3)*(GMWQ!$HN$2:$HN$50=G$1),0),$B31-1973)} -> 2142.593 | H31: {=INDEX(GMWQ!$A$2:$HN$50,MATCH(1,(GMWQ!$HM$2:$HM$50=H$3)*(GMWQ!$HN$2:$HN$50=H$1),0),$B31-1973)} -> 11.3 | I31: {=INDEX(GMWQ!$A$2:$HN$50,MATCH(1,(GMWQ!$HM$2:$HM$50=I$3)*(GMWQ!$HN$2:$HN$50=I$1),0),$B31-1973)} -> 179729 | J31: {=INDEX(GMWQ!$A$2:$HN$50,MATCH(1,(GMWQ!$HM$2:$HM$50=J$3)*(GMWQ!$HN$2:$HN$50=J$1),0),$B31-1973)} -> 3637.157 | K31: {=INDEX(GMWQ!$A$2:$HN$50,MATCH(1,(GMWQ!$HM$2:$HM$50=K$3)*(GMWQ!$HN$2:$HN$50=K$1),0),$B31-1973)} -> 302117 | L31: {=INDEX(GMWQ!$A$2:$HN$50,MATCH(1,(GMWQ!$HM$2:$HM$50=L$3)*(GMWQ!$HN$2:$HN$50=L$1),0),$B31-1973)} -> 24670 | ... P31: {=INDEX(GMWQ!$A$2:$HN$50,MATCH(1,(GMWQ!$HM$2:$HM$50=P$3)*(GMWQ!$HN$2:$HN$50=P$1),0),$B31-1973)} -> 3637.157
B32: =+B31+1 -> 2005 | C32: =+C28+1 -> 1986 | D32: =+D28+1 -> 1986 | E32: {=INDEX(GMWQ!$A$2:$HN$50,MATCH(1,(GMWQ!$HM$2:$HM$50=E$3)*(GMWQ!$HN$2:$HN$50=E$1),0),$B32-1973)} -> 304797 | F32: {=INDEX(GMWQ!$A$2:$HN$50,MATCH(1,(GMWQ!$HM$2:$HM$50=F$3)*(GMWQ!$HN$2:$HN$50=F$1),0),$B32-1973)} -> 24695 | G32: {=INDEX(GMWQ!$A$2:$HN$50,MATCH(1,(GMWQ!$HM$2:$HM$50=G$3)*(GMWQ!$HN$2:$HN$50=G$1),0),$B32-1973)} -> 2185.823 | H32: {=INDEX(GMWQ!$A$2:$HN$50,MATCH(1,(GMWQ!$HM$2:$HM$50=H$3)*(GMWQ!$HN$2:$HN$50=H$1),0),$B32-1973)} -> 11.3 | I32: {=INDEX(GMWQ!$A$2:$HN$50,MATCH(1,(GMWQ!$HM$2:$HM$50=I$3)*(GMWQ!$HN$2:$HN$50=I$1),0),$B32-1973)} -> 186661 | J32: {=INDEX(GMWQ!$A$2:$HN$50,MATCH(1,(GMWQ!$HM$2:$HM$50=J$3)*(GMWQ!$HN$2:$HN$50=J$1),0),$B32-1973)} -> 3792.313 | K32: {=INDEX(GMWQ!$A$2:$HN$50,MATCH(1,(GMWQ!$HM$2:$HM$50=K$3)*(GMWQ!$HN$2:$HN$50=K$1),0),$B32-1973)} -> 304797 | L32: {=INDEX(GMWQ!$A$2:$HN$50,MATCH(1,(GMWQ!$HM$2:$HM$50=L$3)*(GMWQ!$HN$2:$HN$50=L$1),0),$B32-1973)} -> 24695 | ... P32: {=INDEX(GMWQ!$A$2:$HN$50,MATCH(1,(GMWQ!$HM$2:$HM$50=P$3)*(GMWQ!$HN$2:$HN$50=P$1),0),$B32-1973)} -> 3792.313
B33: =+B32+1 -> 2006 | C33: =+C29+1 -> 1986 | D33: =+D29+1 -> 1986 | E33: {=INDEX(GMWQ!$A$2:$HN$50,MATCH(1,(GMWQ!$HM$2:$HM$50=E$3)*(GMWQ!$HN$2:$HN$50=E$1),0),$B33-1973)} -> 306708 | F33: {=INDEX(GMWQ!$A$2:$HN$50,MATCH(1,(GMWQ!$HM$2:$HM$50=F$3)*(GMWQ!$HN$2:$HN$50=F$1),0),$B33-1973)} -> 24770 | G33: {=INDEX(GMWQ!$A$2:$HN$50,MATCH(1,(GMWQ!$HM$2:$HM$50=G$3)*(GMWQ!$HN$2:$HN$50=G$1),0),$B33-1973)} -> 2220.435 | H33: {=INDEX(GMWQ!$A$2:$HN$50,MATCH(1,(GMWQ!$HM$2:$HM$50=H$3)*(GMWQ!$HN$2:$HN$50=H$1),0),$B33-1973)} -> 11.4 | I33: {=INDEX(GMWQ!$A$2:$HN$50,MATCH(1,(GMWQ!$HM$2:$HM$50=I$3)*(GMWQ!$HN$2:$HN$50=I$1),0),$B33-1973)} -> 183119 | J33: {=INDEX(GMWQ!$A$2:$HN$50,MATCH(1,(GMWQ!$HM$2:$HM$50=J$3)*(GMWQ!$HN$2:$HN$50=J$1),0),$B33-1973)} -> 3863.145 | K33: {=INDEX(GMWQ!$A$2:$HN$50,MATCH(1,(GMWQ!$HM$2:$HM$50=K$3)*(GMWQ!$HN$2:$HN$50=K$1),0),$B33-1973)} -> 306708 | L33: {=INDEX(GMWQ!$A$2:$HN$50,MATCH(1,(GMWQ!$HM$2:$HM$50=L$3)*(GMWQ!$HN$2:$HN$50=L$1),0),$B33-1973)} -> 24770 | ... P33: {=INDEX(GMWQ!$A$2:$HN$50,MATCH(1,(GMWQ!$HM$2:$HM$50=P$3)*(GMWQ!$HN$2:$HN$50=P$1),0),$B33-1973)} -> 3863.145
B34: =+B33+1 -> 2007 | C34: =+C30+1 -> 1986 | D34: =+D30+1 -> 1986 | E34: {=INDEX(GMWQ!$A$2:$HN$50,MATCH(1,(GMWQ!$HM$2:$HM$50=E$3)*(GMWQ!$HN$2:$HN$50=E$1),0),$B34-1973)} -> 312615 | F34: {=INDEX(GMWQ!$A$2:$HN$50,MATCH(1,(GMWQ!$HM$2:$HM$50=F$3)*(GMWQ!$HN$2:$HN$50=F$1),0),$B34-1973)} -> 24850 | G34: {=INDEX(GMWQ!$A$2:$HN$50,MATCH(1,(GMWQ!$HM$2:$HM$50=G$3)*(GMWQ!$HN$2:$HN$50=G$1),0),$B34-1973)} -> 2251.233 | H34: {=INDEX(GMWQ!$A$2:$HN$50,MATCH(1,(GMWQ!$HM$2:$HM$50=H$3)*(GMWQ!$HN$2:$HN$50=H$1),0),$B34-1973)} -> 11.3 | I34: {=INDEX(GMWQ!$A$2:$HN$50,MATCH(1,(GMWQ!$HM$2:$HM$50=I$3)*(GMWQ!$HN$2:$HN$50=I$1),0),$B34-1973)} -> 183388 | J34: {=INDEX(GMWQ!$A$2:$HN$50,MATCH(1,(GMWQ!$HM$2:$HM$50=J$3)*(GMWQ!$HN$2:$HN$50=J$1),0),$B34-1973)} -> 3930.603 | K34: {=INDEX(GMWQ!$A$2:$HN$50,MATCH(1,(GMWQ!$HM$2:$HM$50=K$3)*(GMWQ!$HN$2:$HN$50=K$1),0),$B34-1973)} -> 312615 | L34: {=INDEX(GMWQ!$A$2:$HN$50,MATCH(1,(GMWQ!$HM$2:$HM$50=L$3)*(GMWQ!$HN$2:$HN$50=L$1),0),$B34-1973)} -> 24850 | ... P34: {=INDEX(GMWQ!$A$2:$HN$50,MATCH(1,(GMWQ!$HM$2:$HM$50=P$3)*(GMWQ!$HN$2:$HN$50=P$1),0),$B34-1973)} -> 3930.603
A35: 1987 | B35: =+B34+1 -> 2008 | C35: =+C31+1 -> 1987 | D35: =+D31+1 -> 1986 | E35: {=INDEX(GMWQ!$A$2:$HN$50,MATCH(1,(GMWQ!$HM$2:$HM$50=E$3)*(GMWQ!$HN$2:$HN$50=E$1),0),$B35-1973)} -> 314804 | F35: {=INDEX(GMWQ!$A$2:$HN$50,MATCH(1,(GMWQ!$HM$2:$HM$50=F$3)*(GMWQ!$HN$2:$HN$50=F$1),0),$B35-1973)} -> 24925 | G35: {=INDEX(GMWQ!$A$2:$HN$50,MATCH(1,(GMWQ!$HM$2:$HM$50=G$3)*(GMWQ!$HN$2:$HN$50=G$1),0),$B35-1973)} -> 2282.895 | H35: {=INDEX(GMWQ!$A$2:$HN$50,MATCH(1,(GMWQ!$HM$2:$HM$50=H$3)*(GMWQ!$HN$2:$HN$50=H$1),0),$B35-1973)} -> 11.1 | I35: {=INDEX(GMWQ!$A$2:$HN$50,MATCH(1,(GMWQ!$HM$2:$HM$50=I$3)*(GMWQ!$HN$2:$HN$50=I$1),0),$B35-1973)} -> 180901 | J35: {=INDEX(GMWQ!$A$2:$HN$50,MATCH(1,(GMWQ!$HM$2:$HM$50=J$3)*(GMWQ!$HN$2:$HN$50=J$1),0),$B35-1973)} -> 4305 | K35: {=INDEX(GMWQ!$A$2:$HN$50,MATCH(1,(GMWQ!$HM$2:$HM$50=K$3)*(GMWQ!$HN$2:$HN$50=K$1),0),$B35-1973)} -> 314804 | L35: {=INDEX(GMWQ!$A$2:$HN$50,MATCH(1,(GMWQ!$HM$2:$HM$50=L$3)*(GMWQ!$HN$2:$HN$50=L$1),0),$B35-1973)} -> 24925 | ... P35: {=INDEX(GMWQ!$A$2:$HN$50,MATCH(1,(GMWQ!$HM$2:$HM$50=P$3)*(GMWQ!$HN$2:$HN$50=P$1),0),$B35-1973)} -> 4305
B36: =+B35+1 -> 2009 | C36: =+C32+1 -> 1987 | D36: =+D32+1 -> 1987 | E36: {=INDEX(GMWQ!$A$2:$HN$50,MATCH(1,(GMWQ!$HM$2:$HM$50=E$3)*(GMWQ!$HN$2:$HN$50=E$1),0),$B36-1973)} -> 319478 | F36: {=INDEX(GMWQ!$A$2:$HN$50,MATCH(1,(GMWQ!$HM$2:$HM$50=F$3)*(GMWQ!$HN$2:$HN$50=F$1),0),$B36-1973)} -> 25110 | G36: {=INDEX(GMWQ!$A$2:$HN$50,MATCH(1,(GMWQ!$HM$2:$HM$50=G$3)*(GMWQ!$HN$2:$HN$50=G$1),0),$B36-1973)} -> 2321.792 | H36: {=INDEX(GMWQ!$A$2:$HN$50,MATCH(1,(GMWQ!$HM$2:$HM$50=H$3)*(GMWQ!$HN$2:$HN$50=H$1),0),$B36-1973)} -> 10.7 | I36: {=INDEX(GMWQ!$A$2:$HN$50,MATCH(1,(GMWQ!$HM$2:$HM$50=I$3)*(GMWQ!$HN$2:$HN$50=I$1),0),$B36-1973)} -> 185020 | J36: {=INDEX(GMWQ!$A$2:$HN$50,MATCH(1,(GMWQ!$HM$2:$HM$50=J$3)*(GMWQ!$HN$2:$HN$50=J$1),0),$B36-1973)} -> 4334 | K36: {=INDEX(GMWQ!$A$2:$HN$50,MATCH(1,(GMWQ!$HM$2:$HM$50=K$3)*(GMWQ!$HN$2:$HN$50=K$1),0),$B36-1973)} -> 319478 | L36: {=INDEX(GMWQ!$A$2:$HN$50,MATCH(1,(GMWQ!$HM$2:$HM$50=L$3)*(GMWQ!$HN$2:$HN$50=L$1),0),$B36-1973)} -> 25110 | ... P36: {=INDEX(GMWQ!$A$2:$HN$50,MATCH(1,(GMWQ!$HM$2:$HM$50=P$3)*(GMWQ!$HN$2:$HN$50=P$1),0),$B36-1973)} -> 4334
B37: =+B36+1 -> 2010 | C37: =+C33+1 -> 1987 | D37: =+D33+1 -> 1987 | E37: {=INDEX(GMWQ!$A$2:$HN$50,MATCH(1,(GMWQ!$HM$2:$HM$50=E$3)*(GMWQ!$HN$2:$HN$50=E$1),0),$B37-1973)} -> 327346 | F37: {=INDEX(GMWQ!$A$2:$HN$50,MATCH(1,(GMWQ!$HM$2:$HM$50=F$3)*(GMWQ!$HN$2:$HN$50=F$1),0),$B37-1973)} -> 25345 | G37: {=INDEX(GMWQ!$A$2:$HN$50,MATCH(1,(GMWQ!$HM$2:$HM$50=G$3)*(GMWQ!$HN$2:$HN$50=G$1),0),$B37-1973)} -> 2369.95 | H37: {=INDEX(GMWQ!$A$2:$HN$50,MATCH(1,(GMWQ!$HM$2:$HM$50=H$3)*(GMWQ!$HN$2:$HN$50=H$1),0),$B37-1973)} -> 10.2 | I37: {=INDEX(GMWQ!$A$2:$HN$50,MATCH(1,(GMWQ!$HM$2:$HM$50=I$3)*(GMWQ!$HN$2:$HN$50=I$1),0),$B37-1973)} -> 187551 | J37: {=INDEX(GMWQ!$A$2:$HN$50,MATCH(1,(GMWQ!$HM$2:$HM$50=J$3)*(GMWQ!$HN$2:$HN$50=J$1),0),$B37-1973)} -> 4487 | K37: {=INDEX(GMWQ!$A$2:$HN$50,MATCH(1,(GMWQ!$HM$2:$HM$50=K$3)*(GMWQ!$HN$2:$HN$50=K$1),0),$B37-1973)} -> 327346 | L37: {=INDEX(GMWQ!$A$2:$HN$50,MATCH(1,(GMWQ!$HM$2:$HM$50=L$3)*(GMWQ!$HN$2:$HN$50=L$1),0),$B37-1973)} -> 25345 | ... P37: {=INDEX(GMWQ!$A$2:$HN$50,MATCH(1,(GMWQ!$HM$2:$HM$50=P$3)*(GMWQ!$HN$2:$HN$50=P$1),0),$B37-1973)} -> 4487
B38: =+B37+1 -> 2011 | C38: =+C34+1 -> 1987 | D38: =+D34+1 -> 1987 | E38: {=INDEX(GMWQ!$A$2:$HN$50,MATCH(1,(GMWQ!$HM$2:$HM$50=E$3)*(GMWQ!$HN$2:$HN$50=E$1),0),$B38-1973)} -> 331075 | F38: {=INDEX(GMWQ!$A$2:$HN$50,MATCH(1,(GMWQ!$HM$2:$HM$50=F$3)*(GMWQ!$HN$2:$HN$50=F$1),0),$B38-1973)} -> 25575 | G38: {=INDEX(GMWQ!$A$2:$HN$50,MATCH(1,(GMWQ!$HM$2:$HM$50=G$3)*(GMWQ!$HN$2:$HN$50=G$1),0),$B38-1973)} -> 2418.279 | H38: {=INDEX(GMWQ!$A$2:$HN$50,MATCH(1,(GMWQ!$HM$2:$HM$50=H$3)*(GMWQ!$HN$2:$HN$50=H$1),0),$B38-1973)} -> 9.7 | I38: {=INDEX(GMWQ!$A$2:$HN$50,MATCH(1,(GMWQ!$HM$2:$HM$50=I$3)*(GMWQ!$HN$2:$HN$50=I$1),0),$B38-1973)} -> 188860 | J38: {=INDEX(GMWQ!$A$2:$HN$50,MATCH(1,(GMWQ!$HM$2:$HM$50=J$3)*(GMWQ!$HN$2:$HN$50=J$1),0),$B38-1973)} -> 4632 | K38: {=INDEX(GMWQ!$A$2:$HN$50,MATCH(1,(GMWQ!$HM$2:$HM$50=K$3)*(GMWQ!$HN$2:$HN$50=K$1),0),$B38-1973)} -> 331075 | L38: {=INDEX(GMWQ!$A$2:$HN$50,MATCH(1,(GMWQ!$HM$2:$HM$50=L$3)*(GMWQ!$HN$2:$HN$50=L$1),0),$B38-1973)} -> 25575 | ... P38: {=INDEX(GMWQ!$A$2:$HN$50,MATCH(1,(GMWQ!$HM$2:$HM$50=P$3)*(GMWQ!$HN$2:$HN$50=P$1),0),$B38-1973)} -> 4632
A39: 1988 | B39: =+B38+1 -> 2012 | C39: =+C35+1 -> 1988 | D39: =+D35+1 -> 1987 | E39: {=INDEX(GMWQ!$A$2:$HN$50,MATCH(1,(GMWQ!$HM$2:$HM$50=E$3)*(GMWQ!$HN$2:$HN$50=E$1),0),$B39-1973)} -> 336442 | F39: {=INDEX(GMWQ!$A$2:$HN$50,MATCH(1,(GMWQ!$HM$2:$HM$50=F$3)*(GMWQ!$HN$2:$HN$50=F$1),0),$B39-1973)} -> 25795 | G39: {=INDEX(GMWQ!$A$2:$HN$50,MATCH(1,(GMWQ!$HM$2:$HM$50=G$3)*(GMWQ!$HN$2:$HN$50=G$1),0),$B39-1973)} -> 2470.636 | H39: {=INDEX(GMWQ!$A$2:$HN$50,MATCH(1,(GMWQ!$HM$2:$HM$50=H$3)*(GMWQ!$HN$2:$HN$50=H$1),0),$B39-1973)} -> 9.2 | I39: {=INDEX(GMWQ!$A$2:$HN$50,MATCH(1,(GMWQ!$HM$2:$HM$50=I$3)*(GMWQ!$HN$2:$HN$50=I$1),0),$B39-1973)} -> 191709 | J39: {=INDEX(GMWQ!$A$2:$HN$50,MATCH(1,(GMWQ!$HM$2:$HM$50=J$3)*(GMWQ!$HN$2:$HN$50=J$1),0),$B39-1973)} -> 4640 | K39: {=INDEX(GMWQ!$A$2:$HN$50,MATCH(1,(GMWQ!$HM$2:$HM$50=K$3)*(GMWQ!$HN$2:$HN$50=K$1),0),$B39-1973)} -> 336442 | L39: {=INDEX(GMWQ!$A$2:$HN$50,MATCH(1,(GMWQ!$HM$2:$HM$50=L$3)*(GMWQ!$HN$2:$HN$50=L$1),0),$B39-1973)} -> 25795 | ... P39: {=INDEX(GMWQ!$A$2:$HN$50,MATCH(1,(GMWQ!$HM$2:$HM$50=P$3)*(GMWQ!$HN$2:$HN$50=P$1),0),$B39-1973)} -> 4640
B40: =+B39+1 -> 2013 | C40: =+C36+1 -> 1988 | D40: =+D36+1 -> 1988 | E40: {=INDEX(GMWQ!$A$2:$HN$50,MATCH(1,(GMWQ!$HM$2:$HM$50=E$3)*(GMWQ!$HN$2:$HN$50=E$1),0),$B40-1973)} -> 338186 | F40: {=INDEX(GMWQ!$A$2:$HN$50,MATCH(1,(GMWQ!$HM$2:$HM$50=F$3)*(GMWQ!$HN$2:$HN$50=F$1),0),$B40-1973)} -> 25970 | G40: {=INDEX(GMWQ!$A$2:$HN$50,MATCH(1,(GMWQ!$HM$2:$HM$50=G$3)*(GMWQ!$HN$2:$HN$50=G$1),0),$B40-1973)} -> 2512.313 | H40: {=INDEX(GMWQ!$A$2:$HN$50,MATCH(1,(GMWQ!$HM$2:$HM$50=H$3)*(GMWQ!$HN$2:$HN$50=H$1),0),$B40-1973)} -> 8.7 | I40: {=INDEX(GMWQ!$A$2:$HN$50,MATCH(1,(GMWQ!$HM$2:$HM$50=I$3)*(GMWQ!$HN$2:$HN$50=I$1),0),$B40-1973)} -> 194935 | J40: {=INDEX(GMWQ!$A$2:$HN$50,MATCH(1,(GMWQ!$HM$2:$HM$50=J$3)*(GMWQ!$HN$2:$HN$50=J$1),0),$B40-1973)} -> 4879 | K40: {=INDEX(GMWQ!$A$2:$HN$50,MATCH(1,(GMWQ!$HM$2:$HM$50=K$3)*(GMWQ!$HN$2:$HN$50=K$1),0),$B40-1973)} -> 338186 | L40: {=INDEX(GMWQ!$A$2:$HN$50,MATCH(1,(GMWQ!$HM$2:$HM$50=L$3)*(GMWQ!$HN$2:$HN$50=L$1),0),$B40-1973)} -> 25970 | ... P40: {=INDEX(GMWQ!$A$2:$HN$50,MATCH(1,(GMWQ!$HM$2:$HM$50=P$3)*(GMWQ!$HN$2:$HN$50=P$1),0),$B40-1973)} -> 4879
B41: =+B40+1 -> 2014 | C41: =+C37+1 -> 1988 | D41: =+D37+1 -> 1988 | E41: {=INDEX(GMWQ!$A$2:$HN$50,MATCH(1,(GMWQ!$HM$2:$HM$50=E$3)*(GMWQ!$HN$2:$HN$50=E$1),0),$B41-1973)} -> 342414 | F41: {=INDEX(GMWQ!$A$2:$HN$50,MATCH(1,(GMWQ!$HM$2:$HM$50=F$3)*(GMWQ!$HN$2:$HN$50=F$1),0),$B41-1973)} -> 26160 | G41: {=INDEX(GMWQ!$A$2:$HN$50,MATCH(1,(GMWQ!$HM$2:$HM$50=G$3)*(GMWQ!$HN$2:$HN$50=G$1),0),$B41-1973)} -> 2569.618 | H41: {=INDEX(GMWQ!$A$2:$HN$50,MATCH(1,(GMWQ!$HM$2:$HM$50=H$3)*(GMWQ!$HN$2:$HN$50=H$1),0),$B41-1973)} -> 8.4 | I41: {=INDEX(GMWQ!$A$2:$HN$50,MATCH(1,(GMWQ!$HM$2:$HM$50=I$3)*(GMWQ!$HN$2:$HN$50=I$1),0),$B41-1973)} -> 197179 | J41: {=INDEX(GMWQ!$A$2:$HN$50,MATCH(1,(GMWQ!$HM$2:$HM$50=J$3)*(GMWQ!$HN$2:$HN$50=J$1),0),$B41-1973)} -> 5040 | K41: {=INDEX(GMWQ!$A$2:$HN$50,MATCH(1,(GMWQ!$HM$2:$HM$50=K$3)*(GMWQ!$HN$2:$HN$50=K$1),0),$B41-1973)} -> 342414 | L41: {=INDEX(GMWQ!$A$2:$HN$50,MATCH(1,(GMWQ!$HM$2:$HM$50=L$3)*(GMWQ!$HN$2:$HN$50=L$1),0),$B41-1973)} -> 26160 | ... P41: {=INDEX(GMWQ!$A$2:$HN$50,MATCH(1,(GMWQ!$HM$2:$HM$50=P$3)*(GMWQ!$HN$2:$HN$50=P$1),0),$B41-1973)} -> 5040
B42: =+B41+1 -> 2015 | C42: =+C38+1 -> 1988 | D42: =+D38+1 -> 1988 | E42: {=INDEX(GMWQ!$A$2:$HN$50,MATCH(1,(GMWQ!$HM$2:$HM$50=E$3)*(GMWQ!$HN$2:$HN$50=E$1),0),$B42-1973)} -> 345162 | F42: {=INDEX(GMWQ!$A$2:$HN$50,MATCH(1,(GMWQ!$HM$2:$HM$50=F$3)*(GMWQ!$HN$2:$HN$50=F$1),0),$B42-1973)} -> 26355 | G42: {=INDEX(GMWQ!$A$2:$HN$50,MATCH(1,(GMWQ!$HM$2:$HM$50=G$3)*(GMWQ!$HN$2:$HN$50=G$1),0),$B42-1973)} -> 2641.639 | H42: {=INDEX(GMWQ!$A$2:$HN$50,MATCH(1,(GMWQ!$HM$2:$HM$50=H$3)*(GMWQ!$HN$2:$HN$50=H$1),0),$B42-1973)} -> 8 | I42: {=INDEX(GMWQ!$A$2:$HN$50,MATCH(1,(GMWQ!$HM$2:$HM$50=I$3)*(GMWQ!$HN$2:$HN$50=I$1),0),$B42-1973)} -> 198740 | J42: {=INDEX(GMWQ!$A$2:$HN$50,MATCH(1,(GMWQ!$HM$2:$HM$50=J$3)*(GMWQ!$HN$2:$HN$50=J$1),0),$B42-1973)} -> 5234 | K42: {=INDEX(GMWQ!$A$2:$HN$50,MATCH(1,(GMWQ!$HM$2:$HM$50=K$3)*(GMWQ!$HN$2:$HN$50=K$1),0),$B42-1973)} -> 345162 | L42: {=INDEX(GMWQ!$A$2:$HN$50,MATCH(1,(GMWQ!$HM$2:$HM$50=L$3)*(GMWQ!$HN$2:$HN$50=L$1),0),$B42-1973)} -> 26355 | ... P42: {=INDEX(GMWQ!$A$2:$HN$50,MATCH(1,(GMWQ!$HM$2:$HM$50=P$3)*(GMWQ!$HN$2:$HN$50=P$1),0),$B42-1973)} -> 5234
A43: 1989 | B43: =+B42+1 -> 2016 | C43: =+C39+1 -> 1989 | D43: =+D39+1 -> 1988 | E43: {=INDEX(GMWQ!$A$2:$HN$50,MATCH(1,(GMWQ!$HM$2:$HM$50=E$3)*(GMWQ!$HN$2:$HN$50=E$1),0),$B43-1973)} -> 346836 | F43: {=INDEX(GMWQ!$A$2:$HN$50,MATCH(1,(GMWQ!$HM$2:$HM$50=F$3)*(GMWQ!$HN$2:$HN$50=F$1),0),$B43-1973)} -> 26590 | G43: {=INDEX(GMWQ!$A$2:$HN$50,MATCH(1,(GMWQ!$HM$2:$HM$50=G$3)*(GMWQ!$HN$2:$HN$50=G$1),0),$B43-1973)} -> 2684.494 | H43: {=INDEX(GMWQ!$A$2:$HN$50,MATCH(1,(GMWQ!$HM$2:$HM$50=H$3)*(GMWQ!$HN$2:$HN$50=H$1),0),$B43-1973)} -> 7.6 | I43: {=INDEX(GMWQ!$A$2:$HN$50,MATCH(1,(GMWQ!$HM$2:$HM$50=I$3)*(GMWQ!$HN$2:$HN$50=I$1),0),$B43-1973)} -> 201265 | J43: {=INDEX(GMWQ!$A$2:$HN$50,MATCH(1,(GMWQ!$HM$2:$HM$50=J$3)*(GMWQ!$HN$2:$HN$50=J$1),0),$B43-1973)} -> 5239 | K43: {=INDEX(GMWQ!$A$2:$HN$50,MATCH(1,(GMWQ!$HM$2:$HM$50=K$3)*(GMWQ!$HN$2:$HN$50=K$1),0),$B43-1973)} -> 346836 | L43: {=INDEX(GMWQ!$A$2:$HN$50,MATCH(1,(GMWQ!$HM$2:$HM$50=L$3)*(GMWQ!$HN$2:$HN$50=L$1),0),$B43-1973)} -> 26590 | ... P43: {=INDEX(GMWQ!$A$2:$HN$50,MATCH(1,(GMWQ!$HM$2:$HM$50=P$3)*(GMWQ!$HN$2:$HN$50=P$1),0),$B43-1973)} -> 5239
B44: =+B43+1 -> 2017 | C44: =+C40+1 -> 1989 | D44: =+D40+1 -> 1989 | E44: {=INDEX(GMWQ!$A$2:$HN$50,MATCH(1,(GMWQ!$HM$2:$HM$50=E$3)*(GMWQ!$HN$2:$HN$50=E$1),0),$B44-1973)} -> 348997 | F44: {=INDEX(GMWQ!$A$2:$HN$50,MATCH(1,(GMWQ!$HM$2:$HM$50=F$3)*(GMWQ!$HN$2:$HN$50=F$1),0),$B44-1973)} -> 26730 | G44: {=INDEX(GMWQ!$A$2:$HN$50,MATCH(1,(GMWQ!$HM$2:$HM$50=G$3)*(GMWQ!$HN$2:$HN$50=G$1),0),$B44-1973)} -> 2756.293 | H44: {=INDEX(GMWQ!$A$2:$HN$50,MATCH(1,(GMWQ!$HM$2:$HM$50=H$3)*(GMWQ!$HN$2:$HN$50=H$1),0),$B44-1973)} -> 7.2 | I44: {=INDEX(GMWQ!$A$2:$HN$50,MATCH(1,(GMWQ!$HM$2:$HM$50=I$3)*(GMWQ!$HN$2:$HN$50=I$1),0),$B44-1973)} -> 204179 | J44: {=INDEX(GMWQ!$A$2:$HN$50,MATCH(1,(GMWQ!$HM$2:$HM$50=J$3)*(GMWQ!$HN$2:$HN$50=J$1),0),$B44-1973)} -> 5247 | K44: {=INDEX(GMWQ!$A$2:$HN$50,MATCH(1,(GMWQ!$HM$2:$HM$50=K$3)*(GMWQ!$HN$2:$HN$50=K$1),0),$B44-1973)} -> 348997 | L44: {=INDEX(GMWQ!$A$2:$HN$50,MATCH(1,(GMWQ!$HM$2:$HM$50=L$3)*(GMWQ!$HN$2:$HN$50=L$1),0),$B44-1973)} -> 26730 | ... P44: {=INDEX(GMWQ!$A$2:$HN$50,MATCH(1,(GMWQ!$HM$2:$HM$50=P$3)*(GMWQ!$HN$2:$HN$50=P$1),0),$B44-1973)} -> 5247
B45: =+B44+1 -> 2018 | C45: =+C41+1 -> 1989 | D45: =+D41+1 -> 1989 | E45: {=INDEX(GMWQ!$A$2:$HN$50,MATCH(1,(GMWQ!$HM$2:$HM$50=E$3)*(GMWQ!$HN$2:$HN$50=E$1),0),$B45-1973)} -> 349572 | F45: {=INDEX(GMWQ!$A$2:$HN$50,MATCH(1,(GMWQ!$HM$2:$HM$50=F$3)*(GMWQ!$HN$2:$HN$50=F$1),0),$B45-1973)} -> 26795 | G45: {=INDEX(GMWQ!$A$2:$HN$50,MATCH(1,(GMWQ!$HM$2:$HM$50=G$3)*(GMWQ!$HN$2:$HN$50=G$1),0),$B45-1973)} -> 2816.473 | H45: {=INDEX(GMWQ!$A$2:$HN$50,MATCH(1,(GMWQ!$HM$2:$HM$50=H$3)*(GMWQ!$HN$2:$HN$50=H$1),0),$B45-1973)} -> 7.1 | I45: {=INDEX(GMWQ!$A$2:$HN$50,MATCH(1,(GMWQ!$HM$2:$HM$50=I$3)*(GMWQ!$HN$2:$HN$50=I$1),0),$B45-1973)} -> 209872 | J45: {=INDEX(GMWQ!$A$2:$HN$50,MATCH(1,(GMWQ!$HM$2:$HM$50=J$3)*(GMWQ!$HN$2:$HN$50=J$1),0),$B45-1973)} -> 5405 | K45: {=INDEX(GMWQ!$A$2:$HN$50,MATCH(1,(GMWQ!$HM$2:$HM$50=K$3)*(GMWQ!$HN$2:$HN$50=K$1),0),$B45-1973)} -> 349572 | L45: {=INDEX(GMWQ!$A$2:$HN$50,MATCH(1,(GMWQ!$HM$2:$HM$50=L$3)*(GMWQ!$HN$2:$HN$50=L$1),0),$B45-1973)} -> 26795 | ... P45: {=INDEX(GMWQ!$A$2:$HN$50,MATCH(1,(GMWQ!$HM$2:$HM$50=P$3)*(GMWQ!$HN$2:$HN$50=P$1),0),$B45-1973)} -> 5405
B46: =+B45+1 -> 2019 | C46: =+C42+1 -> 1989 | D46: =+D42+1 -> 1989 | E46: {=INDEX(GMWQ!$A$2:$HN$50,MATCH(1,(GMWQ!$HM$2:$HM$50=E$3)*(GMWQ!$HN$2:$HN$50=E$1),0),$B46-1973)} -> 349523 | F46: {=INDEX(GMWQ!$A$2:$HN$50,MATCH(1,(GMWQ!$HM$2:$HM$50=F$3)*(GMWQ!$HN$2:$HN$50=F$1),0),$B46-1973)} -> 26880 | G46: {=INDEX(GMWQ!$A$2:$HN$50,MATCH(1,(GMWQ!$HM$2:$HM$50=G$3)*(GMWQ!$HN$2:$HN$50=G$1),0),$B46-1973)} -> 2895.669 | H46: {=INDEX(GMWQ!$A$2:$HN$50,MATCH(1,(GMWQ!$HM$2:$HM$50=H$3)*(GMWQ!$HN$2:$HN$50=H$1),0),$B46-1973)} -> 7 | I46: {=INDEX(GMWQ!$A$2:$HN$50,MATCH(1,(GMWQ!$HM$2:$HM$50=I$3)*(GMWQ!$HN$2:$HN$50=I$1),0),$B46-1973)} -> 207949 | J46: {=INDEX(GMWQ!$A$2:$HN$50,MATCH(1,(GMWQ!$HM$2:$HM$50=J$3)*(GMWQ!$HN$2:$HN$50=J$1),0),$B46-1973)} -> 5609 | K46: {=INDEX(GMWQ!$A$2:$HN$50,MATCH(1,(GMWQ!$HM$2:$HM$50=K$3)*(GMWQ!$HN$2:$HN$50=K$1),0),$B46-1973)} -> 349523 | L46: {=INDEX(GMWQ!$A$2:$HN$50,MATCH(1,(GMWQ!$HM$2:$HM$50=L$3)*(GMWQ!$HN$2:$HN$50=L$1),0),$B46-1973)} -> 26880 | ... P46: {=INDEX(GMWQ!$A$2:$HN$50,MATCH(1,(GMWQ!$HM$2:$HM$50=P$3)*(GMWQ!$HN$2:$HN$50=P$1),0),$B46-1973)} -> 5609
A47: 1990 | B47: =+B46+1 -> 2020 | C47: =+C43+1 -> 1990 | D47: =+D43+1 -> 1989 | E47: {=INDEX(GMWQ!$A$2:$HN$50,MATCH(1,(GMWQ!$HM$2:$HM$50=E$3)*(GMWQ!$HN$2:$HN$50=E$1),0),$B47-1973)} -> 351299 | F47: {=INDEX(GMWQ!$A$2:$HN$50,MATCH(1,(GMWQ!$HM$2:$HM$50=F$3)*(GMWQ!$HN$2:$HN$50=F$1),0),$B47-1973)} -> 26900 | G47: {=INDEX(GMWQ!$A$2:$HN$50,MATCH(1,(GMWQ!$HM$2:$HM$50=G$3)*(GMWQ!$HN$2:$HN$50=G$1),0),$B47-1973)} -> 2978.668 | H47: {=INDEX(GMWQ!$A$2:$HN$50,MATCH(1,(GMWQ!$HM$2:$HM$50=H$3)*(GMWQ!$HN$2:$HN$50=H$1),0),$B47-1973)} -> 6.9 | I47: {=INDEX(GMWQ!$A$2:$HN$50,MATCH(1,(GMWQ!$HM$2:$HM$50=I$3)*(GMWQ!$HN$2:$HN$50=I$1),0),$B47-1973)} -> 213872 | J47: {=INDEX(GMWQ!$A$2:$HN$50,MATCH(1,(GMWQ!$HM$2:$HM$50=J$3)*(GMWQ!$HN$2:$HN$50=J$1),0),$B47-1973)} -> 5594 | K47: {=INDEX(GMWQ!$A$2:$HN$50,MATCH(1,(GMWQ!$HM$2:$HM$50=K$3)*(GMWQ!$HN$2:$HN$50=K$1),0),$B47-1973)} -> 351299 | L47: {=INDEX(GMWQ!$A$2:$HN$50,MATCH(1,(GMWQ!$HM$2:$HM$50=L$3)*(GMWQ!$HN$2:$HN$50=L$1),0),$B47-1973)} -> 26900 | ... P47: {=INDEX(GMWQ!$A$2:$HN$50,MATCH(1,(GMWQ!$HM$2:$HM$50=P$3)*(GMWQ!$HN$2:$HN$50=P$1),0),$B47-1973)} -> 5594
B48: =+B47+1 -> 2021 | C48: =+C44+1 -> 1990 | D48: =+D44+1 -> 1990 | E48: {=INDEX(GMWQ!$A$2:$HN$50,MATCH(1,(GMWQ!$HM$2:$HM$50=E$3)*(GMWQ!$HN$2:$HN$50=E$1),0),$B48-1973)} -> 353663 | F48: {=INDEX(GMWQ!$A$2:$HN$50,MATCH(1,(GMWQ!$HM$2:$HM$50=F$3)*(GMWQ!$HN$2:$HN$50=F$1),0),$B48-1973)} -> 26935 | G48: {=INDEX(GMWQ!$A$2:$HN$50,MATCH(1,(GMWQ!$HM$2:$HM$50=G$3)*(GMWQ!$HN$2:$HN$50=G$1),0),$B48-1973)} -> 3042.386 | H48: {=INDEX(GMWQ!$A$2:$HN$50,MATCH(1,(GMWQ!$HM$2:$HM$50=H$3)*(GMWQ!$HN$2:$HN$50=H$1),0),$B48-1973)} -> 6.9 | I48: {=INDEX(GMWQ!$A$2:$HN$50,MATCH(1,(GMWQ!$HM$2:$HM$50=I$3)*(GMWQ!$HN$2:$HN$50=I$1),0),$B48-1973)} -> 211391 | J48: {=INDEX(GMWQ!$A$2:$HN$50,MATCH(1,(GMWQ!$HM$2:$HM$50=J$3)*(GMWQ!$HN$2:$HN$50=J$1),0),$B48-1973)} -> 5782 | K48: {=INDEX(GMWQ!$A$2:$HN$50,MATCH(1,(GMWQ!$HM$2:$HM$50=K$3)*(GMWQ!$HN$2:$HN$50=K$1),0),$B48-1973)} -> 353663 | L48: {=INDEX(GMWQ!$A$2:$HN$50,MATCH(1,(GMWQ!$HM$2:$HM$50=L$3)*(GMWQ!$HN$2:$HN$50=L$1),0),$B48-1973)} -> 26935 | ... P48: {=INDEX(GMWQ!$A$2:$HN$50,MATCH(1,(GMWQ!$HM$2:$HM$50=P$3)*(GMWQ!$HN$2:$HN$50=P$1),0),$B48-1973)} -> 5782
