Workbook
Name _DLX1.INC: HAVERD!$A$1:$AL$6

Sheet Calculations
A1: Interest rates - gilts | E1: Interest rates - market expectations | J1: Interest rates - gilts | N1: Interest rates - short rates
B2: Budget Oct24* | C2: 19th December | F2: Budget Oct24 | G2: 19th December | J2: OBR gilt | K2: Markets gilt | L2: Impact | N2: OBR RCB | O2: Markets RCB | P2: Impact | R2: Total impact
A3: 2 | B3: {=TRANSPOSE(HAVERD!B537:G537)+0.25} -> 4.2390909 | C3: {=TRANSPOSE(HAVERD!B538:G538)} -> 4.46 | E3: 2024 | F3: {=TRANSPOSE(HAVERD!H537:M537)+0.25} -> 3.9658356 | G3: {=TRANSPOSE(HAVERD!H538:M538)} -> 4.1867781 | I3: FY2023/24 | J3: 4.273714 | K3: =J3 -> 4.273714 | L3: ='OBR RR Mar24 - Debt interest'!C10*(K3-J3) -> 0 | N3: 5.029625 | O3: =N3 -> 5.029625 | P3: ='OBR RR Mar24 - Debt interest'!C17*(O3-N3) -> 0
A4: 5 | B4: 4.0472727 | C4: 4.39 | E4: 2025 | F4: 3.6815352 | G4: 4.0234214 | I4: FY2024/25 | J4: 4.0656667 | K4: =J4+0.33 -> 4.3956667 | L4: ='OBR RR Mar24 - Debt interest'!D11*(K4-J4)+'OBR RR Mar24 - Debt interest'!D10*(K3-J3) -> 427.0567 | N4: 4.8745814 | O4: =N4+(G3-F3) -> 5.0955239 | P4: ='OBR RR Mar24 - Debt interest'!D18*(O4-N4)+'OBR RR Mar24 - Debt interest'!D17*(O3-N3) -> 2128.0397 | R4: =P4+L4 -> 2555.0964
A5: 10 | B5: 4.1690909 | C5: 4.61 | E5: 2026 | F5: 3.5758239 | G5: 3.8533846 | I5: FY2025/26 | J5: 4.147109 | K5: =J5+0.33 -> 4.477109 | L5: ='OBR RR Mar24 - Debt interest'!E12*(K5-J5)+'OBR RR Mar24 - Debt interest'!E11*(K4-J4)+'OBR RR Mar24 - Debt interest'!E10*(K3-J3) -> 1218.1135 | N5: 3.9095605 | O5: =N5+(G4-F4) -> 4.2514467 | P5: ='OBR RR Mar24 - Debt interest'!E19*(O5-N5)+'OBR RR Mar24 - Debt interest'!E18*(O4-N4) -> 3016.6719 | R5: =P5+L5 -> 4234.7854
A6: 15 | B6: 4.4490909 | C6: 4.89 | E6: 2027 | F6: 3.5328945 | G6: 3.777909 | I6: FY2026/27 | J6: 4.2265644 | K6: =J6+0.33 -> 4.5565644 | L6: ='OBR RR Mar24 - Debt interest'!F13*(K6-J6)+'OBR RR Mar24 - Debt interest'!F12*(K5-J5)+'OBR RR Mar24 - Debt interest'!F11*(K4-J4)+'OBR RR Mar24 - Debt interest'!F10*(K3-J3) -> 1906.2003 | N6: 3.6534969 | O6: =N6+(G5-F5) -> 3.9310576 | P6: ='OBR RR Mar24 - Debt interest'!F20*(O6-N6)+'OBR RR Mar24 - Debt interest'!F19*(O5-N5) -> 2288.609 | R6: =P6+L6 -> 4194.8093
A7: 20 | B7: 4.6427273 | C7: 5.09 | E7: 2028 | F7: 3.5469719 | G7: 3.7745549 | I7: FY2027/28 | J7: 4.3428788 | K7: =J7+0.33 -> 4.6728788 | L7: ='OBR RR Mar24 - Debt interest'!G14*(K7-J7)+'OBR RR Mar24 - Debt interest'!G13*(K6-J6)+'OBR RR Mar24 - Debt interest'!G12*(K5-J5)+'OBR RR Mar24 - Debt interest'!G11*(K4-J4)+'OBR RR Mar24 - Debt interest'!G10*(K3-J3) -> 2507.7654 | N7: 3.5561777 | O7: =N7+(G6-F6) -> 3.8011922 | P7: ='OBR RR Mar24 - Debt interest'!G21*(O7-N7)+'OBR RR Mar24 - Debt interest'!G20*(O6-N6) -> 1773.1502 | R7: =P7+L7 -> 4280.9156
A8: 30 | B8: 4.6954545 | C8: 5.13 | E8: 2029 | F8: 3.6111095 | G8: 3.82074 | I8: FY2028/29 | J8: 4.4869746 | K8: =J8+0.33 -> 4.8169746 | L8: ='OBR RR Mar24 - Debt interest'!H15*(K8-J8)+'OBR RR Mar24 - Debt interest'!H14*(K7-J7)+'OBR RR Mar24 - Debt interest'!H13*(K6-J6)+'OBR RR Mar24 - Debt interest'!H12*(K5-J5)+'OBR RR Mar24 - Debt interest'!H11*(K4-J4)+'OBR RR Mar24 - Debt interest'!H10*(K3-J3) -> 3164.9509 | N8: 3.5217886 | O8: =N8+(G7-F7) -> 3.7493716 | P8: ='OBR RR Mar24 - Debt interest'!H22*(O8-N8)+'OBR RR Mar24 - Debt interest'!H21*(O7-N7) -> 1474.4852 | R8: =P8+L8 -> 4639.436
I9: FY2029/30 | J9: 4.6177629 | K9: =J9+0.33 -> 4.9477629 | L9: ='OBR RR Mar24 - Debt interest'!I16*(K9-J9)+'OBR RR Mar24 - Debt interest'!I15*(K8-J8)+'OBR RR Mar24 - Debt interest'!I14*(K7-J7)+'OBR RR Mar24 - Debt interest'!I13*(K6-J6)+'OBR RR Mar24 - Debt interest'!I12*(K5-J5)+'OBR RR Mar24 - Debt interest'!I11*(K4-J4)+'OBR RR Mar24 - Debt interest'!I10*(K3-J3) -> 3950.0354 | N9: 3.5448441 | O9: =N9+(G8-F8) -> 3.7544746 | P9: ='OBR RR Mar24 - Debt interest'!I23*(O9-N9)+'OBR RR Mar24 - Debt interest'!I22*(O8-N8) -> 1220.0366 | R9: =P9+L9 -> 5170.072
A10: Av | B10: =AVERAGE(B3:B8) -> 4.3737879 | C10: =AVERAGE(C3:C8) -> 4.7616667 | F10: =AVERAGE(F3:F8) -> 3.6523618 | G10: =AVERAGE(G3:G8) -> 3.9061313
A11: Diff | C11: =C10-B10 -> 0.38787879 | G11: =G10-F10 -> 0.25376958

Sheet HAVERD
A1: 20230101 !D | B1: T112G2@INTDAILY | C1: T112G5@INTDAILY | D1: T112GA@INTDAILY | E1: T112GF@INTDAILY | F1: T112GK@INTDAILY | G1: T112GT@INTDAILY | H1: R11212F@INTDAILY | I1: R11224F@INTDAILY | J1: R11236F@INTDAILY | K1: R11248F@INTDAILY | L1: R11260F@INTDAILY | M1: R112I6A@INTDAILY
A2: .DESC | B2: UK: 2-Yr Government Bond Yield (%) | C2: UK: 5-Yr Government Bond Yield (%) | D2: UK: 10-Yr Government Bond Yield (%) | E2: UK: 15-Yr Government Bond Yield (%) | F2: UK: 20-Yr Government Bond Yield (%) | G2: UK: 30-Yr Government Bond Yield (%) | H2: UK: Overnight Index Swap: Forward Yields, 12-Month (% p.a.) | I2: UK: Overnight Index Swap: Forward Yields, 24-Month (% p.a.) | J2: UK: Overnight Index Swap: Forward Yields, 36-Month (% p.a.) | K2: UK: Overnight Index Swap: Forward Yields, 48-Month (% p.a.) | L2: UK: Overnight Index Swap: Forward Yields, 60-Month (% p.a.) | M2: UK: Overnight Index Swap: Forward Yields, 6-Year (% p.a.)
A3: .T1 | B3: 26-Jan-1994 | C3: 03-Jan-1995 | D3: 26-Jan-1994 | E3: 03-Jan-1995 | F3: 03-Jan-1995 | G3: 03-Jan-1995 | H3: 02-Jan-2009 | I3: 02-Jan-2009 | J3: 02-Jan-2009 | K3: 02-Jan-2009 | L3: 02-Jan-2009 | M3: 02-Jan-2018
A4: .TN | B4: 19-Dec-2024 | C4: 19-Dec-2024 | D4: 19-Dec-2024 | E4: 19-Dec-2024 | F4: 19-Dec-2024 | G4: 19-Dec-2024 | H4: 18-Dec-2024 | I4: 18-Dec-2024 | J4: 18-Dec-2024 | K4: 18-Dec-2024 | L4: 18-Dec-2024 | M4: 18-Dec-2024
A5: .LSOURCE | B5: London Stock Exchange Group | C5: London Stock Exchange Group | D5: London Stock Exchange Group | E5: London Stock Exchange Group | F5: London Stock Exchange Group | G5: London Stock Exchange Group | H5: Bank of England | I5: Bank of England | J5: Bank of England | K5: Bank of England | L5: Bank of England | M5: Bank of England
A6: .DTLM | B6: Dec-19-2024 20:54 | C6: Dec-19-2024 20:54 | D6: Dec-19-2024 20:54 | E6: Dec-19-2024 20:54 | F6: Dec-19-2024 20:54 | G6: Dec-19-2024 20:54 | H6: Dec-19-2024 10:01 | I6: Dec-19-2024 10:01 | J6: Dec-19-2024 10:01 | K6: Dec-19-2024 10:01 | L6: Dec-19-2024 10:01 | M6: Dec-19-2024 10:01
A7: 20230102 | B7: #N/A | C7: #N/A | D7: 3.67 | E7: 4 | F7: #N/A | G7: #N/A | H7: #N/A | I7: #N/A | J7: #N/A | K7: #N/A | L7: #N/A | M7: #N/A
A8: 20230103 | B8: 3.57 | C8: 3.61 | D8: 3.65 | E8: 3.98 | F8: 4.03 | G8: 3.95 | H8: 4.6062333 | I8: 4.0860817 | J8: 3.7383644 | K8: 3.5202418 | L8: 3.3603768 | M8: 3.2670637
A9: 20230104 | B9: 3.44 | C9: 3.49 | D9: 3.5 | E9: 3.86 | F9: 3.91 | G9: 3.83 | H9: 4.4897159 | I9: 3.8946255 | J9: 3.5485094 | K9: 3.3581345 | L9: 3.2157631 | M9: 3.1344241
A10: 20230105 | B10: 3.5 | C10: 3.54 | D10: 3.55 | E10: 3.92 | F10: 3.97 | G10: 3.9 | H10: 4.6093366 | I10: 4.0251201 | J10: 3.6258403 | K10: 3.4044061 | L10: 3.248598 | M10: 3.1579104
A11: 20230106 | B11: 3.41 | C11: 3.44 | D11: 3.47 | E11: 3.87 | F11: 3.92 | G11: 3.87 | H11: 4.5135822 | I11: 3.9067508 | J11: 3.5489763 | K11: 3.3517725 | L11: 3.2136096 | M11: 3.1364836
A12: 20230109 | B12: 3.44 | C12: 3.44 | D12: 3.53 | E12: 3.92 | F12: 3.99 | G12: 3.95 | H12: 4.4073146 | I12: 3.8168853 | J12: 3.4943471 | K12: 3.344989 | L12: 3.2567799 | M12: 3.2227345
A13: 20230110 | B13: 3.46 | C13: 3.46 | D13: 3.56 | E13: 3.9 | F13: 3.97 | G13: 3.9 | H13: 4.4532428 | I13: 3.8421403 | J13: 3.5138982 | K13: 3.3666806 | L13: 3.2777326 | M13: 3.2400696
A14: 20230111 | B14: 3.52 | C14: 3.33 | D14: 3.41 | E14: 3.75 | F14: 3.82 | G14: 3.75 | H14: 4.3232654 | I14: 3.6598018 | J14: 3.2991484 | K14: 3.1085172 | L14: 2.9904796 | M14: 2.9381602
A15: 20230112 | B15: 3.41 | C15: 3.22 | D15: 3.32 | E15: 3.67 | F15: 3.74 | G15: 3.68 | H15: 4.2304327 | I15: 3.5443186 | J15: 3.2434023 | K15: 3.1144553 | L15: 3.0281773 | M15: 2.9867674
A16: 20230113 | B16: 3.48 | C16: 3.3 | D16: 3.37 | E16: 3.71 | F16: 3.79 | G16: 3.73 | H16: 4.2881922 | I16: 3.5435797 | J16: 3.2706631 | K16: 3.1708117 | L16: 3.0875293 | M16: 3.0353738
A17: 20230116 | B17: 3.5 | C17: 3.32 | D17: 3.39 | E17: 3.73 | F17: 3.79 | G17: 3.73 | H17: 4.2747053 | I17: 3.542078 | J17: 3.2860175 | K17: 3.1890704 | L17: 3.1073268 | M17: 3.0597315
A18: 20230117 | B18: 3.46 | C18: 3.28 | D18: 3.33 | E18: 3.67 | F18: 3.73 | G18: 3.67 | H18: 4.2581275 | I18: 3.527278 | J18: 3.2329676 | K18: 3.1110108 | L18: 3.0186675 | M18: 2.9668799
A19: 20230118 | B19: 3.48 | C19: 3.26 | D19: 3.31 | E19: 3.65 | F19: 3.72 | G19: 3.67 | H19: 4.2900137 | I19: 3.5371655 | J19: 3.2330216 | K19: 3.0933058 | L19: 2.9859519 | M19: 2.9234031
... A75: 20230406 | B75: 3.33 | C75: 3.24 | D75: 3.41 | E75: 3.69 | F75: 3.74 | G75: 3.75 | H75: 4.158319 | I75: 3.5211395 | J75: 3.3365395 | K75: 3.1897341 | L75: 3.0491198 | M75: 2.95713
A76: 20230407 | B76: #N/A | C76: #N/A | D76: #N/A | E76: #N/A | F76: #N/A | G76: #N/A | H76: #N/A | I76: #N/A | J76: #N/A | K76: #N/A | L76: #N/A | M76: #N/A
A77: 20230410 | B77: 3.36 | C77: 3.26 | D77: #N/A | E77: 3.72 | F77: #N/A | G77: 3.77 | H77: #N/A | I77: #N/A | J77: #N/A | K77: #N/A | L77: #N/A | M77: #N/A
A78: 20230411 | B78: 3.48 | C78: 3.38 | D78: 3.54 | E78: 3.82 | F78: 3.86 | G78: 3.85 | H78: 4.3065134 | I78: 3.6673912 | J78: 3.4384934 | K78: 3.2872516 | L78: 3.1669498 | M78: 3.0930364
A79: 20230412 | B79: 3.52 | C79: 3.41 | D79: 3.57 | E79: 3.85 | F79: 3.9 | G79: 3.89 | H79: 4.3314896 | I79: 3.6943976 | J79: 3.4697311 | K79: 3.3318164 | L79: 3.2106008 | M79: 3.132033
A80: 20230413 | B80: 3.5 | C80: 3.39 | D80: 3.56 | E80: 3.85 | F80: 3.92 | G80: 3.93 | H80: 4.3058688 | I80: 3.6497702 | J80: 3.4739348 | K80: 3.3542761 | L80: 3.2218246 | M80: 3.133631
A81: 20230414 | B81: 3.6 | C81: 3.49 | D81: 3.65 | E81: 3.93 | F81: 4 | G81: 4.01 | H81: 4.3803025 | I81: 3.7827095 | J81: 3.551481 | K81: 3.3722345 | L81: 3.2280545 | M81: 3.1483612
A82: 20230417 | B82: 3.62 | C82: 3.51 | D82: 3.7 | E82: 3.97 | F82: 4.04 | G82: 4.05 | H82: 4.4128215 | I82: 3.7984261 | J82: 3.5516661 | K82: 3.3793774 | L82: 3.2660484 | M82: 3.2154803
A83: 20230418 | B83: 3.69 | C83: 3.58 | D83: 3.75 | E83: 4.02 | F83: 4.08 | G83: 4.1 | H83: 4.5153119 | I83: 3.8540431 | J83: 3.5681877 | K83: 3.4200533 | L83: 3.3183639 | M83: 3.2650511
A84: 20230419 | B84: 3.82 | C84: 3.71 | D84: 3.85 | E84: 4.12 | F84: 4.17 | G84: 4.18 | H84: 4.7060498 | I84: 4.0208502 | J84: 3.6986267 | K84: 3.5281427 | L84: 3.4031273 | M84: 3.3287484
A85: 20230420 | B85: 3.71 | C85: 3.61 | D85: 3.75 | E85: 4.02 | F85: 4.07 | G85: 4.09 | H85: 4.6234793 | I85: 3.901558 | J85: 3.6169639 | K85: 3.433208 | L85: 3.2895766 | M85: 3.2097178
A86: 20230421 | B86: 3.74 | C86: 3.61 | D86: 3.75 | E86: 4.02 | F86: 4.07 | G86: 4.09 | H86: 4.5902956 | I86: 3.9119531 | J86: 3.6309767 | K86: 3.4424543 | L86: 3.30302 | M86: 3.2276621
A87: 20230424 | B87: 3.81 | C87: 3.66 | D87: 3.78 | E87: 4.06 | F87: 4.11 | G87: 4.12 | H87: 4.6552073 | I87: 3.9766732 | J87: 3.6810599 | K87: 3.4826582 | L87: 3.3436555 | M87: 3.2782026
A88: 20230425 | B88: 3.73 | C88: 3.55 | D88: 3.69 | E88: 3.96 | F88: 4.01 | G88: 4.04 | H88: 4.5693727 | I88: 3.8898784 | J88: 3.5795324 | K88: 3.3871226 | L88: 3.2624867 | M88: 3.2031146
A89: 20230426 | B89: 3.77 | C89: 3.61 | D89: 3.74 | E89: 4.02 | F89: 4.08 | G89: 4.1 | H89: 4.5760281 | I89: 3.8704626 | J89: 3.5882628 | K89: 3.4396677 | L89: 3.3302424 | M89: 3.2688646
... A91: 20230428 | B91: 3.78 | C91: 3.61 | D91: 3.72 | E91: 4 | F91: 4.07 | G91: 4.09 | H91: 4.5760379 | I91: 3.9026073 | J91: 3.6412626 | K91: 3.4556032 | L91: 3.3150557 | M91: 3.2404901
A92: 20230501 | B92: 3.78 | C92: 3.61 | D92: #N/A | E92: 4 | F92: 4.07 | G92: 4.09 | H92: #N/A | I92: #N/A | J92: #N/A | K92: #N/A | L92: #N/A | M92: #N/A
A93: 20230502 | B93: 3.73 | C93: 3.54 | D93: 3.66 | E93: 3.94 | F93: 4.02 | G93: 4.05 | H93: 4.5135792 | I93: 3.859902 | J93: 3.5429317 | K93: 3.3629254 | L93: 3.2533834 | M93: 3.2035777
A94: 20230503 | B94: 3.76 | C94: 3.57 | D94: 3.69 | E94: 3.97 | F94: 4.05 | G94: 4.09 | H94: 4.5638913 | I94: 3.8852997 | J94: 3.5623419 | K94: 3.3931169 | L94: 3.282679 | M94: 3.2256626
A95: 20230504 | B95: 3.68 | C95: 3.48 | D95: 3.66 | E95: 3.93 | F95: 4.03 | G95: 4.08 | H95: 4.3394885 | I95: 3.7166109 | J95: 3.5325496 | K95: 3.399807 | L95: 3.297394 | M95: 3.2467831
A96: 20230505 | B96: 3.77 | C96: 3.58 | D96: 3.77 | E96: 4.04 | F96: 4.13 | G96: 4.17 | H96: 4.5183825 | I96: 3.8892196 | J96: 3.6410288 | K96: 3.4875021 | L96: 3.3792269 | M96: 3.3266601
A97: 20230508 | B97: 3.78 | C97: 3.59 | D97: #N/A | E97: 4.05 | F97: 4.13 | G97: 4.18 | H97: #N/A | I97: #N/A | J97: #N/A | K97: #N/A | L97: #N/A | M97: #N/A
A98: 20230509 | B98: 3.87 | C98: 3.68 | D98: 3.86 | E98: 4.12 | F98: 4.2 | G98: 4.24 | H98: 4.5946064 | I98: 3.9952234 | J98: 3.6955484 | K98: 3.5394297 | L98: 3.4530754 | M98: 3.4208425
A99: 20230510 | B99: 3.83 | C99: 3.63 | D99: 3.8 | E99: 4.07 | F99: 4.15 | G99: 4.19 | H99: 4.522911 | I99: 3.9083299 | J99: 3.6306262 | K99: 3.4949506 | L99: 3.4084393 | M99: 3.3692976
A100: 20230511 | B100: 3.73 | C100: 3.54 | D100: 3.71 | E100: 4 | F100: 4.09 | G100: 4.14 | H100: 4.4338141 | I100: 3.770318 | J100: 3.5397911 | K100: 3.4121447 | L100: 3.3229286 | M100: 3.2851298
A101: 20230512 | B101: 3.8 | C101: 3.6 | D101: 3.78 | E101: 4.08 | F101: 4.17 | G101: 4.21 | H101: 4.5270186 | I101: 3.8812399 | J101: 3.6114849 | K101: 3.4586385 | L101: 3.3624506 | M101: 3.326638
A102: 20230515 | B102: 3.83 | C102: 3.63 | D102: 3.82 | E102: 4.12 | F102: 4.2 | G102: 4.25 | H102: 4.5353364 | I102: 3.9048074 | J102: 3.6110428 | K102: 3.4642354 | L102: 3.3918383 | M102: 3.3734823
A103: 20230516 | B103: 3.8 | C103: 3.6 | D103: 3.8 | E103: 4.11 | F103: 4.2 | G103: 4.25 | H103: 4.5174841 | I103: 3.9128926 | J103: 3.626163 | K103: 3.4685628 | L103: 3.373927 | M103: 3.3432491
A104: 20230517 | B104: 3.87 | C104: 3.68 | D104: 3.84 | E104: 4.14 | F104: 4.22 | G104: 4.27 | H104: 4.5673363 | I104: 3.9473768 | J104: 3.6443283 | K104: 3.5106299 | L104: 3.4332676 | M104: 3.3955167
A105: 20230518 | B105: 3.97 | C105: 3.8 | D105: 3.97 | E105: 4.27 | F105: 4.34 | G105: 4.39 | H105: 4.6497411 | I105: 4.0487714 | J105: 3.7636572 | K105: 3.6119387 | L105: 3.5221426 | M105: 3.4901165
A106: 20230519 | B106: 3.96 | C106: 3.83 | D106: 4.01 | E106: 4.3 | F106: 4.37 | G106: 4.42 | H106: 4.6826153 | I106: 4.124897 | J106: 3.8251438 | K106: 3.6561314 | L106: 3.5560651 | M106: 3.5200303
A107: 20230522 | B107: 4.04 | C107: 3.89 | D107: 4.05 | E107: 4.33 | F107: 4.39 | G107: 4.44 | H107: 4.7735364 | I107: 4.2331399 | J107: 3.8755177 | K107: 3.6706258 | L107: 3.5662862 | M107: 3.5370019
A108: 20230523 | B108: 4.13 | C108: 3.99 | D108: 4.16 | E108: 4.44 | F108: 4.49 | G108: 4.53 | H108: 4.8562105 | I108: 4.312745 | J108: 3.9574776 | K108: 3.7741902 | L108: 3.681057 | M108: 3.6482821
A109: 20230524 | B109: 4.38 | C109: 4.14 | D109: 4.22 | E109: 4.48 | F109: 4.52 | G109: 4.54 | H109: 5.2414672 | I109: 4.5354891 | J109: 4.0321081 | K109: 3.7892328 | L109: 3.6667592 | M109: 3.615916
... A111: 20230526 | B111: 4.48 | C111: 4.27 | D111: 4.33 | E111: 4.58 | F111: 4.62 | G111: 4.64 | H111: 5.4063842 | I111: 4.7099696 | J111: 4.2365226 | K111: 3.9606424 | L111: 3.7931963 | M111: 3.711878
A112: 20230529 | B112: 4.51 | C112: 4.3 | D112: #N/A | E112: 4.61 | F112: 4.65 | G112: #N/A | H112: #N/A | I112: #N/A | J112: #N/A | K112: #N/A | L112: #N/A | M112: #N/A
A113: 20230530 | B113: 4.44 | C113: 4.21 | D113: 4.24 | E113: 4.5 | F113: 4.56 | G113: 4.58 | H113: 5.386483 | I113: 4.6259905 | J113: 4.1694719 | K113: 3.9210042 | L113: 3.7500349 | M113: 3.6494754
A114: 20230531 | B114: 4.32 | C114: 4.1 | D114: 4.18 | E114: 4.44 | F114: 4.48 | G114: 4.51 | H114: 5.2091129 | I114: 4.4849554 | J114: 4.0309973 | K114: 3.7974953 | L114: 3.6610337 | M114: 3.5942776
A115: 20230601 | B115: 4.29 | C115: 4.06 | D115: 4.13 | E115: 4.38 | F115: 4.43 | G115: 4.47 | H115: 5.1909582 | I115: 4.4676735 | J115: 4.0246924 | K115: 3.7582531 | L115: 3.5904925 | M115: 3.5079275
A116: 20230602 | B116: 4.36 | C116: 4.1 | D116: 4.15 | E116: 4.4 | F116: 4.44 | G116: 4.47 | H116: 5.2337044 | I116: 4.5496112 | J116: 4.102978 | K116: 3.7975028 | L116: 3.5939947 | M116: 3.4984059
A117: 20230605 | B117: 4.46 | C117: 4.18 | D117: 4.22 | E117: 4.46 | F117: 4.49 | G117: 4.52 | H117: 5.3102871 | I117: 4.6923403 | J117: 4.1769056 | K117: 3.8429261 | L117: 3.6559775 | M117: 3.5796025
A118: 20230606 | B118: 4.46 | C118: 4.17 | D118: 4.19 | E118: 4.42 | F118: 4.44 | G118: 4.46 | H118: 5.3074166 | I118: 4.6596847 | J118: 4.1289912 | K118: 3.8090042 | L118: 3.6327208 | M118: 3.5528237
A119: 20230607 | B119: 4.58 | C119: 4.26 | D119: 4.26 | E119: 4.49 | F119: 4.5 | G119: 4.5 | H119: 5.4151055 | I119: 4.7245384 | J119: 4.1830673 | K119: 3.8865176 | L119: 3.7136601 | M119: 3.6254428
A120: 20230608 | B120: 4.51 | C120: 4.22 | D120: 4.25 | E120: 4.48 | F120: 4.49 | G120: 4.5 | H120: 5.3251165 | I120: 4.6479397 | J120: 4.1920966 | K120: 3.9131029 | L120: 3.7269789 | M120: 3.6262308
A121: 20230609 | B121: 4.52 | C121: 4.25 | D121: 4.24 | E121: 4.47 | F121: 4.49 | G121: 4.48 | H121: 5.3744137 | I121: 4.7061927 | J121: 4.2026967 | K121: 3.8886844 | L121: 3.6900836 | M121: 3.5866481
A122: 20230612 | B122: 4.64 | C122: 4.34 | D122: 4.34 | E122: 4.56 | F122: 4.58 | G122: 4.57 | H122: 5.465126 | I122: 4.8411835 | J122: 4.2912996 | K122: 3.9517401 | L122: 3.7602025 | M122: 3.6758565
A123: 20230613 | B123: 4.88 | C123: 4.52 | D123: 4.43 | E123: 4.63 | F123: 4.63 | G123: 4.61 | H123: 5.8054703 | I123: 5.16186 | J123: 4.456664 | K123: 4.01743 | L123: 3.7845463 | M123: 3.6721841
A124: 20230614 | B124: 4.8 | C124: 4.45 | D124: 4.37 | E124: 4.57 | F124: 4.57 | G124: 4.54 | H124: 5.690747 | I124: 5.0011995 | J124: 4.3708993 | K124: 4.010145 | L124: 3.7864245 | M124: 3.6553173
... A176: 20230825 | B176: 5.01 | C176: 4.78 | D176: 4.44 | E176: 4.65 | F176: 4.66 | G176: 4.63 | H176: 5.7424679 | I176: 4.9701605 | J176: 4.404561 | K176: 4.100723 | L176: 3.8850771 | M176: 3.7451473
A177: 20230828 | B177: 5.27 | C177: #N/A | D177: 4.44 | E177: 4.66 | F177: 4.67 | G177: #N/A | H177: #N/A | I177: #N/A | J177: #N/A | K177: #N/A | L177: #N/A | M177: #N/A
A178: 20230829 | B178: 5.22 | C178: 4.75 | D178: 4.42 | E178: 4.64 | F178: 4.66 | G178: 4.63 | H178: 5.6076631 | I178: 4.8876677 | J178: 4.3556799 | K178: 4.0488357 | L178: 3.8639216 | M178: 3.761181
A179: 20230830 | B179: 5.22 | C179: 4.74 | D179: 4.43 | E179: 4.65 | F179: 4.68 | G179: 4.66 | H179: 5.6971779 | I179: 4.8856831 | J179: 4.3353607 | K179: 4.0457583 | L179: 3.8633533 | M179: 3.7587484
A180: 20230831 | B180: 5.14 | C180: 4.67 | D180: 4.36 | E180: 4.58 | F180: 4.62 | G180: 4.61 | H180: 5.5942671 | I180: 4.8119057 | J180: 4.2734099 | K180: 3.9754311 | L180: 3.7970395 | M180: 3.700318
A181: 20230901 | B181: 5.14 | C181: 4.68 | D181: 4.4 | E181: 4.63 | F181: 4.68 | G181: 4.67 | H181: 5.527424 | I181: 4.8202685 | J181: 4.3437855 | K181: 4.049326 | L181: 3.8608804 | M181: 3.7588716
A182: 20230904 | B182: 5.2 | C182: 4.74 | D182: 4.47 | E182: 4.71 | F182: 4.76 | G182: 4.76 | H182: 5.5848461 | I182: 4.8827135 | J182: 4.3783592 | K182: 4.0830781 | L182: 3.9015316 | M182: 3.8130837
A183: 20230905 | B183: 5.26 | C183: 4.8 | D183: 4.52 | E183: 4.76 | F183: 4.8 | G183: 4.79 | H183: 5.6458062 | I183: 4.9633351 | J183: 4.4281698 | K183: 4.1204571 | L183: 3.9409172 | M183: 3.8517666
A184: 20230906 | B184: 5.22 | C184: 4.8 | D184: 4.53 | E184: 4.75 | F184: 4.79 | G184: 4.78 | H184: 5.6324828 | I184: 4.959134 | J184: 4.4414787 | K184: 4.1452427 | L184: 3.963342 | M184: 3.867282
A185: 20230907 | B185: 5.14 | C185: 4.72 | D185: 4.46 | E185: 4.69 | F185: 4.73 | G185: 4.71 | H185: 5.5037676 | I185: 4.7982363 | J185: 4.3436628 | K185: 4.0855894 | L185: 3.9198601 | M185: 3.8307259
A186: 20230908 | B186: 5.08 | C186: 4.66 | D186: 4.42 | E186: 4.66 | F186: 4.71 | G186: 4.7 | H186: 5.4251103 | I186: 4.7470501 | J186: 4.3092745 | K186: 4.0524679 | L186: 3.8801825 | M186: 3.7849308
A187: 20230911 | B187: 5.08 | C187: 4.7 | D187: 4.47 | E187: 4.7 | F187: 4.77 | G187: 4.77 | H187: 5.4492229 | I187: 4.7580713 | J187: 4.3209379 | K187: 4.0749049 | L187: 3.912653 | M187: 3.8304524
A188: 20230912 | B188: 5.04 | C188: 4.65 | D188: 4.42 | E188: 4.66 | F188: 4.73 | G188: 4.74 | H188: 5.4300347 | I188: 4.7073601 | J188: 4.2642483 | K188: 4.026397 | L188: 3.8734197 | M188: 3.7934619
A189: 20230913 | B189: 4.97 | C189: 4.55 | D189: 4.34 | E189: 4.58 | F189: 4.64 | G189: 4.65 | H189: 5.3638699 | I189: 4.5642859 | J189: 4.1354954 | K189: 3.9296327 | L189: 3.7966204 | M189: 3.7245694
... A261: 20231222 | B261: 4.03 | C261: 3.46 | D261: 3.51 | E261: 3.86 | F261: 4.02 | G261: 4.07 | H261: 3.830588 | I261: 3.0408284 | J261: 2.8657268 | K261: 2.8184912 | L261: 2.8310146 | M261: 2.9072496
A262: 20231225 | B262: #N/A | C262: #N/A | D262: 3.5 | E262: 3.85 | F262: 4.01 | G262: 4.07 | H262: #N/A | I262: #N/A | J262: #N/A | K262: #N/A | L262: #N/A | M262: #N/A
A263: 20231226 | B263: #N/A | C263: #N/A | D263: #N/A | E263: #N/A | F263: #N/A | G263: #N/A | H263: #N/A | I263: #N/A | J263: #N/A | K263: #N/A | L263: #N/A | M263: #N/A
A264: 20231227 | B264: 3.98 | C264: 3.4 | D264: 3.45 | E264: 3.78 | F264: 3.97 | G264: 4.03 | H264: 3.789652 | I264: 2.9998964 | J264: 2.7642487 | K264: 2.7172193 | L264: 2.755303 | M264: 2.8427078
A265: 20231228 | B265: 4 | C265: 3.45 | D265: 3.5 | E265: 3.87 | F265: 4.05 | G265: 4.13 | H265: 3.7600844 | I265: 3.0043413 | J265: 2.8192727 | K265: 2.7968103 | L265: 2.8361326 | M265: 2.9188305
A266: 20231229 | B266: 3.98 | C266: 3.46 | D266: 3.54 | E266: 3.92 | F266: 4.09 | G266: 4.14 | H266: 3.7439483 | I266: 3.0335243 | J266: 2.8890318 | K266: 2.8459768 | L266: 2.8717767 | M266: 2.9648184
A267: 20240101 | B267: #N/A | C267: 3.46 | D267: #N/A | E267: 3.92 | F267: 4.09 | G267: #N/A | H267: #N/A | I267: #N/A | J267: #N/A | K267: #N/A | L267: #N/A | M267: #N/A
A268: 20240102 | B268: 4.06 | C268: 3.55 | D268: 3.65 | E268: 4.04 | F268: 4.22 | G268: 4.28 | H268: 3.8133507 | I268: 3.122496 | J268: 2.9397965 | K268: 2.9139373 | L268: 2.976615 | M268: 3.0953136
A269: 20240103 | B269: 4.07 | C269: 3.55 | D269: 3.61 | E269: 3.99 | F269: 4.19 | G269: 4.26 | H269: 3.8103909 | I269: 3.0582151 | J269: 2.9010166 | K269: 2.8980372 | L269: 2.9573435 | M269: 3.066086
A270: 20240104 | B270: 4.22 | C270: 3.7 | D270: 3.74 | E270: 4.12 | F270: 4.3 | G270: 4.38 | H270: 3.9458216 | I270: 3.2268182 | J270: 3.0787962 | K270: 3.071935 | L270: 3.1227582 | M270: 3.2155848
A271: 20240105 | B271: 4.24 | C271: 3.78 | D271: 3.81 | E271: 4.17 | F271: 4.35 | G271: 4.42 | H271: 4.0318583 | I271: 3.3301963 | J271: 3.1663868 | K271: 3.1551932 | L271: 3.1965007 | M271: 3.2772656
A272: 20240108 | B272: 4.19 | C272: 3.72 | D272: 3.77 | E272: 4.12 | F272: 4.31 | G272: 4.38 | H272: 3.9915985 | I272: 3.3028128 | J272: 3.1397409 | K272: 3.1224812 | L272: 3.1630678 | M272: 3.2511539
A273: 20240109 | B273: 4.21 | C273: 3.73 | D273: 3.79 | E273: 4.15 | F273: 4.32 | G273: 4.4 | H273: 4.0132622 | I273: 3.3161053 | J273: 3.1342282 | K273: 3.1158539 | L273: 3.1673712 | M273: 3.2636287
A274: 20240110 | B274: 4.22 | C274: 3.75 | D274: 3.82 | E274: 4.18 | F274: 4.34 | G274: 4.42 | H274: 4.0516976 | I274: 3.367845 | J274: 3.1564854 | K274: 3.1247781 | L274: 3.1751377 | M274: 3.2731349
A275: 20240111 | B275: 4.25 | C275: 3.76 | D275: 3.85 | E275: 4.2 | F275: 4.36 | G275: 4.44 | H275: 4.0309256 | I275: 3.3363711 | J275: 3.180615 | K275: 3.1794607 | L275: 3.2379589 | M275: 3.3335096
A276: 20240112 | B276: 4.18 | C276: 3.67 | D276: 3.8 | E276: 4.16 | F276: 4.34 | G276: 4.43 | H276: 3.906338 | I276: 3.2413816 | J276: 3.0985542 | K276: 3.1066479 | L276: 3.1735852 | M276: 3.2788019
A277: 20240115 | B277: 4.16 | C277: 3.68 | D277: 3.8 | E277: 4.18 | F277: 4.36 | G277: 4.46 | H277: 3.882187 | I277: 3.2212368 | J277: 3.0832033 | K277: 3.0955378 | L277: 3.1690068 | M277: 3.2852854
A278: 20240116 | B278: 4.19 | C278: 3.7 | D278: 3.83 | E278: 4.22 | F278: 4.41 | G278: 4.51 | H278: 3.8892679 | I278: 3.2276975 | J278: 3.1136786 | K278: 3.1338846 | L278: 3.2156826 | M278: 3.3398985
A279: 20240117 | B279: 4.38 | C279: 3.91 | D279: 3.98 | E279: 4.37 | F279: 4.54 | G279: 4.64 | H279: 4.1724997 | I279: 3.5121132 | J279: 3.3242844 | K279: 3.3045953 | L279: 3.3656448 | M279: 3.4747675
...

Sheet OBR RR Mar24 - Debt interest
A1: Back to notes
A2: Effect of a 1 per cent increase (unless otherwise stated), £ million | B2: Year | C2: 2023-24 | D2: 2024-25 | E2: 2025-26 | F2: 2026-27 | G2: 2027-28 | H2: 2028-29 | I2: 2029-30
A3: RPI inflation | B3: 2023-24 | C3: 165.75062 | D3: 507.16566 | E3: 462.12229 | F3: 432.62358 | G3: 437.46389 | H3: 469.53112 | I3: =H3*H3/G3 -> 503.94896
B4: 2024-25 | C4: 0 | D4: 6359.6374 | E4: 479.01761 | F4: 448.53541 | G4: 462.63978 | H4: 496.48597 | I4: =H4*H3/G3 -> 532.87967
B5: 2025-26 | C5: 0 | D5: 0 | E5: 6776.7488 | F5: 446.77664 | G5: 461.98824 | H5: 499.44227 | I5: =H5*H4/G4 -> 535.98089
B6: 2026-27 | C6: 0 | D6: 0 | E6: 0 | F6: 6945.2949 | G6: 459.97012 | H6: 496.25533 | I6: =H6*H5/G5 -> 536.48744
B7: 2027-28 | C7: 0 | D7: 0 | E7: 0 | F7: 0 | G7: 7353.3938 | H7: 494.49507 | I7: =H7*H6/G6 -> 533.50381 | J7: =G7*G7/F6 -> 7785.4723
B8: 2028-29 | C8: 0 | D8: 0 | E8: 0 | F8: 0 | G8: 0 | H8: 7462.3303 | I8: =H8*H7/G7 -> 501.82074
B9: 2029-30 | C9: 0 | D9: 0 | E9: 0 | F9: 0 | G9: 0 | H9: 0 | I9: =H8*H8/G7 -> 7572.8806
A10: Gilt rates (long-term interest rates) | B10: 2023-24 | C10: 497.21742 | D10: 2185.167 | E10: 2185.167 | F10: 2185.167 | G10: 2185.167 | H10: 2185.167 | I10: =H10*H10/G10 -> 2185.167
B11: 2024-25 | C11: 0 | D11: 1294.1112 | E11: 2405.2559 | F11: 2405.2559 | G11: 2405.2559 | H11: 2405.2559 | I11: =H11*H10/G10 -> 2405.2559
B12: 2025-26 | C12: 0 | D12: 0 | E12: 1285.9971 | F12: 2377.0677 | G12: 2377.0677 | H12: 2377.0677 | I12: =H12*H11/G11 -> 2377.0677
B13: 2026-27 | C13: 0 | D13: 0 | E13: 0 | F13: 994.04099 | G13: 1876.2518 | H13: 1876.2518 | I13: =H13*H12/G12 -> 1876.2518
B14: 2027-28 | C14: 0 | D14: 0 | E14: 0 | F14: 0 | G14: 940.71373 | H14: 1808.3926 | I14: =H14*H13/G13 -> 1808.3926 | J14: =G14*G14/F13 -> 890.24731
B15: 2028-29 | C15: 0 | D15: 0 | E15: 0 | F15: 0 | G15: 0 | H15: 1123.7921 | I15: =H15*H14/G14 -> 2160.3356
B16: 2029-30 | C16: 0 | D16: 0 | E16: 0 | F16: 0 | G16: 0 | H16: 0 | I16: =H15*H15/G14 -> 1342.5005
A17: Short rates (Bank Rate) | B17: 2023-24 | C17: 9915.0201 | D17: 293.78104 | E17: 0 | F17: 0 | G17: 0 | H17: 0 | I17: 0
B18: 2024-25 | C18: 0 | D18: 9631.6442 | E18: 296.30733 | F18: 0 | G18: 0 | H18: 0 | I18: 0
B19: 2025-26 | C19: 0 | D19: 0 | E19: 8632.1274 | F19: 297.64961 | G19: 0 | H19: 0 | I19: 0
B20: 2026-27 | C20: 0 | D20: 0 | E20: 0 | F20: 7878.804 | G20: 297.98628 | H20: 0 | I20: 0
B21: 2027-28 | C21: 0 | D21: 0 | E21: 0 | F21: 0 | G21: 6899.3496 | H21: 298.00561 | I21: 0 | J21: =G21*G21/F20 -> 6041.6562
B22: 2028-29 | C22: 0 | D22: 0 | E22: 0 | F22: 0 | G22: 0 | H22: 6158.0577 | I22: =H21 -> 298.00561
B23: 2029-30 | C23: 0 | D23: 0 | E23: 0 | F23: 0 | G23: 0 | H23: 0 | I23: =H22*H22/G21 -> 5496.4129
A24: CGNCR (£1 billion change) | B24: 2023-24 | C24: 10.429541 | D24: 45.025105 | E24: 45.773715 | F24: 46.879919 | G24: 47.646399 | H24: 48.294611 | I24: =H24 -> 48.294611
B25: 2024-25 | C25: 0 | D25: 20.890821 | E25: 38.739428 | F25: 39.555129 | G25: 39.903279 | H25: 40.221324 | I25: =H25 -> 40.221324
B26: 2025-26 | C26: 0 | D26: 0 | E26: 18.234566 | F26: 38.987219 | G26: 39.271615 | H26: 39.327021 | I26: =H26 -> 39.327021
B27: 2026-27 | C27: 0 | D27: 0 | E27: 0 | F27: 16.865043 | G27: 40.911925 | H27: 40.965874 | I27: =H27 -> 40.965874
B28: 2027-28 | C28: 0 | D28: 0 | E28: 0 | F28: 0 | G28: 16.341186 | H28: 41.090974 | I28: =H28 -> 41.090974 | J28: =G28*G28/F27 -> 15.8336
B29: 2028-29 | C29: 0 | D29: 0 | E29: 0 | F29: 0 | G29: 0 | H29: 17.366496 | I29: =H28 -> 41.090974
B30: 2029-30 | C30: 0 | D30: 0 | E30: 0 | F30: 0 | G30: 0 | H30: 0 | I30: =H29 -> 17.366496
