Workbook
Name _DLX1.INC: HAVERQ!$C$1:$H$213
Name _DLX2.INC: HAVERW!$A$1:$G$6
Name Annual_Data: OE_FCST!$A$1:$A$2
Name Data: [1]sheet0!$C$2

Sheet Chart Data
A1: Inflation forecast
E2: 2016 | I2: 2017 | M2: 2018 | Q2: 2019 | U2: 2020 | Y2: 2021 | AC2: 2022 | AG2: 2023 | AK2: 2024 | AO2: 2025 | AS2: 2026 | AW2: 2027 | BA2: 2028
A3: BoE - Nov24 | B3: 45597 | C3: CPI inflation (LHS) | E3: =100*((HAVERQ!BA$63/HAVERQ!AW$63)-1) -> 0.33500838 | F3: =100*((HAVERQ!BB$63/HAVERQ!AX$63)-1) -> 0.33311126 | G3: =100*((HAVERQ!BC$63/HAVERQ!AY$63)-1) -> 0.69883527 | H3: =100*((HAVERQ!BD$63/HAVERQ!AZ$63)-1) -> 1.1964108 | I3: =100*((HAVERQ!BE$63/HAVERQ!BA$63)-1) -> 2.1702838 | J3: =100*((HAVERQ!BF$63/HAVERQ!BB$63)-1) -> 2.7556441 | K3: =100*((HAVERQ!BG$63/HAVERQ!BC$63)-1) -> 2.8089888 | L3: =100*((HAVERQ!BH$63/HAVERQ!BD$63)-1) -> 3.0213465 | ... AM3: =100*((HAVERQ!CI$63/HAVERQ!CE$63)-1) -> 2.0547945 | AN3: =HAVERQ!CJ93 -> 2.4 | AO3: =HAVERQ!CK93 -> 2.4 | AP3: =HAVERQ!CL93 -> 2.6 | AQ3: =HAVERQ!CM93 -> 2.8 | AR3: =HAVERQ!CN93 -> 2.7 | AS3: =HAVERQ!CO93 -> 2.6 | AT3: =HAVERQ!CP93 -> 2.4 | AU3: =HAVERQ!CQ93 -> 2.3 | ... AZ3: =HAVERQ!CV93 -> 1.8
A4: BoE - Feb25 | B4: 45689 | C4: CPI inflation (LHS) | E4: =100*((HAVERQ!BA$63/HAVERQ!AW$63)-1) -> 0.33500838 | F4: =100*((HAVERQ!BB$63/HAVERQ!AX$63)-1) -> 0.33311126 | G4: =100*((HAVERQ!BC$63/HAVERQ!AY$63)-1) -> 0.69883527 | H4: =100*((HAVERQ!BD$63/HAVERQ!AZ$63)-1) -> 1.1964108 | I4: =100*((HAVERQ!BE$63/HAVERQ!BA$63)-1) -> 2.1702838 | J4: =100*((HAVERQ!BF$63/HAVERQ!BB$63)-1) -> 2.7556441 | K4: =100*((HAVERQ!BG$63/HAVERQ!BC$63)-1) -> 2.8089888 | L4: =100*((HAVERQ!BH$63/HAVERQ!BD$63)-1) -> 3.0213465 | ... AN4: =100*((HAVERQ!CJ$63/HAVERQ!CF$63)-1) -> 2.4753726 | AO4: =HAVERQ!CK94 -> 2.8 | AP4: =HAVERQ!CL94 -> 3.5 | AQ4: =HAVERQ!CM94 -> 3.7 | AR4: =HAVERQ!CN94 -> 3.5 | AS4: =HAVERQ!CO94 -> 3 | AT4: =HAVERQ!CP94 -> 2.6 | AU4: =HAVERQ!CQ94 -> 2.6 | AV4: =HAVERQ!CR94 -> 2.4 | ... BA4: =HAVERQ!CW94 -> 1.9
A5: ZERO LINE | B5: ZERO LINE | C5: =A5 -> ZERO LINE | E5: 0 | F5: 0 | G5: 0 | H5: 0 | I5: 0 | J5: 0 | K5: 0 | L5: 0 | M5: 0 | N5: 0 | O5: 0 | P5: 0 | Q5: 0 | R5: 0 | S5: 0 | T5: 0 | U5: 0 | V5: 0 | W5: 0 | X5: 0 | Y5: 0 | Z5: 0 | AA5: 0 | AB5: 0 | AC5: 0 | AD5: 0 | AE5: 0 | AF5: 0 | AG5: 0 | AH5: 0 | AI5: 0 | AJ5: 0 | AK5: 0 | AL5: 0 | AM5: 0 | AN5: 0 | AO5: 0 | AP5: 0 | AQ5: 0 | AR5: 0 | AS5: 0 | AT5: 0 | AU5: 0 | AV5: 0 | AW5: 0 | AX5: 0 | AY5: 0 | AZ5: 0 | BA5: 0
A6: 2% LINE | B6: 2% LINE | C6: =A6 -> 2% LINE | E6: 2 | F6: 2 | G6: 2 | H6: 2 | I6: 2 | J6: 2 | K6: 2 | L6: 2 | M6: 2 | N6: 2 | O6: 2 | P6: 2 | Q6: 2 | R6: 2 | S6: 2 | T6: 2 | U6: 2 | V6: 2 | W6: 2 | X6: 2 | Y6: 2 | Z6: 2 | AA6: 2 | AB6: 2 | AC6: 2 | AD6: 2 | AE6: 2 | AF6: 2 | AG6: 2 | AH6: 2 | AI6: 2 | AJ6: 2 | AK6: 2 | AL6: 2 | AM6: 2 | AN6: 2 | AO6: 2 | AP6: 2 | AQ6: 2 | AR6: 2 | AS6: 2 | AT6: 2 | AU6: 2 | AV6: 2 | AW6: 2 | AX6: 2 | AY6: 2 | AZ6: 2 | BA6: 2
A7: Oxford Economics | C7: =A7 -> Oxford Economics | AM7: =100*((OE_FCST!HE3/OE_FCST!HA3)-1) -> 2.0547945 | AN7: =100*((OE_FCST!HF3/OE_FCST!HB3)-1) -> 2.4753214 | AO7: =100*((OE_FCST!HG3/OE_FCST!HC3)-1) -> 2.7272927 | AP7: =100*((OE_FCST!HH3/OE_FCST!HD3)-1) -> 2.9570369 | AQ7: =100*((OE_FCST!HI3/OE_FCST!HE3)-1) -> 3.4639821 | AR7: =100*((OE_FCST!HJ3/OE_FCST!HF3)-1) -> 3.3718766 | AS7: =100*((OE_FCST!HK3/OE_FCST!HG3)-1) -> 3.105745 | AT7: =100*((OE_FCST!HL3/OE_FCST!HH3)-1) -> 2.5992301 | ... BA7: =100*((OE_FCST!HS3/OE_FCST!HO3)-1) -> 2.1187229
A8: Historical | E8: =100*((HAVERQ!BA$63/HAVERQ!AW$63)-1) -> 0.33500838 | F8: =100*((HAVERQ!BB$63/HAVERQ!AX$63)-1) -> 0.33311126 | G8: =100*((HAVERQ!BC$63/HAVERQ!AY$63)-1) -> 0.69883527 | H8: =100*((HAVERQ!BD$63/HAVERQ!AZ$63)-1) -> 1.1964108 | I8: =100*((HAVERQ!BE$63/HAVERQ!BA$63)-1) -> 2.1702838 | J8: =100*((HAVERQ!BF$63/HAVERQ!BB$63)-1) -> 2.7556441 | K8: =100*((HAVERQ!BG$63/HAVERQ!BC$63)-1) -> 2.8089888 | L8: =100*((HAVERQ!BH$63/HAVERQ!BD$63)-1) -> 3.0213465 | ... AB8: =100*((HAVERQ!BX$63/HAVERQ!BT$63)-1) -> 4.8899756
C9: Excess supply/excess demand (RHS) | AK9: 0.75 | AO9: 0 | AS9: -0.25 | AW9: -0.25 | BA9: -0.5
D10: Market interest rate expectations | E10: =E4 -> 0.33500838 | F10: =F4 -> 0.33311126 | G10: =G4 -> 0.69883527 | H10: =H4 -> 1.1964108 | I10: =I4 -> 2.1702838 | J10: =J4 -> 2.7556441 | K10: =K4 -> 2.8089888 | L10: =L4 -> 3.0213465 | ... BA10: =BA4 -> 1.9
D11: Constant interest rates | E11: =E10 -> 0.33500838 | F11: =F10 -> 0.33311126 | G11: =G10 -> 0.69883527 | H11: =H10 -> 1.1964108 | I11: =I10 -> 2.1702838 | J11: =J10 -> 2.7556441 | K11: =K10 -> 2.8089888 | L11: =L10 -> 3.0213465 | ... AM11: =AM10 -> 2.0547945 | AN11: =HAVERQ!CJ159 -> #N/A | AO11: =HAVERQ!CK159 -> 2.8 | AP11: =HAVERQ!CL159 -> 3.4 | AQ11: =HAVERQ!CM159 -> 3.5 | AR11: =HAVERQ!CN159 -> 3.2 | AS11: =HAVERQ!CO159 -> 2.7 | AT11: =HAVERQ!CP159 -> 2.3 | AU11: =HAVERQ!CQ159 -> 2.3 | ... BA11: =HAVERQ!CW159 -> 1.7
D12: Modal forecast | E12: =E10 -> 0.33500838 | F12: =F10 -> 0.33311126 | G12: =G10 -> 0.69883527 | H12: =H10 -> 1.1964108 | I12: =I10 -> 2.1702838 | J12: =J10 -> 2.7556441 | K12: =K10 -> 2.8089888 | L12: =L10 -> 3.0213465 | ... BA12: =BA10 -> 1.9
D13: Mean forecast | E13: =E11 -> 0.33500838 | F13: =F11 -> 0.33311126 | G13: =G11 -> 0.69883527 | H13: =H11 -> 1.1964108 | I13: =I11 -> 2.1702838 | J13: =J11 -> 2.7556441 | K13: =K11 -> 2.8089888 | L13: =L11 -> 3.0213465 | ... AM13: =AM11 -> 2.0547945 | AN13: =HAVERQ!CJ160 -> #N/A | AO13: =HAVERQ!CK160 -> 2.8 | AP13: =HAVERQ!CL160 -> 3.5 | AQ13: =HAVERQ!CM160 -> 3.7 | AR13: =HAVERQ!CN160 -> 3.5 | AS13: =HAVERQ!CO160 -> 3 | AT13: =HAVERQ!CP160 -> 2.6 | AU13: =HAVERQ!CQ160 -> 2.6 | ... BA13: =HAVERQ!CW160 -> 1.9
A15: ILO unemployment forecast
E16: 2016 | I16: 2017 | M16: 2018 | Q16: 2019 | U16: 2020 | Y16: 2021 | AC16: 2022 | AG16: 2023 | AK16: 2024 | AO16: 2025 | AS16: 2026 | AW16: 2027 | BA16: 2028
A17: BoE - Nov24 | B17: 45597 | E17: =HAVERQ!BA$95 -> 5.1 | F17: =HAVERQ!BB$95 -> 4.9 | G17: =HAVERQ!BC$95 -> 4.8 | H17: =HAVERQ!BD$95 -> 4.7 | I17: =HAVERQ!BE$95 -> 4.6 | J17: =HAVERQ!BF$95 -> 4.4 | K17: =HAVERQ!BG$95 -> 4.3 | L17: =HAVERQ!BH$95 -> 4.4 | ... AL17: =HAVERQ!CH$95 -> 4.2 | AM17: =HAVERQ!CI125 -> 4.2 | AN17: =HAVERQ!CJ125 -> 4.2 | AO17: =HAVERQ!CK125 -> 4.1 | AP17: =HAVERQ!CL125 -> 4.1 | AQ17: =HAVERQ!CM125 -> 4.1 | AR17: =HAVERQ!CN125 -> 4.1 | AS17: =HAVERQ!CO125 -> 4.2 | AT17: =HAVERQ!CP125 -> 4.2 | ... AZ17: =HAVERQ!CV125 -> 4.4
A18: BoE - Feb25 | B18: 45689 | E18: =HAVERQ!BA$95 -> 5.1 | F18: =HAVERQ!BB$95 -> 4.9 | G18: =HAVERQ!BC$95 -> 4.8 | H18: =HAVERQ!BD$95 -> 4.7 | I18: =HAVERQ!BE$95 -> 4.6 | J18: =HAVERQ!BF$95 -> 4.4 | K18: =HAVERQ!BG$95 -> 4.3 | L18: =HAVERQ!BH$95 -> 4.4 | ... AM18: =HAVERQ!CI$95 -> 4.3 | AN18: =HAVERQ!CJ126 -> 4.4 | AO18: =HAVERQ!CK126 -> 4.5 | AP18: =HAVERQ!CL126 -> 4.5 | AQ18: =HAVERQ!CM126 -> 4.5 | AR18: =HAVERQ!CN126 -> 4.5 | AS18: =HAVERQ!CO126 -> 4.5 | AT18: =HAVERQ!CP126 -> 4.6 | AU18: =HAVERQ!CQ126 -> 4.6 | ... BA18: =HAVERQ!CW126 -> 4.8
B19: Equilibrium | E19: 4.5 | F19: 4.5 | G19: 4.5 | H19: 4.5 | I19: 4.5 | J19: 4.5 | K19: 4.5 | L19: 4.5 | M19: 4.25 | N19: 4.25 | O19: 4.25 | P19: 4.25 | Q19: 4.25 | R19: 4.25 | S19: 4.25 | T19: 4.25 | U19: 4.25 | V19: 4.25 | W19: 4.25 | X19: 4.25 | Y19: 4.25 | Z19: 4.25 | AA19: 4.25 | AB19: 4.25 | AC19: 4.25 | AD19: 4.25 | AE19: 4.25 | AF19: 4.25 | AG19: 4.25 | AH19: 4.25 | AI19: 4.25 | AJ19: 4.5 | AK19: 4.5 | AL19: 4.5 | AM19: 4.5 | AN19: 4.5 | AO19: 4.5 | AP19: 4.5 | AQ19: 4.5 | AR19: 4.5 | AS19: 4.5 | AT19: 4.5 | AU19: 4.5 | AV19: 4.5 | AW19: 4.5 | AX19: 4.5 | AY19: 4.5 | AZ19: 4.5 | BA19: 4.5
A20: Oxford Economics | AL20: =OE_FCST!HD4 -> 4.2 | AM20: =OE_FCST!HE4 -> 4.3 | AN20: =OE_FCST!HF4 -> 4.408384 | AO20: =OE_FCST!HG4 -> 4.492019 | AP20: =OE_FCST!HH4 -> 4.502507 | AQ20: =OE_FCST!HI4 -> 4.512015 | AR20: =OE_FCST!HJ4 -> 4.502531 | AS20: =OE_FCST!HK4 -> 4.483452 | ... BA20: =OE_FCST!HS4 -> 4.201129
A22: Market conditioning path for interest rates
E23: 42370 | F23: 42461 | G23: 42552 | H23: 42644 | I23: 42736 | J23: 42826 | K23: 42917 | L23: 43009 | M23: 43101 | N23: 43191 | O23: 43282 | P23: 43374 | Q23: 43466 | R23: 43556 | S23: 43647 | T23: 43739 | U23: 43831 | V23: 43922 | W23: 44013 | X23: 44105 | Y23: 44197 | Z23: 44287 | AA23: 44378 | AB23: 44470 | AC23: 44562 | AD23: 44652 | AE23: 44743 | AF23: 44835 | AG23: 44927 | AH23: 45017 | AI23: 45108 | AJ23: 45200 | AK23: 45292 | AL23: 45383 | AM23: 45474 | AN23: 45566 | AO23: 45658 | AP23: 45748 | AQ23: 45839 | AR23: 45931 | AS23: 46023 | AT23: 46113 | AU23: 46204 | AV23: 46296 | AW23: 46388 | AX23: 46478 | AY23: 46569 | AZ23: 46661 | BA23: 46753 | BB23: 46844
A24: Bank Rate | B24: Bank Rate | E24: =HAVERQ!BA$127 -> 0.5 | F24: =HAVERQ!BB$127 -> 0.5 | G24: =HAVERQ!BC$127 -> 0.25 | H24: =HAVERQ!BD$127 -> 0.25 | I24: =HAVERQ!BE$127 -> 0.25 | J24: =HAVERQ!BF$127 -> 0.25 | K24: =HAVERQ!BG$127 -> 0.25 | L24: =HAVERQ!BH$127 -> 0.5 | ... AN24: =HAVERQ!CJ$127 -> 4.75
A25: Market expectations (MPR Nov24) | B25: 45597 | AN25: =HAVERQ!CJ157 -> 4.78 | AO25: =HAVERQ!CK157 -> 4.39 | AP25: =HAVERQ!CL157 -> 4.03 | AQ25: =HAVERQ!CM157 -> 3.81 | AR25: =HAVERQ!CN157 -> 3.72 | AS25: =HAVERQ!CO157 -> 3.69 | AT25: =HAVERQ!CP157 -> 3.68 | AU25: =HAVERQ!CQ157 -> 3.67 | ... BA25: =HAVERQ!CW157 -> 3.6
A26: Market expectations (MPR Feb25) | B26: 45689 | AO26: =HAVERQ!CK158 -> 4.55 | AP26: =HAVERQ!CL158 -> 4.37 | AQ26: =HAVERQ!CM158 -> 4.23 | AR26: =HAVERQ!CN158 -> 4.16 | AS26: =HAVERQ!CO158 -> 4.15 | AT26: =HAVERQ!CP158 -> 4.15 | AU26: =HAVERQ!CQ158 -> 4.13 | AV26: =HAVERQ!CR158 -> 4.11 | ... BB26: =HAVERQ!CX158 -> 3.98
A27: Oxford Economics | AN27: =OE_FCST!HF5 -> 4.75 | AO27: =OE_FCST!HG5 -> 4.5 | AP27: =OE_FCST!HH5 -> 4.25 | AQ27: =OE_FCST!HI5 -> 4 | AR27: =OE_FCST!HJ5 -> 3.75 | AS27: =OE_FCST!HK5 -> 3.5 | AT27: =OE_FCST!HL5 -> 3.25 | AU27: =OE_FCST!HM5 -> 3.25 | ... BB27: =OE_FCST!HT5 -> 2.5
A28: ZERO LINE | B28: ZERO LINE | E28: 0 | F28: 0 | G28: 0 | H28: 0 | I28: 0 | J28: 0 | K28: 0 | L28: 0 | M28: 0 | N28: 0 | O28: 0 | P28: 0 | Q28: 0 | R28: 0 | S28: 0 | T28: 0 | U28: 0 | V28: 0 | W28: 0 | X28: 0 | Y28: 0 | Z28: 0 | AA28: 0 | AB28: 0 | AC28: 0 | AD28: 0 | AE28: 0 | AF28: 0 | AG28: 0 | AH28: 0 | AI28: 0 | AJ28: 0 | AK28: 0 | AL28: 0 | AM28: 0 | AN28: 0 | AO28: 0 | AP28: 0 | AQ28: 0 | AR28: 0 | AS28: 0 | AT28: 0 | AU28: 0 | AV28: 0 | AW28: 0 | AX28: 0 | AY28: 0 | AZ28: 0 | BA28: 0 | BB28: 0
A30: Diff - Nov-24 to Feb-25 | AN30: =+AN26-AN25 -> -4.78 | AO30: =+AO26-AO25 -> 0.16 | AP30: =+AP26-AP25 -> 0.34 | AQ30: =+AQ26-AQ25 -> 0.42 | AR30: =+AR26-AR25 -> 0.44 | AS30: =+AS26-AS25 -> 0.46 | AT30: =+AT26-AT25 -> 0.47 | AU30: =+AU26-AU25 -> 0.46 | ... BA30: =+BA26-BA25 -> 0.39
A31: Change in Bank Rate compared with today | AO31: =AO26-4.7 -> -0.15 | AP31: =AP26-4.7 -> -0.33 | AQ31: =AQ26-4.7 -> -0.47 | AR31: =AR26-4.7 -> -0.54 | AS31: =AS26-4.7 -> -0.55 | AT31: =AT26-4.7 -> -0.55 | AU31: =AU26-4.7 -> -0.57 | AV31: =AV26-4.7 -> -0.59 | ... BB31: =BB26-4.7 -> -0.72
A33: Forecasts for UK GDP growth
B34: 2023 | C34: 2024 | D34: 2025 | E34: 2026
A35: BoE* (Feb) | B35: 0.5 | C35: 0.75 | D35: 0.65 | E35: 1.5
A36: BoE* (Nov) | B36: 0.25 | C36: 1 | D36: 1.5 | E36: 1.25
A38: OE (Feb) | B38: 0.4 | C38: 0.75 | D38: 1.01 | E38: 1.558
A39: HMT consensus (Jan) | B39: 0.3 | C39: 0.8 | D39: 1.2 | E39: 1.5
A40: OBR (Oct) | B40: 0.1 | C40: 1.1 | D40: 2 | E40: 1.8
A43: NOT BEING USED>>>>
A44: GDP forecast
E45: 2016 | I45: 2017 | M45: 2018 | Q45: 2019 | U45: 2020 | Y45: 2021 | AC45: 2022 | AG45: 2023 | AK45: 2024
A46: BoE - Nov19 | B46: 43770 | E46: =HAVERQ!BA12 -> 2.07 | F46: =HAVERQ!BB12 -> 1.89 | G46: =HAVERQ!BC12 -> 1.91 | H46: =HAVERQ!BD12 -> 1.81 | I46: =HAVERQ!BE12 -> 2.24 | J46: =HAVERQ!BF12 -> 2.06 | K46: =HAVERQ!BG12 -> 2.01 | L46: =HAVERQ!BH12 -> 1.78 | ... R46: =HAVERQ!BN12 -> 1.35 | S46: 1.13 | T46: =HAVERQ!BP42 -> 0.99 | U46: =HAVERQ!BQ42 -> 0.66 | V46: =HAVERQ!BR42 -> 1.3 | W46: =HAVERQ!BS42 -> 1.34 | X46: =HAVERQ!BT42 -> 1.55 | Y46: =HAVERQ!BU42 -> 1.72 | Z46: =HAVERQ!BV42 -> 1.76 | AA46: =HAVERQ!BW42 -> 1.79 | ... AF46: =HAVERQ!CB42 -> 2.06
A47: BoE - Jan20 | B47: 43831 | E47: =HAVERQ!BA13 -> 2.07 | F47: =HAVERQ!BB13 -> 1.89 | G47: =HAVERQ!BC13 -> 1.91 | H47: =HAVERQ!BD13 -> 1.81 | I47: =HAVERQ!BE13 -> 2.23 | J47: =HAVERQ!BF13 -> 2.05 | K47: =HAVERQ!BG13 -> 2 | L47: =HAVERQ!BH13 -> 1.77 | ... S47: =HAVERQ!BO13 -> 1.11 | T47: 0.99 | U47: =HAVERQ!BQ43 -> 0.37 | V47: =HAVERQ!BR43 -> 0.83 | W47: =HAVERQ!BS43 -> 0.76 | X47: =HAVERQ!BT43 -> 1.21 | Y47: =HAVERQ!BU43 -> 1.37 | Z47: =HAVERQ!BV43 -> 1.45 | AA47: =HAVERQ!BW43 -> 1.48 | AB47: =HAVERQ!BX43 -> 1.46 | ... AG47: =HAVERQ!CC43 -> 1.95
A48: BoE -May20 | B48: 43952 | E48: =HAVERQ!BA18 -> 2 | F48: =HAVERQ!BB18 -> 1.71 | G48: =HAVERQ!BC18 -> 1.62 | H48: =HAVERQ!BD18 -> 1.56 | I48: =HAVERQ!BE18 -> 1.86 | J48: =HAVERQ!BF18 -> 1.7 | K48: =HAVERQ!BG18 -> 1.82 | L48: =HAVERQ!BH18 -> 1.58 | ... T48: =HAVERQ!BP18 -> 1.42 | U48: 0.37 | V48: =HAVERQ!BR48 -> #N/A | W48: =HAVERQ!BS48 -> #N/A | X48: =HAVERQ!BT48 -> #N/A | Y48: =HAVERQ!BU48 -> #N/A | Z48: =HAVERQ!BV48 -> 22.38 | AA48: =HAVERQ!BW48 -> 7.7 | AB48: =HAVERQ!BX48 -> 8.47 | AC48: =HAVERQ!BY48 -> 11.43 | ... AH48: =HAVERQ!CD48 -> 1.53
B49: Trend growth | E49: 1.6 | F49: 1.6 | G49: 1.6 | H49: 1.6 | I49: 1.6 | J49: 1.6 | K49: 1.6 | L49: 1.6 | M49: 1.6 | N49: 1.6 | O49: 1.6 | P49: 1.6 | Q49: 1.1 | R49: 1.1 | S49: 1.1 | T49: 1.1 | U49: 1.1 | V49: 1.1 | W49: 1.1 | X49: 1.1 | Y49: 1.1 | Z49: 1.1 | AA49: 1.1 | AB49: 1.1 | AC49: 1.1 | AD49: 1.1 | AE49: 1.1 | AF49: 1.1 | AG49: 1.1 | AH49: 1.1
A50: Oxford Economics | E50: =100*((OE_FCST!FW2/OE_FCST!FS2)-1) -> 1.9256786 | F50: =100*((OE_FCST!FX2/OE_FCST!FT2)-1) -> 1.8701772 | G50: =100*((OE_FCST!FY2/OE_FCST!FU2)-1) -> 1.9170685 | H50: =100*((OE_FCST!FZ2/OE_FCST!FV2)-1) -> 1.9734702 | I50: =100*((OE_FCST!GA2/OE_FCST!FW2)-1) -> 2.4672907 | J50: =100*((OE_FCST!GB2/OE_FCST!FX2)-1) -> 2.535727 | K50: =100*((OE_FCST!GC2/OE_FCST!FY2)-1) -> 2.748969 | L50: =100*((OE_FCST!GD2/OE_FCST!FZ2)-1) -> 2.8703459 | ... AH50: =100*((OE_FCST!GZ2/OE_FCST!GV2)-1) -> 0.57155711
A51: ZERO LINE | B51: ZERO LINE | E51: 0 | F51: 0 | G51: 0 | H51: 0 | I51: 0 | J51: 0 | K51: 0 | L51: 0 | M51: 0 | N51: 0 | O51: 0 | P51: 0 | Q51: 0 | R51: 0 | S51: 0 | T51: 0 | U51: 0 | V51: 0 | W51: 0 | X51: 0 | Y51: 0 | Z51: 0 | AA51: 0 | AB51: 0 | AC51: 0 | AD51: 0 | AE51: 0 | AF51: 0 | AG51: 0 | AH51: 0

Sheet HAVERQ
C1: 20051 !Q | D1: .DESC | E1: .T1 | F1: .TN | G1: .SOURCE | H1: .DTLM | I1: 20051 | J1: 20052 | K1: 20053 | L1: 20054 | M1: 20061 | N1: 20062 | O1: 20063 | P1: 20064 | Q1: 20071 | R1: 20072 | S1: 20073 | T1: 20074 | U1: 20081 | V1: 20082 | W1: 20083 | X1: 20084 | Y1: 20091 | Z1: 20092 | AA1: 20093 | AB1: 20094 | AC1: 20101 | AD1: 20102 | AE1: 20103 | AF1: 20104 | AG1: 20111 | AH1: 20112 | AI1: 20113 | AJ1: 20114 | AK1: 20121 | AL1: 20122 | AM1: 20123 | AN1: 20124 | AO1: 20131 | AP1: 20132 | AQ1: 20133 | AR1: 20134 | AS1: 20141 | AT1: 20142 | AU1: 20143 | AV1: 20144 | AW1: 20151 | AX1: 20152 | AY1: 20153 | AZ1: 20154 | BA1: 20161 | BB1: 20162 | BC1: 20163 | BD1: 20164 | BE1: 20171 | BF1: 20172 | BG1: 20173 | BH1: 20174 | BI1: 20181 | BJ1: 20182 | BK1: 20183 | BL1: 20184 | BM1: 20191 | BN1: 20192 | BO1: 20193 | BP1: 20194 | BQ1: 20201 | BR1: 20202 | BS1: 20203 | BT1: 20204 | BU1: 20211 | BV1: 20212 | BW1: 20213 | BX1: 20214 | BY1: 20221 | BZ1: 20222 | CA1: 20223 | CB1: 20224 | CC1: 20231 | CD1: 20232 | CE1: 20233 | CF1: 20234 | CG1: 20241 | CH1: 20242 | CI1: 20243 | CJ1: 20244 | CK1: 20251 | CL1: 20252 | CM1: 20253 | CN1: 20254 | CO1: 20261 | CP1: 20262 | CQ1: 20263 | CR1: 20264 | CS1: 20271 | CT1: 20272 | CU1: 20273 | CV1: 20274 | CW1: 20281 | CX1: 20282
A2: GDP backcast | B2: 42856 | C2: UNGB172@UK | D2: UK: BoE MPC Backcasts of GDP Growth: [May 2017] Real GDP (SA, Y/Y % Change) | E2: Q3-2009 | F2: Q1-2017 | G2: DISC | H2: May-11-2017 13:50 | I2: #N/A | J2: #N/A | K2: #N/A | L2: #N/A | M2: #N/A | N2: #N/A | O2: #N/A | P2: #N/A | Q2: #N/A | R2: #N/A | S2: #N/A | T2: #N/A | U2: #N/A | V2: #N/A | W2: #N/A | X2: #N/A | Y2: #N/A | Z2: #N/A | AA2: -4.01 | AB2: -1.39 | AC2: 0.8 | AD2: 2.05 | AE2: 2.55 | AF2: 2.26 | AG2: 2.26 | AH2: 1.3 | AI2: 1.17 | AJ2: 1.31 | AK2: 1.19 | AL2: 1.04 | AM2: 1.75 | AN2: 1.27 | AO2: 1.46 | AP2: 2.07 | AQ2: 1.69 | AR2: 2.42 | AS2: 2.69 | AT2: 3.12 | AU2: 3.23 | AV2: 3.53 | AW2: 3.04 | AX2: 2.58 | AY2: 2.12 | AZ2: 1.94 | BA2: 1.85 | BB2: 1.92 | BC2: 2.06 | BD2: 2.12 | BE2: 2.21
B3: 42948 | C3: UNGB173@UK | D3: UK: BoE MPC Backcasts of GDP Growth: [Aug 2017] Real GDP (SA, Y/Y % Change) | E3: Q4-2009 | F3: Q2-2017 | G3: DISC | H3: Aug-03-2017 15:19 | I3: #N/A | J3: #N/A | K3: #N/A | L3: #N/A | M3: #N/A | N3: #N/A | O3: #N/A | P3: #N/A | Q3: #N/A | R3: #N/A | S3: #N/A | T3: #N/A | U3: #N/A | V3: #N/A | W3: #N/A | X3: #N/A | Y3: #N/A | Z3: #N/A | AA3: #N/A | AB3: -1.39 | AC3: 0.8 | AD3: 2.05 | AE3: 2.55 | AF3: 2.26 | AG3: 2.26 | AH3: 1.3 | AI3: 1.17 | AJ3: 1.31 | AK3: 1.19 | AL3: 1.04 | AM3: 1.75 | AN3: 1.27 | AO3: 1.46 | AP3: 2.07 | AQ3: 1.69 | AR3: 2.42 | AS3: 2.69 | AT3: 3.12 | AU3: 3.22 | AV3: 3.53 | AW3: 3.03 | AX3: 2.57 | AY3: 2.11 | AZ3: 1.93 | BA3: 1.85 | BB3: 1.92 | BC3: 2.05 | BD3: 2.05 | BE3: 2.07 | BF3: 1.82
B4: 43040 | C4: UNGB174@UK | D4: UK: BoE MPC Backcasts of GDP Growth: [Nov 2017] Real GDP (SA, Y/Y % Change) | E4: Q1-2010 | F4: Q3-2017 | G4: DISC | H4: Nov-02-2017 14:14 | I4: #N/A | J4: #N/A | K4: #N/A | L4: #N/A | M4: #N/A | N4: #N/A | O4: #N/A | P4: #N/A | Q4: #N/A | R4: #N/A | S4: #N/A | T4: #N/A | U4: #N/A | V4: #N/A | W4: #N/A | X4: #N/A | Y4: #N/A | Z4: #N/A | AA4: #N/A | AB4: #N/A | AC4: 0.74 | AD4: 1.87 | AE4: 2.19 | AF4: 1.99 | AG4: 2.04 | AH4: 1.28 | AI4: 1.19 | AJ4: 1.31 | AK4: 1.37 | AL4: 1.11 | AM4: 1.89 | AN4: 1.55 | AO4: 1.54 | AP4: 2.2 | AQ4: 1.89 | AR4: 2.57 | AS4: 2.8 | AT4: 3.12 | AU4: 3.03 | AV4: 3.27 | AW4: 2.89 | AX4: 2.62 | AY4: 2.38 | AZ4: 2.26 | BA4: 2.09 | BB4: 1.99 | BC4: 1.91 | BD4: 1.8 | BE4: 1.84 | BF4: 1.65 | BG4: 1.6
B5: 43132 | C5: UNGB181@UK | D5: UK: BoE MPC Backcasts of GDP Growth: [February 2018] Real GDP (SA, Y/Y % Change) | E5: Q2-2010 | F5: Q4-2017 | G5: DISC | H5: Feb-08-2018 15:38 | I5: #N/A | J5: #N/A | K5: #N/A | L5: #N/A | M5: #N/A | N5: #N/A | O5: #N/A | P5: #N/A | Q5: #N/A | R5: #N/A | S5: #N/A | T5: #N/A | U5: #N/A | V5: #N/A | W5: #N/A | X5: #N/A | Y5: #N/A | Z5: #N/A | AA5: #N/A | AB5: #N/A | AC5: #N/A | AD5: 1.87 | AE5: 2.19 | AF5: 1.99 | AG5: 2.04 | AH5: 1.28 | AI5: 1.19 | AJ5: 1.31 | AK5: 1.37 | AL5: 1.11 | AM5: 1.89 | AN5: 1.55 | AO5: 1.54 | AP5: 2.2 | AQ5: 1.89 | AR5: 2.57 | AS5: 2.8 | AT5: 3.12 | AU5: 3.03 | AV5: 3.27 | AW5: 2.89 | AX5: 2.62 | AY5: 2.37 | AZ5: 2.26 | BA5: 2.14 | BB5: 2.03 | BC5: 2.08 | BD5: 2.11 | BE5: 2.17 | BF5: 1.99 | BG5: 1.8 | BH5: 1.62
B6: 43221 | C6: UNGB182@UK | D6: UK: BoE MPC Backcasts of GDP Growth: [May 2018] Real GDP (SA, Y/Y % Change) | E6: Q3-2010 | F6: Q1-2018 | G6: DISC | H6: May-10-2018 13:09 | I6: #N/A | J6: #N/A | K6: #N/A | L6: #N/A | M6: #N/A | N6: #N/A | O6: #N/A | P6: #N/A | Q6: #N/A | R6: #N/A | S6: #N/A | T6: #N/A | U6: #N/A | V6: #N/A | W6: #N/A | X6: #N/A | Y6: #N/A | Z6: #N/A | AA6: #N/A | AB6: #N/A | AC6: #N/A | AD6: #N/A | AE6: 2.19 | AF6: 1.99 | AG6: 2.04 | AH6: 1.28 | AI6: 1.19 | AJ6: 1.31 | AK6: 1.37 | AL6: 1.11 | AM6: 1.89 | AN6: 1.55 | AO6: 1.54 | AP6: 2.2 | AQ6: 1.89 | AR6: 2.57 | AS6: 2.8 | AT6: 3.12 | AU6: 3.03 | AV6: 3.27 | AW6: 2.89 | AX6: 2.61 | AY6: 2.36 | AZ6: 2.25 | BA6: 2.13 | BB6: 2.02 | BC6: 2.08 | BD6: 2.11 | BE6: 2.17 | BF6: 2.05 | BG6: 1.97 | BH6: 1.73 | BI6: 1.62
B7: 43313 | C7: UNGB183@UK | D7: UK: BoE MPC Backcasts of GDP Growth: [Aug 2018] Real GDP (SA, Y/Y % Change) | E7: Q4-2010 | F7: Q1-2018 | G7: DISC | H7: Aug-02-2018 15:07 | I7: #N/A | J7: #N/A | K7: #N/A | L7: #N/A | M7: #N/A | N7: #N/A | O7: #N/A | P7: #N/A | Q7: #N/A | R7: #N/A | S7: #N/A | T7: #N/A | U7: #N/A | V7: #N/A | W7: #N/A | X7: #N/A | Y7: #N/A | Z7: #N/A | AA7: #N/A | AB7: #N/A | AC7: #N/A | AD7: #N/A | AE7: #N/A | AF7: 2.03 | AG7: 2.34 | AH7: 1.61 | AI7: 1.3 | AJ7: 1.34 | AK7: 1.24 | AL7: 1.03 | AM7: 1.96 | AN7: 1.56 | AO7: 1.56 | AP7: 2.17 | AQ7: 1.87 | AR7: 2.58 | AS7: 2.78 | AT7: 3.07 | AU7: 2.87 | AV7: 3.07 | AW7: 2.77 | AX7: 2.53 | AY7: 2.34 | AZ7: 2.36 | BA7: 2.21 | BB7: 1.85 | BC7: 1.82 | BD7: 1.83 | BE7: 1.89 | BF7: 1.97 | BG7: 1.88 | BH7: 1.57 | BI7: 1.43
B8: 43405 | C8: UNGB184@UK | D8: UK: BoE MPC Backcasts of GDP Growth: [Nov 2018] Real GDP (SA, Y/Y % Change) | E8: Q1-2011 | F8: Q2-2018 | G8: DISC | H8: Nov-01-2018 14:59 | I8: #N/A | J8: #N/A | K8: #N/A | L8: #N/A | M8: #N/A | N8: #N/A | O8: #N/A | P8: #N/A | Q8: #N/A | R8: #N/A | S8: #N/A | T8: #N/A | U8: #N/A | V8: #N/A | W8: #N/A | X8: #N/A | Y8: #N/A | Z8: #N/A | AA8: #N/A | AB8: #N/A | AC8: #N/A | AD8: #N/A | AE8: #N/A | AF8: #N/A | AG8: 2.34 | AH8: 1.61 | AI8: 1.3 | AJ8: 1.34 | AK8: 1.24 | AL8: 1.03 | AM8: 1.96 | AN8: 1.56 | AO8: 1.56 | AP8: 2.17 | AQ8: 1.87 | AR8: 2.58 | AS8: 2.78 | AT8: 3.07 | AU8: 2.87 | AV8: 3.07 | AW8: 2.76 | AX8: 2.52 | AY8: 2.32 | AZ8: 2.35 | BA8: 2.2 | BB8: 1.83 | BC8: 1.81 | BD8: 1.82 | BE8: 1.93 | BF8: 2.04 | BG8: 1.94 | BH8: 1.62 | BI8: 1.43 | BJ8: 1.53
B9: 43497 | C9: UNGB191@UK | D9: UK: BoE MPC Backcasts of GDP Growth [Feb-19]: Real GDP(SA, Y/Y % Change) | E9: Q2-2011 | F9: Q3-2018 | G9: DISC | H9: Feb-07-2019 12:39 | I9: #N/A | J9: #N/A | K9: #N/A | L9: #N/A | M9: #N/A | N9: #N/A | O9: #N/A | P9: #N/A | Q9: #N/A | R9: #N/A | S9: #N/A | T9: #N/A | U9: #N/A | V9: #N/A | W9: #N/A | X9: #N/A | Y9: #N/A | Z9: #N/A | AA9: #N/A | AB9: #N/A | AC9: #N/A | AD9: #N/A | AE9: #N/A | AF9: #N/A | AG9: #N/A | AH9: 1.61 | AI9: 1.3 | AJ9: 1.34 | AK9: 1.24 | AL9: 1.03 | AM9: 1.96 | AN9: 1.56 | AO9: 1.56 | AP9: 2.17 | AQ9: 1.87 | AR9: 2.58 | AS9: 2.78 | AT9: 3.07 | AU9: 2.87 | AV9: 3.07 | AW9: 2.76 | AX9: 2.52 | AY9: 2.32 | AZ9: 2.36 | BA9: 2.2 | BB9: 1.83 | BC9: 1.81 | BD9: 1.82 | BE9: 1.91 | BF9: 2.04 | BG9: 2.08 | BH9: 1.79 | BI9: 1.61 | BJ9: 1.72 | BK9: 1.81
B10: 43586 | C10: UNGB192@UK | D10: UK: BoE MPC Backcasts of GDP Growth: Real GDP [May 2019] (SA, Y/Y % Change) | E10: Q3-2011 | F10: Q4-2018 | G10: DISC | H10: May-02-2019 12:20 | I10: #N/A | J10: #N/A | K10: #N/A | L10: #N/A | M10: #N/A | N10: #N/A | O10: #N/A | P10: #N/A | Q10: #N/A | R10: #N/A | S10: #N/A | T10: #N/A | U10: #N/A | V10: #N/A | W10: #N/A | X10: #N/A | Y10: #N/A | Z10: #N/A | AA10: #N/A | AB10: #N/A | AC10: #N/A | AD10: #N/A | AE10: #N/A | AF10: #N/A | AG10: #N/A | AH10: #N/A | AI10: 1.3 | AJ10: 1.34 | AK10: 1.24 | AL10: 1.03 | AM10: 1.96 | AN10: 1.56 | AO10: 1.56 | AP10: 2.17 | AQ10: 1.87 | AR10: 2.58 | AS10: 2.78 | AT10: 3.07 | AU10: 2.87 | AV10: 3.07 | AW10: 2.75 | AX10: 2.51 | AY10: 2.31 | AZ10: 2.35 | BA10: 2.2 | BB10: 1.83 | BC10: 1.82 | BD10: 1.83 | BE10: 1.92 | BF10: 2.05 | BG10: 2.08 | BH10: 1.79 | BI10: 1.62 | BJ10: 1.72 | BK10: 1.82 | BL10: 1.7
B11: 43678 | C11: UNGB193@UK | D11: UK: BoE MPC Backcasts of GDP Growth: Real GDP [Aug 19] (SA, Y/Y % Change) | E11: Q4-2011 | F11: Q1-2019 | G11: DISC | H11: Aug-01-2019 12:24 | I11: #N/A | J11: #N/A | K11: #N/A | L11: #N/A | M11: #N/A | N11: #N/A | O11: #N/A | P11: #N/A | Q11: #N/A | R11: #N/A | S11: #N/A | T11: #N/A | U11: #N/A | V11: #N/A | W11: #N/A | X11: #N/A | Y11: #N/A | Z11: #N/A | AA11: #N/A | AB11: #N/A | AC11: #N/A | AD11: #N/A | AE11: #N/A | AF11: #N/A | AG11: #N/A | AH11: #N/A | AI11: #N/A | AJ11: 1.34 | AK11: 1.24 | AL11: 1.03 | AM11: 1.96 | AN11: 1.56 | AO11: 1.56 | AP11: 2.17 | AQ11: 1.87 | AR11: 2.58 | AS11: 2.78 | AT11: 3.07 | AU11: 2.87 | AV11: 3.07 | AW11: 2.75 | AX11: 2.51 | AY11: 2.3 | AZ11: 2.34 | BA11: 2.19 | BB11: 1.83 | BC11: 1.81 | BD11: 1.82 | BE11: 1.92 | BF11: 2.04 | BG11: 2.07 | BH11: 1.78 | BI11: 1.61 | BJ11: 1.73 | BK11: 1.84 | BL11: 1.74 | BM11: 1.91
B12: 43770 | C12: UNGB194@UK | D12: UK: BoE MPC Backcasts of GDP Growth: Real GDP [Q4-19](SA, Y/Y % Change) | E12: Q1-2012 | F12: Q2-2019 | G12: DISC | H12: Nov-07-2019 15:05 | I12: #N/A | J12: #N/A | K12: #N/A | L12: #N/A | M12: #N/A | N12: #N/A | O12: #N/A | P12: #N/A | Q12: #N/A | R12: #N/A | S12: #N/A | T12: #N/A | U12: #N/A | V12: #N/A | W12: #N/A | X12: #N/A | Y12: #N/A | Z12: #N/A | AA12: #N/A | AB12: #N/A | AC12: #N/A | AD12: #N/A | AE12: #N/A | AF12: #N/A | AG12: #N/A | AH12: #N/A | AI12: #N/A | AJ12: #N/A | AK12: 1.24 | AL12: 1.06 | AM12: 1.98 | AN12: 1.63 | AO12: 1.63 | AP12: 2.26 | AQ12: 1.98 | AR12: 2.68 | AS12: 2.7 | AT12: 2.82 | AU12: 2.44 | AV12: 2.47 | AW12: 2.34 | AX12: 2.4 | AY12: 2.25 | AZ12: 2.44 | BA12: 2.07 | BB12: 1.89 | BC12: 1.91 | BD12: 1.81 | BE12: 2.24 | BF12: 2.06 | BG12: 2.01 | BH12: 1.78 | BI12: 1.44 | BJ12: 1.67 | BK12: 1.87 | BL12: 1.84 | BM12: 2.17 | BN12: 1.35
B13: 43831 | C13: UNGB201@UK | D13: UK: BoE MPC Backcasts of GDP Growth: Real GDP [Q1-20](SA, Y/Y % Change) | E13: Q2-2012 | F13: Q3-2019 | G13: DISC | H13: Jan-30-2020 12:22 | I13: #N/A | J13: #N/A | K13: #N/A | L13: #N/A | M13: #N/A | N13: #N/A | O13: #N/A | P13: #N/A | Q13: #N/A | R13: #N/A | S13: #N/A | T13: #N/A | U13: #N/A | V13: #N/A | W13: #N/A | X13: #N/A | Y13: #N/A | Z13: #N/A | AA13: #N/A | AB13: #N/A | AC13: #N/A | AD13: #N/A | AE13: #N/A | AF13: #N/A | AG13: #N/A | AH13: #N/A | AI13: #N/A | AJ13: #N/A | AK13: #N/A | AL13: 1.06 | AM13: 1.98 | AN13: 1.63 | AO13: 1.63 | AP13: 2.26 | AQ13: 1.98 | AR13: 2.68 | AS13: 2.7 | AT13: 2.82 | AU13: 2.44 | AV13: 2.47 | AW13: 2.34 | AX13: 2.4 | AY13: 2.25 | AZ13: 2.44 | BA13: 2.07 | BB13: 1.89 | BC13: 1.91 | BD13: 1.81 | BE13: 2.23 | BF13: 2.05 | BG13: 2 | BH13: 1.77 | BI13: 1.43 | BJ13: 1.65 | BK13: 1.82 | BL13: 1.68 | BM13: 2.04 | BN13: 1.27 | BO13: 1.11
B14: 44044 | C14: UNGB203@UK | D14: UK: BoE MPC Backcasts of GDP Growth: Real GDP [Aug-20] (SA, Y/Y % Chg) | E14: Q4-2012 | F14: Q1-2020 | G14: DISC | H14: Aug-11-2020 12:33 | I14: #N/A | J14: #N/A | K14: #N/A | L14: #N/A | M14: #N/A | N14: #N/A | O14: #N/A | P14: #N/A | Q14: #N/A | R14: #N/A | S14: #N/A | T14: #N/A | U14: #N/A | V14: #N/A | W14: #N/A | X14: #N/A | Y14: #N/A | Z14: #N/A | AA14: #N/A | AB14: #N/A | AC14: #N/A | AD14: #N/A | AE14: #N/A | AF14: #N/A | AG14: #N/A | AH14: #N/A | AI14: #N/A | AJ14: #N/A | AK14: #N/A | AL14: #N/A | AM14: #N/A | AN14: 1.63 | AO14: 1.63 | AP14: 2.26 | AQ14: 1.98 | AR14: 2.68 | AS14: 2.7 | AT14: 2.82 | AU14: 2.44 | AV14: 2.47 | AW14: 2.34 | AX14: 2.4 | AY14: 2.25 | AZ14: 2.44 | BA14: 2.07 | BB14: 1.89 | BC14: 1.91 | BD14: 1.81 | BE14: 2.24 | BF14: 2.05 | BG14: 1.99 | BH14: 1.76 | BI14: 1.4 | BJ14: 1.62 | BK14: 1.79 | BL14: 1.72 | BM14: 2.15 | BN14: 1.51 | BO14: 1.32 | BP14: 1.08 | BQ14: -1.77
B15: 44136 | C15: UNGB204@UK | D15: UK: BoE MPC Backcasts of GDP Growth: Real GDP [Q4-20] (SA, Y/Y % Change) | E15: Q1-2013 | F15: Q2-2020 | G15: DISC | H15: Nov-05-2020 12:20 | I15: #N/A | J15: #N/A | K15: #N/A | L15: #N/A | M15: #N/A | N15: #N/A | O15: #N/A | P15: #N/A | Q15: #N/A | R15: #N/A | S15: #N/A | T15: #N/A | U15: #N/A | V15: #N/A | W15: #N/A | X15: #N/A | Y15: #N/A | Z15: #N/A | AA15: #N/A | AB15: #N/A | AC15: #N/A | AD15: #N/A | AE15: #N/A | AF15: #N/A | AG15: #N/A | AH15: #N/A | AI15: #N/A | AJ15: #N/A | AK15: #N/A | AL15: #N/A | AM15: #N/A | AN15: #N/A | AO15: 1.38 | AP15: 2.35 | AQ15: 2.06 | AR15: 2.94 | AS15: 3.19 | AT15: 3.03 | AU15: 2.65 | AV15: 2.59 | AW15: 2.36 | AX15: 2.46 | AY15: 2.28 | AZ15: 2.35 | BA15: 2 | BB15: 1.71 | BC15: 1.62 | BD15: 1.56 | BE15: 1.86 | BF15: 1.7 | BG15: 1.82 | BH15: 1.58 | BI15: 1.3 | BJ15: 1.48 | BK15: 1.6 | BL15: 1.53 | BM15: 1.86 | BN15: 1.37 | BO15: 1.15 | BP15: 1.07 | BQ15: -2.02 | BR15: -21.42
B16: 44228 | C16: UNGB211@UK | D16: UK: BoE MPC Backcasts of GDP Growth: Real GDP [Q1-21] (SA, Y/Y % Change) | E16: Q2-2013 | F16: Q3-2020 | G16: DISC | H16: Feb-04-2021 14:25 | I16: #N/A | J16: #N/A | K16: #N/A | L16: #N/A | M16: #N/A | N16: #N/A | O16: #N/A | P16: #N/A | Q16: #N/A | R16: #N/A | S16: #N/A | T16: #N/A | U16: #N/A | V16: #N/A | W16: #N/A | X16: #N/A | Y16: #N/A | Z16: #N/A | AA16: #N/A | AB16: #N/A | AC16: #N/A | AD16: #N/A | AE16: #N/A | AF16: #N/A | AG16: #N/A | AH16: #N/A | AI16: #N/A | AJ16: #N/A | AK16: #N/A | AL16: #N/A | AM16: #N/A | AN16: #N/A | AO16: #N/A | AP16: 2.35 | AQ16: 2.06 | AR16: 2.94 | AS16: 3.19 | AT16: 3.03 | AU16: 2.65 | AV16: 2.59 | AW16: 2.36 | AX16: 2.46 | AY16: 2.28 | AZ16: 2.35 | BA16: 2 | BB16: 1.71 | BC16: 1.62 | BD16: 1.56 | BE16: 1.86 | BF16: 1.7 | BG16: 1.82 | BH16: 1.58 | BI16: 1.22 | BJ16: 1.41 | BK16: 1.7 | BL16: 1.58 | BM16: 1.99 | BN16: 1.64 | BO16: 1.44 | BP16: 1.42 | BQ16: -2.18 | BR16: -20.64 | BS16: -8.4
B17: 44317 | C17: UNGB212@UK | D17: UK: BoE MPC Backcasts of GDP Growth: Real GDP [Q2-21] (SA, Y/Y % Change) | E17: Q3-2013 | F17: Q4-2020 | G17: DISC | H17: May-06-2021 13:01 | I17: #N/A | J17: #N/A | K17: #N/A | L17: #N/A | M17: #N/A | N17: #N/A | O17: #N/A | P17: #N/A | Q17: #N/A | R17: #N/A | S17: #N/A | T17: #N/A | U17: #N/A | V17: #N/A | W17: #N/A | X17: #N/A | Y17: #N/A | Z17: #N/A | AA17: #N/A | AB17: #N/A | AC17: #N/A | AD17: #N/A | AE17: #N/A | AF17: #N/A | AG17: #N/A | AH17: #N/A | AI17: #N/A | AJ17: #N/A | AK17: #N/A | AL17: #N/A | AM17: #N/A | AN17: #N/A | AO17: #N/A | AP17: #N/A | AQ17: 2.06 | AR17: 2.94 | AS17: 3.19 | AT17: 3.03 | AU17: 2.65 | AV17: 2.59 | AW17: 2.36 | AX17: 2.46 | AY17: 2.28 | AZ17: 2.35 | BA17: 2 | BB17: 1.71 | BC17: 1.62 | BD17: 1.56 | BE17: 1.86 | BF17: 1.7 | BG17: 1.82 | BH17: 1.58 | BI17: 1.22 | BJ17: 1.41 | BK17: 1.7 | BL17: 1.58 | BM17: 1.99 | BN17: 1.64 | BO17: 1.44 | BP17: 1.42 | BQ17: -2.01 | BR17: -21.2 | BS17: -8.3 | BT17: -7.34
B18: 44409 | C18: UNGB213@UK | D18: UK: BoE MPC Backcasts of GDP Growth: Real GDP [Q3-21] (SA, Y/Y % Change) | E18: Q4-2013 | F18: Q1-2021 | G18: DISC | H18: Aug-05-2021 12:45 | I18: #N/A | J18: #N/A | K18: #N/A | L18: #N/A | M18: #N/A | N18: #N/A | O18: #N/A | P18: #N/A | Q18: #N/A | R18: #N/A | S18: #N/A | T18: #N/A | U18: #N/A | V18: #N/A | W18: #N/A | X18: #N/A | Y18: #N/A | Z18: #N/A | AA18: #N/A | AB18: #N/A | AC18: #N/A | AD18: #N/A | AE18: #N/A | AF18: #N/A | AG18: #N/A | AH18: #N/A | AI18: #N/A | AJ18: #N/A | AK18: #N/A | AL18: #N/A | AM18: #N/A | AN18: #N/A | AO18: #N/A | AP18: #N/A | AQ18: #N/A | AR18: 2.94 | AS18: 3.19 | AT18: 3.03 | AU18: 2.65 | AV18: 2.59 | AW18: 2.36 | AX18: 2.46 | AY18: 2.28 | AZ18: 2.35 | BA18: 2 | BB18: 1.71 | BC18: 1.62 | BD18: 1.56 | BE18: 1.86 | BF18: 1.7 | BG18: 1.82 | BH18: 1.58 | BI18: 1.22 | BJ18: 1.41 | BK18: 1.7 | BL18: 1.58 | BM18: 1.99 | BN18: 1.64 | BO18: 1.44 | BP18: 1.42 | BQ18: -2.01 | BR18: -21.2 | BS18: -8.3 | BT18: -7.34 | BU18: -6.14
B19: 44501 | C19: UNGB214@UK | D19: UK: BoE MPC Backcasts of GDP Growth: Real GDP [Q4-21] (SA, Y/Y % Change) | E19: Q1-2014 | F19: Q2-2021 | G19: DISC | H19: Nov-04-2021 12:38 | I19: #N/A | J19: #N/A | K19: #N/A | L19: #N/A | M19: #N/A | N19: #N/A | O19: #N/A | P19: #N/A | Q19: #N/A | R19: #N/A | S19: #N/A | T19: #N/A | U19: #N/A | V19: #N/A | W19: #N/A | X19: #N/A | Y19: #N/A | Z19: #N/A | AA19: #N/A | AB19: #N/A | AC19: #N/A | AD19: #N/A | AE19: #N/A | AF19: #N/A | AG19: #N/A | AH19: #N/A | AI19: #N/A | AJ19: #N/A | AK19: #N/A | AL19: #N/A | AM19: #N/A | AN19: #N/A | AO19: #N/A | AP19: #N/A | AQ19: #N/A | AR19: #N/A | AS19: 2.91 | AT19: 3.07 | AU19: 2.97 | AV19: 3.01 | AW19: 2.72 | AX19: 2.65 | AY19: 2.5 | AZ19: 2.63 | BA19: 2.42 | BB19: 2.25 | BC19: 2.16 | BD19: 2.22 | BE19: 2.43 | BF19: 2.16 | BG19: 2.14 | BH19: 1.8 | BI19: 1.39 | BJ19: 1.62 | BK19: 1.83 | BL19: 1.76 | BM19: 2.17 | BN19: 1.75 | BO19: 1.58 | BP19: 1.19 | BQ19: -2.17 | BR19: -21.41 | BS19: -8.13 | BT19: -7.07 | BU19: -5.79 | BV19: 23.58
B20: 44593 | C20: UNGB221@UK | D20: UK: BoE MPC Backcasts of GDP Growth: Real GDP [Q1-22] (SA, Y/Y % Change) | E20: Q2-2014 | F20: Q3-2021 | G20: DISC | H20: Feb-03-2022 15:12 | I20: #N/A | J20: #N/A | K20: #N/A | L20: #N/A | M20: #N/A | N20: #N/A | O20: #N/A | P20: #N/A | Q20: #N/A | R20: #N/A | S20: #N/A | T20: #N/A | U20: #N/A | V20: #N/A | W20: #N/A | X20: #N/A | Y20: #N/A | Z20: #N/A | AA20: #N/A | AB20: #N/A | AC20: #N/A | AD20: #N/A | AE20: #N/A | AF20: #N/A | AG20: #N/A | AH20: #N/A | AI20: #N/A | AJ20: #N/A | AK20: #N/A | AL20: #N/A | AM20: #N/A | AN20: #N/A | AO20: #N/A | AP20: #N/A | AQ20: #N/A | AR20: #N/A | AS20: #N/A | AT20: 3.07 | AU20: 2.97 | AV20: 3.01 | AW20: 2.72 | AX20: 2.65 | AY20: 2.5 | AZ20: 2.63 | BA20: 2.42 | BB20: 2.25 | BC20: 2.16 | BD20: 2.22 | BE20: 2.43 | BF20: 2.16 | BG20: 2.14 | BH20: 1.8 | BI20: 1.39 | BJ20: 1.62 | BK20: 1.83 | BL20: 1.76 | BM20: 2.17 | BN20: 1.75 | BO20: 1.58 | BP20: 1.19 | BQ20: -2.1 | BR20: -21.25 | BS20: -7.83 | BT20: -6.41 | BU20: -5.09 | BV20: 24.23 | BW20: 6.79
B21: 44682 | C21: UNGB222@UK | D21: UK: BoE MPC Backcasts of GDP Growth: Real GDP [Q2-22] (SA, Y/Y % Change) | E21: Q3-2014 | F21: Q4-2021 | G21: DISC | H21: May-05-2022 13:43 | I21: #N/A | J21: #N/A | K21: #N/A | L21: #N/A | M21: #N/A | N21: #N/A | O21: #N/A | P21: #N/A | Q21: #N/A | R21: #N/A | S21: #N/A | T21: #N/A | U21: #N/A | V21: #N/A | W21: #N/A | X21: #N/A | Y21: #N/A | Z21: #N/A | AA21: #N/A | AB21: #N/A | AC21: #N/A | AD21: #N/A | AE21: #N/A | AF21: #N/A | AG21: #N/A | AH21: #N/A | AI21: #N/A | AJ21: #N/A | AK21: #N/A | AL21: #N/A | AM21: #N/A | AN21: #N/A | AO21: #N/A | AP21: #N/A | AQ21: #N/A | AR21: #N/A | AS21: #N/A | AT21: #N/A | AU21: 2.97 | AV21: 3.01 | AW21: 2.72 | AX21: 2.65 | AY21: 2.5 | AZ21: 2.63 | BA21: 2.42 | BB21: 2.25 | BC21: 2.16 | BD21: 2.22 | BE21: 2.43 | BF21: 2.16 | BG21: 2.14 | BH21: 1.8 | BI21: 1.39 | BJ21: 1.62 | BK21: 1.83 | BL21: 1.76 | BM21: 2.17 | BN21: 1.75 | BO21: 1.58 | BP21: 1.19 | BQ21: -1.99 | BR21: -21.14 | BS21: -7.69 | BT21: -6.28 | BU21: -4.97 | BV21: 24.49 | BW21: 6.86 | BX21: 6.64
B22: 44774 | C22: UNGB223@UK | D22: UK: BoE MPC Backcasts of GDP Growth: Real GDP [Q3-22] (SA, Y/Y % Change) | E22: Q4-2014 | F22: Q1-2022 | G22: DISC | H22: Aug-04-2022 12:54 | I22: #N/A | J22: #N/A | K22: #N/A | L22: #N/A | M22: #N/A | N22: #N/A | O22: #N/A | P22: #N/A | Q22: #N/A | R22: #N/A | S22: #N/A | T22: #N/A | U22: #N/A | V22: #N/A | W22: #N/A | X22: #N/A | Y22: #N/A | Z22: #N/A | AA22: #N/A | AB22: #N/A | AC22: #N/A | AD22: #N/A | AE22: #N/A | AF22: #N/A | AG22: #N/A | AH22: #N/A | AI22: #N/A | AJ22: #N/A | AK22: #N/A | AL22: #N/A | AM22: #N/A | AN22: #N/A | AO22: #N/A | AP22: #N/A | AQ22: #N/A | AR22: #N/A | AS22: #N/A | AT22: #N/A | AU22: #N/A | AV22: 3.01 | AW22: 2.72 | AX22: 2.65 | AY22: 2.5 | AZ22: 2.63 | BA22: 2.42 | BB22: 2.25 | BC22: 2.16 | BD22: 2.22 | BE22: 2.43 | BF22: 2.16 | BG22: 2.14 | BH22: 1.8 | BI22: 1.39 | BJ22: 1.62 | BK22: 1.83 | BL22: 1.76 | BM22: 2.17 | BN22: 1.75 | BO22: 1.58 | BP22: 1.19 | BQ22: -1.99 | BR22: -21.14 | BS22: -7.69 | BT22: -6.28 | BU22: -4.97 | BV22: 24.49 | BW22: 6.86 | BX22: 6.64 | BY22: 8.74
B23: 44866 | C23: UNGB224@UK | D23: UK: BoE MPC Backcasts of GDP Growth: Real GDP [Q4-22] (SA, Y/Y % Change) | E23: Q1-2015 | F23: Q2-2022 | G23: DISC | H23: Nov-03-2022 12:37 | I23: #N/A | J23: #N/A | K23: #N/A | L23: #N/A | M23: #N/A | N23: #N/A | O23: #N/A | P23: #N/A | Q23: #N/A | R23: #N/A | S23: #N/A | T23: #N/A | U23: #N/A | V23: #N/A | W23: #N/A | X23: #N/A | Y23: #N/A | Z23: #N/A | AA23: #N/A | AB23: #N/A | AC23: #N/A | AD23: #N/A | AE23: #N/A | AF23: #N/A | AG23: #N/A | AH23: #N/A | AI23: #N/A | AJ23: #N/A | AK23: #N/A | AL23: #N/A | AM23: #N/A | AN23: #N/A | AO23: #N/A | AP23: #N/A | AQ23: #N/A | AR23: #N/A | AS23: #N/A | AT23: #N/A | AU23: #N/A | AV23: #N/A | AW23: 2.72 | AX23: 2.48 | AY23: 2.14 | AZ23: 2.23 | BA23: 2.19 | BB23: 2.18 | BC23: 2.19 | BD23: 2.1 | BE23: 2.48 | BF23: 2.39 | BG23: 2.46 | BH23: 2.44 | BI23: 1.84 | BJ23: 1.76 | BK23: 1.8 | BL23: 1.42 | BM23: 1.91 | BN23: 1.56 | BO23: 1.62 | BP23: 1.33 | BQ23: -1.96 | BR23: -22.63 | BS23: -10.32 | BT23: -9.21 | BU23: -7.84 | BV23: 24.27 | BW23: 8.46 | BX23: 8.89 | BY23: 10.94 | BZ23: 4.38
B24: 44958 | C24: UNGB231@UK | D24: UK: BoE MPC Backcasts of GDP Growth: Real GDP [Q1-23] (SA, Y/Y % Change) | E24: Q2-2015 | F24: Q3-2022 | G24: DISC | H24: Feb-02-2023 13:16 | I24: #N/A | J24: #N/A | K24: #N/A | L24: #N/A | M24: #N/A | N24: #N/A | O24: #N/A | P24: #N/A | Q24: #N/A | R24: #N/A | S24: #N/A | T24: #N/A | U24: #N/A | V24: #N/A | W24: #N/A | X24: #N/A | Y24: #N/A | Z24: #N/A | AA24: #N/A | AB24: #N/A | AC24: #N/A | AD24: #N/A | AE24: #N/A | AF24: #N/A | AG24: #N/A | AH24: #N/A | AI24: #N/A | AJ24: #N/A | AK24: #N/A | AL24: #N/A | AM24: #N/A | AN24: #N/A | AO24: #N/A | AP24: #N/A | AQ24: #N/A | AR24: #N/A | AS24: #N/A | AT24: #N/A | AU24: #N/A | AV24: #N/A | AW24: #N/A | AX24: 2.48 | AY24: 2.14 | AZ24: 2.23 | BA24: 2.19 | BB24: 2.18 | BC24: 2.19 | BD24: 2.1 | BE24: 2.48 | BF24: 2.39 | BG24: 2.46 | BH24: 2.44 | BI24: 1.84 | BJ24: 1.76 | BK24: 1.8 | BL24: 1.42 | BM24: 1.91 | BN24: 1.56 | BO24: 1.62 | BP24: 1.33 | BQ24: -1.96 | BR24: -22.63 | BS24: -10.32 | BT24: -9.21 | BU24: -7.73 | BV24: 24.41 | BW24: 8.54 | BX24: 8.87 | BY24: 10.71 | BZ24: 3.99 | CA24: 1.9
B25: 45047 | C25: UNGB232@UK | D25: UK: BoE MPC Backcasts of GDP Growth: Real GDP [Q2-23] (SA, Y/Y % Change) | E25: Q3-2015 | F25: Q4-2022 | G25: DISC | H25: May-11-2023 13:13 | I25: #N/A | J25: #N/A | K25: #N/A | L25: #N/A | M25: #N/A | N25: #N/A | O25: #N/A | P25: #N/A | Q25: #N/A | R25: #N/A | S25: #N/A | T25: #N/A | U25: #N/A | V25: #N/A | W25: #N/A | X25: #N/A | Y25: #N/A | Z25: #N/A | AA25: #N/A | AB25: #N/A | AC25: #N/A | AD25: #N/A | AE25: #N/A | AF25: #N/A | AG25: #N/A | AH25: #N/A | AI25: #N/A | AJ25: #N/A | AK25: #N/A | AL25: #N/A | AM25: #N/A | AN25: #N/A | AO25: #N/A | AP25: #N/A | AQ25: #N/A | AR25: #N/A | AS25: #N/A | AT25: #N/A | AU25: #N/A | AV25: #N/A | AW25: #N/A | AX25: #N/A | AY25: 2.14 | AZ25: 2.23 | BA25: 2.19 | BB25: 2.18 | BC25: 2.19 | BD25: 2.1 | BE25: 2.48 | BF25: 2.39 | BG25: 2.46 | BH25: 2.44 | BI25: 1.84 | BJ25: 1.76 | BK25: 1.8 | BL25: 1.42 | BM25: 1.91 | BN25: 1.56 | BO25: 1.62 | BP25: 1.33 | BQ25: -1.96 | BR25: -22.63 | BS25: -10.32 | BT25: -9.21 | BU25: -7.73 | BV25: 24.41 | BW25: 8.54 | BX25: 8.87 | BY25: 10.56 | BZ25: 3.84 | CA25: 1.98 | CB25: 0.57
B26: 45139 | C26: UNGB233@UK | D26: UK: BoE MPC Backcasts of GDP Growth: Real GDP [Q3-23] (SA, Y/Y % Change) | E26: Q4-2015 | F26: Q1-2023 | G26: DISC | H26: Aug-03-2023 13:21 | I26: #N/A | J26: #N/A | K26: #N/A | L26: #N/A | M26: #N/A | N26: #N/A | O26: #N/A | P26: #N/A | Q26: #N/A | R26: #N/A | S26: #N/A | T26: #N/A | U26: #N/A | V26: #N/A | W26: #N/A | X26: #N/A | Y26: #N/A | Z26: #N/A | AA26: #N/A | AB26: #N/A | AC26: #N/A | AD26: #N/A | AE26: #N/A | AF26: #N/A | AG26: #N/A | AH26: #N/A | AI26: #N/A | AJ26: #N/A | AK26: #N/A | AL26: #N/A | AM26: #N/A | AN26: #N/A | AO26: #N/A | AP26: #N/A | AQ26: #N/A | AR26: #N/A | AS26: #N/A | AT26: #N/A | AU26: #N/A | AV26: #N/A | AW26: #N/A | AX26: #N/A | AY26: #N/A | AZ26: 2.23 | BA26: 2.19 | BB26: 2.18 | BC26: 2.19 | BD26: 2.1 | BE26: 2.48 | BF26: 2.39 | BG26: 2.46 | BH26: 2.44 | BI26: 1.84 | BJ26: 1.76 | BK26: 1.8 | BL26: 1.42 | BM26: 1.91 | BN26: 1.56 | BO26: 1.62 | BP26: 1.33 | BQ26: -1.96 | BR26: -22.63 | BS26: -10.32 | BT26: -9.21 | BU26: -7.73 | BV26: 24.41 | BW26: 8.54 | BX26: 8.87 | BY26: 10.56 | BZ26: 3.84 | CA26: 1.98 | CB26: 0.57 | CC26: 0.23
B27: 45231 | C27: UNGB234@UK | D27: UK: BoE MPC Backcasts of GDP Growth: Real GDP [Q4-23](SA, Y/Y % Change) | E27: Q1-2016 | F27: Q2-2023 | G27: DISC | H27: Nov-02-2023 12:51 | I27: #N/A | J27: #N/A | K27: #N/A | L27: #N/A | M27: #N/A | N27: #N/A | O27: #N/A | P27: #N/A | Q27: #N/A | R27: #N/A | S27: #N/A | T27: #N/A | U27: #N/A | V27: #N/A | W27: #N/A | X27: #N/A | Y27: #N/A | Z27: #N/A | AA27: #N/A | AB27: #N/A | AC27: #N/A | AD27: #N/A | AE27: #N/A | AF27: #N/A | AG27: #N/A | AH27: #N/A | AI27: #N/A | AJ27: #N/A | AK27: #N/A | AL27: #N/A | AM27: #N/A | AN27: #N/A | AO27: #N/A | AP27: #N/A | AQ27: #N/A | AR27: #N/A | AS27: #N/A | AT27: #N/A | AU27: #N/A | AV27: #N/A | AW27: #N/A | AX27: #N/A | AY27: #N/A | AZ27: #N/A | BA27: 1.9 | BB27: 1.9 | BC27: 1.9 | BD27: 1.9 | BE27: 2.4 | BF27: 2.5 | BG27: 2.8 | BH27: 2.9 | BI27: 2.1 | BJ27: 1.6 | BK27: 1.3 | BL27: 0.7 | BM27: 1.4 | BN27: 1.5 | BO27: 1.9 | BP27: 1.8 | BQ27: -1.7 | BR27: -21.9 | BS27: -9.5 | BT27: -8.3 | BU27: -6.7 | BV27: 25.7 | BW27: 9.5 | BX27: 9.7 | BY27: 11.4 | BZ27: 3.9 | CA27: 2.1 | CB27: 0.7 | CC27: 0.5 | CD27: 0.6
B28: 45323 | C28: UNGB241@UK | D28: UK: BoE MPC Backcasts of GDP Growth: Real GDP [Q1-24](SA, Y/Y % Change) | E28: Q2-2016 | F28: Q3-2023 | G28: DISC | H28: Feb-01-2024 12:59 | I28: #N/A | J28: #N/A | K28: #N/A | L28: #N/A | M28: #N/A | N28: #N/A | O28: #N/A | P28: #N/A | Q28: #N/A | R28: #N/A | S28: #N/A | T28: #N/A | U28: #N/A | V28: #N/A | W28: #N/A | X28: #N/A | Y28: #N/A | Z28: #N/A | AA28: #N/A | AB28: #N/A | AC28: #N/A | AD28: #N/A | AE28: #N/A | AF28: #N/A | AG28: #N/A | AH28: #N/A | AI28: #N/A | AJ28: #N/A | AK28: #N/A | AL28: #N/A | AM28: #N/A | AN28: #N/A | AO28: #N/A | AP28: #N/A | AQ28: #N/A | AR28: #N/A | AS28: #N/A | AT28: #N/A | AU28: #N/A | AV28: #N/A | AW28: #N/A | AX28: #N/A | AY28: #N/A | AZ28: #N/A | BA28: #N/A | BB28: 1.9 | BC28: 1.9 | BD28: 1.9 | BE28: 2.4 | BF28: 2.5 | BG28: 2.8 | BH28: 2.9 | BI28: 2.1 | BJ28: 1.6 | BK28: 1.3 | BL28: 0.7 | BM28: 1.4 | BN28: 1.5 | BO28: 1.9 | BP28: 1.8 | BQ28: -1.7 | BR28: -21.9 | BS28: -9.5 | BT28: -8.3 | BU28: -6.7 | BV28: 25.7 | BW28: 9.5 | BX28: 9.7 | BY28: 11.4 | BZ28: 3.9 | CA28: 2.1 | CB28: 0.6 | CC28: 0.4 | CD28: 0.3 | CE28: 0.3
B29: 45413 | C29: UNGB242@UK | D29: UK: BoE MPC Backcasts of GDP Growth: Real GDP [Q2-24] (SA, Y/Y % Change) | E29: Q3-2016 | F29: Q4-2023 | G29: DISC | H29: May-09-2024 12:57 | I29: #N/A | J29: #N/A | K29: #N/A | L29: #N/A | M29: #N/A | N29: #N/A | O29: #N/A | P29: #N/A | Q29: #N/A | R29: #N/A | S29: #N/A | T29: #N/A | U29: #N/A | V29: #N/A | W29: #N/A | X29: #N/A | Y29: #N/A | Z29: #N/A | AA29: #N/A | AB29: #N/A | AC29: #N/A | AD29: #N/A | AE29: #N/A | AF29: #N/A | AG29: #N/A | AH29: #N/A | AI29: #N/A | AJ29: #N/A | AK29: #N/A | AL29: #N/A | AM29: #N/A | AN29: #N/A | AO29: #N/A | AP29: #N/A | AQ29: #N/A | AR29: #N/A | AS29: #N/A | AT29: #N/A | AU29: #N/A | AV29: #N/A | AW29: #N/A | AX29: #N/A | AY29: #N/A | AZ29: #N/A | BA29: #N/A | BB29: #N/A | BC29: 1.9 | BD29: 1.9 | BE29: 2.4 | BF29: 2.5 | BG29: 2.8 | BH29: 2.9 | BI29: 2.1 | BJ29: 1.6 | BK29: 1.3 | BL29: 0.7 | BM29: 1.4 | BN29: 1.5 | BO29: 1.9 | BP29: 1.8 | BQ29: -1.7 | BR29: -21.9 | BS29: -9.5 | BT29: -8.3 | BU29: -6.7 | BV29: 25.7 | BW29: 9.5 | BX29: 9.7 | BY29: 11.4 | BZ29: 3.9 | CA29: 2.1 | CB29: 0.6 | CC29: 0.3 | CD29: 0.2 | CE29: 0.2 | CF29: -0.2
B30: 45505 | D30: UK: BoE MPC Backcasts of GDP Growth: Real GDP (SA, Y/Y % Change) | E30: Q1-2024 | F30: Q4-2023 | G30: BoE | H30: Aug-01-2024 12:57 | I30: #N/A | J30: #N/A | K30: #N/A | L30: #N/A | M30: #N/A | N30: #N/A | O30: #N/A | P30: #N/A | Q30: #N/A | R30: #N/A | S30: #N/A | T30: #N/A | U30: #N/A | V30: #N/A | W30: #N/A | X30: #N/A | Y30: #N/A | Z30: #N/A | AA30: #N/A | AB30: #N/A | AC30: #N/A | AD30: #N/A | AE30: #N/A | AF30: #N/A | AG30: #N/A | AH30: #N/A | AI30: #N/A | AJ30: #N/A | AK30: #N/A | AL30: #N/A | AM30: #N/A | AN30: #N/A | AO30: #N/A | AP30: #N/A | AQ30: #N/A | AR30: #N/A | AS30: #N/A | AT30: #N/A | AU30: #N/A | AV30: #N/A | AW30: #N/A | AX30: #N/A | AY30: #N/A | AZ30: #N/A | BA30: #N/A | BB30: #N/A | BC30: #N/A | BD30: #N/A | BE30: #N/A | BF30: #N/A | BG30: #N/A | BH30: #N/A | BI30: #N/A | BJ30: #N/A | BK30: #N/A | BL30: #N/A | BM30: #N/A | BN30: #N/A | BO30: #N/A | BP30: #N/A | BQ30: #N/A | BR30: #N/A | BS30: #N/A | BT30: #N/A | BU30: #N/A | BV30: #N/A | BW30: #N/A | BX30: #N/A | BY30: #N/A | BZ30: #N/A | CA30: #N/A | CB30: #N/A | CC30: #N/A | CD30: #N/A | CE30: #N/A | CF30: #N/A
B31: 45597 | D31: UK: BoE MPC Backcasts of GDP Growth: Real GDP (SA, Y/Y % Change) | E31: Q1-2024 | F31: Q4-2023 | G31: BoE | H31: Aug-01-2024 12:57 | I31: #N/A | J31: #N/A | K31: #N/A | L31: #N/A | M31: #N/A | N31: #N/A | O31: #N/A | P31: #N/A | Q31: #N/A | R31: #N/A | S31: #N/A | T31: #N/A | U31: #N/A | V31: #N/A | W31: #N/A | X31: #N/A | Y31: #N/A | Z31: #N/A | AA31: #N/A | AB31: #N/A | AC31: #N/A | AD31: #N/A | AE31: #N/A | AF31: #N/A | AG31: #N/A | AH31: #N/A | AI31: #N/A | AJ31: #N/A | AK31: #N/A | AL31: #N/A | AM31: #N/A | AN31: #N/A | AO31: #N/A | AP31: #N/A | AQ31: #N/A | AR31: #N/A | AS31: #N/A | AT31: #N/A | AU31: #N/A | AV31: #N/A | AW31: #N/A | AX31: #N/A | AY31: #N/A | AZ31: #N/A | BA31: #N/A | BB31: #N/A | BC31: #N/A | BD31: #N/A | BE31: #N/A | BF31: #N/A | BG31: #N/A | BH31: #N/A | BI31: #N/A | BJ31: #N/A | BK31: #N/A | BL31: #N/A | BM31: #N/A | BN31: #N/A | BO31: #N/A | BP31: #N/A | BQ31: #N/A | BR31: #N/A | BS31: #N/A | BT31: #N/A | BU31: #N/A | BV31: #N/A | BW31: #N/A | BX31: #N/A | BY31: #N/A | BZ31: #N/A | CA31: #N/A | CB31: #N/A | CC31: #N/A | CD31: #N/A | CE31: #N/A | CF31: #N/A
A32: GDP fcst | B32: 42856 | C32: UNGD172@UK | D32: UK: BoE GDP Proj Based on Expected Interest Rate [Q2-17]: Mode-DISC(Y/Y % Chg) | E32: Q2-2017 | F32: Q2-2020 | G32: DISC | H32: May-11-2017 13:48 | I32: #N/A | J32: #N/A | K32: #N/A | L32: #N/A | M32: #N/A | N32: #N/A | O32: #N/A | P32: #N/A | Q32: #N/A | R32: #N/A | S32: #N/A | T32: #N/A | U32: #N/A | V32: #N/A | W32: #N/A | X32: #N/A | Y32: #N/A | Z32: #N/A | AA32: #N/A | AB32: #N/A | AC32: #N/A | AD32: #N/A | AE32: #N/A | AF32: #N/A | AG32: #N/A | AH32: #N/A | AI32: #N/A | AJ32: #N/A | AK32: #N/A | AL32: #N/A | AM32: #N/A | AN32: #N/A | AO32: #N/A | AP32: #N/A | AQ32: #N/A | AR32: #N/A | AS32: #N/A | AT32: #N/A | AU32: #N/A | AV32: #N/A | AW32: #N/A | AX32: #N/A | AY32: #N/A | AZ32: #N/A | BA32: #N/A | BB32: #N/A | BC32: #N/A | BD32: #N/A | BE32: #N/A | BF32: 2.05 | BG32: 1.9 | BH32: 1.64 | BI32: 1.65 | BJ32: 1.7 | BK32: 1.75 | BL32: 1.79 | BM32: 1.8 | BN32: 1.79 | BO32: 1.79 | BP32: 1.79 | BQ32: 1.78 | BR32: 1.78
B33: 42948 | C33: UNGD173@UK | D33: UK: BoE GDP Proj Based on Expected Interest Rate [Q3-17]: Mode-DISC(Y/Y % Chg) | E33: Q3-2017 | F33: Q3-2020 | G33: DISC | H33: Aug-03-2017 15:42 | I33: #N/A | J33: #N/A | K33: #N/A | L33: #N/A | M33: #N/A | N33: #N/A | O33: #N/A | P33: #N/A | Q33: #N/A | R33: #N/A | S33: #N/A | T33: #N/A | U33: #N/A | V33: #N/A | W33: #N/A | X33: #N/A | Y33: #N/A | Z33: #N/A | AA33: #N/A | AB33: #N/A | AC33: #N/A | AD33: #N/A | AE33: #N/A | AF33: #N/A | AG33: #N/A | AH33: #N/A | AI33: #N/A | AJ33: #N/A | AK33: #N/A | AL33: #N/A | AM33: #N/A | AN33: #N/A | AO33: #N/A | AP33: #N/A | AQ33: #N/A | AR33: #N/A | AS33: #N/A | AT33: #N/A | AU33: #N/A | AV33: #N/A | AW33: #N/A | AX33: #N/A | AY33: #N/A | AZ33: #N/A | BA33: #N/A | BB33: #N/A | BC33: #N/A | BD33: #N/A | BE33: #N/A | BF33: #N/A | BG33: 1.57 | BH33: 1.32 | BI33: 1.39 | BJ33: 1.54 | BK33: 1.69 | BL33: 1.78 | BM33: 1.79 | BN33: 1.77 | BO33: 1.76 | BP33: 1.75 | BQ33: 1.76 | BR33: 1.77 | BS33: 1.79
B34: 43040 | C34: UNGD174@UK | D34: UK: BoE GDP Proj Based on Expected Interest Rate [Q4-17]: Mode(Y/Y % Chg) | E34: Q4-2017 | F34: Q4-2020 | G34: DISC | H34: Nov-02-2017 14:11 | I34: #N/A | J34: #N/A | K34: #N/A | L34: #N/A | M34: #N/A | N34: #N/A | O34: #N/A | P34: #N/A | Q34: #N/A | R34: #N/A | S34: #N/A | T34: #N/A | U34: #N/A | V34: #N/A | W34: #N/A | X34: #N/A | Y34: #N/A | Z34: #N/A | AA34: #N/A | AB34: #N/A | AC34: #N/A | AD34: #N/A | AE34: #N/A | AF34: #N/A | AG34: #N/A | AH34: #N/A | AI34: #N/A | AJ34: #N/A | AK34: #N/A | AL34: #N/A | AM34: #N/A | AN34: #N/A | AO34: #N/A | AP34: #N/A | AQ34: #N/A | AR34: #N/A | AS34: #N/A | AT34: #N/A | AU34: #N/A | AV34: #N/A | AW34: #N/A | AX34: #N/A | AY34: #N/A | AZ34: #N/A | BA34: #N/A | BB34: #N/A | BC34: #N/A | BD34: #N/A | BE34: #N/A | BF34: #N/A | BG34: #N/A | BH34: 1.46 | BI34: 1.51 | BJ34: 1.65 | BK34: 1.68 | BL34: 1.71 | BM34: 1.72 | BN34: 1.71 | BO34: 1.69 | BP34: 1.67 | BQ34: 1.67 | BR34: 1.69 | BS34: 1.72 | BT34: 1.75
B35: 43132 | C35: UNGD181@UK | D35: UK: BoE GDP Proj Based on Expected Interest Rate [Q1-18]: Mode(Y/Y % Chg) | E35: Q1-2018 | F35: Q1-2021 | G35: DISC | H35: Feb-08-2018 15:57 | I35: #N/A | J35: #N/A | K35: #N/A | L35: #N/A | M35: #N/A | N35: #N/A | O35: #N/A | P35: #N/A | Q35: #N/A | R35: #N/A | S35: #N/A | T35: #N/A | U35: #N/A | V35: #N/A | W35: #N/A | X35: #N/A | Y35: #N/A | Z35: #N/A | AA35: #N/A | AB35: #N/A | AC35: #N/A | AD35: #N/A | AE35: #N/A | AF35: #N/A | AG35: #N/A | AH35: #N/A | AI35: #N/A | AJ35: #N/A | AK35: #N/A | AL35: #N/A | AM35: #N/A | AN35: #N/A | AO35: #N/A | AP35: #N/A | AQ35: #N/A | AR35: #N/A | AS35: #N/A | AT35: #N/A | AU35: #N/A | AV35: #N/A | AW35: #N/A | AX35: #N/A | AY35: #N/A | AZ35: #N/A | BA35: #N/A | BB35: #N/A | BC35: #N/A | BD35: #N/A | BE35: #N/A | BF35: #N/A | BG35: #N/A | BH35: #N/A | BI35: 1.65 | BJ35: 1.8 | BK35: 1.86 | BL35: 1.79 | BM35: 1.77 | BN35: 1.73 | BO35: 1.69 | BP35: 1.67 | BQ35: 1.66 | BR35: 1.66 | BS35: 1.67 | BT35: 1.67 | BU35: 1.68
B36: 43221 | C36: UNGD182@UK | D36: UK: BoE GDP Proj Based on Expected Interest Rate [Q2-18]: Mode(Y/Y % Chg) | E36: Q2-2018 | F36: Q2-2021 | G36: DISC | H36: May-10-2018 15:03 | I36: #N/A | J36: #N/A | K36: #N/A | L36: #N/A | M36: #N/A | N36: #N/A | O36: #N/A | P36: #N/A | Q36: #N/A | R36: #N/A | S36: #N/A | T36: #N/A | U36: #N/A | V36: #N/A | W36: #N/A | X36: #N/A | Y36: #N/A | Z36: #N/A | AA36: #N/A | AB36: #N/A | AC36: #N/A | AD36: #N/A | AE36: #N/A | AF36: #N/A | AG36: #N/A | AH36: #N/A | AI36: #N/A | AJ36: #N/A | AK36: #N/A | AL36: #N/A | AM36: #N/A | AN36: #N/A | AO36: #N/A | AP36: #N/A | AQ36: #N/A | AR36: #N/A | AS36: #N/A | AT36: #N/A | AU36: #N/A | AV36: #N/A | AW36: #N/A | AX36: #N/A | AY36: #N/A | AZ36: #N/A | BA36: #N/A | BB36: #N/A | BC36: #N/A | BD36: #N/A | BE36: #N/A | BF36: #N/A | BG36: #N/A | BH36: #N/A | BI36: #N/A | BJ36: 1.41 | BK36: 1.39 | BL36: 1.44 | BM36: 1.77 | BN36: 1.74 | BO36: 1.71 | BP36: 1.7 | BQ36: 1.71 | BR36: 1.72 | BS36: 1.71 | BT36: 1.7 | BU36: 1.71 | BV36: 1.72
B37: 43313 | C37: UNGD183@UK | D37: UK: BoE GDP Proj Based on Expected Interest Rate [Q3-18]: Mode(Y/Y % Chg) | E37: Q3-2018 | F37: Q3-2021 | G37: DISC | H37: Aug-02-2018 14:57 | I37: #N/A | J37: #N/A | K37: #N/A | L37: #N/A | M37: #N/A | N37: #N/A | O37: #N/A | P37: #N/A | Q37: #N/A | R37: #N/A | S37: #N/A | T37: #N/A | U37: #N/A | V37: #N/A | W37: #N/A | X37: #N/A | Y37: #N/A | Z37: #N/A | AA37: #N/A | AB37: #N/A | AC37: #N/A | AD37: #N/A | AE37: #N/A | AF37: #N/A | AG37: #N/A | AH37: #N/A | AI37: #N/A | AJ37: #N/A | AK37: #N/A | AL37: #N/A | AM37: #N/A | AN37: #N/A | AO37: #N/A | AP37: #N/A | AQ37: #N/A | AR37: #N/A | AS37: #N/A | AT37: #N/A | AU37: #N/A | AV37: #N/A | AW37: #N/A | AX37: #N/A | AY37: #N/A | AZ37: #N/A | BA37: #N/A | BB37: #N/A | BC37: #N/A | BD37: #N/A | BE37: #N/A | BF37: #N/A | BG37: #N/A | BH37: #N/A | BI37: #N/A | BJ37: #N/A | BK37: 1.46 | BL37: 1.54 | BM37: 1.75 | BN37: 1.78 | BO37: 1.77 | BP37: 1.77 | BQ37: 1.75 | BR37: 1.72 | BS37: 1.7 | BT37: 1.68 | BU37: 1.67 | BV37: 1.67 | BW37: 1.68
B38: 43405 | C38: UNGD184@UK | D38: UK: BoE GDP Projections Based on Expected Int Rate [Q4-18]: Mode (Y/Y % Chg) | E38: Q4-2018 | F38: Q4-2021 | G38: DISC | H38: Nov-01-2018 15:04 | I38: #N/A | J38: #N/A | K38: #N/A | L38: #N/A | M38: #N/A | N38: #N/A | O38: #N/A | P38: #N/A | Q38: #N/A | R38: #N/A | S38: #N/A | T38: #N/A | U38: #N/A | V38: #N/A | W38: #N/A | X38: #N/A | Y38: #N/A | Z38: #N/A | AA38: #N/A | AB38: #N/A | AC38: #N/A | AD38: #N/A | AE38: #N/A | AF38: #N/A | AG38: #N/A | AH38: #N/A | AI38: #N/A | AJ38: #N/A | AK38: #N/A | AL38: #N/A | AM38: #N/A | AN38: #N/A | AO38: #N/A | AP38: #N/A | AQ38: #N/A | AR38: #N/A | AS38: #N/A | AT38: #N/A | AU38: #N/A | AV38: #N/A | AW38: #N/A | AX38: #N/A | AY38: #N/A | AZ38: #N/A | BA38: #N/A | BB38: #N/A | BC38: #N/A | BD38: #N/A | BE38: #N/A | BF38: #N/A | BG38: #N/A | BH38: #N/A | BI38: #N/A | BJ38: #N/A | BK38: #N/A | BL38: 1.47 | BM38: 1.8 | BN38: 1.83 | BO38: 1.63 | BP38: 1.72 | BQ38: 1.72 | BR38: 1.72 | BS38: 1.71 | BT38: 1.7 | BU38: 1.7 | BV38: 1.71 | BW38: 1.7 | BX38: 1.7
B39: 43497 | C39: UNGD191@UK | D39: UK: BoE GDP Projects Bsd on Expected Interest Rate[Q1-19]: Mode(Y/Y % Chg) | E39: Q1-2019 | F39: Q1-2022 | G39: DISC | H39: Feb-07-2019 12:39 | I39: #N/A | J39: #N/A | K39: #N/A | L39: #N/A | M39: #N/A | N39: #N/A | O39: #N/A | P39: #N/A | Q39: #N/A | R39: #N/A | S39: #N/A | T39: #N/A | U39: #N/A | V39: #N/A | W39: #N/A | X39: #N/A | Y39: #N/A | Z39: #N/A | AA39: #N/A | AB39: #N/A | AC39: #N/A | AD39: #N/A | AE39: #N/A | AF39: #N/A | AG39: #N/A | AH39: #N/A | AI39: #N/A | AJ39: #N/A | AK39: #N/A | AL39: #N/A | AM39: #N/A | AN39: #N/A | AO39: #N/A | AP39: #N/A | AQ39: #N/A | AR39: #N/A | AS39: #N/A | AT39: #N/A | AU39: #N/A | AV39: #N/A | AW39: #N/A | AX39: #N/A | AY39: #N/A | AZ39: #N/A | BA39: #N/A | BB39: #N/A | BC39: #N/A | BD39: #N/A | BE39: #N/A | BF39: #N/A | BG39: #N/A | BH39: #N/A | BI39: #N/A | BJ39: #N/A | BK39: #N/A | BL39: #N/A | BM39: 1.49 | BN39: 1.3 | BO39: 0.99 | BP39: 1.1 | BQ39: 1.28 | BR39: 1.46 | BS39: 1.58 | BT39: 1.66 | BU39: 1.74 | BV39: 1.83 | BW39: 1.92 | BX39: 1.99 | BY39: 2.05
B40: 43586 | C40: UNGD192@UK | D40: UK: BoE GDP Projections Based on Expected Interest Rate: Mode [Q2-19](Y/Y % Chg) | E40: Q2-2019 | F40: Q2-2022 | G40: DISC | H40: May-02-2019 12:20 | I40: #N/A | J40: #N/A | K40: #N/A | L40: #N/A | M40: #N/A | N40: #N/A | O40: #N/A | P40: #N/A | Q40: #N/A | R40: #N/A | S40: #N/A | T40: #N/A | U40: #N/A | V40: #N/A | W40: #N/A | X40: #N/A | Y40: #N/A | Z40: #N/A | AA40: #N/A | AB40: #N/A | AC40: #N/A | AD40: #N/A | AE40: #N/A | AF40: #N/A | AG40: #N/A | AH40: #N/A | AI40: #N/A | AJ40: #N/A | AK40: #N/A | AL40: #N/A | AM40: #N/A | AN40: #N/A | AO40: #N/A | AP40: #N/A | AQ40: #N/A | AR40: #N/A | AS40: #N/A | AT40: #N/A | AU40: #N/A | AV40: #N/A | AW40: #N/A | AX40: #N/A | AY40: #N/A | AZ40: #N/A | BA40: #N/A | BB40: #N/A | BC40: #N/A | BD40: #N/A | BE40: #N/A | BF40: #N/A | BG40: #N/A | BH40: #N/A | BI40: #N/A | BJ40: #N/A | BK40: #N/A | BL40: #N/A | BM40: #N/A | BN40: 1.59 | BO40: 1.17 | BP40: 1.29 | BQ40: 1.23 | BR40: 1.48 | BS40: 1.7 | BT40: 1.87 | BU40: 1.99 | BV40: 2.08 | BW40: 2.14 | BX40: 2.18 | BY40: 2.2 | BZ40: 2.21
B41: 43678 | C41: UNGD193@UK | D41: UK: BoE GDP Proj Based on Expected Interest Rate: Mode [Q3-19] (Y/Y % Chg) | E41: Q3-2019 | F41: Q3-2022 | G41: DISC | H41: Aug-01-2019 12:24 | I41: #N/A | J41: #N/A | K41: #N/A | L41: #N/A | M41: #N/A | N41: #N/A | O41: #N/A | P41: #N/A | Q41: #N/A | R41: #N/A | S41: #N/A | T41: #N/A | U41: #N/A | V41: #N/A | W41: #N/A | X41: #N/A | Y41: #N/A | Z41: #N/A | AA41: #N/A | AB41: #N/A | AC41: #N/A | AD41: #N/A | AE41: #N/A | AF41: #N/A | AG41: #N/A | AH41: #N/A | AI41: #N/A | AJ41: #N/A | AK41: #N/A | AL41: #N/A | AM41: #N/A | AN41: #N/A | AO41: #N/A | AP41: #N/A | AQ41: #N/A | AR41: #N/A | AS41: #N/A | AT41: #N/A | AU41: #N/A | AV41: #N/A | AW41: #N/A | AX41: #N/A | AY41: #N/A | AZ41: #N/A | BA41: #N/A | BB41: #N/A | BC41: #N/A | BD41: #N/A | BE41: #N/A | BF41: #N/A | BG41: #N/A | BH41: #N/A | BI41: #N/A | BJ41: #N/A | BK41: #N/A | BL41: #N/A | BM41: #N/A | BN41: #N/A | BO41: 0.96 | BP41: 0.91 | BQ41: 0.73 | BR41: 1.19 | BS41: 1.43 | BT41: 1.83 | BU41: 2.12 | BV41: 2.3 | BW41: 2.42 | BX41: 2.47 | BY41: 2.49 | BZ41: 2.5 | CA41: 2.5
B42: 43770 | C42: UNGD194@UK | D42: UK: BoE GDP Proj Based on Expected Interest Rate: Mode [Q4-19](Y/Y % Chg) | E42: Q4-2019 | F42: Q4-2022 | G42: DISC | H42: Nov-07-2019 15:05 | I42: #N/A | J42: #N/A | K42: #N/A | L42: #N/A | M42: #N/A | N42: #N/A | O42: #N/A | P42: #N/A | Q42: #N/A | R42: #N/A | S42: #N/A | T42: #N/A | U42: #N/A | V42: #N/A | W42: #N/A | X42: #N/A | Y42: #N/A | Z42: #N/A | AA42: #N/A | AB42: #N/A | AC42: #N/A | AD42: #N/A | AE42: #N/A | AF42: #N/A | AG42: #N/A | AH42: #N/A | AI42: #N/A | AJ42: #N/A | AK42: #N/A | AL42: #N/A | AM42: #N/A | AN42: #N/A | AO42: #N/A | AP42: #N/A | AQ42: #N/A | AR42: #N/A | AS42: #N/A | AT42: #N/A | AU42: #N/A | AV42: #N/A | AW42: #N/A | AX42: #N/A | AY42: #N/A | AZ42: #N/A | BA42: #N/A | BB42: #N/A | BC42: #N/A | BD42: #N/A | BE42: #N/A | BF42: #N/A | BG42: #N/A | BH42: #N/A | BI42: #N/A | BJ42: #N/A | BK42: #N/A | BL42: #N/A | BM42: #N/A | BN42: #N/A | BO42: #N/A | BP42: 0.99 | BQ42: 0.66 | BR42: 1.3 | BS42: 1.34 | BT42: 1.55 | BU42: 1.72 | BV42: 1.76 | BW42: 1.79 | BX42: 1.84 | BY42: 1.94 | BZ42: 1.99 | CA42: 2.03 | CB42: 2.06
B43: 43831 | C43: UNGD201@UK | D43: UK: BoE GDP Proj Based on Expected Interest Rate: Mode [Q1-20](Y/Y % Chg) | E43: Q1-2020 | F43: Q1-2023 | G43: DISC | H43: Jan-30-2020 12:22 | I43: #N/A | J43: #N/A | K43: #N/A | L43: #N/A | M43: #N/A | N43: #N/A | O43: #N/A | P43: #N/A | Q43: #N/A | R43: #N/A | S43: #N/A | T43: #N/A | U43: #N/A | V43: #N/A | W43: #N/A | X43: #N/A | Y43: #N/A | Z43: #N/A | AA43: #N/A | AB43: #N/A | AC43: #N/A | AD43: #N/A | AE43: #N/A | AF43: #N/A | AG43: #N/A | AH43: #N/A | AI43: #N/A | AJ43: #N/A | AK43: #N/A | AL43: #N/A | AM43: #N/A | AN43: #N/A | AO43: #N/A | AP43: #N/A | AQ43: #N/A | AR43: #N/A | AS43: #N/A | AT43: #N/A | AU43: #N/A | AV43: #N/A | AW43: #N/A | AX43: #N/A | AY43: #N/A | AZ43: #N/A | BA43: #N/A | BB43: #N/A | BC43: #N/A | BD43: #N/A | BE43: #N/A | BF43: #N/A | BG43: #N/A | BH43: #N/A | BI43: #N/A | BJ43: #N/A | BK43: #N/A | BL43: #N/A | BM43: #N/A | BN43: #N/A | BO43: #N/A | BP43: #N/A | BQ43: 0.37 | BR43: 0.83 | BS43: 0.76 | BT43: 1.21 | BU43: 1.37 | BV43: 1.45 | BW43: 1.48 | BX43: 1.46 | BY43: 1.56 | BZ43: 1.68 | CA43: 1.79 | CB43: 1.88 | CC43: 1.95
B44: 44044 | D44: UK: BoE GDP Proj Based on Expected Interest Rate: Mode [Q1-20](Y/Y % Chg) | E44: Q1-2020 | F44: Q1-2023 | G44: BoE | H44: Jan-30-2020 12:22 | I44: #N/A | J44: #N/A | K44: #N/A | L44: #N/A | M44: #N/A | N44: #N/A | O44: #N/A | P44: #N/A | Q44: #N/A | R44: #N/A | S44: #N/A | T44: #N/A | U44: #N/A | V44: #N/A | W44: #N/A | X44: #N/A | Y44: #N/A | Z44: #N/A | AA44: #N/A | AB44: #N/A | AC44: #N/A | AD44: #N/A | AE44: #N/A | AF44: #N/A | AG44: #N/A | AH44: #N/A | AI44: #N/A | AJ44: #N/A | AK44: #N/A | AL44: #N/A | AM44: #N/A | AN44: #N/A | AO44: #N/A | AP44: #N/A | AQ44: #N/A | AR44: #N/A | AS44: #N/A | AT44: #N/A | AU44: #N/A | AV44: #N/A | AW44: #N/A | AX44: #N/A | AY44: #N/A | AZ44: #N/A | BA44: #N/A | BB44: #N/A | BC44: #N/A | BD44: #N/A | BE44: #N/A | BF44: #N/A | BG44: #N/A | BH44: #N/A | BI44: #N/A | BJ44: #N/A | BK44: #N/A | BL44: #N/A | BM44: #N/A | BN44: #N/A | BO44: #N/A | BP44: #N/A | BQ44: 0.37 | BR44: 0.83 | BS44: 0.76 | BT44: 1.21 | BU44: 1.37 | BV44: 1.45 | BW44: 1.48 | BX44: 1.46 | BY44: 1.56 | BZ44: 1.68 | CA44: 1.79 | CB44: 1.88 | CC44: 1.95
B45: 44136
B46: 44228
B47: 44317
B48: 44409 | C48: UNGD213@UK | D48: UK: BoE GDP Proj Based on Expected Interest Rate: Mode [Q3-21] (Y/Y % Chg) | E48: Q2-2021 | F48: Q3-2024 | G48: DISC | H48: Aug-05-2021 12:45 | I48: #N/A | J48: #N/A | K48: #N/A | L48: #N/A | M48: #N/A | N48: #N/A | O48: #N/A | P48: #N/A | Q48: #N/A | R48: #N/A | S48: #N/A | T48: #N/A | U48: #N/A | V48: #N/A | W48: #N/A | X48: #N/A | Y48: #N/A | Z48: #N/A | AA48: #N/A | AB48: #N/A | AC48: #N/A | AD48: #N/A | AE48: #N/A | AF48: #N/A | AG48: #N/A | AH48: #N/A | AI48: #N/A | AJ48: #N/A | AK48: #N/A | AL48: #N/A | AM48: #N/A | AN48: #N/A | AO48: #N/A | AP48: #N/A | AQ48: #N/A | AR48: #N/A | AS48: #N/A | AT48: #N/A | AU48: #N/A | AV48: #N/A | AW48: #N/A | AX48: #N/A | AY48: #N/A | AZ48: #N/A | BA48: #N/A | BB48: #N/A | BC48: #N/A | BD48: #N/A | BE48: #N/A | BF48: #N/A | BG48: #N/A | BH48: #N/A | BI48: #N/A | BJ48: #N/A | BK48: #N/A | BL48: #N/A | BM48: #N/A | BN48: #N/A | BO48: #N/A | BP48: #N/A | BQ48: #N/A | BR48: #N/A | BS48: #N/A | BT48: #N/A | BU48: #N/A | BV48: 22.38 | BW48: 7.7 | BX48: 8.47 | BY48: 11.43 | BZ48: 6.59 | CA48: 4 | CB48: 2.25 | CC48: 1.6 | CD48: 1.53 | CE48: 1.3 | CF48: 1.3 | CG48: 1.17 | CH48: 1.09 | CI48: 1.26
B49: 44501 | C49: UNGD214@UK | D49: UK: BoE GDP Projections Based on Expected Interest Rate: Mode [Q4-21](Y/Y % Chg) | E49: Q3-2021 | F49: Q4-2024 | G49: DISC | H49: Nov-04-2021 12:38 | I49: #N/A | J49: #N/A | K49: #N/A | L49: #N/A | M49: #N/A | N49: #N/A | O49: #N/A | P49: #N/A | Q49: #N/A | R49: #N/A | S49: #N/A | T49: #N/A | U49: #N/A | V49: #N/A | W49: #N/A | X49: #N/A | Y49: #N/A | Z49: #N/A | AA49: #N/A | AB49: #N/A | AC49: #N/A | AD49: #N/A | AE49: #N/A | AF49: #N/A | AG49: #N/A | AH49: #N/A | AI49: #N/A | AJ49: #N/A | AK49: #N/A | AL49: #N/A | AM49: #N/A | AN49: #N/A | AO49: #N/A | AP49: #N/A | AQ49: #N/A | AR49: #N/A | AS49: #N/A | AT49: #N/A | AU49: #N/A | AV49: #N/A | AW49: #N/A | AX49: #N/A | AY49: #N/A | AZ49: #N/A | BA49: #N/A | BB49: #N/A | BC49: #N/A | BD49: #N/A | BE49: #N/A | BF49: #N/A | BG49: #N/A | BH49: #N/A | BI49: #N/A | BJ49: #N/A | BK49: #N/A | BL49: #N/A | BM49: #N/A | BN49: #N/A | BO49: #N/A | BP49: #N/A | BQ49: #N/A | BR49: #N/A | BS49: #N/A | BT49: #N/A | BU49: #N/A | BV49: #N/A | BW49: 6.84 | BX49: 6.68 | BY49: 9.49 | BZ49: 4.43 | CA49: 3.37 | CB49: 2.87 | CC49: 2.07 | CD49: 1.73 | CE49: 1.34 | CF49: 1.14 | CG49: 0.98 | CH49: 0.82 | CI49: 0.92 | CJ49: 0.93
B50: 44593 | C50: UNGD221@UK | D50: UK: BoE GDP Proj Based on Expected Interest Rate: Mode [Q1-22] (Y/Y % Chg) | E50: Q4-2021 | F50: Q1-2025 | G50: DISC | H50: Feb-03-2022 15:12 | I50: #N/A | J50: #N/A | K50: #N/A | L50: #N/A | M50: #N/A | N50: #N/A | O50: #N/A | P50: #N/A | Q50: #N/A | R50: #N/A | S50: #N/A | T50: #N/A | U50: #N/A | V50: #N/A | W50: #N/A | X50: #N/A | Y50: #N/A | Z50: #N/A | AA50: #N/A | AB50: #N/A | AC50: #N/A | AD50: #N/A | AE50: #N/A | AF50: #N/A | AG50: #N/A | AH50: #N/A | AI50: #N/A | AJ50: #N/A | AK50: #N/A | AL50: #N/A | AM50: #N/A | AN50: #N/A | AO50: #N/A | AP50: #N/A | AQ50: #N/A | AR50: #N/A | AS50: #N/A | AT50: #N/A | AU50: #N/A | AV50: #N/A | AW50: #N/A | AX50: #N/A | AY50: #N/A | AZ50: #N/A | BA50: #N/A | BB50: #N/A | BC50: #N/A | BD50: #N/A | BE50: #N/A | BF50: #N/A | BG50: #N/A | BH50: #N/A | BI50: #N/A | BJ50: #N/A | BK50: #N/A | BL50: #N/A | BM50: #N/A | BN50: #N/A | BO50: #N/A | BP50: #N/A | BQ50: #N/A | BR50: #N/A | BS50: #N/A | BT50: #N/A | BU50: #N/A | BV50: #N/A | BW50: #N/A | BX50: 6.4 | BY50: 7.81 | BZ50: 3.23 | CA50: 2.6 | CB50: 1.47 | CC50: 1.81 | CD50: 1.16 | CE50: 0.88 | CF50: 1.17 | CG50: 1.1 | CH50: 0.97 | CI50: 1.02 | CJ50: 0.98 | CK50: 0.93
B51: 44682 | C51: UNGD222@UK | D51: UK: BoE GDP Proj Based on Expected Interest Rate: Mode [Q2-22] (Y/Y % Chg) | E51: Q1-2022 | F51: Q2-2025 | G51: DISC | H51: May-05-2022 13:43 | I51: #N/A | J51: #N/A | K51: #N/A | L51: #N/A | M51: #N/A | N51: #N/A | O51: #N/A | P51: #N/A | Q51: #N/A | R51: #N/A | S51: #N/A | T51: #N/A | U51: #N/A | V51: #N/A | W51: #N/A | X51: #N/A | Y51: #N/A | Z51: #N/A | AA51: #N/A | AB51: #N/A | AC51: #N/A | AD51: #N/A | AE51: #N/A | AF51: #N/A | AG51: #N/A | AH51: #N/A | AI51: #N/A | AJ51: #N/A | AK51: #N/A | AL51: #N/A | AM51: #N/A | AN51: #N/A | AO51: #N/A | AP51: #N/A | AQ51: #N/A | AR51: #N/A | AS51: #N/A | AT51: #N/A | AU51: #N/A | AV51: #N/A | AW51: #N/A | AX51: #N/A | AY51: #N/A | AZ51: #N/A | BA51: #N/A | BB51: #N/A | BC51: #N/A | BD51: #N/A | BE51: #N/A | BF51: #N/A | BG51: #N/A | BH51: #N/A | BI51: #N/A | BJ51: #N/A | BK51: #N/A | BL51: #N/A | BM51: #N/A | BN51: #N/A | BO51: #N/A | BP51: #N/A | BQ51: #N/A | BR51: #N/A | BS51: #N/A | BT51: #N/A | BU51: #N/A | BV51: #N/A | BW51: #N/A | BX51: #N/A | BY51: 8.9 | BZ51: 3.22 | CA51: 2.86 | CB51: 0.66 | CC51: -0.17 | CD51: -0.04 | CE51: -0.81 | CF51: 0.24 | CG51: 0.25 | CH51: 0.21 | CI51: 0.43 | CJ51: 0.49 | CK51: 0.58 | CL51: 0.65
B52: 44774 | C52: UNGD223@UK | D52: UK: BoE GDP Proj Based on Expected Interest Rate: Mode [Q3-22] (Y/Y % Chg) | E52: Q2-2022 | F52: Q3-2025 | G52: DISC | H52: Aug-04-2022 12:54 | I52: #N/A | J52: #N/A | K52: #N/A | L52: #N/A | M52: #N/A | N52: #N/A | O52: #N/A | P52: #N/A | Q52: #N/A | R52: #N/A | S52: #N/A | T52: #N/A | U52: #N/A | V52: #N/A | W52: #N/A | X52: #N/A | Y52: #N/A | Z52: #N/A | AA52: #N/A | AB52: #N/A | AC52: #N/A | AD52: #N/A | AE52: #N/A | AF52: #N/A | AG52: #N/A | AH52: #N/A | AI52: #N/A | AJ52: #N/A | AK52: #N/A | AL52: #N/A | AM52: #N/A | AN52: #N/A | AO52: #N/A | AP52: #N/A | AQ52: #N/A | AR52: #N/A | AS52: #N/A | AT52: #N/A | AU52: #N/A | AV52: #N/A | AW52: #N/A | AX52: #N/A | AY52: #N/A | AZ52: #N/A | BA52: #N/A | BB52: #N/A | BC52: #N/A | BD52: #N/A | BE52: #N/A | BF52: #N/A | BG52: #N/A | BH52: #N/A | BI52: #N/A | BJ52: #N/A | BK52: #N/A | BL52: #N/A | BM52: #N/A | BN52: #N/A | BO52: #N/A | BP52: #N/A | BQ52: #N/A | BR52: #N/A | BS52: #N/A | BT52: #N/A | BU52: #N/A | BV52: #N/A | BW52: #N/A | BX52: #N/A | BY52: #N/A | BZ52: 2.81 | CA52: 2.26 | CB52: 0.07 | CC52: -1.01 | CD52: -1.26 | CE52: -2.07 | CF52: -1.24 | CG52: -0.97 | CH52: -0.52 | CI52: -0.04 | CJ52: 0.07 | CK52: 0.19 | CL52: 0.32 | CM52: 0.38
B53: 44866 | C53: UNGD224@UK | D53: UK: BoE GDP Proj Based on Expected Interest Rate: Mode [Q4-22] (Y/Y % Chg) | E53: Q3-2022 | F53: Q4-2025 | G53: DISC | H53: Nov-03-2022 12:37 | I53: #N/A | J53: #N/A | K53: #N/A | L53: #N/A | M53: #N/A | N53: #N/A | O53: #N/A | P53: #N/A | Q53: #N/A | R53: #N/A | S53: #N/A | T53: #N/A | U53: #N/A | V53: #N/A | W53: #N/A | X53: #N/A | Y53: #N/A | Z53: #N/A | AA53: #N/A | AB53: #N/A | AC53: #N/A | AD53: #N/A | AE53: #N/A | AF53: #N/A | AG53: #N/A | AH53: #N/A | AI53: #N/A | AJ53: #N/A | AK53: #N/A | AL53: #N/A | AM53: #N/A | AN53: #N/A | AO53: #N/A | AP53: #N/A | AQ53: #N/A | AR53: #N/A | AS53: #N/A | AT53: #N/A | AU53: #N/A | AV53: #N/A | AW53: #N/A | AX53: #N/A | AY53: #N/A | AZ53: #N/A | BA53: #N/A | BB53: #N/A | BC53: #N/A | BD53: #N/A | BE53: #N/A | BF53: #N/A | BG53: #N/A | BH53: #N/A | BI53: #N/A | BJ53: #N/A | BK53: #N/A | BL53: #N/A | BM53: #N/A | BN53: #N/A | BO53: #N/A | BP53: #N/A | BQ53: #N/A | BR53: #N/A | BS53: #N/A | BT53: #N/A | BU53: #N/A | BV53: #N/A | BW53: #N/A | BX53: #N/A | BY53: #N/A | BZ53: #N/A | CA53: 2.05 | CB53: 0.17 | CC53: -0.57 | CD53: -1.82 | CE53: -1.92 | CF53: -1.94 | CG53: -1.97 | CH53: -1.09 | CI53: -0.44 | CJ53: -0.13 | CK53: 0.08 | CL53: 0.34 | CM53: 0.51 | CN53: 0.66
B54: 44958 | C54: UNGD231@UK | D54: UK: BoE GDP Proj Based on Expected Interest Rate: Mode [Q1-23] (Y/Y % Chg) | E54: Q4-2022 | F54: Q1-2026 | G54: DISC | H54: Feb-02-2023 13:16 | I54: #N/A | J54: #N/A | K54: #N/A | L54: #N/A | M54: #N/A | N54: #N/A | O54: #N/A | P54: #N/A | Q54: #N/A | R54: #N/A | S54: #N/A | T54: #N/A | U54: #N/A | V54: #N/A | W54: #N/A | X54: #N/A | Y54: #N/A | Z54: #N/A | AA54: #N/A | AB54: #N/A | AC54: #N/A | AD54: #N/A | AE54: #N/A | AF54: #N/A | AG54: #N/A | AH54: #N/A | AI54: #N/A | AJ54: #N/A | AK54: #N/A | AL54: #N/A | AM54: #N/A | AN54: #N/A | AO54: #N/A | AP54: #N/A | AQ54: #N/A | AR54: #N/A | AS54: #N/A | AT54: #N/A | AU54: #N/A | AV54: #N/A | AW54: #N/A | AX54: #N/A | AY54: #N/A | AZ54: #N/A | BA54: #N/A | BB54: #N/A | BC54: #N/A | BD54: #N/A | BE54: #N/A | BF54: #N/A | BG54: #N/A | BH54: #N/A | BI54: #N/A | BJ54: #N/A | BK54: #N/A | BL54: #N/A | BM54: #N/A | BN54: #N/A | BO54: #N/A | BP54: #N/A | BQ54: #N/A | BR54: #N/A | BS54: #N/A | BT54: #N/A | BU54: #N/A | BV54: #N/A | BW54: #N/A | BX54: #N/A | BY54: #N/A | BZ54: #N/A | CA54: #N/A | CB54: 0.47 | CC54: -0.25 | CD54: -0.69 | CE54: -0.54 | CF54: -0.73 | CG54: -0.71 | CH54: -0.3 | CI54: -0.09 | CJ54: 0.05 | CK54: 0.18 | CL54: 0.21 | CM54: 0.37 | CN54: 0.64 | CO54: 0.91
B55: 45047 | C55: UNGD232@UK | D55: UK: BoE GDP Proj Based on Expected Interest Rate: Mode [Q2-23] (Y/Y % Chg) | E55: Q1-2023 | F55: Q2-2026 | G55: DISC | H55: May-11-2023 13:13 | I55: #N/A | J55: #N/A | K55: #N/A | L55: #N/A | M55: #N/A | N55: #N/A | O55: #N/A | P55: #N/A | Q55: #N/A | R55: #N/A | S55: #N/A | T55: #N/A | U55: #N/A | V55: #N/A | W55: #N/A | X55: #N/A | Y55: #N/A | Z55: #N/A | AA55: #N/A | AB55: #N/A | AC55: #N/A | AD55: #N/A | AE55: #N/A | AF55: #N/A | AG55: #N/A | AH55: #N/A | AI55: #N/A | AJ55: #N/A | AK55: #N/A | AL55: #N/A | AM55: #N/A | AN55: #N/A | AO55: #N/A | AP55: #N/A | AQ55: #N/A | AR55: #N/A | AS55: #N/A | AT55: #N/A | AU55: #N/A | AV55: #N/A | AW55: #N/A | AX55: #N/A | AY55: #N/A | AZ55: #N/A | BA55: #N/A | BB55: #N/A | BC55: #N/A | BD55: #N/A | BE55: #N/A | BF55: #N/A | BG55: #N/A | BH55: #N/A | BI55: #N/A | BJ55: #N/A | BK55: #N/A | BL55: #N/A | BM55: #N/A | BN55: #N/A | BO55: #N/A | BP55: #N/A | BQ55: #N/A | BR55: #N/A | BS55: #N/A | BT55: #N/A | BU55: #N/A | BV55: #N/A | BW55: #N/A | BX55: #N/A | BY55: #N/A | BZ55: #N/A | CA55: #N/A | CB55: #N/A | CC55: 0.09 | CD55: 0.03 | CE55: 0.61 | CF55: 0.67 | CG55: 0.8 | CH55: 0.89 | CI55: 0.6 | CJ55: 0.56 | CK55: 0.62 | CL55: 0.74 | CM55: 0.77 | CN55: 0.9 | CO55: 1.02 | CP55: 1.14
B56: 45139 | C56: UNGD233@UK | D56: UK: BoE GDP Projections Based on Expected Int Rate: Mode [Q3-23] (Y/Y % Chg) | E56: Q2-2023 | F56: Q3-2026 | G56: DISC | H56: Aug-03-2023 13:21 | I56: #N/A | J56: #N/A | K56: #N/A | L56: #N/A | M56: #N/A | N56: #N/A | O56: #N/A | P56: #N/A | Q56: #N/A | R56: #N/A | S56: #N/A | T56: #N/A | U56: #N/A | V56: #N/A | W56: #N/A | X56: #N/A | Y56: #N/A | Z56: #N/A | AA56: #N/A | AB56: #N/A | AC56: #N/A | AD56: #N/A | AE56: #N/A | AF56: #N/A | AG56: #N/A | AH56: #N/A | AI56: #N/A | AJ56: #N/A | AK56: #N/A | AL56: #N/A | AM56: #N/A | AN56: #N/A | AO56: #N/A | AP56: #N/A | AQ56: #N/A | AR56: #N/A | AS56: #N/A | AT56: #N/A | AU56: #N/A | AV56: #N/A | AW56: #N/A | AX56: #N/A | AY56: #N/A | AZ56: #N/A | BA56: #N/A | BB56: #N/A | BC56: #N/A | BD56: #N/A | BE56: #N/A | BF56: #N/A | BG56: #N/A | BH56: #N/A | BI56: #N/A | BJ56: #N/A | BK56: #N/A | BL56: #N/A | BM56: #N/A | BN56: #N/A | BO56: #N/A | BP56: #N/A | BQ56: #N/A | BR56: #N/A | BS56: #N/A | BT56: #N/A | BU56: #N/A | BV56: #N/A | BW56: #N/A | BX56: #N/A | BY56: #N/A | BZ56: #N/A | CA56: #N/A | CB56: #N/A | CC56: #N/A | CD56: 0.28 | CE56: 0.78 | CF56: 0.88 | CG56: 0.79 | CH56: 0.64 | CI56: 0.26 | CJ56: 0.05 | CK56: 0.06 | CL56: 0.21 | CM56: 0.34 | CN56: 0.54 | CO56: 0.78 | CP56: 0.99 | CQ56: 1.13
B57: 45231 | C57: UNGD234@UK | D57: UK: BoE GDP Projections Based on Expected Interest Rate: Mode [Q4-23](Y/Y % Chg) | E57: Q3-2023 | F57: Q4-2026 | G57: DISC | H57: Nov-02-2023 12:51 | I57: #N/A | J57: #N/A | K57: #N/A | L57: #N/A | M57: #N/A | N57: #N/A | O57: #N/A | P57: #N/A | Q57: #N/A | R57: #N/A | S57: #N/A | T57: #N/A | U57: #N/A | V57: #N/A | W57: #N/A | X57: #N/A | Y57: #N/A | Z57: #N/A | AA57: #N/A | AB57: #N/A | AC57: #N/A | AD57: #N/A | AE57: #N/A | AF57: #N/A | AG57: #N/A | AH57: #N/A | AI57: #N/A | AJ57: #N/A | AK57: #N/A | AL57: #N/A | AM57: #N/A | AN57: #N/A | AO57: #N/A | AP57: #N/A | AQ57: #N/A | AR57: #N/A | AS57: #N/A | AT57: #N/A | AU57: #N/A | AV57: #N/A | AW57: #N/A | AX57: #N/A | AY57: #N/A | AZ57: #N/A | BA57: #N/A | BB57: #N/A | BC57: #N/A | BD57: #N/A | BE57: #N/A | BF57: #N/A | BG57: #N/A | BH57: #N/A | BI57: #N/A | BJ57: #N/A | BK57: #N/A | BL57: #N/A | BM57: #N/A | BN57: #N/A | BO57: #N/A | BP57: #N/A | BQ57: #N/A | BR57: #N/A | BS57: #N/A | BT57: #N/A | BU57: #N/A | BV57: #N/A | BW57: #N/A | BX57: #N/A | BY57: #N/A | BZ57: #N/A | CA57: #N/A | CB57: #N/A | CC57: #N/A | CD57: #N/A | CE57: 0.6 | CF57: 0.6 | CG57: 0.2 | CH57: 0 | CI57: 0 | CJ57: 0 | CK57: 0 | CL57: 0.1 | CM57: 0.3 | CN57: 0.4 | CO57: 0.6 | CP57: 0.8 | CQ57: 0.9 | CR57: 1.1
B58: 45323 | C58: UNGD241@UK | D58: UK: BoE GDP Proj Based on Expected Interest Rate: Mode [Q1-24](Y/Y % Chg) | E58: Q4-2023 | F58: Q1-2027 | G58: DISC | H58: Feb-01-2024 12:59 | I58: #N/A | J58: #N/A | K58: #N/A | L58: #N/A | M58: #N/A | N58: #N/A | O58: #N/A | P58: #N/A | Q58: #N/A | R58: #N/A | S58: #N/A | T58: #N/A | U58: #N/A | V58: #N/A | W58: #N/A | X58: #N/A | Y58: #N/A | Z58: #N/A | AA58: #N/A | AB58: #N/A | AC58: #N/A | AD58: #N/A | AE58: #N/A | AF58: #N/A | AG58: #N/A | AH58: #N/A | AI58: #N/A | AJ58: #N/A | AK58: #N/A | AL58: #N/A | AM58: #N/A | AN58: #N/A | AO58: #N/A | AP58: #N/A | AQ58: #N/A | AR58: #N/A | AS58: #N/A | AT58: #N/A | AU58: #N/A | AV58: #N/A | AW58: #N/A | AX58: #N/A | AY58: #N/A | AZ58: #N/A | BA58: #N/A | BB58: #N/A | BC58: #N/A | BD58: #N/A | BE58: #N/A | BF58: #N/A | BG58: #N/A | BH58: #N/A | BI58: #N/A | BJ58: #N/A | BK58: #N/A | BL58: #N/A | BM58: #N/A | BN58: #N/A | BO58: #N/A | BP58: #N/A | BQ58: #N/A | BR58: #N/A | BS58: #N/A | BT58: #N/A | BU58: #N/A | BV58: #N/A | BW58: #N/A | BX58: #N/A | BY58: #N/A | BZ58: #N/A | CA58: #N/A | CB58: #N/A | CC58: #N/A | CD58: #N/A | CE58: #N/A | CF58: 0.2 | CG58: 0 | CH58: 0.1 | CI58: 0.4 | CJ58: 0.5 | CK58: 0.5 | CL58: 0.6 | CM58: 0.6 | CN58: 0.7 | CO58: 0.8 | CP58: 1 | CQ58: 1.2 | CR58: 1.4 | CS58: 1.5
B59: 45413 | C59: UNGD242@UK | D59: UK: BoE GDP Proj Based on Expected Interest Rate: Mode [Q2-24] (Y/Y % Chg) | E59: Q1-2024 | F59: Q2-2027 | G59: DISC | H59: May-09-2024 12:57 | I59: #N/A | J59: #N/A | K59: #N/A | L59: #N/A | M59: #N/A | N59: #N/A | O59: #N/A | P59: #N/A | Q59: #N/A | R59: #N/A | S59: #N/A | T59: #N/A | U59: #N/A | V59: #N/A | W59: #N/A | X59: #N/A | Y59: #N/A | Z59: #N/A | AA59: #N/A | AB59: #N/A | AC59: #N/A | AD59: #N/A | AE59: #N/A | AF59: #N/A | AG59: #N/A | AH59: #N/A | AI59: #N/A | AJ59: #N/A | AK59: #N/A | AL59: #N/A | AM59: #N/A | AN59: #N/A | AO59: #N/A | AP59: #N/A | AQ59: #N/A | AR59: #N/A | AS59: #N/A | AT59: #N/A | AU59: #N/A | AV59: #N/A | AW59: #N/A | AX59: #N/A | AY59: #N/A | AZ59: #N/A | BA59: #N/A | BB59: #N/A | BC59: #N/A | BD59: #N/A | BE59: #N/A | BF59: #N/A | BG59: #N/A | BH59: #N/A | BI59: #N/A | BJ59: #N/A | BK59: #N/A | BL59: #N/A | BM59: #N/A | BN59: #N/A | BO59: #N/A | BP59: #N/A | BQ59: #N/A | BR59: #N/A | BS59: #N/A | BT59: #N/A | BU59: #N/A | BV59: #N/A | BW59: #N/A | BX59: #N/A | BY59: #N/A | BZ59: #N/A | CA59: #N/A | CB59: #N/A | CC59: #N/A | CD59: #N/A | CE59: #N/A | CF59: #N/A | CG59: -0.1 | CH59: 0.2 | CI59: 0.5 | CJ59: 1.1 | CK59: 0.9 | CL59: 0.9 | CM59: 0.9 | CN59: 1 | CO59: 1.1 | CP59: 1.2 | CQ59: 1.3 | CR59: 1.4 | CS59: 1.5 | CT59: 1.6
B60: 45505 | C60: UNGD243@UK | D60: UK: BoE GDP Projections Based on Expected Int Rate: Mode [Q3-24] (Y/Y % Chg) | E60: Q2-2024 | F60: Q3-2027 | G60: DISC | H60: Aug-01-2024 13:36 | I60: #N/A | J60: #N/A | K60: #N/A | L60: #N/A | M60: #N/A | N60: #N/A | O60: #N/A | P60: #N/A | Q60: #N/A | R60: #N/A | S60: #N/A | T60: #N/A | U60: #N/A | V60: #N/A | W60: #N/A | X60: #N/A | Y60: #N/A | Z60: #N/A | AA60: #N/A | AB60: #N/A | AC60: #N/A | AD60: #N/A | AE60: #N/A | AF60: #N/A | AG60: #N/A | AH60: #N/A | AI60: #N/A | AJ60: #N/A | AK60: #N/A | AL60: #N/A | AM60: #N/A | AN60: #N/A | AO60: #N/A | AP60: #N/A | AQ60: #N/A | AR60: #N/A | AS60: #N/A | AT60: #N/A | AU60: #N/A | AV60: #N/A | AW60: #N/A | AX60: #N/A | AY60: #N/A | AZ60: #N/A | BA60: #N/A | BB60: #N/A | BC60: #N/A | BD60: #N/A | BE60: #N/A | BF60: #N/A | BG60: #N/A | BH60: #N/A | BI60: #N/A | BJ60: #N/A | BK60: #N/A | BL60: #N/A | BM60: #N/A | BN60: #N/A | BO60: #N/A | BP60: #N/A | BQ60: #N/A | BR60: #N/A | BS60: #N/A | BT60: #N/A | BU60: #N/A | BV60: #N/A | BW60: #N/A | BX60: #N/A | BY60: #N/A | BZ60: #N/A | CA60: #N/A | CB60: #N/A | CC60: #N/A | CD60: #N/A | CE60: #N/A | CF60: #N/A | CG60: #N/A | CH60: 1 | CI60: 1.5 | CJ60: 2 | CK60: 1.4 | CL60: 1 | CM60: 0.8 | CN60: 0.9 | CO60: 1.1 | CP60: 1.3 | CQ60: 1.4 | CR60: 1.5 | CS60: 1.6 | CT60: 1.7 | CU60: 1.7
B61: 45597 | C61: UNGD244@UK | D61: UK: BoE GDP Projections Based on Expected Interest Rate: Mode [Q4-24](Y/Y % Chg) | E61: Q3-2024 | F61: Q4-2027 | G61: DISC | H61: Nov-07-2024 12:46 | I61: #N/A | J61: #N/A | K61: #N/A | L61: #N/A | M61: #N/A | N61: #N/A | O61: #N/A | P61: #N/A | Q61: #N/A | R61: #N/A | S61: #N/A | T61: #N/A | U61: #N/A | V61: #N/A | W61: #N/A | X61: #N/A | Y61: #N/A | Z61: #N/A | AA61: #N/A | AB61: #N/A | AC61: #N/A | AD61: #N/A | AE61: #N/A | AF61: #N/A | AG61: #N/A | AH61: #N/A | AI61: #N/A | AJ61: #N/A | AK61: #N/A | AL61: #N/A | AM61: #N/A | AN61: #N/A | AO61: #N/A | AP61: #N/A | AQ61: #N/A | AR61: #N/A | AS61: #N/A | AT61: #N/A | AU61: #N/A | AV61: #N/A | AW61: #N/A | AX61: #N/A | AY61: #N/A | AZ61: #N/A | BA61: #N/A | BB61: #N/A | BC61: #N/A | BD61: #N/A | BE61: #N/A | BF61: #N/A | BG61: #N/A | BH61: #N/A | BI61: #N/A | BJ61: #N/A | BK61: #N/A | BL61: #N/A | BM61: #N/A | BN61: #N/A | BO61: #N/A | BP61: #N/A | BQ61: #N/A | BR61: #N/A | BS61: #N/A | BT61: #N/A | BU61: #N/A | BV61: #N/A | BW61: #N/A | BX61: #N/A | BY61: #N/A | BZ61: #N/A | CA61: #N/A | CB61: #N/A | CC61: #N/A | CD61: #N/A | CE61: #N/A | CF61: #N/A | CG61: #N/A | CH61: #N/A | CI61: 1 | CJ61: 1.7 | CK61: 1.4 | CL61: 1.4 | CM61: 1.6 | CN61: 1.7 | CO61: 1.6 | CP61: 1.4 | CQ61: 1.3 | CR61: 1.1 | CS61: 1.1 | CT61: 1.2 | CU61: 1.3 | CV61: 1.4
B62: 45689 | C62: UNGD@UK | D62: UK: BoE GDP Projections Based on Expected Interest Rate: Mode (Y/Y % Chg) | E62: Q4-2024 | F62: Q1-2028 | G62: BoE | H62: Feb-06-2025 12:03 | I62: #N/A | J62: #N/A | K62: #N/A | L62: #N/A | M62: #N/A | N62: #N/A | O62: #N/A | P62: #N/A | Q62: #N/A | R62: #N/A | S62: #N/A | T62: #N/A | U62: #N/A | V62: #N/A | W62: #N/A | X62: #N/A | Y62: #N/A | Z62: #N/A | AA62: #N/A | AB62: #N/A | AC62: #N/A | AD62: #N/A | AE62: #N/A | AF62: #N/A | AG62: #N/A | AH62: #N/A | AI62: #N/A | AJ62: #N/A | AK62: #N/A | AL62: #N/A | AM62: #N/A | AN62: #N/A | AO62: #N/A | AP62: #N/A | AQ62: #N/A | AR62: #N/A | AS62: #N/A | AT62: #N/A | AU62: #N/A | AV62: #N/A | AW62: #N/A | AX62: #N/A | AY62: #N/A | AZ62: #N/A | BA62: #N/A | BB62: #N/A | BC62: #N/A | BD62: #N/A | BE62: #N/A | BF62: #N/A | BG62: #N/A | BH62: #N/A | BI62: #N/A | BJ62: #N/A | BK62: #N/A | BL62: #N/A | BM62: #N/A | BN62: #N/A | BO62: #N/A | BP62: #N/A | BQ62: #N/A | BR62: #N/A | BS62: #N/A | BT62: #N/A | BU62: #N/A | BV62: #N/A | BW62: #N/A | BX62: #N/A | BY62: #N/A | BZ62: #N/A | CA62: #N/A | CB62: #N/A | CC62: #N/A | CD62: #N/A | CE62: #N/A | CF62: #N/A | CG62: #N/A | CH62: #N/A | CI62: #N/A | CJ62: 1 | CK62: 0.4 | CL62: 0.3 | CM62: 0.7 | CN62: 1.2 | CO62: 1.5 | CP62: 1.5 | CQ62: 1.5 | CR62: 1.4 | CS62: 1.3 | CT62: 1.4 | CU62: 1.5 | CV62: 1.7 | CW62: 1.8
A63: CPI history | C63: D7BT@UK | D63: UK: Consumer Price Index: All Items (NSA, 2015=100) | E63: Q1-1988 <- Jan-1988 | F63: Q4-2024 <- Dec-2024 | G63: ONS | H63: Jan-15-2025 07:05 | I63: 77.233333 | J63: 78 | K63: 78.4 | L63: 78.766667 | M63: 78.733333 | N63: 79.8 | O63: 80.3 | P63: 80.9 | Q63: 81 | R63: 81.8 | S63: 81.733333 | T63: 82.6 | U63: 82.933333 | V63: 84.6 | W63: 85.633333 | X63: 85.733333 | Y63: 85.433333 | Z63: 86.366667 | AA63: 86.933333 | AB63: 87.566667 | AC63: 88.233333 | AD63: 89.366667 | AE63: 89.633333 | AF63: 90.5 | AG63: 91.833333 | AH63: 93.3 | AI63: 93.833333 | AJ63: 94.733333 | AK63: 95.033333 | AL63: 95.8 | AM63: 96.066667 | AN63: 97.266667 | AO63: 97.666667 | AP63: 98.366667 | AQ63: 98.7 | AR63: 99.3 | AS63: 99.4 | AT63: 100.1 | AU63: 100.13333 | AV63: 100.2 | AW63: 99.5 | AX63: 100.06667 | AY63: 100.16667 | AZ63: 100.3 | BA63: 99.833333 | BB63: 100.4 | BC63: 100.86667 | BD63: 101.5 | BE63: 102 | BF63: 103.16667 | BG63: 103.7 | BH63: 104.56667 | BI63: 104.76667 | BJ63: 105.66667 | BK63: 106.3 | BL63: 106.93333 | BM63: 106.7 | BN63: 107.8 | BO63: 108.26667 | BP63: 108.43333 | BQ63: 108.46667 | BR63: 108.53333 | BS63: 108.93333 | BT63: 109.06667 | BU63: 109.16667 | BV63: 110.73333 | BW63: 111.93333 | BX63: 114.4 | BY63: 115.93333 | BZ63: 120.86667 | CA63: 123.13333 | CB63: 126.7 | CC63: 127.73333 | CD63: 131.06667 | CE63: 131.4 | CF63: 131.96667 | CG63: 132.26667 | CH63: 133.83333 | CI63: 134.1 | CJ63: 135.23333
A64: CPI fcst | B64: 42856 | C64: UNPD172@UK | D64: UK: BoE CPI Proj Based on Expected Interest Rate [Q2-17]: Mode-DISC(Y/Y % Chg) | E64: Q2-2017 | F64: Q2-2020 | G64: DISC | H64: May-11-2017 13:48 | I64: #N/A | J64: #N/A | K64: #N/A | L64: #N/A | M64: #N/A | N64: #N/A | O64: #N/A | P64: #N/A | Q64: #N/A | R64: #N/A | S64: #N/A | T64: #N/A | U64: #N/A | V64: #N/A | W64: #N/A | X64: #N/A | Y64: #N/A | Z64: #N/A | AA64: #N/A | AB64: #N/A | AC64: #N/A | AD64: #N/A | AE64: #N/A | AF64: #N/A | AG64: #N/A | AH64: #N/A | AI64: #N/A | AJ64: #N/A | AK64: #N/A | AL64: #N/A | AM64: #N/A | AN64: #N/A | AO64: #N/A | AP64: #N/A | AQ64: #N/A | AR64: #N/A | AS64: #N/A | AT64: #N/A | AU64: #N/A | AV64: #N/A | AW64: #N/A | AX64: #N/A | AY64: #N/A | AZ64: #N/A | BA64: #N/A | BB64: #N/A | BC64: #N/A | BD64: #N/A | BE64: #N/A | BF64: 2.65 | BG64: 2.64 | BH64: 2.82 | BI64: 2.67 | BJ64: 2.64 | BK64: 2.58 | BL64: 2.43 | BM64: 2.33 | BN64: 2.2 | BO64: 2.16 | BP64: 2.23 | BQ64: 2.26 | BR64: 2.26
B65: 42948 | C65: UNPD173@UK | D65: UK: BoE CPI Proj Based on Expected Interest Rate [Q3-17]: Mode-DISC(Y/Y % Chg) | E65: Q3-2017 | F65: Q3-2020 | G65: DISC | H65: Aug-03-2017 15:42 | I65: #N/A | J65: #N/A | K65: #N/A | L65: #N/A | M65: #N/A | N65: #N/A | O65: #N/A | P65: #N/A | Q65: #N/A | R65: #N/A | S65: #N/A | T65: #N/A | U65: #N/A | V65: #N/A | W65: #N/A | X65: #N/A | Y65: #N/A | Z65: #N/A | AA65: #N/A | AB65: #N/A | AC65: #N/A | AD65: #N/A | AE65: #N/A | AF65: #N/A | AG65: #N/A | AH65: #N/A | AI65: #N/A | AJ65: #N/A | AK65: #N/A | AL65: #N/A | AM65: #N/A | AN65: #N/A | AO65: #N/A | AP65: #N/A | AQ65: #N/A | AR65: #N/A | AS65: #N/A | AT65: #N/A | AU65: #N/A | AV65: #N/A | AW65: #N/A | AX65: #N/A | AY65: #N/A | AZ65: #N/A | BA65: #N/A | BB65: #N/A | BC65: #N/A | BD65: #N/A | BE65: #N/A | BF65: #N/A | BG65: 2.68 | BH65: 2.75 | BI65: 2.73 | BJ65: 2.68 | BK65: 2.58 | BL65: 2.46 | BM65: 2.37 | BN65: 2.25 | BO65: 2.19 | BP65: 2.25 | BQ65: 2.26 | BR65: 2.24 | BS65: 2.22
B66: 43040 | C66: UNPD174@UK | D66: UK: BoE CPI Proj Based on Expected Interest Rate [Q4-17]: Mode(Y/Y % Chg) | E66: Q4-2017 | F66: Q4-2020 | G66: DISC | H66: Nov-02-2017 14:11 | I66: #N/A | J66: #N/A | K66: #N/A | L66: #N/A | M66: #N/A | N66: #N/A | O66: #N/A | P66: #N/A | Q66: #N/A | R66: #N/A | S66: #N/A | T66: #N/A | U66: #N/A | V66: #N/A | W66: #N/A | X66: #N/A | Y66: #N/A | Z66: #N/A | AA66: #N/A | AB66: #N/A | AC66: #N/A | AD66: #N/A | AE66: #N/A | AF66: #N/A | AG66: #N/A | AH66: #N/A | AI66: #N/A | AJ66: #N/A | AK66: #N/A | AL66: #N/A | AM66: #N/A | AN66: #N/A | AO66: #N/A | AP66: #N/A | AQ66: #N/A | AR66: #N/A | AS66: #N/A | AT66: #N/A | AU66: #N/A | AV66: #N/A | AW66: #N/A | AX66: #N/A | AY66: #N/A | AZ66: #N/A | BA66: #N/A | BB66: #N/A | BC66: #N/A | BD66: #N/A | BE66: #N/A | BF66: #N/A | BG66: #N/A | BH66: 2.97 | BI66: 2.6 | BJ66: 2.57 | BK66: 2.46 | BL66: 2.37 | BM66: 2.28 | BN66: 2.22 | BO66: 2.19 | BP66: 2.21 | BQ66: 2.2 | BR66: 2.18 | BS66: 2.15 | BT66: 2.15
B67: 43132 | C67: UNPD181@UK | D67: UK: BoE CPI Proj Based on Expected Interest Rate [Q1-18]: Mode(Y/Y % Chg) | E67: Q1-2018 | F67: Q1-2021 | G67: DISC | H67: Feb-08-2018 15:57 | I67: #N/A | J67: #N/A | K67: #N/A | L67: #N/A | M67: #N/A | N67: #N/A | O67: #N/A | P67: #N/A | Q67: #N/A | R67: #N/A | S67: #N/A | T67: #N/A | U67: #N/A | V67: #N/A | W67: #N/A | X67: #N/A | Y67: #N/A | Z67: #N/A | AA67: #N/A | AB67: #N/A | AC67: #N/A | AD67: #N/A | AE67: #N/A | AF67: #N/A | AG67: #N/A | AH67: #N/A | AI67: #N/A | AJ67: #N/A | AK67: #N/A | AL67: #N/A | AM67: #N/A | AN67: #N/A | AO67: #N/A | AP67: #N/A | AQ67: #N/A | AR67: #N/A | AS67: #N/A | AT67: #N/A | AU67: #N/A | AV67: #N/A | AW67: #N/A | AX67: #N/A | AY67: #N/A | AZ67: #N/A | BA67: #N/A | BB67: #N/A | BC67: #N/A | BD67: #N/A | BE67: #N/A | BF67: #N/A | BG67: #N/A | BH67: #N/A | BI67: 2.92 | BJ67: 2.7 | BK67: 2.54 | BL67: 2.42 | BM67: 2.28 | BN67: 2.19 | BO67: 2.19 | BP67: 2.18 | BQ67: 2.16 | BR67: 2.14 | BS67: 2.11 | BT67: 2.11 | BU67: 2.11
B68: 43221 | C68: UNPD182@UK | D68: UK: BoE CPI Proj Based on Expected Interest Rate [Q2-18]: Mode(Y/Y % Chg) | E68: Q2-2018 | F68: Q2-2021 | G68: DISC | H68: May-10-2018 15:03 | I68: #N/A | J68: #N/A | K68: #N/A | L68: #N/A | M68: #N/A | N68: #N/A | O68: #N/A | P68: #N/A | Q68: #N/A | R68: #N/A | S68: #N/A | T68: #N/A | U68: #N/A | V68: #N/A | W68: #N/A | X68: #N/A | Y68: #N/A | Z68: #N/A | AA68: #N/A | AB68: #N/A | AC68: #N/A | AD68: #N/A | AE68: #N/A | AF68: #N/A | AG68: #N/A | AH68: #N/A | AI68: #N/A | AJ68: #N/A | AK68: #N/A | AL68: #N/A | AM68: #N/A | AN68: #N/A | AO68: #N/A | AP68: #N/A | AQ68: #N/A | AR68: #N/A | AS68: #N/A | AT68: #N/A | AU68: #N/A | AV68: #N/A | AW68: #N/A | AX68: #N/A | AY68: #N/A | AZ68: #N/A | BA68: #N/A | BB68: #N/A | BC68: #N/A | BD68: #N/A | BE68: #N/A | BF68: #N/A | BG68: #N/A | BH68: #N/A | BI68: #N/A | BJ68: 2.43 | BK68: 2.35 | BL68: 2.16 | BM68: 2.14 | BN68: 2.13 | BO68: 2.06 | BP68: 2.08 | BQ68: 2.06 | BR68: 2.03 | BS68: 2 | BT68: 2.01 | BU68: 2 | BV68: 2
B69: 43313 | C69: UNPD183@UK | D69: UK: BoE CPI Proj Based on Expected Interest Rate [Q3-18]: Mode(Y/Y % Chg) | E69: Q3-2018 | F69: Q3-2021 | G69: DISC | H69: Aug-02-2018 14:57 | I69: #N/A | J69: #N/A | K69: #N/A | L69: #N/A | M69: #N/A | N69: #N/A | O69: #N/A | P69: #N/A | Q69: #N/A | R69: #N/A | S69: #N/A | T69: #N/A | U69: #N/A | V69: #N/A | W69: #N/A | X69: #N/A | Y69: #N/A | Z69: #N/A | AA69: #N/A | AB69: #N/A | AC69: #N/A | AD69: #N/A | AE69: #N/A | AF69: #N/A | AG69: #N/A | AH69: #N/A | AI69: #N/A | AJ69: #N/A | AK69: #N/A | AL69: #N/A | AM69: #N/A | AN69: #N/A | AO69: #N/A | AP69: #N/A | AQ69: #N/A | AR69: #N/A | AS69: #N/A | AT69: #N/A | AU69: #N/A | AV69: #N/A | AW69: #N/A | AX69: #N/A | AY69: #N/A | AZ69: #N/A | BA69: #N/A | BB69: #N/A | BC69: #N/A | BD69: #N/A | BE69: #N/A | BF69: #N/A | BG69: #N/A | BH69: #N/A | BI69: #N/A | BJ69: #N/A | BK69: 2.48 | BL69: 2.29 | BM69: 2.32 | BN69: 2.34 | BO69: 2.15 | BP69: 2.17 | BQ69: 2.15 | BR69: 2.13 | BS69: 2.09 | BT69: 2.04 | BU69: 2.03 | BV69: 2.04 | BW69: 2.03
B70: 43405 | C70: UNPD184@UK | D70: UK: BoE CPI Projections Based on Expected Int Rate [Q4-18]: Mode (Y/Y % Chg) | E70: Q4-2018 | F70: Q4-2021 | G70: DISC | H70: Nov-01-2018 15:04 | I70: #N/A | J70: #N/A | K70: #N/A | L70: #N/A | M70: #N/A | N70: #N/A | O70: #N/A | P70: #N/A | Q70: #N/A | R70: #N/A | S70: #N/A | T70: #N/A | U70: #N/A | V70: #N/A | W70: #N/A | X70: #N/A | Y70: #N/A | Z70: #N/A | AA70: #N/A | AB70: #N/A | AC70: #N/A | AD70: #N/A | AE70: #N/A | AF70: #N/A | AG70: #N/A | AH70: #N/A | AI70: #N/A | AJ70: #N/A | AK70: #N/A | AL70: #N/A | AM70: #N/A | AN70: #N/A | AO70: #N/A | AP70: #N/A | AQ70: #N/A | AR70: #N/A | AS70: #N/A | AT70: #N/A | AU70: #N/A | AV70: #N/A | AW70: #N/A | AX70: #N/A | AY70: #N/A | AZ70: #N/A | BA70: #N/A | BB70: #N/A | BC70: #N/A | BD70: #N/A | BE70: #N/A | BF70: #N/A | BG70: #N/A | BH70: #N/A | BI70: #N/A | BJ70: #N/A | BK70: #N/A | BL70: 2.46 | BM70: 2.18 | BN70: 2.32 | BO70: 2.13 | BP70: 2.1 | BQ70: 2.4 | BR70: 2.31 | BS70: 2.24 | BT70: 2.12 | BU70: 2.1 | BV70: 2.06 | BW70: 2.04 | BX70: 2.03
B71: 43497 | C71: UNPD191@UK | D71: UK: BoE CPI Projects Bsd on Expected Interest Rate[Q1-19]: Mode(Y/Y % Chg) | E71: Q1-2019 | F71: Q1-2022 | G71: DISC | H71: Feb-07-2019 12:39 | I71: #N/A | J71: #N/A | K71: #N/A | L71: #N/A | M71: #N/A | N71: #N/A | O71: #N/A | P71: #N/A | Q71: #N/A | R71: #N/A | S71: #N/A | T71: #N/A | U71: #N/A | V71: #N/A | W71: #N/A | X71: #N/A | Y71: #N/A | Z71: #N/A | AA71: #N/A | AB71: #N/A | AC71: #N/A | AD71: #N/A | AE71: #N/A | AF71: #N/A | AG71: #N/A | AH71: #N/A | AI71: #N/A | AJ71: #N/A | AK71: #N/A | AL71: #N/A | AM71: #N/A | AN71: #N/A | AO71: #N/A | AP71: #N/A | AQ71: #N/A | AR71: #N/A | AS71: #N/A | AT71: #N/A | AU71: #N/A | AV71: #N/A | AW71: #N/A | AX71: #N/A | AY71: #N/A | AZ71: #N/A | BA71: #N/A | BB71: #N/A | BC71: #N/A | BD71: #N/A | BE71: #N/A | BF71: #N/A | BG71: #N/A | BH71: #N/A | BI71: #N/A | BJ71: #N/A | BK71: #N/A | BL71: #N/A | BM71: 1.82 | BN71: 1.94 | BO71: 1.76 | BP71: 1.97 | BQ71: 2.35 | BR71: 2.17 | BS71: 2.15 | BT71: 2.05 | BU71: 2.07 | BV71: 2.09 | BW71: 2.1 | BX71: 2.09 | BY71: 2.11
B72: 43586 | C72: UNPD192@UK | D72: UK: BoE CPI Proj Based on Expected Interest Rate: Mode [Q2-19] (Y/Y % Chg) | E72: Q2-2019 | F72: Q2-2022 | G72: DISC | H72: May-02-2019 12:20 | I72: #N/A | J72: #N/A | K72: #N/A | L72: #N/A | M72: #N/A | N72: #N/A | O72: #N/A | P72: #N/A | Q72: #N/A | R72: #N/A | S72: #N/A | T72: #N/A | U72: #N/A | V72: #N/A | W72: #N/A | X72: #N/A | Y72: #N/A | Z72: #N/A | AA72: #N/A | AB72: #N/A | AC72: #N/A | AD72: #N/A | AE72: #N/A | AF72: #N/A | AG72: #N/A | AH72: #N/A | AI72: #N/A | AJ72: #N/A | AK72: #N/A | AL72: #N/A | AM72: #N/A | AN72: #N/A | AO72: #N/A | AP72: #N/A | AQ72: #N/A | AR72: #N/A | AS72: #N/A | AT72: #N/A | AU72: #N/A | AV72: #N/A | AW72: #N/A | AX72: #N/A | AY72: #N/A | AZ72: #N/A | BA72: #N/A | BB72: #N/A | BC72: #N/A | BD72: #N/A | BE72: #N/A | BF72: #N/A | BG72: #N/A | BH72: #N/A | BI72: #N/A | BJ72: #N/A | BK72: #N/A | BL72: #N/A | BM72: #N/A | BN72: 2.08 | BO72: 1.83 | BP72: 1.63 | BQ72: 1.98 | BR72: 1.72 | BS72: 1.74 | BT72: 1.98 | BU72: 2.04 | BV72: 2.05 | BW72: 2.09 | BX72: 2.1 | BY72: 2.13 | BZ72: 2.16
B73: 43678 | C73: UNPD193@UK | D73: UK: BoE CPI Proj Based on Expected Interest Rate: Mode [Q3-19] (Y/Y % Chg) | E73: Q3-2019 | F73: Q3-2022 | G73: DISC | H73: Aug-01-2019 12:24 | I73: #N/A | J73: #N/A | K73: #N/A | L73: #N/A | M73: #N/A | N73: #N/A | O73: #N/A | P73: #N/A | Q73: #N/A | R73: #N/A | S73: #N/A | T73: #N/A | U73: #N/A | V73: #N/A | W73: #N/A | X73: #N/A | Y73: #N/A | Z73: #N/A | AA73: #N/A | AB73: #N/A | AC73: #N/A | AD73: #N/A | AE73: #N/A | AF73: #N/A | AG73: #N/A | AH73: #N/A | AI73: #N/A | AJ73: #N/A | AK73: #N/A | AL73: #N/A | AM73: #N/A | AN73: #N/A | AO73: #N/A | AP73: #N/A | AQ73: #N/A | AR73: #N/A | AS73: #N/A | AT73: #N/A | AU73: #N/A | AV73: #N/A | AW73: #N/A | AX73: #N/A | AY73: #N/A | AZ73: #N/A | BA73: #N/A | BB73: #N/A | BC73: #N/A | BD73: #N/A | BE73: #N/A | BF73: #N/A | BG73: #N/A | BH73: #N/A | BI73: #N/A | BJ73: #N/A | BK73: #N/A | BL73: #N/A | BM73: #N/A | BN73: #N/A | BO73: 1.68 | BP73: 1.56 | BQ73: 1.95 | BR73: 1.77 | BS73: 1.9 | BT73: 2.11 | BU73: 2.15 | BV73: 2.19 | BW73: 2.23 | BX73: 2.24 | BY73: 2.29 | BZ73: 2.33 | CA73: 2.37
B74: 43770 | C74: UNPD194@UK | D74: UK: BoE CPI Proj Based on Expected Interest Rate: Mode [Q4-19](Y/Y % Chg) | E74: Q4-2019 | F74: Q4-2022 | G74: DISC | H74: Nov-07-2019 15:05 | I74: #N/A | J74: #N/A | K74: #N/A | L74: #N/A | M74: #N/A | N74: #N/A | O74: #N/A | P74: #N/A | Q74: #N/A | R74: #N/A | S74: #N/A | T74: #N/A | U74: #N/A | V74: #N/A | W74: #N/A | X74: #N/A | Y74: #N/A | Z74: #N/A | AA74: #N/A | AB74: #N/A | AC74: #N/A | AD74: #N/A | AE74: #N/A | AF74: #N/A | AG74: #N/A | AH74: #N/A | AI74: #N/A | AJ74: #N/A | AK74: #N/A | AL74: #N/A | AM74: #N/A | AN74: #N/A | AO74: #N/A | AP74: #N/A | AQ74: #N/A | AR74: #N/A | AS74: #N/A | AT74: #N/A | AU74: #N/A | AV74: #N/A | AW74: #N/A | AX74: #N/A | AY74: #N/A | AZ74: #N/A | BA74: #N/A | BB74: #N/A | BC74: #N/A | BD74: #N/A | BE74: #N/A | BF74: #N/A | BG74: #N/A | BH74: #N/A | BI74: #N/A | BJ74: #N/A | BK74: #N/A | BL74: #N/A | BM74: #N/A | BN74: #N/A | BO74: #N/A | BP74: 1.43 | BQ74: 1.67 | BR74: 1.2 | BS74: 1.17 | BT74: 1.51 | BU74: 1.67 | BV74: 1.95 | BW74: 2 | BX74: 2.03 | BY74: 2.07 | BZ74: 2.14 | CA74: 2.18 | CB74: 2.25
B75: 43831 | C75: UNPD201@UK | D75: UK: BoE CPI Proj Based on Expected Interest Rate: Mode [Q1-20](Y/Y % Chg) | E75: Q1-2020 | F75: Q1-2023 | G75: DISC | H75: Jan-30-2020 12:22 | I75: #N/A | J75: #N/A | K75: #N/A | L75: #N/A | M75: #N/A | N75: #N/A | O75: #N/A | P75: #N/A | Q75: #N/A | R75: #N/A | S75: #N/A | T75: #N/A | U75: #N/A | V75: #N/A | W75: #N/A | X75: #N/A | Y75: #N/A | Z75: #N/A | AA75: #N/A | AB75: #N/A | AC75: #N/A | AD75: #N/A | AE75: #N/A | AF75: #N/A | AG75: #N/A | AH75: #N/A | AI75: #N/A | AJ75: #N/A | AK75: #N/A | AL75: #N/A | AM75: #N/A | AN75: #N/A | AO75: #N/A | AP75: #N/A | AQ75: #N/A | AR75: #N/A | AS75: #N/A | AT75: #N/A | AU75: #N/A | AV75: #N/A | AW75: #N/A | AX75: #N/A | AY75: #N/A | AZ75: #N/A | BA75: #N/A | BB75: #N/A | BC75: #N/A | BD75: #N/A | BE75: #N/A | BF75: #N/A | BG75: #N/A | BH75: #N/A | BI75: #N/A | BJ75: #N/A | BK75: #N/A | BL75: #N/A | BM75: #N/A | BN75: #N/A | BO75: #N/A | BP75: #N/A | BQ75: 1.8 | BR75: 1.32 | BS75: 1.24 | BT75: 1.43 | BU75: 1.53 | BV75: 1.84 | BW75: 1.91 | BX75: 1.99 | BY75: 2.01 | BZ75: 2.07 | CA75: 2.1 | CB75: 2.15 | CC75: 2.15
B76: 44044 | C76: UNPD203@UK | D76: UK: BoE CPI Proj Based on Expected Interest Rate: Mode [Aug-20] (Y/Y % Chg) | E76: Q3-2020 | F76: Q3-2023 | G76: DISC | H76: Aug-11-2020 12:33 | I76: #N/A | J76: #N/A | K76: #N/A | L76: #N/A | M76: #N/A | N76: #N/A | O76: #N/A | P76: #N/A | Q76: #N/A | R76: #N/A | S76: #N/A | T76: #N/A | U76: #N/A | V76: #N/A | W76: #N/A | X76: #N/A | Y76: #N/A | Z76: #N/A | AA76: #N/A | AB76: #N/A | AC76: #N/A | AD76: #N/A | AE76: #N/A | AF76: #N/A | AG76: #N/A | AH76: #N/A | AI76: #N/A | AJ76: #N/A | AK76: #N/A | AL76: #N/A | AM76: #N/A | AN76: #N/A | AO76: #N/A | AP76: #N/A | AQ76: #N/A | AR76: #N/A | AS76: #N/A | AT76: #N/A | AU76: #N/A | AV76: #N/A | AW76: #N/A | AX76: #N/A | AY76: #N/A | AZ76: #N/A | BA76: #N/A | BB76: #N/A | BC76: #N/A | BD76: #N/A | BE76: #N/A | BF76: #N/A | BG76: #N/A | BH76: #N/A | BI76: #N/A | BJ76: #N/A | BK76: #N/A | BL76: #N/A | BM76: #N/A | BN76: #N/A | BO76: #N/A | BP76: #N/A | BQ76: #N/A | BR76: #N/A | BS76: 0.25 | BT76: 0.26 | BU76: 0.48 | BV76: 1.48 | BW76: 1.81 | BX76: 1.81 | BY76: 1.75 | BZ76: 1.89 | CA76: 1.97 | CB76: 2.06 | CC76: 2.16 | CD76: 2.21 | CE76: 2.22
B77: 44136 | C77: UNPD204@UK | D77: UK: BoE CPI Projections Based on Expected Interest Rate: Mode [Q4-20](Y/Y % Chg) | E77: Q4-2020 | F77: Q4-2023 | G77: DISC | H77: Nov-05-2020 12:20 | I77: #N/A | J77: #N/A | K77: #N/A | L77: #N/A | M77: #N/A | N77: #N/A | O77: #N/A | P77: #N/A | Q77: #N/A | R77: #N/A | S77: #N/A | T77: #N/A | U77: #N/A | V77: #N/A | W77: #N/A | X77: #N/A | Y77: #N/A | Z77: #N/A | AA77: #N/A | AB77: #N/A | AC77: #N/A | AD77: #N/A | AE77: #N/A | AF77: #N/A | AG77: #N/A | AH77: #N/A | AI77: #N/A | AJ77: #N/A | AK77: #N/A | AL77: #N/A | AM77: #N/A | AN77: #N/A | AO77: #N/A | AP77: #N/A | AQ77: #N/A | AR77: #N/A | AS77: #N/A | AT77: #N/A | AU77: #N/A | AV77: #N/A | AW77: #N/A | AX77: #N/A | AY77: #N/A | AZ77: #N/A | BA77: #N/A | BB77: #N/A | BC77: #N/A | BD77: #N/A | BE77: #N/A | BF77: #N/A | BG77: #N/A | BH77: #N/A | BI77: #N/A | BJ77: #N/A | BK77: #N/A | BL77: #N/A | BM77: #N/A | BN77: #N/A | BO77: #N/A | BP77: #N/A | BQ77: #N/A | BR77: #N/A | BS77: #N/A | BT77: 0.57 | BU77: 0.72 | BV77: 1.72 | BW77: 1.75 | BX77: 2.12 | BY77: 2.13 | BZ77: 1.82 | CA77: 1.86 | CB77: 1.95 | CC77: 2.02 | CD77: 2.04 | CE77: 2.05 | CF77: 2.05
B78: 44228 | C78: UNPD211@UK | D78: UK: BoE CPI Projections Based on Expected Interest Rate: Mode [Q1-21](Y/Y % Chg) | E78: Q1-2021 | F78: Q1-2024 | G78: DISC | H78: Feb-04-2021 14:25 | I78: #N/A | J78: #N/A | K78: #N/A | L78: #N/A | M78: #N/A | N78: #N/A | O78: #N/A | P78: #N/A | Q78: #N/A | R78: #N/A | S78: #N/A | T78: #N/A | U78: #N/A | V78: #N/A | W78: #N/A | X78: #N/A | Y78: #N/A | Z78: #N/A | AA78: #N/A | AB78: #N/A | AC78: #N/A | AD78: #N/A | AE78: #N/A | AF78: #N/A | AG78: #N/A | AH78: #N/A | AI78: #N/A | AJ78: #N/A | AK78: #N/A | AL78: #N/A | AM78: #N/A | AN78: #N/A | AO78: #N/A | AP78: #N/A | AQ78: #N/A | AR78: #N/A | AS78: #N/A | AT78: #N/A | AU78: #N/A | AV78: #N/A | AW78: #N/A | AX78: #N/A | AY78: #N/A | AZ78: #N/A | BA78: #N/A | BB78: #N/A | BC78: #N/A | BD78: #N/A | BE78: #N/A | BF78: #N/A | BG78: #N/A | BH78: #N/A | BI78: #N/A | BJ78: #N/A | BK78: #N/A | BL78: #N/A | BM78: #N/A | BN78: #N/A | BO78: #N/A | BP78: #N/A | BQ78: #N/A | BR78: #N/A | BS78: #N/A | BT78: #N/A | BU78: 0.82 | BV78: 1.57 | BW78: 1.46 | BX78: 1.94 | BY78: 2.07 | BZ78: 2 | CA78: 2.15 | CB78: 2.15 | CC78: 2.11 | CD78: 2.09 | CE78: 2.03 | CF78: 2.02 | CG78: 1.98
B79: 44317 | C79: UNPD212@UK | D79: UK: BoE CPI Projections Based on Expected Interest Rate: Mode [Q2-21](Y/Y % Chg) | E79: Q2-2021 | F79: Q2-2024 | G79: DISC | H79: May-06-2021 13:01 | I79: #N/A | J79: #N/A | K79: #N/A | L79: #N/A | M79: #N/A | N79: #N/A | O79: #N/A | P79: #N/A | Q79: #N/A | R79: #N/A | S79: #N/A | T79: #N/A | U79: #N/A | V79: #N/A | W79: #N/A | X79: #N/A | Y79: #N/A | Z79: #N/A | AA79: #N/A | AB79: #N/A | AC79: #N/A | AD79: #N/A | AE79: #N/A | AF79: #N/A | AG79: #N/A | AH79: #N/A | AI79: #N/A | AJ79: #N/A | AK79: #N/A | AL79: #N/A | AM79: #N/A | AN79: #N/A | AO79: #N/A | AP79: #N/A | AQ79: #N/A | AR79: #N/A | AS79: #N/A | AT79: #N/A | AU79: #N/A | AV79: #N/A | AW79: #N/A | AX79: #N/A | AY79: #N/A | AZ79: #N/A | BA79: #N/A | BB79: #N/A | BC79: #N/A | BD79: #N/A | BE79: #N/A | BF79: #N/A | BG79: #N/A | BH79: #N/A | BI79: #N/A | BJ79: #N/A | BK79: #N/A | BL79: #N/A | BM79: #N/A | BN79: #N/A | BO79: #N/A | BP79: #N/A | BQ79: #N/A | BR79: #N/A | BS79: #N/A | BT79: #N/A | BU79: #N/A | BV79: 1.69 | BW79: 1.86 | BX79: 2.47 | BY79: 2.42 | BZ79: 2.31 | CA79: 2.2 | CB79: 2.02 | CC79: 1.99 | CD79: 1.96 | CE79: 1.92 | CF79: 1.93 | CG79: 1.94 | CH79: 1.93
B80: 44409 | C80: UNPD213@UK | D80: UK: BoE CPI Proj Based on Expected Interest Rate: Mode [Q3-21] (Y/Y % Chg) | E80: Q3-2021 | F80: Q3-2024 | G80: DISC | H80: Aug-05-2021 12:45 | I80: #N/A | J80: #N/A | K80: #N/A | L80: #N/A | M80: #N/A | N80: #N/A | O80: #N/A | P80: #N/A | Q80: #N/A | R80: #N/A | S80: #N/A | T80: #N/A | U80: #N/A | V80: #N/A | W80: #N/A | X80: #N/A | Y80: #N/A | Z80: #N/A | AA80: #N/A | AB80: #N/A | AC80: #N/A | AD80: #N/A | AE80: #N/A | AF80: #N/A | AG80: #N/A | AH80: #N/A | AI80: #N/A | AJ80: #N/A | AK80: #N/A | AL80: #N/A | AM80: #N/A | AN80: #N/A | AO80: #N/A | AP80: #N/A | AQ80: #N/A | AR80: #N/A | AS80: #N/A | AT80: #N/A | AU80: #N/A | AV80: #N/A | AW80: #N/A | AX80: #N/A | AY80: #N/A | AZ80: #N/A | BA80: #N/A | BB80: #N/A | BC80: #N/A | BD80: #N/A | BE80: #N/A | BF80: #N/A | BG80: #N/A | BH80: #N/A | BI80: #N/A | BJ80: #N/A | BK80: #N/A | BL80: #N/A | BM80: #N/A | BN80: #N/A | BO80: #N/A | BP80: #N/A | BQ80: #N/A | BR80: #N/A | BS80: #N/A | BT80: #N/A | BU80: #N/A | BV80: #N/A | BW80: 2.7 | BX80: 4 | BY80: 4.02 | BZ80: 3.78 | CA80: 3.28 | CB80: 2.54 | CC80: 2.42 | CD80: 2.19 | CE80: 2.07 | CF80: 1.99 | CG80: 1.96 | CH80: 1.93 | CI80: 1.89
B81: 44501 | C81: UNPD214@UK | D81: UK: BoE CPI Proj Based on Expected Interest Rate: Mode [Q4-21] (Y/Y % Chg) | E81: Q4-2021 | F81: Q4-2024 | G81: DISC | H81: Nov-04-2021 12:38 | I81: #N/A | J81: #N/A | K81: #N/A | L81: #N/A | M81: #N/A | N81: #N/A | O81: #N/A | P81: #N/A | Q81: #N/A | R81: #N/A | S81: #N/A | T81: #N/A | U81: #N/A | V81: #N/A | W81: #N/A | X81: #N/A | Y81: #N/A | Z81: #N/A | AA81: #N/A | AB81: #N/A | AC81: #N/A | AD81: #N/A | AE81: #N/A | AF81: #N/A | AG81: #N/A | AH81: #N/A | AI81: #N/A | AJ81: #N/A | AK81: #N/A | AL81: #N/A | AM81: #N/A | AN81: #N/A | AO81: #N/A | AP81: #N/A | AQ81: #N/A | AR81: #N/A | AS81: #N/A | AT81: #N/A | AU81: #N/A | AV81: #N/A | AW81: #N/A | AX81: #N/A | AY81: #N/A | AZ81: #N/A | BA81: #N/A | BB81: #N/A | BC81: #N/A | BD81: #N/A | BE81: #N/A | BF81: #N/A | BG81: #N/A | BH81: #N/A | BI81: #N/A | BJ81: #N/A | BK81: #N/A | BL81: #N/A | BM81: #N/A | BN81: #N/A | BO81: #N/A | BP81: #N/A | BQ81: #N/A | BR81: #N/A | BS81: #N/A | BT81: #N/A | BU81: #N/A | BV81: #N/A | BW81: #N/A | BX81: 4.33 | BY81: 4.56 | BZ81: 4.8 | CA81: 4.42 | CB81: 3.4 | CC81: 3.26 | CD81: 2.58 | CE81: 2.4 | CF81: 2.23 | CG81: 2.11 | CH81: 1.99 | CI81: 1.96 | CJ81: 1.95
B82: 44593 | C82: UNPD221@UK | D82: UK: BoE CPI Proj Based on Expected Interest Rate: Mode [Q1-22] (Y/Y % Chg) | E82: Q1-2022 | F82: Q1-2025 | G82: DISC | H82: Feb-03-2022 15:12 | I82: #N/A | J82: #N/A | K82: #N/A | L82: #N/A | M82: #N/A | N82: #N/A | O82: #N/A | P82: #N/A | Q82: #N/A | R82: #N/A | S82: #N/A | T82: #N/A | U82: #N/A | V82: #N/A | W82: #N/A | X82: #N/A | Y82: #N/A | Z82: #N/A | AA82: #N/A | AB82: #N/A | AC82: #N/A | AD82: #N/A | AE82: #N/A | AF82: #N/A | AG82: #N/A | AH82: #N/A | AI82: #N/A | AJ82: #N/A | AK82: #N/A | AL82: #N/A | AM82: #N/A | AN82: #N/A | AO82: #N/A | AP82: #N/A | AQ82: #N/A | AR82: #N/A | AS82: #N/A | AT82: #N/A | AU82: #N/A | AV82: #N/A | AW82: #N/A | AX82: #N/A | AY82: #N/A | AZ82: #N/A | BA82: #N/A | BB82: #N/A | BC82: #N/A | BD82: #N/A | BE82: #N/A | BF82: #N/A | BG82: #N/A | BH82: #N/A | BI82: #N/A | BJ82: #N/A | BK82: #N/A | BL82: #N/A | BM82: #N/A | BN82: #N/A | BO82: #N/A | BP82: #N/A | BQ82: #N/A | BR82: #N/A | BS82: #N/A | BT82: #N/A | BU82: #N/A | BV82: #N/A | BW82: #N/A | BX82: #N/A | BY82: 5.73 | BZ82: 7.03 | CA82: 6.7 | CB82: 5.81 | CC82: 5.21 | CD82: 3.49 | CE82: 3.25 | CF82: 2.45 | CG82: 2.15 | CH82: 1.89 | CI82: 1.77 | CJ82: 1.66 | CK82: 1.6
B83: 44682 | C83: UNPD222@UK | D83: UK: BoE CPI Proj Based on Expected Interest Rate: Mode [Q2-22] (Y/Y % Chg) | E83: Q2-2022 | F83: Q2-2025 | G83: DISC | H83: May-05-2022 13:43 | I83: #N/A | J83: #N/A | K83: #N/A | L83: #N/A | M83: #N/A | N83: #N/A | O83: #N/A | P83: #N/A | Q83: #N/A | R83: #N/A | S83: #N/A | T83: #N/A | U83: #N/A | V83: #N/A | W83: #N/A | X83: #N/A | Y83: #N/A | Z83: #N/A | AA83: #N/A | AB83: #N/A | AC83: #N/A | AD83: #N/A | AE83: #N/A | AF83: #N/A | AG83: #N/A | AH83: #N/A | AI83: #N/A | AJ83: #N/A | AK83: #N/A | AL83: #N/A | AM83: #N/A | AN83: #N/A | AO83: #N/A | AP83: #N/A | AQ83: #N/A | AR83: #N/A | AS83: #N/A | AT83: #N/A | AU83: #N/A | AV83: #N/A | AW83: #N/A | AX83: #N/A | AY83: #N/A | AZ83: #N/A | BA83: #N/A | BB83: #N/A | BC83: #N/A | BD83: #N/A | BE83: #N/A | BF83: #N/A | BG83: #N/A | BH83: #N/A | BI83: #N/A | BJ83: #N/A | BK83: #N/A | BL83: #N/A | BM83: #N/A | BN83: #N/A | BO83: #N/A | BP83: #N/A | BQ83: #N/A | BR83: #N/A | BS83: #N/A | BT83: #N/A | BU83: #N/A | BV83: #N/A | BW83: #N/A | BX83: #N/A | BY83: #N/A | BZ83: 9.13 | CA83: 9.46 | CB83: 10.19 | CC83: 9.31 | CD83: 6.65 | CE83: 5.88 | CF83: 3.56 | CG83: 2.91 | CH83: 2.14 | CI83: 1.85 | CJ83: 1.51 | CK83: 1.37 | CL83: 1.3
B84: 44774 | C84: UNPD223@UK | D84: UK: BoE CPI Proj Based on Expected Interest Rate: Mode [Q3-22] (Y/Y % Chg) | E84: Q3-2022 | F84: Q3-2025 | G84: DISC | H84: Aug-04-2022 12:54 | I84: #N/A | J84: #N/A | K84: #N/A | L84: #N/A | M84: #N/A | N84: #N/A | O84: #N/A | P84: #N/A | Q84: #N/A | R84: #N/A | S84: #N/A | T84: #N/A | U84: #N/A | V84: #N/A | W84: #N/A | X84: #N/A | Y84: #N/A | Z84: #N/A | AA84: #N/A | AB84: #N/A | AC84: #N/A | AD84: #N/A | AE84: #N/A | AF84: #N/A | AG84: #N/A | AH84: #N/A | AI84: #N/A | AJ84: #N/A | AK84: #N/A | AL84: #N/A | AM84: #N/A | AN84: #N/A | AO84: #N/A | AP84: #N/A | AQ84: #N/A | AR84: #N/A | AS84: #N/A | AT84: #N/A | AU84: #N/A | AV84: #N/A | AW84: #N/A | AX84: #N/A | AY84: #N/A | AZ84: #N/A | BA84: #N/A | BB84: #N/A | BC84: #N/A | BD84: #N/A | BE84: #N/A | BF84: #N/A | BG84: #N/A | BH84: #N/A | BI84: #N/A | BJ84: #N/A | BK84: #N/A | BL84: #N/A | BM84: #N/A | BN84: #N/A | BO84: #N/A | BP84: #N/A | BQ84: #N/A | BR84: #N/A | BS84: #N/A | BT84: #N/A | BU84: #N/A | BV84: #N/A | BW84: #N/A | BX84: #N/A | BY84: #N/A | BZ84: #N/A | CA84: 9.93 | CB84: 13.1 | CC84: 12.56 | CD84: 10.79 | CE84: 9.53 | CF84: 5.46 | CG84: 4.33 | CH84: 2.64 | CI84: 2 | CJ84: 1.4 | CK84: 1.16 | CL84: 0.93 | CM84: 0.76
B85: 44866 | C85: UNPD224@UK | D85: UK: BoE CPI Proj Based on Expected Interest Rate: Mode [Q4-22] (Y/Y % Chg) | E85: Q4-2022 | F85: Q4-2025 | G85: DISC | H85: Nov-03-2022 12:37 | I85: #N/A | J85: #N/A | K85: #N/A | L85: #N/A | M85: #N/A | N85: #N/A | O85: #N/A | P85: #N/A | Q85: #N/A | R85: #N/A | S85: #N/A | T85: #N/A | U85: #N/A | V85: #N/A | W85: #N/A | X85: #N/A | Y85: #N/A | Z85: #N/A | AA85: #N/A | AB85: #N/A | AC85: #N/A | AD85: #N/A | AE85: #N/A | AF85: #N/A | AG85: #N/A | AH85: #N/A | AI85: #N/A | AJ85: #N/A | AK85: #N/A | AL85: #N/A | AM85: #N/A | AN85: #N/A | AO85: #N/A | AP85: #N/A | AQ85: #N/A | AR85: #N/A | AS85: #N/A | AT85: #N/A | AU85: #N/A | AV85: #N/A | AW85: #N/A | AX85: #N/A | AY85: #N/A | AZ85: #N/A | BA85: #N/A | BB85: #N/A | BC85: #N/A | BD85: #N/A | BE85: #N/A | BF85: #N/A | BG85: #N/A | BH85: #N/A | BI85: #N/A | BJ85: #N/A | BK85: #N/A | BL85: #N/A | BM85: #N/A | BN85: #N/A | BO85: #N/A | BP85: #N/A | BQ85: #N/A | BR85: #N/A | BS85: #N/A | BT85: #N/A | BU85: #N/A | BV85: #N/A | BW85: #N/A | BX85: #N/A | BY85: #N/A | BZ85: #N/A | CA85: #N/A | CB85: 10.86 | CC85: 10.12 | CD85: 9.54 | CE85: 7.87 | CF85: 5.2 | CG85: 3.96 | CH85: 1.09 | CI85: 1.16 | CJ85: 1.43 | CK85: 1.16 | CL85: 0.84 | CM85: 0.57 | CN85: 0.02
B86: 44958 | C86: UNPD231@UK | D86: UK: BoE CPI Proj Based on Expected Interest Rate: Mode [Q1-23] (Y/Y % Chg) | E86: Q1-2023 | F86: Q1-2026 | G86: DISC | H86: Feb-02-2023 13:16 | I86: #N/A | J86: #N/A | K86: #N/A | L86: #N/A | M86: #N/A | N86: #N/A | O86: #N/A | P86: #N/A | Q86: #N/A | R86: #N/A | S86: #N/A | T86: #N/A | U86: #N/A | V86: #N/A | W86: #N/A | X86: #N/A | Y86: #N/A | Z86: #N/A | AA86: #N/A | AB86: #N/A | AC86: #N/A | AD86: #N/A | AE86: #N/A | AF86: #N/A | AG86: #N/A | AH86: #N/A | AI86: #N/A | AJ86: #N/A | AK86: #N/A | AL86: #N/A | AM86: #N/A | AN86: #N/A | AO86: #N/A | AP86: #N/A | AQ86: #N/A | AR86: #N/A | AS86: #N/A | AT86: #N/A | AU86: #N/A | AV86: #N/A | AW86: #N/A | AX86: #N/A | AY86: #N/A | AZ86: #N/A | BA86: #N/A | BB86: #N/A | BC86: #N/A | BD86: #N/A | BE86: #N/A | BF86: #N/A | BG86: #N/A | BH86: #N/A | BI86: #N/A | BJ86: #N/A | BK86: #N/A | BL86: #N/A | BM86: #N/A | BN86: #N/A | BO86: #N/A | BP86: #N/A | BQ86: #N/A | BR86: #N/A | BS86: #N/A | BT86: #N/A | BU86: #N/A | BV86: #N/A | BW86: #N/A | BX86: #N/A | BY86: #N/A | BZ86: #N/A | CA86: #N/A | CB86: #N/A | CC86: 9.73 | CD86: 8.48 | CE86: 6.2 | CF86: 3.92 | CG86: 3.01 | CH86: 0.96 | CI86: 1.67 | CJ86: 1.42 | CK86: 0.95 | CL86: 0.76 | CM86: 0.59 | CN86: 0.47 | CO86: 0.37
B87: 45047 | C87: UNPD232@UK | D87: UK: BoE CPI Proj Based on Expected Interest Rate: Mode [Q2-23] (Y/Y % Chg) | E87: Q2-2023 | F87: Q2-2026 | G87: DISC | H87: May-11-2023 13:13 | I87: #N/A | J87: #N/A | K87: #N/A | L87: #N/A | M87: #N/A | N87: #N/A | O87: #N/A | P87: #N/A | Q87: #N/A | R87: #N/A | S87: #N/A | T87: #N/A | U87: #N/A | V87: #N/A | W87: #N/A | X87: #N/A | Y87: #N/A | Z87: #N/A | AA87: #N/A | AB87: #N/A | AC87: #N/A | AD87: #N/A | AE87: #N/A | AF87: #N/A | AG87: #N/A | AH87: #N/A | AI87: #N/A | AJ87: #N/A | AK87: #N/A | AL87: #N/A | AM87: #N/A | AN87: #N/A | AO87: #N/A | AP87: #N/A | AQ87: #N/A | AR87: #N/A | AS87: #N/A | AT87: #N/A | AU87: #N/A | AV87: #N/A | AW87: #N/A | AX87: #N/A | AY87: #N/A | AZ87: #N/A | BA87: #N/A | BB87: #N/A | BC87: #N/A | BD87: #N/A | BE87: #N/A | BF87: #N/A | BG87: #N/A | BH87: #N/A | BI87: #N/A | BJ87: #N/A | BK87: #N/A | BL87: #N/A | BM87: #N/A | BN87: #N/A | BO87: #N/A | BP87: #N/A | BQ87: #N/A | BR87: #N/A | BS87: #N/A | BT87: #N/A | BU87: #N/A | BV87: #N/A | BW87: #N/A | BX87: #N/A | BY87: #N/A | BZ87: #N/A | CA87: #N/A | CB87: #N/A | CC87: #N/A | CD87: 8.22 | CE87: 6.97 | CF87: 5.12 | CG87: 4.41 | CH87: 3.38 | CI87: 2.91 | CJ87: 2.28 | CK87: 1.52 | CL87: 1.1 | CM87: 1.01 | CN87: 1.02 | CO87: 1.07 | CP87: 1.2
B88: 45139 | C88: UNPD233@UK | D88: UK: BoE CPI Proj Based on Expected Interest Rate: Mode [Q3-23] (Y/Y % Chg) | E88: Q3-2023 | F88: Q3-2026 | G88: DISC | H88: Aug-03-2023 13:21 | I88: #N/A | J88: #N/A | K88: #N/A | L88: #N/A | M88: #N/A | N88: #N/A | O88: #N/A | P88: #N/A | Q88: #N/A | R88: #N/A | S88: #N/A | T88: #N/A | U88: #N/A | V88: #N/A | W88: #N/A | X88: #N/A | Y88: #N/A | Z88: #N/A | AA88: #N/A | AB88: #N/A | AC88: #N/A | AD88: #N/A | AE88: #N/A | AF88: #N/A | AG88: #N/A | AH88: #N/A | AI88: #N/A | AJ88: #N/A | AK88: #N/A | AL88: #N/A | AM88: #N/A | AN88: #N/A | AO88: #N/A | AP88: #N/A | AQ88: #N/A | AR88: #N/A | AS88: #N/A | AT88: #N/A | AU88: #N/A | AV88: #N/A | AW88: #N/A | AX88: #N/A | AY88: #N/A | AZ88: #N/A | BA88: #N/A | BB88: #N/A | BC88: #N/A | BD88: #N/A | BE88: #N/A | BF88: #N/A | BG88: #N/A | BH88: #N/A | BI88: #N/A | BJ88: #N/A | BK88: #N/A | BL88: #N/A | BM88: #N/A | BN88: #N/A | BO88: #N/A | BP88: #N/A | BQ88: #N/A | BR88: #N/A | BS88: #N/A | BT88: #N/A | BU88: #N/A | BV88: #N/A | BW88: #N/A | BX88: #N/A | BY88: #N/A | BZ88: #N/A | CA88: #N/A | CB88: #N/A | CC88: #N/A | CD88: #N/A | CE88: 6.93 | CF88: 4.93 | CG88: 4.32 | CH88: 3.3 | CI88: 2.82 | CJ88: 2.52 | CK88: 2.16 | CL88: 1.74 | CM88: 1.65 | CN88: 1.58 | CO88: 1.52 | CP88: 1.48 | CQ88: 1.46
B89: 45231 | C89: UNPD234@UK | D89: UK: BoE CPI Projections Based on Expected Interest Rate: Mode [Q4-23](Y/Y % Chg) | E89: Q4-2023 | F89: Q4-2026 | G89: DISC | H89: Nov-02-2023 12:51 | I89: #N/A | J89: #N/A | K89: #N/A | L89: #N/A | M89: #N/A | N89: #N/A | O89: #N/A | P89: #N/A | Q89: #N/A | R89: #N/A | S89: #N/A | T89: #N/A | U89: #N/A | V89: #N/A | W89: #N/A | X89: #N/A | Y89: #N/A | Z89: #N/A | AA89: #N/A | AB89: #N/A | AC89: #N/A | AD89: #N/A | AE89: #N/A | AF89: #N/A | AG89: #N/A | AH89: #N/A | AI89: #N/A | AJ89: #N/A | AK89: #N/A | AL89: #N/A | AM89: #N/A | AN89: #N/A | AO89: #N/A | AP89: #N/A | AQ89: #N/A | AR89: #N/A | AS89: #N/A | AT89: #N/A | AU89: #N/A | AV89: #N/A | AW89: #N/A | AX89: #N/A | AY89: #N/A | AZ89: #N/A | BA89: #N/A | BB89: #N/A | BC89: #N/A | BD89: #N/A | BE89: #N/A | BF89: #N/A | BG89: #N/A | BH89: #N/A | BI89: #N/A | BJ89: #N/A | BK89: #N/A | BL89: #N/A | BM89: #N/A | BN89: #N/A | BO89: #N/A | BP89: #N/A | BQ89: #N/A | BR89: #N/A | BS89: #N/A | BT89: #N/A | BU89: #N/A | BV89: #N/A | BW89: #N/A | BX89: #N/A | BY89: #N/A | BZ89: #N/A | CA89: #N/A | CB89: #N/A | CC89: #N/A | CD89: #N/A | CE89: #N/A | CF89: 4.6 | CG89: 4.4 | CH89: 3.6 | CI89: 3.3 | CJ89: 3.1 | CK89: 2.5 | CL89: 2.1 | CM89: 2.1 | CN89: 1.9 | CO89: 1.9 | CP89: 1.7 | CQ89: 1.6 | CR89: 1.5
B90: 45323 | C90: UNPD241@UK | D90: UK: BoE CPI Projections Based on Expected Interest Rate: Mode [Q1-24](Y/Y % Chg) | E90: Q1-2024 | F90: Q1-2027 | G90: DISC | H90: Feb-01-2024 12:59 | I90: #N/A | J90: #N/A | K90: #N/A | L90: #N/A | M90: #N/A | N90: #N/A | O90: #N/A | P90: #N/A | Q90: #N/A | R90: #N/A | S90: #N/A | T90: #N/A | U90: #N/A | V90: #N/A | W90: #N/A | X90: #N/A | Y90: #N/A | Z90: #N/A | AA90: #N/A | AB90: #N/A | AC90: #N/A | AD90: #N/A | AE90: #N/A | AF90: #N/A | AG90: #N/A | AH90: #N/A | AI90: #N/A | AJ90: #N/A | AK90: #N/A | AL90: #N/A | AM90: #N/A | AN90: #N/A | AO90: #N/A | AP90: #N/A | AQ90: #N/A | AR90: #N/A | AS90: #N/A | AT90: #N/A | AU90: #N/A | AV90: #N/A | AW90: #N/A | AX90: #N/A | AY90: #N/A | AZ90: #N/A | BA90: #N/A | BB90: #N/A | BC90: #N/A | BD90: #N/A | BE90: #N/A | BF90: #N/A | BG90: #N/A | BH90: #N/A | BI90: #N/A | BJ90: #N/A | BK90: #N/A | BL90: #N/A | BM90: #N/A | BN90: #N/A | BO90: #N/A | BP90: #N/A | BQ90: #N/A | BR90: #N/A | BS90: #N/A | BT90: #N/A | BU90: #N/A | BV90: #N/A | BW90: #N/A | BX90: #N/A | BY90: #N/A | BZ90: #N/A | CA90: #N/A | CB90: #N/A | CC90: #N/A | CD90: #N/A | CE90: #N/A | CF90: #N/A | CG90: 3.6 | CH90: 2 | CI90: 2.2 | CJ90: 2.7 | CK90: 2.8 | CL90: 2.7 | CM90: 2.7 | CN90: 2.5 | CO90: 2.3 | CP90: 2.2 | CQ90: 2.1 | CR90: 2 | CS90: 1.9
B91: 45413 | C91: UNPD242@UK | D91: UK: BoE CPI Proj Based on Expected Interest Rate: Mode [Q2-24] (Y/Y % Chg) | E91: Q2-2024 | F91: Q2-2027 | G91: DISC | H91: May-09-2024 12:57 | I91: #N/A | J91: #N/A | K91: #N/A | L91: #N/A | M91: #N/A | N91: #N/A | O91: #N/A | P91: #N/A | Q91: #N/A | R91: #N/A | S91: #N/A | T91: #N/A | U91: #N/A | V91: #N/A | W91: #N/A | X91: #N/A | Y91: #N/A | Z91: #N/A | AA91: #N/A | AB91: #N/A | AC91: #N/A | AD91: #N/A | AE91: #N/A | AF91: #N/A | AG91: #N/A | AH91: #N/A | AI91: #N/A | AJ91: #N/A | AK91: #N/A | AL91: #N/A | AM91: #N/A | AN91: #N/A | AO91: #N/A | AP91: #N/A | AQ91: #N/A | AR91: #N/A | AS91: #N/A | AT91: #N/A | AU91: #N/A | AV91: #N/A | AW91: #N/A | AX91: #N/A | AY91: #N/A | AZ91: #N/A | BA91: #N/A | BB91: #N/A | BC91: #N/A | BD91: #N/A | BE91: #N/A | BF91: #N/A | BG91: #N/A | BH91: #N/A | BI91: #N/A | BJ91: #N/A | BK91: #N/A | BL91: #N/A | BM91: #N/A | BN91: #N/A | BO91: #N/A | BP91: #N/A | BQ91: #N/A | BR91: #N/A | BS91: #N/A | BT91: #N/A | BU91: #N/A | BV91: #N/A | BW91: #N/A | BX91: #N/A | BY91: #N/A | BZ91: #N/A | CA91: #N/A | CB91: #N/A | CC91: #N/A | CD91: #N/A | CE91: #N/A | CF91: #N/A | CG91: #N/A | CH91: 2 | CI91: 2.2 | CJ91: 2.6 | CK91: 2.6 | CL91: 2.6 | CM91: 2.5 | CN91: 2.3 | CO91: 2.1 | CP91: 1.9 | CQ91: 1.8 | CR91: 1.6 | CS91: 1.5 | CT91: 1.6
B92: 45505 | C92: UNPD243@UK | D92: UK: BoE CPI Projections Based on Exp Interest Rate: Mode [Q3-24] (Y/Y % Chg) | E92: Q3-2024 | F92: Q3-2027 | G92: DISC | H92: Aug-01-2024 13:36 | I92: #N/A | J92: #N/A | K92: #N/A | L92: #N/A | M92: #N/A | N92: #N/A | O92: #N/A | P92: #N/A | Q92: #N/A | R92: #N/A | S92: #N/A | T92: #N/A | U92: #N/A | V92: #N/A | W92: #N/A | X92: #N/A | Y92: #N/A | Z92: #N/A | AA92: #N/A | AB92: #N/A | AC92: #N/A | AD92: #N/A | AE92: #N/A | AF92: #N/A | AG92: #N/A | AH92: #N/A | AI92: #N/A | AJ92: #N/A | AK92: #N/A | AL92: #N/A | AM92: #N/A | AN92: #N/A | AO92: #N/A | AP92: #N/A | AQ92: #N/A | AR92: #N/A | AS92: #N/A | AT92: #N/A | AU92: #N/A | AV92: #N/A | AW92: #N/A | AX92: #N/A | AY92: #N/A | AZ92: #N/A | BA92: #N/A | BB92: #N/A | BC92: #N/A | BD92: #N/A | BE92: #N/A | BF92: #N/A | BG92: #N/A | BH92: #N/A | BI92: #N/A | BJ92: #N/A | BK92: #N/A | BL92: #N/A | BM92: #N/A | BN92: #N/A | BO92: #N/A | BP92: #N/A | BQ92: #N/A | BR92: #N/A | BS92: #N/A | BT92: #N/A | BU92: #N/A | BV92: #N/A | BW92: #N/A | BX92: #N/A | BY92: #N/A | BZ92: #N/A | CA92: #N/A | CB92: #N/A | CC92: #N/A | CD92: #N/A | CE92: #N/A | CF92: #N/A | CG92: #N/A | CH92: #N/A | CI92: 2.3 | CJ92: 2.7 | CK92: 2.7 | CL92: 2.6 | CM92: 2.4 | CN92: 2.2 | CO92: 2 | CP92: 1.7 | CQ92: 1.7 | CR92: 1.6 | CS92: 1.5 | CT92: 1.5 | CU92: 1.5
B93: 45597 | C93: UNPD244@UK | D93: UK: BoE CPI Projections Based on Expected Interest Rate: Mode [Q4-24](Y/Y % Chg) | E93: Q4-2024 | F93: Q4-2027 | G93: DISC | H93: Nov-07-2024 12:46 | I93: #N/A | J93: #N/A | K93: #N/A | L93: #N/A | M93: #N/A | N93: #N/A | O93: #N/A | P93: #N/A | Q93: #N/A | R93: #N/A | S93: #N/A | T93: #N/A | U93: #N/A | V93: #N/A | W93: #N/A | X93: #N/A | Y93: #N/A | Z93: #N/A | AA93: #N/A | AB93: #N/A | AC93: #N/A | AD93: #N/A | AE93: #N/A | AF93: #N/A | AG93: #N/A | AH93: #N/A | AI93: #N/A | AJ93: #N/A | AK93: #N/A | AL93: #N/A | AM93: #N/A | AN93: #N/A | AO93: #N/A | AP93: #N/A | AQ93: #N/A | AR93: #N/A | AS93: #N/A | AT93: #N/A | AU93: #N/A | AV93: #N/A | AW93: #N/A | AX93: #N/A | AY93: #N/A | AZ93: #N/A | BA93: #N/A | BB93: #N/A | BC93: #N/A | BD93: #N/A | BE93: #N/A | BF93: #N/A | BG93: #N/A | BH93: #N/A | BI93: #N/A | BJ93: #N/A | BK93: #N/A | BL93: #N/A | BM93: #N/A | BN93: #N/A | BO93: #N/A | BP93: #N/A | BQ93: #N/A | BR93: #N/A | BS93: #N/A | BT93: #N/A | BU93: #N/A | BV93: #N/A | BW93: #N/A | BX93: #N/A | BY93: #N/A | BZ93: #N/A | CA93: #N/A | CB93: #N/A | CC93: #N/A | CD93: #N/A | CE93: #N/A | CF93: #N/A | CG93: #N/A | CH93: #N/A | CI93: #N/A | CJ93: 2.4 | CK93: 2.4 | CL93: 2.6 | CM93: 2.8 | CN93: 2.7 | CO93: 2.6 | CP93: 2.4 | CQ93: 2.3 | CR93: 2.2 | CS93: 2.1 | CT93: 1.9 | CU93: 1.9 | CV93: 1.8
B94: 45689 | C94: UNPD@UK | D94: UK: BoE CPI Projections Based on Expected Interest Rate: Mode (Y/Y % Chg) | E94: Q1-2025 | F94: Q1-2028 | G94: BoE | H94: Feb-06-2025 12:03 | I94: #N/A | J94: #N/A | K94: #N/A | L94: #N/A | M94: #N/A | N94: #N/A | O94: #N/A | P94: #N/A | Q94: #N/A | R94: #N/A | S94: #N/A | T94: #N/A | U94: #N/A | V94: #N/A | W94: #N/A | X94: #N/A | Y94: #N/A | Z94: #N/A | AA94: #N/A | AB94: #N/A | AC94: #N/A | AD94: #N/A | AE94: #N/A | AF94: #N/A | AG94: #N/A | AH94: #N/A | AI94: #N/A | AJ94: #N/A | AK94: #N/A | AL94: #N/A | AM94: #N/A | AN94: #N/A | AO94: #N/A | AP94: #N/A | AQ94: #N/A | AR94: #N/A | AS94: #N/A | AT94: #N/A | AU94: #N/A | AV94: #N/A | AW94: #N/A | AX94: #N/A | AY94: #N/A | AZ94: #N/A | BA94: #N/A | BB94: #N/A | BC94: #N/A | BD94: #N/A | BE94: #N/A | BF94: #N/A | BG94: #N/A | BH94: #N/A | BI94: #N/A | BJ94: #N/A | BK94: #N/A | BL94: #N/A | BM94: #N/A | BN94: #N/A | BO94: #N/A | BP94: #N/A | BQ94: #N/A | BR94: #N/A | BS94: #N/A | BT94: #N/A | BU94: #N/A | BV94: #N/A | BW94: #N/A | BX94: #N/A | BY94: #N/A | BZ94: #N/A | CA94: #N/A | CB94: #N/A | CC94: #N/A | CD94: #N/A | CE94: #N/A | CF94: #N/A | CG94: #N/A | CH94: #N/A | CI94: #N/A | CJ94: #N/A | CK94: 2.8 | CL94: 3.5 | CM94: 3.7 | CN94: 3.5 | CO94: 3 | CP94: 2.6 | CQ94: 2.6 | CR94: 2.4 | CS94: 2.3 | CT94: 2.2 | CU94: 2.1 | CV94: 2 | CW94: 1.9
A95: Unemployment history | C95: MGSXQ@UK | D95: UK: LFS: Unemployment Rate: Aged 16 and Over (SA, %) | E95: Q1-1971 | F95: Q3-2024 | G95: ONS | H95: Dec-17-2024 07:20 | I95: 4.7 | J95: 4.8 | K95: 4.7 | L95: 5.1 | M95: 5.2 | N95: 5.5 | O95: 5.5 | P95: 5.5 | Q95: 5.5 | R95: 5.4 | S95: 5.3 | T95: 5.2 | U95: 5.2 | V95: 5.4 | W95: 5.9 | X95: 6.4 | Y95: 7.1 | Z95: 7.8 | AA95: 7.8 | AB95: 7.8 | AC95: 8 | AD95: 7.9 | AE95: 7.8 | AF95: 7.9 | AG95: 7.8 | AH95: 7.9 | AI95: 8.3 | AJ95: 8.4 | AK95: 8.2 | AL95: 8 | AM95: 7.8 | AN95: 7.8 | AO95: 7.8 | AP95: 7.7 | AQ95: 7.6 | AR95: 7.2 | AS95: 6.7 | AT95: 6.3 | AU95: 6 | AV95: 5.7 | AW95: 5.5 | AX95: 5.6 | AY95: 5.3 | AZ95: 5.1 | BA95: 5.1 | BB95: 4.9 | BC95: 4.8 | BD95: 4.7 | BE95: 4.6 | BF95: 4.4 | BG95: 4.3 | BH95: 4.4 | BI95: 4.2 | BJ95: 4 | BK95: 4.1 | BL95: 4 | BM95: 3.8 | BN95: 3.9 | BO95: 3.9 | BP95: 3.7 | BQ95: 4.1 | BR95: 4.1 | BS95: 5 | BT95: 5.3 | BU95: 4.9 | BV95: 4.7 | BW95: 4.4 | BX95: 4.2 | BY95: 3.8 | BZ95: 3.8 | CA95: 3.7 | CB95: 3.9 | CC95: 4 | CD95: 4.2 | CE95: 4.1 | CF95: 3.9 | CG95: 4.3 | CH95: 4.2 | CI95: 4.3
A96: Unemployment fcst | B96: 42856 | C96: UNUMD172@UK | D96: UK: BoE Proj Unemployment Rate Based on Expected Int Rate [Q2-17]: Mode (SA, %) | E96: Q1-2017 | F96: Q2-2020 | G96: DISC | H96: May-11-2017 13:48 | I96: #N/A | J96: #N/A | K96: #N/A | L96: #N/A | M96: #N/A | N96: #N/A | O96: #N/A | P96: #N/A | Q96: #N/A | R96: #N/A | S96: #N/A | T96: #N/A | U96: #N/A | V96: #N/A | W96: #N/A | X96: #N/A | Y96: #N/A | Z96: #N/A | AA96: #N/A | AB96: #N/A | AC96: #N/A | AD96: #N/A | AE96: #N/A | AF96: #N/A | AG96: #N/A | AH96: #N/A | AI96: #N/A | AJ96: #N/A | AK96: #N/A | AL96: #N/A | AM96: #N/A | AN96: #N/A | AO96: #N/A | AP96: #N/A | AQ96: #N/A | AR96: #N/A | AS96: #N/A | AT96: #N/A | AU96: #N/A | AV96: #N/A | AW96: #N/A | AX96: #N/A | AY96: #N/A | AZ96: #N/A | BA96: #N/A | BB96: #N/A | BC96: #N/A | BD96: #N/A | BE96: 4.7 | BF96: 4.7 | BG96: 4.7 | BH96: 4.7 | BI96: 4.7 | BJ96: 4.7 | BK96: 4.7 | BL96: 4.7 | BM96: 4.7 | BN96: 4.6 | BO96: 4.6 | BP96: 4.5 | BQ96: 4.5 | BR96: 4.5
B97: 42948 | C97: UNUMD173@UK | D97: UK: BoE Proj Unemployment Rate Based on Expected Int Rate [Q3-17]: Mode (SA, %) | E97: Q2-2017 | F97: Q3-2020 | G97: DISC | H97: Aug-03-2017 15:42 | I97: #N/A | J97: #N/A | K97: #N/A | L97: #N/A | M97: #N/A | N97: #N/A | O97: #N/A | P97: #N/A | Q97: #N/A | R97: #N/A | S97: #N/A | T97: #N/A | U97: #N/A | V97: #N/A | W97: #N/A | X97: #N/A | Y97: #N/A | Z97: #N/A | AA97: #N/A | AB97: #N/A | AC97: #N/A | AD97: #N/A | AE97: #N/A | AF97: #N/A | AG97: #N/A | AH97: #N/A | AI97: #N/A | AJ97: #N/A | AK97: #N/A | AL97: #N/A | AM97: #N/A | AN97: #N/A | AO97: #N/A | AP97: #N/A | AQ97: #N/A | AR97: #N/A | AS97: #N/A | AT97: #N/A | AU97: #N/A | AV97: #N/A | AW97: #N/A | AX97: #N/A | AY97: #N/A | AZ97: #N/A | BA97: #N/A | BB97: #N/A | BC97: #N/A | BD97: #N/A | BE97: #N/A | BF97: 4.4 | BG97: 4.4 | BH97: 4.4 | BI97: 4.5 | BJ97: 4.5 | BK97: 4.5 | BL97: 4.5 | BM97: 4.5 | BN97: 4.5 | BO97: 4.5 | BP97: 4.5 | BQ97: 4.4 | BR97: 4.4 | BS97: 4.4
B98: 43040 | C98: UNUMD174@UK | D98: UK: BoE Proj Unemployment Rate Based on Expected Int Rate [Q4-17]: Mode (SA, %) | E98: Q3-2017 | F98: Q4-2020 | G98: DISC | H98: Nov-02-2017 14:11 | I98: #N/A | J98: #N/A | K98: #N/A | L98: #N/A | M98: #N/A | N98: #N/A | O98: #N/A | P98: #N/A | Q98: #N/A | R98: #N/A | S98: #N/A | T98: #N/A | U98: #N/A | V98: #N/A | W98: #N/A | X98: #N/A | Y98: #N/A | Z98: #N/A | AA98: #N/A | AB98: #N/A | AC98: #N/A | AD98: #N/A | AE98: #N/A | AF98: #N/A | AG98: #N/A | AH98: #N/A | AI98: #N/A | AJ98: #N/A | AK98: #N/A | AL98: #N/A | AM98: #N/A | AN98: #N/A | AO98: #N/A | AP98: #N/A | AQ98: #N/A | AR98: #N/A | AS98: #N/A | AT98: #N/A | AU98: #N/A | AV98: #N/A | AW98: #N/A | AX98: #N/A | AY98: #N/A | AZ98: #N/A | BA98: #N/A | BB98: #N/A | BC98: #N/A | BD98: #N/A | BE98: #N/A | BF98: #N/A | BG98: 4.3 | BH98: 4.2 | BI98: 4.2 | BJ98: 4.2 | BK98: 4.2 | BL98: 4.2 | BM98: 4.2 | BN98: 4.2 | BO98: 4.2 | BP98: 4.2 | BQ98: 4.2 | BR98: 4.3 | BS98: 4.3 | BT98: 4.3
B99: 43132 | C99: UNUMD181@UK | D99: UK: BoE Proj Unemployment Rate Based on Expected Int Rate [Q1-18]: Mode (SA, %) | E99: Q4-2017 | F99: Q1-2021 | G99: DISC | H99: Feb-08-2018 15:57 | I99: #N/A | J99: #N/A | K99: #N/A | L99: #N/A | M99: #N/A | N99: #N/A | O99: #N/A | P99: #N/A | Q99: #N/A | R99: #N/A | S99: #N/A | T99: #N/A | U99: #N/A | V99: #N/A | W99: #N/A | X99: #N/A | Y99: #N/A | Z99: #N/A | AA99: #N/A | AB99: #N/A | AC99: #N/A | AD99: #N/A | AE99: #N/A | AF99: #N/A | AG99: #N/A | AH99: #N/A | AI99: #N/A | AJ99: #N/A | AK99: #N/A | AL99: #N/A | AM99: #N/A | AN99: #N/A | AO99: #N/A | AP99: #N/A | AQ99: #N/A | AR99: #N/A | AS99: #N/A | AT99: #N/A | AU99: #N/A | AV99: #N/A | AW99: #N/A | AX99: #N/A | AY99: #N/A | AZ99: #N/A | BA99: #N/A | BB99: #N/A | BC99: #N/A | BD99: #N/A | BE99: #N/A | BF99: #N/A | BG99: #N/A | BH99: 4.3 | BI99: 4.3 | BJ99: 4.2 | BK99: 4.2 | BL99: 4.2 | BM99: 4.2 | BN99: 4.2 | BO99: 4.1 | BP99: 4.1 | BQ99: 4.1 | BR99: 4.1 | BS99: 4.1 | BT99: 4.1 | BU99: 4.1
B100: 43221 | C100: UNUMD182@UK | D100: UK: BoE Proj Unemployment Rate Based on Expected Int Rate [Q2-18]: Mode (SA, %) | E100: Q1-2018 | F100: Q2-2021 | G100: DISC | H100: May-10-2018 15:03 | I100: #N/A | J100: #N/A | K100: #N/A | L100: #N/A | M100: #N/A | N100: #N/A | O100: #N/A | P100: #N/A | Q100: #N/A | R100: #N/A | S100: #N/A | T100: #N/A | U100: #N/A | V100: #N/A | W100: #N/A | X100: #N/A | Y100: #N/A | Z100: #N/A | AA100: #N/A | AB100: #N/A | AC100: #N/A | AD100: #N/A | AE100: #N/A | AF100: #N/A | AG100: #N/A | AH100: #N/A | AI100: #N/A | AJ100: #N/A | AK100: #N/A | AL100: #N/A | AM100: #N/A | AN100: #N/A | AO100: #N/A | AP100: #N/A | AQ100: #N/A | AR100: #N/A | AS100: #N/A | AT100: #N/A | AU100: #N/A | AV100: #N/A | AW100: #N/A | AX100: #N/A | AY100: #N/A | AZ100: #N/A | BA100: #N/A | BB100: #N/A | BC100: #N/A | BD100: #N/A | BE100: #N/A | BF100: #N/A | BG100: #N/A | BH100: #N/A | BI100: 4.2 | BJ100: 4.1 | BK100: 4.1 | BL100: 4.1 | BM100: 4 | BN100: 4 | BO100: 4 | BP100: 4 | BQ100: 4 | BR100: 4 | BS100: 4 | BT100: 4 | BU100: 4 | BV100: 4
...

Sheet HAVERW
A1: 20200101W !W | B1: M112B9R9@INTWKLY | C1: M112B9T9@INTWKLY | D1: M112ZJ5J@INTWKLY | E1: M112B9T8@INTWKLY
A2: .DESC | B2: UK: Central Bank Reserves Supplied via Asset Purchase Facility(EOP,NSA, Mil.GBP) | C2: UK: Asset Purchase Facility: Gilt Holdings(EOP, NSA, Mil.GBP) | D2: UK: Asset Purchase Facility: Weekly Holdings of Corporate Bonds (EOP, Mil.GBP) | E2: UK: Asset Purchase Facility: Weekly Purchases of Gilts(NSA, Mil.GBP)
A3: .T1 | B3: 11-Mar-2009W | C3: 11-Mar-2009W | D3: 05-Oct-2016W | E3: 11-Mar-2009W
A4: .TN | B4: 29-Jan-2025W | C4: 29-Jan-2025W | D4: 29-Jan-2025W | E4: 29-Jan-2025W
A5: .LSOURCE | B5: Bank of England | C5: Bank of England | D5: Bank of England | E5: Bank of England
A6: .DTLM | B6: Jan-31-2025 10:01 | C6: Jan-31-2025 10:01 | D6: Jan-31-2025 10:01 | E6: Jan-31-2025 10:01
A7: 20200101W | B7: 444810 | C7: 434990 | D7: 9820 | E7: 0
A8: 20200108W | B8: 444810 | C8: 434990 | D8: 9820 | E8: 0
A9: 20200115W | B9: 444810 | C9: 434990 | D9: 9820 | E9: 0
A10: 20200122W | B10: 444810 | C10: 434990 | D10: 9820 | E10: 0
A11: 20200129W | B11: 444810 | C11: 434990 | D11: 9820 | E11: 0
A12: 20200205W | B12: 444810 | C12: 434990 | D12: 9820 | E12: 0
A13: 20200212W | B13: 444810 | C13: 434990 | D13: 9820 | E13: 0
A14: 20200219W | B14: 444810 | C14: 434990 | D14: 9820 | E14: 0
A15: 20200226W | B15: 444810 | C15: 434990 | D15: 9820 | E15: 0
A16: 20200304W | B16: 444810 | C16: 434990 | D16: 9820 | E16: 0
A17: 20200311W | B17: 444810 | C17: 420432 | D17: 9820 | E17: 0
A18: 20200318W | B18: 444810 | C18: 423344 | D18: 9820 | E18: 2912
... A272: 20250129W | B272: 651734 | C272: 651734 | D272: 0 | E272: 0

Sheet OE_FCST
A1: Location | B1: Indicator | C1: Scenario | D1: Units | E1: Scale | F1: Measurement | G1: 1973 Q1 | H1: 1973 Q2 | I1: 1973 Q3 | J1: 1973 Q4 | K1: 1974 Q1 | L1: 1974 Q2 | M1: 1974 Q3 | N1: 1974 Q4 | O1: 1975 Q1 | P1: 1975 Q2 | Q1: 1975 Q3 | R1: 1975 Q4 | S1: 1976 Q1 | T1: 1976 Q2 | U1: 1976 Q3 | V1: 1976 Q4 | W1: 1977 Q1 | X1: 1977 Q2 | Y1: 1977 Q3 | Z1: 1977 Q4 | AA1: 1978 Q1 | AB1: 1978 Q2 | AC1: 1978 Q3 | AD1: 1978 Q4 | AE1: 1979 Q1 | AF1: 1979 Q2 | AG1: 1979 Q3 | AH1: 1979 Q4 | AI1: 1980 Q1 | AJ1: 1980 Q2 | AK1: 1980 Q3 | AL1: 1980 Q4 | AM1: 1981 Q1 | AN1: 1981 Q2 | AO1: 1981 Q3 | AP1: 1981 Q4 | AQ1: 1982 Q1 | AR1: 1982 Q2 | AS1: 1982 Q3 | AT1: 1982 Q4 | AU1: 1983 Q1 | AV1: 1983 Q2 | AW1: 1983 Q3 | AX1: 1983 Q4 | AY1: 1984 Q1 | AZ1: 1984 Q2 | BA1: 1984 Q3 | BB1: 1984 Q4 | BC1: 1985 Q1 | BD1: 1985 Q2 | BE1: 1985 Q3 | BF1: 1985 Q4 | BG1: 1986 Q1 | BH1: 1986 Q2 | BI1: 1986 Q3 | BJ1: 1986 Q4 | BK1: 1987 Q1 | BL1: 1987 Q2 | BM1: 1987 Q3 | BN1: 1987 Q4 | BO1: 1988 Q1 | BP1: 1988 Q2 | BQ1: 1988 Q3 | BR1: 1988 Q4 | BS1: 1989 Q1 | BT1: 1989 Q2 | BU1: 1989 Q3 | BV1: 1989 Q4 | BW1: 1990 Q1 | BX1: 1990 Q2 | BY1: 1990 Q3 | BZ1: 1990 Q4 | CA1: 1991 Q1 | CB1: 1991 Q2 | CC1: 1991 Q3 | CD1: 1991 Q4 | CE1: 1992 Q1 | CF1: 1992 Q2 | CG1: 1992 Q3 | CH1: 1992 Q4 | CI1: 1993 Q1 | CJ1: 1993 Q2 | CK1: 1993 Q3 | CL1: 1993 Q4 | CM1: 1994 Q1 | CN1: 1994 Q2 | CO1: 1994 Q3 | CP1: 1994 Q4 | CQ1: 1995 Q1 | CR1: 1995 Q2 | CS1: 1995 Q3 | CT1: 1995 Q4 | CU1: 1996 Q1 | CV1: 1996 Q2 | CW1: 1996 Q3 | CX1: 1996 Q4 | CY1: 1997 Q1 | CZ1: 1997 Q2 | DA1: 1997 Q3 | DB1: 1997 Q4 | DC1: 1998 Q1 | DD1: 1998 Q2 | DE1: 1998 Q3 | DF1: 1998 Q4 | DG1: 1999 Q1 | DH1: 1999 Q2 | DI1: 1999 Q3 | DJ1: 1999 Q4 | DK1: 2000 Q1 | DL1: 2000 Q2 | DM1: 2000 Q3 | DN1: 2000 Q4 | DO1: 2001 Q1 | DP1: 2001 Q2 | DQ1: 2001 Q3 | DR1: 2001 Q4 | DS1: 2002 Q1 | DT1: 2002 Q2 | DU1: 2002 Q3 | DV1: 2002 Q4 | DW1: 2003 Q1 | DX1: 2003 Q2 | DY1: 2003 Q3 | DZ1: 2003 Q4 | EA1: 2004 Q1 | EB1: 2004 Q2 | EC1: 2004 Q3 | ED1: 2004 Q4 | EE1: 2005 Q1 | EF1: 2005 Q2 | EG1: 2005 Q3 | EH1: 2005 Q4 | EI1: 2006 Q1 | EJ1: 2006 Q2 | EK1: 2006 Q3 | EL1: 2006 Q4 | EM1: 2007 Q1 | EN1: 2007 Q2 | EO1: 2007 Q3 | EP1: 2007 Q4 | EQ1: 2008 Q1 | ER1: 2008 Q2 | ES1: 2008 Q3 | ET1: 2008 Q4 | EU1: 2009 Q1 | EV1: 2009 Q2 | EW1: 2009 Q3 | EX1: 2009 Q4 | EY1: 2010 Q1 | EZ1: 2010 Q2 | FA1: 2010 Q3 | FB1: 2010 Q4 | FC1: 2011 Q1 | FD1: 2011 Q2 | FE1: 2011 Q3 | FF1: 2011 Q4 | FG1: 2012 Q1 | FH1: 2012 Q2 | FI1: 2012 Q3 | FJ1: 2012 Q4 | FK1: 2013 Q1 | FL1: 2013 Q2 | FM1: 2013 Q3 | FN1: 2013 Q4 | FO1: 2014 Q1 | FP1: 2014 Q2 | FQ1: 2014 Q3 | FR1: 2014 Q4 | FS1: 2015 Q1 | FT1: 2015 Q2 | FU1: 2015 Q3 | FV1: 2015 Q4 | FW1: 2016 Q1 | FX1: 2016 Q2 | FY1: 2016 Q3 | FZ1: 2016 Q4 | GA1: 2017 Q1 | GB1: 2017 Q2 | GC1: 2017 Q3 | GD1: 2017 Q4 | GE1: 2018 Q1 | GF1: 2018 Q2 | GG1: 2018 Q3 | GH1: 2018 Q4 | GI1: 2019 Q1 | GJ1: 2019 Q2 | GK1: 2019 Q3 | GL1: 2019 Q4 | GM1: 2020 Q1 | GN1: 2020 Q2 | GO1: 2020 Q3 | GP1: 2020 Q4 | GQ1: 2021 Q1 | GR1: 2021 Q2 | GS1: 2021 Q3 | GT1: 2021 Q4 | GU1: 2022 Q1 | GV1: 2022 Q2 | GW1: 2022 Q3 | GX1: 2022 Q4 | GY1: 2023 Q1 | GZ1: 2023 Q2 | HA1: 2023 Q3 | HB1: 2023 Q4 | HC1: 2024 Q1 | HD1: 2024 Q2 | HE1: 2024 Q3 | HF1: 2024 Q4 | HG1: 2025 Q1 | HH1: 2025 Q2 | HI1: 2025 Q3 | HJ1: 2025 Q4 | HK1: 2026 Q1 | HL1: 2026 Q2 | HM1: 2026 Q3 | HN1: 2026 Q4 | HO1: 2027 Q1 | HP1: 2027 Q2 | HQ1: 2027 Q3 | HR1: 2027 Q4 | HS1: 2028 Q1 | HT1: 2028 Q2 | HU1: 2028 Q3 | HV1: 2028 Q4 | HW1: 2029 Q1 | HX1: 2029 Q2 | HY1: 2029 Q3 | HZ1: 2029 Q4 | IA1: 2030 Q1 | IB1: 2030 Q2 | IC1: 2030 Q3 | ID1: 2030 Q4 | IE1: 2031 Q1 | IF1: 2031 Q2 | IG1: 2031 Q3 | IH1: 2031 Q4 | II1: 2032 Q1 | IJ1: 2032 Q2 | IK1: 2032 Q3 | IL1: 2032 Q4 | IM1: 2033 Q1 | IN1: 2033 Q2 | IO1: 2033 Q3 | IP1: 2033 Q4 | IQ1: 2034 Q1 | IR1: 2034 Q2 | IS1: 2034 Q3 | IT1: 2034 Q4 | IU1: 2035 Q1 | IV1: 2035 Q2 | IW1: 2035 Q3 | IX1: 2035 Q4 | IY1: 2036 Q1 | IZ1: 2036 Q2 | JA1: 2036 Q3 | JB1: 2036 Q4 | JC1: 2037 Q1 | JD1: 2037 Q2 | JE1: 2037 Q3 | JF1: 2037 Q4 | JG1: 2038 Q1 | JH1: 2038 Q2 | JI1: 2038 Q3 | JJ1: 2038 Q4 | JK1: 2039 Q1 | JL1: 2039 Q2 | JM1: 2039 Q3 | JN1: 2039 Q4 | JO1: 2040 Q1 | JP1: 2040 Q2 | JQ1: 2040 Q3 | JR1: 2040 Q4 | JS1: 2041 Q1 | JT1: 2041 Q2 | JU1: 2041 Q3 | JV1: 2041 Q4 | JW1: 2042 Q1 | JX1: 2042 Q2 | JY1: 2042 Q3 | JZ1: 2042 Q4 | KA1: 2043 Q1 | KB1: 2043 Q2 | KC1: 2043 Q3 | KD1: 2043 Q4 | KE1: 2044 Q1 | KF1: 2044 Q2 | KG1: 2044 Q3 | KH1: 2044 Q4 | KI1: 2045 Q1 | KJ1: 2045 Q2 | KK1: 2045 Q3 | KL1: 2045 Q4 | KM1: 2046 Q1 | KN1: 2046 Q2 | KO1: 2046 Q3 | KP1: 2046 Q4 | KQ1: 2047 Q1 | KR1: 2047 Q2 | KS1: 2047 Q3 | KT1: 2047 Q4 | KU1: 2048 Q1 | KV1: 2048 Q2 | KW1: 2048 Q3 | KX1: 2048 Q4 | KY1: 2049 Q1 | KZ1: 2049 Q2 | LA1: 2049 Q3 | LB1: 2049 Q4 | LC1: 2050 Q1 | LD1: 2050 Q2 | LE1: 2050 Q3 | LF1: 2050 Q4 | LG1: Source | LH1: Seasonally adjusted | LI1: Base year price | LJ1: Base year index | LK1: Historical end year | LL1: Historical end quarter | LM1: Date of last update | LN1: Source details | LO1: Additional source details | LP1: Location code | LQ1: Indicator code | LR1: Databank code
A2: United Kingdom | B2: GDP, real, LCU | C2: FEB005A | D2: Pound | E2: Millions: chained 2022 prices | F2: Level | G2: 247921 | H2: 248384 | I2: 246082 | J2: 245140 | K2: 238319 | L2: 241752 | M2: 243197 | N2: 239612 | O2: 239702 | P2: 235807 | Q2: 235105 | R2: 237747 | S2: 241709 | T2: 241380 | U2: 244367 | V2: 249511 | W2: 249671 | X2: 247936 | Y2: 249578 | Z2: 253819 | AA2: 256193 | AB2: 259127 | AC2: 262661 | AD2: 264972 | AE2: 264185 | AF2: 275695 | AG2: 269599 | AH2: 272359 | AI2: 269776 | AJ2: 264448 | AK2: 264139 | AL2: 261297 | AM2: 261131 | AN2: 261739 | AO2: 264602 | AP2: 264902 | AQ2: 265408 | AR2: 268196 | AS2: 268798 | AT2: 270653 | AU2: 275877 | AV2: 277790 | AW2: 280996 | AX2: 283096 | AY2: 285469 | AZ2: 282605 | BA2: 284676 | BB2: 289829 | BC2: 292612 | BD2: 298873 | BE2: 298814 | BF2: 298979 | BG2: 302117 | BH2: 304797 | BI2: 306708 | BJ2: 312615 | BK2: 314804 | BL2: 319478 | BM2: 327346 | BN2: 331075 | BO2: 336442 | BP2: 338186 | BQ2: 342414 | BR2: 345162 | BS2: 346836 | BT2: 348997 | BU2: 349572 | BV2: 349523 | BW2: 351299 | BX2: 353663 | BY2: 349780 | BZ2: 348006 | CA2: 346292 | CB2: 345892 | CC2: 345216 | CD2: 345643 | CE2: 345523 | CF2: 344987 | CG2: 346628 | CH2: 349299 | CI2: 351046 | CJ2: 352612 | CK2: 355841 | CL2: 358264 | CM2: 361793 | CN2: 365109 | CO2: 368798 | CP2: 370401 | CQ2: 372307 | CR2: 373090 | CS2: 377249 | CT2: 378442 | CU2: 380976 | CV2: 382146 | CW2: 385671 | CX2: 391053 | CY2: 397303 | CZ2: 401790 | DA2: 405233 | DB2: 411352 | DC2: 414377 | DD2: 416909 | DE2: 418294 | DF2: 421074 | DG2: 423875 | DH2: 425920 | DI2: 432860 | DJ2: 439093 | DK2: 444540 | DL2: 447825 | DM2: 450688 | DN2: 453447 | DO2: 457680 | DP2: 459620 | DQ2: 462016 | DR2: 463404 | DS2: 464698 | DT2: 466935 | DU2: 470277 | DV2: 473899 | DW2: 477357 | DX2: 481552 | DY2: 485973 | DZ2: 490059 | EA2: 492014 | EB2: 494824 | EC2: 496642 | ED2: 499020 | EE2: 502702 | EF2: 506906 | EG2: 511132 | EH2: 515935 | EI2: 518495 | EJ2: 520318 | EK2: 521780 | EL2: 524569 | EM2: 529398 | EN2: 533187 | EO2: 537052 | EP2: 540258 | EQ2: 542804 | ER2: 539918 | ES2: 531619 | ET2: 520230 | EU2: 509646 | EV2: 508009 | EW2: 508398 | EX2: 509889 | EY2: 514595 | EZ2: 520128 | FA2: 523173 | FB2: 523515 | FC2: 524955 | FD2: 525418 | FE2: 527034 | FF2: 527698 | FG2: 532300 | FH2: 531663 | FI2: 536720 | FJ2: 536188 | FK2: 537974 | FL2: 541586 | FM2: 546064 | FN2: 549709 | FO2: 554183 | FP2: 559331 | FQ2: 563694 | FR2: 567619 | FS2: 569150 | FT2: 572673 | FU2: 574836 | FV2: 578068 | FW2: 580110 | FX2: 583383 | FY2: 585856 | FZ2: 589476 | GA2: 594423 | GB2: 598176 | GC2: 601961 | GD2: 606396 | GE2: 606785 | GF2: 607775 | GG2: 609653 | GH2: 610481 | GI2: 614936 | GJ2: 616853 | GK2: 621227 | GL2: 621229 | GM2: 604719 | GN2: 481769 | GO2: 562648 | GP2: 570338 | GQ2: 564411 | GR2: 605353 | GS2: 615459 | GT2: 624592 | GU2: 629149 | GV2: 631258 | GW2: 631977 | GX2: 634044 | GY2: 634807 | GZ2: 634866 | HA2: 634052 | HB2: 632365 | HC2: 637023 | HD2: 639269 | HE2: 639452 | HF2: 639398.6 | HG2: 641817.3 | HH2: 644084.1 | HI2: 646341.9 | HJ2: 648754.2 | HK2: 651446.9 | HL2: 653890.7 | HM2: 656571.8 | HN2: 659296.1 | HO2: 662065.3 | HP2: 664978.7 | HQ2: 668004.1 | HR2: 671010.1 | HS2: 674029.7 | HT2: 677096.4 | HU2: 680109.5 | HV2: 683000.1 | HW2: 685766.1 | HX2: 688474.9 | HY2: 691160 | HZ2: 693924.6 | IA2: 696700.3 | IB2: 699487.1 | IC2: 702285.1 | ID2: 705094.2 | IE2: 707914.6 | IF2: 710746.2 | IG2: 713553.7 | IH2: 716336.5 | II2: 719130.3 | IJ2: 721934.9 | IK2: 724822.6 | IL2: 727649.4 | IM2: 730617.4 | IN2: 733494.5 | IO2: 736368.1 | IP2: 739136.4 | IQ2: 742023.6 | IR2: 744839.3 | IS2: 747631.9 | IT2: 750411.9 | IU2: 753290 | IV2: 756177.8 | IW2: 759074.8 | IX2: 761980.9 | IY2: 764962.4 | IZ2: 767956.6 | JA2: 770963.5 | JB2: 773983.1 | JC2: 777015.3 | JD2: 780059.9 | JE2: 783117.4 | JF2: 786187.8 | JG2: 789336.6 | JH2: 792499.1 | JI2: 795676.1 | JJ2: 798867.8 | JK2: 802073.9 | JL2: 805294.5 | JM2: 808529.8 | JN2: 811780.1 | JO2: 815045.2 | JP2: 818323.7 | JQ2: 821615.8 | JR2: 824921.4 | JS2: 828312.9 | JT2: 831719.3 | JU2: 835149.1 | JV2: 838593.9 | JW2: 842053.5 | JX2: 845527.9 | JY2: 848945.8 | JZ2: 852377.5 | KA2: 855822.6 | KB2: 859281.5 | KC2: 862666.9 | KD2: 866064.1 | KE2: 869472.9 | KF2: 872893.5 | KG2: 876165.3 | KH2: 879446.1 | KI2: 882736 | KJ2: 886035 | KK2: 889267.7 | KL2: 892508.3 | KM2: 895756.9 | KN2: 899013.4 | KO2: 902274.5 | KP2: 905543.5 | KQ2: 908820.6 | KR2: 912106.1 | KS2: 915345.3 | KT2: 918591.8 | KU2: 921846.1 | KV2: 925107.8 | KW2: 928353.8 | KX2: 931606.9 | KY2: 934867.1 | KZ2: 938134.6 | LA2: 941335.1 | LB2: 944541.6 | LC2: 947753.8 | LD2: 950970.9 | LE2: 954168.9 | LF2: 957371.6 | LG2: Office for National Statistics\Haver Analytics | LH2: TRUE | LI2: chained 2022 | LJ2: NA | LK2: 2024 | LL2: 3 | LM2: 45693 | LN2: ABMIQ@UK | LO2: U.K.: Real Gross Domestic Product (SA, Mil.Chn.2022.GBP) | LP2: GBR | LQ2: GDP | LR2: Desktop
A3: United Kingdom | B3: Consumer price index | C3: FEB005A | D3: Index | E3: 2015=100 | F3: Level | G3: 11.88749 | H3: 12.3046 | I3: 12.51315 | J3: 13.00846 | K3: 13.47771 | L3: 14.23371 | M3: 14.57261 | N3: 15.2504 | O3: 16.05854 | P3: 17.46627 | Q3: 18.22228 | R3: 18.84793 | S3: 19.42145 | T3: 20.12532 | U3: 20.59456 | V3: 21.50698 | W3: 22.47153 | X3: 23.41002 | Y3: 23.82713 | Z3: 24.13995 | AA3: 24.45278 | AB3: 25.07844 | AC3: 25.46948 | AD3: 25.86051 | AE3: 26.43403 | AF3: 27.26824 | AG3: 28.91059 | AH3: 29.71873 | AI3: 30.60508 | AJ3: 32.24743 | AK3: 32.9513 | AL3: 33.55088 | AM3: 34.3851 | AN3: 36.07959 | AO3: 36.73131 | AP3: 37.43518 | AQ3: 37.87835 | AR3: 39.1818 | AS3: 39.41642 | AT3: 39.88567 | AU3: 40.17243 | AV3: 40.85022 | AW3: 41.2934 | AX3: 41.76264 | AY3: 41.86692 | AZ3: 42.77934 | BA3: 42.98789 | BB3: 43.43106 | BC3: 43.87423 | BD3: 44.9952 | BE3: 45.12555 | BF3: 45.49052 | BG3: 45.64693 | BH3: 46.3508 | BI3: 46.53328 | BJ3: 46.92432 | BK3: 47.23714 | BL3: 47.83673 | BM3: 47.88887 | BN3: 48.43632 | BO3: 48.56667 | BP3: 49.5 | BQ3: 49.9 | BR3: 50.46667 | BS3: 51 | BT3: 52.13334 | BU3: 52.46667 | BV3: 53.26667 | BW3: 53.93333 | BX3: 55.6 | BY3: 56.4 | BZ3: 57.46667 | CA3: 57.66667 | CB3: 60.26667 | CC3: 60.83333 | CD3: 61.46667 | CE3: 61.7 | CF3: 62.83333 | CG3: 62.73333 | CH3: 63.13334 | CI3: 63.2 | CJ3: 64.43333 | CK3: 64.5 | CL3: 64.66666 | CM3: 64.76667 | CN3: 65.7 | CO3: 65.63333 | CP3: 65.8 | CQ3: 66.33334 | CR3: 67.26667 | CS3: 67.4 | CT3: 67.73333 | CU3: 68.1 | CV3: 68.86667 | CW3: 68.93333 | CX3: 69.36667 | CY3: 69.36667 | CZ3: 70 | DA3: 70.26667 | DB3: 70.63333 | DC3: 70.5 | DD3: 71.26667 | DE3: 71.23333 | DF3: 71.63333 | DG3: 71.6 | DH3: 72.3 | DI3: 72.13333 | DJ3: 72.43333 | DK3: 72.13333 | DL3: 72.76667 | DM3: 72.7 | DN3: 73.16666 | DO3: 72.76667 | DP3: 73.83334 | DQ3: 73.86667 | DR3: 73.9 | DS3: 73.86667 | DT3: 74.53333 | DU3: 74.6 | DV3: 75 | DW3: 75 | DX3: 75.46667 | DY3: 75.6 | DZ3: 76.03333 | EA3: 75.96667 | EB3: 76.53333 | EC3: 76.56667 | ED3: 77.1 | EE3: 77.23333 | EF3: 78 | EG3: 78.4 | EH3: 78.76667 | EI3: 78.73333 | EJ3: 79.8 | EK3: 80.3 | EL3: 80.9 | EM3: 81 | EN3: 81.8 | EO3: 81.73333 | EP3: 82.6 | EQ3: 82.93333 | ER3: 84.6 | ES3: 85.63333 | ET3: 85.73333 | EU3: 85.43333 | EV3: 86.36667 | EW3: 86.93333 | EX3: 87.56667 | EY3: 88.23333 | EZ3: 89.36667 | FA3: 89.63333 | FB3: 90.5 | FC3: 91.83334 | FD3: 93.3 | FE3: 93.83334 | FF3: 94.73333 | FG3: 95.03333 | FH3: 95.8 | FI3: 96.06667 | FJ3: 97.26667 | FK3: 97.66666 | FL3: 98.36667 | FM3: 98.7 | FN3: 99.3 | FO3: 99.4 | FP3: 100.1 | FQ3: 100.1333 | FR3: 100.2 | FS3: 99.5 | FT3: 100.0667 | FU3: 100.1667 | FV3: 100.3 | FW3: 99.83334 | FX3: 100.4 | FY3: 100.8667 | FZ3: 101.5 | GA3: 102 | GB3: 103.1667 | GC3: 103.7 | GD3: 104.5667 | GE3: 104.7667 | GF3: 105.6667 | GG3: 106.3 | GH3: 106.9333 | GI3: 106.7 | GJ3: 107.8 | GK3: 108.2667 | GL3: 108.4333 | GM3: 108.4667 | GN3: 108.5333 | GO3: 108.9333 | GP3: 109.0667 | GQ3: 109.1667 | GR3: 110.7333 | GS3: 111.9333 | GT3: 114.4 | GU3: 115.9333 | GV3: 120.8667 | GW3: 123.1333 | GX3: 126.7 | GY3: 127.7333 | GZ3: 131.0667 | HA3: 131.4 | HB3: 131.9667 | HC3: 132.2667 | HD3: 133.8333 | HE3: 134.1 | HF3: 135.2333 | HG3: 135.874 | HH3: 137.7908 | HI3: 138.7452 | HJ3: 139.7932 | HK3: 140.0939 | HL3: 141.3723 | HM3: 141.932 | HN3: 142.6169 | HO3: 142.9446 | HP3: 144.2437 | HQ3: 144.8656 | HR3: 145.5947 | HS3: 145.9732 | HT3: 147.323 | HU3: 147.9987 | HV3: 148.7628 | HW3: 149.0875 | HX3: 150.4123 | HY3: 151.0648 | HZ3: 151.7929 | IA3: 152.0897 | IB3: 153.4171 | IC3: 154.0774 | ID3: 154.8027 | IE3: 155.0981 | IF3: 156.4522 | IG3: 157.1337 | IH3: 157.8554 | II3: 158.1546 | IJ3: 159.5466 | IK3: 160.2596 | IL3: 160.9878 | IM3: 161.2934 | IN3: 162.7203 | IO3: 163.4623 | IP3: 164.1932 | IQ3: 164.5025 | IR3: 165.9637 | IS3: 166.735 | IT3: 167.4676 | IU3: 167.7803 | IV3: 169.2771 | IW3: 170.0795 | IX3: 170.8135 | IY3: 171.1358 | IZ3: 172.6626 | JA3: 173.4811 | JB3: 174.2298 | JC3: 174.5586 | JD3: 176.1158 | JE3: 176.9507 | JF3: 177.7144 | JG3: 178.0497 | JH3: 179.6382 | JI3: 180.4897 | JJ3: 181.2687 | JK3: 181.6107 | JL3: 183.2309 | JM3: 184.0995 | JN3: 184.8941 | JO3: 185.243 | JP3: 186.8955 | JQ3: 187.7815 | JR3: 188.5919 | JS3: 188.9478 | JT3: 190.6335 | JU3: 191.5371 | JV3: 192.3638 | JW3: 192.7268 | JX3: 194.4461 | JY3: 195.3679 | JZ3: 196.2111 | KA3: 196.5813 | KB3: 198.3351 | KC3: 199.2752 | KD3: 200.1353 | KE3: 200.5129 | KF3: 202.3017 | KG3: 203.2607 | KH3: 204.138 | KI3: 204.5232 | KJ3: 206.3478 | KK3: 207.3259 | KL3: 208.2207 | KM3: 208.6136 | KN3: 210.4747 | KO3: 211.4725 | KP3: 212.3852 | KQ3: 212.7859 | KR3: 214.6842 | KS3: 215.7019 | KT3: 216.6329 | KU3: 217.0416 | KV3: 218.9779 | KW3: 220.0159 | KX3: 220.9655 | KY3: 221.3825 | KZ3: 223.3575 | LA3: 224.4163 | LB3: 225.3848 | LC3: 225.8101 | LD3: 227.8246 | LE3: 228.9046 | LF3: 229.8925 | LG3: Office for National Statistics\Haver Analytics | LH3: FALSE | LI3: NA | LJ3: 2015 | LK3: 2024 | LL3: 4 | LM3: 45693 | LN3: D7BT@UK | LO3: UK: Consumer Price Index: All Items (NSA, 2015=100) | LP3: GBR | LQ3: CPI | LR3: Desktop
A4: United Kingdom | B4: Unemployment rate, ILO definition | C4: FEB005A | D4: % | E4: NA | F4: Level | G4: 3.9 | H4: 3.7 | I4: 3.6 | J4: 3.4 | K4: 3.6 | L4: 3.6 | M4: 3.7 | N4: 3.7 | O4: 4 | P4: 4.3 | Q4: 4.7 | R4: 5 | S4: 5.3 | T4: 5.4 | U4: 5.5 | V4: 5.5 | W4: 5.5 | X4: 5.5 | Y4: 5.7 | Z4: 5.7 | AA4: 5.6 | AB4: 5.6 | AC4: 5.5 | AD4: 5.4 | AE4: 5.4 | AF4: 5.3 | AG4: 5.4 | AH4: 5.5 | AI4: 5.8 | AJ4: 6.3 | AK4: 7.1 | AL4: 8 | AM4: 8.9 | AN4: 9.6 | AO4: 9.9 | AP4: 10.2 | AQ4: 10.4 | AR4: 10.6 | AS4: 10.8 | AT4: 11.1 | AU4: 11.3 | AV4: 11.4 | AW4: 11.5 | AX4: 11.7 | AY4: 11.8 | AZ4: 11.9 | BA4: 11.7 | BB4: 11.6 | BC4: 11.5 | BD4: 11.4 | BE4: 11.3 | BF4: 11.3 | BG4: 11.3 | BH4: 11.3 | BI4: 11.4 | BJ4: 11.3 | BK4: 11.1 | BL4: 10.7 | BM4: 10.2 | BN4: 9.7 | BO4: 9.2 | BP4: 8.7 | BQ4: 8.4 | BR4: 8 | BS4: 7.6 | BT4: 7.2 | BU4: 7.1 | BV4: 7 | BW4: 6.9 | BX4: 6.9 | BY4: 7.1 | BZ4: 7.5 | CA4: 8 | CB4: 8.7 | CC4: 9.2 | CD4: 9.5 | CE4: 9.7 | CF4: 9.8 | CG4: 9.9 | CH4: 10.4 | CI4: 10.6 | CJ4: 10.4 | CK4: 10.2 | CL4: 10.3 | CM4: 9.9 | CN4: 9.7 | CO4: 9.4 | CP4: 9 | CQ4: 8.9 | CR4: 8.7 | CS4: 8.6 | CT4: 8.3 | CU4: 8.2 | CV4: 8.3 | CW4: 8.1 | CX4: 7.8 | CY4: 7.3 | CZ4: 7.2 | DA4: 6.8 | DB4: 6.5 | DC4: 6.4 | DD4: 6.3 | DE4: 6.2 | DF4: 6.1 | DG4: 6.2 | DH4: 6 | DI4: 5.9 | DJ4: 5.8 | DK4: 5.8 | DL4: 5.5 | DM4: 5.3 | DN4: 5.2 | DO4: 5.1 | DP4: 5 | DQ4: 5.1 | DR4: 5.2 | DS4: 5.2 | DT4: 5.2 | DU4: 5.3 | DV4: 5.1 | DW4: 5.2 | DX4: 4.9 | DY4: 5 | DZ4: 4.9 | EA4: 4.8 | EB4: 4.8 | EC4: 4.7 | ED4: 4.7 | EE4: 4.7 | EF4: 4.8 | EG4: 4.7 | EH4: 5.1 | EI4: 5.2 | EJ4: 5.5 | EK4: 5.5 | EL4: 5.5 | EM4: 5.5 | EN4: 5.4 | EO4: 5.3 | EP4: 5.2 | EQ4: 5.2 | ER4: 5.4 | ES4: 5.9 | ET4: 6.4 | EU4: 7.1 | EV4: 7.8 | EW4: 7.8 | EX4: 7.8 | EY4: 8 | EZ4: 7.9 | FA4: 7.8 | FB4: 7.9 | FC4: 7.8 | FD4: 7.9 | FE4: 8.3 | FF4: 8.4 | FG4: 8.2 | FH4: 8 | FI4: 7.8 | FJ4: 7.8 | FK4: 7.8 | FL4: 7.7 | FM4: 7.6 | FN4: 7.2 | FO4: 6.7 | FP4: 6.3 | FQ4: 6 | FR4: 5.7 | FS4: 5.5 | FT4: 5.6 | FU4: 5.3 | FV4: 5.1 | FW4: 5.1 | FX4: 4.9 | FY4: 4.8 | FZ4: 4.7 | GA4: 4.6 | GB4: 4.4 | GC4: 4.3 | GD4: 4.4 | GE4: 4.2 | GF4: 4 | GG4: 4.1 | GH4: 4 | GI4: 3.8 | GJ4: 3.9 | GK4: 3.9 | GL4: 3.7 | GM4: 4.1 | GN4: 4.1 | GO4: 5 | GP4: 5.3 | GQ4: 4.9 | GR4: 4.7 | GS4: 4.4 | GT4: 4.2 | GU4: 3.8 | GV4: 3.8 | GW4: 3.7 | GX4: 3.9 | GY4: 4 | GZ4: 4.2 | HA4: 4.1 | HB4: 3.9 | HC4: 4.3 | HD4: 4.2 | HE4: 4.3 | HF4: 4.408384 | HG4: 4.492019 | HH4: 4.502507 | HI4: 4.512015 | HJ4: 4.502531 | HK4: 4.483452 | HL4: 4.473944 | HM4: 4.459678 | HN4: 4.435829 | HO4: 4.404385 | HP4: 4.356714 | HQ4: 4.301379 | HR4: 4.251255 | HS4: 4.201129 | HT4: 4.150939 | HU4: 4.1175 | HV4: 4.08869 | HW4: 4.069581 | HX4: 4.059995 | HY4: 4.050409 | HZ4: 4.038916 | IA4: 4.029231 | IB4: 4.019672 | IC4: 4.010084 | ID4: 4.000039 | IE4: 4.000022 | IF4: 4.000028 | IG4: 4.000031 | IH4: 4.00004 | II4: 4.000034 | IJ4: 4.000052 | IK4: 4.000034 | IL4: 4.000029 | IM4: 4.000023 | IN4: 4.000022 | IO4: 4.00003 | IP4: 4.000037 | IQ4: 4.000028 | IR4: 4.000044 | IS4: 4.00004 | IT4: 3.999995 | IU4: 4.000005 | IV4: 4.000014 | IW4: 4.000024 | IX4: 4.000003 | IY4: 3.999984 | IZ4: 3.999994 | JA4: 3.999983 | JB4: 3.999993 | JC4: 4.000002 | JD4: 4.000012 | JE4: 3.999992 | JF4: 4.000001 | JG4: 4.00001 | JH4: 4.000021 | JI4: 4.00001 | JJ4: 4.00002 | JK4: 3.999999 | JL4: 4.000009 | JM4: 3.99999 | JN4: 3.999999 | JO4: 3.999989 | JP4: 3.999999 | JQ4: 4.000008 | JR4: 3.999988 | JS4: 3.999989 | JT4: 4.000019 | JU4: 4.000004 | JV4: 3.999998 | JW4: 4.000011 | JX4: 4.000015 | JY4: 4.000006 | JZ4: 3.999997 | KA4: 4.000007 | KB4: 4.000007 | KC4: 4.000001 | KD4: 3.999995 | KE4: 4 | KF4: 3.999994 | KG4: 4 | KH4: 4.000007 | KI4: 4.000014 | KJ4: 3.999992 | KK4: 4 | KL4: 4.000017 | KM4: 3.999995 | KN4: 3.999985 | KO4: 3.999998 | KP4: 4.000004 | KQ4: 3.99999 | KR4: 4.000004 | KS4: 4.00001 | KT4: 3.999997 | KU4: 4.000011 | KV4: 3.999999 | KW4: 4.000005 | KX4: 4.000001 | KY4: 4.000007 | KZ4: 4.000003 | LA4: 4.000003 | LB4: 4.000013 | LC4: 4.000004 | LD4: 4.000004 | LE4: 3.999997 | LF4: 4.000008 | LG4: Office for National Statistics\Haver Analytics | LH4: TRUE | LI4: NA | LJ4: NA | LK4: 2024 | LL4: 3 | LM4: 45693 | LN4: MGSXQ@UK | LO4: UK: LFS: Unemployment Rate: Aged 16 and Over (SA, %) | LP4: GBR | LQ4: UPILO | LR4: Desktop
A5: United Kingdom | B5: Interest rate, central bank policy, end of period | C5: FEB005A | D5: % | E5: NA | F5: Level | G5: 8.5 | H5: 7.5 | I5: 11.5 | J5: 13 | K5: 12.5 | L5: 11.75 | M5: 11.5 | N5: 11.5 | O5: 10 | P5: 10 | Q5: 11 | R5: 11.25 | S5: 9 | T5: 11.5 | U5: 13 | V5: 14.25 | W5: 9.5 | X5: 8 | Y5: 6 | Z5: 7 | AA5: 6.5 | AB5: 10 | AC5: 10 | AD5: 12.5 | AE5: 13 | AF5: 14 | AG5: 14 | AH5: 17 | AI5: 17 | AJ5: 17 | AK5: 16 | AL5: 14 | AM5: 12 | AN5: 12 | AO5: 14 | AP5: 14.375 | AQ5: 13.25 | AR5: 12.625 | AS5: 10.125 | AT5: 10 | AU5: 10.5625 | AV5: 9.5625 | AW5: 9.5625 | AX5: 9.0625 | AY5: 8.5625 | AZ5: 8.875 | BA5: 10.5 | BB5: 9.5 | BC5: 12.875 | BD5: 12.375 | BE5: 11.375 | BF5: 11.375 | BG5: 11.375 | BH5: 9.875 | BI5: 9.875 | BJ5: 10.875 | BK5: 9.875 | BL5: 8.875 | BM5: 9.875 | BN5: 8.375 | BO5: 8.375 | BP5: 8.875 | BQ5: 11.875 | BR5: 12.875 | BS5: 12.875 | BT5: 13.75 | BU5: 13.75 | BV5: 14.875 | BW5: 14.875 | BX5: 14.875 | BY5: 14.875 | BZ5: 13.875 | CA5: 12.375 | CB5: 11.375 | CC5: 10.375 | CD5: 10.375 | CE5: 10.375 | CF5: 9.875 | CG5: 8.875 | CH5: 6.875 | CI5: 5.875 | CJ5: 5.875 | CK5: 5.875 | CL5: 5.375 | CM5: 5.125 | CN5: 5.125 | CO5: 5.625 | CP5: 6.125 | CQ5: 6.625 | CR5: 6.625 | CS5: 6.625 | CT5: 6.375 | CU5: 5.9375 | CV5: 5.6875 | CW5: 5.6875 | CX5: 5.9375 | CY5: 5.9375 | CZ5: 6.5 | DA5: 7 | DB5: 7.25 | DC5: 7.25 | DD5: 7.5 | DE5: 7.5 | DF5: 6.25 | DG5: 5.5 | DH5: 5 | DI5: 5.25 | DJ5: 5.5 | DK5: 6 | DL5: 6 | DM5: 6 | DN5: 6 | DO5: 5.75 | DP5: 5.25 | DQ5: 4.75 | DR5: 4 | DS5: 4 | DT5: 4 | DU5: 4 | DV5: 4 | DW5: 3.75 | DX5: 3.75 | DY5: 3.5 | DZ5: 3.75 | EA5: 4 | EB5: 4.5 | EC5: 4.75 | ED5: 4.75 | EE5: 4.75 | EF5: 4.75 | EG5: 4.5 | EH5: 4.5 | EI5: 4.5 | EJ5: 4.5 | EK5: 4.75 | EL5: 5 | EM5: 5.25 | EN5: 5.5 | EO5: 5.75 | EP5: 5.5 | EQ5: 5.25 | ER5: 5 | ES5: 5 | ET5: 2 | EU5: 0.5 | EV5: 0.5 | EW5: 0.5 | EX5: 0.5 | EY5: 0.5 | EZ5: 0.5 | FA5: 0.5 | FB5: 0.5 | FC5: 0.5 | FD5: 0.5 | FE5: 0.5 | FF5: 0.5 | FG5: 0.5 | FH5: 0.5 | FI5: 0.5 | FJ5: 0.5 | FK5: 0.5 | FL5: 0.5 | FM5: 0.5 | FN5: 0.5 | FO5: 0.5 | FP5: 0.5 | FQ5: 0.5 | FR5: 0.5 | FS5: 0.5 | FT5: 0.5 | FU5: 0.5 | FV5: 0.5 | FW5: 0.5 | FX5: 0.5 | FY5: 0.25 | FZ5: 0.25 | GA5: 0.25 | GB5: 0.25 | GC5: 0.25 | GD5: 0.5 | GE5: 0.5 | GF5: 0.5 | GG5: 0.75 | GH5: 0.75 | GI5: 0.75 | GJ5: 0.75 | GK5: 0.75 | GL5: 0.75 | GM5: 0.1 | GN5: 0.1 | GO5: 0.1 | GP5: 0.1 | GQ5: 0.1 | GR5: 0.1 | GS5: 0.1 | GT5: 0.25 | GU5: 0.75 | GV5: 1.25 | GW5: 2.25 | GX5: 3.5 | GY5: 4.25 | GZ5: 5 | HA5: 5.25 | HB5: 5.25 | HC5: 5.25 | HD5: 5.25 | HE5: 5 | HF5: 4.75 | HG5: 4.5 | HH5: 4.25 | HI5: 4 | HJ5: 3.75 | HK5: 3.5 | HL5: 3.25 | HM5: 3.25 | HN5: 3 | HO5: 3 | HP5: 2.75 | HQ5: 2.75 | HR5: 2.5 | HS5: 2.5 | HT5: 2.5 | HU5: 2.5 | HV5: 2.5 | HW5: 2.5 | HX5: 2.5 | HY5: 2.5 | HZ5: 2.5 | IA5: 2.5 | IB5: 2.5 | IC5: 2.5 | ID5: 2.5 | IE5: 2.5 | IF5: 2.5 | IG5: 2.5 | IH5: 2.5 | II5: 2.5 | IJ5: 2.5 | IK5: 2.5 | IL5: 2.5 | IM5: 2.5 | IN5: 2.5 | IO5: 2.5 | IP5: 2.5 | IQ5: 2.5 | IR5: 2.5 | IS5: 2.5 | IT5: 2.5 | IU5: 2.5 | IV5: 2.5 | IW5: 2.5 | IX5: 2.5 | IY5: 2.5 | IZ5: 2.5 | JA5: 2.5 | JB5: 2.5 | JC5: 2.5 | JD5: 2.5 | JE5: 2.5 | JF5: 2.5 | JG5: 2.5 | JH5: 2.5 | JI5: 2.5 | JJ5: 2.5 | JK5: 2.5 | JL5: 2.5 | JM5: 2.5 | JN5: 2.5 | JO5: 2.5 | JP5: 2.5 | JQ5: 2.5 | JR5: 2.5 | JS5: 2.5 | JT5: 2.5 | JU5: 2.5 | JV5: 2.5 | JW5: 2.5 | JX5: 2.5 | JY5: 2.5 | JZ5: 2.5 | KA5: 2.5 | KB5: 2.5 | KC5: 2.5 | KD5: 2.5 | KE5: 2.5 | KF5: 2.5 | KG5: 2.5 | KH5: 2.5 | KI5: 2.5 | KJ5: 2.5 | KK5: 2.5 | KL5: 2.5 | KM5: 2.5 | KN5: 2.5 | KO5: 2.5 | KP5: 2.5 | KQ5: 2.5 | KR5: 2.5 | KS5: 2.5 | KT5: 2.5 | KU5: 2.5 | KV5: 2.5 | KW5: 2.5 | KX5: 2.5 | KY5: 2.5 | KZ5: 2.5 | LA5: 2.5 | LB5: 2.5 | LC5: 2.5 | LD5: 2.5 | LE5: 2.5 | LF5: 2.5 | LG5: Bank of England \Haver Analytics | LH5: FALSE | LI5: NA | LJ5: NA | LK5: 2024 | LL5: 4 | LM5: 45693 | LN5: agg(R112RD@INTDAILY,EOP) | LO5: United Kingdom: Official Bank Rate (%) ,EOP | LP5: GBR | LQ5: RCBEOP | LR5: Desktop

Sheet CHARTS>>>>

Sheet NOT USED>>>>
