Workbook
Name _DLX1.INC: HAVERM!$A$1:$AG$6
Name Data: [1]sheet0!$C$2

Sheet >> CHARTS

Sheet >> DATA

Sheet Chart Data
A1: Quoted mortgage rates | H1: Margins | Q1: Diff vs expiring deal | U1: Interest rates | Z1: Interest rates - change since Bank Rate started to rise | AF1: Interest rates
A2: End-date: | B2: =HAVERM!B4 -> Jun-2025 | C2: =HAVERM!C4 -> Jun-2025 | D2: =HAVERM!D4 -> Jun-2025 | Q2: Standard variable rate * | R2: 2 year fix, 75% LTV ** | S2: 5 year fix, 75% LTV ** | V2: =HAVERM!E4 -> Jun-2025 <- 10-Jul-2025 | W2: =HAVERM!H4 -> May-2025 | X2: =HAVERM!I4 -> May-2025
B3: Standard variable rate | C3: 2 year fix, 75% LTV | D3: 5 year fix, 75% LTV | E3: 2yr | F3: 5yr | H3: Standard variable rate | I3: 2 year fix, 75% LTV | J3: 5 year fix, 75% LTV | L3: Bank Rate | M3: 2 year swap | N3: 5 year swap | Q3: Standard variable rate | R3: 2 year fix, 75% LTV | S3: 5 year fix, 75% LTV | V3: Bank Rate | W3: Non-financial corporations | X3: Secured household | AA3: Companies | AB3: Household mortgages | AC3: Hiking cycle | AD3: Cutting cycle | AG3: Secured household | AH3: Non-financial corporations
A4: 41640 | B4: =HAVERM!B295 -> 4.41 | C4: =HAVERM!C295 -> 2.37 | D4: =HAVERM!D295 -> 3.34 | H4: =B4-L4 -> 3.91 | I4: =C4-M4 -> #N/A | J4: =D4-N4 -> #N/A | L4: =HAVERM!E295 -> 0.5 | M4: =HAVERM!F295 -> #N/A | N4: =HAVERM!G295 -> #N/A | P4: 41640 | U4: 43466 | V4: =HAVERM!E355 -> 0.75 | W4: =HAVERM!H355 -> 3.35 | X4: =HAVERM!I355 -> 2.48 | Z4: 44531 | AA4: =W39-W$38 -> 0.05 | AB4: =X39-X$38 -> -0.01 | AC4: 1000 | AF4: 43466 | AG4: =Data!G191 -> 2.463333 | AH4: =Data!H191 -> 3.343333
A5: 41671 | B5: =HAVERM!B296 -> 4.43 | C5: =HAVERM!C296 -> 2.38 | D5: =HAVERM!D296 -> 3.45 | H5: =B5-L5 -> 3.93 | I5: =C5-M5 -> #N/A | J5: =D5-N5 -> #N/A | L5: =HAVERM!E296 -> 0.5 | M5: =HAVERM!F296 -> #N/A | N5: =HAVERM!G296 -> #N/A | P5: 41671 | U5: 43497 | V5: =HAVERM!E356 -> 0.75 | W5: =HAVERM!H356 -> 3.34 | X5: =HAVERM!I356 -> 2.46 | Z5: 44562 | AA5: =W40-W$38 -> 0.11 | AB5: =X40-X$38 -> -0.01 | AC5: 1000 | AF5: 43556 | AG5: =Data!G192 -> 2.436667 | AH5: =Data!H192 -> 3.323333
A6: 41699 | B6: =HAVERM!B297 -> 4.43 | C6: =HAVERM!C297 -> 2.37 | D6: =HAVERM!D297 -> 3.48 | H6: =B6-L6 -> 3.93 | I6: =C6-M6 -> #N/A | J6: =D6-N6 -> #N/A | L6: =HAVERM!E297 -> 0.5 | M6: =HAVERM!F297 -> #N/A | N6: =HAVERM!G297 -> #N/A | P6: 41699 | U6: 43525 | V6: =HAVERM!E357 -> 0.75 | W6: =HAVERM!H357 -> 3.34 | X6: =HAVERM!I357 -> 2.45 | Z6: 44593 | AA6: =W41-W$38 -> 0.25 | AB6: =X41-X$38 -> 0 | AC6: 1000 | AF6: 43647 | AG6: =Data!G193 -> 2.413333 | AH6: =Data!H193 -> 3.28
A7: 41730 | B7: =HAVERM!B298 -> 4.43 | C7: =HAVERM!C298 -> 2.54 | D7: =HAVERM!D298 -> 3.69 | H7: =B7-L7 -> 3.93 | I7: =C7-M7 -> #N/A | J7: =D7-N7 -> #N/A | L7: =HAVERM!E298 -> 0.5 | M7: =HAVERM!F298 -> #N/A | N7: =HAVERM!G298 -> #N/A | P7: 41730 | U7: 43556 | V7: =HAVERM!E358 -> 0.75 | W7: =HAVERM!H358 -> 3.34 | X7: =HAVERM!I358 -> 2.45 | Z7: 44621 | AA7: =W42-W$38 -> 0.35 | AB7: =X42-X$38 -> 0.03 | AC7: 1000 | AF7: 43739 | AG7: =Data!G194 -> 2.386667 | AH7: =Data!H194 -> 3.26
A8: 41760 | B8: =HAVERM!B299 -> 4.42 | C8: =HAVERM!C299 -> 2.56 | D8: =HAVERM!D299 -> 3.72 | H8: =B8-L8 -> 3.92 | I8: =C8-M8 -> #N/A | J8: =D8-N8 -> #N/A | L8: =HAVERM!E299 -> 0.5 | M8: =HAVERM!F299 -> #N/A | N8: =HAVERM!G299 -> #N/A | P8: 41760 | U8: 43586 | V8: =HAVERM!E359 -> 0.75 | W8: =HAVERM!H359 -> 3.32 | X8: =HAVERM!I359 -> 2.43 | Z8: 44652 | AA8: =W43-W$38 -> 0.45 | AB8: =X43-X$38 -> 0.03 | AC8: 1000 | AF8: 43831 | AG8: =Data!G195 -> 2.356667 | AH8: =Data!H195 -> 3.266667
A9: 41791 | B9: =HAVERM!B300 -> 4.36 | C9: =HAVERM!C300 -> 2.6 | D9: =HAVERM!D300 -> 3.69 | H9: =B9-L9 -> 3.86 | I9: =C9-M9 -> #N/A | J9: =D9-N9 -> #N/A | L9: =HAVERM!E300 -> 0.5 | M9: =HAVERM!F300 -> #N/A | N9: =HAVERM!G300 -> #N/A | P9: 41791 | U9: 43617 | V9: =HAVERM!E360 -> 0.75 | W9: =HAVERM!H360 -> 3.31 | X9: =HAVERM!I360 -> 2.43 | Z9: 44682 | AA9: =W44-W$38 -> 0.65 | AB9: =X44-X$38 -> 0.06 | AC9: 1000 | AF9: 43922 | AG9: =Data!G196 -> 2.183333 | AH9: =Data!H196 -> 2.876667
A10: 41821 | B10: =HAVERM!B301 -> 4.45 | C10: =HAVERM!C301 -> 2.54 | D10: =HAVERM!D301 -> 3.78 | H10: =B10-L10 -> 3.95 | I10: =C10-M10 -> #N/A | J10: =D10-N10 -> #N/A | L10: =HAVERM!E301 -> 0.5 | M10: =HAVERM!F301 -> #N/A | N10: =HAVERM!G301 -> #N/A | P10: 41821 | U10: 43647 | V10: =HAVERM!E361 -> 0.75 | W10: =HAVERM!H361 -> 3.3 | X10: =HAVERM!I361 -> 2.42 | Z10: 44713 | AA10: =W45-W$38 -> 0.78 | AB10: =X45-X$38 -> 0.1 | AC10: 1000 | AF10: 44013 | AG10: =Data!G197 -> 2.143333 | AH10: =Data!H197 -> 2.57
A11: 41852 | B11: =HAVERM!B302 -> 4.45 | C11: =HAVERM!C302 -> 2.54 | D11: =HAVERM!D302 -> 3.76 | H11: =B11-L11 -> 3.95 | I11: =C11-M11 -> 1.5588 | J11: =D11-N11 -> 2.15 | L11: =HAVERM!E302 -> 0.5 | M11: =HAVERM!F302 -> 0.9812 | N11: =HAVERM!G302 -> 1.61 | P11: 41852 | U11: 43678 | V11: =HAVERM!E362 -> 0.75 | W11: =HAVERM!H362 -> 3.27 | X11: =HAVERM!I362 -> 2.42 | Z11: 44743 | AA11: =W46-W$38 -> 0.86 | AB11: =X46-X$38 -> 0.11 | AC11: 1000 | AF11: 44105 | AG11: =Data!G198 -> 2.12 | AH11: =Data!H198 -> 2.453333
A12: 41883 | B12: =HAVERM!B303 -> 4.52 | C12: =HAVERM!C303 -> 2.46 | D12: =HAVERM!D303 -> 3.61 | H12: =B12-L12 -> 4.02 | I12: =C12-M12 -> 1.4812727 | J12: =D12-N12 -> 1.9375955 | L12: =HAVERM!E303 -> 0.5 | M12: =HAVERM!F303 -> 0.97872727 | N12: =HAVERM!G303 -> 1.6724045 | P12: 41883 | U12: 43709 | V12: =HAVERM!E363 -> 0.75 | W12: =HAVERM!H363 -> 3.27 | X12: =HAVERM!I363 -> 2.4 | Z12: 44774 | AA12: =W47-W$38 -> 1.17 | AB12: =X47-X$38 -> 0.16 | AC12: 1000 | AF12: 44197 | AG12: =Data!G199 -> 2.09 | AH12: =Data!H199 -> 2.426667
A13: 41913 | B13: =HAVERM!B304 -> 4.53 | C13: =HAVERM!C304 -> 2.21 | D13: =HAVERM!D304 -> 3.27 | H13: =B13-L13 -> 4.03 | I13: =C13-M13 -> 1.3656522 | J13: =D13-N13 -> 1.8341696 | L13: =HAVERM!E304 -> 0.5 | M13: =HAVERM!F304 -> 0.84434783 | N13: =HAVERM!G304 -> 1.4358304 | P13: 41913 | U13: 43739 | V13: =HAVERM!E364 -> 0.75 | W13: =HAVERM!H364 -> 3.26 | X13: =HAVERM!I364 -> 2.39 | Z13: 44805 | AA13: =W48-W$38 -> 1.38 | AB13: =X48-X$38 -> 0.23 | AC13: 1000 | AF13: 44287 | AG13: =Data!G200 -> 2.073333 | AH13: =Data!H200 -> 2.49
A14: 41944 | B14: =HAVERM!B305 -> 4.49 | C14: =HAVERM!C305 -> 2.17 | D14: =HAVERM!D305 -> 3.21 | H14: =B14-L14 -> 3.99 | I14: =C14-M14 -> 1.4026833 | J14: =D14-N14 -> 1.8787167 | L14: =HAVERM!E305 -> 0.5 | M14: =HAVERM!F305 -> 0.76731667 | N14: =HAVERM!G305 -> 1.3312833 | P14: 41944 | U14: 43770 | V14: =HAVERM!E365 -> 0.75 | W14: =HAVERM!H365 -> 3.24 | X14: =HAVERM!I365 -> 2.4 | Z14: 44835 | AA14: =W49-W$38 -> 1.63 | AB14: =X49-X$38 -> 0.27 | AC14: 1000 | AF14: 44378 | AG14: =Data!G201 -> 2.053333 | AH14: =Data!H201 -> 2.616667
A15: 41974 | B15: =HAVERM!B306 -> 4.48 | C15: =HAVERM!C306 -> 2.08 | D15: =HAVERM!D306 -> 3.21 | H15: =B15-L15 -> 3.98 | I15: =C15-M15 -> 1.3790636 | J15: =D15-N15 -> 2.0094227 | L15: =HAVERM!E306 -> 0.5 | M15: =HAVERM!F306 -> 0.70093636 | N15: =HAVERM!G306 -> 1.2005773 | P15: 41974 | U15: 43800 | V15: =HAVERM!E366 -> 0.75 | W15: =HAVERM!H366 -> 3.28 | X15: =HAVERM!I366 -> 2.37 | Z15: 44866 | AA15: =W50-W$38 -> 2.12 | AB15: =X50-X$38 -> 0.37 | AC15: 1000 | AF15: 44470 | AG15: =Data!G202 -> 2.02 | AH15: =Data!H202 -> 2.703333
A16: 42005 | B16: =HAVERM!B307 -> 4.56 | C16: =HAVERM!C307 -> 2.01 | D16: =HAVERM!D307 -> 3.09 | H16: =B16-L16 -> 4.06 | I16: =C16-M16 -> 1.4174286 | J16: =D16-N16 -> 2.1329952 | L16: =HAVERM!E307 -> 0.5 | M16: =HAVERM!F307 -> 0.59257143 | N16: =HAVERM!G307 -> 0.95700476 | P16: 42005 | Q16: =B16-B4 -> 0.15 | U16: 43831 | V16: =HAVERM!E367 -> 0.75 | W16: =HAVERM!H367 -> 3.29 | X16: =HAVERM!I367 -> 2.37 | Z16: 44896 | AA16: =W51-W$38 -> 2.44 | AB16: =X51-X$38 -> 0.49 | AC16: 1000 | AF16: 44562 | AG16: =Data!G203 -> 2.026667 | AH16: =Data!H203 -> 2.936667
A17: 42036 | B17: =HAVERM!B308 -> 4.51 | C17: =HAVERM!C308 -> 1.96 | D17: =HAVERM!D308 -> 3.05 | H17: =B17-L17 -> 4.01 | I17: =C17-M17 -> 1.280755 | J17: =D17-N17 -> 1.92882 | L17: =HAVERM!E308 -> 0.5 | M17: =HAVERM!F308 -> 0.679245 | N17: =HAVERM!G308 -> 1.12118 | P17: 42036 | Q17: =B17-B5 -> 0.08 | U17: 43862 | V17: =HAVERM!E368 -> 0.75 | W17: =HAVERM!H368 -> 3.3 | X17: =HAVERM!I368 -> 2.37 | Z17: 44927 | AA17: =W52-W$38 -> 2.6 | AB17: =X52-X$38 -> 0.53 | AC17: 1000 | AF17: 44652 | AG17: =Data!G204 -> 2.083333 | AH17: =Data!H204 -> 3.326667
A18: 42064 | B18: =HAVERM!B309 -> 4.51 | C18: =HAVERM!C309 -> 1.99 | D18: =HAVERM!D309 -> 2.98 | H18: =B18-L18 -> 4.01 | I18: =C18-M18 -> 1.3028524 | J18: =D18-N18 -> 1.8285952 | L18: =HAVERM!E309 -> 0.5 | M18: =HAVERM!F309 -> 0.68714762 | N18: =HAVERM!G309 -> 1.1514048 | P18: 42064 | Q18: =B18-B6 -> 0.08 | U18: 43891 | V18: =HAVERM!E369 -> 0.34772727 | W18: =HAVERM!H369 -> 3.21 | X18: =HAVERM!I369 -> 2.33 | Z18: 44958 | AA18: =W53-W$38 -> 2.95 | AB18: =X53-X$38 -> 0.63 | AC18: 1000 | AF18: 44743 | AG18: =Data!G205 -> 2.186667 | AH18: =Data!H205 -> 3.836667
A19: 42095 | B19: =HAVERM!B310 -> 4.53 | C19: =HAVERM!C310 -> 1.95 | D19: =HAVERM!D310 -> 2.92 | H19: =B19-L19 -> 4.03 | I19: =C19-M19 -> 1.3036476 | J19: =D19-N19 -> 1.8594333 | L19: =HAVERM!E310 -> 0.5 | M19: =HAVERM!F310 -> 0.64635238 | N19: =HAVERM!G310 -> 1.0605667 | P19: 42095 | Q19: =B19-B7 -> 0.1 | U19: 43922 | V19: =HAVERM!E370 -> 0.1 | W19: =HAVERM!H370 -> 2.98 | X19: =HAVERM!I370 -> 2.21 | Z19: 44986 | AA19: =W54-W$38 -> 3.09 | AB19: =X54-X$38 -> 0.73 | AC19: 1000 | AF19: 44835 | AG19: =Data!G206 -> 2.396667 | AH19: =Data!H206 -> 4.763333
A20: 42125 | B20: =HAVERM!B311 -> 4.55 | C20: =HAVERM!C311 -> 1.9 | D20: =HAVERM!D311 -> 2.86 | H20: =B20-L20 -> 4.05 | I20: =C20-M20 -> 1.1638524 | J20: =D20-N20 -> 1.5970476 | L20: =HAVERM!E311 -> 0.5 | M20: =HAVERM!F311 -> 0.73614762 | N20: =HAVERM!G311 -> 1.2629524 | P20: 42125 | Q20: =B20-B8 -> 0.13 | U20: 43952 | V20: =HAVERM!E371 -> 0.1 | W20: =HAVERM!H371 -> 2.86 | X20: =HAVERM!I371 -> 2.17 | Z20: 45017 | AA20: =W55-W$38 -> 3.21 | AB20: =X55-X$38 -> 0.74 | AC20: 1000 | AF20: 44927 | AG20: =Data!G207 -> 2.65 | AH20: =Data!H207 -> 5.58
A21: 42156 | B21: =HAVERM!B312 -> 4.49 | C21: =HAVERM!C312 -> 1.83 | D21: =HAVERM!D312 -> 2.82 | H21: =B21-L21 -> 3.99 | I21: =C21-M21 -> 1.0497955 | J21: =D21-N21 -> 1.4679636 | L21: =HAVERM!E312 -> 0.5 | M21: =HAVERM!F312 -> 0.78020455 | N21: =HAVERM!G312 -> 1.3520364 | P21: 42156 | Q21: =B21-B9 -> 0.13 | U21: 43983 | V21: =HAVERM!E372 -> 0.1 | W21: =HAVERM!H372 -> 2.79 | X21: =HAVERM!I372 -> 2.17 | Z21: 45047 | AA21: =W56-W$38 -> 3.34 | AB21: =X56-X$38 -> 0.81 | AC21: 1000 | AF21: 45017 | AG21: =Data!G208 -> 2.84 | AH21: =Data!H208 -> 6.09
A22: 42186 | B22: =HAVERM!B313 -> 4.5 | C22: =HAVERM!C313 -> 1.87 | D22: =HAVERM!D313 -> 2.83 | H22: =B22-L22 -> 4 | I22: =C22-M22 -> 1.0242609 | J22: =D22-N22 -> 1.422013 | L22: =HAVERM!E313 -> 0.5 | M22: =HAVERM!F313 -> 0.84573913 | N22: =HAVERM!G313 -> 1.407987 | P22: 42186 | Q22: =B22-B10 -> 0.05 | U22: 44013 | V22: =HAVERM!E373 -> 0.1 | W22: =HAVERM!H373 -> 2.66 | X22: =HAVERM!I373 -> 2.16 | Z22: 45078 | AA22: =W57-W$38 -> 3.62 | AB22: =X57-X$38 -> 0.91 | AC22: 1000 | AF22: 45108 | AG22: =Data!G209 -> 3.07 | AH22: =Data!H209 -> 6.676667
A23: 42217 | B23: =HAVERM!B314 -> 4.48 | C23: =HAVERM!C314 -> 1.95 | D23: =HAVERM!D314 -> 2.92 | H23: =B23-L23 -> 3.98 | I23: =C23-M23 -> 1.1439048 | J23: =D23-N23 -> 1.5978381 | L23: =HAVERM!E314 -> 0.5 | M23: =HAVERM!F314 -> 0.80609524 | N23: =HAVERM!G314 -> 1.3221619 | P23: 42217 | Q23: =B23-B11 -> 0.03 | U23: 44044 | V23: =HAVERM!E374 -> 0.1 | W23: =HAVERM!H374 -> 2.53 | X23: =HAVERM!I374 -> 2.14 | Z23: 45108 | AA23: =W58-W$38 -> 3.81 | AB23: =X58-X$38 -> 0.96 | AC23: 1000 | AF23: 45200 | AG23: =Data!G210 -> 3.29 | AH23: =Data!H210 -> 6.8
A24: 42248 | B24: =HAVERM!B315 -> 4.5 | C24: =HAVERM!C315 -> 1.91 | D24: =HAVERM!D315 -> 2.84 | H24: =B24-L24 -> 4 | I24: =C24-M24 -> 1.1834227 | J24: =D24-N24 -> 1.6508136 | L24: =HAVERM!E315 -> 0.5 | M24: =HAVERM!F315 -> 0.72657727 | N24: =HAVERM!G315 -> 1.1891864 | P24: 42248 | Q24: =B24-B12 -> -0.02 | U24: 44075 | V24: =HAVERM!E375 -> 0.1 | W24: =HAVERM!H375 -> 2.52 | X24: =HAVERM!I375 -> 2.13 | Z24: 45139 | AA24: =W59-W$38 -> 4.01 | AB24: =X59-X$38 -> 1.05 | AC24: 1000 | AF24: 45292 | AG24: =Data!G211 -> 3.473333 | AH24: =Data!H211 -> 6.856667
A25: 42278 | B25: =HAVERM!B316 -> 4.54 | C25: =HAVERM!C316 -> 1.87 | D25: =HAVERM!D316 -> 2.78 | H25: =B25-L25 -> 4.04 | I25: =C25-M25 -> 1.2124818 | J25: =D25-N25 -> 1.6863545 | L25: =HAVERM!E316 -> 0.5 | M25: =HAVERM!F316 -> 0.65751818 | N25: =HAVERM!G316 -> 1.0936455 | P25: 42278 | Q25: =B25-B13 -> 0.01 | U25: 44105 | V25: =HAVERM!E376 -> 0.1 | W25: =HAVERM!H376 -> 2.46 | X25: =HAVERM!I376 -> 2.12 | Z25: 45170 | AA25: =W60-W$38 -> 4.11 | AB25: =X60-X$38 -> 1.14 | AF25: 45383 | AG25: =Data!G212 -> 3.62 | AH25: =Data!H212 -> 6.89
A26: 42309 | B26: =HAVERM!B317 -> 4.49 | C26: =HAVERM!C317 -> 1.92 | D26: =HAVERM!D317 -> 2.77 | H26: =B26-L26 -> 3.99 | I26: =C26-M26 -> 1.1974619 | J26: =D26-N26 -> 1.5989381 | L26: =HAVERM!E317 -> 0.5 | M26: =HAVERM!F317 -> 0.7225381 | N26: =HAVERM!G317 -> 1.1710619 | P26: 42309 | Q26: =B26-B14 -> 0 | U26: 44136 | V26: =HAVERM!E377 -> 0.1 | W26: =HAVERM!H377 -> 2.45 | X26: =HAVERM!I377 -> 2.12 | Z26: 45200 | AA26: =W61-W$38 -> 4.08 | AB26: =X61-X$38 -> 1.2 | AF26: 45474 | AG26: =Data!G213 -> 3.726667 | AH26: =Data!H213 -> 6.806667
A27: 42339 | B27: =HAVERM!B318 -> 4.49 | C27: =HAVERM!C318 -> 1.9 | D27: =HAVERM!D318 -> 2.75 | H27: =B27-L27 -> 3.99 | I27: =C27-M27 -> 1.1574739 | J27: =D27-N27 -> 1.5918435 | L27: =HAVERM!E318 -> 0.5 | M27: =HAVERM!F318 -> 0.74252609 | N27: =HAVERM!G318 -> 1.1581565 | P27: 42339 | Q27: =B27-B15 -> 0.01 | U27: 44166 | V27: =HAVERM!E378 -> 0.1 | W27: =HAVERM!H378 -> 2.45 | X27: =HAVERM!I378 -> 2.12 | Z27: 45231 | AA27: =W62-W$38 -> 4.1 | AB27: =X62-X$38 -> 1.26 | AF27: 45566 | AG27: =Data!G214 -> 3.8 | AH27: =Data!H214 -> 6.646667
A28: 42370 | B28: =HAVERM!B319 -> 4.56 | C28: =HAVERM!C319 -> 1.93 | D28: =HAVERM!D319 -> 2.68 | H28: =B28-L28 -> 4.06 | I28: =C28-M28 -> 1.3224 | J28: =D28-N28 -> 1.6969905 | L28: =HAVERM!E319 -> 0.5 | M28: =HAVERM!F319 -> 0.6076 | N28: =HAVERM!G319 -> 0.98300952 | P28: 42370 | Q28: =B28-B16 -> 0 | R28: =C28-C4 -> -0.44 | U28: 44197 | V28: =HAVERM!E379 -> 0.1 | W28: =HAVERM!H379 -> 2.41 | X28: =HAVERM!I379 -> 2.09 | Z28: 45261 | AA28: =W63-W$38 -> 4.12 | AB28: =X63-X$38 -> 1.35 | AF28: 45658 | AG28: =Data!G215 -> 3.846667 | AH28: =Data!H215 -> 6.41
A29: 42401 | B29: =HAVERM!B320 -> 4.58 | C29: =HAVERM!C320 -> 1.95 | D29: =HAVERM!D320 -> 2.73 | H29: =B29-L29 -> 4.08 | I29: =C29-M29 -> 1.5433238 | J29: =D29-N29 -> 2.1155333 | L29: =HAVERM!E320 -> 0.5 | M29: =HAVERM!F320 -> 0.40667619 | N29: =HAVERM!G320 -> 0.61446667 | P29: 42401 | Q29: =B29-B17 -> 0.07 | R29: =C29-C5 -> -0.43 | U29: 44228 | V29: =HAVERM!E380 -> 0.1 | W29: =HAVERM!H380 -> 2.43 | X29: =HAVERM!I380 -> 2.09 | Z29: 45292 | AA29: =W64-W$38 -> 4.14 | AB29: =X64-X$38 -> 1.4 | AF29: 45748 | AG29: =Data!G216 -> 3.873333 | AH29: =Data!H216 -> 6.216667
A30: 42430 | B30: =HAVERM!B321 -> 4.57 | C30: =HAVERM!C321 -> 1.9 | D30: =HAVERM!D321 -> 2.7 | H30: =B30-L30 -> 4.07 | I30: =C30-M30 -> 1.4501435 | J30: =D30-N30 -> 2.0500696 | L30: =HAVERM!E321 -> 0.5 | M30: =HAVERM!F321 -> 0.44985652 | N30: =HAVERM!G321 -> 0.64993043 | P30: 42430 | Q30: =B30-B18 -> 0.06 | R30: =C30-C6 -> -0.47 | U30: 44256 | V30: =HAVERM!E381 -> 0.1 | W30: =HAVERM!H381 -> 2.44 | X30: =HAVERM!I381 -> 2.09 | Z30: 45323 | AA30: =W65-W$38 -> 4.15 | AB30: =X65-X$38 -> 1.47 | AF30: 45839 | AG30: =Data!G217 -> 3.854621 | AH30: =Data!H217 -> 6.023008
A31: 42461 | B31: =HAVERM!B322 -> 4.64 | C31: =HAVERM!C322 -> 1.84 | D31: =HAVERM!D322 -> 2.71 | H31: =B31-L31 -> 4.14 | I31: =C31-M31 -> 1.3879619 | J31: =D31-N31 -> 2.0608476 | L31: =HAVERM!E322 -> 0.5 | M31: =HAVERM!F322 -> 0.4520381 | N31: =HAVERM!G322 -> 0.64915238 | P31: 42461 | Q31: =B31-B19 -> 0.11 | R31: =C31-C7 -> -0.7 | U31: 44287 | V31: =HAVERM!E382 -> 0.1 | W31: =HAVERM!H382 -> 2.42 | X31: =HAVERM!I382 -> 2.07 | Z31: 45352 | AA31: =W66-W$38 -> 4.18 | AB31: =X66-X$38 -> 1.49 | AF31: 45931 | AG31: =Data!G218 -> 3.855985 | AH31: =Data!H218 -> 5.811905
A32: 42491 | B32: =HAVERM!B323 -> 4.56 | C32: =HAVERM!C323 -> 1.91 | D32: =HAVERM!D323 -> 2.64 | H32: =B32-L32 -> 4.06 | I32: =C32-M32 -> 1.4411136 | J32: =D32-N32 -> 1.9507182 | L32: =HAVERM!E323 -> 0.5 | M32: =HAVERM!F323 -> 0.46888636 | N32: =HAVERM!G323 -> 0.68928182 | P32: 42491 | Q32: =B32-B20 -> 0.01 | R32: =C32-C8 -> -0.65 | U32: 44317 | V32: =HAVERM!E383 -> 0.1 | W32: =HAVERM!H383 -> 2.5 | X32: =HAVERM!I383 -> 2.07 | Z32: 45383 | AA32: =W67-W$38 -> 4.17 | AB32: =X67-X$38 -> 1.56 | AF32: 46023 | AG32: =Data!G219 -> 3.88 | AH32: =Data!H219 -> 5.606066
A33: 42522 | B33: =HAVERM!B324 -> 4.52 | C33: =HAVERM!C324 -> 1.75 | D33: =HAVERM!D324 -> 2.54 | H33: =B33-L33 -> 4.02 | I33: =C33-M33 -> 1.3929045 | J33: =D33-N33 -> 2.0278727 | L33: =HAVERM!E324 -> 0.5 | M33: =HAVERM!F324 -> 0.35709545 | N33: =HAVERM!G324 -> 0.51212727 | P33: 42522 | Q33: =B33-B21 -> 0.03 | R33: =C33-C9 -> -0.85 | U33: 44348 | V33: =HAVERM!E384 -> 0.1 | W33: =HAVERM!H384 -> 2.55 | X33: =HAVERM!I384 -> 2.08 | Z33: 45413 | AA33: =W68-W$38 -> 4.18 | AB33: =X68-X$38 -> 1.6 | AF33: 46113 | AG33: =Data!G220 -> 3.895385 | AH33: =Data!H220 -> 5.398326
A34: 42552 | B34: =HAVERM!B325 -> 4.55 | C34: =HAVERM!C325 -> 1.72 | D34: =HAVERM!D325 -> 2.51 | H34: =B34-L34 -> 4.05 | I34: =C34-M34 -> 1.5872619 | J34: =D34-N34 -> 2.2893238 | L34: =HAVERM!E325 -> 0.5 | M34: =HAVERM!F325 -> 0.1327381 | N34: =HAVERM!G325 -> 0.22067619 | P34: 42552 | Q34: =B34-B22 -> 0.05 | R34: =C34-C10 -> -0.82 | U34: 44378 | V34: =HAVERM!E385 -> 0.1 | W34: =HAVERM!H385 -> 2.55 | X34: =HAVERM!I385 -> 2.05 | Z34: 45444 | AA34: =W69-W$38 -> 4.22 | AB34: =X69-X$38 -> 1.64 | AF34: 46204 | AG34: =Data!G221 -> 3.944082 | AH34: =Data!H221 -> 5.25076
A35: 42583 | B35: =HAVERM!B326 -> 4.3 | C35: =HAVERM!C326 -> 1.69 | D35: =HAVERM!D326 -> 2.39 | H35: =B35-L35 -> 4.0173913 | I35: =C35-M35 -> 1.5824 | J35: =D35-N35 -> 2.2147217 | L35: =HAVERM!E326 -> 0.2826087 | M35: =HAVERM!F326 -> 0.1076 | N35: =HAVERM!G326 -> 0.17527826 | P35: 42583 | Q35: =B35-B23 -> -0.18 | R35: =C35-C11 -> -0.85 | U35: 44409 | V35: =HAVERM!E386 -> 0.1 | W35: =HAVERM!H386 -> 2.65 | X35: =HAVERM!I386 -> 2.06 | Z35: 45474 | AA35: =W70-W$38 -> 4.18 | AB35: =X70-X$38 -> 1.68 | AF35: 46296 | AG35: =Data!G222 -> 3.99024 | AH35: =Data!H222 -> 5.083459
A36: 42614 | B36: =HAVERM!B327 -> 4.24 | C36: =HAVERM!C327 -> 1.59 | D36: =HAVERM!D327 -> 2.34 | H36: =B36-L36 -> 3.99 | I36: =C36-M36 -> 1.4666318 | J36: =D36-N36 -> 2.1336091 | L36: =HAVERM!E327 -> 0.25 | M36: =HAVERM!F327 -> 0.12336818 | N36: =HAVERM!G327 -> 0.20639091 | P36: 42614 | Q36: =B36-B24 -> -0.26 | R36: =C36-C12 -> -0.87 | U36: 44440 | V36: =HAVERM!E387 -> 0.1 | W36: =HAVERM!H387 -> 2.65 | X36: =HAVERM!I387 -> 2.05 | Z36: 45505 | AA36: =W71-W$38 -> 4.07 | AB36: =X71-X$38 -> 1.71 | AD36: 1000 | AF36: 46388 | AG36: =Data!G223 -> 4.021269 | AH36: =Data!H223 -> 4.943674
A37: 42644 | B37: =HAVERM!B328 -> 4.24 | C37: =HAVERM!C328 -> 1.52 | D37: =HAVERM!D328 -> 2.27 | H37: =B37-L37 -> 3.99 | I37: =C37-M37 -> 1.3240381 | J37: =D37-N37 -> 1.9146571 | L37: =HAVERM!E328 -> 0.25 | M37: =HAVERM!F328 -> 0.1959619 | N37: =HAVERM!G328 -> 0.35534286 | P37: 42644 | Q37: =B37-B25 -> -0.3 | R37: =C37-C13 -> -0.69 | U37: 44470 | V37: =HAVERM!E388 -> 0.1 | W37: =HAVERM!H388 -> 2.66 | X37: =HAVERM!I388 -> 2.03 | Z37: 45536 | AA37: =W72-W$38 -> 4.07 | AB37: =X72-X$38 -> 1.73 | AD37: 1000 | AF37: 46478 | AG37: =Data!G224 -> 4.029451 | AH37: =Data!H224 -> 4.782779
A38: 42675 | B38: =HAVERM!B329 -> 4.28 | C38: =HAVERM!C329 -> 1.43 | D38: =HAVERM!D329 -> 2.25 | H38: =B38-L38 -> 4.03 | I38: =C38-M38 -> 1.1526455 | J38: =D38-N38 -> 1.6863136 | L38: =HAVERM!E329 -> 0.25 | M38: =HAVERM!F329 -> 0.27735455 | N38: =HAVERM!G329 -> 0.56368636 | P38: 42675 | Q38: =B38-B26 -> -0.21 | R38: =C38-C14 -> -0.74 | U38: 44501 | V38: =HAVERM!E389 -> 0.1 | W38: =HAVERM!H389 -> 2.7 | X38: =HAVERM!I389 -> 2.02 | Z38: 45566 | AA38: =W73-W$38 -> 4.05 | AB38: =X73-X$38 -> 1.77 | AD38: 1000 | AF38: 46569 | AG38: =Data!G225 -> 4.010621 | AH38: =Data!H225 -> 4.649104
A39: 42705 | B39: =HAVERM!B330 -> 4.23 | C39: =HAVERM!C330 -> 1.45 | D39: =HAVERM!D330 -> 2.26 | H39: =B39-L39 -> 3.98 | I39: =C39-M39 -> 1.1509364 | J39: =D39-N39 -> 1.6513864 | L39: =HAVERM!E330 -> 0.25 | M39: =HAVERM!F330 -> 0.29906364 | N39: =HAVERM!G330 -> 0.60861364 | P39: 42705 | Q39: =B39-B27 -> -0.26 | R39: =C39-C15 -> -0.63 | U39: 44531 | V39: =HAVERM!E390 -> 0.17826087 | W39: =HAVERM!H390 -> 2.75 | X39: =HAVERM!I390 -> 2.01 | Z39: 45597 | AA39: =W74-W$38 -> 3.91 | AB39: =X74-X$38 -> 1.79 | AD39: 1000 | AF39: 46661 | AG39: =Data!G226 -> 3.930274 | AH39: =Data!H226 -> 4.493542
A40: 42736 | B40: =HAVERM!B331 -> 4.49 | C40: =HAVERM!C331 -> 1.45 | D40: =HAVERM!D331 -> 2.22 | H40: =B40-L40 -> 4.24 | I40: =C40-M40 -> 1.1252182 | J40: =D40-N40 -> 1.61045 | L40: =HAVERM!E331 -> 0.25 | M40: =HAVERM!F331 -> 0.32478182 | N40: =HAVERM!G331 -> 0.60955 | P40: 42736 | Q40: =B40-B28 -> -0.07 | R40: =C40-C16 -> -0.56 | U40: 44562 | V40: =HAVERM!E391 -> 0.25 | W40: =HAVERM!H391 -> 2.81 | X40: =HAVERM!I391 -> 2.01 | Z40: 45627 | AA40: =W75-W$38 -> 3.88 | AB40: =X75-X$38 -> 1.78 | AD40: 1000 | AF40: 46753 | AG40: =Data!G227 -> 3.885861 | AH40: =Data!H227 -> 4.371559
A41: 42767 | B41: =HAVERM!B332 -> 4.37 | C41: =HAVERM!C332 -> 1.42 | D41: =HAVERM!D332 -> 2.2 | H41: =B41-L41 -> 4.12 | I41: =C41-M41 -> 1.12247 | J41: =D41-N41 -> 1.648535 | L41: =HAVERM!E332 -> 0.25 | M41: =HAVERM!F332 -> 0.29753 | N41: =HAVERM!G332 -> 0.551465 | P41: 42767 | Q41: =B41-B29 -> -0.21 | R41: =C41-C17 -> -0.54 | U41: 44593 | V41: =HAVERM!E392 -> 0.475 | W41: =HAVERM!H392 -> 2.95 | X41: =HAVERM!I392 -> 2.02 | Z41: 45658 | AA41: =W76-W$38 -> 3.81 | AB41: =X76-X$38 -> 1.8 | AD41: 1000 | AF41: 46844 | AG41: =Data!G228 -> 3.845469 | AH41: =Data!H228 -> 4.3
A42: 42795 | B42: =HAVERM!B333 -> 4.28 | C42: =HAVERM!C333 -> 1.37 | D42: =HAVERM!D333 -> 2.15 | H42: =B42-L42 -> 4.03 | I42: =C42-M42 -> 1.0473304 | J42: =D42-N42 -> 1.591987 | L42: =HAVERM!E333 -> 0.25 | M42: =HAVERM!F333 -> 0.32266957 | N42: =HAVERM!G333 -> 0.55801304 | P42: 42795 | Q42: =B42-B30 -> -0.29 | R42: =C42-C18 -> -0.62 | U42: 44621 | V42: =HAVERM!E393 -> 0.61956522 | W42: =HAVERM!H393 -> 3.05 | X42: =HAVERM!I393 -> 2.05 | Z42: 45689 | AA42: =W77-W$38 -> 3.68 | AB42: =X77-X$38 -> 1.85 | AD42: 1000 | AF42: 46935 | AG42: =Data!G229 -> 3.774884 | AH42: =Data!H229 -> 4.3
A43: 42826 | B43: =HAVERM!B334 -> 4.54 | C43: =HAVERM!C334 -> 1.35 | D43: =HAVERM!D334 -> 2.09 | H43: =B43-L43 -> 4.29 | I43: =C43-M43 -> 1.07341 | J43: =D43-N43 -> 1.624545 | L43: =HAVERM!E334 -> 0.25 | M43: =HAVERM!F334 -> 0.27659 | N43: =HAVERM!G334 -> 0.465455 | P43: 42826 | Q43: =B43-B31 -> -0.1 | R43: =C43-C19 -> -0.6 | U43: 44652 | V43: =HAVERM!E394 -> 0.75 | W43: =HAVERM!H394 -> 3.15 | X43: =HAVERM!I394 -> 2.05 | Z43: 45717 | AA43: =W78-W$38 -> 3.64 | AB43: =X78-X$38 -> 1.83 | AD43: 1000 | AF43: 47027 | AG43: =Data!G230 -> 3.726523 | AH43: =Data!H230 -> 4.3
A44: 42856 | B44: =HAVERM!B335 -> 4.23 | C44: =HAVERM!C335 -> 1.49 | D44: =HAVERM!D335 -> 2.03 | H44: =B44-L44 -> 3.98 | I44: =C44-M44 -> 1.1840478 | J44: =D44-N44 -> 1.5019739 | L44: =HAVERM!E335 -> 0.25 | M44: =HAVERM!F335 -> 0.30595217 | N44: =HAVERM!G335 -> 0.52802609 | P44: 42856 | Q44: =B44-B32 -> -0.33 | R44: =C44-C20 -> -0.41 | U44: 44682 | V44: =HAVERM!E395 -> 0.96590909 | W44: =HAVERM!H395 -> 3.35 | X44: =HAVERM!I395 -> 2.08 | Z44: 45748 | AA44: =W79-W$38 -> 3.5783335 | AB44: =X79-X$38 -> 1.8416665 | AD44: 1000
A45: 42887 | B45: =HAVERM!B336 -> 4.28 | C45: =HAVERM!C336 -> 1.48 | D45: =HAVERM!D336 -> 1.99 | H45: =B45-L45 -> 4.03 | I45: =C45-M45 -> 1.1347682 | J45: =D45-N45 -> 1.4356773 | L45: =HAVERM!E336 -> 0.25 | M45: =HAVERM!F336 -> 0.34523182 | N45: =HAVERM!G336 -> 0.55432273 | P45: 42887 | Q45: =B45-B33 -> -0.24 | R45: =C45-C21 -> -0.35 | U45: 44713 | V45: =HAVERM!E396 -> 1.125 | W45: =HAVERM!H396 -> 3.48 | X45: =HAVERM!I396 -> 2.12 | Z45: 45778 | AA45: =W80-W$38 -> 3.516667 | AB45: =X80-X$38 -> 1.853333 | AD45: 1000
A46: 42917 | B46: =HAVERM!B337 -> 4.51 | C46: =HAVERM!C337 -> 1.41 | D46: =HAVERM!D337 -> 1.97 | H46: =B46-L46 -> 4.26 | I46: =C46-M46 -> 0.97240952 | J46: =D46-N46 -> 1.2782571 | L46: =HAVERM!E337 -> 0.25 | M46: =HAVERM!F337 -> 0.43759048 | N46: =HAVERM!G337 -> 0.69174286 | P46: 42917 | Q46: =B46-B34 -> -0.04 | R46: =C46-C22 -> -0.46 | U46: 44743 | V46: =HAVERM!E397 -> 1.25 | W46: =HAVERM!H397 -> 3.56 | X46: =HAVERM!I397 -> 2.13 | Z46: 45809 | AA46: =W81-W$38 -> 3.452114 | AB46: =X81-X$38 -> 1.8470957 | AD46: 1000
A47: 42948 | B47: =HAVERM!B338 -> 4.32 | C47: =HAVERM!C338 -> 1.43 | D47: =HAVERM!D338 -> 1.96 | H47: =B47-L47 -> 4.07 | I47: =C47-M47 -> 1.0583739 | J47: =D47-N47 -> 1.3781739 | L47: =HAVERM!E338 -> 0.25 | M47: =HAVERM!F338 -> 0.37162609 | N47: =HAVERM!G338 -> 0.58182609 | P47: 42948 | Q47: =B47-B35 -> 0.02 | R47: =C47-C23 -> -0.52 | U47: 44774 | V47: =HAVERM!E398 -> 1.6847826 | W47: =HAVERM!H398 -> 3.87 | X47: =HAVERM!I398 -> 2.18 | Z47: 45839 | AA47: =W82-W$38 -> 3.387561 | AB47: =X82-X$38 -> 1.8408583 | AD47: 1000
A48: 42979 | B48: =HAVERM!B339 -> 4.31 | C48: =HAVERM!C339 -> 1.4 | D48: =HAVERM!D339 -> 1.9 | H48: =B48-L48 -> 4.06 | I48: =C48-M48 -> 0.86071429 | J48: =D48-N48 -> 1.1466619 | L48: =HAVERM!E339 -> 0.25 | M48: =HAVERM!F339 -> 0.53928571 | N48: =HAVERM!G339 -> 0.7533381 | P48: 42979 | Q48: =B48-B36 -> 0.07 | R48: =C48-C24 -> -0.51 | U48: 44805 | V48: =HAVERM!E399 -> 1.9090909 | W48: =HAVERM!H399 -> 4.08 | X48: =HAVERM!I399 -> 2.25 | Z48: 45870 | AA48: =W83-W$38 -> 3.323008 | AB48: =X83-X$38 -> 1.834621 | AD48: 1000
A49: 43009 | B49: =HAVERM!B340 -> 4.31 | C49: =HAVERM!C340 -> 1.55 | D49: =HAVERM!D340 -> 2.04 | H49: =B49-L49 -> 4.06 | I49: =C49-M49 -> 0.87478182 | J49: =D49-N49 -> 1.1439545 | L49: =HAVERM!E340 -> 0.25 | M49: =HAVERM!F340 -> 0.67521818 | N49: =HAVERM!G340 -> 0.89604545 | P49: 43009 | Q49: =B49-B37 -> 0.07 | R49: =C49-C25 -> -0.32 | U49: 44835 | V49: =HAVERM!E400 -> 2.25 | W49: =HAVERM!H400 -> 4.33 | X49: =HAVERM!I400 -> 2.29 | Z49: 45901 | AA49: =W84-W$38 -> 3.2526403 | AB49: =X84-X$38 -> 1.8350757 | AD49: 1000
A50: 43040 | B50: =HAVERM!B341 -> 4.34 | C50: =HAVERM!C341 -> 1.61 | D50: =HAVERM!D341 -> 2.04 | H50: =B50-L50 -> 3.8513636 | I50: =C50-M50 -> 0.93155238 | J50: =D50-N50 -> 1.1523905 | L50: =HAVERM!E341 -> 0.48863636 | M50: =HAVERM!F341 -> 0.67844762 | N50: =HAVERM!G341 -> 0.88760952 | P50: 43040 | Q50: =B50-B38 -> 0.06 | R50: =C50-C26 -> -0.31 | U50: 44866 | V50: =HAVERM!E401 -> 2.9318182 | W50: =HAVERM!H401 -> 4.82 | X50: =HAVERM!I401 -> 2.39 | Z50: 45931 | AA50: =W85-W$38 -> 3.1822727 | AB50: =X85-X$38 -> 1.8355303 | AD50: 1000
A51: 43070 | B51: =HAVERM!B342 -> 4.54 | C51: =HAVERM!C342 -> 1.57 | D51: =HAVERM!D342 -> 2.07 | H51: =B51-L51 -> 4.04 | I51: =C51-M51 -> 0.88347143 | J51: =D51-N51 -> 1.1779048 | L51: =HAVERM!E342 -> 0.5 | M51: =HAVERM!F342 -> 0.68652857 | N51: =HAVERM!G342 -> 0.89209524 | P51: 43070 | Q51: =B51-B39 -> 0.31 | R51: =C51-C27 -> -0.33 | U51: 44896 | V51: =HAVERM!E402 -> 3.2727273 | W51: =HAVERM!H402 -> 5.14 | X51: =HAVERM!I402 -> 2.51 | Z51: 45962 | AA51: =W86-W$38 -> 3.111905 | AB51: =X86-X$38 -> 1.835985 | AD51: 1000
A52: 43101 | B52: =HAVERM!B343 -> 4.21 | C52: =HAVERM!C343 -> 1.54 | D52: =HAVERM!D343 -> 1.98 | H52: =B52-L52 -> 3.71 | I52: =C52-M52 -> 0.79875455 | J52: =D52-N52 -> 0.99838636 | L52: =HAVERM!E343 -> 0.5 | M52: =HAVERM!F343 -> 0.74124545 | N52: =HAVERM!G343 -> 0.98161364 | P52: 43101 | Q52: =B52-B40 -> -0.28 | R52: =C52-C28 -> -0.39 | U52: 44927 | V52: =HAVERM!E403 -> 3.5 | W52: =HAVERM!H403 -> 5.3 | X52: =HAVERM!I403 -> 2.55 | Z52: 45992 | AA52: =W87-W$38 -> 3.043292 | AB52: =X87-X$38 -> 1.84399 | AD52: 1000
A53: 43132 | B53: =HAVERM!B344 -> 4.23 | C53: =HAVERM!C344 -> 1.49 | D53: =HAVERM!D344 -> 1.99 | H53: =B53-L53 -> 3.73 | I53: =C53-M53 -> 0.62635 | J53: =D53-N53 -> 0.81268 | L53: =HAVERM!E344 -> 0.5 | M53: =HAVERM!F344 -> 0.86365 | N53: =HAVERM!G344 -> 1.17732 | P53: 43132 | Q53: =B53-B41 -> -0.14 | R53: =C53-C29 -> -0.46 | U53: 44958 | V53: =HAVERM!E404 -> 3.975 | W53: =HAVERM!H404 -> 5.65 | X53: =HAVERM!I404 -> 2.65 | Z53: 46023 | AA53: =W88-W$38 -> 2.974679 | AB53: =X88-X$38 -> 1.851995 | AD53: 1000
A54: 43160 | B54: =HAVERM!B345 -> 4.14 | C54: =HAVERM!C345 -> 1.53 | D54: =HAVERM!D345 -> 2.02 | H54: =B54-L54 -> 3.64 | I54: =C54-M54 -> 0.63301818 | J54: =D54-N54 -> 0.89234545 | L54: =HAVERM!E345 -> 0.5 | M54: =HAVERM!F345 -> 0.89698182 | N54: =HAVERM!G345 -> 1.1276545 | P54: 43160 | Q54: =B54-B42 -> -0.14 | R54: =C54-C30 -> -0.37 | U54: 44986 | V54: =HAVERM!E405 -> 4.076087 | W54: =HAVERM!H405 -> 5.79 | X54: =HAVERM!I405 -> 2.75 | Z54: 46054 | AA54: =W89-W$38 -> 2.906066 | AB54: =X89-X$38 -> 1.86 | AD54: 1000
A55: 43191 | B55: =HAVERM!B346 -> 4.17 | C55: =HAVERM!C346 -> 1.72 | D55: =HAVERM!D346 -> 2.01 | H55: =B55-L55 -> 3.67 | I55: =C55-M55 -> 0.8357 | J55: =D55-N55 -> 0.90777143 | L55: =HAVERM!E346 -> 0.5 | M55: =HAVERM!F346 -> 0.8843 | N55: =HAVERM!G346 -> 1.1022286 | P55: 43191 | Q55: =B55-B43 -> -0.37 | R55: =C55-C31 -> -0.12 | U55: 45017 | V55: =HAVERM!E406 -> 4.25 | W55: =HAVERM!H406 -> 5.91 | X55: =HAVERM!I406 -> 2.76 | Z55: 46082 | AA55: =W90-W$38 -> 2.8368193 | AB55: =X90-X$38 -> 1.8651283 | AD55: 1000
... A63: 43435 | B63: =HAVERM!B354 -> 4.4 | C63: =HAVERM!C354 -> 1.73 | D63: =HAVERM!D354 -> 2.01 | H63: =B63-L63 -> 3.65 | I63: =C63-M63 -> 0.8571 | J63: =D63-N63 -> 0.98364286 | L63: =HAVERM!E354 -> 0.75 | M63: =HAVERM!F354 -> 0.8729 | N63: =HAVERM!G354 -> 1.0263571 | P63: 43435 | Q63: =B63-B51 -> -0.14 | R63: =C63-C39 -> 0.28 | U63: 45261 | V63: =HAVERM!E414 -> 5.25 | W63: =HAVERM!H414 -> 6.82 | X63: =HAVERM!I414 -> 3.37 | Z63: 46327 | AA63: =W98-W$38 -> 2.383459 | AB63: =X98-X$38 -> 1.97024 | AD63: 1000
A64: 43466 | B64: =HAVERM!B355 -> 4.48 | C64: =HAVERM!C355 -> 1.72 | D64: =HAVERM!D355 -> 2.05 | F64: 100 | H64: =B64-L64 -> 3.73 | I64: =C64-M64 -> 0.85026087 | J64: =D64-N64 -> 1.0260217 | L64: =HAVERM!E355 -> 0.75 | M64: =HAVERM!F355 -> 0.86973913 | N64: =HAVERM!G355 -> 1.0239783 | P64: 43466 | Q64: =B64-B52 -> 0.27 | R64: =C64-C40 -> 0.27 | S64: =D64-D4 -> -1.29 | U64: 45292 | V64: =HAVERM!E415 -> 5.25 | W64: =HAVERM!H415 -> 6.84 | X64: =HAVERM!I415 -> 3.42 | Z64: 46357 | AA64: =W99-W$38 -> 2.336864 | AB64: =X99-X$38 -> 1.980583 | AD64: 1000
A65: 43497 | B65: =HAVERM!B356 -> 4.31 | C65: =HAVERM!C356 -> 1.7 | D65: =HAVERM!D356 -> 2.05 | F65: 100 | H65: =B65-L65 -> 3.56 | I65: =C65-M65 -> 0.873395 | J65: =D65-N65 -> 1.07894 | L65: =HAVERM!E356 -> 0.75 | M65: =HAVERM!F356 -> 0.826605 | N65: =HAVERM!G356 -> 0.97106 | P65: 43497 | Q65: =B65-B53 -> 0.08 | R65: =C65-C41 -> 0.28 | S65: =D65-D5 -> -1.4 | U65: 45323 | V65: =HAVERM!E416 -> 5.25 | W65: =HAVERM!H416 -> 6.85 | X65: =HAVERM!I416 -> 3.49
A66: 43525 | B66: =HAVERM!B357 -> 4.31 | C66: =HAVERM!C357 -> 1.7 | D66: =HAVERM!D357 -> 2.03 | F66: 100 | H66: =B66-L66 -> 3.56 | I66: =C66-M66 -> 0.90167619 | J66: =D66-N66 -> 1.0868 | L66: =HAVERM!E357 -> 0.75 | M66: =HAVERM!F357 -> 0.79832381 | N66: =HAVERM!G357 -> 0.9432 | P66: 43525 | Q66: =B66-B54 -> 0.17 | R66: =C66-C42 -> 0.33 | S66: =D66-D6 -> -1.45 | U66: 45352 | V66: =HAVERM!E417 -> 5.25 | W66: =HAVERM!H417 -> 6.88 | X66: =HAVERM!I417 -> 3.51
A67: 43556 | B67: =HAVERM!B358 -> 4.31 | C67: =HAVERM!C358 -> 1.66 | D67: =HAVERM!D358 -> 2 | F67: 100 | H67: =B67-L67 -> 3.56 | I67: =C67-M67 -> 0.86787273 | J67: =D67-N67 -> 1.0611364 | L67: =HAVERM!E358 -> 0.75 | M67: =HAVERM!F358 -> 0.79212727 | N67: =HAVERM!G358 -> 0.93886364 | P67: 43556 | Q67: =B67-B55 -> 0.14 | R67: =C67-C43 -> 0.31 | S67: =D67-D7 -> -1.69 | U67: 45383 | V67: =HAVERM!E418 -> 5.25 | W67: =HAVERM!H418 -> 6.87 | X67: =HAVERM!I418 -> 3.58
A68: 43586 | B68: =HAVERM!B359 -> 4.29 | C68: =HAVERM!C359 -> 1.65 | D68: =HAVERM!D359 -> 1.99 | F68: 100 | H68: =B68-L68 -> 3.54 | I68: =C68-M68 -> 0.88321304 | J68: =D68-N68 -> 1.1189522 | L68: =HAVERM!E359 -> 0.75 | M68: =HAVERM!F359 -> 0.76678696 | N68: =HAVERM!G359 -> 0.87104783 | P68: 43586 | Q68: =B68-B56 -> 0.13 | R68: =C68-C44 -> 0.16 | S68: =D68-D8 -> -1.73 | U68: 45413 | V68: =HAVERM!E419 -> 5.25 | W68: =HAVERM!H419 -> 6.88 | X68: =HAVERM!I419 -> 3.62
A69: 43617 | B69: =HAVERM!B360 -> 4.29 | C69: =HAVERM!C360 -> 1.64 | D69: =HAVERM!D360 -> 1.97 | F69: 100 | H69: =B69-L69 -> 3.54 | I69: =C69-M69 -> 0.998995 | J69: =D69-N69 -> 1.290385 | L69: =HAVERM!E360 -> 0.75 | M69: =HAVERM!F360 -> 0.641005 | N69: =HAVERM!G360 -> 0.679615 | P69: 43617 | Q69: =B69-B57 -> 0.23 | R69: =C69-C45 -> 0.16 | S69: =D69-D9 -> -1.72 | U69: 45444 | V69: =HAVERM!E420 -> 5.25 | W69: =HAVERM!H420 -> 6.92 | X69: =HAVERM!I420 -> 3.66
A70: 43647 | B70: =HAVERM!B361 -> 4.29 | C70: =HAVERM!C361 -> 1.61 | D70: =HAVERM!D361 -> 1.93 | F70: 100 | H70: =B70-L70 -> 3.54 | I70: =C70-M70 -> 1.074087 | J70: =D70-N70 -> 1.3573087 | L70: =HAVERM!E361 -> 0.75 | M70: =HAVERM!F361 -> 0.53591304 | N70: =HAVERM!G361 -> 0.5726913 | P70: 43647 | Q70: =B70-B58 -> 0.19 | R70: =C70-C46 -> 0.2 | S70: =D70-D10 -> -1.85 | U70: 45474 | V70: =HAVERM!E421 -> 5.25 | W70: =HAVERM!H421 -> 6.88 | X70: =HAVERM!I421 -> 3.7
A71: 43678 | B71: =HAVERM!B362 -> 4.29 | C71: =HAVERM!C362 -> 1.59 | D71: =HAVERM!D362 -> 1.89 | F71: 100 | H71: =B71-L71 -> 3.54 | I71: =C71-M71 -> 1.1301773 | J71: =D71-N71 -> 1.4921818 | L71: =HAVERM!E362 -> 0.75 | M71: =HAVERM!F362 -> 0.45982273 | N71: =HAVERM!G362 -> 0.39781818 | P71: 43678 | Q71: =B71-B59 -> -0.06 | R71: =C71-C47 -> 0.16 | S71: =D71-D11 -> -1.87 | U71: 45505 | V71: =HAVERM!E422 -> 5 | W71: =HAVERM!H422 -> 6.77 | X71: =HAVERM!I422 -> 3.73
A72: 43709 | B72: =HAVERM!B363 -> 4.29 | C72: =HAVERM!C363 -> 1.55 | D72: =HAVERM!D363 -> 1.79 | F72: 100 | H72: =B72-L72 -> 3.54 | I72: =C72-M72 -> 1.0178952 | J72: =D72-N72 -> 1.3218286 | L72: =HAVERM!E363 -> 0.75 | M72: =HAVERM!F363 -> 0.53210476 | N72: =HAVERM!G363 -> 0.46817143 | P72: 43709 | Q72: =B72-B60 -> -0.1 | R72: =C72-C48 -> 0.15 | S72: =D72-D12 -> -1.82 | U72: 45536 | V72: =HAVERM!E423 -> 5 | W72: =HAVERM!H423 -> 6.77 | X72: =HAVERM!I423 -> 3.75
A73: 43739 | B73: =HAVERM!B364 -> 4.27 | C73: =HAVERM!C364 -> 1.47 | D73: =HAVERM!D364 -> 1.71 | F73: 100 | H73: =B73-L73 -> 3.52 | I73: =C73-M73 -> 0.9451087 | J73: =D73-N73 -> 1.2177696 | L73: =HAVERM!E364 -> 0.75 | M73: =HAVERM!F364 -> 0.5248913 | N73: =HAVERM!G364 -> 0.49223043 | P73: 43739 | Q73: =B73-B61 -> -0.18 | R73: =C73-C49 -> -0.08 | S73: =D73-D13 -> -1.56 | U73: 45566 | V73: =HAVERM!E424 -> 5 | W73: =HAVERM!H424 -> 6.75 | X73: =HAVERM!I424 -> 3.79
A74: 43770 | B74: =HAVERM!B365 -> 4.27 | C74: =HAVERM!C365 -> 1.41 | D74: =HAVERM!D365 -> 1.67 | F74: 100 | H74: =B74-L74 -> 3.52 | I74: =C74-M74 -> 0.82919524 | J74: =D74-N74 -> 1.0745143 | L74: =HAVERM!E365 -> 0.75 | M74: =HAVERM!F365 -> 0.58080476 | N74: =HAVERM!G365 -> 0.59548571 | P74: 43770 | Q74: =B74-B62 -> -0.14 | R74: =C74-C50 -> -0.2 | S74: =D74-D14 -> -1.54 | U74: 45597 | V74: =HAVERM!E425 -> 4.797619 | W74: =HAVERM!H425 -> 6.61 | X74: =HAVERM!I425 -> 3.81
A75: 43800 | B75: =HAVERM!B366 -> 4.27 | C75: =HAVERM!C366 -> 1.42 | D75: =HAVERM!D366 -> 1.67 | F75: 100 | H75: =B75-L75 -> 3.52 | I75: =C75-M75 -> 0.81618182 | J75: =D75-N75 -> 1.0191955 | L75: =HAVERM!E366 -> 0.75 | M75: =HAVERM!F366 -> 0.60381818 | N75: =HAVERM!G366 -> 0.65080455 | P75: 43800 | Q75: =B75-B63 -> -0.13 | R75: =C75-C51 -> -0.15 | S75: =D75-D15 -> -1.54 | U75: 45627 | V75: =HAVERM!E426 -> 4.75 | W75: =HAVERM!H426 -> 6.58 | X75: =HAVERM!I426 -> 3.8
A76: 43831 | B76: =HAVERM!B367 -> 4.27 | C76: =HAVERM!C367 -> 1.41 | D76: =HAVERM!D367 -> 1.68 | H76: =B76-L76 -> 3.52 | I76: =C76-M76 -> 0.908 | J76: =D76-N76 -> 1.1408261 | L76: =HAVERM!E367 -> 0.75 | M76: =HAVERM!F367 -> 0.502 | N76: =HAVERM!G367 -> 0.53917391 | P76: 43831 | Q76: =B76-B64 -> -0.21 | R76: =C76-C52 -> -0.13 | S76: =D76-D16 -> -1.41 | U76: 45658 | V76: =HAVERM!E427 -> 4.75 | W76: =HAVERM!H427 -> 6.51 | X76: =HAVERM!I427 -> 3.82
A77: 43862 | B77: =HAVERM!B368 -> 4.26 | C77: =HAVERM!C368 -> 1.4 | D77: =HAVERM!D368 -> 1.67 | H77: =B77-L77 -> 3.51 | I77: =C77-M77 -> 0.89046 | J77: =D77-N77 -> 1.17575 | L77: =HAVERM!E368 -> 0.75 | M77: =HAVERM!F368 -> 0.50954 | N77: =HAVERM!G368 -> 0.49425 | P77: 43862 | Q77: =B77-B65 -> -0.05 | R77: =C77-C53 -> -0.09 | S77: =D77-D17 -> -1.38 | U77: 45689 | V77: =HAVERM!E428 -> 4.5375 | W77: =HAVERM!H428 -> 6.38 | X77: =HAVERM!I428 -> 3.87
A78: 43891 | B78: =HAVERM!B369 -> 4.1 | C78: =HAVERM!C369 -> 1.4 | D78: =HAVERM!D369 -> 1.66 | H78: =B78-L78 -> 3.7522727 | I78: =C78-M78 -> 1.2043318 | J78: =D78-N78 -> 1.3765318 | L78: =HAVERM!E369 -> 0.34772727 | M78: =HAVERM!F369 -> 0.19566818 | N78: =HAVERM!G369 -> 0.28346818 | P78: 43891 | Q78: =B78-B66 -> -0.21 | R78: =C78-C54 -> -0.13 | S78: =D78-D18 -> -1.32 | U78: 45717 | V78: =HAVERM!E429 -> 4.5 | W78: =HAVERM!H429 -> 6.34 | X78: =HAVERM!I429 -> 3.85
A79: 43922 | B79: =HAVERM!B370 -> 3.66 | C79: =HAVERM!C370 -> 1.38 | D79: =HAVERM!D370 -> 1.67 | H79: =B79-L79 -> 3.56 | I79: =C79-M79 -> 1.2634182 | J79: =D79-N79 -> 1.4713273 | L79: =HAVERM!E370 -> 0.1 | M79: =HAVERM!F370 -> 0.11658182 | N79: =HAVERM!G370 -> 0.19867273 | P79: 43922 | Q79: =B79-B67 -> -0.65 | R79: =C79-C55 -> -0.34 | S79: =D79-D19 -> -1.25 | U79: 45748 | V79: =HAVERM!E430 -> 4.5 | W79: =W78+(W80-W78)*1/2 -> 6.2783335 | X79: =X78+(X80-X78)*1/2 -> 3.8616665
A80: 43952 | B80: =HAVERM!B371 -> 3.65 | C80: =HAVERM!C371 -> 1.42 | D80: =HAVERM!D371 -> 1.7 | H80: =B80-L80 -> 3.55 | I80: =C80-M80 -> 1.3964 | J80: =D80-N80 -> 1.6153 | L80: =HAVERM!E371 -> 0.1 | M80: =HAVERM!F371 -> 0.0236 | N80: =HAVERM!G371 -> 0.0847 | P80: 43952 | Q80: =B80-B68 -> -0.64 | R80: =C80-C56 -> -0.32 | S80: =D80-D20 -> -1.16 | U80: 45778 | V80: ='[2]Daily fcst'!L37 -> 4.3068182 | W80: =Data!H216 -> 6.216667 | X80: =Data!G216 -> 3.873333
A81: 43983 | B81: =HAVERM!B372 -> 3.65 | C81: =HAVERM!C372 -> 1.41 | D81: =HAVERM!D372 -> 1.69 | H81: =B81-L81 -> 3.55 | I81: =C81-M81 -> 1.4068773 | J81: =D81-N81 -> 1.6384455 | L81: =HAVERM!E372 -> 0.1 | M81: =HAVERM!F372 -> 0.0031227273 | N81: =HAVERM!G372 -> 0.051554545 | P81: 43983 | Q81: =B81-B69 -> -0.64 | R81: =C81-C57 -> -0.33 | S81: =D81-D21 -> -1.13 | U81: 45809 | V81: ='[2]Daily fcst'!L38 -> 4.25 | W81: =W80+(W83-W80)*1/3 -> 6.152114 | X81: =X80+(X83-X80)*1/3 -> 3.8670957
A82: 44013 | B82: =HAVERM!B373 -> 3.66 | C82: =HAVERM!C373 -> 1.45 | D82: =HAVERM!D373 -> 1.7 | H82: =B82-L82 -> 3.56 | I82: =C82-M82 -> 1.4926739 | J82: =D82-N82 -> 1.7278957 | L82: =HAVERM!E373 -> 0.1 | M82: =HAVERM!F373 -> -0.042673913 | N82: =HAVERM!G373 -> -0.027895652 | P82: 44013 | Q82: =B82-B70 -> -0.63 | R82: =C82-C58 -> -0.3 | S82: =D82-D22 -> -1.13 | U82: 45839 | V82: ='[2]Daily fcst'!L39 -> 4.25 | W82: =W81+(W83-W80)*1/3 -> 6.087561 | X82: =X81+(X83-X80)*1/3 -> 3.8608583
A83: 44044 | B83: =HAVERM!B374 -> 3.65 | C83: =HAVERM!C374 -> 1.6 | D83: =HAVERM!D374 -> 1.79 | H83: =B83-L83 -> 3.55 | I83: =C83-M83 -> 1.6307238 | J83: =D83-N83 -> 1.7956762 | L83: =HAVERM!E374 -> 0.1 | M83: =HAVERM!F374 -> -0.03072381 | N83: =HAVERM!G374 -> -0.0056761905 | P83: 44044 | Q83: =B83-B71 -> -0.64 | R83: =C83-C59 -> -0.15 | S83: =D83-D23 -> -1.13 | U83: 45870 | V83: ='[2]Daily fcst'!L40 -> 4.047619 | W83: =Data!H217 -> 6.023008 | X83: =Data!G217 -> 3.854621
A84: 44075 | B84: =HAVERM!B375 -> 3.65 | C84: =HAVERM!C375 -> 1.75 | D84: =HAVERM!D375 -> 1.92 | H84: =B84-L84 -> 3.55 | I84: =C84-M84 -> 1.8163909 | J84: =D84-N84 -> 1.95315 | L84: =HAVERM!E375 -> 0.1 | M84: =HAVERM!F375 -> -0.066390909 | N84: =HAVERM!G375 -> -0.03315 | P84: 44075 | Q84: =B84-B72 -> -0.64 | R84: =C84-C60 -> 0.04 | S84: =D84-D24 -> -0.92 | U84: 45901 | V84: ='[2]Daily fcst'!L41 -> 4 | W84: =W83+(W86-W83)*1/3 -> 5.9526403 | X84: =X83+(X86-X83)*1/3 -> 3.8550757
A85: 44105 | B85: =HAVERM!B376 -> 3.64 | C85: =HAVERM!C376 -> 1.94 | D85: =HAVERM!D376 -> 2.05 | H85: =B85-L85 -> 3.54 | I85: =C85-M85 -> 1.9874955 | J85: =D85-N85 -> 2.0552 | L85: =HAVERM!E376 -> 0.1 | M85: =HAVERM!F376 -> -0.047495455 | N85: =HAVERM!G376 -> -0.0052 | P85: 44105 | Q85: =B85-B73 -> -0.63 | R85: =C85-C61 -> 0.14 | S85: =D85-D25 -> -0.73 | U85: 45931 | V85: ='[2]Daily fcst'!L42 -> 4 | W85: =W84+(W86-W83)*1/3 -> 5.8822727 | X85: =X84+(X86-X83)*1/3 -> 3.8555303
A86: 44136 | B86: =HAVERM!B377 -> 3.62 | C86: =HAVERM!C377 -> 1.92 | D86: =HAVERM!D377 -> 2.05 | H86: =B86-L86 -> 3.52 | I86: =C86-M86 -> 1.9391048 | J86: =D86-N86 -> 2.0021714 | L86: =HAVERM!E377 -> 0.1 | M86: =HAVERM!F377 -> -0.019104762 | N86: =HAVERM!G377 -> 0.047828571 | P86: 44136 | Q86: =B86-B74 -> -0.65 | R86: =C86-C62 -> 0.17 | S86: =D86-D26 -> -0.72 | U86: 45962 | V86: ='[2]Daily fcst'!L43 -> 3.7875 | W86: =Data!H218 -> 5.811905 | X86: =Data!G218 -> 3.855985
A87: 44166 | B87: =HAVERM!B378 -> 3.62 | C87: =HAVERM!C378 -> 1.86 | D87: =HAVERM!D378 -> 2 | H87: =B87-L87 -> 3.52 | I87: =C87-M87 -> 1.888087 | J87: =D87-N87 -> 1.9713739 | L87: =HAVERM!E378 -> 0.1 | M87: =HAVERM!F378 -> -0.028086957 | N87: =HAVERM!G378 -> 0.028626087 | P87: 44166 | Q87: =B87-B75 -> -0.65 | R87: =C87-C63 -> 0.13 | S87: =D87-D27 -> -0.75 | U87: 45992 | V87: ='[2]Daily fcst'!L44 -> 3.75 | W87: =W86+(W89-W86)*1/3 -> 5.743292 | X87: =X86+(X89-X86)*1/3 -> 3.86399
A88: 44197 | B88: =HAVERM!B379 -> 3.62 | C88: =HAVERM!C379 -> 1.75 | D88: =HAVERM!D379 -> 1.92 | H88: =B88-L88 -> 3.52 | I88: =C88-M88 -> 1.8021952 | J88: =D88-N88 -> 1.8915286 | L88: =HAVERM!E379 -> 0.1 | M88: =HAVERM!F379 -> -0.052195238 | N88: =HAVERM!G379 -> 0.028471429 | P88: 44197 | Q88: =B88-B76 -> -0.65 | R88: =C88-C64 -> 0.03 | S88: =D88-D28 -> -0.76 | U88: 46023 | V88: ='[2]Daily fcst'!L45 -> 3.75 | W88: =W87+(W89-W86)*1/3 -> 5.674679 | X88: =X87+(X89-X86)*1/3 -> 3.871995
A89: 44228 | B89: =HAVERM!B380 -> 3.62 | C89: =HAVERM!C380 -> 1.61 | D89: =HAVERM!D380 -> 1.8 | H89: =B89-L89 -> 3.52 | I89: =C89-M89 -> 1.57728 | J89: =D89-N89 -> 1.579405 | L89: =HAVERM!E380 -> 0.1 | M89: =HAVERM!F380 -> 0.03272 | N89: =HAVERM!G380 -> 0.220595 | P89: 44228 | Q89: =B89-B77 -> -0.64 | R89: =C89-C65 -> -0.09 | S89: =D89-D29 -> -0.93 | U89: 46054 | V89: ='[2]Daily fcst'!L46 -> 3.5375 | W89: =Data!H219 -> 5.606066 | X89: =Data!G219 -> 3.88
A90: 44256 | B90: =HAVERM!B381 -> 3.62 | C90: =HAVERM!C381 -> 1.56 | D90: =HAVERM!D381 -> 1.74 | H90: =B90-L90 -> 3.52 | I90: =C90-M90 -> 1.4588913 | J90: =D90-N90 -> 1.3311 | L90: =HAVERM!E381 -> 0.1 | M90: =HAVERM!F381 -> 0.1011087 | N90: =HAVERM!G381 -> 0.4089 | P90: 44256 | Q90: =B90-B78 -> -0.48 | R90: =C90-C66 -> -0.14 | S90: =D90-D30 -> -0.96 | U90: 46082 | V90: ='[2]Daily fcst'!L47 -> 3.5 | W90: =W89+(W92-W89)*1/3 -> 5.5368193 | X90: =X89+(X92-X89)*1/3 -> 3.8851283
A91: 44287 | B91: =HAVERM!B382 -> 3.61 | C91: =HAVERM!C382 -> 1.49 | D91: =HAVERM!D382 -> 1.71 | H91: =B91-L91 -> 3.51 | I91: =C91-M91 -> 1.3774682 | J91: =D91-N91 -> 1.2763364 | L91: =HAVERM!E382 -> 0.1 | M91: =HAVERM!F382 -> 0.11253182 | N91: =HAVERM!G382 -> 0.43366364 | P91: 44287 | Q91: =B91-B79 -> -0.05 | R91: =C91-C67 -> -0.17 | S91: =D91-D31 -> -1 | U91: 46113 | V91: ='[2]Daily fcst'!L48 -> 3.5 | W91: =W90+(W92-W89)*1/3 -> 5.4675727 | X91: =X90+(X92-X89)*1/3 -> 3.8902567
A92: 44317 | B92: =HAVERM!B383 -> 3.61 | C92: =HAVERM!C383 -> 1.47 | D92: =HAVERM!D383 -> 1.68 | H92: =B92-L92 -> 3.51 | I92: =C92-M92 -> 1.3356 | J92: =D92-N92 -> 1.2163 | L92: =HAVERM!E383 -> 0.1 | M92: =HAVERM!F383 -> 0.1344 | N92: =HAVERM!G383 -> 0.4637 | P92: 44317 | Q92: =B92-B80 -> -0.04 | R92: =C92-C68 -> -0.18 | S92: =D92-D32 -> -0.96 | U92: 46143 | V92: ='[2]Daily fcst'!L49 -> 3.297619 | W92: =Data!H220 -> 5.398326 | X92: =Data!G220 -> 3.895385
A93: 44348 | B93: =HAVERM!B384 -> 3.61 | C93: =HAVERM!C384 -> 1.39 | D93: =HAVERM!D384 -> 1.6 | H93: =B93-L93 -> 3.51 | I93: =C93-M93 -> 1.2148727 | J93: =D93-N93 -> 1.1281045 | L93: =HAVERM!E384 -> 0.1 | M93: =HAVERM!F384 -> 0.17512727 | N93: =HAVERM!G384 -> 0.47189545 | P93: 44348 | Q93: =B93-B81 -> -0.04 | R93: =C93-C69 -> -0.25 | S93: =D93-D33 -> -0.94 | U93: 46174 | V93: ='[2]Daily fcst'!L50 -> 3.25 | W93: =W92+(W95-W92)*1/3 -> 5.3491373 | X93: =X92+(X95-X92)*1/3 -> 3.9116173
A94: 44378 | B94: =HAVERM!B385 -> 3.61 | C94: =HAVERM!C385 -> 1.29 | D94: =HAVERM!D385 -> 1.45 | H94: =B94-L94 -> 3.51 | I94: =C94-M94 -> 1.0817273 | J94: =D94-N94 -> 1.0199273 | L94: =HAVERM!E385 -> 0.1 | M94: =HAVERM!F385 -> 0.20827273 | N94: =HAVERM!G385 -> 0.43007273 | P94: 44378 | Q94: =B94-B82 -> -0.05 | R94: =C94-C70 -> -0.32 | S94: =D94-D34 -> -1.06 | U94: 46204 | V94: ='[2]Daily fcst'!L51 -> 3.25 | W94: =W93+(W95-W92)*1/3 -> 5.2999487 | X94: =X93+(X95-X92)*1/3 -> 3.9278497
A95: 44409 | B95: =HAVERM!B386 -> 3.61 | C95: =HAVERM!C386 -> 1.23 | D95: =HAVERM!D386 -> 1.39 | H95: =B95-L95 -> 3.51 | I95: =C95-M95 -> 0.96960455 | J95: =D95-N95 -> 0.95339545 | L95: =HAVERM!E386 -> 0.1 | M95: =HAVERM!F386 -> 0.26039545 | N95: =HAVERM!G386 -> 0.43660455 | P95: 44409 | Q95: =B95-B83 -> -0.04 | R95: =C95-C71 -> -0.36 | S95: =D95-D35 -> -1 | U95: 46235 | V95: ='[2]Daily fcst'!L52 -> 3.25 | W95: =Data!H221 -> 5.25076 | X95: =Data!G221 -> 3.944082
A96: 44440 | B96: =HAVERM!B387 -> 3.61 | C96: =HAVERM!C387 -> 1.2 | D96: =HAVERM!D387 -> 1.28 | H96: =B96-L96 -> 3.51 | I96: =C96-M96 -> 0.84570455 | J96: =D96-N96 -> 0.7078 | L96: =HAVERM!E387 -> 0.1 | M96: =HAVERM!F387 -> 0.35429545 | N96: =HAVERM!G387 -> 0.5722 | P96: 44440 | Q96: =B96-B84 -> -0.04 | R96: =C96-C72 -> -0.35 | S96: =D96-D36 -> -1.06 | U96: 46266 | V96: ='[2]Daily fcst'!L53 -> 3.25 | W96: =W95+(W98-W95)*1/3 -> 5.194993 | X96: =X95+(X98-X95)*1/3 -> 3.959468
A97: 44470 | B97: =HAVERM!B388 -> 3.6 | C97: =HAVERM!C388 -> 1.29 | D97: =HAVERM!D388 -> 1.3 | H97: =B97-L97 -> 3.5 | I97: =C97-M97 -> 0.51142857 | J97: =D97-N97 -> 0.39312857 | L97: =HAVERM!E388 -> 0.1 | M97: =HAVERM!F388 -> 0.77857143 | N97: =HAVERM!G388 -> 0.90687143 | P97: 44470 | Q97: =B97-B85 -> -0.04 | R97: =C97-C73 -> -0.18 | S97: =D97-D37 -> -0.97 | U97: 46296 | V97: ='[2]Daily fcst'!L54 -> 3.25 | W97: =W96+(W98-W95)*1/3 -> 5.139226 | X97: =X96+(X98-X95)*1/3 -> 3.974854
A98: 44501 | B98: =HAVERM!B389 -> 3.59 | C98: =HAVERM!C389 -> 1.53 | D98: =HAVERM!D389 -> 1.52 | H98: =B98-L98 -> 3.49 | I98: =C98-M98 -> 0.63360909 | J98: =D98-N98 -> 0.53602727 | L98: =HAVERM!E389 -> 0.1 | M98: =HAVERM!F389 -> 0.89639091 | N98: =HAVERM!G389 -> 0.98397273 | P98: 44501 | Q98: =B98-B86 -> -0.03 | R98: =C98-C74 -> 0.12 | S98: =D98-D38 -> -0.73 | U98: 46327 | V98: ='[2]Daily fcst'!L55 -> 3.0357143 | W98: =Data!H222 -> 5.083459 | X98: =Data!G222 -> 3.99024
A99: 44531 | B99: =HAVERM!B390 -> 3.61 | C99: =HAVERM!C390 -> 1.57 | D99: =HAVERM!D390 -> 1.59 | H99: =B99-L99 -> 3.4317391 | I99: =C99-M99 -> 0.67037826 | J99: =D99-N99 -> 0.65821739 | L99: =HAVERM!E390 -> 0.17826087 | M99: =HAVERM!F390 -> 0.89962174 | N99: =HAVERM!G390 -> 0.93178261 | P99: 44531 | Q99: =B99-B87 -> -0.01 | R99: =C99-C75 -> 0.15 | S99: =D99-D39 -> -0.67 | U99: 46357 | V99: ='[2]Daily fcst'!L56 -> 3 | W99: =W98+(W101-W98)*1/3 -> 5.036864 | X99: =X98+(X101-X98)*1/3 -> 4.000583
A100: 44562 | B100: =HAVERM!B391 -> 3.67 | C100: =HAVERM!C391 -> 1.64 | D100: =HAVERM!D391 -> 1.63 | E100: 100 | H100: =B100-L100 -> 3.42 | I100: =C100-M100 -> 0.50936667 | J100: =D100-N100 -> 0.44407143 | L100: =HAVERM!E391 -> 0.25 | M100: =HAVERM!F391 -> 1.1306333 | N100: =HAVERM!G391 -> 1.1859286 | P100: 44562 | Q100: =B100-B88 -> 0.05 | R100: =C100-C76 -> 0.23 | S100: =D100-D40 -> -0.59 | W100: =W99+(W101-W98)*1/3 -> 4.990269 | X100: =X99+(X101-X98)*1/3 -> 4.010926
A101: 44593 | B101: =HAVERM!B392 -> 3.84 | C101: =HAVERM!C392 -> 1.78 | D101: =HAVERM!D392 -> 1.79 | E101: 100 | H101: =B101-L101 -> 3.365 | I101: =C101-M101 -> 0.125315 | J101: =D101-N101 -> 0.204785 | L101: =HAVERM!E392 -> 0.475 | M101: =HAVERM!F392 -> 1.654685 | N101: =HAVERM!G392 -> 1.585215 | P101: 44593 | Q101: =B101-B89 -> 0.22 | R101: =C101-C77 -> 0.38 | S101: =D101-D41 -> -0.41 | W101: =Data!H223 -> 4.943674 | X101: =Data!G223 -> 4.021269
A102: 44621 | B102: =HAVERM!B393 -> 3.99 | C102: =HAVERM!C393 -> 2.14 | D102: =HAVERM!D393 -> 2.11 | E102: 100 | H102: =B102-L102 -> 3.3704348 | I102: =C102-M102 -> 0.26233478 | J102: =D102-N102 -> 0.34684348 | L102: =HAVERM!E393 -> 0.61956522 | M102: =HAVERM!F393 -> 1.8776652 | N102: =HAVERM!G393 -> 1.7631565 | P102: 44621 | Q102: =B102-B90 -> 0.37 | R102: =C102-C78 -> 0.74 | S102: =D102-D42 -> -0.04
A103: 44652 | B103: =HAVERM!B394 -> 4.11 | C103: =HAVERM!C394 -> 2.35 | D103: =HAVERM!D394 -> 2.35 | E103: 100 | H103: =B103-L103 -> 3.36 | I103: =C103-M103 -> 0.19494762 | J103: =D103-N103 -> 0.29374286 | L103: =HAVERM!E394 -> 0.75 | M103: =HAVERM!F394 -> 2.1550524 | N103: =HAVERM!G394 -> 2.0562571 | P103: 44652 | Q103: =B103-B91 -> 0.5 | R103: =C103-C79 -> 0.97 | S103: =D103-D43 -> 0.26
A104: 44682 | B104: =HAVERM!B395 -> 4.26 | C104: =HAVERM!C395 -> 2.63 | D104: =HAVERM!D395 -> 2.62 | E104: 100 | H104: =B104-L104 -> 3.2940909 | I104: =C104-M104 -> 0.44512273 | J104: =D104-N104 -> 0.52685 | L104: =HAVERM!E395 -> 0.96590909 | M104: =HAVERM!F395 -> 2.1848773 | N104: =HAVERM!G395 -> 2.09315 | P104: 44682 | Q104: =B104-B92 -> 0.65 | R104: =C104-C80 -> 1.21 | S104: =D104-D44 -> 0.59
A105: 44713 | B105: =HAVERM!B396 -> 4.39 | C105: =HAVERM!C396 -> 2.87 | D105: =HAVERM!D396 -> 2.9 | E105: 100 | H105: =B105-L105 -> 3.265 | I105: =C105-M105 -> 0.098968182 | J105: =D105-N105 -> 0.26043182 | L105: =HAVERM!E396 -> 1.125 | M105: =HAVERM!F396 -> 2.7710318 | N105: =HAVERM!G396 -> 2.6395682 | P105: 44713 | Q105: =B105-B93 -> 0.78 | R105: =C105-C81 -> 1.46 | S105: =D105-D45 -> 0.91
A106: 44743 | B106: =HAVERM!B397 -> 4.55 | C106: =HAVERM!C397 -> 3.48 | D106: =HAVERM!D397 -> 3.43 | E106: 100 | H106: =B106-L106 -> 3.3 | I106: =C106-M106 -> 0.83590476 | J106: =D106-N106 -> 1.0384238 | L106: =HAVERM!E397 -> 1.25 | M106: =HAVERM!F397 -> 2.6440952 | N106: =HAVERM!G397 -> 2.3915762 | P106: 44743 | Q106: =B106-B94 -> 0.94 | R106: =C106-C82 -> 2.03 | S106: =D106-D46 -> 1.46
A107: 44774 | B107: =HAVERM!B398 -> 4.88 | C107: =HAVERM!C398 -> 3.6 | D107: =HAVERM!D398 -> 3.61 | E107: 100 | H107: =B107-L107 -> 3.1952174 | I107: =C107-M107 -> 0.40231304 | J107: =D107-N107 -> 0.8439087 | L107: =HAVERM!E398 -> 1.6847826 | M107: =HAVERM!F398 -> 3.197687 | N107: =HAVERM!G398 -> 2.7660913 | P107: 44774 | Q107: =B107-B95 -> 1.27 | R107: =C107-C83 -> 2 | S107: =D107-D47 -> 1.65
...

Sheet HAVERM
A1: 199001 !M | B1: UNTLMV@UK | C1: UNBV34@UK | D1: UNBV42@UK | E1: R112RD@INTDAILY | F1: M112IHH@INTDAILY | G1: M112I5Y@INTDAILY | H1: UNHSDC@UK | I1: UNHSDE@UK
A2: .DESC | B2: UK: Mortgages: Standard Variable Rate: MFIS ex Central Bank (AVG, %) | C2: UK: Mortgages: Fixed Rates: MFIS ex Central Bank: 2-Year 75% LTV (AVG, %) | D2: UK: Mortgages: Fixed Rates: MFIS ex Central Bank: 5-Year 75% LTV (AVG, %) | E2: United Kingdom: Official Bank Rate (%) | F2: UK: 24 Month Overnight Index Swap[Ann,Act/365]v SONIA:Mid Rate[2PM ET](%p.a) | G2: UK: 5 Year Overnight Index Swap[Ann,Act/365]v SONIA:Mid Rate[2PM ET](%p.a) | H2: UK: Banks Weighted Average Interest Rate, Other Loans to Nonfin Corps (%) | I2: UK: Banks Weighted Avg Interest Rate, HH Loans Secured on Dwellings (%)
A3: .T1 | B3: Jan-1995 | C3: Jan-1995 | D3: Jan-1995 | E3: Jan-1954 <- 01-Jan-1954 | F3: Aug-2014 <- 26-Aug-2014 | G3: Aug-2014 <- 26-Aug-2014 | H3: Jan-1999 | I3: Jan-1999
A4: .TN | B4: Jun-2025 | C4: Jun-2025 | D4: Jun-2025 | E4: Jun-2025 <- 10-Jul-2025 | F4: Jun-2025 <- 10-Jul-2025 | G4: Jun-2025 <- 10-Jul-2025 | H4: May-2025 | I4: May-2025
A5: .LSOURCE | B5: Bank of England | C5: Bank of England | D5: Bank of England | E5: Bank of England | F5: Tullett Prebon Information/Haver Analytics | G5: Tullett Prebon Information/Haver Analytics | H5: Bank of England | I5: Bank of England
A6: .DTLM | B6: Jul-07-2025 09:34 | C6: Jul-07-2025 09:34 | D6: Jul-07-2025 09:34 | E6: Jul-10-2025 14:17 | F6: Jul-10-2025 19:25 | G6: Jul-10-2025 19:25 | H6: Jun-30-2025 09:30 | I6: Jun-30-2025 09:30
A7: 199001 | B7: #N/A | C7: #N/A | D7: #N/A | E7: 14.875 | F7: #N/A | G7: #N/A | H7: #N/A | I7: #N/A
A8: 199002 | B8: #N/A | C8: #N/A | D8: #N/A | E8: 14.875 | F8: #N/A | G8: #N/A | H8: #N/A | I8: #N/A
A9: 199003 | B9: #N/A | C9: #N/A | D9: #N/A | E9: 14.875 | F9: #N/A | G9: #N/A | H9: #N/A | I9: #N/A
A10: 199004 | B10: #N/A | C10: #N/A | D10: #N/A | E10: 14.875 | F10: #N/A | G10: #N/A | H10: #N/A | I10: #N/A
A11: 199005 | B11: #N/A | C11: #N/A | D11: #N/A | E11: 14.875 | F11: #N/A | G11: #N/A | H11: #N/A | I11: #N/A
A12: 199006 | B12: #N/A | C12: #N/A | D12: #N/A | E12: 14.875 | F12: #N/A | G12: #N/A | H12: #N/A | I12: #N/A
A13: 199007 | B13: #N/A | C13: #N/A | D13: #N/A | E13: 14.875 | F13: #N/A | G13: #N/A | H13: #N/A | I13: #N/A
A14: 199008 | B14: #N/A | C14: #N/A | D14: #N/A | E14: 14.875 | F14: #N/A | G14: #N/A | H14: #N/A | I14: #N/A
A15: 199009 | B15: #N/A | C15: #N/A | D15: #N/A | E15: 14.875 | F15: #N/A | G15: #N/A | H15: #N/A | I15: #N/A
A16: 199010 | B16: #N/A | C16: #N/A | D16: #N/A | E16: 14.092391 | F16: #N/A | G16: #N/A | H16: #N/A | I16: #N/A
A17: 199011 | B17: #N/A | C17: #N/A | D17: #N/A | E17: 13.875 | F17: #N/A | G17: #N/A | H17: #N/A | I17: #N/A
A18: 199012 | B18: #N/A | C18: #N/A | D18: #N/A | E18: 13.875 | F18: #N/A | G18: #N/A | H18: #N/A | I18: #N/A
... A66: 199412 | B66: #N/A | C66: #N/A | D66: #N/A | E66: 6.0340909 | F66: #N/A | G66: #N/A | H66: #N/A | I66: #N/A
A67: 199501 | B67: 8.21 | C67: 8.13 | D67: 9.44 | E67: 6.125 | F67: #N/A | G67: #N/A | H67: #N/A | I67: #N/A
A68: 199502 | B68: 8.33 | C68: 8.38 | D68: 9.38 | E68: 6.6 | F68: #N/A | G68: #N/A | H68: #N/A | I68: #N/A
A69: 199503 | B69: 8.36 | C69: 8.08 | D69: 9.33 | E69: 6.625 | F69: #N/A | G69: #N/A | H69: #N/A | I69: #N/A
A70: 199504 | B70: 8.36 | C70: 8.29 | D70: 9.4 | E70: 6.625 | F70: #N/A | G70: #N/A | H70: #N/A | I70: #N/A
A71: 199505 | B71: 8.36 | C71: 8.22 | D71: 9.4 | E71: 6.625 | F71: #N/A | G71: #N/A | H71: #N/A | I71: #N/A
A72: 199506 | B72: 8.35 | C72: 7.94 | D72: 9.01 | E72: 6.625 | F72: #N/A | G72: #N/A | H72: #N/A | I72: #N/A
A73: 199507 | B73: 8.36 | C73: 7.89 | D73: 8.93 | E73: 6.625 | F73: #N/A | G73: #N/A | H73: #N/A | I73: #N/A
A74: 199508 | B74: 8.36 | C74: 7.99 | D74: 8.85 | E74: 6.625 | F74: #N/A | G74: #N/A | H74: #N/A | I74: #N/A
A75: 199509 | B75: 8.36 | C75: 7.99 | D75: 8.57 | E75: 6.625 | F75: #N/A | G75: #N/A | H75: #N/A | I75: #N/A
A76: 199510 | B76: 8 | C76: 7.99 | D76: 8.19 | E76: 6.625 | F76: #N/A | G76: #N/A | H76: #N/A | I76: #N/A
A77: 199511 | B77: 7.96 | C77: 7.99 | D77: 8.14 | E77: 6.625 | F77: #N/A | G77: #N/A | H77: #N/A | I77: #N/A
A78: 199512 | B78: 7.95 | C78: 7.99 | D78: 8.13 | E78: 6.4702381 | F78: #N/A | G78: #N/A | H78: #N/A | I78: #N/A
... A114: 199812 | B114: 8 | C114: 6.42 | D114: 6.36 | E114: 6.4021739 | F114: #N/A | G114: #N/A | H114: #N/A | I114: #N/A
A115: 199901 | B115: 7.6 | C115: 5.9 | D115: 5.9 | E115: 6.047619 | F115: #N/A | G115: #N/A | H115: 8.11 | I115: 7.41
A116: 199902 | B116: 7.35 | C116: 5.78 | D116: 5.7 | E116: 5.575 | F116: #N/A | G116: #N/A | H116: 7.69 | I116: 7.21
A117: 199903 | B117: 6.85 | C117: 5.64 | D117: 5.8 | E117: 5.5 | F117: #N/A | G117: #N/A | H117: 7.38 | I117: 6.89
A118: 199904 | B118: 6.83 | C118: 5.71 | D118: 5.89 | E118: 5.3068182 | F118: #N/A | G118: #N/A | H118: 7.14 | I118: 6.87
A119: 199905 | B119: 6.75 | C119: 5.72 | D119: 5.97 | E119: 5.25 | F119: #N/A | G119: #N/A | H119: 7.12 | I119: 6.72
A120: 199906 | B120: 6.73 | C120: 5.89 | D120: 6.29 | E120: 5.0795455 | F120: #N/A | G120: #N/A | H120: 7.05 | I120: 6.63
A121: 199907 | B121: 6.72 | C121: 6 | D121: 6.3 | E121: 5 | F121: #N/A | G121: #N/A | H121: 7.12 | I121: 6.64
A122: 199908 | B122: 6.72 | C122: 6.19 | D122: 6.64 | E122: 5 | F122: #N/A | G122: #N/A | H122: 6.98 | I122: 6.61
A123: 199909 | B123: 6.72 | C123: 6.22 | D123: 6.67 | E123: 5.1931818 | F123: #N/A | G123: #N/A | H123: 7.06 | I123: 6.6
A124: 199910 | B124: 6.82 | C124: 6.5 | D124: 6.88 | E124: 5.25 | F124: #N/A | G124: #N/A | H124: 7.13 | I124: 6.66
A125: 199911 | B125: 6.87 | C125: 6.6 | D125: 6.94 | E125: 5.4659091 | F125: #N/A | G125: #N/A | H125: 7.2 | I125: 6.72
A126: 199912 | B126: 7.1 | C126: 6.52 | D126: 6.92 | E126: 5.5 | F126: #N/A | G126: #N/A | H126: 7.27 | I126: 6.89
... A301: 201407 | B301: 4.45 | C301: 2.54 | D301: 3.78 | E301: 0.5 | F301: #N/A | G301: #N/A | H301: 3.14 | I301: 3.22
A302: 201408 | B302: 4.45 | C302: 2.54 | D302: 3.76 | E302: 0.5 | F302: 0.9812 | G302: 1.61 | H302: 3.14 | I302: 3.22
A303: 201409 | B303: 4.52 | C303: 2.46 | D303: 3.61 | E303: 0.5 | F303: 0.97872727 | G303: 1.6724045 | H303: 3.15 | I303: 3.2
A304: 201410 | B304: 4.53 | C304: 2.21 | D304: 3.27 | E304: 0.5 | F304: 0.84434783 | G304: 1.4358304 | H304: 3.15 | I304: 3.19
A305: 201411 | B305: 4.49 | C305: 2.17 | D305: 3.21 | E305: 0.5 | F305: 0.76731667 | G305: 1.3312833 | H305: 3.14 | I305: 3.19
A306: 201412 | B306: 4.48 | C306: 2.08 | D306: 3.21 | E306: 0.5 | F306: 0.70093636 | G306: 1.2005773 | H306: 3.15 | I306: 3.18
A307: 201501 | B307: 4.56 | C307: 2.01 | D307: 3.09 | E307: 0.5 | F307: 0.59257143 | G307: 0.95700476 | H307: 3.16 | I307: 3.17
A308: 201502 | B308: 4.51 | C308: 1.96 | D308: 3.05 | E308: 0.5 | F308: 0.679245 | G308: 1.12118 | H308: 3.15 | I308: 3.15
A309: 201503 | B309: 4.51 | C309: 1.99 | D309: 2.98 | E309: 0.5 | F309: 0.68714762 | G309: 1.1514048 | H309: 3.15 | I309: 3.14
A310: 201504 | B310: 4.53 | C310: 1.95 | D310: 2.92 | E310: 0.5 | F310: 0.64635238 | G310: 1.0605667 | H310: 3.13 | I310: 3.12
A311: 201505 | B311: 4.55 | C311: 1.9 | D311: 2.86 | E311: 0.5 | F311: 0.73614762 | G311: 1.2629524 | H311: 3.14 | I311: 3.11
A312: 201506 | B312: 4.49 | C312: 1.83 | D312: 2.82 | E312: 0.5 | F312: 0.78020455 | G312: 1.3520364 | H312: 3.14 | I312: 3.09
A313: 201507 | B313: 4.5 | C313: 1.87 | D313: 2.83 | E313: 0.5 | F313: 0.84573913 | G313: 1.407987 | H313: 3.13 | I313: 3.07
... A431: 202505 | B431: 7.09 | C431: 4.19 | D431: 4.22 | E431: 4.3068182 | F431: 3.7838545 | G431: 3.8071 | H431: 6.18 | I431: 3.87
A432: 202506 | B432: 6.98 | C432: 4.32 | D432: 4.3 | E432: 4.25 | F432: 3.7301143 | G432: 3.7583667

Sheet Data
C1: =GMW!C2 -> JUL009E | D1: =$C$1 -> JUL009E | E1: =$C$1 -> JUL009E | F1: =$C$1 -> JUL009E | G1: =$C$1 -> JUL009E | H1: =$C$1 -> JUL009E
C2: UK | D2: UK | E2: UK | F2: UK | G2: UK | H2: UK
C3: PEDIR_UNADJ | D3: PEDIP_UNADJ | E3: RCBEOP | F3: RLGEOP | G3: RBM | H3: RLOAN
C4: GBR | D4: GBR | E4: GBR | F4: GBR | G4: GBR | H4: GBR
C5: L | D5: L | E5: L | F5: L | G5: L | H5: L
B6: =B358+5 -> 2329 | C6: {=_xlfn.CONCAT(INDEX(GMW!$A$2:$NE$60,MATCH(1,(GMW!$NE$2:$NE$60=C$3)*(GMW!$ND$2:$ND$60=C$4),0),$B6-1966),"0",(INDEX(GMW!$A$2:$NE$60,MATCH(1,(GMW!$NE$2:$NE$60=C$3)*(GMW!$ND$2:$ND$60=C$4),0),$B6-1965)))} -> 202501 | D6: {=_xlfn.CONCAT(INDEX(GMW!$A$2:$NE$60,MATCH(1,(GMW!$NE$2:$NE$60=D$3)*(GMW!$ND$2:$ND$60=D$4),0),$B6-1966),"0",(INDEX(GMW!$A$2:$NE$60,MATCH(1,(GMW!$NE$2:$NE$60=D$3)*(GMW!$ND$2:$ND$60=D$4),0),$B6-1965)))} -> 202501 | E6: {=_xlfn.CONCAT(INDEX(GMW!$A$2:$NE$60,MATCH(1,(GMW!$NE$2:$NE$60=E$3)*(GMW!$ND$2:$ND$60=E$4),0),$B6-1966),"0",(INDEX(GMW!$A$2:$NE$60,MATCH(1,(GMW!$NE$2:$NE$60=E$3)*(GMW!$ND$2:$ND$60=E$4),0),$B6-1965)))} -> 202502 | F6: {=_xlfn.CONCAT(INDEX(GMW!$A$2:$NE$60,MATCH(1,(GMW!$NE$2:$NE$60=F$3)*(GMW!$ND$2:$ND$60=F$4),0),$B6-1966),"0",(INDEX(GMW!$A$2:$NE$60,MATCH(1,(GMW!$NE$2:$NE$60=F$3)*(GMW!$ND$2:$ND$60=F$4),0),$B6-1965)))} -> 202502 | G6: {=_xlfn.CONCAT(INDEX(GMW!$A$2:$NE$60,MATCH(1,(GMW!$NE$2:$NE$60=G$3)*(GMW!$ND$2:$ND$60=G$4),0),$B6-1966),"0",(INDEX(GMW!$A$2:$NE$60,MATCH(1,(GMW!$NE$2:$NE$60=G$3)*(GMW!$ND$2:$ND$60=G$4),0),$B6-1965)))} -> 202501 | H6: {=_xlfn.CONCAT(INDEX(GMW!$A$2:$NE$60,MATCH(1,(GMW!$NE$2:$NE$60=H$3)*(GMW!$ND$2:$ND$60=H$4),0),$B6-1966),"0",(INDEX(GMW!$A$2:$NE$60,MATCH(1,(GMW!$NE$2:$NE$60=H$3)*(GMW!$ND$2:$ND$60=H$4),0),$B6-1965)))} -> 202501
A7: 1973 | B7: 1973 | C7: {=INDEX(GMW!$A$2:$NF$60,MATCH(1,(GMW!$NE$2:$NE$60=C$3)*(GMW!$ND$2:$ND$60=C$4),0),$B7-1966)} -> 0.001 | D7: {=INDEX(GMW!$A$2:$NF$60,MATCH(1,(GMW!$NE$2:$NE$60=D$3)*(GMW!$ND$2:$ND$60=D$4),0),$B7-1966)} -> 0.001 | E7: {=INDEX(GMW!$A$2:$NF$60,MATCH(1,(GMW!$NE$2:$NE$60=E$3)*(GMW!$ND$2:$ND$60=E$4),0),$B7-1966)} -> 8.5 | F7: {=INDEX(GMW!$A$2:$NF$60,MATCH(1,(GMW!$NE$2:$NE$60=F$3)*(GMW!$ND$2:$ND$60=F$4),0),$B7-1966)} -> 0.001 | G7: {=INDEX(GMW!$A$2:$NF$60,MATCH(1,(GMW!$NE$2:$NE$60=G$3)*(GMW!$ND$2:$ND$60=G$4),0),$B7-1966)} -> 8.5 | H7: {=INDEX(GMW!$A$2:$NF$60,MATCH(1,(GMW!$NE$2:$NE$60=H$3)*(GMW!$ND$2:$ND$60=H$4),0),$B7-1966)} -> 0.001
B8: =+B7+1 -> 1974 | C8: {=INDEX(GMW!$A$2:$NF$60,MATCH(1,(GMW!$NE$2:$NE$60=C$3)*(GMW!$ND$2:$ND$60=C$4),0),$B8-1966)} -> 0.001 | D8: {=INDEX(GMW!$A$2:$NF$60,MATCH(1,(GMW!$NE$2:$NE$60=D$3)*(GMW!$ND$2:$ND$60=D$4),0),$B8-1966)} -> 0.001 | E8: {=INDEX(GMW!$A$2:$NF$60,MATCH(1,(GMW!$NE$2:$NE$60=E$3)*(GMW!$ND$2:$ND$60=E$4),0),$B8-1966)} -> 7.5 | F8: {=INDEX(GMW!$A$2:$NF$60,MATCH(1,(GMW!$NE$2:$NE$60=F$3)*(GMW!$ND$2:$ND$60=F$4),0),$B8-1966)} -> 0.001 | G8: {=INDEX(GMW!$A$2:$NF$60,MATCH(1,(GMW!$NE$2:$NE$60=G$3)*(GMW!$ND$2:$ND$60=G$4),0),$B8-1966)} -> 9.5 | H8: {=INDEX(GMW!$A$2:$NF$60,MATCH(1,(GMW!$NE$2:$NE$60=H$3)*(GMW!$ND$2:$ND$60=H$4),0),$B8-1966)} -> 0.001
B9: =+B8+1 -> 1975 | C9: {=INDEX(GMW!$A$2:$NF$60,MATCH(1,(GMW!$NE$2:$NE$60=C$3)*(GMW!$ND$2:$ND$60=C$4),0),$B9-1966)} -> 0.001 | D9: {=INDEX(GMW!$A$2:$NF$60,MATCH(1,(GMW!$NE$2:$NE$60=D$3)*(GMW!$ND$2:$ND$60=D$4),0),$B9-1966)} -> 0.001 | E9: {=INDEX(GMW!$A$2:$NF$60,MATCH(1,(GMW!$NE$2:$NE$60=E$3)*(GMW!$ND$2:$ND$60=E$4),0),$B9-1966)} -> 11.5 | F9: {=INDEX(GMW!$A$2:$NF$60,MATCH(1,(GMW!$NE$2:$NE$60=F$3)*(GMW!$ND$2:$ND$60=F$4),0),$B9-1966)} -> 0.001 | G9: {=INDEX(GMW!$A$2:$NF$60,MATCH(1,(GMW!$NE$2:$NE$60=G$3)*(GMW!$ND$2:$ND$60=G$4),0),$B9-1966)} -> 10 | H9: {=INDEX(GMW!$A$2:$NF$60,MATCH(1,(GMW!$NE$2:$NE$60=H$3)*(GMW!$ND$2:$ND$60=H$4),0),$B9-1966)} -> 0.001
B10: =+B9+1 -> 1976 | C10: {=INDEX(GMW!$A$2:$NF$60,MATCH(1,(GMW!$NE$2:$NE$60=C$3)*(GMW!$ND$2:$ND$60=C$4),0),$B10-1966)} -> 0.001 | D10: {=INDEX(GMW!$A$2:$NF$60,MATCH(1,(GMW!$NE$2:$NE$60=D$3)*(GMW!$ND$2:$ND$60=D$4),0),$B10-1966)} -> 0.001 | E10: {=INDEX(GMW!$A$2:$NF$60,MATCH(1,(GMW!$NE$2:$NE$60=E$3)*(GMW!$ND$2:$ND$60=E$4),0),$B10-1966)} -> 13 | F10: {=INDEX(GMW!$A$2:$NF$60,MATCH(1,(GMW!$NE$2:$NE$60=F$3)*(GMW!$ND$2:$ND$60=F$4),0),$B10-1966)} -> 0.001 | G10: {=INDEX(GMW!$A$2:$NF$60,MATCH(1,(GMW!$NE$2:$NE$60=G$3)*(GMW!$ND$2:$ND$60=G$4),0),$B10-1966)} -> 11 | H10: {=INDEX(GMW!$A$2:$NF$60,MATCH(1,(GMW!$NE$2:$NE$60=H$3)*(GMW!$ND$2:$ND$60=H$4),0),$B10-1966)} -> 0.001
A11: 1974 | B11: =+B10+1 -> 1977 | C11: {=INDEX(GMW!$A$2:$NF$60,MATCH(1,(GMW!$NE$2:$NE$60=C$3)*(GMW!$ND$2:$ND$60=C$4),0),$B11-1966)} -> 0.001 | D11: {=INDEX(GMW!$A$2:$NF$60,MATCH(1,(GMW!$NE$2:$NE$60=D$3)*(GMW!$ND$2:$ND$60=D$4),0),$B11-1966)} -> 0.001 | E11: {=INDEX(GMW!$A$2:$NF$60,MATCH(1,(GMW!$NE$2:$NE$60=E$3)*(GMW!$ND$2:$ND$60=E$4),0),$B11-1966)} -> 12.5 | F11: {=INDEX(GMW!$A$2:$NF$60,MATCH(1,(GMW!$NE$2:$NE$60=F$3)*(GMW!$ND$2:$ND$60=F$4),0),$B11-1966)} -> 0.001 | G11: {=INDEX(GMW!$A$2:$NF$60,MATCH(1,(GMW!$NE$2:$NE$60=G$3)*(GMW!$ND$2:$ND$60=G$4),0),$B11-1966)} -> 11 | H11: {=INDEX(GMW!$A$2:$NF$60,MATCH(1,(GMW!$NE$2:$NE$60=H$3)*(GMW!$ND$2:$ND$60=H$4),0),$B11-1966)} -> 0.001
B12: =+B11+1 -> 1978 | C12: {=INDEX(GMW!$A$2:$NF$60,MATCH(1,(GMW!$NE$2:$NE$60=C$3)*(GMW!$ND$2:$ND$60=C$4),0),$B12-1966)} -> 0.001 | D12: {=INDEX(GMW!$A$2:$NF$60,MATCH(1,(GMW!$NE$2:$NE$60=D$3)*(GMW!$ND$2:$ND$60=D$4),0),$B12-1966)} -> 0.001 | E12: {=INDEX(GMW!$A$2:$NF$60,MATCH(1,(GMW!$NE$2:$NE$60=E$3)*(GMW!$ND$2:$ND$60=E$4),0),$B12-1966)} -> 11.75 | F12: {=INDEX(GMW!$A$2:$NF$60,MATCH(1,(GMW!$NE$2:$NE$60=F$3)*(GMW!$ND$2:$ND$60=F$4),0),$B12-1966)} -> 0.001 | G12: {=INDEX(GMW!$A$2:$NF$60,MATCH(1,(GMW!$NE$2:$NE$60=G$3)*(GMW!$ND$2:$ND$60=G$4),0),$B12-1966)} -> 11 | H12: {=INDEX(GMW!$A$2:$NF$60,MATCH(1,(GMW!$NE$2:$NE$60=H$3)*(GMW!$ND$2:$ND$60=H$4),0),$B12-1966)} -> 0.001
B13: =+B12+1 -> 1979 | C13: {=INDEX(GMW!$A$2:$NF$60,MATCH(1,(GMW!$NE$2:$NE$60=C$3)*(GMW!$ND$2:$ND$60=C$4),0),$B13-1966)} -> 0.001 | D13: {=INDEX(GMW!$A$2:$NF$60,MATCH(1,(GMW!$NE$2:$NE$60=D$3)*(GMW!$ND$2:$ND$60=D$4),0),$B13-1966)} -> 0.001 | E13: {=INDEX(GMW!$A$2:$NF$60,MATCH(1,(GMW!$NE$2:$NE$60=E$3)*(GMW!$ND$2:$ND$60=E$4),0),$B13-1966)} -> 11.5 | F13: {=INDEX(GMW!$A$2:$NF$60,MATCH(1,(GMW!$NE$2:$NE$60=F$3)*(GMW!$ND$2:$ND$60=F$4),0),$B13-1966)} -> 0.001 | G13: {=INDEX(GMW!$A$2:$NF$60,MATCH(1,(GMW!$NE$2:$NE$60=G$3)*(GMW!$ND$2:$ND$60=G$4),0),$B13-1966)} -> 11 | H13: {=INDEX(GMW!$A$2:$NF$60,MATCH(1,(GMW!$NE$2:$NE$60=H$3)*(GMW!$ND$2:$ND$60=H$4),0),$B13-1966)} -> 0.001
B14: =+B13+1 -> 1980 | C14: {=INDEX(GMW!$A$2:$NF$60,MATCH(1,(GMW!$NE$2:$NE$60=C$3)*(GMW!$ND$2:$ND$60=C$4),0),$B14-1966)} -> 0.001 | D14: {=INDEX(GMW!$A$2:$NF$60,MATCH(1,(GMW!$NE$2:$NE$60=D$3)*(GMW!$ND$2:$ND$60=D$4),0),$B14-1966)} -> 0.001 | E14: {=INDEX(GMW!$A$2:$NF$60,MATCH(1,(GMW!$NE$2:$NE$60=E$3)*(GMW!$ND$2:$ND$60=E$4),0),$B14-1966)} -> 11.5 | F14: {=INDEX(GMW!$A$2:$NF$60,MATCH(1,(GMW!$NE$2:$NE$60=F$3)*(GMW!$ND$2:$ND$60=F$4),0),$B14-1966)} -> 0.001 | G14: {=INDEX(GMW!$A$2:$NF$60,MATCH(1,(GMW!$NE$2:$NE$60=G$3)*(GMW!$ND$2:$ND$60=G$4),0),$B14-1966)} -> 11 | H14: {=INDEX(GMW!$A$2:$NF$60,MATCH(1,(GMW!$NE$2:$NE$60=H$3)*(GMW!$ND$2:$ND$60=H$4),0),$B14-1966)} -> 0.001
A15: 1975 | B15: =+B14+1 -> 1981 | C15: {=INDEX(GMW!$A$2:$NF$60,MATCH(1,(GMW!$NE$2:$NE$60=C$3)*(GMW!$ND$2:$ND$60=C$4),0),$B15-1966)} -> 0.001 | D15: {=INDEX(GMW!$A$2:$NF$60,MATCH(1,(GMW!$NE$2:$NE$60=D$3)*(GMW!$ND$2:$ND$60=D$4),0),$B15-1966)} -> 0.001 | E15: {=INDEX(GMW!$A$2:$NF$60,MATCH(1,(GMW!$NE$2:$NE$60=E$3)*(GMW!$ND$2:$ND$60=E$4),0),$B15-1966)} -> 10 | F15: {=INDEX(GMW!$A$2:$NF$60,MATCH(1,(GMW!$NE$2:$NE$60=F$3)*(GMW!$ND$2:$ND$60=F$4),0),$B15-1966)} -> 0.001 | G15: {=INDEX(GMW!$A$2:$NF$60,MATCH(1,(GMW!$NE$2:$NE$60=G$3)*(GMW!$ND$2:$ND$60=G$4),0),$B15-1966)} -> 11 | H15: {=INDEX(GMW!$A$2:$NF$60,MATCH(1,(GMW!$NE$2:$NE$60=H$3)*(GMW!$ND$2:$ND$60=H$4),0),$B15-1966)} -> 0.001
B16: =+B15+1 -> 1982 | C16: {=INDEX(GMW!$A$2:$NF$60,MATCH(1,(GMW!$NE$2:$NE$60=C$3)*(GMW!$ND$2:$ND$60=C$4),0),$B16-1966)} -> 0.001 | D16: {=INDEX(GMW!$A$2:$NF$60,MATCH(1,(GMW!$NE$2:$NE$60=D$3)*(GMW!$ND$2:$ND$60=D$4),0),$B16-1966)} -> 0.001 | E16: {=INDEX(GMW!$A$2:$NF$60,MATCH(1,(GMW!$NE$2:$NE$60=E$3)*(GMW!$ND$2:$ND$60=E$4),0),$B16-1966)} -> 10 | F16: {=INDEX(GMW!$A$2:$NF$60,MATCH(1,(GMW!$NE$2:$NE$60=F$3)*(GMW!$ND$2:$ND$60=F$4),0),$B16-1966)} -> 0.001 | G16: {=INDEX(GMW!$A$2:$NF$60,MATCH(1,(GMW!$NE$2:$NE$60=G$3)*(GMW!$ND$2:$ND$60=G$4),0),$B16-1966)} -> 11 | H16: {=INDEX(GMW!$A$2:$NF$60,MATCH(1,(GMW!$NE$2:$NE$60=H$3)*(GMW!$ND$2:$ND$60=H$4),0),$B16-1966)} -> 0.001
B17: =+B16+1 -> 1983 | C17: {=INDEX(GMW!$A$2:$NF$60,MATCH(1,(GMW!$NE$2:$NE$60=C$3)*(GMW!$ND$2:$ND$60=C$4),0),$B17-1966)} -> 0.001 | D17: {=INDEX(GMW!$A$2:$NF$60,MATCH(1,(GMW!$NE$2:$NE$60=D$3)*(GMW!$ND$2:$ND$60=D$4),0),$B17-1966)} -> 0.001 | E17: {=INDEX(GMW!$A$2:$NF$60,MATCH(1,(GMW!$NE$2:$NE$60=E$3)*(GMW!$ND$2:$ND$60=E$4),0),$B17-1966)} -> 11 | F17: {=INDEX(GMW!$A$2:$NF$60,MATCH(1,(GMW!$NE$2:$NE$60=F$3)*(GMW!$ND$2:$ND$60=F$4),0),$B17-1966)} -> 0.001 | G17: {=INDEX(GMW!$A$2:$NF$60,MATCH(1,(GMW!$NE$2:$NE$60=G$3)*(GMW!$ND$2:$ND$60=G$4),0),$B17-1966)} -> 11 | H17: {=INDEX(GMW!$A$2:$NF$60,MATCH(1,(GMW!$NE$2:$NE$60=H$3)*(GMW!$ND$2:$ND$60=H$4),0),$B17-1966)} -> 0.001
B18: =+B17+1 -> 1984 | C18: {=INDEX(GMW!$A$2:$NF$60,MATCH(1,(GMW!$NE$2:$NE$60=C$3)*(GMW!$ND$2:$ND$60=C$4),0),$B18-1966)} -> 0.001 | D18: {=INDEX(GMW!$A$2:$NF$60,MATCH(1,(GMW!$NE$2:$NE$60=D$3)*(GMW!$ND$2:$ND$60=D$4),0),$B18-1966)} -> 0.001 | E18: {=INDEX(GMW!$A$2:$NF$60,MATCH(1,(GMW!$NE$2:$NE$60=E$3)*(GMW!$ND$2:$ND$60=E$4),0),$B18-1966)} -> 11.25 | F18: {=INDEX(GMW!$A$2:$NF$60,MATCH(1,(GMW!$NE$2:$NE$60=F$3)*(GMW!$ND$2:$ND$60=F$4),0),$B18-1966)} -> 0.001 | G18: {=INDEX(GMW!$A$2:$NF$60,MATCH(1,(GMW!$NE$2:$NE$60=G$3)*(GMW!$ND$2:$ND$60=G$4),0),$B18-1966)} -> 11 | H18: {=INDEX(GMW!$A$2:$NF$60,MATCH(1,(GMW!$NE$2:$NE$60=H$3)*(GMW!$ND$2:$ND$60=H$4),0),$B18-1966)} -> 0.001
A19: 1976 | B19: =+B18+1 -> 1985 | C19: {=INDEX(GMW!$A$2:$NF$60,MATCH(1,(GMW!$NE$2:$NE$60=C$3)*(GMW!$ND$2:$ND$60=C$4),0),$B19-1966)} -> 0.001 | D19: {=INDEX(GMW!$A$2:$NF$60,MATCH(1,(GMW!$NE$2:$NE$60=D$3)*(GMW!$ND$2:$ND$60=D$4),0),$B19-1966)} -> 0.001 | E19: {=INDEX(GMW!$A$2:$NF$60,MATCH(1,(GMW!$NE$2:$NE$60=E$3)*(GMW!$ND$2:$ND$60=E$4),0),$B19-1966)} -> 9 | F19: {=INDEX(GMW!$A$2:$NF$60,MATCH(1,(GMW!$NE$2:$NE$60=F$3)*(GMW!$ND$2:$ND$60=F$4),0),$B19-1966)} -> 0.001 | G19: {=INDEX(GMW!$A$2:$NF$60,MATCH(1,(GMW!$NE$2:$NE$60=G$3)*(GMW!$ND$2:$ND$60=G$4),0),$B19-1966)} -> 11 | H19: {=INDEX(GMW!$A$2:$NF$60,MATCH(1,(GMW!$NE$2:$NE$60=H$3)*(GMW!$ND$2:$ND$60=H$4),0),$B19-1966)} -> 0.001
B20: =+B19+1 -> 1986 | C20: {=INDEX(GMW!$A$2:$NF$60,MATCH(1,(GMW!$NE$2:$NE$60=C$3)*(GMW!$ND$2:$ND$60=C$4),0),$B20-1966)} -> 0.001 | D20: {=INDEX(GMW!$A$2:$NF$60,MATCH(1,(GMW!$NE$2:$NE$60=D$3)*(GMW!$ND$2:$ND$60=D$4),0),$B20-1966)} -> 0.001 | E20: {=INDEX(GMW!$A$2:$NF$60,MATCH(1,(GMW!$NE$2:$NE$60=E$3)*(GMW!$ND$2:$ND$60=E$4),0),$B20-1966)} -> 11.5 | F20: {=INDEX(GMW!$A$2:$NF$60,MATCH(1,(GMW!$NE$2:$NE$60=F$3)*(GMW!$ND$2:$ND$60=F$4),0),$B20-1966)} -> 0.001 | G20: {=INDEX(GMW!$A$2:$NF$60,MATCH(1,(GMW!$NE$2:$NE$60=G$3)*(GMW!$ND$2:$ND$60=G$4),0),$B20-1966)} -> 10.5 | H20: {=INDEX(GMW!$A$2:$NF$60,MATCH(1,(GMW!$NE$2:$NE$60=H$3)*(GMW!$ND$2:$ND$60=H$4),0),$B20-1966)} -> 0.001
B21: =+B20+1 -> 1987 | C21: {=INDEX(GMW!$A$2:$NF$60,MATCH(1,(GMW!$NE$2:$NE$60=C$3)*(GMW!$ND$2:$ND$60=C$4),0),$B21-1966)} -> 0.001 | D21: {=INDEX(GMW!$A$2:$NF$60,MATCH(1,(GMW!$NE$2:$NE$60=D$3)*(GMW!$ND$2:$ND$60=D$4),0),$B21-1966)} -> 0.001 | E21: {=INDEX(GMW!$A$2:$NF$60,MATCH(1,(GMW!$NE$2:$NE$60=E$3)*(GMW!$ND$2:$ND$60=E$4),0),$B21-1966)} -> 13 | F21: {=INDEX(GMW!$A$2:$NF$60,MATCH(1,(GMW!$NE$2:$NE$60=F$3)*(GMW!$ND$2:$ND$60=F$4),0),$B21-1966)} -> 0.001 | G21: {=INDEX(GMW!$A$2:$NF$60,MATCH(1,(GMW!$NE$2:$NE$60=G$3)*(GMW!$ND$2:$ND$60=G$4),0),$B21-1966)} -> 10.5 | H21: {=INDEX(GMW!$A$2:$NF$60,MATCH(1,(GMW!$NE$2:$NE$60=H$3)*(GMW!$ND$2:$ND$60=H$4),0),$B21-1966)} -> 0.001
B22: =+B21+1 -> 1988 | C22: {=INDEX(GMW!$A$2:$NF$60,MATCH(1,(GMW!$NE$2:$NE$60=C$3)*(GMW!$ND$2:$ND$60=C$4),0),$B22-1966)} -> 0.001 | D22: {=INDEX(GMW!$A$2:$NF$60,MATCH(1,(GMW!$NE$2:$NE$60=D$3)*(GMW!$ND$2:$ND$60=D$4),0),$B22-1966)} -> 0.001 | E22: {=INDEX(GMW!$A$2:$NF$60,MATCH(1,(GMW!$NE$2:$NE$60=E$3)*(GMW!$ND$2:$ND$60=E$4),0),$B22-1966)} -> 14.25 | F22: {=INDEX(GMW!$A$2:$NF$60,MATCH(1,(GMW!$NE$2:$NE$60=F$3)*(GMW!$ND$2:$ND$60=F$4),0),$B22-1966)} -> 0.001 | G22: {=INDEX(GMW!$A$2:$NF$60,MATCH(1,(GMW!$NE$2:$NE$60=G$3)*(GMW!$ND$2:$ND$60=G$4),0),$B22-1966)} -> 12.25 | H22: {=INDEX(GMW!$A$2:$NF$60,MATCH(1,(GMW!$NE$2:$NE$60=H$3)*(GMW!$ND$2:$ND$60=H$4),0),$B22-1966)} -> 0.001
A23: 1977 | B23: =+B22+1 -> 1989 | C23: {=INDEX(GMW!$A$2:$NF$60,MATCH(1,(GMW!$NE$2:$NE$60=C$3)*(GMW!$ND$2:$ND$60=C$4),0),$B23-1966)} -> 0.001 | D23: {=INDEX(GMW!$A$2:$NF$60,MATCH(1,(GMW!$NE$2:$NE$60=D$3)*(GMW!$ND$2:$ND$60=D$4),0),$B23-1966)} -> 0.001 | E23: {=INDEX(GMW!$A$2:$NF$60,MATCH(1,(GMW!$NE$2:$NE$60=E$3)*(GMW!$ND$2:$ND$60=E$4),0),$B23-1966)} -> 9.5 | F23: {=INDEX(GMW!$A$2:$NF$60,MATCH(1,(GMW!$NE$2:$NE$60=F$3)*(GMW!$ND$2:$ND$60=F$4),0),$B23-1966)} -> 0.001 | G23: {=INDEX(GMW!$A$2:$NF$60,MATCH(1,(GMW!$NE$2:$NE$60=G$3)*(GMW!$ND$2:$ND$60=G$4),0),$B23-1966)} -> 12.25 | H23: {=INDEX(GMW!$A$2:$NF$60,MATCH(1,(GMW!$NE$2:$NE$60=H$3)*(GMW!$ND$2:$ND$60=H$4),0),$B23-1966)} -> 0.001
B24: =+B23+1 -> 1990 | C24: {=INDEX(GMW!$A$2:$NF$60,MATCH(1,(GMW!$NE$2:$NE$60=C$3)*(GMW!$ND$2:$ND$60=C$4),0),$B24-1966)} -> 0.001 | D24: {=INDEX(GMW!$A$2:$NF$60,MATCH(1,(GMW!$NE$2:$NE$60=D$3)*(GMW!$ND$2:$ND$60=D$4),0),$B24-1966)} -> 0.001 | E24: {=INDEX(GMW!$A$2:$NF$60,MATCH(1,(GMW!$NE$2:$NE$60=E$3)*(GMW!$ND$2:$ND$60=E$4),0),$B24-1966)} -> 8 | F24: {=INDEX(GMW!$A$2:$NF$60,MATCH(1,(GMW!$NE$2:$NE$60=F$3)*(GMW!$ND$2:$ND$60=F$4),0),$B24-1966)} -> 0.001 | G24: {=INDEX(GMW!$A$2:$NF$60,MATCH(1,(GMW!$NE$2:$NE$60=G$3)*(GMW!$ND$2:$ND$60=G$4),0),$B24-1966)} -> 11.25 | H24: {=INDEX(GMW!$A$2:$NF$60,MATCH(1,(GMW!$NE$2:$NE$60=H$3)*(GMW!$ND$2:$ND$60=H$4),0),$B24-1966)} -> 0.001
B25: =+B24+1 -> 1991 | C25: {=INDEX(GMW!$A$2:$NF$60,MATCH(1,(GMW!$NE$2:$NE$60=C$3)*(GMW!$ND$2:$ND$60=C$4),0),$B25-1966)} -> 0.001 | D25: {=INDEX(GMW!$A$2:$NF$60,MATCH(1,(GMW!$NE$2:$NE$60=D$3)*(GMW!$ND$2:$ND$60=D$4),0),$B25-1966)} -> 0.001 | E25: {=INDEX(GMW!$A$2:$NF$60,MATCH(1,(GMW!$NE$2:$NE$60=E$3)*(GMW!$ND$2:$ND$60=E$4),0),$B25-1966)} -> 6 | F25: {=INDEX(GMW!$A$2:$NF$60,MATCH(1,(GMW!$NE$2:$NE$60=F$3)*(GMW!$ND$2:$ND$60=F$4),0),$B25-1966)} -> 0.001 | G25: {=INDEX(GMW!$A$2:$NF$60,MATCH(1,(GMW!$NE$2:$NE$60=G$3)*(GMW!$ND$2:$ND$60=G$4),0),$B25-1966)} -> 10.5 | H25: {=INDEX(GMW!$A$2:$NF$60,MATCH(1,(GMW!$NE$2:$NE$60=H$3)*(GMW!$ND$2:$ND$60=H$4),0),$B25-1966)} -> 0.001
B26: =+B25+1 -> 1992 | C26: {=INDEX(GMW!$A$2:$NF$60,MATCH(1,(GMW!$NE$2:$NE$60=C$3)*(GMW!$ND$2:$ND$60=C$4),0),$B26-1966)} -> 0.001 | D26: {=INDEX(GMW!$A$2:$NF$60,MATCH(1,(GMW!$NE$2:$NE$60=D$3)*(GMW!$ND$2:$ND$60=D$4),0),$B26-1966)} -> 0.001 | E26: {=INDEX(GMW!$A$2:$NF$60,MATCH(1,(GMW!$NE$2:$NE$60=E$3)*(GMW!$ND$2:$ND$60=E$4),0),$B26-1966)} -> 7 | F26: {=INDEX(GMW!$A$2:$NF$60,MATCH(1,(GMW!$NE$2:$NE$60=F$3)*(GMW!$ND$2:$ND$60=F$4),0),$B26-1966)} -> 0.001 | G26: {=INDEX(GMW!$A$2:$NF$60,MATCH(1,(GMW!$NE$2:$NE$60=G$3)*(GMW!$ND$2:$ND$60=G$4),0),$B26-1966)} -> 9.5 | H26: {=INDEX(GMW!$A$2:$NF$60,MATCH(1,(GMW!$NE$2:$NE$60=H$3)*(GMW!$ND$2:$ND$60=H$4),0),$B26-1966)} -> 0.001
A27: 1978 | B27: =+B26+1 -> 1993 | C27: {=INDEX(GMW!$A$2:$NF$60,MATCH(1,(GMW!$NE$2:$NE$60=C$3)*(GMW!$ND$2:$ND$60=C$4),0),$B27-1966)} -> 0.001 | D27: {=INDEX(GMW!$A$2:$NF$60,MATCH(1,(GMW!$NE$2:$NE$60=D$3)*(GMW!$ND$2:$ND$60=D$4),0),$B27-1966)} -> 0.001 | E27: {=INDEX(GMW!$A$2:$NF$60,MATCH(1,(GMW!$NE$2:$NE$60=E$3)*(GMW!$ND$2:$ND$60=E$4),0),$B27-1966)} -> 6.5 | F27: {=INDEX(GMW!$A$2:$NF$60,MATCH(1,(GMW!$NE$2:$NE$60=F$3)*(GMW!$ND$2:$ND$60=F$4),0),$B27-1966)} -> 0.001 | G27: {=INDEX(GMW!$A$2:$NF$60,MATCH(1,(GMW!$NE$2:$NE$60=G$3)*(GMW!$ND$2:$ND$60=G$4),0),$B27-1966)} -> 8.5 | H27: {=INDEX(GMW!$A$2:$NF$60,MATCH(1,(GMW!$NE$2:$NE$60=H$3)*(GMW!$ND$2:$ND$60=H$4),0),$B27-1966)} -> 0.001
B28: =+B27+1 -> 1994 | C28: {=INDEX(GMW!$A$2:$NF$60,MATCH(1,(GMW!$NE$2:$NE$60=C$3)*(GMW!$ND$2:$ND$60=C$4),0),$B28-1966)} -> 0.001 | D28: {=INDEX(GMW!$A$2:$NF$60,MATCH(1,(GMW!$NE$2:$NE$60=D$3)*(GMW!$ND$2:$ND$60=D$4),0),$B28-1966)} -> 0.001 | E28: {=INDEX(GMW!$A$2:$NF$60,MATCH(1,(GMW!$NE$2:$NE$60=E$3)*(GMW!$ND$2:$ND$60=E$4),0),$B28-1966)} -> 10 | F28: {=INDEX(GMW!$A$2:$NF$60,MATCH(1,(GMW!$NE$2:$NE$60=F$3)*(GMW!$ND$2:$ND$60=F$4),0),$B28-1966)} -> 0.001 | G28: {=INDEX(GMW!$A$2:$NF$60,MATCH(1,(GMW!$NE$2:$NE$60=G$3)*(GMW!$ND$2:$ND$60=G$4),0),$B28-1966)} -> 8.5 | H28: {=INDEX(GMW!$A$2:$NF$60,MATCH(1,(GMW!$NE$2:$NE$60=H$3)*(GMW!$ND$2:$ND$60=H$4),0),$B28-1966)} -> 0.001
B29: =+B28+1 -> 1995 | C29: {=INDEX(GMW!$A$2:$NF$60,MATCH(1,(GMW!$NE$2:$NE$60=C$3)*(GMW!$ND$2:$ND$60=C$4),0),$B29-1966)} -> 0.001 | D29: {=INDEX(GMW!$A$2:$NF$60,MATCH(1,(GMW!$NE$2:$NE$60=D$3)*(GMW!$ND$2:$ND$60=D$4),0),$B29-1966)} -> 0.001 | E29: {=INDEX(GMW!$A$2:$NF$60,MATCH(1,(GMW!$NE$2:$NE$60=E$3)*(GMW!$ND$2:$ND$60=E$4),0),$B29-1966)} -> 10 | F29: {=INDEX(GMW!$A$2:$NF$60,MATCH(1,(GMW!$NE$2:$NE$60=F$3)*(GMW!$ND$2:$ND$60=F$4),0),$B29-1966)} -> 0.001 | G29: {=INDEX(GMW!$A$2:$NF$60,MATCH(1,(GMW!$NE$2:$NE$60=G$3)*(GMW!$ND$2:$ND$60=G$4),0),$B29-1966)} -> 9.75 | H29: {=INDEX(GMW!$A$2:$NF$60,MATCH(1,(GMW!$NE$2:$NE$60=H$3)*(GMW!$ND$2:$ND$60=H$4),0),$B29-1966)} -> 0.001
B30: =+B29+1 -> 1996 | C30: {=INDEX(GMW!$A$2:$NF$60,MATCH(1,(GMW!$NE$2:$NE$60=C$3)*(GMW!$ND$2:$ND$60=C$4),0),$B30-1966)} -> 0.001 | D30: {=INDEX(GMW!$A$2:$NF$60,MATCH(1,(GMW!$NE$2:$NE$60=D$3)*(GMW!$ND$2:$ND$60=D$4),0),$B30-1966)} -> 0.001 | E30: {=INDEX(GMW!$A$2:$NF$60,MATCH(1,(GMW!$NE$2:$NE$60=E$3)*(GMW!$ND$2:$ND$60=E$4),0),$B30-1966)} -> 12.5 | F30: {=INDEX(GMW!$A$2:$NF$60,MATCH(1,(GMW!$NE$2:$NE$60=F$3)*(GMW!$ND$2:$ND$60=F$4),0),$B30-1966)} -> 0.001 | G30: {=INDEX(GMW!$A$2:$NF$60,MATCH(1,(GMW!$NE$2:$NE$60=G$3)*(GMW!$ND$2:$ND$60=G$4),0),$B30-1966)} -> 10.42 | H30: {=INDEX(GMW!$A$2:$NF$60,MATCH(1,(GMW!$NE$2:$NE$60=H$3)*(GMW!$ND$2:$ND$60=H$4),0),$B30-1966)} -> 0.001
A31: 1979 | B31: =+B30+1 -> 1997 | C31: {=INDEX(GMW!$A$2:$NF$60,MATCH(1,(GMW!$NE$2:$NE$60=C$3)*(GMW!$ND$2:$ND$60=C$4),0),$B31-1966)} -> 0.001 | D31: {=INDEX(GMW!$A$2:$NF$60,MATCH(1,(GMW!$NE$2:$NE$60=D$3)*(GMW!$ND$2:$ND$60=D$4),0),$B31-1966)} -> 0.001 | E31: {=INDEX(GMW!$A$2:$NF$60,MATCH(1,(GMW!$NE$2:$NE$60=E$3)*(GMW!$ND$2:$ND$60=E$4),0),$B31-1966)} -> 13 | F31: {=INDEX(GMW!$A$2:$NF$60,MATCH(1,(GMW!$NE$2:$NE$60=F$3)*(GMW!$ND$2:$ND$60=F$4),0),$B31-1966)} -> 0.001 | G31: {=INDEX(GMW!$A$2:$NF$60,MATCH(1,(GMW!$NE$2:$NE$60=G$3)*(GMW!$ND$2:$ND$60=G$4),0),$B31-1966)} -> 11.75 | H31: {=INDEX(GMW!$A$2:$NF$60,MATCH(1,(GMW!$NE$2:$NE$60=H$3)*(GMW!$ND$2:$ND$60=H$4),0),$B31-1966)} -> 0.001
B32: =+B31+1 -> 1998 | C32: {=INDEX(GMW!$A$2:$NF$60,MATCH(1,(GMW!$NE$2:$NE$60=C$3)*(GMW!$ND$2:$ND$60=C$4),0),$B32-1966)} -> 0.001 | D32: {=INDEX(GMW!$A$2:$NF$60,MATCH(1,(GMW!$NE$2:$NE$60=D$3)*(GMW!$ND$2:$ND$60=D$4),0),$B32-1966)} -> 0.001 | E32: {=INDEX(GMW!$A$2:$NF$60,MATCH(1,(GMW!$NE$2:$NE$60=E$3)*(GMW!$ND$2:$ND$60=E$4),0),$B32-1966)} -> 14 | F32: {=INDEX(GMW!$A$2:$NF$60,MATCH(1,(GMW!$NE$2:$NE$60=F$3)*(GMW!$ND$2:$ND$60=F$4),0),$B32-1966)} -> 0.001 | G32: {=INDEX(GMW!$A$2:$NF$60,MATCH(1,(GMW!$NE$2:$NE$60=G$3)*(GMW!$ND$2:$ND$60=G$4),0),$B32-1966)} -> 11.246 | H32: {=INDEX(GMW!$A$2:$NF$60,MATCH(1,(GMW!$NE$2:$NE$60=H$3)*(GMW!$ND$2:$ND$60=H$4),0),$B32-1966)} -> 0.001
B33: =+B32+1 -> 1999 | C33: {=INDEX(GMW!$A$2:$NF$60,MATCH(1,(GMW!$NE$2:$NE$60=C$3)*(GMW!$ND$2:$ND$60=C$4),0),$B33-1966)} -> 0.001 | D33: {=INDEX(GMW!$A$2:$NF$60,MATCH(1,(GMW!$NE$2:$NE$60=D$3)*(GMW!$ND$2:$ND$60=D$4),0),$B33-1966)} -> 0.001 | E33: {=INDEX(GMW!$A$2:$NF$60,MATCH(1,(GMW!$NE$2:$NE$60=E$3)*(GMW!$ND$2:$ND$60=E$4),0),$B33-1966)} -> 14 | F33: {=INDEX(GMW!$A$2:$NF$60,MATCH(1,(GMW!$NE$2:$NE$60=F$3)*(GMW!$ND$2:$ND$60=F$4),0),$B33-1966)} -> 0.001 | G33: {=INDEX(GMW!$A$2:$NF$60,MATCH(1,(GMW!$NE$2:$NE$60=G$3)*(GMW!$ND$2:$ND$60=G$4),0),$B33-1966)} -> 11.75 | H33: {=INDEX(GMW!$A$2:$NF$60,MATCH(1,(GMW!$NE$2:$NE$60=H$3)*(GMW!$ND$2:$ND$60=H$4),0),$B33-1966)} -> 0.001
B34: =+B33+1 -> 2000 | C34: {=INDEX(GMW!$A$2:$NF$60,MATCH(1,(GMW!$NE$2:$NE$60=C$3)*(GMW!$ND$2:$ND$60=C$4),0),$B34-1966)} -> 0.001 | D34: {=INDEX(GMW!$A$2:$NF$60,MATCH(1,(GMW!$NE$2:$NE$60=D$3)*(GMW!$ND$2:$ND$60=D$4),0),$B34-1966)} -> 0.001 | E34: {=INDEX(GMW!$A$2:$NF$60,MATCH(1,(GMW!$NE$2:$NE$60=E$3)*(GMW!$ND$2:$ND$60=E$4),0),$B34-1966)} -> 17 | F34: {=INDEX(GMW!$A$2:$NF$60,MATCH(1,(GMW!$NE$2:$NE$60=F$3)*(GMW!$ND$2:$ND$60=F$4),0),$B34-1966)} -> 0.001 | G34: {=INDEX(GMW!$A$2:$NF$60,MATCH(1,(GMW!$NE$2:$NE$60=G$3)*(GMW!$ND$2:$ND$60=G$4),0),$B34-1966)} -> 13.38 | H34: {=INDEX(GMW!$A$2:$NF$60,MATCH(1,(GMW!$NE$2:$NE$60=H$3)*(GMW!$ND$2:$ND$60=H$4),0),$B34-1966)} -> 0.001
A35: 1980 | B35: =+B34+1 -> 2001 | C35: {=INDEX(GMW!$A$2:$NF$60,MATCH(1,(GMW!$NE$2:$NE$60=C$3)*(GMW!$ND$2:$ND$60=C$4),0),$B35-1966)} -> 0.001 | D35: {=INDEX(GMW!$A$2:$NF$60,MATCH(1,(GMW!$NE$2:$NE$60=D$3)*(GMW!$ND$2:$ND$60=D$4),0),$B35-1966)} -> 0.001 | E35: {=INDEX(GMW!$A$2:$NF$60,MATCH(1,(GMW!$NE$2:$NE$60=E$3)*(GMW!$ND$2:$ND$60=E$4),0),$B35-1966)} -> 17 | F35: {=INDEX(GMW!$A$2:$NF$60,MATCH(1,(GMW!$NE$2:$NE$60=F$3)*(GMW!$ND$2:$ND$60=F$4),0),$B35-1966)} -> 0.001 | G35: {=INDEX(GMW!$A$2:$NF$60,MATCH(1,(GMW!$NE$2:$NE$60=G$3)*(GMW!$ND$2:$ND$60=G$4),0),$B35-1966)} -> 14.7821 | H35: {=INDEX(GMW!$A$2:$NF$60,MATCH(1,(GMW!$NE$2:$NE$60=H$3)*(GMW!$ND$2:$ND$60=H$4),0),$B35-1966)} -> 21.73742
B36: =+B35+1 -> 2002 | C36: {=INDEX(GMW!$A$2:$NF$60,MATCH(1,(GMW!$NE$2:$NE$60=C$3)*(GMW!$ND$2:$ND$60=C$4),0),$B36-1966)} -> 0.001 | D36: {=INDEX(GMW!$A$2:$NF$60,MATCH(1,(GMW!$NE$2:$NE$60=D$3)*(GMW!$ND$2:$ND$60=D$4),0),$B36-1966)} -> 0.001 | E36: {=INDEX(GMW!$A$2:$NF$60,MATCH(1,(GMW!$NE$2:$NE$60=E$3)*(GMW!$ND$2:$ND$60=E$4),0),$B36-1966)} -> 17 | F36: {=INDEX(GMW!$A$2:$NF$60,MATCH(1,(GMW!$NE$2:$NE$60=F$3)*(GMW!$ND$2:$ND$60=F$4),0),$B36-1966)} -> 0.001 | G36: {=INDEX(GMW!$A$2:$NF$60,MATCH(1,(GMW!$NE$2:$NE$60=G$3)*(GMW!$ND$2:$ND$60=G$4),0),$B36-1966)} -> 14.8755 | H36: {=INDEX(GMW!$A$2:$NF$60,MATCH(1,(GMW!$NE$2:$NE$60=H$3)*(GMW!$ND$2:$ND$60=H$4),0),$B36-1966)} -> 21.10538
B37: =+B36+1 -> 2003 | C37: {=INDEX(GMW!$A$2:$NF$60,MATCH(1,(GMW!$NE$2:$NE$60=C$3)*(GMW!$ND$2:$ND$60=C$4),0),$B37-1966)} -> 0.001 | D37: {=INDEX(GMW!$A$2:$NF$60,MATCH(1,(GMW!$NE$2:$NE$60=D$3)*(GMW!$ND$2:$ND$60=D$4),0),$B37-1966)} -> 0.001 | E37: {=INDEX(GMW!$A$2:$NF$60,MATCH(1,(GMW!$NE$2:$NE$60=E$3)*(GMW!$ND$2:$ND$60=E$4),0),$B37-1966)} -> 16 | F37: {=INDEX(GMW!$A$2:$NF$60,MATCH(1,(GMW!$NE$2:$NE$60=F$3)*(GMW!$ND$2:$ND$60=F$4),0),$B37-1966)} -> 0.001 | G37: {=INDEX(GMW!$A$2:$NF$60,MATCH(1,(GMW!$NE$2:$NE$60=G$3)*(GMW!$ND$2:$ND$60=G$4),0),$B37-1966)} -> 14.8876 | H37: {=INDEX(GMW!$A$2:$NF$60,MATCH(1,(GMW!$NE$2:$NE$60=H$3)*(GMW!$ND$2:$ND$60=H$4),0),$B37-1966)} -> 20.08708
B38: =+B37+1 -> 2004 | C38: {=INDEX(GMW!$A$2:$NF$60,MATCH(1,(GMW!$NE$2:$NE$60=C$3)*(GMW!$ND$2:$ND$60=C$4),0),$B38-1966)} -> 0.001 | D38: {=INDEX(GMW!$A$2:$NF$60,MATCH(1,(GMW!$NE$2:$NE$60=D$3)*(GMW!$ND$2:$ND$60=D$4),0),$B38-1966)} -> 0.001 | E38: {=INDEX(GMW!$A$2:$NF$60,MATCH(1,(GMW!$NE$2:$NE$60=E$3)*(GMW!$ND$2:$ND$60=E$4),0),$B38-1966)} -> 14 | F38: {=INDEX(GMW!$A$2:$NF$60,MATCH(1,(GMW!$NE$2:$NE$60=F$3)*(GMW!$ND$2:$ND$60=F$4),0),$B38-1966)} -> 0.001 | G38: {=INDEX(GMW!$A$2:$NF$60,MATCH(1,(GMW!$NE$2:$NE$60=G$3)*(GMW!$ND$2:$ND$60=G$4),0),$B38-1966)} -> 14.9682 | H38: {=INDEX(GMW!$A$2:$NF$60,MATCH(1,(GMW!$NE$2:$NE$60=H$3)*(GMW!$ND$2:$ND$60=H$4),0),$B38-1966)} -> 20.07705
A39: 1981 | B39: =+B38+1 -> 2005 | C39: {=INDEX(GMW!$A$2:$NF$60,MATCH(1,(GMW!$NE$2:$NE$60=C$3)*(GMW!$ND$2:$ND$60=C$4),0),$B39-1966)} -> 0.001 | D39: {=INDEX(GMW!$A$2:$NF$60,MATCH(1,(GMW!$NE$2:$NE$60=D$3)*(GMW!$ND$2:$ND$60=D$4),0),$B39-1966)} -> 0.001 | E39: {=INDEX(GMW!$A$2:$NF$60,MATCH(1,(GMW!$NE$2:$NE$60=E$3)*(GMW!$ND$2:$ND$60=E$4),0),$B39-1966)} -> 12 | F39: {=INDEX(GMW!$A$2:$NF$60,MATCH(1,(GMW!$NE$2:$NE$60=F$3)*(GMW!$ND$2:$ND$60=F$4),0),$B39-1966)} -> 0.001 | G39: {=INDEX(GMW!$A$2:$NF$60,MATCH(1,(GMW!$NE$2:$NE$60=G$3)*(GMW!$ND$2:$ND$60=G$4),0),$B39-1966)} -> 13.8888 | H39: {=INDEX(GMW!$A$2:$NF$60,MATCH(1,(GMW!$NE$2:$NE$60=H$3)*(GMW!$ND$2:$ND$60=H$4),0),$B39-1966)} -> 20.83951
B40: =+B39+1 -> 2006 | C40: {=INDEX(GMW!$A$2:$NF$60,MATCH(1,(GMW!$NE$2:$NE$60=C$3)*(GMW!$ND$2:$ND$60=C$4),0),$B40-1966)} -> 0.001 | D40: {=INDEX(GMW!$A$2:$NF$60,MATCH(1,(GMW!$NE$2:$NE$60=D$3)*(GMW!$ND$2:$ND$60=D$4),0),$B40-1966)} -> 0.001 | E40: {=INDEX(GMW!$A$2:$NF$60,MATCH(1,(GMW!$NE$2:$NE$60=E$3)*(GMW!$ND$2:$ND$60=E$4),0),$B40-1966)} -> 12 | F40: {=INDEX(GMW!$A$2:$NF$60,MATCH(1,(GMW!$NE$2:$NE$60=F$3)*(GMW!$ND$2:$ND$60=F$4),0),$B40-1966)} -> 0.001 | G40: {=INDEX(GMW!$A$2:$NF$60,MATCH(1,(GMW!$NE$2:$NE$60=G$3)*(GMW!$ND$2:$ND$60=G$4),0),$B40-1966)} -> 13.0457 | H40: {=INDEX(GMW!$A$2:$NF$60,MATCH(1,(GMW!$NE$2:$NE$60=H$3)*(GMW!$ND$2:$ND$60=H$4),0),$B40-1966)} -> 21.33612
B41: =+B40+1 -> 2007 | C41: {=INDEX(GMW!$A$2:$NF$60,MATCH(1,(GMW!$NE$2:$NE$60=C$3)*(GMW!$ND$2:$ND$60=C$4),0),$B41-1966)} -> 0.001 | D41: {=INDEX(GMW!$A$2:$NF$60,MATCH(1,(GMW!$NE$2:$NE$60=D$3)*(GMW!$ND$2:$ND$60=D$4),0),$B41-1966)} -> 0.001 | E41: {=INDEX(GMW!$A$2:$NF$60,MATCH(1,(GMW!$NE$2:$NE$60=E$3)*(GMW!$ND$2:$ND$60=E$4),0),$B41-1966)} -> 14 | F41: {=INDEX(GMW!$A$2:$NF$60,MATCH(1,(GMW!$NE$2:$NE$60=F$3)*(GMW!$ND$2:$ND$60=F$4),0),$B41-1966)} -> 0.001 | G41: {=INDEX(GMW!$A$2:$NF$60,MATCH(1,(GMW!$NE$2:$NE$60=G$3)*(GMW!$ND$2:$ND$60=G$4),0),$B41-1966)} -> 12.6246 | H41: {=INDEX(GMW!$A$2:$NF$60,MATCH(1,(GMW!$NE$2:$NE$60=H$3)*(GMW!$ND$2:$ND$60=H$4),0),$B41-1966)} -> 22.99147
B42: =+B41+1 -> 2008 | C42: {=INDEX(GMW!$A$2:$NF$60,MATCH(1,(GMW!$NE$2:$NE$60=C$3)*(GMW!$ND$2:$ND$60=C$4),0),$B42-1966)} -> 0.001 | D42: {=INDEX(GMW!$A$2:$NF$60,MATCH(1,(GMW!$NE$2:$NE$60=D$3)*(GMW!$ND$2:$ND$60=D$4),0),$B42-1966)} -> 0.001 | E42: {=INDEX(GMW!$A$2:$NF$60,MATCH(1,(GMW!$NE$2:$NE$60=E$3)*(GMW!$ND$2:$ND$60=E$4),0),$B42-1966)} -> 14.375 | F42: {=INDEX(GMW!$A$2:$NF$60,MATCH(1,(GMW!$NE$2:$NE$60=F$3)*(GMW!$ND$2:$ND$60=F$4),0),$B42-1966)} -> 0.001 | G42: {=INDEX(GMW!$A$2:$NF$60,MATCH(1,(GMW!$NE$2:$NE$60=G$3)*(GMW!$ND$2:$ND$60=G$4),0),$B42-1966)} -> 14.7041 | H42: {=INDEX(GMW!$A$2:$NF$60,MATCH(1,(GMW!$NE$2:$NE$60=H$3)*(GMW!$ND$2:$ND$60=H$4),0),$B42-1966)} -> 23.60346
A43: 1982 | B43: =+B42+1 -> 2009 | C43: {=INDEX(GMW!$A$2:$NF$60,MATCH(1,(GMW!$NE$2:$NE$60=C$3)*(GMW!$ND$2:$ND$60=C$4),0),$B43-1966)} -> 0.001 | D43: {=INDEX(GMW!$A$2:$NF$60,MATCH(1,(GMW!$NE$2:$NE$60=D$3)*(GMW!$ND$2:$ND$60=D$4),0),$B43-1966)} -> 0.001 | E43: {=INDEX(GMW!$A$2:$NF$60,MATCH(1,(GMW!$NE$2:$NE$60=E$3)*(GMW!$ND$2:$ND$60=E$4),0),$B43-1966)} -> 13.25 | F43: {=INDEX(GMW!$A$2:$NF$60,MATCH(1,(GMW!$NE$2:$NE$60=F$3)*(GMW!$ND$2:$ND$60=F$4),0),$B43-1966)} -> 0.001 | G43: {=INDEX(GMW!$A$2:$NF$60,MATCH(1,(GMW!$NE$2:$NE$60=G$3)*(GMW!$ND$2:$ND$60=G$4),0),$B43-1966)} -> 14.5939 | H43: {=INDEX(GMW!$A$2:$NF$60,MATCH(1,(GMW!$NE$2:$NE$60=H$3)*(GMW!$ND$2:$ND$60=H$4),0),$B43-1966)} -> 22.09859
B44: =+B43+1 -> 2010 | C44: {=INDEX(GMW!$A$2:$NF$60,MATCH(1,(GMW!$NE$2:$NE$60=C$3)*(GMW!$ND$2:$ND$60=C$4),0),$B44-1966)} -> 0.001 | D44: {=INDEX(GMW!$A$2:$NF$60,MATCH(1,(GMW!$NE$2:$NE$60=D$3)*(GMW!$ND$2:$ND$60=D$4),0),$B44-1966)} -> 0.001 | E44: {=INDEX(GMW!$A$2:$NF$60,MATCH(1,(GMW!$NE$2:$NE$60=E$3)*(GMW!$ND$2:$ND$60=E$4),0),$B44-1966)} -> 12.625 | F44: {=INDEX(GMW!$A$2:$NF$60,MATCH(1,(GMW!$NE$2:$NE$60=F$3)*(GMW!$ND$2:$ND$60=F$4),0),$B44-1966)} -> 0.001 | G44: {=INDEX(GMW!$A$2:$NF$60,MATCH(1,(GMW!$NE$2:$NE$60=G$3)*(GMW!$ND$2:$ND$60=G$4),0),$B44-1966)} -> 13.4576 | H44: {=INDEX(GMW!$A$2:$NF$60,MATCH(1,(GMW!$NE$2:$NE$60=H$3)*(GMW!$ND$2:$ND$60=H$4),0),$B44-1966)} -> 20.679
B45: =+B44+1 -> 2011 | C45: {=INDEX(GMW!$A$2:$NF$60,MATCH(1,(GMW!$NE$2:$NE$60=C$3)*(GMW!$ND$2:$ND$60=C$4),0),$B45-1966)} -> 0.001 | D45: {=INDEX(GMW!$A$2:$NF$60,MATCH(1,(GMW!$NE$2:$NE$60=D$3)*(GMW!$ND$2:$ND$60=D$4),0),$B45-1966)} -> 0.001 | E45: {=INDEX(GMW!$A$2:$NF$60,MATCH(1,(GMW!$NE$2:$NE$60=E$3)*(GMW!$ND$2:$ND$60=E$4),0),$B45-1966)} -> 10.125 | F45: {=INDEX(GMW!$A$2:$NF$60,MATCH(1,(GMW!$NE$2:$NE$60=F$3)*(GMW!$ND$2:$ND$60=F$4),0),$B45-1966)} -> 0.001 | G45: {=INDEX(GMW!$A$2:$NF$60,MATCH(1,(GMW!$NE$2:$NE$60=G$3)*(GMW!$ND$2:$ND$60=G$4),0),$B45-1966)} -> 12.6124 | H45: {=INDEX(GMW!$A$2:$NF$60,MATCH(1,(GMW!$NE$2:$NE$60=H$3)*(GMW!$ND$2:$ND$60=H$4),0),$B45-1966)} -> 18.48189
B46: =+B45+1 -> 2012 | C46: {=INDEX(GMW!$A$2:$NF$60,MATCH(1,(GMW!$NE$2:$NE$60=C$3)*(GMW!$ND$2:$ND$60=C$4),0),$B46-1966)} -> 0.001 | D46: {=INDEX(GMW!$A$2:$NF$60,MATCH(1,(GMW!$NE$2:$NE$60=D$3)*(GMW!$ND$2:$ND$60=D$4),0),$B46-1966)} -> 0.001 | E46: {=INDEX(GMW!$A$2:$NF$60,MATCH(1,(GMW!$NE$2:$NE$60=E$3)*(GMW!$ND$2:$ND$60=E$4),0),$B46-1966)} -> 10 | F46: {=INDEX(GMW!$A$2:$NF$60,MATCH(1,(GMW!$NE$2:$NE$60=F$3)*(GMW!$ND$2:$ND$60=F$4),0),$B46-1966)} -> 0.001 | G46: {=INDEX(GMW!$A$2:$NF$60,MATCH(1,(GMW!$NE$2:$NE$60=G$3)*(GMW!$ND$2:$ND$60=G$4),0),$B46-1966)} -> 10.9634 | H46: {=INDEX(GMW!$A$2:$NF$60,MATCH(1,(GMW!$NE$2:$NE$60=H$3)*(GMW!$ND$2:$ND$60=H$4),0),$B46-1966)} -> 16.29983
A47: 1983 | B47: =+B46+1 -> 2013 | C47: {=INDEX(GMW!$A$2:$NF$60,MATCH(1,(GMW!$NE$2:$NE$60=C$3)*(GMW!$ND$2:$ND$60=C$4),0),$B47-1966)} -> 0.001 | D47: {=INDEX(GMW!$A$2:$NF$60,MATCH(1,(GMW!$NE$2:$NE$60=D$3)*(GMW!$ND$2:$ND$60=D$4),0),$B47-1966)} -> 0.001 | E47: {=INDEX(GMW!$A$2:$NF$60,MATCH(1,(GMW!$NE$2:$NE$60=E$3)*(GMW!$ND$2:$ND$60=E$4),0),$B47-1966)} -> 10.5625 | F47: {=INDEX(GMW!$A$2:$NF$60,MATCH(1,(GMW!$NE$2:$NE$60=F$3)*(GMW!$ND$2:$ND$60=F$4),0),$B47-1966)} -> 0.001 | G47: {=INDEX(GMW!$A$2:$NF$60,MATCH(1,(GMW!$NE$2:$NE$60=G$3)*(GMW!$ND$2:$ND$60=G$4),0),$B47-1966)} -> 9.92754 | H47: {=INDEX(GMW!$A$2:$NF$60,MATCH(1,(GMW!$NE$2:$NE$60=H$3)*(GMW!$ND$2:$ND$60=H$4),0),$B47-1966)} -> 17.09741
B48: =+B47+1 -> 2014 | C48: {=INDEX(GMW!$A$2:$NF$60,MATCH(1,(GMW!$NE$2:$NE$60=C$3)*(GMW!$ND$2:$ND$60=C$4),0),$B48-1966)} -> 0.001 | D48: {=INDEX(GMW!$A$2:$NF$60,MATCH(1,(GMW!$NE$2:$NE$60=D$3)*(GMW!$ND$2:$ND$60=D$4),0),$B48-1966)} -> 0.001 | E48: {=INDEX(GMW!$A$2:$NF$60,MATCH(1,(GMW!$NE$2:$NE$60=E$3)*(GMW!$ND$2:$ND$60=E$4),0),$B48-1966)} -> 9.5625 | F48: {=INDEX(GMW!$A$2:$NF$60,MATCH(1,(GMW!$NE$2:$NE$60=F$3)*(GMW!$ND$2:$ND$60=F$4),0),$B48-1966)} -> 0.001 | G48: {=INDEX(GMW!$A$2:$NF$60,MATCH(1,(GMW!$NE$2:$NE$60=G$3)*(GMW!$ND$2:$ND$60=G$4),0),$B48-1966)} -> 10.0759 | H48: {=INDEX(GMW!$A$2:$NF$60,MATCH(1,(GMW!$NE$2:$NE$60=H$3)*(GMW!$ND$2:$ND$60=H$4),0),$B48-1966)} -> 15.8584
B49: =+B48+1 -> 2015 | C49: {=INDEX(GMW!$A$2:$NF$60,MATCH(1,(GMW!$NE$2:$NE$60=C$3)*(GMW!$ND$2:$ND$60=C$4),0),$B49-1966)} -> 0.001 | D49: {=INDEX(GMW!$A$2:$NF$60,MATCH(1,(GMW!$NE$2:$NE$60=D$3)*(GMW!$ND$2:$ND$60=D$4),0),$B49-1966)} -> 0.001 | E49: {=INDEX(GMW!$A$2:$NF$60,MATCH(1,(GMW!$NE$2:$NE$60=E$3)*(GMW!$ND$2:$ND$60=E$4),0),$B49-1966)} -> 9.5625 | F49: {=INDEX(GMW!$A$2:$NF$60,MATCH(1,(GMW!$NE$2:$NE$60=F$3)*(GMW!$ND$2:$ND$60=F$4),0),$B49-1966)} -> 0.001 | G49: {=INDEX(GMW!$A$2:$NF$60,MATCH(1,(GMW!$NE$2:$NE$60=G$3)*(GMW!$ND$2:$ND$60=G$4),0),$B49-1966)} -> 11.2349 | H49: {=INDEX(GMW!$A$2:$NF$60,MATCH(1,(GMW!$NE$2:$NE$60=H$3)*(GMW!$ND$2:$ND$60=H$4),0),$B49-1966)} -> 16.40517
B50: =+B49+1 -> 2016 | C50: {=INDEX(GMW!$A$2:$NF$60,MATCH(1,(GMW!$NE$2:$NE$60=C$3)*(GMW!$ND$2:$ND$60=C$4),0),$B50-1966)} -> 0.001 | D50: {=INDEX(GMW!$A$2:$NF$60,MATCH(1,(GMW!$NE$2:$NE$60=D$3)*(GMW!$ND$2:$ND$60=D$4),0),$B50-1966)} -> 0.001 | E50: {=INDEX(GMW!$A$2:$NF$60,MATCH(1,(GMW!$NE$2:$NE$60=E$3)*(GMW!$ND$2:$ND$60=E$4),0),$B50-1966)} -> 9.0625 | F50: {=INDEX(GMW!$A$2:$NF$60,MATCH(1,(GMW!$NE$2:$NE$60=F$3)*(GMW!$ND$2:$ND$60=F$4),0),$B50-1966)} -> 0.001 | G50: {=INDEX(GMW!$A$2:$NF$60,MATCH(1,(GMW!$NE$2:$NE$60=G$3)*(GMW!$ND$2:$ND$60=G$4),0),$B50-1966)} -> 11.2541 | H50: {=INDEX(GMW!$A$2:$NF$60,MATCH(1,(GMW!$NE$2:$NE$60=H$3)*(GMW!$ND$2:$ND$60=H$4),0),$B50-1966)} -> 15.68284
A51: 1984 | B51: =+B50+1 -> 2017 | C51: {=INDEX(GMW!$A$2:$NF$60,MATCH(1,(GMW!$NE$2:$NE$60=C$3)*(GMW!$ND$2:$ND$60=C$4),0),$B51-1966)} -> 0.001 | D51: {=INDEX(GMW!$A$2:$NF$60,MATCH(1,(GMW!$NE$2:$NE$60=D$3)*(GMW!$ND$2:$ND$60=D$4),0),$B51-1966)} -> 0.001 | E51: {=INDEX(GMW!$A$2:$NF$60,MATCH(1,(GMW!$NE$2:$NE$60=E$3)*(GMW!$ND$2:$ND$60=E$4),0),$B51-1966)} -> 8.5625 | F51: {=INDEX(GMW!$A$2:$NF$60,MATCH(1,(GMW!$NE$2:$NE$60=F$3)*(GMW!$ND$2:$ND$60=F$4),0),$B51-1966)} -> 10.65 | G51: {=INDEX(GMW!$A$2:$NF$60,MATCH(1,(GMW!$NE$2:$NE$60=G$3)*(GMW!$ND$2:$ND$60=G$4),0),$B51-1966)} -> 11.47 | H51: {=INDEX(GMW!$A$2:$NF$60,MATCH(1,(GMW!$NE$2:$NE$60=H$3)*(GMW!$ND$2:$ND$60=H$4),0),$B51-1966)} -> 16.20954
B52: =+B51+1 -> 2018 | C52: {=INDEX(GMW!$A$2:$NF$60,MATCH(1,(GMW!$NE$2:$NE$60=C$3)*(GMW!$ND$2:$ND$60=C$4),0),$B52-1966)} -> 0.001 | D52: {=INDEX(GMW!$A$2:$NF$60,MATCH(1,(GMW!$NE$2:$NE$60=D$3)*(GMW!$ND$2:$ND$60=D$4),0),$B52-1966)} -> 0.001 | E52: {=INDEX(GMW!$A$2:$NF$60,MATCH(1,(GMW!$NE$2:$NE$60=E$3)*(GMW!$ND$2:$ND$60=E$4),0),$B52-1966)} -> 8.875 | F52: {=INDEX(GMW!$A$2:$NF$60,MATCH(1,(GMW!$NE$2:$NE$60=F$3)*(GMW!$ND$2:$ND$60=F$4),0),$B52-1966)} -> 11.7 | G52: {=INDEX(GMW!$A$2:$NF$60,MATCH(1,(GMW!$NE$2:$NE$60=G$3)*(GMW!$ND$2:$ND$60=G$4),0),$B52-1966)} -> 10.51 | H52: {=INDEX(GMW!$A$2:$NF$60,MATCH(1,(GMW!$NE$2:$NE$60=H$3)*(GMW!$ND$2:$ND$60=H$4),0),$B52-1966)} -> 16.98204
B53: =+B52+1 -> 2019 | C53: {=INDEX(GMW!$A$2:$NF$60,MATCH(1,(GMW!$NE$2:$NE$60=C$3)*(GMW!$ND$2:$ND$60=C$4),0),$B53-1966)} -> 0.001 | D53: {=INDEX(GMW!$A$2:$NF$60,MATCH(1,(GMW!$NE$2:$NE$60=D$3)*(GMW!$ND$2:$ND$60=D$4),0),$B53-1966)} -> 0.001 | E53: {=INDEX(GMW!$A$2:$NF$60,MATCH(1,(GMW!$NE$2:$NE$60=E$3)*(GMW!$ND$2:$ND$60=E$4),0),$B53-1966)} -> 10.5 | F53: {=INDEX(GMW!$A$2:$NF$60,MATCH(1,(GMW!$NE$2:$NE$60=F$3)*(GMW!$ND$2:$ND$60=F$4),0),$B53-1966)} -> 11.03 | G53: {=INDEX(GMW!$A$2:$NF$60,MATCH(1,(GMW!$NE$2:$NE$60=G$3)*(GMW!$ND$2:$ND$60=G$4),0),$B53-1966)} -> 13.08 | H53: {=INDEX(GMW!$A$2:$NF$60,MATCH(1,(GMW!$NE$2:$NE$60=H$3)*(GMW!$ND$2:$ND$60=H$4),0),$B53-1966)} -> 17.41845
B54: =+B53+1 -> 2020 | C54: {=INDEX(GMW!$A$2:$NF$60,MATCH(1,(GMW!$NE$2:$NE$60=C$3)*(GMW!$ND$2:$ND$60=C$4),0),$B54-1966)} -> 0.001 | D54: {=INDEX(GMW!$A$2:$NF$60,MATCH(1,(GMW!$NE$2:$NE$60=D$3)*(GMW!$ND$2:$ND$60=D$4),0),$B54-1966)} -> 0.001 | E54: {=INDEX(GMW!$A$2:$NF$60,MATCH(1,(GMW!$NE$2:$NE$60=E$3)*(GMW!$ND$2:$ND$60=E$4),0),$B54-1966)} -> 9.5 | F54: {=INDEX(GMW!$A$2:$NF$60,MATCH(1,(GMW!$NE$2:$NE$60=F$3)*(GMW!$ND$2:$ND$60=F$4),0),$B54-1966)} -> 11.07 | G54: {=INDEX(GMW!$A$2:$NF$60,MATCH(1,(GMW!$NE$2:$NE$60=G$3)*(GMW!$ND$2:$ND$60=G$4),0),$B54-1966)} -> 12.19 | H54: {=INDEX(GMW!$A$2:$NF$60,MATCH(1,(GMW!$NE$2:$NE$60=H$3)*(GMW!$ND$2:$ND$60=H$4),0),$B54-1966)} -> 16.4152
A55: 1985 | B55: =+B54+1 -> 2021 | C55: {=INDEX(GMW!$A$2:$NF$60,MATCH(1,(GMW!$NE$2:$NE$60=C$3)*(GMW!$ND$2:$ND$60=C$4),0),$B55-1966)} -> 0.001 | D55: {=INDEX(GMW!$A$2:$NF$60,MATCH(1,(GMW!$NE$2:$NE$60=D$3)*(GMW!$ND$2:$ND$60=D$4),0),$B55-1966)} -> 0.001 | E55: {=INDEX(GMW!$A$2:$NF$60,MATCH(1,(GMW!$NE$2:$NE$60=E$3)*(GMW!$ND$2:$ND$60=E$4),0),$B55-1966)} -> 12.875 | F55: {=INDEX(GMW!$A$2:$NF$60,MATCH(1,(GMW!$NE$2:$NE$60=F$3)*(GMW!$ND$2:$ND$60=F$4),0),$B55-1966)} -> 11.09 | G55: {=INDEX(GMW!$A$2:$NF$60,MATCH(1,(GMW!$NE$2:$NE$60=G$3)*(GMW!$ND$2:$ND$60=G$4),0),$B55-1966)} -> 13.25 | H55: {=INDEX(GMW!$A$2:$NF$60,MATCH(1,(GMW!$NE$2:$NE$60=H$3)*(GMW!$ND$2:$ND$60=H$4),0),$B55-1966)} -> 17.15258
B56: =+B55+1 -> 2022 | C56: {=INDEX(GMW!$A$2:$NF$60,MATCH(1,(GMW!$NE$2:$NE$60=C$3)*(GMW!$ND$2:$ND$60=C$4),0),$B56-1966)} -> 0.001 | D56: {=INDEX(GMW!$A$2:$NF$60,MATCH(1,(GMW!$NE$2:$NE$60=D$3)*(GMW!$ND$2:$ND$60=D$4),0),$B56-1966)} -> 0.001 | E56: {=INDEX(GMW!$A$2:$NF$60,MATCH(1,(GMW!$NE$2:$NE$60=E$3)*(GMW!$ND$2:$ND$60=E$4),0),$B56-1966)} -> 12.375 | F56: {=INDEX(GMW!$A$2:$NF$60,MATCH(1,(GMW!$NE$2:$NE$60=F$3)*(GMW!$ND$2:$ND$60=F$4),0),$B56-1966)} -> 11.05 | G56: {=INDEX(GMW!$A$2:$NF$60,MATCH(1,(GMW!$NE$2:$NE$60=G$3)*(GMW!$ND$2:$ND$60=G$4),0),$B56-1966)} -> 14.26 | H56: {=INDEX(GMW!$A$2:$NF$60,MATCH(1,(GMW!$NE$2:$NE$60=H$3)*(GMW!$ND$2:$ND$60=H$4),0),$B56-1966)} -> 16.73122
B57: =+B56+1 -> 2023 | C57: {=INDEX(GMW!$A$2:$NF$60,MATCH(1,(GMW!$NE$2:$NE$60=C$3)*(GMW!$ND$2:$ND$60=C$4),0),$B57-1966)} -> 0.001 | D57: {=INDEX(GMW!$A$2:$NF$60,MATCH(1,(GMW!$NE$2:$NE$60=D$3)*(GMW!$ND$2:$ND$60=D$4),0),$B57-1966)} -> 0.001 | E57: {=INDEX(GMW!$A$2:$NF$60,MATCH(1,(GMW!$NE$2:$NE$60=E$3)*(GMW!$ND$2:$ND$60=E$4),0),$B57-1966)} -> 11.375 | F57: {=INDEX(GMW!$A$2:$NF$60,MATCH(1,(GMW!$NE$2:$NE$60=F$3)*(GMW!$ND$2:$ND$60=F$4),0),$B57-1966)} -> 10.55 | G57: {=INDEX(GMW!$A$2:$NF$60,MATCH(1,(GMW!$NE$2:$NE$60=G$3)*(GMW!$ND$2:$ND$60=G$4),0),$B57-1966)} -> 13.06 | H57: {=INDEX(GMW!$A$2:$NF$60,MATCH(1,(GMW!$NE$2:$NE$60=H$3)*(GMW!$ND$2:$ND$60=H$4),0),$B57-1966)} -> 16.12927
B58: =+B57+1 -> 2024 | C58: {=INDEX(GMW!$A$2:$NF$60,MATCH(1,(GMW!$NE$2:$NE$60=C$3)*(GMW!$ND$2:$ND$60=C$4),0),$B58-1966)} -> 0.001 | D58: {=INDEX(GMW!$A$2:$NF$60,MATCH(1,(GMW!$NE$2:$NE$60=D$3)*(GMW!$ND$2:$ND$60=D$4),0),$B58-1966)} -> 0.001 | E58: {=INDEX(GMW!$A$2:$NF$60,MATCH(1,(GMW!$NE$2:$NE$60=E$3)*(GMW!$ND$2:$ND$60=E$4),0),$B58-1966)} -> 11.375 | F58: {=INDEX(GMW!$A$2:$NF$60,MATCH(1,(GMW!$NE$2:$NE$60=F$3)*(GMW!$ND$2:$ND$60=F$4),0),$B58-1966)} -> 10.83 | G58: {=INDEX(GMW!$A$2:$NF$60,MATCH(1,(GMW!$NE$2:$NE$60=G$3)*(GMW!$ND$2:$ND$60=G$4),0),$B58-1966)} -> 13.01 | H58: {=INDEX(GMW!$A$2:$NF$60,MATCH(1,(GMW!$NE$2:$NE$60=H$3)*(GMW!$ND$2:$ND$60=H$4),0),$B58-1966)} -> 16.05403
A59: 1986 | B59: =+B58+1 -> 2025 | C59: {=INDEX(GMW!$A$2:$NF$60,MATCH(1,(GMW!$NE$2:$NE$60=C$3)*(GMW!$ND$2:$ND$60=C$4),0),$B59-1966)} -> 0.001 | D59: {=INDEX(GMW!$A$2:$NF$60,MATCH(1,(GMW!$NE$2:$NE$60=D$3)*(GMW!$ND$2:$ND$60=D$4),0),$B59-1966)} -> 0.001 | E59: {=INDEX(GMW!$A$2:$NF$60,MATCH(1,(GMW!$NE$2:$NE$60=E$3)*(GMW!$ND$2:$ND$60=E$4),0),$B59-1966)} -> 11.375 | F59: {=INDEX(GMW!$A$2:$NF$60,MATCH(1,(GMW!$NE$2:$NE$60=F$3)*(GMW!$ND$2:$ND$60=F$4),0),$B59-1966)} -> 9.14 | G59: {=INDEX(GMW!$A$2:$NF$60,MATCH(1,(GMW!$NE$2:$NE$60=G$3)*(GMW!$ND$2:$ND$60=G$4),0),$B59-1966)} -> 13 | H59: {=INDEX(GMW!$A$2:$NF$60,MATCH(1,(GMW!$NE$2:$NE$60=H$3)*(GMW!$ND$2:$ND$60=H$4),0),$B59-1966)} -> 15.7982
B60: =+B59+1 -> 2026 | C60: {=INDEX(GMW!$A$2:$NF$60,MATCH(1,(GMW!$NE$2:$NE$60=C$3)*(GMW!$ND$2:$ND$60=C$4),0),$B60-1966)} -> 0.001 | D60: {=INDEX(GMW!$A$2:$NF$60,MATCH(1,(GMW!$NE$2:$NE$60=D$3)*(GMW!$ND$2:$ND$60=D$4),0),$B60-1966)} -> 0.001 | E60: {=INDEX(GMW!$A$2:$NF$60,MATCH(1,(GMW!$NE$2:$NE$60=E$3)*(GMW!$ND$2:$ND$60=E$4),0),$B60-1966)} -> 9.875 | F60: {=INDEX(GMW!$A$2:$NF$60,MATCH(1,(GMW!$NE$2:$NE$60=F$3)*(GMW!$ND$2:$ND$60=F$4),0),$B60-1966)} -> 9.55 | G60: {=INDEX(GMW!$A$2:$NF$60,MATCH(1,(GMW!$NE$2:$NE$60=G$3)*(GMW!$ND$2:$ND$60=G$4),0),$B60-1966)} -> 11.06 | H60: {=INDEX(GMW!$A$2:$NF$60,MATCH(1,(GMW!$NE$2:$NE$60=H$3)*(GMW!$ND$2:$ND$60=H$4),0),$B60-1966)} -> 13.81679
B61: =+B60+1 -> 2027 | C61: {=INDEX(GMW!$A$2:$NF$60,MATCH(1,(GMW!$NE$2:$NE$60=C$3)*(GMW!$ND$2:$ND$60=C$4),0),$B61-1966)} -> 0.001 | D61: {=INDEX(GMW!$A$2:$NF$60,MATCH(1,(GMW!$NE$2:$NE$60=D$3)*(GMW!$ND$2:$ND$60=D$4),0),$B61-1966)} -> 0.001 | E61: {=INDEX(GMW!$A$2:$NF$60,MATCH(1,(GMW!$NE$2:$NE$60=E$3)*(GMW!$ND$2:$ND$60=E$4),0),$B61-1966)} -> 9.875 | F61: {=INDEX(GMW!$A$2:$NF$60,MATCH(1,(GMW!$NE$2:$NE$60=F$3)*(GMW!$ND$2:$ND$60=F$4),0),$B61-1966)} -> 10.86 | G61: {=INDEX(GMW!$A$2:$NF$60,MATCH(1,(GMW!$NE$2:$NE$60=G$3)*(GMW!$ND$2:$ND$60=G$4),0),$B61-1966)} -> 11.04 | H61: {=INDEX(GMW!$A$2:$NF$60,MATCH(1,(GMW!$NE$2:$NE$60=H$3)*(GMW!$ND$2:$ND$60=H$4),0),$B61-1966)} -> 14.83007
B62: =+B61+1 -> 2028 | C62: {=INDEX(GMW!$A$2:$NF$60,MATCH(1,(GMW!$NE$2:$NE$60=C$3)*(GMW!$ND$2:$ND$60=C$4),0),$B62-1966)} -> 0.001 | D62: {=INDEX(GMW!$A$2:$NF$60,MATCH(1,(GMW!$NE$2:$NE$60=D$3)*(GMW!$ND$2:$ND$60=D$4),0),$B62-1966)} -> 0.001 | E62: {=INDEX(GMW!$A$2:$NF$60,MATCH(1,(GMW!$NE$2:$NE$60=E$3)*(GMW!$ND$2:$ND$60=E$4),0),$B62-1966)} -> 10.875 | F62: {=INDEX(GMW!$A$2:$NF$60,MATCH(1,(GMW!$NE$2:$NE$60=F$3)*(GMW!$ND$2:$ND$60=F$4),0),$B62-1966)} -> 10.57 | G62: {=INDEX(GMW!$A$2:$NF$60,MATCH(1,(GMW!$NE$2:$NE$60=G$3)*(GMW!$ND$2:$ND$60=G$4),0),$B62-1966)} -> 12.32 | H62: {=INDEX(GMW!$A$2:$NF$60,MATCH(1,(GMW!$NE$2:$NE$60=H$3)*(GMW!$ND$2:$ND$60=H$4),0),$B62-1966)} -> 16.54061
A63: 1987 | B63: =+B62+1 -> 2029 | C63: {=INDEX(GMW!$A$2:$NF$60,MATCH(1,(GMW!$NE$2:$NE$60=C$3)*(GMW!$ND$2:$ND$60=C$4),0),$B63-1966)} -> 5125 | D63: {=INDEX(GMW!$A$2:$NF$60,MATCH(1,(GMW!$NE$2:$NE$60=D$3)*(GMW!$ND$2:$ND$60=D$4),0),$B63-1966)} -> 6357 | E63: {=INDEX(GMW!$A$2:$NF$60,MATCH(1,(GMW!$NE$2:$NE$60=E$3)*(GMW!$ND$2:$ND$60=E$4),0),$B63-1966)} -> 9.875 | F63: {=INDEX(GMW!$A$2:$NF$60,MATCH(1,(GMW!$NE$2:$NE$60=F$3)*(GMW!$ND$2:$ND$60=F$4),0),$B63-1966)} -> 9.18 | G63: {=INDEX(GMW!$A$2:$NF$60,MATCH(1,(GMW!$NE$2:$NE$60=G$3)*(GMW!$ND$2:$ND$60=G$4),0),$B63-1966)} -> 12.32 | H63: {=INDEX(GMW!$A$2:$NF$60,MATCH(1,(GMW!$NE$2:$NE$60=H$3)*(GMW!$ND$2:$ND$60=H$4),0),$B63-1966)} -> 14.73477
B64: =+B63+1 -> 2030 | C64: {=INDEX(GMW!$A$2:$NF$60,MATCH(1,(GMW!$NE$2:$NE$60=C$3)*(GMW!$ND$2:$ND$60=C$4),0),$B64-1966)} -> 5318 | D64: {=INDEX(GMW!$A$2:$NF$60,MATCH(1,(GMW!$NE$2:$NE$60=D$3)*(GMW!$ND$2:$ND$60=D$4),0),$B64-1966)} -> 6287 | E64: {=INDEX(GMW!$A$2:$NF$60,MATCH(1,(GMW!$NE$2:$NE$60=E$3)*(GMW!$ND$2:$ND$60=E$4),0),$B64-1966)} -> 8.875 | F64: {=INDEX(GMW!$A$2:$NF$60,MATCH(1,(GMW!$NE$2:$NE$60=F$3)*(GMW!$ND$2:$ND$60=F$4),0),$B64-1966)} -> 9.2 | G64: {=INDEX(GMW!$A$2:$NF$60,MATCH(1,(GMW!$NE$2:$NE$60=G$3)*(GMW!$ND$2:$ND$60=G$4),0),$B64-1966)} -> 11.28 | H64: {=INDEX(GMW!$A$2:$NF$60,MATCH(1,(GMW!$NE$2:$NE$60=H$3)*(GMW!$ND$2:$ND$60=H$4),0),$B64-1966)} -> 13.49576
B65: =+B64+1 -> 2031 | C65: {=INDEX(GMW!$A$2:$NF$60,MATCH(1,(GMW!$NE$2:$NE$60=C$3)*(GMW!$ND$2:$ND$60=C$4),0),$B65-1966)} -> 5384 | D65: {=INDEX(GMW!$A$2:$NF$60,MATCH(1,(GMW!$NE$2:$NE$60=D$3)*(GMW!$ND$2:$ND$60=D$4),0),$B65-1966)} -> 6587 | E65: {=INDEX(GMW!$A$2:$NF$60,MATCH(1,(GMW!$NE$2:$NE$60=E$3)*(GMW!$ND$2:$ND$60=E$4),0),$B65-1966)} -> 9.875 | F65: {=INDEX(GMW!$A$2:$NF$60,MATCH(1,(GMW!$NE$2:$NE$60=F$3)*(GMW!$ND$2:$ND$60=F$4),0),$B65-1966)} -> 10.26 | G65: {=INDEX(GMW!$A$2:$NF$60,MATCH(1,(GMW!$NE$2:$NE$60=G$3)*(GMW!$ND$2:$ND$60=G$4),0),$B65-1966)} -> 11.28 | H65: {=INDEX(GMW!$A$2:$NF$60,MATCH(1,(GMW!$NE$2:$NE$60=H$3)*(GMW!$ND$2:$ND$60=H$4),0),$B65-1966)} -> 14.87522
B66: =+B65+1 -> 2032 | C66: {=INDEX(GMW!$A$2:$NF$60,MATCH(1,(GMW!$NE$2:$NE$60=C$3)*(GMW!$ND$2:$ND$60=C$4),0),$B66-1966)} -> 4897 | D66: {=INDEX(GMW!$A$2:$NF$60,MATCH(1,(GMW!$NE$2:$NE$60=D$3)*(GMW!$ND$2:$ND$60=D$4),0),$B66-1966)} -> 7170 | E66: {=INDEX(GMW!$A$2:$NF$60,MATCH(1,(GMW!$NE$2:$NE$60=E$3)*(GMW!$ND$2:$ND$60=E$4),0),$B66-1966)} -> 8.375 | F66: {=INDEX(GMW!$A$2:$NF$60,MATCH(1,(GMW!$NE$2:$NE$60=F$3)*(GMW!$ND$2:$ND$60=F$4),0),$B66-1966)} -> 9.61 | G66: {=INDEX(GMW!$A$2:$NF$60,MATCH(1,(GMW!$NE$2:$NE$60=G$3)*(GMW!$ND$2:$ND$60=G$4),0),$B66-1966)} -> 10.34 | H66: {=INDEX(GMW!$A$2:$NF$60,MATCH(1,(GMW!$NE$2:$NE$60=H$3)*(GMW!$ND$2:$ND$60=H$4),0),$B66-1966)} -> 14.55418
A67: 1988 | B67: =+B66+1 -> 2033 | C67: {=INDEX(GMW!$A$2:$NF$60,MATCH(1,(GMW!$NE$2:$NE$60=C$3)*(GMW!$ND$2:$ND$60=C$4),0),$B67-1966)} -> 5033 | D67: {=INDEX(GMW!$A$2:$NF$60,MATCH(1,(GMW!$NE$2:$NE$60=D$3)*(GMW!$ND$2:$ND$60=D$4),0),$B67-1966)} -> 6637 | E67: {=INDEX(GMW!$A$2:$NF$60,MATCH(1,(GMW!$NE$2:$NE$60=E$3)*(GMW!$ND$2:$ND$60=E$4),0),$B67-1966)} -> 8.375 | F67: {=INDEX(GMW!$A$2:$NF$60,MATCH(1,(GMW!$NE$2:$NE$60=F$3)*(GMW!$ND$2:$ND$60=F$4),0),$B67-1966)} -> 9.09 | G67: {=INDEX(GMW!$A$2:$NF$60,MATCH(1,(GMW!$NE$2:$NE$60=G$3)*(GMW!$ND$2:$ND$60=G$4),0),$B67-1966)} -> 10.26 | H67: {=INDEX(GMW!$A$2:$NF$60,MATCH(1,(GMW!$NE$2:$NE$60=H$3)*(GMW!$ND$2:$ND$60=H$4),0),$B67-1966)} -> 14.27829
B68: =+B67+1 -> 2034 | C68: {=INDEX(GMW!$A$2:$NF$60,MATCH(1,(GMW!$NE$2:$NE$60=C$3)*(GMW!$ND$2:$ND$60=C$4),0),$B68-1966)} -> 5100 | D68: {=INDEX(GMW!$A$2:$NF$60,MATCH(1,(GMW!$NE$2:$NE$60=D$3)*(GMW!$ND$2:$ND$60=D$4),0),$B68-1966)} -> 6806 | E68: {=INDEX(GMW!$A$2:$NF$60,MATCH(1,(GMW!$NE$2:$NE$60=E$3)*(GMW!$ND$2:$ND$60=E$4),0),$B68-1966)} -> 8.875 | F68: {=INDEX(GMW!$A$2:$NF$60,MATCH(1,(GMW!$NE$2:$NE$60=F$3)*(GMW!$ND$2:$ND$60=F$4),0),$B68-1966)} -> 9.8 | G68: {=INDEX(GMW!$A$2:$NF$60,MATCH(1,(GMW!$NE$2:$NE$60=G$3)*(GMW!$ND$2:$ND$60=G$4),0),$B68-1966)} -> 9.78 | H68: {=INDEX(GMW!$A$2:$NF$60,MATCH(1,(GMW!$NE$2:$NE$60=H$3)*(GMW!$ND$2:$ND$60=H$4),0),$B68-1966)} -> 14.10774
B69: =+B68+1 -> 2035 | C69: {=INDEX(GMW!$A$2:$NF$60,MATCH(1,(GMW!$NE$2:$NE$60=C$3)*(GMW!$ND$2:$ND$60=C$4),0),$B69-1966)} -> 5343 | D69: {=INDEX(GMW!$A$2:$NF$60,MATCH(1,(GMW!$NE$2:$NE$60=D$3)*(GMW!$ND$2:$ND$60=D$4),0),$B69-1966)} -> 7710 | E69: {=INDEX(GMW!$A$2:$NF$60,MATCH(1,(GMW!$NE$2:$NE$60=E$3)*(GMW!$ND$2:$ND$60=E$4),0),$B69-1966)} -> 11.875 | F69: {=INDEX(GMW!$A$2:$NF$60,MATCH(1,(GMW!$NE$2:$NE$60=F$3)*(GMW!$ND$2:$ND$60=F$4),0),$B69-1966)} -> 9.88 | G69: {=INDEX(GMW!$A$2:$NF$60,MATCH(1,(GMW!$NE$2:$NE$60=G$3)*(GMW!$ND$2:$ND$60=G$4),0),$B69-1966)} -> 11.54 | H69: {=INDEX(GMW!$A$2:$NF$60,MATCH(1,(GMW!$NE$2:$NE$60=H$3)*(GMW!$ND$2:$ND$60=H$4),0),$B69-1966)} -> 14.98558
B70: =+B69+1 -> 2036 | C70: {=INDEX(GMW!$A$2:$NF$60,MATCH(1,(GMW!$NE$2:$NE$60=C$3)*(GMW!$ND$2:$ND$60=C$4),0),$B70-1966)} -> 6323 | D70: {=INDEX(GMW!$A$2:$NF$60,MATCH(1,(GMW!$NE$2:$NE$60=D$3)*(GMW!$ND$2:$ND$60=D$4),0),$B70-1966)} -> 8784 | E70: {=INDEX(GMW!$A$2:$NF$60,MATCH(1,(GMW!$NE$2:$NE$60=E$3)*(GMW!$ND$2:$ND$60=E$4),0),$B70-1966)} -> 12.875 | F70: {=INDEX(GMW!$A$2:$NF$60,MATCH(1,(GMW!$NE$2:$NE$60=F$3)*(GMW!$ND$2:$ND$60=F$4),0),$B70-1966)} -> 10.11 | G70: {=INDEX(GMW!$A$2:$NF$60,MATCH(1,(GMW!$NE$2:$NE$60=G$3)*(GMW!$ND$2:$ND$60=G$4),0),$B70-1966)} -> 12.75 | H70: {=INDEX(GMW!$A$2:$NF$60,MATCH(1,(GMW!$NE$2:$NE$60=H$3)*(GMW!$ND$2:$ND$60=H$4),0),$B70-1966)} -> 14.89528
A71: 1989 | B71: =+B70+1 -> 2037 | C71: {=INDEX(GMW!$A$2:$NF$60,MATCH(1,(GMW!$NE$2:$NE$60=C$3)*(GMW!$ND$2:$ND$60=C$4),0),$B71-1966)} -> 6880 | D71: {=INDEX(GMW!$A$2:$NF$60,MATCH(1,(GMW!$NE$2:$NE$60=D$3)*(GMW!$ND$2:$ND$60=D$4),0),$B71-1966)} -> 9692 | E71: {=INDEX(GMW!$A$2:$NF$60,MATCH(1,(GMW!$NE$2:$NE$60=E$3)*(GMW!$ND$2:$ND$60=E$4),0),$B71-1966)} -> 12.875 | F71: {=INDEX(GMW!$A$2:$NF$60,MATCH(1,(GMW!$NE$2:$NE$60=F$3)*(GMW!$ND$2:$ND$60=F$4),0),$B71-1966)} -> 10 | G71: {=INDEX(GMW!$A$2:$NF$60,MATCH(1,(GMW!$NE$2:$NE$60=G$3)*(GMW!$ND$2:$ND$60=G$4),0),$B71-1966)} -> 13.46 | H71: {=INDEX(GMW!$A$2:$NF$60,MATCH(1,(GMW!$NE$2:$NE$60=H$3)*(GMW!$ND$2:$ND$60=H$4),0),$B71-1966)} -> 14.84011
B72: =+B71+1 -> 2038 | C72: {=INDEX(GMW!$A$2:$NF$60,MATCH(1,(GMW!$NE$2:$NE$60=C$3)*(GMW!$ND$2:$ND$60=C$4),0),$B72-1966)} -> 7550 | D72: {=INDEX(GMW!$A$2:$NF$60,MATCH(1,(GMW!$NE$2:$NE$60=D$3)*(GMW!$ND$2:$ND$60=D$4),0),$B72-1966)} -> 10649 | E72: {=INDEX(GMW!$A$2:$NF$60,MATCH(1,(GMW!$NE$2:$NE$60=E$3)*(GMW!$ND$2:$ND$60=E$4),0),$B72-1966)} -> 13.75 | F72: {=INDEX(GMW!$A$2:$NF$60,MATCH(1,(GMW!$NE$2:$NE$60=F$3)*(GMW!$ND$2:$ND$60=F$4),0),$B72-1966)} -> 10.41 | G72: {=INDEX(GMW!$A$2:$NF$60,MATCH(1,(GMW!$NE$2:$NE$60=G$3)*(GMW!$ND$2:$ND$60=G$4),0),$B72-1966)} -> 13.43 | H72: {=INDEX(GMW!$A$2:$NF$60,MATCH(1,(GMW!$NE$2:$NE$60=H$3)*(GMW!$ND$2:$ND$60=H$4),0),$B72-1966)} -> 15.50726
B73: =+B72+1 -> 2039 | C73: {=INDEX(GMW!$A$2:$NF$60,MATCH(1,(GMW!$NE$2:$NE$60=C$3)*(GMW!$ND$2:$ND$60=C$4),0),$B73-1966)} -> 7721 | D73: {=INDEX(GMW!$A$2:$NF$60,MATCH(1,(GMW!$NE$2:$NE$60=D$3)*(GMW!$ND$2:$ND$60=D$4),0),$B73-1966)} -> 10881 | E73: {=INDEX(GMW!$A$2:$NF$60,MATCH(1,(GMW!$NE$2:$NE$60=E$3)*(GMW!$ND$2:$ND$60=E$4),0),$B73-1966)} -> 13.75 | F73: {=INDEX(GMW!$A$2:$NF$60,MATCH(1,(GMW!$NE$2:$NE$60=F$3)*(GMW!$ND$2:$ND$60=F$4),0),$B73-1966)} -> 10.46 | G73: {=INDEX(GMW!$A$2:$NF$60,MATCH(1,(GMW!$NE$2:$NE$60=G$3)*(GMW!$ND$2:$ND$60=G$4),0),$B73-1966)} -> 13.48 | H73: {=INDEX(GMW!$A$2:$NF$60,MATCH(1,(GMW!$NE$2:$NE$60=H$3)*(GMW!$ND$2:$ND$60=H$4),0),$B73-1966)} -> 15.19124
B74: =+B73+1 -> 2040 | C74: {=INDEX(GMW!$A$2:$NF$60,MATCH(1,(GMW!$NE$2:$NE$60=C$3)*(GMW!$ND$2:$ND$60=C$4),0),$B74-1966)} -> 8337 | D74: {=INDEX(GMW!$A$2:$NF$60,MATCH(1,(GMW!$NE$2:$NE$60=D$3)*(GMW!$ND$2:$ND$60=D$4),0),$B74-1966)} -> 11595 | E74: {=INDEX(GMW!$A$2:$NF$60,MATCH(1,(GMW!$NE$2:$NE$60=E$3)*(GMW!$ND$2:$ND$60=E$4),0),$B74-1966)} -> 14.875 | F74: {=INDEX(GMW!$A$2:$NF$60,MATCH(1,(GMW!$NE$2:$NE$60=F$3)*(GMW!$ND$2:$ND$60=F$4),0),$B74-1966)} -> 10.41 | G74: {=INDEX(GMW!$A$2:$NF$60,MATCH(1,(GMW!$NE$2:$NE$60=G$3)*(GMW!$ND$2:$ND$60=G$4),0),$B74-1966)} -> 14.44 | H74: {=INDEX(GMW!$A$2:$NF$60,MATCH(1,(GMW!$NE$2:$NE$60=H$3)*(GMW!$ND$2:$ND$60=H$4),0),$B74-1966)} -> 15.8283
A75: 1990 | B75: =+B74+1 -> 2041 | C75: {=INDEX(GMW!$A$2:$NF$60,MATCH(1,(GMW!$NE$2:$NE$60=C$3)*(GMW!$ND$2:$ND$60=C$4),0),$B75-1966)} -> 8663 | D75: {=INDEX(GMW!$A$2:$NF$60,MATCH(1,(GMW!$NE$2:$NE$60=D$3)*(GMW!$ND$2:$ND$60=D$4),0),$B75-1966)} -> 12502 | E75: {=INDEX(GMW!$A$2:$NF$60,MATCH(1,(GMW!$NE$2:$NE$60=E$3)*(GMW!$ND$2:$ND$60=E$4),0),$B75-1966)} -> 14.875 | F75: {=INDEX(GMW!$A$2:$NF$60,MATCH(1,(GMW!$NE$2:$NE$60=F$3)*(GMW!$ND$2:$ND$60=F$4),0),$B75-1966)} -> 12.52 | G75: {=INDEX(GMW!$A$2:$NF$60,MATCH(1,(GMW!$NE$2:$NE$60=G$3)*(GMW!$ND$2:$ND$60=G$4),0),$B75-1966)} -> 15.24 | H75: {=INDEX(GMW!$A$2:$NF$60,MATCH(1,(GMW!$NE$2:$NE$60=H$3)*(GMW!$ND$2:$ND$60=H$4),0),$B75-1966)} -> 17.3733
B76: =+B75+1 -> 2042 | C76: {=INDEX(GMW!$A$2:$NF$60,MATCH(1,(GMW!$NE$2:$NE$60=C$3)*(GMW!$ND$2:$ND$60=C$4),0),$B76-1966)} -> 9207 | D76: {=INDEX(GMW!$A$2:$NF$60,MATCH(1,(GMW!$NE$2:$NE$60=D$3)*(GMW!$ND$2:$ND$60=D$4),0),$B76-1966)} -> 13402 | E76: {=INDEX(GMW!$A$2:$NF$60,MATCH(1,(GMW!$NE$2:$NE$60=E$3)*(GMW!$ND$2:$ND$60=E$4),0),$B76-1966)} -> 14.875 | F76: {=INDEX(GMW!$A$2:$NF$60,MATCH(1,(GMW!$NE$2:$NE$60=F$3)*(GMW!$ND$2:$ND$60=F$4),0),$B76-1966)} -> 11.65 | G76: {=INDEX(GMW!$A$2:$NF$60,MATCH(1,(GMW!$NE$2:$NE$60=G$3)*(GMW!$ND$2:$ND$60=G$4),0),$B76-1966)} -> 15.25 | H76: {=INDEX(GMW!$A$2:$NF$60,MATCH(1,(GMW!$NE$2:$NE$60=H$3)*(GMW!$ND$2:$ND$60=H$4),0),$B76-1966)} -> 18.5471
B77: =+B76+1 -> 2043 | C77: {=INDEX(GMW!$A$2:$NF$60,MATCH(1,(GMW!$NE$2:$NE$60=C$3)*(GMW!$ND$2:$ND$60=C$4),0),$B77-1966)} -> 9914 | D77: {=INDEX(GMW!$A$2:$NF$60,MATCH(1,(GMW!$NE$2:$NE$60=D$3)*(GMW!$ND$2:$ND$60=D$4),0),$B77-1966)} -> 13746 | E77: {=INDEX(GMW!$A$2:$NF$60,MATCH(1,(GMW!$NE$2:$NE$60=E$3)*(GMW!$ND$2:$ND$60=E$4),0),$B77-1966)} -> 14.875 | F77: {=INDEX(GMW!$A$2:$NF$60,MATCH(1,(GMW!$NE$2:$NE$60=F$3)*(GMW!$ND$2:$ND$60=F$4),0),$B77-1966)} -> 12.14 | G77: {=INDEX(GMW!$A$2:$NF$60,MATCH(1,(GMW!$NE$2:$NE$60=G$3)*(GMW!$ND$2:$ND$60=G$4),0),$B77-1966)} -> 15.25 | H77: {=INDEX(GMW!$A$2:$NF$60,MATCH(1,(GMW!$NE$2:$NE$60=H$3)*(GMW!$ND$2:$ND$60=H$4),0),$B77-1966)} -> 18.1157
B78: =+B77+1 -> 2044 | C78: {=INDEX(GMW!$A$2:$NF$60,MATCH(1,(GMW!$NE$2:$NE$60=C$3)*(GMW!$ND$2:$ND$60=C$4),0),$B78-1966)} -> 9670 | D78: {=INDEX(GMW!$A$2:$NF$60,MATCH(1,(GMW!$NE$2:$NE$60=D$3)*(GMW!$ND$2:$ND$60=D$4),0),$B78-1966)} -> 13298 | E78: {=INDEX(GMW!$A$2:$NF$60,MATCH(1,(GMW!$NE$2:$NE$60=E$3)*(GMW!$ND$2:$ND$60=E$4),0),$B78-1966)} -> 13.875 | F78: {=INDEX(GMW!$A$2:$NF$60,MATCH(1,(GMW!$NE$2:$NE$60=F$3)*(GMW!$ND$2:$ND$60=F$4),0),$B78-1966)} -> 11.04 | G78: {=INDEX(GMW!$A$2:$NF$60,MATCH(1,(GMW!$NE$2:$NE$60=G$3)*(GMW!$ND$2:$ND$60=G$4),0),$B78-1966)} -> 14.34 | H78: {=INDEX(GMW!$A$2:$NF$60,MATCH(1,(GMW!$NE$2:$NE$60=H$3)*(GMW!$ND$2:$ND$60=H$4),0),$B78-1966)} -> 16.83296
A79: 1991 | B79: =+B78+1 -> 2045 | C79: {=INDEX(GMW!$A$2:$NF$60,MATCH(1,(GMW!$NE$2:$NE$60=C$3)*(GMW!$ND$2:$ND$60=C$4),0),$B79-1966)} -> 10252 | D79: {=INDEX(GMW!$A$2:$NF$60,MATCH(1,(GMW!$NE$2:$NE$60=D$3)*(GMW!$ND$2:$ND$60=D$4),0),$B79-1966)} -> 13298 | E79: {=INDEX(GMW!$A$2:$NF$60,MATCH(1,(GMW!$NE$2:$NE$60=E$3)*(GMW!$ND$2:$ND$60=E$4),0),$B79-1966)} -> 12.375 | F79: {=INDEX(GMW!$A$2:$NF$60,MATCH(1,(GMW!$NE$2:$NE$60=F$3)*(GMW!$ND$2:$ND$60=F$4),0),$B79-1966)} -> 10.14 | G79: {=INDEX(GMW!$A$2:$NF$60,MATCH(1,(GMW!$NE$2:$NE$60=G$3)*(GMW!$ND$2:$ND$60=G$4),0),$B79-1966)} -> 14.24 | H79: {=INDEX(GMW!$A$2:$NF$60,MATCH(1,(GMW!$NE$2:$NE$60=H$3)*(GMW!$ND$2:$ND$60=H$4),0),$B79-1966)} -> 16.06035
B80: =+B79+1 -> 2046 | C80: {=INDEX(GMW!$A$2:$NF$60,MATCH(1,(GMW!$NE$2:$NE$60=C$3)*(GMW!$ND$2:$ND$60=C$4),0),$B80-1966)} -> 8706 | D80: {=INDEX(GMW!$A$2:$NF$60,MATCH(1,(GMW!$NE$2:$NE$60=D$3)*(GMW!$ND$2:$ND$60=D$4),0),$B80-1966)} -> 12592 | E80: {=INDEX(GMW!$A$2:$NF$60,MATCH(1,(GMW!$NE$2:$NE$60=E$3)*(GMW!$ND$2:$ND$60=E$4),0),$B80-1966)} -> 11.375 | F80: {=INDEX(GMW!$A$2:$NF$60,MATCH(1,(GMW!$NE$2:$NE$60=F$3)*(GMW!$ND$2:$ND$60=F$4),0),$B80-1966)} -> 10.56 | G80: {=INDEX(GMW!$A$2:$NF$60,MATCH(1,(GMW!$NE$2:$NE$60=G$3)*(GMW!$ND$2:$ND$60=G$4),0),$B80-1966)} -> 12.75 | H80: {=INDEX(GMW!$A$2:$NF$60,MATCH(1,(GMW!$NE$2:$NE$60=H$3)*(GMW!$ND$2:$ND$60=H$4),0),$B80-1966)} -> 15.97467
B81: =+B80+1 -> 2047 | C81: {=INDEX(GMW!$A$2:$NF$60,MATCH(1,(GMW!$NE$2:$NE$60=C$3)*(GMW!$ND$2:$ND$60=C$4),0),$B81-1966)} -> 8821 | D81: {=INDEX(GMW!$A$2:$NF$60,MATCH(1,(GMW!$NE$2:$NE$60=D$3)*(GMW!$ND$2:$ND$60=D$4),0),$B81-1966)} -> 11972 | E81: {=INDEX(GMW!$A$2:$NF$60,MATCH(1,(GMW!$NE$2:$NE$60=E$3)*(GMW!$ND$2:$ND$60=E$4),0),$B81-1966)} -> 10.375 | F81: {=INDEX(GMW!$A$2:$NF$60,MATCH(1,(GMW!$NE$2:$NE$60=F$3)*(GMW!$ND$2:$ND$60=F$4),0),$B81-1966)} -> 9.58 | G81: {=INDEX(GMW!$A$2:$NF$60,MATCH(1,(GMW!$NE$2:$NE$60=G$3)*(GMW!$ND$2:$ND$60=G$4),0),$B81-1966)} -> 11.82 | H81: {=INDEX(GMW!$A$2:$NF$60,MATCH(1,(GMW!$NE$2:$NE$60=H$3)*(GMW!$ND$2:$ND$60=H$4),0),$B81-1966)} -> 15.40106
B82: =+B81+1 -> 2048 | C82: {=INDEX(GMW!$A$2:$NF$60,MATCH(1,(GMW!$NE$2:$NE$60=C$3)*(GMW!$ND$2:$ND$60=C$4),0),$B82-1966)} -> 7822 | D82: {=INDEX(GMW!$A$2:$NF$60,MATCH(1,(GMW!$NE$2:$NE$60=D$3)*(GMW!$ND$2:$ND$60=D$4),0),$B82-1966)} -> 11596 | E82: {=INDEX(GMW!$A$2:$NF$60,MATCH(1,(GMW!$NE$2:$NE$60=E$3)*(GMW!$ND$2:$ND$60=E$4),0),$B82-1966)} -> 10.375 | F82: {=INDEX(GMW!$A$2:$NF$60,MATCH(1,(GMW!$NE$2:$NE$60=F$3)*(GMW!$ND$2:$ND$60=F$4),0),$B82-1966)} -> 9.73 | G82: {=INDEX(GMW!$A$2:$NF$60,MATCH(1,(GMW!$NE$2:$NE$60=G$3)*(GMW!$ND$2:$ND$60=G$4),0),$B82-1966)} -> 11.39 | H82: {=INDEX(GMW!$A$2:$NF$60,MATCH(1,(GMW!$NE$2:$NE$60=H$3)*(GMW!$ND$2:$ND$60=H$4),0),$B82-1966)} -> 14.88809
A83: 1992 | B83: =+B82+1 -> 2049 | C83: {=INDEX(GMW!$A$2:$NF$60,MATCH(1,(GMW!$NE$2:$NE$60=C$3)*(GMW!$ND$2:$ND$60=C$4),0),$B83-1966)} -> 10088 | D83: {=INDEX(GMW!$A$2:$NF$60,MATCH(1,(GMW!$NE$2:$NE$60=D$3)*(GMW!$ND$2:$ND$60=D$4),0),$B83-1966)} -> 12466 | E83: {=INDEX(GMW!$A$2:$NF$60,MATCH(1,(GMW!$NE$2:$NE$60=E$3)*(GMW!$ND$2:$ND$60=E$4),0),$B83-1966)} -> 10.375 | F83: {=INDEX(GMW!$A$2:$NF$60,MATCH(1,(GMW!$NE$2:$NE$60=F$3)*(GMW!$ND$2:$ND$60=F$4),0),$B83-1966)} -> 9.9 | G83: {=INDEX(GMW!$A$2:$NF$60,MATCH(1,(GMW!$NE$2:$NE$60=G$3)*(GMW!$ND$2:$ND$60=G$4),0),$B83-1966)} -> 10.96 | H83: {=INDEX(GMW!$A$2:$NF$60,MATCH(1,(GMW!$NE$2:$NE$60=H$3)*(GMW!$ND$2:$ND$60=H$4),0),$B83-1966)} -> 14.37461
B84: =+B83+1 -> 2050 | C84: {=INDEX(GMW!$A$2:$NF$60,MATCH(1,(GMW!$NE$2:$NE$60=C$3)*(GMW!$ND$2:$ND$60=C$4),0),$B84-1966)} -> 7880 | D84: {=INDEX(GMW!$A$2:$NF$60,MATCH(1,(GMW!$NE$2:$NE$60=D$3)*(GMW!$ND$2:$ND$60=D$4),0),$B84-1966)} -> 11383 | E84: {=INDEX(GMW!$A$2:$NF$60,MATCH(1,(GMW!$NE$2:$NE$60=E$3)*(GMW!$ND$2:$ND$60=E$4),0),$B84-1966)} -> 9.875 | F84: {=INDEX(GMW!$A$2:$NF$60,MATCH(1,(GMW!$NE$2:$NE$60=F$3)*(GMW!$ND$2:$ND$60=F$4),0),$B84-1966)} -> 9.11 | G84: {=INDEX(GMW!$A$2:$NF$60,MATCH(1,(GMW!$NE$2:$NE$60=G$3)*(GMW!$ND$2:$ND$60=G$4),0),$B84-1966)} -> 10.82 | H84: {=INDEX(GMW!$A$2:$NF$60,MATCH(1,(GMW!$NE$2:$NE$60=H$3)*(GMW!$ND$2:$ND$60=H$4),0),$B84-1966)} -> 13.85318
B85: =+B84+1 -> 2051 | C85: {=INDEX(GMW!$A$2:$NF$60,MATCH(1,(GMW!$NE$2:$NE$60=C$3)*(GMW!$ND$2:$ND$60=C$4),0),$B85-1966)} -> 7774 | D85: {=INDEX(GMW!$A$2:$NF$60,MATCH(1,(GMW!$NE$2:$NE$60=D$3)*(GMW!$ND$2:$ND$60=D$4),0),$B85-1966)} -> 11075 | E85: {=INDEX(GMW!$A$2:$NF$60,MATCH(1,(GMW!$NE$2:$NE$60=E$3)*(GMW!$ND$2:$ND$60=E$4),0),$B85-1966)} -> 8.875 | F85: {=INDEX(GMW!$A$2:$NF$60,MATCH(1,(GMW!$NE$2:$NE$60=F$3)*(GMW!$ND$2:$ND$60=F$4),0),$B85-1966)} -> 8.96 | G85: {=INDEX(GMW!$A$2:$NF$60,MATCH(1,(GMW!$NE$2:$NE$60=G$3)*(GMW!$ND$2:$ND$60=G$4),0),$B85-1966)} -> 10.6 | H85: {=INDEX(GMW!$A$2:$NF$60,MATCH(1,(GMW!$NE$2:$NE$60=H$3)*(GMW!$ND$2:$ND$60=H$4),0),$B85-1966)} -> 13.69709
B86: =+B85+1 -> 2052 | C86: {=INDEX(GMW!$A$2:$NF$60,MATCH(1,(GMW!$NE$2:$NE$60=C$3)*(GMW!$ND$2:$ND$60=C$4),0),$B86-1966)} -> 6753 | D86: {=INDEX(GMW!$A$2:$NF$60,MATCH(1,(GMW!$NE$2:$NE$60=D$3)*(GMW!$ND$2:$ND$60=D$4),0),$B86-1966)} -> 10240 | E86: {=INDEX(GMW!$A$2:$NF$60,MATCH(1,(GMW!$NE$2:$NE$60=E$3)*(GMW!$ND$2:$ND$60=E$4),0),$B86-1966)} -> 6.875 | F86: {=INDEX(GMW!$A$2:$NF$60,MATCH(1,(GMW!$NE$2:$NE$60=F$3)*(GMW!$ND$2:$ND$60=F$4),0),$B86-1966)} -> 8.17 | G86: {=INDEX(GMW!$A$2:$NF$60,MATCH(1,(GMW!$NE$2:$NE$60=G$3)*(GMW!$ND$2:$ND$60=G$4),0),$B86-1966)} -> 8.98 | H86: {=INDEX(GMW!$A$2:$NF$60,MATCH(1,(GMW!$NE$2:$NE$60=H$3)*(GMW!$ND$2:$ND$60=H$4),0),$B86-1966)} -> 12.96445
A87: 1993 | B87: =+B86+1 -> 2053 | C87: {=INDEX(GMW!$A$2:$NF$60,MATCH(1,(GMW!$NE$2:$NE$60=C$3)*(GMW!$ND$2:$ND$60=C$4),0),$B87-1966)} -> 5846 | D87: {=INDEX(GMW!$A$2:$NF$60,MATCH(1,(GMW!$NE$2:$NE$60=D$3)*(GMW!$ND$2:$ND$60=D$4),0),$B87-1966)} -> 9225 | E87: {=INDEX(GMW!$A$2:$NF$60,MATCH(1,(GMW!$NE$2:$NE$60=E$3)*(GMW!$ND$2:$ND$60=E$4),0),$B87-1966)} -> 5.875 | F87: {=INDEX(GMW!$A$2:$NF$60,MATCH(1,(GMW!$NE$2:$NE$60=F$3)*(GMW!$ND$2:$ND$60=F$4),0),$B87-1966)} -> 7.8 | G87: {=INDEX(GMW!$A$2:$NF$60,MATCH(1,(GMW!$NE$2:$NE$60=G$3)*(GMW!$ND$2:$ND$60=G$4),0),$B87-1966)} -> 8.04 | H87: {=INDEX(GMW!$A$2:$NF$60,MATCH(1,(GMW!$NE$2:$NE$60=H$3)*(GMW!$ND$2:$ND$60=H$4),0),$B87-1966)} -> 12.44909
B88: =+B87+1 -> 2054 | C88: {=INDEX(GMW!$A$2:$NF$60,MATCH(1,(GMW!$NE$2:$NE$60=C$3)*(GMW!$ND$2:$ND$60=C$4),0),$B88-1966)} -> 5963 | D88: {=INDEX(GMW!$A$2:$NF$60,MATCH(1,(GMW!$NE$2:$NE$60=D$3)*(GMW!$ND$2:$ND$60=D$4),0),$B88-1966)} -> 8905 | E88: {=INDEX(GMW!$A$2:$NF$60,MATCH(1,(GMW!$NE$2:$NE$60=E$3)*(GMW!$ND$2:$ND$60=E$4),0),$B88-1966)} -> 5.875 | F88: {=INDEX(GMW!$A$2:$NF$60,MATCH(1,(GMW!$NE$2:$NE$60=F$3)*(GMW!$ND$2:$ND$60=F$4),0),$B88-1966)} -> 7.7 | G88: {=INDEX(GMW!$A$2:$NF$60,MATCH(1,(GMW!$NE$2:$NE$60=G$3)*(GMW!$ND$2:$ND$60=G$4),0),$B88-1966)} -> 8.01 | H88: {=INDEX(GMW!$A$2:$NF$60,MATCH(1,(GMW!$NE$2:$NE$60=H$3)*(GMW!$ND$2:$ND$60=H$4),0),$B88-1966)} -> 12.37718
B89: =+B88+1 -> 2055 | C89: {=INDEX(GMW!$A$2:$NF$60,MATCH(1,(GMW!$NE$2:$NE$60=C$3)*(GMW!$ND$2:$ND$60=C$4),0),$B89-1966)} -> 5830 | D89: {=INDEX(GMW!$A$2:$NF$60,MATCH(1,(GMW!$NE$2:$NE$60=D$3)*(GMW!$ND$2:$ND$60=D$4),0),$B89-1966)} -> 8860 | E89: {=INDEX(GMW!$A$2:$NF$60,MATCH(1,(GMW!$NE$2:$NE$60=E$3)*(GMW!$ND$2:$ND$60=E$4),0),$B89-1966)} -> 5.875 | F89: {=INDEX(GMW!$A$2:$NF$60,MATCH(1,(GMW!$NE$2:$NE$60=F$3)*(GMW!$ND$2:$ND$60=F$4),0),$B89-1966)} -> 6.96 | G89: {=INDEX(GMW!$A$2:$NF$60,MATCH(1,(GMW!$NE$2:$NE$60=G$3)*(GMW!$ND$2:$ND$60=G$4),0),$B89-1966)} -> 8 | H89: {=INDEX(GMW!$A$2:$NF$60,MATCH(1,(GMW!$NE$2:$NE$60=H$3)*(GMW!$ND$2:$ND$60=H$4),0),$B89-1966)} -> 11.09389
B90: =+B89+1 -> 2056 | C90: {=INDEX(GMW!$A$2:$NF$60,MATCH(1,(GMW!$NE$2:$NE$60=C$3)*(GMW!$ND$2:$ND$60=C$4),0),$B90-1966)} -> 5957 | D90: {=INDEX(GMW!$A$2:$NF$60,MATCH(1,(GMW!$NE$2:$NE$60=D$3)*(GMW!$ND$2:$ND$60=D$4),0),$B90-1966)} -> 8936 | E90: {=INDEX(GMW!$A$2:$NF$60,MATCH(1,(GMW!$NE$2:$NE$60=E$3)*(GMW!$ND$2:$ND$60=E$4),0),$B90-1966)} -> 5.375 | F90: {=INDEX(GMW!$A$2:$NF$60,MATCH(1,(GMW!$NE$2:$NE$60=F$3)*(GMW!$ND$2:$ND$60=F$4),0),$B90-1966)} -> 6.2391 | G90: {=INDEX(GMW!$A$2:$NF$60,MATCH(1,(GMW!$NE$2:$NE$60=G$3)*(GMW!$ND$2:$ND$60=G$4),0),$B90-1966)} -> 7.94 | H90: {=INDEX(GMW!$A$2:$NF$60,MATCH(1,(GMW!$NE$2:$NE$60=H$3)*(GMW!$ND$2:$ND$60=H$4),0),$B90-1966)} -> 10.37208
A91: 1994 | B91: =+B90+1 -> 2057 | C91: {=INDEX(GMW!$A$2:$NF$60,MATCH(1,(GMW!$NE$2:$NE$60=C$3)*(GMW!$ND$2:$ND$60=C$4),0),$B91-1966)} -> 5390 | D91: {=INDEX(GMW!$A$2:$NF$60,MATCH(1,(GMW!$NE$2:$NE$60=D$3)*(GMW!$ND$2:$ND$60=D$4),0),$B91-1966)} -> 8891 | E91: {=INDEX(GMW!$A$2:$NF$60,MATCH(1,(GMW!$NE$2:$NE$60=E$3)*(GMW!$ND$2:$ND$60=E$4),0),$B91-1966)} -> 5.125 | F91: {=INDEX(GMW!$A$2:$NF$60,MATCH(1,(GMW!$NE$2:$NE$60=F$3)*(GMW!$ND$2:$ND$60=F$4),0),$B91-1966)} -> 7.5 | G91: {=INDEX(GMW!$A$2:$NF$60,MATCH(1,(GMW!$NE$2:$NE$60=G$3)*(GMW!$ND$2:$ND$60=G$4),0),$B91-1966)} -> 7.66 | H91: {=INDEX(GMW!$A$2:$NF$60,MATCH(1,(GMW!$NE$2:$NE$60=H$3)*(GMW!$ND$2:$ND$60=H$4),0),$B91-1966)} -> 10.67239
B92: =+B91+1 -> 2058 | C92: {=INDEX(GMW!$A$2:$NF$60,MATCH(1,(GMW!$NE$2:$NE$60=C$3)*(GMW!$ND$2:$ND$60=C$4),0),$B92-1966)} -> 5714 | D92: {=INDEX(GMW!$A$2:$NF$60,MATCH(1,(GMW!$NE$2:$NE$60=D$3)*(GMW!$ND$2:$ND$60=D$4),0),$B92-1966)} -> 9343 | E92: {=INDEX(GMW!$A$2:$NF$60,MATCH(1,(GMW!$NE$2:$NE$60=E$3)*(GMW!$ND$2:$ND$60=E$4),0),$B92-1966)} -> 5.125 | F92: {=INDEX(GMW!$A$2:$NF$60,MATCH(1,(GMW!$NE$2:$NE$60=F$3)*(GMW!$ND$2:$ND$60=F$4),0),$B92-1966)} -> 8.59 | G92: {=INDEX(GMW!$A$2:$NF$60,MATCH(1,(GMW!$NE$2:$NE$60=G$3)*(GMW!$ND$2:$ND$60=G$4),0),$B92-1966)} -> 7.61 | H92: {=INDEX(GMW!$A$2:$NF$60,MATCH(1,(GMW!$NE$2:$NE$60=H$3)*(GMW!$ND$2:$ND$60=H$4),0),$B92-1966)} -> 13.02328
B93: =+B92+1 -> 2059 | C93: {=INDEX(GMW!$A$2:$NF$60,MATCH(1,(GMW!$NE$2:$NE$60=C$3)*(GMW!$ND$2:$ND$60=C$4),0),$B93-1966)} -> 5337 | D93: {=INDEX(GMW!$A$2:$NF$60,MATCH(1,(GMW!$NE$2:$NE$60=D$3)*(GMW!$ND$2:$ND$60=D$4),0),$B93-1966)} -> 9086 | E93: {=INDEX(GMW!$A$2:$NF$60,MATCH(1,(GMW!$NE$2:$NE$60=E$3)*(GMW!$ND$2:$ND$60=E$4),0),$B93-1966)} -> 5.625 | F93: {=INDEX(GMW!$A$2:$NF$60,MATCH(1,(GMW!$NE$2:$NE$60=F$3)*(GMW!$ND$2:$ND$60=F$4),0),$B93-1966)} -> 8.8 | G93: {=INDEX(GMW!$A$2:$NF$60,MATCH(1,(GMW!$NE$2:$NE$60=G$3)*(GMW!$ND$2:$ND$60=G$4),0),$B93-1966)} -> 7.57 | H93: {=INDEX(GMW!$A$2:$NF$60,MATCH(1,(GMW!$NE$2:$NE$60=H$3)*(GMW!$ND$2:$ND$60=H$4),0),$B93-1966)} -> 13.47923
B94: =+B93+1 -> 2060 | C94: {=INDEX(GMW!$A$2:$NF$60,MATCH(1,(GMW!$NE$2:$NE$60=C$3)*(GMW!$ND$2:$ND$60=C$4),0),$B94-1966)} -> 5749 | D94: {=INDEX(GMW!$A$2:$NF$60,MATCH(1,(GMW!$NE$2:$NE$60=D$3)*(GMW!$ND$2:$ND$60=D$4),0),$B94-1966)} -> 9357 | E94: {=INDEX(GMW!$A$2:$NF$60,MATCH(1,(GMW!$NE$2:$NE$60=E$3)*(GMW!$ND$2:$ND$60=E$4),0),$B94-1966)} -> 6.125 | F94: {=INDEX(GMW!$A$2:$NF$60,MATCH(1,(GMW!$NE$2:$NE$60=F$3)*(GMW!$ND$2:$ND$60=F$4),0),$B94-1966)} -> 8.7 | G94: {=INDEX(GMW!$A$2:$NF$60,MATCH(1,(GMW!$NE$2:$NE$60=G$3)*(GMW!$ND$2:$ND$60=G$4),0),$B94-1966)} -> 7.84 | H94: {=INDEX(GMW!$A$2:$NF$60,MATCH(1,(GMW!$NE$2:$NE$60=H$3)*(GMW!$ND$2:$ND$60=H$4),0),$B94-1966)} -> 13.42821
A95: 1995 | B95: =+B94+1 -> 2061 | C95: {=INDEX(GMW!$A$2:$NF$60,MATCH(1,(GMW!$NE$2:$NE$60=C$3)*(GMW!$ND$2:$ND$60=C$4),0),$B95-1966)} -> 6546 | D95: {=INDEX(GMW!$A$2:$NF$60,MATCH(1,(GMW!$NE$2:$NE$60=D$3)*(GMW!$ND$2:$ND$60=D$4),0),$B95-1966)} -> 9868 | E95: {=INDEX(GMW!$A$2:$NF$60,MATCH(1,(GMW!$NE$2:$NE$60=E$3)*(GMW!$ND$2:$ND$60=E$4),0),$B95-1966)} -> 6.625 | F95: {=INDEX(GMW!$A$2:$NF$60,MATCH(1,(GMW!$NE$2:$NE$60=F$3)*(GMW!$ND$2:$ND$60=F$4),0),$B95-1966)} -> 8.49 | G95: {=INDEX(GMW!$A$2:$NF$60,MATCH(1,(GMW!$NE$2:$NE$60=G$3)*(GMW!$ND$2:$ND$60=G$4),0),$B95-1966)} -> 8 | H95: {=INDEX(GMW!$A$2:$NF$60,MATCH(1,(GMW!$NE$2:$NE$60=H$3)*(GMW!$ND$2:$ND$60=H$4),0),$B95-1966)} -> 13.26425
B96: =+B95+1 -> 2062 | C96: {=INDEX(GMW!$A$2:$NF$60,MATCH(1,(GMW!$NE$2:$NE$60=C$3)*(GMW!$ND$2:$ND$60=C$4),0),$B96-1966)} -> 6787 | D96: {=INDEX(GMW!$A$2:$NF$60,MATCH(1,(GMW!$NE$2:$NE$60=D$3)*(GMW!$ND$2:$ND$60=D$4),0),$B96-1966)} -> 10163 | E96: {=INDEX(GMW!$A$2:$NF$60,MATCH(1,(GMW!$NE$2:$NE$60=E$3)*(GMW!$ND$2:$ND$60=E$4),0),$B96-1966)} -> 6.625 | F96: {=INDEX(GMW!$A$2:$NF$60,MATCH(1,(GMW!$NE$2:$NE$60=F$3)*(GMW!$ND$2:$ND$60=F$4),0),$B96-1966)} -> 8.48 | G96: {=INDEX(GMW!$A$2:$NF$60,MATCH(1,(GMW!$NE$2:$NE$60=G$3)*(GMW!$ND$2:$ND$60=G$4),0),$B96-1966)} -> 7.95 | H96: {=INDEX(GMW!$A$2:$NF$60,MATCH(1,(GMW!$NE$2:$NE$60=H$3)*(GMW!$ND$2:$ND$60=H$4),0),$B96-1966)} -> 12.6335
B97: =+B96+1 -> 2063 | C97: {=INDEX(GMW!$A$2:$NF$60,MATCH(1,(GMW!$NE$2:$NE$60=C$3)*(GMW!$ND$2:$ND$60=C$4),0),$B97-1966)} -> 6608 | D97: {=INDEX(GMW!$A$2:$NF$60,MATCH(1,(GMW!$NE$2:$NE$60=D$3)*(GMW!$ND$2:$ND$60=D$4),0),$B97-1966)} -> 10060 | E97: {=INDEX(GMW!$A$2:$NF$60,MATCH(1,(GMW!$NE$2:$NE$60=E$3)*(GMW!$ND$2:$ND$60=E$4),0),$B97-1966)} -> 6.625 | F97: {=INDEX(GMW!$A$2:$NF$60,MATCH(1,(GMW!$NE$2:$NE$60=F$3)*(GMW!$ND$2:$ND$60=F$4),0),$B97-1966)} -> 8.12 | G97: {=INDEX(GMW!$A$2:$NF$60,MATCH(1,(GMW!$NE$2:$NE$60=G$3)*(GMW!$ND$2:$ND$60=G$4),0),$B97-1966)} -> 7.9 | H97: {=INDEX(GMW!$A$2:$NF$60,MATCH(1,(GMW!$NE$2:$NE$60=H$3)*(GMW!$ND$2:$ND$60=H$4),0),$B97-1966)} -> 12.50264
B98: =+B97+1 -> 2064 | C98: {=INDEX(GMW!$A$2:$NF$60,MATCH(1,(GMW!$NE$2:$NE$60=C$3)*(GMW!$ND$2:$ND$60=C$4),0),$B98-1966)} -> 6634 | D98: {=INDEX(GMW!$A$2:$NF$60,MATCH(1,(GMW!$NE$2:$NE$60=D$3)*(GMW!$ND$2:$ND$60=D$4),0),$B98-1966)} -> 9867 | E98: {=INDEX(GMW!$A$2:$NF$60,MATCH(1,(GMW!$NE$2:$NE$60=E$3)*(GMW!$ND$2:$ND$60=E$4),0),$B98-1966)} -> 6.375 | F98: {=INDEX(GMW!$A$2:$NF$60,MATCH(1,(GMW!$NE$2:$NE$60=F$3)*(GMW!$ND$2:$ND$60=F$4),0),$B98-1966)} -> 7.43 | G98: {=INDEX(GMW!$A$2:$NF$60,MATCH(1,(GMW!$NE$2:$NE$60=G$3)*(GMW!$ND$2:$ND$60=G$4),0),$B98-1966)} -> 7.48 | H98: {=INDEX(GMW!$A$2:$NF$60,MATCH(1,(GMW!$NE$2:$NE$60=H$3)*(GMW!$ND$2:$ND$60=H$4),0),$B98-1966)} -> 12.12017
A99: 1996 | B99: =+B98+1 -> 2065 | C99: {=INDEX(GMW!$A$2:$NF$60,MATCH(1,(GMW!$NE$2:$NE$60=C$3)*(GMW!$ND$2:$ND$60=C$4),0),$B99-1966)} -> 6041 | D99: {=INDEX(GMW!$A$2:$NF$60,MATCH(1,(GMW!$NE$2:$NE$60=D$3)*(GMW!$ND$2:$ND$60=D$4),0),$B99-1966)} -> 9831 | E99: {=INDEX(GMW!$A$2:$NF$60,MATCH(1,(GMW!$NE$2:$NE$60=E$3)*(GMW!$ND$2:$ND$60=E$4),0),$B99-1966)} -> 5.9375 | F99: {=INDEX(GMW!$A$2:$NF$60,MATCH(1,(GMW!$NE$2:$NE$60=F$3)*(GMW!$ND$2:$ND$60=F$4),0),$B99-1966)} -> 8.15 | G99: {=INDEX(GMW!$A$2:$NF$60,MATCH(1,(GMW!$NE$2:$NE$60=G$3)*(GMW!$ND$2:$ND$60=G$4),0),$B99-1966)} -> 7.03 | H99: {=INDEX(GMW!$A$2:$NF$60,MATCH(1,(GMW!$NE$2:$NE$60=H$3)*(GMW!$ND$2:$ND$60=H$4),0),$B99-1966)} -> 12.16099
B100: =+B99+1 -> 2066 | C100: {=INDEX(GMW!$A$2:$NF$60,MATCH(1,(GMW!$NE$2:$NE$60=C$3)*(GMW!$ND$2:$ND$60=C$4),0),$B100-1966)} -> 6035 | D100: {=INDEX(GMW!$A$2:$NF$60,MATCH(1,(GMW!$NE$2:$NE$60=D$3)*(GMW!$ND$2:$ND$60=D$4),0),$B100-1966)} -> 9604 | E100: {=INDEX(GMW!$A$2:$NF$60,MATCH(1,(GMW!$NE$2:$NE$60=E$3)*(GMW!$ND$2:$ND$60=E$4),0),$B100-1966)} -> 5.6875 | F100: {=INDEX(GMW!$A$2:$NF$60,MATCH(1,(GMW!$NE$2:$NE$60=F$3)*(GMW!$ND$2:$ND$60=F$4),0),$B100-1966)} -> 7.88 | G100: {=INDEX(GMW!$A$2:$NF$60,MATCH(1,(GMW!$NE$2:$NE$60=G$3)*(GMW!$ND$2:$ND$60=G$4),0),$B100-1966)} -> 6.71 | H100: {=INDEX(GMW!$A$2:$NF$60,MATCH(1,(GMW!$NE$2:$NE$60=H$3)*(GMW!$ND$2:$ND$60=H$4),0),$B100-1966)} -> 12.53063
...

Sheet GMW
A1: Location | B1: Indicator | C1: Scenario | D1: Units | E1: Scale | F1: Measurement | G1: 1973 Q1 | H1: 1973 Q2 | I1: 1973 Q3 | J1: 1973 Q4 | K1: 1974 Q1 | L1: 1974 Q2 | M1: 1974 Q3 | N1: 1974 Q4 | O1: 1975 Q1 | P1: 1975 Q2 | Q1: 1975 Q3 | R1: 1975 Q4 | S1: 1976 Q1 | T1: 1976 Q2 | U1: 1976 Q3 | V1: 1976 Q4 | W1: 1977 Q1 | X1: 1977 Q2 | Y1: 1977 Q3 | Z1: 1977 Q4 | AA1: 1978 Q1 | AB1: 1978 Q2 | AC1: 1978 Q3 | AD1: 1978 Q4 | AE1: 1979 Q1 | AF1: 1979 Q2 | AG1: 1979 Q3 | AH1: 1979 Q4 | AI1: 1980 Q1 | AJ1: 1980 Q2 | AK1: 1980 Q3 | AL1: 1980 Q4 | AM1: 1981 Q1 | AN1: 1981 Q2 | AO1: 1981 Q3 | AP1: 1981 Q4 | AQ1: 1982 Q1 | AR1: 1982 Q2 | AS1: 1982 Q3 | AT1: 1982 Q4 | AU1: 1983 Q1 | AV1: 1983 Q2 | AW1: 1983 Q3 | AX1: 1983 Q4 | AY1: 1984 Q1 | AZ1: 1984 Q2 | BA1: 1984 Q3 | BB1: 1984 Q4 | BC1: 1985 Q1 | BD1: 1985 Q2 | BE1: 1985 Q3 | BF1: 1985 Q4 | BG1: 1986 Q1 | BH1: 1986 Q2 | BI1: 1986 Q3 | BJ1: 1986 Q4 | BK1: 1987 Q1 | BL1: 1987 Q2 | BM1: 1987 Q3 | BN1: 1987 Q4 | BO1: 1988 Q1 | BP1: 1988 Q2 | BQ1: 1988 Q3 | BR1: 1988 Q4 | BS1: 1989 Q1 | BT1: 1989 Q2 | BU1: 1989 Q3 | BV1: 1989 Q4 | BW1: 1990 Q1 | BX1: 1990 Q2 | BY1: 1990 Q3 | BZ1: 1990 Q4 | CA1: 1991 Q1 | CB1: 1991 Q2 | CC1: 1991 Q3 | CD1: 1991 Q4 | CE1: 1992 Q1 | CF1: 1992 Q2 | CG1: 1992 Q3 | CH1: 1992 Q4 | CI1: 1993 Q1 | CJ1: 1993 Q2 | CK1: 1993 Q3 | CL1: 1993 Q4 | CM1: 1994 Q1 | CN1: 1994 Q2 | CO1: 1994 Q3 | CP1: 1994 Q4 | CQ1: 1995 Q1 | CR1: 1995 Q2 | CS1: 1995 Q3 | CT1: 1995 Q4 | CU1: 1996 Q1 | CV1: 1996 Q2 | CW1: 1996 Q3 | CX1: 1996 Q4 | CY1: 1997 Q1 | CZ1: 1997 Q2 | DA1: 1997 Q3 | DB1: 1997 Q4 | DC1: 1998 Q1 | DD1: 1998 Q2 | DE1: 1998 Q3 | DF1: 1998 Q4 | DG1: 1999 Q1 | DH1: 1999 Q2 | DI1: 1999 Q3 | DJ1: 1999 Q4 | DK1: 2000 Q1 | DL1: 2000 Q2 | DM1: 2000 Q3 | DN1: 2000 Q4 | DO1: 2001 Q1 | DP1: 2001 Q2 | DQ1: 2001 Q3 | DR1: 2001 Q4 | DS1: 2002 Q1 | DT1: 2002 Q2 | DU1: 2002 Q3 | DV1: 2002 Q4 | DW1: 2003 Q1 | DX1: 2003 Q2 | DY1: 2003 Q3 | DZ1: 2003 Q4 | EA1: 2004 Q1 | EB1: 2004 Q2 | EC1: 2004 Q3 | ED1: 2004 Q4 | EE1: 2005 Q1 | EF1: 2005 Q2 | EG1: 2005 Q3 | EH1: 2005 Q4 | EI1: 2006 Q1 | EJ1: 2006 Q2 | EK1: 2006 Q3 | EL1: 2006 Q4 | EM1: 2007 Q1 | EN1: 2007 Q2 | EO1: 2007 Q3 | EP1: 2007 Q4 | EQ1: 2008 Q1 | ER1: 2008 Q2 | ES1: 2008 Q3 | ET1: 2008 Q4 | EU1: 2009 Q1 | EV1: 2009 Q2 | EW1: 2009 Q3 | EX1: 2009 Q4 | EY1: 2010 Q1 | EZ1: 2010 Q2 | FA1: 2010 Q3 | FB1: 2010 Q4 | FC1: 2011 Q1 | FD1: 2011 Q2 | FE1: 2011 Q3 | FF1: 2011 Q4 | FG1: 2012 Q1 | FH1: 2012 Q2 | FI1: 2012 Q3 | FJ1: 2012 Q4 | FK1: 2013 Q1 | FL1: 2013 Q2 | FM1: 2013 Q3 | FN1: 2013 Q4 | FO1: 2014 Q1 | FP1: 2014 Q2 | FQ1: 2014 Q3 | FR1: 2014 Q4 | FS1: 2015 Q1 | FT1: 2015 Q2 | FU1: 2015 Q3 | FV1: 2015 Q4 | FW1: 2016 Q1 | FX1: 2016 Q2 | FY1: 2016 Q3 | FZ1: 2016 Q4 | GA1: 2017 Q1 | GB1: 2017 Q2 | GC1: 2017 Q3 | GD1: 2017 Q4 | GE1: 2018 Q1 | GF1: 2018 Q2 | GG1: 2018 Q3 | GH1: 2018 Q4 | GI1: 2019 Q1 | GJ1: 2019 Q2 | GK1: 2019 Q3 | GL1: 2019 Q4 | GM1: 2020 Q1 | GN1: 2020 Q2 | GO1: 2020 Q3 | GP1: 2020 Q4 | GQ1: 2021 Q1 | GR1: 2021 Q2 | GS1: 2021 Q3 | GT1: 2021 Q4 | GU1: 2022 Q1 | GV1: 2022 Q2 | GW1: 2022 Q3 | GX1: 2022 Q4 | GY1: 2023 Q1 | GZ1: 2023 Q2 | HA1: 2023 Q3 | HB1: 2023 Q4 | HC1: 2024 Q1 | HD1: 2024 Q2 | HE1: 2024 Q3 | HF1: 2024 Q4 | HG1: 2025 Q1 | HH1: 2025 Q2 | HI1: 2025 Q3 | HJ1: 2025 Q4 | HK1: 2026 Q1 | HL1: 2026 Q2 | HM1: 2026 Q3 | HN1: 2026 Q4 | HO1: 2027 Q1 | HP1: 2027 Q2 | HQ1: 2027 Q3 | HR1: 2027 Q4 | HS1: 2028 Q1 | HT1: 2028 Q2 | HU1: 2028 Q3 | HV1: 2028 Q4 | HW1: 2029 Q1 | HX1: 2029 Q2 | HY1: 2029 Q3 | HZ1: 2029 Q4 | IA1: 2030 Q1 | IB1: 2030 Q2 | IC1: 2030 Q3 | ID1: 2030 Q4 | IE1: 2031 Q1 | IF1: 2031 Q2 | IG1: 2031 Q3 | IH1: 2031 Q4 | II1: 2032 Q1 | IJ1: 2032 Q2 | IK1: 2032 Q3 | IL1: 2032 Q4 | IM1: 2033 Q1 | IN1: 2033 Q2 | IO1: 2033 Q3 | IP1: 2033 Q4 | IQ1: 2034 Q1 | IR1: 2034 Q2 | IS1: 2034 Q3 | IT1: 2034 Q4 | IU1: 2035 Q1 | IV1: 2035 Q2 | IW1: 2035 Q3 | IX1: 2035 Q4 | IY1: 2036 Q1 | IZ1: 2036 Q2 | JA1: 2036 Q3 | JB1: 2036 Q4 | JC1: 2037 Q1 | JD1: 2037 Q2 | JE1: 2037 Q3 | JF1: 2037 Q4 | JG1: 2038 Q1 | JH1: 2038 Q2 | JI1: 2038 Q3 | JJ1: 2038 Q4 | JK1: 2039 Q1 | JL1: 2039 Q2 | JM1: 2039 Q3 | JN1: 2039 Q4 | JO1: 2040 Q1 | JP1: 2040 Q2 | JQ1: 2040 Q3 | JR1: 2040 Q4 | JS1: 2041 Q1 | JT1: 2041 Q2 | JU1: 2041 Q3 | JV1: 2041 Q4 | JW1: 2042 Q1 | JX1: 2042 Q2 | JY1: 2042 Q3 | JZ1: 2042 Q4 | KA1: 2043 Q1 | KB1: 2043 Q2 | KC1: 2043 Q3 | KD1: 2043 Q4 | KE1: 2044 Q1 | KF1: 2044 Q2 | KG1: 2044 Q3 | KH1: 2044 Q4 | KI1: 2045 Q1 | KJ1: 2045 Q2 | KK1: 2045 Q3 | KL1: 2045 Q4 | KM1: 2046 Q1 | KN1: 2046 Q2 | KO1: 2046 Q3 | KP1: 2046 Q4 | KQ1: 2047 Q1 | KR1: 2047 Q2 | KS1: 2047 Q3 | KT1: 2047 Q4 | KU1: 2048 Q1 | KV1: 2048 Q2 | KW1: 2048 Q3 | KX1: 2048 Q4 | KY1: 2049 Q1 | KZ1: 2049 Q2 | LA1: 2049 Q3 | LB1: 2049 Q4 | LC1: 2050 Q1 | LD1: 2050 Q2 | LE1: 2050 Q3 | LF1: 2050 Q4 | LG1: 2051 Q1 | LH1: 2051 Q2 | LI1: 2051 Q3 | LJ1: 2051 Q4 | LK1: 2052 Q1 | LL1: 2052 Q2 | LM1: 2052 Q3 | LN1: 2052 Q4 | LO1: 2053 Q1 | LP1: 2053 Q2 | LQ1: 2053 Q3 | LR1: 2053 Q4 | LS1: 2054 Q1 | LT1: 2054 Q2 | LU1: 2054 Q3 | LV1: 2054 Q4 | LW1: 2055 Q1 | LX1: 2055 Q2 | LY1: 2055 Q3 | LZ1: 2055 Q4 | MA1: 2056 Q1 | MB1: 2056 Q2 | MC1: 2056 Q3 | MD1: 2056 Q4 | ME1: 2057 Q1 | MF1: 2057 Q2 | MG1: 2057 Q3 | MH1: 2057 Q4 | MI1: 2058 Q1 | MJ1: 2058 Q2 | MK1: 2058 Q3 | ML1: 2058 Q4 | MM1: 2059 Q1 | MN1: 2059 Q2 | MO1: 2059 Q3 | MP1: 2059 Q4 | MQ1: 2060 Q1 | MR1: 2060 Q2 | MS1: 2060 Q3 | MT1: 2060 Q4 | MU1: Source | MV1: Seasonally adjusted | MW1: Base year price | MX1: Base year index | MY1: Historical end year | MZ1: Historical end quarter | NA1: Date of last update | NB1: Source details | NC1: Additional source details | ND1: Location code | NE1: Indicator code | NF1: Databank code
A2: United Kingdom | B2: Interest rate on mortgages | C2: JUL009E | D2: % | E2: NA | F2: Level | G2: 8.5 | H2: 9.5 | I2: 10 | J2: 11 | K2: 11 | L2: 11 | M2: 11 | N2: 11 | O2: 11 | P2: 11 | Q2: 11 | R2: 11 | S2: 11 | T2: 10.5 | U2: 10.5 | V2: 12.25 | W2: 12.25 | X2: 11.25 | Y2: 10.5 | Z2: 9.5 | AA2: 8.5 | AB2: 8.5 | AC2: 9.75 | AD2: 10.42 | AE2: 11.75 | AF2: 11.246 | AG2: 11.75 | AH2: 13.38 | AI2: 14.7821 | AJ2: 14.8755 | AK2: 14.8876 | AL2: 14.9682 | AM2: 13.8888 | AN2: 13.0457 | AO2: 12.6246 | AP2: 14.7041 | AQ2: 14.5939 | AR2: 13.4576 | AS2: 12.6124 | AT2: 10.9634 | AU2: 9.92754 | AV2: 10.0759 | AW2: 11.2349 | AX2: 11.2541 | AY2: 11.47 | AZ2: 10.51 | BA2: 13.08 | BB2: 12.19 | BC2: 13.25 | BD2: 14.26 | BE2: 13.06 | BF2: 13.01 | BG2: 13 | BH2: 11.06 | BI2: 11.04 | BJ2: 12.32 | BK2: 12.32 | BL2: 11.28 | BM2: 11.28 | BN2: 10.34 | BO2: 10.26 | BP2: 9.78 | BQ2: 11.54 | BR2: 12.75 | BS2: 13.46 | BT2: 13.43 | BU2: 13.48 | BV2: 14.44 | BW2: 15.24 | BX2: 15.25 | BY2: 15.25 | BZ2: 14.34 | CA2: 14.24 | CB2: 12.75 | CC2: 11.82 | CD2: 11.39 | CE2: 10.96 | CF2: 10.82 | CG2: 10.6 | CH2: 8.98 | CI2: 8.04 | CJ2: 8.01 | CK2: 8 | CL2: 7.94 | CM2: 7.66 | CN2: 7.61 | CO2: 7.57 | CP2: 7.84 | CQ2: 8 | CR2: 7.95 | CS2: 7.9 | CT2: 7.48 | CU2: 7.03 | CV2: 6.71 | CW2: 6.45 | CX2: 6.51 | CY2: 6.66 | CZ2: 6.98 | DA2: 7.5 | DB2: 7.58 | DC2: 7.77 | DD2: 7.78 | DE2: 7.99 | DF2: 7.29 | DG2: 7.17 | DH2: 6.74 | DI2: 6.616667 | DJ2: 6.756667 | DK2: 7.056667 | DL2: 7.143333 | DM2: 7.113333 | DN2: 7.056667 | DO2: 6.936666 | DP2: 6.613333 | DQ2: 6.35 | DR2: 5.846667 | DS2: 5.513333 | DT2: 5.436666 | DU2: 5.313334 | DV2: 5.296667 | DW2: 5.173333 | DX2: 5.01 | DY2: 4.85 | DZ2: 4.806667 | EA2: 4.983333 | EB2: 5.103333 | EC2: 5.463333 | ED2: 5.573333 | EE2: 5.53 | EF2: 5.503334 | EG2: 5.476666 | EH2: 5.35 | EI2: 5.326667 | EJ2: 5.31 | EK2: 5.33 | EL2: 5.45 | EM2: 5.623333 | EN2: 5.703333 | EO2: 5.883333 | EP2: 5.95 | EQ2: 5.856667 | ER2: 5.763333 | ES2: 5.796667 | ET2: 5.386667 | EU2: 4.083333 | EV2: 3.6 | EW2: 3.576667 | EX2: 3.573333 | EY2: 3.666667 | EZ2: 3.66 | FA2: 3.57 | FB2: 3.506667 | FC2: 3.496667 | FD2: 3.47 | FE2: 3.4 | FF2: 3.366667 | FG2: 3.366667 | FH2: 3.38 | FI2: 3.373333 | FJ2: 3.38 | FK2: 3.366667 | FL2: 3.343333 | FM2: 3.316667 | FN2: 3.28 | FO2: 3.25 | FP2: 3.233333 | FQ2: 3.213333 | FR2: 3.186667 | FS2: 3.153333 | FT2: 3.106667 | FU2: 3.056667 | FV2: 3.01 | FW2: 2.95 | FX2: 2.903333 | FY2: 2.82 | FZ2: 2.686667 | GA2: 2.626667 | GB2: 2.586667 | GC2: 2.533333 | GD2: 2.516667 | GE2: 2.52 | GF2: 2.483333 | GG2: 2.48 | GH2: 2.493333 | GI2: 2.463333 | GJ2: 2.436667 | GK2: 2.413333 | GL2: 2.386667 | GM2: 2.356667 | GN2: 2.183333 | GO2: 2.143333 | GP2: 2.12 | GQ2: 2.09 | GR2: 2.073333 | GS2: 2.053333 | GT2: 2.02 | GU2: 2.026667 | GV2: 2.083333 | GW2: 2.186667 | GX2: 2.396667 | GY2: 2.65 | GZ2: 2.84 | HA2: 3.07 | HB2: 3.29 | HC2: 3.473333 | HD2: 3.62 | HE2: 3.726667 | HF2: 3.8 | HG2: 3.846667 | HH2: 3.873333 | HI2: 3.854621 | HJ2: 3.855985 | HK2: 3.88 | HL2: 3.895385 | HM2: 3.944082 | HN2: 3.99024 | HO2: 4.021269 | HP2: 4.029451 | HQ2: 4.010621 | HR2: 3.930274 | HS2: 3.885861 | HT2: 3.845469 | HU2: 3.774884 | HV2: 3.726523 | HW2: 3.694598 | HX2: 3.662805 | HY2: 3.644357 | HZ2: 3.631113 | IA2: 3.614082 | IB2: 3.601967 | IC2: 3.592683 | ID2: 3.583646 | IE2: 3.575486 | IF2: 3.558755 | IG2: 3.542548 | IH2: 3.527422 | II2: 3.51373 | IJ2: 3.499999 | IK2: 3.499999 | IL2: 3.499999 | IM2: 3.5 | IN2: 3.5 | IO2: 3.5 | IP2: 3.5 | IQ2: 3.5 | IR2: 3.5 | IS2: 3.5 | IT2: 3.5 | IU2: 3.5 | IV2: 3.5 | IW2: 3.5 | IX2: 3.5 | IY2: 3.5 | IZ2: 3.5 | JA2: 3.5 | JB2: 3.5 | JC2: 3.5 | JD2: 3.499999 | JE2: 3.499999 | JF2: 3.499999 | JG2: 3.5 | JH2: 3.5 | JI2: 3.5 | JJ2: 3.5 | JK2: 3.5 | JL2: 3.5 | JM2: 3.5 | JN2: 3.499999 | JO2: 3.499999 | JP2: 3.499999 | JQ2: 3.5 | JR2: 3.5 | JS2: 3.5 | JT2: 3.5 | JU2: 3.5 | JV2: 3.5 | JW2: 3.5 | JX2: 3.5 | JY2: 3.5 | JZ2: 3.5 | KA2: 3.5 | KB2: 3.5 | KC2: 3.5 | KD2: 3.5 | KE2: 3.5 | KF2: 3.5 | KG2: 3.5 | KH2: 3.5 | KI2: 3.5 | KJ2: 3.5 | KK2: 3.5 | KL2: 3.5 | KM2: 3.5 | KN2: 3.5 | KO2: 3.5 | KP2: 3.5 | KQ2: 3.5 | KR2: 3.5 | KS2: 3.5 | KT2: 3.499999 | KU2: 3.499999 | KV2: 3.499999 | KW2: 3.499999 | KX2: 3.5 | KY2: 3.5 | KZ2: 3.5 | LA2: 3.5 | LB2: 3.5 | LC2: 3.5 | LD2: 3.5 | LE2: 3.5 | LF2: 3.5 | LG2: 3.5 | LH2: 3.5 | LI2: 3.5 | LJ2: 3.5 | LK2: 3.5 | LL2: 3.5 | LM2: 3.499999 | LN2: 3.499999 | LO2: 3.499999 | LP2: 3.499999 | LQ2: 3.499999 | LR2: 3.499999 | LS2: 3.499999 | LT2: 3.499999 | LU2: 3.499999 | LV2: 3.5 | LW2: 3.5 | LX2: 3.5 | LY2: 3.5 | LZ2: 3.5 | MA2: 3.5 | MB2: 3.5 | MC2: 3.5 | MD2: 3.5 | ME2: 3.5 | MF2: 3.5 | MG2: 3.5 | MH2: 3.5 | MI2: 3.5 | MJ2: 3.5 | MK2: 3.5 | ML2: 3.5 | MM2: 3.5 | MN2: 3.5 | MO2: 3.5 | MP2: 3.5 | MQ2: 3.5 | MR2: 3.5 | MS2: 3.5 | MT2: 3.5 | MU2: Bank of England\Haver Analytics | MV2: False | MW2: NA | MX2: NA | MY2: 2025 | MZ2: 1 | NA2: 09 July 2025 | NB2: UNHSDE@UK,EOP | NC2: UK: Banks Weighted Avg Interest Rate, HH Loans Secured on Dwellings (%) | ND2: GBR | NE2: RBM | NF2: Desktop
A3: United Kingdom | B3: Interest rate on loans | C3: JUL009E | D3: % | E3: NA | F3: Level | G3: 0.001 | H3: 0.001 | I3: 0.001 | J3: 0.001 | K3: 0.001 | L3: 0.001 | M3: 0.001 | N3: 0.001 | O3: 0.001 | P3: 0.001 | Q3: 0.001 | R3: 0.001 | S3: 0.001 | T3: 0.001 | U3: 0.001 | V3: 0.001 | W3: 0.001 | X3: 0.001 | Y3: 0.001 | Z3: 0.001 | AA3: 0.001 | AB3: 0.001 | AC3: 0.001 | AD3: 0.001 | AE3: 0.001 | AF3: 0.001 | AG3: 0.001 | AH3: 0.001 | AI3: 21.73742 | AJ3: 21.10538 | AK3: 20.08708 | AL3: 20.07705 | AM3: 20.83951 | AN3: 21.33612 | AO3: 22.99147 | AP3: 23.60346 | AQ3: 22.09859 | AR3: 20.679 | AS3: 18.48189 | AT3: 16.29983 | AU3: 17.09741 | AV3: 15.8584 | AW3: 16.40517 | AX3: 15.68284 | AY3: 16.20954 | AZ3: 16.98204 | BA3: 17.41845 | BB3: 16.4152 | BC3: 17.15258 | BD3: 16.73122 | BE3: 16.12927 | BF3: 16.05403 | BG3: 15.7982 | BH3: 13.81679 | BI3: 14.83007 | BJ3: 16.54061 | BK3: 14.73477 | BL3: 13.49576 | BM3: 14.87522 | BN3: 14.55418 | BO3: 14.27829 | BP3: 14.10774 | BQ3: 14.98558 | BR3: 14.89528 | BS3: 14.84011 | BT3: 15.50726 | BU3: 15.19124 | BV3: 15.8283 | BW3: 17.3733 | BX3: 18.5471 | BY3: 18.1157 | BZ3: 16.83296 | CA3: 16.06035 | CB3: 15.97467 | CC3: 15.40106 | CD3: 14.88809 | CE3: 14.37461 | CF3: 13.85318 | CG3: 13.69709 | CH3: 12.96445 | CI3: 12.44909 | CJ3: 12.37718 | CK3: 11.09389 | CL3: 10.37208 | CM3: 10.67239 | CN3: 13.02328 | CO3: 13.47923 | CP3: 13.42821 | CQ3: 13.26425 | CR3: 12.6335 | CS3: 12.50264 | CT3: 12.12017 | CU3: 12.16099 | CV3: 12.53063 | CW3: 12.21792 | CX3: 11.70976 | CY3: 11.4412 | CZ3: 11.31494 | DA3: 10.79616 | DB3: 10.06452 | DC3: 9.478765 | DD3: 9.154538 | DE3: 9.030372 | DF3: 8.487697 | DG3: 7.726666 | DH3: 7.103333 | DI3: 7.053333 | DJ3: 7.2 | DK3: 7.606667 | DL3: 7.75 | DM3: 7.753333 | DN3: 7.646667 | DO3: 7.476666 | DP3: 7.16 | DQ3: 6.856667 | DR3: 6.22 | DS3: 5.883333 | DT3: 5.883333 | DU3: 5.856667 | DV3: 5.86 | DW3: 5.716667 | DX3: 5.606667 | DY3: 5.466667 | DZ3: 5.566667 | EA3: 5.606667 | EB3: 5.89 | EC3: 6.32 | ED3: 6.256667 | EE3: 6.243333 | EF3: 6.27 | EG3: 6.086667 | EH3: 6.006667 | EI3: 6.086667 | EJ3: 6.086667 | EK3: 6.23 | EL3: 6.46 | EM3: 6.66 | EN3: 6.836667 | EO3: 7.18 | EP3: 7.276667 | EQ3: 7.01 | ER3: 6.87 | ES3: 6.816667 | ET3: 6.066667 | EU3: 3.816667 | EV3: 2.993333 | EW3: 2.776667 | EX3: 2.656667 | EY3: 2.786667 | EZ3: 2.863333 | FA3: 2.886667 | FB3: 2.903333 | FC3: 2.916667 | FD3: 2.95 | FE3: 2.996667 | FF3: 3.05 | FG3: 3.236667 | FH3: 3.236667 | FI3: 3.18 | FJ3: 3.086667 | FK3: 3.103333 | FL3: 3.11 | FM3: 3.12 | FN3: 3.113333 | FO3: 3.106667 | FP3: 3.136667 | FQ3: 3.143333 | FR3: 3.146667 | FS3: 3.153333 | FT3: 3.136667 | FU3: 3.13 | FV3: 3.123333 | FW3: 3.146667 | FX3: 3.133333 | FY3: 3.05 | FZ3: 2.953333 | GA3: 2.93 | GB3: 2.886667 | GC3: 2.793333 | GD3: 2.896667 | GE3: 3.066667 | GF3: 3.196667 | GG3: 3.253333 | GH3: 3.293333 | GI3: 3.343333 | GJ3: 3.323333 | GK3: 3.28 | GL3: 3.26 | GM3: 3.266667 | GN3: 2.876667 | GO3: 2.57 | GP3: 2.453333 | GQ3: 2.426667 | GR3: 2.49 | GS3: 2.616667 | GT3: 2.703333 | GU3: 2.936667 | GV3: 3.326667 | GW3: 3.836667 | GX3: 4.763333 | GY3: 5.58 | GZ3: 6.09 | HA3: 6.676667 | HB3: 6.8 | HC3: 6.856667 | HD3: 6.89 | HE3: 6.806667 | HF3: 6.646667 | HG3: 6.41 | HH3: 6.216667 | HI3: 6.023008 | HJ3: 5.811905 | HK3: 5.606066 | HL3: 5.398326 | HM3: 5.25076 | HN3: 5.083459 | HO3: 4.943674 | HP3: 4.782779 | HQ3: 4.649104 | HR3: 4.493542 | HS3: 4.371559 | HT3: 4.3 | HU3: 4.3 | HV3: 4.3 | HW3: 4.3 | HX3: 4.3 | HY3: 4.3 | HZ3: 4.3 | IA3: 4.3 | IB3: 4.3 | IC3: 4.3 | ID3: 4.3 | IE3: 4.3 | IF3: 4.3 | IG3: 4.3 | IH3: 4.3 | II3: 4.3 | IJ3: 4.3 | IK3: 4.3 | IL3: 4.3 | IM3: 4.3 | IN3: 4.3 | IO3: 4.3 | IP3: 4.3 | IQ3: 4.3 | IR3: 4.3 | IS3: 4.3 | IT3: 4.3 | IU3: 4.3 | IV3: 4.3 | IW3: 4.3 | IX3: 4.3 | IY3: 4.3 | IZ3: 4.3 | JA3: 4.3 | JB3: 4.3 | JC3: 4.3 | JD3: 4.3 | JE3: 4.3 | JF3: 4.3 | JG3: 4.3 | JH3: 4.3 | JI3: 4.3 | JJ3: 4.3 | JK3: 4.3 | JL3: 4.3 | JM3: 4.3 | JN3: 4.3 | JO3: 4.3 | JP3: 4.3 | JQ3: 4.3 | JR3: 4.3 | JS3: 4.3 | JT3: 4.3 | JU3: 4.3 | JV3: 4.3 | JW3: 4.3 | JX3: 4.3 | JY3: 4.3 | JZ3: 4.3 | KA3: 4.3 | KB3: 4.3 | KC3: 4.3 | KD3: 4.3 | KE3: 4.3 | KF3: 4.3 | KG3: 4.3 | KH3: 4.3 | KI3: 4.3 | KJ3: 4.3 | KK3: 4.3 | KL3: 4.3 | KM3: 4.3 | KN3: 4.3 | KO3: 4.3 | KP3: 4.3 | KQ3: 4.3 | KR3: 4.3 | KS3: 4.3 | KT3: 4.3 | KU3: 4.3 | KV3: 4.3 | KW3: 4.3 | KX3: 4.3 | KY3: 4.3 | KZ3: 4.3 | LA3: 4.3 | LB3: 4.3 | LC3: 4.3 | LD3: 4.3 | LE3: 4.3 | LF3: 4.3 | LG3: 4.3 | LH3: 4.3 | LI3: 4.3 | LJ3: 4.3 | LK3: 4.3 | LL3: 4.3 | LM3: 4.3 | LN3: 4.3 | LO3: 4.3 | LP3: 4.3 | LQ3: 4.3 | LR3: 4.3 | LS3: 4.3 | LT3: 4.3 | LU3: 4.3 | LV3: 4.3 | LW3: 4.3 | LX3: 4.3 | LY3: 4.3 | LZ3: 4.3 | MA3: 4.3 | MB3: 4.3 | MC3: 4.3 | MD3: 4.3 | ME3: 4.3 | MF3: 4.3 | MG3: 4.3 | MH3: 4.3 | MI3: 4.3 | MJ3: 4.3 | MK3: 4.3 | ML3: 4.3 | MM3: 4.3 | MN3: 4.3 | MO3: 4.3 | MP3: 4.3 | MQ3: 4.3 | MR3: 4.3 | MS3: 4.3 | MT3: 4.3 | MU3: Bank of England\Haver Analytics | MV3: False | MW3: NA | MX3: NA | MY3: 2025 | MZ3: 1 | NA3: 09 July 2025 | NB3: UNHSDC@UK | NC3: UK: Banks Weighted Average Interest Rate, Other Loans to Nonfin Corps (%) | ND3: GBR | NE3: RLOAN | NF3: Desktop
A4: United Kingdom | B4: Interest Rate Swap, risk-free reference rate, 2yr | C4: JUL009E | D4: % | E4: NA | F4: Level | G4: 0.001 | H4: 0.001 | I4: 0.001 | J4: 0.001 | K4: 0.001 | L4: 0.001 | M4: 0.001 | N4: 0.001 | O4: 0.001 | P4: 0.001 | Q4: 0.001 | R4: 0.001 | S4: 0.001 | T4: 0.001 | U4: 0.001 | V4: 0.001 | W4: 0.001 | X4: 0.001 | Y4: 0.001 | Z4: 0.001 | AA4: 0.001 | AB4: 0.001 | AC4: 0.001 | AD4: 0.001 | AE4: 0.001 | AF4: 0.001 | AG4: 0.001 | AH4: 0.001 | AI4: 0.001 | AJ4: 0.001 | AK4: 0.001 | AL4: 0.001 | AM4: 0.001 | AN4: 0.001 | AO4: 0.001 | AP4: 0.001 | AQ4: 0.001 | AR4: 0.001 | AS4: 0.001 | AT4: 0.001 | AU4: 0.001 | AV4: 0.001 | AW4: 0.001 | AX4: 0.001 | AY4: 0.001 | AZ4: 0.001 | BA4: 0.001 | BB4: 0.001 | BC4: 0.001 | BD4: 0.001 | BE4: 0.001 | BF4: 0.001 | BG4: 0.001 | BH4: 0.001 | BI4: 0.001 | BJ4: 0.001 | BK4: 0.001 | BL4: 0.001 | BM4: 0.001 | BN4: 0.001 | BO4: 0.001 | BP4: 0.001 | BQ4: 0.001 | BR4: 0.001 | BS4: 0.001 | BT4: 0.001 | BU4: 0.001 | BV4: 0.001 | BW4: 0.001 | BX4: 0.001 | BY4: 0.001 | BZ4: 0.001 | CA4: 0.001 | CB4: 0.001 | CC4: 0.001 | CD4: 0.001 | CE4: 0.001 | CF4: 0.001 | CG4: 0.001 | CH4: 0.001 | CI4: 0.001 | CJ4: 0.001 | CK4: 0.001 | CL4: 0.001 | CM4: 0.001 | CN4: 0.001 | CO4: 0.001 | CP4: 0.001 | CQ4: 0.001 | CR4: 0.001 | CS4: 0.001 | CT4: 0.001 | CU4: 0.001 | CV4: 0.001 | CW4: 0.001 | CX4: 0.001 | CY4: 0.001 | CZ4: 0.001 | DA4: 0.001 | DB4: 0.001 | DC4: 0.001 | DD4: 0.001 | DE4: 0.001 | DF4: 0.001 | DG4: 0.001 | DH4: 0.001 | DI4: 0.001 | DJ4: 0.001 | DK4: 0.001 | DL4: 0.001 | DM4: 0.001 | DN4: 0.001 | DO4: 0.001 | DP4: 0.001 | DQ4: 0.001 | DR4: 0.001 | DS4: 0.001 | DT4: 0.001 | DU4: 0.001 | DV4: 0.001 | DW4: 0.001 | DX4: 0.001 | DY4: 0.001 | DZ4: 0.001 | EA4: 0.001 | EB4: 0.001 | EC4: 0.001 | ED4: 0.001 | EE4: 0.001 | EF4: 0.001 | EG4: 0.001 | EH4: 0.001 | EI4: 0.001 | EJ4: 0.001 | EK4: 0.001 | EL4: 0.001 | EM4: 0.001 | EN4: 0.001 | EO4: 5.81523 | EP4: 5.29735 | EQ4: 4.61636 | ER4: 5.0939 | ES4: 4.83299 | ET4: 2.48783 | EU4: 1.107 | EV4: 1.31001 | EW4: 1.56021 | EX4: 1.43008 | EY4: 1.23196 | EZ4: 1.0097 | FA4: 0.80575 | FB4: 0.83751 | FC4: 1.29715 | FD4: 1.04826 | FE4: 0.57636 | FF4: 0.52529 | FG4: 0.51647 | FH4: 0.47708 | FI4: 0.31758 | FJ4: 0.36157 | FK4: 0.37318 | FL4: 0.39372 | FM4: 0.50308 | FN4: 0.5809 | FO4: 0.72971 | FP4: 0.90707 | FQ4: 0.9791077 | FR4: 0.7722588 | FS4: 0.6525645 | FT4: 0.7218281 | FU4: 0.7934046 | FV4: 0.7078303 | FW4: 0.4868692 | FX4: 0.4256062 | FY4: 0.1208545 | FZ4: 0.2584062 | GA4: 0.3156492 | GB4: 0.3102123 | GC4: 0.4471046 | GD4: 0.679989 | GE4: 0.8330312 | GF4: 0.8182908 | GG4: 0.8723477 | GH4: 0.9135666 | GI4: 0.8328266 | GJ4: 0.7366616 | GK4: 0.5093379 | GL4: 0.5689909 | GM4: 0.4006385 | GN4: 0.04814 | GO4: -0.0467773 | GP4: -0.0316985 | GQ4: 0.02943438 | GR4: 0.1407831 | GS4: 0.2743212 | GT4: 0.8600288 | GU4: 1.562864 | GV4: 2.373632 | GW4: 3.443794 | GX4: 4.553888 | GY4: 4.213575 | GZ4: 4.866643 | HA4: 5.590632 | HB4: 4.760923 | HC4: 4.410969 | HD4: 4.600279 | HE4: 4.132863 | HF4: 4.153136 | HG4: 4.132564 | HH4: 3.760666 | HI4: 3.612839 | HJ4: 3.560919 | HK4: 3.434963 | HL4: 3.31471 | HM4: 3.200597 | HN4: 3.072339 | HO4: 2.961308 | HP4: 2.83165 | HQ4: 2.715522 | HR4: 2.624202 | HS4: 2.604275 | HT4: 2.6 | HU4: 2.6 | HV4: 2.6 | HW4: 2.6 | HX4: 2.6 | HY4: 2.6 | HZ4: 2.6 | IA4: 2.6 | IB4: 2.6 | IC4: 2.6 | ID4: 2.6 | IE4: 2.6 | IF4: 2.6 | IG4: 2.6 | IH4: 2.6 | II4: 2.6 | IJ4: 2.6 | IK4: 2.6 | IL4: 2.6 | IM4: 2.6 | IN4: 2.6 | IO4: 2.6 | IP4: 2.6 | IQ4: 2.6 | IR4: 2.6 | IS4: 2.6 | IT4: 2.6 | IU4: 2.6 | IV4: 2.6 | IW4: 2.6 | IX4: 2.6 | IY4: 2.6 | IZ4: 2.6 | JA4: 2.6 | JB4: 2.6 | JC4: 2.6 | JD4: 2.6 | JE4: 2.6 | JF4: 2.6 | JG4: 2.6 | JH4: 2.6 | JI4: 2.6 | JJ4: 2.6 | JK4: 2.6 | JL4: 2.6 | JM4: 2.6 | JN4: 2.6 | JO4: 2.6 | JP4: 2.6 | JQ4: 2.6 | JR4: 2.6 | JS4: 2.6 | JT4: 2.6 | JU4: 2.6 | JV4: 2.6 | JW4: 2.6 | JX4: 2.6 | JY4: 2.6 | JZ4: 2.6 | KA4: 2.6 | KB4: 2.6 | KC4: 2.6 | KD4: 2.6 | KE4: 2.6 | KF4: 2.6 | KG4: 2.6 | KH4: 2.6 | KI4: 2.6 | KJ4: 2.6 | KK4: 2.6 | KL4: 2.6 | KM4: 2.6 | KN4: 2.6 | KO4: 2.6 | KP4: 2.6 | KQ4: 2.6 | KR4: 2.6 | KS4: 2.6 | KT4: 2.6 | KU4: 2.6 | KV4: 2.6 | KW4: 2.6 | KX4: 2.6 | KY4: 2.6 | KZ4: 2.6 | LA4: 2.6 | LB4: 2.6 | LC4: 2.6 | LD4: 2.6 | LE4: 2.6 | LF4: 2.6 | LG4: 2.6 | LH4: 2.6 | LI4: 2.6 | LJ4: 2.6 | LK4: 2.6 | LL4: 2.6 | LM4: 2.6 | LN4: 2.6 | LO4: 2.6 | LP4: 2.6 | LQ4: 2.6 | LR4: 2.6 | LS4: 2.6 | LT4: 2.6 | LU4: 2.6 | LV4: 2.6 | LW4: 2.6 | LX4: 2.6 | LY4: 2.6 | LZ4: 2.6 | MA4: 2.6 | MB4: 2.6 | MC4: 2.6 | MD4: 2.6 | ME4: 2.6 | MF4: 2.6 | MG4: 2.6 | MH4: 2.6 | MI4: 2.6 | MJ4: 2.6 | MK4: 2.6 | ML4: 2.6 | MM4: 2.6 | MN4: 2.6 | MO4: 2.6 | MP4: 2.6 | MQ4: 2.6 | MR4: 2.6 | MS4: 2.6 | MT4: 2.6 | MU4: Tullett Prebon Information/LSEG Datastream/Haver Analytics | MV4: False | MW4: NA | MX4: NA | MY4: 2025 | MZ4: 2 | NA4: 09 July 2025 | NB4: M112IHH@INTDAILY, spliced with OIGBP2Y | NC4: UK: 24 Month Overnight Index Swap[Ann,Act/365]v SONIA:Mid Rate[2PM ET](%p.a) | ND4: GBR | NE4: RSWAP2YR_RFR | NF4: Desktop
A5: United Kingdom | B5: Interest Rate Swap, risk-free reference rate, 5yr | C5: JUL009E | D5: % | E5: NA | F5: Level | G5: 0.001 | H5: 0.001 | I5: 0.001 | J5: 0.001 | K5: 0.001 | L5: 0.001 | M5: 0.001 | N5: 0.001 | O5: 0.001 | P5: 0.001 | Q5: 0.001 | R5: 0.001 | S5: 0.001 | T5: 0.001 | U5: 0.001 | V5: 0.001 | W5: 0.001 | X5: 0.001 | Y5: 0.001 | Z5: 0.001 | AA5: 0.001 | AB5: 0.001 | AC5: 0.001 | AD5: 0.001 | AE5: 0.001 | AF5: 0.001 | AG5: 0.001 | AH5: 0.001 | AI5: 0.001 | AJ5: 0.001 | AK5: 0.001 | AL5: 0.001 | AM5: 0.001 | AN5: 0.001 | AO5: 0.001 | AP5: 0.001 | AQ5: 0.001 | AR5: 0.001 | AS5: 0.001 | AT5: 0.001 | AU5: 0.001 | AV5: 0.001 | AW5: 0.001 | AX5: 0.001 | AY5: 0.001 | AZ5: 0.001 | BA5: 0.001 | BB5: 0.001 | BC5: 0.001 | BD5: 0.001 | BE5: 0.001 | BF5: 0.001 | BG5: 0.001 | BH5: 0.001 | BI5: 0.001 | BJ5: 0.001 | BK5: 0.001 | BL5: 0.001 | BM5: 0.001 | BN5: 0.001 | BO5: 0.001 | BP5: 0.001 | BQ5: 0.001 | BR5: 0.001 | BS5: 0.001 | BT5: 0.001 | BU5: 0.001 | BV5: 0.001 | BW5: 0.001 | BX5: 0.001 | BY5: 0.001 | BZ5: 0.001 | CA5: 0.001 | CB5: 0.001 | CC5: 0.001 | CD5: 0.001 | CE5: 0.001 | CF5: 0.001 | CG5: 0.001 | CH5: 0.001 | CI5: 0.001 | CJ5: 0.001 | CK5: 0.001 | CL5: 0.001 | CM5: 0.001 | CN5: 0.001 | CO5: 0.001 | CP5: 0.001 | CQ5: 0.001 | CR5: 0.001 | CS5: 0.001 | CT5: 0.001 | CU5: 0.001 | CV5: 0.001 | CW5: 0.001 | CX5: 0.001 | CY5: 0.001 | CZ5: 0.001 | DA5: 0.001 | DB5: 0.001 | DC5: 0.001 | DD5: 0.001 | DE5: 0.001 | DF5: 0.001 | DG5: 0.001 | DH5: 0.001 | DI5: 0.001 | DJ5: 0.001 | DK5: 0.001 | DL5: 0.001 | DM5: 0.001 | DN5: 0.001 | DO5: 0.001 | DP5: 0.001 | DQ5: 0.001 | DR5: 0.001 | DS5: 0.001 | DT5: 0.001 | DU5: 0.001 | DV5: 0.001 | DW5: 0.001 | DX5: 0.001 | DY5: 0.001 | DZ5: 0.001 | EA5: 0.001 | EB5: 0.001 | EC5: 0.001 | ED5: 0.001 | EE5: 0.001 | EF5: 0.001 | EG5: 0.001 | EH5: 0.001 | EI5: 0.001 | EJ5: 0.001 | EK5: 0.001 | EL5: 0.001 | EM5: 0.001 | EN5: 0.001 | EO5: 0.001 | EP5: 0.001 | EQ5: 0.001 | ER5: 0.001 | ES5: 0.001 | ET5: 0.001 | EU5: 0.001 | EV5: 0.001 | EW5: 0.001 | EX5: 0.001 | EY5: 0.001 | EZ5: 0.001 | FA5: 0.001 | FB5: 0.001 | FC5: 0.001 | FD5: 0.001 | FE5: 0.001 | FF5: 0.001 | FG5: 0.001 | FH5: 0.001 | FI5: 0.001 | FJ5: 0.001 | FK5: 0.001 | FL5: 0.001 | FM5: 0.001 | FN5: 0.001 | FO5: 0.001 | FP5: 0.001 | FQ5: 1.662804 | FR5: 1.323808 | FS5: 1.07581 | FT5: 1.227167 | FU5: 1.307745 | FV5: 1.140759 | FW5: 0.7460831 | FX5: 0.6163569 | FY5: 0.2000939 | FZ5: 0.5115815 | GA5: 0.5734416 | GB5: 0.5176739 | GC5: 0.6727492 | GD5: 0.8919812 | GE5: 1.092973 | GF5: 1.062272 | GG5: 1.078463 | GH5: 1.117405 | GI5: 0.9809359 | GJ5: 0.8350984 | GK5: 0.481144 | GL5: 0.5779424 | GM5: 0.4388046 | GN5: 0.1120569 | GO5: -0.0225773 | GP5: 0.02346061 | GQ5: 0.2252266 | GR5: 0.4563077 | GS5: 0.4796258 | GT5: 0.941253 | GU5: 1.518147 | GV5: 2.266172 | GW5: 3.063532 | GX5: 4.181145 | GY5: 3.757868 | GZ5: 4.290757 | HA5: 4.869394 | HB5: 4.201523 | HC5: 3.833702 | HD5: 4.049462 | HE5: 3.719051 | HF5: 3.922152 | HG5: 4.026819 | HH5: 3.781371 | HI5: 3.689037 | HJ5: 3.700985 | HK5: 3.672406 | HL5: 3.605796 | HM5: 3.538721 | HN5: 3.453448 | HO5: 3.356713 | HP5: 3.242027 | HQ5: 3.121783 | HR5: 3.014878 | HS5: 2.965007 | HT5: 2.94 | HU5: 2.94 | HV5: 2.94 | HW5: 2.94 | HX5: 2.94 | HY5: 2.94 | HZ5: 2.94 | IA5: 2.94 | IB5: 2.94 | IC5: 2.94 | ID5: 2.94 | IE5: 2.94 | IF5: 2.94 | IG5: 2.94 | IH5: 2.94 | II5: 2.94 | IJ5: 2.94 | IK5: 2.94 | IL5: 2.94 | IM5: 2.94 | IN5: 2.94 | IO5: 2.94 | IP5: 2.94 | IQ5: 2.94 | IR5: 2.94 | IS5: 2.94 | IT5: 2.94 | IU5: 2.94 | IV5: 2.94 | IW5: 2.94 | IX5: 2.94 | IY5: 2.94 | IZ5: 2.94 | JA5: 2.94 | JB5: 2.94 | JC5: 2.94 | JD5: 2.94 | JE5: 2.94 | JF5: 2.94 | JG5: 2.94 | JH5: 2.94 | JI5: 2.94 | JJ5: 2.94 | JK5: 2.94 | JL5: 2.94 | JM5: 2.94 | JN5: 2.94 | JO5: 2.94 | JP5: 2.94 | JQ5: 2.94 | JR5: 2.94 | JS5: 2.94 | JT5: 2.94 | JU5: 2.94 | JV5: 2.94 | JW5: 2.94 | JX5: 2.94 | JY5: 2.94 | JZ5: 2.94 | KA5: 2.94 | KB5: 2.94 | KC5: 2.94 | KD5: 2.94 | KE5: 2.94 | KF5: 2.94 | KG5: 2.94 | KH5: 2.94 | KI5: 2.94 | KJ5: 2.94 | KK5: 2.94 | KL5: 2.94 | KM5: 2.94 | KN5: 2.94 | KO5: 2.94 | KP5: 2.94 | KQ5: 2.94 | KR5: 2.94 | KS5: 2.94 | KT5: 2.94 | KU5: 2.94 | KV5: 2.94 | KW5: 2.94 | KX5: 2.94 | KY5: 2.94 | KZ5: 2.94 | LA5: 2.94 | LB5: 2.94 | LC5: 2.94 | LD5: 2.94 | LE5: 2.94 | LF5: 2.94 | LG5: 2.94 | LH5: 2.94 | LI5: 2.94 | LJ5: 2.94 | LK5: 2.94 | LL5: 2.94 | LM5: 2.94 | LN5: 2.94 | LO5: 2.94 | LP5: 2.94 | LQ5: 2.94 | LR5: 2.94 | LS5: 2.94 | LT5: 2.94 | LU5: 2.94 | LV5: 2.94 | LW5: 2.94 | LX5: 2.94 | LY5: 2.94 | LZ5: 2.94 | MA5: 2.94 | MB5: 2.94 | MC5: 2.94 | MD5: 2.94 | ME5: 2.94 | MF5: 2.94 | MG5: 2.94 | MH5: 2.94 | MI5: 2.94 | MJ5: 2.94 | MK5: 2.94 | ML5: 2.94 | MM5: 2.94 | MN5: 2.94 | MO5: 2.94 | MP5: 2.94 | MQ5: 2.94 | MR5: 2.94 | MS5: 2.94 | MT5: 2.94 | MU5: Tullett Prebon Information/Haver Analytics | MV5: False | MW5: NA | MX5: NA | MY5: 2025 | MZ5: 2 | NA5: 09 July 2025 | NB5: M112I5Y@INTDAILY | NC5: UK: 5 Year Overnight Index Swap[Ann,Act/365]v SONIA:Mid Rate[2PM ET](%p.a) | ND5: GBR | NE5: RSWAP5YR_RFR | NF5: Desktop
A6: United Kingdom | B6: Interest rate, long-term, end of period | C6: JUL009E | D6: % | E6: NA | F6: Level | G6: 0.001 | H6: 0.001 | I6: 0.001 | J6: 0.001 | K6: 0.001 | L6: 0.001 | M6: 0.001 | N6: 0.001 | O6: 0.001 | P6: 0.001 | Q6: 0.001 | R6: 0.001 | S6: 0.001 | T6: 0.001 | U6: 0.001 | V6: 0.001 | W6: 0.001 | X6: 0.001 | Y6: 0.001 | Z6: 0.001 | AA6: 0.001 | AB6: 0.001 | AC6: 0.001 | AD6: 0.001 | AE6: 0.001 | AF6: 0.001 | AG6: 0.001 | AH6: 0.001 | AI6: 0.001 | AJ6: 0.001 | AK6: 0.001 | AL6: 0.001 | AM6: 0.001 | AN6: 0.001 | AO6: 0.001 | AP6: 0.001 | AQ6: 0.001 | AR6: 0.001 | AS6: 0.001 | AT6: 0.001 | AU6: 0.001 | AV6: 0.001 | AW6: 0.001 | AX6: 0.001 | AY6: 10.65 | AZ6: 11.7 | BA6: 11.03 | BB6: 11.07 | BC6: 11.09 | BD6: 11.05 | BE6: 10.55 | BF6: 10.83 | BG6: 9.14 | BH6: 9.55 | BI6: 10.86 | BJ6: 10.57 | BK6: 9.18 | BL6: 9.2 | BM6: 10.26 | BN6: 9.61 | BO6: 9.09 | BP6: 9.8 | BQ6: 9.88 | BR6: 10.11 | BS6: 10 | BT6: 10.41 | BU6: 10.46 | BV6: 10.41 | BW6: 12.52 | BX6: 11.65 | BY6: 12.14 | BZ6: 11.04 | CA6: 10.14 | CB6: 10.56 | CC6: 9.58 | CD6: 9.73 | CE6: 9.9 | CF6: 9.11 | CG6: 8.96 | CH6: 8.17 | CI6: 7.8 | CJ6: 7.7 | CK6: 6.96 | CL6: 6.2391 | CM6: 7.5 | CN6: 8.59 | CO6: 8.8 | CP6: 8.7 | CQ6: 8.49 | CR6: 8.48 | CS6: 8.12 | CT6: 7.43 | CU6: 8.15 | CV6: 7.88 | CW6: 7.65 | CX6: 7.51 | CY6: 7.62 | CZ6: 7.09 | DA6: 6.44 | DB6: 6.29 | DC6: 5.9 | DD6: 5.84 | DE6: 4.89 | DF6: 4.36 | DG6: 4.58 | DH6: 5.06 | DI6: 5.62 | DJ6: 5.48 | DK6: 5.25 | DL6: 5.17 | DM6: 5.2 | DN6: 4.89 | DO6: 4.87 | DP6: 5.29 | DQ6: 4.88 | DR6: 5.07 | DS6: 5.3 | DT6: 5.02 | DU6: 4.39 | DV6: 4.38 | DW6: 4.29 | DX6: 4.17 | DY6: 4.54 | DZ6: 4.77 | EA6: 4.75 | EB6: 5.1 | EC6: 4.83 | ED6: 4.54 | EE6: 4.69 | EF6: 4.17 | EG6: 4.29 | EH6: 4.09 | EI6: 4.4 | EJ6: 4.7 | EK6: 4.52 | EL6: 4.74 | EM6: 4.94 | EN6: 5.46 | EO6: 5.04 | EP6: 4.57 | EQ6: 4.35 | ER6: 5.13 | ES6: 4.45 | ET6: 3.02 | EU6: 3.16 | EV6: 3.69 | EW6: 3.59 | EX6: 4.01 | EY6: 3.95 | EZ6: 3.36 | FA6: 2.95 | FB6: 3.4 | FC6: 3.69 | FD6: 3.39 | FE6: 2.42 | FF6: 1.98 | FG6: 2.2 | FH6: 1.73 | FI6: 1.72 | FJ6: 1.85 | FK6: 1.78 | FL6: 2.44 | FM6: 2.73 | FN6: 3.04 | FO6: 2.73 | FP6: 2.68 | FQ6: 2.43 | FR6: 1.76 | FS6: 1.58 | FT6: 2.01 | FU6: 1.76 | FV6: 1.96 | FW6: 1.43 | FX6: 0.89 | FY6: 0.76 | FZ6: 1.24 | GA6: 1.14 | GB6: 1.26 | GC6: 1.38 | GD6: 1.19 | GE6: 1.34 | GF6: 1.28 | GG6: 1.57 | GH6: 1.27 | GI6: 0.99 | GJ6: 0.84 | GK6: 0.49 | GL6: 0.83 | GM6: 0.34 | GN6: 0.17 | GO6: 0.23 | GP6: 0.2 | GQ6: 0.85 | GR6: 0.72 | GS6: 1.02 | GT6: 0.97 | GU6: 1.6 | GV6: 2.22 | GW6: 4.08 | GX6: 3.67 | GY6: 3.47 | GZ6: 4.39 | HA6: 4.46 | HB6: 3.54 | HC6: 3.95 | HD6: 4.17 | HE6: 4 | HF6: 4.57 | HG6: 4.7 | HH6: 4.48 | HI6: 4.6 | HJ6: 4.536295 | HK6: 4.462363 | HL6: 4.338197 | HM6: 4.188987 | HN6: 4.030675 | HO6: 3.872072 | HP6: 3.721297 | HQ6: 3.583097 | HR6: 3.465695 | HS6: 3.382509 | HT6: 3.35 | HU6: 3.35 | HV6: 3.35 | HW6: 3.35 | HX6: 3.35 | HY6: 3.35 | HZ6: 3.35 | IA6: 3.35 | IB6: 3.35 | IC6: 3.35 | ID6: 3.35 | IE6: 3.35 | IF6: 3.35 | IG6: 3.35 | IH6: 3.35 | II6: 3.35 | IJ6: 3.35 | IK6: 3.35 | IL6: 3.35 | IM6: 3.35 | IN6: 3.35 | IO6: 3.35 | IP6: 3.35 | IQ6: 3.35 | IR6: 3.35 | IS6: 3.35 | IT6: 3.35 | IU6: 3.35 | IV6: 3.35 | IW6: 3.35 | IX6: 3.35 | IY6: 3.35 | IZ6: 3.35 | JA6: 3.35 | JB6: 3.35 | JC6: 3.35 | JD6: 3.35 | JE6: 3.35 | JF6: 3.35 | JG6: 3.35 | JH6: 3.35 | JI6: 3.35 | JJ6: 3.35 | JK6: 3.35 | JL6: 3.35 | JM6: 3.35 | JN6: 3.35 | JO6: 3.35 | JP6: 3.35 | JQ6: 3.35 | JR6: 3.35 | JS6: 3.35 | JT6: 3.35 | JU6: 3.35 | JV6: 3.35 | JW6: 3.35 | JX6: 3.35 | JY6: 3.35 | JZ6: 3.35 | KA6: 3.35 | KB6: 3.35 | KC6: 3.35 | KD6: 3.35 | KE6: 3.35 | KF6: 3.35 | KG6: 3.35 | KH6: 3.35 | KI6: 3.35 | KJ6: 3.35 | KK6: 3.35 | KL6: 3.35 | KM6: 3.35 | KN6: 3.35 | KO6: 3.35 | KP6: 3.35 | KQ6: 3.35 | KR6: 3.35 | KS6: 3.35 | KT6: 3.35 | KU6: 3.35 | KV6: 3.35 | KW6: 3.35 | KX6: 3.35 | KY6: 3.35 | KZ6: 3.35 | LA6: 3.35 | LB6: 3.35 | LC6: 3.35 | LD6: 3.35 | LE6: 3.35 | LF6: 3.35 | LG6: 3.35 | LH6: 3.35 | LI6: 3.35 | LJ6: 3.35 | LK6: 3.35 | LL6: 3.35 | LM6: 3.35 | LN6: 3.35 | LO6: 3.35 | LP6: 3.35 | LQ6: 3.35 | LR6: 3.35 | LS6: 3.35 | LT6: 3.35 | LU6: 3.35 | LV6: 3.35 | LW6: 3.35 | LX6: 3.35 | LY6: 3.35 | LZ6: 3.35 | MA6: 3.35 | MB6: 3.35 | MC6: 3.35 | MD6: 3.35 | ME6: 3.35 | MF6: 3.35 | MG6: 3.35 | MH6: 3.35 | MI6: 3.35 | MJ6: 3.35 | MK6: 3.35 | ML6: 3.35 | MM6: 3.35 | MN6: 3.35 | MO6: 3.35 | MP6: 3.35 | MQ6: 3.35 | MR6: 3.35 | MS6: 3.35 | MT6: 3.35 | MU6: Refinitiv\Bank of England\Haver Analytics | MV6: False | MW6: NA | MX6: NA | MY6: 2025 | MZ6: 2 | NA6: 09 July 2025 | NB6: agg(T112GA@INTDAILY,EOP), spliced with agg(R112GA@INTDAILY,EOP) | NC6: UK: 10-Yr Government Bond Yield (%), spliced with United Kingdom: Government Securities: 10-Years [Nominal Par Yields] (% p.a.) , (EOP, %) | ND6: GBR | NE6: RLGEOP | NF6: Desktop
A7: United Kingdom | B7: Interest rate, 10y gov. bond yield, Term Premium | C7: JUL009E | D7: % | E7: NA | F7: Level | G7: 0 | H7: 0 | I7: 0 | J7: 0 | K7: 0 | L7: 0 | M7: 0 | N7: 0 | O7: 0 | P7: 0 | Q7: 0 | R7: 0 | S7: 0 | T7: 0 | U7: 0 | V7: 0 | W7: 0 | X7: 0 | Y7: 0 | Z7: 0 | AA7: 0 | AB7: 0 | AC7: 0 | AD7: 0 | AE7: 0 | AF7: 0 | AG7: 0 | AH7: 0 | AI7: 0.02075863 | AJ7: -0.9109759 | AK7: -1.420909 | AL7: -1.483235 | AM7: -0.02038527 | AN7: 0.5896664 | AO7: 0.9220591 | AP7: 1.028612 | AQ7: 1.072135 | AR7: 1.211536 | AS7: 1.195357 | AT7: 0.873498 | AU7: 1.250138 | AV7: 1.348236 | AW7: 2.251987 | AX7: 2.281286 | AY7: 2.866734 | AZ7: 3.357499 | BA7: 2.798276 | BB7: 2.630605 | BC7: 1.638886 | BD7: 1.373749 | BE7: 1.315304 | BF7: 1.306533 | BG7: 0.8512008 | BH7: 0.7188361 | BI7: 1.619958 | BJ7: 2.335945 | BK7: 1.459951 | BL7: 1.427398 | BM7: 2.163983 | BN7: 2.320271 | BO7: 2.275249 | BP7: 2.346591 | BQ7: 1.367612 | BR7: 0.639468 | BS7: 0.1605382 | BT7: 0.1815357 | BU7: -0.4111519 | BV7: -0.6458392 | BW7: 0.175952 | BX7: 0.8359671 | BY7: 0.4982619 | BZ7: 0.2108965 | CA7: -0.4351583 | CB7: 0.2710466 | CC7: 0.2752395 | CD7: 0.1602945 | CE7: -0.01856995 | CF7: 0.05092287 | CG7: 0.5003808 | CH7: 1.342199 | CI7: 1.808402 | CJ7: 2.285599 | CK7: 1.886645 | CL7: 1.67369 | CM7: 2.160304 | CN7: 3.452647 | CO7: 3.726039 | CP7: 3.376331 | CQ7: 3.033681 | CR7: 2.520147 | CS7: 2.317553 | CT7: 1.982157 | CU7: 2.155483 | CV7: 2.579135 | CW7: 2.428135 | CX7: 1.869014 | CY7: 1.670947 | CZ7: 1.566139 | DA7: 0.9892616 | DB7: 0.3934669 | DC7: -0.003460884 | DD7: -0.1501055 | DE7: -0.4108672 | DF7: -0.5877755 | DG7: -0.3080182 | DH7: 0.2176683 | DI7: 0.8138413 | DJ7: 0.650178 | DK7: 0.6010882 | DL7: 0.3332769 | DM7: 0.435874 | DN7: 0.2921057 | DO7: 0.2684191 | DP7: 0.6597365 | DQ7: 0.6513828 | DR7: 0.8785719 | DS7: 1.106802 | DT7: 1.223072 | DU7: 0.7708229 | DV7: 0.623075 | DW7: 0.4296098 | DX7: 0.4778256 | DY7: 0.8453319 | DZ7: 1.08209 | EA7: 0.8304625 | EB7: 0.9005647 | EC7: 0.6293923 | ED7: 0.2766616 | EE7: 0.2411561 | EF7: -0.03669071 | EG7: -0.2788255 | EH7: -0.06832528 | EI7: -0.3262429 | EJ7: -0.04600477 | EK7: -0.247916 | EL7: -0.3946126 | EM7: -0.3468561 | EN7: -0.1685653 | EO7: -0.2017658 | EP7: -0.38415 | EQ7: -0.5081952 | ER7: -0.1072443 | ES7: -0.3842514 | ET7: 0.08224225 | EU7: 0.5106032 | EV7: 1.006509 | EW7: 1.354556 | EX7: 1.435477 | EY7: 1.798731 | EZ7: 1.573323 | FA7: 1.121288 | FB7: 1.216497 | FC7: 1.495052 | FD7: 1.133862 | FE7: 0.1843071 | FF7: -0.3969607 | FG7: -0.5439301 | FH7: -0.8286029 | FI7: -1.064422 | FJ7: -0.8610967 | FK7: -0.5607097 | FL7: -0.6321033 | FM7: 0.1383893 | FN7: 0.4112122 | FO7: 0.4743984 | FP7: 0.4305935 | FQ7: 0.3692981 | FR7: 0.05602062 | FS7: -0.1912934 | FT7: 0.2197689 | FU7: 0.4590952 | FV7: 0.4868888 | FW7: 0.2488452 | FX7: 0.1529139 | FY7: -0.4027671 | FZ7: 0.1690568 | GA7: 0.0386188 | GB7: -0.3793001 | GC7: -0.4588485 | GD7: -0.5432047 | GE7: -0.4993775 | GF7: -0.6754185 | GG7: -0.9232038 | GH7: -0.9835742 | GI7: -1.185091 | GJ7: -1.373087 | GK7: -1.728907 | GL7: -1.522122 | GM7: -1.418604 | GN7: -0.4674457 | GO7: 0.2979573 | GP7: 0.8963537 | GQ7: 1.704473 | GR7: 1.399738 | GS7: 0.8306162 | GT7: 0.720198 | GU7: 0.2984501 | GV7: -0.8227425 | GW7: -1.996774 | GX7: -2.524212 | GY7: -4.018078 | GZ7: -3.607876 | HA7: -3.385372 | HB7: -3.349353 | HC7: -3.141434 | HD7: -2.476906 | HE7: -2.250882 | HF7: -1.34798 | HG7: -0.5421784 | HH7: -0.2057972 | HI7: 0.1298831 | HJ7: 0.2918701 | HK7: 0.4057093 | HL7: 0.4285569 | HM7: 0.43943 | HN7: 0.4114015 | HO7: 0.3681149 | HP7: 0.3621202 | HQ7: 0.3627894 | HR7: 0.3817642 | HS7: 0.3551915 | HT7: 0.3023756 | HU7: 0.3053609 | HV7: 0.3303992 | HW7: 0.3470274 | HX7: 0.3601335 | HY7: 0.3692383 | HZ7: 0.3734791 | IA7: 0.3787743 | IB7: 0.3828475 | IC7: 0.3864415 | ID7: 0.3893167 | IE7: 0.3922638 | IF7: 0.3951629 | IG7: 0.3974153 | IH7: 0.3983017 | II7: 0.3971756 | IJ7: 0.3935816 | IK7: 0.3882865 | IL7: 0.3826081 | IM7: 0.3756834 | IN7: 0.3683517 | IO7: 0.3610439 | IP7: 0.3561562 | IQ7: 0.3530654 | IR7: 0.3517475 | IS7: 0.351508 | IT7: 0.3516996 | IU7: 0.3535205 | IV7: 0.3548863 | IW7: 0.355581 | IX7: 0.3557248 | IY7: 0.3540956 | IZ7: 0.3524903 | JA7: 0.3514839 | JB7: 0.3485129 | JC7: 0.3443439 | JD7: 0.3412292 | JE7: 0.3402947 | JF7: 0.3375392 | JG7: 0.3350474 | JH7: 0.3330827 | JI7: 0.3315492 | JJ7: 0.3306388 | JK7: 0.3296325 | JL7: 0.3287699 | JM7: 0.3278114 | JN7: 0.326853 | JO7: 0.3259426 | JP7: 0.3249124 | JQ7: 0.3240498 | JR7: 0.3232112 | JS7: 0.3217496 | JT7: 0.319809 | JU7: 0.3171732 | JV7: 0.3138907 | JW7: 0.3106561 | JX7: 0.3073738 | JY7: 0.3046662 | JZ7: 0.3024857 | KA7: 0.3014077 | KB7: 0.3014315 | KC7: 0.3027972 | KD7: 0.3055526 | KE7: 0.3090749 | KF7: 0.3134356 | KG7: 0.3185149 | KH7: 0.3242174 | KI7: 0.3306868 | KJ7: 0.3378268 | KK7: 0.3449188 | KL7: 0.3519632 | KM7: 0.3589116 | KN7: 0.3658119 | KO7: 0.3716104 | KP7: 0.3763543 | KQ7: 0.3800442 | KR7: 0.3825361 | KS7: 0.384956 | KT7: 0.3872322 | KU7: 0.3893167 | KV7: 0.3914012 | KW7: 0.3935575 | KX7: 0.3958577 | KY7: 0.3983496 | KZ7: 0.4009612 | LA7: 0.4037166 | LB7: 0.4066877 | LC7: 0.4097545 | LD7: 0.4129652 | LE7: 0.4162238 | LF7: 0.4195541 | LG7: 0.4229804 | LH7: 0.4263828 | LI7: 0.4296893 | LJ7: 0.4327083 | LK7: 0.4354875 | LL7: 0.4381232 | LM7: 0.4409984 | LN7: 0.4442569 | LO7: 0.4478508 | LP7: 0.4518284 | LQ7: 0.4555662 | LR7: 0.4590642 | LS7: 0.4624187 | LT7: 0.4654377 | LU7: 0.4682649 | LV7: 0.4708525 | LW7: 0.4731048 | LX7: 0.4751652 | LY7: 0.4773697 | LZ7: 0.4797177 | MA7: 0.4823053 | MB7: 0.4850368 | MC7: 0.4876245 | MD7: 0.4900684 | ME7: 0.4922727 | MF7: 0.4942853 | MG7: 0.4958907 | MH7: 0.4971604 | MI7: 0.498119 | MJ7: 0.49867 | MK7: 0.499365 | ML7: 0.5001075 | MM7: 0.5009223 | MN7: 0.5019046 | MO7: 0.5028629 | MP7: 0.5038215 | MQ7: 0.5047798 | MR7: 0.5056903 | MS7: 0.5065529 | MT7: 0.5072238 | MU7: Oxford Economics calculations | MV7: False | MW7: NA | MX7: NA | MY7: NA | MZ7: NA | NA7: 09 July 2025 | NB7: Oxford Economics calculation | NC7: NA | ND7: GBR | NE7: RLG_TERM_PREM | NF7: Desktop
A8: United Kingdom | B8: Interest rate, central bank policy | C8: JUL009E | D8: % | E8: NA | F8: Level | G8: 8.788462 | H8: 7.996154 | I8: 10.38461 | J8: 12.23485 | K8: 12.60938 | L8: 11.96923 | M8: 11.72727 | N8: 11.5 | O8: 10.77344 | P8: 9.961538 | Q8: 10.71212 | R8: 11.73106 | S8: 9.838462 | T8: 10.53846 | U8: 11.81818 | V8: 14.71591 | W8: 12.26172 | X8: 8.411538 | Y8: 7.242424 | Z8: 5.884615 | AA8: 6.538462 | AB8: 8.557693 | AC8: 10 | AD8: 11.42308 | AE8: 13.01538 | AF8: 12.44615 | AG8: 14 | AH8: 15.5 | AI8: 17 | AJ8: 17 | AK8: 16.0303 | AL8: 15.18182 | AM8: 13.53125 | AN8: 12 | AO8: 12.51989 | AP8: 14.60417 | AQ8: 13.78516 | AR8: 13.01346 | AS8: 11.3428 | AT8: 9.685606 | AU8: 10.80176 | AV8: 10.02404 | AW8: 9.560606 | AX8: 9.0625 | AY8: 8.943269 | AZ8: 8.844231 | BA8: 10.89615 | BB8: 9.969697 | BC8: 12.86914 | BD8: 12.48269 | BE8: 11.57955 | BF8: 11.375 | BG8: 12.07813 | BH8: 10.32885 | BI8: 9.875 | BJ8: 10.72348 | BK8: 10.66406 | BL8: 9.228847 | BM8: 9.481061 | BN8: 9.018939 | BO8: 8.628846 | BP8: 7.967308 | BQ8: 10.92045 | BR8: 12.275 | BS8: 12.875 | BT8: 13.23846 | BU8: 13.76058 | BV8: 14.80577 | BW8: 14.875 | BX8: 14.875 | BY8: 14.875 | BZ8: 13.95076 | CA8: 13.39063 | CB8: 11.74423 | CC8: 10.79924 | CD8: 10.375 | CE8: 10.375 | CF8: 10.05962 | CG8: 9.768939 | CH8: 7.511364 | CI8: 6.140625 | CJ8: 5.875 | CK8: 5.875 | CL8: 5.655303 | CM8: 5.226563 | CN8: 5.125 | CO8: 5.238636 | CP8: 5.763462 | CQ8: 6.448077 | CR8: 6.625 | CS8: 6.625 | CT8: 6.575 | CU8: 6.128846 | CV8: 5.872116 | CW8: 5.6875 | CX8: 5.857955 | CY8: 5.9375 | CZ8: 6.195192 | DA8: 6.871212 | DB8: 7.151515 | DC8: 7.25 | DD8: 7.323077 | DE8: 7.5 | DF8: 6.837121 | DG8: 5.703125 | DH8: 5.211538 | DI8: 5.064394 | DJ8: 5.409091 | DK8: 5.861538 | DL8: 6 | DM8: 6 | DN8: 6 | DO8: 5.857692 | DP8: 5.369231 | DQ8: 5.053846 | DR8: 4.223485 | DS8: 4 | DT8: 4 | DU8: 4 | DV8: 4 | DW8: 3.851563 | DX8: 3.75 | DY8: 3.526515 | DZ8: 3.651515 | EA8: 3.903846 | EB8: 4.211538 | EC8: 4.655303 | ED8: 4.75 | EE8: 4.75 | EF8: 4.75 | EG8: 4.590909 | EH8: 4.5 | EI8: 4.5 | EJ8: 4.5 | EK8: 4.661539 | EL8: 4.892308 | EM8: 5.219231 | EN8: 5.392308 | EO8: 5.738461 | EP8: 5.681818 | EQ8: 5.353846 | ER8: 5.026923 | ES8: 5 | ET8: 3.325758 | EU8: 1.085938 | EV8: 0.5 | EW8: 0.5 | EX8: 0.5 | EY8: 0.5 | EZ8: 0.5 | FA8: 0.5 | FB8: 0.5 | FC8: 0.5 | FD8: 0.5 | FE8: 0.5 | FF8: 0.5 | FG8: 0.5 | FH8: 0.5 | FI8: 0.5 | FJ8: 0.5 | FK8: 0.5 | FL8: 0.5 | FM8: 0.5 | FN8: 0.5 | FO8: 0.5 | FP8: 0.5 | FQ8: 0.5 | FR8: 0.5 | FS8: 0.5 | FT8: 0.5 | FU8: 0.5 | FV8: 0.5 | FW8: 0.5 | FX8: 0.5 | FY8: 0.3409091 | FZ8: 0.25 | GA8: 0.25 | GB8: 0.25 | GC8: 0.25 | GD8: 0.4115385 | GE8: 0.5 | GF8: 0.5 | GG8: 0.6615385 | GH8: 0.75 | GI8: 0.75 | GJ8: 0.75 | GK8: 0.75 | GL8: 0.75 | GM8: 0.6138462 | GN8: 0.1 | GO8: 0.1 | GP8: 0.1 | GQ8: 0.1 | GR8: 0.1 | GS8: 0.1 | GT8: 0.1272727 | GU8: 0.453125 | GV8: 0.95 | GW8: 1.621212 | GX8: 2.826923 | GY8: 3.85 | GZ8: 4.446154 | HA8: 5.161539 | HB8: 5.25 | HC8: 5.25 | HD8: 5.25 | HE8: 5.087121 | HF8: 4.852273 | HG8: 4.601563 | HH8: 4.353846 | HI8: 4.102273 | HJ8: 3.848485 | HK8: 3.597656 | HL8: 3.35 | HM8: 3.25 | HN8: 3.094697 | HO8: 3 | HP8: 2.846154 | HQ8: 2.75 | HR8: 2.590909 | HS8: 2.5 | HT8: 2.5 | HU8: 2.5 | HV8: 2.5 | HW8: 2.5 | HX8: 2.5 | HY8: 2.5 | HZ8: 2.5 | IA8: 2.5 | IB8: 2.5 | IC8: 2.5 | ID8: 2.5 | IE8: 2.5 | IF8: 2.5 | IG8: 2.5 | IH8: 2.5 | II8: 2.5 | IJ8: 2.5 | IK8: 2.5 | IL8: 2.5 | IM8: 2.5 | IN8: 2.5 | IO8: 2.5 | IP8: 2.5 | IQ8: 2.5 | IR8: 2.5 | IS8: 2.5 | IT8: 2.5 | IU8: 2.5 | IV8: 2.5 | IW8: 2.5 | IX8: 2.5 | IY8: 2.5 | IZ8: 2.5 | JA8: 2.5 | JB8: 2.5 | JC8: 2.5 | JD8: 2.5 | JE8: 2.5 | JF8: 2.5 | JG8: 2.5 | JH8: 2.5 | JI8: 2.5 | JJ8: 2.5 | JK8: 2.5 | JL8: 2.5 | JM8: 2.5 | JN8: 2.5 | JO8: 2.5 | JP8: 2.5 | JQ8: 2.5 | JR8: 2.5 | JS8: 2.5 | JT8: 2.5 | JU8: 2.5 | JV8: 2.5 | JW8: 2.5 | JX8: 2.5 | JY8: 2.5 | JZ8: 2.5 | KA8: 2.5 | KB8: 2.5 | KC8: 2.5 | KD8: 2.5 | KE8: 2.5 | KF8: 2.5 | KG8: 2.5 | KH8: 2.5 | KI8: 2.5 | KJ8: 2.5 | KK8: 2.5 | KL8: 2.5 | KM8: 2.5 | KN8: 2.5 | KO8: 2.5 | KP8: 2.5 | KQ8: 2.5 | KR8: 2.5 | KS8: 2.5 | KT8: 2.5 | KU8: 2.5 | KV8: 2.5 | KW8: 2.5 | KX8: 2.5 | KY8: 2.5 | KZ8: 2.5 | LA8: 2.5 | LB8: 2.5 | LC8: 2.5 | LD8: 2.5 | LE8: 2.5 | LF8: 2.5 | LG8: 2.5 | LH8: 2.5 | LI8: 2.5 | LJ8: 2.5 | LK8: 2.5 | LL8: 2.5 | LM8: 2.5 | LN8: 2.5 | LO8: 2.5 | LP8: 2.5 | LQ8: 2.5 | LR8: 2.5 | LS8: 2.5 | LT8: 2.5 | LU8: 2.5 | LV8: 2.5 | LW8: 2.5 | LX8: 2.5 | LY8: 2.5 | LZ8: 2.5 | MA8: 2.5 | MB8: 2.5 | MC8: 2.5 | MD8: 2.5 | ME8: 2.5 | MF8: 2.5 | MG8: 2.5 | MH8: 2.5 | MI8: 2.5 | MJ8: 2.5 | MK8: 2.5 | ML8: 2.5 | MM8: 2.5 | MN8: 2.5 | MO8: 2.5 | MP8: 2.5 | MQ8: 2.5 | MR8: 2.5 | MS8: 2.5 | MT8: 2.5 | MU8: Bank of England \Haver Analytics | MV8: False | MW8: NA | MX8: NA | MY8: 2025 | MZ8: 2 | NA8: 09 July 2025 | NB8: agg(R112RD@INTDAILY,avg) | NC8: United Kingdom: Official Bank Rate (%) | ND8: GBR | NE8: RCB | NF8: Desktop
A9: United Kingdom | B9: Interest rate, central bank policy, end of period | C9: JUL009E | D9: % | E9: NA | F9: Level | G9: 8.5 | H9: 7.5 | I9: 11.5 | J9: 13 | K9: 12.5 | L9: 11.75 | M9: 11.5 | N9: 11.5 | O9: 10 | P9: 10 | Q9: 11 | R9: 11.25 | S9: 9 | T9: 11.5 | U9: 13 | V9: 14.25 | W9: 9.5 | X9: 8 | Y9: 6 | Z9: 7 | AA9: 6.5 | AB9: 10 | AC9: 10 | AD9: 12.5 | AE9: 13 | AF9: 14 | AG9: 14 | AH9: 17 | AI9: 17 | AJ9: 17 | AK9: 16 | AL9: 14 | AM9: 12 | AN9: 12 | AO9: 14 | AP9: 14.375 | AQ9: 13.25 | AR9: 12.625 | AS9: 10.125 | AT9: 10 | AU9: 10.5625 | AV9: 9.5625 | AW9: 9.5625 | AX9: 9.0625 | AY9: 8.5625 | AZ9: 8.875 | BA9: 10.5 | BB9: 9.5 | BC9: 12.875 | BD9: 12.375 | BE9: 11.375 | BF9: 11.375 | BG9: 11.375 | BH9: 9.875 | BI9: 9.875 | BJ9: 10.875 | BK9: 9.875 | BL9: 8.875 | BM9: 9.875 | BN9: 8.375 | BO9: 8.375 | BP9: 8.875 | BQ9: 11.875 | BR9: 12.875 | BS9: 12.875 | BT9: 13.75 | BU9: 13.75 | BV9: 14.875 | BW9: 14.875 | BX9: 14.875 | BY9: 14.875 | BZ9: 13.875 | CA9: 12.375 | CB9: 11.375 | CC9: 10.375 | CD9: 10.375 | CE9: 10.375 | CF9: 9.875 | CG9: 8.875 | CH9: 6.875 | CI9: 5.875 | CJ9: 5.875 | CK9: 5.875 | CL9: 5.375 | CM9: 5.125 | CN9: 5.125 | CO9: 5.625 | CP9: 6.125 | CQ9: 6.625 | CR9: 6.625 | CS9: 6.625 | CT9: 6.375 | CU9: 5.9375 | CV9: 5.6875 | CW9: 5.6875 | CX9: 5.9375 | CY9: 5.9375 | CZ9: 6.5 | DA9: 7 | DB9: 7.25 | DC9: 7.25 | DD9: 7.5 | DE9: 7.5 | DF9: 6.25 | DG9: 5.5 | DH9: 5 | DI9: 5.25 | DJ9: 5.5 | DK9: 6 | DL9: 6 | DM9: 6 | DN9: 6 | DO9: 5.75 | DP9: 5.25 | DQ9: 4.75 | DR9: 4 | DS9: 4 | DT9: 4 | DU9: 4 | DV9: 4 | DW9: 3.75 | DX9: 3.75 | DY9: 3.5 | DZ9: 3.75 | EA9: 4 | EB9: 4.5 | EC9: 4.75 | ED9: 4.75 | EE9: 4.75 | EF9: 4.75 | EG9: 4.5 | EH9: 4.5 | EI9: 4.5 | EJ9: 4.5 | EK9: 4.75 | EL9: 5 | EM9: 5.25 | EN9: 5.5 | EO9: 5.75 | EP9: 5.5 | EQ9: 5.25 | ER9: 5 | ES9: 5 | ET9: 2 | EU9: 0.5 | EV9: 0.5 | EW9: 0.5 | EX9: 0.5 | EY9: 0.5 | EZ9: 0.5 | FA9: 0.5 | FB9: 0.5 | FC9: 0.5 | FD9: 0.5 | FE9: 0.5 | FF9: 0.5 | FG9: 0.5 | FH9: 0.5 | FI9: 0.5 | FJ9: 0.5 | FK9: 0.5 | FL9: 0.5 | FM9: 0.5 | FN9: 0.5 | FO9: 0.5 | FP9: 0.5 | FQ9: 0.5 | FR9: 0.5 | FS9: 0.5 | FT9: 0.5 | FU9: 0.5 | FV9: 0.5 | FW9: 0.5 | FX9: 0.5 | FY9: 0.25 | FZ9: 0.25 | GA9: 0.25 | GB9: 0.25 | GC9: 0.25 | GD9: 0.5 | GE9: 0.5 | GF9: 0.5 | GG9: 0.75 | GH9: 0.75 | GI9: 0.75 | GJ9: 0.75 | GK9: 0.75 | GL9: 0.75 | GM9: 0.1 | GN9: 0.1 | GO9: 0.1 | GP9: 0.1 | GQ9: 0.1 | GR9: 0.1 | GS9: 0.1 | GT9: 0.25 | GU9: 0.75 | GV9: 1.25 | GW9: 2.25 | GX9: 3.5 | GY9: 4.25 | GZ9: 5 | HA9: 5.25 | HB9: 5.25 | HC9: 5.25 | HD9: 5.25 | HE9: 5 | HF9: 4.75 | HG9: 4.5 | HH9: 4.25 | HI9: 4 | HJ9: 3.75 | HK9: 3.5 | HL9: 3.25 | HM9: 3.25 | HN9: 3 | HO9: 3 | HP9: 2.75 | HQ9: 2.75 | HR9: 2.5 | HS9: 2.5 | HT9: 2.5 | HU9: 2.5 | HV9: 2.5 | HW9: 2.5 | HX9: 2.5 | HY9: 2.5 | HZ9: 2.5 | IA9: 2.5 | IB9: 2.5 | IC9: 2.5 | ID9: 2.5 | IE9: 2.5 | IF9: 2.5 | IG9: 2.5 | IH9: 2.5 | II9: 2.5 | IJ9: 2.5 | IK9: 2.5 | IL9: 2.5 | IM9: 2.5 | IN9: 2.5 | IO9: 2.5 | IP9: 2.5 | IQ9: 2.5 | IR9: 2.5 | IS9: 2.5 | IT9: 2.5 | IU9: 2.5 | IV9: 2.5 | IW9: 2.5 | IX9: 2.5 | IY9: 2.5 | IZ9: 2.5 | JA9: 2.5 | JB9: 2.5 | JC9: 2.5 | JD9: 2.5 | JE9: 2.5 | JF9: 2.5 | JG9: 2.5 | JH9: 2.5 | JI9: 2.5 | JJ9: 2.5 | JK9: 2.5 | JL9: 2.5 | JM9: 2.5 | JN9: 2.5 | JO9: 2.5 | JP9: 2.5 | JQ9: 2.5 | JR9: 2.5 | JS9: 2.5 | JT9: 2.5 | JU9: 2.5 | JV9: 2.5 | JW9: 2.5 | JX9: 2.5 | JY9: 2.5 | JZ9: 2.5 | KA9: 2.5 | KB9: 2.5 | KC9: 2.5 | KD9: 2.5 | KE9: 2.5 | KF9: 2.5 | KG9: 2.5 | KH9: 2.5 | KI9: 2.5 | KJ9: 2.5 | KK9: 2.5 | KL9: 2.5 | KM9: 2.5 | KN9: 2.5 | KO9: 2.5 | KP9: 2.5 | KQ9: 2.5 | KR9: 2.5 | KS9: 2.5 | KT9: 2.5 | KU9: 2.5 | KV9: 2.5 | KW9: 2.5 | KX9: 2.5 | KY9: 2.5 | KZ9: 2.5 | LA9: 2.5 | LB9: 2.5 | LC9: 2.5 | LD9: 2.5 | LE9: 2.5 | LF9: 2.5 | LG9: 2.5 | LH9: 2.5 | LI9: 2.5 | LJ9: 2.5 | LK9: 2.5 | LL9: 2.5 | LM9: 2.5 | LN9: 2.5 | LO9: 2.5 | LP9: 2.5 | LQ9: 2.5 | LR9: 2.5 | LS9: 2.5 | LT9: 2.5 | LU9: 2.5 | LV9: 2.5 | LW9: 2.5 | LX9: 2.5 | LY9: 2.5 | LZ9: 2.5 | MA9: 2.5 | MB9: 2.5 | MC9: 2.5 | MD9: 2.5 | ME9: 2.5 | MF9: 2.5 | MG9: 2.5 | MH9: 2.5 | MI9: 2.5 | MJ9: 2.5 | MK9: 2.5 | ML9: 2.5 | MM9: 2.5 | MN9: 2.5 | MO9: 2.5 | MP9: 2.5 | MQ9: 2.5 | MR9: 2.5 | MS9: 2.5 | MT9: 2.5 | MU9: Bank of England \Haver Analytics | MV9: False | MW9: NA | MX9: NA | MY9: 2025 | MZ9: 2 | NA9: 09 July 2025 | NB9: agg(R112RD@INTDAILY,EOP) | NC9: United Kingdom: Official Bank Rate (%) ,EOP | ND9: GBR | NE9: RCBEOP | NF9: Desktop
A10: United Kingdom | B10: Personal sector debt interest payments, excl. FISIM adjustment | C10: JUL009E | D10: Pound | E10: Millions | F10: Level | G10: 0.001 | H10: 0.001 | I10: 0.001 | J10: 0.001 | K10: 0.001 | L10: 0.001 | M10: 0.001 | N10: 0.001 | O10: 0.001 | P10: 0.001 | Q10: 0.001 | R10: 0.001 | S10: 0.001 | T10: 0.001 | U10: 0.001 | V10: 0.001 | W10: 0.001 | X10: 0.001 | Y10: 0.001 | Z10: 0.001 | AA10: 0.001 | AB10: 0.001 | AC10: 0.001 | AD10: 0.001 | AE10: 0.001 | AF10: 0.001 | AG10: 0.001 | AH10: 0.001 | AI10: 0.001 | AJ10: 0.001 | AK10: 0.001 | AL10: 0.001 | AM10: 0.001 | AN10: 0.001 | AO10: 0.001 | AP10: 0.001 | AQ10: 0.001 | AR10: 0.001 | AS10: 0.001 | AT10: 0.001 | AU10: 0.001 | AV10: 0.001 | AW10: 0.001 | AX10: 0.001 | AY10: 0.001 | AZ10: 0.001 | BA10: 0.001 | BB10: 0.001 | BC10: 0.001 | BD10: 0.001 | BE10: 0.001 | BF10: 0.001 | BG10: 0.001 | BH10: 0.001 | BI10: 0.001 | BJ10: 0.001 | BK10: 6357 | BL10: 6287 | BM10: 6587 | BN10: 7170 | BO10: 6637 | BP10: 6806 | BQ10: 7710 | BR10: 8784 | BS10: 9692 | BT10: 10649 | BU10: 10881 | BV10: 11595 | BW10: 12502 | BX10: 13402 | BY10: 13746 | BZ10: 13298 | CA10: 13298 | CB10: 12592 | CC10: 11972 | CD10: 11596 | CE10: 12466 | CF10: 11383 | CG10: 11075 | CH10: 10240 | CI10: 9225 | CJ10: 8905 | CK10: 8860 | CL10: 8936 | CM10: 8891 | CN10: 9343 | CO10: 9086 | CP10: 9357 | CQ10: 9868 | CR10: 10163 | CS10: 10060 | CT10: 9867 | CU10: 9831 | CV10: 9604 | CW10: 9382 | CX10: 9346 | CY10: 9701 | CZ10: 9854 | DA10: 10600 | DB10: 11308 | DC10: 10912 | DD10: 11401 | DE10: 12066 | DF10: 11966 | DG10: 11508 | DH10: 11374 | DI10: 10963 | DJ10: 11851 | DK10: 12576 | DL10: 13036 | DM10: 13014 | DN10: 13200 | DO10: 13292 | DP10: 13032 | DQ10: 12681 | DR10: 12358 | DS10: 12166 | DT10: 12278 | DU10: 12463 | DV10: 12837 | DW10: 12803 | DX10: 12837 | DY10: 12786 | DZ10: 13144 | EA10: 14142 | EB10: 15019 | EC10: 16209 | ED10: 17013 | EE10: 17757 | EF10: 18326 | EG10: 18490 | EH10: 18710 | EI10: 19010 | EJ10: 19457 | EK10: 20199 | EL10: 21189 | EM10: 22405 | EN10: 23235 | EO10: 24167 | EP10: 24599 | EQ10: 24853 | ER10: 24469 | ES10: 24892 | ET10: 24063 | EU10: 19293 | EV10: 17688 | EW10: 17528 | EX10: 17230 | EY10: 16457 | EZ10: 16329 | FA10: 16005 | FB10: 15827 | FC10: 15816 | FD10: 15576 | FE10: 15289 | FF10: 15311 | FG10: 15463 | FH10: 15351 | FI10: 15308 | FJ10: 15384 | FK10: 15257 | FL10: 15377 | FM10: 15294 | FN10: 15190 | FO10: 15119 | FP10: 14992 | FQ10: 14958 | FR10: 14774 | FS10: 14468 | FT10: 14432 | FU10: 14350 | FV10: 14363 | FW10: 14564 | FX10: 14435 | FY10: 14389 | FZ10: 14141 | GA10: 13900 | GB10: 14045 | GC10: 13887 | GD10: 13832 | GE10: 14042 | GF10: 14070 | GG10: 14173 | GH10: 14376 | GI10: 14287 | GJ10: 14229 | GK10: 14327 | GL10: 14388 | GM10: 14469 | GN10: 13345 | GO10: 13269 | GP10: 13344 | GQ10: 13138 | GR10: 13029 | GS10: 13066 | GT10: 13013 | GU10: 13221 | GV10: 13918 | GW10: 14468 | GX10: 15462 | GY10: 16806 | GZ10: 18307 | HA10: 19665 | HB10: 20813 | HC10: 21827 | HD10: 22358 | HE10: 23002 | HF10: 23474 | HG10: 23464 | HH10: 23714.01 | HI10: 23848.3 | HJ10: 23957.06 | HK10: 24149.41 | HL10: 24312.45 | HM10: 24625.51 | HN10: 24950.39 | HO10: 25235.43 | HP10: 25439.51 | HQ10: 25530.07 | HR10: 25386.57 | HS10: 25429.68 | HT10: 25535.06 | HU10: 25524.67 | HV10: 25604.34 | HW10: 25760.51 | HX10: 25924.55 | HY10: 26155.01 | HZ10: 26416.02 | IA10: 26666.1 | IB10: 26943.44 | IC10: 27226.07 | ID10: 27517.69 | IE10: 27801.47 | IF10: 28047.94 | IG10: 28296.69 | IH10: 28551.13 | II10: 28812.24 | IJ10: 29076.69 | IK10: 29405.56 | IL10: 29734.3 | IM10: 30062.66 | IN10: 30390.53 | IO10: 30717.98 | IP10: 31044.8 | IQ10: 31370.86 | IR10: 31696.25 | IS10: 32021.18 | IT10: 32345.58 | IU10: 32669.41 | IV10: 32992.77 | IW10: 33315.92 | IX10: 33638.81 | IY10: 33961.19 | IZ10: 34282.94 | JA10: 34603.98 | JB10: 34924.16 | JC10: 35243.4 | JD10: 35561.63 | JE10: 35878.79 | JF10: 36194.84 | JG10: 36509.8 | JH10: 36823.64 | JI10: 37136.38 | JJ10: 37448.03 | JK10: 37758.66 | JL10: 38068.29 | JM10: 38376.94 | JN10: 38684.7 | JO10: 38991.62 | JP10: 39297.75 | JQ10: 39603.18 | JR10: 39907.94 | JS10: 40212.13 | JT10: 40515.81 | JU10: 40819.16 | JV10: 41122.24 | JW10: 41425.17 | JX10: 41727.99 | JY10: 42030.79 | JZ10: 42333.63 | KA10: 42636.5 | KB10: 42939.45 | KC10: 43242.55 | KD10: 43545.86 | KE10: 43849.33 | KF10: 44153.02 | KG10: 44456.99 | KH10: 44761.29 | KI10: 45065.78 | KJ10: 45370.49 | KK10: 45675.48 | KL10: 45980.83 | KM10: 46286.49 | KN10: 46592.51 | KO10: 46898.94 | KP10: 47205.84 | KQ10: 47513.27 | KR10: 47821.28 | KS10: 48129.93 | KT10: 48439.29 | KU10: 48749.32 | KV10: 49060.08 | KW10: 49371.61 | KX10: 49683.98 | KY10: 49997.17 | KZ10: 50311.27 | LA10: 50626.28 | LB10: 50942.26 | LC10: 51259.17 | LD10: 51577.03 | LE10: 51895.94 | LF10: 52215.94 | LG10: 52537.03 | LH10: 52859.23 | LI10: 53182.61 | LJ10: 53507.19 | LK10: 53832.96 | LL10: 54159.96 | LM10: 54488.19 | LN10: 54817.74 | LO10: 55148.5 | LP10: 55480.51 | LQ10: 55813.78 | LR10: 56148.36 | LS10: 56484.28 | LT10: 56821.56 | LU10: 57160.23 | LV10: 57500.35 | LW10: 57841.88 | LX10: 58184.86 | LY10: 58529.32 | LZ10: 58875.28 | MA10: 59222.74 | MB10: 59571.7 | MC10: 59922.2 | MD10: 60274.29 | ME10: 60627.95 | MF10: 60983.26 | MG10: 61340.2 | MH10: 61698.84 | MI10: 62059.24 | MJ10: 62421.41 | MK10: 62785.39 | ML10: 63151.21 | MM10: 63518.86 | MN10: 63888.38 | MO10: 64259.78 | MP10: 64633.08 | MQ10: 65008.36 | MR10: 65385.65 | MS10: 65764.95 | MT10: 66146.34 | MU10: Office for National Statistics/Haver Analytics | MV10: True | MW10: NA | MX10: NA | MY10: 2025 | MZ10: 1 | NA10: 09 July 2025 | NB10: J4X3Q@UK | NC10: UK: HH & NPISH: Uses: Interest excluding FISIM Adjustment (SA, Mil.GBP) | ND10: GBR | NE10: PEDIP_UNADJ | NF10: Desktop
A11: United Kingdom | B11: Personal sector debt interest receipts, excl. FISIM adjustment | C11: JUL009E | D11: Pound | E11: Millions | F11: Level | G11: 0.001 | H11: 0.001 | I11: 0.001 | J11: 0.001 | K11: 0.001 | L11: 0.001 | M11: 0.001 | N11: 0.001 | O11: 0.001 | P11: 0.001 | Q11: 0.001 | R11: 0.001 | S11: 0.001 | T11: 0.001 | U11: 0.001 | V11: 0.001 | W11: 0.001 | X11: 0.001 | Y11: 0.001 | Z11: 0.001 | AA11: 0.001 | AB11: 0.001 | AC11: 0.001 | AD11: 0.001 | AE11: 0.001 | AF11: 0.001 | AG11: 0.001 | AH11: 0.001 | AI11: 0.001 | AJ11: 0.001 | AK11: 0.001 | AL11: 0.001 | AM11: 0.001 | AN11: 0.001 | AO11: 0.001 | AP11: 0.001 | AQ11: 0.001 | AR11: 0.001 | AS11: 0.001 | AT11: 0.001 | AU11: 0.001 | AV11: 0.001 | AW11: 0.001 | AX11: 0.001 | AY11: 0.001 | AZ11: 0.001 | BA11: 0.001 | BB11: 0.001 | BC11: 0.001 | BD11: 0.001 | BE11: 0.001 | BF11: 0.001 | BG11: 0.001 | BH11: 0.001 | BI11: 0.001 | BJ11: 0.001 | BK11: 5125 | BL11: 5318 | BM11: 5384 | BN11: 4897 | BO11: 5033 | BP11: 5100 | BQ11: 5343 | BR11: 6323 | BS11: 6880 | BT11: 7550 | BU11: 7721 | BV11: 8337 | BW11: 8663 | BX11: 9207 | BY11: 9914 | BZ11: 9670 | CA11: 10252 | CB11: 8706 | CC11: 8821 | CD11: 7822 | CE11: 10088 | CF11: 7880 | CG11: 7774 | CH11: 6753 | CI11: 5846 | CJ11: 5963 | CK11: 5830 | CL11: 5957 | CM11: 5390 | CN11: 5714 | CO11: 5337 | CP11: 5749 | CQ11: 6546 | CR11: 6787 | CS11: 6608 | CT11: 6634 | CU11: 6041 | CV11: 6035 | CW11: 6087 | CX11: 5828 | CY11: 6177 | CZ11: 5779 | DA11: 6453 | DB11: 6549 | DC11: 6585 | DD11: 6910 | DE11: 7079 | DF11: 7164 | DG11: 5632 | DH11: 5579 | DI11: 5446 | DJ11: 5819 | DK11: 6266 | DL11: 6547 | DM11: 6808 | DN11: 6800 | DO11: 6950 | DP11: 6496 | DQ11: 6074 | DR11: 5580 | DS11: 4720 | DT11: 5048 | DU11: 4882 | DV11: 4791 | DW11: 4824 | DX11: 4971 | DY11: 4646 | DZ11: 4870 | EA11: 5373 | EB11: 5936 | EC11: 6800 | ED11: 7392 | EE11: 7527 | EF11: 7726 | EG11: 8180 | EH11: 7574 | EI11: 8006 | EJ11: 8152 | EK11: 8784 | EL11: 9265 | EM11: 9971 | EN11: 10702 | EO11: 11166 | EP11: 11601 | EQ11: 11005 | ER11: 10959 | ES11: 11290 | ET11: 9604 | EU11: 5672 | EV11: 4933 | EW11: 4770 | EX11: 4712 | EY11: 4755 | EZ11: 4851 | FA11: 4778 | FB11: 4714 | FC11: 5041 | FD11: 5172 | FE11: 5177 | FF11: 5409 | FG11: 5389 | FH11: 5617 | FI11: 5560 | FJ11: 5693 | FK11: 5478 | FL11: 5173 | FM11: 4796 | FN11: 4584 | FO11: 4321 | FP11: 4138 | FQ11: 3945 | FR11: 3789 | FS11: 3677 | FT11: 3718 | FU11: 3746 | FV11: 3688 | FW11: 3686 | FX11: 3566 | FY11: 3443 | FZ11: 3046 | GA11: 2732 | GB11: 2713 | GC11: 2680 | GD11: 2737 | GE11: 2986 | GF11: 2891 | GG11: 3044 | GH11: 3192 | GI11: 3148 | GJ11: 3299 | GK11: 3224 | GL11: 3151 | GM11: 3049 | GN11: 2429 | GO11: 2114 | GP11: 1830 | GQ11: 1701 | GR11: 1714 | GS11: 1639 | GT11: 1763 | GU11: 1900 | GV11: 2676 | GW11: 3259 | GX11: 5360 | GY11: 7223 | GZ11: 9055 | HA11: 11134 | HB11: 12833 | HC11: 13589 | HD11: 13865 | HE11: 14314 | HF11: 14211 | HG11: 13125 | HH11: 13003.82 | HI11: 13058.77 | HJ11: 12877.62 | HK11: 12669.71 | HL11: 12533.04 | HM11: 12576.13 | HN11: 12527.03 | HO11: 12577.11 | HP11: 12517.21 | HQ11: 12550.4 | HR11: 12533.86 | HS11: 12599.93 | HT11: 12784.36 | HU11: 13082.46 | HV11: 13387.72 | HW11: 13700.11 | HX11: 14018.34 | HY11: 14341.86 | HZ11: 14672.96 | IA11: 15012.49 | IB11: 15362.31 | IC11: 15720.75 | ID11: 16087.51 | IE11: 16321.9 | IF11: 16561.01 | IG11: 16800.82 | IH11: 17042.46 | II11: 17285.72 | IJ11: 17528.65 | IK11: 17767.42 | IL11: 18001.84 | IM11: 18232.59 | IN11: 18461.03 | IO11: 18684.8 | IP11: 18903.46 | IQ11: 19118.35 | IR11: 19331.61 | IS11: 19540.74 | IT11: 19745.78 | IU11: 19947.28 | IV11: 20147.75 | IW11: 20344.99 | IX11: 20538.71 | IY11: 20729.84 | IZ11: 20919.6 | JA11: 21108.31 | JB11: 21296.07 | JC11: 21482.89 | JD11: 21668.81 | JE11: 21853.9 | JF11: 22038.19 | JG11: 22221.08 | JH11: 22402.68 | JI11: 22583.06 | JJ11: 22762.3 | JK11: 22940.47 | JL11: 23117.58 | JM11: 23293.72 | JN11: 23468.97 | JO11: 23643.36 | JP11: 23816.89 | JQ11: 23989.66 | JR11: 24161.69 | JS11: 24332.96 | JT11: 24504.01 | JU11: 24674.67 | JV11: 24844.65 | JW11: 25013.94 | JX11: 25182.56 | JY11: 25350.53 | JZ11: 25517.48 | KA11: 25683.71 | KB11: 25849.36 | KC11: 26014.55 | KD11: 26178.69 | KE11: 26342.18 | KF11: 26505.15 | KG11: 26667.68 | KH11: 26828.84 | KI11: 26992.56 | KJ11: 27160.24 | KK11: 27332.35 | KL11: 27508.5 | KM11: 27686.17 | KN11: 27864.31 | KO11: 28042.57 | KP11: 28220.83 | KQ11: 28399.83 | KR11: 28579.64 | KS11: 28760.33 | KT11: 28941.55 | KU11: 29123.98 | KV11: 29307.66 | KW11: 29492.58 | KX11: 29678.54 | KY11: 29865.65 | KZ11: 30053.92 | LA11: 30243.31 | LB11: 30433.27 | LC11: 30624.31 | LD11: 30816.76 | LE11: 31010.48 | LF11: 31205.29 | LG11: 31401.26 | LH11: 31598.41 | LI11: 31796.79 | LJ11: 31996.04 | LK11: 32195.98 | LL11: 32396.55 | LM11: 32597.69 | LN11: 32799.14 | LO11: 33001.22 | LP11: 33204.02 | LQ11: 33407.61 | LR11: 33611.99 | LS11: 33817.15 | LT11: 34023.06 | LU11: 34229.79 | LV11: 34437.18 | LW11: 34645.4 | LX11: 34854.53 | LY11: 35064.5 | LZ11: 35275.29 | MA11: 35487.06 | MB11: 35699.82 | MC11: 35913.67 | MD11: 36128.54 | ME11: 36344.37 | MF11: 36561.2 | MG11: 36778.99 | MH11: 36997.82 | MI11: 37217.62 | MJ11: 37438.38 | MK11: 37660 | ML11: 37882.51 | MM11: 38105.98 | MN11: 38330.51 | MO11: 38556.09 | MP11: 38782.84 | MQ11: 39010.61 | MR11: 39239.37 | MS11: 39469.05 | MT11: 39699.78 | MU11: Office for National Statistics/Haver Analytics | MV11: True | MW11: NA | MX11: NA | MY11: 2025 | MZ11: 1 | NA11: 09 July 2025 | NB11: J4X2Q@UK | NC11: UK: HH & NPISH: Resources: Interest excluding FISIM Adjustment (SA, Mil.GBP) | ND11: GBR | NE11: PEDIR_UNADJ | NF11: Desktop
A12: United Kingdom | B12: Personal sector debt interest payments | C12: JUL009E | D12: Pound | E12: Millions | F12: Level | G12: 0.001 | H12: 0.001 | I12: 0.001 | J12: 0.001 | K12: 0.001 | L12: 0.001 | M12: 0.001 | N12: 0.001 | O12: 0.001 | P12: 0.001 | Q12: 0.001 | R12: 0.001 | S12: 0.001 | T12: 0.001 | U12: 0.001 | V12: 0.001 | W12: 0.001 | X12: 0.001 | Y12: 0.001 | Z12: 0.001 | AA12: 0.001 | AB12: 0.001 | AC12: 0.001 | AD12: 0.001 | AE12: 0.001 | AF12: 0.001 | AG12: 0.001 | AH12: 0.001 | AI12: 0.001 | AJ12: 0.001 | AK12: 0.001 | AL12: 0.001 | AM12: 0.001 | AN12: 0.001 | AO12: 0.001 | AP12: 0.001 | AQ12: 0.001 | AR12: 0.001 | AS12: 0.001 | AT12: 0.001 | AU12: 0.001 | AV12: 0.001 | AW12: 0.001 | AX12: 0.001 | AY12: 0.001 | AZ12: 0.001 | BA12: 0.001 | BB12: 0.001 | BC12: 0.001 | BD12: 0.001 | BE12: 0.001 | BF12: 0.001 | BG12: 0.001 | BH12: 0.001 | BI12: 0.001 | BJ12: 0.001 | BK12: 5414 | BL12: 5168 | BM12: 5394 | BN12: 5967 | BO12: 5380 | BP12: 5508 | BQ12: 6312 | BR12: 7269 | BS12: 8124 | BT12: 9068 | BU12: 9245 | BV12: 9778 | BW12: 10584 | BX12: 11491 | BY12: 11880 | BZ12: 11492 | CA12: 11454 | CB12: 10793 | CC12: 10251 | CD12: 9965 | CE12: 11073 | CF12: 10082 | CG12: 9682 | CH12: 8436 | CI12: 7548 | CJ12: 7324 | CK12: 7370 | CL12: 7335 | CM12: 7287 | CN12: 7722 | CO12: 7486 | CP12: 7720 | CQ12: 8283 | CR12: 8575 | CS12: 8424 | CT12: 8145 | CU12: 8006 | CV12: 7771 | CW12: 7586 | CX12: 7442 | CY12: 7777 | CZ12: 7915 | DA12: 8565 | DB12: 9175 | DC12: 8666 | DD12: 9118 | DE12: 9637 | DF12: 9759 | DG12: 9118 | DH12: 9051 | DI12: 8086 | DJ12: 9064 | DK12: 10293 | DL12: 10693 | DM12: 10594 | DN12: 10714 | DO12: 10928 | DP12: 10417 | DQ12: 9901 | DR12: 8885 | DS12: 8869 | DT12: 9186 | DU12: 9389 | DV12: 9667 | DW12: 9783 | DX12: 9684 | DY12: 9380 | DZ12: 9776 | EA12: 10893 | EB12: 11972 | EC12: 13528 | ED12: 13991 | EE12: 13856 | EF12: 14772 | EG12: 14859 | EH12: 14939 | EI12: 15223 | EJ12: 15513 | EK12: 16282 | EL12: 17312 | EM12: 18398 | EN12: 19478 | EO12: 20406 | EP12: 22142 | EQ12: 23284 | ER12: 22703 | ES12: 22898 | ET12: 21935 | EU12: 11932 | EV12: 9127 | EW12: 7821 | EX12: 7276 | EY12: 5040 | EZ12: 5486 | FA12: 5317 | FB12: 6037 | FC12: 5808 | FD12: 5796 | FE12: 5851 | FF12: 6471 | FG12: 7183 | FH12: 6818 | FI12: 5954 | FJ12: 5688 | FK12: 6172 | FL12: 5864 | FM12: 5556 | FN12: 5019 | FO12: 6151 | FP12: 7292 | FQ12: 7395 | FR12: 7328 | FS12: 6860 | FT12: 7108 | FU12: 6986 | FV12: 7177 | FW12: 6854 | FX12: 7376 | FY12: 7320 | FZ12: 7133 | GA12: 6108 | GB12: 6097 | GC12: 5495 | GD12: 6078 | GE12: 6779 | GF12: 7442 | GG12: 7727 | GH12: 8288 | GI12: 7874 | GJ12: 6868 | GK12: 6617 | GL12: 6347 | GM12: 5789 | GN12: 4314 | GO12: 4477 | GP12: 4795 | GQ12: 5434 | GR12: 5323 | GS12: 5045 | GT12: 5673 | GU12: 7327 | GV12: 9213 | GW12: 11382 | GX12: 15233 | GY12: 19227 | GZ12: 20178 | HA12: 21789 | HB12: 22907 | HC12: 23970 | HD12: 22990 | HE12: 23153 | HF12: 23866 | HG12: 23347 | HH12: 23314.6 | HI12: 23021.57 | HJ12: 22700.48 | HK12: 22466.36 | HL12: 22206.54 | HM12: 22265.08 | HN12: 22272.4 | HO12: 22308.96 | HP12: 22197.14 | HQ12: 22037.57 | HR12: 21572.18 | HS12: 21371.14 | HT12: 21336.01 | HU12: 21185.11 | HV12: 21124.27 | HW12: 21139.93 | HX12: 21163.46 | HY12: 21253.41 | HZ12: 21373.91 | IA12: 21483.48 | IB12: 21620.31 | IC12: 21762.43 | ID12: 21913.54 | IE12: 22197.32 | IF12: 22443.79 | IG12: 22692.54 | IH12: 22946.98 | II12: 23208.09 | IJ12: 23472.54 | IK12: 23801.41 | IL12: 24130.15 | IM12: 24458.51 | IN12: 24786.38 | IO12: 25113.83 | IP12: 25440.65 | IQ12: 25766.71 | IR12: 26092.1 | IS12: 26417.03 | IT12: 26741.43 | IU12: 27065.26 | IV12: 27388.62 | IW12: 27711.77 | IX12: 28034.66 | IY12: 28357.04 | IZ12: 28678.79 | JA12: 28999.83 | JB12: 29320.01 | JC12: 29639.25 | JD12: 29957.48 | JE12: 30274.63 | JF12: 30590.69 | JG12: 30905.65 | JH12: 31219.49 | JI12: 31532.23 | JJ12: 31843.88 | JK12: 32154.51 | JL12: 32464.13 | JM12: 32772.79 | JN12: 33080.55 | JO12: 33387.47 | JP12: 33693.6 | JQ12: 33999.03 | JR12: 34303.79 | JS12: 34607.98 | JT12: 34911.66 | JU12: 35215.01 | JV12: 35518.09 | JW12: 35821.02 | JX12: 36123.84 | JY12: 36426.64 | JZ12: 36729.48 | KA12: 37032.35 | KB12: 37335.3 | KC12: 37638.4 | KD12: 37941.71 | KE12: 38245.18 | KF12: 38548.87 | KG12: 38852.84 | KH12: 39157.14 | KI12: 39461.63 | KJ12: 39766.34 | KK12: 40071.33 | KL12: 40376.68 | KM12: 40682.34 | KN12: 40988.36 | KO12: 41294.79 | KP12: 41601.69 | KQ12: 41909.12 | KR12: 42217.13 | KS12: 42525.78 | KT12: 42835.14 | KU12: 43145.17 | KV12: 43455.93 | KW12: 43767.46 | KX12: 44079.83 | KY12: 44393.02 | KZ12: 44707.12 | LA12: 45022.13 | LB12: 45338.11 | LC12: 45655.02 | LD12: 45972.88 | LE12: 46291.79 | LF12: 46611.79 | LG12: 46932.88 | LH12: 47255.08 | LI12: 47578.46 | LJ12: 47903.04 | LK12: 48228.81 | LL12: 48555.81 | LM12: 48884.04 | LN12: 49213.59 | LO12: 49544.35 | LP12: 49876.36 | LQ12: 50209.63 | LR12: 50544.21 | LS12: 50880.13 | LT12: 51217.41 | LU12: 51556.08 | LV12: 51896.2 | LW12: 52237.73 | LX12: 52580.71 | LY12: 52925.17 | LZ12: 53271.13 | MA12: 53618.59 | MB12: 53967.55 | MC12: 54318.05 | MD12: 54670.14 | ME12: 55023.8 | MF12: 55379.11 | MG12: 55736.05 | MH12: 56094.69 | MI12: 56455.09 | MJ12: 56817.26 | MK12: 57181.24 | ML12: 57547.06 | MM12: 57914.71 | MN12: 58284.23 | MO12: 58655.63 | MP12: 59028.93 | MQ12: 59404.21 | MR12: 59781.5 | MS12: 60160.81 | MT12: 60542.18 | MU12: Office for National Statistics\Haver Analytics | MV12: True | MW12: NA | MX12: NA | MY12: 2025 | MZ12: 1 | NA12: 09 July 2025 | NB12: ROYUQ@UK | NC12: UK: HH & NPISH: Interest, Paid (SA, Mil.GBP) | ND12: GBR | NE12: PEDIP | NF12: Desktop
A13: United Kingdom | B13: Personal sector debt interest receipts | C13: JUL009E | D13: Pound | E13: Millions | F13: Level | G13: 0.001 | H13: 0.001 | I13: 0.001 | J13: 0.001 | K13: 0.001 | L13: 0.001 | M13: 0.001 | N13: 0.001 | O13: 0.001 | P13: 0.001 | Q13: 0.001 | R13: 0.001 | S13: 0.001 | T13: 0.001 | U13: 0.001 | V13: 0.001 | W13: 0.001 | X13: 0.001 | Y13: 0.001 | Z13: 0.001 | AA13: 0.001 | AB13: 0.001 | AC13: 0.001 | AD13: 0.001 | AE13: 0.001 | AF13: 0.001 | AG13: 0.001 | AH13: 0.001 | AI13: 0.001 | AJ13: 0.001 | AK13: 0.001 | AL13: 0.001 | AM13: 0.001 | AN13: 0.001 | AO13: 0.001 | AP13: 0.001 | AQ13: 0.001 | AR13: 0.001 | AS13: 0.001 | AT13: 0.001 | AU13: 0.001 | AV13: 0.001 | AW13: 0.001 | AX13: 0.001 | AY13: 0.001 | AZ13: 0.001 | BA13: 0.001 | BB13: 0.001 | BC13: 0.001 | BD13: 0.001 | BE13: 0.001 | BF13: 0.001 | BG13: 0.001 | BH13: 0.001 | BI13: 0.001 | BJ13: 0.001 | BK13: 5926 | BL13: 6196 | BM13: 6307 | BN13: 5845 | BO13: 6039 | BP13: 6114 | BQ13: 6260 | BR13: 7228 | BS13: 7786 | BT13: 8510 | BU13: 8743 | BV13: 9453 | BW13: 9831 | BX13: 10412 | BY13: 11123 | BZ13: 10844 | CA13: 11404 | CB13: 9829 | CC13: 9917 | CD13: 8876 | CE13: 11087 | CF13: 8884 | CG13: 8875 | CH13: 8006 | CI13: 7122 | CJ13: 7185 | CK13: 7013 | CL13: 7142 | CM13: 6591 | CN13: 6903 | CO13: 6484 | CP13: 6909 | CQ13: 7697 | CR13: 7947 | CS13: 7881 | CT13: 8013 | CU13: 7475 | CV13: 7528 | CW13: 7628 | CX13: 7430 | CY13: 7767 | CZ13: 7714 | DA13: 8698 | DB13: 8809 | DC13: 8925 | DD13: 9229 | DE13: 9454 | DF13: 9424 | DG13: 8791 | DH13: 8031 | DI13: 6551 | DJ13: 7589 | DK13: 9542 | DL13: 9769 | DM13: 9767 | DN13: 8506 | DO13: 9853 | DP13: 8460 | DQ13: 7999 | DR13: 5951 | DS13: 6368 | DT13: 6728 | DU13: 6958 | DV13: 7066 | DW13: 7173 | DX13: 7238 | DY13: 6830 | DZ13: 7495 | EA13: 7981 | EB13: 9099 | EC13: 10669 | ED13: 10997 | EE13: 10247 | EF13: 10832 | EG13: 11362 | EH13: 10825 | EI13: 10976 | EJ13: 11066 | EK13: 12476 | EL13: 13093 | EM13: 13123 | EN13: 14129 | EO13: 15543 | EP13: 15224 | EQ13: 16801 | ER13: 16627 | ES13: 17039 | ET13: 15730 | EU13: 7511 | EV13: 5841 | EW13: 4964 | EX13: 4672 | EY13: 4045 | EZ13: 4513 | FA13: 4650 | FB13: 5102 | FC13: 5206 | FD13: 5058 | FE13: 5206 | FF13: 5766 | FG13: 6130 | FH13: 5911 | FI13: 5193 | FJ13: 5109 | FK13: 5297 | FL13: 5009 | FM13: 4742 | FN13: 4218 | FO13: 5189 | FP13: 6230 | FQ13: 6517 | FR13: 6482 | FS13: 5981 | FT13: 6387 | FU13: 6447 | FV13: 6497 | FW13: 5946 | FX13: 6466 | FY13: 6425 | FZ13: 6084 | GA13: 5216 | GB13: 5035 | GC13: 4684 | GD13: 5040 | GE13: 5847 | GF13: 6250 | GG13: 6775 | GH13: 7302 | GI13: 6574 | GJ13: 5831 | GK13: 5646 | GL13: 5633 | GM13: 4869 | GN13: 3575 | GO13: 4023 | GP13: 4009 | GQ13: 4677 | GR13: 4935 | GS13: 4922 | GT13: 5654 | GU13: 7415 | GV13: 9289 | GW13: 11477 | GX13: 16492 | GY13: 20417 | GZ13: 20973 | HA13: 22844 | HB13: 24288 | HC13: 25311 | HD13: 24573 | HE13: 25041 | HF13: 25708 | HG13: 24824 | HH13: 24704.57 | HI13: 24355.7 | HJ13: 23772.61 | HK13: 23162.88 | HL13: 22623.82 | HM13: 22263.19 | HN13: 21810.96 | HO13: 21457.2 | HP13: 20994.16 | HQ13: 20623.57 | HR13: 20203.55 | HS13: 19865.61 | HT13: 19645.34 | HU13: 19538.12 | HV13: 19438.04 | HW13: 19345.1 | HX13: 19258 | HY13: 19176.19 | HZ13: 19101.96 | IA13: 19036.16 | IB13: 18980.64 | IC13: 18933.76 | ID13: 18895.18 | IE13: 19129.58 | IF13: 19368.68 | IG13: 19608.5 | IH13: 19850.13 | II13: 20093.39 | IJ13: 20336.32 | IK13: 20575.09 | IL13: 20809.52 | IM13: 21040.26 | IN13: 21268.7 | IO13: 21492.47 | IP13: 21711.13 | IQ13: 21926.02 | IR13: 22139.28 | IS13: 22348.41 | IT13: 22553.45 | IU13: 22754.95 | IV13: 22955.42 | IW13: 23152.66 | IX13: 23346.38 | IY13: 23537.51 | IZ13: 23727.27 | JA13: 23915.98 | JB13: 24103.74 | JC13: 24290.56 | JD13: 24476.48 | JE13: 24661.57 | JF13: 24845.86 | JG13: 25028.76 | JH13: 25210.35 | JI13: 25390.73 | JJ13: 25569.98 | JK13: 25748.14 | JL13: 25925.25 | JM13: 26101.4 | JN13: 26276.64 | JO13: 26451.03 | JP13: 26624.56 | JQ13: 26797.33 | JR13: 26969.36 | JS13: 27140.63 | JT13: 27311.68 | JU13: 27482.34 | JV13: 27652.32 | JW13: 27821.61 | JX13: 27990.23 | JY13: 28158.2 | JZ13: 28325.15 | KA13: 28491.38 | KB13: 28657.04 | KC13: 28822.22 | KD13: 28986.36 | KE13: 29149.85 | KF13: 29312.82 | KG13: 29475.36 | KH13: 29636.52 | KI13: 29800.23 | KJ13: 29967.91 | KK13: 30140.02 | KL13: 30316.17 | KM13: 30493.84 | KN13: 30671.98 | KO13: 30850.24 | KP13: 31028.5 | KQ13: 31207.5 | KR13: 31387.31 | KS13: 31568 | KT13: 31749.22 | KU13: 31931.65 | KV13: 32115.33 | KW13: 32300.25 | KX13: 32486.21 | KY13: 32673.32 | KZ13: 32861.59 | LA13: 33050.98 | LB13: 33240.94 | LC13: 33431.98 | LD13: 33624.43 | LE13: 33818.16 | LF13: 34012.96 | LG13: 34208.93 | LH13: 34406.09 | LI13: 34604.46 | LJ13: 34803.71 | LK13: 35003.66 | LL13: 35204.23 | LM13: 35405.36 | LN13: 35606.81 | LO13: 35808.89 | LP13: 36011.69 | LQ13: 36215.28 | LR13: 36419.66 | LS13: 36624.82 | LT13: 36830.73 | LU13: 37037.46 | LV13: 37244.85 | LW13: 37453.07 | LX13: 37662.2 | LY13: 37872.17 | LZ13: 38082.96 | MA13: 38294.73 | MB13: 38507.49 | MC13: 38721.34 | MD13: 38936.21 | ME13: 39152.04 | MF13: 39368.87 | MG13: 39586.66 | MH13: 39805.49 | MI13: 40025.3 | MJ13: 40246.05 | MK13: 40467.67 | ML13: 40690.18 | MM13: 40913.65 | MN13: 41138.18 | MO13: 41363.77 | MP13: 41590.51 | MQ13: 41818.28 | MR13: 42047.04 | MS13: 42276.73 | MT13: 42507.45 | MU13: Office for National Statistics/Haver Analytics | MV13: True | MW13: NA | MX13: NA | MY13: 2025 | MZ13: 1 | NA13: 09 July 2025 | NB13: ROYMQ@UK | NC13: UK: HH & NPISH: Interest, Received (SA, Mil.GBP) | ND13: GBR | NE13: PEDIR | NF13: Desktop
