Workbook
Name _DLX1.INC: HAVERM!$B$2:$AH$7
Name _DLX2.INC: HAVERD!$G$3:$IS$8
Name _DLX3.INC: HAVERQ!$B$2:$H$7
Name Data: [1]sheet0!$C$2

Sheet >> MARKET PRICING CHARTS

Sheet >> DATA
C5: ='Market expectations - Oil'!$N$53:$AL$53,'Market expectations - Oil'!$N$55:$AL$56 -> #VALUE!

Sheet Bloom - Monthly US data
A1: Year | B1: Month | C1: 1. Economic Policy Uncertainty | D1: 2. Monetary policy | E1: Fiscal Policy (Taxes OR Spending) | F1: 3. Taxes | G1: 4. Government spending | H1: 5. Health care | I1: 6. National security | J1: 7. Entitlement programs | K1: 8. Regulation | L1: Financial Regulation | M1: 9. Trade policy | N1: 10. Sovereign debt, currency crises | R1: Source: “Measuring Economic Policy Uncertainty” by Scott Baker, Nicholas Bloom and Steven J. Davis at www.PolicyUncertainty.com. These data can be used freely with attribution to the authors, the paper, and the website.
A2: 1985 | B2: 1 | C2: 213.67883 | D2: 270.46923 | E2: 292.61456 | F2: 295.79079 | G2: 394.09975 | H2: 107.84824 | I2: 179.69985 | J2: 258.34622 | K2: 129.63282 | L2: 113.24718 | M2: 122.61396 | N2: 0
A3: 1985 | B3: 2 | C3: 155.42602 | D3: 219.83568 | E3: 164.23554 | F3: 139.1256 | G3: 225.03278 | H3: 36.73303 | I3: 124.8595 | J3: 82.492997 | K3: 55.191052 | L3: 0 | M3: 41.762223 | N3: 128.389
A4: 1985 | B4: 3 | C4: 121.13737 | D4: 119.03452 | E4: 108.82881 | F4: 115.71434 | G4: 102.02634 | H4: 31.642944 | I4: 63.269264 | J4: 113.69914 | K4: 85.577836 | L4: 149.52152 | M4: 107.92573 | N4: 110.59817
A5: 1985 | B5: 4 | C5: 104.98235 | D5: 122.04476 | E5: 104.73733 | F5: 85.760217 | G5: 138.08053 | H5: 38.066636 | I5: 85.627432 | J5: 51.29276 | K5: 60.054521 | L5: 44.968804 | M5: 194.75287 | N5: 0
A6: 1985 | B6: 5 | C6: 115.73678 | D6: 107.57358 | E6: 134.83997 | F6: 132.17777 | G6: 167.56891 | H6: 54.705931 | I6: 109.38312 | J6: 98.284429 | K6: 65.75614 | L6: 129.25021 | M6: 124.39166 | N6: 95.603868
A7: 1985 | B7: 6 | C7: 139.79243 | D7: 156.64302 | E7: 197.6899 | F7: 190.02239 | G7: 182.43723 | H7: 26.943794 | I7: 161.6203 | J7: 108.91597 | K7: 89.062184 | L7: 42.43892 | M7: 153.16361 | N7: 0
A8: 1985 | B8: 7 | C8: 120.50515 | D8: 173.40758 | E8: 134.14929 | F8: 122.26014 | G8: 201.22261 | H8: 26.003398 | I8: 155.97941 | J8: 116.79397 | K8: 39.069875 | L8: 0 | M8: 59.127152 | N8: 181.77374
A9: 1985 | B9: 8 | C9: 122.68383 | D9: 111.33082 | E9: 118.87554 | F9: 122.82737 | G9: 217.70667 | H9: 56.267169 | I9: 106.07593 | J9: 151.63401 | K9: 57.970918 | L9: 37.982527 | M9: 109.66426 | N9: 168.56963
A10: 1985 | B10: 9 | C10: 91.711134 | D10: 113.58992 | E10: 81.798704 | F10: 67.479869 | G10: 126.92818 | H10: 24.603827 | I10: 83.631037 | J10: 11.050781 | K10: 51.753844 | L10: 77.506519 | M10: 279.72386 | N10: 85.9951
A11: 1985 | B11: 10 | C11: 86.338619 | D11: 69.607238 | E11: 108.07516 | F11: 89.542597 | G11: 103.62251 | H11: 7.1417751 | I11: 42.839395 | J11: 67.362126 | K11: 64.382722 | L11: 33.746831 | M11: 121.79355 | N11: 74.885628
A12: 1985 | B12: 11 | C12: 115.88343 | D12: 70.245579 | E12: 96.548438 | F12: 83.162896 | G12: 99.344154 | H12: 34.234531 | I12: 114.99781 | J12: 36.903362 | K12: 117.27654 | L12: 32.353495 | M12: 93.411958 | N12: 287.17503
A13: 1985 | B13: 12 | C13: 126.42213 | D13: 112.56385 | E13: 150.93895 | F13: 137.02444 | G13: 225.52253 | H13: 6.8573188 | I13: 119.28601 | J13: 55.439227 | K13: 98.909382 | L13: 64.805396 | M13: 70.165513 | N13: 0
... A481: 2024 | B481: 12 | C481: 178.71316 | D481: 155.29582 | E481: 182.71297 | F481: 184.80943 | G481: 144.52786 | H481: 310.54932 | I481: 154.64808 | J481: 277.64988 | K481: 258.82961 | L481: 46.145599 | M481: 1319.0059 | N481: 51.199505
A482: 2025 | B482: 1 | C482: 236.44342 | D482: 222.12527 | E482: 291.74046 | F482: 293.14729 | G482: 208.06876 | H482: 415.24587 | I482: 159.32277 | J482: 448.62547 | K482: 345.67612 | L482: 97.223638 | M482: 1725.7097 | N482: 9.8065141
A483: 2025 | B483: 2 | C483: 318.83708 | D483: 228.812 | E483: 366.30341 | F483: 387.18067 | G483: 324.81819 | H483: 508.7607 | I483: 302.74939 | J483: 517.89384 | K483: 339.19675 | L483: 258.08702 | M483: 2583.8988 | N483: 137.87364
A484: 2025 | B484: 3 | C484: 494.24966 | D484: 448.73962 | E484: 625.94934 | F484: 642.23055 | G484: 526.66807 | H484: 602.54292 | I484: 646.92115 | J484: 749.04636 | K484: 385.29537 | L484: 409.31014 | M484: 5912.1077 | N484: 119.7727
A485: 2025 | B485: 4 | C485: 536.89983 | D485: 452.76532 | E485: 688.94801 | F485: 738.80059 | G485: 370.92482 | H485: 713.75444 | I485: 765.61537 | J485: 688.93701 | K485: 443.26268 | L485: 401.19509 | M485: 7955.647 | N485: 508.72495
A486: 2025 | B486: 5 | C486: 488.92356 | D486: 422.14241 | E486: 618.66266 | F486: 634.2017 | G486: 622.65226 | H486: 912.07601 | I486: 537.53321 | J486: 984.94913 | K486: 466.94638 | L486: 133.01875 | M486: 5780.0371 | N486: 98.391385
A487: 2025 | B487: 6 | C487: 379.36265 | D487: 288.22908 | E487: 494.28389 | F487: 529.56941 | G487: 533.52789 | H487: 677.34828 | I487: 293.7497 | J487: 821.00483 | K487: 400.578 | L487: 170.50673 | M487: 3537.4699 | N487: 378.36156
A488: 2025 | B488: 7 | C488: 364.90501 | D488: 342.21048 | E488: 447.40446 | F488: 483.94887 | G488: 256.16082 | H488: 530.65718 | I488: 277.08186 | J488: 521.63303 | K488: 467.45012 | L488: 243.58568 | M488: 3371.6439 | N488: 63.591386
A489: 2025 | B489: 8 | C489: 291.42825 | D489: 288.02986 | E489: 322.08127 | F489: 344.37666 | G489: 185.19977 | H489: 459.31163 | I489: 270.15901 | J489: 395.66691 | K489: 269.18826 | L489: 159.3794 | M489: 2727.1536 | N489: 10.402046
A490: 2025 | B490: 9 | C490: 331.642 | D490: 374.76442 | E490: 375.56345 | F490: 406.96841 | G490: 228.68564 | H490: 547.44542 | I490: 235.96934 | J490: 526.1493 | K490: 230.60009 | L490: 109.88299 | M490: 3767.4313 | N490: 30.479367
A491: 2025 | B491: 10 | C491: 340.44588 | D491: 244.72468 | E491: 391.26275 | F491: 413.1186 | G491: 244.1528 | H491: 765.28296 | I491: 292.61029 | J491: 726.04576 | K491: 325.18023 | L491: 126.88317 | M491: 2558.2799 | N491: 65.697111
A492: 2025 | B492: 11 | C492: 336.51804 | D492: 261.6806 | E492: 396.77829 | F492: 417.42352 | G492: 294.16563 | H492: 565.06192 | I492: 274.21843 | J492: 633.17046 | K492: 311.30019 | L492: 101.98189 | M492: 3178.6687 | N492: 30.859374
A493: 2025 | B493: 12 | C493: 359.15685 | D493: 247.6231 | E493: 358.45486 | F493: 384.91154 | G493: 222.85369 | H493: 653.26963 | I493: 250.07174 | J493: 467.67266 | K493: 379.42573 | L493: 344.0336 | M493: 3115.9806 | N493: 62.747253
... A496: 2026 | B496: 3 | C496: 388.70268 | D496: 271.2267 | E496: 366.15029 | F496: 397.92815 | G496: 221.16314 | H496: 458.30479 | I496: 643.49907 | J496: 343.84256 | K496: 435.24356 | L496: 491.96596 | M496: 2144.5534 | N496: 214.05745

Sheet Market pricing dates
A2: April 2026 MPR | B2: 46134 | D2: Current market curve | E2: 46191 | I2: * Final date for Feb 2026 MPR forecast will be January 27, ahead of the MPR release on February 5
A4: Last 5 working days | D4: Last 5 working days | I4: * Final date for Apr 2026 MPR forecast will be April 21, ahead of the MPR release on April 30
A5: =TEXT(B5,"dddd") -> Thursday | B5: =IF(A6="Monday",B6-3,B6-1) -> 46128 | D5: =TEXT(E5,"dddd") -> Friday | E5: =IF(D6="Monday",E6-3,E6-1) -> 46185
A6: =TEXT(B6,"dddd") -> Friday | B6: =IF(A7="Monday",B7-3,B7-1) -> 46129 | D6: =TEXT(E6,"dddd") -> Monday | E6: =IF(D7="Monday",E7-3,E7-1) -> 46188
A7: =TEXT(B7,"dddd") -> Monday | B7: =IF(A8="Monday",B8-3,B8-1) -> 46132 | D7: =TEXT(E7,"dddd") -> Tuesday | E7: =IF(D8="Monday",E8-3,E8-1) -> 46189
A8: =TEXT(B8,"dddd") -> Tuesday | B8: =IF(A9="Monday",B9-3,B9-1) -> 46133 | D8: =TEXT(E8,"dddd") -> Wednesday | E8: =IF(D9="Monday",E9-3,E9-1) -> 46190
A9: =TEXT(B9,"dddd") -> Wednesday | B9: =B2 -> 46134 | D9: =TEXT(E9,"dddd") -> Thursday | E9: =E2 -> 46191
B11: =TEXT(B9,"dd mmm yyyy") -> 22 Apr 2026 | E11: =TEXT(E9,"dd mmm yyyy") -> 18 Jun 2026
A12: ="15 working days to "&B11 -> 15 working days to 22 Apr 2026 | D12: ="15 working days to "&E11 -> 15 working days to 18 Jun 2026

Sheet Market expectations - RCB
A1: ='Market pricing dates'!A2 -> April 2026 MPR | C1: ='Market pricing dates'!A12 -> 15 working days to 22 Apr 2026 | BA1: ='Market pricing dates'!D2 -> Current market curve | BC1: ='Market pricing dates'!D12 -> 15 working days to 18 Jun 2026
A2: Column # | B2: =HAVERD!I$1 -> 9 | C2: =+B2+1 -> 10 | D2: =+C2+1 -> 11 | E2: =+D2+1 -> 12 | F2: =+E2+1 -> 13 | G2: =+F2+1 -> 14 | H2: =+G2+1 -> 15 | I2: =+H2+1 -> 16 | J2: =+I2+1 -> 17 | ... AX2: =+AW2+1 -> 57 | BA2: Column # | BB2: =HAVERD!I$1 -> 9 | BC2: =+BB2+1 -> 10 | BD2: =+BC2+1 -> 11 | BE2: =+BD2+1 -> 12 | BF2: =+BE2+1 -> 13 | BG2: =+BF2+1 -> 14 | BH2: =+BG2+1 -> 15 | BI2: =+BH2+1 -> 16 | BJ2: =+BI2+1 -> 17 | ... CX2: =+CW2+1 -> 57
A3: Months | B3: =HAVERD!I$2 -> Overnight | C3: =HAVERD!J$2 -> 1 | D3: =HAVERD!K$2 -> 2 | E3: =HAVERD!L$2 -> 3 | F3: =HAVERD!M$2 -> 4 | G3: =HAVERD!N$2 -> 5 | H3: =HAVERD!O$2 -> 6 | I3: =HAVERD!P$2 -> 7 | ... AX3: =HAVERD!BE$2 -> 48 | BA3: Months | BB3: =HAVERD!I$2 -> Overnight | BC3: =HAVERD!J$2 -> 1 | BD3: =HAVERD!K$2 -> 2 | BE3: =HAVERD!L$2 -> 3 | BF3: =HAVERD!M$2 -> 4 | BG3: =HAVERD!N$2 -> 5 | BH3: =HAVERD!O$2 -> 6 | BI3: =HAVERD!P$2 -> 7 | ... CX3: =HAVERD!BE$2 -> 48
A4: Days | C4: 30.416667 | D4: =+C4+30.4166667 -> 60.833333 | E4: =+D4+30.4166667 -> 91.25 | F4: =+E4+30.4166667 -> 121.66667 | G4: =+F4+30.4166667 -> 152.08333 | H4: =+G4+30.4166667 -> 182.5 | I4: =+H4+30.4166667 -> 212.91667 | J4: =+I4+30.4166667 -> 243.33333 | K4: =+J4+30.4166667 -> 273.75 | ... AX4: =+AW4+30.4166667 -> 1460 | BA4: Days | BC4: 30.416667 | BD4: =+BC4+30.4166667 -> 60.833333 | BE4: =+BD4+30.4166667 -> 91.25 | BF4: =+BE4+30.4166667 -> 121.66667 | BG4: =+BF4+30.4166667 -> 152.08333 | BH4: =+BG4+30.4166667 -> 182.5 | BI4: =+BH4+30.4166667 -> 212.91667 | BJ4: =+BI4+30.4166667 -> 243.33333 | BK4: =+BJ4+30.4166667 -> 273.75 | ... CX4: =+CW4+30.4166667 -> 1460
A5: Dates | BA5: Dates
A6: =A11-7 -> 46114 | B6: =A6 -> 46114 | C6: =$B6+C$4 -> 46144.417 | D6: =$B6+D$4 -> 46174.833 | E6: =$B6+E$4 -> 46205.25 | F6: =$B6+F$4 -> 46235.667 | G6: =$B6+G$4 -> 46266.083 | H6: =$B6+H$4 -> 46296.5 | I6: =$B6+I$4 -> 46326.917 | J6: =$B6+J$4 -> 46357.333 | ... AX6: =$B6+AX$4 -> 47574 | BA6: =BA11-7 -> 46171 | BB6: =BA6 -> 46171 | BC6: =$BA6+BC$4 -> 46201.417 | BD6: =$BA6+BD$4 -> 46231.833 | BE6: =$BA6+BE$4 -> 46262.25 | BF6: =$BA6+BF$4 -> 46292.667 | BG6: =$BA6+BG$4 -> 46323.083 | BH6: =$BA6+BH$4 -> 46353.5 | BI6: =$BA6+BI$4 -> 46383.917 | BJ6: =$BA6+BJ$4 -> 46414.333 | ... CX6: =$BA6+CX$4 -> 47631
A7: =A12-7 -> 46115 | B7: =A7 -> 46115 | C7: =$B7+C$4 -> 46145.417 | D7: =$B7+D$4 -> 46175.833 | E7: =$B7+E$4 -> 46206.25 | F7: =$B7+F$4 -> 46236.667 | G7: =$B7+G$4 -> 46267.083 | H7: =$B7+H$4 -> 46297.5 | I7: =$B7+I$4 -> 46327.917 | J7: =$B7+J$4 -> 46358.333 | ... AX7: =$B7+AX$4 -> 47575 | BA7: =BA12-7 -> 46174 | BB7: =BA7 -> 46174 | BC7: =$BA7+BC$4 -> 46204.417 | BD7: =$BA7+BD$4 -> 46234.833 | BE7: =$BA7+BE$4 -> 46265.25 | BF7: =$BA7+BF$4 -> 46295.667 | BG7: =$BA7+BG$4 -> 46326.083 | BH7: =$BA7+BH$4 -> 46356.5 | BI7: =$BA7+BI$4 -> 46386.917 | BJ7: =$BA7+BJ$4 -> 46417.333 | ... CX7: =$BA7+CX$4 -> 47634
A8: =A13-7 -> 46118 | B8: =A8 -> 46118 | C8: =$B8+C$4 -> 46148.417 | D8: =$B8+D$4 -> 46178.833 | E8: =$B8+E$4 -> 46209.25 | F8: =$B8+F$4 -> 46239.667 | G8: =$B8+G$4 -> 46270.083 | H8: =$B8+H$4 -> 46300.5 | I8: =$B8+I$4 -> 46330.917 | J8: =$B8+J$4 -> 46361.333 | ... AX8: =$B8+AX$4 -> 47578 | BA8: =BA13-7 -> 46175 | BB8: =BA8 -> 46175 | BC8: =$BA8+BC$4 -> 46205.417 | BD8: =$BA8+BD$4 -> 46235.833 | BE8: =$BA8+BE$4 -> 46266.25 | BF8: =$BA8+BF$4 -> 46296.667 | BG8: =$BA8+BG$4 -> 46327.083 | BH8: =$BA8+BH$4 -> 46357.5 | BI8: =$BA8+BI$4 -> 46387.917 | BJ8: =$BA8+BJ$4 -> 46418.333 | ... CX8: =$BA8+CX$4 -> 47635
A9: =A14-7 -> 46119 | B9: =A9 -> 46119 | C9: =$B9+C$4 -> 46149.417 | D9: =$B9+D$4 -> 46179.833 | E9: =$B9+E$4 -> 46210.25 | F9: =$B9+F$4 -> 46240.667 | G9: =$B9+G$4 -> 46271.083 | H9: =$B9+H$4 -> 46301.5 | I9: =$B9+I$4 -> 46331.917 | J9: =$B9+J$4 -> 46362.333 | ... AX9: =$B9+AX$4 -> 47579 | BA9: =BA14-7 -> 46176 | BB9: =BA9 -> 46176 | BC9: =$BA9+BC$4 -> 46206.417 | BD9: =$BA9+BD$4 -> 46236.833 | BE9: =$BA9+BE$4 -> 46267.25 | BF9: =$BA9+BF$4 -> 46297.667 | BG9: =$BA9+BG$4 -> 46328.083 | BH9: =$BA9+BH$4 -> 46358.5 | BI9: =$BA9+BI$4 -> 46388.917 | BJ9: =$BA9+BJ$4 -> 46419.333 | ... CX9: =$BA9+CX$4 -> 47636
A10: =A15-7 -> 46120 | B10: =A10 -> 46120 | C10: =$B10+C$4 -> 46150.417 | D10: =$B10+D$4 -> 46180.833 | E10: =$B10+E$4 -> 46211.25 | F10: =$B10+F$4 -> 46241.667 | G10: =$B10+G$4 -> 46272.083 | H10: =$B10+H$4 -> 46302.5 | I10: =$B10+I$4 -> 46332.917 | J10: =$B10+J$4 -> 46363.333 | ... AX10: =$B10+AX$4 -> 47580 | BA10: =BA15-7 -> 46177 | BB10: =BA10 -> 46177 | BC10: =$BA10+BC$4 -> 46207.417 | BD10: =$BA10+BD$4 -> 46237.833 | BE10: =$BA10+BE$4 -> 46268.25 | BF10: =$BA10+BF$4 -> 46298.667 | BG10: =$BA10+BG$4 -> 46329.083 | BH10: =$BA10+BH$4 -> 46359.5 | BI10: =$BA10+BI$4 -> 46389.917 | BJ10: =$BA10+BJ$4 -> 46420.333 | ... CX10: =$BA10+CX$4 -> 47637
A11: =A16-7 -> 46121 | B11: =A11 -> 46121 | C11: =$B11+C$4 -> 46151.417 | D11: =$B11+D$4 -> 46181.833 | E11: =$B11+E$4 -> 46212.25 | F11: =$B11+F$4 -> 46242.667 | G11: =$B11+G$4 -> 46273.083 | H11: =$B11+H$4 -> 46303.5 | I11: =$B11+I$4 -> 46333.917 | J11: =$B11+J$4 -> 46364.333 | ... AX11: =$B11+AX$4 -> 47581 | BA11: =BA16-7 -> 46178 | BB11: =BA11 -> 46178 | BC11: =$BA11+BC$4 -> 46208.417 | BD11: =$BA11+BD$4 -> 46238.833 | BE11: =$BA11+BE$4 -> 46269.25 | BF11: =$BA11+BF$4 -> 46299.667 | BG11: =$BA11+BG$4 -> 46330.083 | BH11: =$BA11+BH$4 -> 46360.5 | BI11: =$BA11+BI$4 -> 46390.917 | BJ11: =$BA11+BJ$4 -> 46421.333 | ... CX11: =$BA11+CX$4 -> 47638
A12: =A17-7 -> 46122 | B12: =A12 -> 46122 | C12: =$B12+C$4 -> 46152.417 | D12: =$B12+D$4 -> 46182.833 | E12: =$B12+E$4 -> 46213.25 | F12: =$B12+F$4 -> 46243.667 | G12: =$B12+G$4 -> 46274.083 | H12: =$B12+H$4 -> 46304.5 | I12: =$B12+I$4 -> 46334.917 | J12: =$B12+J$4 -> 46365.333 | ... AX12: =$B12+AX$4 -> 47582 | BA12: =BA17-7 -> 46181 | BB12: =BA12 -> 46181 | BC12: =$BA12+BC$4 -> 46211.417 | BD12: =$BA12+BD$4 -> 46241.833 | BE12: =$BA12+BE$4 -> 46272.25 | BF12: =$BA12+BF$4 -> 46302.667 | BG12: =$BA12+BG$4 -> 46333.083 | BH12: =$BA12+BH$4 -> 46363.5 | BI12: =$BA12+BI$4 -> 46393.917 | BJ12: =$BA12+BJ$4 -> 46424.333 | ... CX12: =$BA12+CX$4 -> 47641
A13: =A18-7 -> 46125 | B13: =A13 -> 46125 | C13: =$B13+C$4 -> 46155.417 | D13: =$B13+D$4 -> 46185.833 | E13: =$B13+E$4 -> 46216.25 | F13: =$B13+F$4 -> 46246.667 | G13: =$B13+G$4 -> 46277.083 | H13: =$B13+H$4 -> 46307.5 | I13: =$B13+I$4 -> 46337.917 | J13: =$B13+J$4 -> 46368.333 | ... AX13: =$B13+AX$4 -> 47585 | BA13: =BA18-7 -> 46182 | BB13: =BA13 -> 46182 | BC13: =$BA13+BC$4 -> 46212.417 | BD13: =$BA13+BD$4 -> 46242.833 | BE13: =$BA13+BE$4 -> 46273.25 | BF13: =$BA13+BF$4 -> 46303.667 | BG13: =$BA13+BG$4 -> 46334.083 | BH13: =$BA13+BH$4 -> 46364.5 | BI13: =$BA13+BI$4 -> 46394.917 | BJ13: =$BA13+BJ$4 -> 46425.333 | ... CX13: =$BA13+CX$4 -> 47642
A14: =A19-7 -> 46126 | B14: =A14 -> 46126 | C14: =$B14+C$4 -> 46156.417 | D14: =$B14+D$4 -> 46186.833 | E14: =$B14+E$4 -> 46217.25 | F14: =$B14+F$4 -> 46247.667 | G14: =$B14+G$4 -> 46278.083 | H14: =$B14+H$4 -> 46308.5 | I14: =$B14+I$4 -> 46338.917 | J14: =$B14+J$4 -> 46369.333 | ... AX14: =$B14+AX$4 -> 47586 | BA14: =BA19-7 -> 46183 | BB14: =BA14 -> 46183 | BC14: =$BA14+BC$4 -> 46213.417 | BD14: =$BA14+BD$4 -> 46243.833 | BE14: =$BA14+BE$4 -> 46274.25 | BF14: =$BA14+BF$4 -> 46304.667 | BG14: =$BA14+BG$4 -> 46335.083 | BH14: =$BA14+BH$4 -> 46365.5 | BI14: =$BA14+BI$4 -> 46395.917 | BJ14: =$BA14+BJ$4 -> 46426.333 | ... CX14: =$BA14+CX$4 -> 47643
A15: =A20-7 -> 46127 | B15: =A15 -> 46127 | C15: =$B15+C$4 -> 46157.417 | D15: =$B15+D$4 -> 46187.833 | E15: =$B15+E$4 -> 46218.25 | F15: =$B15+F$4 -> 46248.667 | G15: =$B15+G$4 -> 46279.083 | H15: =$B15+H$4 -> 46309.5 | I15: =$B15+I$4 -> 46339.917 | J15: =$B15+J$4 -> 46370.333 | ... AX15: =$B15+AX$4 -> 47587 | BA15: =BA20-7 -> 46184 | BB15: =BA15 -> 46184 | BC15: =$BA15+BC$4 -> 46214.417 | BD15: =$BA15+BD$4 -> 46244.833 | BE15: =$BA15+BE$4 -> 46275.25 | BF15: =$BA15+BF$4 -> 46305.667 | BG15: =$BA15+BG$4 -> 46336.083 | BH15: =$BA15+BH$4 -> 46366.5 | BI15: =$BA15+BI$4 -> 46396.917 | BJ15: =$BA15+BJ$4 -> 46427.333 | ... CX15: =$BA15+CX$4 -> 47644
A16: ='Market pricing dates'!B5 -> 46128 | B16: =A16 -> 46128 | C16: =$B16+C$4 -> 46158.417 | D16: =$B16+D$4 -> 46188.833 | E16: =$B16+E$4 -> 46219.25 | F16: =$B16+F$4 -> 46249.667 | G16: =$B16+G$4 -> 46280.083 | H16: =$B16+H$4 -> 46310.5 | I16: =$B16+I$4 -> 46340.917 | J16: =$B16+J$4 -> 46371.333 | ... AX16: =$B16+AX$4 -> 47588 | BA16: ='Market pricing dates'!E5 -> 46185 | BB16: =BA16 -> 46185 | BC16: =$BA16+BC$4 -> 46215.417 | BD16: =$BA16+BD$4 -> 46245.833 | BE16: =$BA16+BE$4 -> 46276.25 | BF16: =$BA16+BF$4 -> 46306.667 | BG16: =$BA16+BG$4 -> 46337.083 | BH16: =$BA16+BH$4 -> 46367.5 | BI16: =$BA16+BI$4 -> 46397.917 | BJ16: =$BA16+BJ$4 -> 46428.333 | ... CX16: =$BA16+CX$4 -> 47645
A17: ='Market pricing dates'!B6 -> 46129 | B17: =A17 -> 46129 | C17: =$B17+C$4 -> 46159.417 | D17: =$B17+D$4 -> 46189.833 | E17: =$B17+E$4 -> 46220.25 | F17: =$B17+F$4 -> 46250.667 | G17: =$B17+G$4 -> 46281.083 | H17: =$B17+H$4 -> 46311.5 | I17: =$B17+I$4 -> 46341.917 | J17: =$B17+J$4 -> 46372.333 | ... AX17: =$B17+AX$4 -> 47589 | BA17: ='Market pricing dates'!E6 -> 46188 | BB17: =BA17 -> 46188 | BC17: =$BA17+BC$4 -> 46218.417 | BD17: =$BA17+BD$4 -> 46248.833 | BE17: =$BA17+BE$4 -> 46279.25 | BF17: =$BA17+BF$4 -> 46309.667 | BG17: =$BA17+BG$4 -> 46340.083 | BH17: =$BA17+BH$4 -> 46370.5 | BI17: =$BA17+BI$4 -> 46400.917 | BJ17: =$BA17+BJ$4 -> 46431.333 | ... CX17: =$BA17+CX$4 -> 47648
A18: ='Market pricing dates'!B7 -> 46132 | B18: =A18 -> 46132 | C18: =$B18+C$4 -> 46162.417 | D18: =$B18+D$4 -> 46192.833 | E18: =$B18+E$4 -> 46223.25 | F18: =$B18+F$4 -> 46253.667 | G18: =$B18+G$4 -> 46284.083 | H18: =$B18+H$4 -> 46314.5 | I18: =$B18+I$4 -> 46344.917 | J18: =$B18+J$4 -> 46375.333 | ... AX18: =$B18+AX$4 -> 47592 | BA18: ='Market pricing dates'!E7 -> 46189 | BB18: =BA18 -> 46189 | BC18: =$BA18+BC$4 -> 46219.417 | BD18: =$BA18+BD$4 -> 46249.833 | BE18: =$BA18+BE$4 -> 46280.25 | BF18: =$BA18+BF$4 -> 46310.667 | BG18: =$BA18+BG$4 -> 46341.083 | BH18: =$BA18+BH$4 -> 46371.5 | BI18: =$BA18+BI$4 -> 46401.917 | BJ18: =$BA18+BJ$4 -> 46432.333 | ... CX18: =$BA18+CX$4 -> 47649
A19: ='Market pricing dates'!B8 -> 46133 | B19: =A19 -> 46133 | C19: =$B19+C$4 -> 46163.417 | D19: =$B19+D$4 -> 46193.833 | E19: =$B19+E$4 -> 46224.25 | F19: =$B19+F$4 -> 46254.667 | G19: =$B19+G$4 -> 46285.083 | H19: =$B19+H$4 -> 46315.5 | I19: =$B19+I$4 -> 46345.917 | J19: =$B19+J$4 -> 46376.333 | ... AX19: =$B19+AX$4 -> 47593 | BA19: ='Market pricing dates'!E8 -> 46190 | BB19: =BA19 -> 46190 | BC19: =$BA19+BC$4 -> 46220.417 | BD19: =$BA19+BD$4 -> 46250.833 | BE19: =$BA19+BE$4 -> 46281.25 | BF19: =$BA19+BF$4 -> 46311.667 | BG19: =$BA19+BG$4 -> 46342.083 | BH19: =$BA19+BH$4 -> 46372.5 | BI19: =$BA19+BI$4 -> 46402.917 | BJ19: =$BA19+BJ$4 -> 46433.333 | ... CX19: =$BA19+CX$4 -> 47650
A20: ='Market pricing dates'!B9 -> 46134 | B20: =A20 -> 46134 | C20: =$B20+C$4 -> 46164.417 | D20: =$B20+D$4 -> 46194.833 | E20: =$B20+E$4 -> 46225.25 | F20: =$B20+F$4 -> 46255.667 | G20: =$B20+G$4 -> 46286.083 | H20: =$B20+H$4 -> 46316.5 | I20: =$B20+I$4 -> 46346.917 | J20: =$B20+J$4 -> 46377.333 | ... AX20: =$B20+AX$4 -> 47594 | BA20: ='Market pricing dates'!E9 -> 46191 | BB20: =BA20 -> 46191 | BC20: =$BA20+BC$4 -> 46221.417 | BD20: =$BA20+BD$4 -> 46251.833 | BE20: =$BA20+BE$4 -> 46282.25 | BF20: =$BA20+BF$4 -> 46312.667 | BG20: =$BA20+BG$4 -> 46343.083 | BH20: =$BA20+BH$4 -> 46373.5 | BI20: =$BA20+BI$4 -> 46403.917 | BJ20: =$BA20+BJ$4 -> 46434.333 | ... CX20: =$BA20+CX$4 -> 47651
A22: Market expectations | BA22: Market expectations
A23: =A6 -> 46114 | B23: =VLOOKUP($A23,HAVERD!$A:$BS,B$2,FALSE) -> 3.73 | C23: =VLOOKUP($A23,HAVERD!$A:$BS,C$2,FALSE) -> 3.753596 | D23: =VLOOKUP($A23,HAVERD!$A:$BS,D$2,FALSE) -> 3.8469902 | E23: =VLOOKUP($A23,HAVERD!$A:$BS,E$2,FALSE) -> 3.9435361 | F23: =VLOOKUP($A23,HAVERD!$A:$BS,F$2,FALSE) -> 4.0349473 | G23: =VLOOKUP($A23,HAVERD!$A:$BS,G$2,FALSE) -> 4.1107531 | H23: =VLOOKUP($A23,HAVERD!$A:$BS,H$2,FALSE) -> 4.1657421 | I23: =VLOOKUP($A23,HAVERD!$A:$BS,I$2,FALSE) -> 4.2050498 | ... AX23: =VLOOKUP($A23,HAVERD!$A:$BS,AX$2,FALSE) -> 4.0545917 | BA23: =BA6 -> 46171 | BB23: =_xlfn.IFNA(VLOOKUP($BA23,HAVERD!$A:$BS,BB$2,FALSE),"") -> 3.7302 | BC23: =_xlfn.IFNA(VLOOKUP($BA23,HAVERD!$A:$BS,BC$2,FALSE),"") -> 3.7243672 | BD23: =_xlfn.IFNA(VLOOKUP($BA23,HAVERD!$A:$BS,BD$2,FALSE),"") -> 3.7749219 | BE23: =_xlfn.IFNA(VLOOKUP($BA23,HAVERD!$A:$BS,BE$2,FALSE),"") -> 3.8312141 | BF23: =_xlfn.IFNA(VLOOKUP($BA23,HAVERD!$A:$BS,BF$2,FALSE),"") -> 3.8889022 | BG23: =_xlfn.IFNA(VLOOKUP($BA23,HAVERD!$A:$BS,BG$2,FALSE),"") -> 3.943111 | BH23: =_xlfn.IFNA(VLOOKUP($BA23,HAVERD!$A:$BS,BH$2,FALSE),"") -> 3.9896254 | BI23: =_xlfn.IFNA(VLOOKUP($BA23,HAVERD!$A:$BS,BI$2,FALSE),"") -> 4.0277688 | ... CX23: =_xlfn.IFNA(VLOOKUP($BA23,HAVERD!$A:$BS,CX$2,FALSE),"") -> 4.1525559
A24: =A7 -> 46115 | B24: =VLOOKUP($A24,HAVERD!$A:$BS,B$2,FALSE) -> #N/A | C24: =VLOOKUP($A24,HAVERD!$A:$BS,C$2,FALSE) -> #N/A | D24: =VLOOKUP($A24,HAVERD!$A:$BS,D$2,FALSE) -> #N/A | E24: =VLOOKUP($A24,HAVERD!$A:$BS,E$2,FALSE) -> #N/A | F24: =VLOOKUP($A24,HAVERD!$A:$BS,F$2,FALSE) -> #N/A | G24: =VLOOKUP($A24,HAVERD!$A:$BS,G$2,FALSE) -> #N/A | H24: =VLOOKUP($A24,HAVERD!$A:$BS,H$2,FALSE) -> #N/A | I24: =VLOOKUP($A24,HAVERD!$A:$BS,I$2,FALSE) -> #N/A | ... AX24: =VLOOKUP($A24,HAVERD!$A:$BS,AX$2,FALSE) -> #N/A | BA24: =BA7 -> 46174 | BB24: =_xlfn.IFNA(VLOOKUP($BA24,HAVERD!$A:$BS,BB$2,FALSE),"") -> 3.7291 | BC24: =_xlfn.IFNA(VLOOKUP($BA24,HAVERD!$A:$BS,BC$2,FALSE),"") -> 3.7269077 | BD24: =_xlfn.IFNA(VLOOKUP($BA24,HAVERD!$A:$BS,BD$2,FALSE),"") -> 3.7962168 | BE24: =_xlfn.IFNA(VLOOKUP($BA24,HAVERD!$A:$BS,BE$2,FALSE),"") -> 3.8711315 | BF24: =_xlfn.IFNA(VLOOKUP($BA24,HAVERD!$A:$BS,BF$2,FALSE),"") -> 3.9489032 | BG24: =_xlfn.IFNA(VLOOKUP($BA24,HAVERD!$A:$BS,BG$2,FALSE),"") -> 4.0255473 | BH24: =_xlfn.IFNA(VLOOKUP($BA24,HAVERD!$A:$BS,BH$2,FALSE),"") -> 4.0943756 | BI24: =_xlfn.IFNA(VLOOKUP($BA24,HAVERD!$A:$BS,BI$2,FALSE),"") -> 4.1529887 | ... CX24: =_xlfn.IFNA(VLOOKUP($BA24,HAVERD!$A:$BS,CX$2,FALSE),"") -> 4.1730915
A25: =A8 -> 46118 | B25: =VLOOKUP($A25,HAVERD!$A:$BS,B$2,FALSE) -> #N/A | C25: =VLOOKUP($A25,HAVERD!$A:$BS,C$2,FALSE) -> #N/A | D25: =VLOOKUP($A25,HAVERD!$A:$BS,D$2,FALSE) -> #N/A | E25: =VLOOKUP($A25,HAVERD!$A:$BS,E$2,FALSE) -> #N/A | F25: =VLOOKUP($A25,HAVERD!$A:$BS,F$2,FALSE) -> #N/A | G25: =VLOOKUP($A25,HAVERD!$A:$BS,G$2,FALSE) -> #N/A | H25: =VLOOKUP($A25,HAVERD!$A:$BS,H$2,FALSE) -> #N/A | I25: =VLOOKUP($A25,HAVERD!$A:$BS,I$2,FALSE) -> #N/A | ... AX25: =VLOOKUP($A25,HAVERD!$A:$BS,AX$2,FALSE) -> #N/A | BA25: =BA8 -> 46175 | BB25: =_xlfn.IFNA(VLOOKUP($BA25,HAVERD!$A:$BS,BB$2,FALSE),"") -> 3.7308 | BC25: =_xlfn.IFNA(VLOOKUP($BA25,HAVERD!$A:$BS,BC$2,FALSE),"") -> 3.7471876 | BD25: =_xlfn.IFNA(VLOOKUP($BA25,HAVERD!$A:$BS,BD$2,FALSE),"") -> 3.8232402 | BE25: =_xlfn.IFNA(VLOOKUP($BA25,HAVERD!$A:$BS,BE$2,FALSE),"") -> 3.9025245 | BF25: =_xlfn.IFNA(VLOOKUP($BA25,HAVERD!$A:$BS,BF$2,FALSE),"") -> 3.9810069 | BG25: =_xlfn.IFNA(VLOOKUP($BA25,HAVERD!$A:$BS,BG$2,FALSE),"") -> 4.0551904 | BH25: =_xlfn.IFNA(VLOOKUP($BA25,HAVERD!$A:$BS,BH$2,FALSE),"") -> 4.1202376 | BI25: =_xlfn.IFNA(VLOOKUP($BA25,HAVERD!$A:$BS,BI$2,FALSE),"") -> 4.1750159 | ... CX25: =_xlfn.IFNA(VLOOKUP($BA25,HAVERD!$A:$BS,CX$2,FALSE),"") -> 4.1599836
A26: =A9 -> 46119 | B26: =VLOOKUP($A26,HAVERD!$A:$BS,B$2,FALSE) -> 3.7294 | C26: =VLOOKUP($A26,HAVERD!$A:$BS,C$2,FALSE) -> 3.776504 | D26: =VLOOKUP($A26,HAVERD!$A:$BS,D$2,FALSE) -> 3.8867149 | E26: =VLOOKUP($A26,HAVERD!$A:$BS,E$2,FALSE) -> 3.9978867 | F26: =VLOOKUP($A26,HAVERD!$A:$BS,F$2,FALSE) -> 4.1000884 | G26: =VLOOKUP($A26,HAVERD!$A:$BS,G$2,FALSE) -> 4.1832075 | H26: =VLOOKUP($A26,HAVERD!$A:$BS,H$2,FALSE) -> 4.2431025 | I26: =VLOOKUP($A26,HAVERD!$A:$BS,I$2,FALSE) -> 4.2850013 | ... AX26: =VLOOKUP($A26,HAVERD!$A:$BS,AX$2,FALSE) -> 4.0950511 | BA26: =BA9 -> 46176 | BB26: =_xlfn.IFNA(VLOOKUP($BA26,HAVERD!$A:$BS,BB$2,FALSE),"") -> 3.7306 | BC26: =_xlfn.IFNA(VLOOKUP($BA26,HAVERD!$A:$BS,BC$2,FALSE),"") -> 3.7352615 | BD26: =_xlfn.IFNA(VLOOKUP($BA26,HAVERD!$A:$BS,BD$2,FALSE),"") -> 3.8189074 | BE26: =_xlfn.IFNA(VLOOKUP($BA26,HAVERD!$A:$BS,BE$2,FALSE),"") -> 3.9058851 | BF26: =_xlfn.IFNA(VLOOKUP($BA26,HAVERD!$A:$BS,BF$2,FALSE),"") -> 3.9920061 | BG26: =_xlfn.IFNA(VLOOKUP($BA26,HAVERD!$A:$BS,BG$2,FALSE),"") -> 4.0733447 | BH26: =_xlfn.IFNA(VLOOKUP($BA26,HAVERD!$A:$BS,BH$2,FALSE),"") -> 4.1445301 | BI26: =_xlfn.IFNA(VLOOKUP($BA26,HAVERD!$A:$BS,BI$2,FALSE),"") -> 4.2046457 | ... CX26: =_xlfn.IFNA(VLOOKUP($BA26,HAVERD!$A:$BS,CX$2,FALSE),"") -> 4.2353862
A27: =A10 -> 46120 | B27: =VLOOKUP($A27,HAVERD!$A:$BS,B$2,FALSE) -> 3.7287 | C27: =VLOOKUP($A27,HAVERD!$A:$BS,C$2,FALSE) -> 3.7402463 | D27: =VLOOKUP($A27,HAVERD!$A:$BS,D$2,FALSE) -> 3.8095213 | E27: =VLOOKUP($A27,HAVERD!$A:$BS,E$2,FALSE) -> 3.8771332 | F27: =VLOOKUP($A27,HAVERD!$A:$BS,F$2,FALSE) -> 3.9363881 | G27: =VLOOKUP($A27,HAVERD!$A:$BS,G$2,FALSE) -> 3.9822784 | H27: =VLOOKUP($A27,HAVERD!$A:$BS,H$2,FALSE) -> 4.0134826 | I27: =VLOOKUP($A27,HAVERD!$A:$BS,I$2,FALSE) -> 4.0343722 | ... AX27: =VLOOKUP($A27,HAVERD!$A:$BS,AX$2,FALSE) -> 3.9784106 | BA27: =BA10 -> 46177 | BB27: =_xlfn.IFNA(VLOOKUP($BA27,HAVERD!$A:$BS,BB$2,FALSE),"") -> 3.7308 | BC27: =_xlfn.IFNA(VLOOKUP($BA27,HAVERD!$A:$BS,BC$2,FALSE),"") -> 3.7353573 | BD27: =_xlfn.IFNA(VLOOKUP($BA27,HAVERD!$A:$BS,BD$2,FALSE),"") -> 3.8070084 | BE27: =_xlfn.IFNA(VLOOKUP($BA27,HAVERD!$A:$BS,BE$2,FALSE),"") -> 3.8816702 | BF27: =_xlfn.IFNA(VLOOKUP($BA27,HAVERD!$A:$BS,BF$2,FALSE),"") -> 3.956035 | BG27: =_xlfn.IFNA(VLOOKUP($BA27,HAVERD!$A:$BS,BG$2,FALSE),"") -> 4.0268347 | BH27: =_xlfn.IFNA(VLOOKUP($BA27,HAVERD!$A:$BS,BH$2,FALSE),"") -> 4.0893185 | BI27: =_xlfn.IFNA(VLOOKUP($BA27,HAVERD!$A:$BS,BI$2,FALSE),"") -> 4.1425209 | ... CX27: =_xlfn.IFNA(VLOOKUP($BA27,HAVERD!$A:$BS,CX$2,FALSE),"") -> 4.2138887
A28: =A11 -> 46121 | B28: =VLOOKUP($A28,HAVERD!$A:$BS,B$2,FALSE) -> 3.7294 | C28: =VLOOKUP($A28,HAVERD!$A:$BS,C$2,FALSE) -> 3.7487877 | D28: =VLOOKUP($A28,HAVERD!$A:$BS,D$2,FALSE) -> 3.811008 | E28: =VLOOKUP($A28,HAVERD!$A:$BS,E$2,FALSE) -> 3.8765784 | F28: =VLOOKUP($A28,HAVERD!$A:$BS,F$2,FALSE) -> 3.9370481 | G28: =VLOOKUP($A28,HAVERD!$A:$BS,G$2,FALSE) -> 3.985479 | H28: =VLOOKUP($A28,HAVERD!$A:$BS,H$2,FALSE) -> 4.0194081 | I28: =VLOOKUP($A28,HAVERD!$A:$BS,I$2,FALSE) -> 4.0426574 | ... AX28: =VLOOKUP($A28,HAVERD!$A:$BS,AX$2,FALSE) -> 4.0423239 | BA28: =BA11 -> 46178 | BB28: =_xlfn.IFNA(VLOOKUP($BA28,HAVERD!$A:$BS,BB$2,FALSE),"") -> 3.7312 | BC28: =_xlfn.IFNA(VLOOKUP($BA28,HAVERD!$A:$BS,BC$2,FALSE),"") -> 3.7290185 | BD28: =_xlfn.IFNA(VLOOKUP($BA28,HAVERD!$A:$BS,BD$2,FALSE),"") -> 3.8007483 | BE28: =_xlfn.IFNA(VLOOKUP($BA28,HAVERD!$A:$BS,BE$2,FALSE),"") -> 3.8776733 | BF28: =_xlfn.IFNA(VLOOKUP($BA28,HAVERD!$A:$BS,BF$2,FALSE),"") -> 3.9566784 | BG28: =_xlfn.IFNA(VLOOKUP($BA28,HAVERD!$A:$BS,BG$2,FALSE),"") -> 4.0331583 | BH28: =_xlfn.IFNA(VLOOKUP($BA28,HAVERD!$A:$BS,BH$2,FALSE),"") -> 4.1013572 | BI28: =_xlfn.IFNA(VLOOKUP($BA28,HAVERD!$A:$BS,BI$2,FALSE),"") -> 4.1588616 | ... CX28: =_xlfn.IFNA(VLOOKUP($BA28,HAVERD!$A:$BS,CX$2,FALSE),"") -> 4.1971503
A29: =A12 -> 46122 | B29: =VLOOKUP($A29,HAVERD!$A:$BS,B$2,FALSE) -> 3.7295 | C29: =VLOOKUP($A29,HAVERD!$A:$BS,C$2,FALSE) -> 3.7502304 | D29: =VLOOKUP($A29,HAVERD!$A:$BS,D$2,FALSE) -> 3.830629 | E29: =VLOOKUP($A29,HAVERD!$A:$BS,E$2,FALSE) -> 3.9132973 | F29: =VLOOKUP($A29,HAVERD!$A:$BS,F$2,FALSE) -> 3.9903314 | G29: =VLOOKUP($A29,HAVERD!$A:$BS,G$2,FALSE) -> 4.0546617 | H29: =VLOOKUP($A29,HAVERD!$A:$BS,H$2,FALSE) -> 4.103157 | I29: =VLOOKUP($A29,HAVERD!$A:$BS,I$2,FALSE) -> 4.1378236 | ... AX29: =VLOOKUP($A29,HAVERD!$A:$BS,AX$2,FALSE) -> 4.1206281 | BA29: =BA12 -> 46181 | BB29: =_xlfn.IFNA(VLOOKUP($BA29,HAVERD!$A:$BS,BB$2,FALSE),"") -> 3.73 | BC29: =_xlfn.IFNA(VLOOKUP($BA29,HAVERD!$A:$BS,BC$2,FALSE),"") -> 3.7428238 | BD29: =_xlfn.IFNA(VLOOKUP($BA29,HAVERD!$A:$BS,BD$2,FALSE),"") -> 3.8224712 | BE29: =_xlfn.IFNA(VLOOKUP($BA29,HAVERD!$A:$BS,BE$2,FALSE),"") -> 3.9089257 | BF29: =_xlfn.IFNA(VLOOKUP($BA29,HAVERD!$A:$BS,BF$2,FALSE),"") -> 3.9978099 | BG29: =_xlfn.IFNA(VLOOKUP($BA29,HAVERD!$A:$BS,BG$2,FALSE),"") -> 4.0822041 | BH29: =_xlfn.IFNA(VLOOKUP($BA29,HAVERD!$A:$BS,BH$2,FALSE),"") -> 4.1553974 | BI29: =_xlfn.IFNA(VLOOKUP($BA29,HAVERD!$A:$BS,BI$2,FALSE),"") -> 4.2169744 | ... CX29: =_xlfn.IFNA(VLOOKUP($BA29,HAVERD!$A:$BS,CX$2,FALSE),"") -> 4.2555311
A30: =A13 -> 46125 | B30: =VLOOKUP($A30,HAVERD!$A:$BS,B$2,FALSE) -> 3.729 | C30: =VLOOKUP($A30,HAVERD!$A:$BS,C$2,FALSE) -> 3.7481536 | D30: =VLOOKUP($A30,HAVERD!$A:$BS,D$2,FALSE) -> 3.8370223 | E30: =VLOOKUP($A30,HAVERD!$A:$BS,E$2,FALSE) -> 3.9245377 | F30: =VLOOKUP($A30,HAVERD!$A:$BS,F$2,FALSE) -> 4.0031863 | G30: =VLOOKUP($A30,HAVERD!$A:$BS,G$2,FALSE) -> 4.0679999 | H30: =VLOOKUP($A30,HAVERD!$A:$BS,H$2,FALSE) -> 4.1168948 | I30: =VLOOKUP($A30,HAVERD!$A:$BS,I$2,FALSE) -> 4.1529051 | ... AX30: =VLOOKUP($A30,HAVERD!$A:$BS,AX$2,FALSE) -> 4.0898479 | BA30: =BA13 -> 46182 | BB30: =_xlfn.IFNA(VLOOKUP($BA30,HAVERD!$A:$BS,BB$2,FALSE),"") -> 3.7271 | BC30: =_xlfn.IFNA(VLOOKUP($BA30,HAVERD!$A:$BS,BC$2,FALSE),"") -> 3.7368599 | BD30: =_xlfn.IFNA(VLOOKUP($BA30,HAVERD!$A:$BS,BD$2,FALSE),"") -> 3.8179602 | BE30: =_xlfn.IFNA(VLOOKUP($BA30,HAVERD!$A:$BS,BE$2,FALSE),"") -> 3.9003138 | BF30: =_xlfn.IFNA(VLOOKUP($BA30,HAVERD!$A:$BS,BF$2,FALSE),"") -> 3.9822958 | BG30: =_xlfn.IFNA(VLOOKUP($BA30,HAVERD!$A:$BS,BG$2,FALSE),"") -> 4.0596042 | BH30: =_xlfn.IFNA(VLOOKUP($BA30,HAVERD!$A:$BS,BH$2,FALSE),"") -> 4.1271486 | BI30: =_xlfn.IFNA(VLOOKUP($BA30,HAVERD!$A:$BS,BI$2,FALSE),"") -> 4.1841679 | ... CX30: =_xlfn.IFNA(VLOOKUP($BA30,HAVERD!$A:$BS,CX$2,FALSE),"") -> 4.2316097
A31: =A14 -> 46126 | B31: =VLOOKUP($A31,HAVERD!$A:$BS,B$2,FALSE) -> 3.7293 | C31: =VLOOKUP($A31,HAVERD!$A:$BS,C$2,FALSE) -> 3.7358759 | D31: =VLOOKUP($A31,HAVERD!$A:$BS,D$2,FALSE) -> 3.8031379 | E31: =VLOOKUP($A31,HAVERD!$A:$BS,E$2,FALSE) -> 3.8711445 | F31: =VLOOKUP($A31,HAVERD!$A:$BS,F$2,FALSE) -> 3.9338191 | G31: =VLOOKUP($A31,HAVERD!$A:$BS,G$2,FALSE) -> 3.9861966 | H31: =VLOOKUP($A31,HAVERD!$A:$BS,H$2,FALSE) -> 4.0254154 | I31: =VLOOKUP($A31,HAVERD!$A:$BS,I$2,FALSE) -> 4.0534884 | ... AX31: =VLOOKUP($A31,HAVERD!$A:$BS,AX$2,FALSE) -> 4.0330978 | BA31: =BA14 -> 46183 | BB31: =_xlfn.IFNA(VLOOKUP($BA31,HAVERD!$A:$BS,BB$2,FALSE),"") -> 3.7296 | BC31: =_xlfn.IFNA(VLOOKUP($BA31,HAVERD!$A:$BS,BC$2,FALSE),"") -> 3.7446605 | BD31: =_xlfn.IFNA(VLOOKUP($BA31,HAVERD!$A:$BS,BD$2,FALSE),"") -> 3.8247854 | BE31: =_xlfn.IFNA(VLOOKUP($BA31,HAVERD!$A:$BS,BE$2,FALSE),"") -> 3.9106343 | BF31: =_xlfn.IFNA(VLOOKUP($BA31,HAVERD!$A:$BS,BF$2,FALSE),"") -> 3.9984229 | BG31: =_xlfn.IFNA(VLOOKUP($BA31,HAVERD!$A:$BS,BG$2,FALSE),"") -> 4.0819715 | BH31: =_xlfn.IFNA(VLOOKUP($BA31,HAVERD!$A:$BS,BH$2,FALSE),"") -> 4.1549832 | BI31: =_xlfn.IFNA(VLOOKUP($BA31,HAVERD!$A:$BS,BI$2,FALSE),"") -> 4.2166663 | ... CX31: =_xlfn.IFNA(VLOOKUP($BA31,HAVERD!$A:$BS,CX$2,FALSE),"") -> 4.2737163
A32: =A15 -> 46127 | B32: =VLOOKUP($A32,HAVERD!$A:$BS,B$2,FALSE) -> 3.7301 | C32: =VLOOKUP($A32,HAVERD!$A:$BS,C$2,FALSE) -> 3.7369514 | D32: =VLOOKUP($A32,HAVERD!$A:$BS,D$2,FALSE) -> 3.8144355 | E32: =VLOOKUP($A32,HAVERD!$A:$BS,E$2,FALSE) -> 3.8916902 | F32: =VLOOKUP($A32,HAVERD!$A:$BS,F$2,FALSE) -> 3.9615144 | G32: =VLOOKUP($A32,HAVERD!$A:$BS,G$2,FALSE) -> 4.0188087 | H32: =VLOOKUP($A32,HAVERD!$A:$BS,H$2,FALSE) -> 4.060609 | I32: =VLOOKUP($A32,HAVERD!$A:$BS,I$2,FALSE) -> 4.0900153 | ... AX32: =VLOOKUP($A32,HAVERD!$A:$BS,AX$2,FALSE) -> 4.0897155 | BA32: =BA15 -> 46184 | BB32: =_xlfn.IFNA(VLOOKUP($BA32,HAVERD!$A:$BS,BB$2,FALSE),"") -> 3.7305 | BC32: =_xlfn.IFNA(VLOOKUP($BA32,HAVERD!$A:$BS,BC$2,FALSE),"") -> 3.7443846 | BD32: =_xlfn.IFNA(VLOOKUP($BA32,HAVERD!$A:$BS,BD$2,FALSE),"") -> 3.8200067 | BE32: =_xlfn.IFNA(VLOOKUP($BA32,HAVERD!$A:$BS,BE$2,FALSE),"") -> 3.8992982 | BF32: =_xlfn.IFNA(VLOOKUP($BA32,HAVERD!$A:$BS,BF$2,FALSE),"") -> 3.9800015 | BG32: =_xlfn.IFNA(VLOOKUP($BA32,HAVERD!$A:$BS,BG$2,FALSE),"") -> 4.0575952 | BH32: =_xlfn.IFNA(VLOOKUP($BA32,HAVERD!$A:$BS,BH$2,FALSE),"") -> 4.1269763 | BI32: =_xlfn.IFNA(VLOOKUP($BA32,HAVERD!$A:$BS,BI$2,FALSE),"") -> 4.1870788 | ... CX32: =_xlfn.IFNA(VLOOKUP($BA32,HAVERD!$A:$BS,CX$2,FALSE),"") -> 4.2422921
A33: =A16 -> 46128 | B33: =VLOOKUP($A33,HAVERD!$A:$BS,B$2,FALSE) -> 3.7301 | C33: =VLOOKUP($A33,HAVERD!$A:$BS,C$2,FALSE) -> 3.7265955 | D33: =VLOOKUP($A33,HAVERD!$A:$BS,D$2,FALSE) -> 3.7954942 | E33: =VLOOKUP($A33,HAVERD!$A:$BS,E$2,FALSE) -> 3.8670279 | F33: =VLOOKUP($A33,HAVERD!$A:$BS,F$2,FALSE) -> 3.9349254 | G33: =VLOOKUP($A33,HAVERD!$A:$BS,G$2,FALSE) -> 3.9935864 | H33: =VLOOKUP($A33,HAVERD!$A:$BS,H$2,FALSE) -> 4.0383784 | I33: =VLOOKUP($A33,HAVERD!$A:$BS,I$2,FALSE) -> 4.0707072 | ... AX33: =VLOOKUP($A33,HAVERD!$A:$BS,AX$2,FALSE) -> 4.1356946 | BA33: =BA16 -> 46185 | BB33: =_xlfn.IFNA(VLOOKUP($BA33,HAVERD!$A:$BS,BB$2,FALSE),"") -> 3.7301 | BC33: =_xlfn.IFNA(VLOOKUP($BA33,HAVERD!$A:$BS,BC$2,FALSE),"") -> 3.7380222 | BD33: =_xlfn.IFNA(VLOOKUP($BA33,HAVERD!$A:$BS,BD$2,FALSE),"") -> 3.7882469 | BE33: =_xlfn.IFNA(VLOOKUP($BA33,HAVERD!$A:$BS,BE$2,FALSE),"") -> 3.8427507 | BF33: =_xlfn.IFNA(VLOOKUP($BA33,HAVERD!$A:$BS,BF$2,FALSE),"") -> 3.9008583 | BG33: =_xlfn.IFNA(VLOOKUP($BA33,HAVERD!$A:$BS,BG$2,FALSE),"") -> 3.9590341 | BH33: =_xlfn.IFNA(VLOOKUP($BA33,HAVERD!$A:$BS,BH$2,FALSE),"") -> 4.0123088 | BI33: =_xlfn.IFNA(VLOOKUP($BA33,HAVERD!$A:$BS,BI$2,FALSE),"") -> 4.0579865 | ... CX33: =_xlfn.IFNA(VLOOKUP($BA33,HAVERD!$A:$BS,CX$2,FALSE),"") -> 4.1855202
A34: =A17 -> 46129 | B34: =VLOOKUP($A34,HAVERD!$A:$BS,B$2,FALSE) -> 3.73 | C34: =VLOOKUP($A34,HAVERD!$A:$BS,C$2,FALSE) -> 3.7258284 | D34: =VLOOKUP($A34,HAVERD!$A:$BS,D$2,FALSE) -> 3.7756703 | E34: =VLOOKUP($A34,HAVERD!$A:$BS,E$2,FALSE) -> 3.8267915 | F34: =VLOOKUP($A34,HAVERD!$A:$BS,F$2,FALSE) -> 3.8741249 | G34: =VLOOKUP($A34,HAVERD!$A:$BS,G$2,FALSE) -> 3.9129916 | H34: =VLOOKUP($A34,HAVERD!$A:$BS,H$2,FALSE) -> 3.940405 | I34: =VLOOKUP($A34,HAVERD!$A:$BS,I$2,FALSE) -> 3.9573621 | ... AX34: =VLOOKUP($A34,HAVERD!$A:$BS,AX$2,FALSE) -> 4.037443 | BA34: =BA17 -> 46188 | BB34: =_xlfn.IFNA(VLOOKUP($BA34,HAVERD!$A:$BS,BB$2,FALSE),"") -> 3.7296 | BC34: =_xlfn.IFNA(VLOOKUP($BA34,HAVERD!$A:$BS,BC$2,FALSE),"") -> 3.7425937 | BD34: =_xlfn.IFNA(VLOOKUP($BA34,HAVERD!$A:$BS,BD$2,FALSE),"") -> 3.7901022 | BE34: =_xlfn.IFNA(VLOOKUP($BA34,HAVERD!$A:$BS,BE$2,FALSE),"") -> 3.8404664 | BF34: =_xlfn.IFNA(VLOOKUP($BA34,HAVERD!$A:$BS,BF$2,FALSE),"") -> 3.892434 | BG34: =_xlfn.IFNA(VLOOKUP($BA34,HAVERD!$A:$BS,BG$2,FALSE),"") -> 3.9423885 | BH34: =_xlfn.IFNA(VLOOKUP($BA34,HAVERD!$A:$BS,BH$2,FALSE),"") -> 3.9865195 | BI34: =_xlfn.IFNA(VLOOKUP($BA34,HAVERD!$A:$BS,BI$2,FALSE),"") -> 4.0241474 | ... CX34: =_xlfn.IFNA(VLOOKUP($BA34,HAVERD!$A:$BS,CX$2,FALSE),"") -> 4.1586547
... A37: =A20 -> 46134 | B37: =VLOOKUP($A37,HAVERD!$A:$BS,B$2,FALSE) -> 3.7304 | C37: =VLOOKUP($A37,HAVERD!$A:$BS,C$2,FALSE) -> 3.7335917 | D37: =VLOOKUP($A37,HAVERD!$A:$BS,D$2,FALSE) -> 3.837642 | E37: =VLOOKUP($A37,HAVERD!$A:$BS,E$2,FALSE) -> 3.9403256 | F37: =VLOOKUP($A37,HAVERD!$A:$BS,F$2,FALSE) -> 4.0325264 | G37: =VLOOKUP($A37,HAVERD!$A:$BS,G$2,FALSE) -> 4.108257 | H37: =VLOOKUP($A37,HAVERD!$A:$BS,H$2,FALSE) -> 4.1645157 | I37: =VLOOKUP($A37,HAVERD!$A:$BS,I$2,FALSE) -> 4.2049943 | ... AX37: =VLOOKUP($A37,HAVERD!$A:$BS,AX$2,FALSE) -> 4.1491665 | BA37: =BA20 -> 46191 | BB37: =_xlfn.IFNA(VLOOKUP($BA37,HAVERD!$A:$BS,BB$2,FALSE),"") -> 3.7303 | BC37: =_xlfn.IFNA(VLOOKUP($BA37,HAVERD!$A:$BS,BC$2,FALSE),"") -> 3.7843215 | BD37: =_xlfn.IFNA(VLOOKUP($BA37,HAVERD!$A:$BS,BD$2,FALSE),"") -> 3.8144992 | BE37: =_xlfn.IFNA(VLOOKUP($BA37,HAVERD!$A:$BS,BE$2,FALSE),"") -> 3.831662 | BF37: =_xlfn.IFNA(VLOOKUP($BA37,HAVERD!$A:$BS,BF$2,FALSE),"") -> 3.8526144 | BG37: =_xlfn.IFNA(VLOOKUP($BA37,HAVERD!$A:$BS,BG$2,FALSE),"") -> 3.8943094 | BH37: =_xlfn.IFNA(VLOOKUP($BA37,HAVERD!$A:$BS,BH$2,FALSE),"") -> 3.9492534 | BI37: =_xlfn.IFNA(VLOOKUP($BA37,HAVERD!$A:$BS,BI$2,FALSE),"") -> 4.0036593 | ... CX37: =_xlfn.IFNA(VLOOKUP($BA37,HAVERD!$A:$BS,CX$2,FALSE),"") -> 4.0937068
A39: Average | BA39: Average
A40: Month | B40: =MONTH(B20) -> 4 | C40: =MONTH(C20) -> 5 | D40: =MONTH(D20) -> 6 | E40: =MONTH(E20) -> 7 | F40: =MONTH(F20) -> 8 | G40: =MONTH(G20) -> 9 | H40: =MONTH(H20) -> 10 | I40: =MONTH(I20) -> 11 | ... AX40: =MONTH(AX20) -> 4 | BA40: Month | BB40: =MONTH(BB18) -> 6 | BC40: =MONTH(BC18) -> 7 | BD40: =MONTH(BD18) -> 8 | BE40: =MONTH(BE18) -> 9 | BF40: =MONTH(BF18) -> 10 | BG40: =MONTH(BG18) -> 11 | BH40: =MONTH(BH18) -> 12 | BI40: =MONTH(BI18) -> 1 | ... CX40: =MONTH(CX18) -> 6
A41: Year | B41: =YEAR(B20) -> 2026 | C41: =YEAR(C20) -> 2026 | D41: =YEAR(D20) -> 2026 | E41: =YEAR(E20) -> 2026 | F41: =YEAR(F20) -> 2026 | G41: =YEAR(G20) -> 2026 | H41: =YEAR(H20) -> 2026 | I41: =YEAR(I20) -> 2026 | ... AX41: =YEAR(AX20) -> 2030 | BA41: Year | BB41: =YEAR(BB20) -> 2026 | BC41: =YEAR(BC20) -> 2026 | BD41: =YEAR(BD20) -> 2026 | BE41: =YEAR(BE20) -> 2026 | BF41: =YEAR(BF20) -> 2026 | BG41: =YEAR(BG20) -> 2026 | BH41: =YEAR(BH20) -> 2026 | BI41: =YEAR(BI20) -> 2027 | ... CX41: =YEAR(CX20) -> 2030
A42: YYYYMM | B42: =B41*100+B40 -> 202604 | C42: =C41*100+C40 -> 202605 | D42: =D41*100+D40 -> 202606 | E42: =E41*100+E40 -> 202607 | F42: =F41*100+F40 -> 202608 | G42: =G41*100+G40 -> 202609 | H42: =H41*100+H40 -> 202610 | I42: =I41*100+I40 -> 202611 | ... AX42: =AX41*100+AX40 -> 203004 | BA42: YYYYMM | BB42: =BB41*100+BB40 -> 202606 | BC42: =BC41*100+BC40 -> 202607 | BD42: =BD41*100+BD40 -> 202608 | BE42: =BE41*100+BE40 -> 202609 | BF42: =BF41*100+BF40 -> 202610 | BG42: =BG41*100+BG40 -> 202611 | BH42: =BH41*100+BH40 -> 202612 | BI42: =BI41*100+BI40 -> 202701 | ... CX42: =CX41*100+CX40 -> 203006
A43: Quarter | B43: =IF(B40<4,1,IF(B40<7,2,IF(B40<10,3,4))) -> 2 | C43: =IF(C40<4,1,IF(C40<7,2,IF(C40<10,3,4))) -> 2 | D43: =IF(D40<4,1,IF(D40<7,2,IF(D40<10,3,4))) -> 2 | E43: =IF(E40<4,1,IF(E40<7,2,IF(E40<10,3,4))) -> 3 | F43: =IF(F40<4,1,IF(F40<7,2,IF(F40<10,3,4))) -> 3 | G43: =IF(G40<4,1,IF(G40<7,2,IF(G40<10,3,4))) -> 3 | H43: =IF(H40<4,1,IF(H40<7,2,IF(H40<10,3,4))) -> 4 | I43: =IF(I40<4,1,IF(I40<7,2,IF(I40<10,3,4))) -> 4 | ... AX43: =IF(AX40<4,1,IF(AX40<7,2,IF(AX40<10,3,4))) -> 2 | BA43: Quarter | BB43: =IF(BB40<4,1,IF(BB40<7,2,IF(BB40<10,3,4))) -> 2 | BC43: =IF(BC40<4,1,IF(BC40<7,2,IF(BC40<10,3,4))) -> 3 | BD43: =IF(BD40<4,1,IF(BD40<7,2,IF(BD40<10,3,4))) -> 3 | BE43: =IF(BE40<4,1,IF(BE40<7,2,IF(BE40<10,3,4))) -> 3 | BF43: =IF(BF40<4,1,IF(BF40<7,2,IF(BF40<10,3,4))) -> 4 | BG43: =IF(BG40<4,1,IF(BG40<7,2,IF(BG40<10,3,4))) -> 4 | BH43: =IF(BH40<4,1,IF(BH40<7,2,IF(BH40<10,3,4))) -> 4 | BI43: =IF(BI40<4,1,IF(BI40<7,2,IF(BI40<10,3,4))) -> 1 | ... CX43: =IF(CX40<4,1,IF(CX40<7,2,IF(CX40<10,3,4))) -> 2
A44: YYYYQQ | B44: =B41*100+B43 -> 202602 | C44: =C41*100+C43 -> 202602 | D44: =D41*100+D43 -> 202602 | E44: =E41*100+E43 -> 202603 | F44: =F41*100+F43 -> 202603 | G44: =G41*100+G43 -> 202603 | H44: =H41*100+H43 -> 202604 | I44: =I41*100+I43 -> 202604 | ... AX44: =AX41*100+AX43 -> 203002 | BA44: YYYYQQ | BB44: =BB41*100+BB43 -> 202602 | BC44: =BC41*100+BC43 -> 202603 | BD44: =BD41*100+BD43 -> 202603 | BE44: =BE41*100+BE43 -> 202603 | BF44: =BF41*100+BF43 -> 202604 | BG44: =BG41*100+BG43 -> 202604 | BH44: =BH41*100+BH43 -> 202604 | BI44: =BI41*100+BI43 -> 202701 | ... CX44: =CX41*100+CX43 -> 203002
A45: Average | B45: =AVERAGE(B23:B37) -> #N/A | C45: =AVERAGE(C23:C37) -> #N/A | D45: =AVERAGE(D23:D37) -> #N/A | E45: =AVERAGE(E23:E37) -> #N/A | F45: =AVERAGE(F23:F37) -> #N/A | G45: =AVERAGE(G23:G37) -> #N/A | H45: =AVERAGE(H23:H37) -> #N/A | I45: =AVERAGE(I23:I37) -> #N/A | ... AX45: =AVERAGE(AX23:AX37) -> #N/A | BA45: Average | BB45: =AVERAGE(BB23:BB37) -> 3.73004 | BC45: =AVERAGE(BC23:BC37) -> 3.7402871 | BD45: =AVERAGE(BD23:BD37) -> 3.8040207 | BE45: =AVERAGE(BE23:BE37) -> 3.8709478 | BF45: =AVERAGE(BF23:BF37) -> 3.9395155 | BG45: =AVERAGE(BG23:BG37) -> 4.0066238 | BH45: =AVERAGE(BH23:BH37) -> 4.0669423 | BI45: =AVERAGE(BI23:BI37) -> 4.1184883 | ... CX45: =AVERAGE(CX23:CX37) -> 4.1831548
BA46: Latest | BB46: =BB37 -> 3.7303 | BC46: =BC37 -> 3.7843215 | BD46: =BD37 -> 3.8144992 | BE46: =BE37 -> 3.831662 | BF46: =BF37 -> 3.8526144 | BG46: =BG37 -> 3.8943094 | BH46: =BH37 -> 3.9492534 | BI46: =BI37 -> 4.0036593 | ... CX46: =CX37 -> 4.0937068
A48: Quarterly series | BA48: Quarterly series
B49: =B44 -> 202602 | C49: =IF(RIGHT(B49)="4",B49+97,B49+1) -> 202603 | D49: =IF(RIGHT(C49)="4",C49+97,C49+1) -> 202604 | E49: =IF(RIGHT(D49)="4",D49+97,D49+1) -> 202701 | F49: =IF(RIGHT(E49)="4",E49+97,E49+1) -> 202702 | G49: =IF(RIGHT(F49)="4",F49+97,F49+1) -> 202703 | H49: =IF(RIGHT(G49)="4",G49+97,G49+1) -> 202704 | I49: =IF(RIGHT(H49)="4",H49+97,H49+1) -> 202801 | J49: =IF(RIGHT(I49)="4",I49+97,I49+1) -> 202802 | ... R49: =IF(RIGHT(Q49)="4",Q49+97,Q49+1) -> 203002 | BB49: =BB44 -> 202602 | BC49: =IF(RIGHT(BB49)="4",BB49+97,BB49+1) -> 202603 | BD49: =IF(RIGHT(BC49)="4",BC49+97,BC49+1) -> 202604 | BE49: =IF(RIGHT(BD49)="4",BD49+97,BD49+1) -> 202701 | BF49: =IF(RIGHT(BE49)="4",BE49+97,BE49+1) -> 202702 | BG49: =IF(RIGHT(BF49)="4",BF49+97,BF49+1) -> 202703 | BH49: =IF(RIGHT(BG49)="4",BG49+97,BG49+1) -> 202704 | BI49: =IF(RIGHT(BH49)="4",BH49+97,BH49+1) -> 202801 | BJ49: =IF(RIGHT(BI49)="4",BI49+97,BI49+1) -> 202802 | ... BQ49: =IF(RIGHT(BP49)="4",BP49+97,BP49+1) -> 203001
A50: =A1 -> April 2026 MPR | B50: =AVERAGEIF($B$44:$AX$44,B49,$B$45:$AX$45) -> #N/A | C50: =AVERAGEIF($B$44:$AX$44,C49,$B$45:$AX$45) -> #N/A | D50: =AVERAGEIF($B$44:$AX$44,D49,$B$45:$AX$45) -> #N/A | E50: =AVERAGEIF($B$44:$AX$44,E49,$B$45:$AX$45) -> #N/A | F50: =AVERAGEIF($B$44:$AX$44,F49,$B$45:$AX$45) -> #N/A | G50: =AVERAGEIF($B$44:$AX$44,G49,$B$45:$AX$45) -> #N/A | H50: =AVERAGEIF($B$44:$AX$44,H49,$B$45:$AX$45) -> #N/A | I50: =AVERAGEIF($B$44:$AX$44,I49,$B$45:$AX$45) -> #N/A | ... R50: =AVERAGEIF($B$44:$AX$44,R49,$B$45:$AX$45) -> #N/A | BA50: =BA1 -> Current market curve | BB50: =AVERAGEIF($BB$44:$CW$44,BB49,$BB$45:$CW$45) -> 3.73004 | BC50: =AVERAGEIF($BB$44:$CW$44,BC49,$BB$45:$CW$45) -> 3.8050852 | BD50: =AVERAGEIF($BB$44:$CW$44,BD49,$BB$45:$CW$45) -> 4.0043605 | BE50: =AVERAGEIF($BB$44:$CW$44,BE49,$BB$45:$CW$45) -> 4.1576845 | BF50: =AVERAGEIF($BB$44:$CW$44,BF49,$BB$45:$CW$45) -> 4.238603 | BG50: =AVERAGEIF($BB$44:$CW$44,BG49,$BB$45:$CW$45) -> 4.2623974 | BH50: =AVERAGEIF($BB$44:$CW$44,BH49,$BB$45:$CW$45) -> 4.2437311 | BI50: =AVERAGEIF($BB$44:$CW$44,BI49,$BB$45:$CW$45) -> 4.2043937 | ... BQ50: =AVERAGEIF($BB$44:$CW$44,BQ49,$BB$45:$CW$45) -> 4.1457519
BA52: Comparison - monthly
BB53: 44927 | BC53: 44958 | BD53: 44986 | BE53: 45017 | BF53: 45047 | BG53: 45078 | BH53: 45108 | BI53: 45139 | BJ53: 45170 | BK53: 45200 | BL53: 45231 | BM53: 45261 | BN53: 45292 | BO53: 45323 | BP53: 45352 | BQ53: 45383 | BR53: 45413 | BS53: 45444 | BT53: 45474 | BU53: 45505 | BV53: 45536 | BW53: 45566 | BX53: 45597 | BY53: 45627 | BZ53: 45658 | CA53: 45689 | CB53: 45717 | CC53: 45748 | CD53: 45778 | CE53: 45809 | CF53: 45839 | CG53: 45870 | CH53: 45901 | CI53: 45931 | CJ53: 45962 | CK53: 45992 | CL53: 46023 | CM53: 46054 | CN53: 46082 | CO53: 46113 | CP53: 46143 | CQ53: 46174 | CR53: 46204 | CS53: 46235 | CT53: 46266 | CU53: 46296 | CV53: 46327 | CW53: 46357 | CX53: 46388 | CY53: 46419 | CZ53: 46447 | DA53: 46478 | DB53: 46508 | DC53: 46539 | DD53: 46569 | DE53: 46600 | DF53: 46631 | DG53: 46661 | DH53: 46692 | DI53: 46722 | DJ53: 46753 | DK53: 46784 | DL53: 46813 | DM53: 46844 | DN53: 46874 | DO53: 46905 | DP53: 46935 | DQ53: 46966 | DR53: 46997 | DS53: 47027 | DT53: 47058 | DU53: 47088 | DV53: 47119 | DW53: 47150 | DX53: 47178 | DY53: 47209 | DZ53: 47239 | EA53: 47270 | EB53: 47300 | EC53: 47331 | ED53: 47362 | EE53: 47392 | EF53: 47423 | EG53: 47453
BB54: =MONTH(BB53) -> 1 | BC54: =MONTH(BC53) -> 2 | BD54: =MONTH(BD53) -> 3 | BE54: =MONTH(BE53) -> 4 | BF54: =MONTH(BF53) -> 5 | BG54: =MONTH(BG53) -> 6 | BH54: =MONTH(BH53) -> 7 | BI54: =MONTH(BI53) -> 8 | ... EG54: =MONTH(EG53) -> 12
BB55: 202301 | BC55: =IF(BC54=1,BB55+89,BB55+1) -> 202302 | BD55: =IF(BD54=1,BC55+89,BC55+1) -> 202303 | BE55: =IF(BE54=1,BD55+89,BD55+1) -> 202304 | BF55: =IF(BF54=1,BE55+89,BE55+1) -> 202305 | BG55: =IF(BG54=1,BF55+89,BF55+1) -> 202306 | BH55: =IF(BH54=1,BG55+89,BG55+1) -> 202307 | BI55: =IF(BI54=1,BH55+89,BH55+1) -> 202308 | BJ55: =IF(BJ54=1,BI55+89,BI55+1) -> 202309 | ... EG55: =IF(EG54=1,EF55+89,EF55+1) -> 202912
BA56: Bank Rate | BB56: =VLOOKUP(BB53,HAVERM!$A:$N,14,FALSE) -> 3.5 | BC56: =VLOOKUP(BC53,HAVERM!$A:$N,14,FALSE) -> 4 | BD56: =VLOOKUP(BD53,HAVERM!$A:$N,14,FALSE) -> 4.25 | BE56: =VLOOKUP(BE53,HAVERM!$A:$N,14,FALSE) -> 4.25 | BF56: =VLOOKUP(BF53,HAVERM!$A:$N,14,FALSE) -> 4.5 | BG56: =VLOOKUP(BG53,HAVERM!$A:$N,14,FALSE) -> 5 | BH56: =VLOOKUP(BH53,HAVERM!$A:$N,14,FALSE) -> 5 | BI56: =VLOOKUP(BI53,HAVERM!$A:$N,14,FALSE) -> 5.25 | ... EG56: =VLOOKUP(EG53,HAVERM!$A:$N,14,FALSE) -> #N/A
BA57: =A50 -> April 2026 MPR | BB57: =HLOOKUP(BB$55,$B$42:$AX$45,4,FALSE) -> #N/A | BC57: =HLOOKUP(BC$55,$B$42:$AX$45,4,FALSE) -> #N/A | BD57: =HLOOKUP(BD$55,$B$42:$AX$45,4,FALSE) -> #N/A | BE57: =HLOOKUP(BE$55,$B$42:$AX$45,4,FALSE) -> #N/A | BF57: =HLOOKUP(BF$55,$B$42:$AX$45,4,FALSE) -> #N/A | BG57: =HLOOKUP(BG$55,$B$42:$AX$45,4,FALSE) -> #N/A | BH57: =HLOOKUP(BH$55,$B$42:$AX$45,4,FALSE) -> #N/A | BI57: =HLOOKUP(BI$55,$B$42:$AX$45,4,FALSE) -> #N/A | ... EG57: =HLOOKUP(EG$55,$B$42:$AX$45,4,FALSE) -> #N/A
BA58: =BA50 -> Current market curve | BB58: =HLOOKUP(BB$55,$BB$42:$CW$45,4,FALSE) -> #N/A | BC58: =HLOOKUP(BC$55,$BB$42:$CW$45,4,FALSE) -> #N/A | BD58: =HLOOKUP(BD$55,$BB$42:$CW$45,4,FALSE) -> #N/A | BE58: =HLOOKUP(BE$55,$BB$42:$CW$45,4,FALSE) -> #N/A | BF58: =HLOOKUP(BF$55,$BB$42:$CW$45,4,FALSE) -> #N/A | BG58: =HLOOKUP(BG$55,$BB$42:$CW$45,4,FALSE) -> #N/A | BH58: =HLOOKUP(BH$55,$BB$42:$CW$45,4,FALSE) -> #N/A | BI58: =HLOOKUP(BI$55,$BB$42:$CW$45,4,FALSE) -> #N/A | ... EG58: =HLOOKUP(EG$55,$BB$42:$CW$45,4,FALSE) -> 4.1297051
BA59: Latest | BB59: =HLOOKUP(BB$55,$BB$42:$CW$46,5,FALSE) -> #N/A | BC59: =HLOOKUP(BC$55,$BB$42:$CW$46,5,FALSE) -> #N/A | BD59: =HLOOKUP(BD$55,$BB$42:$CW$46,5,FALSE) -> #N/A | BE59: =HLOOKUP(BE$55,$BB$42:$CW$46,5,FALSE) -> #N/A | BF59: =HLOOKUP(BF$55,$BB$42:$CW$46,5,FALSE) -> #N/A | BG59: =HLOOKUP(BG$55,$BB$42:$CW$46,5,FALSE) -> #N/A | BH59: =HLOOKUP(BH$55,$BB$42:$CW$46,5,FALSE) -> #N/A | BI59: =HLOOKUP(BI$55,$BB$42:$CW$46,5,FALSE) -> #N/A | ... EG59: =HLOOKUP(EG$55,$BB$42:$CW$46,5,FALSE) -> 4.0313396
BA60: Difference | BQ60: =BQ58-BQ57 -> #N/A | BR60: =BR58-BR57 -> #N/A | BS60: =BS58-BS57 -> #N/A | BT60: =BT58-BT57 -> #N/A | BU60: =BU58-BU57 -> #N/A | BV60: =BV58-BV57 -> #N/A | BW60: =BW58-BW57 -> #N/A | BX60: =BX58-BX57 -> #N/A | ... EG60: =EG58-EG57 -> #N/A
BA61: Next 3 years | DC61: =AVERAGE(BW60:DC60) -> #N/A
BA63: Comparison - quarterly
BB64: 44927 | BC64: 45017 | BD64: 45108 | BE64: 45200 | BF64: 45292 | BG64: 45383 | BH64: 45474 | BI64: 45566 | BJ64: 45658 | BK64: 45748 | BL64: 45839 | BM64: 45931 | BN64: 46023 | BO64: 46113 | BP64: 46204 | BQ64: 46296 | BR64: 46388 | BS64: 46478 | BT64: 46569 | BU64: 46661 | BV64: 46753 | BW64: 46844 | BX64: 46935 | BY64: 47027 | BZ64: 47119 | CA64: 47209 | CB64: 47300 | CC64: 47392 | CD64: 47484
BB65: 202301 | BC65: =IF(RIGHT(BB65)="4",BB65+97,BB65+1) -> 202302 | BD65: =IF(RIGHT(BC65)="4",BC65+97,BC65+1) -> 202303 | BE65: =IF(RIGHT(BD65)="4",BD65+97,BD65+1) -> 202304 | BF65: =IF(RIGHT(BE65)="4",BE65+97,BE65+1) -> 202401 | BG65: =IF(RIGHT(BF65)="4",BF65+97,BF65+1) -> 202402 | BH65: =IF(RIGHT(BG65)="4",BG65+97,BG65+1) -> 202403 | BI65: =IF(RIGHT(BH65)="4",BH65+97,BH65+1) -> 202404 | BJ65: =IF(RIGHT(BI65)="4",BI65+97,BI65+1) -> 202501 | ... CD65: =IF(RIGHT(CC65)="4",CC65+97,CC65+1) -> 203001
BA66: Bank Rate | BB66: =VLOOKUP(BB64,HAVERQ!$A:$G,7,FALSE) -> 4.25 | BC66: =VLOOKUP(BC64,HAVERQ!$A:$G,7,FALSE) -> 5 | BD66: =VLOOKUP(BD64,HAVERQ!$A:$G,7,FALSE) -> 5.25 | BE66: =VLOOKUP(BE64,HAVERQ!$A:$G,7,FALSE) -> 5.25 | BF66: =VLOOKUP(BF64,HAVERQ!$A:$G,7,FALSE) -> 5.25 | BG66: =VLOOKUP(BG64,HAVERQ!$A:$G,7,FALSE) -> 5.25 | BH66: =VLOOKUP(BH64,HAVERQ!$A:$G,7,FALSE) -> 5 | BI66: =VLOOKUP(BI64,HAVERQ!$A:$G,7,FALSE) -> 4.75 | ... BN66: =VLOOKUP(BN64,HAVERQ!$A:$G,7,FALSE) -> 3.75
BA67: =A50 -> April 2026 MPR | BB67: =HLOOKUP(BB$65,$B$49:$R$50,2,FALSE) -> #N/A | BC67: =HLOOKUP(BC$65,$B$49:$R$50,2,FALSE) -> #N/A | BD67: =HLOOKUP(BD$65,$B$49:$R$50,2,FALSE) -> #N/A | BE67: =HLOOKUP(BE$65,$B$49:$R$50,2,FALSE) -> #N/A | BF67: =HLOOKUP(BF$65,$B$49:$R$50,2,FALSE) -> #N/A | BG67: =HLOOKUP(BG$65,$B$49:$R$50,2,FALSE) -> #N/A | BH67: =HLOOKUP(BH$65,$B$49:$R$50,2,FALSE) -> #N/A | BI67: =HLOOKUP(BI$65,$B$49:$R$50,2,FALSE) -> #N/A | ... CD67: =HLOOKUP(CD$65,$B$49:$R$50,2,FALSE) -> #N/A
BA68: =BA50 -> Current market curve | BB68: =HLOOKUP(BB$65,$BB$49:$BR$50,2,FALSE) -> #N/A | BC68: =HLOOKUP(BC$65,$BB$49:$BR$50,2,FALSE) -> #N/A | BD68: =HLOOKUP(BD$65,$BB$49:$BR$50,2,FALSE) -> #N/A | BE68: =HLOOKUP(BE$65,$BB$49:$BR$50,2,FALSE) -> #N/A | BF68: =HLOOKUP(BF$65,$BB$49:$BR$50,2,FALSE) -> #N/A | BG68: =HLOOKUP(BG$65,$BB$49:$BR$50,2,FALSE) -> #N/A | BH68: =HLOOKUP(BH$65,$BB$49:$BR$50,2,FALSE) -> #N/A | BI68: =HLOOKUP(BI$65,$BB$49:$BR$50,2,FALSE) -> #N/A | ... CD68: =HLOOKUP(CD$65,$BB$49:$BR$50,2,FALSE) -> 4.1457519
BA69: Difference | BH69: =BH68-BH67 -> #N/A | BI69: =BI68-BI67 -> #N/A | BJ69: =BJ68-BJ67 -> #N/A | BK69: =BK68-BK67 -> #N/A | BL69: =BL68-BL67 -> #N/A | BM69: =BM68-BM67 -> #N/A | BN69: =BN68-BN67 -> #N/A | BO69: =BO68-BO67 -> #N/A | ... CD69: =CD68-CD67 -> #N/A
BA70: Next 3 years | BS70: =AVERAGE(BH69:BS69) -> #N/A
BS76: avg diff | BT76: Proxy impact on growth per year (100bps is 1ppt on the level of GDP)
BS77: =AVERAGE(BN69:BU69) -> #N/A | BT77: =BS77/2 -> #N/A

Sheet Market expectations - Electrici
A1: ='Market pricing dates'!A2 -> April 2026 MPR | C1: ='Market pricing dates'!A12 -> 15 working days to 22 Apr 2026 | AZ1: ='Market pricing dates'!D2 -> Current market curve | BB1: ='Market pricing dates'!D12 -> 15 working days to 18 Jun 2026
A2: Column # | B2: =HAVERD!DR$1 -> 122 | C2: =+B2+1 -> 123 | D2: =+C2+1 -> 124 | E2: =+D2+1 -> 125 | F2: =+E2+1 -> 126 | G2: =+F2+1 -> 127 | H2: =+G2+1 -> 128 | I2: =+H2+1 -> 129 | J2: =+I2+1 -> 130 | ... AW2: =+AV2+1 -> 169 | AZ2: Column # | BA2: =HAVERD!DR$1 -> 122 | BB2: =+BA2+1 -> 123 | BC2: =+BB2+1 -> 124 | BD2: =+BC2+1 -> 125 | BE2: =+BD2+1 -> 126 | BF2: =+BE2+1 -> 127 | BG2: =+BF2+1 -> 128 | BH2: =+BG2+1 -> 129 | BI2: =+BH2+1 -> 130 | ... CV2: =+CU2+1 -> 169
A3: Months | B3: =HAVERD!DR$2 -> Electricity - 1 | C3: =HAVERD!DS$2 -> Electricity - 2 | D3: =HAVERD!DT$2 -> Electricity - 3 | E3: =HAVERD!DU$2 -> Electricity - 4 | F3: =HAVERD!DV$2 -> Electricity - 5 | G3: =HAVERD!DW$2 -> Electricity - 6 | H3: =HAVERD!DX$2 -> Electricity - 7 | I3: =HAVERD!DY$2 -> Electricity - 8 | ... AW3: =HAVERD!FM$2 -> Electricity - 48 | AZ3: Months | BA3: =HAVERD!DR$2 -> Electricity - 1 | BB3: =HAVERD!DS$2 -> Electricity - 2 | BC3: =HAVERD!DT$2 -> Electricity - 3 | BD3: =HAVERD!DU$2 -> Electricity - 4 | BE3: =HAVERD!DV$2 -> Electricity - 5 | BF3: =HAVERD!DW$2 -> Electricity - 6 | BG3: =HAVERD!DX$2 -> Electricity - 7 | BH3: =HAVERD!DY$2 -> Electricity - 8 | ... CV3: =HAVERD!FM$2 -> Electricity - 48
A4: Days | C4: 30.416667 | D4: =+C4+30.4166667 -> 60.833333 | E4: =+D4+30.4166667 -> 91.25 | F4: =+E4+30.4166667 -> 121.66667 | G4: =+F4+30.4166667 -> 152.08333 | H4: =+G4+30.4166667 -> 182.5 | I4: =+H4+30.4166667 -> 212.91667 | J4: =+I4+30.4166667 -> 243.33333 | K4: =+J4+30.4166667 -> 273.75 | ... AW4: =+AV4+30.4166667 -> 1429.5833 | AZ4: Days | BB4: 30.416667 | BC4: =+BB4+30.4166667 -> 60.833333 | BD4: =+BC4+30.4166667 -> 91.25 | BE4: =+BD4+30.4166667 -> 121.66667 | BF4: =+BE4+30.4166667 -> 152.08333 | BG4: =+BF4+30.4166667 -> 182.5 | BH4: =+BG4+30.4166667 -> 212.91667 | BI4: =+BH4+30.4166667 -> 243.33333 | BJ4: =+BI4+30.4166667 -> 273.75 | ... CV4: =+CU4+30.4166667 -> 1429.5833
A5: Dates | AZ5: Dates
A6: =A11-7 -> 46114 | B6: =A6 -> 46114 | C6: =$B6+C$4 -> 46144.417 | D6: =$B6+D$4 -> 46174.833 | E6: =$B6+E$4 -> 46205.25 | F6: =$B6+F$4 -> 46235.667 | G6: =$B6+G$4 -> 46266.083 | H6: =$B6+H$4 -> 46296.5 | I6: =$B6+I$4 -> 46326.917 | J6: =$B6+J$4 -> 46357.333 | ... AW6: =$B6+AW$4 -> 47543.583 | AZ6: =AZ11-7 -> 46171 | BA6: =AZ6 -> 46171 | BB6: =$AZ6+BB$4 -> 46201.417 | BC6: =$AZ6+BC$4 -> 46231.833 | BD6: =$AZ6+BD$4 -> 46262.25 | BE6: =$AZ6+BE$4 -> 46292.667 | BF6: =$AZ6+BF$4 -> 46323.083 | BG6: =$AZ6+BG$4 -> 46353.5 | BH6: =$AZ6+BH$4 -> 46383.917 | BI6: =$AZ6+BI$4 -> 46414.333 | ... CV6: =$AZ6+CV$4 -> 47600.583
A7: =A12-7 -> 46115 | B7: =A7 -> 46115 | C7: =$B7+C$4 -> 46145.417 | D7: =$B7+D$4 -> 46175.833 | E7: =$B7+E$4 -> 46206.25 | F7: =$B7+F$4 -> 46236.667 | G7: =$B7+G$4 -> 46267.083 | H7: =$B7+H$4 -> 46297.5 | I7: =$B7+I$4 -> 46327.917 | J7: =$B7+J$4 -> 46358.333 | ... AW7: =$B7+AW$4 -> 47544.583 | AZ7: =AZ12-7 -> 46174 | BA7: =AZ7 -> 46174 | BB7: =$AZ7+BB$4 -> 46204.417 | BC7: =$AZ7+BC$4 -> 46234.833 | BD7: =$AZ7+BD$4 -> 46265.25 | BE7: =$AZ7+BE$4 -> 46295.667 | BF7: =$AZ7+BF$4 -> 46326.083 | BG7: =$AZ7+BG$4 -> 46356.5 | BH7: =$AZ7+BH$4 -> 46386.917 | BI7: =$AZ7+BI$4 -> 46417.333 | ... CV7: =$AZ7+CV$4 -> 47603.583
A8: =A13-7 -> 46118 | B8: =A8 -> 46118 | C8: =$B8+C$4 -> 46148.417 | D8: =$B8+D$4 -> 46178.833 | E8: =$B8+E$4 -> 46209.25 | F8: =$B8+F$4 -> 46239.667 | G8: =$B8+G$4 -> 46270.083 | H8: =$B8+H$4 -> 46300.5 | I8: =$B8+I$4 -> 46330.917 | J8: =$B8+J$4 -> 46361.333 | ... AW8: =$B8+AW$4 -> 47547.583 | AZ8: =AZ13-7 -> 46175 | BA8: =AZ8 -> 46175 | BB8: =$AZ8+BB$4 -> 46205.417 | BC8: =$AZ8+BC$4 -> 46235.833 | BD8: =$AZ8+BD$4 -> 46266.25 | BE8: =$AZ8+BE$4 -> 46296.667 | BF8: =$AZ8+BF$4 -> 46327.083 | BG8: =$AZ8+BG$4 -> 46357.5 | BH8: =$AZ8+BH$4 -> 46387.917 | BI8: =$AZ8+BI$4 -> 46418.333 | ... CV8: =$AZ8+CV$4 -> 47604.583
A9: =A14-7 -> 46119 | B9: =A9 -> 46119 | C9: =$B9+C$4 -> 46149.417 | D9: =$B9+D$4 -> 46179.833 | E9: =$B9+E$4 -> 46210.25 | F9: =$B9+F$4 -> 46240.667 | G9: =$B9+G$4 -> 46271.083 | H9: =$B9+H$4 -> 46301.5 | I9: =$B9+I$4 -> 46331.917 | J9: =$B9+J$4 -> 46362.333 | ... AW9: =$B9+AW$4 -> 47548.583 | AZ9: =AZ14-7 -> 46176 | BA9: =AZ9 -> 46176 | BB9: =$AZ9+BB$4 -> 46206.417 | BC9: =$AZ9+BC$4 -> 46236.833 | BD9: =$AZ9+BD$4 -> 46267.25 | BE9: =$AZ9+BE$4 -> 46297.667 | BF9: =$AZ9+BF$4 -> 46328.083 | BG9: =$AZ9+BG$4 -> 46358.5 | BH9: =$AZ9+BH$4 -> 46388.917 | BI9: =$AZ9+BI$4 -> 46419.333 | ... CV9: =$AZ9+CV$4 -> 47605.583
A10: =A15-7 -> 46120 | B10: =A10 -> 46120 | C10: =$B10+C$4 -> 46150.417 | D10: =$B10+D$4 -> 46180.833 | E10: =$B10+E$4 -> 46211.25 | F10: =$B10+F$4 -> 46241.667 | G10: =$B10+G$4 -> 46272.083 | H10: =$B10+H$4 -> 46302.5 | I10: =$B10+I$4 -> 46332.917 | J10: =$B10+J$4 -> 46363.333 | ... AW10: =$B10+AW$4 -> 47549.583 | AZ10: =AZ15-7 -> 46177 | BA10: =AZ10 -> 46177 | BB10: =$AZ10+BB$4 -> 46207.417 | BC10: =$AZ10+BC$4 -> 46237.833 | BD10: =$AZ10+BD$4 -> 46268.25 | BE10: =$AZ10+BE$4 -> 46298.667 | BF10: =$AZ10+BF$4 -> 46329.083 | BG10: =$AZ10+BG$4 -> 46359.5 | BH10: =$AZ10+BH$4 -> 46389.917 | BI10: =$AZ10+BI$4 -> 46420.333 | ... CV10: =$AZ10+CV$4 -> 47606.583
A11: =A16-7 -> 46121 | B11: =A11 -> 46121 | C11: =$B11+C$4 -> 46151.417 | D11: =$B11+D$4 -> 46181.833 | E11: =$B11+E$4 -> 46212.25 | F11: =$B11+F$4 -> 46242.667 | G11: =$B11+G$4 -> 46273.083 | H11: =$B11+H$4 -> 46303.5 | I11: =$B11+I$4 -> 46333.917 | J11: =$B11+J$4 -> 46364.333 | ... AW11: =$B11+AW$4 -> 47550.583 | AZ11: =AZ16-7 -> 46178 | BA11: =AZ11 -> 46178 | BB11: =$AZ11+BB$4 -> 46208.417 | BC11: =$AZ11+BC$4 -> 46238.833 | BD11: =$AZ11+BD$4 -> 46269.25 | BE11: =$AZ11+BE$4 -> 46299.667 | BF11: =$AZ11+BF$4 -> 46330.083 | BG11: =$AZ11+BG$4 -> 46360.5 | BH11: =$AZ11+BH$4 -> 46390.917 | BI11: =$AZ11+BI$4 -> 46421.333 | ... CV11: =$AZ11+CV$4 -> 47607.583
A12: =A17-7 -> 46122 | B12: =A12 -> 46122 | C12: =$B12+C$4 -> 46152.417 | D12: =$B12+D$4 -> 46182.833 | E12: =$B12+E$4 -> 46213.25 | F12: =$B12+F$4 -> 46243.667 | G12: =$B12+G$4 -> 46274.083 | H12: =$B12+H$4 -> 46304.5 | I12: =$B12+I$4 -> 46334.917 | J12: =$B12+J$4 -> 46365.333 | ... AW12: =$B12+AW$4 -> 47551.583 | AZ12: =AZ17-7 -> 46181 | BA12: =AZ12 -> 46181 | BB12: =$AZ12+BB$4 -> 46211.417 | BC12: =$AZ12+BC$4 -> 46241.833 | BD12: =$AZ12+BD$4 -> 46272.25 | BE12: =$AZ12+BE$4 -> 46302.667 | BF12: =$AZ12+BF$4 -> 46333.083 | BG12: =$AZ12+BG$4 -> 46363.5 | BH12: =$AZ12+BH$4 -> 46393.917 | BI12: =$AZ12+BI$4 -> 46424.333 | ... CV12: =$AZ12+CV$4 -> 47610.583
A13: =A18-7 -> 46125 | B13: =A13 -> 46125 | C13: =$B13+C$4 -> 46155.417 | D13: =$B13+D$4 -> 46185.833 | E13: =$B13+E$4 -> 46216.25 | F13: =$B13+F$4 -> 46246.667 | G13: =$B13+G$4 -> 46277.083 | H13: =$B13+H$4 -> 46307.5 | I13: =$B13+I$4 -> 46337.917 | J13: =$B13+J$4 -> 46368.333 | ... AW13: =$B13+AW$4 -> 47554.583 | AZ13: =AZ18-7 -> 46182 | BA13: =AZ13 -> 46182 | BB13: =$AZ13+BB$4 -> 46212.417 | BC13: =$AZ13+BC$4 -> 46242.833 | BD13: =$AZ13+BD$4 -> 46273.25 | BE13: =$AZ13+BE$4 -> 46303.667 | BF13: =$AZ13+BF$4 -> 46334.083 | BG13: =$AZ13+BG$4 -> 46364.5 | BH13: =$AZ13+BH$4 -> 46394.917 | BI13: =$AZ13+BI$4 -> 46425.333 | ... CV13: =$AZ13+CV$4 -> 47611.583
A14: =A19-7 -> 46126 | B14: =A14 -> 46126 | C14: =$B14+C$4 -> 46156.417 | D14: =$B14+D$4 -> 46186.833 | E14: =$B14+E$4 -> 46217.25 | F14: =$B14+F$4 -> 46247.667 | G14: =$B14+G$4 -> 46278.083 | H14: =$B14+H$4 -> 46308.5 | I14: =$B14+I$4 -> 46338.917 | J14: =$B14+J$4 -> 46369.333 | ... AW14: =$B14+AW$4 -> 47555.583 | AZ14: =AZ19-7 -> 46183 | BA14: =AZ14 -> 46183 | BB14: =$AZ14+BB$4 -> 46213.417 | BC14: =$AZ14+BC$4 -> 46243.833 | BD14: =$AZ14+BD$4 -> 46274.25 | BE14: =$AZ14+BE$4 -> 46304.667 | BF14: =$AZ14+BF$4 -> 46335.083 | BG14: =$AZ14+BG$4 -> 46365.5 | BH14: =$AZ14+BH$4 -> 46395.917 | BI14: =$AZ14+BI$4 -> 46426.333 | ... CV14: =$AZ14+CV$4 -> 47612.583
A15: =A20-7 -> 46127 | B15: =A15 -> 46127 | C15: =$B15+C$4 -> 46157.417 | D15: =$B15+D$4 -> 46187.833 | E15: =$B15+E$4 -> 46218.25 | F15: =$B15+F$4 -> 46248.667 | G15: =$B15+G$4 -> 46279.083 | H15: =$B15+H$4 -> 46309.5 | I15: =$B15+I$4 -> 46339.917 | J15: =$B15+J$4 -> 46370.333 | ... AW15: =$B15+AW$4 -> 47556.583 | AZ15: =AZ20-7 -> 46184 | BA15: =AZ15 -> 46184 | BB15: =$AZ15+BB$4 -> 46214.417 | BC15: =$AZ15+BC$4 -> 46244.833 | BD15: =$AZ15+BD$4 -> 46275.25 | BE15: =$AZ15+BE$4 -> 46305.667 | BF15: =$AZ15+BF$4 -> 46336.083 | BG15: =$AZ15+BG$4 -> 46366.5 | BH15: =$AZ15+BH$4 -> 46396.917 | BI15: =$AZ15+BI$4 -> 46427.333 | ... CV15: =$AZ15+CV$4 -> 47613.583
A16: ='Market pricing dates'!B5 -> 46128 | B16: =A16 -> 46128 | C16: =$B16+C$4 -> 46158.417 | D16: =$B16+D$4 -> 46188.833 | E16: =$B16+E$4 -> 46219.25 | F16: =$B16+F$4 -> 46249.667 | G16: =$B16+G$4 -> 46280.083 | H16: =$B16+H$4 -> 46310.5 | I16: =$B16+I$4 -> 46340.917 | J16: =$B16+J$4 -> 46371.333 | ... AW16: =$B16+AW$4 -> 47557.583 | AZ16: ='Market pricing dates'!E5 -> 46185 | BA16: =AZ16 -> 46185 | BB16: =$AZ16+BB$4 -> 46215.417 | BC16: =$AZ16+BC$4 -> 46245.833 | BD16: =$AZ16+BD$4 -> 46276.25 | BE16: =$AZ16+BE$4 -> 46306.667 | BF16: =$AZ16+BF$4 -> 46337.083 | BG16: =$AZ16+BG$4 -> 46367.5 | BH16: =$AZ16+BH$4 -> 46397.917 | BI16: =$AZ16+BI$4 -> 46428.333 | ... CV16: =$AZ16+CV$4 -> 47614.583
A17: ='Market pricing dates'!B6 -> 46129 | B17: =A17 -> 46129 | C17: =$B17+C$4 -> 46159.417 | D17: =$B17+D$4 -> 46189.833 | E17: =$B17+E$4 -> 46220.25 | F17: =$B17+F$4 -> 46250.667 | G17: =$B17+G$4 -> 46281.083 | H17: =$B17+H$4 -> 46311.5 | I17: =$B17+I$4 -> 46341.917 | J17: =$B17+J$4 -> 46372.333 | ... AW17: =$B17+AW$4 -> 47558.583 | AZ17: ='Market pricing dates'!E6 -> 46188 | BA17: =AZ17 -> 46188 | BB17: =$AZ17+BB$4 -> 46218.417 | BC17: =$AZ17+BC$4 -> 46248.833 | BD17: =$AZ17+BD$4 -> 46279.25 | BE17: =$AZ17+BE$4 -> 46309.667 | BF17: =$AZ17+BF$4 -> 46340.083 | BG17: =$AZ17+BG$4 -> 46370.5 | BH17: =$AZ17+BH$4 -> 46400.917 | BI17: =$AZ17+BI$4 -> 46431.333 | ... CV17: =$AZ17+CV$4 -> 47617.583
A18: ='Market pricing dates'!B7 -> 46132 | B18: =A18 -> 46132 | C18: =$B18+C$4 -> 46162.417 | D18: =$B18+D$4 -> 46192.833 | E18: =$B18+E$4 -> 46223.25 | F18: =$B18+F$4 -> 46253.667 | G18: =$B18+G$4 -> 46284.083 | H18: =$B18+H$4 -> 46314.5 | I18: =$B18+I$4 -> 46344.917 | J18: =$B18+J$4 -> 46375.333 | ... AW18: =$B18+AW$4 -> 47561.583 | AZ18: ='Market pricing dates'!E7 -> 46189 | BA18: =AZ18 -> 46189 | BB18: =$AZ18+BB$4 -> 46219.417 | BC18: =$AZ18+BC$4 -> 46249.833 | BD18: =$AZ18+BD$4 -> 46280.25 | BE18: =$AZ18+BE$4 -> 46310.667 | BF18: =$AZ18+BF$4 -> 46341.083 | BG18: =$AZ18+BG$4 -> 46371.5 | BH18: =$AZ18+BH$4 -> 46401.917 | BI18: =$AZ18+BI$4 -> 46432.333 | ... CV18: =$AZ18+CV$4 -> 47618.583
A19: ='Market pricing dates'!B8 -> 46133 | B19: =A19 -> 46133 | C19: =$B19+C$4 -> 46163.417 | D19: =$B19+D$4 -> 46193.833 | E19: =$B19+E$4 -> 46224.25 | F19: =$B19+F$4 -> 46254.667 | G19: =$B19+G$4 -> 46285.083 | H19: =$B19+H$4 -> 46315.5 | I19: =$B19+I$4 -> 46345.917 | J19: =$B19+J$4 -> 46376.333 | ... AW19: =$B19+AW$4 -> 47562.583 | AZ19: ='Market pricing dates'!E8 -> 46190 | BA19: =AZ19 -> 46190 | BB19: =$AZ19+BB$4 -> 46220.417 | BC19: =$AZ19+BC$4 -> 46250.833 | BD19: =$AZ19+BD$4 -> 46281.25 | BE19: =$AZ19+BE$4 -> 46311.667 | BF19: =$AZ19+BF$4 -> 46342.083 | BG19: =$AZ19+BG$4 -> 46372.5 | BH19: =$AZ19+BH$4 -> 46402.917 | BI19: =$AZ19+BI$4 -> 46433.333 | ... CV19: =$AZ19+CV$4 -> 47619.583
A20: ='Market pricing dates'!B9 -> 46134 | B20: =A20 -> 46134 | C20: =$B20+C$4 -> 46164.417 | D20: =$B20+D$4 -> 46194.833 | E20: =$B20+E$4 -> 46225.25 | F20: =$B20+F$4 -> 46255.667 | G20: =$B20+G$4 -> 46286.083 | H20: =$B20+H$4 -> 46316.5 | I20: =$B20+I$4 -> 46346.917 | J20: =$B20+J$4 -> 46377.333 | ... AW20: =$B20+AW$4 -> 47563.583 | AZ20: ='Market pricing dates'!E9 -> 46191 | BA20: =AZ20 -> 46191 | BB20: =$AZ20+BB$4 -> 46221.417 | BC20: =$AZ20+BC$4 -> 46251.833 | BD20: =$AZ20+BD$4 -> 46282.25 | BE20: =$AZ20+BE$4 -> 46312.667 | BF20: =$AZ20+BF$4 -> 46343.083 | BG20: =$AZ20+BG$4 -> 46373.5 | BH20: =$AZ20+BH$4 -> 46403.917 | BI20: =$AZ20+BI$4 -> 46434.333 | ... CV20: =$AZ20+CV$4 -> 47620.583
A22: Electricity futures | AZ22: Electricity futures
A23: =A6 -> 46114 | B23: =VLOOKUP($A23,HAVERD!$A:$FM,B$2,FALSE) -> 96.26 | C23: =VLOOKUP($A23,HAVERD!$A:$FM,C$2,FALSE) -> 100.21 | D23: =VLOOKUP($A23,HAVERD!$A:$FM,D$2,FALSE) -> 98.12 | E23: =VLOOKUP($A23,HAVERD!$A:$FM,E$2,FALSE) -> 98.47 | F23: =VLOOKUP($A23,HAVERD!$A:$FM,F$2,FALSE) -> 99.18 | G23: =VLOOKUP($A23,HAVERD!$A:$FM,G$2,FALSE) -> 98.37 | H23: =VLOOKUP($A23,HAVERD!$A:$FM,H$2,FALSE) -> 99.39 | I23: =VLOOKUP($A23,HAVERD!$A:$FM,I$2,FALSE) -> 100.9 | ... AW23: =VLOOKUP($A23,HAVERD!$A:$FM,AW$2,FALSE) -> 66.59 | AZ23: =AZ6 -> 46171 | BA23: =_xlfn.IFNA(VLOOKUP($AZ23,HAVERD!$A:$FM,BA$2,FALSE),"") -> 99.18 | BB23: =_xlfn.IFNA(VLOOKUP($AZ23,HAVERD!$A:$FM,BB$2,FALSE),"") -> 96.76 | BC23: =_xlfn.IFNA(VLOOKUP($AZ23,HAVERD!$A:$FM,BC$2,FALSE),"") -> 99.48 | BD23: =_xlfn.IFNA(VLOOKUP($AZ23,HAVERD!$A:$FM,BD$2,FALSE),"") -> 100.41 | BE23: =_xlfn.IFNA(VLOOKUP($AZ23,HAVERD!$A:$FM,BE$2,FALSE),"") -> 102.12 | BF23: =_xlfn.IFNA(VLOOKUP($AZ23,HAVERD!$A:$FM,BF$2,FALSE),"") -> 103.57 | BG23: =_xlfn.IFNA(VLOOKUP($AZ23,HAVERD!$A:$FM,BG$2,FALSE),"") -> 99.2 | BH23: =_xlfn.IFNA(VLOOKUP($AZ23,HAVERD!$A:$FM,BH$2,FALSE),"") -> 99.93 | ... CV23: =_xlfn.IFNA(VLOOKUP($AZ23,HAVERD!$A:$FM,CV$2,FALSE),"") -> 61.48
A24: =A7 -> 46115 | B24: =VLOOKUP($A24,HAVERD!$A:$FM,B$2,FALSE) -> #N/A | C24: =VLOOKUP($A24,HAVERD!$A:$FM,C$2,FALSE) -> #N/A | D24: =VLOOKUP($A24,HAVERD!$A:$FM,D$2,FALSE) -> #N/A | E24: =VLOOKUP($A24,HAVERD!$A:$FM,E$2,FALSE) -> #N/A | F24: =VLOOKUP($A24,HAVERD!$A:$FM,F$2,FALSE) -> #N/A | G24: =VLOOKUP($A24,HAVERD!$A:$FM,G$2,FALSE) -> #N/A | H24: =VLOOKUP($A24,HAVERD!$A:$FM,H$2,FALSE) -> #N/A | I24: =VLOOKUP($A24,HAVERD!$A:$FM,I$2,FALSE) -> #N/A | ... AW24: =VLOOKUP($A24,HAVERD!$A:$FM,AW$2,FALSE) -> #N/A | AZ24: =AZ7 -> 46174 | BA24: =_xlfn.IFNA(VLOOKUP($AZ24,HAVERD!$A:$FM,BA$2,FALSE),"") -> 103.46 | BB24: =_xlfn.IFNA(VLOOKUP($AZ24,HAVERD!$A:$FM,BB$2,FALSE),"") -> 100.68 | BC24: =_xlfn.IFNA(VLOOKUP($AZ24,HAVERD!$A:$FM,BC$2,FALSE),"") -> 102.79 | BD24: =_xlfn.IFNA(VLOOKUP($AZ24,HAVERD!$A:$FM,BD$2,FALSE),"") -> 103.78 | BE24: =_xlfn.IFNA(VLOOKUP($AZ24,HAVERD!$A:$FM,BE$2,FALSE),"") -> 105.53 | BF24: =_xlfn.IFNA(VLOOKUP($AZ24,HAVERD!$A:$FM,BF$2,FALSE),"") -> 106.78 | BG24: =_xlfn.IFNA(VLOOKUP($AZ24,HAVERD!$A:$FM,BG$2,FALSE),"") -> 101.65 | BH24: =_xlfn.IFNA(VLOOKUP($AZ24,HAVERD!$A:$FM,BH$2,FALSE),"") -> 102.39 | ... CV24: =_xlfn.IFNA(VLOOKUP($AZ24,HAVERD!$A:$FM,CV$2,FALSE),"") -> 61.66
A25: =A8 -> 46118 | B25: =VLOOKUP($A25,HAVERD!$A:$FM,B$2,FALSE) -> 96.26 | C25: =VLOOKUP($A25,HAVERD!$A:$FM,C$2,FALSE) -> 100.21 | D25: =VLOOKUP($A25,HAVERD!$A:$FM,D$2,FALSE) -> 98.12 | E25: =VLOOKUP($A25,HAVERD!$A:$FM,E$2,FALSE) -> 98.47 | F25: =VLOOKUP($A25,HAVERD!$A:$FM,F$2,FALSE) -> 99.18 | G25: =VLOOKUP($A25,HAVERD!$A:$FM,G$2,FALSE) -> 98.37 | H25: =VLOOKUP($A25,HAVERD!$A:$FM,H$2,FALSE) -> 99.39 | I25: =VLOOKUP($A25,HAVERD!$A:$FM,I$2,FALSE) -> 100.9 | ... AW25: =VLOOKUP($A25,HAVERD!$A:$FM,AW$2,FALSE) -> 66.59 | AZ25: =AZ8 -> 46175 | BA25: =_xlfn.IFNA(VLOOKUP($AZ25,HAVERD!$A:$FM,BA$2,FALSE),"") -> 101.13 | BB25: =_xlfn.IFNA(VLOOKUP($AZ25,HAVERD!$A:$FM,BB$2,FALSE),"") -> 98.88 | BC25: =_xlfn.IFNA(VLOOKUP($AZ25,HAVERD!$A:$FM,BC$2,FALSE),"") -> 101.42 | BD25: =_xlfn.IFNA(VLOOKUP($AZ25,HAVERD!$A:$FM,BD$2,FALSE),"") -> 102.28 | BE25: =_xlfn.IFNA(VLOOKUP($AZ25,HAVERD!$A:$FM,BE$2,FALSE),"") -> 104.08 | BF25: =_xlfn.IFNA(VLOOKUP($AZ25,HAVERD!$A:$FM,BF$2,FALSE),"") -> 105.22 | BG25: =_xlfn.IFNA(VLOOKUP($AZ25,HAVERD!$A:$FM,BG$2,FALSE),"") -> 100.96 | BH25: =_xlfn.IFNA(VLOOKUP($AZ25,HAVERD!$A:$FM,BH$2,FALSE),"") -> 101.7 | ... CV25: =_xlfn.IFNA(VLOOKUP($AZ25,HAVERD!$A:$FM,CV$2,FALSE),"") -> 61.66
A26: =A9 -> 46119 | B26: =VLOOKUP($A26,HAVERD!$A:$FM,B$2,FALSE) -> 100.36 | C26: =VLOOKUP($A26,HAVERD!$A:$FM,C$2,FALSE) -> 104.14 | D26: =VLOOKUP($A26,HAVERD!$A:$FM,D$2,FALSE) -> 102.62 | E26: =VLOOKUP($A26,HAVERD!$A:$FM,E$2,FALSE) -> 102.94 | F26: =VLOOKUP($A26,HAVERD!$A:$FM,F$2,FALSE) -> 103.59 | G26: =VLOOKUP($A26,HAVERD!$A:$FM,G$2,FALSE) -> 100.81 | H26: =VLOOKUP($A26,HAVERD!$A:$FM,H$2,FALSE) -> 101.84 | I26: =VLOOKUP($A26,HAVERD!$A:$FM,I$2,FALSE) -> 103.36 | ... AW26: =VLOOKUP($A26,HAVERD!$A:$FM,AW$2,FALSE) -> 66.93 | AZ26: =AZ9 -> 46176 | BA26: =_xlfn.IFNA(VLOOKUP($AZ26,HAVERD!$A:$FM,BA$2,FALSE),"") -> 103.4 | BB26: =_xlfn.IFNA(VLOOKUP($AZ26,HAVERD!$A:$FM,BB$2,FALSE),"") -> 101.02 | BC26: =_xlfn.IFNA(VLOOKUP($AZ26,HAVERD!$A:$FM,BC$2,FALSE),"") -> 103.1 | BD26: =_xlfn.IFNA(VLOOKUP($AZ26,HAVERD!$A:$FM,BD$2,FALSE),"") -> 103.67 | BE26: =_xlfn.IFNA(VLOOKUP($AZ26,HAVERD!$A:$FM,BE$2,FALSE),"") -> 105.54 | BF26: =_xlfn.IFNA(VLOOKUP($AZ26,HAVERD!$A:$FM,BF$2,FALSE),"") -> 106.56 | BG26: =_xlfn.IFNA(VLOOKUP($AZ26,HAVERD!$A:$FM,BG$2,FALSE),"") -> 102.58 | BH26: =_xlfn.IFNA(VLOOKUP($AZ26,HAVERD!$A:$FM,BH$2,FALSE),"") -> 103.32 | ... CV26: =_xlfn.IFNA(VLOOKUP($AZ26,HAVERD!$A:$FM,CV$2,FALSE),"") -> 61.71
A27: =A10 -> 46120 | B27: =VLOOKUP($A27,HAVERD!$A:$FM,B$2,FALSE) -> 89.1 | C27: =VLOOKUP($A27,HAVERD!$A:$FM,C$2,FALSE) -> 92.46 | D27: =VLOOKUP($A27,HAVERD!$A:$FM,D$2,FALSE) -> 91.46 | E27: =VLOOKUP($A27,HAVERD!$A:$FM,E$2,FALSE) -> 91.91 | F27: =VLOOKUP($A27,HAVERD!$A:$FM,F$2,FALSE) -> 92.6 | G27: =VLOOKUP($A27,HAVERD!$A:$FM,G$2,FALSE) -> 89.9 | H27: =VLOOKUP($A27,HAVERD!$A:$FM,H$2,FALSE) -> 90.88 | I27: =VLOOKUP($A27,HAVERD!$A:$FM,I$2,FALSE) -> 92.33 | ... AW27: =VLOOKUP($A27,HAVERD!$A:$FM,AW$2,FALSE) -> 65.16 | AZ27: =AZ10 -> 46177 | BA27: =_xlfn.IFNA(VLOOKUP($AZ27,HAVERD!$A:$FM,BA$2,FALSE),"") -> 102.91 | BB27: =_xlfn.IFNA(VLOOKUP($AZ27,HAVERD!$A:$FM,BB$2,FALSE),"") -> 100.4 | BC27: =_xlfn.IFNA(VLOOKUP($AZ27,HAVERD!$A:$FM,BC$2,FALSE),"") -> 102.16 | BD27: =_xlfn.IFNA(VLOOKUP($AZ27,HAVERD!$A:$FM,BD$2,FALSE),"") -> 103.18 | BE27: =_xlfn.IFNA(VLOOKUP($AZ27,HAVERD!$A:$FM,BE$2,FALSE),"") -> 105.13 | BF27: =_xlfn.IFNA(VLOOKUP($AZ27,HAVERD!$A:$FM,BF$2,FALSE),"") -> 106.1 | BG27: =_xlfn.IFNA(VLOOKUP($AZ27,HAVERD!$A:$FM,BG$2,FALSE),"") -> 101.88 | BH27: =_xlfn.IFNA(VLOOKUP($AZ27,HAVERD!$A:$FM,BH$2,FALSE),"") -> 102.62 | ... CV27: =_xlfn.IFNA(VLOOKUP($AZ27,HAVERD!$A:$FM,CV$2,FALSE),"") -> 60.91
A28: =A11 -> 46121 | B28: =VLOOKUP($A28,HAVERD!$A:$FM,B$2,FALSE) -> 91.5 | C28: =VLOOKUP($A28,HAVERD!$A:$FM,C$2,FALSE) -> 93.68 | D28: =VLOOKUP($A28,HAVERD!$A:$FM,D$2,FALSE) -> 93.2 | E28: =VLOOKUP($A28,HAVERD!$A:$FM,E$2,FALSE) -> 93.48 | F28: =VLOOKUP($A28,HAVERD!$A:$FM,F$2,FALSE) -> 94.24 | G28: =VLOOKUP($A28,HAVERD!$A:$FM,G$2,FALSE) -> 92.01 | H28: =VLOOKUP($A28,HAVERD!$A:$FM,H$2,FALSE) -> 93 | I28: =VLOOKUP($A28,HAVERD!$A:$FM,I$2,FALSE) -> 94.44 | ... AW28: =VLOOKUP($A28,HAVERD!$A:$FM,AW$2,FALSE) -> 65.03 | AZ28: =AZ11 -> 46178 | BA28: =_xlfn.IFNA(VLOOKUP($AZ28,HAVERD!$A:$FM,BA$2,FALSE),"") -> 102.98 | BB28: =_xlfn.IFNA(VLOOKUP($AZ28,HAVERD!$A:$FM,BB$2,FALSE),"") -> 100.2 | BC28: =_xlfn.IFNA(VLOOKUP($AZ28,HAVERD!$A:$FM,BC$2,FALSE),"") -> 101.91 | BD28: =_xlfn.IFNA(VLOOKUP($AZ28,HAVERD!$A:$FM,BD$2,FALSE),"") -> 103.26 | BE28: =_xlfn.IFNA(VLOOKUP($AZ28,HAVERD!$A:$FM,BE$2,FALSE),"") -> 105.26 | BF28: =_xlfn.IFNA(VLOOKUP($AZ28,HAVERD!$A:$FM,BF$2,FALSE),"") -> 105.89 | BG28: =_xlfn.IFNA(VLOOKUP($AZ28,HAVERD!$A:$FM,BG$2,FALSE),"") -> 101.9 | BH28: =_xlfn.IFNA(VLOOKUP($AZ28,HAVERD!$A:$FM,BH$2,FALSE),"") -> 102.64 | ... CV28: =_xlfn.IFNA(VLOOKUP($AZ28,HAVERD!$A:$FM,CV$2,FALSE),"") -> 61.1
A29: =A12 -> 46122 | B29: =VLOOKUP($A29,HAVERD!$A:$FM,B$2,FALSE) -> 86.77 | C29: =VLOOKUP($A29,HAVERD!$A:$FM,C$2,FALSE) -> 90.52 | D29: =VLOOKUP($A29,HAVERD!$A:$FM,D$2,FALSE) -> 89.16 | E29: =VLOOKUP($A29,HAVERD!$A:$FM,E$2,FALSE) -> 89.34 | F29: =VLOOKUP($A29,HAVERD!$A:$FM,F$2,FALSE) -> 90.08 | G29: =VLOOKUP($A29,HAVERD!$A:$FM,G$2,FALSE) -> 89.28 | H29: =VLOOKUP($A29,HAVERD!$A:$FM,H$2,FALSE) -> 90.26 | I29: =VLOOKUP($A29,HAVERD!$A:$FM,I$2,FALSE) -> 91.7 | ... AW29: =VLOOKUP($A29,HAVERD!$A:$FM,AW$2,FALSE) -> 65.53 | AZ29: =AZ12 -> 46181 | BA29: =_xlfn.IFNA(VLOOKUP($AZ29,HAVERD!$A:$FM,BA$2,FALSE),"") -> 105.04 | BB29: =_xlfn.IFNA(VLOOKUP($AZ29,HAVERD!$A:$FM,BB$2,FALSE),"") -> 102.55 | BC29: =_xlfn.IFNA(VLOOKUP($AZ29,HAVERD!$A:$FM,BC$2,FALSE),"") -> 104.44 | BD29: =_xlfn.IFNA(VLOOKUP($AZ29,HAVERD!$A:$FM,BD$2,FALSE),"") -> 105.7 | BE29: =_xlfn.IFNA(VLOOKUP($AZ29,HAVERD!$A:$FM,BE$2,FALSE),"") -> 107.74 | BF29: =_xlfn.IFNA(VLOOKUP($AZ29,HAVERD!$A:$FM,BF$2,FALSE),"") -> 108 | BG29: =_xlfn.IFNA(VLOOKUP($AZ29,HAVERD!$A:$FM,BG$2,FALSE),"") -> 104.16 | BH29: =_xlfn.IFNA(VLOOKUP($AZ29,HAVERD!$A:$FM,BH$2,FALSE),"") -> 104.91 | ... CV29: =_xlfn.IFNA(VLOOKUP($AZ29,HAVERD!$A:$FM,CV$2,FALSE),"") -> 60.86
A30: =A13 -> 46125 | B30: =VLOOKUP($A30,HAVERD!$A:$FM,B$2,FALSE) -> 91.62 | C30: =VLOOKUP($A30,HAVERD!$A:$FM,C$2,FALSE) -> 93.82 | D30: =VLOOKUP($A30,HAVERD!$A:$FM,D$2,FALSE) -> 93.72 | E30: =VLOOKUP($A30,HAVERD!$A:$FM,E$2,FALSE) -> 93.78 | F30: =VLOOKUP($A30,HAVERD!$A:$FM,F$2,FALSE) -> 94.48 | G30: =VLOOKUP($A30,HAVERD!$A:$FM,G$2,FALSE) -> 92.54 | H30: =VLOOKUP($A30,HAVERD!$A:$FM,H$2,FALSE) -> 93.53 | I30: =VLOOKUP($A30,HAVERD!$A:$FM,I$2,FALSE) -> 95 | ... AW30: =VLOOKUP($A30,HAVERD!$A:$FM,AW$2,FALSE) -> 66.48 | AZ30: =AZ13 -> 46182 | BA30: =_xlfn.IFNA(VLOOKUP($AZ30,HAVERD!$A:$FM,BA$2,FALSE),"") -> 102.02 | BB30: =_xlfn.IFNA(VLOOKUP($AZ30,HAVERD!$A:$FM,BB$2,FALSE),"") -> 98.72 | BC30: =_xlfn.IFNA(VLOOKUP($AZ30,HAVERD!$A:$FM,BC$2,FALSE),"") -> 102.06 | BD30: =_xlfn.IFNA(VLOOKUP($AZ30,HAVERD!$A:$FM,BD$2,FALSE),"") -> 103.82 | BE30: =_xlfn.IFNA(VLOOKUP($AZ30,HAVERD!$A:$FM,BE$2,FALSE),"") -> 106.03 | BF30: =_xlfn.IFNA(VLOOKUP($AZ30,HAVERD!$A:$FM,BF$2,FALSE),"") -> 106.64 | BG30: =_xlfn.IFNA(VLOOKUP($AZ30,HAVERD!$A:$FM,BG$2,FALSE),"") -> 102.98 | BH30: =_xlfn.IFNA(VLOOKUP($AZ30,HAVERD!$A:$FM,BH$2,FALSE),"") -> 103.72 | ... CV30: =_xlfn.IFNA(VLOOKUP($AZ30,HAVERD!$A:$FM,CV$2,FALSE),"") -> 60.5
A31: =A14 -> 46126 | B31: =VLOOKUP($A31,HAVERD!$A:$FM,B$2,FALSE) -> 87.27 | C31: =VLOOKUP($A31,HAVERD!$A:$FM,C$2,FALSE) -> 90.78 | D31: =VLOOKUP($A31,HAVERD!$A:$FM,D$2,FALSE) -> 88.88 | E31: =VLOOKUP($A31,HAVERD!$A:$FM,E$2,FALSE) -> 89.06 | F31: =VLOOKUP($A31,HAVERD!$A:$FM,F$2,FALSE) -> 89.76 | G31: =VLOOKUP($A31,HAVERD!$A:$FM,G$2,FALSE) -> 89.58 | H31: =VLOOKUP($A31,HAVERD!$A:$FM,H$2,FALSE) -> 90.54 | I31: =VLOOKUP($A31,HAVERD!$A:$FM,I$2,FALSE) -> 91.99 | ... AW31: =VLOOKUP($A31,HAVERD!$A:$FM,AW$2,FALSE) -> 65.98 | AZ31: =AZ14 -> 46183 | BA31: =_xlfn.IFNA(VLOOKUP($AZ31,HAVERD!$A:$FM,BA$2,FALSE),"") -> 104.07 | BB31: =_xlfn.IFNA(VLOOKUP($AZ31,HAVERD!$A:$FM,BB$2,FALSE),"") -> 100.98 | BC31: =_xlfn.IFNA(VLOOKUP($AZ31,HAVERD!$A:$FM,BC$2,FALSE),"") -> 104.1 | BD31: =_xlfn.IFNA(VLOOKUP($AZ31,HAVERD!$A:$FM,BD$2,FALSE),"") -> 106.04 | BE31: =_xlfn.IFNA(VLOOKUP($AZ31,HAVERD!$A:$FM,BE$2,FALSE),"") -> 108.39 | BF31: =_xlfn.IFNA(VLOOKUP($AZ31,HAVERD!$A:$FM,BF$2,FALSE),"") -> 109.26 | BG31: =_xlfn.IFNA(VLOOKUP($AZ31,HAVERD!$A:$FM,BG$2,FALSE),"") -> 104.25 | BH31: =_xlfn.IFNA(VLOOKUP($AZ31,HAVERD!$A:$FM,BH$2,FALSE),"") -> 104.99 | ... CV31: =_xlfn.IFNA(VLOOKUP($AZ31,HAVERD!$A:$FM,CV$2,FALSE),"") -> 61.04
A32: =A15 -> 46127 | B32: =VLOOKUP($A32,HAVERD!$A:$FM,B$2,FALSE) -> 84.72 | C32: =VLOOKUP($A32,HAVERD!$A:$FM,C$2,FALSE) -> 87.84 | D32: =VLOOKUP($A32,HAVERD!$A:$FM,D$2,FALSE) -> 86.99 | E32: =VLOOKUP($A32,HAVERD!$A:$FM,E$2,FALSE) -> 87.09 | F32: =VLOOKUP($A32,HAVERD!$A:$FM,F$2,FALSE) -> 87.85 | G32: =VLOOKUP($A32,HAVERD!$A:$FM,G$2,FALSE) -> 88.02 | H32: =VLOOKUP($A32,HAVERD!$A:$FM,H$2,FALSE) -> 88.98 | I32: =VLOOKUP($A32,HAVERD!$A:$FM,I$2,FALSE) -> 90.41 | ... AW32: =VLOOKUP($A32,HAVERD!$A:$FM,AW$2,FALSE) -> 66.01 | AZ32: =AZ15 -> 46184 | BA32: =_xlfn.IFNA(VLOOKUP($AZ32,HAVERD!$A:$FM,BA$2,FALSE),"") -> 103.48 | BB32: =_xlfn.IFNA(VLOOKUP($AZ32,HAVERD!$A:$FM,BB$2,FALSE),"") -> 100.06 | BC32: =_xlfn.IFNA(VLOOKUP($AZ32,HAVERD!$A:$FM,BC$2,FALSE),"") -> 103.64 | BD32: =_xlfn.IFNA(VLOOKUP($AZ32,HAVERD!$A:$FM,BD$2,FALSE),"") -> 105.84 | BE32: =_xlfn.IFNA(VLOOKUP($AZ32,HAVERD!$A:$FM,BE$2,FALSE),"") -> 108.35 | BF32: =_xlfn.IFNA(VLOOKUP($AZ32,HAVERD!$A:$FM,BF$2,FALSE),"") -> 109.5 | BG32: =_xlfn.IFNA(VLOOKUP($AZ32,HAVERD!$A:$FM,BG$2,FALSE),"") -> 105.58 | BH32: =_xlfn.IFNA(VLOOKUP($AZ32,HAVERD!$A:$FM,BH$2,FALSE),"") -> 106.33 | ... CV32: =_xlfn.IFNA(VLOOKUP($AZ32,HAVERD!$A:$FM,CV$2,FALSE),"") -> 61.24
A33: =A16 -> 46128 | B33: =VLOOKUP($A33,HAVERD!$A:$FM,B$2,FALSE) -> 87.26 | C33: =VLOOKUP($A33,HAVERD!$A:$FM,C$2,FALSE) -> 90.24 | D33: =VLOOKUP($A33,HAVERD!$A:$FM,D$2,FALSE) -> 88.73 | E33: =VLOOKUP($A33,HAVERD!$A:$FM,E$2,FALSE) -> 89.13 | F33: =VLOOKUP($A33,HAVERD!$A:$FM,F$2,FALSE) -> 89.98 | G33: =VLOOKUP($A33,HAVERD!$A:$FM,G$2,FALSE) -> 91.3 | H33: =VLOOKUP($A33,HAVERD!$A:$FM,H$2,FALSE) -> 92.28 | I33: =VLOOKUP($A33,HAVERD!$A:$FM,I$2,FALSE) -> 93.74 | ... AW33: =VLOOKUP($A33,HAVERD!$A:$FM,AW$2,FALSE) -> 64.46 | AZ33: =AZ16 -> 46185 | BA33: =_xlfn.IFNA(VLOOKUP($AZ33,HAVERD!$A:$FM,BA$2,FALSE),"") -> 99.1 | BB33: =_xlfn.IFNA(VLOOKUP($AZ33,HAVERD!$A:$FM,BB$2,FALSE),"") -> 96.43 | BC33: =_xlfn.IFNA(VLOOKUP($AZ33,HAVERD!$A:$FM,BC$2,FALSE),"") -> 98.16 | BD33: =_xlfn.IFNA(VLOOKUP($AZ33,HAVERD!$A:$FM,BD$2,FALSE),"") -> 101.17 | BE33: =_xlfn.IFNA(VLOOKUP($AZ33,HAVERD!$A:$FM,BE$2,FALSE),"") -> 103.87 | BF33: =_xlfn.IFNA(VLOOKUP($AZ33,HAVERD!$A:$FM,BF$2,FALSE),"") -> 105.12 | BG33: =_xlfn.IFNA(VLOOKUP($AZ33,HAVERD!$A:$FM,BG$2,FALSE),"") -> 101 | BH33: =_xlfn.IFNA(VLOOKUP($AZ33,HAVERD!$A:$FM,BH$2,FALSE),"") -> 101.74 | ... CV33: =_xlfn.IFNA(VLOOKUP($AZ33,HAVERD!$A:$FM,CV$2,FALSE),"") -> 62.02
A34: =A17 -> 46129 | B34: =VLOOKUP($A34,HAVERD!$A:$FM,B$2,FALSE) -> 82.28 | C34: =VLOOKUP($A34,HAVERD!$A:$FM,C$2,FALSE) -> 85 | D34: =VLOOKUP($A34,HAVERD!$A:$FM,D$2,FALSE) -> 83.5 | E34: =VLOOKUP($A34,HAVERD!$A:$FM,E$2,FALSE) -> 83.9 | F34: =VLOOKUP($A34,HAVERD!$A:$FM,F$2,FALSE) -> 84.8 | G34: =VLOOKUP($A34,HAVERD!$A:$FM,G$2,FALSE) -> 86.67 | H34: =VLOOKUP($A34,HAVERD!$A:$FM,H$2,FALSE) -> 87.62 | I34: =VLOOKUP($A34,HAVERD!$A:$FM,I$2,FALSE) -> 89.05 | ... AW34: =VLOOKUP($A34,HAVERD!$A:$FM,AW$2,FALSE) -> 64.18 | AZ34: =AZ17 -> 46188 | BA34: =_xlfn.IFNA(VLOOKUP($AZ34,HAVERD!$A:$FM,BA$2,FALSE),"") -> 92.84 | BB34: =_xlfn.IFNA(VLOOKUP($AZ34,HAVERD!$A:$FM,BB$2,FALSE),"") -> 90.5 | BC34: =_xlfn.IFNA(VLOOKUP($AZ34,HAVERD!$A:$FM,BC$2,FALSE),"") -> 93.63 | BD34: =_xlfn.IFNA(VLOOKUP($AZ34,HAVERD!$A:$FM,BD$2,FALSE),"") -> 95.14 | BE34: =_xlfn.IFNA(VLOOKUP($AZ34,HAVERD!$A:$FM,BE$2,FALSE),"") -> 98.05 | BF34: =_xlfn.IFNA(VLOOKUP($AZ34,HAVERD!$A:$FM,BF$2,FALSE),"") -> 99.36 | BG34: =_xlfn.IFNA(VLOOKUP($AZ34,HAVERD!$A:$FM,BG$2,FALSE),"") -> 96.05 | BH34: =_xlfn.IFNA(VLOOKUP($AZ34,HAVERD!$A:$FM,BH$2,FALSE),"") -> 96.77 | ... CV34: =_xlfn.IFNA(VLOOKUP($AZ34,HAVERD!$A:$FM,CV$2,FALSE),"") -> 61.53
... A37: =A20 -> 46134 | B37: =VLOOKUP($A37,HAVERD!$A:$FM,B$2,FALSE) -> 88.36 | C37: =VLOOKUP($A37,HAVERD!$A:$FM,C$2,FALSE) -> 91.08 | D37: =VLOOKUP($A37,HAVERD!$A:$FM,D$2,FALSE) -> 89.99 | E37: =VLOOKUP($A37,HAVERD!$A:$FM,E$2,FALSE) -> 90.28 | F37: =VLOOKUP($A37,HAVERD!$A:$FM,F$2,FALSE) -> 91.04 | G37: =VLOOKUP($A37,HAVERD!$A:$FM,G$2,FALSE) -> 92 | H37: =VLOOKUP($A37,HAVERD!$A:$FM,H$2,FALSE) -> 92.98 | I37: =VLOOKUP($A37,HAVERD!$A:$FM,I$2,FALSE) -> 94.46 | ... AW37: =VLOOKUP($A37,HAVERD!$A:$FM,AW$2,FALSE) -> 63.94 | AZ37: =AZ20 -> 46191 | BA37: =_xlfn.IFNA(VLOOKUP($AZ37,HAVERD!$A:$FM,BA$2,FALSE),"") -> 91.46 | BB37: =_xlfn.IFNA(VLOOKUP($AZ37,HAVERD!$A:$FM,BB$2,FALSE),"") -> 88.8 | BC37: =_xlfn.IFNA(VLOOKUP($AZ37,HAVERD!$A:$FM,BC$2,FALSE),"") -> 92.06 | BD37: =_xlfn.IFNA(VLOOKUP($AZ37,HAVERD!$A:$FM,BD$2,FALSE),"") -> 93.81 | BE37: =_xlfn.IFNA(VLOOKUP($AZ37,HAVERD!$A:$FM,BE$2,FALSE),"") -> 96.54 | BF37: =_xlfn.IFNA(VLOOKUP($AZ37,HAVERD!$A:$FM,BF$2,FALSE),"") -> 98.24 | BG37: =_xlfn.IFNA(VLOOKUP($AZ37,HAVERD!$A:$FM,BG$2,FALSE),"") -> 95.27 | BH37: =_xlfn.IFNA(VLOOKUP($AZ37,HAVERD!$A:$FM,BH$2,FALSE),"") -> 95.99 | ... CV37: =_xlfn.IFNA(VLOOKUP($AZ37,HAVERD!$A:$FM,CV$2,FALSE),"") -> 62.4
A39: Average | AZ39: Average
A40: Month | B40: =MONTH(B20) -> 4 | C40: =MONTH(C20) -> 5 | D40: =MONTH(D20) -> 6 | E40: =MONTH(E20) -> 7 | F40: =MONTH(F20) -> 8 | G40: =MONTH(G20) -> 9 | H40: =MONTH(H20) -> 10 | I40: =MONTH(I20) -> 11 | ... AW40: =MONTH(AW20) -> 3 | AZ40: Month | BA40: =MONTH(BA20) -> 6 | BB40: =MONTH(BB20) -> 7 | BC40: =MONTH(BC20) -> 8 | BD40: =MONTH(BD20) -> 9 | BE40: =MONTH(BE20) -> 10 | BF40: =MONTH(BF20) -> 11 | BG40: =MONTH(BG20) -> 12 | BH40: =MONTH(BH20) -> 1 | ... CV40: =MONTH(CV20) -> 5
A41: Year | B41: =YEAR(B20) -> 2026 | C41: =YEAR(C20) -> 2026 | D41: =YEAR(D20) -> 2026 | E41: =YEAR(E20) -> 2026 | F41: =YEAR(F20) -> 2026 | G41: =YEAR(G20) -> 2026 | H41: =YEAR(H20) -> 2026 | I41: =YEAR(I20) -> 2026 | ... AW41: =YEAR(AW20) -> 2030 | AZ41: Year | BA41: =YEAR(BA20) -> 2026 | BB41: =YEAR(BB20) -> 2026 | BC41: =YEAR(BC20) -> 2026 | BD41: =YEAR(BD20) -> 2026 | BE41: =YEAR(BE20) -> 2026 | BF41: =YEAR(BF20) -> 2026 | BG41: =YEAR(BG20) -> 2026 | BH41: =YEAR(BH20) -> 2027 | ... CV41: =YEAR(CV20) -> 2030
A42: YYYYMM | B42: =B41*100+B40 -> 202604 | C42: =C41*100+C40 -> 202605 | D42: =D41*100+D40 -> 202606 | E42: =E41*100+E40 -> 202607 | F42: =F41*100+F40 -> 202608 | G42: =G41*100+G40 -> 202609 | H42: =H41*100+H40 -> 202610 | I42: =I41*100+I40 -> 202611 | ... AW42: =AW41*100+AW40 -> 203003 | AZ42: YYYYMM | BA42: =BA41*100+BA40 -> 202606 | BB42: =BB41*100+BB40 -> 202607 | BC42: =BC41*100+BC40 -> 202608 | BD42: =BD41*100+BD40 -> 202609 | BE42: =BE41*100+BE40 -> 202610 | BF42: =BF41*100+BF40 -> 202611 | BG42: =BG41*100+BG40 -> 202612 | BH42: =BH41*100+BH40 -> 202701 | ... CV42: =CV41*100+CV40 -> 203005
A43: Quarter | B43: =IF(B40<4,1,IF(B40<7,2,IF(B40<10,3,4))) -> 2 | C43: =IF(C40<4,1,IF(C40<7,2,IF(C40<10,3,4))) -> 2 | D43: =IF(D40<4,1,IF(D40<7,2,IF(D40<10,3,4))) -> 2 | E43: =IF(E40<4,1,IF(E40<7,2,IF(E40<10,3,4))) -> 3 | F43: =IF(F40<4,1,IF(F40<7,2,IF(F40<10,3,4))) -> 3 | G43: =IF(G40<4,1,IF(G40<7,2,IF(G40<10,3,4))) -> 3 | H43: =IF(H40<4,1,IF(H40<7,2,IF(H40<10,3,4))) -> 4 | I43: =IF(I40<4,1,IF(I40<7,2,IF(I40<10,3,4))) -> 4 | ... AW43: =IF(AW40<4,1,IF(AW40<7,2,IF(AW40<10,3,4))) -> 1 | AZ43: Quarter | BA43: =IF(BA40<4,1,IF(BA40<7,2,IF(BA40<10,3,4))) -> 2 | BB43: =IF(BB40<4,1,IF(BB40<7,2,IF(BB40<10,3,4))) -> 3 | BC43: =IF(BC40<4,1,IF(BC40<7,2,IF(BC40<10,3,4))) -> 3 | BD43: =IF(BD40<4,1,IF(BD40<7,2,IF(BD40<10,3,4))) -> 3 | BE43: =IF(BE40<4,1,IF(BE40<7,2,IF(BE40<10,3,4))) -> 4 | BF43: =IF(BF40<4,1,IF(BF40<7,2,IF(BF40<10,3,4))) -> 4 | BG43: =IF(BG40<4,1,IF(BG40<7,2,IF(BG40<10,3,4))) -> 4 | BH43: =IF(BH40<4,1,IF(BH40<7,2,IF(BH40<10,3,4))) -> 1 | ... CV43: =IF(CV40<4,1,IF(CV40<7,2,IF(CV40<10,3,4))) -> 2
A44: YYYYQQ | B44: =B41*100+B43 -> 202602 | C44: =C41*100+C43 -> 202602 | D44: =D41*100+D43 -> 202602 | E44: =E41*100+E43 -> 202603 | F44: =F41*100+F43 -> 202603 | G44: =G41*100+G43 -> 202603 | H44: =H41*100+H43 -> 202604 | I44: =I41*100+I43 -> 202604 | ... AW44: =AW41*100+AW43 -> 203001 | AZ44: YYYYQQ | BA44: =BA41*100+BA43 -> 202602 | BB44: =BB41*100+BB43 -> 202603 | BC44: =BC41*100+BC43 -> 202603 | BD44: =BD41*100+BD43 -> 202603 | BE44: =BE41*100+BE43 -> 202604 | BF44: =BF41*100+BF43 -> 202604 | BG44: =BG41*100+BG43 -> 202604 | BH44: =BH41*100+BH43 -> 202701 | ... CV44: =CV41*100+CV43 -> 203002
A45: Average | B45: =AVERAGE(B23:B37) -> #N/A | C45: =AVERAGE(C23:C37) -> #N/A | D45: =AVERAGE(D23:D37) -> #N/A | E45: =AVERAGE(E23:E37) -> #N/A | F45: =AVERAGE(F23:F37) -> #N/A | G45: =AVERAGE(G23:G37) -> #N/A | H45: =AVERAGE(H23:H37) -> #N/A | I45: =AVERAGE(I23:I37) -> #N/A | ... AW45: =AVERAGE(AW23:AW37) -> #N/A | AZ45: Average | BA45: =AVERAGE(BA23:BA37) -> 99.796 | BB45: =AVERAGE(BB23:BB37) -> 97.08 | BC45: =AVERAGE(BC23:BC37) -> 99.620667 | BD45: =AVERAGE(BD23:BD37) -> 101.18267 | BE45: =AVERAGE(BE23:BE37) -> 103.456 | BF45: =AVERAGE(BF23:BF37) -> 104.58933 | BG45: =AVERAGE(BG23:BG37) -> 100.57 | BH45: =AVERAGE(BH23:BH37) -> 101.30533 | ... CV45: =AVERAGE(CV23:CV37) -> 61.495333
A47: Quarterly series | AZ47: Quarterly series
B48: =B44 -> 202602 | C48: =IF(RIGHT(B48)="4",B48+97,B48+1) -> 202603 | D48: =IF(RIGHT(C48)="4",C48+97,C48+1) -> 202604 | E48: =IF(RIGHT(D48)="4",D48+97,D48+1) -> 202701 | F48: =IF(RIGHT(E48)="4",E48+97,E48+1) -> 202702 | G48: =IF(RIGHT(F48)="4",F48+97,F48+1) -> 202703 | H48: =IF(RIGHT(G48)="4",G48+97,G48+1) -> 202704 | I48: =IF(RIGHT(H48)="4",H48+97,H48+1) -> 202801 | J48: =IF(RIGHT(I48)="4",I48+97,I48+1) -> 202802 | ... R48: =IF(RIGHT(Q48)="4",Q48+97,Q48+1) -> 203002 | BA48: =BA44 -> 202602 | BB48: =IF(RIGHT(BA48)="4",BA48+97,BA48+1) -> 202603 | BC48: =IF(RIGHT(BB48)="4",BB48+97,BB48+1) -> 202604 | BD48: =IF(RIGHT(BC48)="4",BC48+97,BC48+1) -> 202701 | BE48: =IF(RIGHT(BD48)="4",BD48+97,BD48+1) -> 202702 | BF48: =IF(RIGHT(BE48)="4",BE48+97,BE48+1) -> 202703 | BG48: =IF(RIGHT(BF48)="4",BF48+97,BF48+1) -> 202704 | BH48: =IF(RIGHT(BG48)="4",BG48+97,BG48+1) -> 202801 | BI48: =IF(RIGHT(BH48)="4",BH48+97,BH48+1) -> 202802 | ... BP48: =IF(RIGHT(BO48)="4",BO48+97,BO48+1) -> 203001
A49: =A1 -> April 2026 MPR | B49: =AVERAGEIF($B$44:$AW$44,B48,$B$45:$AW$45) -> #N/A | C49: =AVERAGEIF($B$44:$AW$44,C48,$B$45:$AW$45) -> #N/A | D49: =AVERAGEIF($B$44:$AW$44,D48,$B$45:$AW$45) -> #N/A | E49: =AVERAGEIF($B$44:$AW$44,E48,$B$45:$AW$45) -> #N/A | F49: =AVERAGEIF($B$44:$AW$44,F48,$B$45:$AW$45) -> #N/A | G49: =AVERAGEIF($B$44:$AW$44,G48,$B$45:$AW$45) -> #N/A | H49: =AVERAGEIF($B$44:$AW$44,H48,$B$45:$AW$45) -> #N/A | I49: =AVERAGEIF($B$44:$AW$44,I48,$B$45:$AW$45) -> #N/A | ... R49: =AVERAGEIF($B$44:$AW$44,R48,$B$45:$AW$45) -> #DIV/0! | AZ49: =AZ1 -> Current market curve | BA49: =AVERAGEIF($BA$44:$CV$44,BA48,$BA$45:$CV$45) -> 99.796 | BB49: =AVERAGEIF($BA$44:$CV$44,BB48,$BA$45:$CV$45) -> 99.294444 | BC49: =AVERAGEIF($BA$44:$CV$44,BC48,$BA$45:$CV$45) -> 102.87178 | BD49: =AVERAGEIF($BA$44:$CV$44,BD48,$BA$45:$CV$45) -> 94.423333 | BE49: =AVERAGEIF($BA$44:$CV$44,BE48,$BA$45:$CV$45) -> 75.485778 | BF49: =AVERAGEIF($BA$44:$CV$44,BF48,$BA$45:$CV$45) -> 77.499778 | BG49: =AVERAGEIF($BA$44:$CV$44,BG48,$BA$45:$CV$45) -> 80.087778 | BH49: =AVERAGEIF($BA$44:$CV$44,BH48,$BA$45:$CV$45) -> 74.928444 | ... BP49: =AVERAGEIF($BA$44:$CV$44,BP48,$BA$45:$CV$45) -> 67.441556
AZ51: Comparison - monthly
BA52: 44927 | BB52: 44958 | BC52: 44986 | BD52: 45017 | BE52: 45047 | BF52: 45078 | BG52: 45108 | BH52: 45139 | BI52: 45170 | BJ52: 45200 | BK52: 45231 | BL52: 45261 | BM52: 45292 | BN52: 45323 | BO52: 45352 | BP52: 45383 | BQ52: 45413 | BR52: 45444 | BS52: 45474 | BT52: 45505 | BU52: 45536 | BV52: 45566 | BW52: 45597 | BX52: 45627 | BY52: 45658 | BZ52: 45689 | CA52: 45717 | CB52: 45748 | CC52: 45778 | CD52: 45809 | CE52: 45839 | CF52: 45870 | CG52: 45901 | CH52: 45931 | CI52: 45962 | CJ52: 45992 | CK52: 46023 | CL52: 46054 | CM52: 46082 | CN52: 46113 | CO52: 46143 | CP52: 46174 | CQ52: 46204 | CR52: 46235 | CS52: 46266 | CT52: 46296 | CU52: 46327 | CV52: 46357 | CW52: 46388 | CX52: 46419 | CY52: 46447 | CZ52: 46478 | DA52: 46508 | DB52: 46539 | DC52: 46569 | DD52: 46600 | DE52: 46631 | DF52: 46661 | DG52: 46692 | DH52: 46722 | DI52: 46753 | DJ52: 46784 | DK52: 46813 | DL52: 46844 | DM52: 46874 | DN52: 46905 | DO52: 46935 | DP52: 46966 | DQ52: 46997 | DR52: 47027 | DS52: 47058 | DT52: 47088 | DU52: 47119 | DV52: 47150 | DW52: 47178 | DX52: 47209 | DY52: 47239 | DZ52: 47270
BA53: =MONTH(BA52) -> 1 | BB53: =MONTH(BB52) -> 2 | BC53: =MONTH(BC52) -> 3 | BD53: =MONTH(BD52) -> 4 | BE53: =MONTH(BE52) -> 5 | BF53: =MONTH(BF52) -> 6 | BG53: =MONTH(BG52) -> 7 | BH53: =MONTH(BH52) -> 8 | ... DZ53: =MONTH(DZ52) -> 6
BA54: 202301 | BB54: =IF(BB53=1,BA54+89,BA54+1) -> 202302 | BC54: =IF(BC53=1,BB54+89,BB54+1) -> 202303 | BD54: =IF(BD53=1,BC54+89,BC54+1) -> 202304 | BE54: =IF(BE53=1,BD54+89,BD54+1) -> 202305 | BF54: =IF(BF53=1,BE54+89,BE54+1) -> 202306 | BG54: =IF(BG53=1,BF54+89,BF54+1) -> 202307 | BH54: =IF(BH53=1,BG54+89,BG54+1) -> 202308 | BI54: =IF(BI53=1,BH54+89,BH54+1) -> 202309 | ... DZ54: =IF(DZ53=1,DY54+89,DY54+1) -> 202906
AZ55: =A49 -> April 2026 MPR | BA55: =HLOOKUP(BA$54,$B$42:$AW$45,4,FALSE) -> #N/A | BB55: =HLOOKUP(BB$54,$B$42:$AW$45,4,FALSE) -> #N/A | BC55: =HLOOKUP(BC$54,$B$42:$AW$45,4,FALSE) -> #N/A | BD55: =HLOOKUP(BD$54,$B$42:$AW$45,4,FALSE) -> #N/A | BE55: =HLOOKUP(BE$54,$B$42:$AW$45,4,FALSE) -> #N/A | BF55: =HLOOKUP(BF$54,$B$42:$AW$45,4,FALSE) -> #N/A | BG55: =HLOOKUP(BG$54,$B$42:$AW$45,4,FALSE) -> #N/A | BH55: =HLOOKUP(BH$54,$B$42:$AW$45,4,FALSE) -> #N/A | ... DZ55: =HLOOKUP(DZ$54,$B$42:$AW$45,4,FALSE) -> #N/A
AZ56: =AZ49 -> Current market curve | BA56: =HLOOKUP(BA$54,$BA$42:$CV$45,4,FALSE) -> #N/A | BB56: =HLOOKUP(BB$54,$BA$42:$CV$45,4,FALSE) -> #N/A | BC56: =HLOOKUP(BC$54,$BA$42:$CV$45,4,FALSE) -> #N/A | BD56: =HLOOKUP(BD$54,$BA$42:$CV$45,4,FALSE) -> #N/A | BE56: =HLOOKUP(BE$54,$BA$42:$CV$45,4,FALSE) -> #N/A | BF56: =HLOOKUP(BF$54,$BA$42:$CV$45,4,FALSE) -> #N/A | BG56: =HLOOKUP(BG$54,$BA$42:$CV$45,4,FALSE) -> #N/A | BH56: =HLOOKUP(BH$54,$BA$42:$CV$45,4,FALSE) -> #N/A | ... DZ56: =HLOOKUP(DZ$54,$BA$42:$CV$45,4,FALSE) -> 59.66
AZ57: Difference | BP57: =BP56-BP55 -> #N/A | BQ57: =BQ56-BQ55 -> #N/A | BR57: =BR56-BR55 -> #N/A | BS57: =BS56-BS55 -> #N/A | BT57: =BT56-BT55 -> #N/A | BU57: =BU56-BU55 -> #N/A | BV57: =BV56-BV55 -> #N/A | BW57: =BW56-BW55 -> #N/A | ... DZ57: =DZ56-DZ55 -> #N/A
AZ58: Next 3 years
AZ60: Comparison - quarterly
BA61: 44927 | BB61: 45017 | BC61: 45108 | BD61: 45200 | BE61: 45292 | BF61: 45383 | BG61: 45474 | BH61: 45566 | BI61: 45658 | BJ61: 45748 | BK61: 45839 | BL61: 45931 | BM61: 46023 | BN61: 46113 | BO61: 46204 | BP61: 46296 | BQ61: 46388 | BR61: 46478 | BS61: 46569 | BT61: 46661 | BU61: 46753 | BV61: 46844 | BW61: 46935 | BX61: 47027 | BY61: 47119 | BZ61: 47209
BA62: 202301 | BB62: =IF(RIGHT(BA62)="4",BA62+97,BA62+1) -> 202302 | BC62: =IF(RIGHT(BB62)="4",BB62+97,BB62+1) -> 202303 | BD62: =IF(RIGHT(BC62)="4",BC62+97,BC62+1) -> 202304 | BE62: =IF(RIGHT(BD62)="4",BD62+97,BD62+1) -> 202401 | BF62: =IF(RIGHT(BE62)="4",BE62+97,BE62+1) -> 202402 | BG62: =IF(RIGHT(BF62)="4",BF62+97,BF62+1) -> 202403 | BH62: =IF(RIGHT(BG62)="4",BG62+97,BG62+1) -> 202404 | BI62: =IF(RIGHT(BH62)="4",BH62+97,BH62+1) -> 202501 | ... BZ62: =IF(RIGHT(BY62)="4",BY62+97,BY62+1) -> 202902
AZ63: =A49 -> April 2026 MPR | BA63: =HLOOKUP(BA$62,$B$48:$R$49,2,FALSE) -> #N/A | BB63: =HLOOKUP(BB$62,$B$48:$R$49,2,FALSE) -> #N/A | BC63: =HLOOKUP(BC$62,$B$48:$R$49,2,FALSE) -> #N/A | BD63: =HLOOKUP(BD$62,$B$48:$R$49,2,FALSE) -> #N/A | BE63: =HLOOKUP(BE$62,$B$48:$R$49,2,FALSE) -> #N/A | BF63: =HLOOKUP(BF$62,$B$48:$R$49,2,FALSE) -> #N/A | BG63: =HLOOKUP(BG$62,$B$48:$R$49,2,FALSE) -> #N/A | BH63: =HLOOKUP(BH$62,$B$48:$R$49,2,FALSE) -> #N/A | ... BZ63: =HLOOKUP(BZ$62,$B$48:$R$49,2,FALSE) -> #N/A
AZ64: =AZ49 -> Current market curve | BA64: =HLOOKUP(BA$62,$BA$48:$BQ$49,2,FALSE) -> #N/A | BB64: =HLOOKUP(BB$62,$BA$48:$BQ$49,2,FALSE) -> #N/A | BC64: =HLOOKUP(BC$62,$BA$48:$BQ$49,2,FALSE) -> #N/A | BD64: =HLOOKUP(BD$62,$BA$48:$BQ$49,2,FALSE) -> #N/A | BE64: =HLOOKUP(BE$62,$BA$48:$BQ$49,2,FALSE) -> #N/A | BF64: =HLOOKUP(BF$62,$BA$48:$BQ$49,2,FALSE) -> #N/A | BG64: =HLOOKUP(BG$62,$BA$48:$BQ$49,2,FALSE) -> #N/A | BH64: =HLOOKUP(BH$62,$BA$48:$BQ$49,2,FALSE) -> #N/A | ... BZ64: =HLOOKUP(BZ$62,$BA$48:$BQ$49,2,FALSE) -> 60.120889
AZ65: Difference | BG65: =BG64-BG63 -> #N/A | BH65: =BH64-BH63 -> #N/A | BI65: =BI64-BI63 -> #N/A | BJ65: =BJ64-BJ63 -> #N/A | BK65: =BK64-BK63 -> #N/A | BL65: =BL64-BL63 -> #N/A | BM65: =BM64-BM63 -> #N/A | BN65: =BN64-BN63 -> #N/A | ... BZ65: =BZ64-BZ63 -> #N/A
AZ66: Next 3 years

Sheet Market expectations - Oil
A1: ='Market pricing dates'!A2 -> April 2026 MPR | C1: ='Market pricing dates'!A12 -> 15 working days to 22 Apr 2026 | N1: ='Market pricing dates'!D2 -> Current market curve | P1: ='Market pricing dates'!D12 -> 15 working days to 18 Jun 2026
A2: Column # | B2: =HAVERD!FX$1 -> 180 | C2: =+B2+1 -> 181 | D2: =+C2+1 -> 182 | E2: =+D2+1 -> 183 | F2: =+E2+1 -> 184 | N2: Column # | O2: =HAVERD!FX$1 -> 180 | P2: =HAVERD!FY$1 -> 181 | Q2: =HAVERD!FZ$1 -> 182 | R2: =HAVERD!GA$1 -> 183 | S2: =HAVERD!GB$1 -> 184
A3: Months | B3: =HAVERD!FX$2 -> Oil - 1 | C3: =HAVERD!FY$2 -> Oil - 3 | D3: =HAVERD!FZ$2 -> Oil - 6 | E3: =HAVERD!GA$2 -> Oil - 12 | F3: =HAVERD!GB$2 -> Oil - 24 | N3: Months | O3: =HAVERD!FX$2 -> Oil - 1 | P3: =HAVERD!FY$2 -> Oil - 3 | Q3: =HAVERD!FZ$2 -> Oil - 6 | R3: =HAVERD!GA$2 -> Oil - 12 | S3: =HAVERD!GB$2 -> Oil - 24
A4: Days | C4: =365/4 -> 91.25 | D4: =365/2 -> 182.5 | E4: 365 | F4: =365*2 -> 730 | N4: Days | P4: =365/4 -> 91.25 | Q4: =365/2 -> 182.5 | R4: 365 | S4: =365*2 -> 730
A5: Dates | N5: Dates
A6: =A11-7 -> 46114 | B6: =A6 -> 46114 | C6: =$B6+C$4 -> 46205.25 | D6: =$B6+D$4 -> 46296.5 | E6: =$B6+E$4 -> 46479 | F6: =$B6+F$4 -> 46844 | N6: =N11-7 -> 46171 | O6: =N6 -> 46171 | P6: =$N6+P$4 -> 46262.25 | Q6: =$N6+Q$4 -> 46353.5 | R6: =$N6+R$4 -> 46536 | S6: =$N6+S$4 -> 46901
A7: =A12-7 -> 46115 | B7: =A7 -> 46115 | C7: =$B7+C$4 -> 46206.25 | D7: =$B7+D$4 -> 46297.5 | E7: =$B7+E$4 -> 46480 | F7: =$B7+F$4 -> 46845 | N7: =N12-7 -> 46174 | O7: =N7 -> 46174 | P7: =$N7+P$4 -> 46265.25 | Q7: =$N7+Q$4 -> 46356.5 | R7: =$N7+R$4 -> 46539 | S7: =$N7+S$4 -> 46904
A8: =A13-7 -> 46118 | B8: =A8 -> 46118 | C8: =$B8+C$4 -> 46209.25 | D8: =$B8+D$4 -> 46300.5 | E8: =$B8+E$4 -> 46483 | F8: =$B8+F$4 -> 46848 | N8: =N13-7 -> 46175 | O8: =N8 -> 46175 | P8: =$N8+P$4 -> 46266.25 | Q8: =$N8+Q$4 -> 46357.5 | R8: =$N8+R$4 -> 46540 | S8: =$N8+S$4 -> 46905
A9: =A14-7 -> 46119 | B9: =A9 -> 46119 | C9: =$B9+C$4 -> 46210.25 | D9: =$B9+D$4 -> 46301.5 | E9: =$B9+E$4 -> 46484 | F9: =$B9+F$4 -> 46849 | N9: =N14-7 -> 46176 | O9: =N9 -> 46176 | P9: =$N9+P$4 -> 46267.25 | Q9: =$N9+Q$4 -> 46358.5 | R9: =$N9+R$4 -> 46541 | S9: =$N9+S$4 -> 46906
A10: =A15-7 -> 46120 | B10: =A10 -> 46120 | C10: =$B10+C$4 -> 46211.25 | D10: =$B10+D$4 -> 46302.5 | E10: =$B10+E$4 -> 46485 | F10: =$B10+F$4 -> 46850 | N10: =N15-7 -> 46177 | O10: =N10 -> 46177 | P10: =$N10+P$4 -> 46268.25 | Q10: =$N10+Q$4 -> 46359.5 | R10: =$N10+R$4 -> 46542 | S10: =$N10+S$4 -> 46907
A11: =A16-7 -> 46121 | B11: =A11 -> 46121 | C11: =$B11+C$4 -> 46212.25 | D11: =$B11+D$4 -> 46303.5 | E11: =$B11+E$4 -> 46486 | F11: =$B11+F$4 -> 46851 | N11: =N16-7 -> 46178 | O11: =N11 -> 46178 | P11: =$N11+P$4 -> 46269.25 | Q11: =$N11+Q$4 -> 46360.5 | R11: =$N11+R$4 -> 46543 | S11: =$N11+S$4 -> 46908
A12: =A17-7 -> 46122 | B12: =A12 -> 46122 | C12: =$B12+C$4 -> 46213.25 | D12: =$B12+D$4 -> 46304.5 | E12: =$B12+E$4 -> 46487 | F12: =$B12+F$4 -> 46852 | N12: =N17-7 -> 46181 | O12: =N12 -> 46181 | P12: =$N12+P$4 -> 46272.25 | Q12: =$N12+Q$4 -> 46363.5 | R12: =$N12+R$4 -> 46546 | S12: =$N12+S$4 -> 46911
A13: =A18-7 -> 46125 | B13: =A13 -> 46125 | C13: =$B13+C$4 -> 46216.25 | D13: =$B13+D$4 -> 46307.5 | E13: =$B13+E$4 -> 46490 | F13: =$B13+F$4 -> 46855 | N13: =N18-7 -> 46182 | O13: =N13 -> 46182 | P13: =$N13+P$4 -> 46273.25 | Q13: =$N13+Q$4 -> 46364.5 | R13: =$N13+R$4 -> 46547 | S13: =$N13+S$4 -> 46912
A14: =A19-7 -> 46126 | B14: =A14 -> 46126 | C14: =$B14+C$4 -> 46217.25 | D14: =$B14+D$4 -> 46308.5 | E14: =$B14+E$4 -> 46491 | F14: =$B14+F$4 -> 46856 | N14: =N19-7 -> 46183 | O14: =N14 -> 46183 | P14: =$N14+P$4 -> 46274.25 | Q14: =$N14+Q$4 -> 46365.5 | R14: =$N14+R$4 -> 46548 | S14: =$N14+S$4 -> 46913
A15: =A20-7 -> 46127 | B15: =A15 -> 46127 | C15: =$B15+C$4 -> 46218.25 | D15: =$B15+D$4 -> 46309.5 | E15: =$B15+E$4 -> 46492 | F15: =$B15+F$4 -> 46857 | N15: =N20-7 -> 46184 | O15: =N15 -> 46184 | P15: =$N15+P$4 -> 46275.25 | Q15: =$N15+Q$4 -> 46366.5 | R15: =$N15+R$4 -> 46549 | S15: =$N15+S$4 -> 46914
A16: ='Market pricing dates'!B5 -> 46128 | B16: =A16 -> 46128 | C16: =$B16+C$4 -> 46219.25 | D16: =$B16+D$4 -> 46310.5 | E16: =$B16+E$4 -> 46493 | F16: =$B16+F$4 -> 46858 | N16: ='Market pricing dates'!E5 -> 46185 | O16: =N16 -> 46185 | P16: =$N16+P$4 -> 46276.25 | Q16: =$N16+Q$4 -> 46367.5 | R16: =$N16+R$4 -> 46550 | S16: =$N16+S$4 -> 46915
A17: ='Market pricing dates'!B6 -> 46129 | B17: =A17 -> 46129 | C17: =$B17+C$4 -> 46220.25 | D17: =$B17+D$4 -> 46311.5 | E17: =$B17+E$4 -> 46494 | F17: =$B17+F$4 -> 46859 | N17: ='Market pricing dates'!E6 -> 46188 | O17: =N17 -> 46188 | P17: =$N17+P$4 -> 46279.25 | Q17: =$N17+Q$4 -> 46370.5 | R17: =$N17+R$4 -> 46553 | S17: =$N17+S$4 -> 46918
A18: ='Market pricing dates'!B7 -> 46132 | B18: =A18 -> 46132 | C18: =$B18+C$4 -> 46223.25 | D18: =$B18+D$4 -> 46314.5 | E18: =$B18+E$4 -> 46497 | F18: =$B18+F$4 -> 46862 | N18: ='Market pricing dates'!E7 -> 46189 | O18: =N18 -> 46189 | P18: =$N18+P$4 -> 46280.25 | Q18: =$N18+Q$4 -> 46371.5 | R18: =$N18+R$4 -> 46554 | S18: =$N18+S$4 -> 46919
A19: ='Market pricing dates'!B8 -> 46133 | B19: =A19 -> 46133 | C19: =$B19+C$4 -> 46224.25 | D19: =$B19+D$4 -> 46315.5 | E19: =$B19+E$4 -> 46498 | F19: =$B19+F$4 -> 46863 | N19: ='Market pricing dates'!E8 -> 46190 | O19: =N19 -> 46190 | P19: =$N19+P$4 -> 46281.25 | Q19: =$N19+Q$4 -> 46372.5 | R19: =$N19+R$4 -> 46555 | S19: =$N19+S$4 -> 46920
A20: ='Market pricing dates'!B9 -> 46134 | B20: =A20 -> 46134 | C20: =$B20+C$4 -> 46225.25 | D20: =$B20+D$4 -> 46316.5 | E20: =$B20+E$4 -> 46499 | F20: =$B20+F$4 -> 46864 | N20: ='Market pricing dates'!E9 -> 46191 | O20: =N20 -> 46191 | P20: =$N20+P$4 -> 46282.25 | Q20: =$N20+Q$4 -> 46373.5 | R20: =$N20+R$4 -> 46556 | S20: =$N20+S$4 -> 46921
A22: Oil futures | N22: Oil futures
A23: =A6 -> 46114 | B23: =VLOOKUP($A23,HAVERD!$A:$GB,B$2,FALSE) -> 109.03 | C23: =VLOOKUP($A23,HAVERD!$A:$GB,C$2,FALSE) -> 91.43 | D23: =VLOOKUP($A23,HAVERD!$A:$GB,D$2,FALSE) -> 80.47 | E23: =VLOOKUP($A23,HAVERD!$A:$GB,E$2,FALSE) -> 75.07 | F23: =VLOOKUP($A23,HAVERD!$A:$GB,F$2,FALSE) -> 72.29 | N23: =N6 -> 46171 | O23: =_xlfn.IFNA(VLOOKUP($N23,HAVERD!$A:$GB,O$2,FALSE),"") -> 92.05 | P23: =_xlfn.IFNA(VLOOKUP($N23,HAVERD!$A:$GB,P$2,FALSE),"") -> 89.11 | Q23: =_xlfn.IFNA(VLOOKUP($N23,HAVERD!$A:$GB,Q$2,FALSE),"") -> 84.18 | R23: =_xlfn.IFNA(VLOOKUP($N23,HAVERD!$A:$GB,R$2,FALSE),"") -> 78.93 | S23: =_xlfn.IFNA(VLOOKUP($N23,HAVERD!$A:$GB,S$2,FALSE),"") -> 75.39
A24: =A7 -> 46115 | B24: =VLOOKUP($A24,HAVERD!$A:$GB,B$2,FALSE) -> #N/A | C24: =VLOOKUP($A24,HAVERD!$A:$GB,C$2,FALSE) -> #N/A | D24: =VLOOKUP($A24,HAVERD!$A:$GB,D$2,FALSE) -> #N/A | E24: =VLOOKUP($A24,HAVERD!$A:$GB,E$2,FALSE) -> #N/A | F24: =VLOOKUP($A24,HAVERD!$A:$GB,F$2,FALSE) -> #N/A | N24: =N7 -> 46174 | O24: =_xlfn.IFNA(VLOOKUP($N24,HAVERD!$A:$GB,O$2,FALSE),"") -> 94.98 | P24: =_xlfn.IFNA(VLOOKUP($N24,HAVERD!$A:$GB,P$2,FALSE),"") -> 90.03 | Q24: =_xlfn.IFNA(VLOOKUP($N24,HAVERD!$A:$GB,Q$2,FALSE),"") -> 84.88 | R24: =_xlfn.IFNA(VLOOKUP($N24,HAVERD!$A:$GB,R$2,FALSE),"") -> 79.72 | S24: =_xlfn.IFNA(VLOOKUP($N24,HAVERD!$A:$GB,S$2,FALSE),"") -> 75.85
A25: =A8 -> 46118 | B25: =VLOOKUP($A25,HAVERD!$A:$GB,B$2,FALSE) -> 109.77 | C25: =VLOOKUP($A25,HAVERD!$A:$GB,C$2,FALSE) -> 92.24 | D25: =VLOOKUP($A25,HAVERD!$A:$GB,D$2,FALSE) -> 81.83 | E25: =VLOOKUP($A25,HAVERD!$A:$GB,E$2,FALSE) -> 76.43 | F25: =VLOOKUP($A25,HAVERD!$A:$GB,F$2,FALSE) -> 73.33 | N25: =N8 -> 46175 | O25: =_xlfn.IFNA(VLOOKUP($N25,HAVERD!$A:$GB,O$2,FALSE),"") -> 96 | P25: =_xlfn.IFNA(VLOOKUP($N25,HAVERD!$A:$GB,P$2,FALSE),"") -> 91.05 | Q25: =_xlfn.IFNA(VLOOKUP($N25,HAVERD!$A:$GB,Q$2,FALSE),"") -> 85.99 | R25: =_xlfn.IFNA(VLOOKUP($N25,HAVERD!$A:$GB,R$2,FALSE),"") -> 80.77 | S25: =_xlfn.IFNA(VLOOKUP($N25,HAVERD!$A:$GB,S$2,FALSE),"") -> 76.7
A26: =A9 -> 46119 | B26: =VLOOKUP($A26,HAVERD!$A:$GB,B$2,FALSE) -> 109.27 | C26: =VLOOKUP($A26,HAVERD!$A:$GB,C$2,FALSE) -> 92.77 | D26: =VLOOKUP($A26,HAVERD!$A:$GB,D$2,FALSE) -> 83.13 | E26: =VLOOKUP($A26,HAVERD!$A:$GB,E$2,FALSE) -> 77.57 | F26: =VLOOKUP($A26,HAVERD!$A:$GB,F$2,FALSE) -> 74.22 | N26: =N9 -> 46176 | O26: =_xlfn.IFNA(VLOOKUP($N26,HAVERD!$A:$GB,O$2,FALSE),"") -> 97.81 | P26: =_xlfn.IFNA(VLOOKUP($N26,HAVERD!$A:$GB,P$2,FALSE),"") -> 92.44 | Q26: =_xlfn.IFNA(VLOOKUP($N26,HAVERD!$A:$GB,Q$2,FALSE),"") -> 86.91 | R26: =_xlfn.IFNA(VLOOKUP($N26,HAVERD!$A:$GB,R$2,FALSE),"") -> 81.44 | S26: =_xlfn.IFNA(VLOOKUP($N26,HAVERD!$A:$GB,S$2,FALSE),"") -> 77.12
A27: =A10 -> 46120 | B27: =VLOOKUP($A27,HAVERD!$A:$GB,B$2,FALSE) -> 94.75 | C27: =VLOOKUP($A27,HAVERD!$A:$GB,C$2,FALSE) -> 86.52 | D27: =VLOOKUP($A27,HAVERD!$A:$GB,D$2,FALSE) -> 81.19 | E27: =VLOOKUP($A27,HAVERD!$A:$GB,E$2,FALSE) -> 76.87 | F27: =VLOOKUP($A27,HAVERD!$A:$GB,F$2,FALSE) -> 74.08 | N27: =N10 -> 46177 | O27: =_xlfn.IFNA(VLOOKUP($N27,HAVERD!$A:$GB,O$2,FALSE),"") -> 95.03 | P27: =_xlfn.IFNA(VLOOKUP($N27,HAVERD!$A:$GB,P$2,FALSE),"") -> 90.02 | Q27: =_xlfn.IFNA(VLOOKUP($N27,HAVERD!$A:$GB,Q$2,FALSE),"") -> 85.04 | R27: =_xlfn.IFNA(VLOOKUP($N27,HAVERD!$A:$GB,R$2,FALSE),"") -> 80.05 | S27: =_xlfn.IFNA(VLOOKUP($N27,HAVERD!$A:$GB,S$2,FALSE),"") -> 76.23
A28: =A11 -> 46121 | B28: =VLOOKUP($A28,HAVERD!$A:$GB,B$2,FALSE) -> 95.92 | C28: =VLOOKUP($A28,HAVERD!$A:$GB,C$2,FALSE) -> 86.55 | D28: =VLOOKUP($A28,HAVERD!$A:$GB,D$2,FALSE) -> 81.24 | E28: =VLOOKUP($A28,HAVERD!$A:$GB,E$2,FALSE) -> 76.74 | F28: =VLOOKUP($A28,HAVERD!$A:$GB,F$2,FALSE) -> 73.69 | N28: =N11 -> 46178 | O28: =_xlfn.IFNA(VLOOKUP($N28,HAVERD!$A:$GB,O$2,FALSE),"") -> 93.09 | P28: =_xlfn.IFNA(VLOOKUP($N28,HAVERD!$A:$GB,P$2,FALSE),"") -> 88.61 | Q28: =_xlfn.IFNA(VLOOKUP($N28,HAVERD!$A:$GB,Q$2,FALSE),"") -> 84.12 | R28: =_xlfn.IFNA(VLOOKUP($N28,HAVERD!$A:$GB,R$2,FALSE),"") -> 79.46 | S28: =_xlfn.IFNA(VLOOKUP($N28,HAVERD!$A:$GB,S$2,FALSE),"") -> 75.8
A29: =A12 -> 46122 | B29: =VLOOKUP($A29,HAVERD!$A:$GB,B$2,FALSE) -> 95.2 | C29: =VLOOKUP($A29,HAVERD!$A:$GB,C$2,FALSE) -> 86.82 | D29: =VLOOKUP($A29,HAVERD!$A:$GB,D$2,FALSE) -> 82 | E29: =VLOOKUP($A29,HAVERD!$A:$GB,E$2,FALSE) -> 77.69 | F29: =VLOOKUP($A29,HAVERD!$A:$GB,F$2,FALSE) -> 74.49 | N29: =N12 -> 46181 | O29: =_xlfn.IFNA(VLOOKUP($N29,HAVERD!$A:$GB,O$2,FALSE),"") -> 94.25 | P29: =_xlfn.IFNA(VLOOKUP($N29,HAVERD!$A:$GB,P$2,FALSE),"") -> 90.2 | Q29: =_xlfn.IFNA(VLOOKUP($N29,HAVERD!$A:$GB,Q$2,FALSE),"") -> 85.96 | R29: =_xlfn.IFNA(VLOOKUP($N29,HAVERD!$A:$GB,R$2,FALSE),"") -> 81.14 | S29: =_xlfn.IFNA(VLOOKUP($N29,HAVERD!$A:$GB,S$2,FALSE),"") -> 76.97
A30: =A13 -> 46125 | B30: =VLOOKUP($A30,HAVERD!$A:$GB,B$2,FALSE) -> 99.36 | C30: =VLOOKUP($A30,HAVERD!$A:$GB,C$2,FALSE) -> 89.78 | D30: =VLOOKUP($A30,HAVERD!$A:$GB,D$2,FALSE) -> 84.32 | E30: =VLOOKUP($A30,HAVERD!$A:$GB,E$2,FALSE) -> 79.06 | F30: =VLOOKUP($A30,HAVERD!$A:$GB,F$2,FALSE) -> 75.16 | N30: =N13 -> 46182 | O30: =_xlfn.IFNA(VLOOKUP($N30,HAVERD!$A:$GB,O$2,FALSE),"") -> 91.45 | P30: =_xlfn.IFNA(VLOOKUP($N30,HAVERD!$A:$GB,P$2,FALSE),"") -> 88.23 | Q30: =_xlfn.IFNA(VLOOKUP($N30,HAVERD!$A:$GB,Q$2,FALSE),"") -> 84.58 | R30: =_xlfn.IFNA(VLOOKUP($N30,HAVERD!$A:$GB,R$2,FALSE),"") -> 80.21 | S30: =_xlfn.IFNA(VLOOKUP($N30,HAVERD!$A:$GB,S$2,FALSE),"") -> 76.46
A31: =A14 -> 46126 | B31: =VLOOKUP($A31,HAVERD!$A:$GB,B$2,FALSE) -> 94.79 | C31: =VLOOKUP($A31,HAVERD!$A:$GB,C$2,FALSE) -> 87.32 | D31: =VLOOKUP($A31,HAVERD!$A:$GB,D$2,FALSE) -> 82.48 | E31: =VLOOKUP($A31,HAVERD!$A:$GB,E$2,FALSE) -> 77.75 | F31: =VLOOKUP($A31,HAVERD!$A:$GB,F$2,FALSE) -> 74.38 | N31: =N14 -> 46183 | O31: =_xlfn.IFNA(VLOOKUP($N31,HAVERD!$A:$GB,O$2,FALSE),"") -> 93.1 | P31: =_xlfn.IFNA(VLOOKUP($N31,HAVERD!$A:$GB,P$2,FALSE),"") -> 89.76 | Q31: =_xlfn.IFNA(VLOOKUP($N31,HAVERD!$A:$GB,Q$2,FALSE),"") -> 85.89 | R31: =_xlfn.IFNA(VLOOKUP($N31,HAVERD!$A:$GB,R$2,FALSE),"") -> 81.14 | S31: =_xlfn.IFNA(VLOOKUP($N31,HAVERD!$A:$GB,S$2,FALSE),"") -> 77.04
A32: =A15 -> 46127 | B32: =VLOOKUP($A32,HAVERD!$A:$GB,B$2,FALSE) -> 94.93 | C32: =VLOOKUP($A32,HAVERD!$A:$GB,C$2,FALSE) -> 88.02 | D32: =VLOOKUP($A32,HAVERD!$A:$GB,D$2,FALSE) -> 83.19 | E32: =VLOOKUP($A32,HAVERD!$A:$GB,E$2,FALSE) -> 78.87 | F32: =VLOOKUP($A32,HAVERD!$A:$GB,F$2,FALSE) -> 75.72 | N32: =N15 -> 46184 | O32: =_xlfn.IFNA(VLOOKUP($N32,HAVERD!$A:$GB,O$2,FALSE),"") -> 90.38 | P32: =_xlfn.IFNA(VLOOKUP($N32,HAVERD!$A:$GB,P$2,FALSE),"") -> 87.71 | Q32: =_xlfn.IFNA(VLOOKUP($N32,HAVERD!$A:$GB,Q$2,FALSE),"") -> 84.62 | R32: =_xlfn.IFNA(VLOOKUP($N32,HAVERD!$A:$GB,R$2,FALSE),"") -> 80.49 | S32: =_xlfn.IFNA(VLOOKUP($N32,HAVERD!$A:$GB,S$2,FALSE),"") -> 76.55
A33: =A16 -> 46128 | B33: =VLOOKUP($A33,HAVERD!$A:$GB,B$2,FALSE) -> 99.39 | C33: =VLOOKUP($A33,HAVERD!$A:$GB,C$2,FALSE) -> 89.83 | D33: =VLOOKUP($A33,HAVERD!$A:$GB,D$2,FALSE) -> 83.97 | E33: =VLOOKUP($A33,HAVERD!$A:$GB,E$2,FALSE) -> 78.98 | F33: =VLOOKUP($A33,HAVERD!$A:$GB,F$2,FALSE) -> 75.69 | N33: =N16 -> 46185 | O33: =_xlfn.IFNA(VLOOKUP($N33,HAVERD!$A:$GB,O$2,FALSE),"") -> 87.33 | P33: =_xlfn.IFNA(VLOOKUP($N33,HAVERD!$A:$GB,P$2,FALSE),"") -> 84.78 | Q33: =_xlfn.IFNA(VLOOKUP($N33,HAVERD!$A:$GB,Q$2,FALSE),"") -> 81.69 | R33: =_xlfn.IFNA(VLOOKUP($N33,HAVERD!$A:$GB,R$2,FALSE),"") -> 78.04 | S33: =_xlfn.IFNA(VLOOKUP($N33,HAVERD!$A:$GB,S$2,FALSE),"") -> 74.85
A34: =A17 -> 46129 | B34: =VLOOKUP($A34,HAVERD!$A:$GB,B$2,FALSE) -> 90.38 | C34: =VLOOKUP($A34,HAVERD!$A:$GB,C$2,FALSE) -> 83.86 | D34: =VLOOKUP($A34,HAVERD!$A:$GB,D$2,FALSE) -> 79.41 | E34: =VLOOKUP($A34,HAVERD!$A:$GB,E$2,FALSE) -> 75.41 | F34: =VLOOKUP($A34,HAVERD!$A:$GB,F$2,FALSE) -> 73.01 | N34: =N17 -> 46188 | O34: =_xlfn.IFNA(VLOOKUP($N34,HAVERD!$A:$GB,O$2,FALSE),"") -> 83.17 | P34: =_xlfn.IFNA(VLOOKUP($N34,HAVERD!$A:$GB,P$2,FALSE),"") -> 81.24 | Q34: =_xlfn.IFNA(VLOOKUP($N34,HAVERD!$A:$GB,Q$2,FALSE),"") -> 78.87 | R34: =_xlfn.IFNA(VLOOKUP($N34,HAVERD!$A:$GB,R$2,FALSE),"") -> 76.01 | S34: =_xlfn.IFNA(VLOOKUP($N34,HAVERD!$A:$GB,S$2,FALSE),"") -> 73.55
... A37: =A20 -> 46134 | B37: =VLOOKUP($A37,HAVERD!$A:$GB,B$2,FALSE) -> 101.91 | C37: =VLOOKUP($A37,HAVERD!$A:$GB,C$2,FALSE) -> 91.83 | D37: =VLOOKUP($A37,HAVERD!$A:$GB,D$2,FALSE) -> 84.76 | E37: =VLOOKUP($A37,HAVERD!$A:$GB,E$2,FALSE) -> 78.38 | F37: =VLOOKUP($A37,HAVERD!$A:$GB,F$2,FALSE) -> 74.66 | N37: =N20 -> 46191 | O37: =_xlfn.IFNA(VLOOKUP($N37,HAVERD!$A:$GB,O$2,FALSE),"") -> 79.85 | P37: =_xlfn.IFNA(VLOOKUP($N37,HAVERD!$A:$GB,P$2,FALSE),"") -> 78.82 | Q37: =_xlfn.IFNA(VLOOKUP($N37,HAVERD!$A:$GB,Q$2,FALSE),"") -> 76.81 | R37: =_xlfn.IFNA(VLOOKUP($N37,HAVERD!$A:$GB,R$2,FALSE),"") -> 74 | S37: =_xlfn.IFNA(VLOOKUP($N37,HAVERD!$A:$GB,S$2,FALSE),"") -> 71.95
A39: Average | N39: Average
A40: Month | B40: =MONTH(B20) -> 4 | C40: =MONTH(C20) -> 7 | D40: =MONTH(D20) -> 10 | E40: =MONTH(E20) -> 4 | F40: =MONTH(F20) -> 4 | N40: Month | O40: =MONTH(O20) -> 6 | P40: =MONTH(P20) -> 9 | Q40: =MONTH(Q20) -> 12 | R40: =MONTH(R20) -> 6 | S40: =MONTH(S20) -> 6
A41: Year | B41: =YEAR(B20) -> 2026 | C41: =YEAR(C20) -> 2026 | D41: =YEAR(D20) -> 2026 | E41: =YEAR(E20) -> 2027 | F41: =YEAR(F20) -> 2028 | N41: Year | O41: =YEAR(O20) -> 2026 | P41: =YEAR(P20) -> 2026 | Q41: =YEAR(Q20) -> 2026 | R41: =YEAR(R20) -> 2027 | S41: =YEAR(S20) -> 2028
A42: YYYYMM | B42: =B41*100+B40 -> 202604 | C42: =C41*100+C40 -> 202607 | D42: =D41*100+D40 -> 202610 | E42: =E41*100+E40 -> 202704 | F42: =F41*100+F40 -> 202804 | N42: YYYYMM | O42: =O41*100+O40 -> 202606 | P42: =P41*100+P40 -> 202609 | Q42: =Q41*100+Q40 -> 202612 | R42: =R41*100+R40 -> 202706 | S42: =S41*100+S40 -> 202806
A43: Quarter | B43: =IF(B40<4,1,IF(B40<7,2,IF(B40<10,3,4))) -> 2 | C43: =IF(C40<4,1,IF(C40<7,2,IF(C40<10,3,4))) -> 3 | D43: =IF(D40<4,1,IF(D40<7,2,IF(D40<10,3,4))) -> 4 | E43: =IF(E40<4,1,IF(E40<7,2,IF(E40<10,3,4))) -> 2 | F43: =IF(F40<4,1,IF(F40<7,2,IF(F40<10,3,4))) -> 2 | N43: Quarter | O43: =IF(O40<4,1,IF(O40<7,2,IF(O40<10,3,4))) -> 2 | P43: =IF(P40<4,1,IF(P40<7,2,IF(P40<10,3,4))) -> 3 | Q43: =IF(Q40<4,1,IF(Q40<7,2,IF(Q40<10,3,4))) -> 4 | R43: =IF(R40<4,1,IF(R40<7,2,IF(R40<10,3,4))) -> 2 | S43: =IF(S40<4,1,IF(S40<7,2,IF(S40<10,3,4))) -> 2
A44: YYYYQQ | B44: =B41*100+B43 -> 202602 | C44: =C41*100+C43 -> 202603 | D44: =D41*100+D43 -> 202604 | E44: =E41*100+E43 -> 202702 | F44: =F41*100+F43 -> 202802 | N44: YYYYQQ | O44: =O41*100+O43 -> 202602 | P44: =P41*100+P43 -> 202603 | Q44: =Q41*100+Q43 -> 202604 | R44: =R41*100+R43 -> 202702 | S44: =S41*100+S43 -> 202802
A45: Average | B45: =AVERAGE(B23:B37) -> #N/A | C45: =AVERAGE(C23:C37) -> #N/A | D45: =AVERAGE(D23:D37) -> #N/A | E45: =AVERAGE(E23:E37) -> #N/A | F45: =AVERAGE(F23:F37) -> #N/A | N45: Average | O45: =AVERAGE(O23:O37) -> 89.8 | P45: =AVERAGE(P23:P37) -> 86.578667 | Q45: =AVERAGE(Q23:Q37) -> 82.861333 | R45: =AVERAGE(R23:R37) -> 78.67 | S45: =AVERAGE(S23:S37) -> 75.283333
A47: Quarterly series | N47: Quarterly series
B48: =B44 -> 202602 | C48: =IF(RIGHT(B48)="4",B48+97,B48+1) -> 202603 | D48: =IF(RIGHT(C48)="4",C48+97,C48+1) -> 202604 | E48: =IF(RIGHT(D48)="4",D48+97,D48+1) -> 202701 | F48: =IF(RIGHT(E48)="4",E48+97,E48+1) -> 202702 | G48: =IF(RIGHT(F48)="4",F48+97,F48+1) -> 202703 | H48: =IF(RIGHT(G48)="4",G48+97,G48+1) -> 202704 | I48: =IF(RIGHT(H48)="4",H48+97,H48+1) -> 202801 | J48: =IF(RIGHT(I48)="4",I48+97,I48+1) -> 202802 | O48: =O44 -> 202602 | P48: =IF(RIGHT(O48)="4",O48+97,O48+1) -> 202603 | Q48: =IF(RIGHT(P48)="4",P48+97,P48+1) -> 202604 | R48: =IF(RIGHT(Q48)="4",Q48+97,Q48+1) -> 202701 | S48: =IF(RIGHT(R48)="4",R48+97,R48+1) -> 202702 | T48: =IF(RIGHT(S48)="4",S48+97,S48+1) -> 202703 | U48: =IF(RIGHT(T48)="4",T48+97,T48+1) -> 202704 | V48: =IF(RIGHT(U48)="4",U48+97,U48+1) -> 202801 | W48: =IF(RIGHT(V48)="4",V48+97,V48+1) -> 202802
A49: =A1 -> April 2026 MPR | B49: =AVERAGEIF($B$44:$F$44,B48,$B$45:$F$45) -> #N/A | C49: =AVERAGEIF($B$44:$F$44,C48,$B$45:$F$45) -> #N/A | D49: =AVERAGEIF($B$44:$F$44,D48,$B$45:$F$45) -> #N/A | E49: =AVERAGE(D49,F49) -> #N/A | F49: =AVERAGEIF($B$44:$F$44,F48,$B$45:$F$45) -> #N/A | G49: =F49+(J49-F49)*1/4 -> #N/A | H49: =G49+(J49-F49)*1/4 -> #N/A | I49: =H49+(J49-F49)*1/4 -> #N/A | J49: =AVERAGEIF($B$44:$F$44,J48,$B$45:$F$45) -> #N/A | N49: =N1 -> Current market curve | O49: =AVERAGEIF($O$44:$BJ$44,O48,$O$45:$BJ$45) -> 89.8 | P49: =AVERAGEIF($O$44:$BJ$44,P48,$O$45:$BJ$45) -> 86.578667 | Q49: =AVERAGEIF($O$44:$BJ$44,Q48,$O$45:$BJ$45) -> 82.861333 | R49: =AVERAGE(Q49,S49) -> 80.765667 | S49: =AVERAGEIF($O$44:$BJ$44,S48,$O$45:$BJ$45) -> 78.67 | T49: =S49+(W49-S49)*1/4 -> 77.823333 | U49: =T49+(W49-S49)*1/4 -> 76.976667 | V49: =U49+(W49-S49)*1/4 -> 76.13 | W49: =AVERAGEIF($O$44:$BJ$44,W48,$O$45:$BJ$45) -> 75.283333
N52: Comparison - quarterly
O53: 44927 | P53: 45017 | Q53: 45108 | R53: 45200 | S53: 45292 | T53: 45383 | U53: 45474 | V53: 45566 | W53: 45658 | X53: 45748 | Y53: 45839 | Z53: 45931 | AA53: 46023 | AB53: 46113 | AC53: 46204 | AD53: 46296 | AE53: 46388 | AF53: 46478 | AG53: 46569 | AH53: 46661 | AI53: 46753 | AJ53: 46844 | AK53: 46935 | AL53: 47027
O54: 202301 | P54: =IF(RIGHT(O54)="4",O54+97,O54+1) -> 202302 | Q54: =IF(RIGHT(P54)="4",P54+97,P54+1) -> 202303 | R54: =IF(RIGHT(Q54)="4",Q54+97,Q54+1) -> 202304 | S54: =IF(RIGHT(R54)="4",R54+97,R54+1) -> 202401 | T54: =IF(RIGHT(S54)="4",S54+97,S54+1) -> 202402 | U54: =IF(RIGHT(T54)="4",T54+97,T54+1) -> 202403 | V54: =IF(RIGHT(U54)="4",U54+97,U54+1) -> 202404 | W54: =IF(RIGHT(V54)="4",V54+97,V54+1) -> 202501 | ... AL54: =IF(RIGHT(AK54)="4",AK54+97,AK54+1) -> 202804
N55: =A49 -> April 2026 MPR | O55: =HLOOKUP(O$54,$B$48:$J$49,2,FALSE) -> #N/A | P55: =HLOOKUP(P$54,$B$48:$J$49,2,FALSE) -> #N/A | Q55: =HLOOKUP(Q$54,$B$48:$J$49,2,FALSE) -> #N/A | R55: =HLOOKUP(R$54,$B$48:$J$49,2,FALSE) -> #N/A | S55: =HLOOKUP(S$54,$B$48:$J$49,2,FALSE) -> #N/A | T55: =HLOOKUP(T$54,$B$48:$J$49,2,FALSE) -> #N/A | U55: =HLOOKUP(U$54,$B$48:$J$49,2,FALSE) -> #N/A | V55: =HLOOKUP(V$54,$B$48:$J$49,2,FALSE) -> #N/A | ... AL55: =HLOOKUP(AL$54,$B$48:$J$49,2,FALSE) -> #N/A
N56: =N49 -> Current market curve | O56: =HLOOKUP(O$54,$O$48:$AE$49,2,FALSE) -> #N/A | P56: =HLOOKUP(P$54,$O$48:$AE$49,2,FALSE) -> #N/A | Q56: =HLOOKUP(Q$54,$O$48:$AE$49,2,FALSE) -> #N/A | R56: =HLOOKUP(R$54,$O$48:$AE$49,2,FALSE) -> #N/A | S56: =HLOOKUP(S$54,$O$48:$AE$49,2,FALSE) -> #N/A | T56: =HLOOKUP(T$54,$O$48:$AE$49,2,FALSE) -> #N/A | U56: =HLOOKUP(U$54,$O$48:$AE$49,2,FALSE) -> #N/A | V56: =HLOOKUP(V$54,$O$48:$AE$49,2,FALSE) -> #N/A | ... AL56: =HLOOKUP(AL$54,$O$48:$AE$49,2,FALSE) -> #N/A
N57: Difference | U57: =U56-U55 -> #N/A | V57: =V56-V55 -> #N/A | W57: =W56-W55 -> #N/A | X57: =X56-X55 -> #N/A | Y57: =Y56-Y55 -> #N/A | Z57: =Z56-Z55 -> #N/A | AA57: =AA56-AA55 -> #N/A | AB57: =AB56-AB55 -> #N/A | ... AL57: =AL56-AL55 -> #N/A
N58: Difference % | U58: =100*((U56/U55)-1) -> #N/A | V58: =100*((V56/V55)-1) -> #N/A | W58: =100*((W56/W55)-1) -> #N/A | X58: =100*((X56/X55)-1) -> #N/A | Y58: =100*((Y56/Y55)-1) -> #N/A | Z58: =100*((Z56/Z55)-1) -> #N/A | AA58: =100*((AA56/AA55)-1) -> #N/A | AB58: =100*((AB56/AB55)-1) -> #N/A | ... AL58: =100*((AL56/AL55)-1) -> #N/A

Sheet Market expectations - Other
A1: ='Market pricing dates'!A2 -> April 2026 MPR | C1: ='Market pricing dates'!A12 -> 15 working days to 22 Apr 2026 | G1: ='Market pricing dates'!D2 -> Current market curve | I1: ='Market pricing dates'!D12 -> 15 working days to 18 Jun 2026
A2: Column # | B2: =HAVERD!FO$1 -> 171 | C2: =+B2+1 -> 172 | D2: =+C2+1 -> 173 | E2: =+D2+1 -> 174 | G2: Column # | H2: =HAVERD!FO$1 -> 171 | I2: =+H2+1 -> 172 | J2: =+I2+1 -> 173 | K2: =+J2+1 -> 174
A3: Months | B3: =HAVERD!FO$2 -> £EER broad | C3: =HAVERD!FP$2 -> Oil price | D3: =HAVERD!FQ$2 -> RXD | E3: =HAVERD!FR$2 -> £ oil price | G3: Months | H3: =HAVERD!FO$2 -> £EER broad | I3: =HAVERD!FP$2 -> Oil price | J3: =HAVERD!FQ$2 -> RXD | K3: =HAVERD!FR$2 -> £ oil price
A4: Days | C4: 30.416667 | D4: =+C4+30.4166667 -> 60.833333 | E4: =+D4+30.4166667 -> 91.25 | G4: Days | I4: 30.416667 | J4: =+I4+30.4166667 -> 60.833333 | K4: =+J4+30.4166667 -> 91.25
A5: Dates | G5: Dates
A6: =A11-7 -> 46114 | B6: =A6 -> 46114 | C6: =$B6+C$4 -> 46144.417 | D6: =$B6+D$4 -> 46174.833 | E6: =$B6+E$4 -> 46205.25 | G6: =G11-7 -> 46171 | H6: =G6 -> 46171 | I6: =$G6+I$4 -> 46201.417 | J6: =$G6+J$4 -> 46231.833 | K6: =$G6+K$4 -> 46262.25
A7: =A12-7 -> 46115 | B7: =A7 -> 46115 | C7: =$B7+C$4 -> 46145.417 | D7: =$B7+D$4 -> 46175.833 | E7: =$B7+E$4 -> 46206.25 | G7: =G12-7 -> 46174 | H7: =G7 -> 46174 | I7: =$G7+I$4 -> 46204.417 | J7: =$G7+J$4 -> 46234.833 | K7: =$G7+K$4 -> 46265.25
A8: =A13-7 -> 46118 | B8: =A8 -> 46118 | C8: =$B8+C$4 -> 46148.417 | D8: =$B8+D$4 -> 46178.833 | E8: =$B8+E$4 -> 46209.25 | G8: =G13-7 -> 46175 | H8: =G8 -> 46175 | I8: =$G8+I$4 -> 46205.417 | J8: =$G8+J$4 -> 46235.833 | K8: =$G8+K$4 -> 46266.25
A9: =A14-7 -> 46119 | B9: =A9 -> 46119 | C9: =$B9+C$4 -> 46149.417 | D9: =$B9+D$4 -> 46179.833 | E9: =$B9+E$4 -> 46210.25 | G9: =G14-7 -> 46176 | H9: =G9 -> 46176 | I9: =$G9+I$4 -> 46206.417 | J9: =$G9+J$4 -> 46236.833 | K9: =$G9+K$4 -> 46267.25
A10: =A15-7 -> 46120 | B10: =A10 -> 46120 | C10: =$B10+C$4 -> 46150.417 | D10: =$B10+D$4 -> 46180.833 | E10: =$B10+E$4 -> 46211.25 | G10: =G15-7 -> 46177 | H10: =G10 -> 46177 | I10: =$G10+I$4 -> 46207.417 | J10: =$G10+J$4 -> 46237.833 | K10: =$G10+K$4 -> 46268.25
A11: =A16-7 -> 46121 | B11: =A11 -> 46121 | C11: =$B11+C$4 -> 46151.417 | D11: =$B11+D$4 -> 46181.833 | E11: =$B11+E$4 -> 46212.25 | G11: =G16-7 -> 46178 | H11: =G11 -> 46178 | I11: =$G11+I$4 -> 46208.417 | J11: =$G11+J$4 -> 46238.833 | K11: =$G11+K$4 -> 46269.25
A12: =A17-7 -> 46122 | B12: =A12 -> 46122 | C12: =$B12+C$4 -> 46152.417 | D12: =$B12+D$4 -> 46182.833 | E12: =$B12+E$4 -> 46213.25 | G12: =G17-7 -> 46181 | H12: =G12 -> 46181 | I12: =$G12+I$4 -> 46211.417 | J12: =$G12+J$4 -> 46241.833 | K12: =$G12+K$4 -> 46272.25
A13: =A18-7 -> 46125 | B13: =A13 -> 46125 | C13: =$B13+C$4 -> 46155.417 | D13: =$B13+D$4 -> 46185.833 | E13: =$B13+E$4 -> 46216.25 | G13: =G18-7 -> 46182 | H13: =G13 -> 46182 | I13: =$G13+I$4 -> 46212.417 | J13: =$G13+J$4 -> 46242.833 | K13: =$G13+K$4 -> 46273.25
A14: =A19-7 -> 46126 | B14: =A14 -> 46126 | C14: =$B14+C$4 -> 46156.417 | D14: =$B14+D$4 -> 46186.833 | E14: =$B14+E$4 -> 46217.25 | G14: =G19-7 -> 46183 | H14: =G14 -> 46183 | I14: =$G14+I$4 -> 46213.417 | J14: =$G14+J$4 -> 46243.833 | K14: =$G14+K$4 -> 46274.25
A15: =A20-7 -> 46127 | B15: =A15 -> 46127 | C15: =$B15+C$4 -> 46157.417 | D15: =$B15+D$4 -> 46187.833 | E15: =$B15+E$4 -> 46218.25 | G15: =G20-7 -> 46184 | H15: =G15 -> 46184 | I15: =$G15+I$4 -> 46214.417 | J15: =$G15+J$4 -> 46244.833 | K15: =$G15+K$4 -> 46275.25
A16: ='Market pricing dates'!B5 -> 46128 | B16: =A16 -> 46128 | C16: =$B16+C$4 -> 46158.417 | D16: =$B16+D$4 -> 46188.833 | E16: =$B16+E$4 -> 46219.25 | G16: ='Market pricing dates'!E5 -> 46185 | H16: =G16 -> 46185 | I16: =$G16+I$4 -> 46215.417 | J16: =$G16+J$4 -> 46245.833 | K16: =$G16+K$4 -> 46276.25
A17: ='Market pricing dates'!B6 -> 46129 | B17: =A17 -> 46129 | C17: =$B17+C$4 -> 46159.417 | D17: =$B17+D$4 -> 46189.833 | E17: =$B17+E$4 -> 46220.25 | G17: ='Market pricing dates'!E6 -> 46188 | H17: =G17 -> 46188 | I17: =$G17+I$4 -> 46218.417 | J17: =$G17+J$4 -> 46248.833 | K17: =$G17+K$4 -> 46279.25
A18: ='Market pricing dates'!B7 -> 46132 | B18: =A18 -> 46132 | C18: =$B18+C$4 -> 46162.417 | D18: =$B18+D$4 -> 46192.833 | E18: =$B18+E$4 -> 46223.25 | G18: ='Market pricing dates'!E7 -> 46189 | H18: =G18 -> 46189 | I18: =$G18+I$4 -> 46219.417 | J18: =$G18+J$4 -> 46249.833 | K18: =$G18+K$4 -> 46280.25
A19: ='Market pricing dates'!B8 -> 46133 | B19: =A19 -> 46133 | C19: =$B19+C$4 -> 46163.417 | D19: =$B19+D$4 -> 46193.833 | E19: =$B19+E$4 -> 46224.25 | G19: ='Market pricing dates'!E8 -> 46190 | H19: =G19 -> 46190 | I19: =$G19+I$4 -> 46220.417 | J19: =$G19+J$4 -> 46250.833 | K19: =$G19+K$4 -> 46281.25
A20: ='Market pricing dates'!B9 -> 46134 | B20: =A20 -> 46134 | C20: =$B20+C$4 -> 46164.417 | D20: =$B20+D$4 -> 46194.833 | E20: =$B20+E$4 -> 46225.25 | G20: ='Market pricing dates'!E9 -> 46191 | H20: =G20 -> 46191 | I20: =$G20+I$4 -> 46221.417 | J20: =$G20+J$4 -> 46251.833 | K20: =$G20+K$4 -> 46282.25
A22: Average levels | G22: Average levels
A23: =A6 -> 46114 | B23: =VLOOKUP($A23,HAVERD!$A:$FV,B$2,FALSE) -> 83.9146 | C23: =VLOOKUP($A23,HAVERD!$A:$FV,C$2,FALSE) -> 127.61 | D23: =VLOOKUP($A23,HAVERD!$A:$FV,D$2,FALSE) -> 1.3244 | E23: =VLOOKUP($A23,HAVERD!$A:$FV,E$2,FALSE) -> 0 | G23: =G6 -> 46171 | H23: =_xlfn.IFNA(VLOOKUP($G23,HAVERD!$A:$FV,H$2,FALSE),"") -> 84.6202 | I23: =_xlfn.IFNA(VLOOKUP($G23,HAVERD!$A:$FV,I$2,FALSE),"") -> 92.88 | J23: =_xlfn.IFNA(VLOOKUP($G23,HAVERD!$A:$FV,J$2,FALSE),"") -> 1.3478 | K23: =_xlfn.IFNA(VLOOKUP($G23,HAVERD!$A:$FV,K$2,FALSE),"") -> 0
A24: =A7 -> 46115 | B24: =VLOOKUP($A24,HAVERD!$A:$FV,B$2,FALSE) -> #N/A | C24: =VLOOKUP($A24,HAVERD!$A:$FV,C$2,FALSE) -> #N/A | D24: =VLOOKUP($A24,HAVERD!$A:$FV,D$2,FALSE) -> #N/A | E24: =VLOOKUP($A24,HAVERD!$A:$FV,E$2,FALSE) -> 0 | G24: =G7 -> 46174 | H24: =_xlfn.IFNA(VLOOKUP($G24,HAVERD!$A:$FV,H$2,FALSE),"") -> 84.6246 | I24: =_xlfn.IFNA(VLOOKUP($G24,HAVERD!$A:$FV,I$2,FALSE),"") -> 98.29 | J24: =_xlfn.IFNA(VLOOKUP($G24,HAVERD!$A:$FV,J$2,FALSE),"") -> 1.3437 | K24: =_xlfn.IFNA(VLOOKUP($G24,HAVERD!$A:$FV,K$2,FALSE),"") -> 0
A25: =A8 -> 46118 | B25: =VLOOKUP($A25,HAVERD!$A:$FV,B$2,FALSE) -> #N/A | C25: =VLOOKUP($A25,HAVERD!$A:$FV,C$2,FALSE) -> #N/A | D25: =VLOOKUP($A25,HAVERD!$A:$FV,D$2,FALSE) -> #N/A | E25: =VLOOKUP($A25,HAVERD!$A:$FV,E$2,FALSE) -> 0 | G25: =G8 -> 46175 | H25: =_xlfn.IFNA(VLOOKUP($G25,HAVERD!$A:$FV,H$2,FALSE),"") -> 84.7304 | I25: =_xlfn.IFNA(VLOOKUP($G25,HAVERD!$A:$FV,I$2,FALSE),"") -> 98.49 | J25: =_xlfn.IFNA(VLOOKUP($G25,HAVERD!$A:$FV,J$2,FALSE),"") -> 1.3472 | K25: =_xlfn.IFNA(VLOOKUP($G25,HAVERD!$A:$FV,K$2,FALSE),"") -> 0
A26: =A9 -> 46119 | B26: =VLOOKUP($A26,HAVERD!$A:$FV,B$2,FALSE) -> 83.8587 | C26: =VLOOKUP($A26,HAVERD!$A:$FV,C$2,FALSE) -> 138.21 | D26: =VLOOKUP($A26,HAVERD!$A:$FV,D$2,FALSE) -> 1.3247 | E26: =VLOOKUP($A26,HAVERD!$A:$FV,E$2,FALSE) -> 0 | G26: =G9 -> 46176 | H26: =_xlfn.IFNA(VLOOKUP($G26,HAVERD!$A:$FV,H$2,FALSE),"") -> 84.7074 | I26: =_xlfn.IFNA(VLOOKUP($G26,HAVERD!$A:$FV,I$2,FALSE),"") -> 101.69 | J26: =_xlfn.IFNA(VLOOKUP($G26,HAVERD!$A:$FV,J$2,FALSE),"") -> 1.3437 | K26: =_xlfn.IFNA(VLOOKUP($G26,HAVERD!$A:$FV,K$2,FALSE),"") -> 0
A27: =A10 -> 46120 | B27: =VLOOKUP($A27,HAVERD!$A:$FV,B$2,FALSE) -> 84.4154 | C27: =VLOOKUP($A27,HAVERD!$A:$FV,C$2,FALSE) -> 122.11 | D27: =VLOOKUP($A27,HAVERD!$A:$FV,D$2,FALSE) -> 1.3449 | E27: =VLOOKUP($A27,HAVERD!$A:$FV,E$2,FALSE) -> 0 | G27: =G10 -> 46177 | H27: =_xlfn.IFNA(VLOOKUP($G27,HAVERD!$A:$FV,H$2,FALSE),"") -> 84.6944 | I27: =_xlfn.IFNA(VLOOKUP($G27,HAVERD!$A:$FV,I$2,FALSE),"") -> 98.98 | J27: =_xlfn.IFNA(VLOOKUP($G27,HAVERD!$A:$FV,J$2,FALSE),"") -> 1.3445 | K27: =_xlfn.IFNA(VLOOKUP($G27,HAVERD!$A:$FV,K$2,FALSE),"") -> 0
A28: =A11 -> 46121 | B28: =VLOOKUP($A28,HAVERD!$A:$FV,B$2,FALSE) -> 84.2836 | C28: =VLOOKUP($A28,HAVERD!$A:$FV,C$2,FALSE) -> 119.03 | D28: =VLOOKUP($A28,HAVERD!$A:$FV,D$2,FALSE) -> 1.3415 | E28: =VLOOKUP($A28,HAVERD!$A:$FV,E$2,FALSE) -> 0 | G28: =G11 -> 46178 | H28: =_xlfn.IFNA(VLOOKUP($G28,HAVERD!$A:$FV,H$2,FALSE),"") -> 84.654 | I28: =_xlfn.IFNA(VLOOKUP($G28,HAVERD!$A:$FV,I$2,FALSE),"") -> 97.29 | J28: =_xlfn.IFNA(VLOOKUP($G28,HAVERD!$A:$FV,J$2,FALSE),"") -> 1.3387 | K28: =_xlfn.IFNA(VLOOKUP($G28,HAVERD!$A:$FV,K$2,FALSE),"") -> 0
A29: =A12 -> 46122 | B29: =VLOOKUP($A29,HAVERD!$A:$FV,B$2,FALSE) -> 84.3918 | C29: =VLOOKUP($A29,HAVERD!$A:$FV,C$2,FALSE) -> 119.07 | D29: =VLOOKUP($A29,HAVERD!$A:$FV,D$2,FALSE) -> 1.3461 | E29: =VLOOKUP($A29,HAVERD!$A:$FV,E$2,FALSE) -> 0 | G29: =G12 -> 46181 | H29: =_xlfn.IFNA(VLOOKUP($G29,HAVERD!$A:$FV,H$2,FALSE),"") -> 84.4572 | I29: =_xlfn.IFNA(VLOOKUP($G29,HAVERD!$A:$FV,I$2,FALSE),"") -> 97.46 | J29: =_xlfn.IFNA(VLOOKUP($G29,HAVERD!$A:$FV,J$2,FALSE),"") -> 1.3344 | K29: =_xlfn.IFNA(VLOOKUP($G29,HAVERD!$A:$FV,K$2,FALSE),"") -> 0
A30: =A13 -> 46125 | B30: =VLOOKUP($A30,HAVERD!$A:$FV,B$2,FALSE) -> 84.4447 | C30: =VLOOKUP($A30,HAVERD!$A:$FV,C$2,FALSE) -> 123.28 | D30: =VLOOKUP($A30,HAVERD!$A:$FV,D$2,FALSE) -> 1.3461 | E30: =VLOOKUP($A30,HAVERD!$A:$FV,E$2,FALSE) -> 0 | G30: =G13 -> 46182 | H30: =_xlfn.IFNA(VLOOKUP($G30,HAVERD!$A:$FV,H$2,FALSE),"") -> 84.7225 | I30: =_xlfn.IFNA(VLOOKUP($G30,HAVERD!$A:$FV,I$2,FALSE),"") -> 94.15 | J30: =_xlfn.IFNA(VLOOKUP($G30,HAVERD!$A:$FV,J$2,FALSE),"") -> 1.3398 | K30: =_xlfn.IFNA(VLOOKUP($G30,HAVERD!$A:$FV,K$2,FALSE),"") -> 0
A31: =A14 -> 46126 | B31: =VLOOKUP($A31,HAVERD!$A:$FV,B$2,FALSE) -> 84.7787 | C31: =VLOOKUP($A31,HAVERD!$A:$FV,C$2,FALSE) -> 118.69 | D31: =VLOOKUP($A31,HAVERD!$A:$FV,D$2,FALSE) -> 1.3588 | E31: =VLOOKUP($A31,HAVERD!$A:$FV,E$2,FALSE) -> 0 | G31: =G14 -> 46183 | H31: =_xlfn.IFNA(VLOOKUP($G31,HAVERD!$A:$FV,H$2,FALSE),"") -> 84.8049 | I31: =_xlfn.IFNA(VLOOKUP($G31,HAVERD!$A:$FV,I$2,FALSE),"") -> 95.73 | J31: =_xlfn.IFNA(VLOOKUP($G31,HAVERD!$A:$FV,J$2,FALSE),"") -> 1.3402 | K31: =_xlfn.IFNA(VLOOKUP($G31,HAVERD!$A:$FV,K$2,FALSE),"") -> 0
A32: =A15 -> 46127 | B32: =VLOOKUP($A32,HAVERD!$A:$FV,B$2,FALSE) -> 84.7331 | C32: =VLOOKUP($A32,HAVERD!$A:$FV,C$2,FALSE) -> 114.93 | D32: =VLOOKUP($A32,HAVERD!$A:$FV,D$2,FALSE) -> 1.3569 | E32: =VLOOKUP($A32,HAVERD!$A:$FV,E$2,FALSE) -> 0 | G32: =G15 -> 46184 | H32: =_xlfn.IFNA(VLOOKUP($G32,HAVERD!$A:$FV,H$2,FALSE),"") -> 84.5138 | I32: =_xlfn.IFNA(VLOOKUP($G32,HAVERD!$A:$FV,I$2,FALSE),"") -> 92.84 | J32: =_xlfn.IFNA(VLOOKUP($G32,HAVERD!$A:$FV,J$2,FALSE),"") -> 1.3328 | K32: =_xlfn.IFNA(VLOOKUP($G32,HAVERD!$A:$FV,K$2,FALSE),"") -> 0
A33: =A16 -> 46128 | B33: =VLOOKUP($A33,HAVERD!$A:$FV,B$2,FALSE) -> 84.5552 | C33: =VLOOKUP($A33,HAVERD!$A:$FV,C$2,FALSE) -> 116.63 | D33: =VLOOKUP($A33,HAVERD!$A:$FV,D$2,FALSE) -> 1.3522 | E33: =VLOOKUP($A33,HAVERD!$A:$FV,E$2,FALSE) -> 0 | G33: =G16 -> 46185 | H33: =_xlfn.IFNA(VLOOKUP($G33,HAVERD!$A:$FV,H$2,FALSE),"") -> 84.7225 | I33: =_xlfn.IFNA(VLOOKUP($G33,HAVERD!$A:$FV,I$2,FALSE),"") -> 88.64 | J33: =_xlfn.IFNA(VLOOKUP($G33,HAVERD!$A:$FV,J$2,FALSE),"") -> 1.3413 | K33: =_xlfn.IFNA(VLOOKUP($G33,HAVERD!$A:$FV,K$2,FALSE),"") -> 0
A34: =A17 -> 46129 | B34: =VLOOKUP($A34,HAVERD!$A:$FV,B$2,FALSE) -> 84.5568 | C34: =VLOOKUP($A34,HAVERD!$A:$FV,C$2,FALSE) -> 98.63 | D34: =VLOOKUP($A34,HAVERD!$A:$FV,D$2,FALSE) -> 1.357 | E34: =VLOOKUP($A34,HAVERD!$A:$FV,E$2,FALSE) -> 0 | G34: =G17 -> 46188 | H34: =_xlfn.IFNA(VLOOKUP($G34,HAVERD!$A:$FV,H$2,FALSE),"") -> 84.7207 | I34: =_xlfn.IFNA(VLOOKUP($G34,HAVERD!$A:$FV,I$2,FALSE),"") -> 84.36 | J34: =_xlfn.IFNA(VLOOKUP($G34,HAVERD!$A:$FV,J$2,FALSE),"") -> 1.3441 | K34: =_xlfn.IFNA(VLOOKUP($G34,HAVERD!$A:$FV,K$2,FALSE),"") -> 0
... A37: =A20 -> 46134 | B37: =VLOOKUP($A37,HAVERD!$A:$FV,B$2,FALSE) -> 84.5991 | C37: =VLOOKUP($A37,HAVERD!$A:$FV,C$2,FALSE) -> 113.44 | D37: =VLOOKUP($A37,HAVERD!$A:$FV,D$2,FALSE) -> 1.3499 | E37: =VLOOKUP($A37,HAVERD!$A:$FV,E$2,FALSE) -> 0 | G37: =G20 -> 46191 | H37: =_xlfn.IFNA(VLOOKUP($G37,HAVERD!$A:$FV,H$2,FALSE),"") -> 84.1083 | I37: =_xlfn.IFNA(VLOOKUP($G37,HAVERD!$A:$FV,I$2,FALSE),"") -> 0 | J37: =_xlfn.IFNA(VLOOKUP($G37,HAVERD!$A:$FV,J$2,FALSE),"") -> 1.3253 | K37: =_xlfn.IFNA(VLOOKUP($G37,HAVERD!$A:$FV,K$2,FALSE),"") -> 0
A38: Average | B38: =AVERAGE(B23:B29,B32:B37) -> #N/A | C38: =AVERAGE(C23:C29,C32:C37) -> #N/A | D38: =AVERAGE(D23:D29,D32:D37) -> #N/A | E38: =AVERAGE(E23:E37) -> 0 | G38: Average | H38: =AVERAGE(H23:H37) -> 84.615313 | I38: =AVERAGE(I23:I37) -> 86.775333 | J38: =AVERAGE(J23:J37) -> 1.34038 | K38: =AVERAGE(K23:K37) -> 0
G40: % diff | H40: =100*((H38/B38)-1) -> #N/A | I40: =100*((I38/C38)-1) -> #N/A | J40: =100*((J38/D38)-1) -> #N/A | K40: =100*((K38/E38)-1) -> #DIV/0!

Sheet MPR Chart 2.18 (Aug CPI)
A1: Section 2: Current economic conditions
A3: Chart 2.18 - Contributions to CPI inflation
B5: Contributions, percentage points | H5: Inflation rates, per cent
A6: Date | B6: Food | C6: Electricity and gas | D6: Fuels and lubricants | E6: Other goods | F6: Services | H6: Food | I6: Electricity and gas | J6: Fuels and lubricants | K6: Other goods | L6: Services | M6: CPI
A7: 44227 | B7: -0.1 | C7: -0.3 | D7: -0.3 | E7: 0.4 | F7: 0.8 | H7: -0.7 | I7: -8.4 | J7: -8.2 | K7: 1.4 | L7: 1.7 | M7: 0.7
A8: 44255 | B8: 0 | C8: -0.3 | D8: -0.1 | E8: 0.1 | F8: 0.7 | H8: -0.6 | I8: -7.9 | J8: -3.5 | K8: 0.5 | L8: 1.5 | M8: 0.4
A9: 44286 | B9: -0.1 | C9: -0.2 | D9: 0.1 | E9: 0.3 | F9: 0.7 | H9: -1.4 | I9: -7.3 | J9: 3.5 | K9: 0.9 | L9: 1.5 | M9: 0.7
A10: 44316 | B10: 0 | C10: 0.1 | D10: 0.4 | E10: 0.4 | F10: 0.7 | H10: -0.4 | I10: 2.4 | J10: 13.6 | K10: 1.2 | L10: 1.6 | M10: 1.5
A11: 44347 | B11: -0.1 | C11: 0.1 | D11: 0.5 | E11: 0.8 | F11: 0.9 | H11: -1.3 | I11: 2.6 | J11: 17.9 | K11: 2.2 | L11: 1.9 | M11: 2.1
A12: 44377 | B12: 0 | C12: 0.1 | D12: 0.5 | E12: 1 | F12: 0.9 | H12: -0.6 | I12: 2.5 | J12: 20.3 | K12: 2.7 | L12: 2.1 | M12: 2.5
A13: 44408 | B13: -0.1 | C13: 0.1 | D13: 0.5 | E13: 0.8 | F13: 0.7 | H13: -0.6 | I13: 2.6 | J13: 17.7 | K13: 2.3 | L13: 1.6 | M13: 2
A14: 44439 | B14: 0.1 | C14: 0.1 | D14: 0.5 | E14: 1.2 | F14: 1.4 | H14: 0.3 | I14: 2.6 | J14: 17.7 | K14: 3.2 | L14: 3 | M14: 3.2
A15: 44469 | B15: 0.1 | C15: 0.1 | D15: 0.5 | E15: 1.3 | F15: 1.1 | H15: 0.8 | I15: 2.8 | J15: 17.8 | K15: 3.3 | L15: 2.6 | M15: 3.1
A16: 44500 | B16: 0.2 | C16: 0.8 | D16: 0.6 | E16: 1.3 | F16: 1.4 | H16: 1.2 | I16: 22.9 | J16: 21.5 | K16: 3.4 | L16: 3.2 | M16: 4.2
A17: 44530 | B17: 0.3 | C17: 0.8 | D17: 0.7 | E17: 1.9 | F17: 1.5 | H17: 2.5 | I17: 23.2 | J17: 28.5 | K17: 4.8 | L17: 3.3 | M17: 5.1
A18: 44561 | B18: 0.5 | C18: 0.7 | D18: 0.7 | E18: 2 | F18: 1.5 | H18: 4.2 | I18: 22.7 | J18: 26.8 | K18: 5 | L18: 3.4 | M18: 5.4
... A60: 45838 | B60: 0.5 | C60: 0.2 | D60: -0.3 | E60: 0.8 | F60: 2.4 | H60: 4.5 | I60: 6.8 | J60: -9 | K60: 2.3 | L60: 4.7 | M60: 3.6
A61: July 2025 (Bank staff projections) | B61: 0.527 | C61: 0.287 | D61: -0.205 | E61: 0.689 | F61: 2.457 | H61: 4.736 | I61: 8.731 | J61: -6.64 | K61: 2.142 | L61: 4.878 | M61: 3.755
A62: August 2025 (Bank staff projections) | B62: 0.58 | C62: 0.291 | D62: -0.169 | E62: 0.662 | F62: 2.421 | H62: 5.218 | I62: 8.917 | J62: -5.613 | K62: 2.053 | L62: 4.801 | M62: 3.786
A63: September 2025 (Bank staff projections) | B63: 0.559 | C63: 0.293 | D63: -0.068 | E63: 0.669 | F63: 2.536 | H63: 5.012 | I63: 8.975 | J63: -2.412 | K63: 2.056 | L63: 5.043 | M63: 3.99
A64: October 2025 (Bank staff projections) | B64: 0.581 | C64: 0.028 | D64: -0.017 | E64: 0.626 | F64: 2.488 | H64: 5.236 | I64: 0.84 | J64: -0.715 | K64: 1.923 | L64: 4.954 | M64: 3.706
A65: November 2025 (Bank staff projections) | B65: 0.583 | C65: 0.029 | D65: -0.048 | E65: 0.592 | F65: 2.49 | H65: 5.234 | I65: 0.857 | J65: -1.8 | K65: 1.813 | L65: 4.97 | M65: 3.646
A66: December 2025 (Bank staff projections) | B66: 0.616 | C66: 0.023 | D66: -0.094 | E66: 0.513 | F66: 2.535 | H66: 5.525 | I66: 0.682 | J66: -3.387 | K66: 1.574 | L66: 5.059 | M66: 3.593

Sheet MPR Chart 37 (Nov CPI)
A1: CPI inflation projections, by CPI component
A2: Per cent
A3: Twelve-month percentage change in CPI indices.
B5: Food and non-alcoholic beverages | C5: Electricity and gas | D5: Fuels and lubricants | E5: Other goods | F5: Services | G5: CPI
A6: 45931 | B6: 5 | C6: 1.8 | D6: 1.4 | E6: 1.9 | F6: 4.6 | G6: 3.6
A7: 45962 | B7: 5 | C7: 1.9 | D7: 0.4 | E7: 1.6 | F7: 4.5 | G7: 3.4
A8: 45992 | B8: 5.3 | C8: 1.8 | D8: -1.1 | E8: 1.6 | F8: 4.6 | G8: 3.5
A9: 46023 | B9: 4.4 | C9: 0.1 | D9: -2 | E9: 1.3 | F9: 4.2 | G9: 3
A10: 46054 | B10: 4.5 | C10: 0.1 | D10: -3.6 | E10: 1.8 | F10: 4.2 | G10: 3.1
A11: 46082 | B11: 4.6 | C11: 0.2 | D11: -1.6 | E11: 1.9 | F11: 4.3 | G11: 3.2

Sheet MPR Chart 1.3 (Nov pay)
A1: Section 1: Current economic conditions
A3: Chart 1.3 - Measures of private sector wage growth and higher-frequency wage growth with estimated trend
B5: Measures of private sector wage growth (percentage changes on a year earlier) | I5: Higher-frequency wage growth with estimated trend (three-month on three-month percentage changes)
A6: Date | B6: Private sector regular pay | C6: Agents' pay survey | D6: DMP | E6: Indeed wage tracker | F6: HMRC RTI median (private sector proxy) | I6: =B6 -> Private sector regular pay | J6: Estimated trend | K6: 90% Confidence Band (Lower) | L6: 68% Confidence Band (Lower) | M6: 68% Confidence Band (Upper) | N6: 90% Confidence Band (Upper)
A7: 43131 | B7: 2.716 | C7: n.a. | D7: n.a. | E7: n.a. | F7: 3.131 | H7: 40574 | I7: 1.695 | J7: 1.688 | K7: -0.181 | L7: 0.57 | M7: 2.822 | N7: 3.575
A8: 43159 | B8: 2.912 | C8: n.a. | D8: n.a. | E8: n.a. | F8: 3.288 | H8: 40602 | I8: 2.155 | J8: 1.698 | K8: -0.159 | L8: 0.589 | M8: 2.824 | N8: 3.573
A9: 43190 | B9: 3.018 | C9: n.a. | D9: n.a. | E9: n.a. | F9: 3.196 | H9: 40633 | I9: 3.2 | J9: 1.704 | K9: -0.138 | L9: 0.609 | M9: 2.821 | N9: 3.566
A10: 43220 | B10: 2.966 | C10: n.a. | D10: n.a. | E10: n.a. | F10: 2.96 | H10: 40663 | I10: 1.445 | J10: 1.685 | K10: -0.133 | L10: 0.611 | M10: 2.785 | N10: 3.527
A11: 43251 | B11: 2.905 | C11: n.a. | D11: n.a. | E11: n.a. | F11: 3.144 | H11: 40694 | I11: 1.342 | J11: 1.683 | K11: -0.099 | L11: 0.63 | M11: 2.762 | N11: 3.497
A12: 43281 | B12: 2.799 | C12: n.a. | D12: n.a. | E12: n.a. | F12: 3.408 | H12: 40724 | I12: 0.617 | J12: 1.694 | K12: -0.047 | L12: 0.664 | M12: 2.743 | N12: 3.47
A13: 43312 | B13: 2.995 | C13: n.a. | D13: n.a. | E13: n.a. | F13: 3.714 | H13: 40755 | I13: 1.602 | J13: 1.734 | K13: 0.036 | L13: 0.726 | M13: 2.756 | N13: 3.47
A14: 43343 | B14: 3.173 | C14: n.a. | D14: n.a. | E14: n.a. | F14: 3.832 | H14: 40786 | I14: 1.221 | J14: 1.777 | K14: 0.116 | L14: 0.792 | M14: 2.772 | N14: 3.47
A15: 43373 | B15: 3.275 | C15: n.a. | D15: n.a. | E15: n.a. | F15: 3.702 | H15: 40816 | I15: 1.806 | J15: 1.845 | K15: 0.21 | L15: 0.875 | M15: 2.822 | N15: 3.498
A16: 43404 | B16: 3.406 | C16: n.a. | D16: n.a. | E16: n.a. | F16: 3.775 | H16: 40847 | I16: 2.013 | J16: 1.914 | K16: 0.299 | L16: 0.955 | M16: 2.88 | N16: 3.536
A17: 43434 | B17: 3.442 | C17: n.a. | D17: n.a. | E17: n.a. | F17: 3.699 | H17: 40877 | I17: 2.809 | J17: 1.976 | K17: 0.373 | L17: 1.026 | M17: 2.928 | N17: 3.574
A18: 43465 | B18: 3.528 | C18: n.a. | D18: n.a. | E18: n.a. | F18: 3.69 | H18: 40908 | I18: 2.673 | J18: 1.99 | K18: 0.407 | L18: 1.053 | M18: 2.927 | N18: 3.57
... A20: 43524 | B20: 3.623 | C20: n.a. | D20: n.a. | E20: n.a. | F20: 3.615 | H20: 40968 | I20: 1.915 | J20: 1.911 | K20: 0.369 | L20: 0.995 | M20: 2.829 | N20: 3.463
A21: 43555 | B21: 3.605 | C21: n.a. | D21: n.a. | E21: 4.674 | F21: 3.728 | H21: 40999 | I21: 2.129 | J21: 1.859 | K21: 0.323 | L21: 0.945 | M21: 2.781 | N21: 3.409
A22: 43585 | B22: 3.588 | C22: n.a. | D22: n.a. | E22: 4.725 | F22: 3.758 | H22: 41029 | I22: 2.237 | J22: 1.795 | K22: 0.257 | L22: 0.879 | M22: 2.724 | N22: 3.345
A23: 43616 | B23: 3.694 | C23: n.a. | D23: n.a. | E23: 4.54 | F23: 3.724 | H23: 41060 | I23: 2.21 | J23: 1.706 | K23: 0.164 | L23: 0.788 | M23: 2.637 | N23: 3.257
A24: 43646 | B24: 3.944 | C24: n.a. | D24: n.a. | E24: 4.33 | F24: 3.452 | H24: 41090 | I24: 1.441 | J24: 1.587 | K24: 0.05 | L24: 0.67 | M24: 2.515 | N24: 3.136
A25: 43677 | B25: 3.948 | C25: n.a. | D25: n.a. | E25: 4.088 | F25: 3.371 | H25: 41121 | I25: 1.38 | J25: 1.472 | K25: -0.055 | L25: 0.559 | M25: 2.393 | N25: 3.022
A26: 43708 | B26: 3.881 | C26: n.a. | D26: n.a. | E26: 3.945 | F26: 3.243 | H26: 41152 | I26: 1.214 | J26: 1.359 | K26: -0.151 | L26: 0.454 | M26: 2.273 | N26: 2.909
A27: 43738 | B27: 3.701 | C27: n.a. | D27: n.a. | E27: 3.867 | F27: 3.418 | H27: 41182 | I27: 1.053 | J27: 1.252 | K27: -0.252 | L27: 0.352 | M27: 2.165 | N27: 2.8
A28: 43769 | B28: 3.475 | C28: n.a. | D28: n.a. | E28: 3.727 | F28: 3.202 | H28: 41213 | I28: 0.652 | J28: 1.158 | K28: -0.349 | L28: 0.256 | M28: 2.073 | N28: 2.698
A29: 43799 | B29: 3.318 | C29: n.a. | D29: n.a. | E29: 3.596 | F29: 3.091 | H29: 41243 | I29: 0.434 | J29: 1.092 | K29: -0.424 | L29: 0.184 | M29: 2.011 | N29: 2.626
A30: 43830 | B30: 3.174 | C30: n.a. | D30: n.a. | E30: 3.529 | F30: 3.096 | H30: 41274 | I30: 0.756 | J30: 1.065 | K30: -0.456 | L30: 0.152 | M30: 1.984 | N30: 2.597
A31: 43861 | B31: 3.017 | C31: n.a. | D31: n.a. | E31: 2.948 | F31: 3.334 | H31: 41305 | I31: 0.612 | J31: 1.054 | K31: -0.469 | L31: 0.139 | M31: 1.971 | N31: 2.592
A32: 43890 | B32: 2.871 | C32: n.a. | D32: n.a. | E32: 2.363 | F32: 3.679 | H32: 41333 | I32: 0.186 | J32: 1.065 | K32: -0.462 | L32: 0.148 | M32: 1.983 | N32: 2.611
... A58: 44681 | B58: 5.24 | C58: n.a. | D58: n.a. | E58: 5.29 | F58: 6.633 | H58: 42124 | I58: 4.292 | J58: 2.654 | K58: 0.924 | L58: 1.626 | M58: 3.7 | N58: 4.397
A59: 44712 | B59: 5.437 | C59: n.a. | D59: 5.465 | E59: 6.045 | F59: 6.749 | H59: 42155 | I59: 3.714 | J59: 2.573 | K59: 0.87 | L59: 1.56 | M59: 3.602 | N59: 4.294
A60: 44742 | B60: 5.66 | C60: n.a. | D60: 5.578 | E60: 6.377 | F60: 6.809 | H60: 42185 | I60: 2.308 | J60: 2.451 | K60: 0.784 | L60: 1.455 | M60: 3.458 | N60: 4.147
A61: 44773 | B61: 6.089 | C61: n.a. | D61: 5.541 | E61: 6.214 | F61: 7.077 | H61: 42216 | I61: 2.123 | J61: 2.34 | K61: 0.702 | L61: 1.355 | M61: 3.33 | N61: 4.015
A62: 44804 | B62: 6.362 | C62: n.a. | D62: 5.844 | E62: 6.155 | F62: 7.136 | H62: 42247 | I62: 1.622 | J62: 2.238 | K62: 0.618 | L62: 1.261 | M62: 3.218 | N62: 3.897
A63: 44834 | B63: 6.728 | C63: n.a. | D63: 6.099 | E63: 6.194 | F63: 7.098 | H63: 42277 | I63: 1.261 | J63: 2.165 | K63: 0.548 | L63: 1.188 | M63: 3.145 | N63: 3.819
A64: 44865 | B64: 7.019 | C64: n.a. | D64: 6.307 | E64: 6.384 | F64: 6.98 | H64: 42308 | I64: 0.268 | J64: 2.138 | K64: 0.518 | L64: 1.163 | M64: 3.121 | N64: 3.792
A65: 44895 | B65: 7.336 | C65: n.a. | D65: 6.22 | E65: 6.311 | F65: 6.881 | H65: 42338 | I65: 0.168 | J65: 2.211 | K65: 0.591 | L65: 1.24 | M65: 3.191 | N65: 3.855
A66: 44926 | B66: 7.338 | C66: n.a. | D66: 6.26 | E66: 6.285 | F66: 6.924 | H66: 42369 | I66: 1.278 | J66: 2.39 | K66: 0.766 | L66: 1.427 | M66: 3.363 | N66: 4.014
A67: 44957 | B67: 7.09 | C67: n.a. | D67: 6.34 | E67: 6.176 | F67: 7.088 | H67: 42400 | I67: 3.053 | J67: 2.626 | K67: 0.991 | L67: 1.664 | M67: 3.594 | N67: 4.236
A68: 44985 | B68: 7.057 | C68: n.a. | D68: 6.51 | E68: 6.159 | F68: 7.324 | H68: 42429 | I68: 4.679 | J68: 2.831 | K68: 1.186 | L68: 1.867 | M68: 3.801 | N68: 4.435
A69: 45016 | B69: 7.209 | C69: n.a. | D69: 6.48 | E69: 6.292 | F69: 7.367 | H69: 42460 | I69: 5.264 | J69: 2.928 | K69: 1.286 | L69: 1.965 | M69: 3.898 | N69: 4.527
A70: 45046 | B70: 7.733 | C70: n.a. | D70: 6.565 | E70: 6.676 | F70: 7.281 | H70: 42490 | I70: 4.826 | J70: 2.886 | K70: 1.27 | L70: 1.94 | M70: 3.846 | N70: 4.469
... A98: 45900 | B98: 4.421 | C98: n.a. | D98: 4.622 | E98: 5.715 | F98: 5.327 | H98: 43343 | I98: 3.221 | J98: 3.447 | K98: 1.963 | L98: 2.562 | M98: 4.345 | N98: 4.945
A99: Sep 2025 (Bank staff projections) | B99: 4.233 | C99: n.a. | D99: 4.647 | E99: 5.856 | F99: 5.067 | H99: 43373 | I99: 3.996 | J99: 3.554 | K99: 2.066 | L99: 2.665 | M99: 4.455 | N99: 5.049
A100: 45961 | B100: n.a | C100: n.a. | D100: 4.523 | E100: n.a. | F100: n.a. | H100: 43404 | I100: 4.097 | J100: 3.629 | K100: 2.127 | L100: 2.735 | M100: 4.533 | N100: 5.125
A101: 45991 | B101: n.a | C101: n.a. | D101: n.a. | E101: n.a. | F101: n.a. | H101: 43434 | I101: 3.875 | J101: 3.673 | K101: 2.151 | L101: 2.771 | M101: 4.581 | N101: 5.179
A102: Dec 2025 (Bank staff projections) | B102: 3.513 | C102: 3.7 | D102: 3.966 | E102: n.a. | F102: n.a. | H102: 43465 | I102: 3.959 | J102: 3.707 | K102: 2.167 | L102: 2.795 | M102: 4.62 | N102: 5.23
A103: 46023 | B103: n.a | C103: n.a. | D103: n.a. | E103: n.a. | F103: n.a. | H103: 43496 | I103: 4.135 | J103: 3.727 | K103: 2.173 | L103: 2.804 | M103: 4.652 | N103: 5.269
A104: 46054 | B104: n.a | C104: n.a. | D104: n.a. | E104: n.a. | F104: n.a. | H104: 43524 | I104: 4.214 | J104: 3.727 | K104: 2.158 | L104: 2.794 | M104: 4.668 | N104: 5.29
A105: Mar 2026 (Bank staff projections) | B105: 3.563 | C105: n.a. | D105: n.a. | E105: n.a. | F105: n.a. | H105: 43555 | I105: 4.242 | J105: 3.699 | K105: 2.107 | L105: 2.754 | M105: 4.657 | N105: 5.29
A106: 46113 | B106: n.a | C106: n.a. | D106: n.a. | E106: n.a. | F106: n.a. | H106: 43585 | I106: 3.423 | J106: 3.641 | K106: 2.024 | L106: 2.682 | M106: 4.612 | N106: 5.263
A107: 46143 | B107: n.a | C107: n.a. | D107: n.a. | E107: n.a. | F107: n.a. | H107: 43616 | I107: 3.468 | J107: 3.593 | K107: 1.949 | L107: 2.62 | M107: 4.576 | N107: 5.244
A108: Jun 2026 (Bank staff projections) | B108: 3.246 | C108: n.a. | D108: n.a. | E108: n.a. | F108: n.a. | H108: 43646 | I108: 3.578 | J108: 3.552 | K108: 1.881 | L108: 2.561 | M108: 4.548 | N108: 5.235
H109: 43677 | I109: 4.138 | J109: 3.511 | K109: 1.804 | L109: 2.5 | M109: 4.526 | N109: 5.236
H110: 43708 | I110: 3.969 | J110: 3.436 | K110: 1.685 | L110: 2.398 | M110: 4.479 | N110: 5.225
H111: 43738 | I111: 3.026 | J111: 3.331 | K111: 1.526 | L111: 2.256 | M111: 4.41 | N111: 5.195
H112: 43769 | I112: 2.217 | J112: 3.231 | K112: 1.366 | L112: 2.111 | M112: 4.355 | N112: 5.174
H113: 43799 | I113: 1.643 | J113: 3.167 | K113: 1.228 | L113: 1.998 | M113: 4.338 | N113: 5.182
H114: 43830 | I114: 1.866 | J114: 3.153 | K114: 1.142 | L114: 1.94 | M114: 4.373 | N114: 5.238
H115: 43861 | I115: 2.302 | J115: 3.178 | K115: 1.089 | L115: 1.919 | M115: 4.446 | N115: 5.329
H116: 43890 | I116: 2.42 | J116: 3.224 | K116: 1.06 | L116: 1.918 | M116: 4.544 | N116: 5.446
H117: 43921 | I117: 2.497 | J117: 3.281 | K117: 1.028 | L117: 1.922 | M117: 4.652 | N117: 5.584
H118: 43951 | I118: 1.467 | J118: 3.35 | K118: 1.005 | L118: 1.942 | M118: 4.768 | N118: 5.737
H119: 43982 | I119: 0.63 | J119: 3.454 | K119: 1.031 | L119: 2.007 | M119: 4.909 | N119: 5.917
H120: 44012 | I120: -0.821 | J120: 3.613 | K120: 1.139 | L120: 2.139 | M120: 5.097 | N120: 6.127
... H182: 45900 | I182: 3.476 | J182: 3.847 | K182: 1.773 | L182: 2.597 | M182: 5.117 | N182: 6.097

Sheet MPR Chart 2.17 (Aug pay)
A1: Section 2: Current economic conditions
A3: Chart 2.17 - Measures of private sector wage growth, per cent
A5: Date | B5: Private sector regular pay | C5: Agents' Pay survey | D5: DMP | E5: Indeed wage tracker | F5: HMRC RTI median (private sector proxy)
A6: 43131 | B6: 2.7 | C6: n.a. | D6: n.a. | E6: n.a. | F6: 3.1
A7: 43159 | B7: 2.9 | C7: n.a. | D7: n.a. | E7: n.a. | F7: 3.3
A8: 43190 | B8: 3 | C8: n.a. | D8: n.a. | E8: n.a. | F8: 3.2
A9: 43220 | B9: 3 | C9: n.a. | D9: n.a. | E9: n.a. | F9: 3
A10: 43251 | B10: 2.9 | C10: n.a. | D10: n.a. | E10: n.a. | F10: 3.1
A11: 43281 | B11: 2.8 | C11: n.a. | D11: n.a. | E11: n.a. | F11: 3.4
A12: 43312 | B12: 3 | C12: n.a. | D12: n.a. | E12: n.a. | F12: 3.7
A13: 43343 | B13: 3.2 | C13: n.a. | D13: n.a. | E13: n.a. | F13: 3.9
A14: 43373 | B14: 3.3 | C14: n.a. | D14: n.a. | E14: n.a. | F14: 3.8
A15: 43404 | B15: 3.4 | C15: n.a. | D15: n.a. | E15: n.a. | F15: 3.8
A16: 43434 | B16: 3.4 | C16: n.a. | D16: n.a. | E16: n.a. | F16: 3.7
A17: 43465 | B17: 3.5 | C17: n.a. | D17: n.a. | E17: n.a. | F17: 3.7
... A19: 43524 | B19: 3.6 | C19: n.a. | D19: n.a. | E19: n.a. | F19: 3.6
A20: 43555 | B20: 3.6 | C20: n.a. | D20: n.a. | E20: 4.7 | F20: 3.7
A21: 43585 | B21: 3.6 | C21: n.a. | D21: n.a. | E21: 4.7 | F21: 3.7
A22: 43616 | B22: 3.7 | C22: n.a. | D22: n.a. | E22: 4.5 | F22: 3.7
A23: 43646 | B23: 3.9 | C23: n.a. | D23: n.a. | E23: 4.3 | F23: 3.4
A24: 43677 | B24: 3.9 | C24: n.a. | D24: n.a. | E24: 4.1 | F24: 3.4
A25: 43708 | B25: 3.9 | C25: n.a. | D25: n.a. | E25: 3.9 | F25: 3.2
A26: 43738 | B26: 3.7 | C26: n.a. | D26: n.a. | E26: 3.9 | F26: 3.4
A27: 43769 | B27: 3.5 | C27: n.a. | D27: n.a. | E27: 3.8 | F27: 3.2
A28: 43799 | B28: 3.3 | C28: n.a. | D28: n.a. | E28: 3.6 | F28: 3.1
A29: 43830 | B29: 3.2 | C29: n.a. | D29: n.a. | E29: 3.5 | F29: 3.1
A30: 43861 | B30: 3 | C30: n.a. | D30: n.a. | E30: 3 | F30: 3.3
A31: 43890 | B31: 2.9 | C31: n.a. | D31: n.a. | E31: 2.4 | F31: 3.7
... A57: 44681 | B57: 5.2 | C57: n.a. | D57: n.a. | E57: 5.3 | F57: 6.7
A58: 44712 | B58: 5.4 | C58: n.a. | D58: 5.5 | E58: 6 | F58: 6.8
A59: 44742 | B59: 5.7 | C59: n.a. | D59: 5.6 | E59: 6.4 | F59: 6.8
A60: 44773 | B60: 6.1 | C60: n.a. | D60: 5.5 | E60: 6.2 | F60: 7.1
A61: 44804 | B61: 6.4 | C61: n.a. | D61: 5.8 | E61: 6.2 | F61: 7.1
A62: 44834 | B62: 6.7 | C62: n.a. | D62: 6.1 | E62: 6.2 | F62: 7.1
A63: 44865 | B63: 7 | C63: n.a. | D63: 6.3 | E63: 6.4 | F63: 6.9
A64: 44895 | B64: 7.3 | C64: n.a. | D64: 6.2 | E64: 6.3 | F64: 6.9
A65: 44926 | B65: 7.3 | C65: n.a. | D65: 6.3 | E65: 6.3 | F65: 6.9
A66: 44957 | B66: 7.1 | C66: n.a. | D66: 6.3 | E66: 6.2 | F66: 7.1
A67: 44985 | B67: 7.1 | C67: n.a. | D67: 6.5 | E67: 6.2 | F67: 7.3
A68: 45016 | B68: 7.2 | C68: n.a. | D68: 6.5 | E68: 6.3 | F68: 7.4
A69: 45046 | B69: 7.7 | C69: n.a. | D69: 6.6 | E69: 6.7 | F69: 7.3
... A94: 45808 | B94: 4.9 | C94: n.a. | D94: 4.7 | E94: 5.5 | F94: 5.7
A95: 45838 | B95: n.a. | C95: n.a. | D95: 4.6 | E95: 5.5 | F95: 5.7
A96: 45868 | B96: n.a. | C96: n.a. | D96: 4.7 | E96: n.a. | F96: n.a.
A97: 45900 | B97: n.a. | C97: n.a. | D97: n.a. | E97: n.a. | F97: n.a.
A98: September 2025 (Bank staff projections) | B98: 4.623 | C98: n.a. | D98: n.a. | E98: n.a. | F98: n.a.
A99: 45961 | B99: n.a. | C99: n.a. | D99: n.a. | E99: n.a. | F99: n.a.
A100: 45991 | B100: n.a. | C100: n.a. | D100: n.a. | E100: n.a. | F100: n.a.
A101: December 2025 (Bank staff projections) | B101: 3.657 | C101: 3.7 | D101: 3.966 | E101: n.a. | F101: n.a.

Sheet Chart Data
A1: Services inflation | G1: Private sector pay growth | L1: Inflation forecasts | S1: BoE DMP | Y1: BoE DMP | AE1: Trade policy uncertainty | AI1: Oil price scenarios | AP1: Gas price scenarios
B2: Headline services inflation
B3: Headline services inflation | C3: BoE staff forecast (Aug-25) | D3: BoE staff forecast (Nov-25) | E3: BoE's measure of underlying services inflation* | H3: Outturn | I3: BoE staff forecast (Aug) | J3: BoE staff forecast (Aug) | M3: CPI inflation | N3: BoE market expectations (Nov-25) | O3: Oxford Economics (Jan-26) | P3: HMT consensus (Jan-26) | Q3: 2% LINE | T3: Prices - past year | U3: Prices - next year | V3: Wages - past year | W3: Wages - next year | Z3: Prices - past year | AA3: Prices - next year | AB3: Wages - past year | AC3: Wages - next year | AF3: UK economic policy uncertainty (LHS) | AG3: US trade policy uncertainty (RHS) | AI3: Date | AJ3: Spot | AK3: BoE Scenario A | AL3: BoE Scenario B | AM3: Current market curve | AN3: BoE Scenario C | AP3: =AI3 -> Date | AQ3: Spot | AR3: BoE Scenario A | AS3: BoE Scenario B | AT3: Market curve - 18 June | AV3: BoE Scenario C
A4: 44562 | B4: =100*((HAVERM!D152/HAVERM!D140)-1) -> 3.2685512 | E4: =[2]Monthly!QL406 -> 0.95662297 | G4: 44562 | H4: =HAVERM!E152 -> 4.5 | I4: =NA() -> #N/A | J4: =NA() -> #N/A | L4: 44927 | M4: =100*((HAVERQ!F40/HAVERQ!F36)-1) -> 10.178263 | Q4: 2 | S4: 43466 | T4: =HAVERM!F116 -> 2.79 | U4: =HAVERM!G116 -> 2.53 | V4: =HAVERM!H116 -> #N/A | W4: =HAVERM!I116 -> #N/A | Y4: 43466 | Z4: =HAVERM!J116 -> 2.527 | AA4: =HAVERM!K116 -> 2.471 | AB4: =HAVERM!L116 -> #N/A | AC4: =HAVERM!M116 -> #N/A | AE4: 42005 | AF4: =HAVERM!P68 -> 135.73044 | AG4: ='Bloom - Monthly US data'!M362 -> 33.807758 | AI4: =HAVERD!A791 -> 45658 | AJ4: =HAVERD!IH791 -> 74.83 | AK4: =NA() -> #N/A | AL4: =NA() -> #N/A | AM4: =NA() -> #N/A | AN4: =NA() -> #N/A | AP4: =AI4 -> 45658 | AQ4: =HAVERD!II791 -> #N/A | AR4: =NA() -> #N/A | AS4: =NA() -> #N/A | AT4: =NA() -> #N/A
A5: 44593 | B5: =100*((HAVERM!D153/HAVERM!D141)-1) -> 3.4391534 | E5: =[2]Monthly!QL407 -> 1.0018438 | G5: 44593 | H5: =HAVERM!E153 -> 4.9 | I5: =NA() -> #N/A | J5: =NA() -> #N/A | L5: 45017 | M5: =100*((HAVERQ!F41/HAVERQ!F37)-1) -> 8.4390513 | Q5: 2 | S5: 43497 | T5: =HAVERM!F117 -> 2.278 | U5: =HAVERM!G117 -> 2.587 | V5: =HAVERM!H117 -> #N/A | W5: =HAVERM!I117 -> #N/A | Y5: 43497 | Z5: =HAVERM!J117 -> 2.432 | AA5: =HAVERM!K117 -> 2.433 | AB5: =HAVERM!L117 -> #N/A | AC5: =HAVERM!M117 -> #N/A | AE5: 42036 | AF5: =HAVERM!P69 -> 119.08362 | AG5: ='Bloom - Monthly US data'!M363 -> 15.410779 | AI5: =HAVERD!A792 -> 45659 | AJ5: =HAVERD!IH792 -> 76.05 | AK5: =NA() -> #N/A | AL5: =NA() -> #N/A | AM5: =NA() -> #N/A | AN5: =NA() -> #N/A | AP5: =AI5 -> 45659 | AQ5: =HAVERD!II792 -> 125.18 | AR5: =NA() -> #N/A | AS5: =NA() -> #N/A | AT5: =NA() -> #N/A
A6: 44621 | B6: =100*((HAVERM!D154/HAVERM!D142)-1) -> 3.9612676 | E6: =[2]Monthly!QL408 -> 0.99771662 | G6: 44621 | H6: =HAVERM!E154 -> 5.3 | I6: =NA() -> #N/A | J6: =NA() -> #N/A | L6: 45108 | M6: =100*((HAVERQ!F42/HAVERQ!F38)-1) -> 6.7135896 | Q6: 2 | S6: 43525 | T6: =HAVERM!F118 -> 2.407 | U6: =HAVERM!G118 -> 2.071 | V6: =HAVERM!H118 -> #N/A | W6: =HAVERM!I118 -> #N/A | Y6: 43525 | Z6: =HAVERM!J118 -> 2.492 | AA6: =HAVERM!K118 -> 2.396 | AB6: =HAVERM!L118 -> #N/A | AC6: =HAVERM!M118 -> #N/A | AE6: 42064 | AF6: =HAVERM!P70 -> 131.49865 | AG6: ='Bloom - Monthly US data'!M364 -> 27.907613 | AI6: =HAVERD!A793 -> 45660 | AJ6: =HAVERD!IH793 -> 76.52 | AK6: =NA() -> #N/A | AL6: =NA() -> #N/A | AM6: =NA() -> #N/A | AN6: =NA() -> #N/A | AP6: =AI6 -> 45660 | AQ6: =HAVERD!II793 -> 123.82 | AR6: =NA() -> #N/A | AS6: =NA() -> #N/A | AT6: =NA() -> #N/A
A7: 44652 | B7: =100*((HAVERM!D155/HAVERM!D143)-1) -> 4.7244094 | E7: =[2]Monthly!QL409 -> 0.99370277 | G7: 44652 | H7: =HAVERM!E155 -> 5.2 | I7: =NA() -> #N/A | J7: =NA() -> #N/A | L7: 45200 | M7: =100*((HAVERQ!F43/HAVERQ!F39)-1) -> 4.1568008 | Q7: 2 | S7: 43556 | T7: =HAVERM!F119 -> 2.732 | U7: =HAVERM!G119 -> 2.655 | V7: =HAVERM!H119 -> #N/A | W7: =HAVERM!I119 -> #N/A | Y7: 43556 | Z7: =HAVERM!J119 -> 2.472 | AA7: =HAVERM!K119 -> 2.438 | AB7: =HAVERM!L119 -> #N/A | AC7: =HAVERM!M119 -> #N/A | AE7: 42095 | AF7: =HAVERM!P71 -> 170.47333 | AG7: ='Bloom - Monthly US data'!M365 -> 41.600503 | AI7: =HAVERD!A794 -> 45663 | AJ7: =HAVERD!IH794 -> 76.04 | AK7: =NA() -> #N/A | AL7: =NA() -> #N/A | AM7: =NA() -> #N/A | AN7: =NA() -> #N/A | AP7: =AI7 -> 45663 | AQ7: =HAVERD!II794 -> 117.91 | AR7: =NA() -> #N/A | AS7: =NA() -> #N/A | AT7: =NA() -> #N/A
A8: 44682 | B8: =100*((HAVERM!D156/HAVERM!D144)-1) -> 4.886562 | E8: =[2]Monthly!QL410 -> 0.99868594 | G8: 44682 | H8: =HAVERM!E156 -> 5.4 | I8: =NA() -> #N/A | J8: =NA() -> #N/A | L8: 45292 | M8: =100*((HAVERQ!F44/HAVERQ!F40)-1) -> 3.5490605 | Q8: 2 | S8: 43586 | T8: =HAVERM!F120 -> 1.774 | U8: =HAVERM!G120 -> 2.318 | V8: =HAVERM!H120 -> #N/A | W8: =HAVERM!I120 -> #N/A | Y8: 43586 | Z8: =HAVERM!J120 -> 2.304 | AA8: =HAVERM!K120 -> 2.348 | AB8: =HAVERM!L120 -> #N/A | AC8: =HAVERM!M120 -> #N/A | AE8: 42125 | AF8: =HAVERM!P72 -> 140.91246 | AG8: ='Bloom - Monthly US data'!M366 -> 88.91986 | AI8: =HAVERD!A795 -> 45664 | AJ8: =HAVERD!IH795 -> 77.23 | AK8: =NA() -> #N/A | AL8: =NA() -> #N/A | AM8: =NA() -> #N/A | AN8: =NA() -> #N/A | AP8: =AI8 -> 45664 | AQ8: =HAVERD!II795 -> 118.16 | AR8: =NA() -> #N/A | AS8: =NA() -> #N/A | AT8: =NA() -> #N/A
A9: 44713 | B9: =100*((HAVERM!D157/HAVERM!D145)-1) -> 5.2173913 | E9: =[2]Monthly!QL411 -> 0.99631169 | G9: 44713 | H9: =HAVERM!E157 -> 5.7 | I9: =NA() -> #N/A | J9: =NA() -> #N/A | L9: 45383 | M9: =100*((HAVERQ!F45/HAVERQ!F41)-1) -> 2.110885 | Q9: 2 | S9: 43617 | T9: =HAVERM!F121 -> 2.715 | U9: =HAVERM!G121 -> 2.165 | V9: =HAVERM!H121 -> #N/A | W9: =HAVERM!I121 -> #N/A | Y9: 43617 | Z9: =HAVERM!J121 -> 2.407 | AA9: =HAVERM!K121 -> 2.379 | AB9: =HAVERM!L121 -> #N/A | AC9: =HAVERM!M121 -> #N/A | AE9: 42156 | AF9: =HAVERM!P73 -> 148.81656 | AG9: ='Bloom - Monthly US data'!M367 -> 100.80304 | AI9: =HAVERD!A796 -> 45665 | AJ9: =HAVERD!IH796 -> 76.12 | AK9: =NA() -> #N/A | AL9: =NA() -> #N/A | AM9: =NA() -> #N/A | AN9: =NA() -> #N/A | AP9: =AI9 -> 45665 | AQ9: =HAVERD!II796 -> 114.03 | AR9: =NA() -> #N/A | AS9: =NA() -> #N/A | AT9: =NA() -> #N/A
A10: 44743 | B10: =100*((HAVERM!D158/HAVERM!D146)-1) -> 5.7241977 | E10: =[2]Monthly!QL412 -> 1.0017211 | G10: 44743 | H10: =HAVERM!E158 -> 6.1 | I10: =NA() -> #N/A | J10: =NA() -> #N/A | L10: 45474 | M10: =100*((HAVERQ!F46/HAVERQ!F42)-1) -> 2.0547945 | Q10: 2 | S10: 43647 | T10: =HAVERM!F122 -> 2.265 | U10: =HAVERM!G122 -> 2.099 | V10: =HAVERM!H122 -> #N/A | W10: =HAVERM!I122 -> #N/A | Y10: 43647 | Z10: =HAVERM!J122 -> 2.252 | AA10: =HAVERM!K122 -> 2.194 | AB10: =HAVERM!L122 -> #N/A | AC10: =HAVERM!M122 -> #N/A | AE10: 42186 | AF10: =HAVERM!P74 -> 136.10011 | AG10: ='Bloom - Monthly US data'!M368 -> 51.49282 | AI10: =HAVERD!A797 -> 45666 | AJ10: =HAVERD!IH797 -> 77.08 | AK10: =NA() -> #N/A | AL10: =NA() -> #N/A | AM10: =NA() -> #N/A | AN10: =NA() -> #N/A | AP10: =AI10 -> 45666 | AQ10: =HAVERD!II797 -> 112.93 | AR10: =NA() -> #N/A | AS10: =NA() -> #N/A | AT10: =NA() -> #N/A
A11: 44774 | B11: =100*((HAVERM!D159/HAVERM!D147)-1) -> 5.9585492 | E11: =[2]Monthly!QL413 -> 1.0034465 | G11: 44774 | H11: =HAVERM!E159 -> 6.4 | I11: =NA() -> #N/A | J11: =NA() -> #N/A | L11: 45566 | M11: =100*((HAVERQ!F47/HAVERQ!F43)-1) -> 2.4753726 | Q11: 2 | S11: 43678 | T11: =HAVERM!F123 -> 1.908 | U11: =HAVERM!G123 -> 2.281 | V11: =HAVERM!H123 -> #N/A | W11: =HAVERM!I123 -> #N/A | Y11: 43678 | Z11: =HAVERM!J123 -> 2.296 | AA11: =HAVERM!K123 -> 2.182 | AB11: =HAVERM!L123 -> #N/A | AC11: =HAVERM!M123 -> #N/A | AE11: 42217 | AF11: =HAVERM!P75 -> 86.14368 | AG11: ='Bloom - Monthly US data'!M369 -> 20.829576 | AI11: =HAVERD!A798 -> 45667 | AJ11: =HAVERD!IH798 -> 79.29 | AK11: =NA() -> #N/A | AL11: =NA() -> #N/A | AM11: =NA() -> #N/A | AN11: =NA() -> #N/A | AP11: =AI11 -> 45667 | AQ11: =HAVERD!II798 -> 113.07 | AR11: =NA() -> #N/A | AS11: =NA() -> #N/A | AT11: =NA() -> #N/A
A12: 44805 | B12: =100*((HAVERM!D160/HAVERM!D148)-1) -> 6.1312608 | E12: =[2]Monthly!QL414 -> 1.0021341 | G12: 44805 | H12: =HAVERM!E160 -> 6.7 | I12: =NA() -> #N/A | J12: =NA() -> #N/A | L12: 45658 | M12: =100*((HAVERQ!F48/HAVERQ!F44)-1) -> 2.797379 | Q12: 2 | S12: 43709 | T12: =HAVERM!F124 -> 2.255 | U12: =HAVERM!G124 -> 2.342 | V12: =HAVERM!H124 -> #N/A | W12: =HAVERM!I124 -> #N/A | Y12: 43709 | Z12: =HAVERM!J124 -> 2.143 | AA12: =HAVERM!K124 -> 2.241 | AB12: =HAVERM!L124 -> #N/A | AC12: =HAVERM!M124 -> #N/A | AE12: 42248 | AF12: =HAVERM!P76 -> 135.07501 | AG12: ='Bloom - Monthly US data'!M370 -> 19.60964 | AI12: =HAVERD!A799 -> 45670 | AJ12: =HAVERD!IH799 -> 81.23 | AK12: =NA() -> #N/A | AL12: =NA() -> #N/A | AM12: =NA() -> #N/A | AN12: =NA() -> #N/A | AP12: =AI12 -> 45670 | AQ12: =HAVERD!II799 -> 121.5 | AR12: =NA() -> #N/A | AS12: =NA() -> #N/A | AT12: =NA() -> #N/A
A13: 44835 | B13: =100*((HAVERM!D161/HAVERM!D149)-1) -> 6.2660944 | E13: =[2]Monthly!QL415 -> 1.00101 | G13: 44835 | H13: =HAVERM!E161 -> 7 | I13: =NA() -> #N/A | J13: =NA() -> #N/A | L13: 45748 | M13: =100*((HAVERQ!F49/HAVERQ!F45)-1) -> 3.486924 | Q13: 2 | S13: 43739 | T13: =HAVERM!F125 -> 1.994 | U13: =HAVERM!G125 -> 2.214 | V13: =HAVERM!H125 -> #N/A | W13: =HAVERM!I125 -> #N/A | Y13: 43739 | Z13: =HAVERM!J125 -> 2.052 | AA13: =HAVERM!K125 -> 2.279 | AB13: =HAVERM!L125 -> #N/A | AC13: =HAVERM!M125 -> #N/A | AE13: 42278 | AF13: =HAVERM!P77 -> 89.91453 | AG13: ='Bloom - Monthly US data'!M371 -> 68.608963 | AI13: =HAVERD!A800 -> 45671 | AJ13: =HAVERD!IH800 -> 80.14 | AK13: =NA() -> #N/A | AL13: =NA() -> #N/A | AM13: =NA() -> #N/A | AN13: =NA() -> #N/A | AP13: =AI13 -> 45671 | AQ13: =HAVERD!II800 -> 118.62 | AR13: =NA() -> #N/A | AS13: =NA() -> #N/A | AT13: =NA() -> #N/A
A14: 44866 | B14: =100*((HAVERM!D162/HAVERM!D150)-1) -> 6.3464837 | E14: =[2]Monthly!QL416 -> 1.0006663 | G14: 44866 | H14: =HAVERM!E162 -> 7.3 | I14: =NA() -> #N/A | J14: =NA() -> #N/A | L14: 45839 | M14: =100*((HAVERQ!F50/HAVERQ!F46)-1) -> 3.803132 | N14: =HAVERQ!C50 -> 3.8 | Q14: 2 | S14: 43770 | T14: =HAVERM!F126 -> 1.859 | U14: =HAVERM!G126 -> 2.152 | V14: =HAVERM!H126 -> #N/A | W14: =HAVERM!I126 -> #N/A | Y14: 43770 | Z14: =HAVERM!J126 -> 2.036 | AA14: =HAVERM!K126 -> 2.236 | AB14: =HAVERM!L126 -> #N/A | AC14: =HAVERM!M126 -> #N/A | AE14: 42309 | AF14: =HAVERM!P78 -> 120.86215 | AG14: ='Bloom - Monthly US data'!M372 -> 20.503122 | AI14: =HAVERD!A801 -> 45672 | AJ14: =HAVERD!IH801 -> 81.67 | AK14: =NA() -> #N/A | AL14: =NA() -> #N/A | AM14: =NA() -> #N/A | AN14: =NA() -> #N/A | AP14: =AI14 -> 45672 | AQ14: =HAVERD!II801 -> 118.45 | AR14: =NA() -> #N/A | AS14: =NA() -> #N/A | AT14: =NA() -> #N/A
A15: 44896 | B15: =100*((HAVERM!D163/HAVERM!D151)-1) -> 6.8376068 | E15: =[2]Monthly!QL417 -> 1.0014071 | G15: 44896 | H15: =HAVERM!E163 -> 7.3 | I15: =NA() -> #N/A | J15: =NA() -> #N/A | L15: 45931 | M15: =100*((HAVERQ!F51/HAVERQ!F47)-1) -> 3.3768795 | N15: =HAVERQ!C51 -> 3.4 | O15: =100*((GMW!B218/GMW!B214)-1) -> 3.3769049 | P15: 3.4 | Q15: 2 | S15: 43800 | T15: =HAVERM!F127 -> 1.992 | U15: =HAVERM!G127 -> 2.372 | V15: =HAVERM!H127 -> #N/A | W15: =HAVERM!I127 -> #N/A | Y15: 43800 | Z15: =HAVERM!J127 -> 1.948 | AA15: =HAVERM!K127 -> 2.246 | AB15: =HAVERM!L127 -> #N/A | AC15: =HAVERM!M127 -> #N/A | AE15: 42339 | AF15: =HAVERM!P79 -> 82.87279 | AG15: ='Bloom - Monthly US data'!M373 -> 20.475546 | AI15: =HAVERD!A802 -> 45673 | AJ15: =HAVERD!IH802 -> 81.14 | AK15: =NA() -> #N/A | AL15: =NA() -> #N/A | AM15: =NA() -> #N/A | AN15: =NA() -> #N/A | AP15: =AI15 -> 45673 | AQ15: =HAVERD!II802 -> 116.39 | AR15: =NA() -> #N/A | AS15: =NA() -> #N/A | AT15: =NA() -> #N/A
A16: 44927 | B16: =100*((HAVERM!D164/HAVERM!D152)-1) -> 5.9024808 | E16: =[2]Monthly!QL418 -> 1.0004456 | G16: 44927 | H16: =HAVERM!E164 -> 7.1 | I16: =NA() -> #N/A | J16: =NA() -> #N/A | L16: 46023 | N16: =HAVERQ!C52 -> 3.1 | O16: =100*((GMW!B219/GMW!B215)-1) -> 3.0469961 | Q16: 2 | S16: 43831 | T16: =HAVERM!F128 -> 2.061 | U16: =HAVERM!G128 -> 2.117 | V16: =HAVERM!H128 -> #N/A | W16: =HAVERM!I128 -> #N/A | Y16: 43831 | Z16: =HAVERM!J128 -> 1.971 | AA16: =HAVERM!K128 -> 2.214 | AB16: =HAVERM!L128 -> #N/A | AC16: =HAVERM!M128 -> #N/A | AE16: 42370 | AF16: =HAVERM!P80 -> 135.63232 | AG16: ='Bloom - Monthly US data'!M374 -> 42.781123 | AI16: =HAVERD!A803 -> 45674 | AJ16: =HAVERD!IH803 -> 80.84 | AK16: =NA() -> #N/A | AL16: =NA() -> #N/A | AM16: =NA() -> #N/A | AN16: =NA() -> #N/A | AP16: =AI16 -> 45674 | AQ16: =HAVERD!II803 -> 118.31 | AR16: =NA() -> #N/A | AS16: =NA() -> #N/A | AT16: =NA() -> #N/A
A17: 44958 | B17: =100*((HAVERM!D165/HAVERM!D153)-1) -> 6.6496164 | E17: =[2]Monthly!QL419 -> 1.0043349 | G17: 44958 | H17: =HAVERM!E165 -> 7.1 | I17: =NA() -> #N/A | J17: =NA() -> #N/A | L17: 46113 | N17: =HAVERQ!C53 -> 3.1 | O17: =100*((GMW!B220/GMW!B216)-1) -> 3.5307581 | Q17: 2 | S17: 43862 | T17: =HAVERM!F129 -> 1.739 | U17: =HAVERM!G129 -> 2.094 | V17: =HAVERM!H129 -> #N/A | W17: =HAVERM!I129 -> #N/A | Y17: 43862 | Z17: =HAVERM!J129 -> 1.931 | AA17: =HAVERM!K129 -> 2.195 | AB17: =HAVERM!L129 -> #N/A | AC17: =HAVERM!M129 -> #N/A | AE17: 42401 | AF17: =HAVERM!P81 -> 190.81671 | AG17: ='Bloom - Monthly US data'!M375 -> 26.272142 | AI17: =HAVERD!A804 -> 45677 | AJ17: =HAVERD!IH804 -> 79.04 | AK17: =NA() -> #N/A | AL17: =NA() -> #N/A | AM17: =NA() -> #N/A | AN17: =NA() -> #N/A | AP17: =AI17 -> 45677 | AQ17: =HAVERD!II804 -> 121.35 | AR17: =NA() -> #N/A | AS17: =NA() -> #N/A | AT17: =NA() -> #N/A
A18: 44986 | B18: =100*((HAVERM!D166/HAVERM!D154)-1) -> 6.6892464 | E18: =[2]Monthly!QL420 -> 1.0062135 | G18: 44986 | H18: =HAVERM!E166 -> 7.2 | I18: =NA() -> #N/A | J18: =NA() -> #N/A | L18: 46204 | N18: =HAVERQ!C54 -> 3.3 | O18: =100*((GMW!B221/GMW!B217)-1) -> 4.3968391 | Q18: 2 | S18: 43891 | T18: =HAVERM!F130 -> 1.69 | U18: =HAVERM!G130 -> 1.598 | V18: =HAVERM!H130 -> #N/A | W18: =HAVERM!I130 -> #N/A | Y18: 43891 | Z18: =HAVERM!J130 -> 1.83 | AA18: =HAVERM!K130 -> 1.937 | AB18: =HAVERM!L130 -> #N/A | AC18: =HAVERM!M130 -> #N/A | AE18: 42430 | AF18: =HAVERM!P82 -> 290.92952 | AG18: ='Bloom - Monthly US data'!M376 -> 49.187943 | AI18: =HAVERD!A805 -> 45678 | AJ18: =HAVERD!IH805 -> 78.22 | AK18: =NA() -> #N/A | AL18: =NA() -> #N/A | AM18: =NA() -> #N/A | AN18: =NA() -> #N/A | AP18: =AI18 -> 45678 | AQ18: =HAVERD!II805 -> 126.61 | AR18: =NA() -> #N/A | AS18: =NA() -> #N/A | AT18: =NA() -> #N/A
A19: 45017 | B19: =100*((HAVERM!D167/HAVERM!D155)-1) -> 6.9340017 | E19: =[2]Monthly!QL421 -> 1.0074467 | G19: 45017 | H19: =HAVERM!E167 -> 7.7 | I19: =NA() -> #N/A | J19: =NA() -> #N/A | L19: 46296 | N19: =HAVERQ!C55 -> 3.6 | O19: =100*((GMW!B222/GMW!B218)-1) -> 4.4335479 | P19: 2.1 | Q19: 2 | S19: 43922 | T19: =HAVERM!F131 -> 1.865 | U19: =HAVERM!G131 -> 1.213 | V19: =HAVERM!H131 -> #N/A | W19: =HAVERM!I131 -> #N/A | Y19: 43922 | Z19: =HAVERM!J131 -> 1.765 | AA19: =HAVERM!K131 -> 1.635 | AB19: =HAVERM!L131 -> #N/A | AC19: =HAVERM!M131 -> #N/A | AE19: 42461 | AF19: =HAVERM!P83 -> 197.1708 | AG19: ='Bloom - Monthly US data'!M377 -> 42.923388 | AI19: =HAVERD!A806 -> 45679 | AJ19: =HAVERD!IH806 -> 78.35 | AK19: =NA() -> #N/A | AL19: =NA() -> #N/A | AM19: =NA() -> #N/A | AN19: =NA() -> #N/A | AP19: =AI19 -> 45679 | AQ19: =HAVERD!II806 -> 122.87 | AR19: =NA() -> #N/A | AS19: =NA() -> #N/A | AT19: =NA() -> #N/A
A20: 45047 | B20: =100*((HAVERM!D168/HAVERM!D156)-1) -> 7.3211314 | E20: =[2]Monthly!QL422 -> 1.0102061 | G20: 45047 | H20: =HAVERM!E168 -> 7.9 | I20: =NA() -> #N/A | J20: =NA() -> #N/A | L20: 46388 | N20: =HAVERQ!C56 -> 3.4 | O20: =100*((GMW!B223/GMW!B219)-1) -> 4.1758737 | Q20: 2 | S20: 43952 | T20: =HAVERM!F132 -> 1.722 | U20: =HAVERM!G132 -> 1.389 | V20: =HAVERM!H132 -> #N/A | W20: =HAVERM!I132 -> #N/A | Y20: 43952 | Z20: =HAVERM!J132 -> 1.759 | AA20: =HAVERM!K132 -> 1.4 | AB20: =HAVERM!L132 -> #N/A | AC20: =HAVERM!M132 -> #N/A | AE20: 42491 | AF20: =HAVERM!P84 -> 246.75491 | AG20: ='Bloom - Monthly US data'!M378 -> 76.848017 | AI20: =HAVERD!A807 -> 45680 | AJ20: =HAVERD!IH807 -> 77.57 | AK20: =NA() -> #N/A | AL20: =NA() -> #N/A | AM20: =NA() -> #N/A | AN20: =NA() -> #N/A | AP20: =AI20 -> 45680 | AQ20: =HAVERD!II807 -> 123.5 | AR20: =NA() -> #N/A | AS20: =NA() -> #N/A | AT20: =NA() -> #N/A
A21: 45078 | B21: =100*((HAVERM!D169/HAVERM!D157)-1) -> 7.1900826 | E21: =[2]Monthly!QL423 -> 1.0104651 | G21: 45078 | H21: =HAVERM!E169 -> 8.2 | I21: =NA() -> #N/A | J21: =NA() -> #N/A | L21: 46478 | N21: =HAVERQ!C57 -> 2.9 | O21: =100*((GMW!B224/GMW!B220)-1) -> 2.8273221 | Q21: 2 | S21: 43983 | T21: =HAVERM!F133 -> 1.182 | U21: =HAVERM!G133 -> 1.431 | V21: =HAVERM!H133 -> #N/A | W21: =HAVERM!I133 -> #N/A | Y21: 43983 | Z21: =HAVERM!J133 -> 1.59 | AA21: =HAVERM!K133 -> 1.344 | AB21: =HAVERM!L133 -> #N/A | AC21: =HAVERM!M133 -> #N/A | AE21: 42522 | AF21: =HAVERM!P85 -> 503.94249 | AG21: ='Bloom - Monthly US data'!M379 -> 271.07246 | AI21: =HAVERD!A808 -> 45681 | AJ21: =HAVERD!IH808 -> 77.4 | AK21: =NA() -> #N/A | AL21: =NA() -> #N/A | AM21: =NA() -> #N/A | AN21: =NA() -> #N/A | AP21: =AI21 -> 45681 | AQ21: =HAVERD!II808 -> 124.73 | AR21: =NA() -> #N/A | AS21: =NA() -> #N/A | AT21: =NA() -> #N/A
A22: 45108 | B22: =100*((HAVERM!D170/HAVERM!D158)-1) -> 7.4651354 | E22: =[2]Monthly!QL424 -> 0.96367284 | G22: 45108 | H22: =HAVERM!E170 -> 8.1 | I22: =NA() -> #N/A | J22: =NA() -> #N/A | L22: 46569 | N22: =HAVERQ!C58 -> 2.3 | O22: =100*((GMW!B225/GMW!B221)-1) -> 1.8462652 | Q22: 2 | S22: 44013 | T22: =HAVERM!F134 -> 1.339 | U22: =HAVERM!G134 -> 1.661 | V22: =HAVERM!H134 -> #N/A | W22: =HAVERM!I134 -> #N/A | Y22: 44013 | Z22: =HAVERM!J134 -> 1.414 | AA22: =HAVERM!K134 -> 1.494 | AB22: =HAVERM!L134 -> #N/A | AC22: =HAVERM!M134 -> #N/A | AE22: 42552 | AF22: =HAVERM!P86 -> 558.22364 | AG22: ='Bloom - Monthly US data'!M380 -> 116.30264 | AI22: =HAVERD!A809 -> 45684 | AJ22: =HAVERD!IH809 -> 75.95 | AK22: =NA() -> #N/A | AL22: =NA() -> #N/A | AM22: =NA() -> #N/A | AN22: =NA() -> #N/A | AP22: =AI22 -> 45684 | AQ22: =HAVERD!II809 -> 120.15 | AR22: =NA() -> #N/A | AS22: =NA() -> #N/A | AT22: =NA() -> #N/A
A23: 45139 | B23: =100*((HAVERM!D171/HAVERM!D159)-1) -> 6.7644662 | E23: =[2]Monthly!QL425 -> 0.96559283 | G23: 45139 | H23: =HAVERM!E171 -> 8.1 | I23: =NA() -> #N/A | J23: =NA() -> #N/A | L23: 46661 | N23: =HAVERQ!C59 -> 1.7 | O23: =100*((GMW!B226/GMW!B222)-1) -> 1.7594065 | Q23: 2 | S23: 44044 | T23: =HAVERM!F135 -> 1.039 | U23: =HAVERM!G135 -> 2.158 | V23: =HAVERM!H135 -> #N/A | W23: =HAVERM!I135 -> #N/A | Y23: 44044 | Z23: =HAVERM!J135 -> 1.186 | AA23: =HAVERM!K135 -> 1.75 | AB23: =HAVERM!L135 -> #N/A | AC23: =HAVERM!M135 -> #N/A | AE23: 42583 | AF23: =HAVERM!P87 -> 311.36483 | AG23: ='Bloom - Monthly US data'!M381 -> 155.27431 | AI23: =HAVERD!A810 -> 45685 | AJ23: =HAVERD!IH810 -> 75.94 | AK23: =NA() -> #N/A | AL23: =NA() -> #N/A | AM23: =NA() -> #N/A | AN23: =NA() -> #N/A | AP23: =AI23 -> 45685 | AQ23: =HAVERD!II810 -> 121.2 | AR23: =NA() -> #N/A | AS23: =NA() -> #N/A | AT23: =NA() -> #N/A
A24: 45170 | B24: =100*((HAVERM!D172/HAVERM!D160)-1) -> 6.916192 | E24: =[2]Monthly!QL426 -> 0.96751365 | G24: 45170 | H24: =HAVERM!E172 -> 7.8 | I24: =NA() -> #N/A | J24: =NA() -> #N/A | L24: 46753 | N24: =HAVERQ!C60 -> 1.4 | O24: =100*((GMW!B227/GMW!B223)-1) -> 1.862834 | Q24: 2 | S24: 44075 | T24: =HAVERM!F136 -> 1.572 | U24: =HAVERM!G136 -> 1.853 | V24: =HAVERM!H136 -> #N/A | W24: =HAVERM!I136 -> #N/A | Y24: 44075 | Z24: =HAVERM!J136 -> 1.317 | AA24: =HAVERM!K136 -> 1.891 | AB24: =HAVERM!L136 -> #N/A | AC24: =HAVERM!M136 -> #N/A | AE24: 42614 | AF24: =HAVERM!P88 -> 209.63794 | AG24: ='Bloom - Monthly US data'!M382 -> 93.079444 | AI24: =HAVERD!A811 -> 45686 | AJ24: =HAVERD!IH811 -> 75.59 | AK24: =NA() -> #N/A | AL24: =NA() -> #N/A | AM24: =NA() -> #N/A | AN24: =NA() -> #N/A | AP24: =AI24 -> 45686 | AQ24: =HAVERD!II811 -> 128.56 | AR24: =NA() -> #N/A | AS24: =NA() -> #N/A | AT24: =NA() -> #N/A
A25: 45200 | B25: =100*((HAVERM!D173/HAVERM!D161)-1) -> 6.542811 | E25: =[2]Monthly!QL427 -> 0.96820597 | G25: 45200 | H25: =HAVERM!E173 -> 7.2 | I25: =NA() -> #N/A | J25: =NA() -> #N/A | L25: 46844 | N25: =HAVERQ!C61 -> 1.5 | O25: =100*((GMW!B228/GMW!B224)-1) -> 1.6417736 | Q25: 2 | S25: 44105 | T25: =HAVERM!F137 -> 2.206 | U25: =HAVERM!G137 -> 2.354 | V25: =HAVERM!H137 -> #N/A | W25: =HAVERM!I137 -> #N/A | Y25: 44105 | Z25: =HAVERM!J137 -> 1.606 | AA25: =HAVERM!K137 -> 2.122 | AB25: =HAVERM!L137 -> #N/A | AC25: =HAVERM!M137 -> #N/A | AE25: 42644 | AF25: =HAVERM!P89 -> 270.02349 | AG25: ='Bloom - Monthly US data'!M383 -> 83.538371 | AI25: =HAVERD!A812 -> 45687 | AJ25: =HAVERD!IH812 -> 76.13 | AK25: =NA() -> #N/A | AL25: =NA() -> #N/A | AM25: =NA() -> #N/A | AN25: =NA() -> #N/A | AP25: =AI25 -> 45687 | AQ25: =HAVERD!II812 -> 129.42 | AR25: =NA() -> #N/A | AS25: =NA() -> #N/A | AT25: =NA() -> #N/A
A26: 45231 | B26: =100*((HAVERM!D174/HAVERM!D162)-1) -> 6.2096774 | E26: =[2]Monthly!QL428 -> 0.97068892 | G26: 45231 | H26: =HAVERM!E174 -> 6.6 | I26: =NA() -> #N/A | J26: =NA() -> #N/A | L26: 46935 | N26: =HAVERQ!C62 -> 1.6 | O26: =100*((GMW!B229/GMW!B225)-1) -> 1.6932043 | Q26: 2 | S26: 44136 | T26: =HAVERM!F138 -> 1.689 | U26: =HAVERM!G138 -> 2.092 | V26: =HAVERM!H138 -> #N/A | W26: =HAVERM!I138 -> #N/A | Y26: 44136 | Z26: =HAVERM!J138 -> 1.823 | AA26: =HAVERM!K138 -> 2.099 | AB26: =HAVERM!L138 -> #N/A | AC26: =HAVERM!M138 -> #N/A | AE26: 42675 | AF26: =HAVERM!P90 -> 358.82841 | AG26: ='Bloom - Monthly US data'!M384 -> 540.4187 | AI26: =HAVERD!A813 -> 45688 | AJ26: =HAVERD!IH813 -> 75.9 | AK26: =NA() -> #N/A | AL26: =NA() -> #N/A | AM26: =NA() -> #N/A | AN26: =NA() -> #N/A | AP26: =AI26 -> 45688 | AQ26: =HAVERD!II813 -> 130.54 | AR26: =NA() -> #N/A | AS26: =NA() -> #N/A | AT26: =NA() -> #N/A
A27: 45261 | B27: =100*((HAVERM!D175/HAVERM!D163)-1) -> 6.4 | E27: =[2]Monthly!QL429 -> 0.97338145 | G27: 45261 | H27: =HAVERM!E175 -> 6.2 | I27: =NA() -> #N/A | J27: =NA() -> #N/A | L27: 47027 | N27: =HAVERQ!C63 -> 1.6 | O27: =100*((GMW!B230/GMW!B226)-1) -> 1.7395542 | Q27: 2 | S27: 44166 | T27: =HAVERM!F139 -> 0.879 | U27: =HAVERM!G139 -> 2.705 | V27: =HAVERM!H139 -> #N/A | W27: =HAVERM!I139 -> #N/A | Y27: 44166 | Z27: =HAVERM!J139 -> 1.591 | AA27: =HAVERM!K139 -> 2.383 | AB27: =HAVERM!L139 -> #N/A | AC27: =HAVERM!M139 -> #N/A | AE27: 42705 | AF27: =HAVERM!P91 -> 196.34369 | AG27: ='Bloom - Monthly US data'!M385 -> 275.12017 | AI27: =HAVERD!A814 -> 45691 | AJ27: =HAVERD!IH814 -> 75.9 | AK27: =NA() -> #N/A | AL27: =NA() -> #N/A | AM27: =NA() -> #N/A | AN27: =NA() -> #N/A | AP27: =AI27 -> 45691 | AQ27: =HAVERD!II814 -> 130.85 | AR27: =NA() -> #N/A | AS27: =NA() -> #N/A | AT27: =NA() -> #N/A
A28: 45292 | B28: =100*((HAVERM!D176/HAVERM!D164)-1) -> 6.542811 | E28: =[2]Monthly!QL430 -> 1.010123 | G28: 45292 | H28: =HAVERM!E176 -> 6.1 | I28: =NA() -> #N/A | J28: =NA() -> #N/A | S28: 44197 | T28: =HAVERM!F140 -> 1.833 | U28: =HAVERM!G140 -> 2.507 | V28: =HAVERM!H140 -> #N/A | W28: =HAVERM!I140 -> #N/A | Y28: 44197 | Z28: =HAVERM!J140 -> 1.467 | AA28: =HAVERM!K140 -> 2.434 | AB28: =HAVERM!L140 -> #N/A | AC28: =HAVERM!M140 -> #N/A | AE28: 42736 | AF28: =HAVERM!P92 -> 257.8484 | AG28: ='Bloom - Monthly US data'!M386 -> 474.80271 | AI28: =HAVERD!A815 -> 45692 | AJ28: =HAVERD!IH815 -> 76.19 | AK28: =NA() -> #N/A | AL28: =NA() -> #N/A | AM28: =NA() -> #N/A | AN28: =NA() -> #N/A | AP28: =AI28 -> 45692 | AQ28: =HAVERD!II815 -> 126.65 | AR28: =NA() -> #N/A | AS28: =NA() -> #N/A | AT28: =NA() -> #N/A
A29: 45323 | B29: =100*((HAVERM!D177/HAVERM!D165)-1) -> 6.0751399 | E29: =[2]Monthly!QL431 -> 1.0014451 | G29: 45323 | H29: =HAVERM!E177 -> 5.9 | I29: =NA() -> #N/A | J29: =NA() -> #N/A | S29: 44228 | T29: =HAVERM!F141 -> 2.053 | U29: =HAVERM!G141 -> 2.719 | V29: =HAVERM!H141 -> #N/A | W29: =HAVERM!I141 -> #N/A | Y29: 44228 | Z29: =HAVERM!J141 -> 1.588 | AA29: =HAVERM!K141 -> 2.644 | AB29: =HAVERM!L141 -> #N/A | AC29: =HAVERM!M141 -> #N/A | AE29: 42767 | AF29: =HAVERM!P93 -> 194.0447 | AG29: ='Bloom - Monthly US data'!M387 -> 250.13309 | AI29: =HAVERD!A816 -> 45693 | AJ29: =HAVERD!IH816 -> 74.71 | AK29: =NA() -> #N/A | AL29: =NA() -> #N/A | AM29: =NA() -> #N/A | AN29: =NA() -> #N/A | AP29: =AI29 -> 45693 | AQ29: =HAVERD!II816 -> 130.47 | AR29: =NA() -> #N/A | AS29: =NA() -> #N/A | AT29: =NA() -> #N/A
A30: 45352 | B30: =100*((HAVERM!D178/HAVERM!D166)-1) -> 5.952381 | E30: =[2]Monthly!QL432 -> 1.0032514 | G30: 45352 | H30: =HAVERM!E178 -> 5.9 | I30: =NA() -> #N/A | J30: =NA() -> #N/A | S30: 44256 | T30: =HAVERM!F142 -> 1.635 | U30: =HAVERM!G142 -> 2.981 | V30: =HAVERM!H142 -> #N/A | W30: =HAVERM!I142 -> #N/A | Y30: 44256 | Z30: =HAVERM!J142 -> 1.84 | AA30: =HAVERM!K142 -> 2.736 | AB30: =HAVERM!L142 -> #N/A | AC30: =HAVERM!M142 -> #N/A | AE30: 42795 | AF30: =HAVERM!P94 -> 232.45973 | AG30: ='Bloom - Monthly US data'!M388 -> 151.94312 | AI30: =HAVERD!A817 -> 45694 | AJ30: =HAVERD!IH817 -> 74.35 | AK30: =NA() -> #N/A | AL30: =NA() -> #N/A | AM30: =NA() -> #N/A | AN30: =NA() -> #N/A | AP30: =AI30 -> 45694 | AQ30: =HAVERD!II817 -> 133.19 | AR30: =NA() -> #N/A | AS30: =NA() -> #N/A | AT30: =NA() -> #N/A
A31: 45383 | B31: =100*((HAVERM!D179/HAVERM!D167)-1) -> 5.859375 | E31: =[2]Monthly!QL433 -> 1.0113903 | G31: 45383 | H31: =HAVERM!E179 -> 5.7 | I31: =NA() -> #N/A | J31: =NA() -> #N/A | S31: 44287 | T31: =HAVERM!F143 -> 2.79 | U31: =HAVERM!G143 -> 3.139 | V31: =HAVERM!H143 -> #N/A | W31: =HAVERM!I143 -> #N/A | Y31: 44287 | Z31: =HAVERM!J143 -> 2.159 | AA31: =HAVERM!K143 -> 2.946 | AB31: =HAVERM!L143 -> #N/A | AC31: =HAVERM!M143 -> #N/A | AE31: 42826 | AF31: =HAVERM!P95 -> 169.17604 | AG31: ='Bloom - Monthly US data'!M389 -> 153.35011 | AI31: =HAVERD!A818 -> 45695 | AJ31: =HAVERD!IH818 -> 74.73 | AK31: =NA() -> #N/A | AL31: =NA() -> #N/A | AM31: =NA() -> #N/A | AN31: =NA() -> #N/A | AP31: =AI31 -> 45695 | AQ31: =HAVERD!II818 -> 135.75 | AR31: =NA() -> #N/A | AS31: =NA() -> #N/A | AT31: =NA() -> #N/A
A32: 45413 | B32: =100*((HAVERM!D180/HAVERM!D168)-1) -> 5.7364341 | E32: =[2]Monthly!QL434 -> 1.0144372 | G32: 45413 | H32: =HAVERM!E180 -> 5.6 | I32: =NA() -> #N/A | J32: =NA() -> #N/A | S32: 44317 | T32: =HAVERM!F144 -> 2.829 | U32: =HAVERM!G144 -> 3.442 | V32: =HAVERM!H144 -> #N/A | W32: =HAVERM!I144 -> #N/A | Y32: 44317 | Z32: =HAVERM!J144 -> 2.418 | AA32: =HAVERM!K144 -> 3.187 | AB32: =HAVERM!L144 -> #N/A | AC32: =HAVERM!M144 -> #N/A | AE32: 42856 | AF32: =HAVERM!P96 -> 159.40145 | AG32: ='Bloom - Monthly US data'!M390 -> 87.267511 | AI32: =HAVERD!A819 -> 45698 | AJ32: =HAVERD!IH819 -> 75.95 | AK32: =NA() -> #N/A | AL32: =NA() -> #N/A | AM32: =NA() -> #N/A | AN32: =NA() -> #N/A | AP32: =AI32 -> 45698 | AQ32: =HAVERD!II819 -> 141.25 | AR32: =NA() -> #N/A | AS32: =NA() -> #N/A | AT32: =NA() -> #N/A
A33: 45444 | B33: =100*((HAVERM!D181/HAVERM!D169)-1) -> 5.7054742 | E33: =[2]Monthly!QL435 -> 1.0148662 | G33: 45444 | H33: =HAVERM!E181 -> 5.3 | I33: =NA() -> #N/A | J33: =NA() -> #N/A | S33: 44348 | T33: =HAVERM!F145 -> 3.122 | U33: =HAVERM!G145 -> 3.245 | V33: =HAVERM!H145 -> #N/A | W33: =HAVERM!I145 -> #N/A | Y33: 44348 | Z33: =HAVERM!J145 -> 2.914 | AA33: =HAVERM!K145 -> 3.275 | AB33: =HAVERM!L145 -> #N/A | AC33: =HAVERM!M145 -> #N/A | AE33: 42887 | AF33: =HAVERM!P97 -> 318.99116 | AG33: ='Bloom - Monthly US data'!M391 -> 86.858279 | AI33: =HAVERD!A820 -> 45699 | AJ33: =HAVERD!IH820 -> 77.01 | AK33: =NA() -> #N/A | AL33: =NA() -> #N/A | AM33: =NA() -> #N/A | AN33: =NA() -> #N/A | AP33: =AI33 -> 45699 | AQ33: =HAVERD!II820 -> 140.57 | AR33: =NA() -> #N/A | AS33: =NA() -> #N/A | AT33: =NA() -> #N/A
A34: 45474 | B34: =100*((HAVERM!D182/HAVERM!D170)-1) -> 5.1908397 | E34: =[2]Monthly!QL436 -> 1.0400067 | G34: 45474 | H34: =HAVERM!E182 -> 5.2 | I34: =NA() -> #N/A | J34: =NA() -> #N/A | S34: 44378 | T34: =HAVERM!F146 -> 3.763 | U34: =HAVERM!G146 -> 2.929 | V34: =HAVERM!H146 -> #N/A | W34: =HAVERM!I146 -> #N/A | Y34: 44378 | Z34: =HAVERM!J146 -> 3.238 | AA34: =HAVERM!K146 -> 3.205 | AB34: =HAVERM!L146 -> #N/A | AC34: =HAVERM!M146 -> #N/A | AE34: 42917 | AF34: =HAVERM!P98 -> 183.65895 | AG34: ='Bloom - Monthly US data'!M392 -> 92.143455 | AI34: =HAVERD!A821 -> 45700 | AJ34: =HAVERD!IH821 -> 75.19 | AK34: =NA() -> #N/A | AL34: =NA() -> #N/A | AM34: =NA() -> #N/A | AN34: =NA() -> #N/A | AP34: =AI34 -> 45700 | AQ34: =HAVERD!II821 -> 134.99 | AR34: =NA() -> #N/A | AS34: =NA() -> #N/A | AT34: =NA() -> #N/A
A35: 45505 | B35: =100*((HAVERM!D183/HAVERM!D171)-1) -> 5.5725191 | E35: =[2]Monthly!QL437 -> 1.0413327 | G35: 45505 | H35: =HAVERM!E183 -> 5.1 | I35: =NA() -> #N/A | J35: =NA() -> #N/A | S35: 44409 | T35: =HAVERM!F147 -> 3.432 | U35: =HAVERM!G147 -> 3.236 | V35: =HAVERM!H147 -> #N/A | W35: =HAVERM!I147 -> #N/A | Y35: 44409 | Z35: =HAVERM!J147 -> 3.439 | AA35: =HAVERM!K147 -> 3.137 | AB35: =HAVERM!L147 -> #N/A | AC35: =HAVERM!M147 -> #N/A | AE35: 42948 | AF35: =HAVERM!P99 -> 151.2043 | AG35: ='Bloom - Monthly US data'!M393 -> 91.351067 | AI35: =HAVERD!A822 -> 45701 | AJ35: =HAVERD!IH822 -> 75.1 | AK35: =NA() -> #N/A | AL35: =NA() -> #N/A | AM35: =NA() -> #N/A | AN35: =NA() -> #N/A | AP35: =AI35 -> 45701 | AQ35: =HAVERD!II822 -> 124.25 | AR35: =NA() -> #N/A | AS35: =NA() -> #N/A | AT35: =NA() -> #N/A
A36: 45536 | B36: =100*((HAVERM!D184/HAVERM!D172)-1) -> 4.9467275 | E36: =[2]Monthly!QL438 -> 1.0440379 | G36: 45536 | H36: =HAVERM!E184 -> 5.2 | I36: =NA() -> #N/A | J36: =NA() -> #N/A | S36: 44440 | T36: =HAVERM!F148 -> 4.536 | U36: =HAVERM!G148 -> 4.084 | V36: =HAVERM!H148 -> #N/A | W36: =HAVERM!I148 -> #N/A | Y36: 44440 | Z36: =HAVERM!J148 -> 3.91 | AA36: =HAVERM!K148 -> 3.416 | AB36: =HAVERM!L148 -> #N/A | AC36: =HAVERM!M148 -> #N/A | AE36: 42979 | AF36: =HAVERM!P100 -> 140.77882 | AG36: ='Bloom - Monthly US data'!M394 -> 76.291078 | AI36: =HAVERD!A823 -> 45702 | AJ36: =HAVERD!IH823 -> 74.46 | AK36: =NA() -> #N/A | AL36: =NA() -> #N/A | AM36: =NA() -> #N/A | AN36: =NA() -> #N/A | AP36: =AI36 -> 45702 | AQ36: =HAVERD!II823 -> 122.26 | AR36: =NA() -> #N/A | AS36: =NA() -> #N/A | AT36: =NA() -> #N/A
A37: 45566 | B37: =100*((HAVERM!D185/HAVERM!D173)-1) -> 5.0037908 | E37: =[2]Monthly!QL439 -> 1.0453089 | G37: 45566 | H37: =HAVERM!E185 -> 5.6 | I37: =NA() -> #N/A | J37: =NA() -> #N/A | S37: 44470 | T37: =HAVERM!F149 -> 5.406 | U37: =HAVERM!G149 -> 4.724 | V37: =HAVERM!H149 -> #N/A | W37: =HAVERM!I149 -> #N/A | Y37: 44470 | Z37: =HAVERM!J149 -> 4.458 | AA37: =HAVERM!K149 -> 4.015 | AB37: =HAVERM!L149 -> #N/A | AC37: =HAVERM!M149 -> #N/A | AE37: 43009 | AF37: =HAVERM!P101 -> 184.03005 | AG37: ='Bloom - Monthly US data'!M395 -> 96.872971 | AI37: =HAVERD!A824 -> 45705 | AJ37: =HAVERD!IH824 -> 75.01 | AK37: =NA() -> #N/A | AL37: =NA() -> #N/A | AM37: =NA() -> #N/A | AN37: =NA() -> #N/A | AP37: =AI37 -> 45705 | AQ37: =HAVERD!II824 -> 115.72 | AR37: =NA() -> #N/A | AS37: =NA() -> #N/A | AT37: =NA() -> #N/A
A38: 45597 | B38: =100*((HAVERM!D186/HAVERM!D174)-1) -> 5.0113895 | E38: =[2]Monthly!QL440 -> 1.045885 | G38: 45597 | H38: =HAVERM!E186 -> 6 | I38: =NA() -> #N/A | J38: =NA() -> #N/A | S38: 44501 | T38: =HAVERM!F150 -> 4.81 | U38: =HAVERM!G150 -> 4.411 | V38: =HAVERM!H150 -> #N/A | W38: =HAVERM!I150 -> #N/A | Y38: 44501 | Z38: =HAVERM!J150 -> 4.918 | AA38: =HAVERM!K150 -> 4.406 | AB38: =HAVERM!L150 -> #N/A | AC38: =HAVERM!M150 -> #N/A | AE38: 43040 | AF38: =HAVERM!P102 -> 214.97008 | AG38: ='Bloom - Monthly US data'!M396 -> 49.481161 | AI38: =HAVERD!A825 -> 45706 | AJ38: =HAVERD!IH825 -> 75.41 | AK38: =NA() -> #N/A | AL38: =NA() -> #N/A | AM38: =NA() -> #N/A | AN38: =NA() -> #N/A | AP38: =AI38 -> 45706 | AQ38: =HAVERD!II825 -> 117.9 | AR38: =NA() -> #N/A | AS38: =NA() -> #N/A | AT38: =NA() -> #N/A
A39: 45627 | B39: =100*((HAVERM!D187/HAVERM!D175)-1) -> 4.3609023 | E39: =[2]Monthly!QL441 -> 1.0482921 | G39: 45627 | H39: =HAVERM!E187 -> 6.2 | I39: =NA() -> #N/A | J39: =NA() -> #N/A | S39: 44531 | T39: =HAVERM!F151 -> 5.482 | U39: =HAVERM!G151 -> 5.094 | V39: =HAVERM!H151 -> #N/A | W39: =HAVERM!I151 -> #N/A | Y39: 44531 | Z39: =HAVERM!J151 -> 5.233 | AA39: =HAVERM!K151 -> 4.743 | AB39: =HAVERM!L151 -> #N/A | AC39: =HAVERM!M151 -> #N/A | AE39: 43070 | AF39: =HAVERM!P103 -> 160.7223 | AG39: ='Bloom - Monthly US data'!M397 -> 182.29972 | AI39: =HAVERD!A826 -> 45707 | AJ39: =HAVERD!IH826 -> 75.59 | AK39: =NA() -> #N/A | AL39: =NA() -> #N/A | AM39: =NA() -> #N/A | AN39: =NA() -> #N/A | AP39: =AI39 -> 45707 | AQ39: =HAVERD!II826 -> 114.98 | AR39: =NA() -> #N/A | AS39: =NA() -> #N/A | AT39: =NA() -> #N/A
... A45: 45809 | B45: =100*((HAVERM!D193/HAVERM!D181)-1) -> 4.7410649 | E45: =[2]Monthly!QL447 -> 0.99614259 | G45: 45809 | H45: =HAVERM!E193 -> 4.8 | I45: =NA() -> #N/A | J45: =NA() -> #N/A | S45: 44713 | T45: =HAVERM!F157 -> 7.468 | U45: =HAVERM!G157 -> 6.309 | V45: =HAVERM!H157 -> 5.7 | W45: =HAVERM!I157 -> 5.1 | Y45: 44713 | Z45: =HAVERM!J157 -> 7.078 | AA45: =HAVERM!K157 -> 6.046 | AB45: =HAVERM!L157 -> 5.578 | AC45: =HAVERM!M157 -> 4.931 | AE45: 43252 | AF45: =HAVERM!P109 -> 105.48677 | AG45: ='Bloom - Monthly US data'!M403 -> 688.39964 | AI45: =HAVERD!A832 -> 45715 | AJ45: =HAVERD!IH832 -> 73.49 | AK45: =NA() -> #N/A | AL45: =NA() -> #N/A | AM45: =NA() -> #N/A | AN45: =NA() -> #N/A | AP45: =AI45 -> 45715 | AQ45: =HAVERD!II832 -> 106.79 | AR45: =NA() -> #N/A | AS45: =NA() -> #N/A | AT45: =NA() -> #N/A
A46: 45839 | B46: =100*((HAVERM!D194/HAVERM!D182)-1) -> 4.934688 | C46: ='MPR Chart 2.18 (Aug CPI)'!L61 -> 4.878 | E46: =[2]Monthly!QL448 -> 1.000123 | G46: 45839 | H46: =HAVERM!E194 -> 4.7 | I46: =NA() -> #N/A | J46: =NA() -> #N/A | S46: 44743 | T46: =HAVERM!F158 -> 7.975 | U46: =HAVERM!G158 -> 6.678 | V46: =HAVERM!H158 -> 5.5 | W46: =HAVERM!I158 -> 5.2 | Y46: 44743 | Z46: =HAVERM!J158 -> 7.57 | AA46: =HAVERM!K158 -> 6.273 | AB46: =HAVERM!L158 -> 5.541 | AC46: =HAVERM!M158 -> 5.014 | AE46: 43282 | AF46: =HAVERM!P110 -> 129.62264 | AG46: ='Bloom - Monthly US data'!M404 -> 904.71914 | AI46: =HAVERD!A833 -> 45716 | AJ46: =HAVERD!IH833 -> 72.98 | AK46: =NA() -> #N/A | AL46: =NA() -> #N/A | AM46: =NA() -> #N/A | AN46: =NA() -> #N/A | AP46: =AI46 -> 45716 | AQ46: =HAVERD!II833 -> 104.83 | AR46: =NA() -> #N/A | AS46: =NA() -> #N/A | AT46: =NA() -> #N/A
A47: 45870 | B47: =100*((HAVERM!D195/HAVERM!D183)-1) -> 4.6999277 | C47: ='MPR Chart 2.18 (Aug CPI)'!L62 -> 4.801 | E47: =[2]Monthly!QL449 -> 1.0015941 | G47: 45870 | H47: =HAVERM!E195 -> 4.4 | I47: =NA() -> #N/A | J47: =NA() -> #N/A | S47: 44774 | T47: =HAVERM!F159 -> 7.653 | U47: =HAVERM!G159 -> 6.421 | V47: =HAVERM!H159 -> 6.4 | W47: =HAVERM!I159 -> 5.5 | Y47: 44774 | Z47: =HAVERM!J159 -> 7.698 | AA47: =HAVERM!K159 -> 6.469 | AB47: =HAVERM!L159 -> 5.844 | AC47: =HAVERM!M159 -> 5.244 | AE47: 43313 | AF47: =HAVERM!P111 -> 121.62975 | AG47: ='Bloom - Monthly US data'!M405 -> 469.29295 | AI47: =HAVERD!A834 -> 45719 | AJ47: =HAVERD!IH834 -> 71.21 | AK47: =NA() -> #N/A | AL47: =NA() -> #N/A | AM47: =NA() -> #N/A | AN47: =NA() -> #N/A | AP47: =AI47 -> 45719 | AQ47: =HAVERD!II834 -> 107.16 | AR47: =NA() -> #N/A | AS47: =NA() -> #N/A | AT47: =NA() -> #N/A
A48: 45901 | B48: =100*((HAVERM!D196/HAVERM!D184)-1) -> 4.7135606 | C48: ='MPR Chart 2.18 (Aug CPI)'!L63 -> 5.043 | E48: =[2]Monthly!QL450 -> 1.0046701 | G48: 45901 | H48: =HAVERM!E196 -> 4.2 | I48: ='MPR Chart 2.17 (Aug pay)'!B98 -> 4.623 | J48: ='MPR Chart 1.3 (Nov pay)'!B99 -> 4.233 | S48: 44805 | T48: =HAVERM!F160 -> 7.408 | U48: =HAVERM!G160 -> 6.629 | V48: =HAVERM!H160 -> 6.5 | W48: =HAVERM!I160 -> 5.8 | Y48: 44805 | Z48: =HAVERM!J160 -> 7.679 | AA48: =HAVERM!K160 -> 6.576 | AB48: =HAVERM!L160 -> 6.099 | AC48: =HAVERM!M160 -> 5.501 | AE48: 43344 | AF48: =HAVERM!P112 -> 157.31582 | AG48: ='Bloom - Monthly US data'!M406 -> 323.39119 | AI48: =HAVERD!A835 -> 45720 | AJ48: =HAVERD!IH835 -> 72.31 | AK48: =NA() -> #N/A | AL48: =NA() -> #N/A | AM48: =NA() -> #N/A | AN48: =NA() -> #N/A | AP48: =AI48 -> 45720 | AQ48: =HAVERD!II835 -> 103.57 | AR48: =NA() -> #N/A | AS48: =NA() -> #N/A | AT48: =NA() -> #N/A
A49: 45931 | B49: =100*((HAVERM!D197/HAVERM!D185)-1) -> 4.4765343 | C49: ='MPR Chart 2.18 (Aug CPI)'!L64 -> 4.954 | D49: ='MPR Chart 37 (Nov CPI)'!F6 -> 4.6 | E49: =[2]Monthly!QL451 -> 1.011127 | G49: 45931 | H49: =HAVERM!E197 -> 3.9 | I49: =NA() -> #N/A | J49: =NA() -> #N/A | S49: 44835 | T49: =HAVERM!F161 -> 7.757 | U49: =HAVERM!G161 -> 6.221 | V49: =HAVERM!H161 -> 6.1 | W49: =HAVERM!I161 -> 5.9 | Y49: 44835 | Z49: =HAVERM!J161 -> 7.606 | AA49: =HAVERM!K161 -> 6.423 | AB49: =HAVERM!L161 -> 6.307 | AC49: =HAVERM!M161 -> 5.729 | AE49: 43374 | AF49: =HAVERM!P113 -> 183.25267 | AG49: ='Bloom - Monthly US data'!M407 -> 443.2303 | AI49: =HAVERD!A836 -> 45721 | AJ49: =HAVERD!IH836 -> 70.92 | AK49: =NA() -> #N/A | AL49: =NA() -> #N/A | AM49: =NA() -> #N/A | AN49: =NA() -> #N/A | AP49: =AI49 -> 45721 | AQ49: =HAVERD!II836 -> 100.1 | AR49: =NA() -> #N/A | AS49: =NA() -> #N/A | AT49: =NA() -> #N/A
A50: 45962 | B50: =100*((HAVERM!D198/HAVERM!D186)-1) -> 4.4107014 | C50: ='MPR Chart 2.18 (Aug CPI)'!L65 -> 4.97 | D50: ='MPR Chart 37 (Nov CPI)'!F7 -> 4.5 | E50: =[2]Monthly!QL452 -> 1.012099 | G50: 45962 | H50: =HAVERM!E198 -> 3.6 | I50: =NA() -> #N/A | J50: =NA() -> #N/A | S50: 44866 | T50: =HAVERM!F162 -> 7.177 | U50: =HAVERM!G162 -> 5.709 | V50: =HAVERM!H162 -> 6.1 | W50: =HAVERM!I162 -> 5.8 | Y50: 44866 | Z50: =HAVERM!J162 -> 7.448 | AA50: =HAVERM!K162 -> 6.186 | AB50: =HAVERM!L162 -> 6.22 | AC50: =HAVERM!M162 -> 5.833 | AE50: 43405 | AF50: =HAVERM!P114 -> 191.96646 | AG50: ='Bloom - Monthly US data'!M408 -> 403.07749 | AI50: =HAVERD!A837 -> 45722 | AJ50: =HAVERD!IH837 -> 71.08 | AK50: =NA() -> #N/A | AL50: =NA() -> #N/A | AM50: =NA() -> #N/A | AN50: =NA() -> #N/A | AP50: =AI50 -> 45722 | AQ50: =HAVERD!II837 -> 93.03 | AR50: =NA() -> #N/A | AS50: =NA() -> #N/A | AT50: =NA() -> #N/A
A51: 45992 | B51: =100*((HAVERM!D199/HAVERM!D187)-1) -> 4.4668588 | C51: ='MPR Chart 2.18 (Aug CPI)'!L66 -> 5.059 | D51: ='MPR Chart 37 (Nov CPI)'!F8 -> 4.6 | E51: =[2]Monthly!QL453 -> 1.0140196 | G51: 45992 | I51: ='MPR Chart 2.17 (Aug pay)'!B101 -> 3.657 | J51: ='MPR Chart 1.3 (Nov pay)'!B102 -> 3.513 | S51: 44896 | T51: =HAVERM!F163 -> 8.603 | U51: =HAVERM!G163 -> 5.785 | V51: =HAVERM!H163 -> 6.6 | W51: =HAVERM!I163 -> 6.3 | Y51: 44896 | Z51: =HAVERM!J163 -> 7.846 | AA51: =HAVERM!K163 -> 5.905 | AB51: =HAVERM!L163 -> 6.26 | AC51: =HAVERM!M163 -> 5.983 | AE51: 43435 | AF51: =HAVERM!P115 -> 239.69103 | AG51: ='Bloom - Monthly US data'!M409 -> 681.87189 | AI51: =HAVERD!A838 -> 45723 | AJ51: =HAVERD!IH838 -> 72.49 | AK51: =NA() -> #N/A | AL51: =NA() -> #N/A | AM51: =NA() -> #N/A | AN51: =NA() -> #N/A | AP51: =AI51 -> 45723 | AQ51: =HAVERD!II838 -> 97.7 | AR51: =NA() -> #N/A | AS51: =NA() -> #N/A | AT51: =NA() -> #N/A
A52: 46023 | D52: ='MPR Chart 37 (Nov CPI)'!F9 -> 4.2 | G52: 46023 | J52: =NA() -> #N/A | S52: 44927 | T52: =HAVERM!F164 -> 7.903 | U52: =HAVERM!G164 -> 5.8 | V52: =HAVERM!H164 -> 6.3 | W52: =HAVERM!I164 -> 5.7 | Y52: 44927 | Z52: =HAVERM!J164 -> 7.894 | AA52: =HAVERM!K164 -> 5.765 | AB52: =HAVERM!L164 -> 6.34 | AC52: =HAVERM!M164 -> 5.941 | AE52: 43466 | AF52: =HAVERM!P116 -> 309.97245 | AG52: ='Bloom - Monthly US data'!M410 -> 715.62023 | AI52: =HAVERD!A839 -> 45726 | AJ52: =HAVERD!IH839 -> 69.28 | AK52: =NA() -> #N/A | AL52: =NA() -> #N/A | AM52: =NA() -> #N/A | AN52: =NA() -> #N/A | AP52: =AI52 -> 45726 | AQ52: =HAVERD!II839 -> 100.81 | AR52: =NA() -> #N/A | AS52: =NA() -> #N/A | AT52: =NA() -> #N/A
A53: 46054 | D53: ='MPR Chart 37 (Nov CPI)'!F10 -> 4.2 | G53: 46054 | J53: =NA() -> #N/A | S53: 44958 | T53: =HAVERM!F165 -> 7.763 | U53: =HAVERM!G165 -> 5.367 | V53: =HAVERM!H165 -> 6.6 | W53: =HAVERM!I165 -> 5.8 | Y53: 44958 | Z53: =HAVERM!J165 -> 8.09 | AA53: =HAVERM!K165 -> 5.651 | AB53: =HAVERM!L165 -> 6.51 | AC53: =HAVERM!M165 -> 5.929 | AE53: 43497 | AF53: =HAVERM!P117 -> 196.95946 | AG53: ='Bloom - Monthly US data'!M411 -> 307.09272 | AI53: =HAVERD!A840 -> 45727 | AJ53: =HAVERD!IH840 -> 69.64 | AK53: =NA() -> #N/A | AL53: =NA() -> #N/A | AM53: =NA() -> #N/A | AN53: =NA() -> #N/A | AP53: =AI53 -> 45727 | AQ53: =HAVERD!II840 -> 105.32 | AR53: =NA() -> #N/A | AS53: =NA() -> #N/A | AT53: =NA() -> #N/A
A54: 46082 | D54: ='MPR Chart 37 (Nov CPI)'!F11 -> 4.3 | G54: 46082 | J54: ='MPR Chart 1.3 (Nov pay)'!B105 -> 3.563 | S54: 44986 | T54: =HAVERM!F166 -> 7.824 | U54: =HAVERM!G166 -> 5.314 | V54: =HAVERM!H166 -> 6.5 | W54: =HAVERM!I166 -> 5.6 | Y54: 44986 | Z54: =HAVERM!J166 -> 7.83 | AA54: =HAVERM!K166 -> 5.494 | AB54: =HAVERM!L166 -> 6.48 | AC54: =HAVERM!M166 -> 5.683 | AE54: 43525 | AF54: =HAVERM!P118 -> 212.78254 | AG54: ='Bloom - Monthly US data'!M412 -> 287.66535 | AI54: =HAVERD!A841 -> 45728 | AJ54: =HAVERD!IH841 -> 70.9 | AK54: =NA() -> #N/A | AL54: =NA() -> #N/A | AM54: =NA() -> #N/A | AN54: =NA() -> #N/A | AP54: =AI54 -> 45728 | AQ54: =HAVERD!II841 -> 104.19 | AR54: =NA() -> #N/A | AS54: =NA() -> #N/A | AT54: =NA() -> #N/A
A55: 46113 | G55: 46113 | J55: =NA() -> #N/A | S55: 45017 | T55: =HAVERM!F167 -> 7.438 | U55: =HAVERM!G167 -> 5.957 | V55: =HAVERM!H167 -> 6.6 | W55: =HAVERM!I167 -> 5.4 | Y55: 45017 | Z55: =HAVERM!J167 -> 7.675 | AA55: =HAVERM!K167 -> 5.546 | AB55: =HAVERM!L167 -> 6.565 | AC55: =HAVERM!M167 -> 5.566 | AE55: 43556 | AF55: =HAVERM!P119 -> 135.51848 | AG55: ='Bloom - Monthly US data'!M413 -> 335.67499 | AI55: =HAVERD!A842 -> 45729 | AJ55: =HAVERD!IH842 -> 69.79 | AK55: =NA() -> #N/A | AL55: =NA() -> #N/A | AM55: =NA() -> #N/A | AN55: =NA() -> #N/A | AP55: =AI55 -> 45729 | AQ55: =HAVERD!II842 -> 102.99 | AR55: =NA() -> #N/A | AS55: =NA() -> #N/A | AT55: =NA() -> #N/A
A56: 46143 | G56: 46143 | J56: =NA() -> #N/A | S56: 45047 | T56: =HAVERM!F168 -> 7.77 | U56: =HAVERM!G168 -> 5.054 | V56: =HAVERM!H168 -> 6.8 | W56: =HAVERM!I168 -> 5.2 | Y56: 45047 | Z56: =HAVERM!J168 -> 7.677 | AA56: =HAVERM!K168 -> 5.442 | AB56: =HAVERM!L168 -> 6.611 | AC56: =HAVERM!M168 -> 5.385 | AE56: 43586 | AF56: =HAVERM!P120 -> 158.68261 | AG56: ='Bloom - Monthly US data'!M414 -> 786.54209 | AI56: =HAVERD!A843 -> 45730 | AJ56: =HAVERD!IH843 -> 71.94 | AK56: =NA() -> #N/A | AL56: =NA() -> #N/A | AM56: =NA() -> #N/A | AN56: =NA() -> #N/A | AP56: =AI56 -> 45730 | AQ56: =HAVERD!II843 -> 103.89 | AR56: =NA() -> #N/A | AS56: =NA() -> #N/A | AT56: =NA() -> #N/A
A57: 46174 | G57: 46174 | J57: ='MPR Chart 1.3 (Nov pay)'!B108 -> 3.246 | S57: 45078 | T57: =HAVERM!F169 -> 6.904 | U57: =HAVERM!G169 -> 4.875 | V57: =HAVERM!H169 -> 7.1 | W57: =HAVERM!I169 -> 5.3 | Y57: 45078 | Z57: =HAVERM!J169 -> 7.37 | AA57: =HAVERM!K169 -> 5.296 | AB57: =HAVERM!L169 -> 6.825 | AC57: =HAVERM!M169 -> 5.312 | AE57: 43617 | AF57: =HAVERM!P121 -> 149.8056 | AG57: ='Bloom - Monthly US data'!M415 -> 1374.2801 | AI57: =HAVERD!A844 -> 45733 | AJ57: =HAVERD!IH844 -> 71.93 | AK57: =NA() -> #N/A | AL57: =NA() -> #N/A | AM57: =NA() -> #N/A | AN57: =NA() -> #N/A | AP57: =AI57 -> 45733 | AQ57: =HAVERD!II844 -> 100.94 | AR57: =NA() -> #N/A | AS57: =NA() -> #N/A | AT57: =NA() -> #N/A
A58: 46204 | G58: 46204 | S58: 45108 | T58: =HAVERM!F170 -> 7.761 | U58: =HAVERM!G170 -> 5.557 | V58: =HAVERM!H170 -> 6.7 | W58: =HAVERM!I170 -> 5 | Y58: 45108 | Z58: =HAVERM!J170 -> 7.478 | AA58: =HAVERM!K170 -> 5.162 | AB58: =HAVERM!L170 -> 6.849 | AC58: =HAVERM!M170 -> 5.184 | AE58: 43647 | AF58: =HAVERM!P122 -> 202.04378 | AG58: ='Bloom - Monthly US data'!M416 -> 600.78823 | AI58: =HAVERD!A845 -> 45734 | AJ58: =HAVERD!IH845 -> 71.93 | AK58: =NA() -> #N/A | AL58: =NA() -> #N/A | AM58: =NA() -> #N/A | AN58: =NA() -> #N/A | AP58: =AI58 -> 45734 | AQ58: =HAVERD!II845 -> 100.01 | AR58: =NA() -> #N/A | AS58: =NA() -> #N/A | AT58: =NA() -> #N/A
A59: 46235 | G59: 46235 | S59: 45139 | T59: =HAVERM!F171 -> 7.447 | U59: =HAVERM!G171 -> 4.464 | V59: =HAVERM!H171 -> 6.9 | W59: =HAVERM!I171 -> 5 | Y59: 45139 | Z59: =HAVERM!J171 -> 7.371 | AA59: =HAVERM!K171 -> 4.965 | AB59: =HAVERM!L171 -> 6.892 | AC59: =HAVERM!M171 -> 5.108 | AE59: 43678 | AF59: =HAVERM!P123 -> 238.91571 | AG59: ='Bloom - Monthly US data'!M417 -> 1946.683 | AI59: =HAVERD!A846 -> 45735 | AJ59: =HAVERD!IH846 -> 71.94 | AK59: =NA() -> #N/A | AL59: =NA() -> #N/A | AM59: =NA() -> #N/A | AN59: =NA() -> #N/A | AP59: =AI59 -> 45735 | AQ59: =HAVERD!II846 -> 106.2 | AR59: =NA() -> #N/A | AS59: =NA() -> #N/A | AT59: =NA() -> #N/A
A60: 46266 | G60: 46266 | S60: 45170 | T60: =HAVERM!F172 -> 6.908 | U60: =HAVERM!G172 -> 4.395 | V60: =HAVERM!H172 -> 7.1 | W60: =HAVERM!I172 -> 5.2 | Y60: 45170 | Z60: =HAVERM!J172 -> 7.372 | AA60: =HAVERM!K172 -> 4.805 | AB60: =HAVERM!L172 -> 6.866 | AC60: =HAVERM!M172 -> 5.067 | AE60: 43709 | AF60: =HAVERM!P124 -> 187.41012 | AG60: ='Bloom - Monthly US data'!M418 -> 919.11535 | AI60: =HAVERD!A847 -> 45736 | AJ60: =HAVERD!IH847 -> 72.61 | AK60: =NA() -> #N/A | AL60: =NA() -> #N/A | AM60: =NA() -> #N/A | AN60: =NA() -> #N/A | AP60: =AI60 -> 45736 | AQ60: =HAVERD!II847 -> 104.33 | AR60: =NA() -> #N/A | AS60: =NA() -> #N/A | AT60: =NA() -> #N/A
A61: 46296 | G61: 46296 | S61: 45200 | T61: =HAVERM!F173 -> 6.823 | U61: =HAVERM!G173 -> 4.702 | V61: =HAVERM!H173 -> 6.8 | W61: =HAVERM!I173 -> 5.1 | Y61: 45200 | Z61: =HAVERM!J173 -> 7.059 | AA61: =HAVERM!K173 -> 4.52 | AB61: =HAVERM!L173 -> 6.916 | AC61: =HAVERM!M173 -> 5.097 | AE61: 43739 | AF61: =HAVERM!P125 -> 233.31156 | AG61: ='Bloom - Monthly US data'!M419 -> 842.41319 | AI61: =HAVERD!A848 -> 45737 | AJ61: =HAVERD!IH848 -> 72.64 | AK61: =NA() -> #N/A | AL61: =NA() -> #N/A | AM61: =NA() -> #N/A | AN61: =NA() -> #N/A | AP61: =AI61 -> 45737 | AQ61: =HAVERD!II848 -> 103.79 | AR61: =NA() -> #N/A | AS61: =NA() -> #N/A | AT61: =NA() -> #N/A
A62: 46327 | G62: 46327 | S62: 45231 | T62: =HAVERM!F174 -> 5.953 | U62: =HAVERM!G174 -> 4.23 | V62: =HAVERM!H174 -> 7 | W62: =HAVERM!I174 -> 5.1 | Y62: 45231 | Z62: =HAVERM!J174 -> 6.562 | AA62: =HAVERM!K174 -> 4.442 | AB62: =HAVERM!L174 -> 6.946 | AC62: =HAVERM!M174 -> 5.132 | AE62: 43770 | AF62: =HAVERM!P126 -> 205.59707 | AG62: ='Bloom - Monthly US data'!M420 -> 597.61785 | AI62: =HAVERD!A849 -> 45740 | AJ62: =HAVERD!IH849 -> 72.4 | AK62: =NA() -> #N/A | AL62: =NA() -> #N/A | AM62: =NA() -> #N/A | AN62: =NA() -> #N/A | AP62: =AI62 -> 45740 | AQ62: =HAVERD!II849 -> 103.97 | AR62: =NA() -> #N/A | AS62: =NA() -> #N/A | AT62: =NA() -> #N/A
A63: 46357 | G63: 46357 | S63: 45261 | T63: =HAVERM!F175 -> 4.911 | U63: =HAVERM!G175 -> 4.156 | V63: =HAVERM!H175 -> 7 | W63: =HAVERM!I175 -> 5.4 | Y63: 45261 | Z63: =HAVERM!J175 -> 5.896 | AA63: =HAVERM!K175 -> 4.363 | AB63: =HAVERM!L175 -> 6.937 | AC63: =HAVERM!M175 -> 5.202 | AE63: 43800 | AF63: =HAVERM!P127 -> 271.30406 | AG63: ='Bloom - Monthly US data'!M421 -> 851.97626 | AI63: =HAVERD!A850 -> 45741 | AJ63: =HAVERD!IH850 -> 72.32 | AK63: =NA() -> #N/A | AL63: =NA() -> #N/A | AM63: =NA() -> #N/A | AN63: =NA() -> #N/A | AP63: =AI63 -> 45741 | AQ63: =HAVERD!II850 -> 100.78 | AR63: =NA() -> #N/A | AS63: =NA() -> #N/A | AT63: =NA() -> #N/A
S64: 45292 | T64: =HAVERM!F176 -> 5.796 | U64: =HAVERM!G176 -> 4.522 | V64: =HAVERM!H176 -> 6.6 | W64: =HAVERM!I176 -> 5.2 | Y64: 45292 | Z64: =HAVERM!J176 -> 5.554 | AA64: =HAVERM!K176 -> 4.303 | AB64: =HAVERM!L176 -> 6.853 | AC64: =HAVERM!M176 -> 5.22 | AE64: 43831 | AF64: =HAVERM!P128 -> 198.15649 | AG64: ='Bloom - Monthly US data'!M422 -> 646.81815 | AI64: =HAVERD!A851 -> 45742 | AJ64: =HAVERD!IH851 -> 72.96 | AK64: =NA() -> #N/A | AL64: =NA() -> #N/A | AM64: =NA() -> #N/A | AN64: =NA() -> #N/A | AP64: =AI64 -> 45742 | AQ64: =HAVERD!II851 -> 99 | AR64: =NA() -> #N/A | AS64: =NA() -> #N/A | AT64: =NA() -> #N/A
S65: 45323 | T65: =HAVERM!F177 -> 5.416 | U65: =HAVERM!G177 -> 4.109 | V65: =HAVERM!H177 -> 6.5 | W65: =HAVERM!I177 -> 4.9 | Y65: 45323 | Z65: =HAVERM!J177 -> 5.375 | AA65: =HAVERM!K177 -> 4.263 | AB65: =HAVERM!L177 -> 6.694 | AC65: =HAVERM!M177 -> 5.162 | AE65: 43862 | AF65: =HAVERM!P129 -> 139.62192 | AG65: ='Bloom - Monthly US data'!M423 -> 462.98232 | AI65: =HAVERD!A852 -> 45743 | AJ65: =HAVERD!IH852 -> 74.72 | AK65: =NA() -> #N/A | AL65: =NA() -> #N/A | AM65: =NA() -> #N/A | AN65: =NA() -> #N/A | AP65: =AI65 -> 45743 | AQ65: =HAVERD!II852 -> 99.35 | AR65: =NA() -> #N/A | AS65: =NA() -> #N/A | AT65: =NA() -> #N/A
S66: 45352 | T66: =HAVERM!F178 -> 4.853 | U66: =HAVERM!G178 -> 3.67 | V66: =HAVERM!H178 -> 6.1 | W66: =HAVERM!I178 -> 4.7 | Y66: 45352 | Z66: =HAVERM!J178 -> 5.355 | AA66: =HAVERM!K178 -> 4.1 | AB66: =HAVERM!L178 -> 6.38 | AC66: =HAVERM!M178 -> 4.922 | AE66: 43891 | AF66: =HAVERM!P130 -> 281.20727 | AG66: ='Bloom - Monthly US data'!M424 -> 194.82835 | AI66: =HAVERD!A853 -> 45744 | AJ66: =HAVERD!IH853 -> 74.69 | AK66: =NA() -> #N/A | AL66: =NA() -> #N/A | AM66: =NA() -> #N/A | AN66: =NA() -> #N/A | AP66: =AI66 -> 45744 | AQ66: =HAVERD!II853 -> 98.95 | AR66: =NA() -> #N/A | AS66: =NA() -> #N/A | AT66: =NA() -> #N/A
S67: 45383 | T67: =HAVERM!F179 -> 5.282 | U67: =HAVERM!G179 -> 4.225 | V67: =HAVERM!H179 -> 6 | W67: =HAVERM!I179 -> 4.6 | Y67: 45383 | Z67: =HAVERM!J179 -> 5.184 | AA67: =HAVERM!K179 -> 4.001 | AB67: =HAVERM!L179 -> 6.179 | AC67: =HAVERM!M179 -> 4.747 | AE67: 43922 | AF67: =HAVERM!P131 -> 185.35208 | AG67: ='Bloom - Monthly US data'!M425 -> 239.93283 | AI67: =HAVERD!A854 -> 45747 | AJ67: =HAVERD!IH854 -> 77.23 | AK67: =NA() -> #N/A | AL67: =NA() -> #N/A | AM67: =NA() -> #N/A | AN67: =NA() -> #N/A | AP67: =AI67 -> 45747 | AQ67: =HAVERD!II854 -> 97.76 | AR67: =NA() -> #N/A | AS67: =NA() -> #N/A | AT67: =NA() -> #N/A
S68: 45413 | T68: =HAVERM!F180 -> 4.577 | U68: =HAVERM!G180 -> 3.816 | V68: =HAVERM!H180 -> 6.1 | W68: =HAVERM!I180 -> 4.1 | Y68: 45413 | Z68: =HAVERM!J180 -> 4.904 | AA68: =HAVERM!K180 -> 3.903 | AB68: =HAVERM!L180 -> 6.039 | AC68: =HAVERM!M180 -> 4.483 | AE68: 43952 | AF68: =HAVERM!P132 -> 230.75636 | AG68: ='Bloom - Monthly US data'!M426 -> 161.47694 | AI68: =HAVERD!A855 -> 45748 | AJ68: =HAVERD!IH855 -> 77.78 | AK68: =NA() -> #N/A | AL68: =NA() -> #N/A | AM68: =NA() -> #N/A | AN68: =NA() -> #N/A | AP68: =AI68 -> 45748 | AQ68: =HAVERD!II855 -> 102.65 | AR68: =NA() -> #N/A | AS68: =NA() -> #N/A | AT68: =NA() -> #N/A
S69: 45444 | T69: =HAVERM!F181 -> 3.82 | U69: =HAVERM!G181 -> 3.562 | V69: =HAVERM!H181 -> 5.9 | W69: =HAVERM!I181 -> 4 | Y69: 45444 | Z69: =HAVERM!J181 -> 4.56 | AA69: =HAVERM!K181 -> 3.867 | AB69: =HAVERM!L181 -> 5.992 | AC69: =HAVERM!M181 -> 4.237 | AE69: 43983 | AF69: =HAVERM!P133 -> 167.69786 | AG69: ='Bloom - Monthly US data'!M427 -> 57.086247 | AI69: =HAVERD!A856 -> 45749 | AJ69: =HAVERD!IH856 -> 77.27 | AK69: =NA() -> #N/A | AL69: =NA() -> #N/A | AM69: =NA() -> #N/A | AN69: =NA() -> #N/A | AP69: =AI69 -> 45749 | AQ69: =HAVERD!II856 -> 99.33 | AR69: =NA() -> #N/A | AS69: =NA() -> #N/A | AT69: =NA() -> #N/A
S70: 45474 | T70: =HAVERM!F182 -> 4.329 | U70: =HAVERM!G182 -> 3.689 | V70: =HAVERM!H182 -> 5.7 | W70: =HAVERM!I182 -> 4.1 | Y70: 45474 | Z70: =HAVERM!J182 -> 4.242 | AA70: =HAVERM!K182 -> 3.689 | AB70: =HAVERM!L182 -> 5.892 | AC70: =HAVERM!M182 -> 4.059 | AE70: 44013 | AF70: =HAVERM!P134 -> 189.96194 | AG70: ='Bloom - Monthly US data'!M428 -> 89.809961 | AI70: =HAVERD!A857 -> 45750 | AJ70: =HAVERD!IH857 -> 72.54 | AK70: =NA() -> #N/A | AL70: =NA() -> #N/A | AM70: =NA() -> #N/A | AN70: =NA() -> #N/A | AP70: =AI70 -> 45750 | AQ70: =HAVERD!II857 -> 95.38 | AR70: =NA() -> #N/A | AS70: =NA() -> #N/A | AT70: =NA() -> #N/A
S71: 45505 | T71: =HAVERM!F183 -> 3.882 | U71: =HAVERM!G183 -> 3.325 | V71: =HAVERM!H183 -> 5.7 | W71: =HAVERM!I183 -> 4.1 | Y71: 45505 | Z71: =HAVERM!J183 -> 4.01 | AA71: =HAVERM!K183 -> 3.526 | AB71: =HAVERM!L183 -> 5.766 | AC71: =HAVERM!M183 -> 4.053 | AE71: 44044 | AF71: =HAVERM!P135 -> 176.54884 | AG71: ='Bloom - Monthly US data'!M429 -> 150.9314 | AI71: =HAVERD!A858 -> 45751 | AJ71: =HAVERD!IH858 -> 68.36 | AK71: =NA() -> #N/A | AL71: =NA() -> #N/A | AM71: =NA() -> #N/A | AN71: =NA() -> #N/A | AP71: =AI71 -> 45751 | AQ71: =HAVERD!II858 -> 88.75 | AR71: =NA() -> #N/A | AS71: =NA() -> #N/A | AT71: =NA() -> #N/A
S72: 45536 | T72: =HAVERM!F184 -> 4.466 | U72: =HAVERM!G184 -> 3.607 | V72: =HAVERM!H184 -> 5.7 | W72: =HAVERM!I184 -> 4.1 | Y72: 45536 | Z72: =HAVERM!J184 -> 4.226 | AA72: =HAVERM!K184 -> 3.54 | AB72: =HAVERM!L184 -> 5.683 | AC72: =HAVERM!M184 -> 4.091 | AE72: 44075 | AF72: =HAVERM!P136 -> 184.51675 | AG72: ='Bloom - Monthly US data'!M430 -> 96.581922 | AI72: =HAVERD!A859 -> 45754 | AJ72: =HAVERD!IH859 -> 66.13 | AK72: =NA() -> #N/A | AL72: =NA() -> #N/A | AM72: =NA() -> #N/A | AN72: =NA() -> #N/A | AP72: =AI72 -> 45754 | AQ72: =HAVERD!II859 -> 90.77 | AR72: =NA() -> #N/A | AS72: =NA() -> #N/A | AT72: =NA() -> #N/A
S73: 45566 | T73: =HAVERM!F185 -> 3.626 | U73: =HAVERM!G185 -> 3.599 | V73: =HAVERM!H185 -> 5.4 | W73: =HAVERM!I185 -> 4.1 | Y73: 45566 | Z73: =HAVERM!J185 -> 3.991 | AA73: =HAVERM!K185 -> 3.51 | AB73: =HAVERM!L185 -> 5.598 | AC73: =HAVERM!M185 -> 4.1 | AE73: 44105 | AF73: =HAVERM!P137 -> 189.12477 | AG73: ='Bloom - Monthly US data'!M431 -> 331.19625 | AI73: =HAVERD!A860 -> 45755 | AJ73: =HAVERD!IH860 -> 64.86 | AK73: =NA() -> #N/A | AL73: =NA() -> #N/A | AM73: =NA() -> #N/A | AN73: =NA() -> #N/A | AP73: =AI73 -> 45755 | AQ73: =HAVERD!II860 -> 88.75 | AR73: =NA() -> #N/A | AS73: =NA() -> #N/A | AT73: =NA() -> #N/A
S74: 45597 | T74: =HAVERM!F186 -> 3.681 | U74: =HAVERM!G186 -> 3.788 | V74: =HAVERM!H186 -> 5.5 | W74: =HAVERM!I186 -> 3.8 | Y74: 45597 | Z74: =HAVERM!J186 -> 3.924 | AA74: =HAVERM!K186 -> 3.665 | AB74: =HAVERM!L186 -> 5.512 | AC74: =HAVERM!M186 -> 4.015 | AE74: 44136 | AF74: =HAVERM!P138 -> 214.46165 | AG74: ='Bloom - Monthly US data'!M432 -> 204.60834 | AI74: =HAVERD!A861 -> 45756 | AJ74: =HAVERD!IH861 -> 67.3 | AK74: =NA() -> #N/A | AL74: =NA() -> #N/A | AM74: =NA() -> #N/A | AN74: =NA() -> #N/A | AP74: =AI74 -> 45756 | AQ74: =HAVERD!II861 -> 83.21 | AR74: =NA() -> #N/A | AS74: =NA() -> #N/A | AT74: =NA() -> #N/A
S75: 45627 | T75: =HAVERM!F187 -> 3.979 | U75: =HAVERM!G187 -> 3.986 | V75: =HAVERM!H187 -> 5.3 | W75: =HAVERM!I187 -> 3.9 | Y75: 45627 | Z75: =HAVERM!J187 -> 3.762 | AA75: =HAVERM!K187 -> 3.791 | AB75: =HAVERM!L187 -> 5.384 | AC75: =HAVERM!M187 -> 3.966 | AE75: 44166 | AF75: =HAVERM!P139 -> 207.60651 | AG75: ='Bloom - Monthly US data'!M433 -> 123.58402 | AI75: =HAVERD!A862 -> 45757 | AJ75: =HAVERD!IH862 -> 63.37 | AK75: =NA() -> #N/A | AL75: =NA() -> #N/A | AM75: =NA() -> #N/A | AN75: =NA() -> #N/A | AP75: =AI75 -> 45757 | AQ75: =HAVERD!II862 -> 82.18 | AR75: =NA() -> #N/A | AS75: =NA() -> #N/A | AT75: =NA() -> #N/A
... S87: 45992 | T87: =HAVERM!F199 -> 3.83 | U87: =HAVERM!G199 -> 3.563 | V87: =HAVERM!H199 -> 4.3 | W87: =HAVERM!I199 -> 3.7 | Y87: 45992 | Z87: =HAVERM!J199 -> 3.668 | AA87: =HAVERM!K199 -> 3.597 | AB87: =HAVERM!L199 -> 4.386 | AC87: =HAVERM!M199 -> 3.705 | AE87: 44531 | AF87: =HAVERM!P151 -> 174.83134 | AG87: ='Bloom - Monthly US data'!M445 -> 24.930457 | AI87: =HAVERD!A874 -> 45775 | AJ87: =HAVERD!IH874 -> 66.13 | AK87: =NA() -> #N/A | AL87: =NA() -> #N/A | AM87: =NA() -> #N/A | AN87: =NA() -> #N/A | AP87: =AI87 -> 45775 | AQ87: =HAVERD!II874 -> 78.27 | AR87: =NA() -> #N/A | AS87: =NA() -> #N/A | AT87: =NA() -> #N/A
Y88: 46023 | Z88: =HAVERM!J200 -> 3.734 | AA88: =HAVERM!K200 -> 3.504 | AB88: =HAVERM!L200 -> 4.383 | AC88: =HAVERM!M200 -> 3.593 | AE88: 44562 | AF88: =HAVERM!P152 -> 88.19917 | AG88: ='Bloom - Monthly US data'!M446 -> 37.457077 | AI88: =HAVERD!A875 -> 45776 | AJ88: =HAVERD!IH875 -> 64.04 | AK88: =NA() -> #N/A | AL88: =NA() -> #N/A | AM88: =NA() -> #N/A | AN88: =NA() -> #N/A | AP88: =AI88 -> 45776 | AQ88: =HAVERD!II875 -> 76.67 | AR88: =NA() -> #N/A | AS88: =NA() -> #N/A | AT88: =NA() -> #N/A
Y89: 46054 | Z89: =HAVERM!J201 -> 3.752 | AA89: =HAVERM!K201 -> 3.449 | AB89: =HAVERM!L201 -> 4.327 | AC89: =HAVERM!M201 -> 3.555 | AE89: 44593 | AF89: =HAVERM!P153 -> 80.71515 | AG89: ='Bloom - Monthly US data'!M447 -> 113.83121 | AI89: =HAVERD!A876 -> 45777 | AJ89: =HAVERD!IH876 -> 63.37 | AK89: =NA() -> #N/A | AL89: =NA() -> #N/A | AM89: =NA() -> #N/A | AN89: =NA() -> #N/A | AP89: =AI89 -> 45777 | AQ89: =HAVERD!II876 -> 77.93 | AR89: =NA() -> #N/A | AS89: =NA() -> #N/A | AT89: =NA() -> #N/A
Y90: 46082 | Z90: =HAVERM!J202 -> 3.677 | AA90: =HAVERM!K202 -> 3.501 | AB90: =HAVERM!L202 -> 4.325 | AC90: =HAVERM!M202 -> 3.454 | AE90: 44621 | AF90: =HAVERM!P154 -> 170.04504 | AG90: ='Bloom - Monthly US data'!M448 -> 70.311721 | AI90: =HAVERD!A877 -> 45778 | AJ90: =HAVERD!IH877 -> 62.37 | AK90: =NA() -> #N/A | AL90: =NA() -> #N/A | AM90: =NA() -> #N/A | AN90: =NA() -> #N/A | AP90: =AI90 -> 45778 | AQ90: =HAVERD!II877 -> 77.25 | AR90: =NA() -> #N/A | AS90: =NA() -> #N/A | AT90: =NA() -> #N/A
Y91: 46113 | AE91: 44652 | AF91: =HAVERM!P155 -> 123.43515 | AG91: ='Bloom - Monthly US data'!M449 -> 44.537894 | AI91: =HAVERD!A878 -> 45779 | AJ91: =HAVERD!IH878 -> 61.57 | AK91: =NA() -> #N/A | AL91: =NA() -> #N/A | AM91: =NA() -> #N/A | AN91: =NA() -> #N/A | AP91: =AI91 -> 45779 | AQ91: =HAVERD!II878 -> 80.15 | AR91: =NA() -> #N/A | AS91: =NA() -> #N/A | AT91: =NA() -> #N/A
AE92: 44682 | AF92: =HAVERM!P156 -> 105.19512 | AG92: ='Bloom - Monthly US data'!M450 -> 78.178058 | AI92: =HAVERD!A879 -> 45782 | AJ92: =HAVERD!IH879 -> #N/A | AK92: =NA() -> #N/A | AL92: =NA() -> #N/A | AM92: =NA() -> #N/A | AN92: =NA() -> #N/A | AP92: =AI92 -> 45782 | AQ92: =HAVERD!II879 -> 80.15 | AR92: =NA() -> #N/A | AS92: =NA() -> #N/A | AT92: =NA() -> #N/A
AE93: 44713 | AF93: =HAVERM!P157 -> 118.81206 | AG93: ='Bloom - Monthly US data'!M451 -> 97.342332 | AI93: =HAVERD!A880 -> 45783 | AJ93: =HAVERD!IH880 -> 62.37 | AK93: =NA() -> #N/A | AL93: =NA() -> #N/A | AM93: =NA() -> #N/A | AN93: =NA() -> #N/A | AP93: =AI93 -> 45783 | AQ93: =HAVERD!II880 -> 83.78 | AR93: =NA() -> #N/A | AS93: =NA() -> #N/A | AT93: =NA() -> #N/A
AE94: 44743 | AF94: =HAVERM!P158 -> 184.27249 | AG94: ='Bloom - Monthly US data'!M452 -> 71.545074 | AI94: =HAVERD!A881 -> 45784 | AJ94: =HAVERD!IH881 -> 60.31 | AK94: =NA() -> #N/A | AL94: =NA() -> #N/A | AM94: =NA() -> #N/A | AN94: =NA() -> #N/A | AP94: =AI94 -> 45784 | AQ94: =HAVERD!II881 -> 83.07 | AR94: =NA() -> #N/A | AS94: =NA() -> #N/A | AT94: =NA() -> #N/A
AE95: 44774 | AF95: =HAVERM!P159 -> 124.28908 | AG95: ='Bloom - Monthly US data'!M453 -> 150.4923 | AI95: =HAVERD!A882 -> 45785 | AJ95: =HAVERD!IH882 -> 62.22 | AK95: =NA() -> #N/A | AL95: =NA() -> #N/A | AM95: =NA() -> #N/A | AN95: =NA() -> #N/A | AP95: =AI95 -> 45785 | AQ95: =HAVERD!II882 -> 84.8 | AR95: =NA() -> #N/A | AS95: =NA() -> #N/A | AT95: =NA() -> #N/A
AE96: 44805 | AF96: =HAVERM!P160 -> 230.05941 | AG96: ='Bloom - Monthly US data'!M454 -> 50.425833 | AI96: =HAVERD!A883 -> 45786 | AJ96: =HAVERD!IH883 -> 64.26 | AK96: =NA() -> #N/A | AL96: =NA() -> #N/A | AM96: =NA() -> #N/A | AN96: =NA() -> #N/A | AP96: =AI96 -> 45786 | AQ96: =HAVERD!II883 -> 82.69 | AR96: =NA() -> #N/A | AS96: =NA() -> #N/A | AT96: =NA() -> #N/A
AE97: 44835 | AF97: =HAVERM!P161 -> 399.80611 | AG97: ='Bloom - Monthly US data'!M455 -> 92.840876 | AI97: =HAVERD!A884 -> 45789 | AJ97: =HAVERD!IH884 -> 65.28 | AK97: =NA() -> #N/A | AL97: =NA() -> #N/A | AM97: =NA() -> #N/A | AN97: =NA() -> #N/A | AP97: =AI97 -> 45789 | AQ97: =HAVERD!II884 -> 84.6 | AR97: =NA() -> #N/A | AS97: =NA() -> #N/A | AT97: =NA() -> #N/A
AE98: 44866 | AF98: =HAVERM!P162 -> 220.10556 | AG98: ='Bloom - Monthly US data'!M456 -> 81.308892 | AI98: =HAVERD!A885 -> 45790 | AJ98: =HAVERD!IH885 -> 66.93 | AK98: =NA() -> #N/A | AL98: =NA() -> #N/A | AM98: =NA() -> #N/A | AN98: =NA() -> #N/A | AP98: =AI98 -> 45790 | AQ98: =HAVERD!II885 -> 85.12 | AR98: =NA() -> #N/A | AS98: =NA() -> #N/A | AT98: =NA() -> #N/A
AE99: 44896 | AF99: =HAVERM!P163 -> 167.63101 | AG99: ='Bloom - Monthly US data'!M457 -> 16.205069 | AI99: =HAVERD!A886 -> 45791 | AJ99: =HAVERD!IH886 -> 65.91 | AK99: =NA() -> #N/A | AL99: =NA() -> #N/A | AM99: =NA() -> #N/A | AN99: =NA() -> #N/A | AP99: =AI99 -> 45791 | AQ99: =HAVERD!II886 -> 83.73 | AR99: =NA() -> #N/A | AS99: =NA() -> #N/A | AT99: =NA() -> #N/A
AE100: 44927 | AF100: =HAVERM!P164 -> 140.06709 | AG100: ='Bloom - Monthly US data'!M458 -> 100.53237 | AI100: =HAVERD!A887 -> 45792 | AJ100: =HAVERD!IH887 -> 64.36 | AK100: =NA() -> #N/A | AL100: =NA() -> #N/A | AM100: =NA() -> #N/A | AN100: =NA() -> #N/A | AP100: =AI100 -> 45792 | AQ100: =HAVERD!II887 -> 84.48 | AR100: =NA() -> #N/A | AS100: =NA() -> #N/A | AT100: =NA() -> #N/A
