Workbook
Name Data: [1]sheet0!$C$2

Sheet Chart Data
A1: GDP growth | F1: CPI inflation | K1: Bank Rate
B2: Baseline | C2: $100 for two months | D2: Worst-case scenario | G2: Baseline | H2: $100 for two months | I2: Worst-case scenario | L2: Baseline | M2: $100 for two months | N2: Worst-case scenario
A3: 2025 | B3: =100*(('GEM data - Baseline'!$F187/'GEM data - Baseline'!$F183)-1) -> 1.7614345 | C3: =100*(('GEM data - $100 oil'!$F187/'GEM data - $100 oil'!$F183)-1) -> 1.7614345 | D3: =100*(('GEM data - Worst case'!$F187/'GEM data - Worst case'!$F183)-1) -> 1.7614345 | F3: 2025 | G3: =100*(('GEM data - Baseline'!$H187/'GEM data - Baseline'!$H183)-1) -> 2.7973783 | H3: =100*(('GEM data - $100 oil'!$H187/'GEM data - $100 oil'!$H183)-1) -> 2.7973783 | I3: =100*(('GEM data - Worst case'!$H187/'GEM data - Worst case'!$H183)-1) -> 2.7973783 | K3: 2025 | L3: ='GEM data - Baseline'!$I187 -> 4.601563 | M3: ='GEM data - $100 oil'!$I187 -> 4.601563 | N3: ='GEM data - Worst case'!$I187 -> 4.601563
B4: =100*(('GEM data - Baseline'!$F188/'GEM data - Baseline'!$F184)-1) -> 1.3689449 | C4: =100*(('GEM data - $100 oil'!$F188/'GEM data - $100 oil'!$F184)-1) -> 1.3689449 | D4: =100*(('GEM data - Worst case'!$F188/'GEM data - Worst case'!$F184)-1) -> 1.3689449 | G4: =100*(('GEM data - Baseline'!$H188/'GEM data - Baseline'!$H184)-1) -> 3.4869498 | H4: =100*(('GEM data - $100 oil'!$H188/'GEM data - $100 oil'!$H184)-1) -> 3.4869498 | I4: =100*(('GEM data - Worst case'!$H188/'GEM data - Worst case'!$H184)-1) -> 3.4869498 | L4: ='GEM data - Baseline'!$I188 -> 4.353846 | M4: ='GEM data - $100 oil'!$I188 -> 4.353846 | N4: ='GEM data - Worst case'!$I188 -> 4.353846
B5: =100*(('GEM data - Baseline'!$F189/'GEM data - Baseline'!$F185)-1) -> 1.1959481 | C5: =100*(('GEM data - $100 oil'!$F189/'GEM data - $100 oil'!$F185)-1) -> 1.1959481 | D5: =100*(('GEM data - Worst case'!$F189/'GEM data - Worst case'!$F185)-1) -> 1.1959481 | G5: =100*(('GEM data - Baseline'!$H189/'GEM data - Baseline'!$H185)-1) -> 3.803132 | H5: =100*(('GEM data - $100 oil'!$H189/'GEM data - $100 oil'!$H185)-1) -> 3.803132 | I5: =100*(('GEM data - Worst case'!$H189/'GEM data - Worst case'!$H185)-1) -> 3.803132 | L5: ='GEM data - Baseline'!$I189 -> 4.102273 | M5: ='GEM data - $100 oil'!$I189 -> 4.102273 | N5: ='GEM data - Worst case'!$I189 -> 4.102273
B6: =100*(('GEM data - Baseline'!$F190/'GEM data - Baseline'!$F186)-1) -> 0.97183663 | C6: =100*(('GEM data - $100 oil'!$F190/'GEM data - $100 oil'!$F186)-1) -> 0.97183663 | D6: =100*(('GEM data - Worst case'!$F190/'GEM data - Worst case'!$F186)-1) -> 0.97183663 | G6: =100*(('GEM data - Baseline'!$H190/'GEM data - Baseline'!$H186)-1) -> 3.3769049 | H6: =100*(('GEM data - $100 oil'!$H190/'GEM data - $100 oil'!$H186)-1) -> 3.3769049 | I6: =100*(('GEM data - Worst case'!$H190/'GEM data - Worst case'!$H186)-1) -> 3.3769049 | L6: ='GEM data - Baseline'!$I190 -> 3.962121 | M6: ='GEM data - $100 oil'!$I190 -> 3.962121 | N6: ='GEM data - Worst case'!$I190 -> 3.962121
A7: 2026 | B7: =100*(('GEM data - Baseline'!$F191/'GEM data - Baseline'!$F187)-1) -> 0.6893924 | C7: =100*(('GEM data - $100 oil'!$F191/'GEM data - $100 oil'!$F187)-1) -> 0.6504799 | D7: =100*(('GEM data - Worst case'!$F191/'GEM data - Worst case'!$F187)-1) -> 0.63007821 | F7: 2026 | G7: =100*(('GEM data - Baseline'!$H191/'GEM data - Baseline'!$H187)-1) -> 2.8921052 | H7: =100*(('GEM data - $100 oil'!$H191/'GEM data - $100 oil'!$H187)-1) -> 2.9968367 | I7: =100*(('GEM data - Worst case'!$H191/'GEM data - Worst case'!$H187)-1) -> 3.0805337 | K7: 2026 | L7: ='GEM data - Baseline'!$I191 -> 3.75 | M7: ='GEM data - $100 oil'!$I191 -> 3.75905 | N7: ='GEM data - Worst case'!$I191 -> 3.75
B8: =100*(('GEM data - Baseline'!$F192/'GEM data - Baseline'!$F188)-1) -> 0.7173261 | C8: =100*(('GEM data - $100 oil'!$F192/'GEM data - $100 oil'!$F188)-1) -> 0.53941697 | D8: =100*(('GEM data - Worst case'!$F192/'GEM data - Worst case'!$F188)-1) -> 0.3207302 | G8: =100*(('GEM data - Baseline'!$H192/'GEM data - Baseline'!$H188)-1) -> 2.4896751 | H8: =100*(('GEM data - $100 oil'!$H192/'GEM data - $100 oil'!$H188)-1) -> 3.0145126 | I8: =100*(('GEM data - Worst case'!$H192/'GEM data - Worst case'!$H188)-1) -> 3.7470758 | L8: ='GEM data - Baseline'!$I192 -> 3.580767 | M8: ='GEM data - $100 oil'!$I192 -> 3.627709 | N8: ='GEM data - Worst case'!$I192 -> 3.75
B9: =100*(('GEM data - Baseline'!$F193/'GEM data - Baseline'!$F189)-1) -> 0.86762802 | C9: =100*(('GEM data - $100 oil'!$F193/'GEM data - $100 oil'!$F189)-1) -> 0.53506375 | D9: =100*(('GEM data - Worst case'!$F193/'GEM data - Worst case'!$F189)-1) -> 0.12514411 | G9: =100*(('GEM data - Baseline'!$H193/'GEM data - Baseline'!$H189)-1) -> 2.85 | H9: =100*(('GEM data - $100 oil'!$H193/'GEM data - $100 oil'!$H189)-1) -> 3.809842 | I9: =100*(('GEM data - Worst case'!$H193/'GEM data - Worst case'!$H189)-1) -> 4.8531609 | L9: ='GEM data - Baseline'!$I193 -> 3.499992 | M9: ='GEM data - $100 oil'!$I193 -> 3.613537 | N9: ='GEM data - Worst case'!$I193 -> 3.75
B10: =100*(('GEM data - Baseline'!$F194/'GEM data - Baseline'!$F190)-1) -> 1.0903226 | C10: =100*(('GEM data - $100 oil'!$F194/'GEM data - $100 oil'!$F190)-1) -> 0.72619198 | D10: =100*(('GEM data - Worst case'!$F194/'GEM data - Worst case'!$F190)-1) -> -0.013662693 | G10: =100*(('GEM data - Baseline'!$H194/'GEM data - Baseline'!$H190)-1) -> 2.6402718 | H10: =100*(('GEM data - $100 oil'!$H194/'GEM data - $100 oil'!$H190)-1) -> 3.3717454 | I10: =100*(('GEM data - Worst case'!$H194/'GEM data - Worst case'!$H190)-1) -> 5.4763948 | L10: ='GEM data - Baseline'!$I194 -> 3.344676 | M10: ='GEM data - $100 oil'!$I194 -> 3.550428 | N10: ='GEM data - Worst case'!$I194 -> 3.9
A11: 2027 | B11: =100*(('GEM data - Baseline'!$F195/'GEM data - Baseline'!$F191)-1) -> 1.0644544 | C11: =100*(('GEM data - $100 oil'!$F195/'GEM data - $100 oil'!$F191)-1) -> 0.80959302 | D11: =100*(('GEM data - Worst case'!$F195/'GEM data - Worst case'!$F191)-1) -> -0.083257418 | F11: 2027 | G11: =100*(('GEM data - Baseline'!$H195/'GEM data - Baseline'!$H191)-1) -> 2.5834352 | H11: =100*(('GEM data - $100 oil'!$H195/'GEM data - $100 oil'!$H191)-1) -> 2.8448016 | I11: =100*(('GEM data - Worst case'!$H195/'GEM data - Worst case'!$H191)-1) -> 4.6434239 | K11: 2027 | L11: ='GEM data - Baseline'!$I195 -> 3.249961 | M11: ='GEM data - $100 oil'!$I195 -> 3.547556 | N11: ='GEM data - Worst case'!$I195 -> 4
B12: =100*(('GEM data - Baseline'!$F196/'GEM data - Baseline'!$F192)-1) -> 1.1827226 | C12: =100*(('GEM data - $100 oil'!$F196/'GEM data - $100 oil'!$F192)-1) -> 1.1491395 | D12: =100*(('GEM data - Worst case'!$F196/'GEM data - Worst case'!$F192)-1) -> 0.39548354 | G12: =100*(('GEM data - Baseline'!$H196/'GEM data - Baseline'!$H192)-1) -> 2.1828385 | H12: =100*(('GEM data - $100 oil'!$H196/'GEM data - $100 oil'!$H192)-1) -> 1.9355164 | I12: =100*(('GEM data - Worst case'!$H196/'GEM data - Worst case'!$H192)-1) -> 3.0215805 | L12: ='GEM data - Baseline'!$I196 -> 3.076869 | M12: ='GEM data - $100 oil'!$I196 -> 3.413372 | N12: ='GEM data - Worst case'!$I196 -> 4
B13: =100*(('GEM data - Baseline'!$F197/'GEM data - Baseline'!$F193)-1) -> 1.3700444 | C13: =100*(('GEM data - $100 oil'!$F197/'GEM data - $100 oil'!$F193)-1) -> 1.5367717 | D13: =100*(('GEM data - Worst case'!$F197/'GEM data - Worst case'!$F193)-1) -> 0.94560096 | G13: =100*(('GEM data - Baseline'!$H197/'GEM data - Baseline'!$H193)-1) -> 1.811658 | H13: =100*(('GEM data - $100 oil'!$H197/'GEM data - $100 oil'!$H193)-1) -> 0.98945837 | I13: =100*(('GEM data - Worst case'!$H197/'GEM data - Worst case'!$H193)-1) -> 1.5790418 | L13: ='GEM data - Baseline'!$I197 -> 2.99994 | M13: ='GEM data - $100 oil'!$I197 -> 3.316199 | N13: ='GEM data - Worst case'!$I197 -> 3.96
B14: =100*(('GEM data - Baseline'!$F198/'GEM data - Baseline'!$F194)-1) -> 1.475835 | C14: =100*(('GEM data - $100 oil'!$F198/'GEM data - $100 oil'!$F194)-1) -> 1.6861528 | D14: =100*(('GEM data - Worst case'!$F198/'GEM data - Worst case'!$F194)-1) -> 1.4986082 | G14: =100*(('GEM data - Baseline'!$H198/'GEM data - Baseline'!$H194)-1) -> 2.0344119 | H14: =100*(('GEM data - $100 oil'!$H198/'GEM data - $100 oil'!$H194)-1) -> 1.3515674 | I14: =100*(('GEM data - Worst case'!$H198/'GEM data - Worst case'!$H194)-1) -> 0.73377821 | L14: ='GEM data - Baseline'!$I198 -> 2.999938 | M14: ='GEM data - $100 oil'!$I198 -> 3.248416 | N14: ='GEM data - Worst case'!$I198 -> 3.71
A15: 2028 | B15: =100*(('GEM data - Baseline'!$F199/'GEM data - Baseline'!$F195)-1) -> 1.4959609 | C15: =100*(('GEM data - $100 oil'!$F199/'GEM data - $100 oil'!$F195)-1) -> 1.6661253 | D15: =100*(('GEM data - Worst case'!$F199/'GEM data - Worst case'!$F195)-1) -> 1.6955228 | F15: 2028 | G15: =100*(('GEM data - Baseline'!$H199/'GEM data - Baseline'!$H195)-1) -> 2.1590348 | H15: =100*(('GEM data - $100 oil'!$H199/'GEM data - $100 oil'!$H195)-1) -> 1.8400934 | I15: =100*(('GEM data - Worst case'!$H199/'GEM data - Worst case'!$H195)-1) -> 1.3070763 | K15: 2028 | L15: ='GEM data - Baseline'!$I199 -> 2.999943 | M15: ='GEM data - $100 oil'!$I199 -> 3.160861 | N15: ='GEM data - Worst case'!$I199 -> 3.5
B16: =100*(('GEM data - Baseline'!$F200/'GEM data - Baseline'!$F196)-1) -> 1.5234682 | C16: =100*(('GEM data - $100 oil'!$F200/'GEM data - $100 oil'!$F196)-1) -> 1.6604706 | D16: =100*(('GEM data - Worst case'!$F200/'GEM data - Worst case'!$F196)-1) -> 1.8348823 | G16: =100*(('GEM data - Baseline'!$H200/'GEM data - Baseline'!$H196)-1) -> 1.9743296 | H16: =100*(('GEM data - $100 oil'!$H200/'GEM data - $100 oil'!$H196)-1) -> 1.7307198 | I16: =100*(('GEM data - Worst case'!$H200/'GEM data - Worst case'!$H196)-1) -> 1.1416497 | L16: ='GEM data - Baseline'!$I200 -> 2.838416 | M16: ='GEM data - $100 oil'!$I200 -> 2.92939 | N16: ='GEM data - Worst case'!$I200 -> 3.46
B17: =100*(('GEM data - Baseline'!$F201/'GEM data - Baseline'!$F197)-1) -> 1.5082714 | C17: =100*(('GEM data - $100 oil'!$F201/'GEM data - $100 oil'!$F197)-1) -> 1.6374958 | D17: =100*(('GEM data - Worst case'!$F201/'GEM data - Worst case'!$F197)-1) -> 1.9501475 | G17: =100*(('GEM data - Baseline'!$H201/'GEM data - Baseline'!$H197)-1) -> 1.9798862 | H17: =100*(('GEM data - $100 oil'!$H201/'GEM data - $100 oil'!$H197)-1) -> 1.8691441 | I17: =100*(('GEM data - Worst case'!$H201/'GEM data - Worst case'!$H197)-1) -> 1.3324538 | L17: ='GEM data - Baseline'!$I201 -> 2.749965 | M17: ='GEM data - $100 oil'!$I201 -> 2.794754 | N17: ='GEM data - Worst case'!$I201 -> 3.21
B18: =100*(('GEM data - Baseline'!$F202/'GEM data - Baseline'!$F198)-1) -> 1.4982372 | C18: =100*(('GEM data - $100 oil'!$F202/'GEM data - $100 oil'!$F198)-1) -> 1.6534192 | D18: =100*(('GEM data - Worst case'!$F202/'GEM data - Worst case'!$F198)-1) -> 2.0386514 | G18: =100*(('GEM data - Baseline'!$H202/'GEM data - Baseline'!$H198)-1) -> 1.9713777 | H18: =100*(('GEM data - $100 oil'!$H202/'GEM data - $100 oil'!$H198)-1) -> 1.9223456 | I18: =100*(('GEM data - Worst case'!$H202/'GEM data - Worst case'!$H198)-1) -> 1.4865556 | L18: ='GEM data - Baseline'!$I202 -> 2.749983 | M18: ='GEM data - $100 oil'!$I202 -> 2.765643 | N18: ='GEM data - Worst case'!$I202 -> 2.96
A20: 2025 | B20: =SUMIF('GEM data - Baseline'!$B:$B,'Chart Data'!$A20,'GEM data - Baseline'!$F:$F) -> 2818929 | C20: =SUMIF('GEM data - $100 oil'!$B:$B,'Chart Data'!$A20,'GEM data - $100 oil'!$F:$F) -> 2818929 | D20: =SUMIF('GEM data - Worst case'!$B:$B,'Chart Data'!$A20,'GEM data - Worst case'!$F:$F) -> 2818929
A21: 2026 | B21: =SUMIF('GEM data - Baseline'!$B:$B,'Chart Data'!$A21,'GEM data - Baseline'!$F:$F) -> 2842645.1 | C21: =SUMIF('GEM data - $100 oil'!$B:$B,'Chart Data'!$A21,'GEM data - $100 oil'!$F:$F) -> 2836203.1 | D21: =SUMIF('GEM data - Worst case'!$B:$B,'Chart Data'!$A21,'GEM data - Worst case'!$F:$F) -> 2826407.4
A22: 2027 | B22: =SUMIF('GEM data - Baseline'!$B:$B,'Chart Data'!$A22,'GEM data - Baseline'!$F:$F) -> 2878851.2 | C22: =SUMIF('GEM data - $100 oil'!$B:$B,'Chart Data'!$A22,'GEM data - $100 oil'!$F:$F) -> 2872955.9 | D22: =SUMIF('GEM data - Worst case'!$B:$B,'Chart Data'!$A22,'GEM data - Worst case'!$F:$F) -> 2845863.3
A23: 2028 | B23: =SUMIF('GEM data - Baseline'!$B:$B,'Chart Data'!$A23,'GEM data - Baseline'!$F:$F) -> 2922220.5 | C23: =SUMIF('GEM data - $100 oil'!$B:$B,'Chart Data'!$A23,'GEM data - $100 oil'!$F:$F) -> 2920484.5 | D23: =SUMIF('GEM data - Worst case'!$B:$B,'Chart Data'!$A23,'GEM data - Worst case'!$F:$F) -> 2899376.6
A25: 2026 | B25: =100*((B21/B20)-1) -> 0.84131597 | C25: =100*((C21/C20)-1) -> 0.61278947 | D25: =100*((D21/D20)-1) -> 0.26529224
A26: 2027 | B26: =100*((B22/B21)-1) -> 1.2736764 | C26: =100*((C22/C21)-1) -> 1.2958451 | D26: =100*((D22/D21)-1) -> 0.68836149
A27: 2028 | B27: =100*((B23/B22)-1) -> 1.5064794 | C27: =100*((C23/C22)-1) -> 1.6543449 | D27: =100*((D23/D22)-1) -> 1.880389

Sheet GEM data - Baseline
B1: lookups | C1: lookups | D1: lookups | F1: ='GMW - Baseline'!C2 -> Mar26_1 | G1: =$F$1 -> Mar26_1 | H1: =$F$1 -> Mar26_1 | I1: =$F$1 -> Mar26_1 | J1: =$F$1 -> Mar26_1 | K1: =$F$1 -> Mar26_1 | L1: =$F$1 -> Mar26_1 | M1: =$F$1 -> Mar26_1 | N1: =$F$1 -> Mar26_1 | ... T1: =$F$1 -> Mar26_1
F2: UK | G2: UK | H2: UK | I2: UK | J2: UK | K2: UK | L2: UK | M2: UK | N2: UK | O2: UK | P2: UK | Q2: UK | R2: UK | S2: UK | T2: UK
F3: GDP | G3: C | H3: CPI | I3: RCB
F4: GBR | G4: GBR | H4: GBR | I4: GBR | J4: GBR | K4: GBR | L4: GBR | M4: GBR | N4: GBR | O4: GBR | P4: GBR | Q4: GBR | R4: GBR | S4: GBR | T4: GBR
F5: L | G5: L | H5: L | I5: L | J5: L | K5: L | L5: L | M5: L | N5: L | O5: L | P5: L | Q5: L | R5: L | S5: L | T5: L
B6: CY total | C6: FY total | D6: FY end | E6: =E330+5 -> 2308 | F6: {=_xlfn.CONCAT(INDEX('GMW - Baseline'!$A$2:$MC$200,MATCH(1,('GMW - Baseline'!$MC$2:$MC$200=F$3)*('GMW - Baseline'!$MB$2:$MB$200=F$4),0),$E6-1973),"0",(INDEX('GMW - Baseline'!$A$2:$MC$200,MATCH(1,('GMW - Baseline'!$MC$2:$MC$200=F$3)*('GMW - Baseline'!$MB$2:$MB$200=F$4),0),$E6-1972)))} -> 202504 | G6: {=_xlfn.CONCAT(INDEX('GMW - Baseline'!$A$2:$MC$200,MATCH(1,('GMW - Baseline'!$MC$2:$MC$200=G$3)*('GMW - Baseline'!$MB$2:$MB$200=G$4),0),$E6-1973),"0",(INDEX('GMW - Baseline'!$A$2:$MC$200,MATCH(1,('GMW - Baseline'!$MC$2:$MC$200=G$3)*('GMW - Baseline'!$MB$2:$MB$200=G$4),0),$E6-1972)))} -> 202504 | H6: {=_xlfn.CONCAT(INDEX('GMW - Baseline'!$A$2:$MC$200,MATCH(1,('GMW - Baseline'!$MC$2:$MC$200=H$3)*('GMW - Baseline'!$MB$2:$MB$200=H$4),0),$E6-1973),"0",(INDEX('GMW - Baseline'!$A$2:$MC$200,MATCH(1,('GMW - Baseline'!$MC$2:$MC$200=H$3)*('GMW - Baseline'!$MB$2:$MB$200=H$4),0),$E6-1972)))} -> 202504 | I6: {=_xlfn.CONCAT(INDEX('GMW - Baseline'!$A$2:$MC$200,MATCH(1,('GMW - Baseline'!$MC$2:$MC$200=I$3)*('GMW - Baseline'!$MB$2:$MB$200=I$4),0),$E6-1973),"0",(INDEX('GMW - Baseline'!$A$2:$MC$200,MATCH(1,('GMW - Baseline'!$MC$2:$MC$200=I$3)*('GMW - Baseline'!$MB$2:$MB$200=I$4),0),$E6-1972)))} -> 202504 | J6: {=_xlfn.CONCAT(INDEX('GMW - Baseline'!$A$2:$MC$200,MATCH(1,('GMW - Baseline'!$MC$2:$MC$200=J$3)*('GMW - Baseline'!$MB$2:$MB$200=J$4),0),$E6-1973),"0",(INDEX('GMW - Baseline'!$A$2:$MC$200,MATCH(1,('GMW - Baseline'!$MC$2:$MC$200=J$3)*('GMW - Baseline'!$MB$2:$MB$200=J$4),0),$E6-1972)))} -> #N/A | K6: {=_xlfn.CONCAT(INDEX('GMW - Baseline'!$A$2:$MC$200,MATCH(1,('GMW - Baseline'!$MC$2:$MC$200=K$3)*('GMW - Baseline'!$MB$2:$MB$200=K$4),0),$E6-1973),"0",(INDEX('GMW - Baseline'!$A$2:$MC$200,MATCH(1,('GMW - Baseline'!$MC$2:$MC$200=K$3)*('GMW - Baseline'!$MB$2:$MB$200=K$4),0),$E6-1972)))} -> #N/A | L6: {=_xlfn.CONCAT(INDEX('GMW - Baseline'!$A$2:$MC$200,MATCH(1,('GMW - Baseline'!$MC$2:$MC$200=L$3)*('GMW - Baseline'!$MB$2:$MB$200=L$4),0),$E6-1973),"0",(INDEX('GMW - Baseline'!$A$2:$MC$200,MATCH(1,('GMW - Baseline'!$MC$2:$MC$200=L$3)*('GMW - Baseline'!$MB$2:$MB$200=L$4),0),$E6-1972)))} -> #N/A | M6: {=_xlfn.CONCAT(INDEX('GMW - Baseline'!$A$2:$MC$200,MATCH(1,('GMW - Baseline'!$MC$2:$MC$200=M$3)*('GMW - Baseline'!$MB$2:$MB$200=M$4),0),$E6-1973),"0",(INDEX('GMW - Baseline'!$A$2:$MC$200,MATCH(1,('GMW - Baseline'!$MC$2:$MC$200=M$3)*('GMW - Baseline'!$MB$2:$MB$200=M$4),0),$E6-1972)))} -> #N/A | ... T6: {=_xlfn.CONCAT(INDEX('GMW - Baseline'!$A$2:$MC$200,MATCH(1,('GMW - Baseline'!$MC$2:$MC$200=T$3)*('GMW - Baseline'!$MB$2:$MB$200=T$4),0),$E6-1973),"0",(INDEX('GMW - Baseline'!$A$2:$MC$200,MATCH(1,('GMW - Baseline'!$MC$2:$MC$200=T$3)*('GMW - Baseline'!$MB$2:$MB$200=T$4),0),$E6-1972)))} -> #N/A
A7: 1980 | B7: 1980 | E7: 1980 | F7: {=INDEX('GMW - Baseline'!$A$2:$MC$200,MATCH(1,('GMW - Baseline'!$MC$2:$MC$200=F$3)*('GMW - Baseline'!$MB$2:$MB$200=F$4),0),$E7-1973)} -> 290378 | G7: {=INDEX('GMW - Baseline'!$A$2:$MC$200,MATCH(1,('GMW - Baseline'!$MC$2:$MC$200=G$3)*('GMW - Baseline'!$MB$2:$MB$200=G$4),0),$E7-1973)} -> 153439 | H7: {=INDEX('GMW - Baseline'!$A$2:$MC$200,MATCH(1,('GMW - Baseline'!$MC$2:$MC$200=H$3)*('GMW - Baseline'!$MB$2:$MB$200=H$4),0),$E7-1973)} -> 30.60508 | I7: {=INDEX('GMW - Baseline'!$A$2:$MC$200,MATCH(1,('GMW - Baseline'!$MC$2:$MC$200=I$3)*('GMW - Baseline'!$MB$2:$MB$200=I$4),0),$E7-1973)} -> 17 | J7: {=INDEX('GMW - Baseline'!$A$2:$MC$200,MATCH(1,('GMW - Baseline'!$MC$2:$MC$200=J$3)*('GMW - Baseline'!$MB$2:$MB$200=J$4),0),$E7-1973)} -> #N/A | K7: {=INDEX('GMW - Baseline'!$A$2:$MC$200,MATCH(1,('GMW - Baseline'!$MC$2:$MC$200=K$3)*('GMW - Baseline'!$MB$2:$MB$200=K$4),0),$E7-1973)} -> #N/A | L7: {=INDEX('GMW - Baseline'!$A$2:$MC$200,MATCH(1,('GMW - Baseline'!$MC$2:$MC$200=L$3)*('GMW - Baseline'!$MB$2:$MB$200=L$4),0),$E7-1973)} -> #N/A | M7: {=INDEX('GMW - Baseline'!$A$2:$MC$200,MATCH(1,('GMW - Baseline'!$MC$2:$MC$200=M$3)*('GMW - Baseline'!$MB$2:$MB$200=M$4),0),$E7-1973)} -> #N/A | ... T7: {=INDEX('GMW - Baseline'!$A$2:$MC$200,MATCH(1,('GMW - Baseline'!$MC$2:$MC$200=T$3)*('GMW - Baseline'!$MB$2:$MB$200=T$4),0),$E7-1973)} -> #N/A
B8: 1980 | C8: 1980 | E8: =+E7+1 -> 1981 | F8: {=INDEX('GMW - Baseline'!$A$2:$MC$200,MATCH(1,('GMW - Baseline'!$MC$2:$MC$200=F$3)*('GMW - Baseline'!$MB$2:$MB$200=F$4),0),$E8-1973)} -> 284713 | G8: {=INDEX('GMW - Baseline'!$A$2:$MC$200,MATCH(1,('GMW - Baseline'!$MC$2:$MC$200=G$3)*('GMW - Baseline'!$MB$2:$MB$200=G$4),0),$E8-1973)} -> 149443 | H8: {=INDEX('GMW - Baseline'!$A$2:$MC$200,MATCH(1,('GMW - Baseline'!$MC$2:$MC$200=H$3)*('GMW - Baseline'!$MB$2:$MB$200=H$4),0),$E8-1973)} -> 32.24743 | I8: {=INDEX('GMW - Baseline'!$A$2:$MC$200,MATCH(1,('GMW - Baseline'!$MC$2:$MC$200=I$3)*('GMW - Baseline'!$MB$2:$MB$200=I$4),0),$E8-1973)} -> 17 | J8: {=INDEX('GMW - Baseline'!$A$2:$MC$200,MATCH(1,('GMW - Baseline'!$MC$2:$MC$200=J$3)*('GMW - Baseline'!$MB$2:$MB$200=J$4),0),$E8-1973)} -> #N/A | K8: {=INDEX('GMW - Baseline'!$A$2:$MC$200,MATCH(1,('GMW - Baseline'!$MC$2:$MC$200=K$3)*('GMW - Baseline'!$MB$2:$MB$200=K$4),0),$E8-1973)} -> #N/A | L8: {=INDEX('GMW - Baseline'!$A$2:$MC$200,MATCH(1,('GMW - Baseline'!$MC$2:$MC$200=L$3)*('GMW - Baseline'!$MB$2:$MB$200=L$4),0),$E8-1973)} -> #N/A | M8: {=INDEX('GMW - Baseline'!$A$2:$MC$200,MATCH(1,('GMW - Baseline'!$MC$2:$MC$200=M$3)*('GMW - Baseline'!$MB$2:$MB$200=M$4),0),$E8-1973)} -> #N/A | ... T8: {=INDEX('GMW - Baseline'!$A$2:$MC$200,MATCH(1,('GMW - Baseline'!$MC$2:$MC$200=T$3)*('GMW - Baseline'!$MB$2:$MB$200=T$4),0),$E8-1973)} -> #N/A
B9: 1980 | C9: 1980 | E9: =+E8+1 -> 1982 | F9: {=INDEX('GMW - Baseline'!$A$2:$MC$200,MATCH(1,('GMW - Baseline'!$MC$2:$MC$200=F$3)*('GMW - Baseline'!$MB$2:$MB$200=F$4),0),$E9-1973)} -> 284402 | G9: {=INDEX('GMW - Baseline'!$A$2:$MC$200,MATCH(1,('GMW - Baseline'!$MC$2:$MC$200=G$3)*('GMW - Baseline'!$MB$2:$MB$200=G$4),0),$E9-1973)} -> 151403 | H9: {=INDEX('GMW - Baseline'!$A$2:$MC$200,MATCH(1,('GMW - Baseline'!$MC$2:$MC$200=H$3)*('GMW - Baseline'!$MB$2:$MB$200=H$4),0),$E9-1973)} -> 32.9513 | I9: {=INDEX('GMW - Baseline'!$A$2:$MC$200,MATCH(1,('GMW - Baseline'!$MC$2:$MC$200=I$3)*('GMW - Baseline'!$MB$2:$MB$200=I$4),0),$E9-1973)} -> 16.0303 | J9: {=INDEX('GMW - Baseline'!$A$2:$MC$200,MATCH(1,('GMW - Baseline'!$MC$2:$MC$200=J$3)*('GMW - Baseline'!$MB$2:$MB$200=J$4),0),$E9-1973)} -> #N/A | K9: {=INDEX('GMW - Baseline'!$A$2:$MC$200,MATCH(1,('GMW - Baseline'!$MC$2:$MC$200=K$3)*('GMW - Baseline'!$MB$2:$MB$200=K$4),0),$E9-1973)} -> #N/A | L9: {=INDEX('GMW - Baseline'!$A$2:$MC$200,MATCH(1,('GMW - Baseline'!$MC$2:$MC$200=L$3)*('GMW - Baseline'!$MB$2:$MB$200=L$4),0),$E9-1973)} -> #N/A | M9: {=INDEX('GMW - Baseline'!$A$2:$MC$200,MATCH(1,('GMW - Baseline'!$MC$2:$MC$200=M$3)*('GMW - Baseline'!$MB$2:$MB$200=M$4),0),$E9-1973)} -> #N/A | ... T9: {=INDEX('GMW - Baseline'!$A$2:$MC$200,MATCH(1,('GMW - Baseline'!$MC$2:$MC$200=T$3)*('GMW - Baseline'!$MB$2:$MB$200=T$4),0),$E9-1973)} -> #N/A
B10: 1980 | C10: 1980 | E10: =+E9+1 -> 1983 | F10: {=INDEX('GMW - Baseline'!$A$2:$MC$200,MATCH(1,('GMW - Baseline'!$MC$2:$MC$200=F$3)*('GMW - Baseline'!$MB$2:$MB$200=F$4),0),$E10-1973)} -> 281496 | G10: {=INDEX('GMW - Baseline'!$A$2:$MC$200,MATCH(1,('GMW - Baseline'!$MC$2:$MC$200=G$3)*('GMW - Baseline'!$MB$2:$MB$200=G$4),0),$E10-1973)} -> 148523 | H10: {=INDEX('GMW - Baseline'!$A$2:$MC$200,MATCH(1,('GMW - Baseline'!$MC$2:$MC$200=H$3)*('GMW - Baseline'!$MB$2:$MB$200=H$4),0),$E10-1973)} -> 33.55088 | I10: {=INDEX('GMW - Baseline'!$A$2:$MC$200,MATCH(1,('GMW - Baseline'!$MC$2:$MC$200=I$3)*('GMW - Baseline'!$MB$2:$MB$200=I$4),0),$E10-1973)} -> 15.18182 | J10: {=INDEX('GMW - Baseline'!$A$2:$MC$200,MATCH(1,('GMW - Baseline'!$MC$2:$MC$200=J$3)*('GMW - Baseline'!$MB$2:$MB$200=J$4),0),$E10-1973)} -> #N/A | K10: {=INDEX('GMW - Baseline'!$A$2:$MC$200,MATCH(1,('GMW - Baseline'!$MC$2:$MC$200=K$3)*('GMW - Baseline'!$MB$2:$MB$200=K$4),0),$E10-1973)} -> #N/A | L10: {=INDEX('GMW - Baseline'!$A$2:$MC$200,MATCH(1,('GMW - Baseline'!$MC$2:$MC$200=L$3)*('GMW - Baseline'!$MB$2:$MB$200=L$4),0),$E10-1973)} -> #N/A | M10: {=INDEX('GMW - Baseline'!$A$2:$MC$200,MATCH(1,('GMW - Baseline'!$MC$2:$MC$200=M$3)*('GMW - Baseline'!$MB$2:$MB$200=M$4),0),$E10-1973)} -> #N/A | ... T10: {=INDEX('GMW - Baseline'!$A$2:$MC$200,MATCH(1,('GMW - Baseline'!$MC$2:$MC$200=T$3)*('GMW - Baseline'!$MB$2:$MB$200=T$4),0),$E10-1973)} -> #N/A
A11: 1981 | B11: =+B7+1 -> 1981 | C11: 1980 | D11: 1980 | E11: =+E10+1 -> 1984 | F11: {=INDEX('GMW - Baseline'!$A$2:$MC$200,MATCH(1,('GMW - Baseline'!$MC$2:$MC$200=F$3)*('GMW - Baseline'!$MB$2:$MB$200=F$4),0),$E11-1973)} -> 281257 | G11: {=INDEX('GMW - Baseline'!$A$2:$MC$200,MATCH(1,('GMW - Baseline'!$MC$2:$MC$200=G$3)*('GMW - Baseline'!$MB$2:$MB$200=G$4),0),$E11-1973)} -> 151234 | H11: {=INDEX('GMW - Baseline'!$A$2:$MC$200,MATCH(1,('GMW - Baseline'!$MC$2:$MC$200=H$3)*('GMW - Baseline'!$MB$2:$MB$200=H$4),0),$E11-1973)} -> 34.3851 | I11: {=INDEX('GMW - Baseline'!$A$2:$MC$200,MATCH(1,('GMW - Baseline'!$MC$2:$MC$200=I$3)*('GMW - Baseline'!$MB$2:$MB$200=I$4),0),$E11-1973)} -> 13.53125 | J11: {=INDEX('GMW - Baseline'!$A$2:$MC$200,MATCH(1,('GMW - Baseline'!$MC$2:$MC$200=J$3)*('GMW - Baseline'!$MB$2:$MB$200=J$4),0),$E11-1973)} -> #N/A | K11: {=INDEX('GMW - Baseline'!$A$2:$MC$200,MATCH(1,('GMW - Baseline'!$MC$2:$MC$200=K$3)*('GMW - Baseline'!$MB$2:$MB$200=K$4),0),$E11-1973)} -> #N/A | L11: {=INDEX('GMW - Baseline'!$A$2:$MC$200,MATCH(1,('GMW - Baseline'!$MC$2:$MC$200=L$3)*('GMW - Baseline'!$MB$2:$MB$200=L$4),0),$E11-1973)} -> #N/A | M11: {=INDEX('GMW - Baseline'!$A$2:$MC$200,MATCH(1,('GMW - Baseline'!$MC$2:$MC$200=M$3)*('GMW - Baseline'!$MB$2:$MB$200=M$4),0),$E11-1973)} -> #N/A | ... T11: {=INDEX('GMW - Baseline'!$A$2:$MC$200,MATCH(1,('GMW - Baseline'!$MC$2:$MC$200=T$3)*('GMW - Baseline'!$MB$2:$MB$200=T$4),0),$E11-1973)} -> #N/A
B12: =+B8+1 -> 1981 | C12: =+C8+1 -> 1981 | E12: =+E11+1 -> 1985 | F12: {=INDEX('GMW - Baseline'!$A$2:$MC$200,MATCH(1,('GMW - Baseline'!$MC$2:$MC$200=F$3)*('GMW - Baseline'!$MB$2:$MB$200=F$4),0),$E12-1973)} -> 282155 | G12: {=INDEX('GMW - Baseline'!$A$2:$MC$200,MATCH(1,('GMW - Baseline'!$MC$2:$MC$200=G$3)*('GMW - Baseline'!$MB$2:$MB$200=G$4),0),$E12-1973)} -> 151164 | H12: {=INDEX('GMW - Baseline'!$A$2:$MC$200,MATCH(1,('GMW - Baseline'!$MC$2:$MC$200=H$3)*('GMW - Baseline'!$MB$2:$MB$200=H$4),0),$E12-1973)} -> 36.07959 | I12: {=INDEX('GMW - Baseline'!$A$2:$MC$200,MATCH(1,('GMW - Baseline'!$MC$2:$MC$200=I$3)*('GMW - Baseline'!$MB$2:$MB$200=I$4),0),$E12-1973)} -> 12 | J12: {=INDEX('GMW - Baseline'!$A$2:$MC$200,MATCH(1,('GMW - Baseline'!$MC$2:$MC$200=J$3)*('GMW - Baseline'!$MB$2:$MB$200=J$4),0),$E12-1973)} -> #N/A | K12: {=INDEX('GMW - Baseline'!$A$2:$MC$200,MATCH(1,('GMW - Baseline'!$MC$2:$MC$200=K$3)*('GMW - Baseline'!$MB$2:$MB$200=K$4),0),$E12-1973)} -> #N/A | L12: {=INDEX('GMW - Baseline'!$A$2:$MC$200,MATCH(1,('GMW - Baseline'!$MC$2:$MC$200=L$3)*('GMW - Baseline'!$MB$2:$MB$200=L$4),0),$E12-1973)} -> #N/A | M12: {=INDEX('GMW - Baseline'!$A$2:$MC$200,MATCH(1,('GMW - Baseline'!$MC$2:$MC$200=M$3)*('GMW - Baseline'!$MB$2:$MB$200=M$4),0),$E12-1973)} -> #N/A | ... T12: {=INDEX('GMW - Baseline'!$A$2:$MC$200,MATCH(1,('GMW - Baseline'!$MC$2:$MC$200=T$3)*('GMW - Baseline'!$MB$2:$MB$200=T$4),0),$E12-1973)} -> #N/A
B13: =+B9+1 -> 1981 | C13: =+C9+1 -> 1981 | E13: =+E12+1 -> 1986 | F13: {=INDEX('GMW - Baseline'!$A$2:$MC$200,MATCH(1,('GMW - Baseline'!$MC$2:$MC$200=F$3)*('GMW - Baseline'!$MB$2:$MB$200=F$4),0),$E13-1973)} -> 285437 | G13: {=INDEX('GMW - Baseline'!$A$2:$MC$200,MATCH(1,('GMW - Baseline'!$MC$2:$MC$200=G$3)*('GMW - Baseline'!$MB$2:$MB$200=G$4),0),$E13-1973)} -> 151269 | H13: {=INDEX('GMW - Baseline'!$A$2:$MC$200,MATCH(1,('GMW - Baseline'!$MC$2:$MC$200=H$3)*('GMW - Baseline'!$MB$2:$MB$200=H$4),0),$E13-1973)} -> 36.73131 | I13: {=INDEX('GMW - Baseline'!$A$2:$MC$200,MATCH(1,('GMW - Baseline'!$MC$2:$MC$200=I$3)*('GMW - Baseline'!$MB$2:$MB$200=I$4),0),$E13-1973)} -> 12.51989 | J13: {=INDEX('GMW - Baseline'!$A$2:$MC$200,MATCH(1,('GMW - Baseline'!$MC$2:$MC$200=J$3)*('GMW - Baseline'!$MB$2:$MB$200=J$4),0),$E13-1973)} -> #N/A | K13: {=INDEX('GMW - Baseline'!$A$2:$MC$200,MATCH(1,('GMW - Baseline'!$MC$2:$MC$200=K$3)*('GMW - Baseline'!$MB$2:$MB$200=K$4),0),$E13-1973)} -> #N/A | L13: {=INDEX('GMW - Baseline'!$A$2:$MC$200,MATCH(1,('GMW - Baseline'!$MC$2:$MC$200=L$3)*('GMW - Baseline'!$MB$2:$MB$200=L$4),0),$E13-1973)} -> #N/A | M13: {=INDEX('GMW - Baseline'!$A$2:$MC$200,MATCH(1,('GMW - Baseline'!$MC$2:$MC$200=M$3)*('GMW - Baseline'!$MB$2:$MB$200=M$4),0),$E13-1973)} -> #N/A | ... T13: {=INDEX('GMW - Baseline'!$A$2:$MC$200,MATCH(1,('GMW - Baseline'!$MC$2:$MC$200=T$3)*('GMW - Baseline'!$MB$2:$MB$200=T$4),0),$E13-1973)} -> #N/A
B14: =+B10+1 -> 1981 | C14: =+C10+1 -> 1981 | E14: =+E13+1 -> 1987 | F14: {=INDEX('GMW - Baseline'!$A$2:$MC$200,MATCH(1,('GMW - Baseline'!$MC$2:$MC$200=F$3)*('GMW - Baseline'!$MB$2:$MB$200=F$4),0),$E14-1973)} -> 285814 | G14: {=INDEX('GMW - Baseline'!$A$2:$MC$200,MATCH(1,('GMW - Baseline'!$MC$2:$MC$200=G$3)*('GMW - Baseline'!$MB$2:$MB$200=G$4),0),$E14-1973)} -> 150853 | H14: {=INDEX('GMW - Baseline'!$A$2:$MC$200,MATCH(1,('GMW - Baseline'!$MC$2:$MC$200=H$3)*('GMW - Baseline'!$MB$2:$MB$200=H$4),0),$E14-1973)} -> 37.43518 | I14: {=INDEX('GMW - Baseline'!$A$2:$MC$200,MATCH(1,('GMW - Baseline'!$MC$2:$MC$200=I$3)*('GMW - Baseline'!$MB$2:$MB$200=I$4),0),$E14-1973)} -> 14.60417 | J14: {=INDEX('GMW - Baseline'!$A$2:$MC$200,MATCH(1,('GMW - Baseline'!$MC$2:$MC$200=J$3)*('GMW - Baseline'!$MB$2:$MB$200=J$4),0),$E14-1973)} -> #N/A | K14: {=INDEX('GMW - Baseline'!$A$2:$MC$200,MATCH(1,('GMW - Baseline'!$MC$2:$MC$200=K$3)*('GMW - Baseline'!$MB$2:$MB$200=K$4),0),$E14-1973)} -> #N/A | L14: {=INDEX('GMW - Baseline'!$A$2:$MC$200,MATCH(1,('GMW - Baseline'!$MC$2:$MC$200=L$3)*('GMW - Baseline'!$MB$2:$MB$200=L$4),0),$E14-1973)} -> #N/A | M14: {=INDEX('GMW - Baseline'!$A$2:$MC$200,MATCH(1,('GMW - Baseline'!$MC$2:$MC$200=M$3)*('GMW - Baseline'!$MB$2:$MB$200=M$4),0),$E14-1973)} -> #N/A | ... T14: {=INDEX('GMW - Baseline'!$A$2:$MC$200,MATCH(1,('GMW - Baseline'!$MC$2:$MC$200=T$3)*('GMW - Baseline'!$MB$2:$MB$200=T$4),0),$E14-1973)} -> #N/A
A15: 1982 | B15: =+B11+1 -> 1982 | C15: =+C11+1 -> 1981 | D15: =+D11+1 -> 1981 | E15: =+E14+1 -> 1988 | F15: {=INDEX('GMW - Baseline'!$A$2:$MC$200,MATCH(1,('GMW - Baseline'!$MC$2:$MC$200=F$3)*('GMW - Baseline'!$MB$2:$MB$200=F$4),0),$E15-1973)} -> 286275 | G15: {=INDEX('GMW - Baseline'!$A$2:$MC$200,MATCH(1,('GMW - Baseline'!$MC$2:$MC$200=G$3)*('GMW - Baseline'!$MB$2:$MB$200=G$4),0),$E15-1973)} -> 151361 | H15: {=INDEX('GMW - Baseline'!$A$2:$MC$200,MATCH(1,('GMW - Baseline'!$MC$2:$MC$200=H$3)*('GMW - Baseline'!$MB$2:$MB$200=H$4),0),$E15-1973)} -> 37.87835 | I15: {=INDEX('GMW - Baseline'!$A$2:$MC$200,MATCH(1,('GMW - Baseline'!$MC$2:$MC$200=I$3)*('GMW - Baseline'!$MB$2:$MB$200=I$4),0),$E15-1973)} -> 13.78516 | J15: {=INDEX('GMW - Baseline'!$A$2:$MC$200,MATCH(1,('GMW - Baseline'!$MC$2:$MC$200=J$3)*('GMW - Baseline'!$MB$2:$MB$200=J$4),0),$E15-1973)} -> #N/A | K15: {=INDEX('GMW - Baseline'!$A$2:$MC$200,MATCH(1,('GMW - Baseline'!$MC$2:$MC$200=K$3)*('GMW - Baseline'!$MB$2:$MB$200=K$4),0),$E15-1973)} -> #N/A | L15: {=INDEX('GMW - Baseline'!$A$2:$MC$200,MATCH(1,('GMW - Baseline'!$MC$2:$MC$200=L$3)*('GMW - Baseline'!$MB$2:$MB$200=L$4),0),$E15-1973)} -> #N/A | M15: {=INDEX('GMW - Baseline'!$A$2:$MC$200,MATCH(1,('GMW - Baseline'!$MC$2:$MC$200=M$3)*('GMW - Baseline'!$MB$2:$MB$200=M$4),0),$E15-1973)} -> #N/A | ... T15: {=INDEX('GMW - Baseline'!$A$2:$MC$200,MATCH(1,('GMW - Baseline'!$MC$2:$MC$200=T$3)*('GMW - Baseline'!$MB$2:$MB$200=T$4),0),$E15-1973)} -> #N/A
B16: =+B12+1 -> 1982 | C16: =+C12+1 -> 1982 | E16: =+E15+1 -> 1989 | F16: {=INDEX('GMW - Baseline'!$A$2:$MC$200,MATCH(1,('GMW - Baseline'!$MC$2:$MC$200=F$3)*('GMW - Baseline'!$MB$2:$MB$200=F$4),0),$E16-1973)} -> 289232 | G16: {=INDEX('GMW - Baseline'!$A$2:$MC$200,MATCH(1,('GMW - Baseline'!$MC$2:$MC$200=G$3)*('GMW - Baseline'!$MB$2:$MB$200=G$4),0),$E16-1973)} -> 151251 | H16: {=INDEX('GMW - Baseline'!$A$2:$MC$200,MATCH(1,('GMW - Baseline'!$MC$2:$MC$200=H$3)*('GMW - Baseline'!$MB$2:$MB$200=H$4),0),$E16-1973)} -> 39.1818 | I16: {=INDEX('GMW - Baseline'!$A$2:$MC$200,MATCH(1,('GMW - Baseline'!$MC$2:$MC$200=I$3)*('GMW - Baseline'!$MB$2:$MB$200=I$4),0),$E16-1973)} -> 13.01346 | J16: {=INDEX('GMW - Baseline'!$A$2:$MC$200,MATCH(1,('GMW - Baseline'!$MC$2:$MC$200=J$3)*('GMW - Baseline'!$MB$2:$MB$200=J$4),0),$E16-1973)} -> #N/A | K16: {=INDEX('GMW - Baseline'!$A$2:$MC$200,MATCH(1,('GMW - Baseline'!$MC$2:$MC$200=K$3)*('GMW - Baseline'!$MB$2:$MB$200=K$4),0),$E16-1973)} -> #N/A | L16: {=INDEX('GMW - Baseline'!$A$2:$MC$200,MATCH(1,('GMW - Baseline'!$MC$2:$MC$200=L$3)*('GMW - Baseline'!$MB$2:$MB$200=L$4),0),$E16-1973)} -> #N/A | M16: {=INDEX('GMW - Baseline'!$A$2:$MC$200,MATCH(1,('GMW - Baseline'!$MC$2:$MC$200=M$3)*('GMW - Baseline'!$MB$2:$MB$200=M$4),0),$E16-1973)} -> #N/A | ... T16: {=INDEX('GMW - Baseline'!$A$2:$MC$200,MATCH(1,('GMW - Baseline'!$MC$2:$MC$200=T$3)*('GMW - Baseline'!$MB$2:$MB$200=T$4),0),$E16-1973)} -> #N/A
B17: =+B13+1 -> 1982 | C17: =+C13+1 -> 1982 | E17: =+E16+1 -> 1990 | F17: {=INDEX('GMW - Baseline'!$A$2:$MC$200,MATCH(1,('GMW - Baseline'!$MC$2:$MC$200=F$3)*('GMW - Baseline'!$MB$2:$MB$200=F$4),0),$E17-1973)} -> 289852 | G17: {=INDEX('GMW - Baseline'!$A$2:$MC$200,MATCH(1,('GMW - Baseline'!$MC$2:$MC$200=G$3)*('GMW - Baseline'!$MB$2:$MB$200=G$4),0),$E17-1973)} -> 153796 | H17: {=INDEX('GMW - Baseline'!$A$2:$MC$200,MATCH(1,('GMW - Baseline'!$MC$2:$MC$200=H$3)*('GMW - Baseline'!$MB$2:$MB$200=H$4),0),$E17-1973)} -> 39.41642 | I17: {=INDEX('GMW - Baseline'!$A$2:$MC$200,MATCH(1,('GMW - Baseline'!$MC$2:$MC$200=I$3)*('GMW - Baseline'!$MB$2:$MB$200=I$4),0),$E17-1973)} -> 11.3428 | J17: {=INDEX('GMW - Baseline'!$A$2:$MC$200,MATCH(1,('GMW - Baseline'!$MC$2:$MC$200=J$3)*('GMW - Baseline'!$MB$2:$MB$200=J$4),0),$E17-1973)} -> #N/A | K17: {=INDEX('GMW - Baseline'!$A$2:$MC$200,MATCH(1,('GMW - Baseline'!$MC$2:$MC$200=K$3)*('GMW - Baseline'!$MB$2:$MB$200=K$4),0),$E17-1973)} -> #N/A | L17: {=INDEX('GMW - Baseline'!$A$2:$MC$200,MATCH(1,('GMW - Baseline'!$MC$2:$MC$200=L$3)*('GMW - Baseline'!$MB$2:$MB$200=L$4),0),$E17-1973)} -> #N/A | M17: {=INDEX('GMW - Baseline'!$A$2:$MC$200,MATCH(1,('GMW - Baseline'!$MC$2:$MC$200=M$3)*('GMW - Baseline'!$MB$2:$MB$200=M$4),0),$E17-1973)} -> #N/A | ... T17: {=INDEX('GMW - Baseline'!$A$2:$MC$200,MATCH(1,('GMW - Baseline'!$MC$2:$MC$200=T$3)*('GMW - Baseline'!$MB$2:$MB$200=T$4),0),$E17-1973)} -> #N/A
B18: =+B14+1 -> 1982 | C18: =+C14+1 -> 1982 | E18: =+E17+1 -> 1991 | F18: {=INDEX('GMW - Baseline'!$A$2:$MC$200,MATCH(1,('GMW - Baseline'!$MC$2:$MC$200=F$3)*('GMW - Baseline'!$MB$2:$MB$200=F$4),0),$E18-1973)} -> 291832 | G18: {=INDEX('GMW - Baseline'!$A$2:$MC$200,MATCH(1,('GMW - Baseline'!$MC$2:$MC$200=G$3)*('GMW - Baseline'!$MB$2:$MB$200=G$4),0),$E18-1973)} -> 155106 | H18: {=INDEX('GMW - Baseline'!$A$2:$MC$200,MATCH(1,('GMW - Baseline'!$MC$2:$MC$200=H$3)*('GMW - Baseline'!$MB$2:$MB$200=H$4),0),$E18-1973)} -> 39.88567 | I18: {=INDEX('GMW - Baseline'!$A$2:$MC$200,MATCH(1,('GMW - Baseline'!$MC$2:$MC$200=I$3)*('GMW - Baseline'!$MB$2:$MB$200=I$4),0),$E18-1973)} -> 9.685606 | J18: {=INDEX('GMW - Baseline'!$A$2:$MC$200,MATCH(1,('GMW - Baseline'!$MC$2:$MC$200=J$3)*('GMW - Baseline'!$MB$2:$MB$200=J$4),0),$E18-1973)} -> #N/A | K18: {=INDEX('GMW - Baseline'!$A$2:$MC$200,MATCH(1,('GMW - Baseline'!$MC$2:$MC$200=K$3)*('GMW - Baseline'!$MB$2:$MB$200=K$4),0),$E18-1973)} -> #N/A | L18: {=INDEX('GMW - Baseline'!$A$2:$MC$200,MATCH(1,('GMW - Baseline'!$MC$2:$MC$200=L$3)*('GMW - Baseline'!$MB$2:$MB$200=L$4),0),$E18-1973)} -> #N/A | M18: {=INDEX('GMW - Baseline'!$A$2:$MC$200,MATCH(1,('GMW - Baseline'!$MC$2:$MC$200=M$3)*('GMW - Baseline'!$MB$2:$MB$200=M$4),0),$E18-1973)} -> #N/A | ... T18: {=INDEX('GMW - Baseline'!$A$2:$MC$200,MATCH(1,('GMW - Baseline'!$MC$2:$MC$200=T$3)*('GMW - Baseline'!$MB$2:$MB$200=T$4),0),$E18-1973)} -> #N/A
A19: 1983 | B19: =+B15+1 -> 1983 | C19: =+C15+1 -> 1982 | D19: =+D15+1 -> 1982 | E19: =+E18+1 -> 1992 | F19: {=INDEX('GMW - Baseline'!$A$2:$MC$200,MATCH(1,('GMW - Baseline'!$MC$2:$MC$200=F$3)*('GMW - Baseline'!$MB$2:$MB$200=F$4),0),$E19-1973)} -> 297563 | G19: {=INDEX('GMW - Baseline'!$A$2:$MC$200,MATCH(1,('GMW - Baseline'!$MC$2:$MC$200=G$3)*('GMW - Baseline'!$MB$2:$MB$200=G$4),0),$E19-1973)} -> 157443 | H19: {=INDEX('GMW - Baseline'!$A$2:$MC$200,MATCH(1,('GMW - Baseline'!$MC$2:$MC$200=H$3)*('GMW - Baseline'!$MB$2:$MB$200=H$4),0),$E19-1973)} -> 40.17243 | I19: {=INDEX('GMW - Baseline'!$A$2:$MC$200,MATCH(1,('GMW - Baseline'!$MC$2:$MC$200=I$3)*('GMW - Baseline'!$MB$2:$MB$200=I$4),0),$E19-1973)} -> 10.80176 | J19: {=INDEX('GMW - Baseline'!$A$2:$MC$200,MATCH(1,('GMW - Baseline'!$MC$2:$MC$200=J$3)*('GMW - Baseline'!$MB$2:$MB$200=J$4),0),$E19-1973)} -> #N/A | K19: {=INDEX('GMW - Baseline'!$A$2:$MC$200,MATCH(1,('GMW - Baseline'!$MC$2:$MC$200=K$3)*('GMW - Baseline'!$MB$2:$MB$200=K$4),0),$E19-1973)} -> #N/A | L19: {=INDEX('GMW - Baseline'!$A$2:$MC$200,MATCH(1,('GMW - Baseline'!$MC$2:$MC$200=L$3)*('GMW - Baseline'!$MB$2:$MB$200=L$4),0),$E19-1973)} -> #N/A | M19: {=INDEX('GMW - Baseline'!$A$2:$MC$200,MATCH(1,('GMW - Baseline'!$MC$2:$MC$200=M$3)*('GMW - Baseline'!$MB$2:$MB$200=M$4),0),$E19-1973)} -> #N/A | ... T19: {=INDEX('GMW - Baseline'!$A$2:$MC$200,MATCH(1,('GMW - Baseline'!$MC$2:$MC$200=T$3)*('GMW - Baseline'!$MB$2:$MB$200=T$4),0),$E19-1973)} -> #N/A
B20: =+B16+1 -> 1983 | C20: =+C16+1 -> 1983 | E20: =+E19+1 -> 1993 | F20: {=INDEX('GMW - Baseline'!$A$2:$MC$200,MATCH(1,('GMW - Baseline'!$MC$2:$MC$200=F$3)*('GMW - Baseline'!$MB$2:$MB$200=F$4),0),$E20-1973)} -> 299623 | G20: {=INDEX('GMW - Baseline'!$A$2:$MC$200,MATCH(1,('GMW - Baseline'!$MC$2:$MC$200=G$3)*('GMW - Baseline'!$MB$2:$MB$200=G$4),0),$E20-1973)} -> 158445 | H20: {=INDEX('GMW - Baseline'!$A$2:$MC$200,MATCH(1,('GMW - Baseline'!$MC$2:$MC$200=H$3)*('GMW - Baseline'!$MB$2:$MB$200=H$4),0),$E20-1973)} -> 40.85022 | I20: {=INDEX('GMW - Baseline'!$A$2:$MC$200,MATCH(1,('GMW - Baseline'!$MC$2:$MC$200=I$3)*('GMW - Baseline'!$MB$2:$MB$200=I$4),0),$E20-1973)} -> 10.02404 | J20: {=INDEX('GMW - Baseline'!$A$2:$MC$200,MATCH(1,('GMW - Baseline'!$MC$2:$MC$200=J$3)*('GMW - Baseline'!$MB$2:$MB$200=J$4),0),$E20-1973)} -> #N/A | K20: {=INDEX('GMW - Baseline'!$A$2:$MC$200,MATCH(1,('GMW - Baseline'!$MC$2:$MC$200=K$3)*('GMW - Baseline'!$MB$2:$MB$200=K$4),0),$E20-1973)} -> #N/A | L20: {=INDEX('GMW - Baseline'!$A$2:$MC$200,MATCH(1,('GMW - Baseline'!$MC$2:$MC$200=L$3)*('GMW - Baseline'!$MB$2:$MB$200=L$4),0),$E20-1973)} -> #N/A | M20: {=INDEX('GMW - Baseline'!$A$2:$MC$200,MATCH(1,('GMW - Baseline'!$MC$2:$MC$200=M$3)*('GMW - Baseline'!$MB$2:$MB$200=M$4),0),$E20-1973)} -> #N/A | ... T20: {=INDEX('GMW - Baseline'!$A$2:$MC$200,MATCH(1,('GMW - Baseline'!$MC$2:$MC$200=T$3)*('GMW - Baseline'!$MB$2:$MB$200=T$4),0),$E20-1973)} -> #N/A
B21: =+B17+1 -> 1983 | C21: =+C17+1 -> 1983 | E21: =+E20+1 -> 1994 | F21: {=INDEX('GMW - Baseline'!$A$2:$MC$200,MATCH(1,('GMW - Baseline'!$MC$2:$MC$200=F$3)*('GMW - Baseline'!$MB$2:$MB$200=F$4),0),$E21-1973)} -> 303085 | G21: {=INDEX('GMW - Baseline'!$A$2:$MC$200,MATCH(1,('GMW - Baseline'!$MC$2:$MC$200=G$3)*('GMW - Baseline'!$MB$2:$MB$200=G$4),0),$E21-1973)} -> 161027 | H21: {=INDEX('GMW - Baseline'!$A$2:$MC$200,MATCH(1,('GMW - Baseline'!$MC$2:$MC$200=H$3)*('GMW - Baseline'!$MB$2:$MB$200=H$4),0),$E21-1973)} -> 41.2934 | I21: {=INDEX('GMW - Baseline'!$A$2:$MC$200,MATCH(1,('GMW - Baseline'!$MC$2:$MC$200=I$3)*('GMW - Baseline'!$MB$2:$MB$200=I$4),0),$E21-1973)} -> 9.560606 | J21: {=INDEX('GMW - Baseline'!$A$2:$MC$200,MATCH(1,('GMW - Baseline'!$MC$2:$MC$200=J$3)*('GMW - Baseline'!$MB$2:$MB$200=J$4),0),$E21-1973)} -> #N/A | K21: {=INDEX('GMW - Baseline'!$A$2:$MC$200,MATCH(1,('GMW - Baseline'!$MC$2:$MC$200=K$3)*('GMW - Baseline'!$MB$2:$MB$200=K$4),0),$E21-1973)} -> #N/A | L21: {=INDEX('GMW - Baseline'!$A$2:$MC$200,MATCH(1,('GMW - Baseline'!$MC$2:$MC$200=L$3)*('GMW - Baseline'!$MB$2:$MB$200=L$4),0),$E21-1973)} -> #N/A | M21: {=INDEX('GMW - Baseline'!$A$2:$MC$200,MATCH(1,('GMW - Baseline'!$MC$2:$MC$200=M$3)*('GMW - Baseline'!$MB$2:$MB$200=M$4),0),$E21-1973)} -> #N/A | ... T21: {=INDEX('GMW - Baseline'!$A$2:$MC$200,MATCH(1,('GMW - Baseline'!$MC$2:$MC$200=T$3)*('GMW - Baseline'!$MB$2:$MB$200=T$4),0),$E21-1973)} -> #N/A
B22: =+B18+1 -> 1983 | C22: =+C18+1 -> 1983 | E22: =+E21+1 -> 1995 | F22: {=INDEX('GMW - Baseline'!$A$2:$MC$200,MATCH(1,('GMW - Baseline'!$MC$2:$MC$200=F$3)*('GMW - Baseline'!$MB$2:$MB$200=F$4),0),$E22-1973)} -> 305361 | G22: {=INDEX('GMW - Baseline'!$A$2:$MC$200,MATCH(1,('GMW - Baseline'!$MC$2:$MC$200=G$3)*('GMW - Baseline'!$MB$2:$MB$200=G$4),0),$E22-1973)} -> 161090 | H22: {=INDEX('GMW - Baseline'!$A$2:$MC$200,MATCH(1,('GMW - Baseline'!$MC$2:$MC$200=H$3)*('GMW - Baseline'!$MB$2:$MB$200=H$4),0),$E22-1973)} -> 41.76264 | I22: {=INDEX('GMW - Baseline'!$A$2:$MC$200,MATCH(1,('GMW - Baseline'!$MC$2:$MC$200=I$3)*('GMW - Baseline'!$MB$2:$MB$200=I$4),0),$E22-1973)} -> 9.0625 | J22: {=INDEX('GMW - Baseline'!$A$2:$MC$200,MATCH(1,('GMW - Baseline'!$MC$2:$MC$200=J$3)*('GMW - Baseline'!$MB$2:$MB$200=J$4),0),$E22-1973)} -> #N/A | K22: {=INDEX('GMW - Baseline'!$A$2:$MC$200,MATCH(1,('GMW - Baseline'!$MC$2:$MC$200=K$3)*('GMW - Baseline'!$MB$2:$MB$200=K$4),0),$E22-1973)} -> #N/A | L22: {=INDEX('GMW - Baseline'!$A$2:$MC$200,MATCH(1,('GMW - Baseline'!$MC$2:$MC$200=L$3)*('GMW - Baseline'!$MB$2:$MB$200=L$4),0),$E22-1973)} -> #N/A | M22: {=INDEX('GMW - Baseline'!$A$2:$MC$200,MATCH(1,('GMW - Baseline'!$MC$2:$MC$200=M$3)*('GMW - Baseline'!$MB$2:$MB$200=M$4),0),$E22-1973)} -> #N/A | ... T22: {=INDEX('GMW - Baseline'!$A$2:$MC$200,MATCH(1,('GMW - Baseline'!$MC$2:$MC$200=T$3)*('GMW - Baseline'!$MB$2:$MB$200=T$4),0),$E22-1973)} -> #N/A
A23: 1984 | B23: =+B19+1 -> 1984 | C23: =+C19+1 -> 1983 | D23: =+D19+1 -> 1983 | E23: =+E22+1 -> 1996 | F23: {=INDEX('GMW - Baseline'!$A$2:$MC$200,MATCH(1,('GMW - Baseline'!$MC$2:$MC$200=F$3)*('GMW - Baseline'!$MB$2:$MB$200=F$4),0),$E23-1973)} -> 307964 | G23: {=INDEX('GMW - Baseline'!$A$2:$MC$200,MATCH(1,('GMW - Baseline'!$MC$2:$MC$200=G$3)*('GMW - Baseline'!$MB$2:$MB$200=G$4),0),$E23-1973)} -> 162074 | H23: {=INDEX('GMW - Baseline'!$A$2:$MC$200,MATCH(1,('GMW - Baseline'!$MC$2:$MC$200=H$3)*('GMW - Baseline'!$MB$2:$MB$200=H$4),0),$E23-1973)} -> 41.86692 | I23: {=INDEX('GMW - Baseline'!$A$2:$MC$200,MATCH(1,('GMW - Baseline'!$MC$2:$MC$200=I$3)*('GMW - Baseline'!$MB$2:$MB$200=I$4),0),$E23-1973)} -> 8.943269 | J23: {=INDEX('GMW - Baseline'!$A$2:$MC$200,MATCH(1,('GMW - Baseline'!$MC$2:$MC$200=J$3)*('GMW - Baseline'!$MB$2:$MB$200=J$4),0),$E23-1973)} -> #N/A | K23: {=INDEX('GMW - Baseline'!$A$2:$MC$200,MATCH(1,('GMW - Baseline'!$MC$2:$MC$200=K$3)*('GMW - Baseline'!$MB$2:$MB$200=K$4),0),$E23-1973)} -> #N/A | L23: {=INDEX('GMW - Baseline'!$A$2:$MC$200,MATCH(1,('GMW - Baseline'!$MC$2:$MC$200=L$3)*('GMW - Baseline'!$MB$2:$MB$200=L$4),0),$E23-1973)} -> #N/A | M23: {=INDEX('GMW - Baseline'!$A$2:$MC$200,MATCH(1,('GMW - Baseline'!$MC$2:$MC$200=M$3)*('GMW - Baseline'!$MB$2:$MB$200=M$4),0),$E23-1973)} -> #N/A | ... T23: {=INDEX('GMW - Baseline'!$A$2:$MC$200,MATCH(1,('GMW - Baseline'!$MC$2:$MC$200=T$3)*('GMW - Baseline'!$MB$2:$MB$200=T$4),0),$E23-1973)} -> #N/A
B24: =+B20+1 -> 1984 | C24: =+C20+1 -> 1984 | E24: =+E23+1 -> 1997 | F24: {=INDEX('GMW - Baseline'!$A$2:$MC$200,MATCH(1,('GMW - Baseline'!$MC$2:$MC$200=F$3)*('GMW - Baseline'!$MB$2:$MB$200=F$4),0),$E24-1973)} -> 304892 | G24: {=INDEX('GMW - Baseline'!$A$2:$MC$200,MATCH(1,('GMW - Baseline'!$MC$2:$MC$200=G$3)*('GMW - Baseline'!$MB$2:$MB$200=G$4),0),$E24-1973)} -> 163369 | H24: {=INDEX('GMW - Baseline'!$A$2:$MC$200,MATCH(1,('GMW - Baseline'!$MC$2:$MC$200=H$3)*('GMW - Baseline'!$MB$2:$MB$200=H$4),0),$E24-1973)} -> 42.77934 | I24: {=INDEX('GMW - Baseline'!$A$2:$MC$200,MATCH(1,('GMW - Baseline'!$MC$2:$MC$200=I$3)*('GMW - Baseline'!$MB$2:$MB$200=I$4),0),$E24-1973)} -> 8.844231 | J24: {=INDEX('GMW - Baseline'!$A$2:$MC$200,MATCH(1,('GMW - Baseline'!$MC$2:$MC$200=J$3)*('GMW - Baseline'!$MB$2:$MB$200=J$4),0),$E24-1973)} -> #N/A | K24: {=INDEX('GMW - Baseline'!$A$2:$MC$200,MATCH(1,('GMW - Baseline'!$MC$2:$MC$200=K$3)*('GMW - Baseline'!$MB$2:$MB$200=K$4),0),$E24-1973)} -> #N/A | L24: {=INDEX('GMW - Baseline'!$A$2:$MC$200,MATCH(1,('GMW - Baseline'!$MC$2:$MC$200=L$3)*('GMW - Baseline'!$MB$2:$MB$200=L$4),0),$E24-1973)} -> #N/A | M24: {=INDEX('GMW - Baseline'!$A$2:$MC$200,MATCH(1,('GMW - Baseline'!$MC$2:$MC$200=M$3)*('GMW - Baseline'!$MB$2:$MB$200=M$4),0),$E24-1973)} -> #N/A | ... T24: {=INDEX('GMW - Baseline'!$A$2:$MC$200,MATCH(1,('GMW - Baseline'!$MC$2:$MC$200=T$3)*('GMW - Baseline'!$MB$2:$MB$200=T$4),0),$E24-1973)} -> #N/A
B25: =+B21+1 -> 1984 | C25: =+C21+1 -> 1984 | E25: =+E24+1 -> 1998 | F25: {=INDEX('GMW - Baseline'!$A$2:$MC$200,MATCH(1,('GMW - Baseline'!$MC$2:$MC$200=F$3)*('GMW - Baseline'!$MB$2:$MB$200=F$4),0),$E25-1973)} -> 307122 | G25: {=INDEX('GMW - Baseline'!$A$2:$MC$200,MATCH(1,('GMW - Baseline'!$MC$2:$MC$200=G$3)*('GMW - Baseline'!$MB$2:$MB$200=G$4),0),$E25-1973)} -> 162507 | H25: {=INDEX('GMW - Baseline'!$A$2:$MC$200,MATCH(1,('GMW - Baseline'!$MC$2:$MC$200=H$3)*('GMW - Baseline'!$MB$2:$MB$200=H$4),0),$E25-1973)} -> 42.98789 | I25: {=INDEX('GMW - Baseline'!$A$2:$MC$200,MATCH(1,('GMW - Baseline'!$MC$2:$MC$200=I$3)*('GMW - Baseline'!$MB$2:$MB$200=I$4),0),$E25-1973)} -> 10.89615 | J25: {=INDEX('GMW - Baseline'!$A$2:$MC$200,MATCH(1,('GMW - Baseline'!$MC$2:$MC$200=J$3)*('GMW - Baseline'!$MB$2:$MB$200=J$4),0),$E25-1973)} -> #N/A | K25: {=INDEX('GMW - Baseline'!$A$2:$MC$200,MATCH(1,('GMW - Baseline'!$MC$2:$MC$200=K$3)*('GMW - Baseline'!$MB$2:$MB$200=K$4),0),$E25-1973)} -> #N/A | L25: {=INDEX('GMW - Baseline'!$A$2:$MC$200,MATCH(1,('GMW - Baseline'!$MC$2:$MC$200=L$3)*('GMW - Baseline'!$MB$2:$MB$200=L$4),0),$E25-1973)} -> #N/A | M25: {=INDEX('GMW - Baseline'!$A$2:$MC$200,MATCH(1,('GMW - Baseline'!$MC$2:$MC$200=M$3)*('GMW - Baseline'!$MB$2:$MB$200=M$4),0),$E25-1973)} -> #N/A | ... T25: {=INDEX('GMW - Baseline'!$A$2:$MC$200,MATCH(1,('GMW - Baseline'!$MC$2:$MC$200=T$3)*('GMW - Baseline'!$MB$2:$MB$200=T$4),0),$E25-1973)} -> #N/A
B26: =+B22+1 -> 1984 | C26: =+C22+1 -> 1984 | E26: =+E25+1 -> 1999 | F26: {=INDEX('GMW - Baseline'!$A$2:$MC$200,MATCH(1,('GMW - Baseline'!$MC$2:$MC$200=F$3)*('GMW - Baseline'!$MB$2:$MB$200=F$4),0),$E26-1973)} -> 312697 | G26: {=INDEX('GMW - Baseline'!$A$2:$MC$200,MATCH(1,('GMW - Baseline'!$MC$2:$MC$200=G$3)*('GMW - Baseline'!$MB$2:$MB$200=G$4),0),$E26-1973)} -> 165575 | H26: {=INDEX('GMW - Baseline'!$A$2:$MC$200,MATCH(1,('GMW - Baseline'!$MC$2:$MC$200=H$3)*('GMW - Baseline'!$MB$2:$MB$200=H$4),0),$E26-1973)} -> 43.43106 | I26: {=INDEX('GMW - Baseline'!$A$2:$MC$200,MATCH(1,('GMW - Baseline'!$MC$2:$MC$200=I$3)*('GMW - Baseline'!$MB$2:$MB$200=I$4),0),$E26-1973)} -> 9.969697 | J26: {=INDEX('GMW - Baseline'!$A$2:$MC$200,MATCH(1,('GMW - Baseline'!$MC$2:$MC$200=J$3)*('GMW - Baseline'!$MB$2:$MB$200=J$4),0),$E26-1973)} -> #N/A | K26: {=INDEX('GMW - Baseline'!$A$2:$MC$200,MATCH(1,('GMW - Baseline'!$MC$2:$MC$200=K$3)*('GMW - Baseline'!$MB$2:$MB$200=K$4),0),$E26-1973)} -> #N/A | L26: {=INDEX('GMW - Baseline'!$A$2:$MC$200,MATCH(1,('GMW - Baseline'!$MC$2:$MC$200=L$3)*('GMW - Baseline'!$MB$2:$MB$200=L$4),0),$E26-1973)} -> #N/A | M26: {=INDEX('GMW - Baseline'!$A$2:$MC$200,MATCH(1,('GMW - Baseline'!$MC$2:$MC$200=M$3)*('GMW - Baseline'!$MB$2:$MB$200=M$4),0),$E26-1973)} -> #N/A | ... T26: {=INDEX('GMW - Baseline'!$A$2:$MC$200,MATCH(1,('GMW - Baseline'!$MC$2:$MC$200=T$3)*('GMW - Baseline'!$MB$2:$MB$200=T$4),0),$E26-1973)} -> #N/A
A27: 1985 | B27: =+B23+1 -> 1985 | C27: =+C23+1 -> 1984 | D27: =+D23+1 -> 1984 | E27: =+E26+1 -> 2000 | F27: {=INDEX('GMW - Baseline'!$A$2:$MC$200,MATCH(1,('GMW - Baseline'!$MC$2:$MC$200=F$3)*('GMW - Baseline'!$MB$2:$MB$200=F$4),0),$E27-1973)} -> 315753 | G27: {=INDEX('GMW - Baseline'!$A$2:$MC$200,MATCH(1,('GMW - Baseline'!$MC$2:$MC$200=G$3)*('GMW - Baseline'!$MB$2:$MB$200=G$4),0),$E27-1973)} -> 169390 | H27: {=INDEX('GMW - Baseline'!$A$2:$MC$200,MATCH(1,('GMW - Baseline'!$MC$2:$MC$200=H$3)*('GMW - Baseline'!$MB$2:$MB$200=H$4),0),$E27-1973)} -> 43.87423 | I27: {=INDEX('GMW - Baseline'!$A$2:$MC$200,MATCH(1,('GMW - Baseline'!$MC$2:$MC$200=I$3)*('GMW - Baseline'!$MB$2:$MB$200=I$4),0),$E27-1973)} -> 12.86914 | J27: {=INDEX('GMW - Baseline'!$A$2:$MC$200,MATCH(1,('GMW - Baseline'!$MC$2:$MC$200=J$3)*('GMW - Baseline'!$MB$2:$MB$200=J$4),0),$E27-1973)} -> #N/A | K27: {=INDEX('GMW - Baseline'!$A$2:$MC$200,MATCH(1,('GMW - Baseline'!$MC$2:$MC$200=K$3)*('GMW - Baseline'!$MB$2:$MB$200=K$4),0),$E27-1973)} -> #N/A | L27: {=INDEX('GMW - Baseline'!$A$2:$MC$200,MATCH(1,('GMW - Baseline'!$MC$2:$MC$200=L$3)*('GMW - Baseline'!$MB$2:$MB$200=L$4),0),$E27-1973)} -> #N/A | M27: {=INDEX('GMW - Baseline'!$A$2:$MC$200,MATCH(1,('GMW - Baseline'!$MC$2:$MC$200=M$3)*('GMW - Baseline'!$MB$2:$MB$200=M$4),0),$E27-1973)} -> #N/A | ... T27: {=INDEX('GMW - Baseline'!$A$2:$MC$200,MATCH(1,('GMW - Baseline'!$MC$2:$MC$200=T$3)*('GMW - Baseline'!$MB$2:$MB$200=T$4),0),$E27-1973)} -> #N/A
B28: =+B24+1 -> 1985 | C28: =+C24+1 -> 1985 | E28: =+E27+1 -> 2001 | F28: {=INDEX('GMW - Baseline'!$A$2:$MC$200,MATCH(1,('GMW - Baseline'!$MC$2:$MC$200=F$3)*('GMW - Baseline'!$MB$2:$MB$200=F$4),0),$E28-1973)} -> 322451 | G28: {=INDEX('GMW - Baseline'!$A$2:$MC$200,MATCH(1,('GMW - Baseline'!$MC$2:$MC$200=G$3)*('GMW - Baseline'!$MB$2:$MB$200=G$4),0),$E28-1973)} -> 170284 | H28: {=INDEX('GMW - Baseline'!$A$2:$MC$200,MATCH(1,('GMW - Baseline'!$MC$2:$MC$200=H$3)*('GMW - Baseline'!$MB$2:$MB$200=H$4),0),$E28-1973)} -> 44.9952 | I28: {=INDEX('GMW - Baseline'!$A$2:$MC$200,MATCH(1,('GMW - Baseline'!$MC$2:$MC$200=I$3)*('GMW - Baseline'!$MB$2:$MB$200=I$4),0),$E28-1973)} -> 12.48269 | J28: {=INDEX('GMW - Baseline'!$A$2:$MC$200,MATCH(1,('GMW - Baseline'!$MC$2:$MC$200=J$3)*('GMW - Baseline'!$MB$2:$MB$200=J$4),0),$E28-1973)} -> #N/A | K28: {=INDEX('GMW - Baseline'!$A$2:$MC$200,MATCH(1,('GMW - Baseline'!$MC$2:$MC$200=K$3)*('GMW - Baseline'!$MB$2:$MB$200=K$4),0),$E28-1973)} -> #N/A | L28: {=INDEX('GMW - Baseline'!$A$2:$MC$200,MATCH(1,('GMW - Baseline'!$MC$2:$MC$200=L$3)*('GMW - Baseline'!$MB$2:$MB$200=L$4),0),$E28-1973)} -> #N/A | M28: {=INDEX('GMW - Baseline'!$A$2:$MC$200,MATCH(1,('GMW - Baseline'!$MC$2:$MC$200=M$3)*('GMW - Baseline'!$MB$2:$MB$200=M$4),0),$E28-1973)} -> #N/A | ... T28: {=INDEX('GMW - Baseline'!$A$2:$MC$200,MATCH(1,('GMW - Baseline'!$MC$2:$MC$200=T$3)*('GMW - Baseline'!$MB$2:$MB$200=T$4),0),$E28-1973)} -> #N/A
B29: =+B25+1 -> 1985 | C29: =+C25+1 -> 1985 | E29: =+E28+1 -> 2002 | F29: {=INDEX('GMW - Baseline'!$A$2:$MC$200,MATCH(1,('GMW - Baseline'!$MC$2:$MC$200=F$3)*('GMW - Baseline'!$MB$2:$MB$200=F$4),0),$E29-1973)} -> 322392 | G29: {=INDEX('GMW - Baseline'!$A$2:$MC$200,MATCH(1,('GMW - Baseline'!$MC$2:$MC$200=G$3)*('GMW - Baseline'!$MB$2:$MB$200=G$4),0),$E29-1973)} -> 172709 | H29: {=INDEX('GMW - Baseline'!$A$2:$MC$200,MATCH(1,('GMW - Baseline'!$MC$2:$MC$200=H$3)*('GMW - Baseline'!$MB$2:$MB$200=H$4),0),$E29-1973)} -> 45.12555 | I29: {=INDEX('GMW - Baseline'!$A$2:$MC$200,MATCH(1,('GMW - Baseline'!$MC$2:$MC$200=I$3)*('GMW - Baseline'!$MB$2:$MB$200=I$4),0),$E29-1973)} -> 11.57955 | J29: {=INDEX('GMW - Baseline'!$A$2:$MC$200,MATCH(1,('GMW - Baseline'!$MC$2:$MC$200=J$3)*('GMW - Baseline'!$MB$2:$MB$200=J$4),0),$E29-1973)} -> #N/A | K29: {=INDEX('GMW - Baseline'!$A$2:$MC$200,MATCH(1,('GMW - Baseline'!$MC$2:$MC$200=K$3)*('GMW - Baseline'!$MB$2:$MB$200=K$4),0),$E29-1973)} -> #N/A | L29: {=INDEX('GMW - Baseline'!$A$2:$MC$200,MATCH(1,('GMW - Baseline'!$MC$2:$MC$200=L$3)*('GMW - Baseline'!$MB$2:$MB$200=L$4),0),$E29-1973)} -> #N/A | M29: {=INDEX('GMW - Baseline'!$A$2:$MC$200,MATCH(1,('GMW - Baseline'!$MC$2:$MC$200=M$3)*('GMW - Baseline'!$MB$2:$MB$200=M$4),0),$E29-1973)} -> #N/A | ... T29: {=INDEX('GMW - Baseline'!$A$2:$MC$200,MATCH(1,('GMW - Baseline'!$MC$2:$MC$200=T$3)*('GMW - Baseline'!$MB$2:$MB$200=T$4),0),$E29-1973)} -> #N/A
B30: =+B26+1 -> 1985 | C30: =+C26+1 -> 1985 | E30: =+E29+1 -> 2003 | F30: {=INDEX('GMW - Baseline'!$A$2:$MC$200,MATCH(1,('GMW - Baseline'!$MC$2:$MC$200=F$3)*('GMW - Baseline'!$MB$2:$MB$200=F$4),0),$E30-1973)} -> 322604 | G30: {=INDEX('GMW - Baseline'!$A$2:$MC$200,MATCH(1,('GMW - Baseline'!$MC$2:$MC$200=G$3)*('GMW - Baseline'!$MB$2:$MB$200=G$4),0),$E30-1973)} -> 174066 | H30: {=INDEX('GMW - Baseline'!$A$2:$MC$200,MATCH(1,('GMW - Baseline'!$MC$2:$MC$200=H$3)*('GMW - Baseline'!$MB$2:$MB$200=H$4),0),$E30-1973)} -> 45.49052 | I30: {=INDEX('GMW - Baseline'!$A$2:$MC$200,MATCH(1,('GMW - Baseline'!$MC$2:$MC$200=I$3)*('GMW - Baseline'!$MB$2:$MB$200=I$4),0),$E30-1973)} -> 11.375 | J30: {=INDEX('GMW - Baseline'!$A$2:$MC$200,MATCH(1,('GMW - Baseline'!$MC$2:$MC$200=J$3)*('GMW - Baseline'!$MB$2:$MB$200=J$4),0),$E30-1973)} -> #N/A | K30: {=INDEX('GMW - Baseline'!$A$2:$MC$200,MATCH(1,('GMW - Baseline'!$MC$2:$MC$200=K$3)*('GMW - Baseline'!$MB$2:$MB$200=K$4),0),$E30-1973)} -> #N/A | L30: {=INDEX('GMW - Baseline'!$A$2:$MC$200,MATCH(1,('GMW - Baseline'!$MC$2:$MC$200=L$3)*('GMW - Baseline'!$MB$2:$MB$200=L$4),0),$E30-1973)} -> #N/A | M30: {=INDEX('GMW - Baseline'!$A$2:$MC$200,MATCH(1,('GMW - Baseline'!$MC$2:$MC$200=M$3)*('GMW - Baseline'!$MB$2:$MB$200=M$4),0),$E30-1973)} -> #N/A | ... T30: {=INDEX('GMW - Baseline'!$A$2:$MC$200,MATCH(1,('GMW - Baseline'!$MC$2:$MC$200=T$3)*('GMW - Baseline'!$MB$2:$MB$200=T$4),0),$E30-1973)} -> #N/A
A31: 1986 | B31: =+B27+1 -> 1986 | C31: =+C27+1 -> 1985 | D31: =+D27+1 -> 1985 | E31: =+E30+1 -> 2004 | F31: {=INDEX('GMW - Baseline'!$A$2:$MC$200,MATCH(1,('GMW - Baseline'!$MC$2:$MC$200=F$3)*('GMW - Baseline'!$MB$2:$MB$200=F$4),0),$E31-1973)} -> 325968 | G31: {=INDEX('GMW - Baseline'!$A$2:$MC$200,MATCH(1,('GMW - Baseline'!$MC$2:$MC$200=G$3)*('GMW - Baseline'!$MB$2:$MB$200=G$4),0),$E31-1973)} -> 178852 | H31: {=INDEX('GMW - Baseline'!$A$2:$MC$200,MATCH(1,('GMW - Baseline'!$MC$2:$MC$200=H$3)*('GMW - Baseline'!$MB$2:$MB$200=H$4),0),$E31-1973)} -> 45.64693 | I31: {=INDEX('GMW - Baseline'!$A$2:$MC$200,MATCH(1,('GMW - Baseline'!$MC$2:$MC$200=I$3)*('GMW - Baseline'!$MB$2:$MB$200=I$4),0),$E31-1973)} -> 12.07813 | J31: {=INDEX('GMW - Baseline'!$A$2:$MC$200,MATCH(1,('GMW - Baseline'!$MC$2:$MC$200=J$3)*('GMW - Baseline'!$MB$2:$MB$200=J$4),0),$E31-1973)} -> #N/A | K31: {=INDEX('GMW - Baseline'!$A$2:$MC$200,MATCH(1,('GMW - Baseline'!$MC$2:$MC$200=K$3)*('GMW - Baseline'!$MB$2:$MB$200=K$4),0),$E31-1973)} -> #N/A | L31: {=INDEX('GMW - Baseline'!$A$2:$MC$200,MATCH(1,('GMW - Baseline'!$MC$2:$MC$200=L$3)*('GMW - Baseline'!$MB$2:$MB$200=L$4),0),$E31-1973)} -> #N/A | M31: {=INDEX('GMW - Baseline'!$A$2:$MC$200,MATCH(1,('GMW - Baseline'!$MC$2:$MC$200=M$3)*('GMW - Baseline'!$MB$2:$MB$200=M$4),0),$E31-1973)} -> #N/A | ... T31: {=INDEX('GMW - Baseline'!$A$2:$MC$200,MATCH(1,('GMW - Baseline'!$MC$2:$MC$200=T$3)*('GMW - Baseline'!$MB$2:$MB$200=T$4),0),$E31-1973)} -> #N/A
B32: =+B28+1 -> 1986 | C32: =+C28+1 -> 1986 | E32: =+E31+1 -> 2005 | F32: {=INDEX('GMW - Baseline'!$A$2:$MC$200,MATCH(1,('GMW - Baseline'!$MC$2:$MC$200=F$3)*('GMW - Baseline'!$MB$2:$MB$200=F$4),0),$E32-1973)} -> 328872 | G32: {=INDEX('GMW - Baseline'!$A$2:$MC$200,MATCH(1,('GMW - Baseline'!$MC$2:$MC$200=G$3)*('GMW - Baseline'!$MB$2:$MB$200=G$4),0),$E32-1973)} -> 181672 | H32: {=INDEX('GMW - Baseline'!$A$2:$MC$200,MATCH(1,('GMW - Baseline'!$MC$2:$MC$200=H$3)*('GMW - Baseline'!$MB$2:$MB$200=H$4),0),$E32-1973)} -> 46.3508 | I32: {=INDEX('GMW - Baseline'!$A$2:$MC$200,MATCH(1,('GMW - Baseline'!$MC$2:$MC$200=I$3)*('GMW - Baseline'!$MB$2:$MB$200=I$4),0),$E32-1973)} -> 10.32885 | J32: {=INDEX('GMW - Baseline'!$A$2:$MC$200,MATCH(1,('GMW - Baseline'!$MC$2:$MC$200=J$3)*('GMW - Baseline'!$MB$2:$MB$200=J$4),0),$E32-1973)} -> #N/A | K32: {=INDEX('GMW - Baseline'!$A$2:$MC$200,MATCH(1,('GMW - Baseline'!$MC$2:$MC$200=K$3)*('GMW - Baseline'!$MB$2:$MB$200=K$4),0),$E32-1973)} -> #N/A | L32: {=INDEX('GMW - Baseline'!$A$2:$MC$200,MATCH(1,('GMW - Baseline'!$MC$2:$MC$200=L$3)*('GMW - Baseline'!$MB$2:$MB$200=L$4),0),$E32-1973)} -> #N/A | M32: {=INDEX('GMW - Baseline'!$A$2:$MC$200,MATCH(1,('GMW - Baseline'!$MC$2:$MC$200=M$3)*('GMW - Baseline'!$MB$2:$MB$200=M$4),0),$E32-1973)} -> #N/A | ... T32: {=INDEX('GMW - Baseline'!$A$2:$MC$200,MATCH(1,('GMW - Baseline'!$MC$2:$MC$200=T$3)*('GMW - Baseline'!$MB$2:$MB$200=T$4),0),$E32-1973)} -> #N/A
B33: =+B29+1 -> 1986 | C33: =+C29+1 -> 1986 | E33: =+E32+1 -> 2006 | F33: {=INDEX('GMW - Baseline'!$A$2:$MC$200,MATCH(1,('GMW - Baseline'!$MC$2:$MC$200=F$3)*('GMW - Baseline'!$MB$2:$MB$200=F$4),0),$E33-1973)} -> 330966 | G33: {=INDEX('GMW - Baseline'!$A$2:$MC$200,MATCH(1,('GMW - Baseline'!$MC$2:$MC$200=G$3)*('GMW - Baseline'!$MB$2:$MB$200=G$4),0),$E33-1973)} -> 182857 | H33: {=INDEX('GMW - Baseline'!$A$2:$MC$200,MATCH(1,('GMW - Baseline'!$MC$2:$MC$200=H$3)*('GMW - Baseline'!$MB$2:$MB$200=H$4),0),$E33-1973)} -> 46.53328 | I33: {=INDEX('GMW - Baseline'!$A$2:$MC$200,MATCH(1,('GMW - Baseline'!$MC$2:$MC$200=I$3)*('GMW - Baseline'!$MB$2:$MB$200=I$4),0),$E33-1973)} -> 9.875 | J33: {=INDEX('GMW - Baseline'!$A$2:$MC$200,MATCH(1,('GMW - Baseline'!$MC$2:$MC$200=J$3)*('GMW - Baseline'!$MB$2:$MB$200=J$4),0),$E33-1973)} -> #N/A | K33: {=INDEX('GMW - Baseline'!$A$2:$MC$200,MATCH(1,('GMW - Baseline'!$MC$2:$MC$200=K$3)*('GMW - Baseline'!$MB$2:$MB$200=K$4),0),$E33-1973)} -> #N/A | L33: {=INDEX('GMW - Baseline'!$A$2:$MC$200,MATCH(1,('GMW - Baseline'!$MC$2:$MC$200=L$3)*('GMW - Baseline'!$MB$2:$MB$200=L$4),0),$E33-1973)} -> #N/A | M33: {=INDEX('GMW - Baseline'!$A$2:$MC$200,MATCH(1,('GMW - Baseline'!$MC$2:$MC$200=M$3)*('GMW - Baseline'!$MB$2:$MB$200=M$4),0),$E33-1973)} -> #N/A | ... T33: {=INDEX('GMW - Baseline'!$A$2:$MC$200,MATCH(1,('GMW - Baseline'!$MC$2:$MC$200=T$3)*('GMW - Baseline'!$MB$2:$MB$200=T$4),0),$E33-1973)} -> #N/A
B34: =+B30+1 -> 1986 | C34: =+C30+1 -> 1986 | E34: =+E33+1 -> 2007 | F34: {=INDEX('GMW - Baseline'!$A$2:$MC$200,MATCH(1,('GMW - Baseline'!$MC$2:$MC$200=F$3)*('GMW - Baseline'!$MB$2:$MB$200=F$4),0),$E34-1973)} -> 337367 | G34: {=INDEX('GMW - Baseline'!$A$2:$MC$200,MATCH(1,('GMW - Baseline'!$MC$2:$MC$200=G$3)*('GMW - Baseline'!$MB$2:$MB$200=G$4),0),$E34-1973)} -> 183752 | H34: {=INDEX('GMW - Baseline'!$A$2:$MC$200,MATCH(1,('GMW - Baseline'!$MC$2:$MC$200=H$3)*('GMW - Baseline'!$MB$2:$MB$200=H$4),0),$E34-1973)} -> 46.92432 | I34: {=INDEX('GMW - Baseline'!$A$2:$MC$200,MATCH(1,('GMW - Baseline'!$MC$2:$MC$200=I$3)*('GMW - Baseline'!$MB$2:$MB$200=I$4),0),$E34-1973)} -> 10.72348 | J34: {=INDEX('GMW - Baseline'!$A$2:$MC$200,MATCH(1,('GMW - Baseline'!$MC$2:$MC$200=J$3)*('GMW - Baseline'!$MB$2:$MB$200=J$4),0),$E34-1973)} -> #N/A | K34: {=INDEX('GMW - Baseline'!$A$2:$MC$200,MATCH(1,('GMW - Baseline'!$MC$2:$MC$200=K$3)*('GMW - Baseline'!$MB$2:$MB$200=K$4),0),$E34-1973)} -> #N/A | L34: {=INDEX('GMW - Baseline'!$A$2:$MC$200,MATCH(1,('GMW - Baseline'!$MC$2:$MC$200=L$3)*('GMW - Baseline'!$MB$2:$MB$200=L$4),0),$E34-1973)} -> #N/A | M34: {=INDEX('GMW - Baseline'!$A$2:$MC$200,MATCH(1,('GMW - Baseline'!$MC$2:$MC$200=M$3)*('GMW - Baseline'!$MB$2:$MB$200=M$4),0),$E34-1973)} -> #N/A | ... T34: {=INDEX('GMW - Baseline'!$A$2:$MC$200,MATCH(1,('GMW - Baseline'!$MC$2:$MC$200=T$3)*('GMW - Baseline'!$MB$2:$MB$200=T$4),0),$E34-1973)} -> #N/A
A35: 1987 | B35: =+B31+1 -> 1987 | C35: =+C31+1 -> 1986 | D35: =+D31+1 -> 1986 | E35: =+E34+1 -> 2008 | F35: {=INDEX('GMW - Baseline'!$A$2:$MC$200,MATCH(1,('GMW - Baseline'!$MC$2:$MC$200=F$3)*('GMW - Baseline'!$MB$2:$MB$200=F$4),0),$E35-1973)} -> 339754 | G35: {=INDEX('GMW - Baseline'!$A$2:$MC$200,MATCH(1,('GMW - Baseline'!$MC$2:$MC$200=G$3)*('GMW - Baseline'!$MB$2:$MB$200=G$4),0),$E35-1973)} -> 185943 | H35: {=INDEX('GMW - Baseline'!$A$2:$MC$200,MATCH(1,('GMW - Baseline'!$MC$2:$MC$200=H$3)*('GMW - Baseline'!$MB$2:$MB$200=H$4),0),$E35-1973)} -> 47.23714 | I35: {=INDEX('GMW - Baseline'!$A$2:$MC$200,MATCH(1,('GMW - Baseline'!$MC$2:$MC$200=I$3)*('GMW - Baseline'!$MB$2:$MB$200=I$4),0),$E35-1973)} -> 10.66406 | J35: {=INDEX('GMW - Baseline'!$A$2:$MC$200,MATCH(1,('GMW - Baseline'!$MC$2:$MC$200=J$3)*('GMW - Baseline'!$MB$2:$MB$200=J$4),0),$E35-1973)} -> #N/A | K35: {=INDEX('GMW - Baseline'!$A$2:$MC$200,MATCH(1,('GMW - Baseline'!$MC$2:$MC$200=K$3)*('GMW - Baseline'!$MB$2:$MB$200=K$4),0),$E35-1973)} -> #N/A | L35: {=INDEX('GMW - Baseline'!$A$2:$MC$200,MATCH(1,('GMW - Baseline'!$MC$2:$MC$200=L$3)*('GMW - Baseline'!$MB$2:$MB$200=L$4),0),$E35-1973)} -> #N/A | M35: {=INDEX('GMW - Baseline'!$A$2:$MC$200,MATCH(1,('GMW - Baseline'!$MC$2:$MC$200=M$3)*('GMW - Baseline'!$MB$2:$MB$200=M$4),0),$E35-1973)} -> #N/A | ... T35: {=INDEX('GMW - Baseline'!$A$2:$MC$200,MATCH(1,('GMW - Baseline'!$MC$2:$MC$200=T$3)*('GMW - Baseline'!$MB$2:$MB$200=T$4),0),$E35-1973)} -> #N/A
B36: =+B32+1 -> 1987 | C36: =+C32+1 -> 1987 | E36: =+E35+1 -> 2009 | F36: {=INDEX('GMW - Baseline'!$A$2:$MC$200,MATCH(1,('GMW - Baseline'!$MC$2:$MC$200=F$3)*('GMW - Baseline'!$MB$2:$MB$200=F$4),0),$E36-1973)} -> 344795 | G36: {=INDEX('GMW - Baseline'!$A$2:$MC$200,MATCH(1,('GMW - Baseline'!$MC$2:$MC$200=G$3)*('GMW - Baseline'!$MB$2:$MB$200=G$4),0),$E36-1973)} -> 189091 | H36: {=INDEX('GMW - Baseline'!$A$2:$MC$200,MATCH(1,('GMW - Baseline'!$MC$2:$MC$200=H$3)*('GMW - Baseline'!$MB$2:$MB$200=H$4),0),$E36-1973)} -> 47.83673 | I36: {=INDEX('GMW - Baseline'!$A$2:$MC$200,MATCH(1,('GMW - Baseline'!$MC$2:$MC$200=I$3)*('GMW - Baseline'!$MB$2:$MB$200=I$4),0),$E36-1973)} -> 9.228847 | J36: {=INDEX('GMW - Baseline'!$A$2:$MC$200,MATCH(1,('GMW - Baseline'!$MC$2:$MC$200=J$3)*('GMW - Baseline'!$MB$2:$MB$200=J$4),0),$E36-1973)} -> #N/A | K36: {=INDEX('GMW - Baseline'!$A$2:$MC$200,MATCH(1,('GMW - Baseline'!$MC$2:$MC$200=K$3)*('GMW - Baseline'!$MB$2:$MB$200=K$4),0),$E36-1973)} -> #N/A | L36: {=INDEX('GMW - Baseline'!$A$2:$MC$200,MATCH(1,('GMW - Baseline'!$MC$2:$MC$200=L$3)*('GMW - Baseline'!$MB$2:$MB$200=L$4),0),$E36-1973)} -> #N/A | M36: {=INDEX('GMW - Baseline'!$A$2:$MC$200,MATCH(1,('GMW - Baseline'!$MC$2:$MC$200=M$3)*('GMW - Baseline'!$MB$2:$MB$200=M$4),0),$E36-1973)} -> #N/A | ... T36: {=INDEX('GMW - Baseline'!$A$2:$MC$200,MATCH(1,('GMW - Baseline'!$MC$2:$MC$200=T$3)*('GMW - Baseline'!$MB$2:$MB$200=T$4),0),$E36-1973)} -> #N/A
B37: =+B33+1 -> 1987 | C37: =+C33+1 -> 1987 | E37: =+E36+1 -> 2010 | F37: {=INDEX('GMW - Baseline'!$A$2:$MC$200,MATCH(1,('GMW - Baseline'!$MC$2:$MC$200=F$3)*('GMW - Baseline'!$MB$2:$MB$200=F$4),0),$E37-1973)} -> 353365 | G37: {=INDEX('GMW - Baseline'!$A$2:$MC$200,MATCH(1,('GMW - Baseline'!$MC$2:$MC$200=G$3)*('GMW - Baseline'!$MB$2:$MB$200=G$4),0),$E37-1973)} -> 193017 | H37: {=INDEX('GMW - Baseline'!$A$2:$MC$200,MATCH(1,('GMW - Baseline'!$MC$2:$MC$200=H$3)*('GMW - Baseline'!$MB$2:$MB$200=H$4),0),$E37-1973)} -> 47.88887 | I37: {=INDEX('GMW - Baseline'!$A$2:$MC$200,MATCH(1,('GMW - Baseline'!$MC$2:$MC$200=I$3)*('GMW - Baseline'!$MB$2:$MB$200=I$4),0),$E37-1973)} -> 9.481061 | J37: {=INDEX('GMW - Baseline'!$A$2:$MC$200,MATCH(1,('GMW - Baseline'!$MC$2:$MC$200=J$3)*('GMW - Baseline'!$MB$2:$MB$200=J$4),0),$E37-1973)} -> #N/A | K37: {=INDEX('GMW - Baseline'!$A$2:$MC$200,MATCH(1,('GMW - Baseline'!$MC$2:$MC$200=K$3)*('GMW - Baseline'!$MB$2:$MB$200=K$4),0),$E37-1973)} -> #N/A | L37: {=INDEX('GMW - Baseline'!$A$2:$MC$200,MATCH(1,('GMW - Baseline'!$MC$2:$MC$200=L$3)*('GMW - Baseline'!$MB$2:$MB$200=L$4),0),$E37-1973)} -> #N/A | M37: {=INDEX('GMW - Baseline'!$A$2:$MC$200,MATCH(1,('GMW - Baseline'!$MC$2:$MC$200=M$3)*('GMW - Baseline'!$MB$2:$MB$200=M$4),0),$E37-1973)} -> #N/A | ... T37: {=INDEX('GMW - Baseline'!$A$2:$MC$200,MATCH(1,('GMW - Baseline'!$MC$2:$MC$200=T$3)*('GMW - Baseline'!$MB$2:$MB$200=T$4),0),$E37-1973)} -> #N/A
B38: =+B34+1 -> 1987 | C38: =+C34+1 -> 1987 | E38: =+E37+1 -> 2011 | F38: {=INDEX('GMW - Baseline'!$A$2:$MC$200,MATCH(1,('GMW - Baseline'!$MC$2:$MC$200=F$3)*('GMW - Baseline'!$MB$2:$MB$200=F$4),0),$E38-1973)} -> 357439 | G38: {=INDEX('GMW - Baseline'!$A$2:$MC$200,MATCH(1,('GMW - Baseline'!$MC$2:$MC$200=G$3)*('GMW - Baseline'!$MB$2:$MB$200=G$4),0),$E38-1973)} -> 197212 | H38: {=INDEX('GMW - Baseline'!$A$2:$MC$200,MATCH(1,('GMW - Baseline'!$MC$2:$MC$200=H$3)*('GMW - Baseline'!$MB$2:$MB$200=H$4),0),$E38-1973)} -> 48.43632 | I38: {=INDEX('GMW - Baseline'!$A$2:$MC$200,MATCH(1,('GMW - Baseline'!$MC$2:$MC$200=I$3)*('GMW - Baseline'!$MB$2:$MB$200=I$4),0),$E38-1973)} -> 9.018939 | J38: {=INDEX('GMW - Baseline'!$A$2:$MC$200,MATCH(1,('GMW - Baseline'!$MC$2:$MC$200=J$3)*('GMW - Baseline'!$MB$2:$MB$200=J$4),0),$E38-1973)} -> #N/A | K38: {=INDEX('GMW - Baseline'!$A$2:$MC$200,MATCH(1,('GMW - Baseline'!$MC$2:$MC$200=K$3)*('GMW - Baseline'!$MB$2:$MB$200=K$4),0),$E38-1973)} -> #N/A | L38: {=INDEX('GMW - Baseline'!$A$2:$MC$200,MATCH(1,('GMW - Baseline'!$MC$2:$MC$200=L$3)*('GMW - Baseline'!$MB$2:$MB$200=L$4),0),$E38-1973)} -> #N/A | M38: {=INDEX('GMW - Baseline'!$A$2:$MC$200,MATCH(1,('GMW - Baseline'!$MC$2:$MC$200=M$3)*('GMW - Baseline'!$MB$2:$MB$200=M$4),0),$E38-1973)} -> #N/A | ... T38: {=INDEX('GMW - Baseline'!$A$2:$MC$200,MATCH(1,('GMW - Baseline'!$MC$2:$MC$200=T$3)*('GMW - Baseline'!$MB$2:$MB$200=T$4),0),$E38-1973)} -> #N/A
A39: 1988 | B39: =+B35+1 -> 1988 | C39: =+C35+1 -> 1987 | D39: =+D35+1 -> 1987 | E39: =+E38+1 -> 2012 | F39: {=INDEX('GMW - Baseline'!$A$2:$MC$200,MATCH(1,('GMW - Baseline'!$MC$2:$MC$200=F$3)*('GMW - Baseline'!$MB$2:$MB$200=F$4),0),$E39-1973)} -> 363267 | G39: {=INDEX('GMW - Baseline'!$A$2:$MC$200,MATCH(1,('GMW - Baseline'!$MC$2:$MC$200=G$3)*('GMW - Baseline'!$MB$2:$MB$200=G$4),0),$E39-1973)} -> 199926 | H39: {=INDEX('GMW - Baseline'!$A$2:$MC$200,MATCH(1,('GMW - Baseline'!$MC$2:$MC$200=H$3)*('GMW - Baseline'!$MB$2:$MB$200=H$4),0),$E39-1973)} -> 48.56667 | I39: {=INDEX('GMW - Baseline'!$A$2:$MC$200,MATCH(1,('GMW - Baseline'!$MC$2:$MC$200=I$3)*('GMW - Baseline'!$MB$2:$MB$200=I$4),0),$E39-1973)} -> 8.628846 | J39: {=INDEX('GMW - Baseline'!$A$2:$MC$200,MATCH(1,('GMW - Baseline'!$MC$2:$MC$200=J$3)*('GMW - Baseline'!$MB$2:$MB$200=J$4),0),$E39-1973)} -> #N/A | K39: {=INDEX('GMW - Baseline'!$A$2:$MC$200,MATCH(1,('GMW - Baseline'!$MC$2:$MC$200=K$3)*('GMW - Baseline'!$MB$2:$MB$200=K$4),0),$E39-1973)} -> #N/A | L39: {=INDEX('GMW - Baseline'!$A$2:$MC$200,MATCH(1,('GMW - Baseline'!$MC$2:$MC$200=L$3)*('GMW - Baseline'!$MB$2:$MB$200=L$4),0),$E39-1973)} -> #N/A | M39: {=INDEX('GMW - Baseline'!$A$2:$MC$200,MATCH(1,('GMW - Baseline'!$MC$2:$MC$200=M$3)*('GMW - Baseline'!$MB$2:$MB$200=M$4),0),$E39-1973)} -> #N/A | ... T39: {=INDEX('GMW - Baseline'!$A$2:$MC$200,MATCH(1,('GMW - Baseline'!$MC$2:$MC$200=T$3)*('GMW - Baseline'!$MB$2:$MB$200=T$4),0),$E39-1973)} -> #N/A
B40: =+B36+1 -> 1988 | C40: =+C36+1 -> 1988 | E40: =+E39+1 -> 2013 | F40: {=INDEX('GMW - Baseline'!$A$2:$MC$200,MATCH(1,('GMW - Baseline'!$MC$2:$MC$200=F$3)*('GMW - Baseline'!$MB$2:$MB$200=F$4),0),$E40-1973)} -> 365209 | G40: {=INDEX('GMW - Baseline'!$A$2:$MC$200,MATCH(1,('GMW - Baseline'!$MC$2:$MC$200=G$3)*('GMW - Baseline'!$MB$2:$MB$200=G$4),0),$E40-1973)} -> 202789 | H40: {=INDEX('GMW - Baseline'!$A$2:$MC$200,MATCH(1,('GMW - Baseline'!$MC$2:$MC$200=H$3)*('GMW - Baseline'!$MB$2:$MB$200=H$4),0),$E40-1973)} -> 49.5 | I40: {=INDEX('GMW - Baseline'!$A$2:$MC$200,MATCH(1,('GMW - Baseline'!$MC$2:$MC$200=I$3)*('GMW - Baseline'!$MB$2:$MB$200=I$4),0),$E40-1973)} -> 7.967308 | J40: {=INDEX('GMW - Baseline'!$A$2:$MC$200,MATCH(1,('GMW - Baseline'!$MC$2:$MC$200=J$3)*('GMW - Baseline'!$MB$2:$MB$200=J$4),0),$E40-1973)} -> #N/A | K40: {=INDEX('GMW - Baseline'!$A$2:$MC$200,MATCH(1,('GMW - Baseline'!$MC$2:$MC$200=K$3)*('GMW - Baseline'!$MB$2:$MB$200=K$4),0),$E40-1973)} -> #N/A | L40: {=INDEX('GMW - Baseline'!$A$2:$MC$200,MATCH(1,('GMW - Baseline'!$MC$2:$MC$200=L$3)*('GMW - Baseline'!$MB$2:$MB$200=L$4),0),$E40-1973)} -> #N/A | M40: {=INDEX('GMW - Baseline'!$A$2:$MC$200,MATCH(1,('GMW - Baseline'!$MC$2:$MC$200=M$3)*('GMW - Baseline'!$MB$2:$MB$200=M$4),0),$E40-1973)} -> #N/A | ... T40: {=INDEX('GMW - Baseline'!$A$2:$MC$200,MATCH(1,('GMW - Baseline'!$MC$2:$MC$200=T$3)*('GMW - Baseline'!$MB$2:$MB$200=T$4),0),$E40-1973)} -> #N/A
B41: =+B37+1 -> 1988 | C41: =+C37+1 -> 1988 | E41: =+E40+1 -> 2014 | F41: {=INDEX('GMW - Baseline'!$A$2:$MC$200,MATCH(1,('GMW - Baseline'!$MC$2:$MC$200=F$3)*('GMW - Baseline'!$MB$2:$MB$200=F$4),0),$E41-1973)} -> 369774 | G41: {=INDEX('GMW - Baseline'!$A$2:$MC$200,MATCH(1,('GMW - Baseline'!$MC$2:$MC$200=G$3)*('GMW - Baseline'!$MB$2:$MB$200=G$4),0),$E41-1973)} -> 207502 | H41: {=INDEX('GMW - Baseline'!$A$2:$MC$200,MATCH(1,('GMW - Baseline'!$MC$2:$MC$200=H$3)*('GMW - Baseline'!$MB$2:$MB$200=H$4),0),$E41-1973)} -> 49.9 | I41: {=INDEX('GMW - Baseline'!$A$2:$MC$200,MATCH(1,('GMW - Baseline'!$MC$2:$MC$200=I$3)*('GMW - Baseline'!$MB$2:$MB$200=I$4),0),$E41-1973)} -> 10.92045 | J41: {=INDEX('GMW - Baseline'!$A$2:$MC$200,MATCH(1,('GMW - Baseline'!$MC$2:$MC$200=J$3)*('GMW - Baseline'!$MB$2:$MB$200=J$4),0),$E41-1973)} -> #N/A | K41: {=INDEX('GMW - Baseline'!$A$2:$MC$200,MATCH(1,('GMW - Baseline'!$MC$2:$MC$200=K$3)*('GMW - Baseline'!$MB$2:$MB$200=K$4),0),$E41-1973)} -> #N/A | L41: {=INDEX('GMW - Baseline'!$A$2:$MC$200,MATCH(1,('GMW - Baseline'!$MC$2:$MC$200=L$3)*('GMW - Baseline'!$MB$2:$MB$200=L$4),0),$E41-1973)} -> #N/A | M41: {=INDEX('GMW - Baseline'!$A$2:$MC$200,MATCH(1,('GMW - Baseline'!$MC$2:$MC$200=M$3)*('GMW - Baseline'!$MB$2:$MB$200=M$4),0),$E41-1973)} -> #N/A | ... T41: {=INDEX('GMW - Baseline'!$A$2:$MC$200,MATCH(1,('GMW - Baseline'!$MC$2:$MC$200=T$3)*('GMW - Baseline'!$MB$2:$MB$200=T$4),0),$E41-1973)} -> #N/A
B42: =+B38+1 -> 1988 | C42: =+C38+1 -> 1988 | E42: =+E41+1 -> 2015 | F42: {=INDEX('GMW - Baseline'!$A$2:$MC$200,MATCH(1,('GMW - Baseline'!$MC$2:$MC$200=F$3)*('GMW - Baseline'!$MB$2:$MB$200=F$4),0),$E42-1973)} -> 372752 | G42: {=INDEX('GMW - Baseline'!$A$2:$MC$200,MATCH(1,('GMW - Baseline'!$MC$2:$MC$200=G$3)*('GMW - Baseline'!$MB$2:$MB$200=G$4),0),$E42-1973)} -> 209369 | H42: {=INDEX('GMW - Baseline'!$A$2:$MC$200,MATCH(1,('GMW - Baseline'!$MC$2:$MC$200=H$3)*('GMW - Baseline'!$MB$2:$MB$200=H$4),0),$E42-1973)} -> 50.46667 | I42: {=INDEX('GMW - Baseline'!$A$2:$MC$200,MATCH(1,('GMW - Baseline'!$MC$2:$MC$200=I$3)*('GMW - Baseline'!$MB$2:$MB$200=I$4),0),$E42-1973)} -> 12.275 | J42: {=INDEX('GMW - Baseline'!$A$2:$MC$200,MATCH(1,('GMW - Baseline'!$MC$2:$MC$200=J$3)*('GMW - Baseline'!$MB$2:$MB$200=J$4),0),$E42-1973)} -> #N/A | K42: {=INDEX('GMW - Baseline'!$A$2:$MC$200,MATCH(1,('GMW - Baseline'!$MC$2:$MC$200=K$3)*('GMW - Baseline'!$MB$2:$MB$200=K$4),0),$E42-1973)} -> #N/A | L42: {=INDEX('GMW - Baseline'!$A$2:$MC$200,MATCH(1,('GMW - Baseline'!$MC$2:$MC$200=L$3)*('GMW - Baseline'!$MB$2:$MB$200=L$4),0),$E42-1973)} -> #N/A | M42: {=INDEX('GMW - Baseline'!$A$2:$MC$200,MATCH(1,('GMW - Baseline'!$MC$2:$MC$200=M$3)*('GMW - Baseline'!$MB$2:$MB$200=M$4),0),$E42-1973)} -> #N/A | ... T42: {=INDEX('GMW - Baseline'!$A$2:$MC$200,MATCH(1,('GMW - Baseline'!$MC$2:$MC$200=T$3)*('GMW - Baseline'!$MB$2:$MB$200=T$4),0),$E42-1973)} -> #N/A
A43: 1989 | B43: =+B39+1 -> 1989 | C43: =+C39+1 -> 1988 | D43: =+D39+1 -> 1988 | E43: =+E42+1 -> 2016 | F43: {=INDEX('GMW - Baseline'!$A$2:$MC$200,MATCH(1,('GMW - Baseline'!$MC$2:$MC$200=F$3)*('GMW - Baseline'!$MB$2:$MB$200=F$4),0),$E43-1973)} -> 374612 | G43: {=INDEX('GMW - Baseline'!$A$2:$MC$200,MATCH(1,('GMW - Baseline'!$MC$2:$MC$200=G$3)*('GMW - Baseline'!$MB$2:$MB$200=G$4),0),$E43-1973)} -> 211167 | H43: {=INDEX('GMW - Baseline'!$A$2:$MC$200,MATCH(1,('GMW - Baseline'!$MC$2:$MC$200=H$3)*('GMW - Baseline'!$MB$2:$MB$200=H$4),0),$E43-1973)} -> 51 | I43: {=INDEX('GMW - Baseline'!$A$2:$MC$200,MATCH(1,('GMW - Baseline'!$MC$2:$MC$200=I$3)*('GMW - Baseline'!$MB$2:$MB$200=I$4),0),$E43-1973)} -> 12.875 | J43: {=INDEX('GMW - Baseline'!$A$2:$MC$200,MATCH(1,('GMW - Baseline'!$MC$2:$MC$200=J$3)*('GMW - Baseline'!$MB$2:$MB$200=J$4),0),$E43-1973)} -> #N/A | K43: {=INDEX('GMW - Baseline'!$A$2:$MC$200,MATCH(1,('GMW - Baseline'!$MC$2:$MC$200=K$3)*('GMW - Baseline'!$MB$2:$MB$200=K$4),0),$E43-1973)} -> #N/A | L43: {=INDEX('GMW - Baseline'!$A$2:$MC$200,MATCH(1,('GMW - Baseline'!$MC$2:$MC$200=L$3)*('GMW - Baseline'!$MB$2:$MB$200=L$4),0),$E43-1973)} -> #N/A | M43: {=INDEX('GMW - Baseline'!$A$2:$MC$200,MATCH(1,('GMW - Baseline'!$MC$2:$MC$200=M$3)*('GMW - Baseline'!$MB$2:$MB$200=M$4),0),$E43-1973)} -> #N/A | ... T43: {=INDEX('GMW - Baseline'!$A$2:$MC$200,MATCH(1,('GMW - Baseline'!$MC$2:$MC$200=T$3)*('GMW - Baseline'!$MB$2:$MB$200=T$4),0),$E43-1973)} -> #N/A
B44: =+B40+1 -> 1989 | C44: =+C40+1 -> 1989 | E44: =+E43+1 -> 2017 | F44: {=INDEX('GMW - Baseline'!$A$2:$MC$200,MATCH(1,('GMW - Baseline'!$MC$2:$MC$200=F$3)*('GMW - Baseline'!$MB$2:$MB$200=F$4),0),$E44-1973)} -> 376951 | G44: {=INDEX('GMW - Baseline'!$A$2:$MC$200,MATCH(1,('GMW - Baseline'!$MC$2:$MC$200=G$3)*('GMW - Baseline'!$MB$2:$MB$200=G$4),0),$E44-1973)} -> 212989 | H44: {=INDEX('GMW - Baseline'!$A$2:$MC$200,MATCH(1,('GMW - Baseline'!$MC$2:$MC$200=H$3)*('GMW - Baseline'!$MB$2:$MB$200=H$4),0),$E44-1973)} -> 52.13334 | I44: {=INDEX('GMW - Baseline'!$A$2:$MC$200,MATCH(1,('GMW - Baseline'!$MC$2:$MC$200=I$3)*('GMW - Baseline'!$MB$2:$MB$200=I$4),0),$E44-1973)} -> 13.23846 | J44: {=INDEX('GMW - Baseline'!$A$2:$MC$200,MATCH(1,('GMW - Baseline'!$MC$2:$MC$200=J$3)*('GMW - Baseline'!$MB$2:$MB$200=J$4),0),$E44-1973)} -> #N/A | K44: {=INDEX('GMW - Baseline'!$A$2:$MC$200,MATCH(1,('GMW - Baseline'!$MC$2:$MC$200=K$3)*('GMW - Baseline'!$MB$2:$MB$200=K$4),0),$E44-1973)} -> #N/A | L44: {=INDEX('GMW - Baseline'!$A$2:$MC$200,MATCH(1,('GMW - Baseline'!$MC$2:$MC$200=L$3)*('GMW - Baseline'!$MB$2:$MB$200=L$4),0),$E44-1973)} -> #N/A | M44: {=INDEX('GMW - Baseline'!$A$2:$MC$200,MATCH(1,('GMW - Baseline'!$MC$2:$MC$200=M$3)*('GMW - Baseline'!$MB$2:$MB$200=M$4),0),$E44-1973)} -> #N/A | ... T44: {=INDEX('GMW - Baseline'!$A$2:$MC$200,MATCH(1,('GMW - Baseline'!$MC$2:$MC$200=T$3)*('GMW - Baseline'!$MB$2:$MB$200=T$4),0),$E44-1973)} -> #N/A
B45: =+B41+1 -> 1989 | C45: =+C41+1 -> 1989 | E45: =+E44+1 -> 2018 | F45: {=INDEX('GMW - Baseline'!$A$2:$MC$200,MATCH(1,('GMW - Baseline'!$MC$2:$MC$200=F$3)*('GMW - Baseline'!$MB$2:$MB$200=F$4),0),$E45-1973)} -> 377573 | G45: {=INDEX('GMW - Baseline'!$A$2:$MC$200,MATCH(1,('GMW - Baseline'!$MC$2:$MC$200=G$3)*('GMW - Baseline'!$MB$2:$MB$200=G$4),0),$E45-1973)} -> 212810 | H45: {=INDEX('GMW - Baseline'!$A$2:$MC$200,MATCH(1,('GMW - Baseline'!$MC$2:$MC$200=H$3)*('GMW - Baseline'!$MB$2:$MB$200=H$4),0),$E45-1973)} -> 52.46667 | I45: {=INDEX('GMW - Baseline'!$A$2:$MC$200,MATCH(1,('GMW - Baseline'!$MC$2:$MC$200=I$3)*('GMW - Baseline'!$MB$2:$MB$200=I$4),0),$E45-1973)} -> 13.76058 | J45: {=INDEX('GMW - Baseline'!$A$2:$MC$200,MATCH(1,('GMW - Baseline'!$MC$2:$MC$200=J$3)*('GMW - Baseline'!$MB$2:$MB$200=J$4),0),$E45-1973)} -> #N/A | K45: {=INDEX('GMW - Baseline'!$A$2:$MC$200,MATCH(1,('GMW - Baseline'!$MC$2:$MC$200=K$3)*('GMW - Baseline'!$MB$2:$MB$200=K$4),0),$E45-1973)} -> #N/A | L45: {=INDEX('GMW - Baseline'!$A$2:$MC$200,MATCH(1,('GMW - Baseline'!$MC$2:$MC$200=L$3)*('GMW - Baseline'!$MB$2:$MB$200=L$4),0),$E45-1973)} -> #N/A | M45: {=INDEX('GMW - Baseline'!$A$2:$MC$200,MATCH(1,('GMW - Baseline'!$MC$2:$MC$200=M$3)*('GMW - Baseline'!$MB$2:$MB$200=M$4),0),$E45-1973)} -> #N/A | ... T45: {=INDEX('GMW - Baseline'!$A$2:$MC$200,MATCH(1,('GMW - Baseline'!$MC$2:$MC$200=T$3)*('GMW - Baseline'!$MB$2:$MB$200=T$4),0),$E45-1973)} -> #N/A
B46: =+B42+1 -> 1989 | C46: =+C42+1 -> 1989 | E46: =+E45+1 -> 2019 | F46: {=INDEX('GMW - Baseline'!$A$2:$MC$200,MATCH(1,('GMW - Baseline'!$MC$2:$MC$200=F$3)*('GMW - Baseline'!$MB$2:$MB$200=F$4),0),$E46-1973)} -> 377508 | G46: {=INDEX('GMW - Baseline'!$A$2:$MC$200,MATCH(1,('GMW - Baseline'!$MC$2:$MC$200=G$3)*('GMW - Baseline'!$MB$2:$MB$200=G$4),0),$E46-1973)} -> 213685 | H46: {=INDEX('GMW - Baseline'!$A$2:$MC$200,MATCH(1,('GMW - Baseline'!$MC$2:$MC$200=H$3)*('GMW - Baseline'!$MB$2:$MB$200=H$4),0),$E46-1973)} -> 53.26667 | I46: {=INDEX('GMW - Baseline'!$A$2:$MC$200,MATCH(1,('GMW - Baseline'!$MC$2:$MC$200=I$3)*('GMW - Baseline'!$MB$2:$MB$200=I$4),0),$E46-1973)} -> 14.80577 | J46: {=INDEX('GMW - Baseline'!$A$2:$MC$200,MATCH(1,('GMW - Baseline'!$MC$2:$MC$200=J$3)*('GMW - Baseline'!$MB$2:$MB$200=J$4),0),$E46-1973)} -> #N/A | K46: {=INDEX('GMW - Baseline'!$A$2:$MC$200,MATCH(1,('GMW - Baseline'!$MC$2:$MC$200=K$3)*('GMW - Baseline'!$MB$2:$MB$200=K$4),0),$E46-1973)} -> #N/A | L46: {=INDEX('GMW - Baseline'!$A$2:$MC$200,MATCH(1,('GMW - Baseline'!$MC$2:$MC$200=L$3)*('GMW - Baseline'!$MB$2:$MB$200=L$4),0),$E46-1973)} -> #N/A | M46: {=INDEX('GMW - Baseline'!$A$2:$MC$200,MATCH(1,('GMW - Baseline'!$MC$2:$MC$200=M$3)*('GMW - Baseline'!$MB$2:$MB$200=M$4),0),$E46-1973)} -> #N/A | ... T46: {=INDEX('GMW - Baseline'!$A$2:$MC$200,MATCH(1,('GMW - Baseline'!$MC$2:$MC$200=T$3)*('GMW - Baseline'!$MB$2:$MB$200=T$4),0),$E46-1973)} -> #N/A
A47: 1990 | B47: =+B43+1 -> 1990 | C47: =+C43+1 -> 1989 | D47: =+D43+1 -> 1989 | E47: =+E46+1 -> 2020 | F47: {=INDEX('GMW - Baseline'!$A$2:$MC$200,MATCH(1,('GMW - Baseline'!$MC$2:$MC$200=F$3)*('GMW - Baseline'!$MB$2:$MB$200=F$4),0),$E47-1973)} -> 379458 | G47: {=INDEX('GMW - Baseline'!$A$2:$MC$200,MATCH(1,('GMW - Baseline'!$MC$2:$MC$200=G$3)*('GMW - Baseline'!$MB$2:$MB$200=G$4),0),$E47-1973)} -> 215861 | H47: {=INDEX('GMW - Baseline'!$A$2:$MC$200,MATCH(1,('GMW - Baseline'!$MC$2:$MC$200=H$3)*('GMW - Baseline'!$MB$2:$MB$200=H$4),0),$E47-1973)} -> 53.93333 | I47: {=INDEX('GMW - Baseline'!$A$2:$MC$200,MATCH(1,('GMW - Baseline'!$MC$2:$MC$200=I$3)*('GMW - Baseline'!$MB$2:$MB$200=I$4),0),$E47-1973)} -> 14.875 | J47: {=INDEX('GMW - Baseline'!$A$2:$MC$200,MATCH(1,('GMW - Baseline'!$MC$2:$MC$200=J$3)*('GMW - Baseline'!$MB$2:$MB$200=J$4),0),$E47-1973)} -> #N/A | K47: {=INDEX('GMW - Baseline'!$A$2:$MC$200,MATCH(1,('GMW - Baseline'!$MC$2:$MC$200=K$3)*('GMW - Baseline'!$MB$2:$MB$200=K$4),0),$E47-1973)} -> #N/A | L47: {=INDEX('GMW - Baseline'!$A$2:$MC$200,MATCH(1,('GMW - Baseline'!$MC$2:$MC$200=L$3)*('GMW - Baseline'!$MB$2:$MB$200=L$4),0),$E47-1973)} -> #N/A | M47: {=INDEX('GMW - Baseline'!$A$2:$MC$200,MATCH(1,('GMW - Baseline'!$MC$2:$MC$200=M$3)*('GMW - Baseline'!$MB$2:$MB$200=M$4),0),$E47-1973)} -> #N/A | ... T47: {=INDEX('GMW - Baseline'!$A$2:$MC$200,MATCH(1,('GMW - Baseline'!$MC$2:$MC$200=T$3)*('GMW - Baseline'!$MB$2:$MB$200=T$4),0),$E47-1973)} -> #N/A
B48: =+B44+1 -> 1990 | C48: =+C44+1 -> 1990 | E48: =+E47+1 -> 2021 | F48: {=INDEX('GMW - Baseline'!$A$2:$MC$200,MATCH(1,('GMW - Baseline'!$MC$2:$MC$200=F$3)*('GMW - Baseline'!$MB$2:$MB$200=F$4),0),$E48-1973)} -> 381997 | G48: {=INDEX('GMW - Baseline'!$A$2:$MC$200,MATCH(1,('GMW - Baseline'!$MC$2:$MC$200=G$3)*('GMW - Baseline'!$MB$2:$MB$200=G$4),0),$E48-1973)} -> 216571 | H48: {=INDEX('GMW - Baseline'!$A$2:$MC$200,MATCH(1,('GMW - Baseline'!$MC$2:$MC$200=H$3)*('GMW - Baseline'!$MB$2:$MB$200=H$4),0),$E48-1973)} -> 55.6 | I48: {=INDEX('GMW - Baseline'!$A$2:$MC$200,MATCH(1,('GMW - Baseline'!$MC$2:$MC$200=I$3)*('GMW - Baseline'!$MB$2:$MB$200=I$4),0),$E48-1973)} -> 14.875 | J48: {=INDEX('GMW - Baseline'!$A$2:$MC$200,MATCH(1,('GMW - Baseline'!$MC$2:$MC$200=J$3)*('GMW - Baseline'!$MB$2:$MB$200=J$4),0),$E48-1973)} -> #N/A | K48: {=INDEX('GMW - Baseline'!$A$2:$MC$200,MATCH(1,('GMW - Baseline'!$MC$2:$MC$200=K$3)*('GMW - Baseline'!$MB$2:$MB$200=K$4),0),$E48-1973)} -> #N/A | L48: {=INDEX('GMW - Baseline'!$A$2:$MC$200,MATCH(1,('GMW - Baseline'!$MC$2:$MC$200=L$3)*('GMW - Baseline'!$MB$2:$MB$200=L$4),0),$E48-1973)} -> #N/A | M48: {=INDEX('GMW - Baseline'!$A$2:$MC$200,MATCH(1,('GMW - Baseline'!$MC$2:$MC$200=M$3)*('GMW - Baseline'!$MB$2:$MB$200=M$4),0),$E48-1973)} -> #N/A | ... T48: {=INDEX('GMW - Baseline'!$A$2:$MC$200,MATCH(1,('GMW - Baseline'!$MC$2:$MC$200=T$3)*('GMW - Baseline'!$MB$2:$MB$200=T$4),0),$E48-1973)} -> #N/A
B49: =+B45+1 -> 1990 | C49: =+C45+1 -> 1990 | E49: =+E48+1 -> 2022 | F49: {=INDEX('GMW - Baseline'!$A$2:$MC$200,MATCH(1,('GMW - Baseline'!$MC$2:$MC$200=F$3)*('GMW - Baseline'!$MB$2:$MB$200=F$4),0),$E49-1973)} -> 377831 | G49: {=INDEX('GMW - Baseline'!$A$2:$MC$200,MATCH(1,('GMW - Baseline'!$MC$2:$MC$200=G$3)*('GMW - Baseline'!$MB$2:$MB$200=G$4),0),$E49-1973)} -> 215211 | H49: {=INDEX('GMW - Baseline'!$A$2:$MC$200,MATCH(1,('GMW - Baseline'!$MC$2:$MC$200=H$3)*('GMW - Baseline'!$MB$2:$MB$200=H$4),0),$E49-1973)} -> 56.4 | I49: {=INDEX('GMW - Baseline'!$A$2:$MC$200,MATCH(1,('GMW - Baseline'!$MC$2:$MC$200=I$3)*('GMW - Baseline'!$MB$2:$MB$200=I$4),0),$E49-1973)} -> 14.875 | J49: {=INDEX('GMW - Baseline'!$A$2:$MC$200,MATCH(1,('GMW - Baseline'!$MC$2:$MC$200=J$3)*('GMW - Baseline'!$MB$2:$MB$200=J$4),0),$E49-1973)} -> #N/A | K49: {=INDEX('GMW - Baseline'!$A$2:$MC$200,MATCH(1,('GMW - Baseline'!$MC$2:$MC$200=K$3)*('GMW - Baseline'!$MB$2:$MB$200=K$4),0),$E49-1973)} -> #N/A | L49: {=INDEX('GMW - Baseline'!$A$2:$MC$200,MATCH(1,('GMW - Baseline'!$MC$2:$MC$200=L$3)*('GMW - Baseline'!$MB$2:$MB$200=L$4),0),$E49-1973)} -> #N/A | M49: {=INDEX('GMW - Baseline'!$A$2:$MC$200,MATCH(1,('GMW - Baseline'!$MC$2:$MC$200=M$3)*('GMW - Baseline'!$MB$2:$MB$200=M$4),0),$E49-1973)} -> #N/A | ... T49: {=INDEX('GMW - Baseline'!$A$2:$MC$200,MATCH(1,('GMW - Baseline'!$MC$2:$MC$200=T$3)*('GMW - Baseline'!$MB$2:$MB$200=T$4),0),$E49-1973)} -> #N/A
B50: =+B46+1 -> 1990 | C50: =+C46+1 -> 1990 | E50: =+E49+1 -> 2023 | F50: {=INDEX('GMW - Baseline'!$A$2:$MC$200,MATCH(1,('GMW - Baseline'!$MC$2:$MC$200=F$3)*('GMW - Baseline'!$MB$2:$MB$200=F$4),0),$E50-1973)} -> 375916 | G50: {=INDEX('GMW - Baseline'!$A$2:$MC$200,MATCH(1,('GMW - Baseline'!$MC$2:$MC$200=G$3)*('GMW - Baseline'!$MB$2:$MB$200=G$4),0),$E50-1973)} -> 215007 | H50: {=INDEX('GMW - Baseline'!$A$2:$MC$200,MATCH(1,('GMW - Baseline'!$MC$2:$MC$200=H$3)*('GMW - Baseline'!$MB$2:$MB$200=H$4),0),$E50-1973)} -> 57.46667 | I50: {=INDEX('GMW - Baseline'!$A$2:$MC$200,MATCH(1,('GMW - Baseline'!$MC$2:$MC$200=I$3)*('GMW - Baseline'!$MB$2:$MB$200=I$4),0),$E50-1973)} -> 13.95076 | J50: {=INDEX('GMW - Baseline'!$A$2:$MC$200,MATCH(1,('GMW - Baseline'!$MC$2:$MC$200=J$3)*('GMW - Baseline'!$MB$2:$MB$200=J$4),0),$E50-1973)} -> #N/A | K50: {=INDEX('GMW - Baseline'!$A$2:$MC$200,MATCH(1,('GMW - Baseline'!$MC$2:$MC$200=K$3)*('GMW - Baseline'!$MB$2:$MB$200=K$4),0),$E50-1973)} -> #N/A | L50: {=INDEX('GMW - Baseline'!$A$2:$MC$200,MATCH(1,('GMW - Baseline'!$MC$2:$MC$200=L$3)*('GMW - Baseline'!$MB$2:$MB$200=L$4),0),$E50-1973)} -> #N/A | M50: {=INDEX('GMW - Baseline'!$A$2:$MC$200,MATCH(1,('GMW - Baseline'!$MC$2:$MC$200=M$3)*('GMW - Baseline'!$MB$2:$MB$200=M$4),0),$E50-1973)} -> #N/A | ... T50: {=INDEX('GMW - Baseline'!$A$2:$MC$200,MATCH(1,('GMW - Baseline'!$MC$2:$MC$200=T$3)*('GMW - Baseline'!$MB$2:$MB$200=T$4),0),$E50-1973)} -> #N/A
A51: 1991 | B51: =+B47+1 -> 1991 | C51: =+C47+1 -> 1990 | D51: =+D47+1 -> 1990 | E51: =+E50+1 -> 2024 | F51: {=INDEX('GMW - Baseline'!$A$2:$MC$200,MATCH(1,('GMW - Baseline'!$MC$2:$MC$200=F$3)*('GMW - Baseline'!$MB$2:$MB$200=F$4),0),$E51-1973)} -> 374060 | G51: {=INDEX('GMW - Baseline'!$A$2:$MC$200,MATCH(1,('GMW - Baseline'!$MC$2:$MC$200=G$3)*('GMW - Baseline'!$MB$2:$MB$200=G$4),0),$E51-1973)} -> 214735 | H51: {=INDEX('GMW - Baseline'!$A$2:$MC$200,MATCH(1,('GMW - Baseline'!$MC$2:$MC$200=H$3)*('GMW - Baseline'!$MB$2:$MB$200=H$4),0),$E51-1973)} -> 57.66667 | I51: {=INDEX('GMW - Baseline'!$A$2:$MC$200,MATCH(1,('GMW - Baseline'!$MC$2:$MC$200=I$3)*('GMW - Baseline'!$MB$2:$MB$200=I$4),0),$E51-1973)} -> 13.39063 | J51: {=INDEX('GMW - Baseline'!$A$2:$MC$200,MATCH(1,('GMW - Baseline'!$MC$2:$MC$200=J$3)*('GMW - Baseline'!$MB$2:$MB$200=J$4),0),$E51-1973)} -> #N/A | K51: {=INDEX('GMW - Baseline'!$A$2:$MC$200,MATCH(1,('GMW - Baseline'!$MC$2:$MC$200=K$3)*('GMW - Baseline'!$MB$2:$MB$200=K$4),0),$E51-1973)} -> #N/A | L51: {=INDEX('GMW - Baseline'!$A$2:$MC$200,MATCH(1,('GMW - Baseline'!$MC$2:$MC$200=L$3)*('GMW - Baseline'!$MB$2:$MB$200=L$4),0),$E51-1973)} -> #N/A | M51: {=INDEX('GMW - Baseline'!$A$2:$MC$200,MATCH(1,('GMW - Baseline'!$MC$2:$MC$200=M$3)*('GMW - Baseline'!$MB$2:$MB$200=M$4),0),$E51-1973)} -> #N/A | ... T51: {=INDEX('GMW - Baseline'!$A$2:$MC$200,MATCH(1,('GMW - Baseline'!$MC$2:$MC$200=T$3)*('GMW - Baseline'!$MB$2:$MB$200=T$4),0),$E51-1973)} -> #N/A
B52: =+B48+1 -> 1991 | C52: =+C48+1 -> 1991 | E52: =+E51+1 -> 2025 | F52: {=INDEX('GMW - Baseline'!$A$2:$MC$200,MATCH(1,('GMW - Baseline'!$MC$2:$MC$200=F$3)*('GMW - Baseline'!$MB$2:$MB$200=F$4),0),$E52-1973)} -> 373608 | G52: {=INDEX('GMW - Baseline'!$A$2:$MC$200,MATCH(1,('GMW - Baseline'!$MC$2:$MC$200=G$3)*('GMW - Baseline'!$MB$2:$MB$200=G$4),0),$E52-1973)} -> 213315 | H52: {=INDEX('GMW - Baseline'!$A$2:$MC$200,MATCH(1,('GMW - Baseline'!$MC$2:$MC$200=H$3)*('GMW - Baseline'!$MB$2:$MB$200=H$4),0),$E52-1973)} -> 60.26667 | I52: {=INDEX('GMW - Baseline'!$A$2:$MC$200,MATCH(1,('GMW - Baseline'!$MC$2:$MC$200=I$3)*('GMW - Baseline'!$MB$2:$MB$200=I$4),0),$E52-1973)} -> 11.74423 | J52: {=INDEX('GMW - Baseline'!$A$2:$MC$200,MATCH(1,('GMW - Baseline'!$MC$2:$MC$200=J$3)*('GMW - Baseline'!$MB$2:$MB$200=J$4),0),$E52-1973)} -> #N/A | K52: {=INDEX('GMW - Baseline'!$A$2:$MC$200,MATCH(1,('GMW - Baseline'!$MC$2:$MC$200=K$3)*('GMW - Baseline'!$MB$2:$MB$200=K$4),0),$E52-1973)} -> #N/A | L52: {=INDEX('GMW - Baseline'!$A$2:$MC$200,MATCH(1,('GMW - Baseline'!$MC$2:$MC$200=L$3)*('GMW - Baseline'!$MB$2:$MB$200=L$4),0),$E52-1973)} -> #N/A | M52: {=INDEX('GMW - Baseline'!$A$2:$MC$200,MATCH(1,('GMW - Baseline'!$MC$2:$MC$200=M$3)*('GMW - Baseline'!$MB$2:$MB$200=M$4),0),$E52-1973)} -> #N/A | ... T52: {=INDEX('GMW - Baseline'!$A$2:$MC$200,MATCH(1,('GMW - Baseline'!$MC$2:$MC$200=T$3)*('GMW - Baseline'!$MB$2:$MB$200=T$4),0),$E52-1973)} -> #N/A
B53: =+B49+1 -> 1991 | C53: =+C49+1 -> 1991 | E53: =+E52+1 -> 2026 | F53: {=INDEX('GMW - Baseline'!$A$2:$MC$200,MATCH(1,('GMW - Baseline'!$MC$2:$MC$200=F$3)*('GMW - Baseline'!$MB$2:$MB$200=F$4),0),$E53-1973)} -> 372878 | G53: {=INDEX('GMW - Baseline'!$A$2:$MC$200,MATCH(1,('GMW - Baseline'!$MC$2:$MC$200=G$3)*('GMW - Baseline'!$MB$2:$MB$200=G$4),0),$E53-1973)} -> 213544 | H53: {=INDEX('GMW - Baseline'!$A$2:$MC$200,MATCH(1,('GMW - Baseline'!$MC$2:$MC$200=H$3)*('GMW - Baseline'!$MB$2:$MB$200=H$4),0),$E53-1973)} -> 60.83333 | I53: {=INDEX('GMW - Baseline'!$A$2:$MC$200,MATCH(1,('GMW - Baseline'!$MC$2:$MC$200=I$3)*('GMW - Baseline'!$MB$2:$MB$200=I$4),0),$E53-1973)} -> 10.79924 | J53: {=INDEX('GMW - Baseline'!$A$2:$MC$200,MATCH(1,('GMW - Baseline'!$MC$2:$MC$200=J$3)*('GMW - Baseline'!$MB$2:$MB$200=J$4),0),$E53-1973)} -> #N/A | K53: {=INDEX('GMW - Baseline'!$A$2:$MC$200,MATCH(1,('GMW - Baseline'!$MC$2:$MC$200=K$3)*('GMW - Baseline'!$MB$2:$MB$200=K$4),0),$E53-1973)} -> #N/A | L53: {=INDEX('GMW - Baseline'!$A$2:$MC$200,MATCH(1,('GMW - Baseline'!$MC$2:$MC$200=L$3)*('GMW - Baseline'!$MB$2:$MB$200=L$4),0),$E53-1973)} -> #N/A | M53: {=INDEX('GMW - Baseline'!$A$2:$MC$200,MATCH(1,('GMW - Baseline'!$MC$2:$MC$200=M$3)*('GMW - Baseline'!$MB$2:$MB$200=M$4),0),$E53-1973)} -> #N/A | ... T53: {=INDEX('GMW - Baseline'!$A$2:$MC$200,MATCH(1,('GMW - Baseline'!$MC$2:$MC$200=T$3)*('GMW - Baseline'!$MB$2:$MB$200=T$4),0),$E53-1973)} -> #N/A
B54: =+B50+1 -> 1991 | C54: =+C50+1 -> 1991 | E54: =+E53+1 -> 2027 | F54: {=INDEX('GMW - Baseline'!$A$2:$MC$200,MATCH(1,('GMW - Baseline'!$MC$2:$MC$200=F$3)*('GMW - Baseline'!$MB$2:$MB$200=F$4),0),$E54-1973)} -> 373357 | G54: {=INDEX('GMW - Baseline'!$A$2:$MC$200,MATCH(1,('GMW - Baseline'!$MC$2:$MC$200=G$3)*('GMW - Baseline'!$MB$2:$MB$200=G$4),0),$E54-1973)} -> 213576 | H54: {=INDEX('GMW - Baseline'!$A$2:$MC$200,MATCH(1,('GMW - Baseline'!$MC$2:$MC$200=H$3)*('GMW - Baseline'!$MB$2:$MB$200=H$4),0),$E54-1973)} -> 61.46667 | I54: {=INDEX('GMW - Baseline'!$A$2:$MC$200,MATCH(1,('GMW - Baseline'!$MC$2:$MC$200=I$3)*('GMW - Baseline'!$MB$2:$MB$200=I$4),0),$E54-1973)} -> 10.375 | J54: {=INDEX('GMW - Baseline'!$A$2:$MC$200,MATCH(1,('GMW - Baseline'!$MC$2:$MC$200=J$3)*('GMW - Baseline'!$MB$2:$MB$200=J$4),0),$E54-1973)} -> #N/A | K54: {=INDEX('GMW - Baseline'!$A$2:$MC$200,MATCH(1,('GMW - Baseline'!$MC$2:$MC$200=K$3)*('GMW - Baseline'!$MB$2:$MB$200=K$4),0),$E54-1973)} -> #N/A | L54: {=INDEX('GMW - Baseline'!$A$2:$MC$200,MATCH(1,('GMW - Baseline'!$MC$2:$MC$200=L$3)*('GMW - Baseline'!$MB$2:$MB$200=L$4),0),$E54-1973)} -> #N/A | M54: {=INDEX('GMW - Baseline'!$A$2:$MC$200,MATCH(1,('GMW - Baseline'!$MC$2:$MC$200=M$3)*('GMW - Baseline'!$MB$2:$MB$200=M$4),0),$E54-1973)} -> #N/A | ... T54: {=INDEX('GMW - Baseline'!$A$2:$MC$200,MATCH(1,('GMW - Baseline'!$MC$2:$MC$200=T$3)*('GMW - Baseline'!$MB$2:$MB$200=T$4),0),$E54-1973)} -> #N/A
A55: 1992 | B55: =+B51+1 -> 1992 | C55: =+C51+1 -> 1991 | D55: =+D51+1 -> 1991 | E55: =+E54+1 -> 2028 | F55: {=INDEX('GMW - Baseline'!$A$2:$MC$200,MATCH(1,('GMW - Baseline'!$MC$2:$MC$200=F$3)*('GMW - Baseline'!$MB$2:$MB$200=F$4),0),$E55-1973)} -> 373317 | G55: {=INDEX('GMW - Baseline'!$A$2:$MC$200,MATCH(1,('GMW - Baseline'!$MC$2:$MC$200=G$3)*('GMW - Baseline'!$MB$2:$MB$200=G$4),0),$E55-1973)} -> 213040 | H55: {=INDEX('GMW - Baseline'!$A$2:$MC$200,MATCH(1,('GMW - Baseline'!$MC$2:$MC$200=H$3)*('GMW - Baseline'!$MB$2:$MB$200=H$4),0),$E55-1973)} -> 61.7 | I55: {=INDEX('GMW - Baseline'!$A$2:$MC$200,MATCH(1,('GMW - Baseline'!$MC$2:$MC$200=I$3)*('GMW - Baseline'!$MB$2:$MB$200=I$4),0),$E55-1973)} -> 10.375 | J55: {=INDEX('GMW - Baseline'!$A$2:$MC$200,MATCH(1,('GMW - Baseline'!$MC$2:$MC$200=J$3)*('GMW - Baseline'!$MB$2:$MB$200=J$4),0),$E55-1973)} -> #N/A | K55: {=INDEX('GMW - Baseline'!$A$2:$MC$200,MATCH(1,('GMW - Baseline'!$MC$2:$MC$200=K$3)*('GMW - Baseline'!$MB$2:$MB$200=K$4),0),$E55-1973)} -> #N/A | L55: {=INDEX('GMW - Baseline'!$A$2:$MC$200,MATCH(1,('GMW - Baseline'!$MC$2:$MC$200=L$3)*('GMW - Baseline'!$MB$2:$MB$200=L$4),0),$E55-1973)} -> #N/A | M55: {=INDEX('GMW - Baseline'!$A$2:$MC$200,MATCH(1,('GMW - Baseline'!$MC$2:$MC$200=M$3)*('GMW - Baseline'!$MB$2:$MB$200=M$4),0),$E55-1973)} -> #N/A | ... T55: {=INDEX('GMW - Baseline'!$A$2:$MC$200,MATCH(1,('GMW - Baseline'!$MC$2:$MC$200=T$3)*('GMW - Baseline'!$MB$2:$MB$200=T$4),0),$E55-1973)} -> #N/A
B56: =+B52+1 -> 1992 | C56: =+C52+1 -> 1992 | E56: =+E55+1 -> 2029 | F56: {=INDEX('GMW - Baseline'!$A$2:$MC$200,MATCH(1,('GMW - Baseline'!$MC$2:$MC$200=F$3)*('GMW - Baseline'!$MB$2:$MB$200=F$4),0),$E56-1973)} -> 372751 | G56: {=INDEX('GMW - Baseline'!$A$2:$MC$200,MATCH(1,('GMW - Baseline'!$MC$2:$MC$200=G$3)*('GMW - Baseline'!$MB$2:$MB$200=G$4),0),$E56-1973)} -> 215855 | H56: {=INDEX('GMW - Baseline'!$A$2:$MC$200,MATCH(1,('GMW - Baseline'!$MC$2:$MC$200=H$3)*('GMW - Baseline'!$MB$2:$MB$200=H$4),0),$E56-1973)} -> 62.83333 | I56: {=INDEX('GMW - Baseline'!$A$2:$MC$200,MATCH(1,('GMW - Baseline'!$MC$2:$MC$200=I$3)*('GMW - Baseline'!$MB$2:$MB$200=I$4),0),$E56-1973)} -> 10.05962 | J56: {=INDEX('GMW - Baseline'!$A$2:$MC$200,MATCH(1,('GMW - Baseline'!$MC$2:$MC$200=J$3)*('GMW - Baseline'!$MB$2:$MB$200=J$4),0),$E56-1973)} -> #N/A | K56: {=INDEX('GMW - Baseline'!$A$2:$MC$200,MATCH(1,('GMW - Baseline'!$MC$2:$MC$200=K$3)*('GMW - Baseline'!$MB$2:$MB$200=K$4),0),$E56-1973)} -> #N/A | L56: {=INDEX('GMW - Baseline'!$A$2:$MC$200,MATCH(1,('GMW - Baseline'!$MC$2:$MC$200=L$3)*('GMW - Baseline'!$MB$2:$MB$200=L$4),0),$E56-1973)} -> #N/A | M56: {=INDEX('GMW - Baseline'!$A$2:$MC$200,MATCH(1,('GMW - Baseline'!$MC$2:$MC$200=M$3)*('GMW - Baseline'!$MB$2:$MB$200=M$4),0),$E56-1973)} -> #N/A | ... T56: {=INDEX('GMW - Baseline'!$A$2:$MC$200,MATCH(1,('GMW - Baseline'!$MC$2:$MC$200=T$3)*('GMW - Baseline'!$MB$2:$MB$200=T$4),0),$E56-1973)} -> #N/A
B57: =+B53+1 -> 1992 | C57: =+C53+1 -> 1992 | E57: =+E56+1 -> 2030 | F57: {=INDEX('GMW - Baseline'!$A$2:$MC$200,MATCH(1,('GMW - Baseline'!$MC$2:$MC$200=F$3)*('GMW - Baseline'!$MB$2:$MB$200=F$4),0),$E57-1973)} -> 374537 | G57: {=INDEX('GMW - Baseline'!$A$2:$MC$200,MATCH(1,('GMW - Baseline'!$MC$2:$MC$200=G$3)*('GMW - Baseline'!$MB$2:$MB$200=G$4),0),$E57-1973)} -> 217123 | H57: {=INDEX('GMW - Baseline'!$A$2:$MC$200,MATCH(1,('GMW - Baseline'!$MC$2:$MC$200=H$3)*('GMW - Baseline'!$MB$2:$MB$200=H$4),0),$E57-1973)} -> 62.73333 | I57: {=INDEX('GMW - Baseline'!$A$2:$MC$200,MATCH(1,('GMW - Baseline'!$MC$2:$MC$200=I$3)*('GMW - Baseline'!$MB$2:$MB$200=I$4),0),$E57-1973)} -> 9.768939 | J57: {=INDEX('GMW - Baseline'!$A$2:$MC$200,MATCH(1,('GMW - Baseline'!$MC$2:$MC$200=J$3)*('GMW - Baseline'!$MB$2:$MB$200=J$4),0),$E57-1973)} -> #N/A | K57: {=INDEX('GMW - Baseline'!$A$2:$MC$200,MATCH(1,('GMW - Baseline'!$MC$2:$MC$200=K$3)*('GMW - Baseline'!$MB$2:$MB$200=K$4),0),$E57-1973)} -> #N/A | L57: {=INDEX('GMW - Baseline'!$A$2:$MC$200,MATCH(1,('GMW - Baseline'!$MC$2:$MC$200=L$3)*('GMW - Baseline'!$MB$2:$MB$200=L$4),0),$E57-1973)} -> #N/A | M57: {=INDEX('GMW - Baseline'!$A$2:$MC$200,MATCH(1,('GMW - Baseline'!$MC$2:$MC$200=M$3)*('GMW - Baseline'!$MB$2:$MB$200=M$4),0),$E57-1973)} -> #N/A | ... T57: {=INDEX('GMW - Baseline'!$A$2:$MC$200,MATCH(1,('GMW - Baseline'!$MC$2:$MC$200=T$3)*('GMW - Baseline'!$MB$2:$MB$200=T$4),0),$E57-1973)} -> #N/A
B58: =+B54+1 -> 1992 | C58: =+C54+1 -> 1992 | E58: =+E57+1 -> 2031 | F58: {=INDEX('GMW - Baseline'!$A$2:$MC$200,MATCH(1,('GMW - Baseline'!$MC$2:$MC$200=F$3)*('GMW - Baseline'!$MB$2:$MB$200=F$4),0),$E58-1973)} -> 377418 | G58: {=INDEX('GMW - Baseline'!$A$2:$MC$200,MATCH(1,('GMW - Baseline'!$MC$2:$MC$200=G$3)*('GMW - Baseline'!$MB$2:$MB$200=G$4),0),$E58-1973)} -> 217528 | H58: {=INDEX('GMW - Baseline'!$A$2:$MC$200,MATCH(1,('GMW - Baseline'!$MC$2:$MC$200=H$3)*('GMW - Baseline'!$MB$2:$MB$200=H$4),0),$E58-1973)} -> 63.13334 | I58: {=INDEX('GMW - Baseline'!$A$2:$MC$200,MATCH(1,('GMW - Baseline'!$MC$2:$MC$200=I$3)*('GMW - Baseline'!$MB$2:$MB$200=I$4),0),$E58-1973)} -> 7.511364 | J58: {=INDEX('GMW - Baseline'!$A$2:$MC$200,MATCH(1,('GMW - Baseline'!$MC$2:$MC$200=J$3)*('GMW - Baseline'!$MB$2:$MB$200=J$4),0),$E58-1973)} -> #N/A | K58: {=INDEX('GMW - Baseline'!$A$2:$MC$200,MATCH(1,('GMW - Baseline'!$MC$2:$MC$200=K$3)*('GMW - Baseline'!$MB$2:$MB$200=K$4),0),$E58-1973)} -> #N/A | L58: {=INDEX('GMW - Baseline'!$A$2:$MC$200,MATCH(1,('GMW - Baseline'!$MC$2:$MC$200=L$3)*('GMW - Baseline'!$MB$2:$MB$200=L$4),0),$E58-1973)} -> #N/A | M58: {=INDEX('GMW - Baseline'!$A$2:$MC$200,MATCH(1,('GMW - Baseline'!$MC$2:$MC$200=M$3)*('GMW - Baseline'!$MB$2:$MB$200=M$4),0),$E58-1973)} -> #N/A | ... T58: {=INDEX('GMW - Baseline'!$A$2:$MC$200,MATCH(1,('GMW - Baseline'!$MC$2:$MC$200=T$3)*('GMW - Baseline'!$MB$2:$MB$200=T$4),0),$E58-1973)} -> #N/A
A59: 1993 | B59: =+B55+1 -> 1993 | C59: =+C55+1 -> 1992 | D59: =+D55+1 -> 1992 | E59: =+E58+1 -> 2032 | F59: {=INDEX('GMW - Baseline'!$A$2:$MC$200,MATCH(1,('GMW - Baseline'!$MC$2:$MC$200=F$3)*('GMW - Baseline'!$MB$2:$MB$200=F$4),0),$E59-1973)} -> 379370 | G59: {=INDEX('GMW - Baseline'!$A$2:$MC$200,MATCH(1,('GMW - Baseline'!$MC$2:$MC$200=G$3)*('GMW - Baseline'!$MB$2:$MB$200=G$4),0),$E59-1973)} -> 219343 | H59: {=INDEX('GMW - Baseline'!$A$2:$MC$200,MATCH(1,('GMW - Baseline'!$MC$2:$MC$200=H$3)*('GMW - Baseline'!$MB$2:$MB$200=H$4),0),$E59-1973)} -> 63.2 | I59: {=INDEX('GMW - Baseline'!$A$2:$MC$200,MATCH(1,('GMW - Baseline'!$MC$2:$MC$200=I$3)*('GMW - Baseline'!$MB$2:$MB$200=I$4),0),$E59-1973)} -> 6.140625 | J59: {=INDEX('GMW - Baseline'!$A$2:$MC$200,MATCH(1,('GMW - Baseline'!$MC$2:$MC$200=J$3)*('GMW - Baseline'!$MB$2:$MB$200=J$4),0),$E59-1973)} -> #N/A | K59: {=INDEX('GMW - Baseline'!$A$2:$MC$200,MATCH(1,('GMW - Baseline'!$MC$2:$MC$200=K$3)*('GMW - Baseline'!$MB$2:$MB$200=K$4),0),$E59-1973)} -> #N/A | L59: {=INDEX('GMW - Baseline'!$A$2:$MC$200,MATCH(1,('GMW - Baseline'!$MC$2:$MC$200=L$3)*('GMW - Baseline'!$MB$2:$MB$200=L$4),0),$E59-1973)} -> #N/A | M59: {=INDEX('GMW - Baseline'!$A$2:$MC$200,MATCH(1,('GMW - Baseline'!$MC$2:$MC$200=M$3)*('GMW - Baseline'!$MB$2:$MB$200=M$4),0),$E59-1973)} -> #N/A | ... T59: {=INDEX('GMW - Baseline'!$A$2:$MC$200,MATCH(1,('GMW - Baseline'!$MC$2:$MC$200=T$3)*('GMW - Baseline'!$MB$2:$MB$200=T$4),0),$E59-1973)} -> #N/A
B60: =+B56+1 -> 1993 | C60: =+C56+1 -> 1993 | E60: =+E59+1 -> 2033 | F60: {=INDEX('GMW - Baseline'!$A$2:$MC$200,MATCH(1,('GMW - Baseline'!$MC$2:$MC$200=F$3)*('GMW - Baseline'!$MB$2:$MB$200=F$4),0),$E60-1973)} -> 381045 | G60: {=INDEX('GMW - Baseline'!$A$2:$MC$200,MATCH(1,('GMW - Baseline'!$MC$2:$MC$200=G$3)*('GMW - Baseline'!$MB$2:$MB$200=G$4),0),$E60-1973)} -> 219780 | H60: {=INDEX('GMW - Baseline'!$A$2:$MC$200,MATCH(1,('GMW - Baseline'!$MC$2:$MC$200=H$3)*('GMW - Baseline'!$MB$2:$MB$200=H$4),0),$E60-1973)} -> 64.43333 | I60: {=INDEX('GMW - Baseline'!$A$2:$MC$200,MATCH(1,('GMW - Baseline'!$MC$2:$MC$200=I$3)*('GMW - Baseline'!$MB$2:$MB$200=I$4),0),$E60-1973)} -> 5.875 | J60: {=INDEX('GMW - Baseline'!$A$2:$MC$200,MATCH(1,('GMW - Baseline'!$MC$2:$MC$200=J$3)*('GMW - Baseline'!$MB$2:$MB$200=J$4),0),$E60-1973)} -> #N/A | K60: {=INDEX('GMW - Baseline'!$A$2:$MC$200,MATCH(1,('GMW - Baseline'!$MC$2:$MC$200=K$3)*('GMW - Baseline'!$MB$2:$MB$200=K$4),0),$E60-1973)} -> #N/A | L60: {=INDEX('GMW - Baseline'!$A$2:$MC$200,MATCH(1,('GMW - Baseline'!$MC$2:$MC$200=L$3)*('GMW - Baseline'!$MB$2:$MB$200=L$4),0),$E60-1973)} -> #N/A | M60: {=INDEX('GMW - Baseline'!$A$2:$MC$200,MATCH(1,('GMW - Baseline'!$MC$2:$MC$200=M$3)*('GMW - Baseline'!$MB$2:$MB$200=M$4),0),$E60-1973)} -> #N/A | ... T60: {=INDEX('GMW - Baseline'!$A$2:$MC$200,MATCH(1,('GMW - Baseline'!$MC$2:$MC$200=T$3)*('GMW - Baseline'!$MB$2:$MB$200=T$4),0),$E60-1973)} -> #N/A
B61: =+B57+1 -> 1993 | C61: =+C57+1 -> 1993 | E61: =+E60+1 -> 2034 | F61: {=INDEX('GMW - Baseline'!$A$2:$MC$200,MATCH(1,('GMW - Baseline'!$MC$2:$MC$200=F$3)*('GMW - Baseline'!$MB$2:$MB$200=F$4),0),$E61-1973)} -> 384524 | G61: {=INDEX('GMW - Baseline'!$A$2:$MC$200,MATCH(1,('GMW - Baseline'!$MC$2:$MC$200=G$3)*('GMW - Baseline'!$MB$2:$MB$200=G$4),0),$E61-1973)} -> 223611 | H61: {=INDEX('GMW - Baseline'!$A$2:$MC$200,MATCH(1,('GMW - Baseline'!$MC$2:$MC$200=H$3)*('GMW - Baseline'!$MB$2:$MB$200=H$4),0),$E61-1973)} -> 64.5 | I61: {=INDEX('GMW - Baseline'!$A$2:$MC$200,MATCH(1,('GMW - Baseline'!$MC$2:$MC$200=I$3)*('GMW - Baseline'!$MB$2:$MB$200=I$4),0),$E61-1973)} -> 5.875 | J61: {=INDEX('GMW - Baseline'!$A$2:$MC$200,MATCH(1,('GMW - Baseline'!$MC$2:$MC$200=J$3)*('GMW - Baseline'!$MB$2:$MB$200=J$4),0),$E61-1973)} -> #N/A | K61: {=INDEX('GMW - Baseline'!$A$2:$MC$200,MATCH(1,('GMW - Baseline'!$MC$2:$MC$200=K$3)*('GMW - Baseline'!$MB$2:$MB$200=K$4),0),$E61-1973)} -> #N/A | L61: {=INDEX('GMW - Baseline'!$A$2:$MC$200,MATCH(1,('GMW - Baseline'!$MC$2:$MC$200=L$3)*('GMW - Baseline'!$MB$2:$MB$200=L$4),0),$E61-1973)} -> #N/A | M61: {=INDEX('GMW - Baseline'!$A$2:$MC$200,MATCH(1,('GMW - Baseline'!$MC$2:$MC$200=M$3)*('GMW - Baseline'!$MB$2:$MB$200=M$4),0),$E61-1973)} -> #N/A | ... T61: {=INDEX('GMW - Baseline'!$A$2:$MC$200,MATCH(1,('GMW - Baseline'!$MC$2:$MC$200=T$3)*('GMW - Baseline'!$MB$2:$MB$200=T$4),0),$E61-1973)} -> #N/A
B62: =+B58+1 -> 1993 | C62: =+C58+1 -> 1993 | E62: =+E61+1 -> 2035 | F62: {=INDEX('GMW - Baseline'!$A$2:$MC$200,MATCH(1,('GMW - Baseline'!$MC$2:$MC$200=F$3)*('GMW - Baseline'!$MB$2:$MB$200=F$4),0),$E62-1973)} -> 387143 | G62: {=INDEX('GMW - Baseline'!$A$2:$MC$200,MATCH(1,('GMW - Baseline'!$MC$2:$MC$200=G$3)*('GMW - Baseline'!$MB$2:$MB$200=G$4),0),$E62-1973)} -> 225346 | H62: {=INDEX('GMW - Baseline'!$A$2:$MC$200,MATCH(1,('GMW - Baseline'!$MC$2:$MC$200=H$3)*('GMW - Baseline'!$MB$2:$MB$200=H$4),0),$E62-1973)} -> 64.66666 | I62: {=INDEX('GMW - Baseline'!$A$2:$MC$200,MATCH(1,('GMW - Baseline'!$MC$2:$MC$200=I$3)*('GMW - Baseline'!$MB$2:$MB$200=I$4),0),$E62-1973)} -> 5.655303 | J62: {=INDEX('GMW - Baseline'!$A$2:$MC$200,MATCH(1,('GMW - Baseline'!$MC$2:$MC$200=J$3)*('GMW - Baseline'!$MB$2:$MB$200=J$4),0),$E62-1973)} -> #N/A | K62: {=INDEX('GMW - Baseline'!$A$2:$MC$200,MATCH(1,('GMW - Baseline'!$MC$2:$MC$200=K$3)*('GMW - Baseline'!$MB$2:$MB$200=K$4),0),$E62-1973)} -> #N/A | L62: {=INDEX('GMW - Baseline'!$A$2:$MC$200,MATCH(1,('GMW - Baseline'!$MC$2:$MC$200=L$3)*('GMW - Baseline'!$MB$2:$MB$200=L$4),0),$E62-1973)} -> #N/A | M62: {=INDEX('GMW - Baseline'!$A$2:$MC$200,MATCH(1,('GMW - Baseline'!$MC$2:$MC$200=M$3)*('GMW - Baseline'!$MB$2:$MB$200=M$4),0),$E62-1973)} -> #N/A | ... T62: {=INDEX('GMW - Baseline'!$A$2:$MC$200,MATCH(1,('GMW - Baseline'!$MC$2:$MC$200=T$3)*('GMW - Baseline'!$MB$2:$MB$200=T$4),0),$E62-1973)} -> #N/A
A63: 1994 | B63: =+B59+1 -> 1994 | C63: =+C59+1 -> 1993 | D63: =+D59+1 -> 1993 | E63: =+E62+1 -> 2036 | F63: {=INDEX('GMW - Baseline'!$A$2:$MC$200,MATCH(1,('GMW - Baseline'!$MC$2:$MC$200=F$3)*('GMW - Baseline'!$MB$2:$MB$200=F$4),0),$E63-1973)} -> 391026 | G63: {=INDEX('GMW - Baseline'!$A$2:$MC$200,MATCH(1,('GMW - Baseline'!$MC$2:$MC$200=G$3)*('GMW - Baseline'!$MB$2:$MB$200=G$4),0),$E63-1973)} -> 227586 | H63: {=INDEX('GMW - Baseline'!$A$2:$MC$200,MATCH(1,('GMW - Baseline'!$MC$2:$MC$200=H$3)*('GMW - Baseline'!$MB$2:$MB$200=H$4),0),$E63-1973)} -> 64.76667 | I63: {=INDEX('GMW - Baseline'!$A$2:$MC$200,MATCH(1,('GMW - Baseline'!$MC$2:$MC$200=I$3)*('GMW - Baseline'!$MB$2:$MB$200=I$4),0),$E63-1973)} -> 5.226563 | J63: {=INDEX('GMW - Baseline'!$A$2:$MC$200,MATCH(1,('GMW - Baseline'!$MC$2:$MC$200=J$3)*('GMW - Baseline'!$MB$2:$MB$200=J$4),0),$E63-1973)} -> #N/A | K63: {=INDEX('GMW - Baseline'!$A$2:$MC$200,MATCH(1,('GMW - Baseline'!$MC$2:$MC$200=K$3)*('GMW - Baseline'!$MB$2:$MB$200=K$4),0),$E63-1973)} -> #N/A | L63: {=INDEX('GMW - Baseline'!$A$2:$MC$200,MATCH(1,('GMW - Baseline'!$MC$2:$MC$200=L$3)*('GMW - Baseline'!$MB$2:$MB$200=L$4),0),$E63-1973)} -> #N/A | M63: {=INDEX('GMW - Baseline'!$A$2:$MC$200,MATCH(1,('GMW - Baseline'!$MC$2:$MC$200=M$3)*('GMW - Baseline'!$MB$2:$MB$200=M$4),0),$E63-1973)} -> #N/A | ... T63: {=INDEX('GMW - Baseline'!$A$2:$MC$200,MATCH(1,('GMW - Baseline'!$MC$2:$MC$200=T$3)*('GMW - Baseline'!$MB$2:$MB$200=T$4),0),$E63-1973)} -> #N/A
B64: =+B60+1 -> 1994 | C64: =+C60+1 -> 1994 | E64: =+E63+1 -> 2037 | F64: {=INDEX('GMW - Baseline'!$A$2:$MC$200,MATCH(1,('GMW - Baseline'!$MC$2:$MC$200=F$3)*('GMW - Baseline'!$MB$2:$MB$200=F$4),0),$E64-1973)} -> 394588 | G64: {=INDEX('GMW - Baseline'!$A$2:$MC$200,MATCH(1,('GMW - Baseline'!$MC$2:$MC$200=G$3)*('GMW - Baseline'!$MB$2:$MB$200=G$4),0),$E64-1973)} -> 227983 | H64: {=INDEX('GMW - Baseline'!$A$2:$MC$200,MATCH(1,('GMW - Baseline'!$MC$2:$MC$200=H$3)*('GMW - Baseline'!$MB$2:$MB$200=H$4),0),$E64-1973)} -> 65.7 | I64: {=INDEX('GMW - Baseline'!$A$2:$MC$200,MATCH(1,('GMW - Baseline'!$MC$2:$MC$200=I$3)*('GMW - Baseline'!$MB$2:$MB$200=I$4),0),$E64-1973)} -> 5.125 | J64: {=INDEX('GMW - Baseline'!$A$2:$MC$200,MATCH(1,('GMW - Baseline'!$MC$2:$MC$200=J$3)*('GMW - Baseline'!$MB$2:$MB$200=J$4),0),$E64-1973)} -> #N/A | K64: {=INDEX('GMW - Baseline'!$A$2:$MC$200,MATCH(1,('GMW - Baseline'!$MC$2:$MC$200=K$3)*('GMW - Baseline'!$MB$2:$MB$200=K$4),0),$E64-1973)} -> #N/A | L64: {=INDEX('GMW - Baseline'!$A$2:$MC$200,MATCH(1,('GMW - Baseline'!$MC$2:$MC$200=L$3)*('GMW - Baseline'!$MB$2:$MB$200=L$4),0),$E64-1973)} -> #N/A | M64: {=INDEX('GMW - Baseline'!$A$2:$MC$200,MATCH(1,('GMW - Baseline'!$MC$2:$MC$200=M$3)*('GMW - Baseline'!$MB$2:$MB$200=M$4),0),$E64-1973)} -> #N/A | ... T64: {=INDEX('GMW - Baseline'!$A$2:$MC$200,MATCH(1,('GMW - Baseline'!$MC$2:$MC$200=T$3)*('GMW - Baseline'!$MB$2:$MB$200=T$4),0),$E64-1973)} -> #N/A
B65: =+B61+1 -> 1994 | C65: =+C61+1 -> 1994 | E65: =+E64+1 -> 2038 | F65: {=INDEX('GMW - Baseline'!$A$2:$MC$200,MATCH(1,('GMW - Baseline'!$MC$2:$MC$200=F$3)*('GMW - Baseline'!$MB$2:$MB$200=F$4),0),$E65-1973)} -> 398566 | G65: {=INDEX('GMW - Baseline'!$A$2:$MC$200,MATCH(1,('GMW - Baseline'!$MC$2:$MC$200=G$3)*('GMW - Baseline'!$MB$2:$MB$200=G$4),0),$E65-1973)} -> 229961 | H65: {=INDEX('GMW - Baseline'!$A$2:$MC$200,MATCH(1,('GMW - Baseline'!$MC$2:$MC$200=H$3)*('GMW - Baseline'!$MB$2:$MB$200=H$4),0),$E65-1973)} -> 65.63333 | I65: {=INDEX('GMW - Baseline'!$A$2:$MC$200,MATCH(1,('GMW - Baseline'!$MC$2:$MC$200=I$3)*('GMW - Baseline'!$MB$2:$MB$200=I$4),0),$E65-1973)} -> 5.238636 | J65: {=INDEX('GMW - Baseline'!$A$2:$MC$200,MATCH(1,('GMW - Baseline'!$MC$2:$MC$200=J$3)*('GMW - Baseline'!$MB$2:$MB$200=J$4),0),$E65-1973)} -> #N/A | K65: {=INDEX('GMW - Baseline'!$A$2:$MC$200,MATCH(1,('GMW - Baseline'!$MC$2:$MC$200=K$3)*('GMW - Baseline'!$MB$2:$MB$200=K$4),0),$E65-1973)} -> #N/A | L65: {=INDEX('GMW - Baseline'!$A$2:$MC$200,MATCH(1,('GMW - Baseline'!$MC$2:$MC$200=L$3)*('GMW - Baseline'!$MB$2:$MB$200=L$4),0),$E65-1973)} -> #N/A | M65: {=INDEX('GMW - Baseline'!$A$2:$MC$200,MATCH(1,('GMW - Baseline'!$MC$2:$MC$200=M$3)*('GMW - Baseline'!$MB$2:$MB$200=M$4),0),$E65-1973)} -> #N/A | ... T65: {=INDEX('GMW - Baseline'!$A$2:$MC$200,MATCH(1,('GMW - Baseline'!$MC$2:$MC$200=T$3)*('GMW - Baseline'!$MB$2:$MB$200=T$4),0),$E65-1973)} -> #N/A
B66: =+B62+1 -> 1994 | C66: =+C62+1 -> 1994 | E66: =+E65+1 -> 2039 | F66: {=INDEX('GMW - Baseline'!$A$2:$MC$200,MATCH(1,('GMW - Baseline'!$MC$2:$MC$200=F$3)*('GMW - Baseline'!$MB$2:$MB$200=F$4),0),$E66-1973)} -> 400279 | G66: {=INDEX('GMW - Baseline'!$A$2:$MC$200,MATCH(1,('GMW - Baseline'!$MC$2:$MC$200=G$3)*('GMW - Baseline'!$MB$2:$MB$200=G$4),0),$E66-1973)} -> 231570 | H66: {=INDEX('GMW - Baseline'!$A$2:$MC$200,MATCH(1,('GMW - Baseline'!$MC$2:$MC$200=H$3)*('GMW - Baseline'!$MB$2:$MB$200=H$4),0),$E66-1973)} -> 65.8 | I66: {=INDEX('GMW - Baseline'!$A$2:$MC$200,MATCH(1,('GMW - Baseline'!$MC$2:$MC$200=I$3)*('GMW - Baseline'!$MB$2:$MB$200=I$4),0),$E66-1973)} -> 5.763462 | J66: {=INDEX('GMW - Baseline'!$A$2:$MC$200,MATCH(1,('GMW - Baseline'!$MC$2:$MC$200=J$3)*('GMW - Baseline'!$MB$2:$MB$200=J$4),0),$E66-1973)} -> #N/A | K66: {=INDEX('GMW - Baseline'!$A$2:$MC$200,MATCH(1,('GMW - Baseline'!$MC$2:$MC$200=K$3)*('GMW - Baseline'!$MB$2:$MB$200=K$4),0),$E66-1973)} -> #N/A | L66: {=INDEX('GMW - Baseline'!$A$2:$MC$200,MATCH(1,('GMW - Baseline'!$MC$2:$MC$200=L$3)*('GMW - Baseline'!$MB$2:$MB$200=L$4),0),$E66-1973)} -> #N/A | M66: {=INDEX('GMW - Baseline'!$A$2:$MC$200,MATCH(1,('GMW - Baseline'!$MC$2:$MC$200=M$3)*('GMW - Baseline'!$MB$2:$MB$200=M$4),0),$E66-1973)} -> #N/A | ... T66: {=INDEX('GMW - Baseline'!$A$2:$MC$200,MATCH(1,('GMW - Baseline'!$MC$2:$MC$200=T$3)*('GMW - Baseline'!$MB$2:$MB$200=T$4),0),$E66-1973)} -> #N/A
A67: 1995 | B67: =+B63+1 -> 1995 | C67: =+C63+1 -> 1994 | D67: =+D63+1 -> 1994 | E67: =+E66+1 -> 2040 | F67: {=INDEX('GMW - Baseline'!$A$2:$MC$200,MATCH(1,('GMW - Baseline'!$MC$2:$MC$200=F$3)*('GMW - Baseline'!$MB$2:$MB$200=F$4),0),$E67-1973)} -> 402390 | G67: {=INDEX('GMW - Baseline'!$A$2:$MC$200,MATCH(1,('GMW - Baseline'!$MC$2:$MC$200=G$3)*('GMW - Baseline'!$MB$2:$MB$200=G$4),0),$E67-1973)} -> 231674 | H67: {=INDEX('GMW - Baseline'!$A$2:$MC$200,MATCH(1,('GMW - Baseline'!$MC$2:$MC$200=H$3)*('GMW - Baseline'!$MB$2:$MB$200=H$4),0),$E67-1973)} -> 66.33334 | I67: {=INDEX('GMW - Baseline'!$A$2:$MC$200,MATCH(1,('GMW - Baseline'!$MC$2:$MC$200=I$3)*('GMW - Baseline'!$MB$2:$MB$200=I$4),0),$E67-1973)} -> 6.448077 | J67: {=INDEX('GMW - Baseline'!$A$2:$MC$200,MATCH(1,('GMW - Baseline'!$MC$2:$MC$200=J$3)*('GMW - Baseline'!$MB$2:$MB$200=J$4),0),$E67-1973)} -> #N/A | K67: {=INDEX('GMW - Baseline'!$A$2:$MC$200,MATCH(1,('GMW - Baseline'!$MC$2:$MC$200=K$3)*('GMW - Baseline'!$MB$2:$MB$200=K$4),0),$E67-1973)} -> #N/A | L67: {=INDEX('GMW - Baseline'!$A$2:$MC$200,MATCH(1,('GMW - Baseline'!$MC$2:$MC$200=L$3)*('GMW - Baseline'!$MB$2:$MB$200=L$4),0),$E67-1973)} -> #N/A | M67: {=INDEX('GMW - Baseline'!$A$2:$MC$200,MATCH(1,('GMW - Baseline'!$MC$2:$MC$200=M$3)*('GMW - Baseline'!$MB$2:$MB$200=M$4),0),$E67-1973)} -> #N/A | ... T67: {=INDEX('GMW - Baseline'!$A$2:$MC$200,MATCH(1,('GMW - Baseline'!$MC$2:$MC$200=T$3)*('GMW - Baseline'!$MB$2:$MB$200=T$4),0),$E67-1973)} -> #N/A
B68: =+B64+1 -> 1995 | C68: =+C64+1 -> 1995 | E68: =+E67+1 -> 2041 | F68: {=INDEX('GMW - Baseline'!$A$2:$MC$200,MATCH(1,('GMW - Baseline'!$MC$2:$MC$200=F$3)*('GMW - Baseline'!$MB$2:$MB$200=F$4),0),$E68-1973)} -> 403259 | G68: {=INDEX('GMW - Baseline'!$A$2:$MC$200,MATCH(1,('GMW - Baseline'!$MC$2:$MC$200=G$3)*('GMW - Baseline'!$MB$2:$MB$200=G$4),0),$E68-1973)} -> 233343 | H68: {=INDEX('GMW - Baseline'!$A$2:$MC$200,MATCH(1,('GMW - Baseline'!$MC$2:$MC$200=H$3)*('GMW - Baseline'!$MB$2:$MB$200=H$4),0),$E68-1973)} -> 67.26667 | I68: {=INDEX('GMW - Baseline'!$A$2:$MC$200,MATCH(1,('GMW - Baseline'!$MC$2:$MC$200=I$3)*('GMW - Baseline'!$MB$2:$MB$200=I$4),0),$E68-1973)} -> 6.625 | J68: {=INDEX('GMW - Baseline'!$A$2:$MC$200,MATCH(1,('GMW - Baseline'!$MC$2:$MC$200=J$3)*('GMW - Baseline'!$MB$2:$MB$200=J$4),0),$E68-1973)} -> #N/A | K68: {=INDEX('GMW - Baseline'!$A$2:$MC$200,MATCH(1,('GMW - Baseline'!$MC$2:$MC$200=K$3)*('GMW - Baseline'!$MB$2:$MB$200=K$4),0),$E68-1973)} -> #N/A | L68: {=INDEX('GMW - Baseline'!$A$2:$MC$200,MATCH(1,('GMW - Baseline'!$MC$2:$MC$200=L$3)*('GMW - Baseline'!$MB$2:$MB$200=L$4),0),$E68-1973)} -> #N/A | M68: {=INDEX('GMW - Baseline'!$A$2:$MC$200,MATCH(1,('GMW - Baseline'!$MC$2:$MC$200=M$3)*('GMW - Baseline'!$MB$2:$MB$200=M$4),0),$E68-1973)} -> #N/A | ... T68: {=INDEX('GMW - Baseline'!$A$2:$MC$200,MATCH(1,('GMW - Baseline'!$MC$2:$MC$200=T$3)*('GMW - Baseline'!$MB$2:$MB$200=T$4),0),$E68-1973)} -> #N/A
B69: =+B65+1 -> 1995 | C69: =+C65+1 -> 1995 | E69: =+E68+1 -> 2042 | F69: {=INDEX('GMW - Baseline'!$A$2:$MC$200,MATCH(1,('GMW - Baseline'!$MC$2:$MC$200=F$3)*('GMW - Baseline'!$MB$2:$MB$200=F$4),0),$E69-1973)} -> 407795 | G69: {=INDEX('GMW - Baseline'!$A$2:$MC$200,MATCH(1,('GMW - Baseline'!$MC$2:$MC$200=G$3)*('GMW - Baseline'!$MB$2:$MB$200=G$4),0),$E69-1973)} -> 234345 | H69: {=INDEX('GMW - Baseline'!$A$2:$MC$200,MATCH(1,('GMW - Baseline'!$MC$2:$MC$200=H$3)*('GMW - Baseline'!$MB$2:$MB$200=H$4),0),$E69-1973)} -> 67.4 | I69: {=INDEX('GMW - Baseline'!$A$2:$MC$200,MATCH(1,('GMW - Baseline'!$MC$2:$MC$200=I$3)*('GMW - Baseline'!$MB$2:$MB$200=I$4),0),$E69-1973)} -> 6.625 | J69: {=INDEX('GMW - Baseline'!$A$2:$MC$200,MATCH(1,('GMW - Baseline'!$MC$2:$MC$200=J$3)*('GMW - Baseline'!$MB$2:$MB$200=J$4),0),$E69-1973)} -> #N/A | K69: {=INDEX('GMW - Baseline'!$A$2:$MC$200,MATCH(1,('GMW - Baseline'!$MC$2:$MC$200=K$3)*('GMW - Baseline'!$MB$2:$MB$200=K$4),0),$E69-1973)} -> #N/A | L69: {=INDEX('GMW - Baseline'!$A$2:$MC$200,MATCH(1,('GMW - Baseline'!$MC$2:$MC$200=L$3)*('GMW - Baseline'!$MB$2:$MB$200=L$4),0),$E69-1973)} -> #N/A | M69: {=INDEX('GMW - Baseline'!$A$2:$MC$200,MATCH(1,('GMW - Baseline'!$MC$2:$MC$200=M$3)*('GMW - Baseline'!$MB$2:$MB$200=M$4),0),$E69-1973)} -> #N/A | ... T69: {=INDEX('GMW - Baseline'!$A$2:$MC$200,MATCH(1,('GMW - Baseline'!$MC$2:$MC$200=T$3)*('GMW - Baseline'!$MB$2:$MB$200=T$4),0),$E69-1973)} -> #N/A
B70: =+B66+1 -> 1995 | C70: =+C66+1 -> 1995 | E70: =+E69+1 -> 2043 | F70: {=INDEX('GMW - Baseline'!$A$2:$MC$200,MATCH(1,('GMW - Baseline'!$MC$2:$MC$200=F$3)*('GMW - Baseline'!$MB$2:$MB$200=F$4),0),$E70-1973)} -> 409132 | G70: {=INDEX('GMW - Baseline'!$A$2:$MC$200,MATCH(1,('GMW - Baseline'!$MC$2:$MC$200=G$3)*('GMW - Baseline'!$MB$2:$MB$200=G$4),0),$E70-1973)} -> 237147 | H70: {=INDEX('GMW - Baseline'!$A$2:$MC$200,MATCH(1,('GMW - Baseline'!$MC$2:$MC$200=H$3)*('GMW - Baseline'!$MB$2:$MB$200=H$4),0),$E70-1973)} -> 67.73333 | I70: {=INDEX('GMW - Baseline'!$A$2:$MC$200,MATCH(1,('GMW - Baseline'!$MC$2:$MC$200=I$3)*('GMW - Baseline'!$MB$2:$MB$200=I$4),0),$E70-1973)} -> 6.575 | J70: {=INDEX('GMW - Baseline'!$A$2:$MC$200,MATCH(1,('GMW - Baseline'!$MC$2:$MC$200=J$3)*('GMW - Baseline'!$MB$2:$MB$200=J$4),0),$E70-1973)} -> #N/A | K70: {=INDEX('GMW - Baseline'!$A$2:$MC$200,MATCH(1,('GMW - Baseline'!$MC$2:$MC$200=K$3)*('GMW - Baseline'!$MB$2:$MB$200=K$4),0),$E70-1973)} -> #N/A | L70: {=INDEX('GMW - Baseline'!$A$2:$MC$200,MATCH(1,('GMW - Baseline'!$MC$2:$MC$200=L$3)*('GMW - Baseline'!$MB$2:$MB$200=L$4),0),$E70-1973)} -> #N/A | M70: {=INDEX('GMW - Baseline'!$A$2:$MC$200,MATCH(1,('GMW - Baseline'!$MC$2:$MC$200=M$3)*('GMW - Baseline'!$MB$2:$MB$200=M$4),0),$E70-1973)} -> #N/A | ... T70: {=INDEX('GMW - Baseline'!$A$2:$MC$200,MATCH(1,('GMW - Baseline'!$MC$2:$MC$200=T$3)*('GMW - Baseline'!$MB$2:$MB$200=T$4),0),$E70-1973)} -> #N/A
A71: 1996 | B71: =+B67+1 -> 1996 | C71: =+C67+1 -> 1995 | D71: =+D67+1 -> 1995 | E71: =+E70+1 -> 2044 | F71: {=INDEX('GMW - Baseline'!$A$2:$MC$200,MATCH(1,('GMW - Baseline'!$MC$2:$MC$200=F$3)*('GMW - Baseline'!$MB$2:$MB$200=F$4),0),$E71-1973)} -> 412022 | G71: {=INDEX('GMW - Baseline'!$A$2:$MC$200,MATCH(1,('GMW - Baseline'!$MC$2:$MC$200=G$3)*('GMW - Baseline'!$MB$2:$MB$200=G$4),0),$E71-1973)} -> 239556 | H71: {=INDEX('GMW - Baseline'!$A$2:$MC$200,MATCH(1,('GMW - Baseline'!$MC$2:$MC$200=H$3)*('GMW - Baseline'!$MB$2:$MB$200=H$4),0),$E71-1973)} -> 68.1 | I71: {=INDEX('GMW - Baseline'!$A$2:$MC$200,MATCH(1,('GMW - Baseline'!$MC$2:$MC$200=I$3)*('GMW - Baseline'!$MB$2:$MB$200=I$4),0),$E71-1973)} -> 6.128846 | J71: {=INDEX('GMW - Baseline'!$A$2:$MC$200,MATCH(1,('GMW - Baseline'!$MC$2:$MC$200=J$3)*('GMW - Baseline'!$MB$2:$MB$200=J$4),0),$E71-1973)} -> #N/A | K71: {=INDEX('GMW - Baseline'!$A$2:$MC$200,MATCH(1,('GMW - Baseline'!$MC$2:$MC$200=K$3)*('GMW - Baseline'!$MB$2:$MB$200=K$4),0),$E71-1973)} -> #N/A | L71: {=INDEX('GMW - Baseline'!$A$2:$MC$200,MATCH(1,('GMW - Baseline'!$MC$2:$MC$200=L$3)*('GMW - Baseline'!$MB$2:$MB$200=L$4),0),$E71-1973)} -> #N/A | M71: {=INDEX('GMW - Baseline'!$A$2:$MC$200,MATCH(1,('GMW - Baseline'!$MC$2:$MC$200=M$3)*('GMW - Baseline'!$MB$2:$MB$200=M$4),0),$E71-1973)} -> #N/A | ... T71: {=INDEX('GMW - Baseline'!$A$2:$MC$200,MATCH(1,('GMW - Baseline'!$MC$2:$MC$200=T$3)*('GMW - Baseline'!$MB$2:$MB$200=T$4),0),$E71-1973)} -> #N/A
B72: =+B68+1 -> 1996 | C72: =+C68+1 -> 1996 | E72: =+E71+1 -> 2045 | F72: {=INDEX('GMW - Baseline'!$A$2:$MC$200,MATCH(1,('GMW - Baseline'!$MC$2:$MC$200=F$3)*('GMW - Baseline'!$MB$2:$MB$200=F$4),0),$E72-1973)} -> 413325 | G72: {=INDEX('GMW - Baseline'!$A$2:$MC$200,MATCH(1,('GMW - Baseline'!$MC$2:$MC$200=G$3)*('GMW - Baseline'!$MB$2:$MB$200=G$4),0),$E72-1973)} -> 241559 | H72: {=INDEX('GMW - Baseline'!$A$2:$MC$200,MATCH(1,('GMW - Baseline'!$MC$2:$MC$200=H$3)*('GMW - Baseline'!$MB$2:$MB$200=H$4),0),$E72-1973)} -> 68.86667 | I72: {=INDEX('GMW - Baseline'!$A$2:$MC$200,MATCH(1,('GMW - Baseline'!$MC$2:$MC$200=I$3)*('GMW - Baseline'!$MB$2:$MB$200=I$4),0),$E72-1973)} -> 5.872116 | J72: {=INDEX('GMW - Baseline'!$A$2:$MC$200,MATCH(1,('GMW - Baseline'!$MC$2:$MC$200=J$3)*('GMW - Baseline'!$MB$2:$MB$200=J$4),0),$E72-1973)} -> #N/A | K72: {=INDEX('GMW - Baseline'!$A$2:$MC$200,MATCH(1,('GMW - Baseline'!$MC$2:$MC$200=K$3)*('GMW - Baseline'!$MB$2:$MB$200=K$4),0),$E72-1973)} -> #N/A | L72: {=INDEX('GMW - Baseline'!$A$2:$MC$200,MATCH(1,('GMW - Baseline'!$MC$2:$MC$200=L$3)*('GMW - Baseline'!$MB$2:$MB$200=L$4),0),$E72-1973)} -> #N/A | M72: {=INDEX('GMW - Baseline'!$A$2:$MC$200,MATCH(1,('GMW - Baseline'!$MC$2:$MC$200=M$3)*('GMW - Baseline'!$MB$2:$MB$200=M$4),0),$E72-1973)} -> #N/A | ... T72: {=INDEX('GMW - Baseline'!$A$2:$MC$200,MATCH(1,('GMW - Baseline'!$MC$2:$MC$200=T$3)*('GMW - Baseline'!$MB$2:$MB$200=T$4),0),$E72-1973)} -> #N/A
B73: =+B69+1 -> 1996 | C73: =+C69+1 -> 1996 | E73: =+E72+1 -> 2046 | F73: {=INDEX('GMW - Baseline'!$A$2:$MC$200,MATCH(1,('GMW - Baseline'!$MC$2:$MC$200=F$3)*('GMW - Baseline'!$MB$2:$MB$200=F$4),0),$E73-1973)} -> 417019 | G73: {=INDEX('GMW - Baseline'!$A$2:$MC$200,MATCH(1,('GMW - Baseline'!$MC$2:$MC$200=G$3)*('GMW - Baseline'!$MB$2:$MB$200=G$4),0),$E73-1973)} -> 243639 | H73: {=INDEX('GMW - Baseline'!$A$2:$MC$200,MATCH(1,('GMW - Baseline'!$MC$2:$MC$200=H$3)*('GMW - Baseline'!$MB$2:$MB$200=H$4),0),$E73-1973)} -> 68.93333 | I73: {=INDEX('GMW - Baseline'!$A$2:$MC$200,MATCH(1,('GMW - Baseline'!$MC$2:$MC$200=I$3)*('GMW - Baseline'!$MB$2:$MB$200=I$4),0),$E73-1973)} -> 5.6875 | J73: {=INDEX('GMW - Baseline'!$A$2:$MC$200,MATCH(1,('GMW - Baseline'!$MC$2:$MC$200=J$3)*('GMW - Baseline'!$MB$2:$MB$200=J$4),0),$E73-1973)} -> #N/A | K73: {=INDEX('GMW - Baseline'!$A$2:$MC$200,MATCH(1,('GMW - Baseline'!$MC$2:$MC$200=K$3)*('GMW - Baseline'!$MB$2:$MB$200=K$4),0),$E73-1973)} -> #N/A | L73: {=INDEX('GMW - Baseline'!$A$2:$MC$200,MATCH(1,('GMW - Baseline'!$MC$2:$MC$200=L$3)*('GMW - Baseline'!$MB$2:$MB$200=L$4),0),$E73-1973)} -> #N/A | M73: {=INDEX('GMW - Baseline'!$A$2:$MC$200,MATCH(1,('GMW - Baseline'!$MC$2:$MC$200=M$3)*('GMW - Baseline'!$MB$2:$MB$200=M$4),0),$E73-1973)} -> #N/A | ... T73: {=INDEX('GMW - Baseline'!$A$2:$MC$200,MATCH(1,('GMW - Baseline'!$MC$2:$MC$200=T$3)*('GMW - Baseline'!$MB$2:$MB$200=T$4),0),$E73-1973)} -> #N/A
B74: =+B70+1 -> 1996 | C74: =+C70+1 -> 1996 | E74: =+E73+1 -> 2047 | F74: {=INDEX('GMW - Baseline'!$A$2:$MC$200,MATCH(1,('GMW - Baseline'!$MC$2:$MC$200=F$3)*('GMW - Baseline'!$MB$2:$MB$200=F$4),0),$E74-1973)} -> 422639 | G74: {=INDEX('GMW - Baseline'!$A$2:$MC$200,MATCH(1,('GMW - Baseline'!$MC$2:$MC$200=G$3)*('GMW - Baseline'!$MB$2:$MB$200=G$4),0),$E74-1973)} -> 246780 | H74: {=INDEX('GMW - Baseline'!$A$2:$MC$200,MATCH(1,('GMW - Baseline'!$MC$2:$MC$200=H$3)*('GMW - Baseline'!$MB$2:$MB$200=H$4),0),$E74-1973)} -> 69.36667 | I74: {=INDEX('GMW - Baseline'!$A$2:$MC$200,MATCH(1,('GMW - Baseline'!$MC$2:$MC$200=I$3)*('GMW - Baseline'!$MB$2:$MB$200=I$4),0),$E74-1973)} -> 5.857955 | J74: {=INDEX('GMW - Baseline'!$A$2:$MC$200,MATCH(1,('GMW - Baseline'!$MC$2:$MC$200=J$3)*('GMW - Baseline'!$MB$2:$MB$200=J$4),0),$E74-1973)} -> #N/A | K74: {=INDEX('GMW - Baseline'!$A$2:$MC$200,MATCH(1,('GMW - Baseline'!$MC$2:$MC$200=K$3)*('GMW - Baseline'!$MB$2:$MB$200=K$4),0),$E74-1973)} -> #N/A | L74: {=INDEX('GMW - Baseline'!$A$2:$MC$200,MATCH(1,('GMW - Baseline'!$MC$2:$MC$200=L$3)*('GMW - Baseline'!$MB$2:$MB$200=L$4),0),$E74-1973)} -> #N/A | M74: {=INDEX('GMW - Baseline'!$A$2:$MC$200,MATCH(1,('GMW - Baseline'!$MC$2:$MC$200=M$3)*('GMW - Baseline'!$MB$2:$MB$200=M$4),0),$E74-1973)} -> #N/A | ... T74: {=INDEX('GMW - Baseline'!$A$2:$MC$200,MATCH(1,('GMW - Baseline'!$MC$2:$MC$200=T$3)*('GMW - Baseline'!$MB$2:$MB$200=T$4),0),$E74-1973)} -> #N/A
A75: 1997 | B75: =+B71+1 -> 1997 | C75: =+C71+1 -> 1996 | D75: =+D71+1 -> 1996 | E75: =+E74+1 -> 2048 | F75: {=INDEX('GMW - Baseline'!$A$2:$MC$200,MATCH(1,('GMW - Baseline'!$MC$2:$MC$200=F$3)*('GMW - Baseline'!$MB$2:$MB$200=F$4),0),$E75-1973)} -> 429418 | G75: {=INDEX('GMW - Baseline'!$A$2:$MC$200,MATCH(1,('GMW - Baseline'!$MC$2:$MC$200=G$3)*('GMW - Baseline'!$MB$2:$MB$200=G$4),0),$E75-1973)} -> 249328 | H75: {=INDEX('GMW - Baseline'!$A$2:$MC$200,MATCH(1,('GMW - Baseline'!$MC$2:$MC$200=H$3)*('GMW - Baseline'!$MB$2:$MB$200=H$4),0),$E75-1973)} -> 69.36667 | I75: {=INDEX('GMW - Baseline'!$A$2:$MC$200,MATCH(1,('GMW - Baseline'!$MC$2:$MC$200=I$3)*('GMW - Baseline'!$MB$2:$MB$200=I$4),0),$E75-1973)} -> 5.9375 | J75: {=INDEX('GMW - Baseline'!$A$2:$MC$200,MATCH(1,('GMW - Baseline'!$MC$2:$MC$200=J$3)*('GMW - Baseline'!$MB$2:$MB$200=J$4),0),$E75-1973)} -> #N/A | K75: {=INDEX('GMW - Baseline'!$A$2:$MC$200,MATCH(1,('GMW - Baseline'!$MC$2:$MC$200=K$3)*('GMW - Baseline'!$MB$2:$MB$200=K$4),0),$E75-1973)} -> #N/A | L75: {=INDEX('GMW - Baseline'!$A$2:$MC$200,MATCH(1,('GMW - Baseline'!$MC$2:$MC$200=L$3)*('GMW - Baseline'!$MB$2:$MB$200=L$4),0),$E75-1973)} -> #N/A | M75: {=INDEX('GMW - Baseline'!$A$2:$MC$200,MATCH(1,('GMW - Baseline'!$MC$2:$MC$200=M$3)*('GMW - Baseline'!$MB$2:$MB$200=M$4),0),$E75-1973)} -> #N/A | ... T75: {=INDEX('GMW - Baseline'!$A$2:$MC$200,MATCH(1,('GMW - Baseline'!$MC$2:$MC$200=T$3)*('GMW - Baseline'!$MB$2:$MB$200=T$4),0),$E75-1973)} -> #N/A
B76: =+B72+1 -> 1997 | C76: =+C72+1 -> 1997 | E76: =+E75+1 -> 2049 | F76: {=INDEX('GMW - Baseline'!$A$2:$MC$200,MATCH(1,('GMW - Baseline'!$MC$2:$MC$200=F$3)*('GMW - Baseline'!$MB$2:$MB$200=F$4),0),$E76-1973)} -> 434199 | G76: {=INDEX('GMW - Baseline'!$A$2:$MC$200,MATCH(1,('GMW - Baseline'!$MC$2:$MC$200=G$3)*('GMW - Baseline'!$MB$2:$MB$200=G$4),0),$E76-1973)} -> 253090 | H76: {=INDEX('GMW - Baseline'!$A$2:$MC$200,MATCH(1,('GMW - Baseline'!$MC$2:$MC$200=H$3)*('GMW - Baseline'!$MB$2:$MB$200=H$4),0),$E76-1973)} -> 70 | I76: {=INDEX('GMW - Baseline'!$A$2:$MC$200,MATCH(1,('GMW - Baseline'!$MC$2:$MC$200=I$3)*('GMW - Baseline'!$MB$2:$MB$200=I$4),0),$E76-1973)} -> 6.195192 | J76: {=INDEX('GMW - Baseline'!$A$2:$MC$200,MATCH(1,('GMW - Baseline'!$MC$2:$MC$200=J$3)*('GMW - Baseline'!$MB$2:$MB$200=J$4),0),$E76-1973)} -> #N/A | K76: {=INDEX('GMW - Baseline'!$A$2:$MC$200,MATCH(1,('GMW - Baseline'!$MC$2:$MC$200=K$3)*('GMW - Baseline'!$MB$2:$MB$200=K$4),0),$E76-1973)} -> #N/A | L76: {=INDEX('GMW - Baseline'!$A$2:$MC$200,MATCH(1,('GMW - Baseline'!$MC$2:$MC$200=L$3)*('GMW - Baseline'!$MB$2:$MB$200=L$4),0),$E76-1973)} -> #N/A | M76: {=INDEX('GMW - Baseline'!$A$2:$MC$200,MATCH(1,('GMW - Baseline'!$MC$2:$MC$200=M$3)*('GMW - Baseline'!$MB$2:$MB$200=M$4),0),$E76-1973)} -> #N/A | ... T76: {=INDEX('GMW - Baseline'!$A$2:$MC$200,MATCH(1,('GMW - Baseline'!$MC$2:$MC$200=T$3)*('GMW - Baseline'!$MB$2:$MB$200=T$4),0),$E76-1973)} -> #N/A
B77: =+B73+1 -> 1997 | C77: =+C73+1 -> 1997 | E77: =+E76+1 -> 2050 | F77: {=INDEX('GMW - Baseline'!$A$2:$MC$200,MATCH(1,('GMW - Baseline'!$MC$2:$MC$200=F$3)*('GMW - Baseline'!$MB$2:$MB$200=F$4),0),$E77-1973)} -> 438100 | G77: {=INDEX('GMW - Baseline'!$A$2:$MC$200,MATCH(1,('GMW - Baseline'!$MC$2:$MC$200=G$3)*('GMW - Baseline'!$MB$2:$MB$200=G$4),0),$E77-1973)} -> 256735 | H77: {=INDEX('GMW - Baseline'!$A$2:$MC$200,MATCH(1,('GMW - Baseline'!$MC$2:$MC$200=H$3)*('GMW - Baseline'!$MB$2:$MB$200=H$4),0),$E77-1973)} -> 70.26667 | I77: {=INDEX('GMW - Baseline'!$A$2:$MC$200,MATCH(1,('GMW - Baseline'!$MC$2:$MC$200=I$3)*('GMW - Baseline'!$MB$2:$MB$200=I$4),0),$E77-1973)} -> 6.871212 | J77: {=INDEX('GMW - Baseline'!$A$2:$MC$200,MATCH(1,('GMW - Baseline'!$MC$2:$MC$200=J$3)*('GMW - Baseline'!$MB$2:$MB$200=J$4),0),$E77-1973)} -> #N/A | K77: {=INDEX('GMW - Baseline'!$A$2:$MC$200,MATCH(1,('GMW - Baseline'!$MC$2:$MC$200=K$3)*('GMW - Baseline'!$MB$2:$MB$200=K$4),0),$E77-1973)} -> #N/A | L77: {=INDEX('GMW - Baseline'!$A$2:$MC$200,MATCH(1,('GMW - Baseline'!$MC$2:$MC$200=L$3)*('GMW - Baseline'!$MB$2:$MB$200=L$4),0),$E77-1973)} -> #N/A | M77: {=INDEX('GMW - Baseline'!$A$2:$MC$200,MATCH(1,('GMW - Baseline'!$MC$2:$MC$200=M$3)*('GMW - Baseline'!$MB$2:$MB$200=M$4),0),$E77-1973)} -> #N/A | ... T77: {=INDEX('GMW - Baseline'!$A$2:$MC$200,MATCH(1,('GMW - Baseline'!$MC$2:$MC$200=T$3)*('GMW - Baseline'!$MB$2:$MB$200=T$4),0),$E77-1973)} -> #N/A
B78: =+B74+1 -> 1997 | C78: =+C74+1 -> 1997 | E78: =+E77+1 -> 2051 | F78: {=INDEX('GMW - Baseline'!$A$2:$MC$200,MATCH(1,('GMW - Baseline'!$MC$2:$MC$200=F$3)*('GMW - Baseline'!$MB$2:$MB$200=F$4),0),$E78-1973)} -> 444540 | G78: {=INDEX('GMW - Baseline'!$A$2:$MC$200,MATCH(1,('GMW - Baseline'!$MC$2:$MC$200=G$3)*('GMW - Baseline'!$MB$2:$MB$200=G$4),0),$E78-1973)} -> 258701 | H78: {=INDEX('GMW - Baseline'!$A$2:$MC$200,MATCH(1,('GMW - Baseline'!$MC$2:$MC$200=H$3)*('GMW - Baseline'!$MB$2:$MB$200=H$4),0),$E78-1973)} -> 70.63333 | I78: {=INDEX('GMW - Baseline'!$A$2:$MC$200,MATCH(1,('GMW - Baseline'!$MC$2:$MC$200=I$3)*('GMW - Baseline'!$MB$2:$MB$200=I$4),0),$E78-1973)} -> 7.151515 | J78: {=INDEX('GMW - Baseline'!$A$2:$MC$200,MATCH(1,('GMW - Baseline'!$MC$2:$MC$200=J$3)*('GMW - Baseline'!$MB$2:$MB$200=J$4),0),$E78-1973)} -> #N/A | K78: {=INDEX('GMW - Baseline'!$A$2:$MC$200,MATCH(1,('GMW - Baseline'!$MC$2:$MC$200=K$3)*('GMW - Baseline'!$MB$2:$MB$200=K$4),0),$E78-1973)} -> #N/A | L78: {=INDEX('GMW - Baseline'!$A$2:$MC$200,MATCH(1,('GMW - Baseline'!$MC$2:$MC$200=L$3)*('GMW - Baseline'!$MB$2:$MB$200=L$4),0),$E78-1973)} -> #N/A | M78: {=INDEX('GMW - Baseline'!$A$2:$MC$200,MATCH(1,('GMW - Baseline'!$MC$2:$MC$200=M$3)*('GMW - Baseline'!$MB$2:$MB$200=M$4),0),$E78-1973)} -> #N/A | ... T78: {=INDEX('GMW - Baseline'!$A$2:$MC$200,MATCH(1,('GMW - Baseline'!$MC$2:$MC$200=T$3)*('GMW - Baseline'!$MB$2:$MB$200=T$4),0),$E78-1973)} -> #N/A
A79: 1998 | B79: =+B75+1 -> 1998 | C79: =+C75+1 -> 1997 | D79: =+D75+1 -> 1997 | E79: =+E78+1 -> 2052 | F79: {=INDEX('GMW - Baseline'!$A$2:$MC$200,MATCH(1,('GMW - Baseline'!$MC$2:$MC$200=F$3)*('GMW - Baseline'!$MB$2:$MB$200=F$4),0),$E79-1973)} -> 447712 | G79: {=INDEX('GMW - Baseline'!$A$2:$MC$200,MATCH(1,('GMW - Baseline'!$MC$2:$MC$200=G$3)*('GMW - Baseline'!$MB$2:$MB$200=G$4),0),$E79-1973)} -> 260797 | H79: {=INDEX('GMW - Baseline'!$A$2:$MC$200,MATCH(1,('GMW - Baseline'!$MC$2:$MC$200=H$3)*('GMW - Baseline'!$MB$2:$MB$200=H$4),0),$E79-1973)} -> 70.5 | I79: {=INDEX('GMW - Baseline'!$A$2:$MC$200,MATCH(1,('GMW - Baseline'!$MC$2:$MC$200=I$3)*('GMW - Baseline'!$MB$2:$MB$200=I$4),0),$E79-1973)} -> 7.25 | J79: {=INDEX('GMW - Baseline'!$A$2:$MC$200,MATCH(1,('GMW - Baseline'!$MC$2:$MC$200=J$3)*('GMW - Baseline'!$MB$2:$MB$200=J$4),0),$E79-1973)} -> #N/A | K79: {=INDEX('GMW - Baseline'!$A$2:$MC$200,MATCH(1,('GMW - Baseline'!$MC$2:$MC$200=K$3)*('GMW - Baseline'!$MB$2:$MB$200=K$4),0),$E79-1973)} -> #N/A | L79: {=INDEX('GMW - Baseline'!$A$2:$MC$200,MATCH(1,('GMW - Baseline'!$MC$2:$MC$200=L$3)*('GMW - Baseline'!$MB$2:$MB$200=L$4),0),$E79-1973)} -> #N/A | M79: {=INDEX('GMW - Baseline'!$A$2:$MC$200,MATCH(1,('GMW - Baseline'!$MC$2:$MC$200=M$3)*('GMW - Baseline'!$MB$2:$MB$200=M$4),0),$E79-1973)} -> #N/A | ... T79: {=INDEX('GMW - Baseline'!$A$2:$MC$200,MATCH(1,('GMW - Baseline'!$MC$2:$MC$200=T$3)*('GMW - Baseline'!$MB$2:$MB$200=T$4),0),$E79-1973)} -> #N/A
B80: =+B76+1 -> 1998 | C80: =+C76+1 -> 1998 | E80: =+E79+1 -> 2053 | F80: {=INDEX('GMW - Baseline'!$A$2:$MC$200,MATCH(1,('GMW - Baseline'!$MC$2:$MC$200=F$3)*('GMW - Baseline'!$MB$2:$MB$200=F$4),0),$E80-1973)} -> 450292 | G80: {=INDEX('GMW - Baseline'!$A$2:$MC$200,MATCH(1,('GMW - Baseline'!$MC$2:$MC$200=G$3)*('GMW - Baseline'!$MB$2:$MB$200=G$4),0),$E80-1973)} -> 263411 | H80: {=INDEX('GMW - Baseline'!$A$2:$MC$200,MATCH(1,('GMW - Baseline'!$MC$2:$MC$200=H$3)*('GMW - Baseline'!$MB$2:$MB$200=H$4),0),$E80-1973)} -> 71.26667 | I80: {=INDEX('GMW - Baseline'!$A$2:$MC$200,MATCH(1,('GMW - Baseline'!$MC$2:$MC$200=I$3)*('GMW - Baseline'!$MB$2:$MB$200=I$4),0),$E80-1973)} -> 7.323077 | J80: {=INDEX('GMW - Baseline'!$A$2:$MC$200,MATCH(1,('GMW - Baseline'!$MC$2:$MC$200=J$3)*('GMW - Baseline'!$MB$2:$MB$200=J$4),0),$E80-1973)} -> #N/A | K80: {=INDEX('GMW - Baseline'!$A$2:$MC$200,MATCH(1,('GMW - Baseline'!$MC$2:$MC$200=K$3)*('GMW - Baseline'!$MB$2:$MB$200=K$4),0),$E80-1973)} -> #N/A | L80: {=INDEX('GMW - Baseline'!$A$2:$MC$200,MATCH(1,('GMW - Baseline'!$MC$2:$MC$200=L$3)*('GMW - Baseline'!$MB$2:$MB$200=L$4),0),$E80-1973)} -> #N/A | M80: {=INDEX('GMW - Baseline'!$A$2:$MC$200,MATCH(1,('GMW - Baseline'!$MC$2:$MC$200=M$3)*('GMW - Baseline'!$MB$2:$MB$200=M$4),0),$E80-1973)} -> #N/A | ... T80: {=INDEX('GMW - Baseline'!$A$2:$MC$200,MATCH(1,('GMW - Baseline'!$MC$2:$MC$200=T$3)*('GMW - Baseline'!$MB$2:$MB$200=T$4),0),$E80-1973)} -> #N/A
B81: =+B77+1 -> 1998 | C81: =+C77+1 -> 1998 | E81: =+E80+1 -> 2054 | F81: {=INDEX('GMW - Baseline'!$A$2:$MC$200,MATCH(1,('GMW - Baseline'!$MC$2:$MC$200=F$3)*('GMW - Baseline'!$MB$2:$MB$200=F$4),0),$E81-1973)} -> 451005 | G81: {=INDEX('GMW - Baseline'!$A$2:$MC$200,MATCH(1,('GMW - Baseline'!$MC$2:$MC$200=G$3)*('GMW - Baseline'!$MB$2:$MB$200=G$4),0),$E81-1973)} -> 267649 | H81: {=INDEX('GMW - Baseline'!$A$2:$MC$200,MATCH(1,('GMW - Baseline'!$MC$2:$MC$200=H$3)*('GMW - Baseline'!$MB$2:$MB$200=H$4),0),$E81-1973)} -> 71.23333 | I81: {=INDEX('GMW - Baseline'!$A$2:$MC$200,MATCH(1,('GMW - Baseline'!$MC$2:$MC$200=I$3)*('GMW - Baseline'!$MB$2:$MB$200=I$4),0),$E81-1973)} -> 7.5 | J81: {=INDEX('GMW - Baseline'!$A$2:$MC$200,MATCH(1,('GMW - Baseline'!$MC$2:$MC$200=J$3)*('GMW - Baseline'!$MB$2:$MB$200=J$4),0),$E81-1973)} -> #N/A | K81: {=INDEX('GMW - Baseline'!$A$2:$MC$200,MATCH(1,('GMW - Baseline'!$MC$2:$MC$200=K$3)*('GMW - Baseline'!$MB$2:$MB$200=K$4),0),$E81-1973)} -> #N/A | L81: {=INDEX('GMW - Baseline'!$A$2:$MC$200,MATCH(1,('GMW - Baseline'!$MC$2:$MC$200=L$3)*('GMW - Baseline'!$MB$2:$MB$200=L$4),0),$E81-1973)} -> #N/A | M81: {=INDEX('GMW - Baseline'!$A$2:$MC$200,MATCH(1,('GMW - Baseline'!$MC$2:$MC$200=M$3)*('GMW - Baseline'!$MB$2:$MB$200=M$4),0),$E81-1973)} -> #N/A | ... T81: {=INDEX('GMW - Baseline'!$A$2:$MC$200,MATCH(1,('GMW - Baseline'!$MC$2:$MC$200=T$3)*('GMW - Baseline'!$MB$2:$MB$200=T$4),0),$E81-1973)} -> #N/A
B82: =+B78+1 -> 1998 | C82: =+C78+1 -> 1998 | E82: =+E81+1 -> 2055 | F82: {=INDEX('GMW - Baseline'!$A$2:$MC$200,MATCH(1,('GMW - Baseline'!$MC$2:$MC$200=F$3)*('GMW - Baseline'!$MB$2:$MB$200=F$4),0),$E82-1973)} -> 453937 | G82: {=INDEX('GMW - Baseline'!$A$2:$MC$200,MATCH(1,('GMW - Baseline'!$MC$2:$MC$200=G$3)*('GMW - Baseline'!$MB$2:$MB$200=G$4),0),$E82-1973)} -> 267397 | H82: {=INDEX('GMW - Baseline'!$A$2:$MC$200,MATCH(1,('GMW - Baseline'!$MC$2:$MC$200=H$3)*('GMW - Baseline'!$MB$2:$MB$200=H$4),0),$E82-1973)} -> 71.63333 | I82: {=INDEX('GMW - Baseline'!$A$2:$MC$200,MATCH(1,('GMW - Baseline'!$MC$2:$MC$200=I$3)*('GMW - Baseline'!$MB$2:$MB$200=I$4),0),$E82-1973)} -> 6.837121 | J82: {=INDEX('GMW - Baseline'!$A$2:$MC$200,MATCH(1,('GMW - Baseline'!$MC$2:$MC$200=J$3)*('GMW - Baseline'!$MB$2:$MB$200=J$4),0),$E82-1973)} -> #N/A | K82: {=INDEX('GMW - Baseline'!$A$2:$MC$200,MATCH(1,('GMW - Baseline'!$MC$2:$MC$200=K$3)*('GMW - Baseline'!$MB$2:$MB$200=K$4),0),$E82-1973)} -> #N/A | L82: {=INDEX('GMW - Baseline'!$A$2:$MC$200,MATCH(1,('GMW - Baseline'!$MC$2:$MC$200=L$3)*('GMW - Baseline'!$MB$2:$MB$200=L$4),0),$E82-1973)} -> #N/A | M82: {=INDEX('GMW - Baseline'!$A$2:$MC$200,MATCH(1,('GMW - Baseline'!$MC$2:$MC$200=M$3)*('GMW - Baseline'!$MB$2:$MB$200=M$4),0),$E82-1973)} -> #N/A | ... T82: {=INDEX('GMW - Baseline'!$A$2:$MC$200,MATCH(1,('GMW - Baseline'!$MC$2:$MC$200=T$3)*('GMW - Baseline'!$MB$2:$MB$200=T$4),0),$E82-1973)} -> #N/A
A83: 1999 | B83: =+B79+1 -> 1999 | C83: =+C79+1 -> 1998 | D83: =+D79+1 -> 1998 | E83: =+E82+1 -> 2056 | F83: {=INDEX('GMW - Baseline'!$A$2:$MC$200,MATCH(1,('GMW - Baseline'!$MC$2:$MC$200=F$3)*('GMW - Baseline'!$MB$2:$MB$200=F$4),0),$E83-1973)} -> 457044 | G83: {=INDEX('GMW - Baseline'!$A$2:$MC$200,MATCH(1,('GMW - Baseline'!$MC$2:$MC$200=G$3)*('GMW - Baseline'!$MB$2:$MB$200=G$4),0),$E83-1973)} -> 270159 | H83: {=INDEX('GMW - Baseline'!$A$2:$MC$200,MATCH(1,('GMW - Baseline'!$MC$2:$MC$200=H$3)*('GMW - Baseline'!$MB$2:$MB$200=H$4),0),$E83-1973)} -> 71.6 | I83: {=INDEX('GMW - Baseline'!$A$2:$MC$200,MATCH(1,('GMW - Baseline'!$MC$2:$MC$200=I$3)*('GMW - Baseline'!$MB$2:$MB$200=I$4),0),$E83-1973)} -> 5.703125 | J83: {=INDEX('GMW - Baseline'!$A$2:$MC$200,MATCH(1,('GMW - Baseline'!$MC$2:$MC$200=J$3)*('GMW - Baseline'!$MB$2:$MB$200=J$4),0),$E83-1973)} -> #N/A | K83: {=INDEX('GMW - Baseline'!$A$2:$MC$200,MATCH(1,('GMW - Baseline'!$MC$2:$MC$200=K$3)*('GMW - Baseline'!$MB$2:$MB$200=K$4),0),$E83-1973)} -> #N/A | L83: {=INDEX('GMW - Baseline'!$A$2:$MC$200,MATCH(1,('GMW - Baseline'!$MC$2:$MC$200=L$3)*('GMW - Baseline'!$MB$2:$MB$200=L$4),0),$E83-1973)} -> #N/A | M83: {=INDEX('GMW - Baseline'!$A$2:$MC$200,MATCH(1,('GMW - Baseline'!$MC$2:$MC$200=M$3)*('GMW - Baseline'!$MB$2:$MB$200=M$4),0),$E83-1973)} -> #N/A | ... T83: {=INDEX('GMW - Baseline'!$A$2:$MC$200,MATCH(1,('GMW - Baseline'!$MC$2:$MC$200=T$3)*('GMW - Baseline'!$MB$2:$MB$200=T$4),0),$E83-1973)} -> #N/A
B84: =+B80+1 -> 1999 | C84: =+C80+1 -> 1999 | E84: =+E83+1 -> 2057 | F84: {=INDEX('GMW - Baseline'!$A$2:$MC$200,MATCH(1,('GMW - Baseline'!$MC$2:$MC$200=F$3)*('GMW - Baseline'!$MB$2:$MB$200=F$4),0),$E84-1973)} -> 458710 | G84: {=INDEX('GMW - Baseline'!$A$2:$MC$200,MATCH(1,('GMW - Baseline'!$MC$2:$MC$200=G$3)*('GMW - Baseline'!$MB$2:$MB$200=G$4),0),$E84-1973)} -> 275407 | H84: {=INDEX('GMW - Baseline'!$A$2:$MC$200,MATCH(1,('GMW - Baseline'!$MC$2:$MC$200=H$3)*('GMW - Baseline'!$MB$2:$MB$200=H$4),0),$E84-1973)} -> 72.3 | I84: {=INDEX('GMW - Baseline'!$A$2:$MC$200,MATCH(1,('GMW - Baseline'!$MC$2:$MC$200=I$3)*('GMW - Baseline'!$MB$2:$MB$200=I$4),0),$E84-1973)} -> 5.211538 | J84: {=INDEX('GMW - Baseline'!$A$2:$MC$200,MATCH(1,('GMW - Baseline'!$MC$2:$MC$200=J$3)*('GMW - Baseline'!$MB$2:$MB$200=J$4),0),$E84-1973)} -> #N/A | K84: {=INDEX('GMW - Baseline'!$A$2:$MC$200,MATCH(1,('GMW - Baseline'!$MC$2:$MC$200=K$3)*('GMW - Baseline'!$MB$2:$MB$200=K$4),0),$E84-1973)} -> #N/A | L84: {=INDEX('GMW - Baseline'!$A$2:$MC$200,MATCH(1,('GMW - Baseline'!$MC$2:$MC$200=L$3)*('GMW - Baseline'!$MB$2:$MB$200=L$4),0),$E84-1973)} -> #N/A | M84: {=INDEX('GMW - Baseline'!$A$2:$MC$200,MATCH(1,('GMW - Baseline'!$MC$2:$MC$200=M$3)*('GMW - Baseline'!$MB$2:$MB$200=M$4),0),$E84-1973)} -> #N/A | ... T84: {=INDEX('GMW - Baseline'!$A$2:$MC$200,MATCH(1,('GMW - Baseline'!$MC$2:$MC$200=T$3)*('GMW - Baseline'!$MB$2:$MB$200=T$4),0),$E84-1973)} -> #N/A
B85: =+B81+1 -> 1999 | C85: =+C81+1 -> 1999 | E85: =+E84+1 -> 2058 | F85: {=INDEX('GMW - Baseline'!$A$2:$MC$200,MATCH(1,('GMW - Baseline'!$MC$2:$MC$200=F$3)*('GMW - Baseline'!$MB$2:$MB$200=F$4),0),$E85-1973)} -> 466387 | G85: {=INDEX('GMW - Baseline'!$A$2:$MC$200,MATCH(1,('GMW - Baseline'!$MC$2:$MC$200=G$3)*('GMW - Baseline'!$MB$2:$MB$200=G$4),0),$E85-1973)} -> 278331 | H85: {=INDEX('GMW - Baseline'!$A$2:$MC$200,MATCH(1,('GMW - Baseline'!$MC$2:$MC$200=H$3)*('GMW - Baseline'!$MB$2:$MB$200=H$4),0),$E85-1973)} -> 72.13333 | I85: {=INDEX('GMW - Baseline'!$A$2:$MC$200,MATCH(1,('GMW - Baseline'!$MC$2:$MC$200=I$3)*('GMW - Baseline'!$MB$2:$MB$200=I$4),0),$E85-1973)} -> 5.064394 | J85: {=INDEX('GMW - Baseline'!$A$2:$MC$200,MATCH(1,('GMW - Baseline'!$MC$2:$MC$200=J$3)*('GMW - Baseline'!$MB$2:$MB$200=J$4),0),$E85-1973)} -> #N/A | K85: {=INDEX('GMW - Baseline'!$A$2:$MC$200,MATCH(1,('GMW - Baseline'!$MC$2:$MC$200=K$3)*('GMW - Baseline'!$MB$2:$MB$200=K$4),0),$E85-1973)} -> #N/A | L85: {=INDEX('GMW - Baseline'!$A$2:$MC$200,MATCH(1,('GMW - Baseline'!$MC$2:$MC$200=L$3)*('GMW - Baseline'!$MB$2:$MB$200=L$4),0),$E85-1973)} -> #N/A | M85: {=INDEX('GMW - Baseline'!$A$2:$MC$200,MATCH(1,('GMW - Baseline'!$MC$2:$MC$200=M$3)*('GMW - Baseline'!$MB$2:$MB$200=M$4),0),$E85-1973)} -> #N/A | ... T85: {=INDEX('GMW - Baseline'!$A$2:$MC$200,MATCH(1,('GMW - Baseline'!$MC$2:$MC$200=T$3)*('GMW - Baseline'!$MB$2:$MB$200=T$4),0),$E85-1973)} -> #N/A
B86: =+B82+1 -> 1999 | C86: =+C82+1 -> 1999 | E86: =+E85+1 -> 2059 | F86: {=INDEX('GMW - Baseline'!$A$2:$MC$200,MATCH(1,('GMW - Baseline'!$MC$2:$MC$200=F$3)*('GMW - Baseline'!$MB$2:$MB$200=F$4),0),$E86-1973)} -> 473892 | G86: {=INDEX('GMW - Baseline'!$A$2:$MC$200,MATCH(1,('GMW - Baseline'!$MC$2:$MC$200=G$3)*('GMW - Baseline'!$MB$2:$MB$200=G$4),0),$E86-1973)} -> 280651 | H86: {=INDEX('GMW - Baseline'!$A$2:$MC$200,MATCH(1,('GMW - Baseline'!$MC$2:$MC$200=H$3)*('GMW - Baseline'!$MB$2:$MB$200=H$4),0),$E86-1973)} -> 72.43333 | I86: {=INDEX('GMW - Baseline'!$A$2:$MC$200,MATCH(1,('GMW - Baseline'!$MC$2:$MC$200=I$3)*('GMW - Baseline'!$MB$2:$MB$200=I$4),0),$E86-1973)} -> 5.409091 | J86: {=INDEX('GMW - Baseline'!$A$2:$MC$200,MATCH(1,('GMW - Baseline'!$MC$2:$MC$200=J$3)*('GMW - Baseline'!$MB$2:$MB$200=J$4),0),$E86-1973)} -> #N/A | K86: {=INDEX('GMW - Baseline'!$A$2:$MC$200,MATCH(1,('GMW - Baseline'!$MC$2:$MC$200=K$3)*('GMW - Baseline'!$MB$2:$MB$200=K$4),0),$E86-1973)} -> #N/A | L86: {=INDEX('GMW - Baseline'!$A$2:$MC$200,MATCH(1,('GMW - Baseline'!$MC$2:$MC$200=L$3)*('GMW - Baseline'!$MB$2:$MB$200=L$4),0),$E86-1973)} -> #N/A | M86: {=INDEX('GMW - Baseline'!$A$2:$MC$200,MATCH(1,('GMW - Baseline'!$MC$2:$MC$200=M$3)*('GMW - Baseline'!$MB$2:$MB$200=M$4),0),$E86-1973)} -> #N/A | ... T86: {=INDEX('GMW - Baseline'!$A$2:$MC$200,MATCH(1,('GMW - Baseline'!$MC$2:$MC$200=T$3)*('GMW - Baseline'!$MB$2:$MB$200=T$4),0),$E86-1973)} -> #N/A
A87: 2000 | B87: =+B83+1 -> 2000 | C87: =+C83+1 -> 1999 | D87: =+D83+1 -> 1999 | E87: =+E86+1 -> 2060 | F87: {=INDEX('GMW - Baseline'!$A$2:$MC$200,MATCH(1,('GMW - Baseline'!$MC$2:$MC$200=F$3)*('GMW - Baseline'!$MB$2:$MB$200=F$4),0),$E87-1973)} -> 480212 | G87: {=INDEX('GMW - Baseline'!$A$2:$MC$200,MATCH(1,('GMW - Baseline'!$MC$2:$MC$200=G$3)*('GMW - Baseline'!$MB$2:$MB$200=G$4),0),$E87-1973)} -> 284274 | H87: {=INDEX('GMW - Baseline'!$A$2:$MC$200,MATCH(1,('GMW - Baseline'!$MC$2:$MC$200=H$3)*('GMW - Baseline'!$MB$2:$MB$200=H$4),0),$E87-1973)} -> 72.13333 | I87: {=INDEX('GMW - Baseline'!$A$2:$MC$200,MATCH(1,('GMW - Baseline'!$MC$2:$MC$200=I$3)*('GMW - Baseline'!$MB$2:$MB$200=I$4),0),$E87-1973)} -> 5.861538 | J87: {=INDEX('GMW - Baseline'!$A$2:$MC$200,MATCH(1,('GMW - Baseline'!$MC$2:$MC$200=J$3)*('GMW - Baseline'!$MB$2:$MB$200=J$4),0),$E87-1973)} -> #N/A | K87: {=INDEX('GMW - Baseline'!$A$2:$MC$200,MATCH(1,('GMW - Baseline'!$MC$2:$MC$200=K$3)*('GMW - Baseline'!$MB$2:$MB$200=K$4),0),$E87-1973)} -> #N/A | L87: {=INDEX('GMW - Baseline'!$A$2:$MC$200,MATCH(1,('GMW - Baseline'!$MC$2:$MC$200=L$3)*('GMW - Baseline'!$MB$2:$MB$200=L$4),0),$E87-1973)} -> #N/A | M87: {=INDEX('GMW - Baseline'!$A$2:$MC$200,MATCH(1,('GMW - Baseline'!$MC$2:$MC$200=M$3)*('GMW - Baseline'!$MB$2:$MB$200=M$4),0),$E87-1973)} -> #N/A | ... T87: {=INDEX('GMW - Baseline'!$A$2:$MC$200,MATCH(1,('GMW - Baseline'!$MC$2:$MC$200=T$3)*('GMW - Baseline'!$MB$2:$MB$200=T$4),0),$E87-1973)} -> #N/A
B88: =+B84+1 -> 2000 | C88: =+C84+1 -> 2000 | E88: =+E87+1 -> 2061 | F88: {=INDEX('GMW - Baseline'!$A$2:$MC$200,MATCH(1,('GMW - Baseline'!$MC$2:$MC$200=F$3)*('GMW - Baseline'!$MB$2:$MB$200=F$4),0),$E88-1973)} -> 483672 | G88: {=INDEX('GMW - Baseline'!$A$2:$MC$200,MATCH(1,('GMW - Baseline'!$MC$2:$MC$200=G$3)*('GMW - Baseline'!$MB$2:$MB$200=G$4),0),$E88-1973)} -> 287388 | H88: {=INDEX('GMW - Baseline'!$A$2:$MC$200,MATCH(1,('GMW - Baseline'!$MC$2:$MC$200=H$3)*('GMW - Baseline'!$MB$2:$MB$200=H$4),0),$E88-1973)} -> 72.76667 | I88: {=INDEX('GMW - Baseline'!$A$2:$MC$200,MATCH(1,('GMW - Baseline'!$MC$2:$MC$200=I$3)*('GMW - Baseline'!$MB$2:$MB$200=I$4),0),$E88-1973)} -> 6 | J88: {=INDEX('GMW - Baseline'!$A$2:$MC$200,MATCH(1,('GMW - Baseline'!$MC$2:$MC$200=J$3)*('GMW - Baseline'!$MB$2:$MB$200=J$4),0),$E88-1973)} -> #N/A | K88: {=INDEX('GMW - Baseline'!$A$2:$MC$200,MATCH(1,('GMW - Baseline'!$MC$2:$MC$200=K$3)*('GMW - Baseline'!$MB$2:$MB$200=K$4),0),$E88-1973)} -> #N/A | L88: {=INDEX('GMW - Baseline'!$A$2:$MC$200,MATCH(1,('GMW - Baseline'!$MC$2:$MC$200=L$3)*('GMW - Baseline'!$MB$2:$MB$200=L$4),0),$E88-1973)} -> #N/A | M88: {=INDEX('GMW - Baseline'!$A$2:$MC$200,MATCH(1,('GMW - Baseline'!$MC$2:$MC$200=M$3)*('GMW - Baseline'!$MB$2:$MB$200=M$4),0),$E88-1973)} -> #N/A | ... T88: {=INDEX('GMW - Baseline'!$A$2:$MC$200,MATCH(1,('GMW - Baseline'!$MC$2:$MC$200=T$3)*('GMW - Baseline'!$MB$2:$MB$200=T$4),0),$E88-1973)} -> #N/A
B89: =+B85+1 -> 2000 | C89: =+C85+1 -> 2000 | E89: =+E88+1 -> 2062 | F89: {=INDEX('GMW - Baseline'!$A$2:$MC$200,MATCH(1,('GMW - Baseline'!$MC$2:$MC$200=F$3)*('GMW - Baseline'!$MB$2:$MB$200=F$4),0),$E89-1973)} -> 486617 | G89: {=INDEX('GMW - Baseline'!$A$2:$MC$200,MATCH(1,('GMW - Baseline'!$MC$2:$MC$200=G$3)*('GMW - Baseline'!$MB$2:$MB$200=G$4),0),$E89-1973)} -> 290894 | H89: {=INDEX('GMW - Baseline'!$A$2:$MC$200,MATCH(1,('GMW - Baseline'!$MC$2:$MC$200=H$3)*('GMW - Baseline'!$MB$2:$MB$200=H$4),0),$E89-1973)} -> 72.7 | I89: {=INDEX('GMW - Baseline'!$A$2:$MC$200,MATCH(1,('GMW - Baseline'!$MC$2:$MC$200=I$3)*('GMW - Baseline'!$MB$2:$MB$200=I$4),0),$E89-1973)} -> 6 | J89: {=INDEX('GMW - Baseline'!$A$2:$MC$200,MATCH(1,('GMW - Baseline'!$MC$2:$MC$200=J$3)*('GMW - Baseline'!$MB$2:$MB$200=J$4),0),$E89-1973)} -> #N/A | K89: {=INDEX('GMW - Baseline'!$A$2:$MC$200,MATCH(1,('GMW - Baseline'!$MC$2:$MC$200=K$3)*('GMW - Baseline'!$MB$2:$MB$200=K$4),0),$E89-1973)} -> #N/A | L89: {=INDEX('GMW - Baseline'!$A$2:$MC$200,MATCH(1,('GMW - Baseline'!$MC$2:$MC$200=L$3)*('GMW - Baseline'!$MB$2:$MB$200=L$4),0),$E89-1973)} -> #N/A | M89: {=INDEX('GMW - Baseline'!$A$2:$MC$200,MATCH(1,('GMW - Baseline'!$MC$2:$MC$200=M$3)*('GMW - Baseline'!$MB$2:$MB$200=M$4),0),$E89-1973)} -> #N/A | ... T89: {=INDEX('GMW - Baseline'!$A$2:$MC$200,MATCH(1,('GMW - Baseline'!$MC$2:$MC$200=T$3)*('GMW - Baseline'!$MB$2:$MB$200=T$4),0),$E89-1973)} -> #N/A
B90: =+B86+1 -> 2000 | C90: =+C86+1 -> 2000 | E90: =+E89+1 -> 2063 | F90: {=INDEX('GMW - Baseline'!$A$2:$MC$200,MATCH(1,('GMW - Baseline'!$MC$2:$MC$200=F$3)*('GMW - Baseline'!$MB$2:$MB$200=F$4),0),$E90-1973)} -> 489506 | G90: {=INDEX('GMW - Baseline'!$A$2:$MC$200,MATCH(1,('GMW - Baseline'!$MC$2:$MC$200=G$3)*('GMW - Baseline'!$MB$2:$MB$200=G$4),0),$E90-1973)} -> 293325 | H90: {=INDEX('GMW - Baseline'!$A$2:$MC$200,MATCH(1,('GMW - Baseline'!$MC$2:$MC$200=H$3)*('GMW - Baseline'!$MB$2:$MB$200=H$4),0),$E90-1973)} -> 73.16666 | I90: {=INDEX('GMW - Baseline'!$A$2:$MC$200,MATCH(1,('GMW - Baseline'!$MC$2:$MC$200=I$3)*('GMW - Baseline'!$MB$2:$MB$200=I$4),0),$E90-1973)} -> 6 | J90: {=INDEX('GMW - Baseline'!$A$2:$MC$200,MATCH(1,('GMW - Baseline'!$MC$2:$MC$200=J$3)*('GMW - Baseline'!$MB$2:$MB$200=J$4),0),$E90-1973)} -> #N/A | K90: {=INDEX('GMW - Baseline'!$A$2:$MC$200,MATCH(1,('GMW - Baseline'!$MC$2:$MC$200=K$3)*('GMW - Baseline'!$MB$2:$MB$200=K$4),0),$E90-1973)} -> #N/A | L90: {=INDEX('GMW - Baseline'!$A$2:$MC$200,MATCH(1,('GMW - Baseline'!$MC$2:$MC$200=L$3)*('GMW - Baseline'!$MB$2:$MB$200=L$4),0),$E90-1973)} -> #N/A | M90: {=INDEX('GMW - Baseline'!$A$2:$MC$200,MATCH(1,('GMW - Baseline'!$MC$2:$MC$200=M$3)*('GMW - Baseline'!$MB$2:$MB$200=M$4),0),$E90-1973)} -> #N/A | ... T90: {=INDEX('GMW - Baseline'!$A$2:$MC$200,MATCH(1,('GMW - Baseline'!$MC$2:$MC$200=T$3)*('GMW - Baseline'!$MB$2:$MB$200=T$4),0),$E90-1973)} -> #N/A
A91: 2001 | B91: =+B87+1 -> 2001 | C91: =+C87+1 -> 2000 | D91: =+D87+1 -> 2000 | E91: =+E90+1 -> 2064 | F91: {=INDEX('GMW - Baseline'!$A$2:$MC$200,MATCH(1,('GMW - Baseline'!$MC$2:$MC$200=F$3)*('GMW - Baseline'!$MB$2:$MB$200=F$4),0),$E91-1973)} -> 493575 | G91: {=INDEX('GMW - Baseline'!$A$2:$MC$200,MATCH(1,('GMW - Baseline'!$MC$2:$MC$200=G$3)*('GMW - Baseline'!$MB$2:$MB$200=G$4),0),$E91-1973)} -> 294155 | H91: {=INDEX('GMW - Baseline'!$A$2:$MC$200,MATCH(1,('GMW - Baseline'!$MC$2:$MC$200=H$3)*('GMW - Baseline'!$MB$2:$MB$200=H$4),0),$E91-1973)} -> 72.76667 | I91: {=INDEX('GMW - Baseline'!$A$2:$MC$200,MATCH(1,('GMW - Baseline'!$MC$2:$MC$200=I$3)*('GMW - Baseline'!$MB$2:$MB$200=I$4),0),$E91-1973)} -> 5.857692 | J91: {=INDEX('GMW - Baseline'!$A$2:$MC$200,MATCH(1,('GMW - Baseline'!$MC$2:$MC$200=J$3)*('GMW - Baseline'!$MB$2:$MB$200=J$4),0),$E91-1973)} -> #N/A | K91: {=INDEX('GMW - Baseline'!$A$2:$MC$200,MATCH(1,('GMW - Baseline'!$MC$2:$MC$200=K$3)*('GMW - Baseline'!$MB$2:$MB$200=K$4),0),$E91-1973)} -> #N/A | L91: {=INDEX('GMW - Baseline'!$A$2:$MC$200,MATCH(1,('GMW - Baseline'!$MC$2:$MC$200=L$3)*('GMW - Baseline'!$MB$2:$MB$200=L$4),0),$E91-1973)} -> #N/A | M91: {=INDEX('GMW - Baseline'!$A$2:$MC$200,MATCH(1,('GMW - Baseline'!$MC$2:$MC$200=M$3)*('GMW - Baseline'!$MB$2:$MB$200=M$4),0),$E91-1973)} -> #N/A | ... T91: {=INDEX('GMW - Baseline'!$A$2:$MC$200,MATCH(1,('GMW - Baseline'!$MC$2:$MC$200=T$3)*('GMW - Baseline'!$MB$2:$MB$200=T$4),0),$E91-1973)} -> #N/A
B92: =+B88+1 -> 2001 | C92: =+C88+1 -> 2001 | E92: =+E91+1 -> 2065 | F92: {=INDEX('GMW - Baseline'!$A$2:$MC$200,MATCH(1,('GMW - Baseline'!$MC$2:$MC$200=F$3)*('GMW - Baseline'!$MB$2:$MB$200=F$4),0),$E92-1973)} -> 495602 | G92: {=INDEX('GMW - Baseline'!$A$2:$MC$200,MATCH(1,('GMW - Baseline'!$MC$2:$MC$200=G$3)*('GMW - Baseline'!$MB$2:$MB$200=G$4),0),$E92-1973)} -> 296378 | H92: {=INDEX('GMW - Baseline'!$A$2:$MC$200,MATCH(1,('GMW - Baseline'!$MC$2:$MC$200=H$3)*('GMW - Baseline'!$MB$2:$MB$200=H$4),0),$E92-1973)} -> 73.83334 | I92: {=INDEX('GMW - Baseline'!$A$2:$MC$200,MATCH(1,('GMW - Baseline'!$MC$2:$MC$200=I$3)*('GMW - Baseline'!$MB$2:$MB$200=I$4),0),$E92-1973)} -> 5.369231 | J92: {=INDEX('GMW - Baseline'!$A$2:$MC$200,MATCH(1,('GMW - Baseline'!$MC$2:$MC$200=J$3)*('GMW - Baseline'!$MB$2:$MB$200=J$4),0),$E92-1973)} -> #N/A | K92: {=INDEX('GMW - Baseline'!$A$2:$MC$200,MATCH(1,('GMW - Baseline'!$MC$2:$MC$200=K$3)*('GMW - Baseline'!$MB$2:$MB$200=K$4),0),$E92-1973)} -> #N/A | L92: {=INDEX('GMW - Baseline'!$A$2:$MC$200,MATCH(1,('GMW - Baseline'!$MC$2:$MC$200=L$3)*('GMW - Baseline'!$MB$2:$MB$200=L$4),0),$E92-1973)} -> #N/A | M92: {=INDEX('GMW - Baseline'!$A$2:$MC$200,MATCH(1,('GMW - Baseline'!$MC$2:$MC$200=M$3)*('GMW - Baseline'!$MB$2:$MB$200=M$4),0),$E92-1973)} -> #N/A | ... T92: {=INDEX('GMW - Baseline'!$A$2:$MC$200,MATCH(1,('GMW - Baseline'!$MC$2:$MC$200=T$3)*('GMW - Baseline'!$MB$2:$MB$200=T$4),0),$E92-1973)} -> #N/A
B93: =+B89+1 -> 2001 | C93: =+C89+1 -> 2001 | E93: =+E92+1 -> 2066 | F93: {=INDEX('GMW - Baseline'!$A$2:$MC$200,MATCH(1,('GMW - Baseline'!$MC$2:$MC$200=F$3)*('GMW - Baseline'!$MB$2:$MB$200=F$4),0),$E93-1973)} -> 497938 | G93: {=INDEX('GMW - Baseline'!$A$2:$MC$200,MATCH(1,('GMW - Baseline'!$MC$2:$MC$200=G$3)*('GMW - Baseline'!$MB$2:$MB$200=G$4),0),$E93-1973)} -> 300827 | H93: {=INDEX('GMW - Baseline'!$A$2:$MC$200,MATCH(1,('GMW - Baseline'!$MC$2:$MC$200=H$3)*('GMW - Baseline'!$MB$2:$MB$200=H$4),0),$E93-1973)} -> 73.86667 | I93: {=INDEX('GMW - Baseline'!$A$2:$MC$200,MATCH(1,('GMW - Baseline'!$MC$2:$MC$200=I$3)*('GMW - Baseline'!$MB$2:$MB$200=I$4),0),$E93-1973)} -> 5.053846 | J93: {=INDEX('GMW - Baseline'!$A$2:$MC$200,MATCH(1,('GMW - Baseline'!$MC$2:$MC$200=J$3)*('GMW - Baseline'!$MB$2:$MB$200=J$4),0),$E93-1973)} -> #N/A | K93: {=INDEX('GMW - Baseline'!$A$2:$MC$200,MATCH(1,('GMW - Baseline'!$MC$2:$MC$200=K$3)*('GMW - Baseline'!$MB$2:$MB$200=K$4),0),$E93-1973)} -> #N/A | L93: {=INDEX('GMW - Baseline'!$A$2:$MC$200,MATCH(1,('GMW - Baseline'!$MC$2:$MC$200=L$3)*('GMW - Baseline'!$MB$2:$MB$200=L$4),0),$E93-1973)} -> #N/A | M93: {=INDEX('GMW - Baseline'!$A$2:$MC$200,MATCH(1,('GMW - Baseline'!$MC$2:$MC$200=M$3)*('GMW - Baseline'!$MB$2:$MB$200=M$4),0),$E93-1973)} -> #N/A | ... T93: {=INDEX('GMW - Baseline'!$A$2:$MC$200,MATCH(1,('GMW - Baseline'!$MC$2:$MC$200=T$3)*('GMW - Baseline'!$MB$2:$MB$200=T$4),0),$E93-1973)} -> #N/A
B94: =+B90+1 -> 2001 | C94: =+C90+1 -> 2001 | E94: =+E93+1 -> 2067 | F94: {=INDEX('GMW - Baseline'!$A$2:$MC$200,MATCH(1,('GMW - Baseline'!$MC$2:$MC$200=F$3)*('GMW - Baseline'!$MB$2:$MB$200=F$4),0),$E94-1973)} -> 499278 | G94: {=INDEX('GMW - Baseline'!$A$2:$MC$200,MATCH(1,('GMW - Baseline'!$MC$2:$MC$200=G$3)*('GMW - Baseline'!$MB$2:$MB$200=G$4),0),$E94-1973)} -> 303055 | H94: {=INDEX('GMW - Baseline'!$A$2:$MC$200,MATCH(1,('GMW - Baseline'!$MC$2:$MC$200=H$3)*('GMW - Baseline'!$MB$2:$MB$200=H$4),0),$E94-1973)} -> 73.9 | I94: {=INDEX('GMW - Baseline'!$A$2:$MC$200,MATCH(1,('GMW - Baseline'!$MC$2:$MC$200=I$3)*('GMW - Baseline'!$MB$2:$MB$200=I$4),0),$E94-1973)} -> 4.223485 | J94: {=INDEX('GMW - Baseline'!$A$2:$MC$200,MATCH(1,('GMW - Baseline'!$MC$2:$MC$200=J$3)*('GMW - Baseline'!$MB$2:$MB$200=J$4),0),$E94-1973)} -> #N/A | K94: {=INDEX('GMW - Baseline'!$A$2:$MC$200,MATCH(1,('GMW - Baseline'!$MC$2:$MC$200=K$3)*('GMW - Baseline'!$MB$2:$MB$200=K$4),0),$E94-1973)} -> #N/A | L94: {=INDEX('GMW - Baseline'!$A$2:$MC$200,MATCH(1,('GMW - Baseline'!$MC$2:$MC$200=L$3)*('GMW - Baseline'!$MB$2:$MB$200=L$4),0),$E94-1973)} -> #N/A | M94: {=INDEX('GMW - Baseline'!$A$2:$MC$200,MATCH(1,('GMW - Baseline'!$MC$2:$MC$200=M$3)*('GMW - Baseline'!$MB$2:$MB$200=M$4),0),$E94-1973)} -> #N/A | ... T94: {=INDEX('GMW - Baseline'!$A$2:$MC$200,MATCH(1,('GMW - Baseline'!$MC$2:$MC$200=T$3)*('GMW - Baseline'!$MB$2:$MB$200=T$4),0),$E94-1973)} -> #N/A
A95: 2002 | B95: =+B91+1 -> 2002 | C95: =+C91+1 -> 2001 | D95: =+D91+1 -> 2001 | E95: =+E94+1 -> 2068 | F95: {=INDEX('GMW - Baseline'!$A$2:$MC$200,MATCH(1,('GMW - Baseline'!$MC$2:$MC$200=F$3)*('GMW - Baseline'!$MB$2:$MB$200=F$4),0),$E95-1973)} -> 500794 | G95: {=INDEX('GMW - Baseline'!$A$2:$MC$200,MATCH(1,('GMW - Baseline'!$MC$2:$MC$200=G$3)*('GMW - Baseline'!$MB$2:$MB$200=G$4),0),$E95-1973)} -> 303450 | H95: {=INDEX('GMW - Baseline'!$A$2:$MC$200,MATCH(1,('GMW - Baseline'!$MC$2:$MC$200=H$3)*('GMW - Baseline'!$MB$2:$MB$200=H$4),0),$E95-1973)} -> 73.86667 | I95: {=INDEX('GMW - Baseline'!$A$2:$MC$200,MATCH(1,('GMW - Baseline'!$MC$2:$MC$200=I$3)*('GMW - Baseline'!$MB$2:$MB$200=I$4),0),$E95-1973)} -> 4 | J95: {=INDEX('GMW - Baseline'!$A$2:$MC$200,MATCH(1,('GMW - Baseline'!$MC$2:$MC$200=J$3)*('GMW - Baseline'!$MB$2:$MB$200=J$4),0),$E95-1973)} -> #N/A | K95: {=INDEX('GMW - Baseline'!$A$2:$MC$200,MATCH(1,('GMW - Baseline'!$MC$2:$MC$200=K$3)*('GMW - Baseline'!$MB$2:$MB$200=K$4),0),$E95-1973)} -> #N/A | L95: {=INDEX('GMW - Baseline'!$A$2:$MC$200,MATCH(1,('GMW - Baseline'!$MC$2:$MC$200=L$3)*('GMW - Baseline'!$MB$2:$MB$200=L$4),0),$E95-1973)} -> #N/A | M95: {=INDEX('GMW - Baseline'!$A$2:$MC$200,MATCH(1,('GMW - Baseline'!$MC$2:$MC$200=M$3)*('GMW - Baseline'!$MB$2:$MB$200=M$4),0),$E95-1973)} -> #N/A | ... T95: {=INDEX('GMW - Baseline'!$A$2:$MC$200,MATCH(1,('GMW - Baseline'!$MC$2:$MC$200=T$3)*('GMW - Baseline'!$MB$2:$MB$200=T$4),0),$E95-1973)} -> #N/A
B96: =+B92+1 -> 2002 | C96: =+C92+1 -> 2002 | E96: =+E95+1 -> 2069 | F96: {=INDEX('GMW - Baseline'!$A$2:$MC$200,MATCH(1,('GMW - Baseline'!$MC$2:$MC$200=F$3)*('GMW - Baseline'!$MB$2:$MB$200=F$4),0),$E96-1973)} -> 503433 | G96: {=INDEX('GMW - Baseline'!$A$2:$MC$200,MATCH(1,('GMW - Baseline'!$MC$2:$MC$200=G$3)*('GMW - Baseline'!$MB$2:$MB$200=G$4),0),$E96-1973)} -> 304764 | H96: {=INDEX('GMW - Baseline'!$A$2:$MC$200,MATCH(1,('GMW - Baseline'!$MC$2:$MC$200=H$3)*('GMW - Baseline'!$MB$2:$MB$200=H$4),0),$E96-1973)} -> 74.53333 | I96: {=INDEX('GMW - Baseline'!$A$2:$MC$200,MATCH(1,('GMW - Baseline'!$MC$2:$MC$200=I$3)*('GMW - Baseline'!$MB$2:$MB$200=I$4),0),$E96-1973)} -> 4 | J96: {=INDEX('GMW - Baseline'!$A$2:$MC$200,MATCH(1,('GMW - Baseline'!$MC$2:$MC$200=J$3)*('GMW - Baseline'!$MB$2:$MB$200=J$4),0),$E96-1973)} -> #N/A | K96: {=INDEX('GMW - Baseline'!$A$2:$MC$200,MATCH(1,('GMW - Baseline'!$MC$2:$MC$200=K$3)*('GMW - Baseline'!$MB$2:$MB$200=K$4),0),$E96-1973)} -> #N/A | L96: {=INDEX('GMW - Baseline'!$A$2:$MC$200,MATCH(1,('GMW - Baseline'!$MC$2:$MC$200=L$3)*('GMW - Baseline'!$MB$2:$MB$200=L$4),0),$E96-1973)} -> #N/A | M96: {=INDEX('GMW - Baseline'!$A$2:$MC$200,MATCH(1,('GMW - Baseline'!$MC$2:$MC$200=M$3)*('GMW - Baseline'!$MB$2:$MB$200=M$4),0),$E96-1973)} -> #N/A | ... T96: {=INDEX('GMW - Baseline'!$A$2:$MC$200,MATCH(1,('GMW - Baseline'!$MC$2:$MC$200=T$3)*('GMW - Baseline'!$MB$2:$MB$200=T$4),0),$E96-1973)} -> #N/A
B97: =+B93+1 -> 2002 | C97: =+C93+1 -> 2002 | E97: =+E96+1 -> 2070 | F97: {=INDEX('GMW - Baseline'!$A$2:$MC$200,MATCH(1,('GMW - Baseline'!$MC$2:$MC$200=F$3)*('GMW - Baseline'!$MB$2:$MB$200=F$4),0),$E97-1973)} -> 506386 | G97: {=INDEX('GMW - Baseline'!$A$2:$MC$200,MATCH(1,('GMW - Baseline'!$MC$2:$MC$200=G$3)*('GMW - Baseline'!$MB$2:$MB$200=G$4),0),$E97-1973)} -> 307772 | H97: {=INDEX('GMW - Baseline'!$A$2:$MC$200,MATCH(1,('GMW - Baseline'!$MC$2:$MC$200=H$3)*('GMW - Baseline'!$MB$2:$MB$200=H$4),0),$E97-1973)} -> 74.6 | I97: {=INDEX('GMW - Baseline'!$A$2:$MC$200,MATCH(1,('GMW - Baseline'!$MC$2:$MC$200=I$3)*('GMW - Baseline'!$MB$2:$MB$200=I$4),0),$E97-1973)} -> 4 | J97: {=INDEX('GMW - Baseline'!$A$2:$MC$200,MATCH(1,('GMW - Baseline'!$MC$2:$MC$200=J$3)*('GMW - Baseline'!$MB$2:$MB$200=J$4),0),$E97-1973)} -> #N/A | K97: {=INDEX('GMW - Baseline'!$A$2:$MC$200,MATCH(1,('GMW - Baseline'!$MC$2:$MC$200=K$3)*('GMW - Baseline'!$MB$2:$MB$200=K$4),0),$E97-1973)} -> #N/A | L97: {=INDEX('GMW - Baseline'!$A$2:$MC$200,MATCH(1,('GMW - Baseline'!$MC$2:$MC$200=L$3)*('GMW - Baseline'!$MB$2:$MB$200=L$4),0),$E97-1973)} -> #N/A | M97: {=INDEX('GMW - Baseline'!$A$2:$MC$200,MATCH(1,('GMW - Baseline'!$MC$2:$MC$200=M$3)*('GMW - Baseline'!$MB$2:$MB$200=M$4),0),$E97-1973)} -> #N/A | ... T97: {=INDEX('GMW - Baseline'!$A$2:$MC$200,MATCH(1,('GMW - Baseline'!$MC$2:$MC$200=T$3)*('GMW - Baseline'!$MB$2:$MB$200=T$4),0),$E97-1973)} -> #N/A
B98: =+B94+1 -> 2002 | C98: =+C94+1 -> 2002 | E98: =+E97+1 -> 2071 | F98: {=INDEX('GMW - Baseline'!$A$2:$MC$200,MATCH(1,('GMW - Baseline'!$MC$2:$MC$200=F$3)*('GMW - Baseline'!$MB$2:$MB$200=F$4),0),$E98-1973)} -> 509728 | G98: {=INDEX('GMW - Baseline'!$A$2:$MC$200,MATCH(1,('GMW - Baseline'!$MC$2:$MC$200=G$3)*('GMW - Baseline'!$MB$2:$MB$200=G$4),0),$E98-1973)} -> 310517 | H98: {=INDEX('GMW - Baseline'!$A$2:$MC$200,MATCH(1,('GMW - Baseline'!$MC$2:$MC$200=H$3)*('GMW - Baseline'!$MB$2:$MB$200=H$4),0),$E98-1973)} -> 75 | I98: {=INDEX('GMW - Baseline'!$A$2:$MC$200,MATCH(1,('GMW - Baseline'!$MC$2:$MC$200=I$3)*('GMW - Baseline'!$MB$2:$MB$200=I$4),0),$E98-1973)} -> 4 | J98: {=INDEX('GMW - Baseline'!$A$2:$MC$200,MATCH(1,('GMW - Baseline'!$MC$2:$MC$200=J$3)*('GMW - Baseline'!$MB$2:$MB$200=J$4),0),$E98-1973)} -> #N/A | K98: {=INDEX('GMW - Baseline'!$A$2:$MC$200,MATCH(1,('GMW - Baseline'!$MC$2:$MC$200=K$3)*('GMW - Baseline'!$MB$2:$MB$200=K$4),0),$E98-1973)} -> #N/A | L98: {=INDEX('GMW - Baseline'!$A$2:$MC$200,MATCH(1,('GMW - Baseline'!$MC$2:$MC$200=L$3)*('GMW - Baseline'!$MB$2:$MB$200=L$4),0),$E98-1973)} -> #N/A | M98: {=INDEX('GMW - Baseline'!$A$2:$MC$200,MATCH(1,('GMW - Baseline'!$MC$2:$MC$200=M$3)*('GMW - Baseline'!$MB$2:$MB$200=M$4),0),$E98-1973)} -> #N/A | ... T98: {=INDEX('GMW - Baseline'!$A$2:$MC$200,MATCH(1,('GMW - Baseline'!$MC$2:$MC$200=T$3)*('GMW - Baseline'!$MB$2:$MB$200=T$4),0),$E98-1973)} -> #N/A
A99: 2003 | B99: =+B95+1 -> 2003 | C99: =+C95+1 -> 2002 | D99: =+D95+1 -> 2002 | E99: =+E98+1 -> 2072 | F99: {=INDEX('GMW - Baseline'!$A$2:$MC$200,MATCH(1,('GMW - Baseline'!$MC$2:$MC$200=F$3)*('GMW - Baseline'!$MB$2:$MB$200=F$4),0),$E99-1973)} -> 514031 | G99: {=INDEX('GMW - Baseline'!$A$2:$MC$200,MATCH(1,('GMW - Baseline'!$MC$2:$MC$200=G$3)*('GMW - Baseline'!$MB$2:$MB$200=G$4),0),$E99-1973)} -> 312554 | H99: {=INDEX('GMW - Baseline'!$A$2:$MC$200,MATCH(1,('GMW - Baseline'!$MC$2:$MC$200=H$3)*('GMW - Baseline'!$MB$2:$MB$200=H$4),0),$E99-1973)} -> 75 | I99: {=INDEX('GMW - Baseline'!$A$2:$MC$200,MATCH(1,('GMW - Baseline'!$MC$2:$MC$200=I$3)*('GMW - Baseline'!$MB$2:$MB$200=I$4),0),$E99-1973)} -> 3.851563 | J99: {=INDEX('GMW - Baseline'!$A$2:$MC$200,MATCH(1,('GMW - Baseline'!$MC$2:$MC$200=J$3)*('GMW - Baseline'!$MB$2:$MB$200=J$4),0),$E99-1973)} -> #N/A | K99: {=INDEX('GMW - Baseline'!$A$2:$MC$200,MATCH(1,('GMW - Baseline'!$MC$2:$MC$200=K$3)*('GMW - Baseline'!$MB$2:$MB$200=K$4),0),$E99-1973)} -> #N/A | L99: {=INDEX('GMW - Baseline'!$A$2:$MC$200,MATCH(1,('GMW - Baseline'!$MC$2:$MC$200=L$3)*('GMW - Baseline'!$MB$2:$MB$200=L$4),0),$E99-1973)} -> #N/A | M99: {=INDEX('GMW - Baseline'!$A$2:$MC$200,MATCH(1,('GMW - Baseline'!$MC$2:$MC$200=M$3)*('GMW - Baseline'!$MB$2:$MB$200=M$4),0),$E99-1973)} -> #N/A | ... T99: {=INDEX('GMW - Baseline'!$A$2:$MC$200,MATCH(1,('GMW - Baseline'!$MC$2:$MC$200=T$3)*('GMW - Baseline'!$MB$2:$MB$200=T$4),0),$E99-1973)} -> #N/A
B100: =+B96+1 -> 2003 | C100: =+C96+1 -> 2003 | E100: =+E99+1 -> 2073 | F100: {=INDEX('GMW - Baseline'!$A$2:$MC$200,MATCH(1,('GMW - Baseline'!$MC$2:$MC$200=F$3)*('GMW - Baseline'!$MB$2:$MB$200=F$4),0),$E100-1973)} -> 518802 | G100: {=INDEX('GMW - Baseline'!$A$2:$MC$200,MATCH(1,('GMW - Baseline'!$MC$2:$MC$200=G$3)*('GMW - Baseline'!$MB$2:$MB$200=G$4),0),$E100-1973)} -> 316413 | H100: {=INDEX('GMW - Baseline'!$A$2:$MC$200,MATCH(1,('GMW - Baseline'!$MC$2:$MC$200=H$3)*('GMW - Baseline'!$MB$2:$MB$200=H$4),0),$E100-1973)} -> 75.46667 | I100: {=INDEX('GMW - Baseline'!$A$2:$MC$200,MATCH(1,('GMW - Baseline'!$MC$2:$MC$200=I$3)*('GMW - Baseline'!$MB$2:$MB$200=I$4),0),$E100-1973)} -> 3.75 | J100: {=INDEX('GMW - Baseline'!$A$2:$MC$200,MATCH(1,('GMW - Baseline'!$MC$2:$MC$200=J$3)*('GMW - Baseline'!$MB$2:$MB$200=J$4),0),$E100-1973)} -> #N/A | K100: {=INDEX('GMW - Baseline'!$A$2:$MC$200,MATCH(1,('GMW - Baseline'!$MC$2:$MC$200=K$3)*('GMW - Baseline'!$MB$2:$MB$200=K$4),0),$E100-1973)} -> #N/A | L100: {=INDEX('GMW - Baseline'!$A$2:$MC$200,MATCH(1,('GMW - Baseline'!$MC$2:$MC$200=L$3)*('GMW - Baseline'!$MB$2:$MB$200=L$4),0),$E100-1973)} -> #N/A | M100: {=INDEX('GMW - Baseline'!$A$2:$MC$200,MATCH(1,('GMW - Baseline'!$MC$2:$MC$200=M$3)*('GMW - Baseline'!$MB$2:$MB$200=M$4),0),$E100-1973)} -> #N/A | ... T100: {=INDEX('GMW - Baseline'!$A$2:$MC$200,MATCH(1,('GMW - Baseline'!$MC$2:$MC$200=T$3)*('GMW - Baseline'!$MB$2:$MB$200=T$4),0),$E100-1973)} -> #N/A
...

Sheet GEM data - $100 oil
B1: lookups | C1: lookups | D1: lookups | F1: ='GMW - $100 oil'!C2 -> Oil_100 | G1: =$F$1 -> Oil_100 | H1: =$F$1 -> Oil_100 | I1: =$F$1 -> Oil_100 | J1: =$F$1 -> Oil_100 | K1: =$F$1 -> Oil_100 | L1: =$F$1 -> Oil_100 | M1: =$F$1 -> Oil_100 | N1: =$F$1 -> Oil_100 | ... T1: =$F$1 -> Oil_100
F2: UK | G2: UK | H2: UK | I2: UK | J2: UK | K2: UK | L2: UK | M2: UK | N2: UK | O2: UK | P2: UK | Q2: UK | R2: UK | S2: UK | T2: UK
F3: GDP | G3: C | H3: CPI | I3: RCB
F4: GBR | G4: GBR | H4: GBR | I4: GBR | J4: GBR | K4: GBR | L4: GBR | M4: GBR | N4: GBR | O4: GBR | P4: GBR | Q4: GBR | R4: GBR | S4: GBR | T4: GBR
F5: L | G5: L | H5: L | I5: L | J5: L | K5: L | L5: L | M5: L | N5: L | O5: L | P5: L | Q5: L | R5: L | S5: L | T5: L
B6: CY total | C6: FY total | D6: FY end | E6: =E330+5 -> 2308 | F6: {=_xlfn.CONCAT(INDEX('GMW - $100 oil'!$A$2:$MC$200,MATCH(1,('GMW - $100 oil'!$MC$2:$MC$200=F$3)*('GMW - $100 oil'!$MB$2:$MB$200=F$4),0),$E6-1973),"0",(INDEX('GMW - $100 oil'!$A$2:$MC$200,MATCH(1,('GMW - $100 oil'!$MC$2:$MC$200=F$3)*('GMW - $100 oil'!$MB$2:$MB$200=F$4),0),$E6-1972)))} -> 202504 | G6: {=_xlfn.CONCAT(INDEX('GMW - $100 oil'!$A$2:$MC$200,MATCH(1,('GMW - $100 oil'!$MC$2:$MC$200=G$3)*('GMW - $100 oil'!$MB$2:$MB$200=G$4),0),$E6-1973),"0",(INDEX('GMW - $100 oil'!$A$2:$MC$200,MATCH(1,('GMW - $100 oil'!$MC$2:$MC$200=G$3)*('GMW - $100 oil'!$MB$2:$MB$200=G$4),0),$E6-1972)))} -> 202504 | H6: {=_xlfn.CONCAT(INDEX('GMW - $100 oil'!$A$2:$MC$200,MATCH(1,('GMW - $100 oil'!$MC$2:$MC$200=H$3)*('GMW - $100 oil'!$MB$2:$MB$200=H$4),0),$E6-1973),"0",(INDEX('GMW - $100 oil'!$A$2:$MC$200,MATCH(1,('GMW - $100 oil'!$MC$2:$MC$200=H$3)*('GMW - $100 oil'!$MB$2:$MB$200=H$4),0),$E6-1972)))} -> 202504 | I6: {=_xlfn.CONCAT(INDEX('GMW - $100 oil'!$A$2:$MC$200,MATCH(1,('GMW - $100 oil'!$MC$2:$MC$200=I$3)*('GMW - $100 oil'!$MB$2:$MB$200=I$4),0),$E6-1973),"0",(INDEX('GMW - $100 oil'!$A$2:$MC$200,MATCH(1,('GMW - $100 oil'!$MC$2:$MC$200=I$3)*('GMW - $100 oil'!$MB$2:$MB$200=I$4),0),$E6-1972)))} -> 202504 | J6: {=_xlfn.CONCAT(INDEX('GMW - $100 oil'!$A$2:$MC$200,MATCH(1,('GMW - $100 oil'!$MC$2:$MC$200=J$3)*('GMW - $100 oil'!$MB$2:$MB$200=J$4),0),$E6-1973),"0",(INDEX('GMW - $100 oil'!$A$2:$MC$200,MATCH(1,('GMW - $100 oil'!$MC$2:$MC$200=J$3)*('GMW - $100 oil'!$MB$2:$MB$200=J$4),0),$E6-1972)))} -> #N/A | K6: {=_xlfn.CONCAT(INDEX('GMW - $100 oil'!$A$2:$MC$200,MATCH(1,('GMW - $100 oil'!$MC$2:$MC$200=K$3)*('GMW - $100 oil'!$MB$2:$MB$200=K$4),0),$E6-1973),"0",(INDEX('GMW - $100 oil'!$A$2:$MC$200,MATCH(1,('GMW - $100 oil'!$MC$2:$MC$200=K$3)*('GMW - $100 oil'!$MB$2:$MB$200=K$4),0),$E6-1972)))} -> #N/A | L6: {=_xlfn.CONCAT(INDEX('GMW - $100 oil'!$A$2:$MC$200,MATCH(1,('GMW - $100 oil'!$MC$2:$MC$200=L$3)*('GMW - $100 oil'!$MB$2:$MB$200=L$4),0),$E6-1973),"0",(INDEX('GMW - $100 oil'!$A$2:$MC$200,MATCH(1,('GMW - $100 oil'!$MC$2:$MC$200=L$3)*('GMW - $100 oil'!$MB$2:$MB$200=L$4),0),$E6-1972)))} -> #N/A | M6: {=_xlfn.CONCAT(INDEX('GMW - $100 oil'!$A$2:$MC$200,MATCH(1,('GMW - $100 oil'!$MC$2:$MC$200=M$3)*('GMW - $100 oil'!$MB$2:$MB$200=M$4),0),$E6-1973),"0",(INDEX('GMW - $100 oil'!$A$2:$MC$200,MATCH(1,('GMW - $100 oil'!$MC$2:$MC$200=M$3)*('GMW - $100 oil'!$MB$2:$MB$200=M$4),0),$E6-1972)))} -> #N/A | ... T6: {=_xlfn.CONCAT(INDEX('GMW - $100 oil'!$A$2:$MC$200,MATCH(1,('GMW - $100 oil'!$MC$2:$MC$200=T$3)*('GMW - $100 oil'!$MB$2:$MB$200=T$4),0),$E6-1973),"0",(INDEX('GMW - $100 oil'!$A$2:$MC$200,MATCH(1,('GMW - $100 oil'!$MC$2:$MC$200=T$3)*('GMW - $100 oil'!$MB$2:$MB$200=T$4),0),$E6-1972)))} -> #N/A
A7: 1980 | B7: 1980 | E7: 1980 | F7: {=INDEX('GMW - $100 oil'!$A$2:$MC$200,MATCH(1,('GMW - $100 oil'!$MC$2:$MC$200=F$3)*('GMW - $100 oil'!$MB$2:$MB$200=F$4),0),$E7-1973)} -> 290378 | G7: {=INDEX('GMW - $100 oil'!$A$2:$MC$200,MATCH(1,('GMW - $100 oil'!$MC$2:$MC$200=G$3)*('GMW - $100 oil'!$MB$2:$MB$200=G$4),0),$E7-1973)} -> 153439 | H7: {=INDEX('GMW - $100 oil'!$A$2:$MC$200,MATCH(1,('GMW - $100 oil'!$MC$2:$MC$200=H$3)*('GMW - $100 oil'!$MB$2:$MB$200=H$4),0),$E7-1973)} -> 30.60508 | I7: {=INDEX('GMW - $100 oil'!$A$2:$MC$200,MATCH(1,('GMW - $100 oil'!$MC$2:$MC$200=I$3)*('GMW - $100 oil'!$MB$2:$MB$200=I$4),0),$E7-1973)} -> 17 | J7: {=INDEX('GMW - $100 oil'!$A$2:$MC$200,MATCH(1,('GMW - $100 oil'!$MC$2:$MC$200=J$3)*('GMW - $100 oil'!$MB$2:$MB$200=J$4),0),$E7-1973)} -> #N/A | K7: {=INDEX('GMW - $100 oil'!$A$2:$MC$200,MATCH(1,('GMW - $100 oil'!$MC$2:$MC$200=K$3)*('GMW - $100 oil'!$MB$2:$MB$200=K$4),0),$E7-1973)} -> #N/A | L7: {=INDEX('GMW - $100 oil'!$A$2:$MC$200,MATCH(1,('GMW - $100 oil'!$MC$2:$MC$200=L$3)*('GMW - $100 oil'!$MB$2:$MB$200=L$4),0),$E7-1973)} -> #N/A | M7: {=INDEX('GMW - $100 oil'!$A$2:$MC$200,MATCH(1,('GMW - $100 oil'!$MC$2:$MC$200=M$3)*('GMW - $100 oil'!$MB$2:$MB$200=M$4),0),$E7-1973)} -> #N/A | ... T7: {=INDEX('GMW - $100 oil'!$A$2:$MC$200,MATCH(1,('GMW - $100 oil'!$MC$2:$MC$200=T$3)*('GMW - $100 oil'!$MB$2:$MB$200=T$4),0),$E7-1973)} -> #N/A
B8: 1980 | C8: 1980 | E8: =+E7+1 -> 1981 | F8: {=INDEX('GMW - $100 oil'!$A$2:$MC$200,MATCH(1,('GMW - $100 oil'!$MC$2:$MC$200=F$3)*('GMW - $100 oil'!$MB$2:$MB$200=F$4),0),$E8-1973)} -> 284713 | G8: {=INDEX('GMW - $100 oil'!$A$2:$MC$200,MATCH(1,('GMW - $100 oil'!$MC$2:$MC$200=G$3)*('GMW - $100 oil'!$MB$2:$MB$200=G$4),0),$E8-1973)} -> 149443 | H8: {=INDEX('GMW - $100 oil'!$A$2:$MC$200,MATCH(1,('GMW - $100 oil'!$MC$2:$MC$200=H$3)*('GMW - $100 oil'!$MB$2:$MB$200=H$4),0),$E8-1973)} -> 32.24743 | I8: {=INDEX('GMW - $100 oil'!$A$2:$MC$200,MATCH(1,('GMW - $100 oil'!$MC$2:$MC$200=I$3)*('GMW - $100 oil'!$MB$2:$MB$200=I$4),0),$E8-1973)} -> 17 | J8: {=INDEX('GMW - $100 oil'!$A$2:$MC$200,MATCH(1,('GMW - $100 oil'!$MC$2:$MC$200=J$3)*('GMW - $100 oil'!$MB$2:$MB$200=J$4),0),$E8-1973)} -> #N/A | K8: {=INDEX('GMW - $100 oil'!$A$2:$MC$200,MATCH(1,('GMW - $100 oil'!$MC$2:$MC$200=K$3)*('GMW - $100 oil'!$MB$2:$MB$200=K$4),0),$E8-1973)} -> #N/A | L8: {=INDEX('GMW - $100 oil'!$A$2:$MC$200,MATCH(1,('GMW - $100 oil'!$MC$2:$MC$200=L$3)*('GMW - $100 oil'!$MB$2:$MB$200=L$4),0),$E8-1973)} -> #N/A | M8: {=INDEX('GMW - $100 oil'!$A$2:$MC$200,MATCH(1,('GMW - $100 oil'!$MC$2:$MC$200=M$3)*('GMW - $100 oil'!$MB$2:$MB$200=M$4),0),$E8-1973)} -> #N/A | ... T8: {=INDEX('GMW - $100 oil'!$A$2:$MC$200,MATCH(1,('GMW - $100 oil'!$MC$2:$MC$200=T$3)*('GMW - $100 oil'!$MB$2:$MB$200=T$4),0),$E8-1973)} -> #N/A
B9: 1980 | C9: 1980 | E9: =+E8+1 -> 1982 | F9: {=INDEX('GMW - $100 oil'!$A$2:$MC$200,MATCH(1,('GMW - $100 oil'!$MC$2:$MC$200=F$3)*('GMW - $100 oil'!$MB$2:$MB$200=F$4),0),$E9-1973)} -> 284402 | G9: {=INDEX('GMW - $100 oil'!$A$2:$MC$200,MATCH(1,('GMW - $100 oil'!$MC$2:$MC$200=G$3)*('GMW - $100 oil'!$MB$2:$MB$200=G$4),0),$E9-1973)} -> 151403 | H9: {=INDEX('GMW - $100 oil'!$A$2:$MC$200,MATCH(1,('GMW - $100 oil'!$MC$2:$MC$200=H$3)*('GMW - $100 oil'!$MB$2:$MB$200=H$4),0),$E9-1973)} -> 32.9513 | I9: {=INDEX('GMW - $100 oil'!$A$2:$MC$200,MATCH(1,('GMW - $100 oil'!$MC$2:$MC$200=I$3)*('GMW - $100 oil'!$MB$2:$MB$200=I$4),0),$E9-1973)} -> 16.0303 | J9: {=INDEX('GMW - $100 oil'!$A$2:$MC$200,MATCH(1,('GMW - $100 oil'!$MC$2:$MC$200=J$3)*('GMW - $100 oil'!$MB$2:$MB$200=J$4),0),$E9-1973)} -> #N/A | K9: {=INDEX('GMW - $100 oil'!$A$2:$MC$200,MATCH(1,('GMW - $100 oil'!$MC$2:$MC$200=K$3)*('GMW - $100 oil'!$MB$2:$MB$200=K$4),0),$E9-1973)} -> #N/A | L9: {=INDEX('GMW - $100 oil'!$A$2:$MC$200,MATCH(1,('GMW - $100 oil'!$MC$2:$MC$200=L$3)*('GMW - $100 oil'!$MB$2:$MB$200=L$4),0),$E9-1973)} -> #N/A | M9: {=INDEX('GMW - $100 oil'!$A$2:$MC$200,MATCH(1,('GMW - $100 oil'!$MC$2:$MC$200=M$3)*('GMW - $100 oil'!$MB$2:$MB$200=M$4),0),$E9-1973)} -> #N/A | ... T9: {=INDEX('GMW - $100 oil'!$A$2:$MC$200,MATCH(1,('GMW - $100 oil'!$MC$2:$MC$200=T$3)*('GMW - $100 oil'!$MB$2:$MB$200=T$4),0),$E9-1973)} -> #N/A
B10: 1980 | C10: 1980 | E10: =+E9+1 -> 1983 | F10: {=INDEX('GMW - $100 oil'!$A$2:$MC$200,MATCH(1,('GMW - $100 oil'!$MC$2:$MC$200=F$3)*('GMW - $100 oil'!$MB$2:$MB$200=F$4),0),$E10-1973)} -> 281496 | G10: {=INDEX('GMW - $100 oil'!$A$2:$MC$200,MATCH(1,('GMW - $100 oil'!$MC$2:$MC$200=G$3)*('GMW - $100 oil'!$MB$2:$MB$200=G$4),0),$E10-1973)} -> 148523 | H10: {=INDEX('GMW - $100 oil'!$A$2:$MC$200,MATCH(1,('GMW - $100 oil'!$MC$2:$MC$200=H$3)*('GMW - $100 oil'!$MB$2:$MB$200=H$4),0),$E10-1973)} -> 33.55088 | I10: {=INDEX('GMW - $100 oil'!$A$2:$MC$200,MATCH(1,('GMW - $100 oil'!$MC$2:$MC$200=I$3)*('GMW - $100 oil'!$MB$2:$MB$200=I$4),0),$E10-1973)} -> 15.18182 | J10: {=INDEX('GMW - $100 oil'!$A$2:$MC$200,MATCH(1,('GMW - $100 oil'!$MC$2:$MC$200=J$3)*('GMW - $100 oil'!$MB$2:$MB$200=J$4),0),$E10-1973)} -> #N/A | K10: {=INDEX('GMW - $100 oil'!$A$2:$MC$200,MATCH(1,('GMW - $100 oil'!$MC$2:$MC$200=K$3)*('GMW - $100 oil'!$MB$2:$MB$200=K$4),0),$E10-1973)} -> #N/A | L10: {=INDEX('GMW - $100 oil'!$A$2:$MC$200,MATCH(1,('GMW - $100 oil'!$MC$2:$MC$200=L$3)*('GMW - $100 oil'!$MB$2:$MB$200=L$4),0),$E10-1973)} -> #N/A | M10: {=INDEX('GMW - $100 oil'!$A$2:$MC$200,MATCH(1,('GMW - $100 oil'!$MC$2:$MC$200=M$3)*('GMW - $100 oil'!$MB$2:$MB$200=M$4),0),$E10-1973)} -> #N/A | ... T10: {=INDEX('GMW - $100 oil'!$A$2:$MC$200,MATCH(1,('GMW - $100 oil'!$MC$2:$MC$200=T$3)*('GMW - $100 oil'!$MB$2:$MB$200=T$4),0),$E10-1973)} -> #N/A
A11: 1981 | B11: =+B7+1 -> 1981 | C11: 1980 | D11: 1980 | E11: =+E10+1 -> 1984 | F11: {=INDEX('GMW - $100 oil'!$A$2:$MC$200,MATCH(1,('GMW - $100 oil'!$MC$2:$MC$200=F$3)*('GMW - $100 oil'!$MB$2:$MB$200=F$4),0),$E11-1973)} -> 281257 | G11: {=INDEX('GMW - $100 oil'!$A$2:$MC$200,MATCH(1,('GMW - $100 oil'!$MC$2:$MC$200=G$3)*('GMW - $100 oil'!$MB$2:$MB$200=G$4),0),$E11-1973)} -> 151234 | H11: {=INDEX('GMW - $100 oil'!$A$2:$MC$200,MATCH(1,('GMW - $100 oil'!$MC$2:$MC$200=H$3)*('GMW - $100 oil'!$MB$2:$MB$200=H$4),0),$E11-1973)} -> 34.3851 | I11: {=INDEX('GMW - $100 oil'!$A$2:$MC$200,MATCH(1,('GMW - $100 oil'!$MC$2:$MC$200=I$3)*('GMW - $100 oil'!$MB$2:$MB$200=I$4),0),$E11-1973)} -> 13.53125 | J11: {=INDEX('GMW - $100 oil'!$A$2:$MC$200,MATCH(1,('GMW - $100 oil'!$MC$2:$MC$200=J$3)*('GMW - $100 oil'!$MB$2:$MB$200=J$4),0),$E11-1973)} -> #N/A | K11: {=INDEX('GMW - $100 oil'!$A$2:$MC$200,MATCH(1,('GMW - $100 oil'!$MC$2:$MC$200=K$3)*('GMW - $100 oil'!$MB$2:$MB$200=K$4),0),$E11-1973)} -> #N/A | L11: {=INDEX('GMW - $100 oil'!$A$2:$MC$200,MATCH(1,('GMW - $100 oil'!$MC$2:$MC$200=L$3)*('GMW - $100 oil'!$MB$2:$MB$200=L$4),0),$E11-1973)} -> #N/A | M11: {=INDEX('GMW - $100 oil'!$A$2:$MC$200,MATCH(1,('GMW - $100 oil'!$MC$2:$MC$200=M$3)*('GMW - $100 oil'!$MB$2:$MB$200=M$4),0),$E11-1973)} -> #N/A | ... T11: {=INDEX('GMW - $100 oil'!$A$2:$MC$200,MATCH(1,('GMW - $100 oil'!$MC$2:$MC$200=T$3)*('GMW - $100 oil'!$MB$2:$MB$200=T$4),0),$E11-1973)} -> #N/A
B12: =+B8+1 -> 1981 | C12: =+C8+1 -> 1981 | E12: =+E11+1 -> 1985 | F12: {=INDEX('GMW - $100 oil'!$A$2:$MC$200,MATCH(1,('GMW - $100 oil'!$MC$2:$MC$200=F$3)*('GMW - $100 oil'!$MB$2:$MB$200=F$4),0),$E12-1973)} -> 282155 | G12: {=INDEX('GMW - $100 oil'!$A$2:$MC$200,MATCH(1,('GMW - $100 oil'!$MC$2:$MC$200=G$3)*('GMW - $100 oil'!$MB$2:$MB$200=G$4),0),$E12-1973)} -> 151164 | H12: {=INDEX('GMW - $100 oil'!$A$2:$MC$200,MATCH(1,('GMW - $100 oil'!$MC$2:$MC$200=H$3)*('GMW - $100 oil'!$MB$2:$MB$200=H$4),0),$E12-1973)} -> 36.07959 | I12: {=INDEX('GMW - $100 oil'!$A$2:$MC$200,MATCH(1,('GMW - $100 oil'!$MC$2:$MC$200=I$3)*('GMW - $100 oil'!$MB$2:$MB$200=I$4),0),$E12-1973)} -> 12 | J12: {=INDEX('GMW - $100 oil'!$A$2:$MC$200,MATCH(1,('GMW - $100 oil'!$MC$2:$MC$200=J$3)*('GMW - $100 oil'!$MB$2:$MB$200=J$4),0),$E12-1973)} -> #N/A | K12: {=INDEX('GMW - $100 oil'!$A$2:$MC$200,MATCH(1,('GMW - $100 oil'!$MC$2:$MC$200=K$3)*('GMW - $100 oil'!$MB$2:$MB$200=K$4),0),$E12-1973)} -> #N/A | L12: {=INDEX('GMW - $100 oil'!$A$2:$MC$200,MATCH(1,('GMW - $100 oil'!$MC$2:$MC$200=L$3)*('GMW - $100 oil'!$MB$2:$MB$200=L$4),0),$E12-1973)} -> #N/A | M12: {=INDEX('GMW - $100 oil'!$A$2:$MC$200,MATCH(1,('GMW - $100 oil'!$MC$2:$MC$200=M$3)*('GMW - $100 oil'!$MB$2:$MB$200=M$4),0),$E12-1973)} -> #N/A | ... T12: {=INDEX('GMW - $100 oil'!$A$2:$MC$200,MATCH(1,('GMW - $100 oil'!$MC$2:$MC$200=T$3)*('GMW - $100 oil'!$MB$2:$MB$200=T$4),0),$E12-1973)} -> #N/A
B13: =+B9+1 -> 1981 | C13: =+C9+1 -> 1981 | E13: =+E12+1 -> 1986 | F13: {=INDEX('GMW - $100 oil'!$A$2:$MC$200,MATCH(1,('GMW - $100 oil'!$MC$2:$MC$200=F$3)*('GMW - $100 oil'!$MB$2:$MB$200=F$4),0),$E13-1973)} -> 285437 | G13: {=INDEX('GMW - $100 oil'!$A$2:$MC$200,MATCH(1,('GMW - $100 oil'!$MC$2:$MC$200=G$3)*('GMW - $100 oil'!$MB$2:$MB$200=G$4),0),$E13-1973)} -> 151269 | H13: {=INDEX('GMW - $100 oil'!$A$2:$MC$200,MATCH(1,('GMW - $100 oil'!$MC$2:$MC$200=H$3)*('GMW - $100 oil'!$MB$2:$MB$200=H$4),0),$E13-1973)} -> 36.73131 | I13: {=INDEX('GMW - $100 oil'!$A$2:$MC$200,MATCH(1,('GMW - $100 oil'!$MC$2:$MC$200=I$3)*('GMW - $100 oil'!$MB$2:$MB$200=I$4),0),$E13-1973)} -> 12.51989 | J13: {=INDEX('GMW - $100 oil'!$A$2:$MC$200,MATCH(1,('GMW - $100 oil'!$MC$2:$MC$200=J$3)*('GMW - $100 oil'!$MB$2:$MB$200=J$4),0),$E13-1973)} -> #N/A | K13: {=INDEX('GMW - $100 oil'!$A$2:$MC$200,MATCH(1,('GMW - $100 oil'!$MC$2:$MC$200=K$3)*('GMW - $100 oil'!$MB$2:$MB$200=K$4),0),$E13-1973)} -> #N/A | L13: {=INDEX('GMW - $100 oil'!$A$2:$MC$200,MATCH(1,('GMW - $100 oil'!$MC$2:$MC$200=L$3)*('GMW - $100 oil'!$MB$2:$MB$200=L$4),0),$E13-1973)} -> #N/A | M13: {=INDEX('GMW - $100 oil'!$A$2:$MC$200,MATCH(1,('GMW - $100 oil'!$MC$2:$MC$200=M$3)*('GMW - $100 oil'!$MB$2:$MB$200=M$4),0),$E13-1973)} -> #N/A | ... T13: {=INDEX('GMW - $100 oil'!$A$2:$MC$200,MATCH(1,('GMW - $100 oil'!$MC$2:$MC$200=T$3)*('GMW - $100 oil'!$MB$2:$MB$200=T$4),0),$E13-1973)} -> #N/A
B14: =+B10+1 -> 1981 | C14: =+C10+1 -> 1981 | E14: =+E13+1 -> 1987 | F14: {=INDEX('GMW - $100 oil'!$A$2:$MC$200,MATCH(1,('GMW - $100 oil'!$MC$2:$MC$200=F$3)*('GMW - $100 oil'!$MB$2:$MB$200=F$4),0),$E14-1973)} -> 285814 | G14: {=INDEX('GMW - $100 oil'!$A$2:$MC$200,MATCH(1,('GMW - $100 oil'!$MC$2:$MC$200=G$3)*('GMW - $100 oil'!$MB$2:$MB$200=G$4),0),$E14-1973)} -> 150853 | H14: {=INDEX('GMW - $100 oil'!$A$2:$MC$200,MATCH(1,('GMW - $100 oil'!$MC$2:$MC$200=H$3)*('GMW - $100 oil'!$MB$2:$MB$200=H$4),0),$E14-1973)} -> 37.43518 | I14: {=INDEX('GMW - $100 oil'!$A$2:$MC$200,MATCH(1,('GMW - $100 oil'!$MC$2:$MC$200=I$3)*('GMW - $100 oil'!$MB$2:$MB$200=I$4),0),$E14-1973)} -> 14.60417 | J14: {=INDEX('GMW - $100 oil'!$A$2:$MC$200,MATCH(1,('GMW - $100 oil'!$MC$2:$MC$200=J$3)*('GMW - $100 oil'!$MB$2:$MB$200=J$4),0),$E14-1973)} -> #N/A | K14: {=INDEX('GMW - $100 oil'!$A$2:$MC$200,MATCH(1,('GMW - $100 oil'!$MC$2:$MC$200=K$3)*('GMW - $100 oil'!$MB$2:$MB$200=K$4),0),$E14-1973)} -> #N/A | L14: {=INDEX('GMW - $100 oil'!$A$2:$MC$200,MATCH(1,('GMW - $100 oil'!$MC$2:$MC$200=L$3)*('GMW - $100 oil'!$MB$2:$MB$200=L$4),0),$E14-1973)} -> #N/A | M14: {=INDEX('GMW - $100 oil'!$A$2:$MC$200,MATCH(1,('GMW - $100 oil'!$MC$2:$MC$200=M$3)*('GMW - $100 oil'!$MB$2:$MB$200=M$4),0),$E14-1973)} -> #N/A | ... T14: {=INDEX('GMW - $100 oil'!$A$2:$MC$200,MATCH(1,('GMW - $100 oil'!$MC$2:$MC$200=T$3)*('GMW - $100 oil'!$MB$2:$MB$200=T$4),0),$E14-1973)} -> #N/A
A15: 1982 | B15: =+B11+1 -> 1982 | C15: =+C11+1 -> 1981 | D15: =+D11+1 -> 1981 | E15: =+E14+1 -> 1988 | F15: {=INDEX('GMW - $100 oil'!$A$2:$MC$200,MATCH(1,('GMW - $100 oil'!$MC$2:$MC$200=F$3)*('GMW - $100 oil'!$MB$2:$MB$200=F$4),0),$E15-1973)} -> 286275 | G15: {=INDEX('GMW - $100 oil'!$A$2:$MC$200,MATCH(1,('GMW - $100 oil'!$MC$2:$MC$200=G$3)*('GMW - $100 oil'!$MB$2:$MB$200=G$4),0),$E15-1973)} -> 151361 | H15: {=INDEX('GMW - $100 oil'!$A$2:$MC$200,MATCH(1,('GMW - $100 oil'!$MC$2:$MC$200=H$3)*('GMW - $100 oil'!$MB$2:$MB$200=H$4),0),$E15-1973)} -> 37.87835 | I15: {=INDEX('GMW - $100 oil'!$A$2:$MC$200,MATCH(1,('GMW - $100 oil'!$MC$2:$MC$200=I$3)*('GMW - $100 oil'!$MB$2:$MB$200=I$4),0),$E15-1973)} -> 13.78516 | J15: {=INDEX('GMW - $100 oil'!$A$2:$MC$200,MATCH(1,('GMW - $100 oil'!$MC$2:$MC$200=J$3)*('GMW - $100 oil'!$MB$2:$MB$200=J$4),0),$E15-1973)} -> #N/A | K15: {=INDEX('GMW - $100 oil'!$A$2:$MC$200,MATCH(1,('GMW - $100 oil'!$MC$2:$MC$200=K$3)*('GMW - $100 oil'!$MB$2:$MB$200=K$4),0),$E15-1973)} -> #N/A | L15: {=INDEX('GMW - $100 oil'!$A$2:$MC$200,MATCH(1,('GMW - $100 oil'!$MC$2:$MC$200=L$3)*('GMW - $100 oil'!$MB$2:$MB$200=L$4),0),$E15-1973)} -> #N/A | M15: {=INDEX('GMW - $100 oil'!$A$2:$MC$200,MATCH(1,('GMW - $100 oil'!$MC$2:$MC$200=M$3)*('GMW - $100 oil'!$MB$2:$MB$200=M$4),0),$E15-1973)} -> #N/A | ... T15: {=INDEX('GMW - $100 oil'!$A$2:$MC$200,MATCH(1,('GMW - $100 oil'!$MC$2:$MC$200=T$3)*('GMW - $100 oil'!$MB$2:$MB$200=T$4),0),$E15-1973)} -> #N/A
B16: =+B12+1 -> 1982 | C16: =+C12+1 -> 1982 | E16: =+E15+1 -> 1989 | F16: {=INDEX('GMW - $100 oil'!$A$2:$MC$200,MATCH(1,('GMW - $100 oil'!$MC$2:$MC$200=F$3)*('GMW - $100 oil'!$MB$2:$MB$200=F$4),0),$E16-1973)} -> 289232 | G16: {=INDEX('GMW - $100 oil'!$A$2:$MC$200,MATCH(1,('GMW - $100 oil'!$MC$2:$MC$200=G$3)*('GMW - $100 oil'!$MB$2:$MB$200=G$4),0),$E16-1973)} -> 151251 | H16: {=INDEX('GMW - $100 oil'!$A$2:$MC$200,MATCH(1,('GMW - $100 oil'!$MC$2:$MC$200=H$3)*('GMW - $100 oil'!$MB$2:$MB$200=H$4),0),$E16-1973)} -> 39.1818 | I16: {=INDEX('GMW - $100 oil'!$A$2:$MC$200,MATCH(1,('GMW - $100 oil'!$MC$2:$MC$200=I$3)*('GMW - $100 oil'!$MB$2:$MB$200=I$4),0),$E16-1973)} -> 13.01346 | J16: {=INDEX('GMW - $100 oil'!$A$2:$MC$200,MATCH(1,('GMW - $100 oil'!$MC$2:$MC$200=J$3)*('GMW - $100 oil'!$MB$2:$MB$200=J$4),0),$E16-1973)} -> #N/A | K16: {=INDEX('GMW - $100 oil'!$A$2:$MC$200,MATCH(1,('GMW - $100 oil'!$MC$2:$MC$200=K$3)*('GMW - $100 oil'!$MB$2:$MB$200=K$4),0),$E16-1973)} -> #N/A | L16: {=INDEX('GMW - $100 oil'!$A$2:$MC$200,MATCH(1,('GMW - $100 oil'!$MC$2:$MC$200=L$3)*('GMW - $100 oil'!$MB$2:$MB$200=L$4),0),$E16-1973)} -> #N/A | M16: {=INDEX('GMW - $100 oil'!$A$2:$MC$200,MATCH(1,('GMW - $100 oil'!$MC$2:$MC$200=M$3)*('GMW - $100 oil'!$MB$2:$MB$200=M$4),0),$E16-1973)} -> #N/A | ... T16: {=INDEX('GMW - $100 oil'!$A$2:$MC$200,MATCH(1,('GMW - $100 oil'!$MC$2:$MC$200=T$3)*('GMW - $100 oil'!$MB$2:$MB$200=T$4),0),$E16-1973)} -> #N/A
B17: =+B13+1 -> 1982 | C17: =+C13+1 -> 1982 | E17: =+E16+1 -> 1990 | F17: {=INDEX('GMW - $100 oil'!$A$2:$MC$200,MATCH(1,('GMW - $100 oil'!$MC$2:$MC$200=F$3)*('GMW - $100 oil'!$MB$2:$MB$200=F$4),0),$E17-1973)} -> 289852 | G17: {=INDEX('GMW - $100 oil'!$A$2:$MC$200,MATCH(1,('GMW - $100 oil'!$MC$2:$MC$200=G$3)*('GMW - $100 oil'!$MB$2:$MB$200=G$4),0),$E17-1973)} -> 153796 | H17: {=INDEX('GMW - $100 oil'!$A$2:$MC$200,MATCH(1,('GMW - $100 oil'!$MC$2:$MC$200=H$3)*('GMW - $100 oil'!$MB$2:$MB$200=H$4),0),$E17-1973)} -> 39.41642 | I17: {=INDEX('GMW - $100 oil'!$A$2:$MC$200,MATCH(1,('GMW - $100 oil'!$MC$2:$MC$200=I$3)*('GMW - $100 oil'!$MB$2:$MB$200=I$4),0),$E17-1973)} -> 11.3428 | J17: {=INDEX('GMW - $100 oil'!$A$2:$MC$200,MATCH(1,('GMW - $100 oil'!$MC$2:$MC$200=J$3)*('GMW - $100 oil'!$MB$2:$MB$200=J$4),0),$E17-1973)} -> #N/A | K17: {=INDEX('GMW - $100 oil'!$A$2:$MC$200,MATCH(1,('GMW - $100 oil'!$MC$2:$MC$200=K$3)*('GMW - $100 oil'!$MB$2:$MB$200=K$4),0),$E17-1973)} -> #N/A | L17: {=INDEX('GMW - $100 oil'!$A$2:$MC$200,MATCH(1,('GMW - $100 oil'!$MC$2:$MC$200=L$3)*('GMW - $100 oil'!$MB$2:$MB$200=L$4),0),$E17-1973)} -> #N/A | M17: {=INDEX('GMW - $100 oil'!$A$2:$MC$200,MATCH(1,('GMW - $100 oil'!$MC$2:$MC$200=M$3)*('GMW - $100 oil'!$MB$2:$MB$200=M$4),0),$E17-1973)} -> #N/A | ... T17: {=INDEX('GMW - $100 oil'!$A$2:$MC$200,MATCH(1,('GMW - $100 oil'!$MC$2:$MC$200=T$3)*('GMW - $100 oil'!$MB$2:$MB$200=T$4),0),$E17-1973)} -> #N/A
B18: =+B14+1 -> 1982 | C18: =+C14+1 -> 1982 | E18: =+E17+1 -> 1991 | F18: {=INDEX('GMW - $100 oil'!$A$2:$MC$200,MATCH(1,('GMW - $100 oil'!$MC$2:$MC$200=F$3)*('GMW - $100 oil'!$MB$2:$MB$200=F$4),0),$E18-1973)} -> 291832 | G18: {=INDEX('GMW - $100 oil'!$A$2:$MC$200,MATCH(1,('GMW - $100 oil'!$MC$2:$MC$200=G$3)*('GMW - $100 oil'!$MB$2:$MB$200=G$4),0),$E18-1973)} -> 155106 | H18: {=INDEX('GMW - $100 oil'!$A$2:$MC$200,MATCH(1,('GMW - $100 oil'!$MC$2:$MC$200=H$3)*('GMW - $100 oil'!$MB$2:$MB$200=H$4),0),$E18-1973)} -> 39.88567 | I18: {=INDEX('GMW - $100 oil'!$A$2:$MC$200,MATCH(1,('GMW - $100 oil'!$MC$2:$MC$200=I$3)*('GMW - $100 oil'!$MB$2:$MB$200=I$4),0),$E18-1973)} -> 9.685606 | J18: {=INDEX('GMW - $100 oil'!$A$2:$MC$200,MATCH(1,('GMW - $100 oil'!$MC$2:$MC$200=J$3)*('GMW - $100 oil'!$MB$2:$MB$200=J$4),0),$E18-1973)} -> #N/A | K18: {=INDEX('GMW - $100 oil'!$A$2:$MC$200,MATCH(1,('GMW - $100 oil'!$MC$2:$MC$200=K$3)*('GMW - $100 oil'!$MB$2:$MB$200=K$4),0),$E18-1973)} -> #N/A | L18: {=INDEX('GMW - $100 oil'!$A$2:$MC$200,MATCH(1,('GMW - $100 oil'!$MC$2:$MC$200=L$3)*('GMW - $100 oil'!$MB$2:$MB$200=L$4),0),$E18-1973)} -> #N/A | M18: {=INDEX('GMW - $100 oil'!$A$2:$MC$200,MATCH(1,('GMW - $100 oil'!$MC$2:$MC$200=M$3)*('GMW - $100 oil'!$MB$2:$MB$200=M$4),0),$E18-1973)} -> #N/A | ... T18: {=INDEX('GMW - $100 oil'!$A$2:$MC$200,MATCH(1,('GMW - $100 oil'!$MC$2:$MC$200=T$3)*('GMW - $100 oil'!$MB$2:$MB$200=T$4),0),$E18-1973)} -> #N/A
A19: 1983 | B19: =+B15+1 -> 1983 | C19: =+C15+1 -> 1982 | D19: =+D15+1 -> 1982 | E19: =+E18+1 -> 1992 | F19: {=INDEX('GMW - $100 oil'!$A$2:$MC$200,MATCH(1,('GMW - $100 oil'!$MC$2:$MC$200=F$3)*('GMW - $100 oil'!$MB$2:$MB$200=F$4),0),$E19-1973)} -> 297563 | G19: {=INDEX('GMW - $100 oil'!$A$2:$MC$200,MATCH(1,('GMW - $100 oil'!$MC$2:$MC$200=G$3)*('GMW - $100 oil'!$MB$2:$MB$200=G$4),0),$E19-1973)} -> 157443 | H19: {=INDEX('GMW - $100 oil'!$A$2:$MC$200,MATCH(1,('GMW - $100 oil'!$MC$2:$MC$200=H$3)*('GMW - $100 oil'!$MB$2:$MB$200=H$4),0),$E19-1973)} -> 40.17243 | I19: {=INDEX('GMW - $100 oil'!$A$2:$MC$200,MATCH(1,('GMW - $100 oil'!$MC$2:$MC$200=I$3)*('GMW - $100 oil'!$MB$2:$MB$200=I$4),0),$E19-1973)} -> 10.80176 | J19: {=INDEX('GMW - $100 oil'!$A$2:$MC$200,MATCH(1,('GMW - $100 oil'!$MC$2:$MC$200=J$3)*('GMW - $100 oil'!$MB$2:$MB$200=J$4),0),$E19-1973)} -> #N/A | K19: {=INDEX('GMW - $100 oil'!$A$2:$MC$200,MATCH(1,('GMW - $100 oil'!$MC$2:$MC$200=K$3)*('GMW - $100 oil'!$MB$2:$MB$200=K$4),0),$E19-1973)} -> #N/A | L19: {=INDEX('GMW - $100 oil'!$A$2:$MC$200,MATCH(1,('GMW - $100 oil'!$MC$2:$MC$200=L$3)*('GMW - $100 oil'!$MB$2:$MB$200=L$4),0),$E19-1973)} -> #N/A | M19: {=INDEX('GMW - $100 oil'!$A$2:$MC$200,MATCH(1,('GMW - $100 oil'!$MC$2:$MC$200=M$3)*('GMW - $100 oil'!$MB$2:$MB$200=M$4),0),$E19-1973)} -> #N/A | ... T19: {=INDEX('GMW - $100 oil'!$A$2:$MC$200,MATCH(1,('GMW - $100 oil'!$MC$2:$MC$200=T$3)*('GMW - $100 oil'!$MB$2:$MB$200=T$4),0),$E19-1973)} -> #N/A
B20: =+B16+1 -> 1983 | C20: =+C16+1 -> 1983 | E20: =+E19+1 -> 1993 | F20: {=INDEX('GMW - $100 oil'!$A$2:$MC$200,MATCH(1,('GMW - $100 oil'!$MC$2:$MC$200=F$3)*('GMW - $100 oil'!$MB$2:$MB$200=F$4),0),$E20-1973)} -> 299623 | G20: {=INDEX('GMW - $100 oil'!$A$2:$MC$200,MATCH(1,('GMW - $100 oil'!$MC$2:$MC$200=G$3)*('GMW - $100 oil'!$MB$2:$MB$200=G$4),0),$E20-1973)} -> 158445 | H20: {=INDEX('GMW - $100 oil'!$A$2:$MC$200,MATCH(1,('GMW - $100 oil'!$MC$2:$MC$200=H$3)*('GMW - $100 oil'!$MB$2:$MB$200=H$4),0),$E20-1973)} -> 40.85022 | I20: {=INDEX('GMW - $100 oil'!$A$2:$MC$200,MATCH(1,('GMW - $100 oil'!$MC$2:$MC$200=I$3)*('GMW - $100 oil'!$MB$2:$MB$200=I$4),0),$E20-1973)} -> 10.02404 | J20: {=INDEX('GMW - $100 oil'!$A$2:$MC$200,MATCH(1,('GMW - $100 oil'!$MC$2:$MC$200=J$3)*('GMW - $100 oil'!$MB$2:$MB$200=J$4),0),$E20-1973)} -> #N/A | K20: {=INDEX('GMW - $100 oil'!$A$2:$MC$200,MATCH(1,('GMW - $100 oil'!$MC$2:$MC$200=K$3)*('GMW - $100 oil'!$MB$2:$MB$200=K$4),0),$E20-1973)} -> #N/A | L20: {=INDEX('GMW - $100 oil'!$A$2:$MC$200,MATCH(1,('GMW - $100 oil'!$MC$2:$MC$200=L$3)*('GMW - $100 oil'!$MB$2:$MB$200=L$4),0),$E20-1973)} -> #N/A | M20: {=INDEX('GMW - $100 oil'!$A$2:$MC$200,MATCH(1,('GMW - $100 oil'!$MC$2:$MC$200=M$3)*('GMW - $100 oil'!$MB$2:$MB$200=M$4),0),$E20-1973)} -> #N/A | ... T20: {=INDEX('GMW - $100 oil'!$A$2:$MC$200,MATCH(1,('GMW - $100 oil'!$MC$2:$MC$200=T$3)*('GMW - $100 oil'!$MB$2:$MB$200=T$4),0),$E20-1973)} -> #N/A
B21: =+B17+1 -> 1983 | C21: =+C17+1 -> 1983 | E21: =+E20+1 -> 1994 | F21: {=INDEX('GMW - $100 oil'!$A$2:$MC$200,MATCH(1,('GMW - $100 oil'!$MC$2:$MC$200=F$3)*('GMW - $100 oil'!$MB$2:$MB$200=F$4),0),$E21-1973)} -> 303085 | G21: {=INDEX('GMW - $100 oil'!$A$2:$MC$200,MATCH(1,('GMW - $100 oil'!$MC$2:$MC$200=G$3)*('GMW - $100 oil'!$MB$2:$MB$200=G$4),0),$E21-1973)} -> 161027 | H21: {=INDEX('GMW - $100 oil'!$A$2:$MC$200,MATCH(1,('GMW - $100 oil'!$MC$2:$MC$200=H$3)*('GMW - $100 oil'!$MB$2:$MB$200=H$4),0),$E21-1973)} -> 41.2934 | I21: {=INDEX('GMW - $100 oil'!$A$2:$MC$200,MATCH(1,('GMW - $100 oil'!$MC$2:$MC$200=I$3)*('GMW - $100 oil'!$MB$2:$MB$200=I$4),0),$E21-1973)} -> 9.560606 | J21: {=INDEX('GMW - $100 oil'!$A$2:$MC$200,MATCH(1,('GMW - $100 oil'!$MC$2:$MC$200=J$3)*('GMW - $100 oil'!$MB$2:$MB$200=J$4),0),$E21-1973)} -> #N/A | K21: {=INDEX('GMW - $100 oil'!$A$2:$MC$200,MATCH(1,('GMW - $100 oil'!$MC$2:$MC$200=K$3)*('GMW - $100 oil'!$MB$2:$MB$200=K$4),0),$E21-1973)} -> #N/A | L21: {=INDEX('GMW - $100 oil'!$A$2:$MC$200,MATCH(1,('GMW - $100 oil'!$MC$2:$MC$200=L$3)*('GMW - $100 oil'!$MB$2:$MB$200=L$4),0),$E21-1973)} -> #N/A | M21: {=INDEX('GMW - $100 oil'!$A$2:$MC$200,MATCH(1,('GMW - $100 oil'!$MC$2:$MC$200=M$3)*('GMW - $100 oil'!$MB$2:$MB$200=M$4),0),$E21-1973)} -> #N/A | ... T21: {=INDEX('GMW - $100 oil'!$A$2:$MC$200,MATCH(1,('GMW - $100 oil'!$MC$2:$MC$200=T$3)*('GMW - $100 oil'!$MB$2:$MB$200=T$4),0),$E21-1973)} -> #N/A
B22: =+B18+1 -> 1983 | C22: =+C18+1 -> 1983 | E22: =+E21+1 -> 1995 | F22: {=INDEX('GMW - $100 oil'!$A$2:$MC$200,MATCH(1,('GMW - $100 oil'!$MC$2:$MC$200=F$3)*('GMW - $100 oil'!$MB$2:$MB$200=F$4),0),$E22-1973)} -> 305361 | G22: {=INDEX('GMW - $100 oil'!$A$2:$MC$200,MATCH(1,('GMW - $100 oil'!$MC$2:$MC$200=G$3)*('GMW - $100 oil'!$MB$2:$MB$200=G$4),0),$E22-1973)} -> 161090 | H22: {=INDEX('GMW - $100 oil'!$A$2:$MC$200,MATCH(1,('GMW - $100 oil'!$MC$2:$MC$200=H$3)*('GMW - $100 oil'!$MB$2:$MB$200=H$4),0),$E22-1973)} -> 41.76264 | I22: {=INDEX('GMW - $100 oil'!$A$2:$MC$200,MATCH(1,('GMW - $100 oil'!$MC$2:$MC$200=I$3)*('GMW - $100 oil'!$MB$2:$MB$200=I$4),0),$E22-1973)} -> 9.0625 | J22: {=INDEX('GMW - $100 oil'!$A$2:$MC$200,MATCH(1,('GMW - $100 oil'!$MC$2:$MC$200=J$3)*('GMW - $100 oil'!$MB$2:$MB$200=J$4),0),$E22-1973)} -> #N/A | K22: {=INDEX('GMW - $100 oil'!$A$2:$MC$200,MATCH(1,('GMW - $100 oil'!$MC$2:$MC$200=K$3)*('GMW - $100 oil'!$MB$2:$MB$200=K$4),0),$E22-1973)} -> #N/A | L22: {=INDEX('GMW - $100 oil'!$A$2:$MC$200,MATCH(1,('GMW - $100 oil'!$MC$2:$MC$200=L$3)*('GMW - $100 oil'!$MB$2:$MB$200=L$4),0),$E22-1973)} -> #N/A | M22: {=INDEX('GMW - $100 oil'!$A$2:$MC$200,MATCH(1,('GMW - $100 oil'!$MC$2:$MC$200=M$3)*('GMW - $100 oil'!$MB$2:$MB$200=M$4),0),$E22-1973)} -> #N/A | ... T22: {=INDEX('GMW - $100 oil'!$A$2:$MC$200,MATCH(1,('GMW - $100 oil'!$MC$2:$MC$200=T$3)*('GMW - $100 oil'!$MB$2:$MB$200=T$4),0),$E22-1973)} -> #N/A
A23: 1984 | B23: =+B19+1 -> 1984 | C23: =+C19+1 -> 1983 | D23: =+D19+1 -> 1983 | E23: =+E22+1 -> 1996 | F23: {=INDEX('GMW - $100 oil'!$A$2:$MC$200,MATCH(1,('GMW - $100 oil'!$MC$2:$MC$200=F$3)*('GMW - $100 oil'!$MB$2:$MB$200=F$4),0),$E23-1973)} -> 307964 | G23: {=INDEX('GMW - $100 oil'!$A$2:$MC$200,MATCH(1,('GMW - $100 oil'!$MC$2:$MC$200=G$3)*('GMW - $100 oil'!$MB$2:$MB$200=G$4),0),$E23-1973)} -> 162074 | H23: {=INDEX('GMW - $100 oil'!$A$2:$MC$200,MATCH(1,('GMW - $100 oil'!$MC$2:$MC$200=H$3)*('GMW - $100 oil'!$MB$2:$MB$200=H$4),0),$E23-1973)} -> 41.86692 | I23: {=INDEX('GMW - $100 oil'!$A$2:$MC$200,MATCH(1,('GMW - $100 oil'!$MC$2:$MC$200=I$3)*('GMW - $100 oil'!$MB$2:$MB$200=I$4),0),$E23-1973)} -> 8.943269 | J23: {=INDEX('GMW - $100 oil'!$A$2:$MC$200,MATCH(1,('GMW - $100 oil'!$MC$2:$MC$200=J$3)*('GMW - $100 oil'!$MB$2:$MB$200=J$4),0),$E23-1973)} -> #N/A | K23: {=INDEX('GMW - $100 oil'!$A$2:$MC$200,MATCH(1,('GMW - $100 oil'!$MC$2:$MC$200=K$3)*('GMW - $100 oil'!$MB$2:$MB$200=K$4),0),$E23-1973)} -> #N/A | L23: {=INDEX('GMW - $100 oil'!$A$2:$MC$200,MATCH(1,('GMW - $100 oil'!$MC$2:$MC$200=L$3)*('GMW - $100 oil'!$MB$2:$MB$200=L$4),0),$E23-1973)} -> #N/A | M23: {=INDEX('GMW - $100 oil'!$A$2:$MC$200,MATCH(1,('GMW - $100 oil'!$MC$2:$MC$200=M$3)*('GMW - $100 oil'!$MB$2:$MB$200=M$4),0),$E23-1973)} -> #N/A | ... T23: {=INDEX('GMW - $100 oil'!$A$2:$MC$200,MATCH(1,('GMW - $100 oil'!$MC$2:$MC$200=T$3)*('GMW - $100 oil'!$MB$2:$MB$200=T$4),0),$E23-1973)} -> #N/A
B24: =+B20+1 -> 1984 | C24: =+C20+1 -> 1984 | E24: =+E23+1 -> 1997 | F24: {=INDEX('GMW - $100 oil'!$A$2:$MC$200,MATCH(1,('GMW - $100 oil'!$MC$2:$MC$200=F$3)*('GMW - $100 oil'!$MB$2:$MB$200=F$4),0),$E24-1973)} -> 304892 | G24: {=INDEX('GMW - $100 oil'!$A$2:$MC$200,MATCH(1,('GMW - $100 oil'!$MC$2:$MC$200=G$3)*('GMW - $100 oil'!$MB$2:$MB$200=G$4),0),$E24-1973)} -> 163369 | H24: {=INDEX('GMW - $100 oil'!$A$2:$MC$200,MATCH(1,('GMW - $100 oil'!$MC$2:$MC$200=H$3)*('GMW - $100 oil'!$MB$2:$MB$200=H$4),0),$E24-1973)} -> 42.77934 | I24: {=INDEX('GMW - $100 oil'!$A$2:$MC$200,MATCH(1,('GMW - $100 oil'!$MC$2:$MC$200=I$3)*('GMW - $100 oil'!$MB$2:$MB$200=I$4),0),$E24-1973)} -> 8.844231 | J24: {=INDEX('GMW - $100 oil'!$A$2:$MC$200,MATCH(1,('GMW - $100 oil'!$MC$2:$MC$200=J$3)*('GMW - $100 oil'!$MB$2:$MB$200=J$4),0),$E24-1973)} -> #N/A | K24: {=INDEX('GMW - $100 oil'!$A$2:$MC$200,MATCH(1,('GMW - $100 oil'!$MC$2:$MC$200=K$3)*('GMW - $100 oil'!$MB$2:$MB$200=K$4),0),$E24-1973)} -> #N/A | L24: {=INDEX('GMW - $100 oil'!$A$2:$MC$200,MATCH(1,('GMW - $100 oil'!$MC$2:$MC$200=L$3)*('GMW - $100 oil'!$MB$2:$MB$200=L$4),0),$E24-1973)} -> #N/A | M24: {=INDEX('GMW - $100 oil'!$A$2:$MC$200,MATCH(1,('GMW - $100 oil'!$MC$2:$MC$200=M$3)*('GMW - $100 oil'!$MB$2:$MB$200=M$4),0),$E24-1973)} -> #N/A | ... T24: {=INDEX('GMW - $100 oil'!$A$2:$MC$200,MATCH(1,('GMW - $100 oil'!$MC$2:$MC$200=T$3)*('GMW - $100 oil'!$MB$2:$MB$200=T$4),0),$E24-1973)} -> #N/A
B25: =+B21+1 -> 1984 | C25: =+C21+1 -> 1984 | E25: =+E24+1 -> 1998 | F25: {=INDEX('GMW - $100 oil'!$A$2:$MC$200,MATCH(1,('GMW - $100 oil'!$MC$2:$MC$200=F$3)*('GMW - $100 oil'!$MB$2:$MB$200=F$4),0),$E25-1973)} -> 307122 | G25: {=INDEX('GMW - $100 oil'!$A$2:$MC$200,MATCH(1,('GMW - $100 oil'!$MC$2:$MC$200=G$3)*('GMW - $100 oil'!$MB$2:$MB$200=G$4),0),$E25-1973)} -> 162507 | H25: {=INDEX('GMW - $100 oil'!$A$2:$MC$200,MATCH(1,('GMW - $100 oil'!$MC$2:$MC$200=H$3)*('GMW - $100 oil'!$MB$2:$MB$200=H$4),0),$E25-1973)} -> 42.98789 | I25: {=INDEX('GMW - $100 oil'!$A$2:$MC$200,MATCH(1,('GMW - $100 oil'!$MC$2:$MC$200=I$3)*('GMW - $100 oil'!$MB$2:$MB$200=I$4),0),$E25-1973)} -> 10.89615 | J25: {=INDEX('GMW - $100 oil'!$A$2:$MC$200,MATCH(1,('GMW - $100 oil'!$MC$2:$MC$200=J$3)*('GMW - $100 oil'!$MB$2:$MB$200=J$4),0),$E25-1973)} -> #N/A | K25: {=INDEX('GMW - $100 oil'!$A$2:$MC$200,MATCH(1,('GMW - $100 oil'!$MC$2:$MC$200=K$3)*('GMW - $100 oil'!$MB$2:$MB$200=K$4),0),$E25-1973)} -> #N/A | L25: {=INDEX('GMW - $100 oil'!$A$2:$MC$200,MATCH(1,('GMW - $100 oil'!$MC$2:$MC$200=L$3)*('GMW - $100 oil'!$MB$2:$MB$200=L$4),0),$E25-1973)} -> #N/A | M25: {=INDEX('GMW - $100 oil'!$A$2:$MC$200,MATCH(1,('GMW - $100 oil'!$MC$2:$MC$200=M$3)*('GMW - $100 oil'!$MB$2:$MB$200=M$4),0),$E25-1973)} -> #N/A | ... T25: {=INDEX('GMW - $100 oil'!$A$2:$MC$200,MATCH(1,('GMW - $100 oil'!$MC$2:$MC$200=T$3)*('GMW - $100 oil'!$MB$2:$MB$200=T$4),0),$E25-1973)} -> #N/A
B26: =+B22+1 -> 1984 | C26: =+C22+1 -> 1984 | E26: =+E25+1 -> 1999 | F26: {=INDEX('GMW - $100 oil'!$A$2:$MC$200,MATCH(1,('GMW - $100 oil'!$MC$2:$MC$200=F$3)*('GMW - $100 oil'!$MB$2:$MB$200=F$4),0),$E26-1973)} -> 312697 | G26: {=INDEX('GMW - $100 oil'!$A$2:$MC$200,MATCH(1,('GMW - $100 oil'!$MC$2:$MC$200=G$3)*('GMW - $100 oil'!$MB$2:$MB$200=G$4),0),$E26-1973)} -> 165575 | H26: {=INDEX('GMW - $100 oil'!$A$2:$MC$200,MATCH(1,('GMW - $100 oil'!$MC$2:$MC$200=H$3)*('GMW - $100 oil'!$MB$2:$MB$200=H$4),0),$E26-1973)} -> 43.43106 | I26: {=INDEX('GMW - $100 oil'!$A$2:$MC$200,MATCH(1,('GMW - $100 oil'!$MC$2:$MC$200=I$3)*('GMW - $100 oil'!$MB$2:$MB$200=I$4),0),$E26-1973)} -> 9.969697 | J26: {=INDEX('GMW - $100 oil'!$A$2:$MC$200,MATCH(1,('GMW - $100 oil'!$MC$2:$MC$200=J$3)*('GMW - $100 oil'!$MB$2:$MB$200=J$4),0),$E26-1973)} -> #N/A | K26: {=INDEX('GMW - $100 oil'!$A$2:$MC$200,MATCH(1,('GMW - $100 oil'!$MC$2:$MC$200=K$3)*('GMW - $100 oil'!$MB$2:$MB$200=K$4),0),$E26-1973)} -> #N/A | L26: {=INDEX('GMW - $100 oil'!$A$2:$MC$200,MATCH(1,('GMW - $100 oil'!$MC$2:$MC$200=L$3)*('GMW - $100 oil'!$MB$2:$MB$200=L$4),0),$E26-1973)} -> #N/A | M26: {=INDEX('GMW - $100 oil'!$A$2:$MC$200,MATCH(1,('GMW - $100 oil'!$MC$2:$MC$200=M$3)*('GMW - $100 oil'!$MB$2:$MB$200=M$4),0),$E26-1973)} -> #N/A | ... T26: {=INDEX('GMW - $100 oil'!$A$2:$MC$200,MATCH(1,('GMW - $100 oil'!$MC$2:$MC$200=T$3)*('GMW - $100 oil'!$MB$2:$MB$200=T$4),0),$E26-1973)} -> #N/A
A27: 1985 | B27: =+B23+1 -> 1985 | C27: =+C23+1 -> 1984 | D27: =+D23+1 -> 1984 | E27: =+E26+1 -> 2000 | F27: {=INDEX('GMW - $100 oil'!$A$2:$MC$200,MATCH(1,('GMW - $100 oil'!$MC$2:$MC$200=F$3)*('GMW - $100 oil'!$MB$2:$MB$200=F$4),0),$E27-1973)} -> 315753 | G27: {=INDEX('GMW - $100 oil'!$A$2:$MC$200,MATCH(1,('GMW - $100 oil'!$MC$2:$MC$200=G$3)*('GMW - $100 oil'!$MB$2:$MB$200=G$4),0),$E27-1973)} -> 169390 | H27: {=INDEX('GMW - $100 oil'!$A$2:$MC$200,MATCH(1,('GMW - $100 oil'!$MC$2:$MC$200=H$3)*('GMW - $100 oil'!$MB$2:$MB$200=H$4),0),$E27-1973)} -> 43.87423 | I27: {=INDEX('GMW - $100 oil'!$A$2:$MC$200,MATCH(1,('GMW - $100 oil'!$MC$2:$MC$200=I$3)*('GMW - $100 oil'!$MB$2:$MB$200=I$4),0),$E27-1973)} -> 12.86914 | J27: {=INDEX('GMW - $100 oil'!$A$2:$MC$200,MATCH(1,('GMW - $100 oil'!$MC$2:$MC$200=J$3)*('GMW - $100 oil'!$MB$2:$MB$200=J$4),0),$E27-1973)} -> #N/A | K27: {=INDEX('GMW - $100 oil'!$A$2:$MC$200,MATCH(1,('GMW - $100 oil'!$MC$2:$MC$200=K$3)*('GMW - $100 oil'!$MB$2:$MB$200=K$4),0),$E27-1973)} -> #N/A | L27: {=INDEX('GMW - $100 oil'!$A$2:$MC$200,MATCH(1,('GMW - $100 oil'!$MC$2:$MC$200=L$3)*('GMW - $100 oil'!$MB$2:$MB$200=L$4),0),$E27-1973)} -> #N/A | M27: {=INDEX('GMW - $100 oil'!$A$2:$MC$200,MATCH(1,('GMW - $100 oil'!$MC$2:$MC$200=M$3)*('GMW - $100 oil'!$MB$2:$MB$200=M$4),0),$E27-1973)} -> #N/A | ... T27: {=INDEX('GMW - $100 oil'!$A$2:$MC$200,MATCH(1,('GMW - $100 oil'!$MC$2:$MC$200=T$3)*('GMW - $100 oil'!$MB$2:$MB$200=T$4),0),$E27-1973)} -> #N/A
B28: =+B24+1 -> 1985 | C28: =+C24+1 -> 1985 | E28: =+E27+1 -> 2001 | F28: {=INDEX('GMW - $100 oil'!$A$2:$MC$200,MATCH(1,('GMW - $100 oil'!$MC$2:$MC$200=F$3)*('GMW - $100 oil'!$MB$2:$MB$200=F$4),0),$E28-1973)} -> 322451 | G28: {=INDEX('GMW - $100 oil'!$A$2:$MC$200,MATCH(1,('GMW - $100 oil'!$MC$2:$MC$200=G$3)*('GMW - $100 oil'!$MB$2:$MB$200=G$4),0),$E28-1973)} -> 170284 | H28: {=INDEX('GMW - $100 oil'!$A$2:$MC$200,MATCH(1,('GMW - $100 oil'!$MC$2:$MC$200=H$3)*('GMW - $100 oil'!$MB$2:$MB$200=H$4),0),$E28-1973)} -> 44.9952 | I28: {=INDEX('GMW - $100 oil'!$A$2:$MC$200,MATCH(1,('GMW - $100 oil'!$MC$2:$MC$200=I$3)*('GMW - $100 oil'!$MB$2:$MB$200=I$4),0),$E28-1973)} -> 12.48269 | J28: {=INDEX('GMW - $100 oil'!$A$2:$MC$200,MATCH(1,('GMW - $100 oil'!$MC$2:$MC$200=J$3)*('GMW - $100 oil'!$MB$2:$MB$200=J$4),0),$E28-1973)} -> #N/A | K28: {=INDEX('GMW - $100 oil'!$A$2:$MC$200,MATCH(1,('GMW - $100 oil'!$MC$2:$MC$200=K$3)*('GMW - $100 oil'!$MB$2:$MB$200=K$4),0),$E28-1973)} -> #N/A | L28: {=INDEX('GMW - $100 oil'!$A$2:$MC$200,MATCH(1,('GMW - $100 oil'!$MC$2:$MC$200=L$3)*('GMW - $100 oil'!$MB$2:$MB$200=L$4),0),$E28-1973)} -> #N/A | M28: {=INDEX('GMW - $100 oil'!$A$2:$MC$200,MATCH(1,('GMW - $100 oil'!$MC$2:$MC$200=M$3)*('GMW - $100 oil'!$MB$2:$MB$200=M$4),0),$E28-1973)} -> #N/A | ... T28: {=INDEX('GMW - $100 oil'!$A$2:$MC$200,MATCH(1,('GMW - $100 oil'!$MC$2:$MC$200=T$3)*('GMW - $100 oil'!$MB$2:$MB$200=T$4),0),$E28-1973)} -> #N/A
B29: =+B25+1 -> 1985 | C29: =+C25+1 -> 1985 | E29: =+E28+1 -> 2002 | F29: {=INDEX('GMW - $100 oil'!$A$2:$MC$200,MATCH(1,('GMW - $100 oil'!$MC$2:$MC$200=F$3)*('GMW - $100 oil'!$MB$2:$MB$200=F$4),0),$E29-1973)} -> 322392 | G29: {=INDEX('GMW - $100 oil'!$A$2:$MC$200,MATCH(1,('GMW - $100 oil'!$MC$2:$MC$200=G$3)*('GMW - $100 oil'!$MB$2:$MB$200=G$4),0),$E29-1973)} -> 172709 | H29: {=INDEX('GMW - $100 oil'!$A$2:$MC$200,MATCH(1,('GMW - $100 oil'!$MC$2:$MC$200=H$3)*('GMW - $100 oil'!$MB$2:$MB$200=H$4),0),$E29-1973)} -> 45.12555 | I29: {=INDEX('GMW - $100 oil'!$A$2:$MC$200,MATCH(1,('GMW - $100 oil'!$MC$2:$MC$200=I$3)*('GMW - $100 oil'!$MB$2:$MB$200=I$4),0),$E29-1973)} -> 11.57955 | J29: {=INDEX('GMW - $100 oil'!$A$2:$MC$200,MATCH(1,('GMW - $100 oil'!$MC$2:$MC$200=J$3)*('GMW - $100 oil'!$MB$2:$MB$200=J$4),0),$E29-1973)} -> #N/A | K29: {=INDEX('GMW - $100 oil'!$A$2:$MC$200,MATCH(1,('GMW - $100 oil'!$MC$2:$MC$200=K$3)*('GMW - $100 oil'!$MB$2:$MB$200=K$4),0),$E29-1973)} -> #N/A | L29: {=INDEX('GMW - $100 oil'!$A$2:$MC$200,MATCH(1,('GMW - $100 oil'!$MC$2:$MC$200=L$3)*('GMW - $100 oil'!$MB$2:$MB$200=L$4),0),$E29-1973)} -> #N/A | M29: {=INDEX('GMW - $100 oil'!$A$2:$MC$200,MATCH(1,('GMW - $100 oil'!$MC$2:$MC$200=M$3)*('GMW - $100 oil'!$MB$2:$MB$200=M$4),0),$E29-1973)} -> #N/A | ... T29: {=INDEX('GMW - $100 oil'!$A$2:$MC$200,MATCH(1,('GMW - $100 oil'!$MC$2:$MC$200=T$3)*('GMW - $100 oil'!$MB$2:$MB$200=T$4),0),$E29-1973)} -> #N/A
B30: =+B26+1 -> 1985 | C30: =+C26+1 -> 1985 | E30: =+E29+1 -> 2003 | F30: {=INDEX('GMW - $100 oil'!$A$2:$MC$200,MATCH(1,('GMW - $100 oil'!$MC$2:$MC$200=F$3)*('GMW - $100 oil'!$MB$2:$MB$200=F$4),0),$E30-1973)} -> 322604 | G30: {=INDEX('GMW - $100 oil'!$A$2:$MC$200,MATCH(1,('GMW - $100 oil'!$MC$2:$MC$200=G$3)*('GMW - $100 oil'!$MB$2:$MB$200=G$4),0),$E30-1973)} -> 174066 | H30: {=INDEX('GMW - $100 oil'!$A$2:$MC$200,MATCH(1,('GMW - $100 oil'!$MC$2:$MC$200=H$3)*('GMW - $100 oil'!$MB$2:$MB$200=H$4),0),$E30-1973)} -> 45.49052 | I30: {=INDEX('GMW - $100 oil'!$A$2:$MC$200,MATCH(1,('GMW - $100 oil'!$MC$2:$MC$200=I$3)*('GMW - $100 oil'!$MB$2:$MB$200=I$4),0),$E30-1973)} -> 11.375 | J30: {=INDEX('GMW - $100 oil'!$A$2:$MC$200,MATCH(1,('GMW - $100 oil'!$MC$2:$MC$200=J$3)*('GMW - $100 oil'!$MB$2:$MB$200=J$4),0),$E30-1973)} -> #N/A | K30: {=INDEX('GMW - $100 oil'!$A$2:$MC$200,MATCH(1,('GMW - $100 oil'!$MC$2:$MC$200=K$3)*('GMW - $100 oil'!$MB$2:$MB$200=K$4),0),$E30-1973)} -> #N/A | L30: {=INDEX('GMW - $100 oil'!$A$2:$MC$200,MATCH(1,('GMW - $100 oil'!$MC$2:$MC$200=L$3)*('GMW - $100 oil'!$MB$2:$MB$200=L$4),0),$E30-1973)} -> #N/A | M30: {=INDEX('GMW - $100 oil'!$A$2:$MC$200,MATCH(1,('GMW - $100 oil'!$MC$2:$MC$200=M$3)*('GMW - $100 oil'!$MB$2:$MB$200=M$4),0),$E30-1973)} -> #N/A | ... T30: {=INDEX('GMW - $100 oil'!$A$2:$MC$200,MATCH(1,('GMW - $100 oil'!$MC$2:$MC$200=T$3)*('GMW - $100 oil'!$MB$2:$MB$200=T$4),0),$E30-1973)} -> #N/A
A31: 1986 | B31: =+B27+1 -> 1986 | C31: =+C27+1 -> 1985 | D31: =+D27+1 -> 1985 | E31: =+E30+1 -> 2004 | F31: {=INDEX('GMW - $100 oil'!$A$2:$MC$200,MATCH(1,('GMW - $100 oil'!$MC$2:$MC$200=F$3)*('GMW - $100 oil'!$MB$2:$MB$200=F$4),0),$E31-1973)} -> 325968 | G31: {=INDEX('GMW - $100 oil'!$A$2:$MC$200,MATCH(1,('GMW - $100 oil'!$MC$2:$MC$200=G$3)*('GMW - $100 oil'!$MB$2:$MB$200=G$4),0),$E31-1973)} -> 178852 | H31: {=INDEX('GMW - $100 oil'!$A$2:$MC$200,MATCH(1,('GMW - $100 oil'!$MC$2:$MC$200=H$3)*('GMW - $100 oil'!$MB$2:$MB$200=H$4),0),$E31-1973)} -> 45.64693 | I31: {=INDEX('GMW - $100 oil'!$A$2:$MC$200,MATCH(1,('GMW - $100 oil'!$MC$2:$MC$200=I$3)*('GMW - $100 oil'!$MB$2:$MB$200=I$4),0),$E31-1973)} -> 12.07813 | J31: {=INDEX('GMW - $100 oil'!$A$2:$MC$200,MATCH(1,('GMW - $100 oil'!$MC$2:$MC$200=J$3)*('GMW - $100 oil'!$MB$2:$MB$200=J$4),0),$E31-1973)} -> #N/A | K31: {=INDEX('GMW - $100 oil'!$A$2:$MC$200,MATCH(1,('GMW - $100 oil'!$MC$2:$MC$200=K$3)*('GMW - $100 oil'!$MB$2:$MB$200=K$4),0),$E31-1973)} -> #N/A | L31: {=INDEX('GMW - $100 oil'!$A$2:$MC$200,MATCH(1,('GMW - $100 oil'!$MC$2:$MC$200=L$3)*('GMW - $100 oil'!$MB$2:$MB$200=L$4),0),$E31-1973)} -> #N/A | M31: {=INDEX('GMW - $100 oil'!$A$2:$MC$200,MATCH(1,('GMW - $100 oil'!$MC$2:$MC$200=M$3)*('GMW - $100 oil'!$MB$2:$MB$200=M$4),0),$E31-1973)} -> #N/A | ... T31: {=INDEX('GMW - $100 oil'!$A$2:$MC$200,MATCH(1,('GMW - $100 oil'!$MC$2:$MC$200=T$3)*('GMW - $100 oil'!$MB$2:$MB$200=T$4),0),$E31-1973)} -> #N/A
B32: =+B28+1 -> 1986 | C32: =+C28+1 -> 1986 | E32: =+E31+1 -> 2005 | F32: {=INDEX('GMW - $100 oil'!$A$2:$MC$200,MATCH(1,('GMW - $100 oil'!$MC$2:$MC$200=F$3)*('GMW - $100 oil'!$MB$2:$MB$200=F$4),0),$E32-1973)} -> 328872 | G32: {=INDEX('GMW - $100 oil'!$A$2:$MC$200,MATCH(1,('GMW - $100 oil'!$MC$2:$MC$200=G$3)*('GMW - $100 oil'!$MB$2:$MB$200=G$4),0),$E32-1973)} -> 181672 | H32: {=INDEX('GMW - $100 oil'!$A$2:$MC$200,MATCH(1,('GMW - $100 oil'!$MC$2:$MC$200=H$3)*('GMW - $100 oil'!$MB$2:$MB$200=H$4),0),$E32-1973)} -> 46.3508 | I32: {=INDEX('GMW - $100 oil'!$A$2:$MC$200,MATCH(1,('GMW - $100 oil'!$MC$2:$MC$200=I$3)*('GMW - $100 oil'!$MB$2:$MB$200=I$4),0),$E32-1973)} -> 10.32885 | J32: {=INDEX('GMW - $100 oil'!$A$2:$MC$200,MATCH(1,('GMW - $100 oil'!$MC$2:$MC$200=J$3)*('GMW - $100 oil'!$MB$2:$MB$200=J$4),0),$E32-1973)} -> #N/A | K32: {=INDEX('GMW - $100 oil'!$A$2:$MC$200,MATCH(1,('GMW - $100 oil'!$MC$2:$MC$200=K$3)*('GMW - $100 oil'!$MB$2:$MB$200=K$4),0),$E32-1973)} -> #N/A | L32: {=INDEX('GMW - $100 oil'!$A$2:$MC$200,MATCH(1,('GMW - $100 oil'!$MC$2:$MC$200=L$3)*('GMW - $100 oil'!$MB$2:$MB$200=L$4),0),$E32-1973)} -> #N/A | M32: {=INDEX('GMW - $100 oil'!$A$2:$MC$200,MATCH(1,('GMW - $100 oil'!$MC$2:$MC$200=M$3)*('GMW - $100 oil'!$MB$2:$MB$200=M$4),0),$E32-1973)} -> #N/A | ... T32: {=INDEX('GMW - $100 oil'!$A$2:$MC$200,MATCH(1,('GMW - $100 oil'!$MC$2:$MC$200=T$3)*('GMW - $100 oil'!$MB$2:$MB$200=T$4),0),$E32-1973)} -> #N/A
B33: =+B29+1 -> 1986 | C33: =+C29+1 -> 1986 | E33: =+E32+1 -> 2006 | F33: {=INDEX('GMW - $100 oil'!$A$2:$MC$200,MATCH(1,('GMW - $100 oil'!$MC$2:$MC$200=F$3)*('GMW - $100 oil'!$MB$2:$MB$200=F$4),0),$E33-1973)} -> 330966 | G33: {=INDEX('GMW - $100 oil'!$A$2:$MC$200,MATCH(1,('GMW - $100 oil'!$MC$2:$MC$200=G$3)*('GMW - $100 oil'!$MB$2:$MB$200=G$4),0),$E33-1973)} -> 182857 | H33: {=INDEX('GMW - $100 oil'!$A$2:$MC$200,MATCH(1,('GMW - $100 oil'!$MC$2:$MC$200=H$3)*('GMW - $100 oil'!$MB$2:$MB$200=H$4),0),$E33-1973)} -> 46.53328 | I33: {=INDEX('GMW - $100 oil'!$A$2:$MC$200,MATCH(1,('GMW - $100 oil'!$MC$2:$MC$200=I$3)*('GMW - $100 oil'!$MB$2:$MB$200=I$4),0),$E33-1973)} -> 9.875 | J33: {=INDEX('GMW - $100 oil'!$A$2:$MC$200,MATCH(1,('GMW - $100 oil'!$MC$2:$MC$200=J$3)*('GMW - $100 oil'!$MB$2:$MB$200=J$4),0),$E33-1973)} -> #N/A | K33: {=INDEX('GMW - $100 oil'!$A$2:$MC$200,MATCH(1,('GMW - $100 oil'!$MC$2:$MC$200=K$3)*('GMW - $100 oil'!$MB$2:$MB$200=K$4),0),$E33-1973)} -> #N/A | L33: {=INDEX('GMW - $100 oil'!$A$2:$MC$200,MATCH(1,('GMW - $100 oil'!$MC$2:$MC$200=L$3)*('GMW - $100 oil'!$MB$2:$MB$200=L$4),0),$E33-1973)} -> #N/A | M33: {=INDEX('GMW - $100 oil'!$A$2:$MC$200,MATCH(1,('GMW - $100 oil'!$MC$2:$MC$200=M$3)*('GMW - $100 oil'!$MB$2:$MB$200=M$4),0),$E33-1973)} -> #N/A | ... T33: {=INDEX('GMW - $100 oil'!$A$2:$MC$200,MATCH(1,('GMW - $100 oil'!$MC$2:$MC$200=T$3)*('GMW - $100 oil'!$MB$2:$MB$200=T$4),0),$E33-1973)} -> #N/A
B34: =+B30+1 -> 1986 | C34: =+C30+1 -> 1986 | E34: =+E33+1 -> 2007 | F34: {=INDEX('GMW - $100 oil'!$A$2:$MC$200,MATCH(1,('GMW - $100 oil'!$MC$2:$MC$200=F$3)*('GMW - $100 oil'!$MB$2:$MB$200=F$4),0),$E34-1973)} -> 337367 | G34: {=INDEX('GMW - $100 oil'!$A$2:$MC$200,MATCH(1,('GMW - $100 oil'!$MC$2:$MC$200=G$3)*('GMW - $100 oil'!$MB$2:$MB$200=G$4),0),$E34-1973)} -> 183752 | H34: {=INDEX('GMW - $100 oil'!$A$2:$MC$200,MATCH(1,('GMW - $100 oil'!$MC$2:$MC$200=H$3)*('GMW - $100 oil'!$MB$2:$MB$200=H$4),0),$E34-1973)} -> 46.92432 | I34: {=INDEX('GMW - $100 oil'!$A$2:$MC$200,MATCH(1,('GMW - $100 oil'!$MC$2:$MC$200=I$3)*('GMW - $100 oil'!$MB$2:$MB$200=I$4),0),$E34-1973)} -> 10.72348 | J34: {=INDEX('GMW - $100 oil'!$A$2:$MC$200,MATCH(1,('GMW - $100 oil'!$MC$2:$MC$200=J$3)*('GMW - $100 oil'!$MB$2:$MB$200=J$4),0),$E34-1973)} -> #N/A | K34: {=INDEX('GMW - $100 oil'!$A$2:$MC$200,MATCH(1,('GMW - $100 oil'!$MC$2:$MC$200=K$3)*('GMW - $100 oil'!$MB$2:$MB$200=K$4),0),$E34-1973)} -> #N/A | L34: {=INDEX('GMW - $100 oil'!$A$2:$MC$200,MATCH(1,('GMW - $100 oil'!$MC$2:$MC$200=L$3)*('GMW - $100 oil'!$MB$2:$MB$200=L$4),0),$E34-1973)} -> #N/A | M34: {=INDEX('GMW - $100 oil'!$A$2:$MC$200,MATCH(1,('GMW - $100 oil'!$MC$2:$MC$200=M$3)*('GMW - $100 oil'!$MB$2:$MB$200=M$4),0),$E34-1973)} -> #N/A | ... T34: {=INDEX('GMW - $100 oil'!$A$2:$MC$200,MATCH(1,('GMW - $100 oil'!$MC$2:$MC$200=T$3)*('GMW - $100 oil'!$MB$2:$MB$200=T$4),0),$E34-1973)} -> #N/A
A35: 1987 | B35: =+B31+1 -> 1987 | C35: =+C31+1 -> 1986 | D35: =+D31+1 -> 1986 | E35: =+E34+1 -> 2008 | F35: {=INDEX('GMW - $100 oil'!$A$2:$MC$200,MATCH(1,('GMW - $100 oil'!$MC$2:$MC$200=F$3)*('GMW - $100 oil'!$MB$2:$MB$200=F$4),0),$E35-1973)} -> 339754 | G35: {=INDEX('GMW - $100 oil'!$A$2:$MC$200,MATCH(1,('GMW - $100 oil'!$MC$2:$MC$200=G$3)*('GMW - $100 oil'!$MB$2:$MB$200=G$4),0),$E35-1973)} -> 185943 | H35: {=INDEX('GMW - $100 oil'!$A$2:$MC$200,MATCH(1,('GMW - $100 oil'!$MC$2:$MC$200=H$3)*('GMW - $100 oil'!$MB$2:$MB$200=H$4),0),$E35-1973)} -> 47.23714 | I35: {=INDEX('GMW - $100 oil'!$A$2:$MC$200,MATCH(1,('GMW - $100 oil'!$MC$2:$MC$200=I$3)*('GMW - $100 oil'!$MB$2:$MB$200=I$4),0),$E35-1973)} -> 10.66406 | J35: {=INDEX('GMW - $100 oil'!$A$2:$MC$200,MATCH(1,('GMW - $100 oil'!$MC$2:$MC$200=J$3)*('GMW - $100 oil'!$MB$2:$MB$200=J$4),0),$E35-1973)} -> #N/A | K35: {=INDEX('GMW - $100 oil'!$A$2:$MC$200,MATCH(1,('GMW - $100 oil'!$MC$2:$MC$200=K$3)*('GMW - $100 oil'!$MB$2:$MB$200=K$4),0),$E35-1973)} -> #N/A | L35: {=INDEX('GMW - $100 oil'!$A$2:$MC$200,MATCH(1,('GMW - $100 oil'!$MC$2:$MC$200=L$3)*('GMW - $100 oil'!$MB$2:$MB$200=L$4),0),$E35-1973)} -> #N/A | M35: {=INDEX('GMW - $100 oil'!$A$2:$MC$200,MATCH(1,('GMW - $100 oil'!$MC$2:$MC$200=M$3)*('GMW - $100 oil'!$MB$2:$MB$200=M$4),0),$E35-1973)} -> #N/A | ... T35: {=INDEX('GMW - $100 oil'!$A$2:$MC$200,MATCH(1,('GMW - $100 oil'!$MC$2:$MC$200=T$3)*('GMW - $100 oil'!$MB$2:$MB$200=T$4),0),$E35-1973)} -> #N/A
B36: =+B32+1 -> 1987 | C36: =+C32+1 -> 1987 | E36: =+E35+1 -> 2009 | F36: {=INDEX('GMW - $100 oil'!$A$2:$MC$200,MATCH(1,('GMW - $100 oil'!$MC$2:$MC$200=F$3)*('GMW - $100 oil'!$MB$2:$MB$200=F$4),0),$E36-1973)} -> 344795 | G36: {=INDEX('GMW - $100 oil'!$A$2:$MC$200,MATCH(1,('GMW - $100 oil'!$MC$2:$MC$200=G$3)*('GMW - $100 oil'!$MB$2:$MB$200=G$4),0),$E36-1973)} -> 189091 | H36: {=INDEX('GMW - $100 oil'!$A$2:$MC$200,MATCH(1,('GMW - $100 oil'!$MC$2:$MC$200=H$3)*('GMW - $100 oil'!$MB$2:$MB$200=H$4),0),$E36-1973)} -> 47.83673 | I36: {=INDEX('GMW - $100 oil'!$A$2:$MC$200,MATCH(1,('GMW - $100 oil'!$MC$2:$MC$200=I$3)*('GMW - $100 oil'!$MB$2:$MB$200=I$4),0),$E36-1973)} -> 9.228847 | J36: {=INDEX('GMW - $100 oil'!$A$2:$MC$200,MATCH(1,('GMW - $100 oil'!$MC$2:$MC$200=J$3)*('GMW - $100 oil'!$MB$2:$MB$200=J$4),0),$E36-1973)} -> #N/A | K36: {=INDEX('GMW - $100 oil'!$A$2:$MC$200,MATCH(1,('GMW - $100 oil'!$MC$2:$MC$200=K$3)*('GMW - $100 oil'!$MB$2:$MB$200=K$4),0),$E36-1973)} -> #N/A | L36: {=INDEX('GMW - $100 oil'!$A$2:$MC$200,MATCH(1,('GMW - $100 oil'!$MC$2:$MC$200=L$3)*('GMW - $100 oil'!$MB$2:$MB$200=L$4),0),$E36-1973)} -> #N/A | M36: {=INDEX('GMW - $100 oil'!$A$2:$MC$200,MATCH(1,('GMW - $100 oil'!$MC$2:$MC$200=M$3)*('GMW - $100 oil'!$MB$2:$MB$200=M$4),0),$E36-1973)} -> #N/A | ... T36: {=INDEX('GMW - $100 oil'!$A$2:$MC$200,MATCH(1,('GMW - $100 oil'!$MC$2:$MC$200=T$3)*('GMW - $100 oil'!$MB$2:$MB$200=T$4),0),$E36-1973)} -> #N/A
B37: =+B33+1 -> 1987 | C37: =+C33+1 -> 1987 | E37: =+E36+1 -> 2010 | F37: {=INDEX('GMW - $100 oil'!$A$2:$MC$200,MATCH(1,('GMW - $100 oil'!$MC$2:$MC$200=F$3)*('GMW - $100 oil'!$MB$2:$MB$200=F$4),0),$E37-1973)} -> 353365 | G37: {=INDEX('GMW - $100 oil'!$A$2:$MC$200,MATCH(1,('GMW - $100 oil'!$MC$2:$MC$200=G$3)*('GMW - $100 oil'!$MB$2:$MB$200=G$4),0),$E37-1973)} -> 193017 | H37: {=INDEX('GMW - $100 oil'!$A$2:$MC$200,MATCH(1,('GMW - $100 oil'!$MC$2:$MC$200=H$3)*('GMW - $100 oil'!$MB$2:$MB$200=H$4),0),$E37-1973)} -> 47.88887 | I37: {=INDEX('GMW - $100 oil'!$A$2:$MC$200,MATCH(1,('GMW - $100 oil'!$MC$2:$MC$200=I$3)*('GMW - $100 oil'!$MB$2:$MB$200=I$4),0),$E37-1973)} -> 9.481061 | J37: {=INDEX('GMW - $100 oil'!$A$2:$MC$200,MATCH(1,('GMW - $100 oil'!$MC$2:$MC$200=J$3)*('GMW - $100 oil'!$MB$2:$MB$200=J$4),0),$E37-1973)} -> #N/A | K37: {=INDEX('GMW - $100 oil'!$A$2:$MC$200,MATCH(1,('GMW - $100 oil'!$MC$2:$MC$200=K$3)*('GMW - $100 oil'!$MB$2:$MB$200=K$4),0),$E37-1973)} -> #N/A | L37: {=INDEX('GMW - $100 oil'!$A$2:$MC$200,MATCH(1,('GMW - $100 oil'!$MC$2:$MC$200=L$3)*('GMW - $100 oil'!$MB$2:$MB$200=L$4),0),$E37-1973)} -> #N/A | M37: {=INDEX('GMW - $100 oil'!$A$2:$MC$200,MATCH(1,('GMW - $100 oil'!$MC$2:$MC$200=M$3)*('GMW - $100 oil'!$MB$2:$MB$200=M$4),0),$E37-1973)} -> #N/A | ... T37: {=INDEX('GMW - $100 oil'!$A$2:$MC$200,MATCH(1,('GMW - $100 oil'!$MC$2:$MC$200=T$3)*('GMW - $100 oil'!$MB$2:$MB$200=T$4),0),$E37-1973)} -> #N/A
